{
  "type": "Feature",
  "properties": {
    "iso:country":"US",
    "sg:address":"2525 Royal Ln",
    "sg:city":"Dallas",
    "sg:classifiers":[
        {
            "category":"Arena",
            "subcategory":"Sports Club",
            "type":"Entertainment"
        }
    ],
    "sg:phone":"+1 214 701 3169",
    "sg:postcode":"75229",
    "sg:province":"TX",
    "sg:website":"www.dallastabletennis.net/Welcom...",
    "wof:name":"Dallas Table Tennis Club",
    "wof:placetype":"venue"
},
  "geometry": {"coordinates":[-96.893759,32.898345],"type":"Point"}
}