{
  "type": "Feature",
  "properties": {
    "iso:country":"US",
    "sg:address":"800 N University Dr",
    "sg:city":"Nacogdoches",
    "sg:classifiers":[
        {
            "category":"Home & Garden",
            "subcategory":"Building Materials",
            "type":"Retail Goods"
        }
    ],
    "sg:phone":"+1 936 569 0819",
    "sg:postcode":"75961",
    "sg:province":"TX",
    "sg:tags":[
        "glass",
        "window",
        "plate"
    ],
    "wof:name":"American Glass Co",
    "wof:placetype":"venue"
},
  "geometry": {"coordinates":[-94.64022300000001,31.610965],"type":"Point"}
}