{
  "type": "Feature",
  "properties": {
    "iso:country":"US",
    "sg:address":"1625 W Main St",
    "sg:city":"Houston",
    "sg:classifiers":[
        {
            "category":"Home & Garden",
            "subcategory":"Building Materials",
            "type":"Retail Goods"
        }
    ],
    "sg:phone":"+1 713 807 1131",
    "sg:postcode":"77006",
    "sg:province":"TX",
    "wof:name":"Mab Enterprises Inc",
    "wof:placetype":"venue"
},
  "geometry": {"coordinates":[-95.40138,29.735988],"type":"Point"}
}