{
  "type": "Feature",
  "properties": {
    "iso:country":"US",
    "sg:address":"5736 Sea Breeze Ln",
    "sg:city":"Fort Worth",
    "sg:classifiers":[
        {
            "category":"Shopping",
            "subcategory":"Clothing, Apparel, & Fashions",
            "type":"Retail Goods"
        }
    ],
    "sg:phone":"+1 817 238 8002",
    "sg:postcode":"76135",
    "sg:province":"TX",
    "sg:tags":[
        "family"
    ],
    "wof:name":"Ooh-La-La",
    "wof:placetype":"venue"
},
  "geometry": {"coordinates":[-97.415171,32.824928],"type":"Point"}
}