{
  "type": "Feature",
  "properties": {
    "iso:country":"US",
    "sg:address":"1855 Hormel Dr",
    "sg:city":"San Antonio",
    "sg:classifiers":[
        {
            "category":"Manufacturing",
            "subcategory":"Glass & Minerals",
            "type":"Manufacturing & Wholesale Goods"
        },
        {
            "category":"Building & Trades",
            "subcategory":"Construction",
            "type":"Services"
        }
    ],
    "sg:phone":"+1 210 223 4900",
    "sg:postcode":"78219",
    "sg:province":"TX",
    "sg:tags":[
        "concrete",
        "product",
        "mantel",
        "mfg"
    ],
    "wof:name":"Mission Stone LLP",
    "wof:placetype":"venue"
},
  "geometry": {"coordinates":[-98.431924,29.447285],"type":"Point"}
}