{
  "type": "Feature",
  "properties": {
    "iso:country":"US",
    "sg:address":"208 3rd St",
    "sg:city":"Cuero",
    "sg:classifiers":[
        {
            "category":"Personal",
            "subcategory":"Beauty Salon",
            "type":"Services"
        }
    ],
    "sg:phone":"+1 361 277 2719",
    "sg:postcode":"77954",
    "sg:province":"TX",
    "wof:name":"Gladys' Beauty Bar",
    "wof:placetype":"venue"
},
  "geometry": {"coordinates":[-97.284813,29.100544],"type":"Point"}
}