{
  "type": "Feature",
  "properties": {
    "iso:country":"US",
    "sg:address":"6900 Fannin St",
    "sg:city":"Houston",
    "sg:classifiers":[
        {
            "category":"Health Services",
            "subcategory":"Hospital",
            "type":"Services"
        }
    ],
    "sg:phone":"+1 713 794 5316",
    "sg:postcode":"77030",
    "sg:province":"TX",
    "sg:tags":[
        "specialty"
    ],
    "wof:name":"University Texas Cancer Center",
    "wof:placetype":"venue"
},
  "geometry": {"coordinates":[-95.402993,29.704717],"type":"Point"}
}