{
  "type": "Feature",
  "properties": {
    "iso:country":"US",
    "sg:address":"5500 Preston Rd",
    "sg:city":"Dallas",
    "sg:classifiers":[
        {
            "category":"Real Estate",
            "subcategory":"Real Estate Agent",
            "type":"Services"
        }
    ],
    "sg:phone":"+1 214 521 3099",
    "sg:postcode":"75205",
    "sg:province":"TX",
    "wof:name":"Underwood Financial LTD",
    "wof:placetype":"venue"
},
  "geometry": {"coordinates":[-96.804361,32.838208],"type":"Point"}
}