{
  "type": "Feature",
  "properties": {
    "iso:country":"US",
    "sg:address":"12034 Vintage Pt",
    "sg:city":"San Antonio",
    "sg:classifiers":[
        {
            "category":"Manufacturing",
            "subcategory":"Retail Goods",
            "type":"Manufacturing & Wholesale Goods"
        }
    ],
    "sg:phone":"+1 210 679 8561",
    "sg:postcode":"78253",
    "sg:province":"TX",
    "sg:tags":[
        "product",
        "mfg"
    ],
    "wof:name":"Turners Burners",
    "wof:placetype":"venue"
},
  "geometry": {"coordinates":[-98.730979,29.450566],"type":"Point"}
}