{
  "type": "Feature",
  "properties": {
    "iso:country":"US",
    "sg:address":"411 N 8th Ave",
    "sg:city":"Edinburg",
    "sg:classifiers":[
        {
            "category":"Education",
            "subcategory":"School",
            "type":"Public Place"
        }
    ],
    "sg:phone":"+1 956 316 7200",
    "sg:postcode":"78541",
    "sg:province":"TX",
    "wof:name":"Edinburg Consolidated Independent School District",
    "wof:placetype":"venue"
},
  "geometry": {"coordinates":[-98.165251,26.305029],"type":"Point"}
}