{
  "type": "Feature",
  "properties": {
    "iso:country":"US",
    "sg:address":"311 Kickerillo Dr",
    "sg:city":"Houston",
    "sg:classifiers":[
        {
            "category":"Professional",
            "subcategory":"Business Services",
            "type":"Services"
        }
    ],
    "sg:phone":"+1 281 497 6146",
    "sg:postcode":"77079",
    "sg:province":"TX",
    "wof:name":"Kicktec Technology Corp",
    "wof:placetype":"venue"
},
  "geometry": {"coordinates":[-95.59796900000001,29.762345],"type":"Point"}
}