{
  "type": "Feature",
  "properties": {
    "iso:country":"US",
    "sg:address":"106 SE 2nd St",
    "sg:city":"Kerens",
    "sg:classifiers":[
        {
            "category":"Education",
            "subcategory":"Library",
            "type":"Public Place"
        }
    ],
    "sg:phone":"+1 903 396 2665",
    "sg:postcode":"75144",
    "sg:province":"TX",
    "wof:name":"Friends Of Kerens Library Inc",
    "wof:placetype":"venue"
},
  "geometry": {"coordinates":[-96.227341,32.130371],"type":"Point"}
}