{
  "type": "Feature",
  "properties": {
    "iso:country":"US",
    "sg:address":"2410 Locke Ln",
    "sg:city":"Houston",
    "sg:classifiers":[
        {
            "category":"Professional",
            "type":"Services"
        }
    ],
    "sg:phone":"+1 713 529 6005",
    "sg:postcode":"77019",
    "sg:province":"TX",
    "wof:name":"Atwell Interests Inc",
    "wof:placetype":"venue"
},
  "geometry": {"coordinates":[-95.418356,29.743803],"type":"Point"}
}