{
  "type": "Feature",
  "properties": {
    "iso:country":"US",
    "sg:address":"3166 Stick Horse Ln",
    "sg:city":"Mc Kinney",
    "sg:classifiers":[
        {
            "category":"Shopping",
            "subcategory":"Clothing, Apparel, & Fashions",
            "type":"Retail Goods"
        }
    ],
    "sg:phone":"+1 972 548 0048",
    "sg:postcode":"75071",
    "sg:province":"TX",
    "wof:name":"Fratelli Fashion Inc",
    "wof:placetype":"venue"
},
  "geometry": {"coordinates":[-96.57118199999999,33.201999],"type":"Point"}
}