{
  "type": "Feature",
  "properties": {
    "iso:country":"US",
    "sg:address":"14865 Inwood Rd",
    "sg:city":"Addison",
    "sg:classifiers":[
        {
            "category":"Restaurant",
            "type":"Food & Drink"
        }
    ],
    "sg:phone":"+1 972 991 8322",
    "sg:postcode":"75001",
    "sg:province":"TX",
    "wof:name":"Hana Japanese Restaurant & Bar",
    "wof:placetype":"venue"
},
  "geometry": {"coordinates":[-96.829454,32.950034],"type":"Point"}
}