{
  "type": "Feature",
  "properties": {
    "iso:country":"US",
    "sg:address":"1022 Blume Rd",
    "sg:city":"Rosenberg",
    "sg:classifiers":[
        {
            "category":"Government",
            "subcategory":"Office",
            "type":"Public Place"
        }
    ],
    "sg:phone":"+1 281 342 0141",
    "sg:postcode":"77471",
    "sg:province":"TX",
    "sg:tags":[
        "parish",
        "government-county"
    ],
    "wof:name":"Drainage District",
    "wof:placetype":"venue"
},
  "geometry": {"coordinates":[-95.82714799999999,29.543914],"type":"Point"}
}