{
  "type": "Feature",
  "properties": {
    "iso:country":"US",
    "sg:address":"4938 S Staples St",
    "sg:city":"Corpus Christi",
    "sg:classifiers":[
        {
            "category":"Shopping",
            "subcategory":"Shoes",
            "type":"Retail Goods"
        }
    ],
    "sg:phone":"+1 361 991 9133",
    "sg:postcode":"78411",
    "sg:province":"TX",
    "wof:name":"S A S Factory Shoe Store",
    "wof:placetype":"venue"
},
  "geometry": {"coordinates":[-97.369333,27.711085],"type":"Point"}
}