{
  "type": "Feature",
  "properties": {
    "iso:country":"US",
    "sg:address":"703 E 9th St",
    "sg:city":"Kemp",
    "sg:classifiers":[
        {
            "category":"Food & Beverages",
            "subcategory":"Bakery",
            "type":"Retail Goods"
        }
    ],
    "sg:phone":"+1 903 498 4447",
    "sg:postcode":"75143",
    "sg:province":"TX",
    "wof:name":"Remember That Cake",
    "wof:placetype":"venue"
},
  "geometry": {"coordinates":[-96.22528699999999,32.44475],"type":"Point"}
}