{
  "type": "Feature",
  "properties": {
    "iso:country":"US",
    "sg:address":"1601 W. Koenig Lane",
    "sg:city":"Austin",
    "sg:classifiers":[
        {
            "category":"Personal",
            "subcategory":"Beauty Salon",
            "type":"Services"
        },
        {
            "category":"Personal",
            "subcategory":"Day Spa",
            "type":"Services"
        }
    ],
    "sg:phone":"+1 512 452 0185",
    "sg:postcode":"78756",
    "sg:province":"TX",
    "sg:website":"divinitydayspa.com",
    "wof:name":"Divinity Day Spa",
    "wof:placetype":"venue"
},
  "geometry": {"coordinates":[-97.735129,30.332321],"type":"Point"}
}