{
  "type": "Feature",
  "properties": {
    "iso:country":"US",
    "sg:address":"3301 Kilkenny Rd",
    "sg:city":"El Paso",
    "sg:classifiers":[
        {
            "category":"Shopping",
            "subcategory":"Bicycles & Sporting Goods",
            "type":"Retail Goods"
        }
    ],
    "sg:phone":"+1 915 592 7916",
    "sg:postcode":"79925",
    "sg:province":"TX",
    "wof:name":"Overnight Stringing & Sales",
    "wof:placetype":"venue"
},
  "geometry": {"coordinates":[-106.35096799999999,31.790155],"type":"Point"}
}