{
  "type": "Feature",
  "properties": {
    "iso:country":"US",
    "sg:address":"5900 North Fwy",
    "sg:city":"Houston",
    "sg:classifiers":[
        {
            "category":"Home & Garden",
            "subcategory":"Furniture",
            "type":"Retail Goods"
        },
        {
            "category":"Home & Garden",
            "subcategory":"Home Furnishings",
            "type":"Retail Goods"
        },
        {
            "category":"Home & Garden",
            "subcategory":"Carpets & Floor Coverings",
            "type":"Retail Goods"
        }
    ],
    "sg:phone":"+1 281 201 0079",
    "sg:postcode":"77090",
    "sg:province":"TX",
    "sg:tags":[
        "bedroom",
        "set",
        "store",
        "bed",
        "mattress"
    ],
    "sg:website":"http://mattressesforless.reachlocal.com/?scid=1660719",
    "wof:name":"Mattresses for Less",
    "wof:placetype":"venue"
},
  "geometry": {"coordinates":[-95.41968900000001,29.965955],"type":"Point"}
}