{
  "type": "Feature",
  "properties": {
    "iso:country":"US",
    "sg:address":"2145 Wallbrook Dr",
    "sg:city":"Lewisville",
    "sg:classifiers":[
        {
            "category":"Shopping",
            "subcategory":"Catalog Store",
            "type":"Retail Goods"
        }
    ],
    "sg:phone":"+1 972 459 0559",
    "sg:postcode":"75067",
    "sg:province":"TX",
    "sg:tags":[
        "mail",
        "house"
    ],
    "wof:name":"J & C Collectibles",
    "wof:placetype":"venue"
},
  "geometry": {"coordinates":[-97.004086,33.008449],"type":"Point"}
}