{
  "type": "Feature",
  "properties": {
    "iso:country":"US",
    "sg:address":"18014 Carbridge Dr",
    "sg:city":"Houston",
    "sg:classifiers":[
        {
            "category":"Autos & Motor Vehicles",
            "subcategory":"Automobile Sales",
            "type":"Retail Goods"
        }
    ],
    "sg:phone":"+1 281 858 5103",
    "sg:postcode":"77084",
    "sg:province":"TX",
    "sg:tags":[
        "instrument",
        "aircraft"
    ],
    "wof:name":"Weschler Instruments",
    "wof:placetype":"venue"
},
  "geometry": {"coordinates":[-95.676058,29.858962],"type":"Point"}
}