{
  "type": "Feature",
  "properties": {
    "iso:country":"US",
    "sg:address":"401 Weaver St",
    "sg:city":"Cedar Hill",
    "sg:classifiers":[
        {
            "category":"Personal",
            "subcategory":"Beauty Salon",
            "type":"Services"
        }
    ],
    "sg:phone":"+1 972 291 3936",
    "sg:postcode":"75104",
    "sg:province":"TX",
    "sg:tags":[
        "shop"
    ],
    "wof:name":"Sally Ann Koblick",
    "wof:placetype":"venue"
},
  "geometry": {"coordinates":[-96.93717100000001,32.581103],"type":"Point"}
}