{
  "type": "Feature",
  "properties": {
    "iso:country":"US",
    "sg:address":"5950 Sherry Ln",
    "sg:city":"Dallas",
    "sg:classifiers":[
        {
            "category":"Banks & Credit Unions",
            "subcategory":"Bank",
            "type":"Services"
        }
    ],
    "sg:phone":"+1 214 706 7000",
    "sg:postcode":"75225",
    "sg:province":"TX",
    "sg:tags":[
        "business"
    ],
    "wof:name":"Fleet",
    "wof:placetype":"venue"
},
  "geometry": {"coordinates":[-96.81008,32.862213],"type":"Point"}
}