{
  "type": "Feature",
  "properties": {
    "iso:country":"US",
    "sg:address":"401 N Colorado St",
    "sg:city":"Midland",
    "sg:classifiers":[
        {
            "category":"Real Estate",
            "subcategory":"Real Estate Operator",
            "type":"Services"
        }
    ],
    "sg:phone":"+1 432 682 4251",
    "sg:postcode":"79701",
    "sg:province":"TX",
    "sg:tags":[
        "property",
        "oil"
    ],
    "wof:name":"Iverson Exploration",
    "wof:placetype":"venue"
},
  "geometry": {"coordinates":[-102.07695,32.001635],"type":"Point"}
}