{
  "type": "Feature",
  "properties": {
    "iso:country":"US",
    "sg:address":"5126 Ashbrook Dr",
    "sg:city":"Houston",
    "sg:classifiers":[
        {
            "category":"Utilities",
            "subcategory":"Telephone",
            "type":"Services"
        }
    ],
    "sg:phone":"+1 800 235 9800",
    "sg:postcode":"77081",
    "sg:province":"TX",
    "sg:tags":[
        "communication"
    ],
    "wof:name":"Southwestern Bell Telephone LP",
    "wof:placetype":"venue"
},
  "geometry": {"coordinates":[-95.468538,29.714854],"type":"Point"}
}