{
  "type": "Feature",
  "properties": {
    "iso:country":"US",
    "sg:address":"7320 N Mo Pac Expy",
    "sg:city":"Austin",
    "sg:classifiers":[
        {
            "category":"Wholesale",
            "subcategory":"Computers",
            "type":"Manufacturing & Wholesale Goods"
        }
    ],
    "sg:phone":"+1 512 452 0651",
    "sg:postcode":"78731",
    "sg:province":"TX",
    "sg:tags":[
        "supp",
        "equipment",
        "peripheral"
    ],
    "wof:name":"ARC",
    "wof:placetype":"venue"
},
  "geometry": {"coordinates":[-97.747424,30.355712],"type":"Point"}
}