{
  "type": "Feature",
  "properties": {
    "iso:country":"US",
    "sg:address":"2423 Greenport Dr",
    "sg:city":"Dallas",
    "sg:classifiers":[
        {
            "category":"Insurance",
            "subcategory":"Insurance Agent",
            "type":"Services"
        }
    ],
    "sg:phone":"+1 214 367 8510",
    "sg:postcode":"75228",
    "sg:province":"TX",
    "sg:tags":[
        "consulting",
        "management"
    ],
    "wof:name":"Bill Morrison CLU Chfc",
    "wof:placetype":"venue"
},
  "geometry": {"coordinates":[-96.698514,32.80552],"type":"Point"}
}