{
  "type": "Feature",
  "properties": {
    "iso:country":"US",
    "sg:address":"505 Benton Dr",
    "sg:city":"Allen",
    "sg:classifiers":[
        {
            "category":"Shopping",
            "type":"Retail Goods"
        }
    ],
    "sg:phone":"+1 972 727 8088",
    "sg:postcode":"75013",
    "sg:province":"TX",
    "sg:tags":[
        "merchandise"
    ],
    "wof:name":"Moments of Love Pet Care",
    "wof:placetype":"venue"
},
  "geometry": {"coordinates":[-96.687347,33.105929],"type":"Point"}
}