{
  "type": "Feature",
  "properties": {
    "iso:country":"US",
    "sg:address":"605 Pecan Grove Rd",
    "sg:city":"Austin",
    "sg:classifiers":[
        {
            "category":"Professional",
            "type":"Services"
        }
    ],
    "sg:phone":"+1 512 447 3881",
    "sg:postcode":"78704",
    "sg:province":"TX",
    "sg:tags":[
        "establishment"
    ],
    "wof:name":"Lionshead Designs",
    "wof:placetype":"venue"
},
  "geometry": {"coordinates":[-97.742379,30.248828],"type":"Point"}
}