{
  "type": "Feature",
  "properties": {
    "iso:country":"US",
    "sg:address":"1416 Cranford Dr",
    "sg:city":"Garland",
    "sg:classifiers":[
        {
            "category":"Professional",
            "subcategory":"Engineering",
            "type":"Services"
        }
    ],
    "sg:phone":"+1 972 926 1133",
    "sg:postcode":"75041",
    "sg:province":"TX",
    "sg:tags":[
        "engineer"
    ],
    "sg:website":"www.airhog.com",
    "wof:name":"Airhog.Com Inc",
    "wof:placetype":"venue"
},
  "geometry": {"coordinates":[-96.65122,32.877053],"type":"Point"}
}