{
  "type": "Feature",
  "properties": {
    "iso:country":"US",
    "sg:address":"4602 Cheek St",
    "sg:city":"Beaumont",
    "sg:classifiers":[
        {
            "category":"Organizations",
            "subcategory":"Professional Association",
            "type":"Services"
        }
    ],
    "sg:phone":"+1 409 880 2276",
    "sg:postcode":"77705",
    "sg:province":"TX",
    "wof:name":"Baptist Student Ministry",
    "wof:placetype":"venue"
},
  "geometry": {"coordinates":[-94.07707600000001,30.040147],"type":"Point"}
}