{
  "type": "Feature",
  "properties": {
    "iso:country":"US",
    "sg:address":"2214 FM 523",
    "sg:city":"Freeport",
    "sg:classifiers":[
        {
            "category":"Food & Beverages",
            "subcategory":"Meat & Fish",
            "type":"Retail Goods"
        }
    ],
    "sg:phone":"+1 979 230 0472",
    "sg:postcode":"77541",
    "sg:province":"TX",
    "sg:tags":[
        "seafood"
    ],
    "wof:name":"Freeport Seafood & Bait",
    "wof:placetype":"venue"
},
  "geometry": {"coordinates":[-95.330934,28.993049],"type":"Point"}
}