{
  "type": "Feature",
  "properties": {
    "iso:country":"US",
    "sg:address":"180 Malone St",
    "sg:city":"Houston",
    "sg:classifiers":[
        {
            "category":"Communications",
            "subcategory":"Film & Video Production",
            "type":"Services"
        }
    ],
    "sg:phone":"+1 713 718 7765",
    "sg:postcode":"77007",
    "sg:province":"TX",
    "sg:tags":[
        "motion",
        "picture"
    ],
    "wof:name":"Temenos Production Inc",
    "wof:placetype":"venue"
},
  "geometry": {"coordinates":[-95.419134,29.761501],"type":"Point"}
}