{
  "type": "Feature",
  "properties": {
    "iso:country":"US",
    "sg:address":"6301 Rolling Wood Trl",
    "sg:city":"Fort Worth",
    "sg:classifiers":[
        {
            "category":"Building & Trades",
            "subcategory":"Landscaping Services",
            "type":"Services"
        }
    ],
    "sg:phone":"+1 817 237 1145",
    "sg:postcode":"76135",
    "sg:province":"TX",
    "sg:tags":[
        "lawn",
        "maintenance",
        "grounds"
    ],
    "wof:name":"Evergreen Lawn Care Svc",
    "wof:placetype":"venue"
},
  "geometry": {"coordinates":[-97.493307,32.836974],"type":"Point"}
}