{
  "type": "Feature",
  "properties": {
    "iso:country":"US",
    "sg:address":"25534 I- 45",
    "sg:city":"Spring",
    "sg:classifiers":[
        {
            "category":"Shopping",
            "subcategory":"Clothing, Apparel, & Fashions",
            "type":"Retail Goods"
        }
    ],
    "sg:phone":"+1 281 292 7141",
    "sg:postcode":"77386",
    "sg:province":"TX",
    "sg:tags":[
        "shop",
        "tuxedo",
        "dress",
        "rental",
        "casual",
        "formal"
    ],
    "wof:name":"Affinity",
    "wof:placetype":"venue"
},
  "geometry": {"coordinates":[-95.443316,30.130126],"type":"Point"}
}