{
  "type": "Feature",
  "properties": {
    "iso:country":"US",
    "sg:address":"11400A Burnet Rd",
    "sg:city":"Austin",
    "sg:classifiers":[
        {
            "category":"Restaurant",
            "type":"Food & Drink"
        }
    ],
    "sg:phone":"+1 512 835 5900",
    "sg:postcode":"78758",
    "sg:province":"TX",
    "wof:name":"Kona Grill",
    "wof:placetype":"venue"
},
  "geometry": {"coordinates":[-97.719262,30.39868],"type":"Point"}
}