{
  "type": "Feature",
  "properties": {
    "iso:country":"US",
    "sg:address":"580 W Arapaho Rd",
    "sg:city":"Richardson",
    "sg:classifiers":[
        {
            "category":"Retail",
            "subcategory":"Auto Repair",
            "type":"Services"
        }
    ],
    "sg:phone":"+1 972 238 1488",
    "sg:postcode":"75080",
    "sg:province":"TX",
    "sg:tags":[
        "glass",
        "replacement"
    ],
    "wof:name":"Euro Auto Glass",
    "wof:placetype":"venue"
},
  "geometry": {"coordinates":[-96.73718599999999,32.963215],"type":"Point"}
}