{
  "type": "Feature",
  "properties": {
    "iso:country":"US",
    "sg:address":"2112 Trawood Dr",
    "sg:city":"El Paso",
    "sg:classifiers":[
        {
            "category":"Banks & Credit Unions",
            "subcategory":"Bank",
            "type":"Services"
        }
    ],
    "sg:phone":"+1 325 629 8200",
    "sg:postcode":"79935",
    "sg:province":"TX",
    "sg:tags":[
        "loan",
        "mortgage",
        "real estate"
    ],
    "wof:name":"American Homefront Mortgage",
    "wof:placetype":"venue"
},
  "geometry": {"coordinates":[-106.328822,31.765566],"type":"Point"}
}