{
  "type": "Feature",
  "properties": {
    "iso:country":"US",
    "sg:address":"430 6th St",
    "sg:city":"Honey Grove",
    "sg:classifiers":[
        {
            "category":"Government",
            "subcategory":"Fire Station",
            "type":"Public Place"
        }
    ],
    "sg:phone":"+1 903 378 2666",
    "sg:postcode":"75446",
    "sg:province":"TX",
    "sg:tags":[
        "department"
    ],
    "wof:name":"Honey Grove Ambulance Svc",
    "wof:placetype":"venue"
},
  "geometry": {"coordinates":[-95.90919100000001,33.582667],"type":"Point"}
}