{
  "type": "Feature",
  "properties": {
    "iso:country":"US",
    "sg:address":"5506 Lands End St",
    "sg:city":"Austin",
    "sg:classifiers":[
        {
            "category":"Real Estate",
            "subcategory":"Real Estate Services",
            "type":"Services"
        },
        {
            "category":"Real Estate",
            "subcategory":"Real Estate Agent",
            "type":"Services"
        }
    ],
    "sg:phone":"+1 512 394 5046",
    "sg:postcode":"78734",
    "sg:province":"TX",
    "sg:tags":[
        "buyer",
        "broker"
    ],
    "wof:name":"Lands End Realty",
    "wof:placetype":"venue"
},
  "geometry": {"coordinates":[-97.918497,30.414474],"type":"Point"}
}