{
  "type": "Feature",
  "properties": {
    "iso:country":"US",
    "sg:address":"7010 Industrial Ave",
    "sg:city":"El Paso",
    "sg:classifiers":[
        {
            "category":"Building & Trades",
            "subcategory":"Construction",
            "type":"Services"
        }
    ],
    "sg:phone":"+1 915 775 1848",
    "sg:postcode":"79915",
    "sg:province":"TX",
    "sg:tags":[
        "general",
        "contractor"
    ],
    "wof:name":"Giordano Construction",
    "wof:placetype":"venue"
},
  "geometry": {"coordinates":[-106.38386199999999,31.770539],"type":"Point"}
}