{
  "type": "Feature",
  "properties": {
    "iso:country":"US",
    "sg:address":"7802 Fulton St",
    "sg:city":"Houston",
    "sg:classifiers":[
        {
            "category":"Food & Beverages",
            "subcategory":"Groceries & Convenience Stores",
            "type":"Retail Goods"
        }
    ],
    "sg:phone":"+1 713 692 5580",
    "sg:postcode":"77022",
    "sg:province":"TX",
    "sg:tags":[
        "grocer"
    ],
    "wof:name":"K Food Store",
    "wof:placetype":"venue"
},
  "geometry": {"coordinates":[-95.37585199999999,29.832872],"type":"Point"}
}