{
  "type": "Feature",
  "properties": {
    "iso:country":"US",
    "sg:address":"2011 Baker Dr",
    "sg:city":"Denton",
    "sg:classifiers":[
        {
            "category":"Social Services",
            "subcategory":"Child Care",
            "type":"Services"
        }
    ],
    "sg:phone":"+1 940 498 0972",
    "sg:postcode":"76210",
    "sg:province":"TX",
    "sg:tags":[
        "day"
    ],
    "wof:name":"Landphair Lance Terry Wee",
    "wof:placetype":"venue"
},
  "geometry": {"coordinates":[-97.079667,33.139762],"type":"Point"}
}