{
  "type": "Feature",
  "properties": {
    "iso:country":"US",
    "sg:address":"5041 Robertson Dr",
    "sg:city":"Abilene",
    "sg:classifiers":[
        {
            "category":"Shopping",
            "subcategory":"Computers & Home Electronics",
            "type":"Retail Goods"
        }
    ],
    "sg:phone":"+1 325 795 1663",
    "sg:postcode":"79606",
    "sg:province":"TX",
    "wof:name":"Brown Satellite",
    "wof:placetype":"venue"
},
  "geometry": {"coordinates":[-99.753179,32.390254],"type":"Point"}
}