{
  "type": "Feature",
  "properties": {
    "iso:country":"US",
    "sg:address":"2807 Allen Street Suite 665",
    "sg:city":"Dallas",
    "sg:classifiers":[
        {
            "category":"Banks & Credit Unions",
            "subcategory":"Financial Services",
            "type":"Services"
        }
    ],
    "sg:phone":"+1 214 871 8778",
    "sg:postcode":"75204",
    "sg:province":"TX",
    "sg:website":"www.mortgagejob.com",
    "wof:name":"Mortgage Bankers Consultants",
    "wof:placetype":"venue"
},
  "geometry": {"coordinates":[-96.801272,32.800872],"type":"Point"}
}