{
  "type": "Feature",
  "properties": {
    "iso:country":"US",
    "sg:address":"16401 Lakeview Dr",
    "sg:city":"Houston",
    "sg:classifiers":[
        {
            "category":"Government",
            "subcategory":"Police Station",
            "type":"Public Place"
        }
    ],
    "sg:phone":"+1 713 466 2119",
    "sg:postcode":"77040",
    "sg:province":"TX",
    "sg:tags":[
        "protection"
    ],
    "wof:name":"Police Dept",
    "wof:placetype":"venue"
},
  "geometry": {"coordinates":[-95.57078,29.884248],"type":"Point"}
}