{
  "type": "Feature",
  "properties": {
    "iso:country":"US",
    "sg:address":"319 Ammann Rd",
    "sg:city":"Boerne",
    "sg:classifiers":[
        {
            "category":"Professional",
            "subcategory":"Advertising",
            "type":"Services"
        }
    ],
    "sg:phone":"+1 830 229 5111",
    "sg:postcode":"78006",
    "sg:province":"TX",
    "sg:tags":[
        "medium",
        "production"
    ],
    "wof:name":"Manahuilla Media Company",
    "wof:placetype":"venue"
},
  "geometry": {"coordinates":[-98.638035,29.785385],"type":"Point"}
}