{
  "type": "Feature",
  "properties": {
    "iso:country":"US",
    "sg:address":"4807 West Ave",
    "sg:city":"San Antonio",
    "sg:classifiers":[
        {
            "category":"Freight",
            "type":"Transportation"
        }
    ],
    "sg:phone":"+1 210 320 5757",
    "sg:postcode":"78213",
    "sg:province":"TX",
    "sg:tags":[
        "delivery"
    ],
    "wof:name":"24/7 Courier",
    "wof:placetype":"venue"
},
  "geometry": {"coordinates":[-98.52602,29.510085],"type":"Point"}
}