{
  "type": "Feature",
  "properties": {
    "iso:country":"US",
    "sg:address":"1408 Hailey St",
    "sg:city":"Sweetwater",
    "sg:classifiers":[
        {
            "category":"Health Services",
            "subcategory":"Doctor",
            "type":"Services"
        }
    ],
    "sg:phone":"+1 325 235 8020",
    "sg:postcode":"79556",
    "sg:province":"TX",
    "wof:name":"Jason K Browning DDS",
    "wof:placetype":"venue"
},
  "geometry": {"coordinates":[-100.400873,32.483318],"type":"Point"}
}