{
  "type": "Feature",
  "properties": {
    "iso:country":"US",
    "sg:address":"1912 Baird Farm Rd",
    "sg:city":"Arlington",
    "sg:classifiers":[
        {
            "category":"Shopping",
            "subcategory":"Bicycles & Sporting Goods",
            "type":"Retail Goods"
        }
    ],
    "sg:phone":"+1 817 459 2122",
    "sg:postcode":"76006",
    "sg:province":"TX",
    "wof:name":"D F W Arms Inc",
    "wof:placetype":"venue"
},
  "geometry": {"coordinates":[-97.085408,32.766925],"type":"Point"}
}