{
  "type": "Feature",
  "properties": {
    "iso:country":"US",
    "sg:address":"807 Baylor Dr",
    "sg:city":"Longview",
    "sg:classifiers":[
        {
            "category":"Health Services",
            "subcategory":"Health Practitioner",
            "type":"Services"
        }
    ],
    "sg:phone":"+1 903 753 7600",
    "sg:postcode":"75601",
    "sg:province":"TX",
    "sg:tags":[
        "nurse",
        "registry"
    ],
    "wof:name":"Med-Staff Inc",
    "wof:placetype":"venue"
},
  "geometry": {"coordinates":[-94.751352,32.510196],"type":"Point"}
}