{
  "type": "Feature",
  "properties": {
    "iso:country":"US",
    "sg:address":"9214 Beckenham Dr",
    "sg:city":"Houston",
    "sg:classifiers":[
        {
            "category":"Retail",
            "subcategory":"Photofinishing",
            "type":"Services"
        }
    ],
    "sg:phone":"+1 281 561 7275",
    "sg:postcode":"77099",
    "sg:province":"TX",
    "sg:tags":[
        "laboratory"
    ],
    "wof:name":"Huangs Photo",
    "wof:placetype":"venue"
},
  "geometry": {"coordinates":[-95.61295200000001,29.678154],"type":"Point"}
}