{
  "type": "Feature",
  "properties": {
    "iso:country":"US",
    "sg:address":"9028 W Little York Rd",
    "sg:city":"Houston",
    "sg:classifiers":[
        {
            "category":"Retail",
            "subcategory":"Auto Repair",
            "type":"Services"
        }
    ],
    "sg:phone":"+1 713 466 4461",
    "sg:postcode":"77040",
    "sg:province":"TX",
    "sg:tags":[
        "body",
        "shop"
    ],
    "wof:name":"T & T Auto Service & Body Shop",
    "wof:placetype":"venue"
},
  "geometry": {"coordinates":[-95.535202,29.867901],"type":"Point"}
}