{
  "type": "Feature",
  "properties": {
    "iso:country":"US",
    "sg:address":"7 Ivy Pond Pl",
    "sg:city":"Spring",
    "sg:classifiers":[
        {
            "category":"Professional",
            "type":"Services"
        }
    ],
    "sg:phone":"+1 281 363 3689",
    "sg:postcode":"77381",
    "sg:province":"TX",
    "wof:name":"Ivy Pond LLC",
    "wof:placetype":"venue"
},
  "geometry": {"coordinates":[-95.530208,30.191694],"type":"Point"}
}