{
  "type": "Feature",
  "properties": {
    "iso:country":"US",
    "sg:address":"2563 Berner St",
    "sg:city":"Fort Worth",
    "sg:classifiers":[
        {
            "category":"Wholesale",
            "subcategory":"Motor Vehicles",
            "type":"Manufacturing & Wholesale Goods"
        }
    ],
    "sg:phone":"+1 817 624 5849",
    "sg:postcode":"76111",
    "sg:province":"TX",
    "sg:tags":[
        "trailer"
    ],
    "wof:name":"Atlas Truck Of Texas",
    "wof:placetype":"venue"
},
  "geometry": {"coordinates":[-97.31427499999999,32.802262],"type":"Point"}
}