{
  "type": "Feature",
  "properties": {
    "iso:country":"US",
    "sg:address":"13403 Boyer Ln",
    "sg:city":"Houston",
    "sg:classifiers":[
        {
            "category":"Social Services",
            "subcategory":"Child Care",
            "type":"Services"
        }
    ],
    "sg:phone":"+1 713 453 1076",
    "sg:postcode":"77015",
    "sg:province":"TX",
    "wof:name":"Patricia Lynn Demery",
    "wof:placetype":"venue"
},
  "geometry": {"coordinates":[-95.186042,29.799726],"type":"Point"}
}