{
  "type": "Feature",
  "properties": {
    "iso:country":"US",
    "sg:address":"6144 Airline Dr",
    "sg:city":"Houston",
    "sg:classifiers":[
        {
            "category":"Building & Trades",
            "subcategory":"Construction",
            "type":"Services"
        }
    ],
    "sg:phone":"+1 713 691 5171",
    "sg:postcode":"77076",
    "sg:province":"TX",
    "sg:tags":[
        "contractor"
    ],
    "wof:name":"Rojas Tile",
    "wof:placetype":"venue"
},
  "geometry": {"coordinates":[-95.384552,29.85508],"type":"Point"}
}