{
  "type": "Feature",
  "properties": {
    "iso:country":"US",
    "sg:address":"2321 River Hills Rd",
    "sg:city":"Austin",
    "sg:classifiers":[
        {
            "category":"Real Estate",
            "subcategory":"Real Estate Agent",
            "type":"Services"
        }
    ],
    "sg:phone":"+1 512 263 5111",
    "sg:postcode":"78733",
    "sg:province":"TX",
    "wof:name":"Bradley Properties",
    "wof:placetype":"venue"
},
  "geometry": {"coordinates":[-97.849277,30.342013],"type":"Point"}
}