{
  "type": "Feature",
  "properties": {
    "iso:country":"US",
    "sg:address":"4319 Shadow Oak Ln",
    "sg:city":"Austin",
    "sg:classifiers":[
        {
            "category":"Shopping",
            "subcategory":"Bicycles & Sporting Goods",
            "type":"Retail Goods"
        }
    ],
    "sg:phone":"+1 512 306 0589",
    "sg:postcode":"78746",
    "sg:province":"TX",
    "wof:name":"Db Custom Golf",
    "wof:placetype":"venue"
},
  "geometry": {"coordinates":[-97.78711,30.334194],"type":"Point"}
}