{
  "type": "Feature",
  "properties": {
    "iso:country":"US",
    "sg:address":"300 W 6th St",
    "sg:city":"Austin",
    "sg:classifiers":[
        {
            "category":"Banks & Credit Unions",
            "subcategory":"Investment Brokerage",
            "type":"Services"
        }
    ],
    "sg:phone":"+1 512 542 7870",
    "sg:postcode":"78701",
    "sg:province":"TX",
    "sg:tags":[
        "stock",
        "bond"
    ],
    "wof:name":"Wachovia Securities",
    "wof:placetype":"venue"
},
  "geometry": {"coordinates":[-97.74625899999999,30.269024],"type":"Point"}
}