{
  "type": "Feature",
  "properties": {
    "iso:country":"US",
    "sg:address":"807 S Victory Dr",
    "sg:city":"Houston",
    "sg:classifiers":[
        {
            "category":"Retail",
            "subcategory":"Auto Repair",
            "type":"Services"
        }
    ],
    "sg:phone":"+1 281 847 0769",
    "sg:postcode":"77088",
    "sg:province":"TX",
    "sg:tags":[
        "general"
    ],
    "wof:name":"A&H Auto Shop",
    "wof:placetype":"venue"
},
  "geometry": {"coordinates":[-95.41871500000001,29.870749],"type":"Point"}
}