{
  "type": "Feature",
  "properties": {
    "iso:country":"US",
    "sg:address":"1301 Whitaker Ave",
    "sg:city":"Odessa",
    "sg:classifiers":[
        {
            "category":"Real Estate",
            "subcategory":"Real Estate Operator",
            "type":"Services"
        }
    ],
    "sg:phone":"+1 432 337 3250",
    "sg:postcode":"79763",
    "sg:province":"TX",
    "sg:tags":[
        "building",
        "apartment"
    ],
    "wof:name":"Madera Pointe Apartments",
    "wof:placetype":"venue"
},
  "geometry": {"coordinates":[-102.386875,31.850519],"type":"Point"}
}