{
  "type": "Feature",
  "properties": {
    "iso:country":"US",
    "sg:address":"1600 E Southlake Blvd",
    "sg:city":"Southlake",
    "sg:classifiers":[
        {
            "category":"Home & Garden",
            "subcategory":"Furniture",
            "type":"Retail Goods"
        }
    ],
    "sg:phone":"+1 817 416 1515",
    "sg:postcode":"76092",
    "sg:province":"TX",
    "wof:name":"Drexel Heritage",
    "wof:placetype":"venue"
},
  "geometry": {"coordinates":[-97.127095,32.941058],"type":"Point"}
}