{
  "type": "Feature",
  "properties": {
    "iso:country":"US",
    "sg:address":"3204 N Main St",
    "sg:city":"Fort Worth",
    "sg:classifiers":[
        {
            "category":"Shopping",
            "subcategory":"Discount & Variety Stores",
            "type":"Retail Goods"
        },
        {
            "category":"Shopping",
            "subcategory":"Department Store",
            "type":"Retail Goods"
        }
    ],
    "sg:phone":"+1 817 624 2115",
    "sg:postcode":"76106",
    "sg:province":"TX",
    "sg:tags":[
        "shop"
    ],
    "wof:name":"Family Dollar Stores",
    "wof:placetype":"venue"
},
  "geometry": {"coordinates":[-97.351412,32.804638],"type":"Point"}
}