{
  "type": "Feature",
  "properties": {
    "iso:country":"US",
    "sg:address":"2000 N 23rd St",
    "sg:city":"Mcallen",
    "sg:classifiers":[
        {
            "category":"Education",
            "subcategory":"Library",
            "type":"Public Place"
        }
    ],
    "sg:phone":"+1 956 971 4400",
    "sg:postcode":"78501",
    "sg:province":"TX",
    "wof:name":"Mcauliffe Library",
    "wof:placetype":"venue"
},
  "geometry": {"coordinates":[-98.242239,26.224069],"type":"Point"}
}