{
  "type": "Feature",
  "properties": {
    "iso:country":"US",
    "sg:address":"6912 US Hwy 175",
    "sg:city":"Kaufman",
    "sg:classifiers":[
        {
            "category":"Building & Trades",
            "subcategory":"Landscaping Services",
            "type":"Services"
        }
    ],
    "sg:phone":"+1 972 932 8830",
    "sg:postcode":"75142",
    "sg:province":"TX",
    "sg:tags":[
        "landscape"
    ],
    "wof:name":"Billington Landscaping",
    "wof:placetype":"venue"
},
  "geometry": {"coordinates":[-96.387906,32.607822],"type":"Point"}
}