{
  "type": "Feature",
  "properties": {
    "iso:country":"US",
    "sg:address":"5410 Bell St",
    "sg:city":"Amarillo",
    "sg:classifiers":[
        {
            "category":"Professional",
            "type":"Services"
        }
    ],
    "sg:phone":"+1 806 331 4840",
    "sg:postcode":"79109",
    "sg:province":"TX",
    "wof:name":"Huds Office",
    "wof:placetype":"venue"
},
  "geometry": {"coordinates":[-101.902019,35.146698],"type":"Point"}
}