{
  "type": "Feature",
  "properties": {
    "iso:country":"US",
    "sg:address":"2801 Cantura Dr",
    "sg:city":"Mesquite",
    "sg:classifiers":[
        {
            "category":"Building & Trades",
            "subcategory":"Plumbing",
            "type":"Services"
        }
    ],
    "sg:phone":"+1 972 222 2701",
    "sg:postcode":"75181",
    "sg:province":"TX",
    "sg:tags":[
        "contractor"
    ],
    "wof:name":"Above All Plumbing Service",
    "wof:placetype":"venue"
},
  "geometry": {"coordinates":[-96.567948,32.742545],"type":"Point"}
}