{
  "type": "Feature",
  "properties": {
    "iso:country":"US",
    "sg:address":"14520 Memorial Dr",
    "sg:city":"Houston",
    "sg:classifiers":[
        {
            "category":"Restaurant",
            "type":"Food & Drink"
        }
    ],
    "sg:phone":"+1 281 497 3977",
    "sg:postcode":"77079",
    "sg:province":"TX",
    "sg:tags":[
        "eating",
        "pizza"
    ],
    "sg:website":"http://www.dominospizza.com",
    "wof:name":"Domino's Pizza",
    "wof:placetype":"venue"
},
  "geometry": {"coordinates":[-95.60337800000001,29.770141],"type":"Point"}
}