{
  "type": "Feature",
  "properties": {
    "iso:country":"US",
    "sg:address":"12900 Ranch Road 12",
    "sg:city":"Wimberley",
    "sg:classifiers":[
        {
            "category":"Restaurant",
            "type":"Food & Drink"
        }
    ],
    "sg:phone":"+1 512 847 2528",
    "sg:postcode":"78676",
    "sg:province":"TX",
    "wof:name":"Joffas On Square",
    "wof:placetype":"venue"
},
  "geometry": {"coordinates":[-98.08815199999999,29.992931],"type":"Point"}
}