{
  "type": "Feature",
  "properties": {
    "iso:country":"US",
    "sg:address":"606 Heritage Cove",
    "sg:city":"Hutto",
    "sg:classifiers":[
        {
            "category":"Farming",
            "subcategory":"Farm",
            "type":"Manufacturing & Wholesale Goods"
        }
    ],
    "sg:phone":"+1 512 869 1272",
    "sg:postcode":"78634",
    "sg:province":"TX",
    "sg:tags":[
        "crop",
        "general"
    ],
    "wof:name":"Grasshopper Hill Farm",
    "wof:placetype":"venue"
},
  "geometry": {"coordinates":[-97.551726,30.625613],"type":"Point"}
}