{
  "type": "Feature",
  "properties": {
    "iso:country":"US",
    "sg:address":"8440 Easton Commons",
    "sg:city":"Houston",
    "sg:classifiers":[
        {
            "category":"Real Estate",
            "subcategory":"Real Estate Operator",
            "type":"Services"
        }
    ],
    "sg:phone":"+1 888 283 2162",
    "sg:postcode":"77095",
    "sg:province":"TX",
    "sg:tags":[
        "apartment"
    ],
    "wof:name":"Peppermill Place Apartments",
    "wof:placetype":"venue"
},
  "geometry": {"coordinates":[-95.629715,29.899424],"type":"Point"}
}