{
  "type": "Feature",
  "properties": {
    "iso:country":"US",
    "sg:address":"2334 W Buckingham Rd # 220",
    "sg:city":"Garland",
    "sg:classifiers":[
        {
            "category":"Personal",
            "subcategory":"Beauty Salon",
            "type":"Services"
        },
        {
            "category":"Personal",
            "subcategory":"Barber",
            "type":"Services"
        }
    ],
    "sg:phone":"+1 972 487 5999",
    "sg:postcode":"75042",
    "sg:province":"TX",
    "sg:tags":[
        "hair",
        "accessory",
        "stylist",
        "supply"
    ],
    "sg:website":"http://www.greatclips.com/",
    "wof:name":"Great Clips",
    "wof:placetype":"venue"
},
  "geometry": {"coordinates":[-96.66276999999999,32.930394],"type":"Point"}
}