{
  "type": "Feature",
  "properties": {
    "iso:country":"US",
    "sg:address":"981 S Mason Rd",
    "sg:city":"Katy",
    "sg:classifiers":[
        {
            "category":"Banks & Credit Unions",
            "subcategory":"Bank",
            "type":"Services"
        }
    ],
    "sg:phone":"+1 281 492 3250",
    "sg:postcode":"77450",
    "sg:province":"TX",
    "sg:tags":[
        "loan",
        "real estate"
    ],
    "wof:name":"Countrywide Home Loans",
    "wof:placetype":"venue"
},
  "geometry": {"coordinates":[-95.75157400000001,29.766472],"type":"Point"}
}