{
  "type": "Feature",
  "properties": {
    "iso:country":"US",
    "sg:address":"3 Marine Dr",
    "sg:city":"Harlingen",
    "sg:classifiers":[
        {
            "category":"Shopping",
            "subcategory":"Bicycles & Sporting Goods",
            "type":"Retail Goods"
        }
    ],
    "sg:phone":"+1 956 423 5387",
    "sg:postcode":"78550",
    "sg:province":"TX",
    "wof:name":"Sportsmans Attic",
    "wof:placetype":"venue"
},
  "geometry": {"coordinates":[-97.66792100000001,26.227851],"type":"Point"}
}