{
  "type": "Feature",
  "properties": {
    "iso:country":"US",
    "sg:address":"527 N Village Creek Pkwy",
    "sg:city":"Lumberton",
    "sg:classifiers":[
        {
            "category":"Shopping",
            "subcategory":"Computers & Home Electronics",
            "type":"Retail Goods"
        }
    ],
    "sg:phone":"+1 409 755 4421",
    "sg:postcode":"77657",
    "sg:province":"TX",
    "wof:name":"Frazier Computer Services",
    "wof:placetype":"venue"
},
  "geometry": {"coordinates":[-94.190082,30.26188],"type":"Point"}
}