{
  "type": "Feature",
  "properties": {
    "iso:country":"US",
    "sg:address":"1533 State Hwy 276",
    "sg:city":"Quinlan",
    "sg:classifiers":[
        {
            "category":"Government",
            "subcategory":"Office",
            "type":"Public Place"
        }
    ],
    "sg:phone":"+1 903 447 2285",
    "sg:postcode":"75474",
    "sg:province":"TX",
    "sg:tags":[
        "village"
    ],
    "wof:name":"West Tawakoni City Office",
    "wof:placetype":"venue"
},
  "geometry": {"coordinates":[-96.050949,32.903518],"type":"Point"}
}