{
  "type": "Feature",
  "properties": {
    "iso:country":"US",
    "sg:address":"7241 Blanco Rd",
    "sg:city":"San Antonio",
    "sg:classifiers":[
        {
            "category":"Professional",
            "type":"Services"
        }
    ],
    "sg:phone":"+1 210 342 2620",
    "sg:postcode":"78216",
    "sg:province":"TX",
    "sg:tags":[
        "establishment"
    ],
    "wof:name":"Advantage Wrieless",
    "wof:placetype":"venue"
},
  "geometry": {"coordinates":[-98.50507399999999,29.524884],"type":"Point"}
}