{
  "type": "Feature",
  "properties": {
    "iso:country":"US",
    "sg:address":"101 E Park Blvd",
    "sg:city":"Plano",
    "sg:classifiers":[
        {
            "category":"Professional",
            "subcategory":"Computer Services",
            "type":"Services"
        }
    ],
    "sg:phone":"+1 972 516 3864",
    "sg:postcode":"75074",
    "sg:province":"TX",
    "sg:tags":[
        "prepackaged",
        "software"
    ],
    "wof:name":"Documentum Inc",
    "wof:placetype":"venue"
},
  "geometry": {"coordinates":[-96.706355,33.028763],"type":"Point"}
}