{
  "type": "Feature",
  "properties": {
    "iso:country":"US",
    "sg:address":"1409 Oceanside Ln",
    "sg:city":"League City",
    "sg:classifiers":[
        {
            "category":"Recreation",
            "subcategory":"Marina",
            "type":"Entertainment"
        }
    ],
    "sg:phone":"+1 281 538 2200",
    "sg:postcode":"77573",
    "sg:province":"TX",
    "wof:name":"Marina Village",
    "wof:placetype":"venue"
},
  "geometry": {"coordinates":[-95.063948,29.549482],"type":"Point"}
}