{
  "type": "Feature",
  "properties": {
    "iso:country":"US",
    "sg:address":"615 Gary Ln",
    "sg:city":"El Paso",
    "sg:classifiers":[
        {
            "category":"Shopping",
            "subcategory":"Computers & Home Electronics",
            "type":"Retail Goods"
        }
    ],
    "sg:phone":"+1 915 581 5303",
    "sg:postcode":"79922",
    "sg:province":"TX",
    "wof:name":"Cybernotes",
    "wof:placetype":"venue"
},
  "geometry": {"coordinates":[-106.58069,31.816242],"type":"Point"}
}