{
  "type": "Feature",
  "properties": {
    "iso:country":"US",
    "sg:address":"8105 Shoal Creek Blvd Ste. A",
    "sg:city":"Austin",
    "sg:classifiers":[
        {
            "category":"Health Services",
            "subcategory":"Optometrist",
            "type":"Services"
        },
        {
            "category":"Shopping",
            "subcategory":"Optical Goods",
            "type":"Retail Goods"
        }
    ],
    "sg:phone":"+1 512 454 4641",
    "sg:postcode":"78757",
    "sg:province":"TX",
    "sg:tags":[
        "lens",
        "contact"
    ],
    "sg:website":"www.austinoptometrygrp.com",
    "wof:name":"Austin Optometry Group",
    "wof:placetype":"venue"
},
  "geometry": {"coordinates":[-97.738563,30.364882],"type":"Point"}
}