{
  "type": "Feature",
  "properties": {
    "iso:country":"US",
    "sg:address":"1014 W 18th St",
    "sg:city":"Houston",
    "sg:classifiers":[
        {
            "category":"Wholesale",
            "subcategory":"Auto Parts",
            "type":"Manufacturing & Wholesale Goods"
        }
    ],
    "sg:phone":"+1 713 869 1262",
    "sg:postcode":"77008",
    "sg:province":"TX",
    "sg:tags":[
        "equipment",
        "truck"
    ],
    "wof:name":"Mid Coast Rebuilders",
    "wof:placetype":"venue"
},
  "geometry": {"coordinates":[-95.413027,29.801648],"type":"Point"}
}