{
  "type": "Feature",
  "properties": {
    "iso:country":"US",
    "sg:address":"2002 Ave J",
    "sg:city":"Lubbock",
    "sg:classifiers":[
        {
            "category":"Professional",
            "subcategory":"Business Services",
            "type":"Services"
        }
    ],
    "sg:phone":"+1 806 667 3429",
    "sg:postcode":"79411",
    "sg:province":"TX",
    "wof:name":"United Assoc of Journeyme",
    "wof:placetype":"venue"
},
  "geometry": {"coordinates":[-101.846715,33.575901],"type":"Point"}
}