{
  "type": "Feature",
  "properties": {
    "iso:country":"US",
    "sg:address":"6925 Snowy Owl St",
    "sg:city":"Arlington",
    "sg:classifiers":[
        {
            "category":"Communications",
            "type":"Services"
        }
    ],
    "sg:phone":"+1 817 375 0328",
    "sg:postcode":"76002",
    "sg:province":"TX",
    "sg:tags":[
        "communication"
    ],
    "wof:name":"MLS Communication",
    "wof:placetype":"venue"
},
  "geometry": {"coordinates":[-97.10605099999999,32.630265],"type":"Point"}
}