{
  "type": "Feature",
  "properties": {
    "iso:country":"US",
    "sg:address":"150 S Denton Tap Rd",
    "sg:city":"Coppell",
    "sg:phone":"+1 972 906 0573",
    "sg:postcode":"75019",
    "sg:province":"TX",
    "wof:name":"Chopsticks",
    "wof:placetype":"venue"
},
  "geometry": {"coordinates":[-96.99345700000001,32.966802],"type":"Point"}
}