{
  "type": "Feature",
  "properties": {
    "iso:country":"US",
    "sg:address":"408 W Bluff St",
    "sg:city":"Woodville",
    "sg:classifiers":[
        {
            "category":"Shopping",
            "subcategory":"Gifts & Souvenirs",
            "type":"Retail Goods"
        }
    ],
    "sg:phone":"+1 409 283 3161",
    "sg:postcode":"75979",
    "sg:province":"TX",
    "sg:tags":[
        "shop"
    ],
    "wof:name":"One Unique Place",
    "wof:placetype":"venue"
},
  "geometry": {"coordinates":[-94.41838,30.775337],"type":"Point"}
}