{
  "type": "Feature",
  "properties": {
    "iso:country":"US",
    "sg:address":"9061 FM 32",
    "sg:city":"Fischer",
    "sg:classifiers":[
        {
            "category":"Real Estate",
            "subcategory":"Real Estate Agent",
            "type":"Services"
        }
    ],
    "sg:phone":"+1 830 935 2808",
    "sg:postcode":"78623",
    "sg:province":"TX",
    "wof:name":"Rinco Of Texas Inc",
    "wof:placetype":"venue"
},
  "geometry": {"coordinates":[-98.21207200000001,29.943923],"type":"Point"}
}