{
  "type": "Feature",
  "properties": {
    "iso:country":"US",
    "sg:address":"3200 High Point Dr",
    "sg:city":"Flower Mound",
    "sg:classifiers":[
        {
            "category":"Manufacturing",
            "subcategory":"Tools & Machinery",
            "type":"Manufacturing & Wholesale Goods"
        }
    ],
    "sg:phone":"+1 817 430 4622",
    "sg:postcode":"75022",
    "sg:province":"TX",
    "sg:tags":[
        "industry",
        "aerospace"
    ],
    "wof:name":"Parker-Hannifin Corp",
    "wof:placetype":"venue"
},
  "geometry": {"coordinates":[-97.1161,33.03148],"type":"Point"}
}