{
  "type": "Feature",
  "properties": {
    "iso:country":"US",
    "sg:address":"2420 Superior Dr Ste E",
    "sg:city":"Pantego",
    "sg:classifiers":[
        {
            "category":"Manufacturing",
            "subcategory":"Chemicals & Compounds",
            "type":"Manufacturing & Wholesale Goods"
        },
        {
            "category":"Building & Trades",
            "subcategory":"Pest Control",
            "type":"Services"
        }
    ],
    "sg:phone":"+1 817 548 1166",
    "sg:postcode":"76013",
    "sg:province":"TX",
    "sg:tags":[
        "industrial",
        "supply",
        "services-commercial",
        "termite",
        "equipment",
        "insecticide"
    ],
    "sg:website":"http://www.onestoppest.com",
    "wof:name":"One Stop Termite & Pest Control",
    "wof:placetype":"venue"
},
  "geometry": {"coordinates":[-97.148965,32.708078],"type":"Point"}
}