{
  "type": "Feature",
  "properties": {
    "iso:country":"US",
    "sg:address":"635 Parker Sq",
    "sg:city":"Flower Mound",
    "sg:classifiers":[
        {
            "category":"Restaurant",
            "type":"Food & Drink"
        }
    ],
    "sg:phone":"+1 972 899 5111",
    "sg:postcode":"75028",
    "sg:province":"TX",
    "sg:tags":[
        "delicatessen"
    ],
    "wof:name":"Roly Poly",
    "wof:placetype":"venue"
},
  "geometry": {"coordinates":[-97.050732,33.039171],"type":"Point"}
}