{
  "type": "Feature",
  "properties": {
    "iso:country":"US",
    "sg:address":"3401 Mountcastle Dr",
    "sg:city":"Fort Worth",
    "sg:classifiers":[
        {
            "category":"Organizations",
            "subcategory":"Religious Organization",
            "type":"Services"
        }
    ],
    "sg:phone":"+1 817 534 0258",
    "sg:postcode":"76119",
    "sg:province":"TX",
    "wof:name":"Texas Methodist Foundation",
    "wof:placetype":"venue"
},
  "geometry": {"coordinates":[-97.250907,32.711975],"type":"Point"}
}