{
  "type": "Feature",
  "properties": {
    "iso:country":"US",
    "sg:address":"303 W Goliad Ave",
    "sg:city":"Crockett",
    "sg:classifiers":[
        {
            "category":"Autos & Motor Vehicles",
            "subcategory":"Fuel & Gas Station",
            "type":"Retail Goods"
        }
    ],
    "sg:phone":"+1 936 544 2424",
    "sg:postcode":"75835",
    "sg:province":"TX",
    "sg:tags":[
        "automotive",
        "gasoline",
        "general",
        "station",
        "carwash",
        "r"
    ],
    "wof:name":"KWIK Kar Oil & Lube",
    "wof:placetype":"venue"
},
  "geometry": {"coordinates":[-95.465067,31.316331],"type":"Point"}
}