{
  "type": "Feature",
  "properties": {
    "iso:country":"US",
    "sg:address":"4715 Griggs Rd",
    "sg:city":"Houston",
    "sg:classifiers":[
        {
            "category":"Organizations",
            "subcategory":"Religious Organization",
            "type":"Services"
        }
    ],
    "sg:phone":"+1 713 747 7454",
    "sg:postcode":"77021",
    "sg:province":"TX",
    "wof:name":"Garden of Gethsemane",
    "wof:placetype":"venue"
},
  "geometry": {"coordinates":[-95.34505299999999,29.70077],"type":"Point"}
}