{
  "type": "Feature",
  "properties": {
    "iso:country":"US",
    "sg:address":"5235 S Siesta Ln",
    "sg:city":"Zapata",
    "sg:classifiers":[
        {
            "category":"Utilities",
            "subcategory":"Water",
            "type":"Services"
        }
    ],
    "sg:phone":"+1 956 765 4988",
    "sg:postcode":"78076",
    "sg:province":"TX",
    "sg:tags":[
        "company",
        "sewage"
    ],
    "wof:name":"Siesta Shores Waterworks",
    "wof:placetype":"venue"
},
  "geometry": {"coordinates":[-99.244726,26.86044],"type":"Point"}
}