{
  "type": "Feature",
  "properties": {
    "iso:country":"US",
    "sg:address":"14339 State Hwy 110",
    "sg:city":"Tyler",
    "sg:classifiers":[
        {
            "category":"Building & Trades",
            "subcategory":"Construction",
            "type":"Services"
        }
    ],
    "sg:phone":"+1 903 882 4689",
    "sg:postcode":"75704",
    "sg:province":"TX",
    "sg:tags":[
        "special",
        "contractor"
    ],
    "wof:name":"Eugene Head Ceramic Tile",
    "wof:placetype":"venue"
},
  "geometry": {"coordinates":[-95.51449100000001,32.474126],"type":"Point"}
}