{
  "type": "Feature",
  "properties": {
    "iso:country":"US",
    "sg:address":"3701 S Shepherd Dr",
    "sg:city":"Houston",
    "sg:classifiers":[
        {
            "category":"Retail",
            "subcategory":"Laundry & Dry Cleaning",
            "type":"Services"
        }
    ],
    "sg:phone":"+1 713 942 1002",
    "sg:postcode":"77098",
    "sg:province":"TX",
    "sg:tags":[
        "cleaners"
    ],
    "wof:name":"Bell Cleaners",
    "wof:placetype":"venue"
},
  "geometry": {"coordinates":[-95.410623,29.73256],"type":"Point"}
}