{
  "type": "Feature",
  "properties": {
    "iso:country":"US",
    "sg:address":"11500 Northwest Fwy",
    "sg:city":"Houston",
    "sg:classifiers":[
        {
            "category":"Professional",
            "subcategory":"Lawyer & Legal Services",
            "type":"Services"
        }
    ],
    "sg:phone":"+1 713 957 3395",
    "sg:postcode":"77092",
    "sg:province":"TX",
    "sg:tags":[
        "attorney"
    ],
    "wof:name":"Law Offices",
    "wof:placetype":"venue"
},
  "geometry": {"coordinates":[-95.47167399999999,29.822712],"type":"Point"}
}