{
  "type": "Feature",
  "properties": {
    "iso:country":"US",
    "sg:address":"1540 S University Dr",
    "sg:city":"Fort Worth",
    "sg:classifiers":[
        {
            "category":"Retail",
            "subcategory":"Photofinishing",
            "type":"Services"
        }
    ],
    "sg:phone":"+1 817 878 2460",
    "sg:postcode":"76109",
    "sg:province":"TX",
    "sg:tags":[
        "laboratory"
    ],
    "wof:name":"Ritz Camera",
    "wof:placetype":"venue"
},
  "geometry": {"coordinates":[-97.36139900000001,32.72883],"type":"Point"}
}