{
  "type": "Feature",
  "properties": {
    "iso:country":"US",
    "sg:address":"7049 Lawndale St Ste D",
    "sg:city":"Houston",
    "sg:classifiers":[
        {
            "category":"Personal",
            "subcategory":"Beauty Salon",
            "type":"Services"
        }
    ],
    "sg:phone":"+1 713 921 1440",
    "sg:postcode":"77023",
    "sg:province":"TX",
    "sg:tags":[
        "hair"
    ],
    "sg:website":"www.newwaveshairdesign.com/",
    "wof:name":"New Waves Hair & Nail Design",
    "wof:placetype":"venue"
},
  "geometry": {"coordinates":[-95.297501,29.7174],"type":"Point"}
}