{
  "type": "Feature",
  "properties": {
    "iso:country":"US",
    "sg:address":"5717 Airport Fwy",
    "sg:city":"Fort Worth",
    "sg:classifiers":[
        {
            "category":"Autos & Motor Vehicles",
            "subcategory":"Boat Sales",
            "type":"Retail Goods"
        }
    ],
    "sg:phone":"+1 817 834 7185",
    "sg:postcode":"76117",
    "sg:province":"TX",
    "sg:tags":[
        "watercraft",
        "motorcycle"
    ],
    "wof:name":"Honda Town",
    "wof:placetype":"venue"
},
  "geometry": {"coordinates":[-97.25999899999999,32.787492],"type":"Point"}
}