{
  "type": "Feature",
  "properties": {
    "iso:country":"US",
    "sg:address":"1305 W Villa Maria Rd",
    "sg:city":"Bryan",
    "sg:classifiers":[
        {
            "category":"Arts & Performance",
            "subcategory":"Theater",
            "type":"Entertainment"
        }
    ],
    "sg:phone":"+1 979 823 1578",
    "sg:postcode":"77801",
    "sg:province":"TX",
    "sg:tags":[
        "group"
    ],
    "wof:name":"Zodiac",
    "wof:placetype":"venue"
},
  "geometry": {"coordinates":[-96.372795,30.632976],"type":"Point"}
}