{
  "type": "Feature",
  "properties": {
    "iso:country":"US",
    "sg:address":"4416 Prairie Ave",
    "sg:city":"Amarillo",
    "sg:classifiers":[
        {
            "category":"Manufacturing",
            "subcategory":"Jewelry",
            "type":"Manufacturing & Wholesale Goods"
        }
    ],
    "sg:phone":"+1 806 359 8818",
    "sg:postcode":"79109",
    "sg:province":"TX",
    "wof:name":"Morgan Jim-Josten's",
    "wof:placetype":"venue"
},
  "geometry": {"coordinates":[-101.889191,35.161586],"type":"Point"}
}