{
  "type": "Feature",
  "properties": {
    "iso:country":"US",
    "sg:address":"414 S 24th St",
    "sg:city":"Donna",
    "sg:classifiers":[
        {
            "category":"Building & Trades",
            "subcategory":"Plumbing",
            "type":"Services"
        }
    ],
    "sg:phone":"+1 956 464 6346",
    "sg:postcode":"78537",
    "sg:province":"TX",
    "sg:tags":[
        "contractor"
    ],
    "wof:name":"Pete S Electric AC",
    "wof:placetype":"venue"
},
  "geometry": {"coordinates":[-98.039502,26.161178],"type":"Point"}
}