{
  "type": "Feature",
  "properties": {
    "iso:country":"US",
    "sg:address":"5131 Glenridge Ln",
    "sg:city":"Houston",
    "sg:classifiers":[
        {
            "category":"Education",
            "subcategory":"Vocational School",
            "type":"Public Place"
        }
    ],
    "sg:phone":"+1 713 433 6264",
    "sg:postcode":"77053",
    "sg:province":"TX",
    "sg:tags":[
        "web",
        "training",
        "design",
        "site",
        "software"
    ],
    "wof:name":"Quest Testing & Development",
    "wof:placetype":"venue"
},
  "geometry": {"coordinates":[-95.458724,29.60226],"type":"Point"}
}