{
  "type": "Feature",
  "properties": {
    "iso:country":"US",
    "sg:address":"123 N 5th St",
    "sg:city":"Silsbee",
    "sg:classifiers":[
        {
            "category":"Manufacturing",
            "subcategory":"Signs",
            "type":"Manufacturing & Wholesale Goods"
        }
    ],
    "sg:phone":"+1 409 385 0080",
    "sg:postcode":"77656",
    "sg:province":"TX",
    "sg:tags":[
        "consultant",
        "novelty",
        "advertising",
        "mfg"
    ],
    "wof:name":"Parco Printing",
    "wof:placetype":"venue"
},
  "geometry": {"coordinates":[-94.177879,30.349586],"type":"Point"}
}