{
  "type": "Feature",
  "properties": {
    "iso:country":"US",
    "sg:address":"5223 Pinson St",
    "sg:city":"Fort Worth",
    "sg:classifiers":[
        {
            "category":"Professional",
            "type":"Services"
        }
    ],
    "sg:phone":"+1 817 429 8805",
    "sg:postcode":"76105",
    "sg:province":"TX",
    "wof:name":"Big & Beautiful",
    "wof:placetype":"venue"
},
  "geometry": {"coordinates":[-97.24042300000001,32.714224],"type":"Point"}
}