{
  "type": "Feature",
  "properties": {
    "iso:country":"US",
    "sg:address":"935 Allen Ave",
    "sg:city":"New Braunfels",
    "sg:classifiers":[
        {
            "category":"Banks & Credit Unions",
            "subcategory":"Investment Brokerage",
            "type":"Services"
        }
    ],
    "sg:phone":"+1 830 626 6888",
    "sg:postcode":"78130",
    "sg:province":"TX",
    "sg:tags":[
        "land",
        "oil",
        "lease"
    ],
    "wof:name":"Randy J Boatright",
    "wof:placetype":"venue"
},
  "geometry": {"coordinates":[-98.129426,29.715209],"type":"Point"}
}