{
  "type": "Feature",
  "properties": {
    "iso:country":"US",
    "sg:address":"115 N Dixie Dr",
    "sg:city":"Lake Jackson",
    "sg:classifiers":[
        {
            "category":"Health Services",
            "subcategory":"Doctor",
            "type":"Services"
        }
    ],
    "sg:phone":"+1 979 297 0633",
    "sg:postcode":"77566",
    "sg:province":"TX",
    "sg:tags":[
        "dentist",
        "clinic"
    ],
    "wof:name":"Kim Freeman DMD",
    "wof:placetype":"venue"
},
  "geometry": {"coordinates":[-95.42058299999999,29.020584],"type":"Point"}
}