{
  "type": "Feature",
  "properties": {
    "iso:country":"US",
    "sg:address":"3407 Cotillion Dr",
    "sg:city":"Arlington",
    "sg:classifiers":[
        {
            "category":"Professional",
            "type":"Services"
        }
    ],
    "sg:phone":"+1 817 466 0431",
    "sg:postcode":"76017",
    "sg:province":"TX",
    "sg:tags":[
        "establishment"
    ],
    "wof:name":"OPTE",
    "wof:placetype":"venue"
},
  "geometry": {"coordinates":[-97.16329399999999,32.665262],"type":"Point"}
}