{
  "type": "Feature",
  "properties": {
    "iso:country":"US",
    "sg:address":"3726 N Main St",
    "sg:city":"Baytown",
    "sg:classifiers":[
        {
            "category":"Real Estate",
            "subcategory":"Real Estate Agent",
            "type":"Services"
        }
    ],
    "sg:phone":"+1 281 422 3294",
    "sg:postcode":"77521",
    "sg:province":"TX",
    "wof:name":"Virginia Malone & Assoc",
    "wof:placetype":"venue"
},
  "geometry": {"coordinates":[-94.963922,29.762939],"type":"Point"}
}