{
  "type": "Feature",
  "properties": {
    "iso:country":"US",
    "sg:address":"717 Wayne St",
    "sg:city":"Dallas",
    "sg:classifiers":[
        {
            "category":"Building & Trades",
            "subcategory":"Landscaping Services",
            "type":"Services"
        }
    ],
    "sg:phone":"+1 214 827 1770",
    "sg:postcode":"75223",
    "sg:province":"TX",
    "sg:tags":[
        "landscape",
        "contractor"
    ],
    "wof:name":"Collazo Landscaping Svc",
    "wof:placetype":"venue"
},
  "geometry": {"coordinates":[-96.750879,32.798085],"type":"Point"}
}