{
  "type": "Feature",
  "properties": {
    "iso:country":"US",
    "sg:address":"127 Russwood Cir",
    "sg:city":"Universal City",
    "sg:classifiers":[
        {
            "category":"Shopping",
            "subcategory":"Catalog Store",
            "type":"Retail Goods"
        }
    ],
    "sg:phone":"+1 210 659 3910",
    "sg:postcode":"78148",
    "sg:province":"TX",
    "sg:tags":[
        "mail",
        "house"
    ],
    "wof:name":"Hobows of Texas",
    "wof:placetype":"venue"
},
  "geometry": {"coordinates":[-98.302547,29.559078],"type":"Point"}
}