{
  "type": "Feature",
  "properties": {
    "iso:country":"US",
    "sg:address":"5427 E Grand Ave",
    "sg:city":"Dallas",
    "sg:classifiers":[
        {
            "category":"Restaurant",
            "type":"Food & Drink"
        }
    ],
    "sg:phone":"+1 214 823 5872",
    "sg:postcode":"75223",
    "sg:province":"TX",
    "sg:tags":[
        "eating",
        "tex-mex"
    ],
    "wof:name":"El Taquito Cafe",
    "wof:placetype":"venue"
},
  "geometry": {"coordinates":[-96.748773,32.792658],"type":"Point"}
}