{
  "type": "Feature",
  "properties": {
    "iso:country":"US",
    "sg:address":"100 N Crockett Ave",
    "sg:city":"Cameron",
    "sg:classifiers":[
        {
            "category":"Place Of Worship",
            "type":"Public Place"
        }
    ],
    "sg:phone":"+1 254 697 4151",
    "sg:postcode":"76520",
    "sg:province":"TX",
    "sg:tags":[
        "church"
    ],
    "wof:name":"Restoration Church Of Pearland",
    "wof:placetype":"venue"
},
  "geometry": {"coordinates":[-96.978943,30.851271],"type":"Point"}
}