{
  "type": "Feature",
  "properties": {
    "iso:country":"US",
    "sg:address":"11355 Rojas Dr",
    "sg:city":"El Paso",
    "sg:classifiers":[
        {
            "category":"Freight",
            "type":"Transportation"
        }
    ],
    "sg:phone":"+1 915 592 9955",
    "sg:postcode":"79936",
    "sg:province":"TX",
    "sg:tags":[
        "forwarding"
    ],
    "wof:name":"Force Forwarding Center Corp",
    "wof:placetype":"venue"
},
  "geometry": {"coordinates":[-106.317488,31.739595],"type":"Point"}
}