{
  "type": "Feature",
  "properties": {
    "iso:country":"US",
    "sg:address":"4534 Bruce Dr",
    "sg:city":"Abilene",
    "sg:classifiers":[
        {
            "category":"Professional",
            "subcategory":"Engineering",
            "type":"Services"
        }
    ],
    "sg:phone":"+1 325 695 5149",
    "sg:postcode":"79606",
    "sg:province":"TX",
    "wof:name":"Gary L Smith Radio Equipment",
    "wof:placetype":"venue"
},
  "geometry": {"coordinates":[-99.76960800000001,32.395742],"type":"Point"}
}