{
  "type": "Feature",
  "properties": {
    "iso:country":"US",
    "sg:address":"43 Yu Dr",
    "sg:city":"New Braunfels",
    "sg:classifiers":[
        {
            "category":"Health Services",
            "subcategory":"Doctor",
            "type":"Services"
        }
    ],
    "sg:phone":"+1 830 624 3392",
    "sg:postcode":"78130",
    "sg:province":"TX",
    "sg:tags":[
        "medical"
    ],
    "wof:name":"New Braunfels Osteoporosis Ctr",
    "wof:placetype":"venue"
},
  "geometry": {"coordinates":[-98.094908,29.725949],"type":"Point"}
}