{
  "type": "Feature",
  "properties": {
    "iso:country":"US",
    "sg:address":"9543 Big View Dr",
    "sg:city":"Austin",
    "sg:classifiers":[
        {
            "category":"Utilities",
            "subcategory":"Water",
            "type":"Services"
        }
    ],
    "sg:phone":"+1 512 306 8392",
    "sg:postcode":"78730",
    "sg:province":"TX",
    "sg:tags":[
        "bulk",
        "companies-bottled"
    ],
    "wof:name":"Water To Thrive",
    "wof:placetype":"venue"
},
  "geometry": {"coordinates":[-97.85624199999999,30.361756],"type":"Point"}
}