{
  "type": "Feature",
  "properties": {
    "iso:country":"US",
    "sg:address":"6465 Camp Bowie Blvd",
    "sg:city":"Fort Worth",
    "sg:classifiers":[
        {
            "category":"Restaurant",
            "type":"Food & Drink"
        }
    ],
    "sg:phone":"+1 817 732 3636",
    "sg:postcode":"76116",
    "sg:province":"TX",
    "wof:name":"Mike Salerno's Italian Rstrnt",
    "wof:placetype":"venue"
},
  "geometry": {"coordinates":[-97.425432,32.724505],"type":"Point"}
}