{
  "type": "Feature",
  "properties": {
    "iso:country":"US",
    "sg:address":"4507 Garth Rd",
    "sg:city":"Baytown",
    "sg:classifiers":[
        {
            "category":"Health Services",
            "subcategory":"Podiatrist",
            "type":"Services"
        }
    ],
    "sg:phone":"+1 281 837 1500",
    "sg:postcode":"77521",
    "sg:province":"TX",
    "wof:name":"Mc Kinney Podiatric Assoc",
    "wof:placetype":"venue"
},
  "geometry": {"coordinates":[-94.977625,29.76988],"type":"Point"}
}