{
  "type": "Feature",
  "properties": {
    "iso:country":"US",
    "sg:address":"1514 N Ben Jordan St",
    "sg:city":"Victoria",
    "sg:classifiers":[
        {
            "category":"Mining & Drilling",
            "type":"Manufacturing & Wholesale Goods"
        }
    ],
    "sg:phone":"+1 361 582 4455",
    "sg:postcode":"77901",
    "sg:province":"TX",
    "sg:tags":[
        "field",
        "oil"
    ],
    "wof:name":"4 M Svc Inc",
    "wof:placetype":"venue"
},
  "geometry": {"coordinates":[-96.982349,28.806142],"type":"Point"}
}