{
  "type": "Feature",
  "properties": {
    "iso:country":"US",
    "sg:address":"617 E Cameron Ave",
    "sg:city":"Rockdale",
    "sg:classifiers":[
        {
            "category":"Restaurant",
            "type":"Food & Drink"
        }
    ],
    "sg:phone":"+1 512 446 5355",
    "sg:postcode":"76567",
    "sg:province":"TX",
    "sg:tags":[
        "eating"
    ],
    "wof:name":"Sisters Kitchen & Catering Ser",
    "wof:placetype":"venue"
},
  "geometry": {"coordinates":[-96.99488100000001,30.658535],"type":"Point"}
}