{
  "type": "Feature",
  "properties": {
    "iso:country":"US",
    "sg:address":"4621 Banister Ln",
    "sg:city":"Austin",
    "sg:classifiers":[
        {
            "category":"Building & Trades",
            "subcategory":"Landscaping Services",
            "type":"Services"
        }
    ],
    "sg:phone":"+1 512 442 8482",
    "sg:postcode":"78745",
    "sg:province":"TX",
    "sg:tags":[
        "landscape"
    ],
    "wof:name":"Blossom Gardens",
    "wof:placetype":"venue"
},
  "geometry": {"coordinates":[-97.78284600000001,30.220309],"type":"Point"}
}