{
  "type": "Feature",
  "properties": {
    "iso:country":"US",
    "sg:address":"108 E Sam Rayburn Dr",
    "sg:city":"Bonham",
    "sg:classifiers":[
        {
            "category":"Professional",
            "type":"Services"
        },
        {
            "category":"Utilities",
            "subcategory":"Fuel Oil & Lpg",
            "type":"Services"
        }
    ],
    "sg:phone":"+1 903 583 3072",
    "sg:postcode":"75418",
    "sg:province":"TX",
    "sg:tags":[
        "development",
        "field",
        "exploration",
        "gas"
    ],
    "wof:name":"Texcel Exploration Inc",
    "wof:placetype":"venue"
},
  "geometry": {"coordinates":[-96.17916700000001,33.577064],"type":"Point"}
}