{
  "type": "Feature",
  "properties": {
    "iso:country":"US",
    "sg:address":"2506 White Horse Trl",
    "sg:city":"Austin",
    "sg:classifiers":[
        {
            "category":"Professional",
            "type":"Services"
        }
    ],
    "sg:phone":"+1 512 371 1544",
    "sg:postcode":"78757",
    "sg:province":"TX",
    "sg:tags":[
        "establishment"
    ],
    "wof:name":"Noisetrapper Products",
    "wof:placetype":"venue"
},
  "geometry": {"coordinates":[-97.743708,30.340076],"type":"Point"}
}