{
  "type": "Feature",
  "properties": {
    "iso:country":"US",
    "sg:address":"400 S Tennessee St",
    "sg:city":"Mc Kinney",
    "sg:classifiers":[
        {
            "category":"Professional",
            "subcategory":"Employment Agencies",
            "type":"Services"
        }
    ],
    "sg:phone":"+1 972 542 2959",
    "sg:postcode":"75069",
    "sg:province":"TX",
    "sg:tags":[
        "opportunity"
    ],
    "wof:name":"Adecco",
    "wof:placetype":"venue"
},
  "geometry": {"coordinates":[-96.61515199999999,33.193729],"type":"Point"}
}