{
  "type": "Feature",
  "properties": {
    "iso:country":"US",
    "sg:address":"7729 Tezel Rd",
    "sg:city":"San Antonio",
    "sg:classifiers":[
        {
            "category":"Shopping",
            "subcategory":"Florist",
            "type":"Retail Goods"
        }
    ],
    "sg:phone":"+1 210 680 1982",
    "sg:postcode":"78250",
    "sg:province":"TX",
    "wof:name":"Flower ME Florists",
    "wof:placetype":"venue"
},
  "geometry": {"coordinates":[-98.662415,29.512205],"type":"Point"}
}