{
  "type": "Feature",
  "properties": {
    "iso:country":"US",
    "sg:address":"1418 W Wilson St",
    "sg:city":"Borger",
    "sg:classifiers":[
        {
            "category":"Restaurant",
            "type":"Food & Drink"
        }
    ],
    "sg:menulink":"http://www.allmenus.com/tx/borger/70630-pizza-hut/menu/",
    "sg:phone":"+1 806 274 7245",
    "sg:postcode":"79007",
    "sg:province":"TX",
    "sg:tags":[
        "american",
        "pizza"
    ],
    "wof:name":"Pizza Hut",
    "wof:placetype":"venue"
},
  "geometry": {"coordinates":[-101.41130099999999,35.657801],"type":"Point"}
}