{
  "type": "Feature",
  "properties": {
    "iso:country":"US",
    "sg:address":"2118 Crestline Dr",
    "sg:city":"Abilene",
    "sg:classifiers":[
        {
            "category":"Professional",
            "type":"Services"
        }
    ],
    "sg:phone":"+1 325 677 5766",
    "sg:postcode":"79602",
    "sg:province":"TX",
    "wof:name":"Strings Unlimited Studio",
    "wof:placetype":"venue"
},
  "geometry": {"coordinates":[-99.700215,32.423525],"type":"Point"}
}