{
  "type": "Feature",
  "properties": {
    "iso:country":"US",
    "sg:address":"5882 Westheimer Rd",
    "sg:city":"Houston",
    "sg:classifiers":[
        {
            "category":"Shopping",
            "subcategory":"Clothing, Apparel, & Fashions",
            "type":"Retail Goods"
        }
    ],
    "sg:phone":"+1 713 784 8877",
    "sg:postcode":"77057",
    "sg:province":"TX",
    "sg:tags":[
        "western"
    ],
    "wof:name":"Range The Romancing Inc",
    "wof:placetype":"venue"
},
  "geometry": {"coordinates":[-95.484285,29.737717],"type":"Point"}
}