{
  "type": "Feature",
  "properties": {
    "iso:country":"US",
    "sg:address":"6602 Antoine Dr",
    "sg:city":"Houston",
    "sg:classifiers":[
        {
            "category":"Shopping",
            "subcategory":"Computers & Home Electronics",
            "type":"Retail Goods"
        }
    ],
    "sg:phone":"+1 713 688 0600",
    "sg:postcode":"77091",
    "sg:province":"TX",
    "wof:name":"Radio Shack",
    "wof:placetype":"venue"
},
  "geometry": {"coordinates":[-95.47333999999999,29.860809],"type":"Point"}
}