{
  "type": "Feature",
  "properties": {
    "iso:country":"US",
    "sg:address":"224 Henderson St",
    "sg:city":"Midlothian",
    "sg:classifiers":[
        {
            "category":"Retail",
            "subcategory":"Auto Repair",
            "type":"Services"
        }
    ],
    "sg:phone":"+1 972 723 2010",
    "sg:postcode":"76065",
    "sg:province":"TX",
    "sg:tags":[
        "repairing",
        "automobile",
        "general"
    ],
    "wof:name":"A-Plus + Automotive",
    "wof:placetype":"venue"
},
  "geometry": {"coordinates":[-96.990028,32.500812],"type":"Point"}
}