{
  "type": "Feature",
  "properties": {
    "iso:country":"US",
    "sg:address":"5417 Bright Star Trl",
    "sg:city":"Arlington",
    "sg:classifiers":[
        {
            "category":"Building & Trades",
            "subcategory":"Construction",
            "type":"Services"
        }
    ],
    "sg:phone":"+1 817 563 2735",
    "sg:postcode":"76017",
    "sg:province":"TX",
    "sg:tags":[
        "porch",
        "enclosure",
        "patio",
        "deck"
    ],
    "wof:name":"Clear Vu Concepts",
    "wof:placetype":"venue"
},
  "geometry": {"coordinates":[-97.18401,32.658333],"type":"Point"}
}