{
  "type": "Feature",
  "properties": {
    "iso:country":"US",
    "sg:address":"2316 Riverside Dr",
    "sg:city":"Orange",
    "sg:classifiers":[
        {
            "category":"Building & Trades",
            "subcategory":"Construction",
            "type":"Services"
        }
    ],
    "sg:phone":"+1 409 883 2021",
    "sg:postcode":"77630",
    "sg:province":"TX",
    "sg:tags":[
        "cabinet",
        "carpentry",
        "maker",
        "contractor"
    ],
    "wof:name":"White A J & Son Builders Inc",
    "wof:placetype":"venue"
},
  "geometry": {"coordinates":[-93.731644,30.113373],"type":"Point"}
}