{
  "type": "Feature",
  "properties": {
    "iso:country":"US",
    "sg:address":"320 N Main St",
    "sg:city":"Winnsboro",
    "sg:classifiers":[
        {
            "category":"Health Services",
            "subcategory":"Clinic",
            "type":"Services"
        },
        {
            "category":"Health Services",
            "subcategory":"Health Practitioner",
            "type":"Services"
        }
    ],
    "sg:phone":"+1 903 342 6790",
    "sg:postcode":"75494",
    "sg:province":"TX",
    "sg:tags":[
        "information",
        "therapist",
        "therapy",
        "treatment",
        "alcoholism",
        "physical"
    ],
    "wof:name":"Rehab Solutions",
    "wof:placetype":"venue"
},
  "geometry": {"coordinates":[-95.289974,32.958465],"type":"Point"}
}