{
  "type": "Feature",
  "properties": {
    "iso:country":"US",
    "sg:address":"5539 Huisache St",
    "sg:city":"Bellaire",
    "sg:classifiers":[
        {
            "category":"Restaurant",
            "type":"Food & Drink"
        }
    ],
    "sg:phone":"+1 713 432 1488",
    "sg:postcode":"77401",
    "sg:province":"TX",
    "sg:tags":[
        "eating"
    ],
    "wof:name":"Citrus",
    "wof:placetype":"venue"
},
  "geometry": {"coordinates":[-95.47942999999999,29.6969],"type":"Point"}
}