{
  "type": "Feature",
  "properties": {
    "iso:country":"US",
    "sg:address":"16255 S Post Oak Rd",
    "sg:city":"Houston",
    "sg:classifiers":[
        {
            "category":"Food & Beverages",
            "subcategory":"Groceries & Convenience Stores",
            "type":"Retail Goods"
        }
    ],
    "sg:phone":"+1 281 437 3805",
    "sg:postcode":"77053",
    "sg:province":"TX",
    "wof:name":"U S Mart Inc",
    "wof:placetype":"venue"
},
  "geometry": {"coordinates":[-95.4692,29.5907],"type":"Point"}
}