{
  "type": "Feature",
  "properties": {
    "iso:country":"US",
    "sg:address":"1420 Fishermans Place Rd",
    "sg:city":"Brownsville",
    "sg:classifiers":[
        {
            "category":"Recreation",
            "subcategory":"Marina",
            "type":"Entertainment"
        }
    ],
    "sg:phone":"+1 956 831 9431",
    "sg:postcode":"78521",
    "sg:province":"TX",
    "sg:tags":[
        "repairing",
        "boat"
    ],
    "wof:name":"Harris Boat Maintenance",
    "wof:placetype":"venue"
},
  "geometry": {"coordinates":[-97.338106,25.981405],"type":"Point"}
}