{
  "type": "Feature",
  "properties": {
    "iso:country":"US",
    "sg:address":"6804 State Hwy 6",
    "sg:city":"Houston",
    "sg:classifiers":[
        {
            "category":"Freight",
            "type":"Transportation"
        }
    ],
    "sg:phone":"+1 281 561 0377",
    "sg:postcode":"77099",
    "sg:province":"TX",
    "sg:tags":[
        "mailing"
    ],
    "wof:name":"UPS Stores",
    "wof:placetype":"venue"
},
  "geometry": {"coordinates":[-95.643944,29.700598],"type":"Point"}
}