{
  "type": "Feature",
  "properties": {
    "iso:country":"US",
    "sg:address":"206 Harrington Rd",
    "sg:city":"Waxahachie",
    "sg:classifiers":[
        {
            "category":"Professional",
            "subcategory":"Advertising",
            "type":"Services"
        }
    ],
    "sg:phone":"+1 972 998 2130",
    "sg:postcode":"75165",
    "sg:province":"TX",
    "sg:tags":[
        "agency"
    ],
    "wof:name":"Adsolv",
    "wof:placetype":"venue"
},
  "geometry": {"coordinates":[-96.81530100000001,32.306093],"type":"Point"}
}