{
  "type": "Feature",
  "properties": {
    "iso:country":"US",
    "sg:address":"6117 8th St",
    "sg:city":"Lubbock",
    "sg:classifiers":[
        {
            "category":"Professional",
            "subcategory":"Management & Consulting",
            "type":"Services"
        }
    ],
    "sg:phone":"+1 806 487 6411",
    "sg:postcode":"79416",
    "sg:province":"TX",
    "sg:tags":[
        "educational"
    ],
    "wof:name":"Durham Ulla",
    "wof:placetype":"venue"
},
  "geometry": {"coordinates":[-101.950271,33.588308],"type":"Point"}
}