{
  "type": "Feature",
  "properties": {
    "iso:country":"US",
    "sg:address":"1530 N Cage Blvd",
    "sg:city":"Pharr",
    "sg:classifiers":[
        {
            "category":"Organizations",
            "subcategory":"Non-profit Organization",
            "type":"Services"
        }
    ],
    "sg:phone":"+1 956 283 5000",
    "sg:postcode":"78577",
    "sg:province":"TX",
    "sg:tags":[
        "housing",
        "social"
    ],
    "wof:name":"Naha Inc",
    "wof:placetype":"venue"
},
  "geometry": {"coordinates":[-98.181831,26.208336],"type":"Point"}
}