{
  "type": "Feature",
  "properties": {
    "iso:country":"US",
    "sg:address":"4310 Wiley Post Rd",
    "sg:city":"Addison",
    "sg:classifiers":[
        {
            "category":"Professional",
            "subcategory":"Management & Consulting",
            "type":"Services"
        }
    ],
    "sg:phone":"+1 972 720 8844",
    "sg:postcode":"75001",
    "sg:province":"TX",
    "sg:tags":[
        "consultant",
        "business"
    ],
    "wof:name":"Ultimate Consulting Inc",
    "wof:placetype":"venue"
},
  "geometry": {"coordinates":[-96.837924,32.96015],"type":"Point"}
}