{
  "type": "Feature",
  "properties": {
    "iso:country":"US",
    "sg:address":"121 N Main St",
    "sg:city":"Pleasanton",
    "sg:classifiers":[
        {
            "category":"Retail",
            "subcategory":"Repair Shop",
            "type":"Services"
        }
    ],
    "sg:phone":"+1 830 569 2431",
    "sg:postcode":"78064",
    "sg:province":"TX",
    "wof:name":"Frames & Things",
    "wof:placetype":"venue"
},
  "geometry": {"coordinates":[-98.484279,28.959276],"type":"Point"}
}