{
  "type": "Feature",
  "properties": {
    "iso:country":"US",
    "sg:address":"105 College Ave",
    "sg:city":"Levelland",
    "sg:classifiers":[
        {
            "category":"Autos & Motor Vehicles",
            "subcategory":"Auto Supplies",
            "type":"Retail Goods"
        }
    ],
    "sg:phone":"+1 806 897 0302",
    "sg:postcode":"79336",
    "sg:province":"TX",
    "wof:name":"OReilly Auto Parts",
    "wof:placetype":"venue"
},
  "geometry": {"coordinates":[-102.367583,33.592636],"type":"Point"}
}