{
  "type": "Feature",
  "properties": {
    "iso:country":"US",
    "sg:address":"4209 Cat Mountain Dr",
    "sg:city":"Austin",
    "sg:classifiers":[
        {
            "category":"Building & Trades",
            "subcategory":"Construction",
            "type":"Services"
        }
    ],
    "sg:phone":"+1 512 345 5933",
    "sg:postcode":"78731",
    "sg:province":"TX",
    "sg:tags":[
        "consultant",
        "management"
    ],
    "wof:name":"Borcherding Enterprising Inc",
    "wof:placetype":"venue"
},
  "geometry": {"coordinates":[-97.77352999999999,30.351111],"type":"Point"}
}