{
  "type": "Feature",
  "properties": {
    "iso:country":"US",
    "sg:address":"3007 S Main St",
    "sg:city":"Stafford",
    "sg:classifiers":[
        {
            "category":"Freight",
            "type":"Transportation"
        }
    ],
    "sg:phone":"+1 713 527 0824",
    "sg:postcode":"77477",
    "sg:province":"TX",
    "sg:tags":[
        "mover"
    ],
    "wof:name":"Making Your Moves EZ",
    "wof:placetype":"venue"
},
  "geometry": {"coordinates":[-95.56058899999999,29.615981],"type":"Point"}
}