{
  "type": "Feature",
  "properties": {
    "iso:country":"US",
    "sg:address":"1285 N Main St",
    "sg:city":"Mansfield",
    "sg:classifiers":[
        {
            "category":"Retail",
            "subcategory":"Repair Shop",
            "type":"Services"
        }
    ],
    "sg:phone":"+1 682 518 1660",
    "sg:postcode":"76063",
    "sg:province":"TX",
    "sg:tags":[
        "scooter",
        "motorcycle",
        "motor"
    ],
    "wof:name":"Gmd Computrack DFW",
    "wof:placetype":"venue"
},
  "geometry": {"coordinates":[-97.151335,32.580548],"type":"Point"}
}