{
  "type": "Feature",
  "properties": {
    "iso:country":"US",
    "sg:address":"57 Frj Dr",
    "sg:city":"Longview",
    "sg:classifiers":[
        {
            "category":"Building & Trades",
            "subcategory":"Construction",
            "type":"Services"
        }
    ],
    "sg:phone":"+1 903 238 8300",
    "sg:postcode":"75602",
    "sg:province":"TX",
    "sg:tags":[
        "installation",
        "special",
        "contractor"
    ],
    "wof:name":"Longview Fab & Machine Inc",
    "wof:placetype":"venue"
},
  "geometry": {"coordinates":[-94.69167299999999,32.497304],"type":"Point"}
}