{
  "type": "Feature",
  "properties": {
    "iso:country":"US",
    "sg:address":"710 Egyptian Way",
    "sg:city":"Grand Prairie",
    "sg:classifiers":[
        {
            "category":"Building & Trades",
            "subcategory":"Construction",
            "type":"Services"
        }
    ],
    "sg:phone":"+1 972 262 3859",
    "sg:postcode":"75050",
    "sg:province":"TX",
    "sg:tags":[
        "floor",
        "laying",
        "contractor"
    ],
    "wof:name":"Artists Flooring",
    "wof:placetype":"venue"
},
  "geometry": {"coordinates":[-97.01279100000001,32.764303],"type":"Point"}
}