{
  "type": "Feature",
  "properties": {
    "iso:country":"US",
    "sg:address":"600 N New Rd",
    "sg:city":"Waco",
    "sg:classifiers":[
        {
            "category":"Restaurant",
            "type":"Food & Drink"
        }
    ],
    "sg:menulink":"http://www.allmenus.com/tx/waco/278195-el-tapatios-mexican-rstrnt/menu/",
    "sg:phone":"+1 254 399 9931",
    "sg:postcode":"76710",
    "sg:province":"TX",
    "sg:tags":[
        "mexican"
    ],
    "wof:name":"El Tapatio's Mexican Rstrnt",
    "wof:placetype":"venue"
},
  "geometry": {"coordinates":[-97.173226,31.527915],"type":"Point"}
}