{
  "type": "Feature",
  "properties": {
    "iso:country":"US",
    "sg:address":"9998 County Line Rd N",
    "sg:city":"Electra",
    "sg:classifiers":[
        {
            "category":"Professional",
            "type":"Services"
        }
    ],
    "sg:phone":"+1 940 886 2438",
    "sg:postcode":"76360",
    "sg:province":"TX",
    "wof:name":"Anna Raschke",
    "wof:placetype":"venue"
},
  "geometry": {"coordinates":[-98.950205,34.150129],"type":"Point"}
}