{
  "type": "Feature",
  "properties": {
    "iso:country":"US",
    "sg:address":"2402 Marcella Ave",
    "sg:city":"Laredo",
    "sg:classifiers":[
        {
            "category":"Communications",
            "subcategory":"Film & Video Production",
            "type":"Services"
        }
    ],
    "sg:phone":"+1 956 791 5886",
    "sg:postcode":"78040",
    "sg:province":"TX",
    "sg:tags":[
        "taping"
    ],
    "wof:name":"Sanchez Video",
    "wof:placetype":"venue"
},
  "geometry": {"coordinates":[-99.49387299999999,27.518604],"type":"Point"}
}