{
  "type": "Feature",
  "properties": {
    "iso:country":"US",
    "sg:address":"2202 Mitchell Ln",
    "sg:city":"Rowlett",
    "sg:classifiers":[
        {
            "category":"Shopping",
            "subcategory":"Gifts & Souvenirs",
            "type":"Retail Goods"
        }
    ],
    "sg:phone":"+1 972 412 3122",
    "sg:postcode":"75088",
    "sg:province":"TX",
    "wof:name":"Rustic Charm",
    "wof:placetype":"venue"
},
  "geometry": {"coordinates":[-96.556648,32.880728],"type":"Point"}
}