{
  "type": "Feature",
  "properties": {
    "iso:country":"US",
    "sg:address":"1445 Ross Ave",
    "sg:city":"Dallas",
    "sg:classifiers":[
        {
            "category":"Professional",
            "subcategory":"Lawyer & Legal Services",
            "type":"Services"
        }
    ],
    "sg:phone":"+1 214 855 7538",
    "sg:postcode":"75202",
    "sg:province":"TX",
    "wof:name":"Pegues Michael Atty",
    "wof:placetype":"venue"
},
  "geometry": {"coordinates":[-96.802299,32.784401],"type":"Point"}
}