{
  "type": "Feature",
  "properties": {
    "iso:country":"US",
    "sg:address":"8100 Bee Caves Rd.",
    "sg:city":"Austin",
    "sg:classifiers":[
        {
            "category":"Arena",
            "subcategory":"Sports Club",
            "type":"Entertainment"
        }
    ],
    "sg:phone":"+1 512 799 2116",
    "sg:postcode":"78746",
    "sg:province":"TX",
    "sg:tags":[
        "martial art"
    ],
    "sg:website":"www.jettgarnermartialarts.com",
    "wof:name":"Jett Garner Martial Arts",
    "wof:placetype":"venue"
},
  "geometry": {"coordinates":[-97.85114400000001,30.312655],"type":"Point"}
}