{
  "type": "Feature",
  "properties": {
    "iso:country":"US",
    "sg:address":"6900 Skillman St",
    "sg:city":"Dallas",
    "sg:classifiers":[
        {
            "category":"Shopping",
            "subcategory":"Discount & Variety Stores",
            "type":"Retail Goods"
        }
    ],
    "sg:phone":"+1 214 343 9604",
    "sg:postcode":"75231",
    "sg:province":"TX",
    "sg:tags":[
        "merchandise",
        "general"
    ],
    "wof:name":"Worlds Grtst Hldy Str of",
    "wof:placetype":"venue"
},
  "geometry": {"coordinates":[-96.734703,32.873036],"type":"Point"}
}