{
  "type": "Feature",
  "properties": {
    "iso:country":"US",
    "sg:address":"5400 Bellaire Blvd",
    "sg:city":"Bellaire",
    "sg:classifiers":[
        {
            "category":"Personal",
            "subcategory":"Beauty Salon",
            "type":"Services"
        }
    ],
    "sg:phone":"+1 713 661 5412",
    "sg:postcode":"77401",
    "sg:province":"TX",
    "sg:tags":[
        "shop",
        "manicuring"
    ],
    "wof:name":"Luxury Nails",
    "wof:placetype":"venue"
},
  "geometry": {"coordinates":[-95.475026,29.70561],"type":"Point"}
}