{
  "type": "Feature",
  "properties": {
    "iso:country":"US",
    "sg:address":"777 Taylor St",
    "sg:city":"Fort Worth",
    "sg:classifiers":[
        {
            "category":"Professional",
            "subcategory":"Lawyer & Legal Services",
            "type":"Services"
        }
    ],
    "sg:phone":"+1 817 429 0574",
    "sg:postcode":"76102",
    "sg:province":"TX",
    "wof:name":"F D McCown Aty",
    "wof:placetype":"venue"
},
  "geometry": {"coordinates":[-97.332453,32.752003],"type":"Point"}
}