{
  "type": "Feature",
  "properties": {
    "iso:country":"US",
    "sg:address":"3603 Houston Hwy",
    "sg:city":"Victoria",
    "sg:classifiers":[
        {
            "category":"Restaurant",
            "type":"Food & Drink"
        }
    ],
    "sg:phone":"+1 361 576 6623",
    "sg:postcode":"77901",
    "sg:province":"TX",
    "wof:name":"Whataburger",
    "wof:placetype":"venue"
},
  "geometry": {"coordinates":[-96.96555600000001,28.815787],"type":"Point"}
}