{
  "type": "Feature",
  "properties": {
    "iso:country":"US",
    "sg:address":"9391 Grogans Mill Rd",
    "sg:city":"Spring",
    "sg:classifiers":[
        {
            "category":"Professional",
            "subcategory":"Research",
            "type":"Services"
        }
    ],
    "sg:phone":"+1 281 419 9737",
    "sg:postcode":"77380",
    "sg:province":"TX",
    "sg:tags":[
        "development",
        "laboratory"
    ],
    "wof:name":"Magnolia Research",
    "wof:placetype":"venue"
},
  "geometry": {"coordinates":[-95.46543699999999,30.167548],"type":"Point"}
}