{
  "type": "Feature",
  "properties": {
    "iso:country":"US",
    "sg:address":"2515 Babcock Rd",
    "sg:city":"San Antonio",
    "sg:classifiers":[
        {
            "category":"Health Services",
            "subcategory":"Doctor",
            "type":"Services"
        }
    ],
    "sg:phone":"+1 210 692 1267",
    "sg:postcode":"78229",
    "sg:province":"TX",
    "sg:tags":[
        "physician",
        "surgeon"
    ],
    "wof:name":"Neurology Clinic-San Antonio",
    "wof:placetype":"venue"
},
  "geometry": {"coordinates":[-98.58680099999999,29.506849],"type":"Point"}
}