{
  "type": "Feature",
  "properties": {
    "iso:country":"US",
    "sg:address":"29 Palmetto Pl",
    "sg:city":"Conroe",
    "sg:classifiers":[
        {
            "category":"Organizations",
            "subcategory":"Religious Organization",
            "type":"Services"
        }
    ],
    "sg:phone":"+1 936 756 6445",
    "sg:postcode":"77304",
    "sg:province":"TX",
    "sg:tags":[
        "clergy"
    ],
    "wof:name":"Charles W Wigley",
    "wof:placetype":"venue"
},
  "geometry": {"coordinates":[-95.492757,30.370573],"type":"Point"}
}