{
  "type": "Feature",
  "properties": {
    "iso:country":"US",
    "sg:address":"5225 Houston School Rd",
    "sg:city":"Dallas",
    "sg:classifiers":[
        {
            "category":"Restaurant",
            "type":"Food & Drink"
        }
    ],
    "sg:phone":"+1 214 371 3198",
    "sg:postcode":"75241",
    "sg:province":"TX",
    "sg:tags":[
        "barbeque"
    ],
    "wof:name":"Way Ways Bar B Que N Everything",
    "wof:placetype":"venue"
},
  "geometry": {"coordinates":[-96.80552299999999,32.681444],"type":"Point"}
}