{
  "type": "Feature",
  "properties": {
    "iso:country":"US",
    "sg:address":"4515 Village Fair Dr",
    "sg:city":"Dallas",
    "sg:classifiers":[
        {
            "category":"Arts & Performance",
            "subcategory":"Arts Center",
            "type":"Entertainment"
        },
        {
            "category":"Shopping",
            "subcategory":"Crafts & Fabrics",
            "type":"Retail Goods"
        },
        {
            "category":"Manufacturing",
            "subcategory":"Paper Products",
            "type":"Manufacturing & Wholesale Goods"
        },
        {
            "category":"Shopping",
            "subcategory":"Florist",
            "type":"Retail Goods"
        }
    ],
    "sg:phone":"+1 214 374 8655",
    "sg:postcode":"75224",
    "sg:province":"TX",
    "sg:tags":[
        "plant",
        "etc-retail",
        "tree",
        "artificial",
        "dried",
        "trees-silk",
        "bamboo",
        "flowers"
    ],
    "wof:name":"The Silk Flower Shop",
    "wof:placetype":"venue"
},
  "geometry": {"coordinates":[-96.828746,32.690079],"type":"Point"}
}