{
  "type": "Feature",
  "properties": {
    "iso:country":"US",
    "sg:address":"121 Lake Rd",
    "sg:city":"Belton",
    "sg:classifiers":[
        {
            "category":"Professional",
            "subcategory":"Management & Consulting",
            "type":"Services"
        },
        {
            "category":"Banks & Credit Unions",
            "subcategory":"Financial Services",
            "type":"Services"
        }
    ],
    "sg:phone":"+1 254 933 0358",
    "sg:postcode":"76513",
    "sg:province":"TX",
    "sg:tags":[
        "consultant",
        "financing",
        "planning"
    ],
    "wof:name":"Veritas Pa",
    "wof:placetype":"venue"
},
  "geometry": {"coordinates":[-97.459339,31.084368],"type":"Point"}
}