{
  "type": "Feature",
  "properties": {
    "iso:country":"US",
    "sg:address":"1420 S Fry Rd",
    "sg:city":"Katy",
    "sg:classifiers":[
        {
            "category":"Shopping",
            "subcategory":"Clothing, Apparel, & Fashions",
            "type":"Retail Goods"
        }
    ],
    "sg:phone":"+1 281 599 3489",
    "sg:postcode":"77450",
    "sg:province":"TX",
    "wof:name":"Catherines",
    "wof:placetype":"venue"
},
  "geometry": {"coordinates":[-95.716988,29.766649],"type":"Point"}
}