{
  "type": "Feature",
  "properties": {
    "iso:country":"US",
    "sg:address":"853 Sprucewood Ln",
    "sg:city":"Houston",
    "sg:classifiers":[
        {
            "category":"Professional",
            "subcategory":"Art Services",
            "type":"Services"
        }
    ],
    "sg:phone":"+1 713 468 0918",
    "sg:postcode":"77024",
    "sg:province":"TX",
    "sg:tags":[
        "photography",
        "commercial"
    ],
    "wof:name":"Jodi S Karren",
    "wof:placetype":"venue"
},
  "geometry": {"coordinates":[-95.515801,29.77979],"type":"Point"}
}