{
  "type": "Feature",
  "properties": {
    "iso:country":"US",
    "sg:address":"1087 W Main St",
    "sg:city":"Lewisville",
    "sg:classifiers":[
        {
            "category":"Shopping",
            "subcategory":"Pharmacy",
            "type":"Retail Goods"
        }
    ],
    "sg:phone":"+1 972 420 8590",
    "sg:postcode":"75067",
    "sg:province":"TX",
    "wof:name":"Sav-On Drugs",
    "wof:placetype":"venue"
},
  "geometry": {"coordinates":[-97.02051400000001,33.04216],"type":"Point"}
}