{
  "type": "Feature",
  "properties": {
    "iso:country":"US",
    "sg:address":"10925 Estate Ln",
    "sg:city":"Dallas",
    "sg:classifiers":[
        {
            "category":"Government",
            "subcategory":"Office",
            "type":"Public Place"
        }
    ],
    "sg:phone":"+1 214 340 7660",
    "sg:postcode":"75238",
    "sg:province":"TX",
    "sg:tags":[
        "rehabilitation"
    ],
    "wof:name":"Garland Field Office",
    "wof:placetype":"venue"
},
  "geometry": {"coordinates":[-96.694945,32.882383],"type":"Point"}
}