{
  "type": "Feature",
  "properties": {
    "iso:country":"US",
    "sg:address":"6145 Shadow Bend Pl",
    "sg:city":"Spring",
    "sg:classifiers":[
        {
            "category":"Health Services",
            "subcategory":"Clinic",
            "type":"Services"
        }
    ],
    "sg:phone":"+1 281 364 2549",
    "sg:postcode":"77381",
    "sg:province":"TX",
    "sg:tags":[
        "specialty",
        "outpatient"
    ],
    "wof:name":"Memorial Hermann Aquatic Ctr",
    "wof:placetype":"venue"
},
  "geometry": {"coordinates":[-95.496432,30.184699],"type":"Point"}
}