{
  "type": "Feature",
  "properties": {
    "iso:country":"US",
    "sg:address":"808 Cheyenne Trl",
    "sg:city":"Hewitt",
    "sg:classifiers":[
        {
            "category":"Shopping",
            "type":"Retail Goods"
        }
    ],
    "sg:phone":"+1 254 666 0735",
    "sg:postcode":"76643",
    "sg:province":"TX",
    "sg:tags":[
        "merchandise"
    ],
    "wof:name":"Justen Kayce Creations",
    "wof:placetype":"venue"
},
  "geometry": {"coordinates":[-97.20486200000001,31.456876],"type":"Point"}
}