{
  "type": "Feature",
  "properties": {
    "iso:country":"US",
    "sg:address":"9315 Broadway",
    "sg:city":"San Antonio",
    "sg:classifiers":[
        {
            "category":"Freight",
            "type":"Transportation"
        }
    ],
    "sg:phone":"+1 210 821 7793",
    "sg:postcode":"78217",
    "sg:province":"TX",
    "sg:tags":[
        "warehouse",
        "distribution",
        "center"
    ],
    "wof:name":"Dillards Inc",
    "wof:placetype":"venue"
},
  "geometry": {"coordinates":[-98.45441099999999,29.52685],"type":"Point"}
}