{
  "type": "Feature",
  "properties": {
    "iso:country":"US",
    "sg:address":"14427 Market Street Rd",
    "sg:city":"Houston",
    "sg:classifiers":[
        {
            "category":"Autos & Motor Vehicles",
            "subcategory":"Fuel & Gas Station",
            "type":"Retail Goods"
        }
    ],
    "sg:phone":"+1 713 455 9817",
    "sg:postcode":"77015",
    "sg:province":"TX",
    "sg:website":"www.chevron.com",
    "wof:name":"Hms Chevron Cloverfeaf",
    "wof:placetype":"venue"
},
  "geometry": {"coordinates":[-95.182503,29.7864],"type":"Point"}
}