{
  "type": "Feature",
  "properties": {
    "iso:country":"US",
    "sg:address":"405 S Bowie Dr",
    "sg:city":"Weatherford",
    "sg:classifiers":[
        {
            "category":"Organizations",
            "subcategory":"Religious Organization",
            "type":"Services"
        }
    ],
    "sg:phone":"+1 817 594 1590",
    "sg:postcode":"76086",
    "sg:province":"TX",
    "sg:tags":[
        "church"
    ],
    "wof:name":"Providence Reformed Episcopal",
    "wof:placetype":"venue"
},
  "geometry": {"coordinates":[-97.81443899999999,32.754583],"type":"Point"}
}