{
  "type": "Feature",
  "properties": {
    "iso:country":"US",
    "sg:address":"1475 Pagewood Ave",
    "sg:city":"Odessa",
    "sg:classifiers":[
        {
            "category":"Health Services",
            "subcategory":"Nursing And Care Facility",
            "type":"Services"
        }
    ],
    "sg:phone":"+1 432 362 8035",
    "sg:postcode":"79761",
    "sg:province":"TX",
    "sg:tags":[
        "home",
        "retirement",
        "community"
    ],
    "wof:name":"Lois Owen Assisted Living",
    "wof:placetype":"venue"
},
  "geometry": {"coordinates":[-102.32883,31.873759],"type":"Point"}
}