{
  "type": "Feature",
  "properties": {
    "iso:country":"US",
    "sg:address":"3200 McKnight Ln",
    "sg:city":"Corsicana",
    "sg:classifiers":[
        {
            "category":"Shopping",
            "subcategory":"Books",
            "type":"Retail Goods"
        }
    ],
    "sg:phone":"+1 903 874 2821",
    "sg:postcode":"75110",
    "sg:province":"TX",
    "wof:name":"Maries Personalized Chil",
    "wof:placetype":"venue"
},
  "geometry": {"coordinates":[-96.49178999999999,32.120846],"type":"Point"}
}