{
  "type": "Feature",
  "properties": {
    "iso:country":"US",
    "sg:address":"3913 Pin Oak Ter",
    "sg:city":"Euless",
    "sg:classifiers":[
        {
            "category":"Manufacturing",
            "subcategory":"Printing",
            "type":"Manufacturing & Wholesale Goods"
        }
    ],
    "sg:phone":"+1 817 355 0527",
    "sg:postcode":"76040",
    "sg:province":"TX",
    "sg:tags":[
        "publisher",
        "magazine"
    ],
    "wof:name":"Hearst Corporation",
    "wof:placetype":"venue"
},
  "geometry": {"coordinates":[-97.065675,32.822134],"type":"Point"}
}