{
  "type": "Feature",
  "properties": {
    "iso:country":"US",
    "sg:address":"301 Santa Fe Dr",
    "sg:city":"Waco",
    "sg:classifiers":[
        {
            "category":"Recreation",
            "type":"Entertainment"
        }
    ],
    "sg:phone":"+1 254 235 5702",
    "sg:postcode":"76712",
    "sg:province":"TX",
    "wof:name":"Dugger Billiards",
    "wof:placetype":"venue"
},
  "geometry": {"coordinates":[-97.207183,31.508665],"type":"Point"}
}