{
  "type": "Feature",
  "properties": {
    "iso:country":"US",
    "sg:address":"1320 Inwood Rd",
    "sg:city":"Dallas",
    "sg:classifiers":[
        {
            "category":"Shopping",
            "subcategory":"Shoes",
            "type":"Retail Goods"
        }
    ],
    "sg:phone":"+1 214 631 7463",
    "sg:postcode":"75247",
    "sg:province":"TX",
    "sg:tags":[
        "store"
    ],
    "wof:name":"Shoe Fair",
    "wof:placetype":"venue"
},
  "geometry": {"coordinates":[-96.852097,32.806301],"type":"Point"}
}