{
  "type": "Feature",
  "properties": {
    "iso:country":"US",
    "sg:address":"2211 S Bowen Rd",
    "sg:city":"Arlington",
    "sg:classifiers":[
        {
            "category":"Social Services",
            "subcategory":"Child Care",
            "type":"Services"
        }
    ],
    "sg:phone":"+1 817 226 4245",
    "sg:postcode":"76013",
    "sg:province":"TX",
    "sg:tags":[
        "day"
    ],
    "wof:name":"Gail's Academy",
    "wof:placetype":"venue"
},
  "geometry": {"coordinates":[-97.149123,32.7084],"type":"Point"}
}