{
  "type": "Feature",
  "properties": {
    "iso:country":"US",
    "sg:address":"801 W Main",
    "sg:city":"Tomball",
    "sg:classifiers":[
        {
            "category":"Wholesale",
            "subcategory":"Electrical",
            "type":"Manufacturing & Wholesale Goods"
        }
    ],
    "sg:phone":"+1 281 848 4500",
    "sg:postcode":"77375",
    "sg:province":"TX",
    "sg:tags":[
        "equipment",
        "electronic",
        "supply"
    ],
    "wof:name":"Esco",
    "wof:placetype":"venue"
},
  "geometry": {"coordinates":[-95.62252100000001,30.094407],"type":"Point"}
}