{
  "type": "Feature",
  "properties": {
    "iso:country":"US",
    "sg:address":"1555 Lake Woodlands Dr",
    "sg:city":"Spring",
    "sg:classifiers":[
        {
            "category":"Autos & Motor Vehicles",
            "subcategory":"Auto Supplies",
            "type":"Retail Goods"
        },
        {
            "category":"Retail",
            "subcategory":"Auto Repair",
            "type":"Services"
        }
    ],
    "sg:phone":"+1 281 362 3095",
    "sg:postcode":"77380",
    "sg:province":"TX",
    "sg:tags":[
        "oil",
        "tire",
        "automobile",
        "accessory",
        "lube",
        "part",
        "supplies-used",
        "brake",
        "rebuilt"
    ],
    "sg:website":"http://www.sears.com/shc/s/v_10153_12605_Automotive?adCell=AH",
    "wof:name":"Sears Auto Center",
    "wof:placetype":"venue"
},
  "geometry": {"coordinates":[-95.458701,30.167127],"type":"Point"}
}