{
  "type": "Feature",
  "properties": {
    "iso:country":"US",
    "sg:address":"7002 Ridge Hollow",
    "sg:city":"Austin",
    "sg:classifiers":[
        {
            "category":"Professional",
            "type":"Services"
        }
    ],
    "sg:phone":"+1 512 502 9641",
    "sg:postcode":"78750",
    "sg:province":"TX",
    "wof:name":"Leo Group",
    "wof:placetype":"venue"
},
  "geometry": {"coordinates":[-97.791196,30.372087],"type":"Point"}
}