{
  "type": "Feature",
  "properties": {
    "iso:country":"US",
    "sg:address":"8909 Rockcrest Dr",
    "sg:city":"Austin",
    "sg:classifiers":[
        {
            "category":"Personal",
            "type":"Services"
        }
    ],
    "sg:phone":"+1 512 346 6078",
    "sg:postcode":"78759",
    "sg:province":"TX",
    "wof:name":"Mesa Petsitters",
    "wof:placetype":"venue"
},
  "geometry": {"coordinates":[-97.749233,30.384459],"type":"Point"}
}