{
  "type": "Feature",
  "properties": {
    "iso:country":"US",
    "sg:address":"6705 Biltmore Pl",
    "sg:city":"Plano",
    "sg:classifiers":[
        {
            "category":"Manufacturing",
            "subcategory":"Metals",
            "type":"Manufacturing & Wholesale Goods"
        }
    ],
    "sg:phone":"+1 972 491 2485",
    "sg:postcode":"75023",
    "sg:province":"TX",
    "sg:tags":[
        "painting-production"
    ],
    "wof:name":"Dalton Products",
    "wof:placetype":"venue"
},
  "geometry": {"coordinates":[-96.76705699999999,33.063803],"type":"Point"}
}