{
  "type": "Feature",
  "properties": {
    "iso:country":"US",
    "sg:address":"8431 Gallahad St",
    "sg:city":"Houston",
    "sg:classifiers":[
        {
            "category":"Wholesale",
            "subcategory":"Hardware",
            "type":"Manufacturing & Wholesale Goods"
        }
    ],
    "sg:phone":"+1 713 631 1579",
    "sg:postcode":"77078",
    "sg:province":"TX",
    "wof:name":"Janeth Arcain Fan Club",
    "wof:placetype":"venue"
},
  "geometry": {"coordinates":[-95.27059800000001,29.851678],"type":"Point"}
}