{
  "type": "Feature",
  "properties": {
    "iso:country":"US",
    "sg:address":"120 Casa Grande Dr",
    "sg:city":"Odessa",
    "sg:classifiers":[
        {
            "category":"Wholesale",
            "subcategory":"Electrical",
            "type":"Manufacturing & Wholesale Goods"
        }
    ],
    "sg:phone":"+1 432 580 0218",
    "sg:postcode":"79763",
    "sg:province":"TX",
    "sg:tags":[
        "sound",
        "equipment",
        "system"
    ],
    "wof:name":"Mainsound",
    "wof:placetype":"venue"
},
  "geometry": {"coordinates":[-102.38996400000001,31.855273],"type":"Point"}
}