{
  "type": "Feature",
  "properties": {
    "iso:country":"US",
    "sg:address":"19002 Dallas Pkwy",
    "sg:city":"Dallas",
    "sg:classifiers":[
        {
            "category":"Personal",
            "type":"Services"
        }
    ],
    "sg:phone":"+1 972 930 0102",
    "sg:postcode":"75287",
    "sg:province":"TX",
    "sg:tags":[
        "credit",
        "debt",
        "counseling"
    ],
    "wof:name":"Credit Counseling Ctr",
    "wof:placetype":"venue"
},
  "geometry": {"coordinates":[-96.828399,33.012831],"type":"Point"}
}