{
  "type": "Feature",
  "properties": {
    "iso:country":"US",
    "sg:address":"4376 Bentwood Dr",
    "sg:city":"College Station",
    "sg:classifiers":[
        {
            "category":"Building & Trades",
            "subcategory":"Construction",
            "type":"Services"
        }
    ],
    "sg:phone":"+1 979 690 9980",
    "sg:postcode":"77845",
    "sg:province":"TX",
    "sg:tags":[
        "home",
        "builder"
    ],
    "wof:name":"Click Homes Inc",
    "wof:placetype":"venue"
},
  "geometry": {"coordinates":[-96.270201,30.498248],"type":"Point"}
}