{
  "type": "Feature",
  "properties": {
    "iso:country":"US",
    "sg:address":"1500 S Main St",
    "sg:city":"Lindale",
    "sg:classifiers":[
        {
            "category":"Shopping",
            "subcategory":"Department Store",
            "type":"Retail Goods"
        },
        {
            "category":"Shopping",
            "subcategory":"Discount & Variety Stores",
            "type":"Retail Goods"
        }
    ],
    "sg:phone":"+1 903 881 2243",
    "sg:postcode":"75771",
    "sg:province":"TX",
    "sg:website":"http://www.familydollar.com",
    "wof:name":"Family Dollar Stores",
    "wof:placetype":"venue"
},
  "geometry": {"coordinates":[-95.405063,32.49951],"type":"Point"}
}