{
  "type": "Feature",
  "properties": {
    "iso:country":"US",
    "sg:address":"22299 US Hwy 59",
    "sg:city":"Humble",
    "sg:classifiers":[
        {
            "category":"Health Services",
            "subcategory":"Doctor",
            "type":"Services"
        }
    ],
    "sg:phone":"+1 281 312 5006",
    "sg:postcode":"77339",
    "sg:province":"TX",
    "sg:tags":[
        "medical"
    ],
    "wof:name":"Achi Jyothi MD PA",
    "wof:placetype":"venue"
},
  "geometry": {"coordinates":[-95.257216,30.032255],"type":"Point"}
}