{
  "type": "Feature",
  "properties": {
    "iso:country":"US",
    "sg:address":"5745 TX-121",
    "sg:city":"The Colony",
    "sg:classifiers":[
        {
            "category":"Bars & Pubs",
            "type":"Food & Drink"
        }
    ],
    "sg:menulink":"http://www.allmenus.com/tx/hebron/176009-dickeys-barbecue-pit/menu/",
    "sg:phone":"+1 469 362 2179",
    "sg:postcode":"75056",
    "sg:province":"TX",
    "sg:tags":[
        "barbecue",
        "american"
    ],
    "wof:name":"Dickey's Barbecue Pit",
    "wof:placetype":"venue"
},
  "geometry": {"coordinates":[-96.853858,33.081344],"type":"Point"}
}