{
  "type": "Feature",
  "properties": {
    "iso:country":"US",
    "sg:address":"1616 Magnolia Ave",
    "sg:city":"Port Neches",
    "sg:classifiers":[
        {
            "category":"Retail",
            "subcategory":"Laundry & Dry Cleaning",
            "type":"Services"
        }
    ],
    "sg:phone":"+1 409 727 7171",
    "sg:postcode":"77651",
    "sg:province":"TX",
    "sg:tags":[
        "drycleaning",
        "plant",
        "agent",
        "garment"
    ],
    "wof:name":"Magnolia Cleaners",
    "wof:placetype":"venue"
},
  "geometry": {"coordinates":[-93.969117,29.984503],"type":"Point"}
}