{
  "type": "Feature",
  "properties": {
    "iso:country":"US",
    "sg:address":"1350 E Whitestone Blvd",
    "sg:city":"Cedar Park",
    "sg:classifiers":[
        {
            "category":"Retail",
            "subcategory":"Car Wash",
            "type":"Services"
        }
    ],
    "sg:phone":"+1 512 259 5252",
    "sg:postcode":"78613",
    "sg:province":"TX",
    "sg:website":"www.towerexpresscarwash.com",
    "wof:name":"Tower Express Car Wash",
    "wof:placetype":"venue"
},
  "geometry": {"coordinates":[-97.814652,30.52556],"type":"Point"}
}