{
  "type": "Feature",
  "properties": {
    "iso:country":"US",
    "sg:address":"1802 Ave B",
    "sg:city":"Lubbock",
    "sg:classifiers":[
        {
            "category":"Organizations",
            "subcategory":"Religious Organization",
            "type":"Services"
        }
    ],
    "sg:phone":"+1 806 747 4170",
    "sg:postcode":"79401",
    "sg:province":"TX",
    "wof:name":"St Paul Historic Church",
    "wof:placetype":"venue"
},
  "geometry": {"coordinates":[-101.837551,33.57782],"type":"Point"}
}