{
  "type": "Feature",
  "properties": {
    "iso:country":"US",
    "sg:address":"3340 N Beach St",
    "sg:city":"Haltom City",
    "sg:classifiers":[
        {
            "category":"Building & Trades",
            "subcategory":"Electrical",
            "type":"Services"
        }
    ],
    "sg:phone":"+1 817 237 2406",
    "sg:postcode":"76111",
    "sg:province":"TX",
    "sg:tags":[
        "electric",
        "contractor"
    ],
    "wof:name":"All-Fair Electric Inc",
    "wof:placetype":"venue"
},
  "geometry": {"coordinates":[-97.290471,32.805465],"type":"Point"}
}