{
  "type": "Feature",
  "properties": {
    "iso:country":"US",
    "sg:address":"505 E Highway 199",
    "sg:city":"Springtown",
    "sg:classifiers":[
        {
            "category":"Personal",
            "subcategory":"Nail Salon",
            "type":"Services"
        }
    ],
    "sg:phone":"+1 817 523 5318",
    "sg:postcode":"76082",
    "sg:province":"TX",
    "wof:name":"Solar Nails 1",
    "wof:placetype":"venue"
},
  "geometry": {"coordinates":[-97.67159599999999,32.958603],"type":"Point"}
}