{
  "type": "Feature",
  "properties": {
    "iso:country":"US",
    "sg:address":"205 N Davis Dr Ste 2",
    "sg:city":"Arlington",
    "sg:classifiers":[
        {
            "category":"Insurance",
            "subcategory":"Hazard Insurance",
            "type":"Services"
        }
    ],
    "sg:phone":"+1 817 274 3004",
    "sg:postcode":"76012",
    "sg:province":"TX",
    "sg:tags":[
        "commercial",
        "business"
    ],
    "sg:website":"http://www.farmersagent.com/cwofford/",
    "wof:name":"Clifton Wofford Jr - Farmers Insurance",
    "wof:placetype":"venue"
},
  "geometry": {"coordinates":[-97.12323000000001,32.737864],"type":"Point"}
}