{
  "type": "Feature",
  "properties": {
    "iso:country":"US",
    "sg:address":"3100 Gaston Dr",
    "sg:city":"El Paso",
    "sg:classifiers":[
        {
            "category":"Professional",
            "subcategory":"Detective & Security Services",
            "type":"Services"
        }
    ],
    "sg:phone":"+1 915 590 0060",
    "sg:postcode":"79935",
    "sg:province":"TX",
    "sg:tags":[
        "private",
        "investigator"
    ],
    "wof:name":"Ppj Investigations",
    "wof:placetype":"venue"
},
  "geometry": {"coordinates":[-106.32772199999999,31.785317],"type":"Point"}
}