{
  "type": "Feature",
  "properties": {
    "iso:country":"US",
    "sg:address":"11302 Sageway Dr",
    "sg:city":"Houston",
    "sg:classifiers":[
        {
            "category":"Wholesale",
            "subcategory":"Durable Goods & Equipment",
            "type":"Manufacturing & Wholesale Goods"
        }
    ],
    "sg:phone":"+1 281 481 0188",
    "sg:postcode":"77089",
    "sg:province":"TX",
    "sg:tags":[
        "representative",
        "manufacturer"
    ],
    "sg:website":"www.antistress.com",
    "wof:name":"Enviroshield Products",
    "wof:placetype":"venue"
},
  "geometry": {"coordinates":[-95.20862,29.601894],"type":"Point"}
}