{
  "type": "Feature",
  "properties": {
    "iso:country":"US",
    "sg:address":"7500 Bellaire Blvd",
    "sg:city":"Houston",
    "sg:classifiers":[
        {
            "category":"Manufacturing",
            "subcategory":"Metals",
            "type":"Manufacturing & Wholesale Goods"
        },
        {
            "category":"Shopping",
            "subcategory":"Jewelry",
            "type":"Retail Goods"
        },
        {
            "category":"Manufacturing",
            "subcategory":"Jewelry",
            "type":"Manufacturing & Wholesale Goods"
        }
    ],
    "sg:phone":"+1 713 772 1218",
    "sg:postcode":"77036",
    "sg:province":"TX",
    "sg:tags":[
        "repairing",
        "manufacturer",
        "metals-precious",
        "jewelers-wholesale",
        "jeweler"
    ],
    "wof:name":"View Gold & Watch Supplies",
    "wof:placetype":"venue"
},
  "geometry": {"coordinates":[-95.51584800000001,29.70518],"type":"Point"}
}