{
  "type": "Feature",
  "properties": {
    "iso:country":"US",
    "sg:address":"3205 Junction Hwy",
    "sg:city":"Ingram",
    "sg:classifiers":[
        {
            "category":"Building & Trades",
            "subcategory":"Equipment Rental",
            "type":"Services"
        },
        {
            "category":"Shopping",
            "type":"Retail Goods"
        },
        {
            "category":"Home & Garden",
            "subcategory":"Furniture",
            "type":"Retail Goods"
        }
    ],
    "sg:phone":"+1 830 367 2773",
    "sg:postcode":"78025",
    "sg:province":"TX",
    "sg:tags":[
        "renting",
        "rent-to-own",
        "leasing",
        "yard",
        "store"
    ],
    "wof:name":"General Rental Center",
    "wof:placetype":"venue"
},
  "geometry": {"coordinates":[-99.22794500000001,30.073311],"type":"Point"}
}