{
  "type": "Feature",
  "properties": {
    "iso:country":"US",
    "sg:address":"56 W Elm St",
    "sg:city":"Hillsboro",
    "sg:classifiers":[
        {
            "category":"Shopping",
            "subcategory":"Clothing, Apparel, & Fashions",
            "type":"Retail Goods"
        }
    ],
    "sg:phone":"+1 254 582 5151",
    "sg:postcode":"76645",
    "sg:province":"TX",
    "wof:name":"Lazy Sb",
    "wof:placetype":"venue"
},
  "geometry": {"coordinates":[-97.13108699999999,32.010681],"type":"Point"}
}