{
  "type": "Feature",
  "properties": {
    "iso:country":"US",
    "sg:address":"10225 T S Saul Rd",
    "sg:city":"Brenham",
    "sg:classifiers":[
        {
            "category":"Mining & Drilling",
            "type":"Manufacturing & Wholesale Goods"
        }
    ],
    "sg:phone":"+1 979 830 8580",
    "sg:postcode":"77833",
    "sg:province":"TX",
    "sg:tags":[
        "field"
    ],
    "wof:name":"Jims Field Service",
    "wof:placetype":"venue"
},
  "geometry": {"coordinates":[-96.344579,30.317725],"type":"Point"}
}