{
  "type": "Feature",
  "properties": {
    "iso:country":"US",
    "sg:address":"5709 Parkwood Dr",
    "sg:city":"Austin",
    "sg:classifiers":[
        {
            "category":"Building & Trades",
            "subcategory":"Construction",
            "type":"Services"
        }
    ],
    "sg:phone":"+1 512 899 1542",
    "sg:postcode":"78735",
    "sg:province":"TX",
    "sg:tags":[
        "house"
    ],
    "wof:name":"Stetson Construction",
    "wof:placetype":"venue"
},
  "geometry": {"coordinates":[-97.853171,30.240465],"type":"Point"}
}