{
  "type": "Feature",
  "properties": {
    "iso:country":"US",
    "sg:address":"1834 N Loop 1604 E ",
    "sg:city":"San Antonio",
    "sg:classifiers":[
        {
            "category":"Restaurant",
            "type":"Food & Drink"
        }
    ],
    "sg:menulink":"http://www.allmenus.com/tx/san-antonio/269546-wildfish-seafood-grille---san-antonio/menu/",
    "sg:phone":"+1 210 493 1600",
    "sg:postcode":"78232",
    "sg:province":"TX",
    "sg:tags":[
        "seafood",
        "american"
    ],
    "wof:name":"Wildfish Seafood Grille - San Antonio",
    "wof:placetype":"venue"
},
  "geometry": {"coordinates":[-98.462369,29.607291],"type":"Point"}
}