{
  "type": "Feature",
  "properties": {
    "iso:country":"US",
    "sg:address":"7515 Lemmon Ave",
    "sg:city":"Dallas",
    "sg:classifiers":[
        {
            "category":"Airport",
            "type":"Transportation"
        }
    ],
    "sg:phone":"+1 214 352 2600",
    "sg:postcode":"75204",
    "sg:province":"TX",
    "sg:tags":[
        "airplane",
        "corporate",
        "hangar"
    ],
    "wof:name":"Exxon",
    "wof:placetype":"venue"
},
  "geometry": {"coordinates":[-96.838515,32.848366],"type":"Point"}
}