{
  "type": "Feature",
  "properties": {
    "iso:country":"US",
    "sg:address":"7676 Hillmont St",
    "sg:city":"Houston",
    "sg:classifiers":[
        {
            "category":"Professional",
            "subcategory":"Computer Services",
            "type":"Services"
        }
    ],
    "sg:phone":"+1 713 996 9396",
    "sg:postcode":"77040",
    "sg:province":"TX",
    "sg:tags":[
        "information",
        "technology"
    ],
    "wof:name":"Modis Technical Ctr",
    "wof:placetype":"venue"
},
  "geometry": {"coordinates":[-95.50558700000001,29.843719],"type":"Point"}
}