{
  "type": "Feature",
  "properties": {
    "iso:country":"US",
    "sg:address":"2000 Crawford St",
    "sg:city":"Houston",
    "sg:classifiers":[
        {
            "category":"Health Services",
            "subcategory":"Doctor",
            "type":"Services"
        }
    ],
    "sg:phone":"+1 832 366 1477",
    "sg:postcode":"77002",
    "sg:province":"TX",
    "sg:tags":[
        "physician",
        "surgeon"
    ],
    "wof:name":"Shaista Husain MD",
    "wof:placetype":"venue"
},
  "geometry": {"coordinates":[-95.36577699999999,29.746236],"type":"Point"}
}