{
  "type": "Feature",
  "properties": {
    "iso:country":"US",
    "sg:address":"10750 Cradlerock Dr",
    "sg:city":"Dallas",
    "sg:classifiers":[
        {
            "category":"Education",
            "subcategory":"School",
            "type":"Public Place"
        }
    ],
    "sg:phone":"+1 972 749 6100",
    "sg:postcode":"75217",
    "sg:province":"TX",
    "sg:website":"www.dallasisd.org",
    "wof:name":"Schools",
    "wof:placetype":"venue"
},
  "geometry": {"coordinates":[-96.640923,32.741269],"type":"Point"}
}