{
  "type": "Feature",
  "properties": {
    "iso:country":"US",
    "sg:address":"16414 US Hwy 281",
    "sg:city":"San Antonio",
    "sg:classifiers":[
        {
            "category":"Professional",
            "subcategory":"Employment Agencies",
            "type":"Services"
        }
    ],
    "sg:phone":"+1 210 495 5900",
    "sg:postcode":"78232",
    "sg:province":"TX",
    "sg:tags":[
        "opportunity"
    ],
    "wof:name":"Bullock Personnel Inc",
    "wof:placetype":"venue"
},
  "geometry": {"coordinates":[-98.473373,29.592089],"type":"Point"}
}