{
  "type": "Feature",
  "properties": {
    "iso:country":"US",
    "sg:address":"2539 Anzio Dr",
    "sg:city":"Dallas",
    "sg:classifiers":[
        {
            "category":"Professional",
            "subcategory":"Business Services",
            "type":"Services"
        }
    ],
    "sg:phone":"+1 214 948 7996",
    "sg:postcode":"75224",
    "sg:province":"TX",
    "wof:name":"Mind Resource Assoc Inc",
    "wof:placetype":"venue"
},
  "geometry": {"coordinates":[-96.831265,32.718946],"type":"Point"}
}