{
  "type": "Feature",
  "properties": {
    "iso:country":"US",
    "sg:address":"1923 Castlerock Rd",
    "sg:city":"Houston",
    "sg:classifiers":[
        {
            "category":"Wholesale",
            "subcategory":"Jewelry",
            "type":"Manufacturing & Wholesale Goods"
        }
    ],
    "sg:phone":"+1 281 537 1992",
    "sg:postcode":"77090",
    "sg:province":"TX",
    "sg:tags":[
        "stone"
    ],
    "wof:name":"Beaded Treasures",
    "wof:placetype":"venue"
},
  "geometry": {"coordinates":[-95.466099,30.020451],"type":"Point"}
}