{
  "type": "Feature",
  "properties": {
    "iso:country":"US",
    "sg:address":"5903 Brock St",
    "sg:city":"Houston",
    "sg:classifiers":[
        {
            "category":"Building & Trades",
            "subcategory":"Construction",
            "type":"Services"
        }
    ],
    "sg:phone":"+1 713 923 9184",
    "sg:postcode":"77023",
    "sg:province":"TX",
    "sg:tags":[
        "hanging",
        "contractor"
    ],
    "wof:name":"Universal Refinish & Painting",
    "wof:placetype":"venue"
},
  "geometry": {"coordinates":[-95.320688,29.707155],"type":"Point"}
}