{
  "type": "Feature",
  "properties": {
    "iso:country":"US",
    "sg:address":"209 E 7th St",
    "sg:city":"Seven Points",
    "sg:classifiers":[
        {
            "category":"Organizations",
            "subcategory":"Community Association",
            "type":"Services"
        }
    ],
    "sg:phone":"+1 903 432 2138",
    "sg:postcode":"75143",
    "sg:province":"TX",
    "sg:tags":[
        "military"
    ],
    "wof:name":"Veterans Of Foreign Wars",
    "wof:placetype":"venue"
},
  "geometry": {"coordinates":[-96.231139,32.444211],"type":"Point"}
}