{
  "type": "Feature",
  "properties": {
    "iso:country":"US",
    "sg:address":"3210 Potomac Dr",
    "sg:city":"Amarillo",
    "sg:classifiers":[
        {
            "category":"Building & Trades",
            "subcategory":"Construction",
            "type":"Services"
        }
    ],
    "sg:phone":"+1 806 381 0180",
    "sg:postcode":"79108",
    "sg:province":"TX",
    "sg:tags":[
        "system",
        "specialty",
        "heating",
        "mechanical",
        "contractor",
        "air conditioning"
    ],
    "wof:name":"Cosselmon Mechanical",
    "wof:placetype":"venue"
},
  "geometry": {"coordinates":[-101.8725,35.301787],"type":"Point"}
}