{
  "type": "Feature",
  "properties": {
    "iso:country":"US",
    "sg:address":"2807 Little York Rd",
    "sg:city":"Houston",
    "sg:classifiers":[
        {
            "category":"Health Services",
            "subcategory":"Doctor",
            "type":"Services"
        }
    ],
    "sg:phone":"+1 713 694 7476",
    "sg:postcode":"77093",
    "sg:province":"TX",
    "wof:name":"Borges Rafael G MD",
    "wof:placetype":"venue"
},
  "geometry": {"coordinates":[-95.340401,29.871201],"type":"Point"}
}