{
  "type": "Feature",
  "properties": {
    "iso:country":"US",
    "sg:address":"7807 S Cooper St",
    "sg:city":"Arlington",
    "sg:classifiers":[
        {
            "category":"Personal",
            "subcategory":"Beauty Salon",
            "type":"Services"
        }
    ],
    "sg:phone":"+1 817 466 4493",
    "sg:postcode":"76001",
    "sg:province":"TX",
    "wof:name":"Top Cuts",
    "wof:placetype":"venue"
},
  "geometry": {"coordinates":[-97.138353,32.618137],"type":"Point"}
}