{
  "type": "Feature",
  "properties": {
    "iso:country":"US",
    "sg:address":"1619 Fannin St",
    "sg:city":"Houston",
    "sg:classifiers":[
        {
            "category":"Food & Beverages",
            "subcategory":"Groceries & Convenience Stores",
            "type":"Retail Goods"
        }
    ],
    "sg:phone":"+1 713 650 3101",
    "sg:postcode":"77002",
    "sg:province":"TX",
    "wof:name":"Express Grocery & Deli the",
    "wof:placetype":"venue"
},
  "geometry": {"coordinates":[-95.368103,29.7512],"type":"Point"}
}