{
  "type": "Feature",
  "properties": {
    "iso:country":"US",
    "sg:address":"407 Palmetto St",
    "sg:city":"Corpus Christi",
    "sg:classifiers":[
        {
            "category":"Professional",
            "subcategory":"Business Services",
            "type":"Services"
        }
    ],
    "sg:phone":"+1 361 985 9610",
    "sg:postcode":"78412",
    "sg:province":"TX",
    "wof:name":"Advanced Systems Solutions",
    "wof:placetype":"venue"
},
  "geometry": {"coordinates":[-97.349147,27.718474],"type":"Point"}
}