{
  "type": "Feature",
  "properties": {
    "iso:country":"US",
    "sg:address":"1601 Picnic Cove",
    "sg:city":"Round Rock",
    "sg:classifiers":[
        {
            "category":"Arts & Performance",
            "subcategory":"Theater",
            "type":"Entertainment"
        }
    ],
    "sg:phone":"+1 512 341 0735",
    "sg:postcode":"78664",
    "sg:province":"TX",
    "sg:tags":[
        "group"
    ],
    "wof:name":"Ctown Collective Inc",
    "wof:placetype":"venue"
},
  "geometry": {"coordinates":[-97.662772,30.497944],"type":"Point"}
}