{
  "type": "Feature",
  "properties": {
    "iso:country":"US",
    "sg:address":"11334 Russell St",
    "sg:city":"Mesquite",
    "sg:classifiers":[
        {
            "category":"Shopping",
            "subcategory":"Musical Instruments",
            "type":"Retail Goods"
        }
    ],
    "sg:phone":"+1 972 289 9390",
    "sg:postcode":"75180",
    "sg:province":"TX",
    "sg:tags":[
        "organs"
    ],
    "wof:name":"Range Organ Co & Inc",
    "wof:placetype":"venue"
},
  "geometry": {"coordinates":[-96.632903,32.741284],"type":"Point"}
}