{
  "type": "Feature",
  "properties": {
    "iso:country":"US",
    "sg:address":"600 E Austin St",
    "sg:city":"Kermit",
    "sg:classifiers":[
        {
            "category":"Professional",
            "subcategory":"Accounting & Tax Preparation",
            "type":"Services"
        }
    ],
    "sg:phone":"+1 432 586 2698",
    "sg:postcode":"79745",
    "sg:province":"TX",
    "wof:name":"Betty Hyes Bookkeeping Tax Svc",
    "wof:placetype":"venue"
},
  "geometry": {"coordinates":[-103.088218,31.859178],"type":"Point"}
}