{
  "type": "Feature",
  "properties": {
    "iso:country":"US",
    "sg:address":"2419 Webster Ranch Rd",
    "sg:city":"Friendswood",
    "sg:classifiers":[
        {
            "category":"Real Estate",
            "subcategory":"Real Estate Agent",
            "type":"Services"
        }
    ],
    "sg:phone":"+1 409 941 0584",
    "sg:postcode":"77546",
    "sg:province":"TX",
    "sg:tags":[
        "appraiser"
    ],
    "wof:name":"Hamilton & Assoc",
    "wof:placetype":"venue"
},
  "geometry": {"coordinates":[-95.166219,29.538205],"type":"Point"}
}