{
  "type": "Feature",
  "properties": {
    "iso:country":"US",
    "sg:address":"3919 W 16th St",
    "sg:city":"Odessa",
    "sg:classifiers":[
        {
            "category":"Manufacturing",
            "subcategory":"Metals",
            "type":"Manufacturing & Wholesale Goods"
        }
    ],
    "sg:phone":"+1 432 381 1392",
    "sg:postcode":"79763",
    "sg:province":"TX",
    "sg:tags":[
        "ball",
        "bronze"
    ],
    "wof:name":"Texas Specialty Ball Co",
    "wof:placetype":"venue"
},
  "geometry": {"coordinates":[-102.419245,31.844621],"type":"Point"}
}