{
  "type": "Feature",
  "properties": {
    "iso:country":"US",
    "sg:address":"2210 Loop 431",
    "sg:city":"Eagle Pass",
    "sg:classifiers":[
        {
            "category":"Communications",
            "subcategory":"Television Station",
            "type":"Services"
        }
    ],
    "sg:phone":"+1 830 773 3668",
    "sg:postcode":"78852",
    "sg:province":"TX",
    "sg:tags":[
        "broadcasting",
        "co"
    ],
    "wof:name":"Hispanic Television Network",
    "wof:placetype":"venue"
},
  "geometry": {"coordinates":[-100.49097399999999,28.73833],"type":"Point"}
}