{
  "type": "Feature",
  "properties": {
    "iso:country":"US",
    "sg:address":"5283 Hardy Weedon Rd",
    "sg:city":"College Station",
    "sg:classifiers":[
        {
            "category":"Food & Beverages",
            "subcategory":"Dairy",
            "type":"Retail Goods"
        }
    ],
    "sg:phone":"+1 979 776 8372",
    "sg:postcode":"77845",
    "sg:province":"TX",
    "sg:tags":[
        "product"
    ],
    "wof:name":"Morgan Cook",
    "wof:placetype":"venue"
},
  "geometry": {"coordinates":[-96.24901800000001,30.660836],"type":"Point"}
}