{
  "type": "Feature",
  "properties": {
    "iso:country":"US",
    "sg:address":"515 Congress Avenue",
    "sg:city":"Austin",
    "sg:classifiers":[
        {
            "category":"Restaurant",
            "type":"Food & Drink"
        }
    ],
    "sg:phone":"+1 512 457 4900",
    "sg:postcode":"78701",
    "sg:province":"TX",
    "wof:name":"Jimmy John's Gourmet Sandwiches",
    "wof:placetype":"venue"
},
  "geometry": {"coordinates":[-97.743098,30.267259],"type":"Point"}
}