{
  "type": "Feature",
  "properties": {
    "iso:country":"US",
    "sg:address":"2400 Fannin Ave",
    "sg:city":"Midland",
    "sg:classifiers":[
        {
            "category":"Education",
            "subcategory":"School",
            "type":"Public Place"
        }
    ],
    "sg:phone":"+1 432 689 1450",
    "sg:postcode":"79705",
    "sg:province":"TX",
    "wof:name":"Fannin Elementary School",
    "wof:placetype":"venue"
},
  "geometry": {"coordinates":[-102.110885,32.017544],"type":"Point"}
}