{
  "type": "Feature",
  "properties": {
    "iso:country":"US",
    "sg:address":"1315 South Congress Above the Continental Club",
    "sg:city":"Austin",
    "sg:classifiers":[
        {
            "category":"Bars & Pubs",
            "type":"Food & Drink"
        },
        {
            "category":"Arts & Performance",
            "subcategory":"Jazz & Blues",
            "type":"Entertainment"
        }
    ],
    "sg:phone":"+1 512 441 2444",
    "sg:postcode":"78704",
    "sg:province":"TX",
    "sg:website":"www.continentalclub.com/Austin.html",
    "wof:name":"Continental Gallery",
    "wof:placetype":"venue"
},
  "geometry": {"coordinates":[-97.749093,30.250423],"type":"Point"}
}