{
  "type": "Feature",
  "properties": {
    "iso:country":"US",
    "sg:address":"2069 S Garland Ave",
    "sg:city":"Garland",
    "sg:classifiers":[
        {
            "category":"Home & Garden",
            "subcategory":"Carpets & Floor Coverings",
            "type":"Retail Goods"
        }
    ],
    "sg:phone":"+1 972 271 3018",
    "sg:postcode":"75041",
    "sg:province":"TX",
    "sg:tags":[
        "rug",
        "carpeting"
    ],
    "wof:name":"Tim's Carpets",
    "wof:placetype":"venue"
},
  "geometry": {"coordinates":[-96.64969600000001,32.893398],"type":"Point"}
}