{
  "type": "Feature",
  "properties": {
    "iso:country":"US",
    "sg:address":"990 Apple Ln",
    "sg:city":"Midlothian",
    "sg:classifiers":[
        {
            "category":"Professional",
            "type":"Services"
        }
    ],
    "sg:phone":"+1 972 775 8760",
    "sg:postcode":"76065",
    "sg:province":"TX",
    "wof:name":"Texas Lamp Co",
    "wof:placetype":"venue"
},
  "geometry": {"coordinates":[-97.00318300000001,32.439988],"type":"Point"}
}