{
  "type": "Feature",
  "properties": {
    "iso:country":"US",
    "sg:address":"304 Main St",
    "sg:city":"Holliday",
    "sg:classifiers":[
        {
            "category":"Wholesale",
            "subcategory":"Durable Goods & Equipment",
            "type":"Manufacturing & Wholesale Goods"
        }
    ],
    "sg:phone":"+1 940 583 4080",
    "sg:postcode":"76366",
    "sg:province":"TX",
    "wof:name":"Power Supply Of Texas",
    "wof:placetype":"venue"
},
  "geometry": {"coordinates":[-98.693117,33.811972],"type":"Point"}
}