{
  "type": "Feature",
  "properties": {
    "iso:country":"US",
    "sg:address":"310 E Houston Ave",
    "sg:city":"Crockett",
    "sg:classifiers":[
        {
            "category":"Banks & Credit Unions",
            "subcategory":"Bank",
            "type":"Services"
        }
    ],
    "sg:phone":"+1 936 544 8989",
    "sg:postcode":"75835",
    "sg:province":"TX",
    "sg:tags":[
        "mortgage"
    ],
    "wof:name":"Homestead Mortgage",
    "wof:placetype":"venue"
},
  "geometry": {"coordinates":[-95.458636,31.318447],"type":"Point"}
}