{
  "type": "Feature",
  "properties": {
    "iso:country":"US",
    "sg:address":"955 Co Rd 342",
    "sg:city":"Hondo",
    "sg:classifiers":[
        {
            "category":"Retail",
            "subcategory":"Repair Shop",
            "type":"Services"
        }
    ],
    "sg:phone":"+1 830 426 4264",
    "sg:postcode":"78861",
    "sg:province":"TX",
    "wof:name":"Performance Horseshoeing",
    "wof:placetype":"venue"
},
  "geometry": {"coordinates":[-99.099718,29.434209],"type":"Point"}
}