{
  "type": "Feature",
  "properties": {
    "iso:country":"US",
    "sg:address":"2005 Center St",
    "sg:city":"Deer Park",
    "sg:classifiers":[
        {
            "category":"Personal",
            "subcategory":"Beauty Salon",
            "type":"Services"
        }
    ],
    "sg:phone":"+1 281 930 1974",
    "sg:postcode":"77536",
    "sg:province":"TX",
    "sg:tags":[
        "shop",
        "manicuring"
    ],
    "wof:name":"Donna's Nail Boutique",
    "wof:placetype":"venue"
},
  "geometry": {"coordinates":[-95.12354999999999,29.693357],"type":"Point"}
}