{
  "type": "Feature",
  "properties": {
    "iso:country":"US",
    "sg:address":"209 Airport Dr",
    "sg:city":"Tyler",
    "sg:classifiers":[
        {
            "category":"Manufacturing",
            "subcategory":"Aerospace",
            "type":"Manufacturing & Wholesale Goods"
        },
        {
            "category":"Autos & Motor Vehicles",
            "subcategory":"Recreational Vehicle Sales",
            "type":"Retail Goods"
        }
    ],
    "sg:phone":"+1 903 595 4222",
    "sg:postcode":"75704",
    "sg:province":"TX",
    "sg:tags":[
        "equipment",
        "aircraft",
        "part",
        "supplies-wholesale",
        "manufacturer"
    ],
    "wof:name":"Wilke & Associates",
    "wof:placetype":"venue"
},
  "geometry": {"coordinates":[-95.398819,32.359222],"type":"Point"}
}