{
  "type": "Feature",
  "properties": {
    "iso:country":"US",
    "sg:address":"5605 Versailles Ct",
    "sg:city":"Colleyville",
    "sg:classifiers":[
        {
            "category":"Professional",
            "subcategory":"Management & Consulting",
            "type":"Services"
        }
    ],
    "sg:phone":"+1 817 355 0911",
    "sg:postcode":"76034",
    "sg:province":"TX",
    "sg:tags":[
        "public",
        "relations"
    ],
    "wof:name":"Gw Sports Promotions Inc",
    "wof:placetype":"venue"
},
  "geometry": {"coordinates":[-97.136674,32.890904],"type":"Point"}
}