{
  "type": "Feature",
  "properties": {
    "iso:country":"US",
    "sg:address":"102 S William St",
    "sg:city":"Victoria",
    "sg:classifiers":[
        {
            "category":"Retail",
            "subcategory":"Car Wash",
            "type":"Services"
        },
        {
            "category":"Manufacturing",
            "subcategory":"Chemicals & Compounds",
            "type":"Manufacturing & Wholesale Goods"
        }
    ],
    "sg:phone":"+1 361 575 7508",
    "sg:postcode":"77901",
    "sg:province":"TX",
    "sg:tags":[
        "carwash",
        "specialty"
    ],
    "wof:name":"L A Detailing",
    "wof:placetype":"venue"
},
  "geometry": {"coordinates":[-97.004384,28.797638],"type":"Point"}
}