{
  "type": "Feature",
  "properties": {
    "iso:country":"US",
    "sg:address":"701 College St",
    "sg:city":"Crandall",
    "sg:classifiers":[
        {
            "category":"Professional",
            "subcategory":"Art Services",
            "type":"Services"
        }
    ],
    "sg:phone":"+1 972 427 8862",
    "sg:postcode":"75114",
    "sg:province":"TX",
    "sg:tags":[
        "designer",
        "display",
        "producer"
    ],
    "wof:name":"Art Jw Design",
    "wof:placetype":"venue"
},
  "geometry": {"coordinates":[-96.450478,32.62355],"type":"Point"}
}