{
  "type": "Feature",
  "properties": {
    "iso:country":"US",
    "sg:address":"6911 Clearglen Dr",
    "sg:city":"Dallas",
    "sg:classifiers":[
        {
            "category":"Manufacturing",
            "subcategory":"Printing",
            "type":"Manufacturing & Wholesale Goods"
        }
    ],
    "sg:phone":"+1 214 371 9867",
    "sg:postcode":"75232",
    "sg:province":"TX",
    "sg:tags":[
        "publishing"
    ],
    "wof:name":"Ksm Publishing Co",
    "wof:placetype":"venue"
},
  "geometry": {"coordinates":[-96.837367,32.662968],"type":"Point"}
}