{
  "type": "Feature",
  "properties": {
    "iso:country":"US",
    "sg:address":"600 South Bell Blvd. #15",
    "sg:city":"Cedar Park",
    "sg:classifiers":[
        {
            "category":"Home & Garden",
            "subcategory":"Household Appliances",
            "type":"Retail Goods"
        }
    ],
    "sg:phone":"+1 512 331 7711",
    "sg:postcode":"78613",
    "sg:province":"TX",
    "sg:tags":[
        "repair"
    ],
    "sg:website":"BarronsVacuumCenter.com",
    "wof:name":"Barron's Vacuum Center",
    "wof:placetype":"venue"
},
  "geometry": {"coordinates":[-97.818854,30.504023],"type":"Point"}
}