{
  "type": "Feature",
  "properties": {
    "iso:country":"US",
    "sg:address":"3612 Rolling Oaks Dr",
    "sg:city":"Flower Mound",
    "sg:classifiers":[
        {
            "category":"Professional",
            "subcategory":"Detective & Security Services",
            "type":"Services"
        }
    ],
    "sg:phone":"+1 972 874 0214",
    "sg:postcode":"75022",
    "sg:province":"TX",
    "sg:tags":[
        "system"
    ],
    "wof:name":"Durable Networks",
    "wof:placetype":"venue"
},
  "geometry": {"coordinates":[-97.085931,33.03199],"type":"Point"}
}