{
  "type": "Feature",
  "properties": {
    "iso:country":"US",
    "sg:address":"16475 Dallas Pkwy",
    "sg:city":"Addison",
    "sg:classifiers":[
        {
            "category":"Professional",
            "subcategory":"Lawyer & Legal Services",
            "type":"Services"
        }
    ],
    "sg:phone":"+1 972 349 2284",
    "sg:postcode":"75001",
    "sg:province":"TX",
    "wof:name":"Tobin Jennifer C atty",
    "wof:placetype":"venue"
},
  "geometry": {"coordinates":[-96.825271,32.976335],"type":"Point"}
}