{
  "type": "Feature",
  "properties": {
    "iso:country":"US",
    "sg:address":"1902 S Congress Ave",
    "sg:city":"Austin",
    "sg:classifiers":[
        {
            "category":"Personal",
            "subcategory":"Massage",
            "type":"Services"
        }
    ],
    "sg:phone":"+1 512 809 6708",
    "sg:postcode":"78704",
    "sg:province":"TX",
    "sg:website":"www.tigerlilystudios.com",
    "wof:name":"Shane Epperly & Susan Epperly, LMT",
    "wof:placetype":"venue"
},
  "geometry": {"coordinates":[-97.75182,30.244994],"type":"Point"}
}