{
  "type": "Feature",
  "properties": {
    "iso:country":"US",
    "sg:address":"5101 80th St",
    "sg:city":"Lubbock",
    "sg:classifiers":[
        {
            "category":"Real Estate",
            "subcategory":"Real Estate Agent",
            "type":"Services"
        }
    ],
    "sg:phone":"+1 806 698 8282",
    "sg:postcode":"79424",
    "sg:province":"TX",
    "sg:tags":[
        "appraiser"
    ],
    "wof:name":"Chris Raney Appraisal Svc",
    "wof:placetype":"venue"
},
  "geometry": {"coordinates":[-101.919479,33.521243],"type":"Point"}
}