{
  "type": "Feature",
  "properties": {
    "iso:country":"US",
    "sg:address":"19031 Appletree Hill Ln",
    "sg:city":"Houston",
    "sg:classifiers":[
        {
            "category":"Building & Trades",
            "subcategory":"Landscaping Services",
            "type":"Services"
        }
    ],
    "sg:phone":"+1 281 300 1126",
    "sg:postcode":"77084",
    "sg:province":"TX",
    "sg:tags":[
        "landscape"
    ],
    "wof:name":"Boston Fern Landscape & Irriga",
    "wof:placetype":"venue"
},
  "geometry": {"coordinates":[-95.70201,29.819837],"type":"Point"}
}