{
  "type": "Feature",
  "properties": {
    "iso:country":"US",
    "sg:address":"8630 Easton Commons Dr # 1202",
    "sg:city":"Houston",
    "sg:classifiers":[
        {
            "category":"Shopping",
            "subcategory":"Crafts & Fabrics",
            "type":"Retail Goods"
        }
    ],
    "sg:phone":"+1 281 858 0352",
    "sg:postcode":"77095",
    "sg:province":"TX",
    "sg:tags":[
        "art",
        "supply"
    ],
    "wof:name":"Angry Hippo Productions",
    "wof:placetype":"venue"
},
  "geometry": {"coordinates":[-95.629833,29.904122],"type":"Point"}
}