{
  "type": "Feature",
  "properties": {
    "iso:country":"US",
    "sg:address":"7620 Bellaire Blvd",
    "sg:city":"Houston",
    "sg:classifiers":[
        {
            "category":"Autos & Motor Vehicles",
            "subcategory":"Automobile Sales",
            "type":"Retail Goods"
        }
    ],
    "sg:phone":"+1 713 981 0880",
    "sg:postcode":"77036",
    "sg:province":"TX",
    "wof:name":"Matrix Motorcar",
    "wof:placetype":"venue"
},
  "geometry": {"coordinates":[-95.51910700000001,29.705256],"type":"Point"}
}