{
  "type": "Feature",
  "properties": {
    "iso:country":"US",
    "sg:address":"1302 Green St",
    "sg:city":"Quanah",
    "sg:classifiers":[
        {
            "category":"Professional",
            "type":"Services"
        }
    ],
    "sg:phone":"+1 940 663 2897",
    "sg:postcode":"79252",
    "sg:province":"TX",
    "wof:name":"Jimmy Oneal",
    "wof:placetype":"venue"
},
  "geometry": {"coordinates":[-99.744576,34.288073],"type":"Point"}
}