{
  "type": "Feature",
  "properties": {
    "iso:country":"US",
    "sg:address":"1238 Belt Line Rd Ste 310",
    "sg:city":"Garland",
    "sg:classifiers":[
        {
            "category":"Restaurant",
            "type":"Food & Drink"
        }
    ],
    "sg:phone":"+1 972 414 0177",
    "sg:postcode":"75040",
    "sg:province":"TX",
    "sg:tags":[
        "italian",
        "pizza"
    ],
    "wof:name":"Sali's Pizza & Pasta",
    "wof:placetype":"venue"
},
  "geometry": {"coordinates":[-96.645599,32.944599],"type":"Point"}
}