{
  "type": "Feature",
  "properties": {
    "iso:country":"US",
    "sg:address":"1601 Olympus Dr",
    "sg:city":"Austin",
    "sg:classifiers":[
        {
            "category":"Professional",
            "subcategory":"Business Services",
            "type":"Services"
        }
    ],
    "sg:phone":"+1 512 263 1208",
    "sg:postcode":"78733",
    "sg:province":"TX",
    "wof:name":"Baron Ray Enterprises Inc",
    "wof:placetype":"venue"
},
  "geometry": {"coordinates":[-97.859799,30.338681],"type":"Point"}
}