{
  "type": "Feature",
  "properties": {
    "iso:country":"US",
    "sg:address":"14951 FM 2586",
    "sg:city":"Dalhart",
    "sg:classifiers":[
        {
            "category":"Farming",
            "subcategory":"Farm",
            "type":"Manufacturing & Wholesale Goods"
        }
    ],
    "sg:phone":"+1 806 362 4580",
    "sg:postcode":"79022",
    "sg:province":"TX",
    "wof:name":"Jay Howard Farms",
    "wof:placetype":"venue"
},
  "geometry": {"coordinates":[-102.890997,36.4628],"type":"Point"}
}