{
  "type": "Feature",
  "properties": {
    "iso:country":"US",
    "sg:address":"617 Beaumont Ave",
    "sg:city":"Mcallen",
    "sg:classifiers":[
        {
            "category":"Wholesale",
            "subcategory":"Electrical",
            "type":"Manufacturing & Wholesale Goods"
        }
    ],
    "sg:phone":"+1 956 686 9502",
    "sg:postcode":"78501",
    "sg:province":"TX",
    "sg:tags":[
        "electric",
        "motor"
    ],
    "wof:name":"Mc Allen Armature Works",
    "wof:placetype":"venue"
},
  "geometry": {"coordinates":[-98.22801200000001,26.201656],"type":"Point"}
}