{
  "type": "Feature",
  "properties": {
    "iso:country":"US",
    "sg:address":"5 N Cedar Lawn Dr",
    "sg:city":"Galveston",
    "sg:classifiers":[
        {
            "category":"Organizations",
            "subcategory":"Community Association",
            "type":"Services"
        }
    ],
    "sg:phone":"+1 409 763 4083",
    "sg:postcode":"77551",
    "sg:province":"TX",
    "wof:name":"Cedar Lawn Association Inc",
    "wof:placetype":"venue"
},
  "geometry": {"coordinates":[-94.817133,29.291473],"type":"Point"}
}