{
  "type": "Feature",
  "properties": {
    "iso:country":"US",
    "sg:address":"4905 Neptune St",
    "sg:city":"Corpus Christi",
    "sg:classifiers":[
        {
            "category":"Taxi",
            "type":"Transportation"
        }
    ],
    "sg:phone":"+1 361 299 9999",
    "sg:postcode":"78405",
    "sg:province":"TX",
    "sg:tags":[
        "taxicab"
    ],
    "wof:name":"Green N Go Cab Co",
    "wof:placetype":"venue"
},
  "geometry": {"coordinates":[-97.451386,27.781026],"type":"Point"}
}