{
  "type": "Feature",
  "properties": {
    "iso:country":"US",
    "sg:address":"3120 Rogerdale Rd",
    "sg:city":"Houston",
    "sg:classifiers":[
        {
            "category":"Real Estate",
            "subcategory":"Real Estate Agent",
            "type":"Services"
        }
    ],
    "sg:phone":"+1 713 532 0977",
    "sg:postcode":"77042",
    "sg:province":"TX",
    "wof:name":"Gulf Coast Commercial Group",
    "wof:placetype":"venue"
},
  "geometry": {"coordinates":[-95.55977300000001,29.728548],"type":"Point"}
}