{
  "type": "Feature",
  "properties": {
    "iso:country":"US",
    "sg:address":"2700 E Lancaster Ave",
    "sg:city":"Fort Worth",
    "sg:classifiers":[
        {
            "category":"Restaurant",
            "type":"Food & Drink"
        }
    ],
    "sg:phone":"+1 817 534 2512",
    "sg:postcode":"76103",
    "sg:province":"TX",
    "wof:name":"Mexican Inn Cafes",
    "wof:placetype":"venue"
},
  "geometry": {"coordinates":[-97.285854,32.742024],"type":"Point"}
}