{
  "type": "Feature",
  "properties": {
    "iso:country":"US",
    "sg:address":"104 Interurban Rd",
    "sg:city":"Ennis",
    "sg:classifiers":[
        {
            "category":"Government",
            "subcategory":"Fire Station",
            "type":"Public Place"
        }
    ],
    "sg:phone":"+1 972 875 6832",
    "sg:postcode":"75119",
    "sg:province":"TX",
    "sg:tags":[
        "department"
    ],
    "wof:name":"Alma Fire House",
    "wof:placetype":"venue"
},
  "geometry": {"coordinates":[-96.546092,32.284827],"type":"Point"}
}