{
  "type": "Feature",
  "properties": {
    "iso:country":"US",
    "sg:address":"212 Dinn Dr",
    "sg:city":"San Antonio",
    "sg:classifiers":[
        {
            "category":"Manufacturing",
            "subcategory":"Tools & Machinery",
            "type":"Manufacturing & Wholesale Goods"
        }
    ],
    "sg:phone":"+1 210 653 9599",
    "sg:postcode":"78218",
    "sg:province":"TX",
    "sg:tags":[
        "industrial",
        "mfg"
    ],
    "wof:name":"Taber Machine & Welding",
    "wof:placetype":"venue"
},
  "geometry": {"coordinates":[-98.396428,29.491989],"type":"Point"}
}