{
  "type": "Feature",
  "properties": {
    "iso:country":"US",
    "sg:address":"330 E 4th St",
    "sg:city":"Fort Worth",
    "sg:classifiers":[
        {
            "category":"Museum",
            "type":"Entertainment"
        }
    ],
    "sg:phone":"+1 817 665 6500",
    "sg:postcode":"76102",
    "sg:province":"TX",
    "sg:tags":[
        "organization",
        "arts",
        "information"
    ],
    "sg:website":"www.fwsymphony.org",
    "wof:name":"Fort Worth Symphony Associatio",
    "wof:placetype":"venue"
},
  "geometry": {"coordinates":[-97.32902900000001,32.755505],"type":"Point"}
}