{
  "type": "Feature",
  "properties": {
    "iso:country":"US",
    "sg:address":"1930 Garner Field Rd",
    "sg:city":"Uvalde",
    "sg:classifiers":[
        {
            "category":"Real Estate",
            "subcategory":"Real Estate Services",
            "type":"Services"
        },
        {
            "category":"Real Estate",
            "subcategory":"Real Estate Operator",
            "type":"Services"
        }
    ],
    "sg:phone":"+1 830 278 8106",
    "sg:postcode":"78801",
    "sg:province":"TX",
    "sg:tags":[
        "vacancy",
        "apartment",
        "rental",
        "listing"
    ],
    "wof:name":"Nopal Place Apartments",
    "wof:placetype":"venue"
},
  "geometry": {"coordinates":[-99.75318,29.218315],"type":"Point"}
}