{
  "type": "Feature",
  "properties": {
    "iso:country":"US",
    "sg:address":"4212 Gnarl Dr",
    "sg:city":"Austin",
    "sg:classifiers":[
        {
            "category":"Professional",
            "subcategory":"Management & Consulting",
            "type":"Services"
        }
    ],
    "sg:phone":"+1 512 453 0075",
    "sg:postcode":"78731",
    "sg:province":"TX",
    "sg:tags":[
        "consultant",
        "business"
    ],
    "wof:name":"C & H Business Mgmt Svc",
    "wof:placetype":"venue"
},
  "geometry": {"coordinates":[-97.76925,30.364575],"type":"Point"}
}