{
  "type": "Feature",
  "properties": {
    "iso:country":"US",
    "sg:address":"8069 Old Austin Rd",
    "sg:city":"Schertz",
    "sg:classifiers":[
        {
            "category":"Utilities",
            "subcategory":"Telephone",
            "type":"Services"
        }
    ],
    "sg:phone":"+1 210 651 5977",
    "sg:postcode":"78154",
    "sg:province":"TX",
    "sg:tags":[
        "communications"
    ],
    "wof:name":"A1 Bizcom Inc",
    "wof:placetype":"venue"
},
  "geometry": {"coordinates":[-98.329801,29.574089],"type":"Point"}
}