{
  "type": "Feature",
  "properties": {
    "iso:country":"US",
    "sg:address":"808 Twin Creek",
    "sg:city":"Mansfield",
    "sg:classifiers":[
        {
            "category":"Communications",
            "subcategory":"Film & Video Production",
            "type":"Services"
        }
    ],
    "sg:phone":"+1 817 477 5034",
    "sg:postcode":"76063",
    "sg:province":"TX",
    "sg:tags":[
        "motion"
    ],
    "wof:name":"Pro Tree Productions",
    "wof:placetype":"venue"
},
  "geometry": {"coordinates":[-97.13590000000001,32.593574],"type":"Point"}
}