{
  "type": "Feature",
  "properties": {
    "iso:country":"US",
    "sg:address":"1004 Morningside Dr",
    "sg:city":"San Antonio",
    "sg:classifiers":[
        {
            "category":"Professional",
            "subcategory":"Management & Consulting",
            "type":"Services"
        }
    ],
    "sg:phone":"+1 210 930 4663",
    "sg:postcode":"78209",
    "sg:province":"TX",
    "wof:name":"Atomic Marketing",
    "wof:placetype":"venue"
},
  "geometry": {"coordinates":[-98.431095,29.483312],"type":"Point"}
}