{
  "type": "Feature",
  "properties": {
    "iso:country":"US",
    "sg:address":"500 E Palestine St",
    "sg:city":"Hutchins",
    "sg:classifiers":[
        {
            "category":"Education",
            "subcategory":"School",
            "type":"Public Place"
        }
    ],
    "sg:phone":"+1 972 225 2351",
    "sg:postcode":"75141",
    "sg:province":"TX",
    "wof:name":"Hutchins Elementary School",
    "wof:placetype":"venue"
},
  "geometry": {"coordinates":[-96.70828299999999,32.648787],"type":"Point"}
}