{
  "type": "Feature",
  "properties": {
    "iso:country":"US",
    "sg:address":"8900 Bissonnet St",
    "sg:city":"Houston",
    "sg:classifiers":[
        {
            "category":"Retail",
            "subcategory":"Auto Repair",
            "type":"Services"
        }
    ],
    "sg:phone":"+1 713 995 5398",
    "sg:postcode":"77074",
    "sg:province":"TX",
    "sg:tags":[
        "transmission"
    ],
    "wof:name":"L Alvarez United Transmissions",
    "wof:placetype":"venue"
},
  "geometry": {"coordinates":[-95.532912,29.67633],"type":"Point"}
}