{
  "type": "Feature",
  "properties": {
    "iso:country":"US",
    "sg:address":"2600 NE 6th Ave",
    "sg:city":"Amarillo",
    "sg:classifiers":[
        {
            "category":"Retail",
            "subcategory":"Auto Repair",
            "type":"Services"
        }
    ],
    "sg:phone":"+1 806 318 3078",
    "sg:postcode":"79107",
    "sg:province":"TX",
    "sg:tags":[
        "body",
        "automobile",
        "painting",
        "repairing"
    ],
    "wof:name":"Tony's Body Shop",
    "wof:placetype":"venue"
},
  "geometry": {"coordinates":[-101.80551199999999,35.216405],"type":"Point"}
}