{
  "type": "Feature",
  "properties": {
    "iso:country":"US",
    "sg:address":"728 Water Oak Dr",
    "sg:city":"Plano",
    "sg:classifiers":[
        {
            "category":"Professional",
            "subcategory":"Business Services",
            "type":"Services"
        }
    ],
    "sg:phone":"+1 972 517 3557",
    "sg:postcode":"75025",
    "sg:province":"TX",
    "wof:name":"Chintz & Ivy",
    "wof:placetype":"venue"
},
  "geometry": {"coordinates":[-96.700065,33.075404],"type":"Point"}
}