{
  "type": "Feature",
  "properties": {
    "iso:country":"US",
    "sg:address":"504 Joliet St",
    "sg:city":"Plainview",
    "sg:classifiers":[
        {
            "category":"Social Services",
            "type":"Services"
        }
    ],
    "sg:phone":"+1 806 293 8008",
    "sg:postcode":"79072",
    "sg:province":"TX",
    "wof:name":"Faith In Sharing House",
    "wof:placetype":"venue"
},
  "geometry": {"coordinates":[-101.715538,34.185531],"type":"Point"}
}