{
  "type": "Feature",
  "properties": {
    "iso:country":"US",
    "sg:address":"8464 Southland Dr",
    "sg:city":"Tyler",
    "sg:classifiers":[
        {
            "category":"Wholesale",
            "subcategory":"Machinery & Supplies",
            "type":"Manufacturing & Wholesale Goods"
        }
    ],
    "sg:phone":"+1 903 581 1620",
    "sg:postcode":"75703",
    "sg:province":"TX",
    "sg:tags":[
        "paint",
        "finishing",
        "equipment"
    ],
    "wof:name":"Ramco Finishing Systems",
    "wof:placetype":"venue"
},
  "geometry": {"coordinates":[-95.30170200000001,32.263366],"type":"Point"}
}