{
  "type": "Feature",
  "properties": {
    "iso:country":"US",
    "sg:address":"12873 Grand River Dr",
    "sg:city":"El Paso",
    "sg:classifiers":[
        {
            "category":"Building & Trades",
            "subcategory":"Construction",
            "type":"Services"
        }
    ],
    "sg:phone":"+1 915 852 0887",
    "sg:postcode":"79928",
    "sg:province":"TX",
    "sg:tags":[
        "sandblasting"
    ],
    "wof:name":"C & Sons Sandblasting Painting",
    "wof:placetype":"venue"
},
  "geometry": {"coordinates":[-106.24193699999999,31.671501],"type":"Point"}
}