{
  "type": "Feature",
  "properties": {
    "iso:country":"US",
    "sg:address":"375 US Hwy 77",
    "sg:city":"San Benito",
    "sg:classifiers":[
        {
            "category":"Retail",
            "subcategory":"Auto Repair",
            "type":"Services"
        }
    ],
    "sg:phone":"+1 956 399 7747",
    "sg:postcode":"78586",
    "sg:province":"TX",
    "sg:tags":[
        "repairing",
        "automobile"
    ],
    "wof:name":"Elisio Muniz",
    "wof:placetype":"venue"
},
  "geometry": {"coordinates":[-97.638497,26.127833],"type":"Point"}
}