{
  "type": "Feature",
  "properties": {
    "iso:country":"US",
    "sg:address":"3906 Oak Dale Dr",
    "sg:city":"Pearland",
    "sg:classifiers":[
        {
            "category":"Professional",
            "subcategory":"Accounting & Tax Preparation",
            "type":"Services"
        }
    ],
    "sg:phone":"+1 281 482 4421",
    "sg:postcode":"77581",
    "sg:province":"TX",
    "sg:tags":[
        "return"
    ],
    "wof:name":"D L Miller",
    "wof:placetype":"venue"
},
  "geometry": {"coordinates":[-95.247637,29.538021],"type":"Point"}
}