{
  "type": "Feature",
  "properties": {
    "iso:country":"US",
    "sg:address":"5135 W Alabama St",
    "sg:city":"Houston",
    "sg:classifiers":[
        {
            "category":"Wholesale",
            "subcategory":"Stationery",
            "type":"Manufacturing & Wholesale Goods"
        }
    ],
    "sg:phone":"+1 713 621 7442",
    "sg:postcode":"77056",
    "sg:province":"TX",
    "sg:tags":[
        "card"
    ],
    "wof:name":"American Greetings",
    "wof:placetype":"venue"
},
  "geometry": {"coordinates":[-95.464699,29.738001],"type":"Point"}
}