{
  "type": "Feature",
  "properties": {
    "iso:country":"US",
    "sg:address":"19306 Highway 59 N",
    "sg:city":"Humble",
    "sg:classifiers":[
        {
            "category":"Communications",
            "type":"Services"
        }
    ],
    "sg:phone":"+1 281 540 2262",
    "sg:postcode":"77338",
    "sg:province":"TX",
    "sg:tags":[
        "consultant",
        "telecommunication"
    ],
    "wof:name":"Net Star Telecommunications Inc",
    "wof:placetype":"venue"
},
  "geometry": {"coordinates":[-95.270478,29.997792],"type":"Point"}
}