{
  "type": "Feature",
  "properties": {
    "iso:country":"US",
    "sg:address":"822 S Fordham St",
    "sg:city":"Perryton",
    "sg:classifiers":[
        {
            "category":"Professional",
            "subcategory":"Accounting & Tax Preparation",
            "type":"Services"
        }
    ],
    "sg:phone":"+1 806 435 5162",
    "sg:postcode":"79070",
    "sg:province":"TX",
    "sg:tags":[
        "return"
    ],
    "wof:name":"Bond Financial Services",
    "wof:placetype":"venue"
},
  "geometry": {"coordinates":[-100.810514,36.391998],"type":"Point"}
}