{
  "type": "Feature",
  "properties": {
    "iso:country":"US",
    "sg:address":"1910 Oak Bluff Dr",
    "sg:city":"Carrollton",
    "sg:classifiers":[
        {
            "category":"Building & Trades",
            "subcategory":"Plumbing",
            "type":"Services"
        }
    ],
    "sg:phone":"+1 972 394 1413",
    "sg:postcode":"75007",
    "sg:province":"TX",
    "sg:tags":[
        "air",
        "heating",
        "conditioning",
        "contractor"
    ],
    "wof:name":"Settle Air Inc",
    "wof:placetype":"venue"
},
  "geometry": {"coordinates":[-96.883544,33.020372],"type":"Point"}
}