{
  "type": "Feature",
  "properties": {
    "iso:country":"US",
    "sg:address":"6320 Spring Branch Rd",
    "sg:city":"Montgomery",
    "sg:classifiers":[
        {
            "category":"Building & Trades",
            "subcategory":"Electrical",
            "type":"Services"
        }
    ],
    "sg:phone":"+1 936 449 4610",
    "sg:postcode":"77316",
    "sg:province":"TX",
    "sg:tags":[
        "electric",
        "contractor"
    ],
    "wof:name":"H 3 Electrical Svc",
    "wof:placetype":"venue"
},
  "geometry": {"coordinates":[-95.713657,30.327838],"type":"Point"}
}