{
  "type": "Feature",
  "properties": {
    "iso:country":"US",
    "sg:address":"1803 N Galloway Ave",
    "sg:city":"Mesquite",
    "sg:classifiers":[
        {
            "category":"Food & Beverages",
            "subcategory":"Groceries & Convenience Stores",
            "type":"Retail Goods"
        }
    ],
    "sg:phone":"+1 972 285 8293",
    "sg:postcode":"75149",
    "sg:province":"TX",
    "wof:name":"7-Eleven Stores",
    "wof:placetype":"venue"
},
  "geometry": {"coordinates":[-96.606903,32.7873],"type":"Point"}
}