{
  "type": "Feature",
  "properties": {
    "iso:country":"US",
    "sg:address":"1420 W Irving Blvd # 104",
    "sg:city":"Irving",
    "sg:classifiers":[
        {
            "category":"Wholesale",
            "subcategory":"Electrical",
            "type":"Manufacturing & Wholesale Goods"
        }
    ],
    "sg:phone":"+1 972 986 1806",
    "sg:postcode":"75061",
    "sg:province":"TX",
    "sg:tags":[
        "systems-wholesale",
        "communication",
        "manufacturer",
        "radio",
        "equipment"
    ],
    "wof:name":"Leisure Lectronics",
    "wof:placetype":"venue"
},
  "geometry": {"coordinates":[-96.963607,32.817752],"type":"Point"}
}