{
  "type": "Feature",
  "properties": {
    "iso:country":"US",
    "sg:address":"1326 N Palace Ave",
    "sg:city":"Tyler",
    "sg:classifiers":[
        {
            "category":"Organizations",
            "subcategory":"Religious Organization",
            "type":"Services"
        }
    ],
    "sg:phone":"+1 903 592 5649",
    "sg:postcode":"75702",
    "sg:province":"TX",
    "sg:tags":[
        "church"
    ],
    "wof:name":"Church Of The Living God",
    "wof:placetype":"venue"
},
  "geometry": {"coordinates":[-95.310247,32.364524],"type":"Point"}
}