{
  "type": "Feature",
  "properties": {
    "iso:country":"US",
    "sg:address":"3331 Bandell Dr",
    "sg:city":"Houston",
    "sg:classifiers":[
        {
            "category":"Building & Trades",
            "subcategory":"Cleaning & Sanitation",
            "type":"Services"
        }
    ],
    "sg:phone":"+1 713 413 1446",
    "sg:postcode":"77045",
    "sg:province":"TX",
    "sg:tags":[
        "maintenance"
    ],
    "wof:name":"Metro Area Cleaning Service",
    "wof:placetype":"venue"
},
  "geometry": {"coordinates":[-95.42639,29.641828],"type":"Point"}
}