{
  "type": "Feature",
  "properties": {
    "iso:country":"US",
    "sg:address":"1612 Hawkins Ct",
    "sg:city":"Carrollton",
    "sg:classifiers":[
        {
            "category":"Shopping",
            "type":"Retail Goods"
        },
        {
            "category":"Shopping",
            "subcategory":"Beauty & Cosmetics",
            "type":"Retail Goods"
        }
    ],
    "sg:phone":"+1 972 395 7772",
    "sg:postcode":"75010",
    "sg:province":"TX",
    "sg:tags":[
        "merchandise",
        "perfume"
    ],
    "wof:name":"Monica Herrera",
    "wof:placetype":"venue"
},
  "geometry": {"coordinates":[-96.935446,33.02641],"type":"Point"}
}