{
  "type": "Feature",
  "properties": {
    "iso:country":"US",
    "sg:address":"1111 W Park Ave",
    "sg:city":"Orange",
    "sg:classifiers":[
        {
            "category":"Retail",
            "subcategory":"Repair Shop",
            "type":"Services"
        }
    ],
    "sg:phone":"+1 409 883 2455",
    "sg:postcode":"77630",
    "sg:province":"TX",
    "sg:tags":[
        "upholsterer"
    ],
    "wof:name":"Barnett's Upholstery",
    "wof:placetype":"venue"
},
  "geometry": {"coordinates":[-93.74145900000001,30.099217],"type":"Point"}
}