{
  "type": "Feature",
  "properties": {
    "iso:country":"US",
    "sg:address":"7577 Neely Dr",
    "sg:city":"Lumberton",
    "sg:classifiers":[
        {
            "category":"Retail",
            "subcategory":"Auto Repair",
            "type":"Services"
        }
    ],
    "sg:phone":"+1 409 755 6756",
    "sg:postcode":"77657",
    "sg:province":"TX",
    "sg:tags":[
        "repairing",
        "transmission",
        "general",
        "automobile"
    ],
    "wof:name":"Ronnie's Garage",
    "wof:placetype":"venue"
},
  "geometry": {"coordinates":[-94.19908599999999,30.226713],"type":"Point"}
}