{
  "type": "Feature",
  "properties": {
    "iso:country":"US",
    "sg:address":"10853 Forest Dr",
    "sg:city":"College Station",
    "sg:classifiers":[
        {
            "category":"Professional",
            "subcategory":"Management & Consulting",
            "type":"Services"
        }
    ],
    "sg:phone":"+1 979 774 9095",
    "sg:postcode":"77845",
    "sg:province":"TX",
    "sg:tags":[
        "agricultural",
        "consultant"
    ],
    "wof:name":"Agri Service Intl",
    "wof:placetype":"venue"
},
  "geometry": {"coordinates":[-96.230745,30.672219],"type":"Point"}
}