{
  "type": "Feature",
  "properties": {
    "iso:country":"US",
    "sg:address":"3701 S Cooper St",
    "sg:city":"Arlington",
    "sg:classifiers":[
        {
            "category":"Shopping",
            "type":"Retail Goods"
        }
    ],
    "sg:phone":"+1 817 417 6964",
    "sg:postcode":"76015",
    "sg:province":"TX",
    "sg:tags":[
        "candle"
    ],
    "wof:name":"Salon M",
    "wof:placetype":"venue"
},
  "geometry": {"coordinates":[-97.13245000000001,32.684388],"type":"Point"}
}