{
  "type": "Feature",
  "properties": {
    "iso:country":"US",
    "sg:address":"1439 Elkwood Dr",
    "sg:city":"Missouri City",
    "sg:classifiers":[
        {
            "category":"Wholesale",
            "subcategory":"Non-durable Goods",
            "type":"Manufacturing & Wholesale Goods"
        }
    ],
    "sg:phone":"+1 281 208 0398",
    "sg:postcode":"77489",
    "sg:province":"TX",
    "wof:name":"Pan American Export",
    "wof:placetype":"venue"
},
  "geometry": {"coordinates":[-95.52433000000001,29.608512],"type":"Point"}
}