{
  "type": "Feature",
  "properties": {
    "iso:country":"US",
    "sg:address":"2302 Post Office St",
    "sg:city":"Galveston",
    "sg:classifiers":[
        {
            "category":"Health Services",
            "subcategory":"Nursing And Care Facility",
            "type":"Services"
        }
    ],
    "sg:phone":"+1 409 763 6000",
    "sg:postcode":"77550",
    "sg:province":"TX",
    "sg:tags":[
        "home",
        "convalescent"
    ],
    "wof:name":"Regent Care Ctr",
    "wof:placetype":"venue"
},
  "geometry": {"coordinates":[-94.794645,29.304317],"type":"Point"}
}