{
  "type": "Feature",
  "properties": {
    "iso:country":"US",
    "sg:address":"1222 Bryant St",
    "sg:city":"Benbrook",
    "sg:classifiers":[
        {
            "category":"Insurance",
            "subcategory":"Insurance Agent",
            "type":"Services"
        }
    ],
    "sg:phone":"+1 817 249 0408",
    "sg:postcode":"76126",
    "sg:province":"TX",
    "wof:name":"Leeanne Inc",
    "wof:placetype":"venue"
},
  "geometry": {"coordinates":[-97.46412100000001,32.666087],"type":"Point"}
}