{
  "type": "Feature",
  "properties": {
    "iso:country":"US",
    "sg:address":"2409 Broadway St",
    "sg:city":"Lubbock",
    "sg:classifiers":[
        {
            "category":"Shopping",
            "subcategory":"Computers & Home Electronics",
            "type":"Retail Goods"
        }
    ],
    "sg:phone":"+1 806 763 6049",
    "sg:postcode":"79401",
    "sg:province":"TX",
    "sg:tags":[
        "equipment",
        "dealer"
    ],
    "wof:name":"Computer & Bus Systems Inc",
    "wof:placetype":"venue"
},
  "geometry": {"coordinates":[-101.87047699999999,33.584369],"type":"Point"}
}