{
  "type": "Feature",
  "properties": {
    "iso:country":"US",
    "sg:address":"1354 Basse Rd",
    "sg:city":"San Antonio",
    "sg:classifiers":[
        {
            "category":"Health Services",
            "subcategory":"Hospital",
            "type":"Services"
        }
    ],
    "sg:phone":"+1 210 734 6323",
    "sg:postcode":"78212",
    "sg:province":"TX",
    "sg:tags":[
        "specialty"
    ],
    "wof:name":"A R C",
    "wof:placetype":"venue"
},
  "geometry": {"coordinates":[-98.507065,29.488085],"type":"Point"}
}