{
  "type": "Feature",
  "properties": {
    "iso:country":"US",
    "sg:address":"9507 W Savile Cir",
    "sg:city":"Houston",
    "sg:classifiers":[
        {
            "category":"Personal",
            "type":"Services"
        }
    ],
    "sg:phone":"+1 281 897 9505",
    "sg:postcode":"77065",
    "sg:province":"TX",
    "wof:name":"Handee Man Plus",
    "wof:placetype":"venue"
},
  "geometry": {"coordinates":[-95.598727,29.912076],"type":"Point"}
}