{
  "type": "Feature",
  "properties": {
    "iso:country":"US",
    "sg:address":"501 Sims Dr",
    "sg:city":"Angleton",
    "sg:classifiers":[
        {
            "category":"Autos & Motor Vehicles",
            "subcategory":"Fuel & Gas Station",
            "type":"Retail Goods"
        }
    ],
    "sg:phone":"+1 979 849 0364",
    "sg:postcode":"77515",
    "sg:province":"TX",
    "sg:tags":[
        "station",
        "gasoline"
    ],
    "wof:name":"Joe Cools Service Station",
    "wof:placetype":"venue"
},
  "geometry": {"coordinates":[-95.41485400000001,29.161696],"type":"Point"}
}