{
  "type": "Feature",
  "properties": {
    "iso:country":"US",
    "sg:address":"400 E Weatherford St",
    "sg:city":"Fort Worth",
    "sg:classifiers":[
        {
            "category":"Communications",
            "subcategory":"Film & Video Production",
            "type":"Services"
        }
    ],
    "sg:phone":"+1 817 336 1133",
    "sg:postcode":"76102",
    "sg:province":"TX",
    "sg:tags":[
        "motion"
    ],
    "wof:name":"Reel Partners Inc",
    "wof:placetype":"venue"
},
  "geometry": {"coordinates":[-97.32990700000001,32.758604],"type":"Point"}
}