{
  "type": "Feature",
  "properties": {
    "iso:country":"US",
    "sg:address":"2944 E Illinois Ave",
    "sg:city":"Dallas",
    "sg:classifiers":[
        {
            "category":"Retail",
            "subcategory":"Veterinary Services",
            "type":"Services"
        }
    ],
    "sg:phone":"+1 214 371 6013",
    "sg:postcode":"75216",
    "sg:province":"TX",
    "wof:name":"D E McGruder",
    "wof:placetype":"venue"
},
  "geometry": {"coordinates":[-96.779017,32.716512],"type":"Point"}
}