{
  "type": "Feature",
  "properties": {
    "iso:country":"US",
    "sg:address":"5707 S Broadway Ave",
    "sg:city":"Tyler",
    "sg:classifiers":[
        {
            "category":"Restaurant",
            "type":"Food & Drink"
        }
    ],
    "sg:phone":"+1 903 939 0133",
    "sg:postcode":"75703",
    "sg:province":"TX",
    "wof:name":"Ming's Cafe Inc",
    "wof:placetype":"venue"
},
  "geometry": {"coordinates":[-95.30390199999999,32.287708],"type":"Point"}
}