{
  "type": "Feature",
  "properties": {
    "iso:country":"US",
    "sg:address":"1240 W Belt Line Rd",
    "sg:city":"Desoto",
    "sg:classifiers":[
        {
            "category":"Food & Beverages",
            "subcategory":"Bakery",
            "type":"Retail Goods"
        }
    ],
    "sg:phone":"+1 972 230 4250",
    "sg:postcode":"75115",
    "sg:province":"TX",
    "sg:tags":[
        "sandwich"
    ],
    "wof:name":"Subway Sandwiches",
    "wof:placetype":"venue"
},
  "geometry": {"coordinates":[-96.88945,32.589534],"type":"Point"}
}