{
  "type": "Feature",
  "properties": {
    "iso:country":"US",
    "sg:address":"1341 Gayle Ln",
    "sg:city":"Poteet",
    "sg:classifiers":[
        {
            "category":"Professional",
            "subcategory":"Management & Consulting",
            "type":"Services"
        }
    ],
    "sg:phone":"+1 830 276 4778",
    "sg:postcode":"78065",
    "sg:province":"TX",
    "sg:tags":[
        "party",
        "planning"
    ],
    "wof:name":"Bounce Across Texas",
    "wof:placetype":"venue"
},
  "geometry": {"coordinates":[-98.60945599999999,29.140846],"type":"Point"}
}