{
  "type": "Feature",
  "properties": {
    "iso:country":"US",
    "sg:address":"22 Palm Cir",
    "sg:city":"Galveston",
    "sg:classifiers":[
        {
            "category":"Professional",
            "subcategory":"Business Services",
            "type":"Services"
        }
    ],
    "sg:phone":"+1 409 765 9660",
    "sg:postcode":"77511",
    "sg:province":"TX",
    "wof:name":"Palm Cir Drv Resident Conusel",
    "wof:placetype":"venue"
},
  "geometry": {"coordinates":[-95.246105,29.411833],"type":"Point"}
}