{
  "type": "Feature",
  "properties": {
    "iso:country":"US",
    "sg:address":"20205 Fox Glen Ln",
    "sg:city":"Humble",
    "sg:classifiers":[
        {
            "category":"Personal",
            "subcategory":"Beauty Salon",
            "type":"Services"
        }
    ],
    "sg:phone":"+1 281 446 4846",
    "sg:postcode":"77338",
    "sg:province":"TX",
    "sg:tags":[
        "shop"
    ],
    "wof:name":"Headliner",
    "wof:placetype":"venue"
},
  "geometry": {"coordinates":[-95.32085499999999,30.01349],"type":"Point"}
}