{
  "type": "Feature",
  "properties": {
    "iso:country":"US",
    "sg:address":"80 8th St",
    "sg:city":"Honey Grove",
    "sg:classifiers":[
        {
            "category":"Organizations",
            "subcategory":"Religious Organization",
            "type":"Services"
        }
    ],
    "sg:phone":"+1 903 378 3337",
    "sg:postcode":"75446",
    "sg:province":"TX",
    "sg:tags":[
        "church"
    ],
    "wof:name":"Eight Street United Methodist",
    "wof:placetype":"venue"
},
  "geometry": {"coordinates":[-95.90785099999999,33.578435],"type":"Point"}
}