{
  "type": "Feature",
  "properties": {
    "iso:country":"US",
    "sg:address":"3119 Garwood St",
    "sg:city":"Austin",
    "sg:classifiers":[
        {
            "category":"Building & Trades",
            "subcategory":"Construction",
            "type":"Services"
        }
    ],
    "sg:phone":"+1 512 389 0677",
    "sg:postcode":"78702",
    "sg:province":"TX",
    "sg:tags":[
        "house"
    ],
    "wof:name":"Lzm Construction Co",
    "wof:placetype":"venue"
},
  "geometry": {"coordinates":[-97.706141,30.260093],"type":"Point"}
}