{
  "type": "Feature",
  "properties": {
    "iso:country":"US",
    "sg:address":"8511 S Braeswood Blvd",
    "sg:city":"Houston",
    "sg:classifiers":[
        {
            "category":"Recreation",
            "type":"Entertainment"
        }
    ],
    "sg:phone":"+1 713 271 7222",
    "sg:postcode":"77071",
    "sg:province":"TX",
    "sg:tags":[
        "psychic",
        "medium"
    ],
    "wof:name":"Mrs Bush Spiritualists Card",
    "wof:placetype":"venue"
},
  "geometry": {"coordinates":[-95.526455,29.671276],"type":"Point"}
}