{
  "type": "Feature",
  "properties": {
    "iso:country":"US",
    "sg:address":"948 Texas Ave",
    "sg:city":"Port Arthur",
    "sg:classifiers":[
        {
            "category":"Organizations",
            "subcategory":"Religious Organization",
            "type":"Services"
        }
    ],
    "sg:phone":"+1 409 985 5412",
    "sg:postcode":"77640",
    "sg:province":"TX",
    "sg:tags":[
        "church"
    ],
    "wof:name":"Israel Chapel AME Church",
    "wof:placetype":"venue"
},
  "geometry": {"coordinates":[-93.94582200000001,29.868649],"type":"Point"}
}