{
  "type": "Feature",
  "properties": {
    "iso:country":"US",
    "sg:address":"3819 Cedarbrush Dr",
    "sg:city":"Dallas",
    "sg:classifiers":[
        {
            "category":"Banks & Credit Unions",
            "subcategory":"Bank",
            "type":"Services"
        }
    ],
    "sg:phone":"+1 214 352 0334",
    "sg:postcode":"75229",
    "sg:province":"TX",
    "sg:tags":[
        "savings",
        "loan",
        "association"
    ],
    "wof:name":"American Dream Savings",
    "wof:placetype":"venue"
},
  "geometry": {"coordinates":[-96.84677499999999,32.908161],"type":"Point"}
}