{
  "type": "Feature",
  "properties": {
    "iso:country":"US",
    "sg:address":"913 E Seminary Dr",
    "sg:city":"Fort Worth",
    "sg:classifiers":[
        {
            "category":"Organizations",
            "subcategory":"Religious Organization",
            "type":"Services"
        }
    ],
    "sg:phone":"+1 817 924 9995",
    "sg:postcode":"76115",
    "sg:province":"TX",
    "sg:tags":[
        "church"
    ],
    "wof:name":"Christian Outreach Center",
    "wof:placetype":"venue"
},
  "geometry": {"coordinates":[-97.31773699999999,32.684402],"type":"Point"}
}