{
  "type": "Feature",
  "properties": {
    "iso:country":"US",
    "sg:address":"14841 Trinity Blvd",
    "sg:city":"Fort Worth",
    "sg:classifiers":[
        {
            "category":"Manufacturing",
            "subcategory":"Metals",
            "type":"Manufacturing & Wholesale Goods"
        }
    ],
    "sg:phone":"+1 817 318 8855",
    "sg:postcode":"76155",
    "sg:province":"TX",
    "sg:tags":[
        "marker",
        "wire",
        "cable"
    ],
    "sg:website":"www.gocsc.com",
    "wof:name":"Communications Supply Corp",
    "wof:placetype":"venue"
},
  "geometry": {"coordinates":[-97.047179,32.822076],"type":"Point"}
}