{
  "type": "Feature",
  "properties": {
    "iso:country":"US",
    "sg:address":"2608 Flower Mound Rd",
    "sg:city":"Flower Mound",
    "sg:classifiers":[
        {
            "category":"Insurance",
            "subcategory":"Insurance Agent",
            "type":"Services"
        }
    ],
    "sg:phone":"+1 972 355 8241",
    "sg:postcode":"75028",
    "sg:province":"TX",
    "wof:name":"Tony R Jones Insurance",
    "wof:placetype":"venue"
},
  "geometry": {"coordinates":[-97.068529,33.013803],"type":"Point"}
}