{
  "type": "Feature",
  "properties": {
    "iso:country":"US",
    "sg:address":"400 E Humble St",
    "sg:city":"Baytown",
    "sg:classifiers":[
        {
            "category":"Building & Trades",
            "subcategory":"Landscaping Services",
            "type":"Services"
        }
    ],
    "sg:phone":"+1 832 513 0179",
    "sg:postcode":"77520",
    "sg:province":"TX",
    "sg:tags":[
        "lawn"
    ],
    "wof:name":"Cerda Landscaping",
    "wof:placetype":"venue"
},
  "geometry": {"coordinates":[-94.964546,29.728733],"type":"Point"}
}