{
  "type": "Feature",
  "properties": {
    "iso:country":"US",
    "sg:address":"10440 N Central Expy",
    "sg:city":"Dallas",
    "sg:classifiers":[
        {
            "category":"Manufacturing",
            "subcategory":"Chemicals & Compounds",
            "type":"Manufacturing & Wholesale Goods"
        }
    ],
    "sg:phone":"+1 214 373 4562",
    "sg:postcode":"75231",
    "sg:province":"TX",
    "sg:tags":[
        "aeronautical",
        "synthetic",
        "rubber",
        "engineer",
        "mfg"
    ],
    "wof:name":"Globe Composite Solutions",
    "wof:placetype":"venue"
},
  "geometry": {"coordinates":[-96.769434,32.888173],"type":"Point"}
}