{
  "type": "Feature",
  "properties": {
    "iso:country":"US",
    "sg:address":"5532 Weatherby Ln",
    "sg:city":"Plano",
    "sg:classifiers":[
        {
            "category":"Professional",
            "subcategory":"Management & Consulting",
            "type":"Services"
        }
    ],
    "sg:phone":"+1 972 612 3799",
    "sg:postcode":"75093",
    "sg:province":"TX",
    "wof:name":"R Scott Stone Management Inc",
    "wof:placetype":"venue"
},
  "geometry": {"coordinates":[-96.813362,33.036485],"type":"Point"}
}