{
  "type": "Feature",
  "properties": {
    "iso:country":"US",
    "sg:address":"12901 Nicholson Rd Ste 230",
    "sg:city":"Dallas",
    "sg:classifiers":[
        {
            "category":"Home & Garden",
            "subcategory":"Carpets & Floor Coverings",
            "type":"Retail Goods"
        }
    ],
    "sg:phone":"+1 972 484 9973",
    "sg:postcode":"75234",
    "sg:province":"TX",
    "sg:tags":[
        "carpeting"
    ],
    "wof:name":"Classic Floors",
    "wof:placetype":"venue"
},
  "geometry": {"coordinates":[-96.907799,32.9217],"type":"Point"}
}