{
  "type": "Feature",
  "properties": {
    "iso:country":"US",
    "sg:address":"3330 S Western St",
    "sg:city":"Amarillo",
    "sg:classifiers":[
        {
            "category":"Restaurant",
            "type":"Food & Drink"
        }
    ],
    "sg:phone":"+1 806 355 6555",
    "sg:postcode":"79109",
    "sg:province":"TX",
    "wof:name":"Mr Gatti's Pizza",
    "wof:placetype":"venue"
},
  "geometry": {"coordinates":[-101.884033,35.176718],"type":"Point"}
}