{
  "type": "Feature",
  "properties": {
    "iso:country":"US",
    "sg:address":"1111 Hermann Dr",
    "sg:city":"Houston",
    "sg:classifiers":[
        {
            "category":"Professional",
            "subcategory":"Computer Services",
            "type":"Services"
        }
    ],
    "sg:phone":"+1 713 529 6344",
    "sg:postcode":"77004",
    "sg:province":"TX",
    "sg:tags":[
        "consultant",
        "geophysical"
    ],
    "wof:name":"Talwani Associates Inc",
    "wof:placetype":"venue"
},
  "geometry": {"coordinates":[-95.389291,29.723218],"type":"Point"}
}