{
  "type": "Feature",
  "properties": {
    "iso:country":"US",
    "sg:address":"330A Little York Rd",
    "sg:city":"Houston",
    "sg:classifiers":[
        {
            "category":"Fast Food",
            "type":"Food & Drink"
        },
        {
            "category":"Food & Beverages",
            "subcategory":"Meat & Fish",
            "type":"Retail Goods"
        }
    ],
    "sg:phone":"+1 713 692 9494",
    "sg:postcode":"77076",
    "sg:province":"TX",
    "sg:tags":[
        "burger",
        "hot",
        "dog"
    ],
    "wof:name":"Burger King",
    "wof:placetype":"venue"
},
  "geometry": {"coordinates":[-95.379846,29.869972],"type":"Point"}
}