{
  "type": "Feature",
  "properties": {
    "iso:country":"US",
    "sg:address":"2527 Orion Dr",
    "sg:city":"League City",
    "sg:classifiers":[
        {
            "category":"Professional",
            "subcategory":"Secretarial Services",
            "type":"Services"
        }
    ],
    "sg:phone":"+1 281 316 6000",
    "sg:postcode":"77573",
    "sg:province":"TX",
    "sg:tags":[
        "convention",
        "court",
        "reporter"
    ],
    "wof:name":"Advantage Video Svc",
    "wof:placetype":"venue"
},
  "geometry": {"coordinates":[-95.12777199999999,29.485256],"type":"Point"}
}