{
  "type": "Feature",
  "properties": {
    "iso:country":"US",
    "sg:address":"5211 Boyd Blvd",
    "sg:city":"Rowlett",
    "sg:classifiers":[
        {
            "category":"Freight",
            "type":"Transportation"
        }
    ],
    "sg:phone":"+1 214 381 7111",
    "sg:postcode":"75088",
    "sg:province":"TX",
    "sg:tags":[
        "operator",
        "mover",
        "local",
        "trucking"
    ],
    "wof:name":"Miller's Movers World",
    "wof:placetype":"venue"
},
  "geometry": {"coordinates":[-96.578903,32.9063],"type":"Point"}
}