{
  "type": "Feature",
  "properties": {
    "iso:country":"US",
    "sg:address":"3492 E Rosemeade Pkwy",
    "sg:city":"Carrollton",
    "sg:classifiers":[
        {
            "category":"Retail",
            "subcategory":"Veterinary Services",
            "type":"Services"
        }
    ],
    "sg:phone":"+1 972 307 7400",
    "sg:postcode":"75007",
    "sg:province":"TX",
    "sg:tags":[
        "veterinarian"
    ],
    "wof:name":"All Creatures Pet Care Center",
    "wof:placetype":"venue"
},
  "geometry": {"coordinates":[-96.850601,33.0116],"type":"Point"}
}