{
  "type": "Feature",
  "properties": {
    "iso:country":"US",
    "sg:address":"1306 Cuernavaca Dr N",
    "sg:city":"Austin",
    "sg:classifiers":[
        {
            "category":"Wholesale",
            "subcategory":"Metals & Minerals",
            "type":"Manufacturing & Wholesale Goods"
        }
    ],
    "sg:phone":"+1 512 263 8870",
    "sg:postcode":"78733",
    "sg:province":"TX",
    "sg:tags":[
        "metalwork",
        "sheet",
        "center",
        "mfg"
    ],
    "wof:name":"Westside Sheet Metal",
    "wof:placetype":"venue"
},
  "geometry": {"coordinates":[-97.865934,30.335335],"type":"Point"}
}