{
  "type": "Feature",
  "properties": {
    "iso:country":"US",
    "sg:address":"4210 82nd St",
    "sg:city":"Lubbock",
    "sg:classifiers":[
        {
            "category":"Wholesale",
            "subcategory":"Wine & Distilled Alcoholic Beverages",
            "type":"Manufacturing & Wholesale Goods"
        }
    ],
    "sg:phone":"+1 806 771 4886",
    "sg:postcode":"79423",
    "sg:province":"TX",
    "sg:tags":[
        "broker"
    ],
    "wof:name":"D'Vine Wine of Lubbock",
    "wof:placetype":"venue"
},
  "geometry": {"coordinates":[-101.902098,33.519748],"type":"Point"}
}