{
  "type": "Feature",
  "properties": {
    "iso:country":"US",
    "sg:address":"1910 Thornberry Dr",
    "sg:city":"Melissa",
    "sg:classifiers":[
        {
            "category":"Professional",
            "subcategory":"Art Services",
            "type":"Services"
        }
    ],
    "sg:phone":"+1 972 838 9252",
    "sg:postcode":"75454",
    "sg:province":"TX",
    "sg:tags":[
        "photography",
        "commercial"
    ],
    "wof:name":"Richard L Bennett Photogr",
    "wof:placetype":"venue"
},
  "geometry": {"coordinates":[-96.56673600000001,33.275821],"type":"Point"}
}