{
  "type": "Feature",
  "properties": {
    "iso:country":"US",
    "sg:address":"5110 Griggs Rd",
    "sg:city":"Houston",
    "sg:classifiers":[
        {
            "category":"Professional",
            "type":"Services"
        }
    ],
    "sg:phone":"+1 832 515 4153",
    "sg:postcode":"77021",
    "sg:province":"TX",
    "wof:name":"Iced Out",
    "wof:placetype":"venue"
},
  "geometry": {"coordinates":[-95.337986,29.698224],"type":"Point"}
}