{
  "type": "Feature",
  "properties": {
    "iso:country":"US",
    "sg:address":"416 Spencer Hwy",
    "sg:city":"South Houston",
    "sg:classifiers":[
        {
            "category":"Restaurant",
            "type":"Food & Drink"
        }
    ],
    "sg:phone":"+1 713 910 0188",
    "sg:postcode":"77587",
    "sg:province":"TX",
    "sg:website":"www.la-favorita.com",
    "wof:name":"La Favorita",
    "wof:placetype":"venue"
},
  "geometry": {"coordinates":[-95.226601,29.6644],"type":"Point"}
}