{
  "type": "Feature",
  "properties": {
    "iso:country":"US",
    "sg:address":"5402 Middle Fiskville Rd",
    "sg:city":"Austin",
    "sg:classifiers":[
        {
            "category":"Professional",
            "type":"Services"
        }
    ],
    "sg:phone":"+1 512 377 5625",
    "sg:postcode":"78751",
    "sg:province":"TX",
    "wof:name":"Kwiklocks",
    "wof:placetype":"venue"
},
  "geometry": {"coordinates":[-97.71419899999999,30.317139],"type":"Point"}
}