{
  "type": "Feature",
  "properties": {
    "iso:country":"US",
    "sg:address":"13738 Pebble Oak Dr",
    "sg:city":"San Antonio",
    "sg:classifiers":[
        {
            "category":"Manufacturing",
            "subcategory":"Leather Goods",
            "type":"Manufacturing & Wholesale Goods"
        }
    ],
    "sg:phone":"+1 210 492 4495",
    "sg:postcode":"78231",
    "sg:province":"TX",
    "sg:tags":[
        "mfg"
    ],
    "wof:name":"Lucky R Leather Shop",
    "wof:placetype":"venue"
},
  "geometry": {"coordinates":[-98.537615,29.566408],"type":"Point"}
}