{
  "type": "Feature",
  "properties": {
    "iso:country":"US",
    "sg:address":"540 Oak Centre Dr",
    "sg:city":"San Antonio",
    "sg:classifiers":[
        {
            "category":"Health Services",
            "subcategory":"Doctor",
            "type":"Services"
        }
    ],
    "sg:phone":"+1 210 494 4290",
    "sg:postcode":"78258",
    "sg:province":"TX",
    "sg:tags":[
        "physician",
        "medical",
        "surgeon"
    ],
    "wof:name":"Yolonda Marcos MD",
    "wof:placetype":"venue"
},
  "geometry": {"coordinates":[-98.49205600000001,29.618819],"type":"Point"}
}