{
  "type": "Feature",
  "properties": {
    "iso:country":"US",
    "sg:address":"1300 Apache Dr",
    "sg:city":"Richardson",
    "sg:classifiers":[
        {
            "category":"Social Services",
            "subcategory":"Job Training",
            "type":"Services"
        }
    ],
    "sg:phone":"+1 972 644 2555",
    "sg:postcode":"75080",
    "sg:province":"TX",
    "wof:name":"Frank Coy & Associates",
    "wof:placetype":"venue"
},
  "geometry": {"coordinates":[-96.767144,32.96714],"type":"Point"}
}