{
  "type": "Feature",
  "properties": {
    "iso:country":"US",
    "sg:address":"2305 Montego Dr",
    "sg:city":"Arlington",
    "sg:classifiers":[
        {
            "category":"Retail",
            "subcategory":"Auto Repair",
            "type":"Services"
        }
    ],
    "sg:phone":"+1 817 472 6159",
    "sg:postcode":"76002",
    "sg:province":"TX",
    "sg:tags":[
        "automotive"
    ],
    "wof:name":"Able Trailer Towing",
    "wof:placetype":"venue"
},
  "geometry": {"coordinates":[-97.06846,32.633047],"type":"Point"}
}