{
  "type": "Feature",
  "properties": {
    "iso:country":"US",
    "sg:address":"9200 Broadway",
    "sg:city":"San Antonio",
    "sg:classifiers":[
        {
            "category":"Personal",
            "type":"Services"
        },
        {
            "category":"Shopping",
            "subcategory":"Clothing, Apparel, & Fashions",
            "type":"Retail Goods"
        }
    ],
    "sg:phone":"+1 210 824 5299",
    "sg:postcode":"78217",
    "sg:province":"TX",
    "sg:tags":[
        "hair",
        "replacement"
    ],
    "wof:name":"Lillian's Hair Systems",
    "wof:placetype":"venue"
},
  "geometry": {"coordinates":[-98.456355,29.524808],"type":"Point"}
}