{
  "type": "Feature",
  "properties": {
    "iso:country":"US",
    "sg:address":"422 N Lindbergh Ct",
    "sg:city":"Baytown",
    "sg:classifiers":[
        {
            "category":"Real Estate",
            "subcategory":"Real Estate Services",
            "type":"Services"
        },
        {
            "category":"Building & Trades",
            "subcategory":"Cleaning & Sanitation",
            "type":"Services"
        }
    ],
    "sg:phone":"+1 832 858 4241",
    "sg:postcode":"77521",
    "sg:province":"TX",
    "sg:tags":[
        "maintenance",
        "cleaners-interior"
    ],
    "wof:name":"Apo's Maintenance Services",
    "wof:placetype":"venue"
},
  "geometry": {"coordinates":[-94.966628,29.766481],"type":"Point"}
}