{
  "type": "Feature",
  "properties": {
    "iso:country":"US",
    "sg:address":"4710 Spencer Hwy",
    "sg:city":"Pasadena",
    "sg:classifiers":[
        {
            "category":"Personal",
            "type":"Services"
        }
    ],
    "sg:phone":"+1 281 991 0080",
    "sg:postcode":"77505",
    "sg:province":"TX",
    "sg:tags":[
        "sewing",
        "alteration"
    ],
    "wof:name":"The Perfect Fit",
    "wof:placetype":"venue"
},
  "geometry": {"coordinates":[-95.17201799999999,29.665186],"type":"Point"}
}