{
  "type": "Feature",
  "properties": {
    "iso:country":"US",
    "sg:address":"1135 E 22nd St",
    "sg:city":"San Angelo",
    "sg:classifiers":[
        {
            "category":"Building & Trades",
            "subcategory":"Construction",
            "type":"Services"
        }
    ],
    "sg:phone":"+1 325 658 8118",
    "sg:postcode":"76903",
    "sg:province":"TX",
    "sg:tags":[
        "house"
    ],
    "wof:name":"R Construction",
    "wof:placetype":"venue"
},
  "geometry": {"coordinates":[-100.430374,31.485243],"type":"Point"}
}