{
  "type": "Feature",
  "properties": {
    "iso:country":"US",
    "sg:address":"1100 Judson Rd",
    "sg:city":"Longview",
    "sg:classifiers":[
        {
            "category":"Banks & Credit Unions",
            "subcategory":"Bank",
            "type":"Services"
        }
    ],
    "sg:phone":"+1 903 446 9000",
    "sg:postcode":"75601",
    "sg:province":"TX",
    "sg:tags":[
        "loan",
        "real estate"
    ],
    "wof:name":"Maverick Mortgage",
    "wof:placetype":"venue"
},
  "geometry": {"coordinates":[-94.73820000000001,32.509971],"type":"Point"}
}