{
  "type": "Feature",
  "properties": {
    "iso:country":"US",
    "sg:address":"4545 Post Oak Place Dr Ste 144",
    "sg:city":"Houston",
    "sg:classifiers":[
        {
            "category":"Real Estate",
            "subcategory":"Real Estate Services",
            "type":"Services"
        }
    ],
    "sg:phone":"+1 713 622 9955",
    "sg:postcode":"77027",
    "sg:province":"TX",
    "sg:tags":[
        "management",
        "property"
    ],
    "sg:website":"www.management-mullins.com",
    "wof:name":"Mullins Management Company",
    "wof:placetype":"venue"
},
  "geometry": {"coordinates":[-95.450699,29.7502],"type":"Point"}
}