{
  "type": "Feature",
  "properties": {
    "iso:country":"US",
    "sg:address":"1306 Barak Ln",
    "sg:city":"Bryan",
    "sg:classifiers":[
        {
            "category":"Social Services",
            "subcategory":"Child Care",
            "type":"Services"
        }
    ],
    "sg:phone":"+1 979 260 2679",
    "sg:postcode":"77802",
    "sg:province":"TX",
    "sg:tags":[
        "day"
    ],
    "wof:name":"Child Development",
    "wof:placetype":"venue"
},
  "geometry": {"coordinates":[-96.341623,30.648221],"type":"Point"}
}