{
  "type": "Feature",
  "properties": {
    "iso:country":"US",
    "sg:address":"10606 Shady Trl Ste 21",
    "sg:city":"Dallas",
    "sg:classifiers":[
        {
            "category":"Building & Trades",
            "subcategory":"Construction",
            "type":"Services"
        }
    ],
    "sg:phone":"+1 214 769 8027",
    "sg:postcode":"75220",
    "sg:province":"TX",
    "sg:tags":[
        "wallcoverings-installation",
        "wallpaper",
        "painting",
        "contractor"
    ],
    "wof:name":"C S Painting",
    "wof:placetype":"venue"
},
  "geometry": {"coordinates":[-96.890489,32.868781],"type":"Point"}
}