{
  "type": "Feature",
  "properties": {
    "iso:country":"US",
    "sg:address":"12617 Beltex Rd",
    "sg:city":"Manor",
    "sg:classifiers":[
        {
            "category":"Building & Trades",
            "subcategory":"Construction",
            "type":"Services"
        }
    ],
    "sg:phone":"+1 512 278 0200",
    "sg:postcode":"78653",
    "sg:province":"TX",
    "sg:tags":[
        "steel"
    ],
    "wof:name":"Viger Group Inc",
    "wof:placetype":"venue"
},
  "geometry": {"coordinates":[-97.51513,30.34487],"type":"Point"}
}