{
  "type": "Feature",
  "properties": {
    "iso:country":"US",
    "sg:address":"5925 Colhurst St",
    "sg:city":"Dallas",
    "sg:classifiers":[
        {
            "category":"Banks & Credit Unions",
            "subcategory":"Investment Brokerage",
            "type":"Services"
        }
    ],
    "sg:phone":"+1 214 739 5804",
    "sg:postcode":"75230",
    "sg:province":"TX",
    "sg:tags":[
        "advisory"
    ],
    "wof:name":"Pointe Force Co",
    "wof:placetype":"venue"
},
  "geometry": {"coordinates":[-96.80465,32.881274],"type":"Point"}
}