{
  "type": "Feature",
  "properties": {
    "iso:country":"US",
    "sg:address":"5435 Gaston Ave",
    "sg:city":"Dallas",
    "sg:classifiers":[
        {
            "category":"Personal",
            "subcategory":"Barber",
            "type":"Services"
        }
    ],
    "sg:phone":"+1 214 821 4578",
    "sg:postcode":"75214",
    "sg:province":"TX",
    "sg:tags":[
        "shop"
    ],
    "wof:name":"Doing His Will",
    "wof:placetype":"venue"
},
  "geometry": {"coordinates":[-96.76423800000001,32.804362],"type":"Point"}
}