{
  "type": "Feature",
  "properties": {
    "iso:country":"US",
    "sg:address":"213 Durango Dr",
    "sg:city":"Roanoke",
    "sg:classifiers":[
        {
            "category":"Communications",
            "subcategory":"Film & Video Production",
            "type":"Services"
        }
    ],
    "sg:phone":"+1 817 285 9179",
    "sg:postcode":"76262",
    "sg:province":"TX",
    "sg:tags":[
        "motion"
    ],
    "wof:name":"Daniel Ochinciuc",
    "wof:placetype":"venue"
},
  "geometry": {"coordinates":[-97.207656,33.005806],"type":"Point"}
}