{
  "type": "Feature",
  "properties": {
    "iso:country":"US",
    "sg:address":"3804 Serene Pl",
    "sg:city":"Plano",
    "sg:classifiers":[
        {
            "category":"Personal",
            "type":"Services"
        }
    ],
    "sg:phone":"+1 972 985 7659",
    "sg:postcode":"75075",
    "sg:province":"TX",
    "sg:tags":[
        "massage"
    ],
    "wof:name":"Tender Touch Canine Massage Th",
    "wof:placetype":"venue"
},
  "geometry": {"coordinates":[-96.765776,33.031537],"type":"Point"}
}