{
  "type": "Feature",
  "properties": {
    "iso:country":"US",
    "sg:address":"447 Whitney St",
    "sg:city":"Cedar Hill",
    "sg:classifiers":[
        {
            "category":"Building & Trades",
            "subcategory":"Pest Control",
            "type":"Services"
        }
    ],
    "sg:phone":"+1 972 291 9359",
    "sg:postcode":"75104",
    "sg:province":"TX",
    "wof:name":"Jerkins Pest Control",
    "wof:placetype":"venue"
},
  "geometry": {"coordinates":[-96.937389,32.58619],"type":"Point"}
}