{
  "type": "Feature",
  "properties": {
    "iso:country":"US",
    "sg:address":"2915 Four Pines Dr",
    "sg:city":"Humble",
    "sg:classifiers":[
        {
            "category":"Professional",
            "subcategory":"Management & Consulting",
            "type":"Services"
        }
    ],
    "sg:phone":"+1 281 360 4238",
    "sg:postcode":"77345",
    "sg:province":"TX",
    "sg:tags":[
        "business"
    ],
    "wof:name":"Rlg Consulting LLC",
    "wof:placetype":"venue"
},
  "geometry": {"coordinates":[-95.17521600000001,30.058528],"type":"Point"}
}