{
  "type": "Feature",
  "properties": {
    "iso:country":"US",
    "sg:address":"13330 Preston Rd",
    "sg:city":"Dallas",
    "sg:classifiers":[
        {
            "category":"Personal",
            "subcategory":"Beauty Salon",
            "type":"Services"
        }
    ],
    "sg:phone":"+1 972 404 8484",
    "sg:postcode":"75240",
    "sg:province":"TX",
    "wof:name":"Healthy Hair With Sherry",
    "wof:placetype":"venue"
},
  "geometry": {"coordinates":[-96.803535,32.932583],"type":"Point"}
}