{
  "type": "Feature",
  "properties": {
    "iso:country":"US",
    "sg:address":"11 Roaring Springs Rd",
    "sg:city":"Joshua",
    "sg:classifiers":[
        {
            "category":"Professional",
            "subcategory":"Business Services",
            "type":"Services"
        }
    ],
    "sg:phone":"+1 817 533 8300",
    "sg:postcode":"76058",
    "sg:province":"TX",
    "sg:tags":[
        "interior",
        "consultant",
        "design",
        "decorator"
    ],
    "wof:name":"S & S Interiors Of Texas",
    "wof:placetype":"venue"
},
  "geometry": {"coordinates":[-97.37779999999999,32.478755],"type":"Point"}
}