{
  "type": "Feature",
  "properties": {
    "iso:country":"US",
    "sg:address":"1255 Co Rd 878B",
    "sg:city":"Sweeny",
    "sg:classifiers":[
        {
            "category":"Professional",
            "subcategory":"Business Services",
            "type":"Services"
        }
    ],
    "sg:phone":"+1 979 548 3666",
    "sg:postcode":"77480",
    "sg:province":"TX",
    "wof:name":"Van Tastic Designs",
    "wof:placetype":"venue"
},
  "geometry": {"coordinates":[-95.701564,29.06005],"type":"Point"}
}