{
  "type": "Feature",
  "properties": {
    "iso:country":"US",
    "sg:address":"4740 Farmer St",
    "sg:city":"Houston",
    "sg:classifiers":[
        {
            "category":"Shopping",
            "subcategory":"Florist",
            "type":"Retail Goods"
        }
    ],
    "sg:phone":"+1 281 288 3660",
    "sg:postcode":"77020",
    "sg:province":"TX",
    "wof:name":"Always In Bloom",
    "wof:placetype":"venue"
},
  "geometry": {"coordinates":[-95.32221699999999,29.775448],"type":"Point"}
}