{
  "type": "Feature",
  "properties": {
    "iso:country":"US",
    "sg:address":"4700 Loyola Lane Suite 116",
    "sg:city":"Austin",
    "sg:classifiers":[
        {
            "category":"Personal",
            "subcategory":"Beauty Salon",
            "type":"Services"
        }
    ],
    "sg:phone":"+1 512 928 9883",
    "sg:postcode":"78723",
    "sg:province":"TX",
    "sg:tags":[
        "spa"
    ],
    "sg:website":"www.jaeundreas.net",
    "wof:name":"Jae Undreas",
    "wof:placetype":"venue"
},
  "geometry": {"coordinates":[-97.666301,30.309655],"type":"Point"}
}