{
  "type": "Feature",
  "properties": {
    "iso:country":"US",
    "sg:address":"10351 Canton Field",
    "sg:city":"San Antonio",
    "sg:classifiers":[
        {
            "category":"Shopping",
            "subcategory":"Jewelry",
            "type":"Retail Goods"
        }
    ],
    "sg:phone":"+1 210 675 1146",
    "sg:postcode":"78245",
    "sg:province":"TX",
    "wof:name":"Mos Joyas",
    "wof:placetype":"venue"
},
  "geometry": {"coordinates":[-98.69616600000001,29.392695],"type":"Point"}
}