{
  "type": "Feature",
  "properties": {
    "iso:country":"US",
    "sg:address":"116 Gregory Rd",
    "sg:city":"Conroe",
    "sg:classifiers":[
        {
            "category":"Building & Trades",
            "subcategory":"Construction",
            "type":"Services"
        }
    ],
    "sg:phone":"+1 936 760 3298",
    "sg:postcode":"77304",
    "sg:province":"TX",
    "sg:tags":[
        "house"
    ],
    "wof:name":"Texas Woodsmiths",
    "wof:placetype":"venue"
},
  "geometry": {"coordinates":[-95.513876,30.316453],"type":"Point"}
}