{
  "type": "Feature",
  "properties": {
    "iso:country":"US",
    "sg:address":"3201 Bagarry St",
    "sg:city":"Amarillo",
    "sg:classifiers":[
        {
            "category":"Professional",
            "subcategory":"Computer Services",
            "type":"Services"
        }
    ],
    "sg:phone":"+1 806 376 4494",
    "sg:postcode":"79103",
    "sg:province":"TX",
    "sg:tags":[
        "related"
    ],
    "wof:name":"Erwin Consulting",
    "wof:placetype":"venue"
},
  "geometry": {"coordinates":[-101.782516,35.179868],"type":"Point"}
}