{
  "type": "Feature",
  "properties": {
    "iso:country":"US",
    "sg:address":"208 Windwood Cir",
    "sg:city":"Seguin",
    "sg:classifiers":[
        {
            "category":"Building & Trades",
            "subcategory":"Construction",
            "type":"Services"
        }
    ],
    "sg:phone":"+1 830 560 1466",
    "sg:postcode":"78155",
    "sg:province":"TX",
    "sg:tags":[
        "dry wall",
        "contractor"
    ],
    "wof:name":"Randy Jones Acoustical",
    "wof:placetype":"venue"
},
  "geometry": {"coordinates":[-98.02466699999999,29.60983],"type":"Point"}
}