{
  "type": "Feature",
  "properties": {
    "iso:country":"US",
    "sg:address":"1303 Warwickshire Dr",
    "sg:city":"Houston",
    "sg:classifiers":[
        {
            "category":"Professional",
            "subcategory":"Business Services",
            "type":"Services"
        }
    ],
    "sg:phone":"+1 281 293 8144",
    "sg:postcode":"77077",
    "sg:province":"TX",
    "sg:tags":[
        "agent",
        "artist"
    ],
    "sg:website":"http://www.kjtenterprises.net",
    "wof:name":"Kms Technology",
    "wof:placetype":"venue"
},
  "geometry": {"coordinates":[-95.589123,29.756058],"type":"Point"}
}