{
  "type": "Feature",
  "properties": {
    "iso:country":"US",
    "sg:address":"7803 Royal Ln",
    "sg:city":"Dallas",
    "sg:classifiers":[
        {
            "category":"Shopping",
            "subcategory":"Shoes",
            "type":"Retail Goods"
        }
    ],
    "sg:phone":"+1 214 696 0209",
    "sg:postcode":"75230",
    "sg:province":"TX",
    "wof:name":"Susan Kagan",
    "wof:placetype":"venue"
},
  "geometry": {"coordinates":[-96.77136299999999,32.898554],"type":"Point"}
}