{
  "type": "Feature",
  "properties": {
    "iso:country":"US",
    "sg:address":"3620 N Josey Ln",
    "sg:city":"Carrollton",
    "sg:classifiers":[
        {
            "category":"Wholesale",
            "subcategory":"Computers",
            "type":"Manufacturing & Wholesale Goods"
        },
        {
            "category":"Professional",
            "subcategory":"Business Services",
            "type":"Services"
        }
    ],
    "sg:phone":"+1 972 492 0930",
    "sg:postcode":"75007",
    "sg:province":"TX",
    "sg:tags":[
        "equipment",
        "b",
        "programing",
        "microfilming",
        "custom"
    ],
    "sg:website":"www.iiri.com",
    "wof:name":"Image Retrieval Inc",
    "wof:placetype":"venue"
},
  "geometry": {"coordinates":[-96.886775,33.011068],"type":"Point"}
}