{
  "type": "Feature",
  "properties": {
    "iso:country":"US",
    "sg:address":"100 E Grauwyler Rd",
    "sg:city":"Irving",
    "sg:classifiers":[
        {
            "category":"Organizations",
            "subcategory":"Non-profit Organization",
            "type":"Services"
        }
    ],
    "sg:phone":"+1 972 579 7399",
    "sg:postcode":"75061",
    "sg:province":"TX",
    "sg:tags":[
        "information",
        "alcoholism",
        "treatment"
    ],
    "wof:name":"Alcoholics Anonymous",
    "wof:placetype":"venue"
},
  "geometry": {"coordinates":[-96.94394200000001,32.829383],"type":"Point"}
}