{
  "type": "Feature",
  "properties": {
    "iso:country":"US",
    "sg:address":"1543 Telephone Rd",
    "sg:city":"Houston",
    "sg:classifiers":[
        {
            "category":"Wholesale",
            "subcategory":"Scrap",
            "type":"Manufacturing & Wholesale Goods"
        }
    ],
    "sg:phone":"+1 713 921 4922",
    "sg:postcode":"77023",
    "sg:province":"TX",
    "sg:tags":[
        "metal",
        "iron"
    ],
    "wof:name":"John Kubica",
    "wof:placetype":"venue"
},
  "geometry": {"coordinates":[-95.32550500000001,29.727611],"type":"Point"}
}