{
  "type": "Feature",
  "properties": {
    "iso:country":"US",
    "sg:address":"6260 Highway 6",
    "sg:city":"Missouri City",
    "sg:classifiers":[
        {
            "category":"Restaurant",
            "type":"Food & Drink"
        }
    ],
    "sg:menulink":"http://www.allmenus.com/tx/sugar-land/130890-subway/menu/",
    "sg:phone":"+1 281 208 3360",
    "sg:postcode":"77459",
    "sg:province":"TX",
    "sg:tags":[
        "american",
        "sandwich"
    ],
    "wof:name":"Subway",
    "wof:placetype":"venue"
},
  "geometry": {"coordinates":[-95.56311700000001,29.563924],"type":"Point"}
}