{
  "type": "Feature",
  "properties": {
    "iso:country":"US",
    "sg:address":"5916 Annapolis St",
    "sg:city":"Houston",
    "sg:classifiers":[
        {
            "category":"Professional",
            "subcategory":"Business Services",
            "type":"Services"
        }
    ],
    "sg:phone":"+1 713 661 3801",
    "sg:postcode":"77005",
    "sg:province":"TX",
    "sg:tags":[
        "operations",
        "undetermined"
    ],
    "wof:name":"Calispos",
    "wof:placetype":"venue"
},
  "geometry": {"coordinates":[-95.42092,29.717542],"type":"Point"}
}