{
  "type": "Feature",
  "properties": {
    "iso:country":"US",
    "sg:address":"144 W Bay Area Blvd",
    "sg:city":"Webster",
    "sg:classifiers":[
        {
            "category":"Shopping",
            "subcategory":"Shoes",
            "type":"Retail Goods"
        }
    ],
    "sg:phone":"+1 281 338 2815",
    "sg:postcode":"77598",
    "sg:province":"TX",
    "wof:name":"S A S Factory Shoe Store",
    "wof:placetype":"venue"
},
  "geometry": {"coordinates":[-95.12894300000001,29.548826],"type":"Point"}
}