{
  "type": "Feature",
  "properties": {
    "iso:country":"US",
    "sg:address":"1930 N Coit Rd",
    "sg:city":"Richardson",
    "sg:classifiers":[
        {
            "category":"Coffee & Tea",
            "type":"Food & Drink"
        }
    ],
    "sg:menulink":"http://www.allmenus.com/tx/northeast/113103-starbucks-coffee/menu/",
    "sg:phone":"+1 972 889 3137",
    "sg:postcode":"75080",
    "sg:province":"TX",
    "sg:tags":[
        "american"
    ],
    "wof:name":"Starbucks Coffee",
    "wof:placetype":"venue"
},
  "geometry": {"coordinates":[-96.768187,32.976361],"type":"Point"}
}