{
  "type": "Feature",
  "properties": {
    "iso:country":"US",
    "sg:address":"23603 Northwood Ln",
    "sg:city":"San Antonio",
    "sg:classifiers":[
        {
            "category":"Professional",
            "type":"Services"
        }
    ],
    "sg:phone":"+1 210 497 8995",
    "sg:postcode":"78259",
    "sg:province":"TX",
    "sg:tags":[
        "establishment"
    ],
    "wof:name":"Creative Capital Inc",
    "wof:placetype":"venue"
},
  "geometry": {"coordinates":[-98.443884,29.659039],"type":"Point"}
}