{
  "type": "Feature",
  "properties": {
    "iso:country":"US",
    "sg:address":"400 Sam Houston Pkwy",
    "sg:city":"Houston",
    "sg:classifiers":[
        {
            "category":"Manufacturing",
            "subcategory":"Tools & Machinery",
            "type":"Manufacturing & Wholesale Goods"
        }
    ],
    "sg:phone":"+1 281 878 8000",
    "sg:postcode":"77060",
    "sg:province":"TX",
    "sg:tags":[
        "field",
        "oil",
        "equipment"
    ],
    "sg:website":"www.grantprideco.com",
    "wof:name":"Grant PRIDECO Inc",
    "wof:placetype":"venue"
},
  "geometry": {"coordinates":[-95.39585099999999,29.938585],"type":"Point"}
}