{
  "type": "Feature",
  "properties": {
    "iso:country":"US",
    "sg:address":"604 Roene Ln",
    "sg:city":"West Columbia",
    "sg:classifiers":[
        {
            "category":"Professional",
            "type":"Services"
        }
    ],
    "sg:phone":"+1 979 345 4841",
    "sg:postcode":"77486",
    "sg:province":"TX",
    "wof:name":"Music Forte Studio",
    "wof:placetype":"venue"
},
  "geometry": {"coordinates":[-95.640619,29.123854],"type":"Point"}
}