{
  "type": "Feature",
  "properties": {
    "iso:country":"US",
    "sg:address":"120 S Jupiter Rd",
    "sg:city":"Garland",
    "sg:classifiers":[
        {
            "category":"Local Transit",
            "type":"Transportation"
        }
    ],
    "sg:phone":"+1 214 228 2730",
    "sg:postcode":"75042",
    "sg:province":"TX",
    "sg:tags":[
        "passenger"
    ],
    "wof:name":"Friends & Family Limousine Co",
    "wof:placetype":"venue"
},
  "geometry": {"coordinates":[-96.682979,32.913432],"type":"Point"}
}