{
  "type": "Feature",
  "properties": {
    "iso:country":"US",
    "sg:address":"1405 N Colorado St",
    "sg:city":"San Antonio",
    "sg:classifiers":[
        {
            "category":"Bars & Pubs",
            "type":"Food & Drink"
        }
    ],
    "sg:phone":"+1 210 732 9109",
    "sg:postcode":"78207",
    "sg:province":"TX",
    "sg:tags":[
        "drinking"
    ],
    "wof:name":"Old Tin Barn Saloon",
    "wof:placetype":"venue"
},
  "geometry": {"coordinates":[-98.50943100000001,29.440569],"type":"Point"}
}