{
  "type": "Feature",
  "properties": {
    "iso:country":"US",
    "sg:address":"5611 Glen Allen Ln",
    "sg:city":"Houston",
    "sg:classifiers":[
        {
            "category":"Professional",
            "subcategory":"Management & Consulting",
            "type":"Services"
        }
    ],
    "sg:phone":"+1 281 440 5953",
    "sg:postcode":"77069",
    "sg:province":"TX",
    "sg:tags":[
        "technical",
        "logistics"
    ],
    "wof:name":"Delta Group",
    "wof:placetype":"venue"
},
  "geometry": {"coordinates":[-95.527151,29.993163],"type":"Point"}
}