{
  "type": "Feature",
  "properties": {
    "iso:country":"US",
    "sg:address":"18590 N Lyford Dr",
    "sg:city":"Katy",
    "sg:classifiers":[
        {
            "category":"Real Estate",
            "subcategory":"Real Estate Agent",
            "type":"Services"
        }
    ],
    "sg:phone":"+1 713 523 2227",
    "sg:postcode":"77449",
    "sg:province":"TX",
    "wof:name":"Buy Appointment Only",
    "wof:placetype":"venue"
},
  "geometry": {"coordinates":[-95.693275,29.862348],"type":"Point"}
}