{
  "type": "Feature",
  "properties": {
    "iso:country":"US",
    "sg:address":"18447 Woodhollow Dr",
    "sg:city":"Flint",
    "sg:classifiers":[
        {
            "category":"Shopping",
            "subcategory":"Bicycles & Sporting Goods",
            "type":"Retail Goods"
        }
    ],
    "sg:phone":"+1 903 894 5953",
    "sg:postcode":"75762",
    "sg:province":"TX",
    "wof:name":"Gun Room",
    "wof:placetype":"venue"
},
  "geometry": {"coordinates":[-95.357671,32.21266],"type":"Point"}
}