{
  "type": "Feature",
  "properties": {
    "iso:country":"US",
    "sg:address":"11930 Proctor Rd",
    "sg:city":"Houston",
    "sg:classifiers":[
        {
            "category":"Shopping",
            "type":"Retail Goods"
        }
    ],
    "sg:phone":"+1 877 741 8548",
    "sg:postcode":"77038",
    "sg:province":"TX",
    "sg:website":"www.beststainless.com/",
    "wof:name":"Best Stainless & Alloys",
    "wof:placetype":"venue"
},
  "geometry": {"coordinates":[-95.465564,29.907313],"type":"Point"}
}