{
  "type": "Feature",
  "properties": {
    "iso:country":"US",
    "sg:address":"2650 Calder Ave",
    "sg:city":"Beaumont",
    "sg:classifiers":[
        {
            "category":"Freight",
            "type":"Transportation"
        }
    ],
    "sg:phone":"+1 409 892 3546",
    "sg:postcode":"77702",
    "sg:province":"TX",
    "sg:tags":[
        "car",
        "pilot"
    ],
    "wof:name":"Escorts-Motorcycle Police",
    "wof:placetype":"venue"
},
  "geometry": {"coordinates":[-94.128648,30.085717],"type":"Point"}
}