{
  "type": "Feature",
  "properties": {
    "iso:country":"US",
    "sg:address":"1019 W Davis St",
    "sg:city":"Dallas",
    "sg:classifiers":[
        {
            "category":"Retail",
            "subcategory":"Repair Shop",
            "type":"Services"
        }
    ],
    "sg:phone":"+1 214 946 5656",
    "sg:postcode":"75208",
    "sg:province":"TX",
    "wof:name":"Exellent Electronics",
    "wof:placetype":"venue"
},
  "geometry": {"coordinates":[-96.840189,32.749554],"type":"Point"}
}