{
  "type": "Feature",
  "properties": {
    "iso:country":"US",
    "sg:address":"2834 N O Connor Rd",
    "sg:city":"Irving",
    "sg:classifiers":[
        {
            "category":"Shopping",
            "subcategory":"Optician",
            "type":"Retail Goods"
        }
    ],
    "sg:phone":"+1 972 258 9880",
    "sg:postcode":"75062",
    "sg:province":"TX",
    "sg:tags":[
        "eyewear"
    ],
    "wof:name":"Fast Z Optical",
    "wof:placetype":"venue"
},
  "geometry": {"coordinates":[-96.95104000000001,32.844653],"type":"Point"}
}