{
  "type": "Feature",
  "properties": {
    "iso:country":"US",
    "sg:address":"801 Western Ave",
    "sg:city":"Angleton",
    "sg:classifiers":[
        {
            "category":"Government",
            "subcategory":"Office",
            "type":"Public Place"
        }
    ],
    "sg:phone":"+1 979 849 3154",
    "sg:postcode":"77515",
    "sg:province":"TX",
    "wof:name":"Judge J Ray Gayle Iii",
    "wof:placetype":"venue"
},
  "geometry": {"coordinates":[-95.44423,29.165482],"type":"Point"}
}