{
  "type": "Feature",
  "properties": {
    "iso:country":"US",
    "sg:address":"2000 S Burleson Blvd",
    "sg:city":"Burleson",
    "sg:classifiers":[
        {
            "category":"Retail",
            "subcategory":"Laundry & Dry Cleaning",
            "type":"Services"
        }
    ],
    "sg:phone":"+1 817 447 1297",
    "sg:postcode":"76028",
    "sg:province":"TX",
    "sg:tags":[
        "cleaners",
        "rug",
        "carpet"
    ],
    "wof:name":"Ultimate Carpet & Upholstery",
    "wof:placetype":"venue"
},
  "geometry": {"coordinates":[-97.292531,32.501151],"type":"Point"}
}