{
  "type": "Feature",
  "properties": {
    "iso:country":"US",
    "sg:address":"9834 Perrin Beitel Rd",
    "sg:city":"San Antonio",
    "sg:classifiers":[
        {
            "category":"Government",
            "subcategory":"Office",
            "type":"Public Place"
        }
    ],
    "sg:phone":"+1 210 655 8102",
    "sg:postcode":"78217",
    "sg:province":"TX",
    "sg:tags":[
        "state",
        "program"
    ],
    "wof:name":"Drivers License",
    "wof:placetype":"venue"
},
  "geometry": {"coordinates":[-98.410977,29.531201],"type":"Point"}
}