{
  "type": "Feature",
  "properties": {
    "iso:country":"US",
    "sg:address":"12203 Montego Plz",
    "sg:city":"Dallas",
    "sg:classifiers":[
        {
            "category":"Professional",
            "subcategory":"Business Services",
            "type":"Services"
        }
    ],
    "sg:phone":"+1 972 239 3327",
    "sg:postcode":"75230",
    "sg:province":"TX",
    "sg:tags":[
        "interior",
        "designer"
    ],
    "wof:name":"Janice Henry Lane Interiors",
    "wof:placetype":"venue"
},
  "geometry": {"coordinates":[-96.815057,32.920257],"type":"Point"}
}