{
  "type": "Feature",
  "properties": {
    "iso:country":"US",
    "sg:address":"2508 Westwood Dr",
    "sg:city":"Mesquite",
    "sg:classifiers":[
        {
            "category":"Utilities",
            "subcategory":"Telephone",
            "type":"Services"
        }
    ],
    "sg:phone":"+1 972 288 2719",
    "sg:postcode":"75150",
    "sg:province":"TX",
    "sg:tags":[
        "telecommunication"
    ],
    "wof:name":"Mas Tec",
    "wof:placetype":"venue"
},
  "geometry": {"coordinates":[-96.620723,32.795843],"type":"Point"}
}