{
  "type": "Feature",
  "properties": {
    "iso:country":"US",
    "sg:address":"103 S Pine St",
    "sg:city":"Van",
    "sg:classifiers":[
        {
            "category":"Real Estate",
            "subcategory":"Real Estate Operator",
            "type":"Services"
        }
    ],
    "sg:phone":"+1 903 963 3757",
    "sg:postcode":"75790",
    "sg:province":"TX",
    "sg:tags":[
        "apartment"
    ],
    "wof:name":"Woodcreek Apartments",
    "wof:placetype":"venue"
},
  "geometry": {"coordinates":[-95.641644,32.524102],"type":"Point"}
}