{
  "type": "Feature",
  "properties": {
    "iso:country":"US",
    "sg:address":"1124 Wynnwood Ln",
    "sg:city":"Houston",
    "sg:classifiers":[
        {
            "category":"Retail",
            "subcategory":"Auto Rental",
            "type":"Services"
        }
    ],
    "sg:phone":"+1 713 861 0655",
    "sg:postcode":"77008",
    "sg:province":"TX",
    "sg:tags":[
        "limousine"
    ],
    "wof:name":"Randall's Limousine Svc",
    "wof:placetype":"venue"
},
  "geometry": {"coordinates":[-95.41966499999999,29.794411],"type":"Point"}
}