{
  "type": "Feature",
  "properties": {
    "iso:country":"US",
    "sg:address":"15503 Old Stone Trl",
    "sg:city":"Houston",
    "sg:classifiers":[
        {
            "category":"Professional",
            "subcategory":"Management & Consulting",
            "type":"Services"
        }
    ],
    "sg:phone":"+1 281 493 5207",
    "sg:postcode":"77079",
    "sg:province":"TX",
    "sg:tags":[
        "business"
    ],
    "wof:name":"Schulte Prof Consulting",
    "wof:placetype":"venue"
},
  "geometry": {"coordinates":[-95.62849199999999,29.774854],"type":"Point"}
}