{
  "type": "Feature",
  "properties": {
    "iso:country":"US",
    "sg:address":"1111 E Scott Ave",
    "sg:city":"Wichita Falls",
    "sg:classifiers":[
        {
            "category":"Shopping",
            "subcategory":"Clothing, Apparel, & Fashions",
            "type":"Retail Goods"
        }
    ],
    "sg:phone":"+1 940 766 0972",
    "sg:postcode":"76301",
    "sg:province":"TX",
    "sg:tags":[
        "western",
        "wear"
    ],
    "wof:name":"Browse Shop",
    "wof:placetype":"venue"
},
  "geometry": {"coordinates":[-98.46827500000001,33.89937],"type":"Point"}
}