{
  "type": "Feature",
  "properties": {
    "iso:country":"US",
    "sg:address":"3804 Winslow Dr",
    "sg:city":"Fort Worth",
    "sg:classifiers":[
        {
            "category":"Wholesale",
            "subcategory":"Apparel",
            "type":"Manufacturing & Wholesale Goods"
        }
    ],
    "sg:phone":"+1 817 922 9477",
    "sg:postcode":"76109",
    "sg:province":"TX",
    "sg:tags":[
        "clothing"
    ],
    "wof:name":"Hip Chic",
    "wof:placetype":"venue"
},
  "geometry": {"coordinates":[-97.374253,32.692385],"type":"Point"}
}