{
  "type": "Feature",
  "properties": {
    "iso:country":"US",
    "sg:address":"4003 Colleyville Blvd",
    "sg:city":"Colleyville",
    "sg:classifiers":[
        {
            "category":"Retail",
            "subcategory":"Repair Shop",
            "type":"Services"
        }
    ],
    "sg:phone":"+1 817 332 1612",
    "sg:postcode":"76034",
    "sg:province":"TX",
    "sg:tags":[
        "locksmith"
    ],
    "wof:name":"Aa Security",
    "wof:placetype":"venue"
},
  "geometry": {"coordinates":[-97.171781,32.867497],"type":"Point"}
}