{
  "type": "Feature",
  "properties": {
    "iso:country":"US",
    "sg:address":"3013 Crisantema St",
    "sg:city":"Mission",
    "sg:classifiers":[
        {
            "category":"Transit Center",
            "subcategory":"Freight",
            "type":"Transportation"
        },
        {
            "category":"Freight",
            "type":"Transportation"
        }
    ],
    "sg:phone":"+1 956 424 3451",
    "sg:postcode":"78574",
    "sg:province":"TX",
    "sg:tags":[
        "local",
        "trucking-motor",
        "trucking"
    ],
    "wof:name":"Marcelo Gonzalez Trucking",
    "wof:placetype":"venue"
},
  "geometry": {"coordinates":[-98.34597100000001,26.244937],"type":"Point"}
}