{
  "type": "Feature",
  "properties": {
    "iso:country":"US",
    "sg:address":"2701 N Town East Blvd",
    "sg:city":"Mesquite",
    "sg:classifiers":[
        {
            "category":"Place Of Worship",
            "type":"Public Place"
        }
    ],
    "sg:phone":"+1 214 402 1956",
    "sg:postcode":"75150",
    "sg:province":"TX",
    "sg:tags":[
        "church"
    ],
    "wof:name":"Iglesia Cristiana Bet El",
    "wof:placetype":"venue"
},
  "geometry": {"coordinates":[-96.638893,32.80788],"type":"Point"}
}