{
  "type": "Feature",
  "properties": {
    "iso:country":"US",
    "sg:address":"11030 Jones Rd W",
    "sg:city":"Houston",
    "sg:classifiers":[
        {
            "category":"Wholesale",
            "subcategory":"Machinery & Supplies",
            "type":"Manufacturing & Wholesale Goods"
        }
    ],
    "sg:phone":"+1 281 970 3248",
    "sg:postcode":"77065",
    "sg:province":"TX",
    "sg:tags":[
        "equipment",
        "establishment"
    ],
    "wof:name":"K B Mannikins",
    "wof:placetype":"venue"
},
  "geometry": {"coordinates":[-95.585233,29.93564],"type":"Point"}
}