{
  "type": "Feature",
  "properties": {
    "iso:country":"US",
    "sg:address":"3317 Mariana Ave",
    "sg:city":"Midland",
    "sg:classifiers":[
        {
            "category":"Building & Trades",
            "subcategory":"Construction",
            "type":"Services"
        }
    ],
    "sg:phone":"+1 432 520 3457",
    "sg:postcode":"79703",
    "sg:province":"TX",
    "sg:tags":[
        "painter"
    ],
    "wof:name":"J C Painting & Counter Tops",
    "wof:placetype":"venue"
},
  "geometry": {"coordinates":[-102.117053,31.987352],"type":"Point"}
}