{
  "type": "Feature",
  "properties": {
    "iso:country":"US",
    "sg:address":"3003 Nederland Ave",
    "sg:city":"Nederland",
    "sg:classifiers":[
        {
            "category":"Professional",
            "subcategory":"Lawyer & Legal Services",
            "type":"Services"
        }
    ],
    "sg:phone":"+1 409 727 7994",
    "sg:postcode":"77627",
    "sg:province":"TX",
    "wof:name":"Mary R Cooper",
    "wof:placetype":"venue"
},
  "geometry": {"coordinates":[-94.001926,29.96102],"type":"Point"}
}