{
  "type": "Feature",
  "properties": {
    "iso:country":"US",
    "sg:address":"3113 San Bernardo Ave",
    "sg:city":"Laredo",
    "sg:classifiers":[
        {
            "category":"Travel",
            "subcategory":"Hotels & Motels",
            "type":"Entertainment"
        }
    ],
    "sg:phone":"+1 956 727 1001",
    "sg:postcode":"78040",
    "sg:province":"TX",
    "wof:name":"El Cortez Courtesy Motel",
    "wof:placetype":"venue"
},
  "geometry": {"coordinates":[-99.504341,27.528053],"type":"Point"}
}