{
  "type": "Feature",
  "properties": {
    "iso:country":"US",
    "sg:address":"1501 Ranch Rd 620 S",
    "sg:city":"Lakeway",
    "sg:classifiers":[
        {
            "category":"Retail",
            "subcategory":"Car Wash",
            "type":"Services"
        }
    ],
    "sg:phone":"+1 512 263 7715",
    "sg:postcode":"78734",
    "sg:province":"TX",
    "sg:tags":[
        "polishing",
        "washing"
    ],
    "wof:name":"Lakeway Car Wash & Storage",
    "wof:placetype":"venue"
},
  "geometry": {"coordinates":[-97.965425,30.345264],"type":"Point"}
}