{
  "type": "Feature",
  "properties": {
    "iso:country":"US",
    "sg:address":"9600 N Mo Pac Expy",
    "sg:city":"Austin",
    "sg:classifiers":[
        {
            "category":"Professional",
            "subcategory":"Management & Consulting",
            "type":"Services"
        }
    ],
    "sg:phone":"+1 512 231 4500",
    "sg:postcode":"78759",
    "sg:province":"TX",
    "sg:tags":[
        "employee",
        "consultant",
        "benefit"
    ],
    "sg:website":"www.administaff.com",
    "wof:name":"Administaff Inc",
    "wof:placetype":"venue"
},
  "geometry": {"coordinates":[-97.736504,30.383877],"type":"Point"}
}