{
  "type": "Feature",
  "properties": {
    "iso:country":"US",
    "sg:address":"2831 E Division St",
    "sg:city":"Arlington",
    "sg:classifiers":[
        {
            "category":"Shopping",
            "subcategory":"Music",
            "type":"Retail Goods"
        }
    ],
    "sg:phone":"+1 817 649 1938",
    "sg:postcode":"76011",
    "sg:province":"TX",
    "sg:tags":[
        "product",
        "prerecorded",
        "tape",
        "blank",
        "small",
        "video",
        "audio"
    ],
    "wof:name":"Suncoast",
    "wof:placetype":"venue"
},
  "geometry": {"coordinates":[-97.05984599999999,32.742611],"type":"Point"}
}