{
  "type": "Feature",
  "properties": {
    "iso:country":"US",
    "sg:address":"28 April Point Dr S",
    "sg:city":"Montgomery",
    "sg:classifiers":[
        {
            "category":"Wholesale",
            "subcategory":"Jewelry",
            "type":"Manufacturing & Wholesale Goods"
        }
    ],
    "sg:phone":"+1 936 588 3320",
    "sg:postcode":"77356",
    "sg:province":"TX",
    "sg:tags":[
        "jeweler"
    ],
    "wof:name":"Southwest Expressions",
    "wof:placetype":"venue"
},
  "geometry": {"coordinates":[-95.61002000000001,30.373914],"type":"Point"}
}