{
  "type": "Feature",
  "properties": {
    "iso:country":"US",
    "sg:address":"2929 S Westmoreland Rd",
    "sg:city":"Dallas",
    "sg:classifiers":[
        {
            "category":"Manufacturing",
            "subcategory":"Printing",
            "type":"Manufacturing & Wholesale Goods"
        }
    ],
    "sg:phone":"+1 214 333 9063",
    "sg:postcode":"75233",
    "sg:province":"TX",
    "sg:tags":[
        "publishing"
    ],
    "wof:name":"Pachanga Music Publishing Svc",
    "wof:placetype":"venue"
},
  "geometry": {"coordinates":[-96.874166,32.711405],"type":"Point"}
}