{
  "type": "Feature",
  "properties": {
    "iso:country":"US",
    "sg:address":"3516 Pace Bend Rd S",
    "sg:city":"Spicewood",
    "sg:classifiers":[
        {
            "category":"Building & Trades",
            "subcategory":"Construction",
            "type":"Services"
        }
    ],
    "sg:phone":"+1 512 264 9926",
    "sg:postcode":"78669",
    "sg:province":"TX",
    "sg:tags":[
        "house"
    ],
    "wof:name":"Shumate Homes Inc",
    "wof:placetype":"venue"
},
  "geometry": {"coordinates":[-98.084366,30.386396],"type":"Point"}
}