{
  "type": "Feature",
  "properties": {
    "iso:country":"US",
    "sg:address":"1411 E Campbell Rd",
    "sg:city":"Richardson",
    "sg:classifiers":[
        {
            "category":"Professional",
            "subcategory":"Engineering",
            "type":"Services"
        }
    ],
    "sg:phone":"+1 972 792 7962",
    "sg:postcode":"75081",
    "sg:province":"TX",
    "sg:tags":[
        "wireless",
        "telecommunication"
    ],
    "wof:name":"Techsync",
    "wof:placetype":"venue"
},
  "geometry": {"coordinates":[-96.69805700000001,32.97471],"type":"Point"}
}