{
  "type": "Feature",
  "properties": {
    "iso:country":"US",
    "sg:address":"1530 N Alamo St",
    "sg:city":"San Antonio",
    "sg:classifiers":[
        {
            "category":"Professional",
            "subcategory":"Lawyer & Legal Services",
            "type":"Services"
        }
    ],
    "sg:phone":"+1 210 225 1955",
    "sg:postcode":"78215",
    "sg:province":"TX",
    "sg:tags":[
        "attorney"
    ],
    "wof:name":"David Van Os & Assoc",
    "wof:placetype":"venue"
},
  "geometry": {"coordinates":[-98.476713,29.439935],"type":"Point"}
}