{
  "type": "Feature",
  "properties": {
    "iso:country":"US",
    "sg:address":"1419 S Loop Fwy",
    "sg:city":"Houston",
    "sg:classifiers":[
        {
            "category":"Shopping",
            "type":"Retail Goods"
        }
    ],
    "sg:phone":"+1 713 791 1300",
    "sg:postcode":"77054",
    "sg:province":"TX",
    "sg:tags":[
        "merchandise"
    ],
    "wof:name":"Choice Wireless",
    "wof:placetype":"venue"
},
  "geometry": {"coordinates":[-95.398015,29.679514],"type":"Point"}
}