{
  "type": "Feature",
  "properties": {
    "iso:country":"US",
    "sg:address":"1001 W Elm St",
    "sg:city":"Tyler",
    "sg:classifiers":[
        {
            "category":"Wholesale",
            "subcategory":"Hardware",
            "type":"Manufacturing & Wholesale Goods"
        }
    ],
    "sg:phone":"+1 903 595 4133",
    "sg:postcode":"75702",
    "sg:province":"TX",
    "sg:tags":[
        "plumbing",
        "supply"
    ],
    "wof:name":"American Supply Company",
    "wof:placetype":"venue"
},
  "geometry": {"coordinates":[-95.312068,32.349452],"type":"Point"}
}