{
  "type": "Feature",
  "properties": {
    "iso:country":"US",
    "sg:address":"2914 Spartacus Dr",
    "sg:city":"Grand Prairie",
    "sg:classifiers":[
        {
            "category":"Professional",
            "type":"Services"
        }
    ],
    "sg:phone":"+1 972 602 9044",
    "sg:postcode":"75052",
    "sg:province":"TX",
    "wof:name":"GTS Planners",
    "wof:placetype":"venue"
},
  "geometry": {"coordinates":[-97.05212,32.684108],"type":"Point"}
}