{
  "type": "Feature",
  "properties": {
    "iso:country":"US",
    "sg:address":"2013 N Ash Ave",
    "sg:city":"Lubbock",
    "sg:classifiers":[
        {
            "category":"Restaurant",
            "type":"Food & Drink"
        }
    ],
    "sg:phone":"+1 806 762 5555",
    "sg:postcode":"79403",
    "sg:province":"TX",
    "sg:tags":[
        "eating"
    ],
    "wof:name":"Fatt Butz Eatin Joint",
    "wof:placetype":"venue"
},
  "geometry": {"coordinates":[-101.83604099999999,33.623023],"type":"Point"}
}