{
  "type": "Feature",
  "properties": {
    "iso:country":"US",
    "sg:address":"2005 Lake Robbins Dr",
    "sg:city":"Spring",
    "sg:classifiers":[
        {
            "category":"Recreation",
            "type":"Entertainment"
        }
    ],
    "sg:phone":"+1 281 363 3300",
    "sg:postcode":"77380",
    "sg:province":"TX",
    "sg:tags":[
        "hall",
        "auditorium"
    ],
    "wof:name":"Cynthia Woods Mitchell Pvlln",
    "wof:placetype":"venue"
},
  "geometry": {"coordinates":[-95.464687,30.162512],"type":"Point"}
}