{
  "type": "Feature",
  "properties": {
    "iso:country":"US",
    "sg:address":"725 S 14th St",
    "sg:city":"Kingsville",
    "sg:classifiers":[
        {
            "category":"Sports & Exercise",
            "subcategory":"Gym",
            "type":"Entertainment"
        }
    ],
    "sg:phone":"+1 361 595 5811",
    "sg:postcode":"78363",
    "sg:province":"TX",
    "sg:tags":[
        "club",
        "health",
        "studio",
        "gymnasium"
    ],
    "wof:name":"Pure Platinum Gym",
    "wof:placetype":"venue"
},
  "geometry": {"coordinates":[-97.856116,27.510491],"type":"Point"}
}