{
  "type": "Feature",
  "properties": {
    "iso:country":"US",
    "sg:address":"16752 State Hwy 105",
    "sg:city":"Sour Lake",
    "sg:classifiers":[
        {
            "category":"Autos & Motor Vehicles",
            "subcategory":"Recreational Vehicle Sales",
            "type":"Retail Goods"
        },
        {
            "category":"Retail",
            "subcategory":"Auto Repair",
            "type":"Services"
        }
    ],
    "sg:phone":"+1 409 753 2290",
    "sg:postcode":"77659",
    "sg:province":"TX",
    "sg:tags":[
        "automotive",
        "parts",
        "trailer"
    ],
    "wof:name":"A & N Trailers & Repair",
    "wof:placetype":"venue"
},
  "geometry": {"coordinates":[-94.344679,30.138897],"type":"Point"}
}