{
  "type": "Feature",
  "properties": {
    "iso:country":"US",
    "sg:address":"954 US Hwy 385",
    "sg:city":"Fort Stockton",
    "sg:classifiers":[
        {
            "category":"Communications",
            "subcategory":"Radio Station",
            "type":"Services"
        }
    ],
    "sg:phone":"+1 432 336 2228",
    "sg:postcode":"79735",
    "sg:province":"TX",
    "sg:tags":[
        "broadcasting"
    ],
    "wof:name":"K F S T Am/FM",
    "wof:placetype":"venue"
},
  "geometry": {"coordinates":[-102.870051,30.892963],"type":"Point"}
}