{
  "type": "Feature",
  "properties": {
    "iso:country":"US",
    "sg:address":"1417 Richey St",
    "sg:city":"Pasadena",
    "sg:classifiers":[
        {
            "category":"Personal",
            "subcategory":"Beauty Salon",
            "type":"Services"
        }
    ],
    "sg:phone":"+1 713 473 9954",
    "sg:postcode":"77502",
    "sg:province":"TX",
    "sg:tags":[
        "nail",
        "shop"
    ],
    "wof:name":"Nails by Vee",
    "wof:placetype":"venue"
},
  "geometry": {"coordinates":[-95.219803,29.688999],"type":"Point"}
}