{
  "type": "Feature",
  "properties": {
    "iso:country":"US",
    "sg:address":"1508 Livingston Dr",
    "sg:city":"Plano",
    "sg:classifiers":[
        {
            "category":"Shopping",
            "type":"Retail Goods"
        }
    ],
    "sg:phone":"+1 972 612 9539",
    "sg:postcode":"75093",
    "sg:province":"TX",
    "sg:tags":[
        "merchandise"
    ],
    "wof:name":"Kennedy Discount Outlet",
    "wof:placetype":"venue"
},
  "geometry": {"coordinates":[-96.77786999999999,33.01959],"type":"Point"}
}