{
  "type": "Feature",
  "properties": {
    "iso:country":"US",
    "sg:address":"92 Trailcrest St",
    "sg:city":"San Antonio",
    "sg:classifiers":[
        {
            "category":"Professional",
            "subcategory":"Secretarial Services",
            "type":"Services"
        }
    ],
    "sg:phone":"+1 210 698 2727",
    "sg:postcode":"78232",
    "sg:province":"TX",
    "sg:tags":[
        "reporting",
        "court"
    ],
    "wof:name":"Eddie Morris Court Reporters",
    "wof:placetype":"venue"
},
  "geometry": {"coordinates":[-98.475452,29.608164],"type":"Point"}
}