{
  "type": "Feature",
  "properties": {
    "iso:country":"US",
    "sg:address":"141 Village Ln",
    "sg:city":"Victoria",
    "sg:classifiers":[
        {
            "category":"Professional",
            "type":"Services"
        }
    ],
    "sg:phone":"+1 361 578 8722",
    "sg:postcode":"77905",
    "sg:province":"TX",
    "wof:name":"Sonny Timme",
    "wof:placetype":"venue"
},
  "geometry": {"coordinates":[-97.06453999999999,28.784802],"type":"Point"}
}