{
  "type": "Feature",
  "properties": {
    "iso:country":"US",
    "sg:address":"1801 Gateway Blvd Ste 101",
    "sg:city":"Richardson",
    "sg:classifiers":[
        {
            "category":"Professional",
            "subcategory":"Employment Agencies",
            "type":"Services"
        }
    ],
    "sg:phone":"+1 972 644 2800",
    "sg:postcode":"75080",
    "sg:province":"TX",
    "wof:name":"C & P Engineering Ltd",
    "wof:placetype":"venue"
},
  "geometry": {"coordinates":[-96.721603,32.972698],"type":"Point"}
}