{
  "type": "Feature",
  "properties": {
    "iso:country":"US",
    "sg:address":"18228 Lakeside Ln",
    "sg:city":"Houston",
    "sg:classifiers":[
        {
            "category":"Professional",
            "subcategory":"Art Services",
            "type":"Services"
        }
    ],
    "sg:phone":"+1 713 299 4956",
    "sg:postcode":"77058",
    "sg:province":"TX",
    "sg:tags":[
        "commercial",
        "design"
    ],
    "wof:name":"Garcia Nielsen & Company",
    "wof:placetype":"venue"
},
  "geometry": {"coordinates":[-95.07509400000001,29.552456],"type":"Point"}
}