{
  "type": "Feature",
  "properties": {
    "iso:country":"US",
    "sg:address":"1508 N 24th St",
    "sg:city":"Nederland",
    "sg:classifiers":[
        {
            "category":"Building & Trades",
            "subcategory":"Landscaping Services",
            "type":"Services"
        }
    ],
    "sg:phone":"+1 409 727 3199",
    "sg:postcode":"77627",
    "sg:province":"TX",
    "sg:tags":[
        "landscape"
    ],
    "wof:name":"Bs Quality Works",
    "wof:placetype":"venue"
},
  "geometry": {"coordinates":[-94.00927299999999,29.973676],"type":"Point"}
}