{
  "type": "Feature",
  "properties": {
    "iso:country":"US",
    "sg:address":"2125 W Southlake Blvd",
    "sg:city":"Southlake",
    "sg:classifiers":[
        {
            "category":"Personal",
            "type":"Services"
        }
    ],
    "sg:phone":"+1 817 421 3433",
    "sg:postcode":"76092",
    "sg:province":"TX",
    "sg:tags":[
        "shop",
        "salon",
        "beauty"
    ],
    "wof:name":"Old World Salon",
    "wof:placetype":"venue"
},
  "geometry": {"coordinates":[-97.183558,32.939104],"type":"Point"}
}