{
  "type": "Feature",
  "properties": {
    "iso:country":"US",
    "sg:address":"4409 Sunflower Ln",
    "sg:city":"Temple",
    "sg:classifiers":[
        {
            "category":"Professional",
            "subcategory":"Accounting & Tax Preparation",
            "type":"Services"
        }
    ],
    "sg:phone":"+1 254 899 0389",
    "sg:postcode":"76502",
    "sg:province":"TX",
    "sg:tags":[
        "public",
        "accountants-certified"
    ],
    "wof:name":"Warren R Smith Cpa",
    "wof:placetype":"venue"
},
  "geometry": {"coordinates":[-97.396269,31.102119],"type":"Point"}
}