{
  "type": "Feature",
  "properties": {
    "iso:country":"US",
    "sg:address":"11952 Hempstead Rd",
    "sg:city":"Houston",
    "sg:classifiers":[
        {
            "category":"Building & Trades",
            "subcategory":"Construction",
            "type":"Services"
        }
    ],
    "sg:phone":"+1 713 934 8434",
    "sg:postcode":"77092",
    "sg:province":"TX",
    "sg:tags":[
        "marking",
        "maintenance",
        "parking"
    ],
    "wof:name":"Ace Parking Lot Svc",
    "wof:placetype":"venue"
},
  "geometry": {"coordinates":[-95.490692,29.823649],"type":"Point"}
}