{
  "type": "Feature",
  "properties": {
    "iso:country":"US",
    "sg:address":"8911 Eastcove Cir",
    "sg:city":"Houston",
    "sg:classifiers":[
        {
            "category":"Shopping",
            "subcategory":"Used Merchandise",
            "type":"Retail Goods"
        }
    ],
    "sg:phone":"+1 713 213 9427",
    "sg:postcode":"77064",
    "sg:province":"TX",
    "sg:tags":[
        "clothing"
    ],
    "wof:name":"Babywearing",
    "wof:placetype":"venue"
},
  "geometry": {"coordinates":[-95.553325,29.899263],"type":"Point"}
}