{
  "type": "Feature",
  "properties": {
    "iso:country":"US",
    "sg:address":"7638 Park Place Blvd",
    "sg:city":"Houston",
    "sg:classifiers":[
        {
            "category":"Building & Trades",
            "subcategory":"Construction",
            "type":"Services"
        }
    ],
    "sg:phone":"+1 713 649 1928",
    "sg:postcode":"77087",
    "sg:province":"TX",
    "sg:tags":[
        "interior",
        "design"
    ],
    "wof:name":"Wilkins Ruth Gardner Interior Desgn",
    "wof:placetype":"venue"
},
  "geometry": {"coordinates":[-95.2882,29.6852],"type":"Point"}
}