{
  "type": "Feature",
  "properties": {
    "iso:country":"US",
    "sg:address":"4601 Southwest Pkwy",
    "sg:city":"Austin",
    "sg:classifiers":[
        {
            "category":"Health Services",
            "subcategory":"Chiropractor",
            "type":"Services"
        }
    ],
    "sg:phone":"+1 512 892 4445",
    "sg:postcode":"78735",
    "sg:province":"TX",
    "wof:name":"Landers Dr Leonora",
    "wof:placetype":"venue"
},
  "geometry": {"coordinates":[-97.83033,30.239772],"type":"Point"}
}