{
  "type": "Feature",
  "properties": {
    "iso:country":"US",
    "sg:address":"715 State Hwy 62",
    "sg:city":"Buna",
    "sg:classifiers":[
        {
            "category":"Shopping",
            "subcategory":"Florist",
            "type":"Retail Goods"
        }
    ],
    "sg:phone":"+1 409 994 2925",
    "sg:postcode":"77630",
    "sg:province":"TX",
    "wof:name":"Melanie's Flowers",
    "wof:placetype":"venue"
},
  "geometry": {"coordinates":[-93.821714,30.071852],"type":"Point"}
}