{
  "type": "Feature",
  "properties": {
    "iso:country":"US",
    "sg:address":"2121 52nd St",
    "sg:city":"Dallas",
    "sg:classifiers":[
        {
            "category":"Real Estate",
            "subcategory":"Real Estate Operator",
            "type":"Services"
        }
    ],
    "sg:phone":"+1 214 375 4600",
    "sg:postcode":"75216",
    "sg:province":"TX",
    "sg:tags":[
        "apartment"
    ],
    "wof:name":"Rose Garden Apartments",
    "wof:placetype":"venue"
},
  "geometry": {"coordinates":[-96.79078199999999,32.689937],"type":"Point"}
}