{
  "type": "Feature",
  "properties": {
    "iso:country":"US",
    "sg:address":"9801 Westheimer Rd",
    "sg:city":"Houston",
    "sg:classifiers":[
        {
            "category":"Manufacturing",
            "subcategory":"Metals",
            "type":"Manufacturing & Wholesale Goods"
        }
    ],
    "sg:phone":"+1 713 917 6878",
    "sg:postcode":"77042",
    "sg:province":"TX",
    "sg:tags":[
        "steel",
        "closure",
        "oil",
        "facility",
        "mfg",
        "truck",
        "axle",
        "forging"
    ],
    "wof:name":"Sypris Technologies Inc",
    "wof:placetype":"venue"
},
  "geometry": {"coordinates":[-95.542267,29.737067],"type":"Point"}
}