{
  "type": "Feature",
  "properties": {
    "iso:country":"US",
    "sg:address":"2507 Briarfield Dr",
    "sg:city":"Richardson",
    "sg:classifiers":[
        {
            "category":"Banks & Credit Unions",
            "subcategory":"Investment Brokerage",
            "type":"Services"
        }
    ],
    "sg:phone":"+1 972 690 3407",
    "sg:postcode":"75080",
    "sg:province":"TX",
    "sg:tags":[
        "commodity",
        "contract"
    ],
    "wof:name":"Red Eggleston Inc",
    "wof:placetype":"venue"
},
  "geometry": {"coordinates":[-96.725039,32.985174],"type":"Point"}
}