{
  "type": "Feature",
  "properties": {
    "iso:country":"US",
    "sg:address":"219 Rogers Hill Rd",
    "sg:city":"Waco",
    "sg:classifiers":[
        {
            "category":"Farming",
            "subcategory":"Dairy Farm",
            "type":"Manufacturing & Wholesale Goods"
        }
    ],
    "sg:phone":"+1 254 829 2304",
    "sg:postcode":"76705",
    "sg:province":"TX",
    "wof:name":"Knust Dairy Inc",
    "wof:placetype":"venue"
},
  "geometry": {"coordinates":[-97.151687,31.699327],"type":"Point"}
}