{
  "type": "Feature",
  "properties": {
    "iso:country":"US",
    "sg:address":"706 N Dallas St",
    "sg:city":"El Paso",
    "sg:classifiers":[
        {
            "category":"Food & Beverages",
            "subcategory":"Fruits & Vegetables",
            "type":"Retail Goods"
        }
    ],
    "sg:phone":"+1 915 544 0253",
    "sg:postcode":"79902",
    "sg:province":"TX",
    "sg:tags":[
        "produce"
    ],
    "wof:name":"JAR",
    "wof:placetype":"venue"
},
  "geometry": {"coordinates":[-106.475661,31.772991],"type":"Point"}
}