{
  "type": "Feature",
  "properties": {
    "iso:country":"US",
    "sg:address":"2200 Walnut Ave",
    "sg:city":"Austin",
    "sg:classifiers":[
        {
            "category":"Professional",
            "subcategory":"Engineering",
            "type":"Services"
        }
    ],
    "sg:phone":"+1 512 481 0304",
    "sg:postcode":"78722",
    "sg:province":"TX",
    "wof:name":"Black Materials",
    "wof:placetype":"venue"
},
  "geometry": {"coordinates":[-97.714186,30.285092],"type":"Point"}
}