{
  "type": "Feature",
  "properties": {
    "iso:country":"US",
    "sg:address":"190 W Robertson St",
    "sg:city":"San Benito",
    "sg:classifiers":[
        {
            "category":"Restaurant",
            "type":"Food & Drink"
        }
    ],
    "sg:phone":"+1 956 399 3661",
    "sg:postcode":"78586",
    "sg:province":"TX",
    "wof:name":"New Noe's",
    "wof:placetype":"venue"
},
  "geometry": {"coordinates":[-97.63295599999999,26.130895],"type":"Point"}
}