{
  "type": "Feature",
  "properties": {
    "iso:country":"US",
    "sg:address":"2717 Raspberry Ln",
    "sg:city":"Pasadena",
    "sg:classifiers":[
        {
            "category":"Shopping",
            "subcategory":"Gifts & Souvenirs",
            "type":"Retail Goods"
        }
    ],
    "sg:phone":"+1 713 943 0390",
    "sg:postcode":"77502",
    "sg:province":"TX",
    "wof:name":"Lane Raspberry Gifts",
    "wof:placetype":"venue"
},
  "geometry": {"coordinates":[-95.19013099999999,29.670548],"type":"Point"}
}