{
  "type": "Feature",
  "properties": {
    "iso:country":"US",
    "sg:address":"3818 FM 359",
    "sg:city":"Richmond",
    "sg:classifiers":[
        {
            "category":"Restaurant",
            "type":"Food & Drink"
        }
    ],
    "sg:phone":"+1 281 342 4758",
    "sg:postcode":"77469",
    "sg:province":"TX",
    "sg:website":"www.swingingdoor.com",
    "wof:name":"Swinging Door",
    "wof:placetype":"venue"
},
  "geometry": {"coordinates":[-95.768794,29.626999],"type":"Point"}
}