{
  "type": "Feature",
  "properties": {
    "iso:country":"US",
    "sg:address":"8383 Westheimer Rd",
    "sg:city":"Houston",
    "sg:classifiers":[
        {
            "category":"Shopping",
            "subcategory":"Shoes",
            "type":"Retail Goods"
        }
    ],
    "sg:phone":"+1 713 977 8691",
    "sg:postcode":"77063",
    "sg:province":"TX",
    "wof:name":"Dsw Shoe Warehouse",
    "wof:placetype":"venue"
},
  "geometry": {"coordinates":[-95.51469899999999,29.737303],"type":"Point"}
}