{
  "type": "Feature",
  "properties": {
    "iso:country":"US",
    "sg:address":"910 S Crowley Rd Ste 21",
    "sg:city":"Crowley",
    "sg:classifiers":[
        {
            "category":"Restaurant",
            "type":"Food & Drink"
        }
    ],
    "sg:phone":"+1 817 297 6728",
    "sg:postcode":"76036",
    "sg:province":"TX",
    "sg:tags":[
        "chinese",
        "buffet"
    ],
    "sg:website":"www.oldchinaking.com",
    "wof:name":"Old China King Buffet",
    "wof:placetype":"venue"
},
  "geometry": {"coordinates":[-97.35216200000001,32.564972],"type":"Point"}
}