{
  "type": "Feature",
  "properties": {
    "iso:country":"US",
    "sg:address":"4414 Swingle Rd",
    "sg:city":"Houston",
    "sg:classifiers":[
        {
            "category":"Building & Trades",
            "subcategory":"Landscaping Services",
            "type":"Services"
        }
    ],
    "sg:phone":"+1 713 991 3200",
    "sg:postcode":"77048",
    "sg:province":"TX",
    "sg:tags":[
        "mowing"
    ],
    "wof:name":"Cains Lawn Svc",
    "wof:placetype":"venue"
},
  "geometry": {"coordinates":[-95.348133,29.62093],"type":"Point"}
}