{
  "type": "Feature",
  "properties": {
    "iso:country":"US",
    "sg:address":"641 S Chadbourne St",
    "sg:city":"San Angelo",
    "sg:classifiers":[
        {
            "category":"Shopping",
            "subcategory":"Luggage & Leather Goods",
            "type":"Retail Goods"
        }
    ],
    "sg:phone":"+1 325 653 9984",
    "sg:postcode":"76903",
    "sg:province":"TX",
    "wof:name":"Narbaiz & Daughters Novelties",
    "wof:placetype":"venue"
},
  "geometry": {"coordinates":[-100.434651,31.454738],"type":"Point"}
}