{
  "type": "Feature",
  "properties": {
    "iso:country":"US",
    "sg:address":"2301 E Saunders St",
    "sg:city":"Laredo",
    "sg:classifiers":[
        {
            "category":"Shopping",
            "subcategory":"Shoes",
            "type":"Retail Goods"
        }
    ],
    "sg:phone":"+1 956 727 5050",
    "sg:postcode":"78041",
    "sg:province":"TX",
    "wof:name":"Meldisco K-M",
    "wof:placetype":"venue"
},
  "geometry": {"coordinates":[-99.474011,27.530464],"type":"Point"}
}