{
  "type": "Feature",
  "properties": {
    "iso:country":"US",
    "sg:address":"400 Oak St",
    "sg:city":"Abilene",
    "sg:classifiers":[
        {
            "category":"Government",
            "subcategory":"Office",
            "type":"Public Place"
        }
    ],
    "sg:phone":"+1 325 674 1224",
    "sg:postcode":"79602",
    "sg:province":"TX",
    "sg:tags":[
        "parish",
        "government-county"
    ],
    "wof:name":"Taylor County",
    "wof:placetype":"venue"
},
  "geometry": {"coordinates":[-99.732803,32.445351],"type":"Point"}
}