{
  "type": "Feature",
  "properties": {
    "iso:country":"US",
    "sg:address":"802 Kingsmark Dr",
    "sg:city":"Houston",
    "sg:classifiers":[
        {
            "category":"Professional",
            "subcategory":"Management & Consulting",
            "type":"Services"
        }
    ],
    "sg:phone":"+1 281 646 8824",
    "sg:postcode":"77094",
    "sg:province":"TX",
    "wof:name":"Hammerly Wirtcrest Management",
    "wof:placetype":"venue"
},
  "geometry": {"coordinates":[-95.699257,29.775116],"type":"Point"}
}