{
  "type": "Feature",
  "properties": {
    "iso:country":"US",
    "sg:address":"234 Fannin St",
    "sg:city":"Abilene",
    "sg:classifiers":[
        {
            "category":"Organizations",
            "subcategory":"Religious Organization",
            "type":"Services"
        }
    ],
    "sg:phone":"+1 325 672 8017",
    "sg:postcode":"79603",
    "sg:province":"TX",
    "wof:name":"Mission",
    "wof:placetype":"venue"
},
  "geometry": {"coordinates":[-99.75690299999999,32.452654],"type":"Point"}
}