{
  "type": "Feature",
  "properties": {
    "iso:country":"US",
    "sg:address":"3638 Highway 6",
    "sg:city":"Sugar Land",
    "sg:classifiers":[
        {
            "category":"Restaurant",
            "type":"Food & Drink"
        }
    ],
    "sg:menulink":"http://www.allmenus.com/tx/sugar-land/70491-pizza-hut/menu/",
    "sg:phone":"+1 281 265 1000",
    "sg:postcode":"77478",
    "sg:province":"TX",
    "sg:tags":[
        "american",
        "pizza"
    ],
    "wof:name":"PIZZA HUT",
    "wof:placetype":"venue"
},
  "geometry": {"coordinates":[-95.598213,29.589478],"type":"Point"}
}