{
  "type": "Feature",
  "properties": {
    "iso:country":"US",
    "sg:address":"301 Koch St",
    "sg:city":"Schertz",
    "sg:classifiers":[
        {
            "category":"Building & Trades",
            "subcategory":"Construction",
            "type":"Services"
        }
    ],
    "sg:phone":"+1 210 658 5608",
    "sg:postcode":"78154",
    "sg:province":"TX",
    "sg:tags":[
        "residential",
        "remodeling",
        "commercial",
        "remodel",
        "home"
    ],
    "wof:name":"Hank Wilson Company",
    "wof:placetype":"venue"
},
  "geometry": {"coordinates":[-98.265771,29.556103],"type":"Point"}
}