{
  "type": "Feature",
  "properties": {
    "iso:country":"US",
    "sg:address":"8841 Timber Path",
    "sg:city":"San Antonio",
    "sg:classifiers":[
        {
            "category":"Shopping",
            "subcategory":"Catalog Store",
            "type":"Retail Goods"
        }
    ],
    "sg:phone":"+1 210 543 8085",
    "sg:postcode":"78250",
    "sg:province":"TX",
    "sg:tags":[
        "mail",
        "order"
    ],
    "wof:name":"Neal Enterprises",
    "wof:placetype":"venue"
},
  "geometry": {"coordinates":[-98.658396,29.482861],"type":"Point"}
}