{
  "type": "Feature",
  "properties": {
    "iso:country":"US",
    "sg:address":"1714 S Houston St",
    "sg:city":"Kaufman",
    "sg:classifiers":[
        {
            "category":"Personal",
            "subcategory":"Barber",
            "type":"Services"
        }
    ],
    "sg:phone":"+1 972 932 6066",
    "sg:postcode":"75142",
    "sg:province":"TX",
    "sg:tags":[
        "shop",
        "beauty"
    ],
    "wof:name":"Classic Cut",
    "wof:placetype":"venue"
},
  "geometry": {"coordinates":[-96.314081,32.578139],"type":"Point"}
}