{
  "type": "Feature",
  "properties": {
    "iso:country":"US",
    "sg:address":"8389 Beverly Pl",
    "sg:city":"El Paso",
    "sg:classifiers":[
        {
            "category":"Building & Trades",
            "subcategory":"Plumbing",
            "type":"Services"
        }
    ],
    "sg:phone":"+1 915 592 8659",
    "sg:postcode":"79907",
    "sg:province":"TX",
    "sg:tags":[
        "contractor"
    ],
    "wof:name":"Amigo Plumbing",
    "wof:placetype":"venue"
},
  "geometry": {"coordinates":[-106.334338,31.725414],"type":"Point"}
}