{
  "type": "Feature",
  "properties": {
    "iso:country":"US",
    "sg:address":"9757 Sierra Dr",
    "sg:city":"Frisco",
    "sg:classifiers":[
        {
            "category":"Professional",
            "subcategory":"Business Services",
            "type":"Services"
        }
    ],
    "sg:phone":"+1 972 712 1776",
    "sg:postcode":"75034",
    "sg:province":"TX",
    "wof:name":"Turftechs Enterprises LLC",
    "wof:placetype":"venue"
},
  "geometry": {"coordinates":[-96.867283,33.159352],"type":"Point"}
}