{
  "type": "Feature",
  "properties": {
    "iso:country":"US",
    "sg:address":"6025 Wiser Ave",
    "sg:city":"Fort Worth",
    "sg:classifiers":[
        {
            "category":"Professional",
            "subcategory":"Testing Lab",
            "type":"Services"
        }
    ],
    "sg:phone":"+1 817 346 8636",
    "sg:postcode":"76133",
    "sg:province":"TX",
    "sg:tags":[
        "laboratory",
        "metallurgist"
    ],
    "wof:name":"L & N Metallurical Products Co",
    "wof:placetype":"venue"
},
  "geometry": {"coordinates":[-97.378822,32.65634],"type":"Point"}
}