{
  "type": "Feature",
  "properties": {
    "iso:country":"US",
    "sg:address":"327 Congress Ave",
    "sg:city":"Austin",
    "sg:classifiers":[
        {
            "category":"Professional",
            "subcategory":"Lawyer & Legal Services",
            "type":"Services"
        }
    ],
    "sg:phone":"+1 512 404 7800",
    "sg:postcode":"78701",
    "sg:province":"TX",
    "sg:tags":[
        "environmental",
        "attorney"
    ],
    "wof:name":"Mathews & Freeland",
    "wof:placetype":"venue"
},
  "geometry": {"coordinates":[-97.743498,30.265964],"type":"Point"}
}