{
  "type": "Feature",
  "properties": {
    "iso:country":"US",
    "sg:address":"2301 Coit Rd",
    "sg:city":"Plano",
    "sg:classifiers":[
        {
            "category":"Health Services",
            "subcategory":"Doctor",
            "type":"Services"
        }
    ],
    "sg:phone":"+1 972 985 7100",
    "sg:postcode":"75075",
    "sg:province":"TX",
    "sg:tags":[
        "physician",
        "surgeon",
        "medical"
    ],
    "wof:name":"Daniel S Achtman MD",
    "wof:placetype":"venue"
},
  "geometry": {"coordinates":[-96.770248,33.029919],"type":"Point"}
}