{
  "type": "Feature",
  "properties": {
    "iso:country":"US",
    "sg:address":"948 Azalia Dr",
    "sg:city":"Lewisville",
    "sg:classifiers":[
        {
            "category":"Professional",
            "type":"Services"
        }
    ],
    "sg:phone":"+1 214 222 0061",
    "sg:postcode":"75067",
    "sg:province":"TX",
    "wof:name":"Tejas Licensing Svc",
    "wof:placetype":"venue"
},
  "geometry": {"coordinates":[-97.03148,33.032907],"type":"Point"}
}