{
  "type": "Feature",
  "properties": {
    "iso:country":"US",
    "sg:address":"12503 Mill Hedge Dr",
    "sg:city":"Houston",
    "sg:classifiers":[
        {
            "category":"Food & Beverages",
            "subcategory":"Specialty",
            "type":"Retail Goods"
        },
        {
            "category":"Professional",
            "subcategory":"Management & Consulting",
            "type":"Services"
        }
    ],
    "sg:phone":"+1 281 955 2654",
    "sg:postcode":"77070",
    "sg:province":"TX",
    "sg:tags":[
        "gourmet",
        "shop"
    ],
    "wof:name":"C B Sales & Marketing",
    "wof:placetype":"venue"
},
  "geometry": {"coordinates":[-95.577896,29.955406],"type":"Point"}
}