{
  "type": "Feature",
  "properties": {
    "iso:country":"US",
    "sg:address":"1000 S Midkiff Rd",
    "sg:city":"Midland",
    "sg:classifiers":[
        {
            "category":"Travel",
            "subcategory":"Hotels & Motels",
            "type":"Entertainment"
        }
    ],
    "sg:phone":"+1 432 694 3700",
    "sg:postcode":"79701",
    "sg:province":"TX",
    "wof:name":"Executive Inn",
    "wof:placetype":"venue"
},
  "geometry": {"coordinates":[-102.11116,31.976796],"type":"Point"}
}