{
  "type": "Feature",
  "properties": {
    "iso:country":"US",
    "sg:address":"9150 RESEARCH BLVD",
    "sg:city":"AUSTIN",
    "sg:phone":"+1 512 451 7411",
    "sg:postcode":"78758",
    "sg:province":"TX",
    "sg:website":"http://www.townnorth.com",
    "wof:name":"Town North Nissan",
    "wof:placetype":"venue"
},
  "geometry": {"coordinates":[-97.73105099999999,30.374797],"type":"Point"}
}