{
  "type": "Feature",
  "properties": {
    "iso:country":"US",
    "sg:address":"4801 W Commerce St",
    "sg:city":"San Antonio",
    "sg:classifiers":[
        {
            "category":"Shopping",
            "subcategory":"Discount & Variety Stores",
            "type":"Retail Goods"
        }
    ],
    "sg:phone":"+1 210 432 4212",
    "sg:postcode":"78237",
    "sg:province":"TX",
    "wof:name":"Big Lots Stores Inc",
    "wof:placetype":"venue"
},
  "geometry": {"coordinates":[-98.555815,29.430919],"type":"Point"}
}