{
  "type": "Feature",
  "properties": {
    "iso:country":"US",
    "sg:address":"515 W Mayfield Rd",
    "sg:city":"Arlington",
    "sg:classifiers":[
        {
            "category":"Health Services",
            "subcategory":"Podiatrist",
            "type":"Services"
        }
    ],
    "sg:phone":"+1 817 467 1990",
    "sg:postcode":"76014",
    "sg:province":"TX",
    "wof:name":"Southerland Joe",
    "wof:placetype":"venue"
},
  "geometry": {"coordinates":[-97.113438,32.691068],"type":"Point"}
}