{
  "type": "Feature",
  "properties": {
    "iso:country":"US",
    "sg:address":"17626 Kings Ct",
    "sg:city":"Cypress",
    "sg:classifiers":[
        {
            "category":"Health Services",
            "subcategory":"Nursing And Care Facility",
            "type":"Services"
        }
    ],
    "sg:phone":"+1 281 256 2755",
    "sg:postcode":"77429",
    "sg:province":"TX",
    "wof:name":"Kings Court Group Home",
    "wof:placetype":"venue"
},
  "geometry": {"coordinates":[-95.697132,29.979095],"type":"Point"}
}