{
  "type": "Feature",
  "properties": {
    "iso:country":"US",
    "sg:address":"1010 Staffordshire Rd",
    "sg:city":"Stafford",
    "sg:classifiers":[
        {
            "category":"Personal",
            "subcategory":"Beauty Salon",
            "type":"Services"
        },
        {
            "category":"Personal",
            "subcategory":"Day Spa",
            "type":"Services"
        }
    ],
    "sg:phone":"+1 281 208 9119",
    "sg:postcode":"77477",
    "sg:province":"TX",
    "wof:name":"The Woodhouse Day Spa",
    "wof:placetype":"venue"
},
  "geometry": {"coordinates":[-95.549958,29.605769],"type":"Point"}
}