{
  "type": "Feature",
  "properties": {
    "iso:country":"US",
    "sg:address":"901 W Crockett St",
    "sg:city":"Floydada",
    "sg:classifiers":[
        {
            "category":"Health Services",
            "subcategory":"Doctor",
            "type":"Services"
        }
    ],
    "sg:phone":"+1 806 983 2975",
    "sg:postcode":"79235",
    "sg:province":"TX",
    "sg:tags":[
        "dentist"
    ],
    "wof:name":"William Dean DDS",
    "wof:placetype":"venue"
},
  "geometry": {"coordinates":[-101.347858,33.977643],"type":"Point"}
}