{
  "type": "Feature",
  "properties": {
    "iso:country":"US",
    "sg:address":"890 N 11th St",
    "sg:city":"Beaumont",
    "sg:classifiers":[
        {
            "category":"Autos & Motor Vehicles",
            "subcategory":"Automobile Sales",
            "type":"Retail Goods"
        }
    ],
    "sg:phone":"+1 409 832 8880",
    "sg:postcode":"77702",
    "sg:province":"TX",
    "wof:name":"Barnett Motor Co Inc",
    "wof:placetype":"venue"
},
  "geometry": {"coordinates":[-94.129801,30.088684],"type":"Point"}
}