{
  "type": "Feature",
  "properties": {
    "iso:country":"US",
    "sg:address":"1515 Fairfield Dr",
    "sg:city":"Austin",
    "sg:classifiers":[
        {
            "category":"Personal",
            "type":"Services"
        }
    ],
    "sg:phone":"+1 512 322 0255",
    "sg:postcode":"78757",
    "sg:province":"TX",
    "wof:name":"Hubbell Nncy Lee Mssage Thrapy",
    "wof:placetype":"venue"
},
  "geometry": {"coordinates":[-97.719204,30.361039],"type":"Point"}
}