{
  "type": "Feature",
  "properties": {
    "iso:country":"US",
    "sg:address":"11961 Royal Woods Dr",
    "sg:city":"El Paso",
    "sg:classifiers":[
        {
            "category":"Building & Trades",
            "subcategory":"Electrical",
            "type":"Services"
        }
    ],
    "sg:phone":"+1 915 856 1607",
    "sg:postcode":"79936",
    "sg:province":"TX",
    "sg:tags":[
        "electrical",
        "electric",
        "contractor"
    ],
    "wof:name":"Lucius Electrical Contractors",
    "wof:placetype":"venue"
},
  "geometry": {"coordinates":[-106.28061599999999,31.777747],"type":"Point"}
}