{
  "type": "Feature",
  "properties": {
    "iso:country":"US",
    "sg:address":"423 Hide A Way Ln E",
    "sg:city":"Hideaway",
    "sg:classifiers":[
        {
            "category":"Shopping",
            "subcategory":"Gifts & Souvenirs",
            "type":"Retail Goods"
        }
    ],
    "sg:phone":"+1 903 881 5495",
    "sg:postcode":"75771",
    "sg:province":"TX",
    "sg:tags":[
        "basket"
    ],
    "wof:name":"Wrapped In Love",
    "wof:placetype":"venue"
},
  "geometry": {"coordinates":[-95.452619,32.49303],"type":"Point"}
}