{
  "type": "Feature",
  "properties": {
    "iso:country":"US",
    "sg:address":"4408 Secretariat Dr",
    "sg:city":"Killeen",
    "sg:classifiers":[
        {
            "category":"Wholesale",
            "subcategory":"Toys & Hobbies",
            "type":"Manufacturing & Wholesale Goods"
        }
    ],
    "sg:phone":"+1 254 616 2775",
    "sg:postcode":"76549",
    "sg:province":"TX",
    "wof:name":"Baskets Bags & Boxes",
    "wof:placetype":"venue"
},
  "geometry": {"coordinates":[-97.78751800000001,31.103337],"type":"Point"}
}