{
  "type": "Feature",
  "properties": {
    "iso:country":"US",
    "sg:address":"115 North Ave",
    "sg:city":"Laredo",
    "sg:classifiers":[
        {
            "category":"Food & Beverages",
            "subcategory":"Specialty",
            "type":"Retail Goods"
        }
    ],
    "sg:phone":"+1 956 724 4968",
    "sg:postcode":"78045",
    "sg:province":"TX",
    "wof:name":"Herbalife Independent Distr",
    "wof:placetype":"venue"
},
  "geometry": {"coordinates":[-99.48572299999999,27.573569],"type":"Point"}
}