{
  "type": "Feature",
  "properties": {
    "iso:country":"US",
    "sg:address":"1445 Yale St",
    "sg:city":"Houston",
    "sg:classifiers":[
        {
            "category":"Restaurant",
            "type":"Food & Drink"
        }
    ],
    "sg:phone":"+1 713 869 5002",
    "sg:postcode":"77008",
    "sg:province":"TX",
    "sg:tags":[
        "party",
        "planning",
        "eating",
        "event"
    ],
    "sg:website":"www.doncarloscatering.com",
    "wof:name":"Don Carlos Catering",
    "wof:placetype":"venue"
},
  "geometry": {"coordinates":[-95.39919999999999,29.797701],"type":"Point"}
}