{
  "type": "Feature",
  "properties": {
    "iso:country":"US",
    "sg:address":"3930 Accent Dr Ste 2027",
    "sg:city":"Dallas",
    "sg:classifiers":[
        {
            "category":"Building & Trades",
            "subcategory":"Construction",
            "type":"Services"
        }
    ],
    "sg:phone":"+1 972 245 4025",
    "sg:postcode":"75287",
    "sg:province":"TX",
    "sg:tags":[
        "contractor"
    ],
    "wof:name":"JCI Roofing Company",
    "wof:placetype":"venue"
},
  "geometry": {"coordinates":[-96.843896,32.988992],"type":"Point"}
}