{
  "type": "Feature",
  "properties": {
    "iso:country":"US",
    "sg:address":"703 Dana Dr",
    "sg:city":"Burkburnett",
    "sg:classifiers":[
        {
            "category":"Social Services",
            "subcategory":"Child Care",
            "type":"Services"
        }
    ],
    "sg:phone":"+1 940 569 5006",
    "sg:postcode":"76354",
    "sg:province":"TX",
    "sg:tags":[
        "day"
    ],
    "wof:name":"Trents Day Care Center",
    "wof:placetype":"venue"
},
  "geometry": {"coordinates":[-98.56075,34.077562],"type":"Point"}
}