{
  "type": "Feature",
  "properties": {
    "iso:country":"US",
    "sg:address":"211 Broadway St",
    "sg:city":"Lubbock",
    "sg:classifiers":[
        {
            "category":"Shopping",
            "type":"Retail Goods"
        }
    ],
    "sg:phone":"+1 806 765 7887",
    "sg:postcode":"79401",
    "sg:province":"TX",
    "sg:tags":[
        "merchandise"
    ],
    "wof:name":"Sierra Thrift Warehouse",
    "wof:placetype":"venue"
},
  "geometry": {"coordinates":[-101.837294,33.584444],"type":"Point"}
}