{
  "type": "Feature",
  "properties": {
    "iso:country":"US",
    "sg:address":"4208 Caruth Blvd",
    "sg:city":"Dallas",
    "sg:classifiers":[
        {
            "category":"Professional",
            "subcategory":"Business Services",
            "type":"Services"
        }
    ],
    "sg:phone":"+1 214 361 1888",
    "sg:postcode":"75225",
    "sg:province":"TX",
    "sg:tags":[
        "house"
    ],
    "wof:name":"Royal European Design Inc",
    "wof:placetype":"venue"
},
  "geometry": {"coordinates":[-96.808459,32.85894],"type":"Point"}
}