{
  "type": "Feature",
  "properties": {
    "iso:country":"US",
    "sg:address":"1010 N Loop 250 W",
    "sg:city":"Midland",
    "sg:classifiers":[
        {
            "category":"Freight",
            "type":"Transportation"
        }
    ],
    "sg:phone":"+1 432 697 5932",
    "sg:postcode":"79703",
    "sg:province":"TX",
    "sg:tags":[
        "warehouse",
        "self",
        "storage"
    ],
    "wof:name":"Colonial Storage Center 215",
    "wof:placetype":"venue"
},
  "geometry": {"coordinates":[-102.151056,31.990778],"type":"Point"}
}