{
  "type": "Feature",
  "properties": {
    "iso:country":"US",
    "sg:address":"10301 Sandpiper Dr",
    "sg:city":"Houston",
    "sg:classifiers":[
        {
            "category":"Professional",
            "type":"Services"
        }
    ],
    "sg:phone":"+1 713 776 8302",
    "sg:postcode":"77096",
    "sg:province":"TX",
    "wof:name":"Gvj Liquidators",
    "wof:placetype":"venue"
},
  "geometry": {"coordinates":[-95.504249,29.668928],"type":"Point"}
}