{
  "type": "Feature",
  "properties": {
    "iso:country":"US",
    "sg:address":"4426 Hunters Lodge Dr",
    "sg:city":"Round Rock",
    "sg:classifiers":[
        {
            "category":"Professional",
            "type":"Services"
        }
    ],
    "sg:phone":"+1 512 310 8582",
    "sg:postcode":"78681",
    "sg:province":"TX",
    "wof:name":"Littles Donald Ray",
    "wof:placetype":"venue"
},
  "geometry": {"coordinates":[-97.761753,30.550353],"type":"Point"}
}