{
  "type": "Feature",
  "properties": {
    "iso:country":"US",
    "sg:address":"803 Fuqua St",
    "sg:city":"Arlington",
    "sg:classifiers":[
        {
            "category":"Professional",
            "type":"Services"
        }
    ],
    "sg:phone":"+1 817 461 7432",
    "sg:postcode":"76012",
    "sg:province":"TX",
    "wof:name":"Metro Pool League Arlingt",
    "wof:placetype":"venue"
},
  "geometry": {"coordinates":[-97.129181,32.745671],"type":"Point"}
}