{
  "type": "Feature",
  "properties": {
    "iso:country":"US",
    "sg:address":"9605 Milltrail Dr",
    "sg:city":"Dallas",
    "sg:classifiers":[
        {
            "category":"Shopping",
            "subcategory":"Gifts & Souvenirs",
            "type":"Retail Goods"
        }
    ],
    "sg:phone":"+1 214 341 6034",
    "sg:postcode":"75238",
    "sg:province":"TX",
    "wof:name":"Rone Bierfeld",
    "wof:placetype":"venue"
},
  "geometry": {"coordinates":[-96.720607,32.8924],"type":"Point"}
}