{
  "type": "Feature",
  "properties": {
    "iso:country":"US",
    "sg:address":"151 Cherokee Rd",
    "sg:city":"Mckinney",
    "sg:classifiers":[
        {
            "category":"Shopping",
            "subcategory":"Florist",
            "type":"Retail Goods"
        }
    ],
    "sg:phone":"+1 972 548 1986",
    "sg:postcode":"75071",
    "sg:province":"TX",
    "wof:name":"Always Flowers",
    "wof:placetype":"venue"
},
  "geometry": {"coordinates":[-96.56468700000001,33.213941],"type":"Point"}
}