{
  "type": "Feature",
  "properties": {
    "iso:country":"US",
    "sg:address":"2120 Longwood Ln",
    "sg:city":"Dallas",
    "sg:classifiers":[
        {
            "category":"Home & Garden",
            "subcategory":"Hardware",
            "type":"Retail Goods"
        }
    ],
    "sg:phone":"+1 214 327 1779",
    "sg:postcode":"75228",
    "sg:province":"TX",
    "wof:name":"Stephen M Farr",
    "wof:placetype":"venue"
},
  "geometry": {"coordinates":[-96.70518300000001,32.809367],"type":"Point"}
}