{
  "type": "Feature",
  "properties": {
    "iso:country":"US",
    "sg:address":"8310 Yale Dr",
    "sg:city":"Tyler",
    "sg:classifiers":[
        {
            "category":"Building & Trades",
            "subcategory":"Landscaping Services",
            "type":"Services"
        }
    ],
    "sg:phone":"+1 903 581 0640",
    "sg:postcode":"75703",
    "sg:province":"TX",
    "wof:name":"Cannon Lawn and Grounds",
    "wof:placetype":"venue"
},
  "geometry": {"coordinates":[-95.304363,32.267987],"type":"Point"}
}