{
  "type": "Feature",
  "properties": {
    "iso:country":"US",
    "sg:address":"20143 Glen Breeze Ct",
    "sg:city":"Humble",
    "sg:classifiers":[
        {
            "category":"Personal",
            "subcategory":"Beauty Salon",
            "type":"Services"
        }
    ],
    "sg:phone":"+1 832 206 2327",
    "sg:postcode":"77346",
    "sg:province":"TX",
    "wof:name":"Hcj Hair Styles",
    "wof:placetype":"venue"
},
  "geometry": {"coordinates":[-95.17455699999999,30.006502],"type":"Point"}
}