{
  "type": "Feature",
  "properties": {
    "iso:country":"US",
    "sg:address":"2 Turtle Creek Bend",
    "sg:city":"Dallas",
    "sg:classifiers":[
        {
            "category":"Professional",
            "subcategory":"Lawyer & Legal Services",
            "type":"Services"
        }
    ],
    "sg:phone":"+1 214 528 5000",
    "sg:postcode":"75204",
    "sg:province":"TX",
    "sg:tags":[
        "law"
    ],
    "wof:name":"Ronald Massingill PC",
    "wof:placetype":"venue"
},
  "geometry": {"coordinates":[-96.799014,32.818681],"type":"Point"}
}