{
  "type": "Feature",
  "properties": {
    "iso:country":"US",
    "sg:address":"809 E 24th St",
    "sg:city":"Plainview",
    "sg:classifiers":[
        {
            "category":"Restaurant",
            "type":"Food & Drink"
        }
    ],
    "sg:phone":"+1 806 293 9764",
    "sg:postcode":"79072",
    "sg:province":"TX",
    "sg:tags":[
        "eating"
    ],
    "wof:name":"Jsj Game Room",
    "wof:placetype":"venue"
},
  "geometry": {"coordinates":[-101.692599,34.205578],"type":"Point"}
}