{
  "type": "Feature",
  "properties": {
    "iso:country":"US",
    "sg:address":"5400 Mockingbird Ln",
    "sg:city":"Dallas",
    "sg:classifiers":[
        {
            "category":"Personal",
            "type":"Services"
        }
    ],
    "sg:phone":"+1 214 841 8500",
    "sg:postcode":"75206",
    "sg:province":"TX",
    "wof:name":"Relocationcentral Search",
    "wof:placetype":"venue"
},
  "geometry": {"coordinates":[-96.776156,32.836512],"type":"Point"}
}