{
  "type": "Feature",
  "properties": {
    "iso:country":"US",
    "sg:address":"1200 Lomaland Dr",
    "sg:city":"El Paso",
    "sg:classifiers":[
        {
            "category":"Building & Trades",
            "subcategory":"Electrical",
            "type":"Services"
        }
    ],
    "sg:phone":"+1 915 598 3622",
    "sg:postcode":"79907",
    "sg:province":"TX",
    "sg:tags":[
        "electrical",
        "electric",
        "contractor"
    ],
    "wof:name":"Sun City Electric Company Inc",
    "wof:placetype":"venue"
},
  "geometry": {"coordinates":[-106.33261400000001,31.741846],"type":"Point"}
}