{
  "type": "Feature",
  "properties": {
    "iso:country":"US",
    "sg:address":"4500 Harry Hines Boulevard",
    "sg:city":"Dallas",
    "sg:classifiers":[
        {
            "category":"Travel",
            "subcategory":"Hotels & Motels",
            "type":"Entertainment"
        },
        {
            "category":"Retail",
            "subcategory":"Event Space",
            "type":"Services"
        }
    ],
    "sg:phone":"+1 214 219 3333",
    "sg:postcode":"75219",
    "sg:province":"TX",
    "sg:tags":[
        "venue"
    ],
    "sg:website":"www.holidayinn.com",
    "wof:name":"Holiday Inn Hotel Dallas Market Center",
    "wof:placetype":"venue"
},
  "geometry": {"coordinates":[-96.829323,32.8066],"type":"Point"}
}