{
  "type": "Feature",
  "properties": {
    "iso:country":"US",
    "sg:address":"111 N Wills St",
    "sg:city":"Wills Point",
    "sg:classifiers":[
        {
            "category":"Building & Trades",
            "subcategory":"Construction",
            "type":"Services"
        }
    ],
    "sg:phone":"+1 903 873 2023",
    "sg:postcode":"75169",
    "sg:province":"TX",
    "sg:tags":[
        "house"
    ],
    "wof:name":"JB Custom Homes Inc",
    "wof:placetype":"venue"
},
  "geometry": {"coordinates":[-96.01131100000001,32.709313],"type":"Point"}
}