{
  "type": "Feature",
  "properties": {
    "iso:country":"US",
    "sg:address":"4050 E Loop 820 S",
    "sg:city":"Fort Worth",
    "sg:classifiers":[
        {
            "category":"Retail",
            "subcategory":"Repair Shop",
            "type":"Services"
        }
    ],
    "sg:phone":"+1 817 429 7188",
    "sg:postcode":"76119",
    "sg:province":"TX",
    "sg:tags":[
        "scale"
    ],
    "wof:name":"Tomco Services Inc",
    "wof:placetype":"venue"
},
  "geometry": {"coordinates":[-97.23321900000001,32.705779],"type":"Point"}
}