{
  "type": "Feature",
  "properties": {
    "iso:country":"US",
    "sg:address":"1203 Bingle Rd",
    "sg:city":"Houston",
    "sg:classifiers":[
        {
            "category":"Food & Beverages",
            "subcategory":"Bakery",
            "type":"Retail Goods"
        }
    ],
    "sg:phone":"+1 713 464 4741",
    "sg:postcode":"77055",
    "sg:province":"TX",
    "sg:tags":[
        "shop",
        "bridal"
    ],
    "wof:name":"Cakes By Sondra",
    "wof:placetype":"venue"
},
  "geometry": {"coordinates":[-95.500416,29.787981],"type":"Point"}
}