{
  "type": "Feature",
  "properties": {
    "iso:country":"US",
    "sg:address":"2459 Denbury Dr",
    "sg:city":"Fort Worth",
    "sg:classifiers":[
        {
            "category":"Shopping",
            "subcategory":"Clothing, Apparel, & Fashions",
            "type":"Retail Goods"
        }
    ],
    "sg:phone":"+1 817 294 7134",
    "sg:postcode":"76133",
    "sg:province":"TX",
    "sg:tags":[
        "family"
    ],
    "wof:name":"Ran Ki Ke",
    "wof:placetype":"venue"
},
  "geometry": {"coordinates":[-97.35668099999999,32.657813],"type":"Point"}
}