{
  "type": "Feature",
  "properties": {
    "iso:country":"US",
    "sg:address":"1516 Texas Blvd",
    "sg:city":"Texarkana",
    "sg:classifiers":[
        {
            "category":"Building & Trades",
            "subcategory":"Construction",
            "type":"Services"
        }
    ],
    "sg:phone":"+1 903 793 3542",
    "sg:postcode":"75501",
    "sg:province":"TX",
    "sg:tags":[
        "consulting",
        "management",
        "contractor"
    ],
    "wof:name":"Masco",
    "wof:placetype":"venue"
},
  "geometry": {"coordinates":[-94.052646,33.433039],"type":"Point"}
}