{
  "type": "Feature",
  "properties": {
    "iso:country":"US",
    "sg:address":"1200 S Main St",
    "sg:city":"Grapevine",
    "sg:classifiers":[
        {
            "category":"Professional",
            "type":"Services"
        }
    ],
    "sg:phone":"+1 817 552 1094",
    "sg:postcode":"76051",
    "sg:province":"TX",
    "sg:tags":[
        "establishment"
    ],
    "wof:name":"Alianza Seguros",
    "wof:placetype":"venue"
},
  "geometry": {"coordinates":[-97.078361,32.927183],"type":"Point"}
}