{
  "type": "Feature",
  "properties": {
    "iso:country":"US",
    "sg:address":"1712 Southmost Rd",
    "sg:city":"Brownsville",
    "sg:classifiers":[
        {
            "category":"Autos & Motor Vehicles",
            "subcategory":"Automobile Sales",
            "type":"Retail Goods"
        }
    ],
    "sg:phone":"+1 956 504 6180",
    "sg:postcode":"78521",
    "sg:province":"TX",
    "sg:tags":[
        "dealers-used",
        "car",
        "used",
        "cars-wholesale",
        "new"
    ],
    "wof:name":"Gloria Q Mares Auto Sales",
    "wof:placetype":"venue"
},
  "geometry": {"coordinates":[-97.475849,25.911202],"type":"Point"}
}