{
  "type": "Feature",
  "properties": {
    "iso:country":"US",
    "sg:address":"931 Austin Hwy",
    "sg:city":"San Antonio",
    "sg:classifiers":[
        {
            "category":"Organizations",
            "subcategory":"Non-profit Organization",
            "type":"Services"
        }
    ],
    "sg:phone":"+1 210 826 2239",
    "sg:postcode":"78209",
    "sg:province":"TX",
    "sg:tags":[
        "social"
    ],
    "wof:name":"Austin Highway Revitalization",
    "wof:placetype":"venue"
},
  "geometry": {"coordinates":[-98.45390500000001,29.484667],"type":"Point"}
}