{
  "type": "Feature",
  "properties": {
    "iso:country":"US",
    "sg:address":"3409 Hopper Rd",
    "sg:city":"Houston",
    "sg:classifiers":[
        {
            "category":"Retail",
            "subcategory":"Repair Shop",
            "type":"Services"
        }
    ],
    "sg:phone":"+1 281 449 7281",
    "sg:postcode":"77093",
    "sg:province":"TX",
    "sg:tags":[
        "welding"
    ],
    "wof:name":"Gray Welding Inc",
    "wof:placetype":"venue"
},
  "geometry": {"coordinates":[-95.33488,29.879609],"type":"Point"}
}