{
  "type": "Feature",
  "properties": {
    "iso:country":"US",
    "sg:address":"1018 Lynnwood Ave",
    "sg:city":"Liberty",
    "sg:classifiers":[
        {
            "category":"Autos & Motor Vehicles",
            "subcategory":"Auto Supplies",
            "type":"Retail Goods"
        }
    ],
    "sg:phone":"+1 936 336 5426",
    "sg:postcode":"77575",
    "sg:province":"TX",
    "wof:name":"M & D Sales",
    "wof:placetype":"venue"
},
  "geometry": {"coordinates":[-94.789756,30.070145],"type":"Point"}
}