{
  "type": "Feature",
  "properties": {
    "iso:country":"US",
    "sg:address":"4105 McCann Rd",
    "sg:city":"Longview",
    "sg:classifiers":[
        {
            "category":"Organizations",
            "subcategory":"Religious Organization",
            "type":"Services"
        }
    ],
    "sg:phone":"+1 903 663 0223",
    "sg:postcode":"75605",
    "sg:province":"TX",
    "sg:tags":[
        "church"
    ],
    "wof:name":"Providence Baptist Church",
    "wof:placetype":"venue"
},
  "geometry": {"coordinates":[-94.76307300000001,32.554462],"type":"Point"}
}