{
  "type": "Feature",
  "properties": {
    "iso:country":"US",
    "sg:address":"2727 Ave E E",
    "sg:city":"Arlington",
    "sg:classifiers":[
        {
            "category":"Professional",
            "type":"Services"
        }
    ],
    "sg:phone":"+1 817 385 4444",
    "sg:postcode":"76011",
    "sg:province":"TX",
    "sg:tags":[
        "establishment"
    ],
    "wof:name":"Arbitronix Texas",
    "wof:placetype":"venue"
},
  "geometry": {"coordinates":[-97.060467,32.75658],"type":"Point"}
}