{
  "type": "Feature",
  "properties": {
    "iso:country":"US",
    "sg:address":"18502 Clay Rd",
    "sg:city":"Houston",
    "sg:classifiers":[
        {
            "category":"Professional",
            "subcategory":"Management & Consulting",
            "type":"Services"
        },
        {
            "category":"Professional",
            "subcategory":"Advertising",
            "type":"Services"
        }
    ],
    "sg:phone":"+1 281 855 0609",
    "sg:postcode":"77084",
    "sg:province":"TX",
    "sg:tags":[
        "marketing",
        "program",
        "consultant"
    ],
    "wof:name":"The Art Advantage",
    "wof:placetype":"venue"
},
  "geometry": {"coordinates":[-95.685286,29.831169],"type":"Point"}
}