{
  "type": "Feature",
  "properties": {
    "iso:country":"US",
    "sg:address":"1340 Fry Rd",
    "sg:city":"Houston",
    "sg:classifiers":[
        {
            "category":"Restaurant",
            "type":"Food & Drink"
        }
    ],
    "sg:menulink":"http://www.allmenus.com/tx/houston/136864-smoothie-king/menu/",
    "sg:phone":"+1 281 578 8300",
    "sg:postcode":"77084",
    "sg:province":"TX",
    "sg:tags":[
        "smoothy",
        "juice",
        "american"
    ],
    "wof:name":"Smoothie King",
    "wof:placetype":"venue"
},
  "geometry": {"coordinates":[-95.71894500000001,29.790746],"type":"Point"}
}