{
  "type": "Feature",
  "properties": {
    "iso:country":"US",
    "sg:address":"1310 Jacksonville Dr",
    "sg:city":"Henderson",
    "sg:classifiers":[
        {
            "category":"Shopping",
            "subcategory":"Florist",
            "type":"Retail Goods"
        }
    ],
    "sg:phone":"+1 903 655 8515",
    "sg:postcode":"75654",
    "sg:province":"TX",
    "wof:name":"Glendas Florist & Gifts",
    "wof:placetype":"venue"
},
  "geometry": {"coordinates":[-94.801748,32.13977],"type":"Point"}
}