{
  "type": "Feature",
  "properties": {
    "iso:country":"US",
    "sg:address":"1612 Robeson St",
    "sg:city":"Bryan",
    "sg:classifiers":[
        {
            "category":"Shopping",
            "subcategory":"Jewelry",
            "type":"Retail Goods"
        }
    ],
    "sg:phone":"+1 979 779 1348",
    "sg:postcode":"77803",
    "sg:province":"TX",
    "wof:name":"Vasquez Jewelry",
    "wof:placetype":"venue"
},
  "geometry": {"coordinates":[-96.399185,30.670358],"type":"Point"}
}