{
  "type": "Feature",
  "properties": {
    "iso:country":"US",
    "sg:address":"12103 Jekel Cir",
    "sg:city":"Austin",
    "sg:classifiers":[
        {
            "category":"Building & Trades",
            "subcategory":"Construction",
            "type":"Services"
        }
    ],
    "sg:phone":"+1 512 258 5000",
    "sg:postcode":"78727",
    "sg:province":"TX",
    "sg:tags":[
        "house",
        "contractor"
    ],
    "wof:name":"Austex Fence & Door",
    "wof:placetype":"venue"
},
  "geometry": {"coordinates":[-97.76357400000001,30.432928],"type":"Point"}
}