{
  "type": "Feature",
  "properties": {
    "iso:country":"US",
    "sg:address":"9006 Dusti Dr",
    "sg:city":"Dallas",
    "sg:classifiers":[
        {
            "category":"Professional",
            "type":"Services"
        }
    ],
    "sg:phone":"+1 214 340 3947",
    "sg:postcode":"75243",
    "sg:province":"TX",
    "sg:tags":[
        "establishment"
    ],
    "wof:name":"JFJ Development Inc",
    "wof:placetype":"venue"
},
  "geometry": {"coordinates":[-96.74257299999999,32.904433],"type":"Point"}
}