{
  "type": "Feature",
  "properties": {
    "iso:country":"US",
    "sg:address":"250 E Houston St",
    "sg:city":"San Antonio",
    "sg:classifiers":[
        {
            "category":"Shopping",
            "subcategory":"Gifts & Souvenirs",
            "type":"Retail Goods"
        }
    ],
    "sg:phone":"+1 210 227 8851",
    "sg:postcode":"78205",
    "sg:province":"TX",
    "sg:tags":[
        "cards",
        "greeting"
    ],
    "wof:name":"The Pink Giraffe Gift Shop",
    "wof:placetype":"venue"
},
  "geometry": {"coordinates":[-98.49133399999999,29.426463],"type":"Point"}
}