{
  "type": "Feature",
  "properties": {
    "iso:country":"US",
    "sg:address":"500 Sunset Dr",
    "sg:city":"Burnet",
    "sg:classifiers":[
        {
            "category":"Retail",
            "subcategory":"Funeral Services",
            "type":"Services"
        }
    ],
    "sg:phone":"+1 512 756 7334",
    "sg:postcode":"78611",
    "sg:province":"TX",
    "wof:name":"Crematory Clements Wilcox",
    "wof:placetype":"venue"
},
  "geometry": {"coordinates":[-98.256339,30.75674],"type":"Point"}
}