{
  "type": "Feature",
  "properties": {
    "iso:country":"US",
    "sg:address":"112 Kerrybrook Dr",
    "sg:city":"Converse",
    "sg:classifiers":[
        {
            "category":"Health Services",
            "subcategory":"Nursing And Care Facility",
            "type":"Services"
        }
    ],
    "sg:phone":"+1 210 566 1950",
    "sg:postcode":"78109",
    "sg:province":"TX",
    "wof:name":"Southwestern Medical Dist",
    "wof:placetype":"venue"
},
  "geometry": {"coordinates":[-98.3038,29.502655],"type":"Point"}
}