{
  "type": "Feature",
  "properties": {
    "iso:country":"US",
    "sg:address":"115 N Commerce St",
    "sg:city":"Lockhart",
    "sg:classifiers":[
        {
            "category":"Manufacturing",
            "subcategory":"Printing",
            "type":"Manufacturing & Wholesale Goods"
        }
    ],
    "sg:phone":"+1 512 398 5352",
    "sg:postcode":"78644",
    "sg:province":"TX",
    "sg:tags":[
        "lithographic",
        "commercial"
    ],
    "wof:name":"Printing Solutions",
    "wof:placetype":"venue"
},
  "geometry": {"coordinates":[-97.671623,29.885475],"type":"Point"}
}