{
  "type": "Feature",
  "properties": {
    "iso:country":"US",
    "sg:address":"308 Cloud St",
    "sg:city":"Killeen",
    "sg:classifiers":[
        {
            "category":"Retail",
            "subcategory":"Repair Shop",
            "type":"Services"
        }
    ],
    "sg:phone":"+1 254 238 6324",
    "sg:postcode":"76541",
    "sg:province":"TX",
    "wof:name":"Detailz",
    "wof:placetype":"venue"
},
  "geometry": {"coordinates":[-97.739818,31.123961],"type":"Point"}
}