{
  "type": "Feature",
  "properties": {
    "iso:country":"US",
    "sg:address":"618 Sagebrush Ln",
    "sg:city":"Allen",
    "sg:classifiers":[
        {
            "category":"Retail",
            "subcategory":"Auto Repair",
            "type":"Services"
        }
    ],
    "sg:phone":"+1 972 390 7235",
    "sg:postcode":"75002",
    "sg:province":"TX",
    "sg:tags":[
        "general"
    ],
    "wof:name":"S&B Garage Doors",
    "wof:placetype":"venue"
},
  "geometry": {"coordinates":[-96.660737,33.090228],"type":"Point"}
}