{
  "type": "Feature",
  "properties": {
    "iso:country":"US",
    "sg:address":"549 US Hwy 287 E",
    "sg:city":"Henrietta",
    "sg:classifiers":[
        {
            "category":"Manufacturing",
            "subcategory":"Motor Vehicles & Parts",
            "type":"Manufacturing & Wholesale Goods"
        }
    ],
    "sg:phone":"+1 940 538 5643",
    "sg:postcode":"76384",
    "sg:province":"TX",
    "sg:tags":[
        "body",
        "construction",
        "machinery",
        "mfg"
    ],
    "wof:name":"Pierce Sales",
    "wof:placetype":"venue"
},
  "geometry": {"coordinates":[-99.2704,34.157739],"type":"Point"}
}