{
  "type": "Feature",
  "properties": {
    "iso:country":"US",
    "sg:address":"1717 Main St Ste 2800",
    "sg:city":"Dallas",
    "sg:classifiers":[
        {
            "category":"Professional",
            "subcategory":"Lawyer & Legal Services",
            "type":"Services"
        }
    ],
    "sg:phone":"+1 214 939 5525",
    "sg:postcode":"75201",
    "sg:province":"TX",
    "wof:name":"Steinfield Arlene F atty",
    "wof:placetype":"venue"
},
  "geometry": {"coordinates":[-96.79690600000001,32.781268],"type":"Point"}
}