{
  "type": "Feature",
  "properties": {
    "iso:country":"US",
    "sg:address":"101 N Padre Island Dr",
    "sg:city":"Corpus Christi",
    "sg:classifiers":[
        {
            "category":"Home & Garden",
            "subcategory":"Building Materials",
            "type":"Retail Goods"
        }
    ],
    "sg:phone":"+1 361 884 3995",
    "sg:postcode":"78406",
    "sg:province":"TX",
    "sg:tags":[
        "glass",
        "window",
        "plate"
    ],
    "wof:name":"Evins Glass Svc",
    "wof:placetype":"venue"
},
  "geometry": {"coordinates":[-97.46837600000001,27.764142],"type":"Point"}
}