{
  "type": "Feature",
  "properties": {
    "iso:country":"US",
    "sg:address":"400 Greens Rd",
    "sg:city":"Houston",
    "sg:classifiers":[
        {
            "category":"Professional",
            "type":"Services"
        }
    ],
    "sg:phone":"+1 281 872 8069",
    "sg:postcode":"77060",
    "sg:province":"TX",
    "wof:name":"Pennis Professional Nail",
    "wof:placetype":"venue"
},
  "geometry": {"coordinates":[-95.406701,29.950428],"type":"Point"}
}