{
  "type": "Feature",
  "properties": {
    "iso:country":"US",
    "sg:address":"511 N 10th St",
    "sg:city":"Mcallen",
    "sg:classifiers":[
        {
            "category":"Organizations",
            "subcategory":"Non-profit Organization",
            "type":"Services"
        }
    ],
    "sg:phone":"+1 956 686 6101",
    "sg:postcode":"78501",
    "sg:province":"TX",
    "sg:tags":[
        "information",
        "alcoholism",
        "treatment"
    ],
    "wof:name":"Sendero Group",
    "wof:placetype":"venue"
},
  "geometry": {"coordinates":[-98.229198,26.20865],"type":"Point"}
}