{
  "type": "Feature",
  "properties": {
    "iso:country":"US",
    "sg:address":"500 Throckmorton St.",
    "sg:city":"Fort Worth",
    "sg:classifiers":[
        {
            "category":"Professional",
            "subcategory":"Computer Services",
            "type":"Services"
        }
    ],
    "sg:phone":"+1 817 332 0069",
    "sg:postcode":"76102",
    "sg:province":"TX",
    "sg:tags":[
        "user-experience",
        "user-experience-design",
        "uxd",
        "user-centered-design",
        "ucd",
        "video-production",
        "online-video",
        "analytics",
        "rich-internet-applications",
        "ria",
        "interactive-agency",
        "digital-agency",
        "dallas",
        "fort-worth",
        "tx",
        "texas",
        "dfw"
    ],
    "sg:website":"http://www.algorhythm.tv",
    "wof:name":"{algo+rhythm}",
    "wof:placetype":"venue"
},
  "geometry": {"coordinates":[-97.33228,32.753109],"type":"Point"}
}