{
  "type": "Feature",
  "properties": {
    "iso:country":"US",
    "sg:address":"531 Cascade St",
    "sg:city":"Bellaire",
    "sg:classifiers":[
        {
            "category":"Building & Trades",
            "subcategory":"Construction",
            "type":"Services"
        }
    ],
    "sg:phone":"+1 713 661 3523",
    "sg:postcode":"77401",
    "sg:province":"TX",
    "sg:tags":[
        "residential",
        "nonresidential"
    ],
    "wof:name":"Craig & Associates",
    "wof:placetype":"venue"
},
  "geometry": {"coordinates":[-95.460089,29.699047],"type":"Point"}
}