{
  "type": "Feature",
  "properties": {
    "iso:country":"US",
    "sg:address":"1201 E Main St",
    "sg:city":"Alice",
    "sg:classifiers":[
        {
            "category":"Restaurant",
            "type":"Food & Drink"
        }
    ],
    "sg:phone":"+1 361 668 8323",
    "sg:postcode":"78332",
    "sg:province":"TX",
    "sg:tags":[
        "pizza"
    ],
    "wof:name":"Pizza Inn",
    "wof:placetype":"venue"
},
  "geometry": {"coordinates":[-98.05904099999999,27.754769],"type":"Point"}
}