{
  "type": "Feature",
  "properties": {
    "iso:country":"US",
    "sg:address":"3053 Windmill Ln",
    "sg:city":"Dallas",
    "sg:classifiers":[
        {
            "category":"Professional",
            "type":"Services"
        }
    ],
    "sg:phone":"+1 972 484 8644",
    "sg:postcode":"75234",
    "sg:province":"TX",
    "wof:name":"Van Phung Mieng",
    "wof:placetype":"venue"
},
  "geometry": {"coordinates":[-96.873543,32.944473],"type":"Point"}
}