{
  "type": "Feature",
  "properties": {
    "iso:country":"US",
    "sg:address":"156 Night Hawk Dr",
    "sg:city":"Elgin",
    "sg:classifiers":[
        {
            "category":"Building & Trades",
            "subcategory":"Construction",
            "type":"Services"
        }
    ],
    "sg:phone":"+1 512 281 5610",
    "sg:postcode":"78621",
    "sg:province":"TX",
    "sg:tags":[
        "concrete",
        "staining",
        "contractor"
    ],
    "sg:website":"http://www.architecturalconcreteservices.com",
    "wof:name":"Architectural Concrete Services",
    "wof:placetype":"venue"
},
  "geometry": {"coordinates":[-97.301478,30.360254],"type":"Point"}
}