{
  "type": "Feature",
  "properties": {
    "iso:country":"US",
    "sg:address":"2036 Co Rd 242",
    "sg:city":"Dublin",
    "sg:classifiers":[
        {
            "category":"Farming",
            "subcategory":"Dairy Farm",
            "type":"Manufacturing & Wholesale Goods"
        }
    ],
    "sg:phone":"+1 254 445 3024",
    "sg:postcode":"76446",
    "sg:province":"TX",
    "wof:name":"Sunrise Farms Inc",
    "wof:placetype":"venue"
},
  "geometry": {"coordinates":[-98.294163,32.177165],"type":"Point"}
}