{
  "type": "Feature",
  "properties": {
    "iso:country":"US",
    "sg:address":"4800 Matlock Rd",
    "sg:city":"Arlington",
    "sg:classifiers":[
        {
            "category":"Home & Garden",
            "subcategory":"Building Materials",
            "type":"Retail Goods"
        },
        {
            "category":"Manufacturing",
            "subcategory":"Glass & Minerals",
            "type":"Manufacturing & Wholesale Goods"
        },
        {
            "category":"Manufacturing",
            "subcategory":"Building Materials",
            "type":"Manufacturing & Wholesale Goods"
        }
    ],
    "sg:phone":"+1 817 784 0465",
    "sg:postcode":"76018",
    "sg:province":"TX",
    "sg:tags":[
        "accessory",
        "window",
        "skylight",
        "doors",
        "frames",
        "skylights-wholesale",
        "manufacturer"
    ],
    "wof:name":"Solatube",
    "wof:placetype":"venue"
},
  "geometry": {"coordinates":[-97.115059,32.669242],"type":"Point"}
}