{
  "type": "Feature",
  "properties": {
    "iso:country":"US",
    "sg:address":"4107 Luckenbach Rd",
    "sg:city":"San Antonio",
    "sg:classifiers":[
        {
            "category":"Professional",
            "type":"Services"
        }
    ],
    "sg:phone":"+1 210 680 5665",
    "sg:postcode":"78251",
    "sg:province":"TX",
    "wof:name":"Look It Corp",
    "wof:placetype":"venue"
},
  "geometry": {"coordinates":[-98.68428900000001,29.474038],"type":"Point"}
}