{
  "type": "Feature",
  "properties": {
    "iso:country":"US",
    "sg:address":"415 W Bermuda St",
    "sg:city":"Quitman",
    "sg:classifiers":[
        {
            "category":"Shopping",
            "subcategory":"Beauty & Cosmetics",
            "type":"Retail Goods"
        }
    ],
    "sg:phone":"+1 903 763 5194",
    "sg:postcode":"75783",
    "sg:province":"TX",
    "sg:tags":[
        "equipment",
        "perfume",
        "salons-equipment",
        "supply"
    ],
    "sg:website":"http://www.merlenorman.com",
    "wof:name":"Merle Norman Cosmetic Studio",
    "wof:placetype":"venue"
},
  "geometry": {"coordinates":[-95.45460300000001,32.795391],"type":"Point"}
}