{
  "type": "Feature",
  "properties": {
    "iso:country":"US",
    "sg:address":"6107 Bayonne Dr",
    "sg:city":"Spring",
    "sg:classifiers":[
        {
            "category":"Building & Trades",
            "subcategory":"Cleaning & Sanitation",
            "type":"Services"
        }
    ],
    "sg:phone":"+1 281 376 7349",
    "sg:postcode":"77389",
    "sg:province":"TX",
    "sg:tags":[
        "maintenance"
    ],
    "wof:name":"Oncall Building Maintenance Lc",
    "wof:placetype":"venue"
},
  "geometry": {"coordinates":[-95.512621,30.10203],"type":"Point"}
}