{
  "type": "Feature",
  "properties": {
    "iso:country":"US",
    "sg:address":"5913 Stratford Dr",
    "sg:city":"Waco",
    "sg:classifiers":[
        {
            "category":"Professional",
            "subcategory":"Accounting & Tax Preparation",
            "type":"Services"
        }
    ],
    "sg:phone":"+1 254 776 8488",
    "sg:postcode":"76710",
    "sg:province":"TX",
    "sg:tags":[
        "bookkeeping",
        "general"
    ],
    "wof:name":"Maggard Bookkeeping & Tax Svc",
    "wof:placetype":"venue"
},
  "geometry": {"coordinates":[-97.189592,31.520718],"type":"Point"}
}