{
  "type": "Feature",
  "properties": {
    "iso:country":"US",
    "sg:address":"5604 Vinewood Dr",
    "sg:city":"Garland",
    "sg:classifiers":[
        {
            "category":"Building & Trades",
            "subcategory":"Construction",
            "type":"Services"
        }
    ],
    "sg:phone":"+1 972 270 1881",
    "sg:postcode":"75043",
    "sg:province":"TX",
    "sg:tags":[
        "roofing",
        "contractor"
    ],
    "wof:name":"M Crowley Roofing",
    "wof:placetype":"venue"
},
  "geometry": {"coordinates":[-96.616724,32.85129],"type":"Point"}
}