{
  "type": "Feature",
  "properties": {
    "iso:country":"US",
    "sg:address":"22536 State Highway 249",
    "sg:city":"Houston",
    "sg:classifiers":[
        {
            "category":"Fast Food",
            "type":"Food & Drink"
        }
    ],
    "sg:phone":"+1 832 717 3585",
    "sg:postcode":"77070",
    "sg:province":"TX",
    "sg:tags":[
        "restaurant"
    ],
    "sg:website":"http://www.bk.com",
    "wof:name":"Burger King",
    "wof:placetype":"venue"
},
  "geometry": {"coordinates":[-95.588448,30.010405],"type":"Point"}
}