{
  "type": "Feature",
  "properties": {
    "iso:country":"US",
    "sg:address":"1700 Brook Hollow Dr",
    "sg:city":"Bryan",
    "sg:classifiers":[
        {
            "category":"Real Estate",
            "subcategory":"Developer",
            "type":"Services"
        }
    ],
    "sg:phone":"+1 979 823 3966",
    "sg:postcode":"77802",
    "sg:province":"TX",
    "wof:name":"Windover Co of Bryan",
    "wof:placetype":"venue"
},
  "geometry": {"coordinates":[-96.35956400000001,30.655865],"type":"Point"}
}