{
  "type": "Feature",
  "properties": {
    "iso:country":"US",
    "sg:address":"101 N Ave C",
    "sg:city":"Olney",
    "sg:classifiers":[
        {
            "category":"Health Services",
            "subcategory":"Hospital",
            "type":"Services"
        }
    ],
    "sg:phone":"+1 940 564 5521",
    "sg:postcode":"76374",
    "sg:province":"TX",
    "wof:name":"Hamilton Hospital",
    "wof:placetype":"venue"
},
  "geometry": {"coordinates":[-98.75263,33.37059],"type":"Point"}
}