{
  "type": "Feature",
  "properties": {
    "iso:country":"US",
    "sg:address":"21110 Concordia Park Ln",
    "sg:city":"Richmond",
    "sg:classifiers":[
        {
            "category":"Autos & Motor Vehicles",
            "subcategory":"Auto Supplies",
            "type":"Retail Goods"
        }
    ],
    "sg:phone":"+1 832 595 8038",
    "sg:postcode":"77407",
    "sg:province":"TX",
    "sg:tags":[
        "wheel"
    ],
    "wof:name":"Shar S Ribs On Wheels",
    "wof:placetype":"venue"
},
  "geometry": {"coordinates":[-95.74835400000001,29.698878],"type":"Point"}
}