{
  "type": "Feature",
  "properties": {
    "iso:country":"US",
    "sg:address":"7148 Blanco Rd",
    "sg:city":"San Antonio",
    "sg:classifiers":[
        {
            "category":"Shopping",
            "subcategory":"Bicycles & Sporting Goods",
            "type":"Retail Goods"
        }
    ],
    "sg:phone":"+1 210 344 2303",
    "sg:postcode":"78216",
    "sg:province":"TX",
    "wof:name":"Bike World Retail Stores",
    "wof:placetype":"venue"
},
  "geometry": {"coordinates":[-98.506118,29.521452],"type":"Point"}
}