{
  "type": "Feature",
  "properties": {
    "iso:country":"US",
    "sg:address":"104 College Park Dr",
    "sg:city":"Weatherford",
    "sg:classifiers":[
        {
            "category":"Shopping",
            "subcategory":"Pharmacy",
            "type":"Retail Goods"
        }
    ],
    "sg:phone":"+1 817 441 9651",
    "sg:postcode":"76086",
    "sg:province":"TX",
    "sg:tags":[
        "drug",
        "store"
    ],
    "wof:name":"Eckerd",
    "wof:placetype":"venue"
},
  "geometry": {"coordinates":[-97.795979,32.738831],"type":"Point"}
}