{
  "type": "Feature",
  "properties": {
    "iso:country":"US",
    "sg:address":"1009 Harvey St",
    "sg:city":"Mcallen",
    "sg:phone":"+1 956 687 4004",
    "sg:postcode":"78501",
    "sg:province":"TX",
    "wof:name":"Kuressence",
    "wof:placetype":"venue"
},
  "geometry": {"coordinates":[-98.225849,26.228612],"type":"Point"}
}