{
  "type": "Feature",
  "properties": {
    "iso:country":"US",
    "sg:address":"10602 Sageberry Dr",
    "sg:city":"Houston",
    "sg:classifiers":[
        {
            "category":"Education",
            "subcategory":"Special Training",
            "type":"Public Place"
        }
    ],
    "sg:phone":"+1 281 484 1856",
    "sg:postcode":"77089",
    "sg:province":"TX",
    "sg:tags":[
        "educational"
    ],
    "wof:name":"Francisco Ramales Flores",
    "wof:placetype":"venue"
},
  "geometry": {"coordinates":[-95.234585,29.594683],"type":"Point"}
}