{
  "type": "Feature",
  "properties": {
    "iso:country":"US",
    "sg:address":"2099 Sam Houston St",
    "sg:city":"Liberty",
    "sg:classifiers":[
        {
            "category":"Communications",
            "subcategory":"Radio Station",
            "type":"Services"
        }
    ],
    "sg:phone":"+1 936 336 5793",
    "sg:postcode":"77575",
    "sg:province":"TX",
    "sg:tags":[
        "company",
        "broadcasting"
    ],
    "wof:name":"KSHN",
    "wof:placetype":"venue"
},
  "geometry": {"coordinates":[-94.795857,30.058795],"type":"Point"}
}