{
  "type": "Feature",
  "properties": {
    "iso:country":"US",
    "sg:address":"503 Zeta Cir",
    "sg:city":"San Antonio",
    "sg:classifiers":[
        {
            "category":"Wholesale",
            "subcategory":"Machinery & Supplies",
            "type":"Manufacturing & Wholesale Goods"
        }
    ],
    "sg:phone":"+1 210 403 9240",
    "sg:postcode":"78258",
    "sg:province":"TX",
    "sg:tags":[
        "contractor"
    ],
    "wof:name":"Ranger Equipment",
    "wof:placetype":"venue"
},
  "geometry": {"coordinates":[-98.50054299999999,29.631763],"type":"Point"}
}