{
  "type": "Feature",
  "properties": {
    "iso:country":"US",
    "sg:address":"4800 Texoma Pkwy",
    "sg:city":"Sherman",
    "sg:classifiers":[
        {
            "category":"Shopping",
            "subcategory":"Tobacco",
            "type":"Retail Goods"
        }
    ],
    "sg:phone":"+1 903 868 0273",
    "sg:postcode":"75090",
    "sg:province":"TX",
    "sg:tags":[
        "cigarette",
        "product",
        "cigar",
        "dealer"
    ],
    "wof:name":"Tobacco Isle",
    "wof:placetype":"venue"
},
  "geometry": {"coordinates":[-96.58098,33.687988],"type":"Point"}
}