{
  "type": "Feature",
  "properties": {
    "iso:country":"US",
    "sg:address":"505 Julie Rivers Dr",
    "sg:city":"Sugar Land",
    "sg:classifiers":[
        {
            "category":"Wholesale",
            "subcategory":"Machinery & Supplies",
            "type":"Manufacturing & Wholesale Goods"
        }
    ],
    "sg:phone":"+1 281 277 9299",
    "sg:postcode":"77478",
    "sg:province":"TX",
    "sg:tags":[
        "machine",
        "tool"
    ],
    "wof:name":"Butcher Carter & Preston Bcp",
    "wof:placetype":"venue"
},
  "geometry": {"coordinates":[-95.601145,29.634999],"type":"Point"}
}