{
  "type": "Feature",
  "properties": {
    "iso:country":"US",
    "sg:address":"9801 Anderson Mill Rd",
    "sg:city":"Austin",
    "sg:classifiers":[
        {
            "category":"Organizations",
            "subcategory":"Community Association",
            "type":"Services"
        }
    ],
    "sg:phone":"+1 512 219 5043",
    "sg:postcode":"78750",
    "sg:province":"TX",
    "sg:tags":[
        "educational"
    ],
    "sg:website":"www.504idea.org",
    "wof:name":"Council-Ed-Stdnts-Disabilities",
    "wof:placetype":"venue"
},
  "geometry": {"coordinates":[-97.798801,30.447004],"type":"Point"}
}