{
  "type": "Feature",
  "properties": {
    "iso:country":"US",
    "sg:address":"11650 Sunset Ranch",
    "sg:city":"San Antonio",
    "sg:classifiers":[
        {
            "category":"Arts & Performance",
            "subcategory":"Theater",
            "type":"Entertainment"
        }
    ],
    "sg:phone":"+1 210 681 6939",
    "sg:postcode":"78254",
    "sg:province":"TX",
    "sg:tags":[
        "band",
        "orchestra"
    ],
    "wof:name":"Ken Ryan & Crossover",
    "wof:placetype":"venue"
},
  "geometry": {"coordinates":[-98.722847,29.548075],"type":"Point"}
}