{
  "type": "Feature",
  "properties": {
    "iso:country":"US",
    "sg:address":"3506 Cedar Springs Rd",
    "sg:city":"Dallas",
    "sg:classifiers":[
        {
            "category":"Professional",
            "subcategory":"Lawyer & Legal Services",
            "type":"Services"
        }
    ],
    "sg:phone":"+1 214 219 0846",
    "sg:postcode":"75219",
    "sg:province":"TX",
    "wof:name":"Malouf Stephen F PC",
    "wof:placetype":"venue"
},
  "geometry": {"coordinates":[-96.805702,32.8069],"type":"Point"}
}