{
  "type": "Feature",
  "properties": {
    "iso:country":"US",
    "sg:address":"16734 Co Rd 345",
    "sg:city":"Terrell",
    "sg:classifiers":[
        {
            "category":"Building & Trades",
            "subcategory":"Construction",
            "type":"Services"
        }
    ],
    "sg:phone":"+1 972 524 4114",
    "sg:postcode":"75161",
    "sg:province":"TX",
    "sg:tags":[
        "residential"
    ],
    "wof:name":"Southwest Contracting",
    "wof:placetype":"venue"
},
  "geometry": {"coordinates":[-96.148876,32.794608],"type":"Point"}
}