{
  "type": "Feature",
  "properties": {
    "iso:country":"US",
    "sg:address":"6108 Camp Bowie Blvd",
    "sg:city":"Fort Worth",
    "sg:classifiers":[
        {
            "category":"Shopping",
            "subcategory":"Shoes",
            "type":"Retail Goods"
        }
    ],
    "sg:phone":"+1 817 989 2475",
    "sg:postcode":"76116",
    "sg:province":"TX",
    "wof:name":"Take 5 Birkenstock",
    "wof:placetype":"venue"
},
  "geometry": {"coordinates":[-97.416313,32.728433],"type":"Point"}
}