{
  "type": "Feature",
  "properties": {
    "iso:country":"US",
    "sg:address":"7849 Almeda Rd",
    "sg:city":"Houston",
    "sg:classifiers":[
        {
            "category":"Social Services",
            "subcategory":"Child Care",
            "type":"Services"
        }
    ],
    "sg:phone":"+1 713 748 2020",
    "sg:postcode":"77054",
    "sg:province":"TX",
    "sg:tags":[
        "day"
    ],
    "wof:name":"Best Care Learning Center 2",
    "wof:placetype":"venue"
},
  "geometry": {"coordinates":[-95.390198,29.6884],"type":"Point"}
}