{
  "type": "Feature",
  "properties": {
    "iso:country":"US",
    "sg:address":"703 E Leon St",
    "sg:city":"Gatesville",
    "sg:classifiers":[
        {
            "category":"Education",
            "subcategory":"Dance Studio",
            "type":"Public Place"
        }
    ],
    "sg:phone":"+1 254 699 7779",
    "sg:postcode":"76528",
    "sg:province":"TX",
    "sg:tags":[
        "instruction",
        "dancing"
    ],
    "wof:name":"Tina's Dance & Gymnastics Ctr",
    "wof:placetype":"venue"
},
  "geometry": {"coordinates":[-97.74954,31.434115],"type":"Point"}
}