{
  "type": "Feature",
  "properties": {
    "iso:country":"US",
    "sg:address":"8208 E Fm 917",
    "sg:city":"Alvarado",
    "sg:classifiers":[
        {
            "category":"Retail",
            "subcategory":"Auto Repair",
            "type":"Services"
        }
    ],
    "sg:phone":"+1 817 790 0303",
    "sg:postcode":"76009",
    "sg:province":"TX",
    "sg:tags":[
        "body",
        "shop"
    ],
    "wof:name":"Jag Custom Paint & Body Shop",
    "wof:placetype":"venue"
},
  "geometry": {"coordinates":[-97.233101,32.469799],"type":"Point"}
}