{
  "type": "Feature",
  "properties": {
    "iso:country":"US",
    "sg:address":"2576 E Grant St",
    "sg:city":"Roma",
    "sg:classifiers":[
        {
            "category":"Professional",
            "type":"Services"
        }
    ],
    "sg:phone":"+1 956 849 1043",
    "sg:postcode":"78584",
    "sg:province":"TX",
    "wof:name":"Prime Time 2",
    "wof:placetype":"venue"
},
  "geometry": {"coordinates":[-98.983834,26.406159],"type":"Point"}
}