{
  "type": "Feature",
  "properties": {
    "iso:country":"US",
    "sg:address":"1115 N Hwy 175",
    "sg:city":"Seagoville",
    "sg:classifiers":[
        {
            "category":"Home & Garden",
            "subcategory":"Building Materials",
            "type":"Retail Goods"
        }
    ],
    "sg:phone":"+1 972 913 0080",
    "sg:postcode":"75159",
    "sg:province":"TX",
    "sg:tags":[
        "door",
        "gate",
        "operating",
        "devices"
    ],
    "wof:name":"Automatic Access Doors Inc",
    "wof:placetype":"venue"
},
  "geometry": {"coordinates":[-96.55270400000001,32.652698],"type":"Point"}
}