{
  "type": "Feature",
  "properties": {
    "iso:country":"US",
    "sg:address":"6309 Goodnight Ln",
    "sg:city":"Austin",
    "sg:classifiers":[
        {
            "category":"Building & Trades",
            "subcategory":"Construction",
            "type":"Services"
        }
    ],
    "sg:phone":"+1 512 420 9942",
    "sg:postcode":"78757",
    "sg:province":"TX",
    "sg:tags":[
        "house"
    ],
    "wof:name":"H & H Quality Construction",
    "wof:placetype":"venue"
},
  "geometry": {"coordinates":[-97.733772,30.337594],"type":"Point"}
}