{
  "type": "Feature",
  "properties": {
    "iso:country":"US",
    "sg:address":"3711 W Pioneer Pkwy",
    "sg:city":"Arlington",
    "sg:classifiers":[
        {
            "category":"Personal",
            "type":"Services"
        }
    ],
    "sg:phone":"+1 817 461 3299",
    "sg:postcode":"76013",
    "sg:province":"TX",
    "wof:name":"Handy Man Can",
    "wof:placetype":"venue"
},
  "geometry": {"coordinates":[-97.16873200000001,32.715809],"type":"Point"}
}