{
  "type": "Feature",
  "properties": {
    "iso:country":"US",
    "sg:address":"521 Northcliffe Dr",
    "sg:city":"Belton",
    "sg:classifiers":[
        {
            "category":"Organizations",
            "subcategory":"Labor Organization",
            "type":"Services"
        }
    ],
    "sg:phone":"+1 254 780 1611",
    "sg:postcode":"76513",
    "sg:province":"TX",
    "wof:name":"Texas Scs Reunion",
    "wof:placetype":"venue"
},
  "geometry": {"coordinates":[-97.4746,31.119462],"type":"Point"}
}