{
  "type": "Feature",
  "properties": {
    "iso:country":"US",
    "sg:address":"3016 Hatley Dr",
    "sg:city":"Austin",
    "sg:classifiers":[
        {
            "category":"Personal",
            "type":"Services"
        }
    ],
    "sg:phone":"+1 512 474 9451",
    "sg:postcode":"78746",
    "sg:province":"TX",
    "sg:tags":[
        "therapist",
        "massage"
    ],
    "wof:name":"Personal Touch Massage Therapy",
    "wof:placetype":"venue"
},
  "geometry": {"coordinates":[-97.78797299999999,30.280265],"type":"Point"}
}