{
  "type": "Feature",
  "properties": {
    "iso:country":"US",
    "sg:address":"2331 Texas Ave",
    "sg:city":"Texas City",
    "sg:classifiers":[
        {
            "category":"Organizations",
            "subcategory":"Labor Organization",
            "type":"Services"
        }
    ],
    "sg:phone":"+1 409 945 4776",
    "sg:postcode":"77590",
    "sg:province":"TX",
    "wof:name":"Houston Area Laborers Training",
    "wof:placetype":"venue"
},
  "geometry": {"coordinates":[-94.92915000000001,29.383822],"type":"Point"}
}