{
  "type": "Feature",
  "properties": {
    "iso:country":"US",
    "sg:address":"1600 Vanderbilt Dr",
    "sg:city":"Arlington",
    "sg:classifiers":[
        {
            "category":"Shopping",
            "subcategory":"Gifts & Souvenirs",
            "type":"Retail Goods"
        }
    ],
    "sg:phone":"+1 817 293 7464",
    "sg:postcode":"76014",
    "sg:province":"TX",
    "wof:name":"Heavenly Words",
    "wof:placetype":"venue"
},
  "geometry": {"coordinates":[-97.08819800000001,32.69532],"type":"Point"}
}