{
  "type": "Feature",
  "properties": {
    "iso:country":"US",
    "sg:address":"1402 W Mayfield Rd",
    "sg:city":"Arlington",
    "sg:classifiers":[
        {
            "category":"Shopping",
            "subcategory":"Computers & Home Electronics",
            "type":"Retail Goods"
        }
    ],
    "sg:phone":"+1 817 419 2810",
    "sg:postcode":"76015",
    "sg:province":"TX",
    "sg:tags":[
        "software"
    ],
    "wof:name":"Metro Software Consultant",
    "wof:placetype":"venue"
},
  "geometry": {"coordinates":[-97.130002,32.691969],"type":"Point"}
}