{
  "type": "Feature",
  "properties": {
    "iso:country":"US",
    "sg:address":"7415 N Main St",
    "sg:city":"Houston",
    "sg:classifiers":[
        {
            "category":"Real Estate",
            "subcategory":"Real Estate Agent",
            "type":"Services"
        }
    ],
    "sg:phone":"+1 713 695 9312",
    "sg:postcode":"77022",
    "sg:province":"TX",
    "wof:name":"Inner City Interest",
    "wof:placetype":"venue"
},
  "geometry": {"coordinates":[-95.39304799999999,29.817588],"type":"Point"}
}