{
  "type": "Feature",
  "properties": {
    "iso:country":"US",
    "sg:address":"506 S Washington St",
    "sg:city":"Beeville",
    "sg:classifiers":[
        {
            "category":"Retail",
            "subcategory":"Auto Repair",
            "type":"Services"
        }
    ],
    "sg:phone":"+1 361 358 4774",
    "sg:postcode":"78102",
    "sg:province":"TX",
    "sg:tags":[
        "automotive"
    ],
    "wof:name":"B Rental",
    "wof:placetype":"venue"
},
  "geometry": {"coordinates":[-97.747045,28.39782],"type":"Point"}
}