{
  "type": "Feature",
  "properties": {
    "iso:country":"US",
    "sg:address":"6122 Chaffin St",
    "sg:city":"Houston",
    "sg:classifiers":[
        {
            "category":"Social Services",
            "subcategory":"Child Care",
            "type":"Services"
        }
    ],
    "sg:phone":"+1 713 643 6970",
    "sg:postcode":"77087",
    "sg:province":"TX",
    "sg:tags":[
        "day"
    ],
    "wof:name":"Victorian Childhood Dev",
    "wof:placetype":"venue"
},
  "geometry": {"coordinates":[-95.30286,29.675571],"type":"Point"}
}