{
  "type": "Feature",
  "properties": {
    "iso:country":"US",
    "sg:address":"15280 Addison Rd Ste 300",
    "sg:city":"Addison",
    "sg:classifiers":[
        {
            "category":"Real Estate",
            "subcategory":"Real Estate Services",
            "type":"Services"
        },
        {
            "category":"Real Estate",
            "subcategory":"Real Estate Agent",
            "type":"Services"
        }
    ],
    "sg:phone":"+1 972 934 2575",
    "sg:postcode":"75001",
    "sg:province":"TX",
    "sg:tags":[
        "buyer",
        "management",
        "broker"
    ],
    "wof:name":"Bill Kiene",
    "wof:placetype":"venue"
},
  "geometry": {"coordinates":[-96.829814,32.957161],"type":"Point"}
}