{
  "type": "Feature",
  "properties": {
    "iso:country":"US",
    "sg:address":"100 E Ridge Rd",
    "sg:city":"Mcallen",
    "sg:classifiers":[
        {
            "category":"Health Services",
            "subcategory":"Doctor",
            "type":"Services"
        }
    ],
    "sg:phone":"+1 956 682 1888",
    "sg:postcode":"78503",
    "sg:province":"TX",
    "sg:tags":[
        "physician",
        "surgeon",
        "surgeons",
        "cardiology"
    ],
    "sg:website":"http://www.riograndeheartspecialists.com",
    "wof:name":"Rio Grande Heart Specialists",
    "wof:placetype":"venue"
},
  "geometry": {"coordinates":[-98.224129,26.18593],"type":"Point"}
}