{
  "type": "Feature",
  "properties": {
    "iso:country":"US",
    "sg:address":"2810 Leisure Ln",
    "sg:city":"Carrollton",
    "sg:classifiers":[
        {
            "category":"Health Services",
            "subcategory":"Doctor",
            "type":"Services"
        }
    ],
    "sg:phone":"+1 972 416 9850",
    "sg:postcode":"75006",
    "sg:province":"TX",
    "sg:tags":[
        "medical"
    ],
    "wof:name":"Susan Ellis",
    "wof:placetype":"venue"
},
  "geometry": {"coordinates":[-96.859122,32.962731],"type":"Point"}
}