{
  "type": "Feature",
  "properties": {
    "iso:country":"US",
    "sg:address":"519 S Main St",
    "sg:city":"Temple",
    "sg:classifiers":[
        {
            "category":"Professional",
            "subcategory":"Engineering",
            "type":"Services"
        }
    ],
    "sg:phone":"+1 254 773 4470",
    "sg:postcode":"76504",
    "sg:province":"TX",
    "sg:tags":[
        "engineer"
    ],
    "wof:name":"Maxfield's Air Conditioning",
    "wof:placetype":"venue"
},
  "geometry": {"coordinates":[-97.343298,31.090845],"type":"Point"}
}