{
  "type": "Feature",
  "properties": {
    "iso:country":"US",
    "sg:address":"9901 Montana Ave",
    "sg:city":"El Paso",
    "sg:classifiers":[
        {
            "category":"Autos & Motor Vehicles",
            "subcategory":"Automobile Sales",
            "type":"Retail Goods"
        }
    ],
    "sg:phone":"+1 915 599 2334",
    "sg:postcode":"79925",
    "sg:province":"TX",
    "sg:tags":[
        "car",
        "dealer"
    ],
    "wof:name":"National Auto Sales",
    "wof:placetype":"venue"
},
  "geometry": {"coordinates":[-106.348528,31.795935],"type":"Point"}
}