{
  "type": "Feature",
  "properties": {
    "iso:country":"US",
    "sg:address":"2516 Fort Worth Ave",
    "sg:city":"Dallas",
    "sg:classifiers":[
        {
            "category":"Restaurant",
            "type":"Food & Drink"
        }
    ],
    "sg:phone":"+1 214 333 4677",
    "sg:postcode":"75211",
    "sg:province":"TX",
    "wof:name":"Sonic-Drive In",
    "wof:placetype":"venue"
},
  "geometry": {"coordinates":[-96.862801,32.759201],"type":"Point"}
}