{
  "type": "Feature",
  "properties": {
    "iso:country":"US",
    "sg:address":"8719 Grissom Rd",
    "sg:city":"San Antonio",
    "sg:classifiers":[
        {
            "category":"Retail",
            "subcategory":"Auto Repair",
            "type":"Services"
        }
    ],
    "sg:phone":"+1 210 682 2584",
    "sg:postcode":"78251",
    "sg:province":"TX",
    "sg:tags":[
        "general"
    ],
    "wof:name":"Discount Auto & Body Perf",
    "wof:placetype":"venue"
},
  "geometry": {"coordinates":[-98.65673700000001,29.479518],"type":"Point"}
}