{
  "type": "Feature",
  "properties": {
    "iso:country":"US",
    "sg:address":"7430 Westville Dr",
    "sg:city":"San Antonio",
    "sg:classifiers":[
        {
            "category":"Manufacturing",
            "subcategory":"Printing",
            "type":"Manufacturing & Wholesale Goods"
        }
    ],
    "sg:phone":"+1 210 673 0547",
    "sg:postcode":"78227",
    "sg:province":"TX",
    "sg:tags":[
        "book"
    ],
    "wof:name":"Ex Pow Stories",
    "wof:placetype":"venue"
},
  "geometry": {"coordinates":[-98.637849,29.412315],"type":"Point"}
}