{
  "type": "Feature",
  "properties": {
    "iso:country":"US",
    "sg:address":"3776 Elmora St",
    "sg:city":"Houston",
    "sg:classifiers":[
        {
            "category":"Building & Trades",
            "subcategory":"Equipment Rental",
            "type":"Services"
        }
    ],
    "sg:phone":"+1 713 666 8104",
    "sg:postcode":"77005",
    "sg:province":"TX",
    "wof:name":"Tradewinds Equipment & Leasing",
    "wof:placetype":"venue"
},
  "geometry": {"coordinates":[-95.43487500000001,29.709264],"type":"Point"}
}