{
  "type": "Feature",
  "properties": {
    "iso:country":"US",
    "sg:address":"117 H and O Ln",
    "sg:city":"Alvarado",
    "sg:classifiers":[
        {
            "category":"Building & Trades",
            "subcategory":"Construction",
            "type":"Services"
        }
    ],
    "sg:phone":"+1 817 790 6618",
    "sg:postcode":"76009",
    "sg:province":"TX",
    "wof:name":"Best Built Buildings",
    "wof:placetype":"venue"
},
  "geometry": {"coordinates":[-97.271373,32.40492],"type":"Point"}
}