{
  "type": "Feature",
  "properties": {
    "iso:country":"US",
    "sg:address":"8408 Axis Dr",
    "sg:city":"Austin",
    "sg:classifiers":[
        {
            "category":"Manufacturing",
            "subcategory":"Aerospace",
            "type":"Manufacturing & Wholesale Goods"
        }
    ],
    "sg:phone":"+1 512 474 5000",
    "sg:postcode":"78749",
    "sg:province":"TX",
    "sg:tags":[
        "aircraft",
        "transportation",
        "mfg"
    ],
    "wof:name":"Aviation Depot Inc",
    "wof:placetype":"venue"
},
  "geometry": {"coordinates":[-97.856854,30.206462],"type":"Point"}
}