{
  "type": "Feature",
  "properties": {
    "iso:country":"US",
    "sg:address":"2505 Warren Ln",
    "sg:city":"Fort Worth",
    "sg:classifiers":[
        {
            "category":"Banks & Credit Unions",
            "subcategory":"Financial Services",
            "type":"Services"
        }
    ],
    "sg:phone":"+1 817 492 8842",
    "sg:postcode":"76112",
    "sg:province":"TX",
    "sg:tags":[
        "investor"
    ],
    "wof:name":"Williams Investments Inc",
    "wof:placetype":"venue"
},
  "geometry": {"coordinates":[-97.20548100000001,32.74347],"type":"Point"}
}