{
  "type": "Feature",
  "properties": {
    "iso:country":"US",
    "sg:address":"3654 W Pioneer Pkwy",
    "sg:city":"Arlington",
    "sg:classifiers":[
        {
            "category":"Freight",
            "type":"Transportation"
        }
    ],
    "sg:phone":"+1 817 274 1259",
    "sg:postcode":"76013",
    "sg:province":"TX",
    "sg:tags":[
        "general"
    ],
    "wof:name":"Colonial Storage Center 200",
    "wof:placetype":"venue"
},
  "geometry": {"coordinates":[-97.170873,32.716893],"type":"Point"}
}