{
  "type": "Feature",
  "properties": {
    "iso:country":"US",
    "sg:address":"1404 S Washington St",
    "sg:city":"Kaufman",
    "sg:classifiers":[
        {
            "category":"Insurance",
            "subcategory":"Insurance Agent",
            "type":"Services"
        }
    ],
    "sg:phone":"+1 972 932 6653",
    "sg:postcode":"75142",
    "sg:province":"TX",
    "wof:name":"State Farm Insurance",
    "wof:placetype":"venue"
},
  "geometry": {"coordinates":[-96.309234,32.579665],"type":"Point"}
}