{
  "type": "Feature",
  "properties": {
    "iso:country":"US",
    "sg:address":"6300 Okner Ln",
    "sg:city":"Austin",
    "sg:classifiers":[
        {
            "category":"Shopping",
            "subcategory":"Music",
            "type":"Retail Goods"
        }
    ],
    "sg:phone":"+1 512 383 0016",
    "sg:postcode":"78745",
    "sg:province":"TX",
    "wof:name":"Down Boy Records",
    "wof:placetype":"venue"
},
  "geometry": {"coordinates":[-97.791065,30.203888],"type":"Point"}
}