{
  "type": "Feature",
  "properties": {
    "iso:country":"US",
    "sg:address":"804 W Hwy 90",
    "sg:city":"Dayton",
    "sg:classifiers":[
        {
            "category":"Professional",
            "subcategory":"Business Services",
            "type":"Services"
        }
    ],
    "sg:phone":"+1 936 258 2555",
    "sg:postcode":"77535",
    "sg:province":"TX",
    "wof:name":"Action Auto Group LTD",
    "wof:placetype":"venue"
},
  "geometry": {"coordinates":[-94.909088,30.03087],"type":"Point"}
}