{
  "type": "Feature",
  "properties": {
    "iso:country":"US",
    "sg:address":"11900 Gate Way",
    "sg:city":"Austin",
    "sg:classifiers":[
        {
            "category":"Health Services",
            "subcategory":"Doctor",
            "type":"Services"
        }
    ],
    "sg:phone":"+1 512 346 8353",
    "sg:postcode":"78727",
    "sg:province":"TX",
    "sg:tags":[
        "physician",
        "surgeon"
    ],
    "wof:name":"Magic By Dr Giggles",
    "wof:placetype":"venue"
},
  "geometry": {"coordinates":[-97.739048,30.416457],"type":"Point"}
}