{
  "type": "Feature",
  "properties": {
    "iso:country":"US",
    "sg:address":"12601 Bissonnet St",
    "sg:city":"Houston",
    "sg:classifiers":[
        {
            "category":"Autos & Motor Vehicles",
            "subcategory":"Auto Supplies",
            "type":"Retail Goods"
        }
    ],
    "sg:phone":"+1 281 568 6647",
    "sg:postcode":"77099",
    "sg:province":"TX",
    "sg:tags":[
        "tire"
    ],
    "wof:name":"Firestone",
    "wof:placetype":"venue"
},
  "geometry": {"coordinates":[-95.600284,29.677353],"type":"Point"}
}