{
  "type": "Feature",
  "properties": {
    "iso:country":"US",
    "sg:address":"2545 Rutgers Dr",
    "sg:city":"Irving",
    "sg:classifiers":[
        {
            "category":"Shopping",
            "subcategory":"Hobbies, Toys, & Games",
            "type":"Retail Goods"
        }
    ],
    "sg:phone":"+1 972 255 8066",
    "sg:postcode":"75062",
    "sg:province":"TX",
    "wof:name":"C&B Enterprises",
    "wof:placetype":"venue"
},
  "geometry": {"coordinates":[-96.981392,32.843749],"type":"Point"}
}