{
  "type": "Feature",
  "properties": {
    "iso:country":"US",
    "sg:address":"2109 Arbor Creek Dr",
    "sg:city":"Carrollton",
    "sg:classifiers":[
        {
            "category":"Education",
            "subcategory":"School",
            "type":"Public Place"
        }
    ],
    "sg:phone":"+1 469 713 5971",
    "sg:postcode":"75010",
    "sg:province":"TX",
    "sg:tags":[
        "high",
        "middle",
        "elementary"
    ],
    "sg:website":"www.lisd.net",
    "wof:name":"Lewisville Independent School District",
    "wof:placetype":"venue"
},
  "geometry": {"coordinates":[-96.874179,33.393121],"type":"Point"}
}