{
  "type": "Feature",
  "properties": {
    "iso:country":"US",
    "sg:address":"204 N Morningside Ave",
    "sg:city":"Denver City",
    "sg:classifiers":[
        {
            "category":"Shopping",
            "subcategory":"Clothing, Apparel, & Fashions",
            "type":"Retail Goods"
        }
    ],
    "sg:phone":"+1 806 592 4511",
    "sg:postcode":"79323",
    "sg:province":"TX",
    "wof:name":"Sisters n Friends",
    "wof:placetype":"venue"
},
  "geometry": {"coordinates":[-102.82378300000001,32.9663],"type":"Point"}
}