{
  "type": "Feature",
  "properties": {
    "iso:country":"US",
    "sg:address":"307 Euclid Ave",
    "sg:city":"Panhandle",
    "sg:classifiers":[
        {
            "category":"Shopping",
            "type":"Retail Goods"
        }
    ],
    "sg:phone":"+1 806 537 3655",
    "sg:postcode":"79068",
    "sg:province":"TX",
    "sg:tags":[
        "wedding",
        "supply"
    ],
    "wof:name":"Kathy's",
    "wof:placetype":"venue"
},
  "geometry": {"coordinates":[-101.381274,35.344061],"type":"Point"}
}