{
  "type": "Feature",
  "properties": {
    "iso:country":"US",
    "sg:address":"2112 Reagan Blvd",
    "sg:city":"Carrollton",
    "sg:classifiers":[
        {
            "category":"Building & Trades",
            "subcategory":"Plumbing",
            "type":"Services"
        }
    ],
    "sg:phone":"+1 972 418 7049",
    "sg:postcode":"75006",
    "sg:province":"TX",
    "sg:tags":[
        "contractor"
    ],
    "wof:name":"Stewart Air Conditioning",
    "wof:placetype":"venue"
},
  "geometry": {"coordinates":[-96.884516,32.950804],"type":"Point"}
}