{
  "type": "Feature",
  "properties": {
    "iso:country":"US",
    "sg:address":"2605 Greenlawn Pkwy",
    "sg:city":"Austin",
    "sg:classifiers":[
        {
            "category":"Real Estate",
            "subcategory":"Real Estate Agent",
            "type":"Services"
        }
    ],
    "sg:phone":"+1 512 459 4759",
    "sg:postcode":"78757",
    "sg:province":"TX",
    "sg:tags":[
        "business"
    ],
    "wof:name":"Warren Morrow & Associates",
    "wof:placetype":"venue"
},
  "geometry": {"coordinates":[-97.73948799999999,30.349985],"type":"Point"}
}