{
  "type": "Feature",
  "properties": {
    "iso:country":"US",
    "sg:address":"4769 Eastpark Dr",
    "sg:city":"Houston",
    "sg:classifiers":[
        {
            "category":"Home & Garden",
            "subcategory":"Furniture",
            "type":"Retail Goods"
        }
    ],
    "sg:phone":"+1 713 670 0442",
    "sg:postcode":"77028",
    "sg:province":"TX",
    "wof:name":"Famsa Inc",
    "wof:placetype":"venue"
},
  "geometry": {"coordinates":[-95.299189,29.801693],"type":"Point"}
}