{
  "type": "Feature",
  "properties": {
    "iso:country":"US",
    "sg:address":"2801 Swiss Ave",
    "sg:city":"Dallas",
    "sg:classifiers":[
        {
            "category":"Organizations",
            "subcategory":"Non-profit Organization",
            "type":"Services"
        }
    ],
    "sg:phone":"+1 214 942 6698",
    "sg:postcode":"75204",
    "sg:province":"TX",
    "sg:tags":[
        "service/non-profit",
        "community"
    ],
    "wof:name":"Plan Fund",
    "wof:placetype":"venue"
},
  "geometry": {"coordinates":[-96.786585,32.788572],"type":"Point"}
}