{
  "type": "Feature",
  "properties": {
    "iso:country":"US",
    "sg:address":"7940 Forest Ln",
    "sg:city":"Dallas",
    "sg:classifiers":[
        {
            "category":"Restaurant",
            "type":"Food & Drink"
        }
    ],
    "sg:phone":"+1 214 692 6404",
    "sg:postcode":"75230",
    "sg:province":"TX",
    "wof:name":"Taco Bueno",
    "wof:placetype":"venue"
},
  "geometry": {"coordinates":[-96.7715,32.9091],"type":"Point"}
}