{
  "type": "Feature",
  "properties": {
    "iso:country":"US",
    "sg:address":"142 Fay Ave",
    "sg:city":"San Antonio",
    "sg:classifiers":[
        {
            "category":"Professional",
            "subcategory":"Business Services",
            "type":"Services"
        }
    ],
    "sg:phone":"+1 210 927 3292",
    "sg:postcode":"78211",
    "sg:province":"TX",
    "wof:name":"Top End Performance X-Treme",
    "wof:placetype":"venue"
},
  "geometry": {"coordinates":[-98.541042,29.369607],"type":"Point"}
}