{
  "type": "Feature",
  "properties": {
    "iso:country":"US",
    "sg:address":"4701 West Gate Blvd",
    "sg:city":"Austin",
    "sg:classifiers":[
        {
            "category":"Education",
            "subcategory":"Special Training",
            "type":"Public Place"
        },
        {
            "category":"Education",
            "subcategory":"School",
            "type":"Public Place"
        }
    ],
    "sg:phone":"+1 512 467 0800",
    "sg:postcode":"78745",
    "sg:province":"TX",
    "sg:tags":[
        "tutoring"
    ],
    "wof:name":"C 2 Education",
    "wof:placetype":"venue"
},
  "geometry": {"coordinates":[-97.80109400000001,30.229065],"type":"Point"}
}