{
  "type": "Feature",
  "properties": {
    "iso:country":"US",
    "sg:address":"408 N Main St",
    "sg:city":"Duncanville",
    "sg:classifiers":[
        {
            "category":"Shopping",
            "subcategory":"Stationery & Office Supplies",
            "type":"Retail Goods"
        }
    ],
    "sg:phone":"+1 972 298 1656",
    "sg:postcode":"75116",
    "sg:province":"TX",
    "wof:name":"Accent Office Supply",
    "wof:placetype":"venue"
},
  "geometry": {"coordinates":[-96.90746799999999,32.657276],"type":"Point"}
}