{
  "type": "Feature",
  "properties": {
    "iso:country":"US",
    "sg:address":"1501 N Grandview Ave",
    "sg:city":"Odessa",
    "sg:classifiers":[
        {
            "category":"Organizations",
            "subcategory":"Religious Organization",
            "type":"Services"
        }
    ],
    "sg:phone":"+1 432 550 5111",
    "sg:postcode":"79761",
    "sg:province":"TX",
    "sg:tags":[
        "synagogue"
    ],
    "wof:name":"Temple Beth-El",
    "wof:placetype":"venue"
},
  "geometry": {"coordinates":[-102.345512,31.868868],"type":"Point"}
}