{
  "type": "Feature",
  "properties": {
    "iso:country":"US",
    "sg:address":"10001 Westheimer Rd",
    "sg:city":"Houston",
    "sg:classifiers":[
        {
            "category":"Food & Beverages",
            "subcategory":"Liquor & Beverages",
            "type":"Retail Goods"
        },
        {
            "category":"Bars & Pubs",
            "subcategory":"Wine Bar",
            "type":"Food & Drink"
        },
        {
            "category":"Wholesale",
            "subcategory":"Wine & Distilled Alcoholic Beverages",
            "type":"Manufacturing & Wholesale Goods"
        }
    ],
    "sg:phone":"+1 713 532 9463",
    "sg:postcode":"77042",
    "sg:province":"TX",
    "sg:tags":[
        "broker"
    ],
    "sg:website":"www.vintropolisbar.com",
    "wof:name":"Vintropolis",
    "wof:placetype":"venue"
},
  "geometry": {"coordinates":[-95.549379,29.736956],"type":"Point"}
}