{
  "type": "Feature",
  "properties": {
    "iso:country":"US",
    "sg:address":"11334 Gemini Ln",
    "sg:city":"Dallas",
    "sg:classifiers":[
        {
            "category":"Manufacturing",
            "subcategory":"Wood Products",
            "type":"Manufacturing & Wholesale Goods"
        }
    ],
    "sg:phone":"+1 972 280 0636",
    "sg:postcode":"75229",
    "sg:province":"TX",
    "sg:tags":[
        "picture",
        "frame"
    ],
    "wof:name":"Gallary Warehouse",
    "wof:placetype":"venue"
},
  "geometry": {"coordinates":[-96.884187,32.89207],"type":"Point"}
}