{
  "type": "Feature",
  "properties": {
    "iso:country":"US",
    "sg:address":"3300 Rollingbrook St",
    "sg:city":"Baytown",
    "sg:classifiers":[
        {
            "category":"Real Estate",
            "subcategory":"Real Estate Operator",
            "type":"Services"
        }
    ],
    "sg:phone":"+1 281 428 1385",
    "sg:postcode":"77521",
    "sg:province":"TX",
    "sg:tags":[
        "apartment",
        "complex"
    ],
    "wof:name":"Raintree Apartments",
    "wof:placetype":"venue"
},
  "geometry": {"coordinates":[-94.991922,29.759148],"type":"Point"}
}