{
  "type": "Feature",
  "properties": {
    "iso:country":"US",
    "sg:address":"212 N Crowdus St",
    "sg:city":"Dallas",
    "sg:classifiers":[
        {
            "category":"Restaurant",
            "type":"Food & Drink"
        }
    ],
    "sg:phone":"+1 214 744 6842",
    "sg:postcode":"75226",
    "sg:province":"TX",
    "wof:name":"Omega's Cafe",
    "wof:placetype":"venue"
},
  "geometry": {"coordinates":[-96.783665,32.784998],"type":"Point"}
}