{
  "type": "Feature",
  "properties": {
    "iso:country":"US",
    "sg:address":"2802 Hamilton Blvd",
    "sg:city":"Wichita Falls",
    "sg:classifiers":[
        {
            "category":"Shopping",
            "type":"Retail Goods"
        }
    ],
    "sg:phone":"+1 940 767 4196",
    "sg:postcode":"76308",
    "sg:province":"TX",
    "sg:tags":[
        "merchandise"
    ],
    "wof:name":"Anodyne Med Prod LLC",
    "wof:placetype":"venue"
},
  "geometry": {"coordinates":[-98.507535,33.883357],"type":"Point"}
}