{
  "type": "Feature",
  "properties": {
    "iso:country":"US",
    "sg:address":"5955 Phelan Blvd",
    "sg:city":"Beaumont",
    "sg:classifiers":[
        {
            "category":"Home & Garden",
            "subcategory":"Carpets & Floor Coverings",
            "type":"Retail Goods"
        },
        {
            "category":"Building & Trades",
            "subcategory":"Construction",
            "type":"Services"
        }
    ],
    "sg:phone":"+1 409 892 7650",
    "sg:postcode":"77706",
    "sg:province":"TX",
    "sg:tags":[
        "tile",
        "dealer"
    ],
    "wof:name":"J & W Flooring",
    "wof:placetype":"venue"
},
  "geometry": {"coordinates":[-94.16419999999999,30.079778],"type":"Point"}
}