{
  "type": "Feature",
  "properties": {
    "iso:country":"US",
    "sg:address":"3144 Bee Caves Rd",
    "sg:city":"Austin",
    "sg:classifiers":[
        {
            "category":"Health Services",
            "subcategory":"Doctor",
            "type":"Services"
        }
    ],
    "sg:phone":"+1 512 328 2010",
    "sg:postcode":"78746",
    "sg:province":"TX",
    "sg:tags":[
        "medical"
    ],
    "wof:name":"J William Lavalley",
    "wof:placetype":"venue"
},
  "geometry": {"coordinates":[-97.798323,30.273065],"type":"Point"}
}