{
  "type": "Feature",
  "properties": {
    "iso:country":"US",
    "sg:address":"3330 Audley St Ste 110",
    "sg:city":"Houston",
    "sg:classifiers":[
        {
            "category":"Personal",
            "subcategory":"Massage",
            "type":"Services"
        },
        {
            "category":"Personal",
            "subcategory":"Beauty Salon",
            "type":"Services"
        },
        {
            "category":"Personal",
            "subcategory":"Day Spa",
            "type":"Services"
        }
    ],
    "sg:phone":"+1 713 874 1387",
    "sg:postcode":"77098",
    "sg:province":"TX",
    "sg:tags":[
        "therapist"
    ],
    "wof:name":"Greenway Therapeutic Massage",
    "wof:placetype":"venue"
},
  "geometry": {"coordinates":[-95.426288,29.735355],"type":"Point"}
}