{
  "type": "Feature",
  "properties": {
    "iso:country":"US",
    "sg:address":"1765 N Mockingbird Ln",
    "sg:city":"Midlothian",
    "sg:classifiers":[
        {
            "category":"Retail",
            "subcategory":"Animal Services",
            "type":"Services"
        }
    ],
    "sg:phone":"+1 214 435 0803",
    "sg:postcode":"76065",
    "sg:province":"TX",
    "sg:tags":[
        "horse",
        "breeding"
    ],
    "wof:name":"Star Canyon Ranch",
    "wof:placetype":"venue"
},
  "geometry": {"coordinates":[-96.925302,32.502789],"type":"Point"}
}