{
  "type": "Feature",
  "properties": {
    "iso:country":"US",
    "sg:address":"103 Spring Groves Dr",
    "sg:city":"Liberty Hill",
    "sg:classifiers":[
        {
            "category":"Health Services",
            "subcategory":"Clinic",
            "type":"Services"
        }
    ],
    "sg:phone":"+1 254 793 2566",
    "sg:postcode":"78642",
    "sg:province":"TX",
    "sg:tags":[
        "home"
    ],
    "wof:name":"Heavens Helpers",
    "wof:placetype":"venue"
},
  "geometry": {"coordinates":[-97.880464,30.738851],"type":"Point"}
}