{
  "type": "Feature",
  "properties": {
    "iso:country":"US",
    "sg:address":"905 W Division St",
    "sg:city":"Orange",
    "sg:classifiers":[
        {
            "category":"Museum",
            "type":"Entertainment"
        }
    ],
    "sg:phone":"+1 409 886 5385",
    "sg:postcode":"77630",
    "sg:province":"TX",
    "sg:tags":[
        "gallery"
    ],
    "wof:name":"Heritage History Museum",
    "wof:placetype":"venue"
},
  "geometry": {"coordinates":[-93.73779399999999,30.090027],"type":"Point"}
}