{
  "type": "Feature",
  "properties": {
    "iso:country":"US",
    "sg:address":"4526 Burnet Rd",
    "sg:city":"Austin",
    "sg:classifiers":[
        {
            "category":"Real Estate",
            "subcategory":"Architect",
            "type":"Services"
        }
    ],
    "sg:phone":"+1 512 452 7961",
    "sg:postcode":"78756",
    "sg:province":"TX",
    "wof:name":"Studio Momentum Architects",
    "wof:placetype":"venue"
},
  "geometry": {"coordinates":[-97.741018,30.316386],"type":"Point"}
}