{
  "type": "Feature",
  "properties": {
    "iso:country":"US",
    "sg:address":"1108 Albrad St",
    "sg:city":"Pharr",
    "sg:classifiers":[
        {
            "category":"Wholesale",
            "subcategory":"Machinery & Supplies",
            "type":"Manufacturing & Wholesale Goods"
        }
    ],
    "sg:phone":"+1 956 702 1116",
    "sg:postcode":"78577",
    "sg:province":"TX",
    "sg:tags":[
        "bulk",
        "equipment",
        "industrial",
        "gas"
    ],
    "wof:name":"Matheson Tri-Gas Inc",
    "wof:placetype":"venue"
},
  "geometry": {"coordinates":[-98.19816299999999,26.207862],"type":"Point"}
}