{
  "type": "Feature",
  "properties": {
    "iso:country":"US",
    "sg:address":"2000 S Commercial Ave",
    "sg:city":"Coleman",
    "sg:classifiers":[
        {
            "category":"Restaurant",
            "type":"Food & Drink"
        },
        {
            "category":"Ice Cream",
            "type":"Food & Drink"
        }
    ],
    "sg:menulink":"http://www.allmenus.com/tx/coleman/162154-dairy-queen/menu/",
    "sg:phone":"+1 325 625 4266",
    "sg:postcode":"76834",
    "sg:province":"TX",
    "sg:tags":[
        "burger",
        "american",
        "ice",
        "cream"
    ],
    "wof:name":"Dairy Queen",
    "wof:placetype":"venue"
},
  "geometry": {"coordinates":[-99.423029,31.814617],"type":"Point"}
}