{
  "type": "Feature",
  "properties": {
    "iso:country":"US",
    "sg:address":"9020 N Capital of Texas Hwy",
    "sg:city":"Austin",
    "sg:classifiers":[
        {
            "category":"Professional",
            "subcategory":"Lawyer & Legal Services",
            "type":"Services"
        }
    ],
    "sg:phone":"+1 512 338 8800",
    "sg:postcode":"78759",
    "sg:province":"TX",
    "wof:name":"Knisely Prehoditch & Panzer PC",
    "wof:placetype":"venue"
},
  "geometry": {"coordinates":[-97.757048,30.388387],"type":"Point"}
}