{
  "type": "Feature",
  "properties": {
    "iso:country":"US",
    "sg:address":"9510 Windfern Rd",
    "sg:city":"Houston",
    "sg:classifiers":[
        {
            "category":"Recreation",
            "type":"Entertainment"
        },
        {
            "category":"Retail",
            "subcategory":"Animal Services",
            "type":"Services"
        }
    ],
    "sg:phone":"+1 713 937 3538",
    "sg:postcode":"77064",
    "sg:province":"TX",
    "sg:tags":[
        "horse",
        "training",
        "stable"
    ],
    "wof:name":"Irish Day Farm Inc",
    "wof:placetype":"venue"
},
  "geometry": {"coordinates":[-95.538465,29.912087],"type":"Point"}
}