{
  "type": "Feature",
  "properties": {
    "iso:country":"US",
    "sg:address":"9938 W Bradley Dr",
    "sg:city":"Odessa",
    "sg:classifiers":[
        {
            "category":"Manufacturing",
            "subcategory":"Jewelry",
            "type":"Manufacturing & Wholesale Goods"
        }
    ],
    "sg:phone":"+1 432 530 1006",
    "sg:postcode":"79764",
    "sg:province":"TX",
    "sg:tags":[
        "material",
        "mfg"
    ],
    "wof:name":"Rock-N-Jewel",
    "wof:placetype":"venue"
},
  "geometry": {"coordinates":[-102.491332,31.845292],"type":"Point"}
}