{
  "type": "Feature",
  "properties": {
    "iso:country":"US",
    "sg:address":"712 S Main St",
    "sg:city":"Cotulla",
    "sg:classifiers":[
        {
            "category":"Social Services",
            "subcategory":"Child Care",
            "type":"Services"
        }
    ],
    "sg:phone":"+1 830 879 3537",
    "sg:postcode":"78014",
    "sg:province":"TX",
    "wof:name":"Tiny Tots",
    "wof:placetype":"venue"
},
  "geometry": {"coordinates":[-99.23723200000001,28.42905],"type":"Point"}
}