{
  "type": "Feature",
  "properties": {
    "iso:country":"US",
    "sg:address":"1319 Industrial Dr W",
    "sg:city":"Sulphur Springs",
    "sg:classifiers":[
        {
            "category":"Retail",
            "subcategory":"Auto Repair",
            "type":"Services"
        }
    ],
    "sg:phone":"+1 903 438 1300",
    "sg:postcode":"75482",
    "sg:province":"TX",
    "sg:tags":[
        "general"
    ],
    "wof:name":"Accurate Car Care",
    "wof:placetype":"venue"
},
  "geometry": {"coordinates":[-95.626893,33.118913],"type":"Point"}
}