{
  "type": "Feature",
  "properties": {
    "iso:country":"US",
    "sg:address":"4828 Racell St",
    "sg:city":"Dallas",
    "sg:classifiers":[
        {
            "category":"Manufacturing",
            "subcategory":"Furniture",
            "type":"Manufacturing & Wholesale Goods"
        }
    ],
    "sg:phone":"+1 214 428 3131",
    "sg:postcode":"75210",
    "sg:province":"TX",
    "sg:tags":[
        "wood",
        "material",
        "mfg"
    ],
    "wof:name":"Stone Resources Ltd",
    "wof:placetype":"venue"
},
  "geometry": {"coordinates":[-96.740943,32.765701],"type":"Point"}
}