{
  "type": "Feature",
  "properties": {
    "iso:country":"US",
    "sg:address":"2653 E Davis St",
    "sg:city":"Conroe",
    "sg:classifiers":[
        {
            "category":"Shopping",
            "subcategory":"Used Merchandise",
            "type":"Retail Goods"
        }
    ],
    "sg:phone":"+1 936 788 5357",
    "sg:postcode":"77301",
    "sg:province":"TX",
    "sg:tags":[
        "shop",
        "consignment"
    ],
    "wof:name":"Dealin' Dallas",
    "wof:placetype":"venue"
},
  "geometry": {"coordinates":[-95.415384,30.320717],"type":"Point"}
}