{
  "type": "Feature",
  "properties": {
    "iso:country":"US",
    "sg:address":"6115 Clarewood Dr",
    "sg:city":"Houston",
    "sg:classifiers":[
        {
            "category":"Retail",
            "subcategory":"Auto Repair",
            "type":"Services"
        },
        {
            "category":"Wholesale",
            "subcategory":"Auto Parts",
            "type":"Manufacturing & Wholesale Goods"
        }
    ],
    "sg:phone":"+1 713 773 0887",
    "sg:postcode":"77081",
    "sg:province":"TX",
    "sg:tags":[
        "repairing",
        "automobile"
    ],
    "wof:name":"F & J European Car Parts Inc",
    "wof:placetype":"venue"
},
  "geometry": {"coordinates":[-95.49028199999999,29.709042],"type":"Point"}
}