{
  "type": "Feature",
  "properties": {
    "iso:country":"US",
    "sg:address":"114 Virginia St",
    "sg:city":"Pasadena",
    "sg:classifiers":[
        {
            "category":"Building & Trades",
            "subcategory":"Construction",
            "type":"Services"
        }
    ],
    "sg:phone":"+1 713 943 3070",
    "sg:postcode":"77587",
    "sg:province":"TX",
    "sg:tags":[
        "roofing",
        "contractor"
    ],
    "wof:name":"Flore's Roofing",
    "wof:placetype":"venue"
},
  "geometry": {"coordinates":[-95.233779,29.668169],"type":"Point"}
}