{
  "type": "Feature",
  "properties": {
    "iso:country":"US",
    "sg:address":"504 Hemlock Dr",
    "sg:city":"Arlington",
    "sg:classifiers":[
        {
            "category":"Professional",
            "subcategory":"Business Services",
            "type":"Services"
        }
    ],
    "sg:phone":"+1 817 468 0657",
    "sg:postcode":"76018",
    "sg:province":"TX",
    "wof:name":"Clear & Pure Health Solutions",
    "wof:placetype":"venue"
},
  "geometry": {"coordinates":[-97.106617,32.656335],"type":"Point"}
}