{
  "type": "Feature",
  "properties": {
    "iso:country":"US",
    "sg:address":"510 San Jacinto Blvd",
    "sg:city":"Austin",
    "sg:classifiers":[
        {
            "category":"Banks & Credit Unions",
            "subcategory":"Bank",
            "type":"Services"
        }
    ],
    "sg:phone":"+1 512 476 6412",
    "sg:postcode":"78701",
    "sg:province":"TX",
    "sg:tags":[
        "personal",
        "institution"
    ],
    "wof:name":"World Acceptance Corporation",
    "wof:placetype":"venue"
},
  "geometry": {"coordinates":[-97.740478,30.267319],"type":"Point"}
}