{
  "type": "Feature",
  "properties": {
    "iso:country":"US",
    "sg:address":"6010 Hansford Ln",
    "sg:city":"Sugar Land",
    "sg:classifiers":[
        {
            "category":"Professional",
            "subcategory":"Business Services",
            "type":"Services"
        }
    ],
    "sg:phone":"+1 281 565 1920",
    "sg:postcode":"77479",
    "sg:province":"TX",
    "wof:name":"Turner Ewing Enterprises",
    "wof:placetype":"venue"
},
  "geometry": {"coordinates":[-95.669934,29.601955],"type":"Point"}
}