{
  "type": "Feature",
  "properties": {
    "iso:country":"US",
    "sg:address":"1615 Rutland St",
    "sg:city":"Houston",
    "sg:classifiers":[
        {
            "category":"Education",
            "subcategory":"School",
            "type":"Public Place"
        }
    ],
    "sg:phone":"+1 713 867 5220",
    "sg:postcode":"77008",
    "sg:province":"TX",
    "sg:tags":[
        "high",
        "middle",
        "elementary"
    ],
    "wof:name":"Houston Independent School District",
    "wof:placetype":"venue"
},
  "geometry": {"coordinates":[-95.4015,29.799993],"type":"Point"}
}