{
  "type": "Feature",
  "properties": {
    "iso:country":"US",
    "sg:address":"17430 W Little York Rd",
    "sg:city":"Houston",
    "sg:classifiers":[
        {
            "category":"Manufacturing",
            "subcategory":"Building Materials",
            "type":"Manufacturing & Wholesale Goods"
        }
    ],
    "sg:phone":"+1 281 858 9452",
    "sg:postcode":"77084",
    "sg:province":"TX",
    "sg:tags":[
        "shutter"
    ],
    "wof:name":"Winstar Shutters",
    "wof:placetype":"venue"
},
  "geometry": {"coordinates":[-95.674266,29.865465],"type":"Point"}
}