{
  "type": "Feature",
  "properties": {
    "iso:country":"US",
    "sg:address":"555 Manco Rd",
    "sg:city":"Lewisville",
    "sg:classifiers":[
        {
            "category":"Health Services",
            "subcategory":"Doctor",
            "type":"Services"
        }
    ],
    "sg:phone":"+1 972 434 9494",
    "sg:postcode":"75067",
    "sg:province":"TX",
    "sg:tags":[
        "dentist"
    ],
    "wof:name":"Lewisville Dental Ctr",
    "wof:placetype":"venue"
},
  "geometry": {"coordinates":[-97.015191,33.043132],"type":"Point"}
}