{
  "type": "Feature",
  "properties": {
    "iso:country":"US",
    "sg:address":"525 Post Oak Dr",
    "sg:city":"Newark",
    "sg:classifiers":[
        {
            "category":"Real Estate",
            "subcategory":"Real Estate Agent",
            "type":"Services"
        }
    ],
    "sg:phone":"+1 817 489 1810",
    "sg:postcode":"76071",
    "sg:province":"TX",
    "wof:name":"Capital Home Management S J",
    "wof:placetype":"venue"
},
  "geometry": {"coordinates":[-97.48600999999999,33.013193],"type":"Point"}
}