{
  "type": "Feature",
  "properties": {
    "iso:country":"US",
    "sg:address":"5411 W Lovers Ln",
    "sg:city":"Dallas",
    "sg:classifiers":[
        {
            "category":"Utilities",
            "subcategory":"Mobile Phone",
            "type":"Services"
        }
    ],
    "sg:phone":"+1 214 357 7174",
    "sg:postcode":"75209",
    "sg:province":"TX",
    "sg:tags":[
        "communication",
        "radiotelephone",
        "merchandise"
    ],
    "wof:name":"Verizon",
    "wof:placetype":"venue"
},
  "geometry": {"coordinates":[-96.82037,32.851251],"type":"Point"}
}