{
  "type": "Feature",
  "properties": {
    "iso:country":"US",
    "sg:address":"145 Duncan Dr",
    "sg:city":"San Antonio",
    "sg:classifiers":[
        {
            "category":"Government",
            "subcategory":"Office",
            "type":"Public Place"
        }
    ],
    "sg:phone":"+1 210 340 2885",
    "sg:postcode":"78226",
    "sg:province":"TX",
    "wof:name":"Senator Kay Bailey Hutchison",
    "wof:placetype":"venue"
},
  "geometry": {"coordinates":[-98.561145,29.38197],"type":"Point"}
}