{
  "type": "Feature",
  "properties": {
    "iso:country":"US",
    "sg:address":"4000 Dunning Ln",
    "sg:city":"Austin",
    "sg:classifiers":[
        {
            "category":"Professional",
            "subcategory":"Business Services",
            "type":"Services"
        }
    ],
    "sg:phone":"+1 512 328 4553",
    "sg:postcode":"78746",
    "sg:province":"TX",
    "wof:name":"Meredith Holden",
    "wof:placetype":"venue"
},
  "geometry": {"coordinates":[-97.783557,30.312431],"type":"Point"}
}