{
  "type": "Feature",
  "properties": {
    "iso:country":"US",
    "sg:address":"109 Dickens Dr",
    "sg:city":"Coppell",
    "sg:classifiers":[
        {
            "category":"Shopping",
            "type":"Retail Goods"
        }
    ],
    "sg:phone":"+1 972 489 7171",
    "sg:postcode":"75019",
    "sg:province":"TX",
    "sg:tags":[
        "merchandise"
    ],
    "wof:name":"John A Heath",
    "wof:placetype":"venue"
},
  "geometry": {"coordinates":[-96.99071499999999,32.970183],"type":"Point"}
}