{
  "type": "Feature",
  "properties": {
    "iso:country":"US",
    "sg:address":"1423 Cook",
    "sg:city":"Odem",
    "sg:classifiers":[
        {
            "category":"Building & Trades",
            "subcategory":"Equipment Rental",
            "type":"Services"
        }
    ],
    "sg:phone":"+1 361 368 7330",
    "sg:postcode":"78370",
    "sg:province":"TX",
    "sg:tags":[
        "yard",
        "leasing",
        "store"
    ],
    "wof:name":"Little Bitz Party Rentals",
    "wof:placetype":"venue"
},
  "geometry": {"coordinates":[-97.593082,27.942952],"type":"Point"}
}