{
  "type": "Feature",
  "properties": {
    "iso:country":"US",
    "sg:address":"3335 Calder Ave",
    "sg:city":"Beaumont",
    "sg:classifiers":[
        {
            "category":"Health Services",
            "subcategory":"Doctor",
            "type":"Services"
        }
    ],
    "sg:phone":"+1 409 832 1366",
    "sg:postcode":"77706",
    "sg:province":"TX",
    "wof:name":"Bitar K C",
    "wof:placetype":"venue"
},
  "geometry": {"coordinates":[-94.137162,30.085409],"type":"Point"}
}