{
  "type": "Feature",
  "properties": {
    "iso:country":"US",
    "sg:address":"2702 McCullough Ave",
    "sg:city":"San Antonio",
    "sg:classifiers":[
        {
            "category":"Health Services",
            "subcategory":"Health Practitioner",
            "type":"Services"
        }
    ],
    "sg:phone":"+1 210 735 6231",
    "sg:postcode":"78212",
    "sg:province":"TX",
    "sg:tags":[
        "psychologist"
    ],
    "wof:name":"Arthur G Bouton PHD",
    "wof:placetype":"venue"
},
  "geometry": {"coordinates":[-98.49173,29.455157],"type":"Point"}
}