{
  "type": "Feature",
  "properties": {
    "iso:country":"US",
    "sg:address":"412 Pecan St",
    "sg:city":"Leonard",
    "sg:classifiers":[
        {
            "category":"Real Estate",
            "subcategory":"Real Estate Operator",
            "type":"Services"
        }
    ],
    "sg:phone":"+1 903 587 3461",
    "sg:postcode":"75452",
    "sg:province":"TX",
    "sg:tags":[
        "building",
        "apartment"
    ],
    "wof:name":"Village Apartments",
    "wof:placetype":"venue"
},
  "geometry": {"coordinates":[-96.24003,33.382667],"type":"Point"}
}