{
  "type": "Feature",
  "properties": {
    "iso:country":"US",
    "sg:address":"1903 White Rose Ln",
    "sg:city":"Carrollton",
    "sg:classifiers":[
        {
            "category":"Local Transit",
            "type":"Transportation"
        }
    ],
    "sg:phone":"+1 972 492 7203",
    "sg:postcode":"75007",
    "sg:province":"TX",
    "wof:name":"Saqras Shuttle",
    "wof:placetype":"venue"
},
  "geometry": {"coordinates":[-96.882868,33.009904],"type":"Point"}
}