{
  "type": "Feature",
  "properties": {
    "iso:country":"US",
    "sg:address":"3708 Hidden Hollow",
    "sg:city":"Austin",
    "sg:classifiers":[
        {
            "category":"Professional",
            "type":"Services"
        }
    ],
    "sg:phone":"+1 512 345 7563",
    "sg:postcode":"78731",
    "sg:province":"TX",
    "wof:name":"Gary B Burnett",
    "wof:placetype":"venue"
},
  "geometry": {"coordinates":[-97.756518,30.362654],"type":"Point"}
}