{
  "type": "Feature",
  "properties": {
    "iso:country":"US",
    "sg:address":"14035 Main St",
    "sg:city":"Houston",
    "sg:classifiers":[
        {
            "category":"Home & Garden",
            "subcategory":"Furniture",
            "type":"Retail Goods"
        }
    ],
    "sg:phone":"+1 713 721 0555",
    "sg:postcode":"77035",
    "sg:province":"TX",
    "sg:tags":[
        "store"
    ],
    "wof:name":"Lee Blum Furniture & Clearance Center",
    "wof:placetype":"venue"
},
  "geometry": {"coordinates":[-95.490196,29.637199],"type":"Point"}
}