{
  "type": "Feature",
  "properties": {
    "iso:country":"US",
    "sg:address":"2603 Boston Ave",
    "sg:city":"Lubbock",
    "sg:classifiers":[
        {
            "category":"Social Services",
            "type":"Services"
        }
    ],
    "sg:phone":"+1 806 762 5981",
    "sg:postcode":"79410",
    "sg:province":"TX",
    "sg:tags":[
        "counseling"
    ],
    "wof:name":"David W Allison",
    "wof:placetype":"venue"
},
  "geometry": {"coordinates":[-101.875094,33.569643],"type":"Point"}
}