{
  "type": "Feature",
  "properties": {
    "iso:country":"US",
    "sg:address":"1310 S Treadaway Blvd",
    "sg:city":"Abilene",
    "sg:classifiers":[
        {
            "category":"Retail",
            "subcategory":"Laundry & Dry Cleaning",
            "type":"Services"
        }
    ],
    "sg:phone":"+1 325 672 5190",
    "sg:postcode":"79602",
    "sg:province":"TX",
    "sg:tags":[
        "lining",
        "truck",
        "bed"
    ],
    "wof:name":"Rhino Linings Of Abilene",
    "wof:placetype":"venue"
},
  "geometry": {"coordinates":[-99.72870899999999,32.432998],"type":"Point"}
}