{
  "type": "Feature",
  "properties": {
    "iso:country":"US",
    "sg:address":"3226 FM 367 W",
    "sg:city":"Iowa Park",
    "sg:classifiers":[
        {
            "category":"Building & Trades",
            "subcategory":"Construction",
            "type":"Services"
        }
    ],
    "sg:phone":"+1 940 592 4440",
    "sg:postcode":"76367",
    "sg:province":"TX",
    "sg:tags":[
        "general",
        "contractor"
    ],
    "wof:name":"Jim Stevens Construction Inc",
    "wof:placetype":"venue"
},
  "geometry": {"coordinates":[-98.719491,33.925263],"type":"Point"}
}