{
  "type": "Feature",
  "properties": {
    "iso:country":"US",
    "sg:address":"924 Tony Lama St",
    "sg:city":"El Paso",
    "sg:classifiers":[
        {
            "category":"Wholesale",
            "subcategory":"Machinery & Supplies",
            "type":"Manufacturing & Wholesale Goods"
        }
    ],
    "sg:phone":"+1 915 592 5859",
    "sg:postcode":"79915",
    "sg:province":"TX",
    "sg:tags":[
        "fastener",
        "industrial",
        "retail"
    ],
    "wof:name":"Swifco",
    "wof:placetype":"venue"
},
  "geometry": {"coordinates":[-106.37595,31.761323],"type":"Point"}
}