{
  "type": "Feature",
  "properties": {
    "iso:country":"US",
    "sg:address":"320 S Oak St",
    "sg:city":"Pecos",
    "sg:classifiers":[
        {
            "category":"Farming",
            "subcategory":"Livestock Farm",
            "type":"Manufacturing & Wholesale Goods"
        }
    ],
    "sg:phone":"+1 432 445 9475",
    "sg:postcode":"79772",
    "sg:province":"TX",
    "sg:tags":[
        "ranch"
    ],
    "wof:name":"J M Fowlkes",
    "wof:placetype":"venue"
},
  "geometry": {"coordinates":[-103.495205,31.425357],"type":"Point"}
}