{
  "type": "Feature",
  "properties": {
    "iso:country":"US",
    "sg:address":"910 1st St",
    "sg:city":"Louise",
    "sg:classifiers":[
        {
            "category":"Professional",
            "type":"Services"
        }
    ],
    "sg:phone":"+1 979 648 2496",
    "sg:postcode":"77455",
    "sg:province":"TX",
    "wof:name":"Kelyac Services",
    "wof:placetype":"venue"
},
  "geometry": {"coordinates":[-96.41172299999999,29.11009],"type":"Point"}
}