{
  "type": "Feature",
  "properties": {
    "iso:country":"US",
    "sg:address":"20770 US Hwy 281",
    "sg:city":"San Antonio",
    "sg:classifiers":[
        {
            "category":"Insurance",
            "subcategory":"Insurance Agent",
            "type":"Services"
        }
    ],
    "sg:phone":"+1 210 495 9096",
    "sg:postcode":"78258",
    "sg:province":"TX",
    "wof:name":"Allstate Insurance",
    "wof:placetype":"venue"
},
  "geometry": {"coordinates":[-98.456655,29.636719],"type":"Point"}
}