{
  "type": "Feature",
  "properties": {
    "iso:country":"US",
    "sg:address":"4300 FM 1061",
    "sg:city":"Amarillo",
    "sg:classifiers":[
        {
            "category":"Shopping",
            "subcategory":"Hobbies, Toys, & Games",
            "type":"Retail Goods"
        }
    ],
    "sg:phone":"+1 806 359 6915",
    "sg:postcode":"79124",
    "sg:province":"TX",
    "wof:name":"Sandras Graphics",
    "wof:placetype":"venue"
},
  "geometry": {"coordinates":[-101.94515,35.256318],"type":"Point"}
}