{
  "type": "Feature",
  "properties": {
    "iso:country":"US",
    "sg:address":"2714 Ave I",
    "sg:city":"Rosenberg",
    "sg:classifiers":[
        {
            "category":"Building & Trades",
            "subcategory":"Pest Control",
            "type":"Services"
        }
    ],
    "sg:phone":"+1 281 342 4328",
    "sg:postcode":"77471",
    "sg:province":"TX",
    "wof:name":"Austin Exterminating",
    "wof:placetype":"venue"
},
  "geometry": {"coordinates":[-95.79886399999999,29.557276],"type":"Point"}
}