{
  "type": "Feature",
  "properties": {
    "iso:country":"US",
    "sg:address":"2000 Whitley Rd",
    "sg:city":"Keller",
    "sg:classifiers":[
        {
            "category":"Real Estate",
            "subcategory":"Real Estate Services",
            "type":"Services"
        },
        {
            "category":"Real Estate",
            "subcategory":"Real Estate Agent",
            "type":"Services"
        }
    ],
    "sg:phone":"+1 817 431 6636",
    "sg:postcode":"76248",
    "sg:province":"TX",
    "sg:tags":[
        "buyer",
        "broker"
    ],
    "wof:name":"Robinson Meuli",
    "wof:placetype":"venue"
},
  "geometry": {"coordinates":[-97.254735,32.900417],"type":"Point"}
}