{
  "type": "Feature",
  "properties": {
    "iso:country":"US",
    "sg:address":"901 Wilderness Pass",
    "sg:city":"Cedar Hill",
    "sg:classifiers":[
        {
            "category":"Building & Trades",
            "subcategory":"Landscaping Services",
            "type":"Services"
        }
    ],
    "sg:phone":"+1 972 291 2703",
    "sg:postcode":"75104",
    "sg:province":"TX",
    "wof:name":"Leroy Lawncare Service",
    "wof:placetype":"venue"
},
  "geometry": {"coordinates":[-96.953656,32.573234],"type":"Point"}
}