{
  "type": "Feature",
  "properties": {
    "iso:country":"US",
    "sg:address":"13531 Montfort Dr",
    "sg:city":"Dallas",
    "sg:classifiers":[
        {
            "category":"Personal",
            "subcategory":"Beauty Salon",
            "type":"Services"
        }
    ],
    "sg:phone":"+1 972 661 1515",
    "sg:postcode":"75240",
    "sg:province":"TX",
    "wof:name":"Salon Marin",
    "wof:placetype":"venue"
},
  "geometry": {"coordinates":[-96.81247500000001,32.931702],"type":"Point"}
}