{
  "type": "Feature",
  "properties": {
    "iso:country":"US",
    "sg:address":"301 E 1st St",
    "sg:city":"Elgin",
    "sg:classifiers":[
        {
            "category":"Shopping",
            "subcategory":"Department Store",
            "type":"Retail Goods"
        }
    ],
    "sg:phone":"+1 512 285 3933",
    "sg:postcode":"78621",
    "sg:province":"TX",
    "sg:tags":[
        "oils-vegetable"
    ],
    "wof:name":"Elgin Cotton Oil Mill",
    "wof:placetype":"venue"
},
  "geometry": {"coordinates":[-97.36879,30.349199],"type":"Point"}
}