{
  "type": "Feature",
  "properties": {
    "iso:country":"US",
    "sg:address":"2603 Redleaf Ln",
    "sg:city":"Austin",
    "sg:classifiers":[
        {
            "category":"Building & Trades",
            "subcategory":"Construction",
            "type":"Services"
        }
    ],
    "sg:phone":"+1 512 810 0937",
    "sg:postcode":"78745",
    "sg:province":"TX",
    "sg:tags":[
        "roofing",
        "contractor"
    ],
    "wof:name":"Capital Siding and Roofing Contractors",
    "wof:placetype":"venue"
},
  "geometry": {"coordinates":[-97.816801,30.200337],"type":"Point"}
}