{
  "type": "Feature",
  "properties": {
    "iso:country":"US",
    "sg:address":"4850 E Grand Ave Ste A",
    "sg:city":"Dallas",
    "sg:classifiers":[
        {
            "category":"Personal",
            "subcategory":"Beauty Salon",
            "type":"Services"
        }
    ],
    "sg:phone":"+1 214 823 5546",
    "sg:postcode":"75223",
    "sg:province":"TX",
    "sg:tags":[
        "hair",
        "cosmetologist"
    ],
    "wof:name":"Taurus Beauty Salon",
    "wof:placetype":"venue"
},
  "geometry": {"coordinates":[-96.75509599999999,32.786701],"type":"Point"}
}