{
  "type": "Feature",
  "properties": {
    "iso:country":"US",
    "sg:address":"946 Pennygent Ln",
    "sg:city":"Channelview",
    "sg:classifiers":[
        {
            "category":"Professional",
            "type":"Services"
        }
    ],
    "sg:phone":"+1 281 452 1241",
    "sg:postcode":"77530",
    "sg:province":"TX",
    "wof:name":"Patrick Guide",
    "wof:placetype":"venue"
},
  "geometry": {"coordinates":[-95.15179999999999,29.792999],"type":"Point"}
}