{
  "type": "Feature",
  "properties": {
    "iso:country":"US",
    "sg:address":"601 E Gibbs St",
    "sg:city":"Del Rio",
    "sg:classifiers":[
        {
            "category":"Professional",
            "subcategory":"Business Services",
            "type":"Services"
        }
    ],
    "sg:phone":"+1 830 734 1699",
    "sg:postcode":"78840",
    "sg:province":"TX",
    "wof:name":"Images",
    "wof:placetype":"venue"
},
  "geometry": {"coordinates":[-100.895515,29.366601],"type":"Point"}
}