{
  "type": "Feature",
  "properties": {
    "iso:country":"US",
    "sg:address":"600 I- 35 Svc Rd N",
    "sg:city":"Austin",
    "sg:classifiers":[
        {
            "category":"Building & Trades",
            "subcategory":"Construction",
            "type":"Services"
        }
    ],
    "sg:phone":"+1 512 388 2665",
    "sg:postcode":"78701",
    "sg:province":"TX",
    "sg:tags":[
        "general",
        "contractor"
    ],
    "wof:name":"Brath Inc",
    "wof:placetype":"venue"
},
  "geometry": {"coordinates":[-97.73466500000001,30.266823],"type":"Point"}
}