{
  "type": "Feature",
  "properties": {
    "iso:country":"US",
    "sg:address":"1602 Harley Dr",
    "sg:city":"Harker Heights",
    "sg:classifiers":[
        {
            "category":"Building & Trades",
            "subcategory":"Landscaping Services",
            "type":"Services"
        }
    ],
    "sg:phone":"+1 254 699 8680",
    "sg:postcode":"76548",
    "sg:province":"TX",
    "wof:name":"JJ & W Lawn Care",
    "wof:placetype":"venue"
},
  "geometry": {"coordinates":[-97.672882,31.078715],"type":"Point"}
}