{
  "type": "Feature",
  "properties": {
    "iso:country":"US",
    "sg:address":"216 Texas St",
    "sg:city":"Cedar Hill",
    "sg:classifiers":[
        {
            "category":"Retail",
            "subcategory":"Veterinary Services",
            "type":"Services"
        }
    ],
    "sg:phone":"+1 972 291 7933",
    "sg:postcode":"75104",
    "sg:province":"TX",
    "wof:name":"Central Animal Clinic Inc",
    "wof:placetype":"venue"
},
  "geometry": {"coordinates":[-96.95077999999999,32.587885],"type":"Point"}
}