{
  "type": "Feature",
  "properties": {
    "iso:country":"US",
    "sg:address":"105 Lion St",
    "sg:city":"Desoto",
    "sg:classifiers":[
        {
            "category":"Banks & Credit Unions",
            "subcategory":"Financial Services",
            "type":"Services"
        }
    ],
    "sg:phone":"+1 972 274 9498",
    "sg:postcode":"75115",
    "sg:province":"TX",
    "sg:tags":[
        "broker",
        "mortgage"
    ],
    "wof:name":"Value Mortgage Loans",
    "wof:placetype":"venue"
},
  "geometry": {"coordinates":[-96.856914,32.591467],"type":"Point"}
}