{
  "type": "Feature",
  "properties": {
    "iso:country":"US",
    "sg:address":"8414 F M 2244",
    "sg:city":"Austin",
    "sg:classifiers":[
        {
            "category":"Restaurant",
            "type":"Food & Drink"
        }
    ],
    "sg:phone":"+1 512 306 9040",
    "sg:postcode":"78701",
    "sg:province":"TX",
    "wof:name":"Bee Caves B-B-Q",
    "wof:placetype":"venue"
},
  "geometry": {"coordinates":[-97.862184,30.318309],"type":"Point"}
}