{
  "type": "Feature",
  "properties": {
    "iso:country":"US",
    "sg:address":"12200 W Co Rd 129",
    "sg:city":"Odessa",
    "sg:classifiers":[
        {
            "category":"Mining & Drilling",
            "type":"Manufacturing & Wholesale Goods"
        }
    ],
    "sg:phone":"+1 432 563 3752",
    "sg:postcode":"79765",
    "sg:province":"TX",
    "sg:tags":[
        "field",
        "oil"
    ],
    "wof:name":"Hard Band Industries Inc",
    "wof:placetype":"venue"
},
  "geometry": {"coordinates":[-102.243331,31.901351],"type":"Point"}
}