{
  "type": "Feature",
  "properties": {
    "iso:country":"US",
    "sg:address":"825 N Crockett St",
    "sg:city":"Sherman",
    "sg:classifiers":[
        {
            "category":"Retail",
            "subcategory":"Veterinary Services",
            "type":"Services"
        }
    ],
    "sg:phone":"+1 903 893 1175",
    "sg:postcode":"75090",
    "sg:province":"TX",
    "wof:name":"Brakebill Veterinary Hospital",
    "wof:placetype":"venue"
},
  "geometry": {"coordinates":[-96.612368,33.642759],"type":"Point"}
}