{
  "type": "Feature",
  "properties": {
    "iso:country":"US",
    "sg:address":"16006 Congo Ln",
    "sg:city":"Houston",
    "sg:classifiers":[
        {
            "category":"Home & Garden",
            "subcategory":"Furniture",
            "type":"Retail Goods"
        }
    ],
    "sg:phone":"+1 713 849 9052",
    "sg:postcode":"77040",
    "sg:province":"TX",
    "sg:tags":[
        "consulting",
        "business"
    ],
    "wof:name":"Corporate Results",
    "wof:placetype":"venue"
},
  "geometry": {"coordinates":[-95.56303,29.883347],"type":"Point"}
}