{
  "type": "Feature",
  "properties": {
    "iso:country":"US",
    "sg:address":"110 Kessler Ave",
    "sg:city":"Schulenburg",
    "sg:classifiers":[
        {
            "category":"Food & Beverages",
            "subcategory":"Bakery",
            "type":"Retail Goods"
        }
    ],
    "sg:phone":"+1 979 743 4342",
    "sg:postcode":"78956",
    "sg:province":"TX",
    "wof:name":"Kountry Bakery",
    "wof:placetype":"venue"
},
  "geometry": {"coordinates":[-96.902531,29.68704],"type":"Point"}
}