{
  "type": "Feature",
  "properties": {
    "iso:country":"US",
    "sg:address":"14715 Knights Way Dr",
    "sg:city":"Houston",
    "sg:classifiers":[
        {
            "category":"Building & Trades",
            "subcategory":"Electrical",
            "type":"Services"
        }
    ],
    "sg:phone":"+1 832 328 1429",
    "sg:postcode":"77083",
    "sg:province":"TX",
    "sg:tags":[
        "electric",
        "contractor"
    ],
    "wof:name":"Anamet Electrical Inc",
    "wof:placetype":"venue"
},
  "geometry": {"coordinates":[-95.64554800000001,29.682854],"type":"Point"}
}