{
  "type": "Feature",
  "properties": {
    "iso:country":"US",
    "sg:address":"1350 S Main St",
    "sg:city":"Fort Worth",
    "sg:classifiers":[
        {
            "category":"Health Services",
            "subcategory":"Medical Lab",
            "type":"Services"
        }
    ],
    "sg:phone":"+1 817 877 5379",
    "sg:postcode":"76104",
    "sg:province":"TX",
    "sg:tags":[
        "laboratory"
    ],
    "wof:name":"Metwest Inc",
    "wof:placetype":"venue"
},
  "geometry": {"coordinates":[-97.325968,32.730045],"type":"Point"}
}