{
  "type": "Feature",
  "properties": {
    "iso:country":"US",
    "sg:address":"18110 Lakeside Ln",
    "sg:city":"Houston",
    "sg:classifiers":[
        {
            "category":"Real Estate",
            "subcategory":"Developer",
            "type":"Services"
        }
    ],
    "sg:phone":"+1 281 335 1582",
    "sg:postcode":"77058",
    "sg:province":"TX",
    "wof:name":"Ke Commercial",
    "wof:placetype":"venue"
},
  "geometry": {"coordinates":[-95.075952,29.55338],"type":"Point"}
}