{
  "type": "Feature",
  "properties": {
    "iso:country":"US",
    "sg:address":"9118 Diplomacy Row",
    "sg:city":"Dallas",
    "sg:classifiers":[
        {
            "category":"Manufacturing",
            "subcategory":"Printing",
            "type":"Manufacturing & Wholesale Goods"
        }
    ],
    "sg:phone":"+1 214 638 5225",
    "sg:postcode":"75247",
    "sg:province":"TX",
    "sg:tags":[
        "label"
    ],
    "wof:name":"Advantage Marking & Labeling",
    "wof:placetype":"venue"
},
  "geometry": {"coordinates":[-96.895202,32.819361],"type":"Point"}
}