{
  "type": "Feature",
  "properties": {
    "iso:country":"US",
    "sg:address":"7410 Arborcrest Dr",
    "sg:city":"Dallas",
    "sg:classifiers":[
        {
            "category":"Home & Garden",
            "subcategory":"Carpets & Floor Coverings",
            "type":"Retail Goods"
        }
    ],
    "sg:phone":"+1 214 833 6785",
    "sg:postcode":"75232",
    "sg:province":"TX",
    "wof:name":"Square Foot",
    "wof:placetype":"venue"
},
  "geometry": {"coordinates":[-96.826503,32.658725],"type":"Point"}
}