{
  "type": "Feature",
  "properties": {
    "iso:country":"US",
    "sg:address":"1101 Phenie Ave",
    "sg:city":"Texarkana",
    "sg:classifiers":[
        {
            "category":"Organizations",
            "subcategory":"Religious Organization",
            "type":"Services"
        }
    ],
    "sg:phone":"+1 903 792 4357",
    "sg:postcode":"75501",
    "sg:province":"TX",
    "sg:tags":[
        "church"
    ],
    "wof:name":"New Hope Baptist Church",
    "wof:placetype":"venue"
},
  "geometry": {"coordinates":[-94.06062300000001,33.415796],"type":"Point"}
}