{
  "type": "Feature",
  "properties": {
    "iso:country":"US",
    "sg:address":"4200 N Sylvania Ave",
    "sg:city":"Fort Worth",
    "sg:classifiers":[
        {
            "category":"Building & Trades",
            "subcategory":"Construction",
            "type":"Services"
        }
    ],
    "sg:phone":"+1 817 759 2488",
    "sg:postcode":"76137",
    "sg:province":"TX",
    "sg:tags":[
        "general",
        "contractor"
    ],
    "wof:name":"Bob Moore Construction",
    "wof:placetype":"venue"
},
  "geometry": {"coordinates":[-97.308046,32.817619],"type":"Point"}
}