{
  "type": "Feature",
  "properties": {
    "iso:country":"US",
    "sg:address":"1921 67th St",
    "sg:city":"Lubbock",
    "sg:classifiers":[
        {
            "category":"Building & Trades",
            "subcategory":"Landscaping Services",
            "type":"Services"
        }
    ],
    "sg:phone":"+1 806 786 4457",
    "sg:postcode":"79412",
    "sg:province":"TX",
    "sg:tags":[
        "lawn",
        "maintenance"
    ],
    "wof:name":"Garcia S Lawn Care Ir",
    "wof:placetype":"venue"
},
  "geometry": {"coordinates":[-101.85883699999999,33.533441],"type":"Point"}
}