{
  "type": "Feature",
  "properties": {
    "iso:country":"US",
    "sg:address":"2307 Fortune Dr",
    "sg:city":"Austin",
    "sg:classifiers":[
        {
            "category":"Manufacturing",
            "subcategory":"Tools & Machinery",
            "type":"Manufacturing & Wholesale Goods"
        }
    ],
    "sg:phone":"+1 512 707 0630",
    "sg:postcode":"78704",
    "sg:province":"TX",
    "sg:tags":[
        "industrial",
        "mfg"
    ],
    "wof:name":"Quick Draw Design & Drafting",
    "wof:placetype":"venue"
},
  "geometry": {"coordinates":[-97.78039800000001,30.252839],"type":"Point"}
}