{
  "type": "Feature",
  "properties": {
    "iso:country":"US",
    "sg:address":"416 Montreal Dr",
    "sg:city":"Hurst",
    "sg:classifiers":[
        {
            "category":"Professional",
            "subcategory":"Business Services",
            "type":"Services"
        }
    ],
    "sg:phone":"+1 817 577 1589",
    "sg:postcode":"76054",
    "sg:province":"TX",
    "wof:name":"Northernlight Fire Technology",
    "wof:placetype":"venue"
},
  "geometry": {"coordinates":[-97.175662,32.872086],"type":"Point"}
}