{
  "type": "Feature",
  "properties": {
    "iso:country":"US",
    "sg:address":"519 Jackson Ave",
    "sg:city":"Pasadena",
    "sg:classifiers":[
        {
            "category":"Professional",
            "subcategory":"Management & Consulting",
            "type":"Services"
        }
    ],
    "sg:phone":"+1 713 472 3347",
    "sg:postcode":"77506",
    "sg:province":"TX",
    "wof:name":"Plata Express Management LLC",
    "wof:placetype":"venue"
},
  "geometry": {"coordinates":[-95.20650000000001,29.705428],"type":"Point"}
}