{
  "type": "Feature",
  "properties": {
    "iso:country":"US",
    "sg:address":"529 Ronson Dr",
    "sg:city":"Corpus Christi",
    "sg:classifiers":[
        {
            "category":"Professional",
            "type":"Services"
        }
    ],
    "sg:phone":"+1 361 991 4123",
    "sg:postcode":"78412",
    "sg:province":"TX",
    "wof:name":"Bar Inverted TI Ltd",
    "wof:placetype":"venue"
},
  "geometry": {"coordinates":[-97.358351,27.721153],"type":"Point"}
}