{
  "type": "Feature",
  "properties": {
    "iso:country":"US",
    "sg:address":"4175 Hwy 190 W",
    "sg:city":"Livingston",
    "sg:classifiers":[
        {
            "category":"Building & Trades",
            "subcategory":"Construction",
            "type":"Services"
        }
    ],
    "sg:phone":"+1 936 967 0494",
    "sg:postcode":"77351",
    "sg:province":"TX",
    "sg:tags":[
        "mobile",
        "home"
    ],
    "wof:name":"Ranger Mobile Home Rpr & Supl",
    "wof:placetype":"venue"
},
  "geometry": {"coordinates":[-94.954182,30.712364],"type":"Point"}
}