{
  "type": "Feature",
  "properties": {
    "iso:country":"US",
    "sg:address":"3106 Timberview Rd",
    "sg:city":"Dallas",
    "sg:classifiers":[
        {
            "category":"Social Services",
            "subcategory":"Child Care",
            "type":"Services"
        }
    ],
    "sg:phone":"+1 214 358 0302",
    "sg:postcode":"75229",
    "sg:province":"TX",
    "sg:tags":[
        "day"
    ],
    "wof:name":"Ratchers Day Care Center",
    "wof:placetype":"venue"
},
  "geometry": {"coordinates":[-96.869016,32.883657],"type":"Point"}
}