{
  "type": "Feature",
  "properties": {
    "iso:country":"US",
    "sg:address":"1430 Enclave Pkwy",
    "sg:city":"Houston",
    "sg:classifiers":[
        {
            "category":"Professional",
            "subcategory":"Management & Consulting",
            "type":"Services"
        }
    ],
    "sg:phone":"+1 281 368 4024",
    "sg:postcode":"77077",
    "sg:province":"TX",
    "wof:name":"Entergyshaw General Management",
    "wof:placetype":"venue"
},
  "geometry": {"coordinates":[-95.618714,29.757035],"type":"Point"}
}