{
  "type": "Feature",
  "properties": {
    "iso:country":"US",
    "sg:address":"3759 Country Place Dr",
    "sg:city":"Stafford",
    "sg:classifiers":[
        {
            "category":"Professional",
            "subcategory":"Business Services",
            "type":"Services"
        }
    ],
    "sg:phone":"+1 281 403 0391",
    "sg:postcode":"77477",
    "sg:province":"TX",
    "wof:name":"Cyber Web & Graphics",
    "wof:placetype":"venue"
},
  "geometry": {"coordinates":[-95.566588,29.609038],"type":"Point"}
}