{
  "type": "Feature",
  "properties": {
    "iso:country":"US",
    "sg:address":"203 Fisk Ave",
    "sg:city":"Brownwood",
    "sg:classifiers":[
        {
            "category":"Personal",
            "subcategory":"Beauty Salon",
            "type":"Services"
        }
    ],
    "sg:phone":"+1 325 646 8822",
    "sg:postcode":"76801",
    "sg:province":"TX",
    "sg:tags":[
        "school"
    ],
    "wof:name":"Ranger College Beauty School",
    "wof:placetype":"venue"
},
  "geometry": {"coordinates":[-98.980295,31.720592],"type":"Point"}
}