{
  "type": "Feature",
  "properties": {
    "iso:country":"US",
    "sg:address":"6206 Burk Burnett Ct",
    "sg:city":"Austin",
    "sg:classifiers":[
        {
            "category":"Professional",
            "type":"Services"
        }
    ],
    "sg:phone":"+1 512 288 1086",
    "sg:postcode":"78749",
    "sg:province":"TX",
    "wof:name":"Keith Askew",
    "wof:placetype":"venue"
},
  "geometry": {"coordinates":[-97.87263400000001,30.22026],"type":"Point"}
}