{
  "type": "Feature",
  "properties": {
    "iso:country":"US",
    "sg:address":"1724 5th St",
    "sg:city":"Rosenberg",
    "sg:classifiers":[
        {
            "category":"Retail",
            "subcategory":"Repair Shop",
            "type":"Services"
        }
    ],
    "sg:phone":"+1 832 595 0019",
    "sg:postcode":"77471",
    "sg:province":"TX",
    "wof:name":"Americas Repair Service",
    "wof:placetype":"venue"
},
  "geometry": {"coordinates":[-95.804446,29.550562],"type":"Point"}
}