{
  "type": "Feature",
  "properties": {
    "iso:country":"US",
    "sg:address":"3415 Lee St",
    "sg:city":"Greenville",
    "sg:classifiers":[
        {
            "category":"Retail",
            "subcategory":"Auto Repair",
            "type":"Services"
        }
    ],
    "sg:phone":"+1 903 455 6894",
    "sg:postcode":"75401",
    "sg:province":"TX",
    "sg:tags":[
        "body",
        "automobile",
        "painting"
    ],
    "wof:name":"Jesse's Body Shop",
    "wof:placetype":"venue"
},
  "geometry": {"coordinates":[-96.11788199999999,33.139879],"type":"Point"}
}