{
  "type": "Feature",
  "properties": {
    "iso:country":"US",
    "sg:address":"5301 Scottsboro Ln",
    "sg:city":"Midland",
    "sg:classifiers":[
        {
            "category":"Mining & Drilling",
            "type":"Manufacturing & Wholesale Goods"
        }
    ],
    "sg:phone":"+1 432 697 8420",
    "sg:postcode":"79707",
    "sg:province":"TX",
    "sg:tags":[
        "development",
        "gas",
        "oil",
        "exploration"
    ],
    "wof:name":"Gulf Coast Oil & Gas Co",
    "wof:placetype":"venue"
},
  "geometry": {"coordinates":[-102.172904,32.058436],"type":"Point"}
}