{
  "type": "Feature",
  "properties": {
    "iso:country":"US",
    "sg:address":"3333 Eastside St",
    "sg:city":"Houston",
    "sg:classifiers":[
        {
            "category":"Professional",
            "subcategory":"Management & Consulting",
            "type":"Services"
        }
    ],
    "sg:phone":"+1 713 526 7933",
    "sg:postcode":"77098",
    "sg:province":"TX",
    "sg:tags":[
        "consultant",
        "educational"
    ],
    "wof:name":"Sheila Doran-Benyon",
    "wof:placetype":"venue"
},
  "geometry": {"coordinates":[-95.42446700000001,29.734954],"type":"Point"}
}