{
  "type": "Feature",
  "properties": {
    "iso:country":"US",
    "sg:address":"2930 Magoffin Ave",
    "sg:city":"El Paso",
    "sg:classifiers":[
        {
            "category":"Taxi",
            "type":"Transportation"
        }
    ],
    "sg:phone":"+1 915 544 2211",
    "sg:postcode":"79905",
    "sg:province":"TX",
    "sg:tags":[
        "taxicab"
    ],
    "wof:name":"Sun City Cab Co",
    "wof:placetype":"venue"
},
  "geometry": {"coordinates":[-106.459999,31.772815],"type":"Point"}
}