{
  "type": "Feature",
  "properties": {
    "iso:country":"US",
    "sg:address":"100 N Shore Dr",
    "sg:city":"Amarillo",
    "sg:classifiers":[
        {
            "category":"Government",
            "subcategory":"Office",
            "type":"Public Place"
        }
    ],
    "sg:phone":"+1 806 622 8711",
    "sg:postcode":"79118",
    "sg:province":"TX",
    "sg:tags":[
        "executive"
    ],
    "wof:name":"Volunteer Fire Department",
    "wof:placetype":"venue"
},
  "geometry": {"coordinates":[-101.782301,35.063685],"type":"Point"}
}