{
  "type": "Feature",
  "properties": {
    "iso:country":"US",
    "sg:address":"12077 State Highway 195",
    "sg:city":"Killeen",
    "sg:classifiers":[
        {
            "category":"Autos & Motor Vehicles",
            "subcategory":"Auto Supplies",
            "type":"Retail Goods"
        }
    ],
    "sg:phone":"+1 254 634 7518",
    "sg:postcode":"76542",
    "sg:province":"TX",
    "sg:tags":[
        "automobile",
        "part",
        "accessory"
    ],
    "wof:name":"Do-Rite Wrecking",
    "wof:placetype":"venue"
},
  "geometry": {"coordinates":[-97.753714,31.018133],"type":"Point"}
}