{
  "type": "Feature",
  "properties": {
    "iso:country":"US",
    "sg:address":"550 W Cardinal Dr",
    "sg:city":"Beaumont",
    "sg:classifiers":[
        {
            "category":"Autos & Motor Vehicles",
            "subcategory":"Fuel & Gas Station",
            "type":"Retail Goods"
        }
    ],
    "sg:phone":"+1 409 832 2264",
    "sg:postcode":"77705",
    "sg:province":"TX",
    "sg:tags":[
        "oil"
    ],
    "wof:name":"Cardinal Exxon Svc Ctr",
    "wof:placetype":"venue"
},
  "geometry": {"coordinates":[-94.08216899999999,30.029697],"type":"Point"}
}