{
  "type": "Feature",
  "properties": {
    "iso:country":"US",
    "sg:address":"1336 N Galloway Ave",
    "sg:city":"Mesquite",
    "sg:classifiers":[
        {
            "category":"Health Services",
            "subcategory":"Doctor",
            "type":"Services"
        }
    ],
    "sg:phone":"+1 972 329 5437",
    "sg:postcode":"75149",
    "sg:province":"TX",
    "wof:name":"Anil K Reddy DDS MPH",
    "wof:placetype":"venue"
},
  "geometry": {"coordinates":[-96.600617,32.780832],"type":"Point"}
}