{
  "type": "Feature",
  "properties": {
    "iso:country":"US",
    "sg:address":"2150 Idlewild Dr",
    "sg:city":"Frisco",
    "sg:classifiers":[
        {
            "category":"Wholesale",
            "subcategory":"Medical Equipment & Supplies",
            "type":"Manufacturing & Wholesale Goods"
        }
    ],
    "sg:phone":"+1 972 712 8994",
    "sg:postcode":"75034",
    "sg:province":"TX",
    "sg:tags":[
        "oxygen"
    ],
    "wof:name":"Red Oxygen",
    "wof:placetype":"venue"
},
  "geometry": {"coordinates":[-96.87240300000001,33.148278],"type":"Point"}
}