{
  "type": "Feature",
  "properties": {
    "iso:country":"US",
    "sg:address":"1502 Fair Oaks Dr",
    "sg:city":"Richardson",
    "sg:classifiers":[
        {
            "category":"Wholesale",
            "subcategory":"Vending Machines",
            "type":"Manufacturing & Wholesale Goods"
        }
    ],
    "sg:phone":"+1 972 238 1150",
    "sg:postcode":"75081",
    "sg:province":"TX",
    "sg:tags":[
        "operator"
    ],
    "wof:name":"Vincents Snack & Vending",
    "wof:placetype":"venue"
},
  "geometry": {"coordinates":[-96.697304,32.958119],"type":"Point"}
}