{
  "type": "Feature",
  "properties": {
    "iso:country":"US",
    "sg:address":"6802 Spruce Gum Ln",
    "sg:city":"Austin",
    "sg:classifiers":[
        {
            "category":"Autos & Motor Vehicles",
            "subcategory":"Automobile Sales",
            "type":"Retail Goods"
        }
    ],
    "sg:phone":"+1 512 462 3647",
    "sg:postcode":"78744",
    "sg:province":"TX",
    "sg:tags":[
        "dealers-used",
        "car",
        "used",
        "cars-wholesale"
    ],
    "wof:name":"Arias Auto Sale",
    "wof:placetype":"venue"
},
  "geometry": {"coordinates":[-97.767184,30.184436],"type":"Point"}
}