{
  "type": "Feature",
  "properties": {
    "iso:country":"US",
    "sg:address":"2026 W Pioneer Pkwy",
    "sg:city":"Pantego",
    "sg:classifiers":[
        {
            "category":"Professional",
            "type":"Services"
        }
    ],
    "sg:phone":"+1 817 860 7165",
    "sg:postcode":"76013",
    "sg:province":"TX",
    "sg:tags":[
        "establishment"
    ],
    "wof:name":"Sonny & Son's",
    "wof:placetype":"venue"
},
  "geometry": {"coordinates":[-97.140215,32.709152],"type":"Point"}
}