{
  "type": "Feature",
  "properties": {
    "iso:country":"US",
    "sg:address":"1907 N Lamar Boulevard Suite 200",
    "sg:city":"Austin",
    "sg:classifiers":[
        {
            "category":"Professional",
            "subcategory":"Accounting & Tax Preparation",
            "type":"Services"
        }
    ],
    "sg:phone":"+1 512 477 6866",
    "sg:postcode":"78705",
    "sg:province":"TX",
    "sg:tags":[
        "accountant"
    ],
    "wof:name":"Mayes Management Company",
    "wof:placetype":"venue"
},
  "geometry": {"coordinates":[-97.752279,30.283969],"type":"Point"}
}