{
  "type": "Feature",
  "properties": {
    "iso:country":"US",
    "sg:address":"15410 Kuykendahl Rd",
    "sg:city":"Houston",
    "sg:classifiers":[
        {
            "category":"Retail",
            "subcategory":"Auto Repair",
            "type":"Services"
        }
    ],
    "sg:phone":"+1 281 537 5317",
    "sg:postcode":"77090",
    "sg:province":"TX",
    "sg:tags":[
        "muffler",
        "exhaust",
        "system"
    ],
    "wof:name":"Midas Auto Svc Experts",
    "wof:placetype":"venue"
},
  "geometry": {"coordinates":[-95.457583,29.999592],"type":"Point"}
}