{
  "type": "Feature",
  "properties": {
    "iso:country":"US",
    "sg:address":"1208 Taylor Creek",
    "sg:city":"Mesquite",
    "sg:classifiers":[
        {
            "category":"Social Services",
            "subcategory":"Child Care",
            "type":"Services"
        }
    ],
    "sg:phone":"+1 972 222 7199",
    "sg:postcode":"75181",
    "sg:province":"TX",
    "sg:tags":[
        "day"
    ],
    "wof:name":"Tenisons Tiny Tots Learning C",
    "wof:placetype":"venue"
},
  "geometry": {"coordinates":[-96.558758,32.752427],"type":"Point"}
}