{
  "type": "Feature",
  "properties": {
    "iso:country":"US",
    "sg:address":"7911 Oakington Dr",
    "sg:city":"Houston",
    "sg:classifiers":[
        {
            "category":"Real Estate",
            "subcategory":"Real Estate Agent",
            "type":"Services"
        }
    ],
    "sg:phone":"+1 713 850 9700",
    "sg:postcode":"77071",
    "sg:province":"TX",
    "sg:tags":[
        "realtor"
    ],
    "wof:name":"Arturo Singer",
    "wof:placetype":"venue"
},
  "geometry": {"coordinates":[-95.517116,29.658428],"type":"Point"}
}