{
  "type": "Feature",
  "properties": {
    "iso:country":"US",
    "sg:address":"4700 Lewis Dr",
    "sg:city":"Port Arthur",
    "sg:classifiers":[
        {
            "category":"Personal",
            "subcategory":"Beauty Salon",
            "type":"Services"
        }
    ],
    "sg:phone":"+1 409 983 4747",
    "sg:postcode":"77642",
    "sg:province":"TX",
    "sg:tags":[
        "shop"
    ],
    "wof:name":"Denises Beauty Salon ( Inc )",
    "wof:placetype":"venue"
},
  "geometry": {"coordinates":[-93.905812,29.914407],"type":"Point"}
}