{
  "type": "Feature",
  "properties": {
    "iso:country":"US",
    "sg:address":"6005 Liberty Grove Rd",
    "sg:city":"Rowlett",
    "sg:classifiers":[
        {
            "category":"Professional",
            "type":"Services"
        }
    ],
    "sg:phone":"+1 972 475 2097",
    "sg:postcode":"75089",
    "sg:province":"TX",
    "wof:name":"Woodcrafts",
    "wof:placetype":"venue"
},
  "geometry": {"coordinates":[-96.55574,32.915476],"type":"Point"}
}