{
  "type": "Feature",
  "properties": {
    "iso:country":"US",
    "sg:address":"2908 Edgewood Ln",
    "sg:city":"Colleyville",
    "sg:classifiers":[
        {
            "category":"Professional",
            "subcategory":"Business Services",
            "type":"Services"
        }
    ],
    "sg:phone":"+1 817 868 1977",
    "sg:postcode":"76034",
    "sg:province":"TX",
    "wof:name":"Shoppa Family Ltd Partnership",
    "wof:placetype":"venue"
},
  "geometry": {"coordinates":[-97.120536,32.884887],"type":"Point"}
}