{
  "type": "Feature",
  "properties": {
    "iso:country":"US",
    "sg:address":"5810 Brookside Rd",
    "sg:city":"Pearland",
    "sg:classifiers":[
        {
            "category":"Education",
            "subcategory":"School",
            "type":"Public Place"
        }
    ],
    "sg:phone":"+1 281 412 1445",
    "sg:postcode":"77581",
    "sg:province":"TX",
    "sg:tags":[
        "high",
        "middle",
        "elementary"
    ],
    "wof:name":"Schools-Public",
    "wof:placetype":"venue"
},
  "geometry": {"coordinates":[-95.321027,29.587625],"type":"Point"}
}