{
  "type": "Feature",
  "properties": {
    "iso:country":"US",
    "sg:address":"3434 Ivanhoe Ln",
    "sg:city":"Garland",
    "sg:classifiers":[
        {
            "category":"Retail",
            "subcategory":"Auto Repair",
            "type":"Services"
        }
    ],
    "sg:phone":"+1 972 495 0084",
    "sg:postcode":"75044",
    "sg:province":"TX",
    "sg:tags":[
        "automotive",
        "trade",
        "contractor"
    ],
    "wof:name":"Eclipse Solar Control",
    "wof:placetype":"venue"
},
  "geometry": {"coordinates":[-96.68026399999999,32.964268],"type":"Point"}
}