{
  "type": "Feature",
  "properties": {
    "iso:country":"US",
    "sg:address":"10121 Lake June Rd",
    "sg:city":"Dallas",
    "sg:classifiers":[
        {
            "category":"Social Services",
            "subcategory":"Child Care",
            "type":"Services"
        }
    ],
    "sg:phone":"+1 972 288 2820",
    "sg:postcode":"75217",
    "sg:province":"TX",
    "sg:tags":[
        "day"
    ],
    "wof:name":"Dream House Learning Center",
    "wof:placetype":"venue"
},
  "geometry": {"coordinates":[-96.651149,32.73429],"type":"Point"}
}