{
  "type": "Feature",
  "properties": {
    "iso:country":"US",
    "sg:address":"539 S Texas Blvd",
    "sg:city":"Weslaco",
    "sg:classifiers":[
        {
            "category":"Professional",
            "subcategory":"Accounting & Tax Preparation",
            "type":"Services"
        }
    ],
    "sg:phone":"+1 956 969 3748",
    "sg:postcode":"78596",
    "sg:province":"TX",
    "sg:tags":[
        "return",
        "filing"
    ],
    "wof:name":"Tio Sam Tax Svc",
    "wof:placetype":"venue"
},
  "geometry": {"coordinates":[-97.99055,26.156434],"type":"Point"}
}