{
  "type": "Feature",
  "properties": {
    "iso:country":"US",
    "sg:address":"202 Aldine Bender Rd",
    "sg:city":"Houston",
    "sg:classifiers":[
        {
            "category":"Insurance",
            "subcategory":"Hazard Insurance",
            "type":"Services"
        }
    ],
    "sg:phone":"+1 281 931 9411",
    "sg:postcode":"77060",
    "sg:province":"TX",
    "sg:tags":[
        "carrier"
    ],
    "wof:name":"H&L Multi Service Agency",
    "wof:placetype":"venue"
},
  "geometry": {"coordinates":[-95.400113,29.931715],"type":"Point"}
}