{
  "type": "Feature",
  "properties": {
    "iso:country":"US",
    "sg:address":"709 S Marienfeld St",
    "sg:city":"Midland",
    "sg:classifiers":[
        {
            "category":"Professional",
            "type":"Services"
        }
    ],
    "sg:phone":"+1 432 687 1846",
    "sg:postcode":"79701",
    "sg:province":"TX",
    "sg:tags":[
        "establishment"
    ],
    "wof:name":"E O I Inc",
    "wof:placetype":"venue"
},
  "geometry": {"coordinates":[-102.079005,31.990178],"type":"Point"}
}