{
  "type": "Feature",
  "properties": {
    "iso:country":"US",
    "sg:address":"2600 S 23rd St",
    "sg:city":"Mcallen",
    "sg:classifiers":[
        {
            "category":"Autos & Motor Vehicles",
            "subcategory":"Automobile Sales",
            "type":"Retail Goods"
        }
    ],
    "sg:phone":"+1 956 682 0068",
    "sg:postcode":"78503",
    "sg:province":"TX",
    "sg:tags":[
        "dealers-used",
        "car",
        "used",
        "cars-wholesale"
    ],
    "wof:name":"Gutierrez Motors",
    "wof:placetype":"venue"
},
  "geometry": {"coordinates":[-98.24897,26.18235],"type":"Point"}
}