{
  "type": "Feature",
  "properties": {
    "iso:country":"US",
    "sg:address":"13405 Kleberg Rd",
    "sg:city":"Dallas",
    "sg:classifiers":[
        {
            "category":"Shopping",
            "subcategory":"Used Merchandise",
            "type":"Retail Goods"
        }
    ],
    "sg:phone":"+1 972 286 8377",
    "sg:postcode":"75253",
    "sg:province":"TX",
    "sg:tags":[
        "shop",
        "thrift"
    ],
    "wof:name":"Kat's Korner",
    "wof:placetype":"venue"
},
  "geometry": {"coordinates":[-96.613184,32.668573],"type":"Point"}
}