{
  "type": "Feature",
  "properties": {
    "iso:country":"US",
    "sg:address":"1306 S Magnolia St",
    "sg:city":"Woodville",
    "sg:classifiers":[
        {
            "category":"Organizations",
            "subcategory":"Community Association",
            "type":"Services"
        }
    ],
    "sg:phone":"+1 409 283 5348",
    "sg:postcode":"75979",
    "sg:province":"TX",
    "wof:name":"Rotary International",
    "wof:placetype":"venue"
},
  "geometry": {"coordinates":[-94.416629,30.762843],"type":"Point"}
}