{
  "type": "Feature",
  "properties": {
    "iso:country":"US",
    "sg:address":"103 Carey Ln",
    "sg:city":"Daingerfield",
    "sg:classifiers":[
        {
            "category":"Food & Beverages",
            "subcategory":"Specialty",
            "type":"Retail Goods"
        }
    ],
    "sg:phone":"+1 903 645 7108",
    "sg:postcode":"75638",
    "sg:province":"TX",
    "wof:name":"Loyd/Maddox New Total",
    "wof:placetype":"venue"
},
  "geometry": {"coordinates":[-94.723547,33.010321],"type":"Point"}
}