{
  "type": "Feature",
  "properties": {
    "iso:country":"US",
    "sg:address":"627 Darnel Dr",
    "sg:city":"Mesquite",
    "sg:classifiers":[
        {
            "category":"Restaurant",
            "type":"Food & Drink"
        }
    ],
    "sg:phone":"+1 972 285 6410",
    "sg:postcode":"75149",
    "sg:province":"TX",
    "sg:tags":[
        "eating"
    ],
    "wof:name":"Skyline Catering",
    "wof:placetype":"venue"
},
  "geometry": {"coordinates":[-96.57923099999999,32.757756],"type":"Point"}
}