{
  "type": "Feature",
  "properties": {
    "iso:country":"US",
    "sg:address":"2917 W Anderson Ln",
    "sg:city":"Austin",
    "sg:classifiers":[
        {
            "category":"Food & Beverages",
            "subcategory":"Groceries & Convenience Stores",
            "type":"Retail Goods"
        },
        {
            "category":"Food & Beverages",
            "subcategory":"Specialty",
            "type":"Retail Goods"
        }
    ],
    "sg:phone":"+1 512 451 0669",
    "sg:postcode":"78757",
    "sg:province":"TX",
    "sg:tags":[
        "health",
        "diet"
    ],
    "wof:name":"Sun Harvest Farms Inc",
    "wof:placetype":"venue"
},
  "geometry": {"coordinates":[-97.735614,30.358244],"type":"Point"}
}