{
  "type": "Feature",
  "properties": {
    "iso:country":"US",
    "sg:address":"1220 E Palestine Ave",
    "sg:city":"Palestine",
    "sg:classifiers":[
        {
            "category":"Shopping",
            "subcategory":"Discount & Variety Stores",
            "type":"Retail Goods"
        }
    ],
    "sg:phone":"+1 903 729 2831",
    "sg:postcode":"75801",
    "sg:province":"TX",
    "sg:tags":[
        "merchandise",
        "general"
    ],
    "wof:name":"J JS 107",
    "wof:placetype":"venue"
},
  "geometry": {"coordinates":[-95.61857000000001,31.776456],"type":"Point"}
}