{
  "type": "Feature",
  "properties": {
    "iso:country":"US",
    "sg:address":"1705 E Guadalupe St",
    "sg:city":"Victoria",
    "sg:classifiers":[
        {
            "category":"Shopping",
            "subcategory":"Gifts & Souvenirs",
            "type":"Retail Goods"
        }
    ],
    "sg:phone":"+1 361 897 2036",
    "sg:postcode":"77901",
    "sg:province":"TX",
    "sg:tags":[
        "shop",
        "novelty"
    ],
    "wof:name":"Victoria Womens Bowling Assn",
    "wof:placetype":"venue"
},
  "geometry": {"coordinates":[-96.984787,28.808971],"type":"Point"}
}