{
  "type": "Feature",
  "properties": {
    "iso:country":"US",
    "sg:address":"2300 Highland Village Rd",
    "sg:city":"Lewisville",
    "sg:classifiers":[
        {
            "category":"Health Services",
            "subcategory":"Doctor",
            "type":"Services"
        }
    ],
    "sg:phone":"+1 972 966 1318",
    "sg:postcode":"75077",
    "sg:province":"TX",
    "sg:tags":[
        "physician"
    ],
    "wof:name":"Pediatric & Fmly Physicians PA",
    "wof:placetype":"venue"
},
  "geometry": {"coordinates":[-97.057585,33.072181],"type":"Point"}
}