{
  "type": "Feature",
  "properties": {
    "iso:country":"US",
    "sg:address":"3801 S Capital of Texas Hwy",
    "sg:city":"Austin",
    "sg:classifiers":[
        {
            "category":"Wholesale",
            "subcategory":"Computers",
            "type":"Manufacturing & Wholesale Goods"
        }
    ],
    "sg:phone":"+1 512 428 9744",
    "sg:postcode":"78704",
    "sg:province":"TX",
    "sg:tags":[
        "mfg",
        "software"
    ],
    "wof:name":"Trimedia Austin Design Center",
    "wof:placetype":"venue"
},
  "geometry": {"coordinates":[-97.80137499999999,30.243381],"type":"Point"}
}