{
  "type": "Feature",
  "properties": {
    "iso:country":"US",
    "sg:address":"8109 Gladys Ave",
    "sg:city":"Beaumont",
    "sg:classifiers":[
        {
            "category":"Health Services",
            "subcategory":"Health Practitioner",
            "type":"Services"
        }
    ],
    "sg:phone":"+1 409 860 9397",
    "sg:postcode":"77706",
    "sg:province":"TX",
    "sg:tags":[
        "psychotherapist"
    ],
    "wof:name":"Therapy Associates",
    "wof:placetype":"venue"
},
  "geometry": {"coordinates":[-94.18213,30.091286],"type":"Point"}
}