{
  "type": "Feature",
  "properties": {
    "iso:country":"US",
    "sg:address":"15811 Darton St",
    "sg:city":"Houston",
    "sg:classifiers":[
        {
            "category":"Professional",
            "type":"Services"
        }
    ],
    "sg:phone":"+1 281 438 6057",
    "sg:postcode":"77053",
    "sg:province":"TX",
    "wof:name":"Jaetn Hill",
    "wof:placetype":"venue"
},
  "geometry": {"coordinates":[-95.46834,29.596053],"type":"Point"}
}