{
  "type": "Feature",
  "properties": {
    "iso:country":"US",
    "sg:address":"2401 Central Expy",
    "sg:city":"Plano",
    "sg:classifiers":[
        {
            "category":"Autos & Motor Vehicles",
            "subcategory":"Automobile Sales",
            "type":"Retail Goods"
        }
    ],
    "sg:phone":"+1 972 422 1100",
    "sg:postcode":"75075",
    "sg:province":"TX",
    "wof:name":"Crest Infiniti",
    "wof:placetype":"venue"
},
  "geometry": {"coordinates":[-96.70654399999999,33.034414],"type":"Point"}
}