{
  "type": "Feature",
  "properties": {
    "iso:country":"US",
    "sg:address":"505 S Erskine St",
    "sg:city":"Angleton",
    "sg:classifiers":[
        {
            "category":"Retail",
            "subcategory":"Auto Repair",
            "type":"Services"
        }
    ],
    "sg:phone":"+1 979 849 2179",
    "sg:postcode":"77515",
    "sg:province":"TX",
    "sg:tags":[
        "injection",
        "part",
        "engines-diesel-fuel"
    ],
    "wof:name":"4 & 18 Mechanic Shop",
    "wof:placetype":"venue"
},
  "geometry": {"coordinates":[-95.434567,29.160208],"type":"Point"}
}