{
  "type": "Feature",
  "properties": {
    "iso:country":"US",
    "sg:address":"306 Llano St",
    "sg:city":"Pasadena",
    "sg:classifiers":[
        {
            "category":"Organizations",
            "subcategory":"Religious Organization",
            "type":"Services"
        }
    ],
    "sg:phone":"+1 713 946 0826",
    "sg:postcode":"77504",
    "sg:province":"TX",
    "wof:name":"Fellowship Baptst Church A B A",
    "wof:placetype":"venue"
},
  "geometry": {"coordinates":[-95.20245799999999,29.654141],"type":"Point"}
}