{
  "type": "Feature",
  "properties": {
    "iso:country":"US",
    "sg:address":"10060 West Rd",
    "sg:city":"Houston",
    "sg:classifiers":[
        {
            "category":"Retail",
            "subcategory":"Car Wash",
            "type":"Services"
        }
    ],
    "sg:phone":"+1 832 237 6324",
    "sg:postcode":"77064",
    "sg:province":"TX",
    "wof:name":"Paradise Car Wash",
    "wof:placetype":"venue"
},
  "geometry": {"coordinates":[-95.567511,29.909998],"type":"Point"}
}