{
  "type": "Feature",
  "properties": {
    "iso:country":"US",
    "sg:address":"13244 Northwest Fwy",
    "sg:city":"Houston",
    "sg:classifiers":[
        {
            "category":"Shopping",
            "subcategory":"Shoes",
            "type":"Retail Goods"
        }
    ],
    "sg:phone":"+1 713 934 8535",
    "sg:postcode":"77040",
    "sg:province":"TX",
    "sg:tags":[
        "store"
    ],
    "sg:website":"www.shoecarnival.com",
    "wof:name":"Shoe Carnival",
    "wof:placetype":"venue"
},
  "geometry": {"coordinates":[-95.50379599999999,29.848526],"type":"Point"}
}