{
  "type": "Feature",
  "properties": {
    "iso:country":"US",
    "sg:address":"2717 Moon River Ln",
    "sg:city":"Dallas",
    "sg:classifiers":[
        {
            "category":"Wholesale",
            "subcategory":"Durable Goods & Equipment",
            "type":"Manufacturing & Wholesale Goods"
        }
    ],
    "sg:phone":"+1 972 243 1635",
    "sg:postcode":"75234",
    "sg:province":"TX",
    "sg:tags":[
        "representative",
        "manufacturer"
    ],
    "wof:name":"Just N Case",
    "wof:placetype":"venue"
},
  "geometry": {"coordinates":[-96.88541499999999,32.945926],"type":"Point"}
}