{
  "type": "Feature",
  "properties": {
    "iso:country":"US",
    "sg:address":"501 Bennett Ln",
    "sg:city":"Lewisville",
    "sg:classifiers":[
        {
            "category":"Building & Trades",
            "subcategory":"Plumbing",
            "type":"Services"
        }
    ],
    "sg:phone":"+1 972 420 0941",
    "sg:postcode":"75057",
    "sg:province":"TX",
    "wof:name":"AA-Amazing Fishing & Hunting Service",
    "wof:placetype":"venue"
},
  "geometry": {"coordinates":[-96.978798,33.0275],"type":"Point"}
}