{
  "type": "Feature",
  "properties": {
    "iso:country":"US",
    "sg:address":"5013 Santa Elena Ct",
    "sg:city":"Granbury",
    "sg:classifiers":[
        {
            "category":"Banks & Credit Unions",
            "subcategory":"Investment Brokerage",
            "type":"Services"
        }
    ],
    "sg:phone":"+1 817 326 4293",
    "sg:postcode":"76049",
    "sg:province":"TX",
    "sg:tags":[
        "advisory"
    ],
    "wof:name":"Becker Skaggs Financial",
    "wof:placetype":"venue"
},
  "geometry": {"coordinates":[-97.69711100000001,32.429377],"type":"Point"}
}