{
  "type": "Feature",
  "properties": {
    "iso:country":"US",
    "sg:address":"3301 NE 28th St",
    "sg:city":"Fort Worth",
    "sg:classifiers":[
        {
            "category":"Restaurant",
            "type":"Food & Drink"
        }
    ],
    "sg:phone":"+1 817 838 6199",
    "sg:postcode":"76111",
    "sg:province":"TX",
    "wof:name":"Sikhay",
    "wof:placetype":"venue"
},
  "geometry": {"coordinates":[-97.29740700000001,32.795121],"type":"Point"}
}