{
  "type": "Feature",
  "properties": {
    "iso:country":"US",
    "sg:address":"7050 Comanche Trl",
    "sg:city":"Austin",
    "sg:classifiers":[
        {
            "category":"Freight",
            "type":"Transportation"
        }
    ],
    "sg:phone":"+1 512 266 1423",
    "sg:postcode":"78732",
    "sg:province":"TX",
    "sg:tags":[
        "warehouse",
        "public"
    ],
    "wof:name":"Geisler Logistics Services",
    "wof:placetype":"venue"
},
  "geometry": {"coordinates":[-97.894555,30.414541],"type":"Point"}
}