{
  "type": "Feature",
  "properties": {
    "iso:country":"US",
    "sg:address":"416 Main St",
    "sg:city":"Houston",
    "sg:classifiers":[
        {
            "category":"Restaurant",
            "type":"Food & Drink"
        }
    ],
    "sg:phone":"+1 713 228 7222",
    "sg:postcode":"77002",
    "sg:province":"TX",
    "sg:tags":[
        "eating"
    ],
    "wof:name":"Saba Blue Water Cafe",
    "wof:placetype":"venue"
},
  "geometry": {"coordinates":[-95.36170199999999,29.7612],"type":"Point"}
}