{
  "type": "Feature",
  "properties": {
    "iso:country":"US",
    "sg:address":"5314 Oak Cove Dr",
    "sg:city":"Houston",
    "sg:classifiers":[
        {
            "category":"Shopping",
            "subcategory":"Gifts & Souvenirs",
            "type":"Retail Goods"
        }
    ],
    "sg:phone":"+1 713 681 2253",
    "sg:postcode":"77091",
    "sg:province":"TX",
    "wof:name":"Vela Real Creations By Lu",
    "wof:placetype":"venue"
},
  "geometry": {"coordinates":[-95.464378,29.856514],"type":"Point"}
}