{
  "type": "Feature",
  "properties": {
    "iso:country":"US",
    "sg:address":"10713 FM 620 N",
    "sg:city":"Austin",
    "sg:classifiers":[
        {
            "category":"Insurance",
            "subcategory":"Insurance Agent",
            "type":"Services"
        }
    ],
    "sg:phone":"+1 512 506 9132",
    "sg:postcode":"78726",
    "sg:province":"TX",
    "wof:name":"Allstate Insurance",
    "wof:placetype":"venue"
},
  "geometry": {"coordinates":[-97.83199999999999,30.446038],"type":"Point"}
}