{
  "type": "Feature",
  "properties": {
    "iso:country":"US",
    "sg:address":"9000 Airport Blvd",
    "sg:city":"Houston",
    "sg:classifiers":[
        {
            "category":"Travel",
            "subcategory":"Hotels & Motels",
            "type":"Entertainment"
        }
    ],
    "sg:phone":"+1 713 943 0035",
    "sg:postcode":"77061",
    "sg:province":"TX",
    "wof:name":"Comfort Inn",
    "wof:placetype":"venue"
},
  "geometry": {"coordinates":[-95.257768,29.652112],"type":"Point"}
}