{
  "type": "Feature",
  "properties": {
    "iso:country":"US",
    "sg:address":"1390 N. Main St. Apt#2724",
    "sg:city":"Euless",
    "sg:classifiers":[
        {
            "category":"Utilities",
            "subcategory":"Electric",
            "type":"Services"
        }
    ],
    "sg:phone":"+1 817 896 5322",
    "sg:postcode":"76039",
    "sg:province":"TX",
    "sg:tags":[
        "equipment",
        "supplies-repair",
        "electronic"
    ],
    "wof:name":"Suneel Ali",
    "wof:placetype":"venue"
},
  "geometry": {"coordinates":[-97.08251300000001,32.855432],"type":"Point"}
}