{
  "type": "Feature",
  "properties": {
    "iso:country":"US",
    "sg:address":"5 Lynx Ln",
    "sg:city":"Spring",
    "sg:classifiers":[
        {
            "category":"Social Services",
            "type":"Services"
        }
    ],
    "sg:phone":"+1 281 367 3108",
    "sg:postcode":"77380",
    "sg:province":"TX",
    "wof:name":"Personal Solutions",
    "wof:placetype":"venue"
},
  "geometry": {"coordinates":[-95.461186,30.134579],"type":"Point"}
}