{
  "type": "Feature",
  "properties": {
    "iso:country":"US",
    "sg:address":"1019 S Belt Line Rd",
    "sg:city":"Mesquite",
    "sg:classifiers":[
        {
            "category":"Retail",
            "subcategory":"Auto Repair",
            "type":"Services"
        }
    ],
    "sg:phone":"+1 972 289 9313",
    "sg:postcode":"75149",
    "sg:province":"TX",
    "sg:tags":[
        "transmission",
        "automotive",
        "shop"
    ],
    "wof:name":"Reliable Autmtc & Std Transm",
    "wof:placetype":"venue"
},
  "geometry": {"coordinates":[-96.59696099999999,32.755496],"type":"Point"}
}