{
  "type": "Feature",
  "properties": {
    "iso:country":"US",
    "sg:address":"800 Basse Rd",
    "sg:city":"San Antonio",
    "sg:classifiers":[
        {
            "category":"Real Estate",
            "subcategory":"Real Estate Operator",
            "type":"Services"
        }
    ],
    "sg:phone":"+1 210 733 6303",
    "sg:postcode":"78212",
    "sg:province":"TX",
    "sg:tags":[
        "building",
        "apartment"
    ],
    "wof:name":"Olmos Club",
    "wof:placetype":"venue"
},
  "geometry": {"coordinates":[-98.499253,29.488135],"type":"Point"}
}