{
  "type": "Feature",
  "properties": {
    "iso:country":"US",
    "sg:address":"2200 Watercrest Dr",
    "sg:city":"Keller",
    "sg:classifiers":[
        {
            "category":"Social Services",
            "type":"Services"
        }
    ],
    "sg:phone":"+1 817 337 1665",
    "sg:postcode":"76248",
    "sg:province":"TX",
    "wof:name":"Q4 Learning Inc",
    "wof:placetype":"venue"
},
  "geometry": {"coordinates":[-97.199725,32.924968],"type":"Point"}
}