{
  "type": "Feature",
  "properties": {
    "iso:country":"US",
    "sg:address":"13923 E Creek Dr",
    "sg:city":"Sugar Land",
    "sg:classifiers":[
        {
            "category":"Building & Trades",
            "subcategory":"Construction",
            "type":"Services"
        }
    ],
    "sg:phone":"+1 281 242 0685",
    "sg:postcode":"77478",
    "sg:province":"TX",
    "sg:tags":[
        "house"
    ],
    "wof:name":"Mireles Construction Co",
    "wof:placetype":"venue"
},
  "geometry": {"coordinates":[-95.632352,29.668845],"type":"Point"}
}