{
  "type": "Feature",
  "properties": {
    "iso:country":"US",
    "sg:address":"2900 Woodridge Dr",
    "sg:city":"Houston",
    "sg:classifiers":[
        {
            "category":"Banks & Credit Unions",
            "subcategory":"Bank",
            "type":"Services"
        }
    ],
    "sg:phone":"+1 713 216 7000",
    "sg:postcode":"77087",
    "sg:province":"TX",
    "wof:name":"Chase Bank of Texas Na",
    "wof:placetype":"venue"
},
  "geometry": {"coordinates":[-95.29650100000001,29.700899],"type":"Point"}
}