{
  "type": "Feature",
  "properties": {
    "iso:country":"US",
    "sg:address":"3701 Kirby Dr Ste 800",
    "sg:city":"Houston",
    "sg:classifiers":[
        {
            "category":"Real Estate",
            "subcategory":"Architect",
            "type":"Services"
        }
    ],
    "sg:phone":"+1 713 523 2289",
    "sg:postcode":"77098",
    "sg:province":"TX",
    "wof:name":"Edgecomb & Associates Inc",
    "wof:placetype":"venue"
},
  "geometry": {"coordinates":[-95.41804999999999,29.733119],"type":"Point"}
}