{
  "type": "Feature",
  "properties": {
    "iso:country":"US",
    "sg:address":"1507 N Austin St",
    "sg:city":"Comanche",
    "sg:classifiers":[
        {
            "category":"Organizations",
            "subcategory":"Religious Organization",
            "type":"Services"
        }
    ],
    "sg:phone":"+1 325 356 1021",
    "sg:postcode":"76442",
    "sg:province":"TX",
    "sg:tags":[
        "church"
    ],
    "wof:name":"Church Of Jesus Christ Of Lds",
    "wof:placetype":"venue"
},
  "geometry": {"coordinates":[-98.596734,31.911902],"type":"Point"}
}