{
  "type": "Feature",
  "properties": {
    "iso:country":"US",
    "sg:address":"6115 Old Oak Cir",
    "sg:city":"Sugar Land",
    "sg:classifiers":[
        {
            "category":"Real Estate",
            "subcategory":"Real Estate Operator",
            "type":"Services"
        }
    ],
    "sg:phone":"+1 281 499 2304",
    "sg:postcode":"77479",
    "sg:province":"TX",
    "sg:tags":[
        "building",
        "nonresidential"
    ],
    "wof:name":"Pecan Manor Property Owners",
    "wof:placetype":"venue"
},
  "geometry": {"coordinates":[-95.594388,29.536597],"type":"Point"}
}