{
  "type": "Feature",
  "properties": {
    "iso:country":"US",
    "sg:address":"4724 Alcott St",
    "sg:city":"Dallas",
    "sg:classifiers":[
        {
            "category":"Building & Trades",
            "subcategory":"Cleaning & Sanitation",
            "type":"Services"
        }
    ],
    "sg:phone":"+1 214 821 0388",
    "sg:postcode":"75204",
    "sg:province":"TX",
    "sg:tags":[
        "maintenance"
    ],
    "wof:name":"Rv Maintenance",
    "wof:placetype":"venue"
},
  "geometry": {"coordinates":[-96.787083,32.814757],"type":"Point"}
}