{
  "type": "Feature",
  "properties": {
    "iso:country":"US",
    "sg:address":"1905 N Lamar Blvd",
    "sg:city":"Austin",
    "sg:classifiers":[
        {
            "category":"Real Estate",
            "subcategory":"Real Estate Agent",
            "type":"Services"
        }
    ],
    "sg:phone":"+1 512 320 8500",
    "sg:postcode":"78705",
    "sg:province":"TX",
    "sg:tags":[
        "business"
    ],
    "wof:name":"Residential Valuation",
    "wof:placetype":"venue"
},
  "geometry": {"coordinates":[-97.752863,30.284855],"type":"Point"}
}