{
  "type": "Feature",
  "properties": {
    "iso:country":"US",
    "sg:address":"1005 The Cliffs Blvd",
    "sg:city":"Montgomery",
    "sg:classifiers":[
        {
            "category":"Banks & Credit Unions",
            "subcategory":"Bank",
            "type":"Services"
        }
    ],
    "sg:phone":"+1 936 448 1090",
    "sg:postcode":"77356",
    "sg:province":"TX",
    "sg:tags":[
        "financing"
    ],
    "wof:name":"Cit Group Inc",
    "wof:placetype":"venue"
},
  "geometry": {"coordinates":[-95.63324900000001,30.38209],"type":"Point"}
}