{
  "type": "Feature",
  "properties": {
    "iso:country":"US",
    "sg:address":"104 E 9th St",
    "sg:city":"Pecos",
    "sg:classifiers":[
        {
            "category":"Personal",
            "subcategory":"Barber",
            "type":"Services"
        }
    ],
    "sg:phone":"+1 432 445 3224",
    "sg:postcode":"79772",
    "sg:province":"TX",
    "sg:tags":[
        "shop"
    ],
    "wof:name":"Woody's Way Barber Salon",
    "wof:placetype":"venue"
},
  "geometry": {"coordinates":[-103.491623,31.419968],"type":"Point"}
}