{
  "type": "Feature",
  "properties": {
    "iso:country":"US",
    "sg:address":"6001 Antoine Dr",
    "sg:city":"Houston",
    "sg:classifiers":[
        {
            "category":"Manufacturing",
            "subcategory":"Metals",
            "type":"Manufacturing & Wholesale Goods"
        },
        {
            "category":"Manufacturing",
            "subcategory":"Chemicals & Compounds",
            "type":"Manufacturing & Wholesale Goods"
        }
    ],
    "sg:phone":"+1 713 682 1711",
    "sg:postcode":"77091",
    "sg:province":"TX",
    "sg:tags":[
        "paint",
        "coating",
        "sale",
        "mfg"
    ],
    "sg:website":"www.internationalpaint.com",
    "wof:name":"International Paint Inc",
    "wof:placetype":"venue"
},
  "geometry": {"coordinates":[-95.473377,29.85419],"type":"Point"}
}