{
  "type": "Feature",
  "properties": {
    "iso:country":"US",
    "sg:address":"1300 Guadalupe St",
    "sg:city":"Austin",
    "sg:classifiers":[
        {
            "category":"Organizations",
            "subcategory":"Professional Association",
            "type":"Services"
        }
    ],
    "sg:phone":"+1 512 479 5000",
    "sg:postcode":"78701",
    "sg:province":"TX",
    "wof:name":"Texas Land & Mineral Owners",
    "wof:placetype":"venue"
},
  "geometry": {"coordinates":[-97.743335,30.27694],"type":"Point"}
}