{
  "type": "Feature",
  "properties": {
    "iso:country":"US",
    "sg:address":"8181 Eastpoint Dr",
    "sg:city":"Dallas",
    "sg:classifiers":[
        {
            "category":"Wholesale",
            "subcategory":"Medical Equipment & Supplies",
            "type":"Manufacturing & Wholesale Goods"
        },
        {
            "category":"Shopping",
            "subcategory":"Pharmacy",
            "type":"Retail Goods"
        }
    ],
    "sg:phone":"+1 214 275 6748",
    "sg:postcode":"75227",
    "sg:province":"TX",
    "sg:tags":[
        "home",
        "health",
        "care"
    ],
    "wof:name":"Pcitechnology",
    "wof:placetype":"venue"
},
  "geometry": {"coordinates":[-96.682304,32.785044],"type":"Point"}
}