{
  "type": "Feature",
  "properties": {
    "iso:country":"US",
    "sg:address":"1633 Richey St",
    "sg:city":"Pasadena",
    "sg:classifiers":[
        {
            "category":"Manufacturing",
            "subcategory":"Food",
            "type":"Manufacturing & Wholesale Goods"
        }
    ],
    "sg:phone":"+1 713 472 1340",
    "sg:postcode":"77502",
    "sg:province":"TX",
    "sg:tags":[
        "product",
        "mfg"
    ],
    "wof:name":"Mrs Bairds Bakeries",
    "wof:placetype":"venue"
},
  "geometry": {"coordinates":[-95.220275,29.68827],"type":"Point"}
}