{
  "type": "Feature",
  "properties": {
    "iso:country":"US",
    "sg:address":"103 Woodbine Pl",
    "sg:city":"Longview",
    "sg:classifiers":[
        {
            "category":"Organizations",
            "subcategory":"Non-profit Organization",
            "type":"Services"
        }
    ],
    "sg:phone":"+1 903 758 0596",
    "sg:postcode":"75601",
    "sg:province":"TX",
    "sg:tags":[
        "info",
        "addiction",
        "abuse",
        "treatment",
        "drug"
    ],
    "wof:name":"Woodbine Treatment Ctr",
    "wof:placetype":"venue"
},
  "geometry": {"coordinates":[-94.744288,32.526004],"type":"Point"}
}