{
  "type": "Feature",
  "properties": {
    "iso:country":"US",
    "sg:address":"4108 Shagbark St",
    "sg:city":"Fort Worth",
    "sg:classifiers":[
        {
            "category":"Building & Trades",
            "subcategory":"Landscaping Services",
            "type":"Services"
        }
    ],
    "sg:phone":"+1 817 847 0636",
    "sg:postcode":"76137",
    "sg:province":"TX",
    "wof:name":"Boyd & Son Lawn Care",
    "wof:placetype":"venue"
},
  "geometry": {"coordinates":[-97.29621299999999,32.876763],"type":"Point"}
}