{
  "type": "Feature",
  "properties": {
    "iso:country":"US",
    "sg:address":"1821 Judson Rd",
    "sg:city":"Longview",
    "sg:classifiers":[
        {
            "category":"Wholesale",
            "subcategory":"Chemicals & Plastics",
            "type":"Manufacturing & Wholesale Goods"
        }
    ],
    "sg:phone":"+1 903 757 3358",
    "sg:postcode":"75605",
    "sg:province":"TX",
    "sg:tags":[
        "cleaning",
        "compound"
    ],
    "wof:name":"Mingo Sales & Svc Co",
    "wof:placetype":"venue"
},
  "geometry": {"coordinates":[-94.742667,32.527379],"type":"Point"}
}