{
  "type": "Feature",
  "properties": {
    "iso:country":"US",
    "sg:address":"9002 Wayfarer Ln",
    "sg:city":"Houston",
    "sg:classifiers":[
        {
            "category":"Wholesale",
            "subcategory":"Hardware",
            "type":"Manufacturing & Wholesale Goods"
        },
        {
            "category":"Home & Garden",
            "subcategory":"Garden Supply",
            "type":"Retail Goods"
        },
        {
            "category":"Retail",
            "subcategory":"Repair Shop",
            "type":"Services"
        }
    ],
    "sg:phone":"+1 713 991 9800",
    "sg:postcode":"77075",
    "sg:province":"TX",
    "sg:tags":[
        "renting",
        "lawn",
        "outdoor",
        "power",
        "landscaping",
        "equipment-sales",
        "equipment",
        "saw"
    ],
    "sg:website":"http://www.stihlusa.com/",
    "wof:name":"NTS Mikedon",
    "wof:placetype":"venue"
},
  "geometry": {"coordinates":[-95.255545,29.618521],"type":"Point"}
}