{
  "type": "Feature",
  "properties": {
    "iso:country":"US",
    "sg:address":"102 N Main St",
    "sg:city":"Dawson",
    "sg:classifiers":[
        {
            "category":"Professional",
            "subcategory":"Engineering",
            "type":"Services"
        }
    ],
    "sg:phone":"+1 254 578 3005",
    "sg:postcode":"76639",
    "sg:province":"TX",
    "sg:tags":[
        "system",
        "equipment",
        "air conditioning"
    ],
    "wof:name":"Country Air Service",
    "wof:placetype":"venue"
},
  "geometry": {"coordinates":[-96.71500899999999,31.893907],"type":"Point"}
}