{
  "type": "Feature",
  "properties": {
    "iso:country":"US",
    "sg:address":"2909 N Henderson Ave",
    "sg:city":"Dallas",
    "sg:classifiers":[
        {
            "category":"Shopping",
            "subcategory":"Antiques",
            "type":"Retail Goods"
        }
    ],
    "sg:phone":"+1 214 828 0624",
    "sg:postcode":"75206",
    "sg:province":"TX",
    "sg:website":"www.nickbrock.com",
    "wof:name":"Brock Nick Antiques",
    "wof:placetype":"venue"
},
  "geometry": {"coordinates":[-96.785004,32.8204],"type":"Point"}
}