{
  "type": "Feature",
  "properties": {
    "iso:country":"US",
    "sg:address":"4647 Bronze Way",
    "sg:city":"Dallas",
    "sg:classifiers":[
        {
            "category":"Manufacturing",
            "subcategory":"Food",
            "type":"Manufacturing & Wholesale Goods"
        }
    ],
    "sg:phone":"+1 214 339 5551",
    "sg:postcode":"75236",
    "sg:province":"TX",
    "sg:tags":[
        "preparation",
        "mfg"
    ],
    "wof:name":"Nakano Foods Inc",
    "wof:placetype":"venue"
},
  "geometry": {"coordinates":[-96.89445000000001,32.687337],"type":"Point"}
}