{
  "type": "Feature",
  "properties": {
    "iso:country":"US",
    "sg:address":"5406 E Lancaster Ave",
    "sg:city":"Fort Worth",
    "sg:classifiers":[
        {
            "category":"Retail",
            "subcategory":"Repair Shop",
            "type":"Services"
        }
    ],
    "sg:phone":"+1 817 535 7040",
    "sg:postcode":"76112",
    "sg:province":"TX",
    "sg:tags":[
        "upholsterer"
    ],
    "wof:name":"Elegance Upholstery",
    "wof:placetype":"venue"
},
  "geometry": {"coordinates":[-97.236799,32.738948],"type":"Point"}
}