{
  "type": "Feature",
  "properties": {
    "iso:country":"US",
    "sg:address":"8530 Braun Rd",
    "sg:city":"San Antonio",
    "sg:classifiers":[
        {
            "category":"Insurance",
            "subcategory":"Insurance Agent",
            "type":"Services"
        }
    ],
    "sg:phone":"+1 210 509 7111",
    "sg:postcode":"78254",
    "sg:province":"TX",
    "wof:name":"Allstate Insurance Co",
    "wof:placetype":"venue"
},
  "geometry": {"coordinates":[-98.656443,29.531632],"type":"Point"}
}