{
  "type": "Feature",
  "properties": {
    "iso:country":"US",
    "sg:address":"4851 Lyndon B Johnson Fwy Ste 220",
    "sg:city":"Dallas",
    "sg:classifiers":[
        {
            "category":"Real Estate",
            "subcategory":"Real Estate Services",
            "type":"Services"
        }
    ],
    "sg:phone":"+1 469 461 5350",
    "sg:postcode":"75244",
    "sg:province":"TX",
    "sg:tags":[
        "management",
        "property"
    ],
    "wof:name":"Jones Lang Lasalle Americas Inc",
    "wof:placetype":"venue"
},
  "geometry": {"coordinates":[-96.823995,32.926654],"type":"Point"}
}