{
  "type": "Feature",
  "properties": {
    "iso:country":"US",
    "sg:address":"2307 Goldenrod St",
    "sg:city":"Highlands",
    "sg:classifiers":[
        {
            "category":"Shopping",
            "subcategory":"Hobbies, Toys, & Games",
            "type":"Retail Goods"
        }
    ],
    "sg:phone":"+1 281 426 4471",
    "sg:postcode":"77562",
    "sg:province":"TX",
    "wof:name":"Precious Tiers of Joy",
    "wof:placetype":"venue"
},
  "geometry": {"coordinates":[-95.025863,29.822039],"type":"Point"}
}