{
  "type": "Feature",
  "properties": {
    "iso:country":"US",
    "sg:address":"701 N Kilgore St",
    "sg:city":"Kilgore",
    "sg:classifiers":[
        {
            "category":"Shopping",
            "subcategory":"Gifts & Souvenirs",
            "type":"Retail Goods"
        }
    ],
    "sg:phone":"+1 903 984 3137",
    "sg:postcode":"75662",
    "sg:province":"TX",
    "wof:name":"Penny Patch",
    "wof:placetype":"venue"
},
  "geometry": {"coordinates":[-94.87121,32.39019],"type":"Point"}
}