{
  "type": "Feature",
  "properties": {
    "iso:country":"US",
    "sg:address":"1300 E Calton Rd",
    "sg:city":"Laredo",
    "sg:classifiers":[
        {
            "category":"Real Estate",
            "subcategory":"Real Estate Operator",
            "type":"Services"
        }
    ],
    "sg:phone":"+1 956 727 5705",
    "sg:postcode":"78041",
    "sg:province":"TX",
    "sg:tags":[
        "building",
        "apartment"
    ],
    "wof:name":"Cherry Hill Apartments",
    "wof:placetype":"venue"
},
  "geometry": {"coordinates":[-99.479713,27.540819],"type":"Point"}
}