{
  "type": "Feature",
  "properties": {
    "iso:country":"US",
    "sg:address":"900 Bay Ave",
    "sg:city":"Seadrift",
    "sg:classifiers":[
        {
            "category":"Real Estate",
            "subcategory":"Real Estate Agent",
            "type":"Services"
        }
    ],
    "sg:phone":"+1 361 785 6151",
    "sg:postcode":"77983",
    "sg:province":"TX",
    "wof:name":"Russell Cain Real Estate",
    "wof:placetype":"venue"
},
  "geometry": {"coordinates":[-96.721177,28.40915],"type":"Point"}
}