{
  "type": "Feature",
  "properties": {
    "iso:country":"US",
    "sg:address":"8725 Marbach Rd",
    "sg:city":"San Antonio",
    "sg:classifiers":[
        {
            "category":"Health Services",
            "subcategory":"Doctor",
            "type":"Services"
        }
    ],
    "sg:phone":"+1 210 674 2222",
    "sg:postcode":"78227",
    "sg:province":"TX",
    "sg:tags":[
        "clinic"
    ],
    "wof:name":"Planned Parenthood",
    "wof:placetype":"venue"
},
  "geometry": {"coordinates":[-98.65773900000001,29.417835],"type":"Point"}
}