{
  "type": "Feature",
  "properties": {
    "iso:country":"US",
    "sg:address":"10100 Hicks Field Rd",
    "sg:city":"Fort Worth",
    "sg:classifiers":[
        {
            "category":"Wholesale",
            "subcategory":"Motor Vehicles",
            "type":"Manufacturing & Wholesale Goods"
        }
    ],
    "sg:phone":"+1 817 306 8969",
    "sg:postcode":"76179",
    "sg:province":"TX",
    "sg:tags":[
        "automobile",
        "truck",
        "broker"
    ],
    "wof:name":"Midtex Logistics",
    "wof:placetype":"venue"
},
  "geometry": {"coordinates":[-97.401414,32.9053],"type":"Point"}
}