{
  "type": "Feature",
  "properties": {
    "iso:country":"US",
    "sg:address":"18 Mullaney Dr",
    "sg:city":"Greenville",
    "sg:classifiers":[
        {
            "category":"Organizations",
            "subcategory":"Membership Organization",
            "type":"Services"
        }
    ],
    "sg:phone":"+1 903 450 9262",
    "sg:postcode":"75402",
    "sg:province":"TX",
    "wof:name":"Nationl Scty Dghtrs Amer Revo",
    "wof:placetype":"venue"
},
  "geometry": {"coordinates":[-96.0813,33.107245],"type":"Point"}
}