{
  "type": "Feature",
  "properties": {
    "iso:country":"US",
    "sg:address":"23694 W Hwy 6",
    "sg:city":"Alvin",
    "sg:classifiers":[
        {
            "category":"Freight",
            "type":"Transportation"
        }
    ],
    "sg:phone":"+1 281 331 5239",
    "sg:postcode":"77511",
    "sg:province":"TX",
    "sg:tags":[
        "general"
    ],
    "wof:name":"Alvin Parkway Mini Storage",
    "wof:placetype":"venue"
},
  "geometry": {"coordinates":[-95.250118,29.430968],"type":"Point"}
}