{
  "type": "Feature",
  "properties": {
    "iso:country":"US",
    "sg:address":"5050 Benbrook Blvd",
    "sg:city":"Benbrook",
    "sg:classifiers":[
        {
            "category":"Building & Trades",
            "subcategory":"Landscaping Services",
            "type":"Services"
        },
        {
            "category":"Home & Garden",
            "subcategory":"Garden Supply",
            "type":"Retail Goods"
        },
        {
            "category":"Shopping",
            "subcategory":"Crafts & Fabrics",
            "type":"Retail Goods"
        },
        {
            "category":"Manufacturing",
            "subcategory":"Paper Products",
            "type":"Manufacturing & Wholesale Goods"
        },
        {
            "category":"Farming",
            "subcategory":"Nursery",
            "type":"Manufacturing & Wholesale Goods"
        }
    ],
    "sg:phone":"+1 817 244 2109",
    "sg:postcode":"76116",
    "sg:province":"TX",
    "sg:tags":[
        "lawn",
        "florists'",
        "nurseries-plants",
        "tree",
        "florist",
        "bamboo",
        "supplies-wholesale",
        "manufacturer"
    ],
    "wof:name":"The Plant Shed",
    "wof:placetype":"venue"
},
  "geometry": {"coordinates":[-97.45289200000001,32.699532],"type":"Point"}
}