{
  "type": "Feature",
  "properties": {
    "iso:country":"US",
    "sg:address":"47 Valley View Rd",
    "sg:city":"Canyon",
    "sg:classifiers":[
        {
            "category":"Real Estate",
            "subcategory":"Real Estate Operator",
            "type":"Services"
        }
    ],
    "sg:phone":"+1 806 316 5519",
    "sg:postcode":"79015",
    "sg:province":"TX",
    "sg:tags":[
        "apartment"
    ],
    "sg:website":"www.collegiatestation.com/apartm...",
    "wof:name":"Collegiate Station Apartments",
    "wof:placetype":"venue"
},
  "geometry": {"coordinates":[-101.901746,34.982741],"type":"Point"}
}