{
  "type": "Feature",
  "properties": {
    "iso:country":"US",
    "sg:address":"2305 Sheppard Access Rd",
    "sg:city":"Wichita Falls",
    "sg:classifiers":[
        {
            "category":"Retail",
            "subcategory":"Auto Repair",
            "type":"Services"
        }
    ],
    "sg:phone":"+1 940 766 0805",
    "sg:postcode":"76306",
    "sg:province":"TX",
    "sg:tags":[
        "general"
    ],
    "wof:name":"Pradels Auto Service",
    "wof:placetype":"venue"
},
  "geometry": {"coordinates":[-98.511978,33.940317],"type":"Point"}
}