{
  "type": "Feature",
  "properties": {
    "iso:country":"US",
    "sg:address":"3014 Elsbury Ln",
    "sg:city":"Pearland",
    "sg:classifiers":[
        {
            "category":"Professional",
            "subcategory":"Computer Services",
            "type":"Services"
        }
    ],
    "sg:phone":"+1 281 412 2785",
    "sg:postcode":"77584",
    "sg:province":"TX",
    "sg:tags":[
        "related"
    ],
    "wof:name":"Mm Consulting",
    "wof:placetype":"venue"
},
  "geometry": {"coordinates":[-95.360409,29.541062],"type":"Point"}
}