{
  "type": "Feature",
  "properties": {
    "iso:country":"US",
    "sg:address":"4 Windmere Pl",
    "sg:city":"Texarkana",
    "sg:classifiers":[
        {
            "category":"Professional",
            "subcategory":"Detective & Security Services",
            "type":"Services"
        }
    ],
    "sg:phone":"+1 903 832 8924",
    "sg:postcode":"75503",
    "sg:province":"TX",
    "sg:tags":[
        "car"
    ],
    "wof:name":"Johnson Investigations Inc",
    "wof:placetype":"venue"
},
  "geometry": {"coordinates":[-94.105428,33.464687],"type":"Point"}
}