{
  "type": "Feature",
  "properties": {
    "iso:country":"US",
    "sg:address":"2328 W Vickery Blvd",
    "sg:city":"Fort Worth",
    "sg:classifiers":[
        {
            "category":"Autos & Motor Vehicles",
            "subcategory":"Automobile Sales",
            "type":"Retail Goods"
        }
    ],
    "sg:phone":"+1 817 810 9390",
    "sg:postcode":"76102",
    "sg:province":"TX",
    "sg:tags":[
        "used"
    ],
    "wof:name":"Planet Auto",
    "wof:placetype":"venue"
},
  "geometry": {"coordinates":[-97.35222899999999,32.736813],"type":"Point"}
}