{
  "type": "Feature",
  "properties": {
    "iso:country":"US",
    "sg:address":"804 W Arkansas Ln",
    "sg:city":"Arlington",
    "sg:classifiers":[
        {
            "category":"Personal",
            "subcategory":"Beauty Salon",
            "type":"Services"
        }
    ],
    "sg:phone":"+1 817 303 5777",
    "sg:postcode":"76013",
    "sg:province":"TX",
    "sg:tags":[
        "nail",
        "manicuring"
    ],
    "wof:name":"Vogue Nails",
    "wof:placetype":"venue"
},
  "geometry": {"coordinates":[-97.11562600000001,32.70644],"type":"Point"}
}