{
  "type": "Feature",
  "properties": {
    "iso:country":"US",
    "sg:address":"2200 Post Oak Blvd",
    "sg:city":"Houston",
    "sg:classifiers":[
        {
            "category":"Mining & Drilling",
            "type":"Manufacturing & Wholesale Goods"
        }
    ],
    "sg:phone":"+1 713 877 1906",
    "sg:postcode":"77056",
    "sg:province":"TX",
    "sg:tags":[
        "crude",
        "production",
        "gas"
    ],
    "wof:name":"L B Windham Inc",
    "wof:placetype":"venue"
},
  "geometry": {"coordinates":[-95.461074,29.74494],"type":"Point"}
}