{
  "type": "Feature",
  "properties": {
    "iso:country":"US",
    "sg:address":"9421 Fm 2920 Rd",
    "sg:city":"Tomball",
    "sg:classifiers":[
        {
            "category":"Autos & Motor Vehicles",
            "subcategory":"Automobile Sales",
            "type":"Retail Goods"
        }
    ],
    "sg:phone":"+1 281 255 4900",
    "sg:postcode":"77375",
    "sg:province":"TX",
    "sg:tags":[
        "new",
        "used",
        "car"
    ],
    "wof:name":"Retro Motorworks",
    "wof:placetype":"venue"
},
  "geometry": {"coordinates":[-95.566751,30.08424],"type":"Point"}
}