{
  "type": "Feature",
  "properties": {
    "iso:country":"US",
    "sg:address":"3205 Coit Rd",
    "sg:city":"Plano",
    "sg:classifiers":[
        {
            "category":"Shopping",
            "subcategory":"Used Merchandise",
            "type":"Retail Goods"
        }
    ],
    "sg:phone":"+1 972 769 9297",
    "sg:postcode":"75075",
    "sg:province":"TX",
    "sg:tags":[
        "clothing"
    ],
    "wof:name":"Consigning Women",
    "wof:placetype":"venue"
},
  "geometry": {"coordinates":[-96.770152,33.040655],"type":"Point"}
}