{
  "type": "Feature",
  "properties": {
    "iso:country":"US",
    "sg:address":"7879 Ranch Rd 3237",
    "sg:city":"Driftwood",
    "sg:classifiers":[
        {
            "category":"Wholesale",
            "subcategory":"Plants",
            "type":"Manufacturing & Wholesale Goods"
        },
        {
            "category":"Farming",
            "subcategory":"Nursery",
            "type":"Manufacturing & Wholesale Goods"
        }
    ],
    "sg:phone":"+1 512 847 2361",
    "sg:postcode":"78676",
    "sg:province":"TX",
    "sg:tags":[
        "ornamental",
        "tree"
    ],
    "wof:name":"Wild About You",
    "wof:placetype":"venue"
},
  "geometry": {"coordinates":[-98.032725,30.039285],"type":"Point"}
}