{
  "type": "Feature",
  "properties": {
    "iso:country":"US",
    "sg:address":"209 Skylark St",
    "sg:city":"Mesquite",
    "sg:classifiers":[
        {
            "category":"Retail",
            "subcategory":"Repair Shop",
            "type":"Services"
        }
    ],
    "sg:phone":"+1 972 285 9993",
    "sg:postcode":"75149",
    "sg:province":"TX",
    "sg:tags":[
        "equipment",
        "conditioning",
        "air"
    ],
    "wof:name":"Thermal Choice AC",
    "wof:placetype":"venue"
},
  "geometry": {"coordinates":[-96.640968,32.769472],"type":"Point"}
}