{
  "type": "Feature",
  "properties": {
    "iso:country":"US",
    "sg:address":"2001 Post Oak Rd",
    "sg:city":"Hutchins",
    "sg:classifiers":[
        {
            "category":"Utilities",
            "subcategory":"Telephone",
            "type":"Services"
        }
    ],
    "sg:phone":"+1 972 225 8460",
    "sg:postcode":"75141",
    "sg:province":"TX",
    "sg:tags":[
        "telecommunication"
    ],
    "wof:name":"American Tower Corp",
    "wof:placetype":"venue"
},
  "geometry": {"coordinates":[-96.678269,32.642115],"type":"Point"}
}