{
  "type": "Feature",
  "properties": {
    "iso:country":"US",
    "sg:address":"1823 Glen Arbor Dr",
    "sg:city":"Tyler",
    "sg:classifiers":[
        {
            "category":"Professional",
            "type":"Services"
        }
    ],
    "sg:phone":"+1 903 561 0519",
    "sg:postcode":"75703",
    "sg:province":"TX",
    "wof:name":"Gary Fleet",
    "wof:placetype":"venue"
},
  "geometry": {"coordinates":[-95.27945699999999,32.306841],"type":"Point"}
}