{
  "type": "Feature",
  "properties": {
    "iso:country":"US",
    "sg:address":"14340 Torrey Chase Blvd",
    "sg:city":"Houston",
    "sg:classifiers":[
        {
            "category":"Manufacturing",
            "subcategory":"Watercraft",
            "type":"Manufacturing & Wholesale Goods"
        }
    ],
    "sg:phone":"+1 281 880 6820",
    "sg:postcode":"77014",
    "sg:province":"TX",
    "wof:name":"Laird Cammell",
    "wof:placetype":"venue"
},
  "geometry": {"coordinates":[-95.491437,29.98504],"type":"Point"}
}