{
  "type": "Feature",
  "properties": {
    "iso:country":"US",
    "sg:address":"1708 Markley Ln",
    "sg:city":"Laredo",
    "sg:classifiers":[
        {
            "category":"Freight",
            "type":"Transportation"
        }
    ],
    "sg:phone":"+1 956 753 6225",
    "sg:postcode":"78041",
    "sg:province":"TX",
    "sg:tags":[
        "arrangement"
    ],
    "wof:name":"Rensa Forwarding",
    "wof:placetype":"venue"
},
  "geometry": {"coordinates":[-99.512598,27.540862],"type":"Point"}
}