{
  "type": "Feature",
  "properties": {
    "iso:country":"US",
    "sg:address":"307 de Vaca Dr",
    "sg:city":"Universal City",
    "sg:classifiers":[
        {
            "category":"Professional",
            "type":"Services"
        }
    ],
    "sg:phone":"+1 210 658 2926",
    "sg:postcode":"78148",
    "sg:province":"TX",
    "wof:name":"French Seam Inc",
    "wof:placetype":"venue"
},
  "geometry": {"coordinates":[-98.31467600000001,29.550749],"type":"Point"}
}