{
  "type": "Feature",
  "properties": {
    "iso:country":"US",
    "sg:address":"9709 Burleson Dr",
    "sg:city":"Dallas",
    "sg:classifiers":[
        {
            "category":"Manufacturing",
            "subcategory":"Chemicals & Compounds",
            "type":"Manufacturing & Wholesale Goods"
        }
    ],
    "sg:phone":"+1 972 669 1026",
    "sg:postcode":"75243",
    "sg:province":"TX",
    "sg:tags":[
        "mfg",
        "plastic"
    ],
    "wof:name":"Jem Plas",
    "wof:placetype":"venue"
},
  "geometry": {"coordinates":[-96.721559,32.917288],"type":"Point"}
}