{
  "type": "Feature",
  "properties": {
    "iso:country":"US",
    "sg:address":"4336 Wilson Rd",
    "sg:city":"Lumberton",
    "sg:classifiers":[
        {
            "category":"Freight",
            "type":"Transportation"
        }
    ],
    "sg:phone":"+1 409 755 3688",
    "sg:postcode":"77657",
    "sg:province":"TX",
    "wof:name":"Turbos Transport",
    "wof:placetype":"venue"
},
  "geometry": {"coordinates":[-94.24827500000001,30.278294],"type":"Point"}
}