{
  "type": "Feature",
  "properties": {
    "iso:country":"US",
    "sg:address":"4117 Murray Ave",
    "sg:city":"Haltom City",
    "sg:classifiers":[
        {
            "category":"Professional",
            "subcategory":"Art Services",
            "type":"Services"
        }
    ],
    "sg:phone":"+1 817 281 1507",
    "sg:postcode":"76117",
    "sg:province":"TX",
    "sg:tags":[
        "graphic",
        "designer"
    ],
    "wof:name":"Walker Graphics",
    "wof:placetype":"venue"
},
  "geometry": {"coordinates":[-97.28193400000001,32.827957],"type":"Point"}
}