{
  "type": "Feature",
  "properties": {
    "iso:country":"US",
    "sg:address":"331 Rainbow Cir",
    "sg:city":"El Paso",
    "sg:classifiers":[
        {
            "category":"Health Services",
            "subcategory":"Doctor",
            "type":"Services"
        }
    ],
    "sg:phone":"+1 915 584 3238",
    "sg:postcode":"79912",
    "sg:province":"TX",
    "wof:name":"Himelstein Philip PHD",
    "wof:placetype":"venue"
},
  "geometry": {"coordinates":[-106.53299699999999,31.8386],"type":"Point"}
}