{
  "type": "Feature",
  "properties": {
    "iso:country":"US",
    "sg:address":"407 Bluebonnet Dr",
    "sg:city":"Kerrville",
    "sg:classifiers":[
        {
            "category":"Farming",
            "subcategory":"Livestock Farm",
            "type":"Manufacturing & Wholesale Goods"
        }
    ],
    "sg:phone":"+1 830 792 6742",
    "sg:postcode":"78028",
    "sg:province":"TX",
    "sg:tags":[
        "animal",
        "general"
    ],
    "wof:name":"8 M Ranch",
    "wof:placetype":"venue"
},
  "geometry": {"coordinates":[-99.148797,30.062407],"type":"Point"}
}