{
  "type": "Feature",
  "properties": {
    "iso:country":"US",
    "sg:address":"1704 E 18th St",
    "sg:city":"Austin",
    "sg:classifiers":[
        {
            "category":"Freight",
            "type":"Transportation"
        }
    ],
    "sg:phone":"+1 512 469 9605",
    "sg:postcode":"78702",
    "sg:province":"TX",
    "sg:tags":[
        "consultant"
    ],
    "wof:name":"Freight World Wide Air",
    "wof:placetype":"venue"
},
  "geometry": {"coordinates":[-97.722013,30.27871],"type":"Point"}
}