{
  "type": "Feature",
  "properties": {
    "iso:country":"US",
    "sg:address":"3528 Marsh Pl",
    "sg:city":"Amarillo",
    "sg:classifiers":[
        {
            "category":"Professional",
            "type":"Services"
        }
    ],
    "sg:phone":"+1 806 353 7291",
    "sg:postcode":"79121",
    "sg:province":"TX",
    "wof:name":"Across My Heart",
    "wof:placetype":"venue"
},
  "geometry": {"coordinates":[-101.925042,35.172193],"type":"Point"}
}