{
  "type": "Feature",
  "properties": {
    "iso:country":"US",
    "sg:address":"205 N McKinney St",
    "sg:city":"Ennis",
    "sg:classifiers":[
        {
            "category":"Government",
            "subcategory":"Post Office",
            "type":"Public Place"
        }
    ],
    "sg:phone":"+1 972 000 1111",
    "sg:postcode":"75119",
    "sg:province":"TX",
    "wof:name":"US Post Office",
    "wof:placetype":"venue"
},
  "geometry": {"coordinates":[-96.630137,32.328389],"type":"Point"}
}