{
  "type": "Feature",
  "properties": {
    "iso:country":"US",
    "sg:address":"9025 Texas Sun Dr",
    "sg:city":"Austin",
    "sg:classifiers":[
        {
            "category":"Professional",
            "subcategory":"Secretarial Services",
            "type":"Services"
        }
    ],
    "sg:phone":"+1 512 291 1366",
    "sg:postcode":"78748",
    "sg:province":"TX",
    "sg:tags":[
        "reporting"
    ],
    "wof:name":"Briarcliffe Transcription Serv",
    "wof:placetype":"venue"
},
  "geometry": {"coordinates":[-97.811258,30.180305],"type":"Point"}
}