{
  "type": "Feature",
  "properties": {
    "iso:country":"US",
    "sg:address":"820 W Austin St",
    "sg:city":"Giddings",
    "sg:classifiers":[
        {
            "category":"Restaurant",
            "type":"Food & Drink"
        }
    ],
    "sg:phone":"+1 979 542 5470",
    "sg:postcode":"78942",
    "sg:province":"TX",
    "wof:name":"Mae's Kitchen",
    "wof:placetype":"venue"
},
  "geometry": {"coordinates":[-96.94535500000001,30.184226],"type":"Point"}
}