{
  "type": "Feature",
  "properties": {
    "iso:country":"US",
    "sg:address":"5826 Mapleshade Ln",
    "sg:city":"Dallas",
    "sg:classifiers":[
        {
            "category":"Professional",
            "subcategory":"Computer Services",
            "type":"Services"
        }
    ],
    "sg:phone":"+1 972 248 1401",
    "sg:postcode":"75252",
    "sg:province":"TX",
    "sg:tags":[
        "consultant",
        "designer"
    ],
    "wof:name":"Softec Data Systems Inc",
    "wof:placetype":"venue"
},
  "geometry": {"coordinates":[-96.806343,33.006004],"type":"Point"}
}