{
  "type": "Feature",
  "properties": {
    "iso:country":"US",
    "sg:address":"4300 Staten Island Dr",
    "sg:city":"Plano",
    "sg:classifiers":[
        {
            "category":"Wholesale",
            "subcategory":"Electrical",
            "type":"Manufacturing & Wholesale Goods"
        }
    ],
    "sg:phone":"+1 972 208 8604",
    "sg:postcode":"75024",
    "sg:province":"TX",
    "sg:tags":[
        "electronic"
    ],
    "wof:name":"Sino Link Intl Trdg Corp",
    "wof:placetype":"venue"
},
  "geometry": {"coordinates":[-96.776151,33.076045],"type":"Point"}
}