{
  "type": "Feature",
  "properties": {
    "iso:country":"US",
    "sg:address":"1500 Ruth St",
    "sg:city":"Houston",
    "sg:classifiers":[
        {
            "category":"Personal",
            "type":"Services"
        }
    ],
    "sg:phone":"+1 713 528 5541",
    "sg:postcode":"77004",
    "sg:province":"TX",
    "sg:tags":[
        "therapist",
        "massage"
    ],
    "wof:name":"Clinicare Massage",
    "wof:placetype":"venue"
},
  "geometry": {"coordinates":[-95.378833,29.729774],"type":"Point"}
}