{
  "type": "Feature",
  "properties": {
    "iso:country":"US",
    "sg:address":"4404 N Laurent St",
    "sg:city":"Victoria",
    "sg:classifiers":[
        {
            "category":"Building & Trades",
            "subcategory":"Equipment Rental",
            "type":"Services"
        }
    ],
    "sg:phone":"+1 361 576 6599",
    "sg:postcode":"77901",
    "sg:province":"TX",
    "sg:tags":[
        "durable",
        "medical",
        "lease"
    ],
    "wof:name":"Rogers Home Medical Eqp & Svcs",
    "wof:placetype":"venue"
},
  "geometry": {"coordinates":[-96.992991,28.834323],"type":"Point"}
}