{
  "type": "Feature",
  "properties": {
    "iso:country":"US",
    "sg:address":"10127 Leawood Blvd",
    "sg:city":"Houston",
    "sg:classifiers":[
        {
            "category":"Building & Trades",
            "subcategory":"Construction",
            "type":"Services"
        }
    ],
    "sg:phone":"+1 281 568 1330",
    "sg:postcode":"77099",
    "sg:province":"TX",
    "sg:tags":[
        "hanging",
        "contractor"
    ],
    "wof:name":"Quick Painting",
    "wof:placetype":"venue"
},
  "geometry": {"coordinates":[-95.578079,29.666336],"type":"Point"}
}