{
  "type": "Feature",
  "properties": {
    "iso:country":"US",
    "sg:address":"3706 Acorn Run Ln",
    "sg:city":"Spring",
    "sg:classifiers":[
        {
            "category":"Restaurant",
            "type":"Food & Drink"
        }
    ],
    "sg:phone":"+1 281 350 8350",
    "sg:postcode":"77389",
    "sg:province":"TX",
    "sg:tags":[
        "eating"
    ],
    "wof:name":"Sunshine Hut",
    "wof:placetype":"venue"
},
  "geometry": {"coordinates":[-95.473268,30.08881],"type":"Point"}
}