{
  "type": "Feature",
  "properties": {
    "iso:country":"US",
    "sg:address":"716 N Church St",
    "sg:city":"Palestine",
    "sg:classifiers":[
        {
            "category":"Banks & Credit Unions",
            "subcategory":"Investment Brokerage",
            "type":"Services"
        }
    ],
    "sg:phone":"+1 903 727 0673",
    "sg:postcode":"75801",
    "sg:province":"TX",
    "sg:tags":[
        "land",
        "oil",
        "lease"
    ],
    "wof:name":"Royalty Valuation Svc Group",
    "wof:placetype":"venue"
},
  "geometry": {"coordinates":[-95.62664599999999,31.766646],"type":"Point"}
}