{
  "type": "Feature",
  "properties": {
    "iso:country":"US",
    "sg:address":"710 W 3rd Ave",
    "sg:city":"Amarillo",
    "sg:classifiers":[
        {
            "category":"Wholesale",
            "subcategory":"Metals & Minerals",
            "type":"Manufacturing & Wholesale Goods"
        }
    ],
    "sg:phone":"+1 806 376 4129",
    "sg:postcode":"79101",
    "sg:province":"AR",
    "sg:tags":[
        "pipe"
    ],
    "wof:name":"Texas Pipe & Steel Works Inc",
    "wof:placetype":"venue"
},
  "geometry": {"coordinates":[-101.843878,35.211665],"type":"Point"}
}