{
  "type": "Feature",
  "properties": {
    "iso:country":"US",
    "sg:address":"9838 Buffalo Speedway",
    "sg:city":"Houston",
    "sg:classifiers":[
        {
            "category":"Shopping",
            "subcategory":"Pharmacy",
            "type":"Retail Goods"
        }
    ],
    "sg:phone":"+1 713 218 4490",
    "sg:postcode":"77025",
    "sg:province":"TX",
    "sg:tags":[
        "drugstore"
    ],
    "sg:website":"www.cvs.com",
    "wof:name":"CVS Pharmacy",
    "wof:placetype":"venue"
},
  "geometry": {"coordinates":[-95.425563,29.679531],"type":"Point"}
}