{
  "type": "Feature",
  "properties": {
    "iso:country":"US",
    "sg:address":"130 W Houston St",
    "sg:city":"Jasper",
    "sg:classifiers":[
        {
            "category":"Building & Trades",
            "subcategory":"Construction",
            "type":"Services"
        }
    ],
    "sg:phone":"+1 409 384 9959",
    "sg:postcode":"75951",
    "sg:province":"TX",
    "sg:tags":[
        "contractor"
    ],
    "wof:name":"Dabs Building",
    "wof:placetype":"venue"
},
  "geometry": {"coordinates":[-94.000979,30.920858],"type":"Point"}
}