{
  "type": "Feature",
  "properties": {
    "iso:country":"US",
    "sg:address":"3719 W Waco Dr",
    "sg:city":"Waco",
    "sg:classifiers":[
        {
            "category":"Personal",
            "subcategory":"Beauty Salon",
            "type":"Services"
        }
    ],
    "sg:phone":"+1 254 756 1223",
    "sg:postcode":"76710",
    "sg:province":"TX",
    "sg:tags":[
        "shop"
    ],
    "wof:name":"Roffler Of WACO",
    "wof:placetype":"venue"
},
  "geometry": {"coordinates":[-97.165628,31.532983],"type":"Point"}
}