{
  "type": "Feature",
  "properties": {
    "iso:country":"US",
    "sg:address":"341 E Belt Line Rd",
    "sg:city":"Wilmer",
    "sg:classifiers":[
        {
            "category":"Shopping",
            "subcategory":"Discount & Variety Stores",
            "type":"Retail Goods"
        }
    ],
    "sg:phone":"+1 972 525 3226",
    "sg:postcode":"75172",
    "sg:province":"TX",
    "sg:website":"http://www.familydollar.com",
    "wof:name":"Family Dollar Stores",
    "wof:placetype":"venue"
},
  "geometry": {"coordinates":[-96.68212,32.590542],"type":"Point"}
}