{
  "type": "Feature",
  "properties": {
    "iso:country":"US",
    "sg:address":"2000 S Cynthia St",
    "sg:city":"Mcallen",
    "sg:classifiers":[
        {
            "category":"Health Services",
            "subcategory":"Clinic",
            "type":"Services"
        },
        {
            "category":"Health Services",
            "subcategory":"Hospital",
            "type":"Services"
        }
    ],
    "sg:phone":"+1 956 994 3374",
    "sg:postcode":"78503",
    "sg:province":"TX",
    "sg:tags":[
        "medical",
        "dialysis"
    ],
    "wof:name":"Valley Dialysis Of McAllen",
    "wof:placetype":"venue"
},
  "geometry": {"coordinates":[-98.22008599999999,26.183244],"type":"Point"}
}