{
  "type": "Feature",
  "properties": {
    "iso:country":"US",
    "sg:address":"402 S Front St",
    "sg:city":"Freeport",
    "sg:classifiers":[
        {
            "category":"Personal",
            "subcategory":"Beauty Salon",
            "type":"Services"
        }
    ],
    "sg:phone":"+1 979 233 4799",
    "sg:postcode":"77541",
    "sg:province":"TX",
    "wof:name":"Quality Cuts and Styles",
    "wof:placetype":"venue"
},
  "geometry": {"coordinates":[-95.358918,28.956791],"type":"Point"}
}