{
  "type": "Feature",
  "properties": {
    "iso:country":"US",
    "sg:address":"2776 Co Rd 324",
    "sg:city":"Edna",
    "sg:classifiers":[
        {
            "category":"Home & Garden",
            "subcategory":"Garden Supply",
            "type":"Retail Goods"
        }
    ],
    "sg:phone":"+1 361 782 7126",
    "sg:postcode":"77957",
    "sg:province":"TX",
    "sg:tags":[
        "fertilizer"
    ],
    "wof:name":"Agro Distribution LLC",
    "wof:placetype":"venue"
},
  "geometry": {"coordinates":[-96.696423,28.869063],"type":"Point"}
}