{
  "type": "Feature",
  "properties": {
    "iso:country":"US",
    "sg:address":"217 Elm St",
    "sg:city":"Sanger",
    "sg:classifiers":[
        {
            "category":"Building & Trades",
            "subcategory":"Electrical",
            "type":"Services"
        }
    ],
    "sg:phone":"+1 940 458 5010",
    "sg:postcode":"76266",
    "sg:province":"TX",
    "sg:tags":[
        "electric",
        "contractor"
    ],
    "wof:name":"R & T Electrical Contractors",
    "wof:placetype":"venue"
},
  "geometry": {"coordinates":[-97.171532,33.363309],"type":"Point"}
}