{
  "type": "Feature",
  "properties": {
    "iso:country":"US",
    "sg:address":"3905 Shaver St",
    "sg:city":"Pasadena",
    "sg:classifiers":[
        {
            "category":"Restaurant",
            "type":"Food & Drink"
        }
    ],
    "sg:phone":"+1 713 946 8777",
    "sg:postcode":"77504",
    "sg:province":"TX",
    "wof:name":"Mr Rice",
    "wof:placetype":"venue"
},
  "geometry": {"coordinates":[-95.20790100000001,29.650999],"type":"Point"}
}