{
  "type": "Feature",
  "properties": {
    "iso:country":"US",
    "sg:address":"212 Dashing Creek Dr",
    "sg:city":"De Soto",
    "sg:classifiers":[
        {
            "category":"Building & Trades",
            "subcategory":"Construction",
            "type":"Services"
        }
    ],
    "sg:phone":"+1 972 217 3590",
    "sg:postcode":"75115",
    "sg:province":"TX",
    "sg:tags":[
        "house"
    ],
    "wof:name":"Billings 2 Construction Co",
    "wof:placetype":"venue"
},
  "geometry": {"coordinates":[-96.89648699999999,32.586707],"type":"Point"}
}