{
  "type": "Feature",
  "properties": {
    "iso:country":"US",
    "sg:address":"209 Loop 337",
    "sg:city":"New Braunfels",
    "sg:classifiers":[
        {
            "category":"Health Services",
            "subcategory":"Medical Lab",
            "type":"Services"
        }
    ],
    "sg:phone":"+1 830 625 2333",
    "sg:postcode":"78130",
    "sg:province":"TX",
    "sg:tags":[
        "laboratory"
    ],
    "wof:name":"Dental Lab Of New Braunfels",
    "wof:placetype":"venue"
},
  "geometry": {"coordinates":[-98.096592,29.702892],"type":"Point"}
}