{
  "type": "Feature",
  "properties": {
    "iso:country":"US",
    "sg:address":"4408 N Main St",
    "sg:city":"Liberty",
    "sg:classifiers":[
        {
            "category":"Mining & Drilling",
            "type":"Manufacturing & Wholesale Goods"
        }
    ],
    "sg:phone":"+1 936 336 7313",
    "sg:postcode":"77575",
    "sg:province":"TX",
    "sg:tags":[
        "field",
        "oil"
    ],
    "wof:name":"Ward Mc Carty Inc",
    "wof:placetype":"venue"
},
  "geometry": {"coordinates":[-94.759055,30.089973],"type":"Point"}
}