{
  "type": "Feature",
  "properties": {
    "iso:country":"US",
    "sg:address":"10082 Leprachun Ln",
    "sg:city":"Forney",
    "sg:classifiers":[
        {
            "category":"Professional",
            "subcategory":"Business Services",
            "type":"Services"
        }
    ],
    "sg:phone":"+1 972 816 4408",
    "sg:postcode":"75126",
    "sg:province":"TX",
    "wof:name":"Hassler Interiors",
    "wof:placetype":"venue"
},
  "geometry": {"coordinates":[-96.400578,32.708638],"type":"Point"}
}