{
  "type": "Feature",
  "properties": {
    "iso:country":"US",
    "sg:address":"8780 Eagle Mountain Cir",
    "sg:city":"Fort Worth",
    "sg:classifiers":[
        {
            "category":"Organizations",
            "subcategory":"Religious Organization",
            "type":"Services"
        }
    ],
    "sg:phone":"+1 817 237 4135",
    "sg:postcode":"76135",
    "sg:province":"TX",
    "wof:name":"Southern Baptist",
    "wof:placetype":"venue"
},
  "geometry": {"coordinates":[-97.473753,32.865439],"type":"Point"}
}