{
  "type": "Feature",
  "properties": {
    "iso:country":"US",
    "sg:address":"309 S Marsalis Ave",
    "sg:city":"Dallas",
    "sg:classifiers":[
        {
            "category":"Autos & Motor Vehicles",
            "subcategory":"Fuel & Gas Station",
            "type":"Retail Goods"
        }
    ],
    "sg:phone":"+1 214 943 3585",
    "sg:postcode":"75203",
    "sg:province":"TX",
    "wof:name":"A & A Mart Inc",
    "wof:placetype":"venue"
},
  "geometry": {"coordinates":[-96.815755,32.744846],"type":"Point"}
}