{
  "type": "Feature",
  "properties": {
    "iso:country":"US",
    "sg:address":"400 W Illinois Ave Suite 1400",
    "sg:city":"Midland",
    "sg:classifiers":[
        {
            "category":"Professional",
            "subcategory":"Lawyer & Legal Services",
            "type":"Services"
        }
    ],
    "sg:phone":"+1 432 687 0011",
    "sg:postcode":"79701",
    "sg:province":"TX",
    "sg:tags":[
        "living",
        "attorney",
        "law",
        "estate",
        "wills",
        "elder",
        "planning",
        "trust",
        "probate"
    ],
    "sg:website":"http://www.dgclaw.com",
    "wof:name":"Davis, Gerald & Cremer",
    "wof:placetype":"venue"
},
  "geometry": {"coordinates":[-102.078018,31.99955],"type":"Point"}
}