{
  "type": "Feature",
  "properties": {
    "iso:country":"US",
    "sg:address":"523 E Florida St",
    "sg:city":"Pearsall",
    "sg:classifiers":[
        {
            "category":"Education",
            "subcategory":"School",
            "type":"Public Place"
        }
    ],
    "sg:phone":"+1 830 334 3316",
    "sg:postcode":"78061",
    "sg:province":"TX",
    "sg:website":"www.pearsall.k12.tx.us",
    "wof:name":"Pearsall Intermediate School",
    "wof:placetype":"venue"
},
  "geometry": {"coordinates":[-99.091229,28.897201],"type":"Point"}
}