{
  "type": "Feature",
  "properties": {
    "iso:country":"US",
    "sg:address":"2070 Lakeland Dr",
    "sg:city":"New Braunfels",
    "sg:classifiers":[
        {
            "category":"Professional",
            "type":"Services"
        }
    ],
    "sg:phone":"+1 830 223 5351",
    "sg:postcode":"78133",
    "sg:province":"TX",
    "wof:name":"Norman Borchardtllc",
    "wof:placetype":"venue"
},
  "geometry": {"coordinates":[-98.217973,29.901712],"type":"Point"}
}