{
  "type": "Feature",
  "properties": {
    "iso:country":"US",
    "sg:address":"4100 Wolflin Ave",
    "sg:city":"Amarillo",
    "sg:classifiers":[
        {
            "category":"Arts & Performance",
            "subcategory":"Theater",
            "type":"Entertainment"
        }
    ],
    "sg:phone":"+1 806 331 4100",
    "sg:postcode":"79102",
    "sg:province":"TX",
    "sg:tags":[
        "entertainer",
        "family"
    ],
    "wof:name":"Club Illuminati",
    "wof:placetype":"venue"
},
  "geometry": {"coordinates":[-101.883038,35.191881],"type":"Point"}
}