{
  "type": "Feature",
  "properties": {
    "iso:country":"US",
    "sg:address":"6011 FM 1942 E",
    "sg:city":"Baytown",
    "sg:classifiers":[
        {
            "category":"Professional",
            "type":"Services"
        }
    ],
    "sg:phone":"+1 281 839 1303",
    "sg:postcode":"77521",
    "sg:province":"TX",
    "wof:name":"Shirley Ann Ulrich",
    "wof:placetype":"venue"
},
  "geometry": {"coordinates":[-94.974709,29.845053],"type":"Point"}
}