{
  "type": "Feature",
  "properties": {
    "iso:country":"US",
    "sg:address":"22710 US Highway 281 N",
    "sg:city":"San Antonio",
    "sg:classifiers":[
        {
            "category":"Shopping",
            "subcategory":"Clothing, Apparel, & Fashions",
            "type":"Retail Goods"
        }
    ],
    "sg:phone":"+1 210 481 5544",
    "sg:postcode":"78258",
    "sg:province":"TX",
    "sg:tags":[
        "children's",
        "clothing"
    ],
    "sg:website":"www.gymboree.com",
    "wof:name":"GYMBOREE",
    "wof:placetype":"venue"
},
  "geometry": {"coordinates":[-98.449057,29.655137],"type":"Point"}
}