{
  "type": "Feature",
  "properties": {
    "iso:country":"US",
    "sg:address":"2219 Le Mans Dr",
    "sg:city":"Carrollton",
    "sg:classifiers":[
        {
            "category":"Travel",
            "subcategory":"Travel Agent",
            "type":"Entertainment"
        }
    ],
    "sg:phone":"+1 972 418 8765",
    "sg:postcode":"75006",
    "sg:province":"TX",
    "sg:tags":[
        "agency",
        "bureau"
    ],
    "wof:name":"Cruise One",
    "wof:placetype":"venue"
},
  "geometry": {"coordinates":[-96.88077800000001,32.968077],"type":"Point"}
}