{
  "type": "Feature",
  "properties": {
    "iso:country":"US",
    "sg:address":"1005 Waugh Dr Ste C",
    "sg:city":"Houston",
    "sg:classifiers":[
        {
            "category":"Personal",
            "subcategory":"Massage",
            "type":"Services"
        },
        {
            "category":"Personal",
            "subcategory":"Beauty Salon",
            "type":"Services"
        },
        {
            "category":"Personal",
            "subcategory":"Skin Care",
            "type":"Services"
        }
    ],
    "sg:phone":"+1 713 527 7800",
    "sg:postcode":"77019",
    "sg:province":"TX",
    "sg:tags":[
        "hair"
    ],
    "sg:website":"www.thairapysalonspa.com",
    "wof:name":"Thairapy Salon & Spa",
    "wof:placetype":"venue"
},
  "geometry": {"coordinates":[-95.39777100000001,29.756371],"type":"Point"}
}