{
  "type": "Feature",
  "properties": {
    "iso:country":"US",
    "sg:address":"10909 Sabo Rd Suite 115",
    "sg:city":"Houston",
    "sg:classifiers":[
        {
            "category":"Banks & Credit Unions",
            "subcategory":"Financial Services",
            "type":"Services"
        }
    ],
    "sg:phone":"+1 281 214 5248",
    "sg:postcode":"77089",
    "sg:province":"TX",
    "sg:tags":[
        "planner"
    ],
    "wof:name":"Primamerica Financial Service",
    "wof:placetype":"venue"
},
  "geometry": {"coordinates":[-95.22272599999999,29.611644],"type":"Point"}
}