{
  "type": "Feature",
  "properties": {
    "iso:country":"US",
    "sg:address":"102 E N Loop Blvd",
    "sg:city":"Austin",
    "sg:classifiers":[
        {
            "category":"Professional",
            "subcategory":"Art Services",
            "type":"Services"
        },
        {
            "category":"Communications",
            "type":"Services"
        }
    ],
    "sg:phone":"+1 512 407 9409",
    "sg:postcode":"78751",
    "sg:province":"TX",
    "sg:tags":[
        "web",
        "graphic",
        "design"
    ],
    "sg:website":"www.northloopsigns.com",
    "wof:name":"North Loop Sign & Graphics Shop",
    "wof:placetype":"venue"
},
  "geometry": {"coordinates":[-97.722301,30.318052],"type":"Point"}
}