{
  "type": "Feature",
  "properties": {
    "iso:country":"US",
    "sg:address":"3709 Ashby Dr",
    "sg:city":"Flower Mound",
    "sg:classifiers":[
        {
            "category":"Airport",
            "type":"Transportation"
        }
    ],
    "sg:phone":"+1 972 355 5823",
    "sg:postcode":"75022",
    "sg:province":"TX",
    "wof:name":"Amblin Antique Air",
    "wof:placetype":"venue"
},
  "geometry": {"coordinates":[-97.08669,33.00869],"type":"Point"}
}