{
  "type": "Feature",
  "properties": {
    "iso:country":"US",
    "sg:address":"1525 Woodlawn Ave",
    "sg:city":"Corsicana",
    "sg:classifiers":[
        {
            "category":"Real Estate",
            "subcategory":"Real Estate Operator",
            "type":"Services"
        }
    ],
    "sg:phone":"+1 903 872 2087",
    "sg:postcode":"75110",
    "sg:province":"TX",
    "sg:tags":[
        "building",
        "house",
        "apartment"
    ],
    "wof:name":"Fred Slauson Co",
    "wof:placetype":"venue"
},
  "geometry": {"coordinates":[-96.48394,32.092652],"type":"Point"}
}