{
  "type": "Feature",
  "properties": {
    "iso:country":"US",
    "sg:address":"635 Old Hwy 90 W",
    "sg:city":"Vidor",
    "sg:classifiers":[
        {
            "category":"Manufacturing",
            "subcategory":"Metals",
            "type":"Manufacturing & Wholesale Goods"
        }
    ],
    "sg:phone":"+1 409 783 0009",
    "sg:postcode":"77662",
    "sg:province":"TX",
    "sg:tags":[
        "fabrication",
        "structural"
    ],
    "wof:name":"Southeast Texas Industries",
    "wof:placetype":"venue"
},
  "geometry": {"coordinates":[-94.018568,30.121319],"type":"Point"}
}