{
  "type": "Feature",
  "properties": {
    "iso:country":"US",
    "sg:address":"4141 Greenbriar",
    "sg:city":"Houston",
    "sg:classifiers":[
        {
            "category":"Retail",
            "subcategory":"Auto Repair",
            "type":"Services"
        }
    ],
    "sg:phone":"+1 713 528 8811",
    "sg:postcode":"77098",
    "sg:province":"TX",
    "sg:website":"mymechanichouston.com",
    "wof:name":"My Mechanic",
    "wof:placetype":"venue"
},
  "geometry": {"coordinates":[-95.412464,29.728827],"type":"Point"}
}