{
  "type": "Feature",
  "properties": {
    "iso:country":"US",
    "sg:address":"409 Spriggsdale Ave",
    "sg:city":"San Antonio",
    "sg:classifiers":[
        {
            "category":"Personal",
            "subcategory":"Barber",
            "type":"Services"
        }
    ],
    "sg:phone":"+1 210 223 1483",
    "sg:postcode":"78220",
    "sg:province":"TX",
    "sg:tags":[
        "shop"
    ],
    "wof:name":"Hargrove's Barber Shop",
    "wof:placetype":"venue"
},
  "geometry": {"coordinates":[-98.438288,29.416468],"type":"Point"}
}