{
  "type": "Feature",
  "properties": {
    "iso:country":"US",
    "sg:address":"1710 Sam Bass Blvd",
    "sg:city":"Denton",
    "sg:classifiers":[
        {
            "category":"Real Estate",
            "subcategory":"Real Estate Operator",
            "type":"Services"
        }
    ],
    "sg:phone":"+1 940 382 1535",
    "sg:postcode":"76205",
    "sg:province":"TX",
    "sg:tags":[
        "apartment"
    ],
    "wof:name":"Westwind Apartments",
    "wof:placetype":"venue"
},
  "geometry": {"coordinates":[-97.13102000000001,33.194396],"type":"Point"}
}