{
  "type": "Feature",
  "properties": {
    "iso:country":"US",
    "sg:address":"402 N Kauffman St",
    "sg:city":"Linden",
    "sg:classifiers":[
        {
            "category":"Real Estate",
            "subcategory":"Real Estate Operator",
            "type":"Services"
        }
    ],
    "sg:phone":"+1 903 756 5581",
    "sg:postcode":"75563",
    "sg:province":"TX",
    "sg:tags":[
        "building",
        "medical",
        "nonresidential"
    ],
    "wof:name":"Early James MD Faafp",
    "wof:placetype":"venue"
},
  "geometry": {"coordinates":[-94.364486,33.01446],"type":"Point"}
}