{
  "type": "Feature",
  "properties": {
    "iso:country":"US",
    "sg:address":"17221 Cardinal Ln",
    "sg:city":"Troup",
    "sg:classifiers":[
        {
            "category":"Banks & Credit Unions",
            "subcategory":"Financial Services",
            "type":"Services"
        }
    ],
    "sg:phone":"+1 903 839 4800",
    "sg:postcode":"75789",
    "sg:province":"TX",
    "sg:tags":[
        "company",
        "holding"
    ],
    "wof:name":"Cockrell Holding Co",
    "wof:placetype":"venue"
},
  "geometry": {"coordinates":[-95.124859,32.220715],"type":"Point"}
}