{
  "type": "Feature",
  "properties": {
    "iso:country":"US",
    "sg:address":"14665 Preston Rd",
    "sg:city":"Dallas",
    "sg:classifiers":[
        {
            "category":"Personal",
            "subcategory":"Beauty Salon",
            "type":"Services"
        }
    ],
    "sg:phone":"+1 972 239 5338",
    "sg:postcode":"75254",
    "sg:province":"TX",
    "sg:tags":[
        "shop"
    ],
    "wof:name":"Gavio Tangela",
    "wof:placetype":"venue"
},
  "geometry": {"coordinates":[-96.80372300000001,32.947628],"type":"Point"}
}