{
  "type": "Feature",
  "properties": {
    "iso:country":"US",
    "sg:address":"3963 Heritage Trl",
    "sg:city":"Celina",
    "sg:classifiers":[
        {
            "category":"Restaurant",
            "type":"Food & Drink"
        }
    ],
    "sg:phone":"+1 214 675 8520",
    "sg:postcode":"75009",
    "sg:province":"TX",
    "sg:tags":[
        "eating"
    ],
    "wof:name":"Downys Bar & Grill",
    "wof:placetype":"venue"
},
  "geometry": {"coordinates":[-96.775009,33.27686],"type":"Point"}
}