{
  "type": "Feature",
  "properties": {
    "iso:country":"US",
    "sg:address":"1615 Sycamore Ave",
    "sg:city":"Huntsville",
    "sg:classifiers":[
        {
            "category":"Real Estate",
            "subcategory":"Real Estate Operator",
            "type":"Services"
        }
    ],
    "sg:phone":"+1 936 439 5234",
    "sg:postcode":"77340",
    "sg:province":"TX",
    "sg:tags":[
        "apartment"
    ],
    "wof:name":"Villas On Sycamore",
    "wof:placetype":"venue"
},
  "geometry": {"coordinates":[-95.540327,30.716955],"type":"Point"}
}