{
  "type": "Feature",
  "properties": {
    "iso:country":"US",
    "sg:address":"14284 Antonio Dr",
    "sg:city":"Helotes",
    "sg:classifiers":[
        {
            "category":"Communications",
            "subcategory":"Film & Video Production",
            "type":"Services"
        }
    ],
    "sg:phone":"+1 210 695 3924",
    "sg:postcode":"78023",
    "sg:province":"TX",
    "sg:tags":[
        "motion"
    ],
    "wof:name":"Randys Studio",
    "wof:placetype":"venue"
},
  "geometry": {"coordinates":[-98.69500499999999,29.575783],"type":"Point"}
}