{
  "type": "Feature",
  "properties": {
    "iso:country":"US",
    "sg:address":"111 W Cherry Ave",
    "sg:city":"Orange",
    "sg:classifiers":[
        {
            "category":"Organizations",
            "subcategory":"Religious Organization",
            "type":"Services"
        }
    ],
    "sg:phone":"+1 409 886 8950",
    "sg:postcode":"77630",
    "sg:province":"TX",
    "wof:name":"Gods Living Word Mission",
    "wof:placetype":"venue"
},
  "geometry": {"coordinates":[-93.72880499999999,30.0981],"type":"Point"}
}