{
  "type": "Feature",
  "properties": {
    "iso:country":"US",
    "sg:address":"135 Slaughter Lane W",
    "sg:city":"Austin",
    "sg:classifiers":[
        {
            "category":"Health Services",
            "subcategory":"Dentist",
            "type":"Services"
        }
    ],
    "sg:phone":"+1 512 280 1117",
    "sg:postcode":"78748",
    "sg:province":"TX",
    "wof:name":"Euers David W DDS",
    "wof:placetype":"venue"
},
  "geometry": {"coordinates":[-97.78854699999999,30.167055],"type":"Point"}
}