{
  "type": "Feature",
  "properties": {
    "iso:country":"US",
    "sg:address":"1 Baylor Plz Ste 286A",
    "sg:city":"Houston",
    "sg:classifiers":[
        {
            "category":"Health Services",
            "subcategory":"Doctor",
            "type":"Services"
        }
    ],
    "sg:phone":"+1 713 798 4661",
    "sg:postcode":"77030",
    "sg:province":"TX",
    "sg:tags":[
        "physician",
        "surgeon",
        "surgeons",
        "pathology"
    ],
    "wof:name":"Department Ofpathology",
    "wof:placetype":"venue"
},
  "geometry": {"coordinates":[-95.39666699999999,29.710791],"type":"Point"}
}