{
  "type": "Feature",
  "properties": {
    "iso:country":"US",
    "sg:address":"11658 Bandera Rd",
    "sg:city":"San Antonio",
    "sg:classifiers":[
        {
            "category":"Banks & Credit Unions",
            "subcategory":"Bank",
            "type":"Services"
        }
    ],
    "sg:phone":"+1 210 256 3900",
    "sg:postcode":"78250",
    "sg:province":"TX",
    "wof:name":"Bank Of America",
    "wof:placetype":"venue"
},
  "geometry": {"coordinates":[-98.66591,29.552515],"type":"Point"}
}