{
  "type": "Feature",
  "properties": {
    "iso:country":"US",
    "sg:address":"305 E Main St",
    "sg:city":"Midlothian",
    "sg:classifiers":[
        {
            "category":"Retail",
            "subcategory":"Laundry & Dry Cleaning",
            "type":"Services"
        },
        {
            "category":"Manufacturing",
            "subcategory":"Building Materials",
            "type":"Manufacturing & Wholesale Goods"
        },
        {
            "category":"Home & Garden",
            "subcategory":"Carpets & Floor Coverings",
            "type":"Retail Goods"
        }
    ],
    "sg:phone":"+1 972 723 8312",
    "sg:postcode":"76065",
    "sg:province":"TX",
    "sg:tags":[
        "cleaner",
        "materials-wholesale",
        "rug",
        "manufacturer"
    ],
    "wof:name":"J & W Carpets",
    "wof:placetype":"venue"
},
  "geometry": {"coordinates":[-96.990871,32.481905],"type":"Point"}
}