{
  "type": "Feature",
  "properties": {
    "iso:country":"US",
    "sg:address":"7803 Westshire Dr",
    "sg:city":"San Antonio",
    "sg:classifiers":[
        {
            "category":"Shopping",
            "subcategory":"Gifts & Souvenirs",
            "type":"Retail Goods"
        }
    ],
    "sg:phone":"+1 210 675 4781",
    "sg:postcode":"78227",
    "sg:province":"TX",
    "wof:name":"Gifts From Above",
    "wof:placetype":"venue"
},
  "geometry": {"coordinates":[-98.64460200000001,29.411803],"type":"Point"}
}