{
  "type": "Feature",
  "properties": {
    "iso:country":"US",
    "sg:address":"705 Turner St",
    "sg:city":"Kilgore",
    "sg:classifiers":[
        {
            "category":"Shopping",
            "subcategory":"Bicycles & Sporting Goods",
            "type":"Retail Goods"
        }
    ],
    "sg:phone":"+1 903 984 6349",
    "sg:postcode":"75662",
    "sg:province":"TX",
    "wof:name":"Lonestar Outdoors",
    "wof:placetype":"venue"
},
  "geometry": {"coordinates":[-94.872456,32.359571],"type":"Point"}
}