{
  "type": "Feature",
  "properties": {
    "iso:country":"US",
    "sg:address":"15626 Silver Ridge Dr",
    "sg:city":"Houston",
    "sg:classifiers":[
        {
            "category":"Real Estate",
            "subcategory":"Real Estate Agent",
            "type":"Services"
        },
        {
            "category":"Social Services",
            "type":"Services"
        }
    ],
    "sg:phone":"+1 281 397 0995",
    "sg:postcode":"77090",
    "sg:province":"TX",
    "sg:tags":[
        "counseling"
    ],
    "wof:name":"First Step Counseling",
    "wof:placetype":"venue"
},
  "geometry": {"coordinates":[-95.45719800000001,30.010388],"type":"Point"}
}