{
  "type": "Feature",
  "properties": {
    "iso:country":"US",
    "sg:address":"4340 Jana Dr",
    "sg:city":"Fort Worth",
    "sg:classifiers":[
        {
            "category":"Personal",
            "type":"Services"
        }
    ],
    "sg:phone":"+1 817 535 4426",
    "sg:postcode":"76119",
    "sg:province":"TX",
    "sg:tags":[
        "consultant",
        "wedding"
    ],
    "wof:name":"Mari Anna's Enchanting Events",
    "wof:placetype":"venue"
},
  "geometry": {"coordinates":[-97.25894599999999,32.703424],"type":"Point"}
}