{
  "type": "Feature",
  "properties": {
    "iso:country":"US",
    "sg:address":"3100 Carlisle St",
    "sg:city":"Dallas",
    "sg:classifiers":[
        {
            "category":"Wholesale",
            "subcategory":"Construction Materials",
            "type":"Manufacturing & Wholesale Goods"
        }
    ],
    "sg:phone":"+1 214 855 5051",
    "sg:postcode":"75204",
    "sg:province":"TX",
    "sg:tags":[
        "brick",
        "common",
        "face"
    ],
    "sg:website":"www.blacksonbrick.com",
    "wof:name":"Blackson Brick Co",
    "wof:placetype":"venue"
},
  "geometry": {"coordinates":[-96.802532,32.803933],"type":"Point"}
}