{
  "type": "Feature",
  "properties": {
    "iso:country":"US",
    "sg:address":"6030 S Rice Ave",
    "sg:city":"Houston",
    "sg:classifiers":[
        {
            "category":"Personal",
            "type":"Services"
        }
    ],
    "sg:phone":"+1 713 668 7867",
    "sg:postcode":"77081",
    "sg:province":"TX",
    "sg:tags":[
        "party",
        "planning",
        "event"
    ],
    "wof:name":"Piu South Llc",
    "wof:placetype":"venue"
},
  "geometry": {"coordinates":[-95.46816699999999,29.716069],"type":"Point"}
}