{
  "type": "Feature",
  "properties": {
    "iso:country":"US",
    "sg:address":"1250 S. Capitol of Texas Hwy Building 1, Suite 520",
    "sg:city":"Austin",
    "sg:classifiers":[
        {
            "category":"Manufacturing",
            "subcategory":"Electronics",
            "type":"Manufacturing & Wholesale Goods"
        }
    ],
    "sg:phone":"+1 512 330 9818",
    "sg:postcode":"78746",
    "sg:province":"TX",
    "sg:tags":[
        "processor-verification",
        "microprocessor-verification",
        "cpu-verification",
        "arm-verification",
        "multiprocessor-verification"
    ],
    "sg:website":"http://www.obsidiansoft.com",
    "wof:name":"Obsidian Software",
    "wof:placetype":"venue"
},
  "geometry": {"coordinates":[-97.78989,30.262877],"type":"Point"}
}