{
  "type": "Feature",
  "properties": {
    "iso:country":"US",
    "sg:address":"920 W Avenue E G",
    "sg:city":"Garland",
    "sg:phone":"+1 214 646 7102",
    "sg:postcode":"75040",
    "sg:province":"TX",
    "wof:name":"United Boxing Gym",
    "wof:placetype":"venue"
},
  "geometry": {"coordinates":[-96.641741,32.908045],"type":"Point"}
}