{
  "type": "Feature",
  "properties": {
    "iso:country":"US",
    "sg:address":"11931 Radium St",
    "sg:city":"San Antonio",
    "sg:classifiers":[
        {
            "category":"Organizations",
            "subcategory":"Religious Organization",
            "type":"Services"
        }
    ],
    "sg:phone":"+1 210 344 7203",
    "sg:postcode":"78216",
    "sg:province":"TX",
    "sg:tags":[
        "monastery",
        "convent"
    ],
    "wof:name":"Jesus Sisters Of Sacred Heart",
    "wof:placetype":"venue"
},
  "geometry": {"coordinates":[-98.496003,29.551622],"type":"Point"}
}