{
  "type": "Feature",
  "properties": {
    "iso:country":"US",
    "sg:address":"2422 Sendero Trl",
    "sg:city":"Lewisville",
    "sg:classifiers":[
        {
            "category":"Building & Trades",
            "subcategory":"Construction",
            "type":"Services"
        }
    ],
    "sg:phone":"+1 972 874 8272",
    "sg:postcode":"75067",
    "sg:province":"TX",
    "sg:tags":[
        "contractor"
    ],
    "wof:name":"Lee Roofing & Construction Co",
    "wof:placetype":"venue"
},
  "geometry": {"coordinates":[-96.996297,33.008631],"type":"Point"}
}