{
  "type": "Feature",
  "properties": {
    "iso:country":"US",
    "sg:address":"712 Huntland Dr E",
    "sg:city":"Austin",
    "sg:classifiers":[
        {
            "category":"Professional",
            "subcategory":"Management & Consulting",
            "type":"Services"
        }
    ],
    "sg:phone":"+1 512 922 8221",
    "sg:postcode":"78752",
    "sg:province":"TX",
    "sg:tags":[
        "business"
    ],
    "wof:name":"Georgia Wise Swbt",
    "wof:placetype":"venue"
},
  "geometry": {"coordinates":[-97.706232,30.330154],"type":"Point"}
}