{
  "type": "Feature",
  "properties": {
    "iso:country":"US",
    "sg:address":"610 E Crestwood Dr",
    "sg:city":"Victoria",
    "sg:classifiers":[
        {
            "category":"Building & Trades",
            "subcategory":"Electrical",
            "type":"Services"
        }
    ],
    "sg:phone":"+1 361 573 1634",
    "sg:postcode":"77901",
    "sg:province":"TX",
    "sg:tags":[
        "electric",
        "contractor"
    ],
    "wof:name":"Mr Electric",
    "wof:placetype":"venue"
},
  "geometry": {"coordinates":[-96.999938,28.828081],"type":"Point"}
}