{
  "type": "Feature",
  "properties": {
    "iso:country":"US",
    "sg:address":"5020 Foster Ave",
    "sg:city":"Groves",
    "sg:classifiers":[
        {
            "category":"Health Services",
            "subcategory":"Health Practitioner",
            "type":"Services"
        }
    ],
    "sg:phone":"+1 409 960 7177",
    "sg:postcode":"77619",
    "sg:province":"TX",
    "sg:tags":[
        "therapist",
        "physical"
    ],
    "wof:name":"Absolute Therapy Svc",
    "wof:placetype":"venue"
},
  "geometry": {"coordinates":[-93.93844900000001,29.942366],"type":"Point"}
}