{
  "type": "Feature",
  "properties": {
    "iso:country":"US",
    "sg:address":"2810 Market Loop",
    "sg:city":"Southlake",
    "sg:classifiers":[
        {
            "category":"Building & Trades",
            "subcategory":"Construction",
            "type":"Services"
        }
    ],
    "sg:phone":"+1 817 481 6200",
    "sg:postcode":"76092",
    "sg:province":"TX",
    "sg:tags":[
        "painter"
    ],
    "wof:name":"Platinum Painting Inc",
    "wof:placetype":"venue"
},
  "geometry": {"coordinates":[-97.10539,32.935237],"type":"Point"}
}