{
  "type": "Feature",
  "properties": {
    "iso:country":"US",
    "sg:address":"63 Deerwood Dr",
    "sg:city":"Woodville",
    "sg:classifiers":[
        {
            "category":"Professional",
            "subcategory":"Management & Consulting",
            "type":"Services"
        }
    ],
    "sg:phone":"+1 409 283 8693",
    "sg:postcode":"75979",
    "sg:province":"TX",
    "sg:tags":[
        "business"
    ],
    "wof:name":"Dosser Forestry",
    "wof:placetype":"venue"
},
  "geometry": {"coordinates":[-94.41964299999999,30.727913],"type":"Point"}
}