{
  "type": "Feature",
  "properties": {
    "iso:country":"US",
    "sg:address":"4938 S Staples St",
    "sg:city":"Corpus Christi",
    "sg:classifiers":[
        {
            "category":"Personal",
            "type":"Services"
        }
    ],
    "sg:phone":"+1 361 906 0653",
    "sg:postcode":"78411",
    "sg:province":"TX",
    "sg:tags":[
        "therapist",
        "massage"
    ],
    "wof:name":"Alternative Relief",
    "wof:placetype":"venue"
},
  "geometry": {"coordinates":[-97.369333,27.711085],"type":"Point"}
}