{
  "type": "Feature",
  "properties": {
    "iso:country":"US",
    "sg:address":"15011 Rain Shadow Ct",
    "sg:city":"Houston",
    "sg:classifiers":[
        {
            "category":"Wholesale",
            "subcategory":"Machinery & Supplies",
            "type":"Manufacturing & Wholesale Goods"
        }
    ],
    "sg:phone":"+1 281 376 8882",
    "sg:postcode":"77070",
    "sg:province":"TX",
    "sg:tags":[
        "industry",
        "management",
        "consulting"
    ],
    "wof:name":"Essi",
    "wof:placetype":"venue"
},
  "geometry": {"coordinates":[-95.609523,29.991146],"type":"Point"}
}