{
  "type": "Feature",
  "properties": {
    "iso:country":"US",
    "sg:address":"1521 W 16th St",
    "sg:city":"Mount Pleasant",
    "sg:classifiers":[
        {
            "category":"Wholesale",
            "subcategory":"Auto Parts",
            "type":"Manufacturing & Wholesale Goods"
        }
    ],
    "sg:phone":"+1 903 572 4972",
    "sg:postcode":"75455",
    "sg:province":"TX",
    "wof:name":"Macs Radiator Company",
    "wof:placetype":"venue"
},
  "geometry": {"coordinates":[-94.99076100000001,33.166003],"type":"Point"}
}