{
  "type": "Feature",
  "properties": {
    "iso:country":"US",
    "sg:address":"1413 Cedarbrook Ct",
    "sg:city":"Seabrook",
    "sg:classifiers":[
        {
            "category":"Building & Trades",
            "subcategory":"Cleaning & Sanitation",
            "type":"Services"
        }
    ],
    "sg:phone":"+1 281 474 4278",
    "sg:postcode":"77586",
    "sg:province":"TX",
    "sg:tags":[
        "janitorial",
        "maintenance"
    ],
    "wof:name":"Williams Janitorial",
    "wof:placetype":"venue"
},
  "geometry": {"coordinates":[-95.019257,29.565685],"type":"Point"}
}