{
  "type": "Feature",
  "properties": {
    "iso:country":"US",
    "sg:address":"2902 Shady Lake Cir",
    "sg:city":"Carrollton",
    "sg:classifiers":[
        {
            "category":"Restaurant",
            "type":"Food & Drink"
        }
    ],
    "sg:phone":"+1 972 418 7421",
    "sg:postcode":"75006",
    "sg:province":"TX",
    "sg:tags":[
        "eating"
    ],
    "wof:name":"Cherry Pyeatt",
    "wof:placetype":"venue"
},
  "geometry": {"coordinates":[-96.857247,32.963317],"type":"Point"}
}