{
  "type": "Feature",
  "properties": {
    "iso:country":"US",
    "sg:address":"2016 Reynolds St",
    "sg:city":"Laredo",
    "sg:classifiers":[
        {
            "category":"Wholesale",
            "subcategory":"Durable Goods & Equipment",
            "type":"Manufacturing & Wholesale Goods"
        }
    ],
    "sg:phone":"+1 956 727 1667",
    "sg:postcode":"78043",
    "sg:province":"TX",
    "sg:tags":[
        "importer"
    ],
    "wof:name":"Cuevas Crafts Imports",
    "wof:placetype":"venue"
},
  "geometry": {"coordinates":[-99.47534,27.518676],"type":"Point"}
}