{
  "type": "Feature",
  "properties": {
    "iso:country":"US",
    "sg:address":"3200 S Lamar Blvd",
    "sg:city":"Austin",
    "sg:classifiers":[
        {
            "category":"Building & Trades",
            "subcategory":"Pest Control",
            "type":"Services"
        }
    ],
    "sg:phone":"+1 512 443 0280",
    "sg:postcode":"78704",
    "sg:province":"TX",
    "wof:name":"A OK Pest Services",
    "wof:placetype":"venue"
},
  "geometry": {"coordinates":[-97.78536099999999,30.241398],"type":"Point"}
}