{
  "type": "Feature",
  "properties": {
    "iso:country":"US",
    "sg:address":"2224 W Buckingham Rd",
    "sg:city":"Garland",
    "sg:classifiers":[
        {
            "category":"Shopping",
            "subcategory":"Music",
            "type":"Retail Goods"
        }
    ],
    "sg:phone":"+1 972 487 7879",
    "sg:postcode":"75042",
    "sg:province":"TX",
    "wof:name":"Hollywood Video",
    "wof:placetype":"venue"
},
  "geometry": {"coordinates":[-96.66364400000001,32.930511],"type":"Point"}
}