{
  "type": "Feature",
  "properties": {
    "iso:country":"US",
    "sg:address":"614 N 14th St",
    "sg:city":"La Porte",
    "sg:classifiers":[
        {
            "category":"Building & Trades",
            "subcategory":"Cleaning & Sanitation",
            "type":"Services"
        }
    ],
    "sg:phone":"+1 281 470 1475",
    "sg:postcode":"77571",
    "sg:province":"TX",
    "sg:tags":[
        "provide"
    ],
    "wof:name":"Fin Foam",
    "wof:placetype":"venue"
},
  "geometry": {"coordinates":[-95.03401599999999,29.672805],"type":"Point"}
}