{
  "type": "Feature",
  "properties": {
    "iso:country":"US",
    "sg:address":"1711 Lawson Rd",
    "sg:city":"Mesquite",
    "sg:classifiers":[
        {
            "category":"Sports & Exercise",
            "subcategory":"Race Track",
            "type":"Entertainment"
        }
    ],
    "sg:phone":"+1 972 222 2421",
    "sg:postcode":"75181",
    "sg:province":"TX",
    "sg:tags":[
        "operation"
    ],
    "wof:name":"Devils Bowl Speedway Inc",
    "wof:placetype":"venue"
},
  "geometry": {"coordinates":[-96.528296,32.732944],"type":"Point"}
}