{
  "type": "Feature",
  "properties": {
    "iso:country":"US",
    "sg:address":"3717 Robinhood St",
    "sg:city":"Houston",
    "sg:classifiers":[
        {
            "category":"Building & Trades",
            "subcategory":"Construction",
            "type":"Services"
        }
    ],
    "sg:phone":"+1 832 778 0775",
    "sg:postcode":"77005",
    "sg:province":"TX",
    "sg:tags":[
        "house"
    ],
    "wof:name":"Brentwood Homes Inc",
    "wof:placetype":"venue"
},
  "geometry": {"coordinates":[-95.436986,29.72106],"type":"Point"}
}