{
  "type": "Feature",
  "properties": {
    "iso:country":"US",
    "sg:address":"1004 Carla Ct",
    "sg:city":"Arlington",
    "sg:classifiers":[
        {
            "category":"Building & Trades",
            "subcategory":"Landscaping Services",
            "type":"Services"
        }
    ],
    "sg:phone":"+1 866 670 4275",
    "sg:postcode":"76014",
    "sg:province":"TX",
    "sg:tags":[
        "lawn",
        "installation",
        "sprinklers-garden"
    ],
    "wof:name":"Chairez Irrigation",
    "wof:placetype":"venue"
},
  "geometry": {"coordinates":[-97.09501,32.703132],"type":"Point"}
}