{
  "type": "Feature",
  "properties": {
    "iso:country":"US",
    "sg:address":"26 N Kaysie St",
    "sg:city":"Angleton",
    "sg:classifiers":[
        {
            "category":"Shopping",
            "subcategory":"Used Merchandise",
            "type":"Retail Goods"
        }
    ],
    "sg:phone":"+1 979 849 7788",
    "sg:postcode":"77515",
    "sg:province":"TX",
    "wof:name":"A To Z Antiques & More",
    "wof:placetype":"venue"
},
  "geometry": {"coordinates":[-95.434893,29.176668],"type":"Point"}
}