{
  "type": "Feature",
  "properties": {
    "iso:country":"US",
    "sg:address":"15618 Ranchita Dr",
    "sg:city":"Dallas",
    "sg:classifiers":[
        {
            "category":"Building & Trades",
            "subcategory":"Cleaning & Sanitation",
            "type":"Services"
        }
    ],
    "sg:phone":"+1 972 732 7474",
    "sg:postcode":"75248",
    "sg:province":"TX",
    "sg:tags":[
        "carpet"
    ],
    "wof:name":"Picaso Carpet Cleaning",
    "wof:placetype":"venue"
},
  "geometry": {"coordinates":[-96.802916,32.96042],"type":"Point"}
}