{
  "type": "Feature",
  "properties": {
    "iso:country":"US",
    "sg:address":"1908 Broadway St",
    "sg:city":"Pearland",
    "sg:classifiers":[
        {
            "category":"Sports & Exercise",
            "subcategory":"Stables",
            "type":"Entertainment"
        }
    ],
    "sg:phone":"+1 281 996 1515",
    "sg:postcode":"77581",
    "sg:province":"TX",
    "sg:tags":[
        "riding",
        "academy"
    ],
    "sg:website":"http://www.baectx.com",
    "wof:name":"Bay Area Equestrian Center",
    "wof:placetype":"venue"
},
  "geometry": {"coordinates":[-95.24185199999999,29.547661],"type":"Point"}
}