{
  "type": "Feature",
  "properties": {
    "iso:country":"US",
    "sg:address":"12719 Cypress Valley Rd",
    "sg:city":"Cypress",
    "sg:classifiers":[
        {
            "category":"Home & Garden",
            "subcategory":"Garden Supply",
            "type":"Retail Goods"
        }
    ],
    "sg:phone":"+1 281 373 0993",
    "sg:postcode":"77429",
    "sg:province":"TX",
    "sg:tags":[
        "sprinkler"
    ],
    "wof:name":"Marek Irrigation & Landscaping",
    "wof:placetype":"venue"
},
  "geometry": {"coordinates":[-95.660096,29.96144],"type":"Point"}
}