{
  "type": "Feature",
  "properties": {
    "iso:country":"US",
    "sg:address":"9226 Needville Fairchilds Rd",
    "sg:city":"Needville",
    "sg:classifiers":[
        {
            "category":"Professional",
            "subcategory":"Business Services",
            "type":"Services"
        }
    ],
    "sg:phone":"+1 979 793 3428",
    "sg:postcode":"77461",
    "sg:province":"TX",
    "sg:tags":[
        "consultant",
        "coach"
    ],
    "wof:name":"G & G Survey & Consulting Inc",
    "wof:placetype":"venue"
},
  "geometry": {"coordinates":[-95.783092,29.42872],"type":"Point"}
}