{
  "type": "Feature",
  "properties": {
    "iso:country":"US",
    "sg:address":"3827 Youpon Dr",
    "sg:city":"La Porte",
    "sg:classifiers":[
        {
            "category":"Utilities",
            "subcategory":"Telephone",
            "type":"Services"
        }
    ],
    "sg:phone":"+1 281 487 0981",
    "sg:postcode":"77571",
    "sg:province":"TX",
    "sg:tags":[
        "communication",
        "datum"
    ],
    "wof:name":"Amp Electric Co",
    "wof:placetype":"venue"
},
  "geometry": {"coordinates":[-95.064173,29.653327],"type":"Point"}
}