{
  "type": "Feature",
  "properties": {
    "iso:country":"US",
    "sg:address":"3008 Taylor St",
    "sg:city":"Dallas",
    "sg:classifiers":[
        {
            "category":"Social Services",
            "subcategory":"Child Care",
            "type":"Services"
        }
    ],
    "sg:phone":"+1 214 413 2802",
    "sg:postcode":"75226",
    "sg:province":"TX",
    "sg:tags":[
        "day"
    ],
    "wof:name":"After School All Stars Dallas",
    "wof:placetype":"venue"
},
  "geometry": {"coordinates":[-96.77891099999999,32.781974],"type":"Point"}
}