{
  "type": "Feature",
  "properties": {
    "iso:country":"US",
    "sg:address":"7010 Zoltowski St",
    "sg:city":"Houston",
    "sg:classifiers":[
        {
            "category":"Wholesale",
            "subcategory":"Metals & Minerals",
            "type":"Manufacturing & Wholesale Goods"
        }
    ],
    "sg:phone":"+1 713 676 1800",
    "sg:postcode":"77020",
    "sg:province":"TX",
    "sg:tags":[
        "rope",
        "hardware",
        "wire"
    ],
    "wof:name":"Usha Martin Americas Inc",
    "wof:placetype":"venue"
},
  "geometry": {"coordinates":[-95.29523500000001,29.753626],"type":"Point"}
}