{
  "type": "Feature",
  "properties": {
    "iso:country":"US",
    "sg:address":"905 Hemingway Ct",
    "sg:city":"Allen",
    "sg:classifiers":[
        {
            "category":"Restaurant",
            "type":"Food & Drink"
        }
    ],
    "sg:phone":"+1 972 396 1582",
    "sg:postcode":"75002",
    "sg:province":"TX",
    "sg:tags":[
        "eating"
    ],
    "wof:name":"Rapp Ed With Love Catering",
    "wof:placetype":"venue"
},
  "geometry": {"coordinates":[-96.65696699999999,33.085291],"type":"Point"}
}