{
  "type": "Feature",
  "properties": {
    "iso:country":"US",
    "sg:address":"2601 S Mayhill Rd 51",
    "sg:city":"Denton",
    "sg:classifiers":[
        {
            "category":"Professional",
            "subcategory":"Management & Consulting",
            "type":"Services"
        },
        {
            "category":"Professional",
            "subcategory":"Advertising",
            "type":"Services"
        }
    ],
    "sg:phone":"+1 940 565 1972",
    "sg:postcode":"76208",
    "sg:province":"TX",
    "sg:tags":[
        "marketing",
        "program",
        "consultant"
    ],
    "wof:name":"Dl & J Marketing",
    "wof:placetype":"venue"
},
  "geometry": {"coordinates":[-97.085632,33.182159],"type":"Point"}
}