{
  "type": "Feature",
  "properties": {
    "iso:country":"US",
    "sg:address":"4722 Everhart Rd",
    "sg:city":"Corpus Christi",
    "sg:classifiers":[
        {
            "category":"Banks & Credit Unions",
            "subcategory":"Bank",
            "type":"Services"
        }
    ],
    "sg:phone":"+1 361 994 1519",
    "sg:postcode":"78411",
    "sg:province":"TX",
    "sg:tags":[
        "loan",
        "real estate"
    ],
    "wof:name":"Family Tree Mortgage",
    "wof:placetype":"venue"
},
  "geometry": {"coordinates":[-97.38078,27.720171],"type":"Point"}
}