{
  "type": "Feature",
  "properties": {
    "iso:country":"US",
    "sg:address":"9915 Chimney Hill Ln",
    "sg:city":"Dallas",
    "sg:classifiers":[
        {
            "category":"Shopping",
            "subcategory":"Pets & Pet Supplies",
            "type":"Retail Goods"
        }
    ],
    "sg:phone":"+1 972 238 9083",
    "sg:postcode":"75243",
    "sg:province":"TX",
    "sg:tags":[
        "furnishing",
        "dog",
        "store",
        "cat"
    ],
    "wof:name":"Docktor Pet Center",
    "wof:placetype":"venue"
},
  "geometry": {"coordinates":[-96.728638,32.91575],"type":"Point"}
}