{
  "type": "Feature",
  "properties": {
    "iso:country":"US",
    "sg:address":"7806 Glenneagle Dr",
    "sg:city":"Dallas",
    "sg:classifiers":[
        {
            "category":"Real Estate",
            "subcategory":"Real Estate Agent",
            "type":"Services"
        }
    ],
    "sg:phone":"+1 972 385 7071",
    "sg:postcode":"75248",
    "sg:province":"TX",
    "wof:name":"Breckenridge Jim Co",
    "wof:placetype":"venue"
},
  "geometry": {"coordinates":[-96.769755,32.973786],"type":"Point"}
}