{
  "type": "Feature",
  "properties": {
    "iso:country":"US",
    "sg:address":"1701 N Loop 289",
    "sg:city":"Lubbock",
    "sg:classifiers":[
        {
            "category":"Freight",
            "type":"Transportation"
        }
    ],
    "sg:phone":"+1 806 765 7752",
    "sg:postcode":"79415",
    "sg:province":"TX",
    "wof:name":"Penske Logistics",
    "wof:placetype":"venue"
},
  "geometry": {"coordinates":[-101.855576,33.620802],"type":"Point"}
}