{
  "type": "Feature",
  "properties": {
    "iso:country":"US",
    "sg:address":"Inside Hotel ZaZa 2332 Leonard St",
    "sg:city":"Dallas",
    "sg:classifiers":[
        {
            "category":"Bars & Pubs",
            "subcategory":"Lounge",
            "type":"Food & Drink"
        },
        {
            "category":"Restaurant",
            "type":"Food & Drink"
        }
    ],
    "sg:phone":"+1 214 550 9500",
    "sg:postcode":"75201",
    "sg:province":"TX",
    "sg:tags":[
        "new",
        "american"
    ],
    "sg:website":"www.hotelzaza.com/dallas/dining_...",
    "wof:name":"Dragonfly",
    "wof:placetype":"venue"
},
  "geometry": {"coordinates":[-96.801416,32.794261],"type":"Point"}
}