{
  "type": "Feature",
  "properties": {
    "iso:country":"US",
    "sg:address":"171 Pasadena Town Sq",
    "sg:city":"Pasadena",
    "sg:classifiers":[
        {
            "category":"Shopping",
            "subcategory":"Hobbies, Toys, & Games",
            "type":"Retail Goods"
        }
    ],
    "sg:phone":"+1 713 475 0260",
    "sg:postcode":"77506",
    "sg:province":"TX",
    "sg:tags":[
        "toy",
        "store"
    ],
    "sg:website":"www.toysrus.com",
    "wof:name":"Toys R Us",
    "wof:placetype":"venue"
},
  "geometry": {"coordinates":[-95.201241,29.711463],"type":"Point"}
}