{
  "type": "Feature",
  "properties": {
    "iso:country":"US",
    "sg:address":"4700 Blaney Ave",
    "sg:city":"Fort Worth",
    "sg:classifiers":[
        {
            "category":"Professional",
            "subcategory":"Management & Consulting",
            "type":"Services"
        }
    ],
    "sg:phone":"+1 817 281 4466",
    "sg:postcode":"76180",
    "sg:province":"TX",
    "sg:tags":[
        "retail",
        "direct",
        "sales"
    ],
    "wof:name":"Winorr Company",
    "wof:placetype":"venue"
},
  "geometry": {"coordinates":[-97.22930100000001,32.833739],"type":"Point"}
}