{
  "type": "Feature",
  "properties": {
    "iso:country":"US",
    "sg:address":"201 Rodeo Rd",
    "sg:city":"Inez",
    "sg:classifiers":[
        {
            "category":"Building & Trades",
            "subcategory":"Electrical",
            "type":"Services"
        }
    ],
    "sg:phone":"+1 361 575 4770",
    "sg:postcode":"77968",
    "sg:province":"TX",
    "sg:tags":[
        "electrical",
        "contractor"
    ],
    "wof:name":"William Ponton Inc",
    "wof:placetype":"venue"
},
  "geometry": {"coordinates":[-96.84223900000001,28.918925],"type":"Point"}
}