{
  "type": "Feature",
  "properties": {
    "iso:country":"US",
    "sg:address":"215 W Main St",
    "sg:city":"Fredericksburg",
    "sg:classifiers":[
        {
            "category":"Home & Garden",
            "subcategory":"Home Furnishings",
            "type":"Retail Goods"
        }
    ],
    "sg:phone":"+1 830 990 0300",
    "sg:postcode":"78624",
    "sg:province":"TX",
    "wof:name":"Touches Finale",
    "wof:placetype":"venue"
},
  "geometry": {"coordinates":[-98.875547,30.277389],"type":"Point"}
}