{
  "type": "Feature",
  "properties": {
    "iso:country":"US",
    "sg:address":"1204 Zaragosa St",
    "sg:city":"Laredo",
    "sg:classifiers":[
        {
            "category":"Shopping",
            "subcategory":"Bicycles & Sporting Goods",
            "type":"Retail Goods"
        }
    ],
    "sg:phone":"+1 956 723 4700",
    "sg:postcode":"78040",
    "sg:province":"TX",
    "wof:name":"Vaswani Soccer Ventures LLC",
    "wof:placetype":"venue"
},
  "geometry": {"coordinates":[-99.508511,27.502218],"type":"Point"}
}