{
  "type": "Feature",
  "properties": {
    "iso:country":"US",
    "sg:address":"3731 Drossett Drive",
    "sg:city":"Austin",
    "sg:classifiers":[
        {
            "category":"Shopping",
            "subcategory":"Stationery & Office Supplies",
            "type":"Retail Goods"
        }
    ],
    "sg:phone":"+1 512 443 9377",
    "sg:postcode":"78744",
    "sg:province":"TX",
    "sg:tags":[
        "equipment"
    ],
    "sg:website":"www.furniturelogistix.com",
    "wof:name":"Furniture Logistix",
    "wof:placetype":"venue"
},
  "geometry": {"coordinates":[-97.73066900000001,30.211513],"type":"Point"}
}