{
  "type": "Feature",
  "properties": {
    "iso:country":"US",
    "sg:address":"8012 Tisdale Dr",
    "sg:city":"Austin",
    "sg:classifiers":[
        {
            "category":"Building & Trades",
            "subcategory":"Construction",
            "type":"Services"
        }
    ],
    "sg:phone":"+1 512 451 1117",
    "sg:postcode":"78757",
    "sg:province":"TX",
    "sg:tags":[
        "repairing",
        "remodeling",
        "contractor"
    ],
    "wof:name":"Barefoot Builders",
    "wof:placetype":"venue"
},
  "geometry": {"coordinates":[-97.717338,30.353788],"type":"Point"}
}