{
  "type": "Feature",
  "properties": {
    "iso:country":"US",
    "sg:address":"555 S Main Ave",
    "sg:city":"San Antonio",
    "sg:classifiers":[
        {
            "category":"Professional",
            "type":"Services"
        },
        {
            "category":"Professional",
            "subcategory":"Business Services",
            "type":"Services"
        }
    ],
    "sg:phone":"+1 210 225 5245",
    "sg:postcode":"78204",
    "sg:province":"TX",
    "wof:name":"Green Kelly K Bail Bond Svc",
    "wof:placetype":"venue"
},
  "geometry": {"coordinates":[-98.495205,29.419928],"type":"Point"}
}