{
  "type": "Feature",
  "properties": {
    "iso:country":"US",
    "sg:address":"518 Woodland Hills Dr",
    "sg:city":"Tyler",
    "sg:classifiers":[
        {
            "category":"Shopping",
            "subcategory":"Florist",
            "type":"Retail Goods"
        }
    ],
    "sg:phone":"+1 903 534 4755",
    "sg:postcode":"75701",
    "sg:province":"TX",
    "sg:tags":[
        "business"
    ],
    "wof:name":"Designs By Eileen",
    "wof:placetype":"venue"
},
  "geometry": {"coordinates":[-95.305808,32.307853],"type":"Point"}
}