{
  "type": "Feature",
  "properties": {
    "iso:country":"US",
    "sg:address":"887 Landa St",
    "sg:city":"New Braunfels",
    "sg:classifiers":[
        {
            "category":"Building & Trades",
            "subcategory":"Construction",
            "type":"Services"
        }
    ],
    "sg:phone":"+1 830 620 4636",
    "sg:postcode":"78130",
    "sg:province":"TX",
    "sg:tags":[
        "house"
    ],
    "wof:name":"Texas Heritage Construction",
    "wof:placetype":"venue"
},
  "geometry": {"coordinates":[-98.13466699999999,29.705213],"type":"Point"}
}