{
  "type": "Feature",
  "properties": {
    "iso:country":"US",
    "sg:address":"1410 N I H 35 Ste 200",
    "sg:city":"Austin",
    "sg:classifiers":[
        {
            "category":"Health Services",
            "subcategory":"Hospital",
            "type":"Services"
        }
    ],
    "sg:phone":"+1 512 324 8000",
    "sg:postcode":"78701",
    "sg:province":"TX",
    "wof:name":"Children's Hospital of Austin",
    "wof:placetype":"venue"
},
  "geometry": {"coordinates":[-97.73200199999999,30.2743],"type":"Point"}
}