{
  "type": "Feature",
  "properties": {
    "iso:country":"US",
    "sg:address":"4305 N 10th St",
    "sg:city":"Mcallen",
    "sg:classifiers":[
        {
            "category":"Insurance",
            "subcategory":"Insurance Agent",
            "type":"Services"
        }
    ],
    "sg:phone":"+1 956 928 0004",
    "sg:postcode":"78504",
    "sg:province":"TX",
    "wof:name":"Security First Insurance",
    "wof:placetype":"venue"
},
  "geometry": {"coordinates":[-98.22348,26.241969],"type":"Point"}
}