{
  "type": "Feature",
  "properties": {
    "iso:country":"US",
    "sg:address":"301 N College St",
    "sg:city":"Waxahachie",
    "sg:classifiers":[
        {
            "category":"Professional",
            "type":"Services"
        },
        {
            "category":"Personal",
            "subcategory":"Beauty Salon",
            "type":"Services"
        }
    ],
    "sg:phone":"+1 972 937 9292",
    "sg:postcode":"75165",
    "sg:province":"TX",
    "wof:name":"Pony Tailz and Nailz",
    "wof:placetype":"venue"
},
  "geometry": {"coordinates":[-96.845725,32.388357],"type":"Point"}
}