{
  "type": "Feature",
  "properties": {
    "iso:country":"US",
    "sg:address":"703 W Oaklawn Rd",
    "sg:city":"Pleasanton",
    "sg:phone":"+1 830 569 8877",
    "sg:postcode":"78064",
    "sg:province":"TX",
    "sg:website":"http://www.upsstore.com",
    "wof:name":"The UPS Store",
    "wof:placetype":"venue"
},
  "geometry": {"coordinates":[-98.491283,28.957085],"type":"Point"}
}