{
  "type": "Feature",
  "properties": {
    "iso:country":"US",
    "sg:address":"14206 FM 346 W",
    "sg:city":"Bullard",
    "sg:classifiers":[
        {
            "category":"Restaurant",
            "type":"Food & Drink"
        }
    ],
    "sg:phone":"+1 903 825 0116",
    "sg:postcode":"75757",
    "sg:province":"TX",
    "sg:tags":[
        "eating"
    ],
    "wof:name":"Teaselville Snack Shack",
    "wof:placetype":"venue"
},
  "geometry": {"coordinates":[-95.40414,32.150545],"type":"Point"}
}