{
  "type": "Feature",
  "properties": {
    "iso:country":"US",
    "sg:address":"25550 I- 45",
    "sg:city":"Spring",
    "sg:classifiers":[
        {
            "category":"Education",
            "subcategory":"Dance Studio",
            "type":"Public Place"
        }
    ],
    "sg:phone":"+1 281 292 1803",
    "sg:postcode":"77386",
    "sg:province":"TX",
    "wof:name":"Dallas Nite Club",
    "wof:placetype":"venue"
},
  "geometry": {"coordinates":[-95.44438599999999,30.134759],"type":"Point"}
}