{
  "type": "Feature",
  "properties": {
    "iso:country":"US",
    "sg:address":"3343 Boca Chica Blvd",
    "sg:city":"Brownsville",
    "sg:classifiers":[
        {
            "category":"Restaurant",
            "type":"Food & Drink"
        }
    ],
    "sg:phone":"+1 956 546 2510",
    "sg:postcode":"78521",
    "sg:province":"TX",
    "wof:name":"Long John Silver's",
    "wof:placetype":"venue"
},
  "geometry": {"coordinates":[-97.46869700000001,25.920872],"type":"Point"}
}