{
  "type": "Feature",
  "properties": {
    "iso:country":"US",
    "sg:address":"4189 Bellaire Blvd",
    "sg:city":"Houston",
    "sg:classifiers":[
        {
            "category":"Professional",
            "subcategory":"Management & Consulting",
            "type":"Services"
        },
        {
            "category":"Manufacturing",
            "subcategory":"Watercraft",
            "type":"Manufacturing & Wholesale Goods"
        }
    ],
    "sg:phone":"+1 713 668 7100",
    "sg:postcode":"77025",
    "sg:province":"TX",
    "sg:tags":[
        "firm",
        "barge"
    ],
    "wof:name":"Marinus Management Corporation",
    "wof:placetype":"venue"
},
  "geometry": {"coordinates":[-95.444146,29.705863],"type":"Point"}
}