{
  "type": "Feature",
  "properties": {
    "iso:country":"US",
    "sg:address":"1565 Rhonda B Rd",
    "sg:city":"Azle",
    "sg:classifiers":[
        {
            "category":"Food & Beverages",
            "subcategory":"Liquor & Beverages",
            "type":"Retail Goods"
        }
    ],
    "sg:phone":"+1 817 444 2012",
    "sg:postcode":"76020",
    "sg:province":"TX",
    "sg:tags":[
        "grocery",
        "alcoholic"
    ],
    "wof:name":"Last Stop West",
    "wof:placetype":"venue"
},
  "geometry": {"coordinates":[-97.551399,32.922856],"type":"Point"}
}