{
  "type": "Feature",
  "properties": {
    "iso:country":"US",
    "sg:address":"9297 College St",
    "sg:city":"Beaumont",
    "sg:classifiers":[
        {
            "category":"Restaurant",
            "type":"Food & Drink"
        }
    ],
    "sg:phone":"+1 409 866 1216",
    "sg:postcode":"77707",
    "sg:province":"TX",
    "wof:name":"La Casita Restaurant",
    "wof:placetype":"venue"
},
  "geometry": {"coordinates":[-94.200675,30.065771],"type":"Point"}
}