{
  "type": "Feature",
  "properties": {
    "iso:country":"US",
    "sg:address":"112 E Rice St",
    "sg:city":"Falfurrias",
    "sg:classifiers":[
        {
            "category":"Shopping",
            "subcategory":"Clothing, Apparel, & Fashions",
            "type":"Retail Goods"
        }
    ],
    "sg:phone":"+1 361 325 5077",
    "sg:postcode":"78355",
    "sg:province":"TX",
    "sg:tags":[
        "shop",
        "bridal"
    ],
    "wof:name":"Salazar Sewing Ctr",
    "wof:placetype":"venue"
},
  "geometry": {"coordinates":[-98.14412400000001,27.226636],"type":"Point"}
}