{
  "type": "Feature",
  "properties": {
    "iso:country":"US",
    "sg:address":"408 Oleander St",
    "sg:city":"Lake Jackson",
    "sg:classifiers":[
        {
            "category":"Professional",
            "subcategory":"Business Services",
            "type":"Services"
        }
    ],
    "sg:phone":"+1 979 297 8562",
    "sg:postcode":"77566",
    "sg:province":"TX",
    "sg:tags":[
        "messenger"
    ],
    "wof:name":"Swift Courier Svc",
    "wof:placetype":"venue"
},
  "geometry": {"coordinates":[-95.44865,29.027262],"type":"Point"}
}