{
  "type": "Feature",
  "properties": {
    "iso:country":"US",
    "sg:address":"2006 N W S Young Dr",
    "sg:city":"Killeen",
    "sg:classifiers":[
        {
            "category":"Shopping",
            "subcategory":"Beauty & Cosmetics",
            "type":"Retail Goods"
        },
        {
            "category":"Personal",
            "subcategory":"Beauty Salon",
            "type":"Services"
        }
    ],
    "sg:phone":"+1 254 200 2897",
    "sg:postcode":"76543",
    "sg:province":"TX",
    "sg:tags":[
        "perfume",
        "salons-equipment",
        "supply"
    ],
    "wof:name":"Avon Beauty Center",
    "wof:placetype":"venue"
},
  "geometry": {"coordinates":[-97.70628600000001,31.12991],"type":"Point"}
}