{
  "type": "Feature",
  "properties": {
    "iso:country":"US",
    "sg:address":"1208 Co Rd 7760",
    "sg:city":"Lubbock",
    "sg:classifiers":[
        {
            "category":"Wholesale",
            "subcategory":"Machinery & Supplies",
            "type":"Manufacturing & Wholesale Goods"
        }
    ],
    "sg:phone":"+1 806 863 3199",
    "sg:postcode":"79423",
    "sg:province":"TX",
    "sg:tags":[
        "equipment",
        "irrigation",
        "system"
    ],
    "wof:name":"Jay's Irrigation Repair",
    "wof:placetype":"venue"
},
  "geometry": {"coordinates":[-101.84536300000001,33.418269],"type":"Point"}
}