{
  "type": "Feature",
  "properties": {
    "iso:country":"US",
    "sg:address":"1305 N Main St",
    "sg:city":"Fort Stockton",
    "sg:classifiers":[
        {
            "category":"Building & Trades",
            "subcategory":"Electrical",
            "type":"Services"
        }
    ],
    "sg:phone":"+1 432 336 3305",
    "sg:postcode":"79735",
    "sg:province":"TX",
    "sg:tags":[
        "electric",
        "contractor"
    ],
    "wof:name":"Comanche Electric Co Inc",
    "wof:placetype":"venue"
},
  "geometry": {"coordinates":[-102.87916300000001,30.897874],"type":"Point"}
}