{
  "type": "Feature",
  "properties": {
    "iso:country":"US",
    "sg:address":"5411 Havencrest Dr",
    "sg:city":"San Antonio",
    "sg:classifiers":[
        {
            "category":"Manufacturing",
            "subcategory":"Signs",
            "type":"Manufacturing & Wholesale Goods"
        }
    ],
    "sg:phone":"+1 210 675 1298",
    "sg:postcode":"78242",
    "sg:province":"TX",
    "sg:tags":[
        "specialty",
        "mfg"
    ],
    "wof:name":"Rude Dog Signs",
    "wof:placetype":"venue"
},
  "geometry": {"coordinates":[-98.60414900000001,29.366398],"type":"Point"}
}