{
  "type": "Feature",
  "properties": {
    "iso:country":"US",
    "sg:address":"2300 S Bell Blvd",
    "sg:city":"Cedar Park",
    "sg:classifiers":[
        {
            "category":"Social Services",
            "type":"Services"
        }
    ],
    "sg:phone":"+1 512 258 0817",
    "sg:postcode":"78613",
    "sg:province":"TX",
    "sg:tags":[
        "youth",
        "organization",
        "center"
    ],
    "wof:name":"YMCA",
    "wof:placetype":"venue"
},
  "geometry": {"coordinates":[-97.8053,30.481942],"type":"Point"}
}