{
  "type": "Feature",
  "properties": {
    "iso:country":"US",
    "sg:address":"600 W Campbell Rd",
    "sg:city":"Richardson",
    "sg:classifiers":[
        {
            "category":"Health Services",
            "subcategory":"Chiropractor",
            "type":"Services"
        }
    ],
    "sg:phone":"+1 972 238 0500",
    "sg:postcode":"75080",
    "sg:province":"TX",
    "wof:name":"Texas Chiropractic",
    "wof:placetype":"venue"
},
  "geometry": {"coordinates":[-96.741742,32.97808],"type":"Point"}
}