{
  "type": "Feature",
  "properties": {
    "iso:country":"US",
    "sg:address":"2634 Fairmont Dr",
    "sg:city":"Grand Prairie",
    "sg:classifiers":[
        {
            "category":"Professional",
            "subcategory":"Business Services",
            "type":"Services"
        }
    ],
    "sg:phone":"+1 972 641 7836",
    "sg:postcode":"75052",
    "sg:province":"TX",
    "wof:name":"Boateng Enterprise",
    "wof:placetype":"venue"
},
  "geometry": {"coordinates":[-97.044786,32.662572],"type":"Point"}
}