{
  "type": "Feature",
  "properties": {
    "iso:country":"US",
    "sg:address":"9258 Bellaire Blvd",
    "sg:city":"Houston",
    "sg:classifiers":[
        {
            "category":"Cinema",
            "subcategory":"Movie Rental",
            "type":"Entertainment"
        }
    ],
    "sg:phone":"+1 713 272 6565",
    "sg:postcode":"77036",
    "sg:province":"TX",
    "sg:tags":[
        "game",
        "video"
    ],
    "wof:name":"G & H Video",
    "wof:placetype":"venue"
},
  "geometry": {"coordinates":[-95.546097,29.705099],"type":"Point"}
}