{
  "type": "Feature",
  "properties": {
    "iso:country":"US",
    "sg:address":"119 Bristle Ct",
    "sg:city":"Coppell",
    "sg:classifiers":[
        {
            "category":"Professional",
            "subcategory":"Computer Services",
            "type":"Services"
        }
    ],
    "sg:phone":"+1 972 745 3399",
    "sg:postcode":"75019",
    "sg:province":"TX",
    "sg:tags":[
        "prepackaged",
        "software"
    ],
    "wof:name":"Knight Software Sol",
    "wof:placetype":"venue"
},
  "geometry": {"coordinates":[-96.98849800000001,32.969901],"type":"Point"}
}