{
  "type": "Feature",
  "properties": {
    "iso:country":"US",
    "sg:address":"200 N Main St",
    "sg:city":"Winnsboro",
    "sg:classifiers":[
        {
            "category":"Autos & Motor Vehicles",
            "subcategory":"Automobile Sales",
            "type":"Retail Goods"
        }
    ],
    "sg:phone":"+1 903 342 5357",
    "sg:postcode":"75494",
    "sg:province":"TX",
    "sg:tags":[
        "car",
        "dealer"
    ],
    "wof:name":"Newman Brothers",
    "wof:placetype":"venue"
},
  "geometry": {"coordinates":[-95.29005600000001,32.958312],"type":"Point"}
}