{
  "type": "Feature",
  "properties": {
    "iso:country":"US",
    "sg:address":"12330 Lanny Ln",
    "sg:city":"Houston",
    "sg:classifiers":[
        {
            "category":"Professional",
            "subcategory":"Engineering",
            "type":"Services"
        }
    ],
    "sg:phone":"+1 281 558 5418",
    "sg:postcode":"77077",
    "sg:province":"TX",
    "sg:tags":[
        "engineer"
    ],
    "wof:name":"Early Consulting",
    "wof:placetype":"venue"
},
  "geometry": {"coordinates":[-95.59925,29.759192],"type":"Point"}
}