{
  "type": "Feature",
  "properties": {
    "iso:country":"US",
    "sg:address":"107 Crockett St",
    "sg:city":"Hutchins",
    "sg:classifiers":[
        {
            "category":"Wholesale",
            "subcategory":"Furniture",
            "type":"Manufacturing & Wholesale Goods"
        }
    ],
    "sg:phone":"+1 972 225 1833",
    "sg:postcode":"75141",
    "sg:province":"TX",
    "wof:name":"Hutchins Furniture",
    "wof:placetype":"venue"
},
  "geometry": {"coordinates":[-96.719555,32.643884],"type":"Point"}
}