{
  "type": "Feature",
  "properties": {
    "iso:country":"US",
    "sg:address":"10641 Haddington Dr",
    "sg:city":"Houston",
    "sg:classifiers":[
        {
            "category":"Shopping",
            "subcategory":"Stationery & Office Supplies",
            "type":"Retail Goods"
        }
    ],
    "sg:phone":"+1 713 468 2166",
    "sg:postcode":"77043",
    "sg:province":"TX",
    "sg:tags":[
        "equipment"
    ],
    "wof:name":"J Tyler Office Furniture & Services",
    "wof:placetype":"venue"
},
  "geometry": {"coordinates":[-95.558899,29.8006],"type":"Point"}
}