{
  "type": "Feature",
  "properties": {
    "iso:country":"US",
    "sg:address":"611 W Orange Ave",
    "sg:city":"Orange Grove",
    "sg:classifiers":[
        {
            "category":"Restaurant",
            "type":"Food & Drink"
        }
    ],
    "sg:phone":"+1 361 384 0166",
    "sg:postcode":"78372",
    "sg:province":"TX",
    "wof:name":"A A A's Fast Food & Bar-B-Que",
    "wof:placetype":"venue"
},
  "geometry": {"coordinates":[-97.941687,27.959253],"type":"Point"}
}