{
  "type": "Feature",
  "properties": {
    "iso:country":"US",
    "sg:address":"1945 Meander Rd",
    "sg:city":"Granbury",
    "sg:classifiers":[
        {
            "category":"Professional",
            "type":"Services"
        }
    ],
    "sg:phone":"+1 817 279 9228",
    "sg:postcode":"76049",
    "sg:province":"TX",
    "wof:name":"Specialty Buildings",
    "wof:placetype":"venue"
},
  "geometry": {"coordinates":[-97.739447,32.497595],"type":"Point"}
}