{
  "type": "Feature",
  "properties": {
    "iso:country":"US",
    "sg:address":"8802 Brookhollow Dr",
    "sg:city":"Rowlett",
    "sg:classifiers":[
        {
            "category":"Wholesale",
            "subcategory":"Vending Machines",
            "type":"Manufacturing & Wholesale Goods"
        }
    ],
    "sg:phone":"+1 972 475 8600",
    "sg:postcode":"75089",
    "sg:province":"TX",
    "wof:name":"Chewy Sales",
    "wof:placetype":"venue"
},
  "geometry": {"coordinates":[-96.51581400000001,32.924036],"type":"Point"}
}