{
  "type": "Feature",
  "properties": {
    "iso:country":"US",
    "sg:address":"701 Tillery Street",
    "sg:city":"Austin",
    "sg:classifiers":[
        {
            "category":"Organizations",
            "subcategory":"Religious Organization",
            "type":"Services"
        }
    ],
    "sg:phone":"+1 512 386 9145",
    "sg:postcode":"78702",
    "sg:province":"TX",
    "wof:name":"Austin Area Interreligious Ministries",
    "wof:placetype":"venue"
},
  "geometry": {"coordinates":[-97.70469199999999,30.260572],"type":"Point"}
}