{
  "type": "Feature",
  "properties": {
    "iso:country":"US",
    "sg:address":"5904 Sandhills Cir",
    "sg:city":"Plano",
    "sg:classifiers":[
        {
            "category":"Building & Trades",
            "subcategory":"Construction",
            "type":"Services"
        }
    ],
    "sg:phone":"+1 972 608 8808",
    "sg:postcode":"75093",
    "sg:province":"TX",
    "sg:tags":[
        "interior",
        "decorator"
    ],
    "wof:name":"Distinctive Decorating",
    "wof:placetype":"venue"
},
  "geometry": {"coordinates":[-96.82413200000001,33.048355],"type":"Point"}
}