{
  "type": "Feature",
  "properties": {
    "iso:country":"US",
    "sg:address":"3406 Granite Dr",
    "sg:city":"Killeen",
    "sg:classifiers":[
        {
            "category":"Government",
            "subcategory":"Office",
            "type":"Public Place"
        }
    ],
    "sg:phone":"+1 254 287 3594",
    "sg:postcode":"76549",
    "sg:province":"TX",
    "sg:tags":[
        "national",
        "security"
    ],
    "wof:name":"Army  United States Dept of",
    "wof:placetype":"venue"
},
  "geometry": {"coordinates":[-97.766518,31.087425],"type":"Point"}
}