{
  "type": "Feature",
  "properties": {
    "iso:country":"US",
    "sg:address":"1717 Marshall St",
    "sg:city":"Vernon",
    "sg:classifiers":[
        {
            "category":"Organizations",
            "subcategory":"Community Association",
            "type":"Services"
        }
    ],
    "sg:phone":"+1 940 552 5800",
    "sg:postcode":"76384",
    "sg:province":"TX",
    "sg:tags":[
        "fraternal"
    ],
    "wof:name":"Masonic Lodge",
    "wof:placetype":"venue"
},
  "geometry": {"coordinates":[-99.284277,34.151786],"type":"Point"}
}