{
  "type": "Feature",
  "properties": {
    "iso:country":"US",
    "sg:address":"507 US Hwy 77",
    "sg:city":"Waxahachie",
    "sg:classifiers":[
        {
            "category":"Shopping",
            "type":"Retail Goods"
        },
        {
            "category":"Shopping",
            "subcategory":"Computers & Home Electronics",
            "type":"Retail Goods"
        }
    ],
    "sg:phone":"+1 972 923 2318",
    "sg:postcode":"75165",
    "sg:province":"TX",
    "sg:tags":[
        "telephone",
        "cellular"
    ],
    "wof:name":"Radio Shack",
    "wof:placetype":"venue"
},
  "geometry": {"coordinates":[-96.841666,32.412881],"type":"Point"}
}