{
  "type": "Feature",
  "properties": {
    "iso:country":"US",
    "sg:address":"5820 Alpha Rd",
    "sg:city":"Dallas",
    "sg:classifiers":[
        {
            "category":"Banks & Credit Unions",
            "subcategory":"Bank",
            "type":"Services"
        }
    ],
    "sg:phone":"+1 972 980 4443",
    "sg:postcode":"75240",
    "sg:province":"TX",
    "wof:name":"Sterling Bank",
    "wof:placetype":"venue"
},
  "geometry": {"coordinates":[-96.806991,32.93263],"type":"Point"}
}