{
  "type": "Feature",
  "properties": {
    "iso:country":"US",
    "sg:address":"2021 S Cooper St",
    "sg:city":"Arlington",
    "sg:classifiers":[
        {
            "category":"Home & Garden",
            "subcategory":"Home Furnishings",
            "type":"Retail Goods"
        }
    ],
    "sg:phone":"+1 817 226 7890",
    "sg:postcode":"76010",
    "sg:province":"TX",
    "sg:tags":[
        "curtain",
        "made",
        "drapery"
    ],
    "sg:website":"www.lelandswallpaper.com",
    "wof:name":"Leland's Wallpaper & Interiors",
    "wof:placetype":"venue"
},
  "geometry": {"coordinates":[-97.11453299999999,32.712562],"type":"Point"}
}