{
  "type": "Feature",
  "properties": {
    "iso:country":"US",
    "sg:address":"7931 Northaven Rd",
    "sg:city":"Dallas",
    "sg:classifiers":[
        {
            "category":"Retail",
            "subcategory":"Auto Repair",
            "type":"Services"
        }
    ],
    "sg:phone":"+1 214 750 8858",
    "sg:postcode":"75230",
    "sg:province":"TX",
    "sg:tags":[
        "automobile",
        "lubrication"
    ],
    "wof:name":"Northaven Lube & Oil Change",
    "wof:placetype":"venue"
},
  "geometry": {"coordinates":[-96.76952,32.901797],"type":"Point"}
}