{
  "type": "Feature",
  "properties": {
    "iso:country":"US",
    "sg:address":"1210 Boston Ave",
    "sg:city":"New Boston",
    "sg:classifiers":[
        {
            "category":"Organizations",
            "subcategory":"Religious Organization",
            "type":"Services"
        }
    ],
    "sg:phone":"+1 903 849 5116",
    "sg:postcode":"75570",
    "sg:province":"TX",
    "wof:name":"Servanthood Ministries Inc",
    "wof:placetype":"venue"
},
  "geometry": {"coordinates":[-94.419791,33.441533],"type":"Point"}
}