{
  "type": "Feature",
  "properties": {
    "iso:country":"US",
    "sg:address":"808 S Central Expy",
    "sg:city":"Dallas",
    "sg:classifiers":[
        {
            "category":"Retail",
            "subcategory":"Auto Repair",
            "type":"Services"
        }
    ],
    "sg:phone":"+1 972 852 0378",
    "sg:postcode":"75201",
    "sg:province":"TX",
    "sg:tags":[
        "body",
        "automobile",
        "painting"
    ],
    "wof:name":"Service King Collision",
    "wof:placetype":"venue"
},
  "geometry": {"coordinates":[-96.78883500000001,32.779082],"type":"Point"}
}