{
  "type": "Feature",
  "properties": {
    "iso:country":"US",
    "sg:address":"240 S Stemmons Fwy",
    "sg:city":"Lewisville",
    "sg:classifiers":[
        {
            "category":"Shopping",
            "subcategory":"Clothing, Apparel, & Fashions",
            "type":"Retail Goods"
        }
    ],
    "sg:phone":"+1 972 315 0739",
    "sg:postcode":"75067",
    "sg:province":"TX",
    "sg:website":"www.augustmaxwoman.com",
    "wof:name":"August Max Woman",
    "wof:placetype":"venue"
},
  "geometry": {"coordinates":[-97.00738800000001,33.044758],"type":"Point"}
}