{
  "type": "Feature",
  "properties": {
    "iso:country":"US",
    "sg:address":"7121 Robin Meadow St",
    "sg:city":"Pearland",
    "sg:classifiers":[
        {
            "category":"Professional",
            "subcategory":"Management & Consulting",
            "type":"Services"
        }
    ],
    "sg:phone":"+1 281 996 8791",
    "sg:postcode":"77581",
    "sg:province":"TX",
    "sg:tags":[
        "business"
    ],
    "wof:name":"Ahh Services Inc",
    "wof:placetype":"venue"
},
  "geometry": {"coordinates":[-95.330579,29.574441],"type":"Point"}
}