{
  "type": "Feature",
  "properties": {
    "iso:country":"US",
    "sg:address":"10700 McPherson Ave",
    "sg:city":"Laredo",
    "sg:classifiers":[
        {
            "category":"Health Services",
            "subcategory":"Doctor",
            "type":"Services"
        }
    ],
    "sg:phone":"+1 956 724 8543",
    "sg:postcode":"78045",
    "sg:province":"TX",
    "sg:tags":[
        "physician",
        "surgeon"
    ],
    "wof:name":"Medical Oncology/Hematology",
    "wof:placetype":"venue"
},
  "geometry": {"coordinates":[-99.476493,27.607882],"type":"Point"}
}