{
  "type": "Feature",
  "properties": {
    "iso:country":"US",
    "sg:address":"1621 Austin Ave",
    "sg:city":"Brownwood",
    "sg:classifiers":[
        {
            "category":"Retail",
            "subcategory":"Repair Shop",
            "type":"Services"
        }
    ],
    "sg:phone":"+1 325 646 8183",
    "sg:postcode":"76801",
    "sg:province":"TX",
    "sg:tags":[
        "satellite",
        "system"
    ],
    "wof:name":"Shaw TV",
    "wof:placetype":"venue"
},
  "geometry": {"coordinates":[-98.97551900000001,31.707488],"type":"Point"}
}