{
  "type": "Feature",
  "properties": {
    "iso:country":"US",
    "sg:address":"5189 Texas Ave",
    "sg:city":"Abilene",
    "sg:classifiers":[
        {
            "category":"Professional",
            "subcategory":"Research",
            "type":"Services"
        }
    ],
    "sg:phone":"+1 325 692 4690",
    "sg:postcode":"79605",
    "sg:province":"TX",
    "sg:tags":[
        "environmental",
        "ecological"
    ],
    "wof:name":"International Consultants",
    "wof:placetype":"venue"
},
  "geometry": {"coordinates":[-99.790356,32.423636],"type":"Point"}
}