{
  "type": "Feature",
  "properties": {
    "iso:country":"US",
    "sg:address":"2905 S Zapata Hwy",
    "sg:city":"Laredo",
    "sg:classifiers":[
        {
            "category":"Insurance",
            "subcategory":"Insurance Agent",
            "type":"Services"
        },
        {
            "category":"Banks & Credit Unions",
            "subcategory":"Investment Brokerage",
            "type":"Services"
        },
        {
            "category":"Insurance",
            "subcategory":"Hazard Insurance",
            "type":"Services"
        }
    ],
    "sg:phone":"+1 956 729 1858",
    "sg:postcode":"78046",
    "sg:province":"TX",
    "sg:tags":[
        "auto",
        "motorcycle",
        "resume"
    ],
    "sg:website":"http://www.directgeneral.com",
    "wof:name":"Direct Auto Insurance",
    "wof:placetype":"venue"
},
  "geometry": {"coordinates":[-99.476645,27.471352],"type":"Point"}
}