{
  "type": "Feature",
  "properties": {
    "iso:country":"US",
    "sg:address":"2123 Silverado Dr",
    "sg:city":"Dallas",
    "sg:classifiers":[
        {
            "category":"Manufacturing",
            "subcategory":"Glass & Minerals",
            "type":"Manufacturing & Wholesale Goods"
        }
    ],
    "sg:phone":"+1 972 557 3909",
    "sg:postcode":"75253",
    "sg:province":"TX",
    "sg:tags":[
        "mfg"
    ],
    "wof:name":"B & A Glass",
    "wof:placetype":"venue"
},
  "geometry": {"coordinates":[-96.62364100000001,32.681722],"type":"Point"}
}