{
  "type": "Feature",
  "properties": {
    "iso:country":"US",
    "sg:address":"2815 N Macarthur Blvd",
    "sg:city":"Irving",
    "sg:classifiers":[
        {
            "category":"Insurance",
            "subcategory":"Hazard Insurance",
            "type":"Services"
        }
    ],
    "sg:phone":"+1 972 252 4546",
    "sg:postcode":"75062",
    "sg:province":"TX",
    "sg:tags":[
        "carrier"
    ],
    "wof:name":"All-Star Insurance Agency",
    "wof:placetype":"venue"
},
  "geometry": {"coordinates":[-96.95913299999999,32.845337],"type":"Point"}
}