{
  "type": "Feature",
  "properties": {
    "iso:country":"US",
    "sg:address":"3218 Timber Village Dr",
    "sg:city":"Houston",
    "sg:classifiers":[
        {
            "category":"Professional",
            "subcategory":"Management & Consulting",
            "type":"Services"
        }
    ],
    "sg:phone":"+1 281 586 8744",
    "sg:postcode":"77068",
    "sg:province":"TX",
    "wof:name":"Cornerstone Sales Assoc",
    "wof:placetype":"venue"
},
  "geometry": {"coordinates":[-95.484627,30.008639],"type":"Point"}
}