{
  "type": "Feature",
  "properties": {
    "iso:country":"US",
    "sg:address":"5440 Babcock Rd",
    "sg:city":"San Antonio",
    "sg:classifiers":[
        {
            "category":"Recreation",
            "type":"Entertainment"
        }
    ],
    "sg:phone":"+1 210 699 3686",
    "sg:postcode":"78240",
    "sg:province":"TX",
    "sg:tags":[
        "martial",
        "arts",
        "instruction"
    ],
    "wof:name":"American Kenpo Karate",
    "wof:placetype":"venue"
},
  "geometry": {"coordinates":[-98.594542,29.516929],"type":"Point"}
}