{
  "type": "Feature",
  "properties": {
    "iso:country":"US",
    "sg:address":"8390 Bellaire Blvd",
    "sg:city":"Houston",
    "sg:classifiers":[
        {
            "category":"Autos & Motor Vehicles",
            "subcategory":"Automobile Sales",
            "type":"Retail Goods"
        }
    ],
    "sg:phone":"+1 713 774 2344",
    "sg:postcode":"77036",
    "sg:province":"TX",
    "wof:name":"Cegi Cars",
    "wof:placetype":"venue"
},
  "geometry": {"coordinates":[-95.532479,29.705121],"type":"Point"}
}