{
  "type": "Feature",
  "properties": {
    "iso:country":"US",
    "sg:address":"525 State Hwy 276",
    "sg:city":"Quinlan",
    "sg:classifiers":[
        {
            "category":"Food & Beverages",
            "subcategory":"Liquor & Beverages",
            "type":"Retail Goods"
        }
    ],
    "sg:phone":"+1 903 447 4002",
    "sg:postcode":"75474",
    "sg:province":"TX",
    "wof:name":"Scottie's Liquor",
    "wof:placetype":"venue"
},
  "geometry": {"coordinates":[-96.14014,32.910315],"type":"Point"}
}