{
  "type": "Feature",
  "properties": {
    "iso:country":"US",
    "sg:address":"3621 8th Ave",
    "sg:city":"Fort Worth",
    "sg:classifiers":[
        {
            "category":"Building & Trades",
            "subcategory":"Construction",
            "type":"Services"
        }
    ],
    "sg:phone":"+1 817 926 3250",
    "sg:postcode":"76110",
    "sg:province":"TX",
    "sg:tags":[
        "concrete",
        "contractor"
    ],
    "wof:name":"R Jones Concrete Construction",
    "wof:placetype":"venue"
},
  "geometry": {"coordinates":[-97.34369100000001,32.695307],"type":"Point"}
}