{
  "type": "Feature",
  "properties": {
    "iso:country":"US",
    "sg:address":"2111 Dickson Drive",
    "sg:city":"Austin",
    "sg:classifiers":[
        {
            "category":"Health Services",
            "subcategory":"Health Practitioner",
            "type":"Services"
        }
    ],
    "sg:phone":"+1 512 707 7688",
    "sg:postcode":"78704",
    "sg:province":"TX",
    "sg:tags":[
        "therapy",
        "physical"
    ],
    "wof:name":"Shunn Brenda E Lpt Rmt",
    "wof:placetype":"venue"
},
  "geometry": {"coordinates":[-97.78036400000001,30.245695],"type":"Point"}
}