{
  "type": "Feature",
  "properties": {
    "iso:country":"US",
    "sg:address":"3040 Timberview Rd",
    "sg:city":"Dallas",
    "sg:classifiers":[
        {
            "category":"Autos & Motor Vehicles",
            "subcategory":"Automobile Sales",
            "type":"Retail Goods"
        }
    ],
    "sg:postcode":"75229",
    "sg:province":"TX",
    "sg:tags":[
        "automotive"
    ],
    "wof:name":"Stoid Racing",
    "wof:placetype":"venue"
},
  "geometry": {"coordinates":[-96.87276300000001,32.883164],"type":"Point"}
}