{
  "type": "Feature",
  "properties": {
    "iso:country":"US",
    "sg:address":"6133 Airline Dr",
    "sg:city":"Houston",
    "sg:classifiers":[
        {
            "category":"Banks & Credit Unions",
            "subcategory":"Bank",
            "type":"Services"
        }
    ],
    "sg:phone":"+1 713 699 0868",
    "sg:postcode":"77076",
    "sg:province":"TX",
    "sg:tags":[
        "depository",
        "banking"
    ],
    "wof:name":"Telegiro Nino",
    "wof:placetype":"venue"
},
  "geometry": {"coordinates":[-95.384704,29.855232],"type":"Point"}
}