{
  "type": "Feature",
  "properties": {
    "iso:country":"US",
    "sg:address":"17112 Rocky Ridge Rd",
    "sg:city":"Austin",
    "sg:classifiers":[
        {
            "category":"Wholesale",
            "subcategory":"Durable Goods & Equipment",
            "type":"Manufacturing & Wholesale Goods"
        }
    ],
    "sg:phone":"+1 512 266 2706",
    "sg:postcode":"78734",
    "sg:province":"TX",
    "wof:name":"Weinberg Bros Partnership",
    "wof:placetype":"venue"
},
  "geometry": {"coordinates":[-97.93846000000001,30.419933],"type":"Point"}
}