{
  "type": "Feature",
  "properties": {
    "iso:country":"US",
    "sg:address":"202 Lakeview Dr",
    "sg:city":"Mathis",
    "sg:classifiers":[
        {
            "category":"Shopping",
            "subcategory":"Gifts & Souvenirs",
            "type":"Retail Goods"
        }
    ],
    "sg:phone":"+1 361 547 3696",
    "sg:postcode":"78368",
    "sg:province":"TX",
    "wof:name":"Unique Crafts",
    "wof:placetype":"venue"
},
  "geometry": {"coordinates":[-97.86799600000001,28.090166],"type":"Point"}
}