{
  "type": "Feature",
  "properties": {
    "iso:country":"US",
    "sg:address":"543 State Hwy 46 W",
    "sg:city":"Boerne",
    "sg:classifiers":[
        {
            "category":"Professional",
            "type":"Services"
        }
    ],
    "sg:phone":"+1 830 537 4600",
    "sg:postcode":"78006",
    "sg:province":"TX",
    "sg:tags":[
        "establishment"
    ],
    "wof:name":"Alamo Area Operating",
    "wof:placetype":"venue"
},
  "geometry": {"coordinates":[-98.815297,29.751453],"type":"Point"}
}