{
  "type": "Feature",
  "properties": {
    "iso:country":"US",
    "sg:address":"1301 S Lincoln Ave",
    "sg:city":"San Juan",
    "sg:classifiers":[
        {
            "category":"Shopping",
            "subcategory":"Gifts & Souvenirs",
            "type":"Retail Goods"
        }
    ],
    "sg:phone":"+1 956 787 7778",
    "sg:postcode":"78589",
    "sg:province":"TX",
    "wof:name":"Cherchwerks",
    "wof:placetype":"venue"
},
  "geometry": {"coordinates":[-98.15832899999999,26.181936],"type":"Point"}
}