{
  "type": "Feature",
  "properties": {
    "iso:country":"US",
    "sg:address":"1407 E Rusk St",
    "sg:city":"Jacksonville",
    "sg:classifiers":[
        {
            "category":"Restaurant",
            "type":"Food & Drink"
        }
    ],
    "sg:phone":"+1 903 589 9043",
    "sg:postcode":"75766",
    "sg:province":"TX",
    "wof:name":"Hot Biscuit Family",
    "wof:placetype":"venue"
},
  "geometry": {"coordinates":[-95.249893,31.966008],"type":"Point"}
}