{
  "type": "Feature",
  "properties": {
    "iso:country":"US",
    "sg:address":"6435 FM 603",
    "sg:city":"Clyde",
    "sg:classifiers":[
        {
            "category":"Retail",
            "subcategory":"Car Wash",
            "type":"Services"
        }
    ],
    "sg:phone":"+1 325 529 4891",
    "sg:postcode":"79510",
    "sg:province":"TX",
    "sg:tags":[
        "polishing",
        "carwash",
        "washing"
    ],
    "wof:name":"Steve's Mobile Wash",
    "wof:placetype":"venue"
},
  "geometry": {"coordinates":[-99.562133,32.335476],"type":"Point"}
}