{
  "type": "Feature",
  "properties": {
    "iso:country":"US",
    "sg:address":"2807 Hillcrest Dr",
    "sg:city":"San Antonio",
    "sg:classifiers":[
        {
            "category":"Restaurant",
            "type":"Food & Drink"
        }
    ],
    "sg:phone":"+1 210 734 6766",
    "sg:postcode":"78201",
    "sg:province":"TX",
    "sg:tags":[
        "eating"
    ],
    "wof:name":"Culebra Meat Market No 13",
    "wof:placetype":"venue"
},
  "geometry": {"coordinates":[-98.559152,29.484579],"type":"Point"}
}