{
  "type": "Feature",
  "properties": {
    "iso:country":"US",
    "sg:address":"5002 S 2nd Ave",
    "sg:city":"Dallas",
    "sg:classifiers":[
        {
            "category":"Food & Beverages",
            "subcategory":"Liquor & Beverages",
            "type":"Retail Goods"
        }
    ],
    "sg:phone":"+1 214 421 8535",
    "sg:postcode":"75210",
    "sg:province":"TX",
    "sg:tags":[
        "beer",
        "wine",
        "spirit",
        "alcoholic"
    ],
    "wof:name":"Buy & Save",
    "wof:placetype":"venue"
},
  "geometry": {"coordinates":[-96.74299600000001,32.759602],"type":"Point"}
}