{
  "type": "Feature",
  "properties": {
    "iso:country":"US",
    "sg:address":"2603 San Paula Ave",
    "sg:city":"Dallas",
    "sg:classifiers":[
        {
            "category":"Building & Trades",
            "subcategory":"Construction",
            "type":"Services"
        }
    ],
    "sg:phone":"+1 214 320 2608",
    "sg:postcode":"75228",
    "sg:province":"TX",
    "sg:tags":[
        "contractor"
    ],
    "wof:name":"Abundis & Sons Trading Co",
    "wof:placetype":"venue"
},
  "geometry": {"coordinates":[-96.669979,32.832148],"type":"Point"}
}