{
  "type": "Feature",
  "properties": {
    "iso:country":"US",
    "sg:address":"7803 Dashwood Dr",
    "sg:city":"Houston",
    "sg:classifiers":[
        {
            "category":"Professional",
            "subcategory":"Management & Consulting",
            "type":"Services"
        }
    ],
    "sg:phone":"+1 713 771 6739",
    "sg:postcode":"77036",
    "sg:province":"TX",
    "sg:tags":[
        "call",
        "center",
        "for",
        "operational"
    ],
    "wof:name":"Richardson and Associates",
    "wof:placetype":"venue"
},
  "geometry": {"coordinates":[-95.52269099999999,29.70741],"type":"Point"}
}