{
  "type": "Feature",
  "properties": {
    "iso:country":"US",
    "sg:address":"399 Melrose Dr",
    "sg:city":"Richardson",
    "sg:classifiers":[
        {
            "category":"Health Services",
            "subcategory":"Doctor",
            "type":"Services"
        }
    ],
    "sg:phone":"+1 972 421 4673",
    "sg:postcode":"75080",
    "sg:province":"TX",
    "wof:name":"Gressler Volker MD",
    "wof:placetype":"venue"
},
  "geometry": {"coordinates":[-96.72945199999999,32.969442],"type":"Point"}
}