{
  "type": "Feature",
  "properties": {
    "iso:country":"US",
    "sg:address":"2202 Ave Gregory",
    "sg:city":"Brownsville",
    "sg:classifiers":[
        {
            "category":"Food & Beverages",
            "subcategory":"Groceries & Convenience Stores",
            "type":"Retail Goods"
        }
    ],
    "sg:phone":"+1 956 574 0786",
    "sg:postcode":"78526",
    "sg:province":"TX",
    "sg:tags":[
        "grocer"
    ],
    "wof:name":"Grocery Services South",
    "wof:placetype":"venue"
},
  "geometry": {"coordinates":[-97.4828,25.970629],"type":"Point"}
}