{
  "type": "Feature",
  "properties": {
    "iso:country":"US",
    "sg:address":"2706 Double Lake Dr",
    "sg:city":"Missouri City",
    "sg:classifiers":[
        {
            "category":"Professional",
            "subcategory":"Business Services",
            "type":"Services"
        }
    ],
    "sg:phone":"+1 281 261 2293",
    "sg:postcode":"77459",
    "sg:province":"TX",
    "sg:tags":[
        "broker",
        "sign"
    ],
    "wof:name":"Coree Sign Co",
    "wof:placetype":"venue"
},
  "geometry": {"coordinates":[-95.579387,29.577378],"type":"Point"}
}