{
  "type": "Feature",
  "properties": {
    "iso:country":"US",
    "sg:address":"34011 Dobbin Hufsmith Rd",
    "sg:city":"Magnolia",
    "sg:classifiers":[
        {
            "category":"Shopping",
            "subcategory":"Bicycles & Sporting Goods",
            "type":"Retail Goods"
        }
    ],
    "sg:phone":"+1 281 259 6723",
    "sg:postcode":"77354",
    "sg:province":"TX",
    "wof:name":"Quarter Box 3 Performance",
    "wof:placetype":"venue"
},
  "geometry": {"coordinates":[-95.67524299999999,30.208367],"type":"Point"}
}