{
  "type": "Feature",
  "properties": {
    "iso:country":"US",
    "sg:address":"1515 Old Ector Rd",
    "sg:city":"Bonham",
    "sg:classifiers":[
        {
            "category":"Travel",
            "subcategory":"Hotels & Motels",
            "type":"Entertainment"
        },
        {
            "category":"Professional",
            "subcategory":"Management & Consulting",
            "type":"Services"
        }
    ],
    "sg:phone":"+1 903 583 3121",
    "sg:postcode":"75418",
    "sg:province":"TX",
    "sg:tags":[
        "consultant",
        "lodging"
    ],
    "sg:website":"http://www.americasbestvalueinn.com",
    "wof:name":"Americas Best Value Inn",
    "wof:placetype":"venue"
},
  "geometry": {"coordinates":[-96.195975,33.573792],"type":"Point"}
}