{
  "type": "Feature",
  "properties": {
    "iso:country":"US",
    "sg:address":"5203 Seguin Rd",
    "sg:city":"San Antonio",
    "sg:classifiers":[
        {
            "category":"Health Services",
            "subcategory":"Medical Lab",
            "type":"Services"
        }
    ],
    "sg:phone":"+1 210 666 3397",
    "sg:postcode":"78219",
    "sg:province":"TX",
    "sg:tags":[
        "laboratory",
        "dental"
    ],
    "wof:name":"Quality Denture Lab",
    "wof:placetype":"venue"
},
  "geometry": {"coordinates":[-98.390154,29.467005],"type":"Point"}
}