{
  "type": "Feature",
  "properties": {
    "iso:country":"US",
    "sg:address":"9933 Regal Row",
    "sg:city":"Houston",
    "sg:classifiers":[
        {
            "category":"Building & Trades",
            "subcategory":"Construction",
            "type":"Services"
        },
        {
            "category":"Home & Garden",
            "subcategory":"Carpets & Floor Coverings",
            "type":"Retail Goods"
        }
    ],
    "sg:phone":"+1 713 869 9800",
    "sg:postcode":"77040",
    "sg:province":"TX",
    "sg:tags":[
        "sub",
        "rug"
    ],
    "sg:website":"http://www.texascontract.net",
    "wof:name":"Texas Contract Carpet",
    "wof:placetype":"venue"
},
  "geometry": {"coordinates":[-95.548436,29.873129],"type":"Point"}
}