{
  "type": "Feature",
  "properties": {
    "iso:country":"US",
    "sg:address":"919 Dutton Ave",
    "sg:city":"Waco",
    "sg:classifiers":[
        {
            "category":"Organizations",
            "subcategory":"Religious Organization",
            "type":"Services"
        }
    ],
    "sg:phone":"+1 254 754 0924",
    "sg:postcode":"76706",
    "sg:province":"TX",
    "sg:tags":[
        "church"
    ],
    "wof:name":"Greater Ebenezer Baptist",
    "wof:placetype":"venue"
},
  "geometry": {"coordinates":[-97.126549,31.545478],"type":"Point"}
}