{
  "type": "Feature",
  "properties": {
    "iso:country":"US",
    "sg:address":"5741 San Felipe St Ste 1700",
    "sg:city":"Houston",
    "sg:classifiers":[
        {
            "category":"Health Services",
            "subcategory":"Clinic",
            "type":"Services"
        },
        {
            "category":"Insurance",
            "subcategory":"Health Insurance",
            "type":"Services"
        }
    ],
    "sg:phone":"+1 866 941 9473",
    "sg:postcode":"77057",
    "sg:province":"TX",
    "sg:tags":[
        "loss",
        "market",
        "weight"
    ],
    "sg:website":"www.naturallyhealthychefs.com",
    "wof:name":"Naturally Healthy Chefs",
    "wof:placetype":"venue"
},
  "geometry": {"coordinates":[-95.478663,29.749948],"type":"Point"}
}