{
  "type": "Feature",
  "properties": {
    "iso:country":"US",
    "sg:address":"1300 Kings Brook Ct",
    "sg:city":"Southlake",
    "sg:classifiers":[
        {
            "category":"Retail",
            "subcategory":"Laundry & Dry Cleaning",
            "type":"Services"
        }
    ],
    "sg:phone":"+1 817 329 1592",
    "sg:postcode":"76092",
    "sg:province":"TX",
    "wof:name":"JW Designs",
    "wof:placetype":"venue"
},
  "geometry": {"coordinates":[-97.125552,32.935274],"type":"Point"}
}