{
  "type": "Feature",
  "properties": {
    "iso:country":"US",
    "sg:address":"1228 W Scyene Rd",
    "sg:city":"Mesquite",
    "sg:classifiers":[
        {
            "category":"Retail",
            "subcategory":"Auto Repair",
            "type":"Services"
        }
    ],
    "sg:phone":"+1 972 329 5855",
    "sg:postcode":"75149",
    "sg:province":"TX",
    "sg:tags":[
        "repairing",
        "automobile"
    ],
    "wof:name":"Winfred's Benz Svc",
    "wof:placetype":"venue"
},
  "geometry": {"coordinates":[-96.61724700000001,32.769552],"type":"Point"}
}