{
  "type": "Feature",
  "properties": {
    "iso:country":"US",
    "sg:address":"2100 W Loop Fwy",
    "sg:city":"Houston",
    "sg:classifiers":[
        {
            "category":"Professional",
            "type":"Services"
        }
    ],
    "sg:phone":"+1 713 590 5055",
    "sg:postcode":"77027",
    "sg:province":"TX",
    "sg:tags":[
        "establishment"
    ],
    "wof:name":"Adv Chemical",
    "wof:placetype":"venue"
},
  "geometry": {"coordinates":[-95.45718100000001,29.74675],"type":"Point"}
}