{
  "type": "Feature",
  "properties": {
    "iso:country":"US",
    "sg:address":"7154 Oaklawn Dr",
    "sg:city":"San Antonio",
    "sg:classifiers":[
        {
            "category":"Education",
            "subcategory":"Special Training",
            "type":"Public Place"
        },
        {
            "category":"Professional",
            "subcategory":"Employment Agencies",
            "type":"Services"
        }
    ],
    "sg:phone":"+1 210 344 7317",
    "sg:postcode":"78229",
    "sg:province":"TX",
    "sg:tags":[
        "school"
    ],
    "wof:name":"Bartending Schl of San Antonio",
    "wof:placetype":"venue"
},
  "geometry": {"coordinates":[-98.555864,29.499457],"type":"Point"}
}