{
  "type": "Feature",
  "properties": {
    "iso:country":"US",
    "sg:address":"4123 W 34th Ave",
    "sg:city":"Amarillo",
    "sg:classifiers":[
        {
            "category":"Retail",
            "subcategory":"Repair Shop",
            "type":"Services"
        }
    ],
    "sg:phone":"+1 806 359 5611",
    "sg:postcode":"79109",
    "sg:province":"TX",
    "sg:tags":[
        "repairing",
        "picture",
        "frame"
    ],
    "wof:name":"Right Angle",
    "wof:placetype":"venue"
},
  "geometry": {"coordinates":[-101.882835,35.178278],"type":"Point"}
}