{
  "type": "Feature",
  "properties": {
    "iso:country":"US",
    "sg:address":"211 N Anglin St",
    "sg:city":"Cleburne",
    "sg:classifiers":[
        {
            "category":"Shopping",
            "type":"Retail Goods"
        }
    ],
    "sg:phone":"+1 817 645 5565",
    "sg:postcode":"76031",
    "sg:province":"TX",
    "sg:tags":[
        "merchandise"
    ],
    "wof:name":"Jones Audiology & Hearing Aid",
    "wof:placetype":"venue"
},
  "geometry": {"coordinates":[-97.385335,32.348683],"type":"Point"}
}