{
  "type": "Feature",
  "properties": {
    "iso:country":"US",
    "sg:address":"108 N Wood St",
    "sg:city":"Gilmer",
    "sg:classifiers":[
        {
            "category":"Retail",
            "subcategory":"Auto Repair",
            "type":"Services"
        }
    ],
    "sg:phone":"+1 903 843 2913",
    "sg:postcode":"75644",
    "sg:province":"TX",
    "sg:tags":[
        "repairing",
        "automobile"
    ],
    "wof:name":"Speedy Jim's Auto Svc",
    "wof:placetype":"venue"
},
  "geometry": {"coordinates":[-94.94279,32.729682],"type":"Point"}
}