{
  "type": "Feature",
  "properties": {
    "iso:country":"US",
    "sg:address":"909 US Hwy 83",
    "sg:city":"Zapata",
    "sg:classifiers":[
        {
            "category":"Food & Beverages",
            "subcategory":"Groceries & Convenience Stores",
            "type":"Retail Goods"
        }
    ],
    "sg:phone":"+1 956 765 4861",
    "sg:postcode":"78076",
    "sg:province":"TX",
    "sg:tags":[
        "grocer"
    ],
    "wof:name":"Super S Foods",
    "wof:placetype":"venue"
},
  "geometry": {"coordinates":[-99.260563,26.888241],"type":"Point"}
}