{
  "type": "Feature",
  "properties": {
    "iso:country":"US",
    "sg:address":"9335 Stella Link Rd",
    "sg:city":"Houston",
    "sg:classifiers":[
        {
            "category":"Home & Garden",
            "subcategory":"Household Appliances",
            "type":"Retail Goods"
        }
    ],
    "sg:phone":"+1 713 218 8844",
    "sg:postcode":"77025",
    "sg:province":"TX",
    "sg:tags":[
        "machine",
        "repair",
        "major",
        "dishwashing",
        "appliances-small"
    ],
    "sg:website":"http://www.conns.com",
    "wof:name":"Conn's",
    "wof:placetype":"venue"
},
  "geometry": {"coordinates":[-95.439697,29.680401],"type":"Point"}
}