{
  "type": "Feature",
  "properties": {
    "iso:country":"US",
    "sg:address":"9203 Saddle Horn Ct",
    "sg:city":"Prosper",
    "sg:classifiers":[
        {
            "category":"Real Estate",
            "subcategory":"Real Estate Agent",
            "type":"Services"
        }
    ],
    "sg:phone":"+1 972 569 9996",
    "sg:postcode":"75078",
    "sg:province":"TX",
    "wof:name":"Lish Co",
    "wof:placetype":"venue"
},
  "geometry": {"coordinates":[-96.753563,33.276504],"type":"Point"}
}