{
  "type": "Feature",
  "properties": {
    "iso:country":"US",
    "sg:address":"4340 Cedar Springs Rd",
    "sg:city":"Dallas",
    "sg:classifiers":[
        {
            "category":"Arts & Performance",
            "subcategory":"Theater",
            "type":"Entertainment"
        }
    ],
    "sg:phone":"+1 214 526 3554",
    "sg:postcode":"75219",
    "sg:province":"TX",
    "sg:tags":[
        "group"
    ],
    "wof:name":"Kalimka",
    "wof:placetype":"venue"
},
  "geometry": {"coordinates":[-96.815657,32.814563],"type":"Point"}
}