{
  "type": "Feature",
  "properties": {
    "iso:country":"US",
    "sg:address":"7800 Lyons Ave",
    "sg:city":"Houston",
    "sg:classifiers":[
        {
            "category":"Autos & Motor Vehicles",
            "subcategory":"Auto Supplies",
            "type":"Retail Goods"
        }
    ],
    "sg:phone":"+1 713 670 9959",
    "sg:postcode":"77029",
    "sg:province":"TX",
    "sg:tags":[
        "tire"
    ],
    "wof:name":"R D M Tire Service",
    "wof:placetype":"venue"
},
  "geometry": {"coordinates":[-95.28822599999999,29.776652],"type":"Point"}
}