{
  "type": "Feature",
  "properties": {
    "iso:country":"US",
    "sg:address":"2819 Long Grove Ln",
    "sg:city":"Richmond",
    "sg:classifiers":[
        {
            "category":"Manufacturing",
            "subcategory":"Petroleum Products",
            "type":"Manufacturing & Wholesale Goods"
        }
    ],
    "sg:phone":"+1 281 762 7694",
    "sg:postcode":"77469",
    "sg:province":"TX",
    "sg:tags":[
        "contract"
    ],
    "wof:name":"Dosgris Minig And Manufacturing Company",
    "wof:placetype":"venue"
},
  "geometry": {"coordinates":[-95.75806799999999,29.523366],"type":"Point"}
}