{
  "type": "Feature",
  "properties": {
    "iso:country":"US",
    "sg:address":"1520 S Mason Rd",
    "sg:city":"Katy",
    "sg:classifiers":[
        {
            "category":"Retail",
            "subcategory":"Laundry & Dry Cleaning",
            "type":"Services"
        }
    ],
    "sg:phone":"+1 281 395 2551",
    "sg:postcode":"77450",
    "sg:province":"TX",
    "sg:tags":[
        "drycleaning",
        "plant"
    ],
    "wof:name":"Cinco Cleaners",
    "wof:placetype":"venue"
},
  "geometry": {"coordinates":[-95.75167,29.758859],"type":"Point"}
}