{
  "type": "Feature",
  "properties": {
    "iso:country":"US",
    "sg:address":"5005 Davis Blvd",
    "sg:city":"Fort Worth",
    "sg:classifiers":[
        {
            "category":"Home & Garden",
            "subcategory":"Household Appliances",
            "type":"Retail Goods"
        }
    ],
    "sg:phone":"+1 817 788 5974",
    "sg:postcode":"76180",
    "sg:province":"TX",
    "sg:tags":[
        "repair",
        "electrical"
    ],
    "wof:name":"Evans Vacuum Cleaner",
    "wof:placetype":"venue"
},
  "geometry": {"coordinates":[-97.21432799999999,32.838673],"type":"Point"}
}