{
  "type": "Feature",
  "properties": {
    "iso:country":"US",
    "sg:address":"1817 Firman Dr",
    "sg:city":"Richardson",
    "sg:classifiers":[
        {
            "category":"Wholesale",
            "subcategory":"Electrical",
            "type":"Manufacturing & Wholesale Goods"
        }
    ],
    "sg:phone":"+1 972 437 1030",
    "sg:postcode":"75081",
    "sg:province":"TX",
    "sg:tags":[
        "equipment",
        "telecommunication"
    ],
    "wof:name":"Omnicom International",
    "wof:placetype":"venue"
},
  "geometry": {"coordinates":[-96.708608,32.973017],"type":"Point"}
}