{
  "type": "Feature",
  "properties": {
    "iso:country":"US",
    "sg:address":"730 N Post Oak Rd",
    "sg:city":"Houston",
    "sg:classifiers":[
        {
            "category":"Professional",
            "subcategory":"Secretarial Services",
            "type":"Services"
        },
        {
            "category":"Professional",
            "subcategory":"Employment Agencies",
            "type":"Services"
        },
        {
            "category":"Organizations",
            "subcategory":"Professional Association",
            "type":"Services"
        }
    ],
    "sg:phone":"+1 713 686 2111",
    "sg:postcode":"77024",
    "sg:province":"TX",
    "sg:tags":[
        "transcription",
        "typing"
    ],
    "sg:website":"http://www.transtechmedical.com",
    "wof:name":"Transtech Medical Solutions",
    "wof:placetype":"venue"
},
  "geometry": {"coordinates":[-95.456734,29.781099],"type":"Point"}
}