{
  "type": "Feature",
  "properties": {
    "iso:country":"US",
    "sg:address":"2400 Grand Avenue Pkwy",
    "sg:city":"Austin",
    "sg:classifiers":[
        {
            "category":"Home & Garden",
            "subcategory":"Furniture",
            "type":"Retail Goods"
        }
    ],
    "sg:phone":"+1 512 989 7953",
    "sg:postcode":"78728",
    "sg:province":"TX",
    "wof:name":"Ashley Furniture Home Store",
    "wof:placetype":"venue"
},
  "geometry": {"coordinates":[-97.67622299999999,30.457643],"type":"Point"}
}