{
  "type": "Feature",
  "properties": {
    "iso:country":"US",
    "sg:address":"1903 N Fir St",
    "sg:city":"Pharr",
    "sg:classifiers":[
        {
            "category":"Government",
            "subcategory":"Office",
            "type":"Public Place"
        }
    ],
    "sg:phone":"+1 956 787 1531",
    "sg:postcode":"78577",
    "sg:province":"TX",
    "sg:tags":[
        "county",
        "program",
        "health"
    ],
    "wof:name":"Hidalgo County Health Dept",
    "wof:placetype":"venue"
},
  "geometry": {"coordinates":[-98.173365,26.210639],"type":"Point"}
}