{
  "type": "Feature",
  "properties": {
    "iso:country":"US",
    "sg:address":"1221 River Bend Dr",
    "sg:city":"Dallas",
    "sg:classifiers":[
        {
            "category":"Manufacturing",
            "subcategory":"Printing",
            "type":"Manufacturing & Wholesale Goods"
        }
    ],
    "sg:phone":"+1 214 688 7777",
    "sg:postcode":"75247",
    "sg:province":"TX",
    "sg:tags":[
        "typesetting"
    ],
    "wof:name":"Seven World Wide",
    "wof:placetype":"venue"
},
  "geometry": {"coordinates":[-96.865301,32.816286],"type":"Point"}
}