{
  "type": "Feature",
  "properties": {
    "iso:country":"US",
    "sg:address":"3838 Oak Lawn Ave",
    "sg:city":"Dallas",
    "sg:classifiers":[
        {
            "category":"Professional",
            "subcategory":"Accounting & Tax Preparation",
            "type":"Services"
        }
    ],
    "sg:phone":"+1 214 520 1401",
    "sg:postcode":"75219",
    "sg:province":"TX",
    "sg:tags":[
        "accountant"
    ],
    "wof:name":"Robert Trachta & Co",
    "wof:placetype":"venue"
},
  "geometry": {"coordinates":[-96.80224200000001,32.815619],"type":"Point"}
}