{
  "type": "Feature",
  "properties": {
    "iso:country":"US",
    "sg:address":"13241 Bellaire Blvd",
    "sg:city":"Houston",
    "sg:classifiers":[
        {
            "category":"Restaurant",
            "type":"Food & Drink"
        }
    ],
    "sg:phone":"+1 832 351 2363",
    "sg:postcode":"77083",
    "sg:province":"TX",
    "sg:tags":[
        "eating"
    ],
    "wof:name":"Pho Tan Cinh",
    "wof:placetype":"venue"
},
  "geometry": {"coordinates":[-95.615651,29.703451],"type":"Point"}
}