{
  "type": "Feature",
  "properties": {
    "iso:country":"US",
    "sg:address":"6901 State Hwy 6",
    "sg:city":"Houston",
    "sg:classifiers":[
        {
            "category":"Restaurant",
            "type":"Food & Drink"
        }
    ],
    "sg:phone":"+1 281 568 8653",
    "sg:postcode":"77083",
    "sg:province":"TX",
    "wof:name":"Mc Donald's",
    "wof:placetype":"venue"
},
  "geometry": {"coordinates":[-95.64378600000001,29.700319],"type":"Point"}
}