{
  "type": "Feature",
  "properties": {
    "iso:country":"US",
    "sg:address":"115 N Richmond Rd",
    "sg:city":"Wharton",
    "sg:classifiers":[
        {
            "category":"Autos & Motor Vehicles",
            "subcategory":"Fuel & Gas Station",
            "type":"Retail Goods"
        }
    ],
    "sg:phone":"+1 979 532 3474",
    "sg:postcode":"77488",
    "sg:province":"TX",
    "sg:tags":[
        "station",
        "gasoline"
    ],
    "wof:name":"Diamond Shamrock No 939",
    "wof:placetype":"venue"
},
  "geometry": {"coordinates":[-96.102794,29.312544],"type":"Point"}
}