{
  "type": "Feature",
  "properties": {
    "iso:country":"US",
    "sg:address":"527 S Houston Ave",
    "sg:city":"Humble",
    "sg:classifiers":[
        {
            "category":"Education",
            "subcategory":"School",
            "type":"Public Place"
        },
        {
            "category":"Organizations",
            "subcategory":"Community Association",
            "type":"Services"
        }
    ],
    "sg:phone":"+1 281 446 2933",
    "sg:postcode":"77338",
    "sg:province":"TX",
    "sg:tags":[
        "consultant",
        "spiritual",
        "religious",
        "interest"
    ],
    "wof:name":"Religious Education Offic",
    "wof:placetype":"venue"
},
  "geometry": {"coordinates":[-95.258263,29.992137],"type":"Point"}
}