{
  "type": "Feature",
  "properties": {
    "iso:country":"US",
    "sg:address":"9727 Whitehurst Dr",
    "sg:city":"Dallas",
    "sg:classifiers":[
        {
            "category":"Personal",
            "type":"Services"
        }
    ],
    "sg:phone":"+1 214 565 0033",
    "sg:postcode":"75243",
    "sg:province":"TX",
    "wof:name":"Dallas Handyman",
    "wof:placetype":"venue"
},
  "geometry": {"coordinates":[-96.72769099999999,32.901209],"type":"Point"}
}