{
  "type": "Feature",
  "properties": {
    "iso:country":"US",
    "sg:address":"9207 Village Dr",
    "sg:city":"San Antonio",
    "sg:classifiers":[
        {
            "category":"Professional",
            "subcategory":"Computer Services",
            "type":"Services"
        }
    ],
    "sg:phone":"+1 210 654 8442",
    "sg:postcode":"78217",
    "sg:province":"TX",
    "sg:tags":[
        "consulting",
        "technology"
    ],
    "wof:name":"Kem Consulting",
    "wof:placetype":"venue"
},
  "geometry": {"coordinates":[-98.426481,29.525191],"type":"Point"}
}