{
  "type": "Feature",
  "properties": {
    "iso:country":"US",
    "sg:address":"5418 Jason St",
    "sg:city":"Houston",
    "sg:classifiers":[
        {
            "category":"Manufacturing",
            "subcategory":"Building Materials",
            "type":"Manufacturing & Wholesale Goods"
        }
    ],
    "sg:phone":"+1 713 668 5563",
    "sg:postcode":"77096",
    "sg:province":"TX",
    "sg:tags":[
        "mfg"
    ],
    "wof:name":"Ladds Touch With Wood",
    "wof:placetype":"venue"
},
  "geometry": {"coordinates":[-95.480772,29.6843],"type":"Point"}
}