{
  "type": "Feature",
  "properties": {
    "iso:country":"US",
    "sg:address":"1445 Snider Ln",
    "sg:city":"Allen",
    "sg:classifiers":[
        {
            "category":"Manufacturing",
            "subcategory":"Glass & Minerals",
            "type":"Manufacturing & Wholesale Goods"
        }
    ],
    "sg:phone":"+1 972 442 2127",
    "sg:postcode":"75002",
    "sg:province":"TX",
    "sg:tags":[
        "product",
        "nonmetallic",
        "mfg"
    ],
    "wof:name":"Stanovskys",
    "wof:placetype":"venue"
},
  "geometry": {"coordinates":[-96.55891800000001,33.103845],"type":"Point"}
}