{
  "type": "Feature",
  "properties": {
    "iso:country":"US",
    "sg:address":"805 Fighting Buck Ave",
    "sg:city":"Alpine",
    "sg:classifiers":[
        {
            "category":"Government",
            "subcategory":"Police Station",
            "type":"Public Place"
        }
    ],
    "sg:phone":"+1 432 837 3421",
    "sg:postcode":"79830",
    "sg:province":"TX",
    "sg:tags":[
        "federal"
    ],
    "wof:name":"US Drug Enforcement Adm",
    "wof:placetype":"venue"
},
  "geometry": {"coordinates":[-103.661495,30.366176],"type":"Point"}
}