{
  "type": "Feature",
  "properties": {
    "iso:country":"US",
    "sg:address":"501 Timber Oaks Dr",
    "sg:city":"El Paso",
    "sg:classifiers":[
        {
            "category":"Manufacturing",
            "subcategory":"Leather Goods",
            "type":"Manufacturing & Wholesale Goods"
        }
    ],
    "sg:phone":"+1 915 845 5101",
    "sg:postcode":"79932",
    "sg:province":"TX",
    "sg:tags":[
        "personal",
        "mfg"
    ],
    "wof:name":"Ancient Amazons Bazaar",
    "wof:placetype":"venue"
},
  "geometry": {"coordinates":[-106.60880400000001,31.852597],"type":"Point"}
}