{
  "type": "Feature",
  "properties": {
    "iso:country":"US",
    "sg:address":"5604 State Hwy 43 E",
    "sg:city":"Henderson",
    "sg:classifiers":[
        {
            "category":"Building & Trades",
            "subcategory":"Construction",
            "type":"Services"
        }
    ],
    "sg:phone":"+1 903 836 2060",
    "sg:postcode":"75652",
    "sg:province":"TX",
    "sg:tags":[
        "general",
        "contractor"
    ],
    "wof:name":"B D & Y Construction Co Inc",
    "wof:placetype":"venue"
},
  "geometry": {"coordinates":[-94.71168900000001,32.215244],"type":"Point"}
}