{
  "type": "Feature",
  "properties": {
    "iso:country":"US",
    "sg:address":"103 E Davis St",
    "sg:city":"Conroe",
    "sg:classifiers":[
        {
            "category":"Autos & Motor Vehicles",
            "subcategory":"Auto Supplies",
            "type":"Retail Goods"
        }
    ],
    "sg:phone":"+1 936 756 9591",
    "sg:postcode":"77301",
    "sg:province":"TX",
    "wof:name":"Jac Tire Service",
    "wof:placetype":"venue"
},
  "geometry": {"coordinates":[-95.454953,30.312166],"type":"Point"}
}