{
  "type": "Feature",
  "properties": {
    "iso:country":"US",
    "sg:address":"643 Pickering St",
    "sg:city":"Houston",
    "sg:phone":"+1 713 694 5508",
    "sg:postcode":"77091",
    "sg:province":"TX",
    "sg:website":"http://www.gasandsupply.com",
    "wof:name":"Iws Gas & Supply Of Texas",
    "wof:placetype":"venue"
},
  "geometry": {"coordinates":[-95.410636,29.857126],"type":"Point"}
}