{
  "type": "Feature",
  "properties": {
    "iso:country":"US",
    "sg:address":"507 White St",
    "sg:city":"Blue Ridge",
    "sg:classifiers":[
        {
            "category":"Freight",
            "type":"Transportation"
        }
    ],
    "sg:phone":"+1 972 752 5571",
    "sg:postcode":"75424",
    "sg:province":"TX",
    "sg:tags":[
        "commercial",
        "storage"
    ],
    "wof:name":"Blue Ridge Mini Storage",
    "wof:placetype":"venue"
},
  "geometry": {"coordinates":[-96.40472200000001,33.301212],"type":"Point"}
}