{
  "type": "Feature",
  "properties": {
    "iso:country":"US",
    "sg:address":"5405 Ave I",
    "sg:city":"Rosenberg",
    "sg:classifiers":[
        {
            "category":"Restaurant",
            "type":"Food & Drink"
        }
    ],
    "sg:phone":"+1 281 342 7010",
    "sg:postcode":"77471",
    "sg:province":"TX",
    "sg:tags":[
        "eating"
    ],
    "wof:name":"Domino's Pizza",
    "wof:placetype":"venue"
},
  "geometry": {"coordinates":[-95.77243900000001,29.558239],"type":"Point"}
}