{
  "type": "Feature",
  "properties": {
    "iso:country":"US",
    "sg:address":"314 Loma Vista St",
    "sg:city":"New Braunfels",
    "sg:classifiers":[
        {
            "category":"Professional",
            "subcategory":"Business Services",
            "type":"Services"
        }
    ],
    "sg:phone":"+1 830 608 9580",
    "sg:postcode":"78130",
    "sg:province":"TX",
    "wof:name":"A Action Bail Bonds",
    "wof:placetype":"venue"
},
  "geometry": {"coordinates":[-98.14311600000001,29.67588],"type":"Point"}
}