{
  "type": "Feature",
  "properties": {
    "iso:country":"US",
    "sg:address":"3811 Halifax Ct",
    "sg:city":"Arlington",
    "sg:classifiers":[
        {
            "category":"Professional",
            "subcategory":"Management & Consulting",
            "type":"Services"
        }
    ],
    "sg:phone":"+1 817 548 9751",
    "sg:postcode":"76013",
    "sg:province":"TX",
    "sg:tags":[
        "business"
    ],
    "wof:name":"D V I",
    "wof:placetype":"venue"
},
  "geometry": {"coordinates":[-97.164525,32.724865],"type":"Point"}
}