{
  "type": "Feature",
  "properties": {
    "iso:country":"US",
    "sg:address":"4402 Dolphin Pl",
    "sg:city":"Corpus Christi",
    "sg:classifiers":[
        {
            "category":"Banks & Credit Unions",
            "subcategory":"Investment Brokerage",
            "type":"Services"
        }
    ],
    "sg:phone":"+1 361 852 5431",
    "sg:postcode":"78411",
    "sg:province":"TX",
    "sg:tags":[
        "advisory"
    ],
    "wof:name":"Dental Financial Services LLC",
    "wof:placetype":"venue"
},
  "geometry": {"coordinates":[-97.38652399999999,27.728375],"type":"Point"}
}