{
  "type": "Feature",
  "properties": {
    "iso:country":"US",
    "sg:address":"126 Pine Vw Lp",
    "sg:city":"Bastrop",
    "sg:classifiers":[
        {
            "category":"Professional",
            "type":"Services"
        }
    ],
    "sg:phone":"+1 512 332 2616",
    "sg:postcode":"78602",
    "sg:province":"TX",
    "sg:tags":[
        "establishment"
    ],
    "wof:name":"Calpine Commissioning",
    "wof:placetype":"venue"
},
  "geometry": {"coordinates":[-97.27629399999999,30.130713],"type":"Point"}
}