{
  "type": "Feature",
  "properties": {
    "iso:country":"US",
    "sg:address":"116 W Industrial Rd",
    "sg:city":"Booker",
    "sg:classifiers":[
        {
            "category":"Retail",
            "subcategory":"Auto Repair",
            "type":"Services"
        }
    ],
    "sg:phone":"+1 806 658 4494",
    "sg:postcode":"79005",
    "sg:province":"TX",
    "sg:tags":[
        "repairing",
        "automobile"
    ],
    "wof:name":"Rice's Garage Inc",
    "wof:placetype":"venue"
},
  "geometry": {"coordinates":[-100.541234,36.455444],"type":"Point"}
}