{
  "type": "Feature",
  "properties": {
    "iso:country":"US",
    "sg:address":"1770 Saint James Pl Ste 300",
    "sg:city":"Houston",
    "sg:classifiers":[
        {
            "category":"Professional",
            "subcategory":"Lawyer & Legal Services",
            "type":"Services"
        }
    ],
    "sg:phone":"+1 713 522 4881",
    "sg:postcode":"77056",
    "sg:province":"TX",
    "sg:website":"www.gscottwilliams.com",
    "wof:name":"Williams G Scott Atty",
    "wof:placetype":"venue"
},
  "geometry": {"coordinates":[-95.473855,29.748418],"type":"Point"}
}