{
  "type": "Feature",
  "properties": {
    "iso:country":"US",
    "sg:address":"724 W Main St",
    "sg:city":"Lewisville",
    "sg:classifiers":[
        {
            "category":"Health Services",
            "subcategory":"Health Practitioner",
            "type":"Services"
        }
    ],
    "sg:phone":"+1 972 434 6024",
    "sg:postcode":"75067",
    "sg:province":"TX",
    "sg:tags":[
        "therapist",
        "physical"
    ],
    "sg:website":"www.advancedtherapyservices.com",
    "wof:name":"Advanced Physical Therapy",
    "wof:placetype":"venue"
},
  "geometry": {"coordinates":[-97.01227799999999,33.045483],"type":"Point"}
}