{
  "type": "Feature",
  "properties": {
    "iso:country":"US",
    "sg:address":"10084 Socorro Rd",
    "sg:city":"El Paso",
    "sg:classifiers":[
        {
            "category":"Retail",
            "subcategory":"Auto Repair",
            "type":"Services"
        }
    ],
    "sg:phone":"+1 915 860 4644",
    "sg:postcode":"79927",
    "sg:province":"TX",
    "sg:tags":[
        "automobile",
        "inspection",
        "automotive"
    ],
    "wof:name":"Rodela's Service",
    "wof:placetype":"venue"
},
  "geometry": {"coordinates":[-106.303785,31.657835],"type":"Point"}
}