{
  "type": "Feature",
  "properties": {
    "iso:country":"US",
    "sg:address":"17625 el Camino Real",
    "sg:city":"Houston",
    "sg:classifiers":[
        {
            "category":"Professional",
            "subcategory":"Management & Consulting",
            "type":"Services"
        }
    ],
    "sg:phone":"+1 281 480 4888",
    "sg:postcode":"77058",
    "sg:province":"TX",
    "sg:tags":[
        "export"
    ],
    "wof:name":"American Trade Co",
    "wof:placetype":"venue"
},
  "geometry": {"coordinates":[-95.10781799999999,29.547593],"type":"Point"}
}