{
  "type": "Feature",
  "properties": {
    "iso:country":"US",
    "sg:address":"3939 US Hwy 80 E",
    "sg:city":"Mesquite",
    "sg:classifiers":[
        {
            "category":"Health Services",
            "subcategory":"Clinic",
            "type":"Services"
        }
    ],
    "sg:phone":"+1 972 682 0727",
    "sg:postcode":"75150",
    "sg:province":"TX",
    "sg:tags":[
        "home",
        "care"
    ],
    "wof:name":"Heartbeat Home Health Agency",
    "wof:placetype":"venue"
},
  "geometry": {"coordinates":[-96.659126,32.794832],"type":"Point"}
}