{
  "type": "Feature",
  "properties": {
    "iso:country":"US",
    "sg:address":"8805 Hornaday Cir N",
    "sg:city":"Fort Worth",
    "sg:classifiers":[
        {
            "category":"Shopping",
            "subcategory":"Luggage & Leather Goods",
            "type":"Retail Goods"
        }
    ],
    "sg:phone":"+1 817 261 7796",
    "sg:postcode":"76120",
    "sg:province":"TX",
    "sg:tags":[
        "organization",
        "religious"
    ],
    "wof:name":"Love Offering Inc",
    "wof:placetype":"venue"
},
  "geometry": {"coordinates":[-97.160427,32.762514],"type":"Point"}
}