{
  "type": "Feature",
  "properties": {
    "iso:country":"US",
    "sg:address":"605 Red Oak Dr",
    "sg:city":"Copperas Cove",
    "sg:classifiers":[
        {
            "category":"Organizations",
            "subcategory":"Religious Organization",
            "type":"Services"
        }
    ],
    "sg:phone":"+1 254 547 3455",
    "sg:postcode":"76522",
    "sg:province":"TX",
    "wof:name":"Bethesda Fellowship of Co",
    "wof:placetype":"venue"
},
  "geometry": {"coordinates":[-97.893289,31.10962],"type":"Point"}
}