{
  "type": "Feature",
  "properties": {
    "iso:country":"US",
    "sg:address":"12002 Merewood Ln",
    "sg:city":"Houston",
    "sg:classifiers":[
        {
            "category":"Education",
            "subcategory":"Special Training",
            "type":"Public Place"
        }
    ],
    "sg:phone":"+1 713 995 8629",
    "sg:postcode":"77071",
    "sg:province":"TX",
    "wof:name":"Smokers Help Seminars Inc",
    "wof:placetype":"venue"
},
  "geometry": {"coordinates":[-95.529365,29.647163],"type":"Point"}
}