{
  "type": "Feature",
  "properties": {
    "iso:country":"US",
    "sg:address":"3659 Glen Haven Blvd",
    "sg:city":"Houston",
    "sg:classifiers":[
        {
            "category":"Professional",
            "type":"Services"
        }
    ],
    "sg:phone":"+1 713 432 0343",
    "sg:postcode":"77025",
    "sg:province":"TX",
    "sg:tags":[
        "information",
        "bureau"
    ],
    "wof:name":"Infofax Investigative & Info",
    "wof:placetype":"venue"
},
  "geometry": {"coordinates":[-95.432456,29.701216],"type":"Point"}
}