{
  "type": "Feature",
  "properties": {
    "iso:country":"US",
    "sg:address":"145 Kai Vista Dr",
    "sg:city":"Kyle",
    "sg:classifiers":[
        {
            "category":"Restaurant",
            "type":"Food & Drink"
        }
    ],
    "sg:phone":"+1 512 376 1952",
    "sg:postcode":"78640",
    "sg:province":"TX",
    "sg:tags":[
        "eating"
    ],
    "wof:name":"Soul Food",
    "wof:placetype":"venue"
},
  "geometry": {"coordinates":[-97.74853400000001,30.033908],"type":"Point"}
}