{
  "type": "Feature",
  "properties": {
    "iso:country":"US",
    "sg:address":"2722 Alamo St",
    "sg:city":"Dallas",
    "sg:classifiers":[
        {
            "category":"Utilities",
            "subcategory":"Refuse",
            "type":"Services"
        }
    ],
    "sg:phone":"+1 214 366 3333",
    "sg:postcode":"75201",
    "sg:province":"TX",
    "sg:tags":[
        "mill",
        "system",
        "pulp"
    ],
    "wof:name":"Vista Fibers",
    "wof:placetype":"venue"
},
  "geometry": {"coordinates":[-96.809437,32.791052],"type":"Point"}
}