{
  "type": "Feature",
  "properties": {
    "iso:country":"US",
    "sg:address":"819 Congress St",
    "sg:city":"Texarkana",
    "sg:classifiers":[
        {
            "category":"Retail",
            "subcategory":"Auto Repair",
            "type":"Services"
        }
    ],
    "sg:phone":"+1 903 794 5342",
    "sg:postcode":"75501",
    "sg:province":"TX",
    "sg:tags":[
        "body"
    ],
    "wof:name":"Auto Trim & Upholstery",
    "wof:placetype":"venue"
},
  "geometry": {"coordinates":[-94.05568100000001,33.425104],"type":"Point"}
}