{
  "type": "Feature",
  "properties": {
    "iso:country":"US",
    "sg:address":"799 Windemere Way",
    "sg:city":"Keller",
    "sg:classifiers":[
        {
            "category":"Building & Trades",
            "subcategory":"Construction",
            "type":"Services"
        }
    ],
    "sg:phone":"+1 817 571 6964",
    "sg:postcode":"76248",
    "sg:province":"TX",
    "sg:tags":[
        "development",
        "brokerage",
        "land",
        "firm"
    ],
    "wof:name":"Ashbrook Group",
    "wof:placetype":"venue"
},
  "geometry": {"coordinates":[-97.225961,32.918965],"type":"Point"}
}