{
  "type": "Feature",
  "properties": {
    "iso:country":"US",
    "sg:address":"3311 Sul Ross St",
    "sg:city":"Houston",
    "sg:classifiers":[
        {
            "category":"Building & Trades",
            "subcategory":"Construction",
            "type":"Services"
        }
    ],
    "sg:phone":"+1 713 807 7607",
    "sg:postcode":"77098",
    "sg:province":"TX",
    "sg:tags":[
        "contractor"
    ],
    "wof:name":"Vin De Garde Ltd",
    "wof:placetype":"venue"
},
  "geometry": {"coordinates":[-95.426804,29.737301],"type":"Point"}
}