{
  "type": "Feature",
  "properties": {
    "iso:country":"US",
    "sg:address":"15715 Brook Pine Ln",
    "sg:city":"Houston",
    "sg:classifiers":[
        {
            "category":"Building & Trades",
            "subcategory":"Construction",
            "type":"Services"
        }
    ],
    "sg:phone":"+1 281 685 9131",
    "sg:postcode":"77082",
    "sg:province":"TX",
    "sg:tags":[
        "house"
    ],
    "wof:name":"Villanueva Construction",
    "wof:placetype":"venue"
},
  "geometry": {"coordinates":[-95.661298,29.724123],"type":"Point"}
}