{
  "type": "Feature",
  "properties": {
    "iso:country":"US",
    "sg:address":"13801 Luthe Rd",
    "sg:city":"Houston",
    "sg:classifiers":[
        {
            "category":"Retail",
            "subcategory":"Auto Repair",
            "type":"Services"
        }
    ],
    "sg:phone":"+1 281 987 2987",
    "sg:postcode":"77039",
    "sg:province":"TX",
    "sg:tags":[
        "automotive"
    ],
    "wof:name":"Espinoza Framing",
    "wof:placetype":"venue"
},
  "geometry": {"coordinates":[-95.37189499999999,29.916624],"type":"Point"}
}