{
  "type": "Feature",
  "properties": {
    "iso:country":"US",
    "sg:address":"12035 de Forrest St",
    "sg:city":"Houston",
    "sg:classifiers":[
        {
            "category":"Social Services",
            "subcategory":"Child Care",
            "type":"Services"
        }
    ],
    "sg:phone":"+1 281 895 0606",
    "sg:postcode":"77066",
    "sg:province":"TX",
    "sg:tags":[
        "day"
    ],
    "wof:name":"Lone Star Montessori",
    "wof:placetype":"venue"
},
  "geometry": {"coordinates":[-95.4945,29.972901],"type":"Point"}
}