{
  "type": "Feature",
  "properties": {
    "iso:country":"US",
    "sg:address":"6435 Miller Rd Two",
    "sg:city":"Houston",
    "sg:classifiers":[
        {
            "category":"Food & Beverages",
            "subcategory":"Farmers Market",
            "type":"Retail Goods"
        }
    ],
    "sg:phone":"+1 713 492 4804",
    "sg:postcode":"77049",
    "sg:province":"TX",
    "sg:website":"www.lawranch.com",
    "wof:name":"Law Ranch Cattle Company",
    "wof:placetype":"venue"
},
  "geometry": {"coordinates":[-95.142917,29.818814],"type":"Point"}
}