{
  "type": "Feature",
  "properties": {
    "iso:country":"US",
    "sg:address":"3701 S Lamar St",
    "sg:city":"Dallas",
    "sg:classifiers":[
        {
            "category":"Education",
            "subcategory":"School",
            "type":"Public Place"
        }
    ],
    "sg:phone":"+1 972 925 4953",
    "sg:postcode":"75215",
    "sg:province":"TX",
    "wof:name":"Dallas Independent School District Frequently Called Numbers",
    "wof:placetype":"venue"
},
  "geometry": {"coordinates":[-96.77318699999999,32.754226],"type":"Point"}
}