{
  "type": "Feature",
  "properties": {
    "iso:country":"US",
    "sg:address":"4726 Crystal Farm",
    "sg:city":"San Antonio",
    "sg:classifiers":[
        {
            "category":"Social Services",
            "subcategory":"Child Care",
            "type":"Services"
        }
    ],
    "sg:phone":"+1 210 666 2883",
    "sg:postcode":"78244",
    "sg:province":"TX",
    "wof:name":"Bright Beginning Child Care",
    "wof:placetype":"venue"
},
  "geometry": {"coordinates":[-98.361532,29.470493],"type":"Point"}
}