{
  "type": "Feature",
  "properties": {
    "iso:country":"US",
    "sg:address":"6815 Castleview Ln",
    "sg:city":"Missouri City",
    "sg:classifiers":[
        {
            "category":"Professional",
            "subcategory":"Management & Consulting",
            "type":"Services"
        }
    ],
    "sg:phone":"+1 281 437 1075",
    "sg:postcode":"77489",
    "sg:province":"TX",
    "wof:name":"Johnson Enterprises",
    "wof:placetype":"venue"
},
  "geometry": {"coordinates":[-95.488799,29.601698],"type":"Point"}
}