{
  "type": "Feature",
  "properties": {
    "iso:country":"US",
    "sg:address":"6326 La Vista Dr",
    "sg:city":"Dallas",
    "sg:classifiers":[
        {
            "category":"Bars & Pubs",
            "subcategory":"Dive Bar",
            "type":"Food & Drink"
        }
    ],
    "sg:phone":"+1 214 818 0100",
    "sg:postcode":"75214",
    "sg:province":"TX",
    "wof:name":"Lakewood Tavern",
    "wof:placetype":"venue"
},
  "geometry": {"coordinates":[-96.75397700000001,32.812692],"type":"Point"}
}