{
  "type": "Feature",
  "properties": {
    "iso:country":"US",
    "sg:address":"5444 Westheimer Rd",
    "sg:city":"Houston",
    "sg:classifiers":[
        {
            "category":"Mining & Drilling",
            "type":"Manufacturing & Wholesale Goods"
        }
    ],
    "sg:phone":"+1 713 626 4700",
    "sg:postcode":"77056",
    "sg:province":"TX",
    "sg:tags":[
        "development",
        "gas",
        "oil",
        "exploration"
    ],
    "wof:name":"ERHC",
    "wof:placetype":"venue"
},
  "geometry": {"coordinates":[-95.473992,29.738062],"type":"Point"}
}