{
  "type": "Feature",
  "properties": {
    "iso:country":"US",
    "sg:address":"200 Sage St",
    "sg:city":"Kingsland",
    "sg:classifiers":[
        {
            "category":"Building & Trades",
            "subcategory":"Construction",
            "type":"Services"
        }
    ],
    "sg:phone":"+1 325 388 4283",
    "sg:postcode":"78639",
    "sg:province":"TX",
    "sg:tags":[
        "house"
    ],
    "wof:name":"Norred Construction",
    "wof:placetype":"venue"
},
  "geometry": {"coordinates":[-98.411823,30.634007],"type":"Point"}
}