{
  "type": "Feature",
  "properties": {
    "iso:country":"US",
    "sg:address":"11217 Barrington Way",
    "sg:city":"Austin",
    "sg:classifiers":[
        {
            "category":"Professional",
            "subcategory":"Management & Consulting",
            "type":"Services"
        }
    ],
    "sg:phone":"+1 512 331 8648",
    "sg:postcode":"78759",
    "sg:province":"TX",
    "sg:tags":[
        "business"
    ],
    "wof:name":"Aycock Maritime Consulting",
    "wof:placetype":"venue"
},
  "geometry": {"coordinates":[-97.773751,30.423258],"type":"Point"}
}