{
  "type": "Feature",
  "properties": {
    "iso:country":"US",
    "sg:address":"4162 Redbird Ln E",
    "sg:city":"Burleson",
    "sg:classifiers":[
        {
            "category":"Shopping",
            "subcategory":"Used Merchandise",
            "type":"Retail Goods"
        }
    ],
    "sg:phone":"+1 817 293 1634",
    "sg:postcode":"76028",
    "sg:province":"TX",
    "wof:name":"Face of Time",
    "wof:placetype":"venue"
},
  "geometry": {"coordinates":[-97.27006299999999,32.573856],"type":"Point"}
}