{
  "type": "Feature",
  "properties": {
    "iso:country":"US",
    "sg:address":"5706 College St",
    "sg:city":"Beaumont",
    "sg:classifiers":[
        {
            "category":"Professional",
            "subcategory":"Business Services",
            "type":"Services"
        }
    ],
    "sg:phone":"+1 409 866 0000",
    "sg:postcode":"77707",
    "sg:province":"TX",
    "sg:tags":[
        "repossessing"
    ],
    "wof:name":"American Lenders Service Co",
    "wof:placetype":"venue"
},
  "geometry": {"coordinates":[-94.155782,30.067951],"type":"Point"}
}