{
  "type": "Feature",
  "properties": {
    "iso:country":"US",
    "sg:address":"12222 Port Dr",
    "sg:city":"Pasadena",
    "sg:classifiers":[
        {
            "category":"Banks & Credit Unions",
            "subcategory":"Bank",
            "type":"Services"
        }
    ],
    "sg:phone":"+1 281 474 1638",
    "sg:postcode":"77507",
    "sg:province":"TX",
    "sg:tags":[
        "broker",
        "mortgage"
    ],
    "wof:name":"Providence Mortgage",
    "wof:placetype":"venue"
},
  "geometry": {"coordinates":[-95.020056,29.60392],"type":"Point"}
}