{
  "type": "Feature",
  "properties": {
    "iso:country":"US",
    "sg:address":"104 Apache Cir",
    "sg:city":"Cibolo",
    "sg:classifiers":[
        {
            "category":"Building & Trades",
            "subcategory":"Construction",
            "type":"Services"
        }
    ],
    "sg:phone":"+1 210 887 8343",
    "sg:postcode":"78108",
    "sg:province":"TX",
    "sg:tags":[
        "floor",
        "laying",
        "contractor"
    ],
    "wof:name":"Sth Flooring",
    "wof:placetype":"venue"
},
  "geometry": {"coordinates":[-98.231656,29.566609],"type":"Point"}
}