{
  "type": "Feature",
  "properties": {
    "iso:country":"US",
    "sg:address":"301 N Mccoll Rd",
    "sg:city":"Mcallen",
    "sg:classifiers":[
        {
            "category":"Professional",
            "subcategory":"Engineering",
            "type":"Services"
        },
        {
            "category":"Building & Trades",
            "subcategory":"Cleaning & Sanitation",
            "type":"Services"
        },
        {
            "category":"Building & Trades",
            "subcategory":"Construction",
            "type":"Services"
        },
        {
            "category":"Home & Garden",
            "subcategory":"Household Appliances",
            "type":"Retail Goods"
        }
    ],
    "sg:phone":"+1 956 668 7327",
    "sg:postcode":"78501",
    "sg:province":"TX",
    "sg:tags":[
        "major",
        "duct",
        "specialty",
        "appliances-small",
        "system",
        "equipment",
        "heating",
        "contractor",
        "air conditioning"
    ],
    "sg:website":"http://www.hessair.com",
    "wof:name":"Weldinghouse Inc",
    "wof:placetype":"venue"
},
  "geometry": {"coordinates":[-98.21254,26.203362],"type":"Point"}
}