{
  "type": "Feature",
  "properties": {
    "iso:country":"US",
    "sg:address":"4605 Biltmoore Dr",
    "sg:city":"Frisco",
    "sg:classifiers":[
        {
            "category":"Shopping",
            "subcategory":"Clothing, Apparel, & Fashions",
            "type":"Retail Goods"
        }
    ],
    "sg:phone":"+1 972 381 0000",
    "sg:postcode":"75034",
    "sg:province":"TX",
    "sg:tags":[
        "infant",
        "wear"
    ],
    "wof:name":"Kiddie Korral",
    "wof:placetype":"venue"
},
  "geometry": {"coordinates":[-96.852345,33.101711],"type":"Point"}
}