{
  "type": "Feature",
  "properties": {
    "iso:country":"US",
    "sg:address":"268 S Clark Dr",
    "sg:city":"El Paso",
    "sg:classifiers":[
        {
            "category":"Professional",
            "subcategory":"Detective & Security Services",
            "type":"Services"
        }
    ],
    "sg:phone":"+1 915 778 7750",
    "sg:postcode":"79905",
    "sg:province":"TX",
    "sg:tags":[
        "guard",
        "patrol"
    ],
    "wof:name":"Mike Garcia Merchant Security",
    "wof:placetype":"venue"
},
  "geometry": {"coordinates":[-106.414063,31.761962],"type":"Point"}
}