{
  "type": "Feature",
  "properties": {
    "iso:country":"US",
    "sg:address":"1034 Austin St",
    "sg:city":"San Antonio",
    "sg:classifiers":[
        {
            "category":"Wholesale",
            "subcategory":"Chemicals & Plastics",
            "type":"Manufacturing & Wholesale Goods"
        }
    ],
    "sg:phone":"+1 210 223 5726",
    "sg:postcode":"78208",
    "sg:province":"TX",
    "sg:tags":[
        "farm",
        "supply"
    ],
    "wof:name":"Wholesale Salt",
    "wof:placetype":"venue"
},
  "geometry": {"coordinates":[-98.474541,29.439929],"type":"Point"}
}