{
  "type": "Feature",
  "properties": {
    "iso:country":"US",
    "sg:address":"1014 Memorial Dr",
    "sg:city":"Denison",
    "sg:classifiers":[
        {
            "category":"Health Services",
            "subcategory":"Doctor",
            "type":"Services"
        }
    ],
    "sg:phone":"+1 903 465 3624",
    "sg:postcode":"75020",
    "sg:province":"TX",
    "sg:tags":[
        "physician",
        "surgeon",
        "medical"
    ],
    "wof:name":"Texoma Heart Group PA",
    "wof:placetype":"venue"
},
  "geometry": {"coordinates":[-96.549201,33.766162],"type":"Point"}
}