{
  "type": "Feature",
  "properties": {
    "iso:country":"US",
    "sg:address":"1516 Sandalwood Ln",
    "sg:city":"Odessa",
    "sg:classifiers":[
        {
            "category":"Travel",
            "subcategory":"Hotels & Motels",
            "type":"Entertainment"
        }
    ],
    "sg:phone":"+1 432 362 7553",
    "sg:postcode":"79761",
    "sg:province":"TX",
    "sg:tags":[
        "membership",
        "lodging"
    ],
    "wof:name":"Texas Garden Clubs Inc",
    "wof:placetype":"venue"
},
  "geometry": {"coordinates":[-102.33638000000001,31.874497],"type":"Point"}
}