{
  "type": "Feature",
  "properties": {
    "iso:country":"US",
    "sg:address":"11180 Harry Hines Blvd",
    "sg:city":"Dallas",
    "sg:classifiers":[
        {
            "category":"Restaurant",
            "type":"Food & Drink"
        }
    ],
    "sg:phone":"+1 972 484 0808",
    "sg:postcode":"75229",
    "sg:province":"TX",
    "sg:tags":[
        "chinese"
    ],
    "wof:name":"Chef Hsu Chinese Super Buffet",
    "wof:placetype":"venue"
},
  "geometry": {"coordinates":[-96.888496,32.888901],"type":"Point"}
}