{
  "type": "Feature",
  "properties": {
    "iso:country":"US",
    "sg:address":"14655 Preston Rd",
    "sg:city":"Dallas",
    "sg:classifiers":[
        {
            "category":"Social Services",
            "subcategory":"Job Training",
            "type":"Services"
        }
    ],
    "sg:phone":"+1 972 788 1961",
    "sg:postcode":"75254",
    "sg:province":"TX",
    "sg:tags":[
        "rehabilitation"
    ],
    "wof:name":"Rehabworks",
    "wof:placetype":"venue"
},
  "geometry": {"coordinates":[-96.80372300000001,32.947823],"type":"Point"}
}