{
  "type": "Feature",
  "properties": {
    "iso:country":"US",
    "sg:address":"802 Barry St",
    "sg:city":"Corpus Christi",
    "sg:classifiers":[
        {
            "category":"Professional",
            "type":"Services"
        }
    ],
    "sg:phone":"+1 361 853 0100",
    "sg:postcode":"78411",
    "sg:province":"TX",
    "wof:name":"Fys",
    "wof:placetype":"venue"
},
  "geometry": {"coordinates":[-97.379914,27.72764],"type":"Point"}
}