{
  "type": "Feature",
  "properties": {
    "iso:country":"US",
    "sg:address":"11259 Southwest Fwy",
    "sg:city":"Houston",
    "sg:classifiers":[
        {
            "category":"Professional",
            "subcategory":"Employment Agencies",
            "type":"Services"
        }
    ],
    "sg:phone":"+1 713 921 4445",
    "sg:postcode":"77031",
    "sg:province":"TX",
    "sg:tags":[
        "opportunity"
    ],
    "wof:name":"Dunhill Staffing Systems",
    "wof:placetype":"venue"
},
  "geometry": {"coordinates":[-95.56269899999999,29.65594],"type":"Point"}
}