{
  "type": "Feature",
  "properties": {
    "iso:country":"US",
    "sg:address":"1511 Faro Dr",
    "sg:city":"Austin",
    "sg:classifiers":[
        {
            "category":"Real Estate",
            "subcategory":"Real Estate Operator",
            "type":"Services"
        }
    ],
    "sg:phone":"+1 512 385 2605",
    "sg:postcode":"78741",
    "sg:province":"TX",
    "sg:tags":[
        "building",
        "apartment"
    ],
    "wof:name":"Wildcreek Apartments",
    "wof:placetype":"venue"
},
  "geometry": {"coordinates":[-97.712901,30.234273],"type":"Point"}
}