{
  "type": "Feature",
  "properties": {
    "iso:country":"US",
    "sg:address":"1601 Oceola Ave",
    "sg:city":"Wichita Falls",
    "sg:classifiers":[
        {
            "category":"Shopping",
            "subcategory":"Clothing, Apparel, & Fashions",
            "type":"Retail Goods"
        }
    ],
    "sg:phone":"+1 940 767 7215",
    "sg:postcode":"76301",
    "sg:province":"TX",
    "wof:name":"Mona Lisas Acc & Things",
    "wof:placetype":"venue"
},
  "geometry": {"coordinates":[-98.46363100000001,33.895137],"type":"Point"}
}