{
  "type": "Feature",
  "properties": {
    "iso:country":"US",
    "sg:address":"11252 Goodnight Ln # 100",
    "sg:city":"Dallas",
    "sg:classifiers":[
        {
            "category":"Professional",
            "subcategory":"Detective & Security Services",
            "type":"Services"
        }
    ],
    "sg:phone":"+1 972 247 2808",
    "sg:postcode":"75229",
    "sg:province":"TX",
    "sg:tags":[
        "control",
        "monitoring",
        "fire",
        "consultant",
        "alarm",
        "system",
        "equipment"
    ],
    "sg:website":"http://www.c-jsystems.com",
    "wof:name":"C & J Systems, Inc",
    "wof:placetype":"venue"
},
  "geometry": {"coordinates":[-96.90184499999999,32.891553],"type":"Point"}
}