{
  "type": "Feature",
  "properties": {
    "iso:country":"US",
    "sg:address":"9130 Wurzbach Rd",
    "sg:city":"San Antonio",
    "sg:classifiers":[
        {
            "category":"Health Services",
            "subcategory":"Medical Lab",
            "type":"Services"
        }
    ],
    "sg:phone":"+1 210 692 0299",
    "sg:postcode":"78240",
    "sg:province":"TX",
    "sg:tags":[
        "laboratory"
    ],
    "wof:name":"Biotox Inc",
    "wof:placetype":"venue"
},
  "geometry": {"coordinates":[-98.567684,29.525358],"type":"Point"}
}