{
  "type": "Feature",
  "properties": {
    "iso:country":"US",
    "sg:address":"13319 Oak Plaza Dr",
    "sg:city":"Cypress",
    "sg:classifiers":[
        {
            "category":"Professional",
            "subcategory":"Computer Services",
            "type":"Services"
        }
    ],
    "sg:phone":"+1 281 469 4418",
    "sg:postcode":"77429",
    "sg:province":"TX",
    "sg:tags":[
        "programing",
        "custom"
    ],
    "wof:name":"System Fx Inc",
    "wof:placetype":"venue"
},
  "geometry": {"coordinates":[-95.597042,29.957741],"type":"Point"}
}