{
  "type": "Feature",
  "properties": {
    "iso:country":"US",
    "sg:address":"11921 N Mo Pac Expy",
    "sg:city":"Austin",
    "sg:classifiers":[
        {
            "category":"Professional",
            "subcategory":"Management & Consulting",
            "type":"Services"
        }
    ],
    "sg:phone":"+1 512 519 3900",
    "sg:postcode":"78759",
    "sg:province":"TX",
    "sg:tags":[
        "provide",
        "chemical"
    ],
    "wof:name":"Haas Tcm",
    "wof:placetype":"venue"
},
  "geometry": {"coordinates":[-97.719235,30.407196],"type":"Point"}
}