{
  "type": "Feature",
  "properties": {
    "iso:country":"US",
    "sg:address":"108 W Missouri St",
    "sg:city":"Floydada",
    "sg:classifiers":[
        {
            "category":"Wholesale",
            "subcategory":"Groceries",
            "type":"Manufacturing & Wholesale Goods"
        }
    ],
    "sg:phone":"+1 806 983 3688",
    "sg:postcode":"79235",
    "sg:province":"TX",
    "sg:tags":[
        "confectionery",
        "candy"
    ],
    "wof:name":"Lone Star Candy",
    "wof:placetype":"venue"
},
  "geometry": {"coordinates":[-101.334918,33.985632],"type":"Point"}
}