{
  "type": "Feature",
  "properties": {
    "iso:country":"US",
    "sg:address":"2311 Anzio Dr",
    "sg:city":"Dallas",
    "sg:classifiers":[
        {
            "category":"Organizations",
            "subcategory":"Religious Organization",
            "type":"Services"
        }
    ],
    "sg:phone":"+1 214 941 6502",
    "sg:postcode":"75224",
    "sg:province":"TX",
    "wof:name":"In His NM Mnstrs Wrldwd Inc",
    "wof:placetype":"venue"
},
  "geometry": {"coordinates":[-96.83435900000001,32.716287],"type":"Point"}
}