{
  "type": "Feature",
  "properties": {
    "iso:country":"US",
    "sg:address":"200 E Expy 83",
    "sg:city":"Pharr",
    "sg:classifiers":[
        {
            "category":"Manufacturing",
            "subcategory":"Printing",
            "type":"Manufacturing & Wholesale Goods"
        }
    ],
    "sg:phone":"+1 956 702 8286",
    "sg:postcode":"78577",
    "sg:province":"TX",
    "sg:tags":[
        "multimedia"
    ],
    "wof:name":"Newspan Media",
    "wof:placetype":"venue"
},
  "geometry": {"coordinates":[-98.18025,26.206151],"type":"Point"}
}