{
  "type": "Feature",
  "properties": {
    "iso:country":"US",
    "sg:address":"2608 Inler Ave",
    "sg:city":"Lubbock",
    "sg:classifiers":[
        {
            "category":"Professional",
            "subcategory":"Business Services",
            "type":"Services"
        }
    ],
    "sg:phone":"+1 806 799 4422",
    "sg:postcode":"79407",
    "sg:province":"TX",
    "sg:tags":[
        "auctioneer"
    ],
    "wof:name":"Fletcher & Co Auctioneers",
    "wof:placetype":"venue"
},
  "geometry": {"coordinates":[-102.009182,33.570713],"type":"Point"}
}