{
  "type": "Feature",
  "properties": {
    "iso:country":"US",
    "sg:address":"2614 E 14th St",
    "sg:city":"Brownsville",
    "sg:classifiers":[
        {
            "category":"Retail",
            "subcategory":"Auto Repair",
            "type":"Services"
        }
    ],
    "sg:phone":"+1 956 541 0209",
    "sg:postcode":"78521",
    "sg:province":"TX",
    "sg:tags":[
        "automotive"
    ],
    "wof:name":"Lopez Auto Electric",
    "wof:placetype":"venue"
},
  "geometry": {"coordinates":[-97.481627,25.911536],"type":"Point"}
}