{
  "type": "Feature",
  "properties": {
    "iso:country":"US",
    "sg:address":"3403 Flaming Candle Dr",
    "sg:city":"Spring",
    "sg:classifiers":[
        {
            "category":"Building & Trades",
            "subcategory":"Equipment Rental",
            "type":"Services"
        }
    ],
    "sg:phone":"+1 281 350 4091",
    "sg:postcode":"77388",
    "sg:province":"TX",
    "wof:name":"Kallus & Co Inc",
    "wof:placetype":"venue"
},
  "geometry": {"coordinates":[-95.45726999999999,30.040601],"type":"Point"}
}