{
  "type": "Feature",
  "properties": {
    "iso:country":"US",
    "sg:address":"4102 Weber Rd",
    "sg:city":"Corpus Christi",
    "sg:classifiers":[
        {
            "category":"Real Estate",
            "subcategory":"Real Estate Agent",
            "type":"Services"
        }
    ],
    "sg:phone":"+1 361 853 2486",
    "sg:postcode":"78411",
    "sg:province":"TX",
    "wof:name":"Seven Bell RE & Auctn Agcy",
    "wof:placetype":"venue"
},
  "geometry": {"coordinates":[-97.38924400000001,27.736715],"type":"Point"}
}