{
  "type": "Feature",
  "properties": {
    "iso:country":"US",
    "sg:address":"1226 Corporate Dr W",
    "sg:city":"Arlington",
    "sg:classifiers":[
        {
            "category":"Autos & Motor Vehicles",
            "subcategory":"Automobile Sales",
            "type":"Retail Goods"
        }
    ],
    "sg:phone":"+1 817 652 8867",
    "sg:postcode":"76006",
    "sg:province":"TX",
    "sg:tags":[
        "used"
    ],
    "wof:name":"Texas Auto Gallary",
    "wof:placetype":"venue"
},
  "geometry": {"coordinates":[-97.06797299999999,32.767527],"type":"Point"}
}