{
  "type": "Feature",
  "properties": {
    "iso:country":"US",
    "sg:address":"2712 King Arthur Blvd",
    "sg:city":"Carrollton",
    "sg:classifiers":[
        {
            "category":"Building & Trades",
            "subcategory":"Construction",
            "type":"Services"
        }
    ],
    "sg:phone":"+1 972 416 7209",
    "sg:postcode":"75006",
    "sg:province":"TX",
    "sg:tags":[
        "contractor"
    ],
    "wof:name":"Garvey Homes",
    "wof:placetype":"venue"
},
  "geometry": {"coordinates":[-96.88359800000001,32.960098],"type":"Point"}
}