{
  "type": "Feature",
  "properties": {
    "iso:country":"US",
    "sg:address":"5921 Culebra Rd",
    "sg:city":"San Antonio",
    "sg:classifiers":[
        {
            "category":"Shopping",
            "type":"Retail Goods"
        }
    ],
    "sg:phone":"+1 210 523 2777",
    "sg:postcode":"78238",
    "sg:province":"TX",
    "sg:tags":[
        "trophy",
        "gift",
        "pin",
        "it",
        "award",
        "item",
        "ribbon",
        "desk",
        "medal",
        "plaque"
    ],
    "wof:name":"Casanova's Trophy Showcase",
    "wof:placetype":"venue"
},
  "geometry": {"coordinates":[-98.60503,29.449596],"type":"Point"}
}