{
  "type": "Feature",
  "properties": {
    "iso:country":"US",
    "sg:address":"3701 Pecan Cir",
    "sg:city":"Bedford",
    "sg:classifiers":[
        {
            "category":"Communications",
            "type":"Services"
        }
    ],
    "sg:phone":"+1 817 259 0590",
    "sg:postcode":"76021",
    "sg:province":"TX",
    "wof:name":"Communications Completed",
    "wof:placetype":"venue"
},
  "geometry": {"coordinates":[-97.121105,32.864018],"type":"Point"}
}