{
  "type": "Feature",
  "properties": {
    "iso:country":"US",
    "sg:address":"11347 Woodridge Forest",
    "sg:city":"San Antonio",
    "sg:classifiers":[
        {
            "category":"Restaurant",
            "type":"Food & Drink"
        }
    ],
    "sg:phone":"+1 210 921 0880",
    "sg:postcode":"78249",
    "sg:province":"TX",
    "sg:tags":[
        "eating"
    ],
    "wof:name":"Salzamoras Restaurant",
    "wof:placetype":"venue"
},
  "geometry": {"coordinates":[-98.60322499999999,29.54774],"type":"Point"}
}