{
  "type": "Feature",
  "properties": {
    "iso:country":"US",
    "sg:address":"6800 W Gate Blvd # 132",
    "sg:city":"Austin",
    "sg:classifiers":[
        {
            "category":"Professional",
            "type":"Services"
        }
    ],
    "sg:phone":"+1 512 801 1796",
    "sg:postcode":"78745",
    "sg:province":"TX",
    "sg:tags":[
        "field",
        "oil"
    ],
    "wof:name":"Hot Shot Services",
    "wof:placetype":"venue"
},
  "geometry": {"coordinates":[-97.814407,30.208811],"type":"Point"}
}