{
  "type": "Feature",
  "properties": {
    "iso:country":"US",
    "sg:address":"900 Isom Rd",
    "sg:city":"San Antonio",
    "sg:classifiers":[
        {
            "category":"Professional",
            "subcategory":"Computer Services",
            "type":"Services"
        },
        {
            "category":"Shopping",
            "subcategory":"Computers & Home Electronics",
            "type":"Retail Goods"
        }
    ],
    "sg:phone":"+1 210 366 3982",
    "sg:postcode":"78216",
    "sg:province":"TX",
    "sg:tags":[
        "development",
        "software"
    ],
    "sg:website":"www.dcitx.com",
    "wof:name":"Data Concepts Inc",
    "wof:placetype":"venue"
},
  "geometry": {"coordinates":[-98.48663999999999,29.534347],"type":"Point"}
}