{
  "type": "Feature",
  "properties": {
    "iso:country":"US",
    "sg:address":"5014 Gessner Dr",
    "sg:city":"Houston",
    "sg:classifiers":[
        {
            "category":"Health Services",
            "subcategory":"Medical Lab",
            "type":"Services"
        }
    ],
    "sg:phone":"+1 713 365 0828",
    "sg:postcode":"77041",
    "sg:province":"TX",
    "sg:tags":[
        "laboratory"
    ],
    "wof:name":"Ace Dental Lab",
    "wof:placetype":"venue"
},
  "geometry": {"coordinates":[-95.54500400000001,29.841621],"type":"Point"}
}