{
  "type": "Feature",
  "properties": {
    "iso:country":"US",
    "sg:address":"6126 Wyche Blvd",
    "sg:city":"Dallas",
    "sg:classifiers":[
        {
            "category":"Building & Trades",
            "subcategory":"Plumbing",
            "type":"Services"
        }
    ],
    "sg:phone":"+1 214 637 3490",
    "sg:postcode":"75235",
    "sg:province":"TX",
    "sg:tags":[
        "installs",
        "lawn",
        "sprinkler"
    ],
    "wof:name":"King Lawn Sprinkler Co",
    "wof:placetype":"venue"
},
  "geometry": {"coordinates":[-96.851393,32.818628],"type":"Point"}
}