{
  "type": "Feature",
  "properties": {
    "iso:country":"US",
    "sg:address":"300 N Coit Rd",
    "sg:city":"Richardson",
    "sg:classifiers":[
        {
            "category":"Professional",
            "subcategory":"Computer Services",
            "type":"Services"
        }
    ],
    "sg:phone":"+1 972 231 0484",
    "sg:postcode":"75080",
    "sg:province":"TX",
    "wof:name":"OMI International Inc",
    "wof:placetype":"venue"
},
  "geometry": {"coordinates":[-96.76898300000001,32.953964],"type":"Point"}
}