{
  "type": "Feature",
  "properties": {
    "iso:country":"US",
    "sg:address":"1900 Speight Ave",
    "sg:city":"Waco",
    "sg:classifiers":[
        {
            "category":"Insurance",
            "subcategory":"Insurance Agent",
            "type":"Services"
        }
    ],
    "sg:phone":"+1 254 755 0055",
    "sg:postcode":"76706",
    "sg:province":"TX",
    "wof:name":"Amco Insurance Agency",
    "wof:placetype":"venue"
},
  "geometry": {"coordinates":[-97.130459,31.534851],"type":"Point"}
}