{
  "type": "Feature",
  "properties": {
    "iso:country":"US",
    "sg:address":"5211 Spring Arrow",
    "sg:city":"San Antonio",
    "sg:classifiers":[
        {
            "category":"Building & Trades",
            "subcategory":"Pest Control",
            "type":"Services"
        }
    ],
    "sg:phone":"+1 210 824 7790",
    "sg:postcode":"78247",
    "sg:province":"TX",
    "wof:name":"Professional Inspectors Group",
    "wof:placetype":"venue"
},
  "geometry": {"coordinates":[-98.388029,29.581167],"type":"Point"}
}