{
  "type": "Feature",
  "properties": {
    "iso:country":"US",
    "sg:address":"1512 W 35th St Cutoff Ste 300",
    "sg:city":"Austin",
    "sg:classifiers":[
        {
            "category":"Shopping",
            "subcategory":"Stationery & Office Supplies",
            "type":"Retail Goods"
        },
        {
            "category":"Building & Trades",
            "subcategory":"Construction",
            "type":"Services"
        },
        {
            "category":"Real Estate",
            "subcategory":"Architect",
            "type":"Services"
        }
    ],
    "sg:phone":"+1 512 480 8898",
    "sg:postcode":"78731",
    "sg:province":"TX",
    "sg:tags":[
        "interior",
        "equipment",
        "design"
    ],
    "sg:website":"www.bommaritogroup.com",
    "wof:name":"Bommarito Group",
    "wof:placetype":"venue"
},
  "geometry": {"coordinates":[-97.74956899999999,30.307174],"type":"Point"}
}