{
  "type": "Feature",
  "properties": {
    "iso:country":"US",
    "sg:address":"115 Coney St",
    "sg:city":"San Antonio",
    "sg:classifiers":[
        {
            "category":"Autos & Motor Vehicles",
            "subcategory":"Automobile Sales",
            "type":"Retail Goods"
        }
    ],
    "sg:phone":"+1 210 337 5323",
    "sg:postcode":"78223",
    "sg:province":"TX",
    "sg:tags":[
        "used"
    ],
    "wof:name":"North America Cars Inc",
    "wof:placetype":"venue"
},
  "geometry": {"coordinates":[-98.445831,29.365993],"type":"Point"}
}