{
  "type": "Feature",
  "properties": {
    "iso:country":"US",
    "sg:address":"4309 Palmdale Dr",
    "sg:city":"Plano",
    "sg:classifiers":[
        {
            "category":"Professional",
            "subcategory":"Management & Consulting",
            "type":"Services"
        }
    ],
    "sg:phone":"+1 972 987 5688",
    "sg:postcode":"75024",
    "sg:province":"TX",
    "sg:tags":[
        "marketing"
    ],
    "wof:name":"Harvey Communications Inc",
    "wof:placetype":"venue"
},
  "geometry": {"coordinates":[-96.77615299999999,33.083585],"type":"Point"}
}