{
  "type": "Feature",
  "properties": {
    "iso:country":"US",
    "sg:address":"2120 Forest Oaks Dr",
    "sg:city":"Dallas",
    "sg:classifiers":[
        {
            "category":"Building & Trades",
            "subcategory":"Pest Control",
            "type":"Services"
        }
    ],
    "sg:phone":"+1 214 321 1887",
    "sg:postcode":"75228",
    "sg:province":"TX",
    "wof:name":"Exterminator Co the",
    "wof:placetype":"venue"
},
  "geometry": {"coordinates":[-96.70610000000001,32.810902],"type":"Point"}
}