{
  "type": "Feature",
  "properties": {
    "iso:country":"US",
    "sg:address":"141 Tahitian Dr",
    "sg:city":"Bastrop",
    "sg:classifiers":[
        {
            "category":"Shopping",
            "subcategory":"Pharmacy",
            "type":"Retail Goods"
        }
    ],
    "sg:phone":"+1 512 303 3802",
    "sg:postcode":"78602",
    "sg:province":"TX",
    "wof:name":"Manestream Hair Salon",
    "wof:placetype":"venue"
},
  "geometry": {"coordinates":[-97.284358,30.101903],"type":"Point"}
}