{
  "type": "Feature",
  "properties": {
    "iso:country":"US",
    "sg:address":"610 Brazos St Ste 600",
    "sg:city":"Austin",
    "sg:classifiers":[
        {
            "category":"Real Estate",
            "subcategory":"Architect",
            "type":"Services"
        }
    ],
    "sg:phone":"+1 512 474 7111",
    "sg:postcode":"78701",
    "sg:province":"TX",
    "sg:website":"www.HAJEKassociates.com",
    "wof:name":"Hajek & Associates",
    "wof:placetype":"venue"
},
  "geometry": {"coordinates":[-97.741474,30.268384],"type":"Point"}
}