{
  "type": "Feature",
  "properties": {
    "iso:country":"US",
    "sg:address":"8481 Gulf Fwy",
    "sg:city":"Houston",
    "sg:classifiers":[
        {
            "category":"Shopping",
            "subcategory":"Jewelry",
            "type":"Retail Goods"
        }
    ],
    "sg:phone":"+1 713 910 0010",
    "sg:postcode":"77017",
    "sg:province":"TX",
    "sg:website":"www.vanmarkjewelry.com",
    "wof:name":"Reese Harold Jewelry",
    "wof:placetype":"venue"
},
  "geometry": {"coordinates":[-95.262901,29.6709],"type":"Point"}
}