{
  "type": "Feature",
  "properties": {
    "iso:country":"US",
    "sg:address":"3028 Sesbania Dr",
    "sg:city":"Austin",
    "sg:classifiers":[
        {
            "category":"Professional",
            "subcategory":"Management & Consulting",
            "type":"Services"
        }
    ],
    "sg:phone":"+1 512 280 1559",
    "sg:postcode":"78748",
    "sg:province":"TX",
    "sg:tags":[
        "consultant",
        "business"
    ],
    "wof:name":"Project Directions Inc",
    "wof:placetype":"venue"
},
  "geometry": {"coordinates":[-97.853562,30.164284],"type":"Point"}
}