{
  "type": "Feature",
  "properties": {
    "iso:country":"US",
    "sg:address":"1215 Elm Ave",
    "sg:city":"Friona",
    "sg:classifiers":[
        {
            "category":"Manufacturing",
            "subcategory":"Printing",
            "type":"Manufacturing & Wholesale Goods"
        }
    ],
    "sg:phone":"+1 806 250 5200",
    "sg:postcode":"79035",
    "sg:province":"TX",
    "sg:tags":[
        "printer"
    ],
    "wof:name":"Intheden Graphics",
    "wof:placetype":"venue"
},
  "geometry": {"coordinates":[-102.72389699999999,34.643511],"type":"Point"}
}