{
  "type": "Feature",
  "properties": {
    "iso:country":"US",
    "sg:address":"20803 Chappell Knoll Dr",
    "sg:city":"Cypress",
    "sg:classifiers":[
        {
            "category":"Professional",
            "subcategory":"Management & Consulting",
            "type":"Services"
        }
    ],
    "sg:phone":"+1 281 373 5961",
    "sg:postcode":"77433",
    "sg:province":"TX",
    "wof:name":"McGhee King & Assoc",
    "wof:placetype":"venue"
},
  "geometry": {"coordinates":[-95.743574,29.999378],"type":"Point"}
}