{
  "type": "Feature",
  "properties": {
    "iso:country":"US",
    "sg:address":"1303 S Oakes St",
    "sg:city":"San Angelo",
    "sg:classifiers":[
        {
            "category":"Professional",
            "type":"Services"
        }
    ],
    "sg:phone":"+1 325 658 4888",
    "sg:postcode":"76903",
    "sg:province":"TX",
    "sg:tags":[
        "establishment"
    ],
    "wof:name":"LA Esperanza Outreach",
    "wof:placetype":"venue"
},
  "geometry": {"coordinates":[-100.431847,31.447268],"type":"Point"}
}