{
  "type": "Feature",
  "properties": {
    "iso:country":"US",
    "sg:address":"6161 Doniphan Dr",
    "sg:city":"El Paso",
    "sg:classifiers":[
        {
            "category":"Freight",
            "type":"Transportation"
        }
    ],
    "sg:phone":"+1 915 587 9317",
    "sg:postcode":"79932",
    "sg:province":"TX",
    "sg:tags":[
        "trucking"
    ],
    "wof:name":"G C Transportation",
    "wof:placetype":"venue"
},
  "geometry": {"coordinates":[-106.591959,31.872736],"type":"Point"}
}