{
  "type": "Feature",
  "properties": {
    "iso:country":"US",
    "sg:address":"1030 Red Rock Canyon Dr",
    "sg:city":"Katy",
    "sg:classifiers":[
        {
            "category":"Sports & Exercise",
            "subcategory":"Swimming Pool",
            "type":"Entertainment"
        },
        {
            "category":"Building & Trades",
            "subcategory":"Construction",
            "type":"Services"
        },
        {
            "category":"Recreation",
            "subcategory":"Barbecue",
            "type":"Entertainment"
        },
        {
            "category":"Home & Garden",
            "subcategory":"Furniture",
            "type":"Retail Goods"
        }
    ],
    "sg:phone":"+1 281 392 2098",
    "sg:postcode":"77450",
    "sg:province":"TX",
    "sg:tags":[
        "grill",
        "supply",
        "builder",
        "deck",
        "cabinet",
        "equipment-household",
        "patio",
        "kitchen"
    ],
    "sg:website":"http://www.sunsetbayoutdoor.com",
    "wof:name":"Sunset Bay Outdoor Kitchens, TX",
    "wof:placetype":"venue"
},
  "geometry": {"coordinates":[-95.76203700000001,29.765227],"type":"Point"}
}