{
  "type": "Feature",
  "properties": {
    "iso:country":"US",
    "sg:address":"830 E Pipe Creek Dr",
    "sg:city":"Pipe Creek",
    "sg:classifiers":[
        {
            "category":"Shopping",
            "subcategory":"Gifts & Souvenirs",
            "type":"Retail Goods"
        }
    ],
    "sg:phone":"+1 830 510 6253",
    "sg:postcode":"78063",
    "sg:province":"TX",
    "sg:tags":[
        "collectible"
    ],
    "wof:name":"Motorsports Connection",
    "wof:placetype":"venue"
},
  "geometry": {"coordinates":[-98.941452,29.717128],"type":"Point"}
}