{
  "type": "Feature",
  "properties": {
    "iso:country":"US",
    "sg:address":"1912 E Hebron Pkwy",
    "sg:city":"Carrollton",
    "sg:classifiers":[
        {
            "category":"Shopping",
            "subcategory":"Florist",
            "type":"Retail Goods"
        }
    ],
    "sg:phone":"+1 972 423 2501",
    "sg:postcode":"75007",
    "sg:province":"TX",
    "sg:website":"www.inbloomflowers.com",
    "wof:name":"In Bloom Flowers",
    "wof:placetype":"venue"
},
  "geometry": {"coordinates":[-96.883499,33.024601],"type":"Point"}
}