{
  "type": "Feature",
  "properties": {
    "iso:country":"US",
    "sg:address":"4115 Firstview Dr",
    "sg:city":"Austin",
    "sg:classifiers":[
        {
            "category":"Professional",
            "subcategory":"Computer Services",
            "type":"Services"
        }
    ],
    "sg:phone":"+1 512 323 5300",
    "sg:postcode":"78731",
    "sg:province":"TX",
    "sg:tags":[
        "design",
        "system"
    ],
    "wof:name":"Candlelight Ranch Retreat",
    "wof:placetype":"venue"
},
  "geometry": {"coordinates":[-97.771874,30.34928],"type":"Point"}
}