{
  "type": "Feature",
  "properties": {
    "iso:country":"US",
    "sg:address":"709 King Dr",
    "sg:city":"Bedford",
    "sg:classifiers":[
        {
            "category":"Building & Trades",
            "subcategory":"Plumbing",
            "type":"Services"
        }
    ],
    "sg:phone":"+1 817 268 5334",
    "sg:postcode":"76022",
    "sg:province":"TX",
    "sg:tags":[
        "contractor"
    ],
    "wof:name":"Rw Frederick & Assoc",
    "wof:placetype":"venue"
},
  "geometry": {"coordinates":[-97.15268500000001,32.82824],"type":"Point"}
}