{
  "type": "Feature",
  "properties": {
    "iso:country":"US",
    "sg:address":"426 W Greens Rd",
    "sg:city":"Houston",
    "sg:classifiers":[
        {
            "category":"Personal",
            "subcategory":"Beauty Salon",
            "type":"Services"
        }
    ],
    "sg:phone":"+1 281 874 0300",
    "sg:postcode":"77067",
    "sg:province":"TX",
    "wof:name":"Heidi & Jojo",
    "wof:placetype":"venue"
},
  "geometry": {"coordinates":[-95.42229500000001,29.949067],"type":"Point"}
}