{
  "type": "Feature",
  "properties": {
    "iso:country":"US",
    "sg:address":"728 Elizabeth St",
    "sg:city":"Corpus Christi",
    "sg:classifiers":[
        {
            "category":"Real Estate",
            "subcategory":"Real Estate Agent",
            "type":"Services"
        }
    ],
    "sg:phone":"+1 361 885 0584",
    "sg:postcode":"78404",
    "sg:province":"TX",
    "sg:tags":[
        "finding",
        "apartment",
        "rental"
    ],
    "wof:name":"Guess Enterprises",
    "wof:placetype":"venue"
},
  "geometry": {"coordinates":[-97.398219,27.777382],"type":"Point"}
}