{
  "type": "Feature",
  "properties": {
    "iso:country":"US",
    "sg:address":"9624 Homeplace Dr",
    "sg:city":"Dallas",
    "sg:classifiers":[
        {
            "category":"Professional",
            "type":"Services"
        }
    ],
    "sg:phone":"+1 469 547 0741",
    "sg:postcode":"75217",
    "sg:province":"TX",
    "wof:name":"Keiths International",
    "wof:placetype":"venue"
},
  "geometry": {"coordinates":[-96.65424400000001,32.724598],"type":"Point"}
}