{
  "type": "Feature",
  "properties": {
    "iso:country":"US",
    "sg:address":"2205 Ave I",
    "sg:city":"Rosenberg",
    "sg:classifiers":[
        {
            "category":"Government",
            "subcategory":"Office",
            "type":"Public Place"
        }
    ],
    "sg:phone":"+1 281 239 8470",
    "sg:postcode":"77471",
    "sg:province":"TX",
    "wof:name":"Us Engineering Office",
    "wof:placetype":"venue"
},
  "geometry": {"coordinates":[-95.80403699999999,29.557348],"type":"Point"}
}