{
  "type": "Feature",
  "properties": {
    "iso:country":"US",
    "sg:address":"17714 Scarlett Falls Ln",
    "sg:city":"Richmond",
    "sg:classifiers":[
        {
            "category":"Professional",
            "subcategory":"Employment Agencies",
            "type":"Services"
        }
    ],
    "sg:phone":"+1 281 242 4257",
    "sg:postcode":"77407",
    "sg:province":"TX",
    "sg:tags":[
        "contractor"
    ],
    "wof:name":"Golden Hands Staffing Inc",
    "wof:placetype":"venue"
},
  "geometry": {"coordinates":[-95.69049200000001,29.688677],"type":"Point"}
}