{
  "type": "Feature",
  "properties": {
    "iso:country":"US",
    "sg:address":"350 Utopia Ave",
    "sg:city":"San Antonio",
    "sg:classifiers":[
        {
            "category":"Organizations",
            "subcategory":"Religious Organization",
            "type":"Services"
        }
    ],
    "sg:phone":"+1 210 337 6108",
    "sg:postcode":"78223",
    "sg:province":"TX",
    "sg:tags":[
        "church"
    ],
    "wof:name":"First United Pentecostal Chr",
    "wof:placetype":"venue"
},
  "geometry": {"coordinates":[-98.44211199999999,29.35943],"type":"Point"}
}