{
  "type": "Feature",
  "properties": {
    "iso:country":"US",
    "sg:address":"12000 E Osr",
    "sg:city":"Hearne",
    "sg:classifiers":[
        {
            "category":"Farming",
            "subcategory":"Livestock Farm",
            "type":"Manufacturing & Wholesale Goods"
        }
    ],
    "sg:phone":"+1 979 828 5525",
    "sg:postcode":"77808",
    "sg:province":"TX",
    "sg:tags":[
        "beef",
        "ranch",
        "feedlot",
        "animal",
        "cattle"
    ],
    "wof:name":"Deshazer Cattle Company",
    "wof:placetype":"venue"
},
  "geometry": {"coordinates":[-96.363542,30.890653],"type":"Point"}
}