{
  "type": "Feature",
  "properties": {
    "iso:country":"US",
    "sg:address":"4023 Parkside Dr",
    "sg:city":"Dallas",
    "sg:classifiers":[
        {
            "category":"Professional",
            "subcategory":"Management & Consulting",
            "type":"Services"
        }
    ],
    "sg:phone":"+1 214 739 2568",
    "sg:postcode":"75209",
    "sg:province":"TX",
    "sg:tags":[
        "business"
    ],
    "wof:name":"Nancy Whittington",
    "wof:placetype":"venue"
},
  "geometry": {"coordinates":[-96.84103500000001,32.852086],"type":"Point"}
}