{
  "type": "Feature",
  "properties": {
    "iso:country":"US",
    "sg:address":"717 S Good Latimer Expy",
    "sg:city":"Dallas",
    "sg:classifiers":[
        {
            "category":"Professional",
            "subcategory":"Business Services",
            "type":"Services"
        }
    ],
    "sg:phone":"+1 214 823 3154",
    "sg:postcode":"75226",
    "sg:province":"TX",
    "sg:tags":[
        "party",
        "decorating",
        "planning",
        "event",
        "contractor"
    ],
    "sg:website":"www.billreed.com",
    "wof:name":"Bill Reed Decorations Inc",
    "wof:placetype":"venue"
},
  "geometry": {"coordinates":[-96.784897,32.779499],"type":"Point"}
}