{
  "type": "Feature",
  "properties": {
    "iso:country":"US",
    "sg:address":"309 E Schreck St",
    "sg:city":"Baytown",
    "sg:classifiers":[
        {
            "category":"Retail",
            "subcategory":"Repair Shop",
            "type":"Services"
        }
    ],
    "sg:phone":"+1 281 424 9769",
    "sg:postcode":"77520",
    "sg:province":"TX",
    "sg:tags":[
        "bathtub",
        "sink",
        "refinishing"
    ],
    "wof:name":"American Bathtub Refinishing",
    "wof:placetype":"venue"
},
  "geometry": {"coordinates":[-95.02941800000001,29.761317],"type":"Point"}
}