{
  "type": "Feature",
  "properties": {
    "iso:country":"US",
    "sg:address":"2126 Brinton Oaks Ct",
    "sg:city":"Katy",
    "sg:classifiers":[
        {
            "category":"Health Services",
            "subcategory":"Clinic",
            "type":"Services"
        }
    ],
    "sg:phone":"+1 281 829 1365",
    "sg:postcode":"77450",
    "sg:province":"TX",
    "wof:name":"Legacy Health Care",
    "wof:placetype":"venue"
},
  "geometry": {"coordinates":[-95.745268,29.750908],"type":"Point"}
}