{
  "type": "Feature",
  "properties": {
    "iso:country":"US",
    "sg:address":"7462 Leopard St",
    "sg:city":"Corpus Christi",
    "sg:classifiers":[
        {
            "category":"Wholesale",
            "subcategory":"Machinery & Supplies",
            "type":"Manufacturing & Wholesale Goods"
        },
        {
            "category":"Manufacturing",
            "subcategory":"Tools & Machinery",
            "type":"Manufacturing & Wholesale Goods"
        }
    ],
    "sg:phone":"+1 361 289 6853",
    "sg:postcode":"78409",
    "sg:province":"TX",
    "sg:tags":[
        "equipment",
        "field",
        "oil",
        "mfg"
    ],
    "wof:name":"Seaboard Arval Corp",
    "wof:placetype":"venue"
},
  "geometry": {"coordinates":[-97.504705,27.808439],"type":"Point"}
}