{
  "type": "Feature",
  "properties": {
    "iso:country":"US",
    "sg:address":"1108 Hillside Dr",
    "sg:city":"Keller",
    "sg:classifiers":[
        {
            "category":"Bars & Pubs",
            "type":"Food & Drink"
        }
    ],
    "sg:phone":"+1 817 337 0042",
    "sg:postcode":"76248",
    "sg:province":"TX",
    "sg:tags":[
        "drinking"
    ],
    "wof:name":"Bull Pen",
    "wof:placetype":"venue"
},
  "geometry": {"coordinates":[-97.23456,32.950957],"type":"Point"}
}