{
  "type": "Feature",
  "properties": {
    "iso:country":"US",
    "sg:address":"5000 Alabama St",
    "sg:city":"El Paso",
    "sg:classifiers":[
        {
            "category":"Health Services",
            "subcategory":"Doctor",
            "type":"Services"
        }
    ],
    "sg:phone":"+1 915 564 4406",
    "sg:postcode":"79930",
    "sg:province":"TX",
    "sg:tags":[
        "physician"
    ],
    "wof:name":"James B Beard D O",
    "wof:placetype":"venue"
},
  "geometry": {"coordinates":[-106.46552200000001,31.82179],"type":"Point"}
}