{
  "type": "Feature",
  "properties": {
    "iso:country":"US",
    "sg:address":"807 Martin Luther King",
    "sg:city":"Liberty",
    "sg:classifiers":[
        {
            "category":"Professional",
            "type":"Services"
        }
    ],
    "sg:phone":"+1 936 336 2080",
    "sg:postcode":"77575",
    "sg:province":"TX",
    "wof:name":"Aging Young Center Inc",
    "wof:placetype":"venue"
},
  "geometry": {"coordinates":[-94.74534800000001,30.033407],"type":"Point"}
}