{
  "type": "Feature",
  "properties": {
    "iso:country":"US",
    "sg:address":"116 Givens Ave",
    "sg:city":"Del Rio",
    "sg:classifiers":[
        {
            "category":"Building & Trades",
            "subcategory":"Construction",
            "type":"Services"
        }
    ],
    "sg:phone":"+1 830 774 1012",
    "sg:postcode":"78840",
    "sg:province":"TX",
    "sg:tags":[
        "hanging",
        "contractor"
    ],
    "wof:name":"Juan Venegas",
    "wof:placetype":"venue"
},
  "geometry": {"coordinates":[-100.89339,29.346106],"type":"Point"}
}