{
  "type": "Feature",
  "properties": {
    "iso:country":"US",
    "sg:address":"4920 S Hulen St",
    "sg:city":"Fort Worth",
    "sg:classifiers":[
        {
            "category":"Cinema",
            "subcategory":"Movie Theater",
            "type":"Entertainment"
        }
    ],
    "sg:phone":"+1 817 294 2621",
    "sg:postcode":"76132",
    "sg:province":"TX",
    "sg:tags":[
        "motion",
        "picture"
    ],
    "wof:name":"Regal Cinemas Inc",
    "wof:placetype":"venue"
},
  "geometry": {"coordinates":[-97.397965,32.675269],"type":"Point"}
}