{
  "type": "Feature",
  "properties": {
    "iso:country":"US",
    "sg:address":"610 FM 1092",
    "sg:city":"Stafford",
    "sg:classifiers":[
        {
            "category":"Shopping",
            "subcategory":"Musical Instruments",
            "type":"Retail Goods"
        }
    ],
    "sg:phone":"+1 281 261 3030",
    "sg:postcode":"77477",
    "sg:province":"TX",
    "sg:tags":[
        "music",
        "dealer"
    ],
    "wof:name":"Blockerboy Music",
    "wof:placetype":"venue"
},
  "geometry": {"coordinates":[-95.564543,29.610272],"type":"Point"}
}