{
  "type": "Feature",
  "properties": {
    "iso:country":"US",
    "sg:address":"2109 N John Redditt Dr",
    "sg:city":"Lufkin",
    "sg:classifiers":[
        {
            "category":"Professional",
            "type":"Services"
        }
    ],
    "sg:phone":"+1 936 633 7992",
    "sg:postcode":"75904",
    "sg:province":"TX",
    "wof:name":"Jedon Inc",
    "wof:placetype":"venue"
},
  "geometry": {"coordinates":[-94.765045,31.35517],"type":"Point"}
}