{
  "type": "Feature",
  "properties": {
    "iso:country":"US",
    "sg:address":"2918 Cowboy Dr",
    "sg:city":"Dallas",
    "sg:classifiers":[
        {
            "category":"Professional",
            "subcategory":"Business Services",
            "type":"Services"
        }
    ],
    "sg:phone":"+1 972 709 1914",
    "sg:postcode":"75237",
    "sg:province":"TX",
    "sg:tags":[
        "broker"
    ],
    "wof:name":"Chameleon Business Ventures",
    "wof:placetype":"venue"
},
  "geometry": {"coordinates":[-96.86485500000001,32.659922],"type":"Point"}
}