{
  "type": "Feature",
  "properties": {
    "iso:country":"US",
    "sg:address":"11482 S Highway 181",
    "sg:city":"Kenedy",
    "sg:classifiers":[
        {
            "category":"Government",
            "subcategory":"Office",
            "type":"Public Place"
        }
    ],
    "sg:phone":"+1 830 583 2603",
    "sg:postcode":"78119",
    "sg:province":"TX",
    "wof:name":"Lee Hammack",
    "wof:placetype":"venue"
},
  "geometry": {"coordinates":[-97.846605,28.711535],"type":"Point"}
}