{
  "type": "Feature",
  "properties": {
    "iso:country":"US",
    "sg:address":"15519 Luna Rdg",
    "sg:city":"Helotes",
    "sg:classifiers":[
        {
            "category":"Communications",
            "subcategory":"Radio Station",
            "type":"Services"
        }
    ],
    "sg:phone":"+1 210 385 3961",
    "sg:postcode":"78023",
    "sg:province":"TX",
    "sg:tags":[
        "broadcast"
    ],
    "wof:name":"George C George",
    "wof:placetype":"venue"
},
  "geometry": {"coordinates":[-98.65482,29.589499],"type":"Point"}
}