{
  "type": "Feature",
  "properties": {
    "iso:country":"US",
    "sg:address":"505 E Mcintyre St",
    "sg:city":"Edinburg",
    "sg:classifiers":[
        {
            "category":"Tea Room",
            "subcategory":"None",
            "type":"Food & Drink"
        },
        {
            "category":"Coffee & Tea",
            "type":"Food & Drink"
        }
    ],
    "sg:phone":"+1 956 383 2646",
    "sg:postcode":"78541",
    "sg:province":"TX",
    "wof:name":"Corina's Tea Room",
    "wof:placetype":"venue"
},
  "geometry": {"coordinates":[-98.15771700000001,26.301833],"type":"Point"}
}