{
  "type": "Feature",
  "properties": {
    "iso:country":"US",
    "sg:address":"1072 Colabe Rd",
    "sg:city":"Livingston",
    "sg:classifiers":[
        {
            "category":"Place Of Worship",
            "subcategory":"Church",
            "type":"Public Place"
        },
        {
            "category":"Place Of Worship",
            "type":"Public Place"
        }
    ],
    "sg:phone":"+1 936 563 4259",
    "sg:postcode":"77351",
    "sg:province":"TX",
    "sg:tags":[
        "churches-presbyterian-arp",
        "churches-presbyterian"
    ],
    "wof:name":"Indian Presbyterian Church",
    "wof:placetype":"venue"
},
  "geometry": {"coordinates":[-94.673923,30.715192],"type":"Point"}
}