{
  "type": "Feature",
  "properties": {
    "iso:country":"US",
    "sg:address":"14500 Dallas Pkwy Apt 126",
    "sg:city":"Dallas",
    "sg:classifiers":[
        {
            "category":"Autos & Motor Vehicles",
            "subcategory":"Automobile Sales",
            "type":"Retail Goods"
        }
    ],
    "sg:phone":"+1 972 991 6336",
    "sg:postcode":"75254",
    "sg:province":"TX",
    "sg:tags":[
        "limo"
    ],
    "wof:name":"A-1 Airport & Limousine Service",
    "wof:placetype":"venue"
},
  "geometry": {"coordinates":[-96.8228,32.945599],"type":"Point"}
}