{
  "type": "Feature",
  "properties": {
    "iso:country":"US",
    "sg:address":"305 Las Colinas Dr",
    "sg:city":"Georgetown",
    "sg:classifiers":[
        {
            "category":"Insurance",
            "subcategory":"Hazard Insurance",
            "type":"Services"
        }
    ],
    "sg:phone":"+1 512 864 7506",
    "sg:postcode":"78628",
    "sg:province":"TX",
    "sg:tags":[
        "commercial",
        "business"
    ],
    "wof:name":"Mierendorf Financial Serv",
    "wof:placetype":"venue"
},
  "geometry": {"coordinates":[-97.683729,30.709875],"type":"Point"}
}