{
  "type": "Feature",
  "properties": {
    "iso:country":"US",
    "sg:address":"2005 Royalwood Dr",
    "sg:city":"Arlington",
    "sg:classifiers":[
        {
            "category":"Building & Trades",
            "subcategory":"Equipment Rental",
            "type":"Services"
        }
    ],
    "sg:phone":"+1 817 860 3121",
    "sg:postcode":"76006",
    "sg:province":"TX",
    "wof:name":"Medtex Rentals Inc",
    "wof:placetype":"venue"
},
  "geometry": {"coordinates":[-97.073774,32.770707],"type":"Point"}
}