{
  "type": "Feature",
  "properties": {
    "iso:country":"US",
    "sg:address":"923 Salmon Dr",
    "sg:city":"Dallas",
    "sg:classifiers":[
        {
            "category":"Arts & Performance",
            "subcategory":"Art Gallery",
            "type":"Entertainment"
        }
    ],
    "sg:phone":"+1 214 914 1099",
    "sg:postcode":"75208",
    "sg:province":"TX",
    "sg:website":"www.dallasartdealers.org",
    "wof:name":"Dallas Art Dealers Association",
    "wof:placetype":"venue"
},
  "geometry": {"coordinates":[-96.83860199999999,32.757358],"type":"Point"}
}