{
  "type": "Feature",
  "properties": {
    "iso:country":"US",
    "sg:address":"1910 S 1st St",
    "sg:city":"Garland",
    "sg:classifiers":[
        {
            "category":"Restaurant",
            "type":"Food & Drink"
        }
    ],
    "sg:phone":"+1 972 278 4770",
    "sg:postcode":"75040",
    "sg:province":"TX",
    "sg:tags":[
        "american",
        "latin"
    ],
    "wof:name":"Rosi's Pupuseria",
    "wof:placetype":"venue"
},
  "geometry": {"coordinates":[-96.630826,32.89519],"type":"Point"}
}