{
  "type": "Feature",
  "properties": {
    "iso:country":"US",
    "sg:address":"1325 N Mockingbird Ln",
    "sg:city":"Abilene",
    "sg:classifiers":[
        {
            "category":"Retail",
            "subcategory":"Repair Shop",
            "type":"Services"
        }
    ],
    "sg:phone":"+1 325 673 8644",
    "sg:postcode":"79603",
    "sg:province":"TX",
    "sg:tags":[
        "electrical"
    ],
    "wof:name":"Rogers Appliance Sales",
    "wof:placetype":"venue"
},
  "geometry": {"coordinates":[-99.757745,32.463972],"type":"Point"}
}