{
  "type": "Feature",
  "properties": {
    "iso:country":"US",
    "sg:address":"1517 Westlake Dr",
    "sg:city":"Wichita Falls",
    "sg:classifiers":[
        {
            "category":"Building & Trades",
            "subcategory":"Construction",
            "type":"Services"
        }
    ],
    "sg:phone":"+1 940 322 6230",
    "sg:postcode":"76309",
    "sg:province":"TX",
    "sg:tags":[
        "residential"
    ],
    "wof:name":"R&R Roofing & Remodeling",
    "wof:placetype":"venue"
},
  "geometry": {"coordinates":[-98.528858,33.901344],"type":"Point"}
}