{
  "type": "Feature",
  "properties": {
    "iso:country":"US",
    "sg:address":"8314 Scyene Rd",
    "sg:city":"Dallas",
    "sg:classifiers":[
        {
            "category":"Organizations",
            "subcategory":"Religious Organization",
            "type":"Services"
        }
    ],
    "sg:phone":"+1 214 388 3434",
    "sg:postcode":"75227",
    "sg:province":"TX",
    "sg:tags":[
        "church"
    ],
    "wof:name":"Real Baptist Church",
    "wof:placetype":"venue"
},
  "geometry": {"coordinates":[-96.677482,32.763817],"type":"Point"}
}