{
  "type": "Feature",
  "properties": {
    "iso:country":"US",
    "sg:address":"1913 Morningstar Trl",
    "sg:city":"Richardson",
    "sg:classifiers":[
        {
            "category":"Professional",
            "subcategory":"Management & Consulting",
            "type":"Services"
        }
    ],
    "sg:phone":"+1 972 889 1237",
    "sg:postcode":"75081",
    "sg:province":"TX",
    "sg:tags":[
        "business"
    ],
    "wof:name":"Rosa General Services",
    "wof:placetype":"venue"
},
  "geometry": {"coordinates":[-96.687073,32.940297],"type":"Point"}
}