{
  "type": "Feature",
  "properties": {
    "iso:country":"US",
    "sg:address":"907 Lake Breeze",
    "sg:city":"Lewisville",
    "sg:classifiers":[
        {
            "category":"Autos & Motor Vehicles",
            "subcategory":"Automobile Sales",
            "type":"Retail Goods"
        }
    ],
    "sg:phone":"+1 972 966 8441",
    "sg:postcode":"75077",
    "sg:province":"TX",
    "sg:tags":[
        "equipment",
        "aircraft"
    ],
    "wof:name":"Morgan Aviation",
    "wof:placetype":"venue"
},
  "geometry": {"coordinates":[-97.066765,33.094229],"type":"Point"}
}