{
  "type": "Feature",
  "properties": {
    "iso:country":"US",
    "sg:address":"10370 Richmond Ave",
    "sg:city":"Houston",
    "sg:classifiers":[
        {
            "category":"Marine",
            "type":"Transportation"
        }
    ],
    "sg:phone":"+1 713 977 4333",
    "sg:postcode":"77042",
    "sg:province":"TX",
    "sg:tags":[
        "towing"
    ],
    "wof:name":"Bowring Marine LTD Of Tx",
    "wof:placetype":"venue"
},
  "geometry": {"coordinates":[-95.556764,29.727708],"type":"Point"}
}