{
  "type": "Feature",
  "properties": {
    "iso:country":"US",
    "sg:address":"3717 Tripoli Dr",
    "sg:city":"Corpus Christi",
    "sg:classifiers":[
        {
            "category":"Building & Trades",
            "subcategory":"Cleaning & Sanitation",
            "type":"Services"
        },
        {
            "category":"Building & Trades",
            "subcategory":"Construction",
            "type":"Services"
        }
    ],
    "sg:phone":"+1 361 854 6270",
    "sg:postcode":"78415",
    "sg:province":"TX",
    "sg:tags":[
        "roofing",
        "maintenance",
        "contractor"
    ],
    "wof:name":"Mac's General Contracting",
    "wof:placetype":"venue"
},
  "geometry": {"coordinates":[-97.409342,27.716065],"type":"Point"}
}