{
  "type": "Feature",
  "properties": {
    "iso:country":"US",
    "sg:address":"3110 Owls Roost",
    "sg:city":"Greenville",
    "sg:classifiers":[
        {
            "category":"Shopping",
            "subcategory":"Bicycles & Sporting Goods",
            "type":"Retail Goods"
        },
        {
            "category":"Sports & Exercise",
            "subcategory":"Golf",
            "type":"Entertainment"
        }
    ],
    "sg:phone":"+1 903 883 3010",
    "sg:postcode":"75402",
    "sg:province":"TX",
    "sg:tags":[
        "equipment",
        "course",
        "supply"
    ],
    "wof:name":"Golfers Attic",
    "wof:placetype":"venue"
},
  "geometry": {"coordinates":[-96.010257,33.042194],"type":"Point"}
}