{
  "type": "Feature",
  "properties": {
    "iso:country":"US",
    "sg:address":"374 Sulky Trail St",
    "sg:city":"Houston",
    "sg:classifiers":[
        {
            "category":"Shopping",
            "subcategory":"Jewelry",
            "type":"Retail Goods"
        }
    ],
    "sg:phone":"+1 281 591 8481",
    "sg:postcode":"77060",
    "sg:province":"TX",
    "wof:name":"Marys Retail Jewelry",
    "wof:placetype":"venue"
},
  "geometry": {"coordinates":[-95.396479,29.930391],"type":"Point"}
}