{
  "type": "Feature",
  "properties": {
    "iso:country":"US",
    "sg:address":"1701 N Banks St",
    "sg:city":"Pampa",
    "sg:classifiers":[
        {
            "category":"Communications",
            "subcategory":"Radio Station",
            "type":"Services"
        }
    ],
    "sg:phone":"+1 806 669 9592",
    "sg:postcode":"79065",
    "sg:province":"TX",
    "sg:tags":[
        "company",
        "broadcasting"
    ],
    "wof:name":"KGRO",
    "wof:placetype":"venue"
},
  "geometry": {"coordinates":[-100.973212,35.552628],"type":"Point"}
}