{
  "type": "Feature",
  "properties": {
    "iso:country":"US",
    "sg:address":"2915 E Cesar Chavez St",
    "sg:city":"Austin",
    "sg:classifiers":[
        {
            "category":"Professional",
            "subcategory":"Business Services",
            "type":"Services"
        }
    ],
    "sg:phone":"+1 512 385 3030",
    "sg:postcode":"78702",
    "sg:province":"TX",
    "wof:name":"Trb Enterprises",
    "wof:placetype":"venue"
},
  "geometry": {"coordinates":[-97.71095800000001,30.252296],"type":"Point"}
}