{
  "type": "Feature",
  "properties": {
    "iso:country":"US",
    "sg:address":"944 S Buckner Blvd",
    "sg:city":"Dallas",
    "sg:classifiers":[
        {
            "category":"Autos & Motor Vehicles",
            "subcategory":"Automobile Sales",
            "type":"Retail Goods"
        }
    ],
    "sg:phone":"+1 214 398 1561",
    "sg:postcode":"75217",
    "sg:province":"TX",
    "sg:tags":[
        "dealers-used",
        "car",
        "used",
        "cars-wholesale",
        "new"
    ],
    "wof:name":"Price Auto Sales",
    "wof:placetype":"venue"
},
  "geometry": {"coordinates":[-96.68287100000001,32.728098],"type":"Point"}
}