{
  "type": "Feature",
  "properties": {
    "iso:country":"US",
    "sg:address":"19747 Eastex Fwy",
    "sg:city":"Humble",
    "sg:classifiers":[
        {
            "category":"Insurance",
            "subcategory":"Insurance Agent",
            "type":"Services"
        }
    ],
    "sg:phone":"+1 281 446 2545",
    "sg:postcode":"77338",
    "sg:province":"TX",
    "wof:name":"Maxey Rk Insurance Agency",
    "wof:placetype":"venue"
},
  "geometry": {"coordinates":[-95.269318,30.003016],"type":"Point"}
}