{
  "type": "Feature",
  "properties": {
    "iso:country":"US",
    "sg:address":"2515 Plantation Ln",
    "sg:city":"Sugar Land",
    "sg:classifiers":[
        {
            "category":"Health Services",
            "subcategory":"Doctor",
            "type":"Services"
        }
    ],
    "sg:phone":"+1 281 494 3526",
    "sg:postcode":"77478",
    "sg:province":"TX",
    "sg:tags":[
        "medical"
    ],
    "wof:name":"Bryce R Mc Kee MD",
    "wof:placetype":"venue"
},
  "geometry": {"coordinates":[-95.59479399999999,29.618577],"type":"Point"}
}