{
  "type": "Feature",
  "properties": {
    "iso:country":"US",
    "sg:address":"5701 Woodway Dr Ste 330",
    "sg:city":"Houston",
    "sg:classifiers":[
        {
            "category":"Professional",
            "subcategory":"Lawyer & Legal Services",
            "type":"Services"
        }
    ],
    "sg:phone":"+1 713 974 6700",
    "sg:postcode":"77057",
    "sg:province":"TX",
    "wof:name":"King Ben R Atty",
    "wof:placetype":"venue"
},
  "geometry": {"coordinates":[-95.477997,29.7637],"type":"Point"}
}