{
  "type": "Feature",
  "properties": {
    "iso:country":"US",
    "sg:address":"11250 Taylor Draper Ln",
    "sg:city":"Austin",
    "sg:classifiers":[
        {
            "category":"Organizations",
            "subcategory":"Religious Organization",
            "type":"Services"
        }
    ],
    "sg:phone":"+1 512 970 3819",
    "sg:postcode":"78759",
    "sg:province":"TX",
    "wof:name":"Faith Austin Center Inc",
    "wof:placetype":"venue"
},
  "geometry": {"coordinates":[-97.747964,30.409944],"type":"Point"}
}