{
  "type": "Feature",
  "properties": {
    "iso:country":"US",
    "sg:address":"24 Grant Cir",
    "sg:city":"Richardson",
    "sg:classifiers":[
        {
            "category":"Organizations",
            "subcategory":"Religious Organization",
            "type":"Services"
        }
    ],
    "sg:phone":"+1 972 231 7755",
    "sg:postcode":"75081",
    "sg:province":"TX",
    "wof:name":"D Vine Ministries Intl",
    "wof:placetype":"venue"
},
  "geometry": {"coordinates":[-96.69311999999999,32.964715],"type":"Point"}
}