{
  "type": "Feature",
  "properties": {
    "iso:country":"US",
    "sg:address":"5416 Milwee St",
    "sg:city":"Houston",
    "sg:classifiers":[
        {
            "category":"Building & Trades",
            "subcategory":"Construction",
            "type":"Services"
        }
    ],
    "sg:phone":"+1 713 680 2630",
    "sg:postcode":"77092",
    "sg:province":"TX",
    "sg:tags":[
        "specializing",
        "residential",
        "rep",
        "commercial",
        "contractor"
    ],
    "wof:name":"B & M Construction Inc",
    "wof:placetype":"venue"
},
  "geometry": {"coordinates":[-95.469902,29.8225],"type":"Point"}
}