{
  "type": "Feature",
  "properties": {
    "iso:country":"US",
    "sg:address":"7630 Windmill Ln",
    "sg:city":"Garland",
    "sg:classifiers":[
        {
            "category":"Manufacturing",
            "subcategory":"Apparel",
            "type":"Manufacturing & Wholesale Goods"
        }
    ],
    "sg:phone":"+1 972 675 5352",
    "sg:postcode":"75044",
    "sg:province":"TX",
    "wof:name":"Made By Monica",
    "wof:placetype":"venue"
},
  "geometry": {"coordinates":[-96.675246,32.981873],"type":"Point"}
}