{
  "type": "Feature",
  "properties": {
    "iso:country":"US",
    "sg:address":"8427 Major Blizzard Dr",
    "sg:city":"Houston",
    "sg:classifiers":[
        {
            "category":"Personal",
            "subcategory":"Beauty Salon",
            "type":"Services"
        }
    ],
    "sg:phone":"+1 281 412 4275",
    "sg:postcode":"77089",
    "sg:province":"TX",
    "sg:tags":[
        "shop"
    ],
    "wof:name":"We Are World 24 Hour Child",
    "wof:placetype":"venue"
},
  "geometry": {"coordinates":[-95.248256,29.585509],"type":"Point"}
}