{
  "type": "Feature",
  "properties": {
    "iso:country":"US",
    "sg:address":"5416 Parkcrest Ste 800",
    "sg:city":"Austin",
    "sg:classifiers":[
        {
            "category":"Personal",
            "subcategory":"Hair Removal",
            "type":"Services"
        },
        {
            "category":"Personal",
            "subcategory":"Day Spa",
            "type":"Services"
        },
        {
            "category":"Personal",
            "subcategory":"Nail Salon",
            "type":"Services"
        },
        {
            "category":"Personal",
            "subcategory":"Tanning Parlor",
            "type":"Services"
        },
        {
            "category":"Personal",
            "subcategory":"Skin Care",
            "type":"Services"
        },
        {
            "category":"Personal",
            "subcategory":"Beauty Salon",
            "type":"Services"
        }
    ],
    "sg:phone":"+1 512 323 6015",
    "sg:postcode":"78731",
    "sg:province":"TX",
    "sg:tags":[
        "braiding",
        "stylist"
    ],
    "sg:website":"www.thomassaverio.com",
    "wof:name":"Thomas Saverio Salon & Spa",
    "wof:placetype":"venue"
},
  "geometry": {"coordinates":[-97.75869899999999,30.335733],"type":"Point"}
}