{
  "type": "Feature",
  "properties": {
    "iso:country":"US",
    "sg:address":"2656 S Loop Fwy",
    "sg:city":"Houston",
    "sg:classifiers":[
        {
            "category":"Education",
            "subcategory":"Special Training",
            "type":"Public Place"
        }
    ],
    "sg:phone":"+1 713 660 7700",
    "sg:postcode":"77054",
    "sg:province":"TX",
    "sg:tags":[
        "modeling",
        "school"
    ],
    "wof:name":"Glam Modeling Academy",
    "wof:placetype":"venue"
},
  "geometry": {"coordinates":[-95.419246,29.678119],"type":"Point"}
}