{
  "type": "Feature",
  "properties": {
    "iso:country":"US",
    "sg:address":"1711 US Hwy 79 N",
    "sg:city":"Henderson",
    "sg:classifiers":[
        {
            "category":"Manufacturing",
            "subcategory":"Printing",
            "type":"Manufacturing & Wholesale Goods"
        }
    ],
    "sg:phone":"+1 903 657 2501",
    "sg:postcode":"75652",
    "sg:province":"TX",
    "sg:tags":[
        "newspaper"
    ],
    "sg:website":"www.hendersondailynews.com",
    "wof:name":"Henderson Daily News",
    "wof:placetype":"venue"
},
  "geometry": {"coordinates":[-94.78419599999999,32.158652],"type":"Point"}
}