{
  "type": "Feature",
  "properties": {
    "iso:country":"US",
    "sg:address":"3004 S W S Young Dr",
    "sg:city":"Killeen",
    "sg:classifiers":[
        {
            "category":"Health Services",
            "subcategory":"Doctor",
            "type":"Services"
        }
    ],
    "sg:phone":"+1 254 634 7337",
    "sg:postcode":"76542",
    "sg:province":"TX",
    "sg:tags":[
        "physician",
        "family",
        "practice",
        "surgeons",
        "medicine",
        "surgeon"
    ],
    "sg:website":"www.abcpeds.org",
    "wof:name":"ABC Pediatrics",
    "wof:placetype":"venue"
},
  "geometry": {"coordinates":[-97.72178599999999,31.083117],"type":"Point"}
}