{
  "type": "Feature",
  "properties": {
    "iso:country":"US",
    "sg:address":"11303 Piney Point Cir",
    "sg:city":"Houston",
    "sg:classifiers":[
        {
            "category":"Real Estate",
            "subcategory":"Real Estate Agent",
            "type":"Services"
        }
    ],
    "sg:phone":"+1 713 278 8002",
    "sg:postcode":"77024",
    "sg:province":"TX",
    "wof:name":"Nichols Realty Investments I",
    "wof:placetype":"venue"
},
  "geometry": {"coordinates":[-95.517411,29.752683],"type":"Point"}
}