{
  "type": "Feature",
  "properties": {
    "iso:country":"US",
    "sg:address":"6923 San Pedro Ave",
    "sg:city":"San Antonio",
    "sg:classifiers":[
        {
            "category":"Travel",
            "subcategory":"Hotels & Motels",
            "type":"Entertainment"
        }
    ],
    "sg:phone":"+1 210 344 1698",
    "sg:postcode":"78216",
    "sg:province":"TX",
    "sg:tags":[
        "lodge",
        "operations"
    ],
    "wof:name":"Suburban Lodges San Antonio N",
    "wof:placetype":"venue"
},
  "geometry": {"coordinates":[-98.499348,29.506777],"type":"Point"}
}