{
  "type": "Feature",
  "properties": {
    "iso:country":"US",
    "sg:address":"3700 W 15th St",
    "sg:city":"Plano",
    "sg:classifiers":[
        {
            "category":"Health Services",
            "subcategory":"Health Practitioner",
            "type":"Services"
        }
    ],
    "sg:phone":"+1 972 964 7494",
    "sg:postcode":"75075",
    "sg:province":"TX",
    "sg:tags":[
        "pathologist",
        "speech"
    ],
    "wof:name":"In Home Speech & Language",
    "wof:placetype":"venue"
},
  "geometry": {"coordinates":[-96.765671,33.019242],"type":"Point"}
}