{
  "type": "Feature",
  "properties": {
    "iso:country":"US",
    "sg:address":"709 Saxon Trl",
    "sg:city":"Southlake",
    "sg:classifiers":[
        {
            "category":"Shopping",
            "subcategory":"Gifts & Souvenirs",
            "type":"Retail Goods"
        }
    ],
    "sg:phone":"+1 817 416 1172",
    "sg:postcode":"76092",
    "sg:province":"TX",
    "wof:name":"K Bad Creations",
    "wof:placetype":"venue"
},
  "geometry": {"coordinates":[-97.142318,32.934636],"type":"Point"}
}