{
  "type": "Feature",
  "properties": {
    "iso:country":"US",
    "sg:address":"100 Stadium Dr",
    "sg:city":"Georgetown",
    "sg:classifiers":[
        {
            "category":"Organizations",
            "subcategory":"Professional Association",
            "type":"Services"
        }
    ],
    "sg:phone":"+1 512 930 3535",
    "sg:postcode":"78626",
    "sg:province":"TX",
    "sg:tags":[
        "chamber",
        "commerce"
    ],
    "sg:website":"http://www.georgetownchamber.org",
    "wof:name":"Georgetown Chamber Of Commerce",
    "wof:placetype":"venue"
},
  "geometry": {"coordinates":[-97.67514,30.65094],"type":"Point"}
}