{
  "type": "Feature",
  "properties": {
    "iso:country":"US",
    "sg:address":"9911 Denton Dr",
    "sg:city":"Dallas",
    "sg:classifiers":[
        {
            "category":"Restaurant",
            "type":"Food & Drink"
        }
    ],
    "sg:phone":"+1 214 351 9122",
    "sg:postcode":"75220",
    "sg:province":"TX",
    "wof:name":"Noches Latinas",
    "wof:placetype":"venue"
},
  "geometry": {"coordinates":[-96.87772699999999,32.856684],"type":"Point"}
}