{
  "type": "Feature",
  "properties": {
    "iso:country":"US",
    "sg:address":"806 Barkley Dr",
    "sg:city":"Hamilton",
    "sg:classifiers":[
        {
            "category":"Professional",
            "subcategory":"Computer Services",
            "type":"Services"
        }
    ],
    "sg:phone":"+1 254 386 5809",
    "sg:postcode":"76531",
    "sg:province":"TX",
    "sg:tags":[
        "related"
    ],
    "wof:name":"DSigns By DAnn",
    "wof:placetype":"venue"
},
  "geometry": {"coordinates":[-98.112127,31.69304],"type":"Point"}
}