{
  "type": "Feature",
  "properties": {
    "iso:country":"US",
    "sg:address":"4712 Langley Rd",
    "sg:city":"Houston",
    "sg:classifiers":[
        {
            "category":"Personal",
            "subcategory":"Beauty Salon",
            "type":"Services"
        }
    ],
    "sg:phone":"+1 713 697 5598",
    "sg:postcode":"77093",
    "sg:province":"TX",
    "sg:tags":[
        "shop"
    ],
    "wof:name":"Betty Maries Beauty Shop",
    "wof:placetype":"venue"
},
  "geometry": {"coordinates":[-95.321376,29.866554],"type":"Point"}
}