{
  "type": "Feature",
  "properties": {
    "iso:country":"US",
    "sg:address":"431 Electra Dr",
    "sg:city":"Houston",
    "sg:classifiers":[
        {
            "category":"Mining & Drilling",
            "type":"Manufacturing & Wholesale Goods"
        }
    ],
    "sg:phone":"+1 713 461 9886",
    "sg:postcode":"77024",
    "sg:province":"TX",
    "sg:tags":[
        "exploration"
    ],
    "wof:name":"Weaver Oil & Gas Corp Aus",
    "wof:placetype":"venue"
},
  "geometry": {"coordinates":[-95.56596399999999,29.769994],"type":"Point"}
}