{
  "type": "Feature",
  "properties": {
    "iso:country":"US",
    "sg:address":"13610 Bluffcircle",
    "sg:city":"San Antonio",
    "sg:classifiers":[
        {
            "category":"Professional",
            "subcategory":"Management & Consulting",
            "type":"Services"
        }
    ],
    "sg:phone":"+1 210 344 0211",
    "sg:postcode":"78216",
    "sg:province":"TX",
    "sg:tags":[
        "consultant",
        "business"
    ],
    "wof:name":"James Barko & Assoc Inc",
    "wof:placetype":"venue"
},
  "geometry": {"coordinates":[-98.500604,29.565724],"type":"Point"}
}