{
  "type": "Feature",
  "properties": {
    "iso:country":"US",
    "sg:address":"345 N Alister St",
    "sg:city":"Port Aransas",
    "sg:classifiers":[
        {
            "category":"Shopping",
            "subcategory":"Clothing, Apparel, & Fashions",
            "type":"Retail Goods"
        }
    ],
    "sg:phone":"+1 361 749 7570",
    "sg:postcode":"78373",
    "sg:province":"TX",
    "wof:name":"Island Woman",
    "wof:placetype":"venue"
},
  "geometry": {"coordinates":[-97.061222,27.835397],"type":"Point"}
}