{
  "type": "Feature",
  "properties": {
    "iso:country":"US",
    "sg:address":"604 Doug Russell Rd",
    "sg:city":"Arlington",
    "sg:classifiers":[
        {
            "category":"Banks & Credit Unions",
            "subcategory":"Investment Brokerage",
            "type":"Services"
        },
        {
            "category":"Professional",
            "subcategory":"Management & Consulting",
            "type":"Services"
        }
    ],
    "sg:phone":"+1 817 261 6287",
    "sg:postcode":"76010",
    "sg:province":"TX",
    "sg:tags":[
        "advisory",
        "financial"
    ],
    "wof:name":"Pnk Financial Group America",
    "wof:placetype":"venue"
},
  "geometry": {"coordinates":[-97.11456099999999,32.725186],"type":"Point"}
}