{
  "type": "Feature",
  "properties": {
    "iso:country":"US",
    "sg:address":"6315 N McDonald St",
    "sg:city":"Mc Kinney",
    "sg:classifiers":[
        {
            "category":"Freight",
            "type":"Transportation"
        }
    ],
    "sg:phone":"+1 972 547 6677",
    "sg:postcode":"75069",
    "sg:province":"TX",
    "sg:tags":[
        "commercial",
        "storage"
    ],
    "wof:name":"Stor-All Self Storage",
    "wof:placetype":"venue"
},
  "geometry": {"coordinates":[-96.589114,33.265987],"type":"Point"}
}