{
  "type": "Feature",
  "properties": {
    "iso:country":"US",
    "sg:address":"17514 Cypress Glen St",
    "sg:city":"Cypress",
    "sg:classifiers":[
        {
            "category":"Professional",
            "type":"Services"
        }
    ],
    "sg:phone":"+1 281 351 4226",
    "sg:postcode":"77429",
    "sg:province":"TX",
    "wof:name":"Orion Endeavors Inc",
    "wof:placetype":"venue"
},
  "geometry": {"coordinates":[-95.688388,30.017004],"type":"Point"}
}