{
  "type": "Feature",
  "properties": {
    "iso:country":"US",
    "sg:address":"1205 N Carrier Pkwy",
    "sg:city":"Grand Prairie",
    "sg:classifiers":[
        {
            "category":"Wholesale",
            "subcategory":"Furniture",
            "type":"Manufacturing & Wholesale Goods"
        }
    ],
    "sg:phone":"+1 972 975 2808",
    "sg:postcode":"75050",
    "sg:province":"TX",
    "wof:name":"Clayton Installation Resources",
    "wof:placetype":"venue"
},
  "geometry": {"coordinates":[-97.020009,32.758225],"type":"Point"}
}