{
  "type": "Feature",
  "properties": {
    "iso:country":"US",
    "sg:address":"14060 Co Rd 945",
    "sg:city":"Rockwall",
    "sg:classifiers":[
        {
            "category":"Professional",
            "subcategory":"Computer Services",
            "type":"Services"
        }
    ],
    "sg:phone":"+1 972 722 1772",
    "sg:postcode":"75087",
    "sg:province":"TX",
    "sg:tags":[
        "internet"
    ],
    "sg:website":"www.rockwall.net",
    "wof:name":"Rockwall Net",
    "wof:placetype":"venue"
},
  "geometry": {"coordinates":[-96.469922,32.99435],"type":"Point"}
}