{
  "type": "Feature",
  "properties": {
    "iso:country":"US",
    "sg:address":"209 Flecha Ln",
    "sg:city":"Laredo",
    "sg:classifiers":[
        {
            "category":"Professional",
            "subcategory":"Management & Consulting",
            "type":"Services"
        }
    ],
    "sg:phone":"+1 956 726 6363",
    "sg:postcode":"78045",
    "sg:province":"TX",
    "sg:tags":[
        "consultant",
        "business"
    ],
    "wof:name":"Solstice Intl",
    "wof:placetype":"venue"
},
  "geometry": {"coordinates":[-99.52227600000001,27.577106],"type":"Point"}
}