{
  "type": "Feature",
  "properties": {
    "iso:country":"US",
    "sg:address":"3802 Esters Rd",
    "sg:city":"Irving",
    "sg:classifiers":[
        {
            "category":"Shopping",
            "subcategory":"Gifts & Souvenirs",
            "type":"Retail Goods"
        }
    ],
    "sg:phone":"+1 972 255 8305",
    "sg:postcode":"75038",
    "sg:province":"TX",
    "wof:name":"Perfect 10 Entertainment",
    "wof:placetype":"venue"
},
  "geometry": {"coordinates":[-97.00784899999999,32.858523],"type":"Point"}
}