{
  "type": "Feature",
  "properties": {
    "iso:country":"US",
    "sg:address":"913 Lum Ave",
    "sg:city":"Corpus Christi",
    "sg:classifiers":[
        {
            "category":"Building & Trades",
            "subcategory":"Plumbing",
            "type":"Services"
        }
    ],
    "sg:phone":"+1 361 986 0779",
    "sg:postcode":"78412",
    "sg:province":"TX",
    "sg:tags":[
        "plumbing",
        "contractor"
    ],
    "wof:name":"ASAP Plumbing",
    "wof:placetype":"venue"
},
  "geometry": {"coordinates":[-97.363812,27.716775],"type":"Point"}
}