{
  "type": "Feature",
  "properties": {
    "iso:country":"US",
    "sg:address":"604 W University Dr",
    "sg:city":"Denton",
    "sg:classifiers":[
        {
            "category":"Retail",
            "subcategory":"Car Wash",
            "type":"Services"
        }
    ],
    "sg:phone":"+1 940 565 0395",
    "sg:postcode":"76201",
    "sg:province":"TX",
    "sg:tags":[
        "carwash"
    ],
    "wof:name":"Wash N Go",
    "wof:placetype":"venue"
},
  "geometry": {"coordinates":[-97.137676,33.230983],"type":"Point"}
}