{
  "type": "Feature",
  "properties": {
    "iso:country":"US",
    "sg:address":"6025 Portridge Dr",
    "sg:city":"Fort Worth",
    "sg:classifiers":[
        {
            "category":"Professional",
            "type":"Services"
        }
    ],
    "sg:phone":"+1 817 238 8163",
    "sg:postcode":"76135",
    "sg:province":"TX",
    "wof:name":"Richard Ringstaff Etux Da",
    "wof:placetype":"venue"
},
  "geometry": {"coordinates":[-97.419174,32.828354],"type":"Point"}
}