{
  "type": "Feature",
  "properties": {
    "iso:country":"US",
    "sg:address":"3107 Mustang Dr",
    "sg:city":"Grapevine",
    "sg:classifiers":[
        {
            "category":"Home & Garden",
            "subcategory":"Building Materials",
            "type":"Retail Goods"
        }
    ],
    "sg:phone":"+1 817 722 8400",
    "sg:postcode":"76051",
    "sg:province":"TX",
    "sg:tags":[
        "door"
    ],
    "wof:name":"Glen Catlett",
    "wof:placetype":"venue"
},
  "geometry": {"coordinates":[-97.11530999999999,32.918937],"type":"Point"}
}