{
  "type": "Feature",
  "properties": {
    "iso:country":"US",
    "sg:address":"6812 Poss Rd",
    "sg:city":"San Antonio",
    "sg:classifiers":[
        {
            "category":"Real Estate",
            "subcategory":"Real Estate Operator",
            "type":"Services"
        }
    ],
    "sg:phone":"+1 210 684 3171",
    "sg:postcode":"78238",
    "sg:province":"TX",
    "sg:tags":[
        "apartment"
    ],
    "wof:name":"Leon Trace Apartments",
    "wof:placetype":"venue"
},
  "geometry": {"coordinates":[-98.61882199999999,29.497444],"type":"Point"}
}