{
  "type": "Feature",
  "properties": {
    "iso:country":"US",
    "sg:address":"201 W Main Dr",
    "sg:city":"El Paso",
    "sg:classifiers":[
        {
            "category":"Insurance",
            "subcategory":"Insurance Agent",
            "type":"Services"
        }
    ],
    "sg:phone":"+1 915 534 3200",
    "sg:postcode":"79901",
    "sg:province":"TX",
    "wof:name":"New York Life Insurance Co",
    "wof:placetype":"venue"
},
  "geometry": {"coordinates":[-106.49101,31.758637],"type":"Point"}
}