{
  "type": "Feature",
  "properties": {
    "iso:country":"US",
    "sg:address":"16953 Wilson Rd",
    "sg:city":"Tyler",
    "sg:classifiers":[
        {
            "category":"Building & Trades",
            "subcategory":"Landscaping Services",
            "type":"Services"
        }
    ],
    "sg:phone":"+1 903 566 6861",
    "sg:postcode":"75707",
    "sg:province":"TX",
    "sg:tags":[
        "lawn"
    ],
    "wof:name":"Richards Landscaping Service",
    "wof:placetype":"venue"
},
  "geometry": {"coordinates":[-95.126034,32.24911],"type":"Point"}
}