{
  "type": "Feature",
  "properties": {
    "iso:country":"US",
    "sg:address":"3202 Mallards Pond St",
    "sg:city":"Garland",
    "sg:classifiers":[
        {
            "category":"Professional",
            "type":"Services"
        }
    ],
    "sg:phone":"+1 972 463 0664",
    "sg:postcode":"75043",
    "sg:province":"TX",
    "wof:name":"Snap-On Tools",
    "wof:placetype":"venue"
},
  "geometry": {"coordinates":[-96.596526,32.877835],"type":"Point"}
}