{
  "type": "Feature",
  "properties": {
    "iso:country":"US",
    "sg:address":"1000 Irene St",
    "sg:city":"Seagoville",
    "sg:classifiers":[
        {
            "category":"Wholesale",
            "subcategory":"Vending Machines",
            "type":"Manufacturing & Wholesale Goods"
        }
    ],
    "sg:phone":"+1 972 287 1038",
    "sg:postcode":"75159",
    "sg:province":"TX",
    "sg:tags":[
        "operator"
    ],
    "wof:name":"Campbell Vending",
    "wof:placetype":"venue"
},
  "geometry": {"coordinates":[-96.53111,32.623074],"type":"Point"}
}