{
  "type": "Feature",
  "properties": {
    "iso:country":"US",
    "sg:address":"1495 S Peachtree Rd",
    "sg:city":"Mesquite",
    "sg:classifiers":[
        {
            "category":"Manufacturing",
            "subcategory":"Food",
            "type":"Manufacturing & Wholesale Goods"
        },
        {
            "category":"Food & Beverages",
            "subcategory":"Groceries & Convenience Stores",
            "type":"Retail Goods"
        }
    ],
    "sg:phone":"+1 972 288 8283",
    "sg:postcode":"75180",
    "sg:province":"TX",
    "sg:tags":[
        "product"
    ],
    "wof:name":"Big 5 Food Store",
    "wof:placetype":"venue"
},
  "geometry": {"coordinates":[-96.63387299999999,32.693409],"type":"Point"}
}