{
  "type": "Feature",
  "properties": {
    "iso:country":"US",
    "sg:address":"108 Redbud St",
    "sg:city":"Pittsburg",
    "sg:classifiers":[
        {
            "category":"Professional",
            "type":"Services"
        }
    ],
    "sg:phone":"+1 903 855 0292",
    "sg:postcode":"75686",
    "sg:province":"TX",
    "wof:name":"Stanleys Service Co",
    "wof:placetype":"venue"
},
  "geometry": {"coordinates":[-94.94102100000001,33.002996],"type":"Point"}
}