{
  "type": "Feature",
  "properties": {
    "iso:country":"US",
    "sg:address":"14707 Hermes Dr",
    "sg:city":"Selma",
    "sg:classifiers":[
        {
            "category":"Wholesale",
            "subcategory":"Jewelry",
            "type":"Manufacturing & Wholesale Goods"
        },
        {
            "category":"Shopping",
            "subcategory":"Crafts & Fabrics",
            "type":"Retail Goods"
        }
    ],
    "sg:phone":"+1 210 658 2341",
    "sg:postcode":"78154",
    "sg:province":"TX",
    "sg:tags":[
        "bead",
        "beads-wholesale",
        "manufacturer"
    ],
    "wof:name":"Bonnie's Designs",
    "wof:placetype":"venue"
},
  "geometry": {"coordinates":[-98.31717,29.573156],"type":"Point"}
}