{
  "type": "Feature",
  "properties": {
    "iso:country":"US",
    "sg:address":"230 N Texas Ave",
    "sg:city":"Mercedes",
    "sg:classifiers":[
        {
            "category":"Food & Beverages",
            "subcategory":"Bakery",
            "type":"Retail Goods"
        }
    ],
    "sg:phone":"+1 956 825 9911",
    "sg:postcode":"78570",
    "sg:province":"TX",
    "wof:name":"Dela Garza Bakery",
    "wof:placetype":"venue"
},
  "geometry": {"coordinates":[-97.913607,26.154153],"type":"Point"}
}