{
  "type": "Feature",
  "properties": {
    "iso:country":"US",
    "sg:address":"9520 FM 1097 W",
    "sg:city":"Willis",
    "sg:classifiers":[
        {
            "category":"Insurance",
            "subcategory":"Insurance Agent",
            "type":"Services"
        }
    ],
    "sg:phone":"+1 936 228 0377",
    "sg:postcode":"77318",
    "sg:province":"TX",
    "wof:name":"David Mercer Insurance",
    "wof:placetype":"venue"
},
  "geometry": {"coordinates":[-95.49484200000001,30.420633],"type":"Point"}
}