{
  "type": "Feature",
  "properties": {
    "iso:country":"US",
    "sg:address":"1621 Collingsworth St",
    "sg:city":"Houston",
    "sg:classifiers":[
        {
            "category":"Autos & Motor Vehicles",
            "subcategory":"Fuel & Gas Station",
            "type":"Retail Goods"
        }
    ],
    "sg:phone":"+1 713 223 8911",
    "sg:postcode":"77009",
    "sg:province":"TX",
    "sg:tags":[
        "convenience",
        "gasoline",
        "store"
    ],
    "wof:name":"Chevron",
    "wof:placetype":"venue"
},
  "geometry": {"coordinates":[-95.351339,29.793305],"type":"Point"}
}