{
  "type": "Feature",
  "properties": {
    "iso:country":"US",
    "sg:address":"318 W Magnolia Ave",
    "sg:city":"San Antonio",
    "sg:classifiers":[
        {
            "category":"Professional",
            "subcategory":"Accounting & Tax Preparation",
            "type":"Services"
        }
    ],
    "sg:phone":"+1 210 732 1313",
    "sg:postcode":"78212",
    "sg:province":"TX",
    "sg:tags":[
        "prepackaged",
        "accountant",
        "se",
        "software"
    ],
    "wof:name":"Vincent Beaullieu CPA",
    "wof:placetype":"venue"
},
  "geometry": {"coordinates":[-98.498992,29.454751],"type":"Point"}
}