{
  "type": "Feature",
  "properties": {
    "iso:country":"US",
    "sg:address":"4606 Willow St",
    "sg:city":"Bellaire",
    "sg:classifiers":[
        {
            "category":"Manufacturing",
            "subcategory":"Chemicals & Compounds",
            "type":"Manufacturing & Wholesale Goods"
        }
    ],
    "sg:phone":"+1 713 838 0137",
    "sg:postcode":"77401",
    "sg:province":"TX",
    "sg:tags":[
        "preparation",
        "pharmaceutical",
        "mfg"
    ],
    "wof:name":"Synthrx Inc",
    "wof:placetype":"venue"
},
  "geometry": {"coordinates":[-95.45853099999999,29.702692],"type":"Point"}
}