{
  "type": "Feature",
  "properties": {
    "iso:country":"US",
    "sg:address":"18502 Skippers Helm",
    "sg:city":"Humble",
    "sg:classifiers":[
        {
            "category":"Sports & Exercise",
            "subcategory":"Sports Center",
            "type":"Entertainment"
        }
    ],
    "sg:phone":"+1 281 852 8782",
    "sg:postcode":"77346",
    "sg:province":"TX",
    "sg:tags":[
        "manager",
        "promoter"
    ],
    "wof:name":"Boston Sports Enterprises Inc",
    "wof:placetype":"venue"
},
  "geometry": {"coordinates":[-95.142411,29.985575],"type":"Point"}
}