{
  "type": "Feature",
  "properties": {
    "iso:country":"US",
    "sg:address":"2637 Halsey St",
    "sg:city":"Corpus Christi",
    "sg:classifiers":[
        {
            "category":"Building & Trades",
            "subcategory":"Construction",
            "type":"Services"
        }
    ],
    "sg:phone":"+1 361 883 9955",
    "sg:postcode":"78405",
    "sg:province":"TX",
    "sg:tags":[
        "excavation",
        "contractor"
    ],
    "wof:name":"J R Gatica & Sons Backhoe Svc",
    "wof:placetype":"venue"
},
  "geometry": {"coordinates":[-97.42224299999999,27.769177],"type":"Point"}
}