{
  "type": "Feature",
  "properties": {
    "iso:country":"US",
    "sg:address":"1820 Co Rd 222",
    "sg:city":"Tow",
    "sg:classifiers":[
        {
            "category":"Manufacturing",
            "subcategory":"Food",
            "type":"Manufacturing & Wholesale Goods"
        }
    ],
    "sg:phone":"+1 325 379 5361",
    "sg:postcode":"78672",
    "sg:province":"TX",
    "sg:tags":[
        "winery"
    ],
    "sg:website":"www.fcv.com",
    "wof:name":"Fall Creek Vineyards",
    "wof:placetype":"venue"
},
  "geometry": {"coordinates":[-98.45711799999999,30.902049],"type":"Point"}
}