{
  "type": "Feature",
  "properties": {
    "iso:country":"US",
    "sg:address":"3922 Little York Rd",
    "sg:city":"Houston",
    "sg:classifiers":[
        {
            "category":"Restaurant",
            "type":"Food & Drink"
        }
    ],
    "sg:phone":"+1 713 694 4192",
    "sg:postcode":"77093",
    "sg:province":"TX",
    "sg:tags":[
        "mexican"
    ],
    "wof:name":"Taco Cabana Two",
    "wof:placetype":"venue"
},
  "geometry": {"coordinates":[-95.328985,29.869699],"type":"Point"}
}