{
  "type": "Feature",
  "properties": {
    "iso:country":"US",
    "sg:address":"1425 Adkins Rd",
    "sg:city":"Houston",
    "sg:classifiers":[
        {
            "category":"Manufacturing",
            "subcategory":"Paper Products",
            "type":"Manufacturing & Wholesale Goods"
        }
    ],
    "sg:phone":"+1 713 467 7427",
    "sg:postcode":"77055",
    "sg:province":"TX",
    "sg:tags":[
        "mill"
    ],
    "wof:name":"Mother & Daughter Crafts",
    "wof:placetype":"venue"
},
  "geometry": {"coordinates":[-95.52039000000001,29.793968],"type":"Point"}
}