{
  "type": "Feature",
  "properties": {
    "iso:country":"US",
    "sg:address":"10455 N Central Expy",
    "sg:city":"Dallas",
    "sg:classifiers":[
        {
            "category":"Professional",
            "subcategory":"Business Services",
            "type":"Services"
        }
    ],
    "sg:phone":"+1 214 361 7353",
    "sg:postcode":"75231",
    "sg:province":"TX",
    "sg:tags":[
        "packaging",
        "labeling"
    ],
    "wof:name":"UPS Stores The",
    "wof:placetype":"venue"
},
  "geometry": {"coordinates":[-96.770321,32.88798],"type":"Point"}
}