{
  "type": "Feature",
  "properties": {
    "iso:country":"US",
    "sg:address":"5802 S Staples St",
    "sg:city":"Corpus Christi",
    "sg:classifiers":[
        {
            "category":"Restaurant",
            "type":"Food & Drink"
        }
    ],
    "sg:phone":"+1 361 993 0251",
    "sg:postcode":"78413",
    "sg:province":"TX",
    "sg:tags":[
        "eating"
    ],
    "wof:name":"Andy's Kitchen",
    "wof:placetype":"venue"
},
  "geometry": {"coordinates":[-97.37711400000001,27.696208],"type":"Point"}
}