{
  "type": "Feature",
  "properties": {
    "iso:country":"US",
    "sg:address":"1797 George Dieter Dr",
    "sg:city":"El Paso",
    "sg:classifiers":[
        {
            "category":"Food & Beverages",
            "subcategory":"Groceries & Convenience Stores",
            "type":"Retail Goods"
        }
    ],
    "sg:phone":"+1 915 594 1832",
    "sg:postcode":"79936",
    "sg:province":"TX",
    "wof:name":"7-Eleven",
    "wof:placetype":"venue"
},
  "geometry": {"coordinates":[-106.302121,31.763745],"type":"Point"}
}