{
  "type": "Feature",
  "properties": {
    "iso:country":"US",
    "sg:address":"3105 W University Dr",
    "sg:city":"Edinburg",
    "sg:classifiers":[
        {
            "category":"Government",
            "subcategory":"Office",
            "type":"Public Place"
        }
    ],
    "sg:phone":"+1 956 381 4632",
    "sg:postcode":"78539",
    "sg:province":"TX",
    "sg:tags":[
        "county",
        "resource"
    ],
    "wof:name":"Hidalgo County Wic Program",
    "wof:placetype":"venue"
},
  "geometry": {"coordinates":[-98.185996,26.304886],"type":"Point"}
}