{
  "type": "Feature",
  "properties": {
    "iso:country":"US",
    "sg:address":"19 Devon Wood",
    "sg:city":"San Antonio",
    "sg:classifiers":[
        {
            "category":"Travel",
            "subcategory":"Campground",
            "type":"Entertainment"
        }
    ],
    "sg:phone":"+1 210 698 3816",
    "sg:postcode":"78257",
    "sg:province":"TX",
    "sg:tags":[
        "camp"
    ],
    "wof:name":"Alpine Lakes Ranch Inc",
    "wof:placetype":"venue"
},
  "geometry": {"coordinates":[-98.61183200000001,29.661461],"type":"Point"}
}