{
  "type": "Feature",
  "properties": {
    "iso:country":"US",
    "sg:address":"8315 Nyad Ln",
    "sg:city":"Humble",
    "sg:classifiers":[
        {
            "category":"Professional",
            "subcategory":"Business Services",
            "type":"Services"
        }
    ],
    "sg:phone":"+1 281 812 3019",
    "sg:postcode":"77346",
    "sg:province":"TX",
    "wof:name":"Artful Interiors",
    "wof:placetype":"venue"
},
  "geometry": {"coordinates":[-95.154268,29.992792],"type":"Point"}
}