{
  "type": "Feature",
  "properties": {
    "iso:country":"US",
    "sg:address":"811 I- 20 W",
    "sg:city":"Arlington",
    "sg:classifiers":[
        {
            "category":"Health Services",
            "subcategory":"Doctor",
            "type":"Services"
        }
    ],
    "sg:phone":"+1 817 468 3393",
    "sg:postcode":"76017",
    "sg:province":"TX",
    "sg:tags":[
        "physician",
        "surgeon"
    ],
    "sg:website":"www.mcnet.com",
    "wof:name":"Medical Clinic-North Texas",
    "wof:placetype":"venue"
},
  "geometry": {"coordinates":[-97.119164,32.678689],"type":"Point"}
}