{
  "type": "Feature",
  "properties": {
    "iso:country":"US",
    "sg:address":"1622 Festival Dr",
    "sg:city":"Houston",
    "sg:classifiers":[
        {
            "category":"Professional",
            "subcategory":"Management & Consulting",
            "type":"Services"
        }
    ],
    "sg:phone":"+1 281 450 6525",
    "sg:postcode":"77062",
    "sg:province":"TX",
    "sg:tags":[
        "business"
    ],
    "wof:name":"American Quality Services",
    "wof:placetype":"venue"
},
  "geometry": {"coordinates":[-95.12171499999999,29.575703],"type":"Point"}
}