{
  "type": "Feature",
  "properties": {
    "iso:country":"US",
    "sg:address":"10646 Goodnight Ln",
    "sg:city":"Dallas",
    "sg:classifiers":[
        {
            "category":"Manufacturing",
            "subcategory":"Metals",
            "type":"Manufacturing & Wholesale Goods"
        }
    ],
    "sg:phone":"+1 972 556 0101",
    "sg:postcode":"75220",
    "sg:province":"TX",
    "sg:tags":[
        "product",
        "sheet",
        "name",
        "mfg",
        "spray",
        "painting"
    ],
    "wof:name":"National Spray Painters",
    "wof:placetype":"venue"
},
  "geometry": {"coordinates":[-96.902314,32.86788],"type":"Point"}
}