{
  "type": "Feature",
  "properties": {
    "iso:country":"US",
    "sg:address":"11150 Research Blvd Ste 201",
    "sg:city":"Austin",
    "sg:classifiers":[
        {
            "category":"Restaurant",
            "type":"Food & Drink"
        }
    ],
    "sg:phone":"+1 512 345 9781",
    "sg:postcode":"78759",
    "sg:province":"TX",
    "sg:tags":[
        "chinese"
    ],
    "sg:website":"hwayuan.tripod.com/",
    "wof:name":"Hwa Yuan Chinese Restaurant",
    "wof:placetype":"venue"
},
  "geometry": {"coordinates":[-97.746773,30.406807],"type":"Point"}
}