{
  "type": "Feature",
  "properties": {
    "iso:country":"US",
    "sg:address":"4301 San Bernardo Ave",
    "sg:city":"Laredo",
    "sg:classifiers":[
        {
            "category":"Shopping",
            "subcategory":"Used Merchandise",
            "type":"Retail Goods"
        }
    ],
    "sg:phone":"+1 956 722 1019",
    "sg:postcode":"78041",
    "sg:province":"TX",
    "wof:name":"Pronto Pawn",
    "wof:placetype":"venue"
},
  "geometry": {"coordinates":[-99.504336,27.539165],"type":"Point"}
}