{
  "type": "Feature",
  "properties": {
    "iso:country":"US",
    "sg:address":"9043 Onate Way",
    "sg:city":"El Paso",
    "sg:classifiers":[
        {
            "category":"Building & Trades",
            "subcategory":"Plumbing",
            "type":"Services"
        }
    ],
    "sg:phone":"+1 915 858 0338",
    "sg:postcode":"79907",
    "sg:province":"TX",
    "sg:tags":[
        "sheet",
        "work",
        "metal",
        "contractor"
    ],
    "wof:name":"Mor Sheet Metal Inc",
    "wof:placetype":"venue"
},
  "geometry": {"coordinates":[-106.323942,31.696451],"type":"Point"}
}