{
  "type": "Feature",
  "properties": {
    "iso:country":"US",
    "sg:address":"16 Cedar Pl",
    "sg:city":"New Caney",
    "sg:classifiers":[
        {
            "category":"Building & Trades",
            "subcategory":"Construction",
            "type":"Services"
        }
    ],
    "sg:phone":"+1 281 399 1238",
    "sg:postcode":"77357",
    "sg:province":"TX",
    "sg:tags":[
        "roofing",
        "contractor"
    ],
    "wof:name":"Trahan Roofing & Remodeling",
    "wof:placetype":"venue"
},
  "geometry": {"coordinates":[-95.083978,30.1423],"type":"Point"}
}