{
  "type": "Feature",
  "properties": {
    "iso:country":"US",
    "sg:address":"1606 S Siesta Ln",
    "sg:city":"Zapata",
    "sg:classifiers":[
        {
            "category":"Real Estate",
            "subcategory":"Real Estate Agent",
            "type":"Services"
        }
    ],
    "sg:phone":"+1 956 765 6211",
    "sg:postcode":"78076",
    "sg:province":"TX",
    "wof:name":"Oval Realty",
    "wof:placetype":"venue"
},
  "geometry": {"coordinates":[-99.245046,26.860518],"type":"Point"}
}