{
  "type": "Feature",
  "properties": {
    "iso:country":"US",
    "sg:address":"1101 Early Blvd",
    "sg:city":"Brownwood",
    "sg:classifiers":[
        {
            "category":"Shopping",
            "subcategory":"Used Merchandise",
            "type":"Retail Goods"
        }
    ],
    "sg:phone":"+1 325 646 9503",
    "sg:postcode":"76802",
    "sg:province":"TX",
    "sg:tags":[
        "antique"
    ],
    "wof:name":"Mary's Antiques",
    "wof:placetype":"venue"
},
  "geometry": {"coordinates":[-98.93077700000001,31.748379],"type":"Point"}
}