{
  "type": "Feature",
  "properties": {
    "iso:country":"US",
    "sg:address":"7618 Virginia Water Ln",
    "sg:city":"Houston",
    "sg:classifiers":[
        {
            "category":"Building & Trades",
            "subcategory":"Construction",
            "type":"Services"
        }
    ],
    "sg:phone":"+1 281 855 9998",
    "sg:postcode":"77095",
    "sg:province":"TX",
    "sg:tags":[
        "concrete",
        "contractor"
    ],
    "wof:name":"CST Concrete Services Texas",
    "wof:placetype":"venue"
},
  "geometry": {"coordinates":[-95.62305000000001,29.888063],"type":"Point"}
}