{
  "type": "Feature",
  "properties": {
    "iso:country":"US",
    "sg:address":"3711 Hatcher St",
    "sg:city":"Dallas",
    "sg:classifiers":[
        {
            "category":"Retail",
            "subcategory":"Auto Repair",
            "type":"Services"
        }
    ],
    "sg:phone":"+1 214 421 0978",
    "sg:postcode":"75210",
    "sg:province":"TX",
    "sg:tags":[
        "general"
    ],
    "wof:name":"Greens Garage",
    "wof:placetype":"venue"
},
  "geometry": {"coordinates":[-96.74319199999999,32.764283],"type":"Point"}
}