{
  "type": "Feature",
  "properties": {
    "iso:country":"US",
    "sg:address":"114 S George St",
    "sg:city":"Victoria",
    "sg:classifiers":[
        {
            "category":"Building & Trades",
            "subcategory":"Construction",
            "type":"Services"
        }
    ],
    "sg:phone":"+1 361 573 7270",
    "sg:postcode":"77901",
    "sg:province":"TX",
    "sg:tags":[
        "hanging",
        "contractor"
    ],
    "wof:name":"Mingos Painting & Wlpr Svc",
    "wof:placetype":"venue"
},
  "geometry": {"coordinates":[-96.995745,28.795501],"type":"Point"}
}