{
  "type": "Feature",
  "properties": {
    "iso:country":"US",
    "sg:address":"5704 Zachary Scott St",
    "sg:city":"Austin",
    "sg:classifiers":[
        {
            "category":"Social Services",
            "type":"Services"
        },
        {
            "category":"Professional",
            "subcategory":"Employment Agencies",
            "type":"Services"
        }
    ],
    "sg:phone":"+1 512 358 6730",
    "sg:postcode":"78747",
    "sg:province":"TX",
    "sg:tags":[
        "workers'",
        "placement",
        "volunteer"
    ],
    "wof:name":"G & H Equitas Foundation",
    "wof:placetype":"venue"
},
  "geometry": {"coordinates":[-97.770292,30.139214],"type":"Point"}
}