{
  "type": "Feature",
  "properties": {
    "iso:country":"US",
    "sg:address":"13431 San Pedro Ave",
    "sg:city":"San Antonio",
    "sg:classifiers":[
        {
            "category":"Building & Trades",
            "subcategory":"Cleaning & Sanitation",
            "type":"Services"
        }
    ],
    "sg:phone":"+1 210 736 0163",
    "sg:postcode":"78216",
    "sg:province":"TX",
    "sg:tags":[
        "maintenance"
    ],
    "wof:name":"Artios Window Cleaning & Sup",
    "wof:placetype":"venue"
},
  "geometry": {"coordinates":[-98.483231,29.563822],"type":"Point"}
}