{
  "type": "Feature",
  "properties": {
    "iso:country":"US",
    "sg:address":"5021 Broadway",
    "sg:city":"San Antonio",
    "sg:classifiers":[
        {
            "category":"Shopping",
            "subcategory":"Bicycles & Sporting Goods",
            "type":"Retail Goods"
        }
    ],
    "sg:phone":"+1 210 822 8405",
    "sg:postcode":"78209",
    "sg:province":"TX",
    "sg:tags":[
        "equipment",
        "skateboard"
    ],
    "wof:name":"Gravity Wake N Skate",
    "wof:placetype":"venue"
},
  "geometry": {"coordinates":[-98.46287599999999,29.472823],"type":"Point"}
}