{
  "type": "Feature",
  "properties": {
    "iso:country":"US",
    "sg:address":"855 Military Rd",
    "sg:city":"Brownsville",
    "sg:classifiers":[
        {
            "category":"Education",
            "subcategory":"School",
            "type":"Public Place"
        }
    ],
    "sg:phone":"+1 956 982 2630",
    "sg:postcode":"78520",
    "sg:province":"TX",
    "sg:tags":[
        "elementary"
    ],
    "wof:name":"Garden Park Elementary School",
    "wof:placetype":"venue"
},
  "geometry": {"coordinates":[-97.531367,25.934237],"type":"Point"}
}