{
  "type": "Feature",
  "properties": {
    "iso:country":"US",
    "sg:address":"4727 N Midkiff Rd",
    "sg:city":"Midland",
    "sg:classifiers":[
        {
            "category":"Restaurant",
            "type":"Food & Drink"
        }
    ],
    "sg:menulink":"http://www.allmenus.com/tx/midland/177165-kfc---kentucky-fried-chicken/menu/",
    "sg:phone":"+1 432 694 0503",
    "sg:postcode":"79705",
    "sg:province":"TX",
    "sg:tags":[
        "american",
        "chicken"
    ],
    "wof:name":"KFC - Kentucky Fried Chicken",
    "wof:placetype":"venue"
},
  "geometry": {"coordinates":[-102.129678,32.034525],"type":"Point"}
}