{
  "type": "Feature",
  "properties": {
    "iso:country":"US",
    "sg:address":"7213 Mcneil Dr",
    "sg:city":"Austin",
    "sg:classifiers":[
        {
            "category":"Building & Trades",
            "subcategory":"Construction",
            "type":"Services"
        },
        {
            "category":"Personal",
            "subcategory":"Day Spa",
            "type":"Services"
        }
    ],
    "sg:phone":"+1 512 335 5000",
    "sg:postcode":"78729",
    "sg:province":"TX",
    "sg:tags":[
        "hot",
        "tub",
        "pool",
        "swimming"
    ],
    "sg:website":"http://www.austexspas.com",
    "wof:name":"Austex Spas",
    "wof:placetype":"venue"
},
  "geometry": {"coordinates":[-97.76541899999999,30.43574],"type":"Point"}
}