{
  "type": "Feature",
  "properties": {
    "iso:country":"US",
    "sg:address":"13117 Halsell Dr",
    "sg:city":"Austin",
    "sg:classifiers":[
        {
            "category":"Professional",
            "type":"Services"
        }
    ],
    "sg:phone":"+1 512 266 0430",
    "sg:postcode":"78732",
    "sg:province":"TX",
    "wof:name":"Dorothy R Caldrer",
    "wof:placetype":"venue"
},
  "geometry": {"coordinates":[-97.89892999999999,30.380146],"type":"Point"}
}