{
  "type": "Feature",
  "properties": {
    "iso:country":"US",
    "sg:address":"4120 Dartmouth St",
    "sg:city":"Houston",
    "sg:classifiers":[
        {
            "category":"Shopping",
            "subcategory":"Used Merchandise",
            "type":"Retail Goods"
        }
    ],
    "sg:phone":"+1 713 661 6592",
    "sg:postcode":"77005",
    "sg:province":"TX",
    "wof:name":"Rose Cottage Antiques",
    "wof:placetype":"venue"
},
  "geometry": {"coordinates":[-95.444332,29.723221],"type":"Point"}
}