{
  "type": "Feature",
  "properties": {
    "iso:country":"US",
    "sg:address":"553 Pump Station Rd",
    "sg:city":"Karnack",
    "sg:classifiers":[
        {
            "category":"Government",
            "subcategory":"City Hall",
            "type":"Public Place"
        },
        {
            "category":"Government",
            "subcategory":"Office",
            "type":"Public Place"
        }
    ],
    "sg:phone":"+1 903 679 3265",
    "sg:postcode":"75661",
    "sg:province":"TX",
    "sg:tags":[
        "town",
        "township",
        "planner",
        "government-city",
        "village"
    ],
    "wof:name":"City Of Marshall",
    "wof:placetype":"venue"
},
  "geometry": {"coordinates":[-94.23568899999999,32.712288],"type":"Point"}
}