{
  "type": "Feature",
  "properties": {
    "iso:country":"US",
    "sg:address":"13724 Northwest Fwy",
    "sg:city":"Houston",
    "sg:classifiers":[
        {
            "category":"Personal",
            "subcategory":"Barber",
            "type":"Services"
        }
    ],
    "sg:phone":"+1 713 462 6740",
    "sg:postcode":"77040",
    "sg:province":"TX",
    "wof:name":"Sport Clips",
    "wof:placetype":"venue"
},
  "geometry": {"coordinates":[-95.51370199999999,29.854],"type":"Point"}
}