{
  "type": "Feature",
  "properties": {
    "iso:country":"US",
    "sg:address":"111 S Murphy Rd",
    "sg:city":"Murphy",
    "sg:classifiers":[
        {
            "category":"Insurance",
            "subcategory":"Insurance Agent",
            "type":"Services"
        }
    ],
    "sg:phone":"+1 972 633 9919",
    "sg:postcode":"75094",
    "sg:province":"TX",
    "wof:name":"State Farm Insurance",
    "wof:placetype":"venue"
},
  "geometry": {"coordinates":[-96.61309900000001,33.01018],"type":"Point"}
}