{
  "type": "Feature",
  "properties": {
    "iso:country":"US",
    "sg:address":"1013 Winding Creek Dr",
    "sg:city":"Cedar Hill",
    "sg:classifiers":[
        {
            "category":"Professional",
            "type":"Services"
        }
    ],
    "sg:phone":"+1 972 293 9719",
    "sg:postcode":"75104",
    "sg:province":"TX",
    "wof:name":"4 Star Events LLC",
    "wof:placetype":"venue"
},
  "geometry": {"coordinates":[-96.92168700000001,32.600484],"type":"Point"}
}