{
  "type": "Feature",
  "properties": {
    "iso:country":"US",
    "sg:address":"610 10th Ave N",
    "sg:city":"Texas City",
    "sg:classifiers":[
        {
            "category":"Real Estate",
            "subcategory":"Real Estate Operator",
            "type":"Services"
        }
    ],
    "sg:phone":"+1 409 945 0884",
    "sg:postcode":"77590",
    "sg:province":"TX",
    "sg:tags":[
        "building",
        "apartment"
    ],
    "wof:name":"10th Avenue Apartments",
    "wof:placetype":"venue"
},
  "geometry": {"coordinates":[-94.903114,29.394461],"type":"Point"}
}