{
  "type": "Feature",
  "properties": {
    "iso:country":"US",
    "sg:address":"500 S Velasco St",
    "sg:city":"Angleton",
    "sg:classifiers":[
        {
            "category":"Restaurant",
            "type":"Food & Drink"
        }
    ],
    "sg:phone":"+1 979 848 0084",
    "sg:postcode":"77515",
    "sg:province":"TX",
    "sg:tags":[
        "eating"
    ],
    "wof:name":"ME Maws Kitchen",
    "wof:placetype":"venue"
},
  "geometry": {"coordinates":[-95.431528,29.160369],"type":"Point"}
}