{
  "type": "Feature",
  "properties": {
    "iso:country":"US",
    "sg:address":"1350 E Southcross Blvd",
    "sg:city":"San Antonio",
    "sg:classifiers":[
        {
            "category":"Home & Garden",
            "subcategory":"Furniture",
            "type":"Retail Goods"
        }
    ],
    "sg:phone":"+1 210 733 1269",
    "sg:postcode":"78223",
    "sg:province":"TX",
    "wof:name":"Artchitectural Interiors",
    "wof:placetype":"venue"
},
  "geometry": {"coordinates":[-98.47597,29.37493],"type":"Point"}
}