{
  "type": "Feature",
  "properties": {
    "iso:country":"US",
    "sg:address":"1109 New Dallas Hwy",
    "sg:city":"Waco",
    "sg:classifiers":[
        {
            "category":"Real Estate",
            "subcategory":"Real Estate Operator",
            "type":"Services"
        }
    ],
    "sg:phone":"+1 254 867 8930",
    "sg:postcode":"76705",
    "sg:province":"TX",
    "sg:tags":[
        "mobile",
        "home",
        "site"
    ],
    "wof:name":"Oaklawn Mobile Home Park",
    "wof:placetype":"venue"
},
  "geometry": {"coordinates":[-97.11481499999999,31.585205],"type":"Point"}
}