{
  "type": "Feature",
  "properties": {
    "iso:country":"US",
    "sg:address":"2201 19th St",
    "sg:city":"Hondo",
    "sg:classifiers":[
        {
            "category":"Food & Beverages",
            "subcategory":"Liquor & Beverages",
            "type":"Retail Goods"
        }
    ],
    "sg:phone":"+1 830 426 5239",
    "sg:postcode":"78861",
    "sg:province":"TX",
    "sg:tags":[
        "grocery",
        "alcoholic"
    ],
    "wof:name":"McBee Beverage Barn",
    "wof:placetype":"venue"
},
  "geometry": {"coordinates":[-99.15263899999999,29.346522],"type":"Point"}
}