{
  "type": "Feature",
  "properties": {
    "iso:country":"US",
    "sg:address":"108 N Johnson St",
    "sg:city":"Mineola",
    "sg:classifiers":[
        {
            "category":"Health Services",
            "subcategory":"Health Practitioner",
            "type":"Services"
        }
    ],
    "sg:phone":"+1 903 569 6978",
    "sg:postcode":"75773",
    "sg:province":"TX",
    "sg:tags":[
        "audiologists"
    ],
    "wof:name":"Avada Audiology & Hearing Care",
    "wof:placetype":"venue"
},
  "geometry": {"coordinates":[-95.488893,32.66446],"type":"Point"}
}