{
  "type": "Feature",
  "properties": {
    "iso:country":"US",
    "sg:address":"209 5th St",
    "sg:city":"Palacios",
    "sg:classifiers":[
        {
            "category":"Professional",
            "subcategory":"Lawyer & Legal Services",
            "type":"Services"
        }
    ],
    "sg:phone":"+1 361 972 2567",
    "sg:postcode":"77465",
    "sg:province":"TX",
    "sg:tags":[
        "attorney"
    ],
    "wof:name":"Mayfield & Mayfield",
    "wof:placetype":"venue"
},
  "geometry": {"coordinates":[-96.21687300000001,28.7008],"type":"Point"}
}