{
  "type": "Feature",
  "properties": {
    "iso:country":"US",
    "sg:address":"117 W Nolana St",
    "sg:city":"Mcallen",
    "sg:classifiers":[
        {
            "category":"Utilities",
            "subcategory":"Mobile Phone",
            "type":"Services"
        },
        {
            "category":"Shopping",
            "type":"Retail Goods"
        },
        {
            "category":"Professional",
            "subcategory":"Management & Consulting",
            "type":"Services"
        }
    ],
    "sg:phone":"+1 956 994 3007",
    "sg:postcode":"78504",
    "sg:province":"TX",
    "sg:tags":[
        "business",
        "mfg",
        "telephone",
        "r",
        "cellular",
        "merchandise"
    ],
    "wof:name":"Nextel Nexwave Communications",
    "wof:placetype":"venue"
},
  "geometry": {"coordinates":[-98.214673,26.238186],"type":"Point"}
}