{
  "type": "Feature",
  "properties": {
    "iso:country":"US",
    "sg:address":"3830 Old Denton Rd",
    "sg:city":"Carrollton",
    "sg:classifiers":[
        {
            "category":"Real Estate",
            "subcategory":"Real Estate Operator",
            "type":"Services"
        }
    ],
    "sg:phone":"+1 972 394 0414",
    "sg:postcode":"75007",
    "sg:province":"TX",
    "sg:tags":[
        "apartment",
        "complex"
    ],
    "wof:name":"Rosemeade Townhomes",
    "wof:placetype":"venue"
},
  "geometry": {"coordinates":[-96.91296199999999,33.014821],"type":"Point"}
}