{
  "type": "Feature",
  "properties": {
    "iso:country":"US",
    "sg:address":"4901 Kinsey Dr",
    "sg:city":"Tyler",
    "sg:classifiers":[
        {
            "category":"Professional",
            "subcategory":"Computer Services",
            "type":"Services"
        }
    ],
    "sg:phone":"+1 903 561 8815",
    "sg:postcode":"75703",
    "sg:province":"TX",
    "sg:tags":[
        "programing",
        "custom"
    ],
    "wof:name":"Wood Computer Svc",
    "wof:placetype":"venue"
},
  "geometry": {"coordinates":[-95.315472,32.295215],"type":"Point"}
}