{
  "type": "Feature",
  "properties": {
    "iso:country":"US",
    "sg:address":"6413 University Ave",
    "sg:city":"Lubbock",
    "sg:classifiers":[
        {
            "category":"Professional",
            "subcategory":"Employment Agencies",
            "type":"Services"
        }
    ],
    "sg:phone":"+1 806 797 4161",
    "sg:postcode":"79413",
    "sg:province":"TX",
    "sg:tags":[
        "help",
        "supply"
    ],
    "wof:name":"G Boren Staffing Services",
    "wof:placetype":"venue"
},
  "geometry": {"coordinates":[-101.870338,33.534368],"type":"Point"}
}