{
  "type": "Feature",
  "properties": {
    "iso:country":"US",
    "sg:address":"202 Thigpen Dr",
    "sg:city":"Tyler",
    "sg:classifiers":[
        {
            "category":"Real Estate",
            "subcategory":"Real Estate Operator",
            "type":"Services"
        }
    ],
    "sg:phone":"+1 903 561 0596",
    "sg:postcode":"75703",
    "sg:province":"TX",
    "sg:tags":[
        "management"
    ],
    "wof:name":"Brookhollow Apartments",
    "wof:placetype":"venue"
},
  "geometry": {"coordinates":[-95.308161,32.272335],"type":"Point"}
}