{
  "type": "Feature",
  "properties": {
    "iso:country":"US",
    "sg:address":"3803 Lost Cavern Cv",
    "sg:city":"Austin",
    "sg:classifiers":[
        {
            "category":"Personal",
            "subcategory":"Barber",
            "type":"Services"
        }
    ],
    "sg:phone":"+1 512 906 2973",
    "sg:postcode":"78739",
    "sg:province":"TX",
    "wof:name":"Capitol City Barber Shop",
    "wof:placetype":"venue"
},
  "geometry": {"coordinates":[-97.87204300000001,30.159171],"type":"Point"}
}