{
  "type": "Feature",
  "properties": {
    "iso:country":"US",
    "sg:address":"4 Greens Shadow",
    "sg:city":"San Antonio",
    "sg:classifiers":[
        {
            "category":"Building & Trades",
            "subcategory":"Construction",
            "type":"Services"
        }
    ],
    "sg:phone":"+1 210 408 6060",
    "sg:postcode":"78216",
    "sg:province":"TX",
    "sg:tags":[
        "house"
    ],
    "wof:name":"Prestige Homes Rogers Ranch",
    "wof:placetype":"venue"
},
  "geometry": {"coordinates":[-98.50223200000001,29.579075],"type":"Point"}
}