{
  "type": "Feature",
  "properties": {
    "iso:country":"US",
    "sg:address":"202 E 7th St",
    "sg:city":"Dumas",
    "sg:classifiers":[
        {
            "category":"Banks & Credit Unions",
            "subcategory":"Bank",
            "type":"Services"
        }
    ],
    "sg:phone":"+1 806 935 7161",
    "sg:postcode":"79029",
    "sg:province":"TX",
    "sg:tags":[
        "savings",
        "loan",
        "association"
    ],
    "wof:name":"Dalhart Federal Savings & Loan",
    "wof:placetype":"venue"
},
  "geometry": {"coordinates":[-101.97183800000001,35.858682],"type":"Point"}
}