{
  "type": "Feature",
  "properties": {
    "iso:country":"US",
    "sg:address":"500 W Pleasant Run Rd",
    "sg:city":"Lancaster",
    "sg:classifiers":[
        {
            "category":"Autos & Motor Vehicles",
            "subcategory":"Auto Supplies",
            "type":"Retail Goods"
        }
    ],
    "sg:phone":"+1 972 218 5903",
    "sg:postcode":"75146",
    "sg:province":"TX",
    "wof:name":"OReilly Automotive Inc",
    "wof:placetype":"venue"
},
  "geometry": {"coordinates":[-96.767732,32.605078],"type":"Point"}
}