{
  "type": "Feature",
  "properties": {
    "iso:country":"US",
    "sg:address":"13713 N Lone Star Pkwy",
    "sg:city":"Valley Mills",
    "sg:classifiers":[
        {
            "category":"Shopping",
            "subcategory":"Used Merchandise",
            "type":"Retail Goods"
        }
    ],
    "sg:phone":"+1 254 932 5227",
    "sg:postcode":"76689",
    "sg:province":"TX",
    "wof:name":"Red Tag Resale Store",
    "wof:placetype":"venue"
},
  "geometry": {"coordinates":[-97.460269,31.623289],"type":"Point"}
}