{
  "type": "Feature",
  "properties": {
    "iso:country":"US",
    "sg:address":"5866 S Staples St",
    "sg:city":"Corpus Christi",
    "sg:classifiers":[
        {
            "category":"Professional",
            "subcategory":"Engineering",
            "type":"Services"
        }
    ],
    "sg:phone":"+1 361 991 8877",
    "sg:postcode":"78413",
    "sg:province":"TX",
    "wof:name":"Hayden Assoc Cnslting Engneers",
    "wof:placetype":"venue"
},
  "geometry": {"coordinates":[-97.377713,27.69522],"type":"Point"}
}