{
  "type": "Feature",
  "properties": {
    "iso:country":"US",
    "sg:address":"1962 Shady Rest Ct",
    "sg:city":"Bedford",
    "sg:classifiers":[
        {
            "category":"Building & Trades",
            "subcategory":"Cleaning & Sanitation",
            "type":"Services"
        }
    ],
    "sg:phone":"+1 817 283 1112",
    "sg:postcode":"76021",
    "sg:province":"TX",
    "sg:tags":[
        "janitor"
    ],
    "wof:name":"D M Svc",
    "wof:placetype":"venue"
},
  "geometry": {"coordinates":[-97.150104,32.842779],"type":"Point"}
}