{
  "type": "Feature",
  "properties": {
    "iso:country":"US",
    "sg:address":"1424 Airport Fwy",
    "sg:city":"Bedford",
    "sg:classifiers":[
        {
            "category":"Shopping",
            "subcategory":"Hobbies, Toys, & Games",
            "type":"Retail Goods"
        }
    ],
    "sg:phone":"+1 817 267 0991",
    "sg:postcode":"76022",
    "sg:province":"TX",
    "sg:tags":[
        "p",
        "lead",
        "mfg"
    ],
    "wof:name":"Hobby Maker Inc",
    "wof:placetype":"venue"
},
  "geometry": {"coordinates":[-97.147965,32.837573],"type":"Point"}
}