{
  "type": "Feature",
  "properties": {
    "iso:country":"US",
    "sg:address":"213 Rogers Cir",
    "sg:city":"Denver City",
    "sg:classifiers":[
        {
            "category":"Sports & Exercise",
            "subcategory":"Bowling",
            "type":"Entertainment"
        }
    ],
    "sg:phone":"+1 806 592 3791",
    "sg:postcode":"79323",
    "sg:province":"TX",
    "sg:tags":[
        "center"
    ],
    "wof:name":"Womens Intl Bowl Congress",
    "wof:placetype":"venue"
},
  "geometry": {"coordinates":[-102.819337,32.965857],"type":"Point"}
}