{
  "type": "Feature",
  "properties": {
    "iso:country":"US",
    "sg:address":"5900 Chimney Rock Rd Space N",
    "sg:city":"Houston",
    "sg:classifiers":[
        {
            "category":"Shopping",
            "subcategory":"Beauty & Cosmetics",
            "type":"Retail Goods"
        }
    ],
    "sg:phone":"+1 713 665 4916",
    "sg:postcode":"77081",
    "sg:province":"TX",
    "sg:tags":[
        "equipment",
        "supply"
    ],
    "sg:website":"http://www.sallybeauty.com/",
    "wof:name":"Sally Beauty Supply",
    "wof:placetype":"venue"
},
  "geometry": {"coordinates":[-95.476508,29.717598],"type":"Point"}
}