{
  "type": "Feature",
  "properties": {
    "iso:country":"US",
    "sg:address":"3770 Judson Rd",
    "sg:city":"Longview",
    "sg:classifiers":[
        {
            "category":"Retail",
            "subcategory":"Veterinary Services",
            "type":"Services"
        }
    ],
    "sg:phone":"+1 903 663 1111",
    "sg:postcode":"75605",
    "sg:province":"TX",
    "wof:name":"Hounsel Ken Dvm",
    "wof:placetype":"venue"
},
  "geometry": {"coordinates":[-94.751718,32.557196],"type":"Point"}
}