{
  "type": "Feature",
  "properties": {
    "iso:country":"US",
    "sg:address":"22027 Shady Valley Dr",
    "sg:city":"Katy",
    "sg:classifiers":[
        {
            "category":"Professional",
            "subcategory":"Management & Consulting",
            "type":"Services"
        }
    ],
    "sg:phone":"+1 281 392 3331",
    "sg:postcode":"77450",
    "sg:province":"TX",
    "sg:tags":[
        "consultant"
    ],
    "wof:name":"Bob Rowe's Petroleum Cnsltnts",
    "wof:placetype":"venue"
},
  "geometry": {"coordinates":[-95.75407199999999,29.759949],"type":"Point"}
}