{
  "type": "Feature",
  "properties": {
    "iso:country":"US",
    "sg:address":"214 Lydia Cir",
    "sg:city":"Irving",
    "sg:classifiers":[
        {
            "category":"Professional",
            "subcategory":"Management & Consulting",
            "type":"Services"
        }
    ],
    "sg:phone":"+1 972 445 0555",
    "sg:postcode":"75060",
    "sg:province":"TX",
    "wof:name":"Global Business Services",
    "wof:placetype":"venue"
},
  "geometry": {"coordinates":[-96.927463,32.812599],"type":"Point"}
}