{
  "type": "Feature",
  "properties": {
    "iso:country":"US",
    "sg:address":"701 E Harrison Ave",
    "sg:city":"Harlingen",
    "sg:classifiers":[
        {
            "category":"Autos & Motor Vehicles",
            "subcategory":"Automobile Sales",
            "type":"Retail Goods"
        }
    ],
    "sg:phone":"+1 956 425 6595",
    "sg:postcode":"78550",
    "sg:province":"TX",
    "sg:tags":[
        "used"
    ],
    "wof:name":"T J Auto Sales",
    "wof:placetype":"venue"
},
  "geometry": {"coordinates":[-97.68807200000001,26.190685],"type":"Point"}
}