{
  "type": "Feature",
  "properties": {
    "iso:country":"US",
    "sg:address":"500 N Jackson Rd",
    "sg:city":"Pharr",
    "sg:classifiers":[
        {
            "category":"Shopping",
            "subcategory":"Clothing, Apparel, & Fashions",
            "type":"Retail Goods"
        }
    ],
    "sg:phone":"+1 956 782 1733",
    "sg:postcode":"78577",
    "sg:province":"TX",
    "wof:name":"Visions",
    "wof:placetype":"venue"
},
  "geometry": {"coordinates":[-98.203236,26.202912],"type":"Point"}
}