{
  "type": "Feature",
  "properties": {
    "iso:country":"US",
    "sg:address":"2340 State Hwy 6",
    "sg:city":"Houston",
    "sg:classifiers":[
        {
            "category":"Shopping",
            "subcategory":"Bicycles & Sporting Goods",
            "type":"Retail Goods"
        }
    ],
    "sg:phone":"+1 281 752 8041",
    "sg:postcode":"77077",
    "sg:province":"TX",
    "sg:tags":[
        "equipment",
        "exercise"
    ],
    "wof:name":"Busy Body Home Fitness",
    "wof:placetype":"venue"
},
  "geometry": {"coordinates":[-95.644216,29.739913],"type":"Point"}
}