{
  "type": "Feature",
  "properties": {
    "iso:country":"US",
    "sg:address":"9302 Beverlyhill St",
    "sg:city":"Houston",
    "sg:classifiers":[
        {
            "category":"Building & Trades",
            "subcategory":"Landscaping Services",
            "type":"Services"
        }
    ],
    "sg:phone":"+1 713 975 6242",
    "sg:postcode":"77063",
    "sg:province":"TX",
    "wof:name":"Andrew Cruz Lawn Service",
    "wof:placetype":"venue"
},
  "geometry": {"coordinates":[-95.531387,29.730256],"type":"Point"}
}