{
  "type": "Feature",
  "properties": {
    "iso:country":"US",
    "sg:address":"1501 W 23rd St",
    "sg:city":"Houston",
    "sg:classifiers":[
        {
            "category":"Organizations",
            "subcategory":"Religious Organization",
            "type":"Services"
        }
    ],
    "sg:phone":"+1 713 862 7040",
    "sg:postcode":"77008",
    "sg:province":"TX",
    "wof:name":"Shady Acre Full Gospel Church",
    "wof:placetype":"venue"
},
  "geometry": {"coordinates":[-95.42921699999999,29.806656],"type":"Point"}
}