{
  "type": "Feature",
  "properties": {
    "iso:country":"US",
    "sg:address":"502 Sycamore St",
    "sg:city":"Bardwell",
    "sg:classifiers":[
        {
            "category":"Banks & Credit Unions",
            "subcategory":"Financial Services",
            "type":"Services"
        }
    ],
    "sg:phone":"+1 972 646 5223",
    "sg:postcode":"75101",
    "sg:province":"TX",
    "sg:tags":[
        "investor"
    ],
    "wof:name":"J & J Investments",
    "wof:placetype":"venue"
},
  "geometry": {"coordinates":[-96.69361000000001,32.267082],"type":"Point"}
}