{
  "type": "Feature",
  "properties": {
    "iso:country":"US",
    "sg:address":"10714 Plainfield St",
    "sg:city":"Houston",
    "sg:classifiers":[
        {
            "category":"Professional",
            "subcategory":"Computer Services",
            "type":"Services"
        }
    ],
    "sg:phone":"+1 713 774 9757",
    "sg:postcode":"77031",
    "sg:province":"TX",
    "sg:tags":[
        "prepackaged",
        "software",
        "programing",
        "custom"
    ],
    "wof:name":"Advancedcrmcom",
    "wof:placetype":"venue"
},
  "geometry": {"coordinates":[-95.544567,29.662873],"type":"Point"}
}