{
  "type": "Feature",
  "properties": {
    "iso:country":"US",
    "sg:address":"103 E Frey St",
    "sg:city":"Stephenville",
    "sg:classifiers":[
        {
            "category":"Health Services",
            "subcategory":"Doctor",
            "type":"Services"
        }
    ],
    "sg:phone":"+1 254 918 2484",
    "sg:postcode":"76401",
    "sg:province":"TX",
    "sg:tags":[
        "physician",
        "pediatrics-emergency",
        "pediatrics",
        "family",
        "practice",
        "surgeons",
        "medicine",
        "surgeon"
    ],
    "wof:name":"Miller Pediatrics Pa",
    "wof:placetype":"venue"
},
  "geometry": {"coordinates":[-98.206643,32.227207],"type":"Point"}
}