{
  "type": "Feature",
  "properties": {
    "iso:country":"US",
    "sg:address":"305 Dryden Pl",
    "sg:city":"Port Arthur",
    "sg:classifiers":[
        {
            "category":"Organizations",
            "subcategory":"Community Association",
            "type":"Services"
        }
    ],
    "sg:phone":"+1 409 982 0709",
    "sg:postcode":"77642",
    "sg:province":"TX",
    "wof:name":"Royal Order Jesters Court 97",
    "wof:placetype":"venue"
},
  "geometry": {"coordinates":[-93.90908899999999,29.897741],"type":"Point"}
}