{
  "type": "Feature",
  "properties": {
    "iso:country":"US",
    "sg:address":"1020 Kane St",
    "sg:city":"Benbrook",
    "sg:classifiers":[
        {
            "category":"Freight",
            "type":"Transportation"
        }
    ],
    "sg:phone":"+1 817 625 7051",
    "sg:postcode":"76126",
    "sg:province":"TX",
    "sg:tags":[
        "broker",
        "trucking"
    ],
    "wof:name":"Watts Trucking Co",
    "wof:placetype":"venue"
},
  "geometry": {"coordinates":[-97.455062,32.674827],"type":"Point"}
}