{
  "type": "Feature",
  "properties": {
    "iso:country":"US",
    "sg:address":"11951 Bissonnet St",
    "sg:city":"Houston",
    "sg:classifiers":[
        {
            "category":"Professional",
            "type":"Services"
        }
    ],
    "sg:phone":"+1 281 530 6899",
    "sg:postcode":"77099",
    "sg:province":"TX",
    "sg:tags":[
        "establishment"
    ],
    "wof:name":"Masgid Ul Aala",
    "wof:placetype":"venue"
},
  "geometry": {"coordinates":[-95.587846,29.675171],"type":"Point"}
}