{
  "type": "Feature",
  "properties": {
    "iso:country":"US",
    "sg:address":"810 W 10th St",
    "sg:city":"Austin",
    "sg:classifiers":[
        {
            "category":"Building & Trades",
            "subcategory":"Construction",
            "type":"Services"
        }
    ],
    "sg:phone":"+1 512 472 1266",
    "sg:postcode":"78701",
    "sg:province":"TX",
    "sg:tags":[
        "interior",
        "design"
    ],
    "wof:name":"Arb Designs",
    "wof:placetype":"venue"
},
  "geometry": {"coordinates":[-97.74949599999999,30.274099],"type":"Point"}
}