{
  "type": "Feature",
  "properties": {
    "iso:country":"US",
    "sg:address":"14001 Fondren Rd",
    "sg:city":"Missouri City",
    "sg:classifiers":[
        {
            "category":"Real Estate",
            "subcategory":"Real Estate Operator",
            "type":"Services"
        }
    ],
    "sg:phone":"+1 281 437 9993",
    "sg:postcode":"77489",
    "sg:province":"TX",
    "sg:tags":[
        "apartment"
    ],
    "sg:website":"www.willowparkapartments.com",
    "wof:name":"Willow Park Apartments",
    "wof:placetype":"venue"
},
  "geometry": {"coordinates":[-95.508499,29.619249],"type":"Point"}
}