{
  "type": "Feature",
  "properties": {
    "iso:country":"US",
    "sg:address":"801 Grove St",
    "sg:city":"Fort Worth",
    "sg:classifiers":[
        {
            "category":"Freight",
            "type":"Transportation"
        }
    ],
    "sg:phone":"+1 817 870 2310",
    "sg:postcode":"76102",
    "sg:province":"TX",
    "sg:tags":[
        "special",
        "real estate"
    ],
    "wof:name":"Tindall Record Storage",
    "wof:placetype":"venue"
},
  "geometry": {"coordinates":[-97.32595999999999,32.753704],"type":"Point"}
}