{
  "type": "Feature",
  "properties": {
    "iso:country":"US",
    "sg:address":"2218 Iowa St",
    "sg:city":"San Antonio",
    "sg:classifiers":[
        {
            "category":"Shopping",
            "subcategory":"Jewelry",
            "type":"Retail Goods"
        }
    ],
    "sg:phone":"+1 210 532 2215",
    "sg:postcode":"78203",
    "sg:province":"TX",
    "wof:name":"Janie Palomo",
    "wof:placetype":"venue"
},
  "geometry": {"coordinates":[-98.45144000000001,29.412036],"type":"Point"}
}