{
  "type": "Feature",
  "properties": {
    "iso:country":"US",
    "sg:address":"17440 W Little York Rd",
    "sg:city":"Houston",
    "sg:classifiers":[
        {
            "category":"Wholesale",
            "subcategory":"Machinery & Supplies",
            "type":"Manufacturing & Wholesale Goods"
        }
    ],
    "sg:phone":"+1 281 345 6244",
    "sg:postcode":"77084",
    "sg:province":"TX",
    "sg:tags":[
        "utensil",
        "cooking",
        "janitorial"
    ],
    "wof:name":"Janitorial & Restaurant Supply",
    "wof:placetype":"venue"
},
  "geometry": {"coordinates":[-95.674485,29.865463],"type":"Point"}
}