{
  "type": "Feature",
  "properties": {
    "iso:country":"US",
    "sg:address":"808 N Crowley Rd",
    "sg:city":"Crowley",
    "sg:classifiers":[
        {
            "category":"Shopping",
            "subcategory":"Gifts & Souvenirs",
            "type":"Retail Goods"
        }
    ],
    "sg:phone":"+1 817 297 2713",
    "sg:postcode":"76036",
    "sg:province":"TX",
    "sg:tags":[
        "shop"
    ],
    "wof:name":"Nanny's Nook & Cranny",
    "wof:placetype":"venue"
},
  "geometry": {"coordinates":[-97.351105,32.585888],"type":"Point"}
}