{
  "type": "Feature",
  "properties": {
    "iso:country":"US",
    "sg:address":"700 Fredericksburg Rd",
    "sg:city":"San Antonio",
    "sg:classifiers":[
        {
            "category":"Shopping",
            "subcategory":"Hobbies, Toys, & Games",
            "type":"Retail Goods"
        }
    ],
    "sg:phone":"+1 210 731 8232",
    "sg:postcode":"78201",
    "sg:province":"TX",
    "wof:name":"Tom Bush Game Sales",
    "wof:placetype":"venue"
},
  "geometry": {"coordinates":[-98.511314,29.449382],"type":"Point"}
}