{
  "type": "Feature",
  "properties": {
    "iso:country":"US",
    "sg:address":"12955 Stafford Rd",
    "sg:city":"Stafford",
    "sg:classifiers":[
        {
            "category":"Organizations",
            "subcategory":"Religious Organization",
            "type":"Services"
        }
    ],
    "sg:phone":"+1 281 568 5007",
    "sg:postcode":"77477",
    "sg:province":"TX",
    "wof:name":"International Bible Church",
    "wof:placetype":"venue"
},
  "geometry": {"coordinates":[-95.546263,29.633489],"type":"Point"}
}