{
  "type": "Feature",
  "properties": {
    "iso:country":"US",
    "sg:address":"1920 Abrams Pkwy",
    "sg:city":"Dallas",
    "sg:classifiers":[
        {
            "category":"Banks & Credit Unions",
            "subcategory":"Financial Services",
            "type":"Services"
        }
    ],
    "sg:phone":"+1 972 489 7925",
    "sg:postcode":"75214",
    "sg:province":"TX",
    "sg:tags":[
        "retail",
        "franchising"
    ],
    "wof:name":"Discount Sport Nutrition Fran",
    "wof:placetype":"venue"
},
  "geometry": {"coordinates":[-96.75278400000001,32.812014],"type":"Point"}
}