{
  "type": "Feature",
  "properties": {
    "iso:country":"US",
    "sg:address":"2605 N Guadalupe St",
    "sg:city":"Seguin",
    "sg:classifiers":[
        {
            "category":"Government",
            "subcategory":"Office",
            "type":"Public Place"
        }
    ],
    "sg:phone":"+1 830 379 9721",
    "sg:postcode":"78155",
    "sg:province":"TX",
    "sg:tags":[
        "parish",
        "government-county"
    ],
    "wof:name":"Guadalupe-County",
    "wof:placetype":"venue"
},
  "geometry": {"coordinates":[-97.97000300000001,29.599615],"type":"Point"}
}