{
  "type": "Feature",
  "properties": {
    "iso:country":"US",
    "sg:address":"15 Lakewood Ln",
    "sg:city":"Seabrook",
    "sg:classifiers":[
        {
            "category":"Professional",
            "subcategory":"Business Services",
            "type":"Services"
        }
    ],
    "sg:phone":"+1 281 291 7001",
    "sg:postcode":"77586",
    "sg:province":"TX",
    "wof:name":"Binnacle Enterprises Inc",
    "wof:placetype":"venue"
},
  "geometry": {"coordinates":[-95.030998,29.559958],"type":"Point"}
}