{
  "type": "Feature",
  "properties": {
    "iso:country":"US",
    "sg:address":"6700 Davis Blvd",
    "sg:city":"Fort Worth",
    "sg:classifiers":[
        {
            "category":"Manufacturing",
            "subcategory":"Rubber & Plastics",
            "type":"Manufacturing & Wholesale Goods"
        }
    ],
    "sg:phone":"+1 817 498 5310",
    "sg:postcode":"76180",
    "sg:province":"TX",
    "sg:tags":[
        "product",
        "mfg"
    ],
    "wof:name":"Delta Concepts",
    "wof:placetype":"venue"
},
  "geometry": {"coordinates":[-97.208377,32.86858],"type":"Point"}
}