{
  "type": "Feature",
  "properties": {
    "iso:country":"US",
    "sg:address":"4395 Oleander St",
    "sg:city":"Vidor",
    "sg:classifiers":[
        {
            "category":"Professional",
            "subcategory":"Business Services",
            "type":"Services"
        }
    ],
    "sg:phone":"+1 409 681 0475",
    "sg:postcode":"77662",
    "sg:province":"TX",
    "wof:name":"Kressman Enterprises",
    "wof:placetype":"venue"
},
  "geometry": {"coordinates":[-94.062442,30.193414],"type":"Point"}
}