{
  "type": "Feature",
  "properties": {
    "iso:country":"US",
    "sg:address":"1125 Kirkwood St",
    "sg:city":"Abilene",
    "sg:classifiers":[
        {
            "category":"Bakery",
            "type":"Food & Drink"
        }
    ],
    "sg:phone":"+1 325 672 8743",
    "sg:postcode":"79603",
    "sg:province":"TX",
    "wof:name":"Touch Of Class Cakes",
    "wof:placetype":"venue"
},
  "geometry": {"coordinates":[-99.749073,32.462159],"type":"Point"}
}