{
  "type": "Feature",
  "properties": {
    "iso:country":"US",
    "sg:address":"6311 Garth Rd",
    "sg:city":"Baytown",
    "sg:classifiers":[
        {
            "category":"Autos & Motor Vehicles",
            "subcategory":"Automobile Sales",
            "type":"Retail Goods"
        },
        {
            "category":"Retail",
            "subcategory":"Auto Rental",
            "type":"Services"
        }
    ],
    "sg:phone":"+1 281 421 2825",
    "sg:postcode":"77521",
    "sg:province":"TX",
    "sg:tags":[
        "truck",
        "leasing",
        "car"
    ],
    "sg:website":"http://www.enterprise.com/car_rental/deeplinkmap.do?gpbr=0686&bid=004&cnty=US&arc=YPTRL01&cm_mmc=Yellowpages.com-_-IYP-_-Tradelisting-_-branch",
    "wof:name":"Enterprise Rent-A-Car",
    "wof:placetype":"venue"
},
  "geometry": {"coordinates":[-94.980154,29.792542],"type":"Point"}
}