{
  "type": "Feature",
  "properties": {
    "iso:country":"US",
    "sg:address":"3001 Pablo Kisel Blvd",
    "sg:city":"Brownsville",
    "sg:classifiers":[
        {
            "category":"Restaurant",
            "type":"Food & Drink"
        }
    ],
    "sg:phone":"+1 956 574 9888",
    "sg:postcode":"78526",
    "sg:province":"TX",
    "sg:tags":[
        "italian"
    ],
    "wof:name":"Tre Fratelli",
    "wof:placetype":"venue"
},
  "geometry": {"coordinates":[-97.50598599999999,25.957765],"type":"Point"}
}