{
  "type": "Feature",
  "properties": {
    "iso:country":"US",
    "sg:address":"2650 S Peek Rd",
    "sg:city":"Katy",
    "sg:classifiers":[
        {
            "category":"Social Services",
            "subcategory":"Child Care",
            "type":"Services"
        }
    ],
    "sg:phone":"+1 281 392 2650",
    "sg:postcode":"77450",
    "sg:province":"TX",
    "wof:name":"Kinder Care Learning Ctr",
    "wof:placetype":"venue"
},
  "geometry": {"coordinates":[-95.768717,29.744906],"type":"Point"}
}