{
  "type": "Feature",
  "properties": {
    "iso:country":"US",
    "sg:address":"212 Grande Blvd",
    "sg:city":"Tyler",
    "sg:classifiers":[
        {
            "category":"Government",
            "subcategory":"Office",
            "type":"Public Place"
        }
    ],
    "sg:phone":"+1 903 561 8632",
    "sg:postcode":"75703",
    "sg:province":"TX",
    "sg:tags":[
        "federal",
        "human"
    ],
    "wof:name":"US Social Security Adm",
    "wof:placetype":"venue"
},
  "geometry": {"coordinates":[-95.30837099999999,32.282558],"type":"Point"}
}