{
  "type": "Feature",
  "properties": {
    "iso:country":"US",
    "sg:address":"5709 Northbrook Dr",
    "sg:city":"Plano",
    "sg:classifiers":[
        {
            "category":"Professional",
            "type":"Services"
        }
    ],
    "sg:phone":"+1 972 608 0685",
    "sg:postcode":"75093",
    "sg:province":"TX",
    "wof:name":"Fick Family Ltd",
    "wof:placetype":"venue"
},
  "geometry": {"coordinates":[-96.816799,33.041878],"type":"Point"}
}