{
  "type": "Feature",
  "properties": {
    "iso:country":"US",
    "sg:address":"815 Market St",
    "sg:city":"Galveston",
    "sg:classifiers":[
        {
            "category":"Health Services",
            "subcategory":"Doctor",
            "type":"Services"
        }
    ],
    "sg:phone":"+1 409 770 6731",
    "sg:postcode":"77550",
    "sg:province":"TX",
    "sg:tags":[
        "physician",
        "surgeon"
    ],
    "wof:name":"Ut-Med Group Practice Of Med",
    "wof:placetype":"venue"
},
  "geometry": {"coordinates":[-94.777629,29.309573],"type":"Point"}
}