{
  "type": "Feature",
  "properties": {
    "iso:country":"US",
    "sg:address":"4920 NE Stallings Dr",
    "sg:city":"Nacogdoches",
    "sg:classifiers":[
        {
            "category":"Shopping",
            "subcategory":"Gifts & Souvenirs",
            "type":"Retail Goods"
        }
    ],
    "sg:phone":"+1 936 568 3184",
    "sg:postcode":"75965",
    "sg:province":"TX",
    "sg:tags":[
        "shop"
    ],
    "wof:name":"Nmch Gift Shop",
    "wof:placetype":"venue"
},
  "geometry": {"coordinates":[-94.653429,31.6521],"type":"Point"}
}