{
  "type": "Feature",
  "properties": {
    "iso:country":"US",
    "sg:address":"604 N McCoy Blvd",
    "sg:city":"New Boston",
    "sg:classifiers":[
        {
            "category":"Education",
            "subcategory":"School",
            "type":"Public Place"
        }
    ],
    "sg:phone":"+1 903 628 6521",
    "sg:postcode":"75570",
    "sg:province":"TX",
    "wof:name":"Crestview Elementary School",
    "wof:placetype":"venue"
},
  "geometry": {"coordinates":[-94.40867,33.467825],"type":"Point"}
}