{
  "type": "Feature",
  "properties": {
    "iso:country":"US",
    "sg:address":"5181 River Oaks Blvd",
    "sg:city":"Fort Worth",
    "sg:classifiers":[
        {
            "category":"Restaurant",
            "type":"Food & Drink"
        }
    ],
    "sg:menulink":"http://www.allmenus.com/tx/fort-worth/13311-churchs-chicken/menu/",
    "sg:phone":"+1 817 626 5535",
    "sg:postcode":"76114",
    "sg:province":"TX",
    "sg:tags":[
        "chicken",
        "wing"
    ],
    "wof:name":"Church's Chicken",
    "wof:placetype":"venue"
},
  "geometry": {"coordinates":[-97.39883500000001,32.773584],"type":"Point"}
}