{
  "type": "Feature",
  "properties": {
    "iso:country":"US",
    "sg:address":"6897 Bandera Rd",
    "sg:city":"San Antonio",
    "sg:classifiers":[
        {
            "category":"Shopping",
            "type":"Retail Goods"
        },
        {
            "category":"Building & Trades",
            "subcategory":"Construction",
            "type":"Services"
        }
    ],
    "sg:phone":"+1 210 520 7014",
    "sg:postcode":"78238",
    "sg:province":"TX",
    "sg:tags":[
        "plastering",
        "coping",
        "pool",
        "tiling",
        "merchandise",
        "swimming"
    ],
    "wof:name":"Leslies Swimming Pool Supplies",
    "wof:placetype":"venue"
},
  "geometry": {"coordinates":[-98.62172099999999,29.497717],"type":"Point"}
}