{
  "type": "Feature",
  "properties": {
    "iso:country":"US",
    "sg:address":"348 Bluebonnet Cir",
    "sg:city":"Mc Gregor",
    "sg:classifiers":[
        {
            "category":"Real Estate",
            "subcategory":"Real Estate Agent",
            "type":"Services"
        }
    ],
    "sg:phone":"+1 254 717 2160",
    "sg:postcode":"76657",
    "sg:province":"TX",
    "wof:name":"Oak Tree Realty",
    "wof:placetype":"venue"
},
  "geometry": {"coordinates":[-97.311195,31.475772],"type":"Point"}
}