{
  "type": "Feature",
  "properties": {
    "iso:country":"US",
    "sg:address":"802 E Hayes Ave",
    "sg:city":"Morton",
    "sg:classifiers":[
        {
            "category":"Restaurant",
            "type":"Food & Drink"
        }
    ],
    "sg:phone":"+1 806 266 8881",
    "sg:postcode":"79346",
    "sg:province":"TX",
    "sg:tags":[
        "eating"
    ],
    "wof:name":"Randy A Gattis",
    "wof:placetype":"venue"
},
  "geometry": {"coordinates":[-102.75114000000001,33.718208],"type":"Point"}
}