{
  "type": "Feature",
  "properties": {
    "iso:country":"US",
    "sg:address":"425 Parkway Blvd",
    "sg:city":"Coppell",
    "sg:classifiers":[
        {
            "category":"Manufacturing",
            "subcategory":"Printing",
            "type":"Manufacturing & Wholesale Goods"
        }
    ],
    "sg:phone":"+1 972 393 0011",
    "sg:postcode":"75019",
    "sg:province":"TX",
    "sg:tags":[
        "publishing"
    ],
    "wof:name":"Maxwell Creative Services",
    "wof:placetype":"venue"
},
  "geometry": {"coordinates":[-96.982935,32.978325],"type":"Point"}
}