{
  "type": "Feature",
  "properties": {
    "iso:country":"US",
    "sg:address":"5181 Keller Springs Rd",
    "sg:city":"Dallas",
    "sg:classifiers":[
        {
            "category":"Banks & Credit Unions",
            "subcategory":"Bank",
            "type":"Services"
        }
    ],
    "sg:phone":"+1 972 248 2656",
    "sg:postcode":"75248",
    "sg:province":"TX",
    "sg:tags":[
        "loan",
        "real estate"
    ],
    "wof:name":"North Texas Affordable Mtg",
    "wof:placetype":"venue"
},
  "geometry": {"coordinates":[-96.82074299999999,32.968615],"type":"Point"}
}