{
  "type": "Feature",
  "properties": {
    "iso:country":"US",
    "sg:address":"2520 Tarpley Rd",
    "sg:city":"Carrollton",
    "sg:classifiers":[
        {
            "category":"Shopping",
            "subcategory":"Computers & Home Electronics",
            "type":"Retail Goods"
        }
    ],
    "sg:phone":"+1 214 552 5772",
    "sg:postcode":"75006",
    "sg:province":"TX",
    "sg:tags":[
        "game",
        "video"
    ],
    "wof:name":"Quarterly Statements",
    "wof:placetype":"venue"
},
  "geometry": {"coordinates":[-96.851585,32.983256],"type":"Point"}
}