{
  "type": "Feature",
  "properties": {
    "iso:country":"US",
    "sg:address":"832 Saint James",
    "sg:city":"Seguin",
    "sg:classifiers":[
        {
            "category":"Manufacturing",
            "subcategory":"Printing",
            "type":"Manufacturing & Wholesale Goods"
        }
    ],
    "sg:phone":"+1 830 303 1097",
    "sg:postcode":"78155",
    "sg:province":"TX",
    "sg:tags":[
        "lithographic",
        "commercial"
    ],
    "wof:name":"Futura Print Solutions",
    "wof:placetype":"venue"
},
  "geometry": {"coordinates":[-97.976551,29.548199],"type":"Point"}
}