{
  "type": "Feature",
  "properties": {
    "iso:country":"US",
    "sg:address":"1 Flat Top Cir",
    "sg:city":"Wichita Falls",
    "sg:classifiers":[
        {
            "category":"Health Services",
            "subcategory":"Health Practitioner",
            "type":"Services"
        }
    ],
    "sg:phone":"+1 940 691 6523",
    "sg:postcode":"76308",
    "sg:province":"TX",
    "wof:name":"John Salkeld",
    "wof:placetype":"venue"
},
  "geometry": {"coordinates":[-98.545036,33.848346],"type":"Point"}
}