{
  "type": "Feature",
  "properties": {
    "iso:country":"US",
    "sg:address":"240 Hill St",
    "sg:city":"Albany",
    "sg:classifiers":[
        {
            "category":"Retail",
            "subcategory":"Funeral Services",
            "type":"Services"
        }
    ],
    "sg:phone":"+1 325 762 2211",
    "sg:postcode":"76430",
    "sg:province":"TX",
    "sg:tags":[
        "director"
    ],
    "wof:name":"Godfrey-Neese Funeral Home",
    "wof:placetype":"venue"
},
  "geometry": {"coordinates":[-99.29089999999999,32.729849],"type":"Point"}
}