{
  "type": "Feature",
  "properties": {
    "iso:country":"US",
    "sg:address":"2217 Hollister St",
    "sg:city":"Houston",
    "sg:classifiers":[
        {
            "category":"Organizations",
            "subcategory":"Religious Organization",
            "type":"Services"
        }
    ],
    "sg:phone":"+1 713 984 0657",
    "sg:postcode":"77080",
    "sg:province":"TX",
    "wof:name":"Scarttered Seed Ministries",
    "wof:placetype":"venue"
},
  "geometry": {"coordinates":[-95.509641,29.813975],"type":"Point"}
}