{
  "type": "Feature",
  "properties": {
    "iso:country":"US",
    "sg:address":"120 Jena Ln",
    "sg:city":"Lumberton",
    "sg:classifiers":[
        {
            "category":"Wholesale",
            "subcategory":"Construction Materials",
            "type":"Manufacturing & Wholesale Goods"
        }
    ],
    "sg:phone":"+1 409 755 4528",
    "sg:postcode":"77657",
    "sg:province":"TX",
    "sg:tags":[
        "building",
        "broker"
    ],
    "wof:name":"Bayless Enterprises",
    "wof:placetype":"venue"
},
  "geometry": {"coordinates":[-94.208327,30.273748],"type":"Point"}
}