{
  "type": "Feature",
  "properties": {
    "iso:country":"US",
    "sg:address":"190 W State Highway 114 C",
    "sg:city":"Southlake",
    "sg:classifiers":[
        {
            "category":"Professional",
            "subcategory":"Management & Consulting",
            "type":"Services"
        },
        {
            "category":"Professional",
            "subcategory":"Engineering",
            "type":"Services"
        }
    ],
    "sg:phone":"+1 817 481 6280",
    "sg:postcode":"76092",
    "sg:province":"TX",
    "sg:tags":[
        "environmental",
        "ecological",
        "engineer",
        "consultant"
    ],
    "sg:website":"http://www.dfwiaq.com",
    "wof:name":"I A Q Consultants Inc",
    "wof:placetype":"venue"
},
  "geometry": {"coordinates":[-97.152687,32.962501],"type":"Point"}
}