{
  "type": "Feature",
  "properties": {
    "iso:country":"US",
    "sg:address":"2902 Silver Falls Dr",
    "sg:city":"Humble",
    "sg:classifiers":[
        {
            "category":"Professional",
            "subcategory":"Engineering",
            "type":"Services"
        }
    ],
    "sg:phone":"+1 281 359 2017",
    "sg:postcode":"77339",
    "sg:province":"TX",
    "wof:name":"Ladecs Engineering",
    "wof:placetype":"venue"
},
  "geometry": {"coordinates":[-95.19817500000001,30.06703],"type":"Point"}
}