{
  "type": "Feature",
  "properties": {
    "iso:country":"US",
    "sg:address":"3721 Cedar Plaza Ln",
    "sg:city":"Dallas",
    "sg:classifiers":[
        {
            "category":"Building & Trades",
            "subcategory":"Construction",
            "type":"Services"
        }
    ],
    "sg:phone":"+1 214 599 0607",
    "sg:postcode":"75209",
    "sg:province":"TX",
    "sg:tags":[
        "painter"
    ],
    "wof:name":"Dodd's Make Ready Svc",
    "wof:placetype":"venue"
},
  "geometry": {"coordinates":[-96.81932500000001,32.82785],"type":"Point"}
}