{
  "type": "Feature",
  "properties": {
    "iso:country":"US",
    "sg:address":"1999 Bryan St Ste 3470",
    "sg:city":"Dallas",
    "sg:classifiers":[
        {
            "category":"Professional",
            "subcategory":"Lawyer & Legal Services",
            "type":"Services"
        }
    ],
    "sg:phone":"+1 214 665 4155",
    "sg:postcode":"75201",
    "sg:province":"TX",
    "wof:name":"Wiggins Kevin Atty",
    "wof:placetype":"venue"
},
  "geometry": {"coordinates":[-96.7967,32.784599],"type":"Point"}
}