{
  "type": "Feature",
  "properties": {
    "iso:country":"US",
    "sg:address":"2501 Versailles Dr",
    "sg:city":"Cedar Park",
    "sg:classifiers":[
        {
            "category":"Banks & Credit Unions",
            "subcategory":"Bank",
            "type":"Services"
        }
    ],
    "sg:phone":"+1 512 258 5404",
    "sg:postcode":"78613",
    "sg:province":"TX",
    "sg:tags":[
        "loan",
        "real estate"
    ],
    "wof:name":"Drummond Mortgage Investments",
    "wof:placetype":"venue"
},
  "geometry": {"coordinates":[-97.806439,30.482342],"type":"Point"}
}