{
  "type": "Feature",
  "properties": {
    "iso:country":"US",
    "sg:address":"4601 Hondo Pass Ave",
    "sg:city":"El Paso",
    "sg:classifiers":[
        {
            "category":"Shopping",
            "subcategory":"Bicycles & Sporting Goods",
            "type":"Retail Goods"
        }
    ],
    "sg:phone":"+1 915 757 8585",
    "sg:postcode":"79904",
    "sg:province":"TX",
    "wof:name":"Franklin Mountain Cyclery",
    "wof:placetype":"venue"
},
  "geometry": {"coordinates":[-106.434657,31.869747],"type":"Point"}
}