{
  "type": "Feature",
  "properties": {
    "iso:country":"US",
    "sg:address":"4122 S Hughes St",
    "sg:city":"Amarillo",
    "sg:classifiers":[
        {
            "category":"Insurance",
            "subcategory":"Insurance Agent",
            "type":"Services"
        }
    ],
    "sg:phone":"+1 806 358 0988",
    "sg:postcode":"79110",
    "sg:province":"TX",
    "wof:name":"O'Dell Insurance",
    "wof:placetype":"venue"
},
  "geometry": {"coordinates":[-101.849761,35.169521],"type":"Point"}
}