{
  "type": "Feature",
  "properties": {
    "iso:country":"US",
    "sg:address":"2914 Gateway Blvd E",
    "sg:city":"El Paso",
    "sg:classifiers":[
        {
            "category":"Home & Garden",
            "subcategory":"Household Appliances",
            "type":"Retail Goods"
        }
    ],
    "sg:phone":"+1 915 544 3350",
    "sg:postcode":"79905",
    "sg:province":"TX",
    "wof:name":"Akrit Appliance Parts",
    "wof:placetype":"venue"
},
  "geometry": {"coordinates":[-106.46015199999999,31.777525],"type":"Point"}
}