{
  "type": "Feature",
  "properties": {
    "iso:country":"US",
    "sg:address":"2055 Silber Rd Ste 130",
    "sg:city":"Houston",
    "sg:classifiers":[
        {
            "category":"Shopping",
            "subcategory":"Stationery & Office Supplies",
            "type":"Retail Goods"
        }
    ],
    "sg:phone":"+1 713 812 7722",
    "sg:postcode":"77055",
    "sg:province":"TX",
    "sg:tags":[
        "equipment"
    ],
    "wof:name":"Royal Office Products Inc",
    "wof:placetype":"venue"
},
  "geometry": {"coordinates":[-95.46820099999999,29.8053],"type":"Point"}
}