{
  "type": "Feature",
  "properties": {
    "iso:country":"US",
    "sg:address":"9419 N Fitzgerald Way",
    "sg:city":"Missouri City",
    "sg:classifiers":[
        {
            "category":"Education",
            "subcategory":"Special Training",
            "type":"Public Place"
        }
    ],
    "sg:phone":"+1 281 778 7696",
    "sg:postcode":"77459",
    "sg:province":"TX",
    "wof:name":"Georgias Garden",
    "wof:placetype":"venue"
},
  "geometry": {"coordinates":[-95.532629,29.501947],"type":"Point"}
}