{
  "type": "Feature",
  "properties": {
    "iso:country":"US",
    "sg:address":"2206 Gano St",
    "sg:city":"Houston",
    "sg:classifiers":[
        {
            "category":"Shopping",
            "subcategory":"Gifts & Souvenirs",
            "type":"Retail Goods"
        }
    ],
    "sg:phone":"+1 713 223 5203",
    "sg:postcode":"77009",
    "sg:province":"TX",
    "wof:name":"Rossy Pulido",
    "wof:placetype":"venue"
},
  "geometry": {"coordinates":[-95.354613,29.782314],"type":"Point"}
}