{
  "type": "Feature",
  "properties": {
    "iso:country":"US",
    "sg:address":"14405 Walters Rd",
    "sg:city":"Houston",
    "sg:classifiers":[
        {
            "category":"Professional",
            "subcategory":"Research",
            "type":"Services"
        }
    ],
    "sg:phone":"+1 281 444 0040",
    "sg:postcode":"77014",
    "sg:province":"TX",
    "sg:tags":[
        "analysis",
        "market"
    ],
    "wof:name":"The Gallup Organization",
    "wof:placetype":"venue"
},
  "geometry": {"coordinates":[-95.48186200000001,29.990978],"type":"Point"}
}