{
  "type": "Feature",
  "properties": {
    "iso:country":"US",
    "sg:address":"2219 Larry Dr",
    "sg:city":"Port Lavaca",
    "sg:classifiers":[
        {
            "category":"Health Services",
            "subcategory":"Doctor",
            "type":"Services"
        }
    ],
    "sg:phone":"+1 361 552 9510",
    "sg:postcode":"77979",
    "sg:province":"TX",
    "wof:name":"Jack E Beeler DDS",
    "wof:placetype":"venue"
},
  "geometry": {"coordinates":[-96.634315,28.592835],"type":"Point"}
}