{
  "type": "Feature",
  "properties": {
    "iso:country":"US",
    "sg:address":"2812 N MacArthur Blvd",
    "sg:city":"Irving",
    "sg:classifiers":[
        {
            "category":"Bakery",
            "type":"Food & Drink"
        }
    ],
    "sg:phone":"+1 972 258 6585",
    "sg:postcode":"75062",
    "sg:province":"TX",
    "wof:name":"Busy B's Bakery",
    "wof:placetype":"venue"
},
  "geometry": {"coordinates":[-96.958995,32.844946],"type":"Point"}
}