{
  "type": "Feature",
  "properties": {
    "iso:country":"US",
    "sg:address":"3800 Commerce St",
    "sg:city":"Dallas",
    "sg:classifiers":[
        {
            "category":"Real Estate",
            "subcategory":"Real Estate Agent",
            "type":"Services"
        }
    ],
    "sg:phone":"+1 214 824 7700",
    "sg:postcode":"75226",
    "sg:province":"TX",
    "wof:name":"Kirtland Realty Gruop",
    "wof:placetype":"venue"
},
  "geometry": {"coordinates":[-96.77109799999999,32.784298],"type":"Point"}
}