{
  "type": "Feature",
  "properties": {
    "iso:country":"US",
    "sg:address":"118 W Texas St",
    "sg:city":"Sherman",
    "sg:classifiers":[
        {
            "category":"Building & Trades",
            "subcategory":"Construction",
            "type":"Services"
        }
    ],
    "sg:phone":"+1 903 892 2777",
    "sg:postcode":"75092",
    "sg:province":"TX",
    "sg:tags":[
        "general",
        "contractor"
    ],
    "wof:name":"3 D Construction",
    "wof:placetype":"venue"
},
  "geometry": {"coordinates":[-96.61681,33.651958],"type":"Point"}
}