{
  "type": "Feature",
  "properties": {
    "iso:country":"US",
    "sg:address":"1193 US Hwy 90",
    "sg:city":"Hondo",
    "sg:phone":"+1 830 426 5838",
    "sg:postcode":"78861",
    "sg:province":"TX",
    "sg:tags":[
        "farm",
        "ranch"
    ],
    "wof:name":"Schoellman Farm Inc",
    "wof:placetype":"venue"
},
  "geometry": {"coordinates":[-99.094341,29.349849],"type":"Point"}
}