{
  "type": "Feature",
  "properties": {
    "iso:country":"US",
    "sg:address":"3630 W Pioneer Pkwy",
    "sg:city":"Arlington",
    "sg:classifiers":[
        {
            "category":"Travel",
            "subcategory":"Travel Agent",
            "type":"Entertainment"
        }
    ],
    "sg:phone":"+1 817 548 8887",
    "sg:postcode":"76013",
    "sg:province":"TX",
    "sg:tags":[
        "agency",
        "bureau"
    ],
    "wof:name":"Resort Travel Marketing",
    "wof:placetype":"venue"
},
  "geometry": {"coordinates":[-97.16416700000001,32.713013],"type":"Point"}
}