{
  "type": "Feature",
  "properties": {
    "iso:country":"US",
    "sg:address":"421 E 34th Ave",
    "sg:city":"Amarillo",
    "sg:classifiers":[
        {
            "category":"Wholesale",
            "subcategory":"Books, Periodicals, & Newspapers",
            "type":"Manufacturing & Wholesale Goods"
        }
    ],
    "sg:phone":"+1 806 376 6251",
    "sg:postcode":"79103",
    "sg:province":"TX",
    "sg:tags":[
        "dealer"
    ],
    "sg:website":"www.andersonmerch.com",
    "wof:name":"Anderson Merchandisers Inc",
    "wof:placetype":"venue"
},
  "geometry": {"coordinates":[-101.835312,35.178405],"type":"Point"}
}