{
  "type": "Feature",
  "properties": {
    "iso:country":"US",
    "sg:address":"6473 de Zavala Rd",
    "sg:city":"San Antonio",
    "sg:classifiers":[
        {
            "category":"Retail",
            "subcategory":"Auto Repair",
            "type":"Services"
        },
        {
            "category":"Retail",
            "subcategory":"Auto Rental",
            "type":"Services"
        }
    ],
    "sg:phone":"+1 210 697 8884",
    "sg:postcode":"78249",
    "sg:province":"TX",
    "sg:tags":[
        "passenger",
        "conversion",
        "van",
        "handicap",
        "car",
        "vehicle",
        "sales",
        "accessory",
        "truck",
        "bus",
        "modifies"
    ],
    "sg:website":"www.alamomobility.com",
    "wof:name":"Alamo Mobility Inc",
    "wof:placetype":"venue"
},
  "geometry": {"coordinates":[-98.615076,29.560753],"type":"Point"}
}