{
  "type": "Feature",
  "properties": {
    "iso:country":"US",
    "sg:address":"16843 Bouldgreen",
    "sg:city":"Houston",
    "sg:classifiers":[
        {
            "category":"Shopping",
            "subcategory":"Computers & Home Electronics",
            "type":"Retail Goods"
        }
    ],
    "sg:phone":"+1 281 856 8002",
    "sg:postcode":"77084",
    "sg:province":"TX",
    "wof:name":"Alltech Computer Service Inc",
    "wof:placetype":"venue"
},
  "geometry": {"coordinates":[-95.663551,29.872803],"type":"Point"}
}