{
  "type": "Feature",
  "properties": {
    "iso:country":"US",
    "sg:address":"10301 Northwest Fwy Ste 408",
    "sg:city":"Houston",
    "sg:classifiers":[
        {
            "category":"Health Services",
            "subcategory":"Dentist",
            "type":"Services"
        }
    ],
    "sg:phone":"+1 713 957 2222",
    "sg:postcode":"77092",
    "sg:province":"TX",
    "wof:name":"Stanford Ben Properties BDS",
    "wof:placetype":"venue"
},
  "geometry": {"coordinates":[-95.457497,29.808399],"type":"Point"}
}