{
  "type": "Feature",
  "properties": {
    "iso:country":"US",
    "sg:address":"1305 Preston Ave",
    "sg:city":"Pasadena",
    "sg:classifiers":[
        {
            "category":"Autos & Motor Vehicles",
            "subcategory":"Auto Supplies",
            "type":"Retail Goods"
        }
    ],
    "sg:phone":"+1 713 395 3321",
    "sg:postcode":"77503",
    "sg:province":"TX",
    "sg:tags":[
        "tire"
    ],
    "wof:name":"Oscar's Tire Service",
    "wof:placetype":"venue"
},
  "geometry": {"coordinates":[-95.1726,29.691601],"type":"Point"}
}