{
  "type": "Feature",
  "properties": {
    "iso:country":"US",
    "sg:address":"737 Anderson St",
    "sg:city":"Corpus Christi",
    "sg:classifiers":[
        {
            "category":"Building & Trades",
            "subcategory":"Pest Control",
            "type":"Services"
        }
    ],
    "sg:phone":"+1 361 855 5319",
    "sg:postcode":"78411",
    "sg:province":"TX",
    "wof:name":"Perfection Pest",
    "wof:placetype":"venue"
},
  "geometry": {"coordinates":[-97.387495,27.746904],"type":"Point"}
}