{
  "type": "Feature",
  "properties": {
    "iso:country":"US",
    "sg:address":"1101 Navasota St",
    "sg:city":"Austin",
    "sg:classifiers":[
        {
            "category":"Real Estate",
            "subcategory":"Real Estate Agent",
            "type":"Services"
        }
    ],
    "sg:phone":"+1 512 457 0993",
    "sg:postcode":"78702",
    "sg:province":"TX",
    "sg:tags":[
        "building",
        "operator",
        "apartment"
    ],
    "wof:name":"Commerce Austin Realty",
    "wof:placetype":"venue"
},
  "geometry": {"coordinates":[-97.727087,30.269226],"type":"Point"}
}