{
  "type": "Feature",
  "properties": {
    "iso:country":"US",
    "sg:address":"6600 US Hwy 183",
    "sg:city":"Liberty Hill",
    "sg:classifiers":[
        {
            "category":"Utilities",
            "subcategory":"Electric",
            "type":"Services"
        }
    ],
    "sg:phone":"+1 254 793 3009",
    "sg:postcode":"78642",
    "sg:province":"TX",
    "sg:tags":[
        "company"
    ],
    "wof:name":"LCRA Andice Sub-Station",
    "wof:placetype":"venue"
},
  "geometry": {"coordinates":[-97.876493,30.750222],"type":"Point"}
}