{
  "type": "Feature",
  "properties": {
    "iso:country":"US",
    "sg:address":"25000 Pitkin Rd",
    "sg:city":"Spring",
    "sg:classifiers":[
        {
            "category":"Social Services",
            "type":"Services"
        }
    ],
    "sg:phone":"+1 281 298 6622",
    "sg:postcode":"77386",
    "sg:province":"TX",
    "wof:name":"Young Life Latin American Reg",
    "wof:placetype":"venue"
},
  "geometry": {"coordinates":[-95.439903,30.122019],"type":"Point"}
}