{
  "type": "Feature",
  "properties": {
    "iso:country":"US",
    "sg:address":"5003 Orange Tree Dr",
    "sg:city":"Pasadena",
    "sg:classifiers":[
        {
            "category":"Airport",
            "type":"Transportation"
        }
    ],
    "sg:phone":"+1 281 998 9575",
    "sg:postcode":"77505",
    "sg:province":"TX",
    "wof:name":"M C Aviation Inc",
    "wof:placetype":"venue"
},
  "geometry": {"coordinates":[-95.134471,29.637164],"type":"Point"}
}