{
  "type": "Feature",
  "properties": {
    "iso:country":"US",
    "sg:address":"2307 Austin Hwy",
    "sg:city":"San Antonio",
    "sg:classifiers":[
        {
            "category":"Banks & Credit Unions",
            "subcategory":"Bank",
            "type":"Services"
        }
    ],
    "sg:phone":"+1 210 653 3839",
    "sg:postcode":"78218",
    "sg:province":"TX",
    "wof:name":"Family Credit Motors",
    "wof:placetype":"venue"
},
  "geometry": {"coordinates":[-98.415851,29.50433],"type":"Point"}
}