{
  "type": "Feature",
  "properties": {
    "iso:country":"US",
    "sg:address":"3618 3rd St",
    "sg:city":"Brookshire",
    "sg:classifiers":[
        {
            "category":"Health Services",
            "subcategory":"Doctor",
            "type":"Services"
        }
    ],
    "sg:phone":"+1 281 375 6994",
    "sg:postcode":"77423",
    "sg:province":"TX",
    "sg:tags":[
        "medical"
    ],
    "wof:name":"Brookshire Diagnstc Trtmnt Ctr",
    "wof:placetype":"venue"
},
  "geometry": {"coordinates":[-95.94860199999999,29.789235],"type":"Point"}
}