{
  "type": "Feature",
  "properties": {
    "iso:country":"US",
    "sg:address":"932 Harrington St",
    "sg:city":"Borger",
    "sg:classifiers":[
        {
            "category":"Home & Garden",
            "subcategory":"Mobile Homes",
            "type":"Retail Goods"
        }
    ],
    "sg:phone":"+1 806 273 9714",
    "sg:postcode":"79007",
    "sg:province":"TX",
    "wof:name":"Home Sale Lindas",
    "wof:placetype":"venue"
},
  "geometry": {"coordinates":[-101.402447,35.680469],"type":"Point"}
}