{
  "type": "Feature",
  "properties": {
    "iso:country":"US",
    "sg:address":"607 Franklin St",
    "sg:city":"Fredericksburg",
    "sg:classifiers":[
        {
            "category":"Professional",
            "type":"Services"
        }
    ],
    "sg:phone":"+1 830 997 2799",
    "sg:postcode":"78624",
    "sg:province":"TX",
    "sg:tags":[
        "establishment"
    ],
    "wof:name":"Cottage Collections",
    "wof:placetype":"venue"
},
  "geometry": {"coordinates":[-98.86404400000001,30.265043],"type":"Point"}
}