{
  "type": "Feature",
  "properties": {
    "iso:country":"US",
    "sg:address":"2103 Muddy Peak Dr",
    "sg:city":"San Antonio",
    "sg:classifiers":[
        {
            "category":"Professional",
            "subcategory":"Detective & Security Services",
            "type":"Services"
        }
    ],
    "sg:phone":"+1 210 678 9466",
    "sg:postcode":"78245",
    "sg:province":"TX",
    "sg:tags":[
        "guard"
    ],
    "wof:name":"Claude Denson",
    "wof:placetype":"venue"
},
  "geometry": {"coordinates":[-98.696871,29.406872],"type":"Point"}
}