{
  "type": "Feature",
  "properties": {
    "iso:country":"US",
    "sg:address":"1330 Post Oak Blvd",
    "sg:city":"Houston",
    "sg:classifiers":[
        {
            "category":"Cafe",
            "type":"Food & Drink"
        }
    ],
    "sg:menulink":"http://www.allmenus.com/tx/houston/15241-alonti-market-cafe/menu/",
    "sg:phone":"+1 713 850 8285",
    "sg:postcode":"77056",
    "sg:province":"TX",
    "sg:tags":[
        "american"
    ],
    "wof:name":"Alonti Market Cafe",
    "wof:placetype":"venue"
},
  "geometry": {"coordinates":[-95.45948199999999,29.752974],"type":"Point"}
}