{
  "type": "Feature",
  "properties": {
    "iso:country":"US",
    "sg:address":"700 S Cockrell Hill Rd",
    "sg:city":"Duncanville",
    "sg:classifiers":[
        {
            "category":"Banks & Credit Unions",
            "subcategory":"Bank",
            "type":"Services"
        }
    ],
    "sg:phone":"+1 972 296 1841",
    "sg:postcode":"75137",
    "sg:province":"TX",
    "sg:tags":[
        "financing"
    ],
    "wof:name":"Citi Financial Svc",
    "wof:placetype":"venue"
},
  "geometry": {"coordinates":[-96.8914,32.641904],"type":"Point"}
}