{
  "type": "Feature",
  "properties": {
    "iso:country":"US",
    "sg:address":"16922 Serenity Cove Cir",
    "sg:city":"Friendswood",
    "sg:classifiers":[
        {
            "category":"Fast Food",
            "type":"Food & Drink"
        },
        {
            "category":"Restaurant",
            "type":"Food & Drink"
        }
    ],
    "sg:phone":"+1 281 724 8859",
    "sg:postcode":"77546",
    "sg:province":"TX",
    "sg:tags":[
        "take"
    ],
    "wof:name":"Friendswood Bullet Co",
    "wof:placetype":"venue"
},
  "geometry": {"coordinates":[-95.167152,29.529383],"type":"Point"}
}