{
  "type": "Feature",
  "properties": {
    "iso:country":"US",
    "sg:address":"2010 N Loop Fwy",
    "sg:city":"Houston",
    "sg:classifiers":[
        {
            "category":"Professional",
            "subcategory":"Computer Services",
            "type":"Services"
        }
    ],
    "sg:phone":"+1 713 956 6060",
    "sg:postcode":"77018",
    "sg:province":"TX",
    "sg:tags":[
        "repair"
    ],
    "wof:name":"Computer Troubleshooters",
    "wof:placetype":"venue"
},
  "geometry": {"coordinates":[-95.43592200000001,29.811807],"type":"Point"}
}