{
  "type": "Feature",
  "properties": {
    "iso:country":"US",
    "sg:address":"1401 N 3rd St",
    "sg:city":"Temple",
    "sg:classifiers":[
        {
            "category":"Freight",
            "type":"Transportation"
        }
    ],
    "sg:phone":"+1 254 773 6812",
    "sg:postcode":"76501",
    "sg:province":"TX",
    "sg:tags":[
        "general"
    ],
    "wof:name":"Coca-Cola",
    "wof:placetype":"venue"
},
  "geometry": {"coordinates":[-97.33754399999999,31.111849],"type":"Point"}
}