{
  "type": "Feature",
  "properties": {
    "iso:country":"US",
    "sg:address":"311 S Marable St",
    "sg:city":"West",
    "sg:classifiers":[
        {
            "category":"Personal",
            "subcategory":"Beauty Salon",
            "type":"Services"
        }
    ],
    "sg:phone":"+1 254 826 5048",
    "sg:postcode":"76691",
    "sg:province":"TX",
    "wof:name":"Ann S Mary Beauty Shop",
    "wof:placetype":"venue"
},
  "geometry": {"coordinates":[-97.097324,31.800032],"type":"Point"}
}