{
  "type": "Feature",
  "properties": {
    "iso:country":"US",
    "sg:address":"2718 Elder Rd",
    "sg:city":"Katy",
    "sg:classifiers":[
        {
            "category":"Manufacturing",
            "subcategory":"Retail Goods",
            "type":"Manufacturing & Wholesale Goods"
        }
    ],
    "sg:phone":"+1 281 391 8397",
    "sg:postcode":"77493",
    "sg:province":"TX",
    "sg:tags":[
        "product",
        "mfg"
    ],
    "wof:name":"Marys Embrace",
    "wof:placetype":"venue"
},
  "geometry": {"coordinates":[-95.82055200000001,29.816497],"type":"Point"}
}