{
  "type": "Feature",
  "properties": {
    "iso:country":"US",
    "sg:address":"159 Mockingbird Ln",
    "sg:city":"Livingston",
    "sg:classifiers":[
        {
            "category":"Professional",
            "subcategory":"Management & Consulting",
            "type":"Services"
        }
    ],
    "sg:phone":"+1 936 327 2255",
    "sg:postcode":"77351",
    "sg:province":"TX",
    "wof:name":"Rounds GP Management LLC",
    "wof:placetype":"venue"
},
  "geometry": {"coordinates":[-94.940433,30.698694],"type":"Point"}
}