{
  "type": "Feature",
  "properties": {
    "iso:country":"US",
    "sg:address":"4203 Oro Ct",
    "sg:city":"Georgetown",
    "sg:classifiers":[
        {
            "category":"Building & Trades",
            "subcategory":"Landscaping Services",
            "type":"Services"
        }
    ],
    "sg:phone":"+1 512 626 7550",
    "sg:postcode":"78628",
    "sg:province":"TX",
    "wof:name":"Residential Lawn Care",
    "wof:placetype":"venue"
},
  "geometry": {"coordinates":[-97.695882,30.690052],"type":"Point"}
}