{
  "type": "Feature",
  "properties": {
    "iso:country":"US",
    "sg:address":"4609 Fairlane Ave",
    "sg:city":"Fort Worth",
    "sg:classifiers":[
        {
            "category":"Wholesale",
            "subcategory":"Machinery & Supplies",
            "type":"Manufacturing & Wholesale Goods"
        }
    ],
    "sg:phone":"+1 817 534 9192",
    "sg:postcode":"76119",
    "sg:province":"TX",
    "sg:tags":[
        "industrial",
        "metal",
        "center",
        "mfg"
    ],
    "wof:name":"Texas Alloys & Tool Co",
    "wof:placetype":"venue"
},
  "geometry": {"coordinates":[-97.254508,32.693822],"type":"Point"}
}