{
  "type": "Feature",
  "properties": {
    "iso:country":"US",
    "sg:address":"1217 N Main Ave",
    "sg:city":"Monahans",
    "sg:classifiers":[
        {
            "category":"Restaurant",
            "type":"Food & Drink"
        }
    ],
    "sg:phone":"+1 432 943 7220",
    "sg:postcode":"79756",
    "sg:province":"TX",
    "sg:tags":[
        "eating"
    ],
    "wof:name":"Cindy's Restaurant",
    "wof:placetype":"venue"
},
  "geometry": {"coordinates":[-102.89858,31.603031],"type":"Point"}
}