{
  "type": "Feature",
  "properties": {
    "iso:country":"US",
    "sg:address":"510 County Road 161",
    "sg:city":"Ovalo",
    "sg:classifiers":[
        {
            "category":"Insurance",
            "subcategory":"Hazard Insurance",
            "type":"Services"
        }
    ],
    "sg:phone":"+1 325 554 9069",
    "sg:postcode":"79541",
    "sg:province":"TX",
    "sg:tags":[
        "commercial",
        "business"
    ],
    "sg:website":"http://www.farmers.com",
    "wof:name":"Farmers Insurance Group",
    "wof:placetype":"venue"
},
  "geometry": {"coordinates":[-99.787758,32.189072],"type":"Point"}
}