{
  "type": "Feature",
  "properties": {
    "iso:country":"US",
    "sg:address":"107 E Cordele St",
    "sg:city":"Edna",
    "sg:classifiers":[
        {
            "category":"Real Estate",
            "subcategory":"Real Estate Services",
            "type":"Services"
        },
        {
            "category":"Real Estate",
            "subcategory":"Real Estate Operator",
            "type":"Services"
        }
    ],
    "sg:phone":"+1 361 782 5872",
    "sg:postcode":"77957",
    "sg:province":"TX",
    "sg:tags":[
        "vacancy",
        "apartment",
        "rental",
        "listing"
    ],
    "wof:name":"Cordele Village",
    "wof:placetype":"venue"
},
  "geometry": {"coordinates":[-96.651909,28.991528],"type":"Point"}
}