{
  "type": "Feature",
  "properties": {
    "iso:country":"US",
    "sg:address":"203 Oakwood Loop",
    "sg:city":"San Marcos",
    "sg:classifiers":[
        {
            "category":"Food & Beverages",
            "subcategory":"Bakery",
            "type":"Retail Goods"
        }
    ],
    "sg:phone":"+1 512 396 4007",
    "sg:postcode":"78666",
    "sg:province":"TX",
    "wof:name":"Cakes By Sue",
    "wof:placetype":"venue"
},
  "geometry": {"coordinates":[-98.075467,29.939829],"type":"Point"}
}