{
  "type": "Feature",
  "properties": {
    "iso:country":"US",
    "sg:address":"3562 Good Hope St",
    "sg:city":"Houston",
    "sg:classifiers":[
        {
            "category":"Personal",
            "subcategory":"Barber",
            "type":"Services"
        }
    ],
    "sg:phone":"+1 713 747 4032",
    "sg:postcode":"77021",
    "sg:province":"TX",
    "wof:name":"Big Willie's Three-In-One",
    "wof:placetype":"venue"
},
  "geometry": {"coordinates":[-95.373908,29.684139],"type":"Point"}
}