{
  "type": "Feature",
  "properties": {
    "iso:country":"US",
    "sg:address":"2057 Commerce St",
    "sg:city":"Belton",
    "sg:classifiers":[
        {
            "category":"Manufacturing",
            "subcategory":"Tools & Machinery",
            "type":"Manufacturing & Wholesale Goods"
        }
    ],
    "sg:phone":"+1 254 939 9404",
    "sg:postcode":"76513",
    "sg:province":"TX",
    "sg:tags":[
        "boring",
        "drilling"
    ],
    "sg:website":"www.belltec.net",
    "wof:name":"Belltec Industries Inc",
    "wof:placetype":"venue"
},
  "geometry": {"coordinates":[-97.464561,31.079322],"type":"Point"}
}