{
  "type": "Feature",
  "properties": {
    "iso:country":"US",
    "sg:address":"2317 E Missouri Ave",
    "sg:city":"El Paso",
    "sg:classifiers":[
        {
            "category":"Manufacturing",
            "subcategory":"Printing",
            "type":"Manufacturing & Wholesale Goods"
        }
    ],
    "sg:phone":"+1 915 544 4704",
    "sg:postcode":"79903",
    "sg:province":"TX",
    "sg:tags":[
        "printer"
    ],
    "wof:name":"Celestial Business Forms",
    "wof:placetype":"venue"
},
  "geometry": {"coordinates":[-106.46612,31.77705],"type":"Point"}
}