{
  "type": "Feature",
  "properties": {
    "iso:country":"US",
    "sg:address":"855 W Washington St",
    "sg:city":"Stephenville",
    "sg:classifiers":[
        {
            "category":"Retail",
            "subcategory":"Auto Repair",
            "type":"Services"
        }
    ],
    "sg:phone":"+1 254 968 2285",
    "sg:postcode":"76401",
    "sg:province":"TX",
    "sg:tags":[
        "repairing",
        "automobile"
    ],
    "wof:name":"Dewayne's Automotive Ctr",
    "wof:placetype":"venue"
},
  "geometry": {"coordinates":[-98.209098,32.217248],"type":"Point"}
}