{
  "type": "Feature",
  "properties": {
    "iso:country":"US",
    "sg:address":"3117 Rosa Ave",
    "sg:city":"El Paso",
    "sg:classifiers":[
        {
            "category":"Building & Trades",
            "subcategory":"Plumbing",
            "type":"Services"
        }
    ],
    "sg:phone":"+1 915 533 1756",
    "sg:postcode":"79905",
    "sg:province":"TX",
    "sg:tags":[
        "conditioning",
        "air",
        "system",
        "contractor"
    ],
    "wof:name":"Gateway Air Conditioning Co",
    "wof:placetype":"venue"
},
  "geometry": {"coordinates":[-106.457162,31.775571],"type":"Point"}
}