{
  "type": "Feature",
  "properties": {
    "iso:country":"US",
    "sg:address":"2637 E Carter Ave",
    "sg:city":"Fort Worth",
    "sg:classifiers":[
        {
            "category":"Wholesale",
            "subcategory":"Non-durable Goods",
            "type":"Manufacturing & Wholesale Goods"
        }
    ],
    "sg:phone":"+1 817 536 2316",
    "sg:postcode":"76103",
    "sg:province":"TX",
    "sg:tags":[
        "business"
    ],
    "wof:name":"Verner Publishing",
    "wof:placetype":"venue"
},
  "geometry": {"coordinates":[-97.288048,32.746768],"type":"Point"}
}