{
  "type": "Feature",
  "properties": {
    "iso:country":"US",
    "sg:address":"907 W 5th St",
    "sg:city":"Austin",
    "sg:classifiers":[
        {
            "category":"Utilities",
            "subcategory":"Mobile Phone",
            "type":"Services"
        },
        {
            "category":"Coffee & Tea",
            "type":"Food & Drink"
        }
    ],
    "sg:phone":"+1 512 708 9103",
    "sg:postcode":"78703",
    "sg:province":"TX",
    "sg:tags":[
        "shop",
        "wi-fi",
        "espresso",
        "hotspot",
        "restaurant"
    ],
    "sg:website":"http://www.starbuckscoffee.com",
    "wof:name":"Starbuck's Coffee",
    "wof:placetype":"venue"
},
  "geometry": {"coordinates":[-97.753304,30.2698],"type":"Point"}
}