{
  "type": "Feature",
  "properties": {
    "iso:country":"US",
    "sg:address":"2911B S 1st St",
    "sg:city":"Austin",
    "sg:classifiers":[
        {
            "category":"Personal",
            "subcategory":"Nail Salon",
            "type":"Services"
        }
    ],
    "sg:phone":"+1 512 804 5228",
    "sg:postcode":"78704",
    "sg:province":"TX",
    "wof:name":"Great Nails & Spa",
    "wof:placetype":"venue"
},
  "geometry": {"coordinates":[-97.763344,30.235657],"type":"Point"}
}