{
  "type": "Feature",
  "properties": {
    "iso:country":"US",
    "sg:address":"8928 Sweetwater Dr",
    "sg:city":"Dallas",
    "sg:classifiers":[
        {
            "category":"Manufacturing",
            "subcategory":"Printing",
            "type":"Manufacturing & Wholesale Goods"
        }
    ],
    "sg:phone":"+1 214 327 3571",
    "sg:postcode":"75228",
    "sg:province":"TX",
    "sg:tags":[
        "publishing"
    ],
    "wof:name":"Desktop Solutions",
    "wof:placetype":"venue"
},
  "geometry": {"coordinates":[-96.695329,32.810075],"type":"Point"}
}