{
  "type": "Feature",
  "properties": {
    "iso:country":"US",
    "sg:address":"6995 Alamo Downs Pkwy",
    "sg:city":"San Antonio",
    "sg:classifiers":[
        {
            "category":"Freight",
            "type":"Transportation"
        }
    ],
    "sg:phone":"+1 210 368 8585",
    "sg:postcode":"78238",
    "sg:province":"TX",
    "sg:tags":[
        "operator",
        "local",
        "trucking"
    ],
    "wof:name":"United Express Delivery Svc",
    "wof:placetype":"venue"
},
  "geometry": {"coordinates":[-98.621414,29.456751],"type":"Point"}
}