{
  "type": "Feature",
  "properties": {
    "iso:country":"US",
    "sg:address":"101 Uhland Rd",
    "sg:city":"San Marcos",
    "sg:classifiers":[
        {
            "category":"Education",
            "subcategory":"School",
            "type":"Public Place"
        }
    ],
    "sg:phone":"+1 512 245 2541",
    "sg:postcode":"78666",
    "sg:province":"TX",
    "wof:name":"Drug Free San Marcos",
    "wof:placetype":"venue"
},
  "geometry": {"coordinates":[-97.9186,29.898912],"type":"Point"}
}