{
  "type": "Feature",
  "properties": {
    "iso:country":"US",
    "sg:address":"3031 Co Rd 310",
    "sg:city":"Brazoria",
    "sg:classifiers":[
        {
            "category":"Building & Trades",
            "subcategory":"Pest Control",
            "type":"Services"
        }
    ],
    "sg:phone":"+1 979 297 9650",
    "sg:postcode":"77422",
    "sg:province":"TX",
    "sg:tags":[
        "disinfecting"
    ],
    "wof:name":"A & S Pest Control",
    "wof:placetype":"venue"
},
  "geometry": {"coordinates":[-95.56163100000001,28.967879],"type":"Point"}
}