{
  "type": "Feature",
  "properties": {
    "iso:country":"US",
    "sg:address":"1600 Hospital Pkwy",
    "sg:city":"Bedford",
    "sg:classifiers":[
        {
            "category":"Organizations",
            "subcategory":"Non-profit Organization",
            "type":"Services"
        }
    ],
    "sg:phone":"+1 817 355 7700",
    "sg:postcode":"76022",
    "sg:province":"TX",
    "sg:tags":[
        "info",
        "addiction",
        "abuse",
        "treatment",
        "drug"
    ],
    "wof:name":"Harris Methodist HEB Hosp",
    "wof:placetype":"venue"
},
  "geometry": {"coordinates":[-97.12528399999999,32.832755],"type":"Point"}
}