{
  "type": "Feature",
  "properties": {
    "iso:country":"US",
    "sg:address":"4701 Preston Ave",
    "sg:city":"Pasadena",
    "sg:classifiers":[
        {
            "category":"Professional",
            "subcategory":"Lawyer & Legal Services",
            "type":"Services"
        }
    ],
    "sg:phone":"+1 281 991 6095",
    "sg:postcode":"77505",
    "sg:province":"TX",
    "wof:name":"Joyner Dexter D",
    "wof:placetype":"venue"
},
  "geometry": {"coordinates":[-95.170952,29.640414],"type":"Point"}
}