{
  "type": "Feature",
  "properties": {
    "iso:country":"US",
    "sg:address":"9463 Gonzales Dr",
    "sg:city":"Dallas",
    "sg:classifiers":[
        {
            "category":"Communications",
            "subcategory":"Film & Video Production",
            "type":"Services"
        },
        {
            "category":"Organizations",
            "subcategory":"Religious Organization",
            "type":"Services"
        }
    ],
    "sg:phone":"+1 214 381 1750",
    "sg:postcode":"75227",
    "sg:province":"TX",
    "sg:tags":[
        "motion",
        "church"
    ],
    "wof:name":"Peanut's Productions",
    "wof:placetype":"venue"
},
  "geometry": {"coordinates":[-96.657726,32.766921],"type":"Point"}
}