{
  "type": "Feature",
  "properties": {
    "iso:country":"US",
    "sg:address":"4206 Oak Country Dr",
    "sg:city":"Arlington",
    "sg:classifiers":[
        {
            "category":"Building & Trades",
            "subcategory":"Cleaning & Sanitation",
            "type":"Services"
        }
    ],
    "sg:phone":"+1 817 563 7787",
    "sg:postcode":"76017",
    "sg:province":"TX",
    "sg:tags":[
        "maintenance"
    ],
    "wof:name":"B&J Building Maintenance",
    "wof:placetype":"venue"
},
  "geometry": {"coordinates":[-97.174888,32.663272],"type":"Point"}
}