{
  "type": "Feature",
  "properties": {
    "iso:country":"US",
    "sg:address":"121 Enterprise Row",
    "sg:city":"Conroe",
    "sg:classifiers":[
        {
            "category":"Airline",
            "type":"Transportation"
        }
    ],
    "sg:phone":"+1 936 760 1721",
    "sg:postcode":"77301",
    "sg:province":"TX",
    "sg:tags":[
        "courier",
        "air"
    ],
    "wof:name":"Fedex",
    "wof:placetype":"venue"
},
  "geometry": {"coordinates":[-95.456791,30.288055],"type":"Point"}
}