{
  "type": "Feature",
  "properties": {
    "iso:country":"US",
    "sg:address":"2826 Real Street",
    "sg:city":"Austin",
    "sg:classifiers":[
        {
            "category":"Arts & Performance",
            "subcategory":"Arts Center",
            "type":"Entertainment"
        },
        {
            "category":"Education",
            "subcategory":"Special Training",
            "type":"Public Place"
        }
    ],
    "sg:phone":"+1 512 836 5437",
    "sg:postcode":"78722",
    "sg:province":"TX",
    "sg:tags":[
        "school",
        "performing"
    ],
    "sg:website":"www.kidsactingstudio.com",
    "wof:name":"kidsActing Studio",
    "wof:placetype":"venue"
},
  "geometry": {"coordinates":[-97.7107,30.283129],"type":"Point"}
}