{
  "type": "Feature",
  "properties": {
    "iso:country":"US",
    "sg:address":"6706 Calumet Rd",
    "sg:city":"Amarillo",
    "sg:classifiers":[
        {
            "category":"Shopping",
            "subcategory":"Hobbies, Toys, & Games",
            "type":"Retail Goods"
        }
    ],
    "sg:phone":"+1 806 358 1177",
    "sg:postcode":"79106",
    "sg:province":"TX",
    "wof:name":"Jane Marcks Studio",
    "wof:placetype":"venue"
},
  "geometry": {"coordinates":[-101.91457,35.180863],"type":"Point"}
}