{
  "type": "Feature",
  "properties": {
    "iso:country":"US",
    "sg:address":"806 N Earl Rudder Fwy",
    "sg:city":"Bryan",
    "sg:classifiers":[
        {
            "category":"Restaurant",
            "type":"Food & Drink"
        }
    ],
    "sg:menulink":"http://www.allmenus.com/tx/south-brazos/130960-subway/menu/",
    "sg:phone":"+1 979 846 7533",
    "sg:postcode":"77802",
    "sg:province":"TX",
    "sg:tags":[
        "american",
        "sandwich"
    ],
    "wof:name":"Subway",
    "wof:placetype":"venue"
},
  "geometry": {"coordinates":[-96.332194,30.667562],"type":"Point"}
}