{
  "type": "Feature",
  "properties": {
    "iso:country":"US",
    "sg:address":"7712 Ironstone Trl",
    "sg:city":"Fort Worth",
    "sg:classifiers":[
        {
            "category":"Professional",
            "subcategory":"Computer Services",
            "type":"Services"
        }
    ],
    "sg:phone":"+1 817 236 5120",
    "sg:postcode":"76179",
    "sg:province":"TX",
    "sg:tags":[
        "programing",
        "custom"
    ],
    "wof:name":"Rh Consulting",
    "wof:placetype":"venue"
},
  "geometry": {"coordinates":[-97.445988,32.880529],"type":"Point"}
}