{
  "type": "Feature",
  "properties": {
    "iso:country":"US",
    "sg:address":"11980 Banner Crest Dr",
    "sg:city":"El Paso",
    "sg:classifiers":[
        {
            "category":"Professional",
            "subcategory":"Research",
            "type":"Services"
        }
    ],
    "sg:phone":"+1 915 494 9640",
    "sg:postcode":"79936",
    "sg:province":"TX",
    "sg:tags":[
        "operations",
        "engineering",
        "architecture",
        "enterprise"
    ],
    "wof:name":"Neologica Engrg Cnsulting Svcs",
    "wof:placetype":"venue"
},
  "geometry": {"coordinates":[-106.272818,31.789703],"type":"Point"}
}