{
  "type": "Feature",
  "properties": {
    "iso:country":"US",
    "sg:address":"4119 Forest Ln",
    "sg:city":"Garland",
    "sg:classifiers":[
        {
            "category":"Manufacturing",
            "subcategory":"Food",
            "type":"Manufacturing & Wholesale Goods"
        },
        {
            "category":"Wholesale",
            "subcategory":"Groceries",
            "type":"Manufacturing & Wholesale Goods"
        }
    ],
    "sg:phone":"+1 972 272 0959",
    "sg:postcode":"75042",
    "sg:province":"TX",
    "sg:tags":[
        "tortilla",
        "mfg"
    ],
    "wof:name":"Aztec Tortillas",
    "wof:placetype":"venue"
},
  "geometry": {"coordinates":[-96.69559700000001,32.90907],"type":"Point"}
}