{
  "type": "Feature",
  "properties": {
    "iso:country":"US",
    "sg:address":"2325 Central Fwy",
    "sg:city":"Wichita Falls",
    "sg:classifiers":[
        {
            "category":"Wholesale",
            "subcategory":"Auto Parts",
            "type":"Manufacturing & Wholesale Goods"
        }
    ],
    "sg:phone":"+1 940 767 4359",
    "sg:postcode":"76302",
    "sg:province":"TX",
    "sg:tags":[
        "equipment",
        "truck"
    ],
    "wof:name":"Jim's Truck & Trailer Equip",
    "wof:placetype":"venue"
},
  "geometry": {"coordinates":[-98.450557,33.884993],"type":"Point"}
}