{
  "type": "Feature",
  "properties": {
    "iso:country":"US",
    "sg:address":"107 Mary Louise Dr",
    "sg:city":"San Antonio",
    "sg:classifiers":[
        {
            "category":"Real Estate",
            "subcategory":"Real Estate Agent",
            "type":"Services"
        }
    ],
    "sg:phone":"+1 210 733 7141",
    "sg:postcode":"78201",
    "sg:province":"TX",
    "wof:name":"C M Furr Co Realtors",
    "wof:placetype":"venue"
},
  "geometry": {"coordinates":[-98.52690699999999,29.464856],"type":"Point"}
}