{
  "type": "Feature",
  "properties": {
    "iso:country":"US",
    "sg:address":"9525 Katy Fwy Ste 300",
    "sg:city":"Houston",
    "sg:classifiers":[
        {
            "category":"Professional",
            "type":"Services"
        }
    ],
    "sg:phone":"+1 713 984 9400",
    "sg:postcode":"77024",
    "sg:province":"TX",
    "wof:name":"Law Offices of Thomas D. Solomon",
    "wof:placetype":"venue"
},
  "geometry": {"coordinates":[-95.527905,29.782707],"type":"Point"}
}