{
  "type": "Feature",
  "properties": {
    "iso:country":"US",
    "sg:address":"4507 Jinx Ave",
    "sg:city":"Austin",
    "sg:classifiers":[
        {
            "category":"Shopping",
            "subcategory":"Hobbies, Toys, & Games",
            "type":"Retail Goods"
        }
    ],
    "sg:phone":"+1 512 448 1554",
    "sg:postcode":"78745",
    "sg:province":"TX",
    "wof:name":"Alyssa E Allen",
    "wof:placetype":"venue"
},
  "geometry": {"coordinates":[-97.781097,30.220289],"type":"Point"}
}