{
  "type": "Feature",
  "properties": {
    "iso:country":"US",
    "sg:address":"6305 County Road 7405",
    "sg:city":"Lubbock",
    "sg:classifiers":[
        {
            "category":"Building & Trades",
            "subcategory":"Landscaping Services",
            "type":"Services"
        }
    ],
    "sg:phone":"+1 806 787 3987",
    "sg:postcode":"79424",
    "sg:province":"TX",
    "sg:tags":[
        "lawn"
    ],
    "wof:name":"Lawnsmart Landscape Design & M",
    "wof:placetype":"venue"
},
  "geometry": {"coordinates":[-101.953671,33.4753],"type":"Point"}
}