{
  "type": "Feature",
  "properties": {
    "iso:country":"US",
    "sg:address":"2031 E Hwy 377",
    "sg:city":"Granbury",
    "sg:classifiers":[
        {
            "category":"Wholesale",
            "subcategory":"Farm Supplies",
            "type":"Manufacturing & Wholesale Goods"
        }
    ],
    "sg:phone":"+1 817 279 7556",
    "sg:postcode":"76049",
    "sg:province":"TX",
    "wof:name":"Arrow Feed & Ranch Inc",
    "wof:placetype":"venue"
},
  "geometry": {"coordinates":[-97.75281699999999,32.443118],"type":"Point"}
}