{
  "type": "Feature",
  "properties": {
    "iso:country":"US",
    "sg:address":"203 Virginia St",
    "sg:city":"Freeport",
    "sg:classifiers":[
        {
            "category":"Travel",
            "subcategory":"Hotels & Motels",
            "type":"Entertainment"
        }
    ],
    "sg:phone":"+1 979 233 7437",
    "sg:postcode":"77575",
    "sg:province":"TX",
    "wof:name":"Sea View Motel",
    "wof:placetype":"venue"
},
  "geometry": {"coordinates":[-94.80828700000001,30.057525],"type":"Point"}
}