{
  "type": "Feature",
  "properties": {
    "iso:country":"US",
    "sg:address":"4975 Preston Park Blvd",
    "sg:city":"Plano",
    "sg:classifiers":[
        {
            "category":"Education",
            "subcategory":"Special Training",
            "type":"Public Place"
        }
    ],
    "sg:phone":"+1 972 943 1402",
    "sg:postcode":"75093",
    "sg:province":"TX",
    "sg:tags":[
        "self",
        "motivational",
        "improvement"
    ],
    "wof:name":"Maritz Performance Improvement",
    "wof:placetype":"venue"
},
  "geometry": {"coordinates":[-96.78863,33.026876],"type":"Point"}
}