{
  "type": "Feature",
  "properties": {
    "iso:country":"US",
    "sg:address":"28 Brittany Ln",
    "sg:city":"Odessa",
    "sg:classifiers":[
        {
            "category":"Professional",
            "type":"Services"
        }
    ],
    "sg:phone":"+1 432 367 9686",
    "sg:postcode":"79761",
    "sg:province":"TX",
    "wof:name":"Bobby R Simpkins",
    "wof:placetype":"venue"
},
  "geometry": {"coordinates":[-102.317859,31.874801],"type":"Point"}
}