{
  "type": "Feature",
  "properties": {
    "iso:country":"US",
    "sg:address":"125 S Shore Dr",
    "sg:city":"Port Isabel",
    "sg:phone":"+1 956 943 1027",
    "sg:postcode":"78578",
    "sg:province":"TX",
    "sg:tags":[
        "oil"
    ],
    "wof:name":"South Shore Ice & Fuel",
    "wof:placetype":"venue"
},
  "geometry": {"coordinates":[-97.21189200000001,26.074245],"type":"Point"}
}