{
  "type": "Feature",
  "properties": {
    "iso:country":"US",
    "sg:address":"1914 N Grand Ave",
    "sg:city":"Sherman",
    "sg:classifiers":[
        {
            "category":"Professional",
            "subcategory":"Employment Agencies",
            "type":"Services"
        }
    ],
    "sg:phone":"+1 903 893 1122",
    "sg:postcode":"75090",
    "sg:province":"TX",
    "sg:tags":[
        "help",
        "supply"
    ],
    "wof:name":"Express Personnel Services",
    "wof:placetype":"venue"
},
  "geometry": {"coordinates":[-96.601603,33.65622],"type":"Point"}
}