{
  "type": "Feature",
  "properties": {
    "iso:country":"US",
    "sg:address":"503 Suncreek Dr",
    "sg:city":"Allen",
    "sg:classifiers":[
        {
            "category":"Wholesale",
            "subcategory":"Durable Goods & Equipment",
            "type":"Manufacturing & Wholesale Goods"
        }
    ],
    "sg:phone":"+1 972 390 7600",
    "sg:postcode":"75013",
    "sg:province":"TX",
    "sg:tags":[
        "representative",
        "manufacturer"
    ],
    "wof:name":"Bud Johnson & Assoc",
    "wof:placetype":"venue"
},
  "geometry": {"coordinates":[-96.707663,33.099293],"type":"Point"}
}