{
  "type": "Feature",
  "properties": {
    "iso:country":"US",
    "sg:address":"3980 Deep Valley Dr",
    "sg:city":"Dallas",
    "sg:classifiers":[
        {
            "category":"Professional",
            "subcategory":"Business Services",
            "type":"Services"
        }
    ],
    "sg:phone":"+1 972 488 3980",
    "sg:postcode":"75244",
    "sg:province":"TX",
    "wof:name":"Mendes Enterprises",
    "wof:placetype":"venue"
},
  "geometry": {"coordinates":[-96.848304,32.911749],"type":"Point"}
}