{
  "type": "Feature",
  "properties": {
    "iso:country":"US",
    "sg:address":"11234 Jones Rd W",
    "sg:city":"Houston",
    "sg:classifiers":[
        {
            "category":"Wholesale",
            "subcategory":"Machinery & Supplies",
            "type":"Manufacturing & Wholesale Goods"
        }
    ],
    "sg:phone":"+1 832 912 9063",
    "sg:postcode":"77065",
    "sg:province":"TX",
    "sg:tags":[
        "equipment",
        "industrial"
    ],
    "wof:name":"Legacy Automation Power",
    "wof:placetype":"venue"
},
  "geometry": {"coordinates":[-95.587604,29.935615],"type":"Point"}
}