{
  "type": "Feature",
  "properties": {
    "iso:country":"US",
    "sg:address":"802 N General Bruce Dr",
    "sg:city":"Temple",
    "sg:classifiers":[
        {
            "category":"Banks & Credit Unions",
            "subcategory":"Investment Brokerage",
            "type":"Services"
        }
    ],
    "sg:phone":"+1 254 778 8086",
    "sg:postcode":"76504",
    "sg:province":"TX",
    "sg:tags":[
        "security"
    ],
    "wof:name":"Suvarna Investments LLC",
    "wof:placetype":"venue"
},
  "geometry": {"coordinates":[-97.355396,31.114348],"type":"Point"}
}