{
  "type": "Feature",
  "properties": {
    "iso:country":"US",
    "sg:address":"5355 E Loop 820 S",
    "sg:city":"Fort Worth",
    "sg:classifiers":[
        {
            "category":"Restaurant",
            "type":"Food & Drink"
        }
    ],
    "sg:menulink":"http://www.allmenus.com/tx/fort-worth/199919-long-john-silvers/menu/",
    "sg:phone":"+1 817 572 2300",
    "sg:postcode":"76119",
    "sg:province":"TX",
    "sg:tags":[
        "seafood",
        "american"
    ],
    "wof:name":"Long John Silver's",
    "wof:placetype":"venue"
},
  "geometry": {"coordinates":[-97.239645,32.680021],"type":"Point"}
}