{
  "type": "Feature",
  "properties": {
    "iso:country":"US",
    "sg:address":"2900 Briarpark Dr",
    "sg:city":"Houston",
    "sg:classifiers":[
        {
            "category":"Retail",
            "subcategory":"Auto Rental",
            "type":"Services"
        }
    ],
    "sg:phone":"+1 713 278 1805",
    "sg:postcode":"77042",
    "sg:province":"TX",
    "sg:tags":[
        "renting",
        "automobile"
    ],
    "wof:name":"Enterprise Rent-A-Car",
    "wof:placetype":"venue"
},
  "geometry": {"coordinates":[-95.54915099999999,29.733176],"type":"Point"}
}