{
  "type": "Feature",
  "properties": {
    "iso:country":"US",
    "sg:address":"5494 Glen Lakes Dr",
    "sg:city":"Dallas",
    "sg:classifiers":[
        {
            "category":"Health Services",
            "subcategory":"Optometrist",
            "type":"Services"
        },
        {
            "category":"Shopping",
            "subcategory":"Optical Goods",
            "type":"Retail Goods"
        },
        {
            "category":"Health Services",
            "subcategory":"Doctor",
            "type":"Services"
        },
        {
            "category":"Health Services",
            "subcategory":"Health Practitioner",
            "type":"Services"
        }
    ],
    "sg:phone":"+1 214 692 6220",
    "sg:postcode":"75231",
    "sg:province":"TX",
    "sg:tags":[
        "physician",
        "laser",
        "ophthalmologist",
        "correction",
        "surgeons",
        "lens",
        "ophthalmology",
        "contact",
        "surgeon",
        "vision"
    ],
    "sg:website":"http://www.dallaseyecare.com",
    "wof:name":"Dallas Eye Care Associates Pllc",
    "wof:placetype":"venue"
},
  "geometry": {"coordinates":[-96.766098,32.883301],"type":"Point"}
}