{
  "type": "Feature",
  "properties": {
    "iso:country":"US",
    "sg:address":"2300 N Robison Rd",
    "sg:city":"Texarkana",
    "sg:classifiers":[
        {
            "category":"Shopping",
            "subcategory":"Computers & Home Electronics",
            "type":"Retail Goods"
        }
    ],
    "sg:phone":"+1 903 838 8444",
    "sg:postcode":"75501",
    "sg:province":"TX",
    "sg:tags":[
        "equipment",
        "electronic",
        "supply"
    ],
    "wof:name":"Radio Shack",
    "wof:placetype":"venue"
},
  "geometry": {"coordinates":[-94.08030100000001,33.438975],"type":"Point"}
}