{
  "type": "Feature",
  "properties": {
    "iso:country":"US",
    "sg:address":"15 Sherry Ridge",
    "sg:city":"Texarkana",
    "sg:classifiers":[
        {
            "category":"Building & Trades",
            "subcategory":"Construction",
            "type":"Services"
        }
    ],
    "sg:phone":"+1 903 838 9033",
    "sg:postcode":"75501",
    "sg:province":"TX",
    "sg:tags":[
        "general"
    ],
    "wof:name":"Roy Melton Construction",
    "wof:placetype":"venue"
},
  "geometry": {"coordinates":[-94.12835699999999,33.349986],"type":"Point"}
}