{
  "type": "Feature",
  "properties": {
    "iso:country":"US",
    "sg:address":"2323 Observation Dr",
    "sg:city":"San Antonio",
    "sg:classifiers":[
        {
            "category":"Organizations",
            "subcategory":"Religious Organization",
            "type":"Services"
        }
    ],
    "sg:phone":"+1 210 675 3830",
    "sg:postcode":"78227",
    "sg:province":"TX",
    "sg:tags":[
        "church"
    ],
    "wof:name":"Glorious Pentecostal Church",
    "wof:placetype":"venue"
},
  "geometry": {"coordinates":[-98.646956,29.403997],"type":"Point"}
}