{
  "type": "Feature",
  "properties": {
    "iso:country":"US",
    "sg:address":"6018 76th St",
    "sg:city":"Lubbock",
    "sg:classifiers":[
        {
            "category":"Professional",
            "subcategory":"Business Services",
            "type":"Services"
        }
    ],
    "sg:phone":"+1 806 794 1653",
    "sg:postcode":"79424",
    "sg:province":"TX",
    "sg:tags":[
        "interior",
        "consultant",
        "design",
        "decorator"
    ],
    "wof:name":"Interior Expressions",
    "wof:placetype":"venue"
},
  "geometry": {"coordinates":[-101.944058,33.524968],"type":"Point"}
}