{
  "type": "Feature",
  "properties": {
    "iso:country":"US",
    "sg:address":"1405 Fernwood Ave",
    "sg:city":"Dallas",
    "sg:classifiers":[
        {
            "category":"Autos & Motor Vehicles",
            "subcategory":"Automobile Sales",
            "type":"Retail Goods"
        }
    ],
    "sg:phone":"+1 214 391 5559",
    "sg:postcode":"75216",
    "sg:province":"TX",
    "sg:tags":[
        "car",
        "dealer"
    ],
    "wof:name":"Mc Daniel Motor Co",
    "wof:placetype":"venue"
},
  "geometry": {"coordinates":[-96.80917599999999,32.729608],"type":"Point"}
}