{
  "type": "Feature",
  "properties": {
    "iso:country":"US",
    "sg:address":"6 Concord Cir",
    "sg:city":"Austin",
    "sg:classifiers":[
        {
            "category":"Education",
            "subcategory":"Vocational School",
            "type":"Public Place"
        }
    ],
    "sg:phone":"+1 512 288 9537",
    "sg:postcode":"78737",
    "sg:province":"TX",
    "sg:tags":[
        "training",
        "business"
    ],
    "wof:name":"Jim Bagnola",
    "wof:placetype":"venue"
},
  "geometry": {"coordinates":[-97.961341,30.143069],"type":"Point"}
}