{
  "type": "Feature",
  "properties": {
    "iso:country":"US",
    "sg:address":"659 Co Rd 1572",
    "sg:city":"Carthage",
    "sg:classifiers":[
        {
            "category":"Professional",
            "subcategory":"Secretarial Services",
            "type":"Services"
        }
    ],
    "sg:phone":"+1 903 693 2346",
    "sg:postcode":"75633",
    "sg:province":"TX",
    "sg:tags":[
        "court",
        "reporter"
    ],
    "wof:name":"Marian T Cruse",
    "wof:placetype":"venue"
},
  "geometry": {"coordinates":[-94.45917,32.049681],"type":"Point"}
}