{
  "type": "Feature",
  "properties": {
    "iso:country":"US",
    "sg:address":"1357 Bernard St",
    "sg:city":"Denton",
    "sg:classifiers":[
        {
            "category":"Health Services",
            "subcategory":"Medical Lab",
            "type":"Services"
        }
    ],
    "sg:phone":"+1 940 387 0979",
    "sg:postcode":"76201",
    "sg:province":"TX",
    "sg:tags":[
        "laboratories-pathological",
        "laboratory"
    ],
    "wof:name":"Prolab",
    "wof:placetype":"venue"
},
  "geometry": {"coordinates":[-97.141593,33.201106],"type":"Point"}
}