{
  "type": "Feature",
  "properties": {
    "iso:country":"US",
    "sg:address":"7006 Boyce St",
    "sg:city":"Houston",
    "sg:classifiers":[
        {
            "category":"Building & Trades",
            "subcategory":"Construction",
            "type":"Services"
        }
    ],
    "sg:phone":"+1 713 675 6408",
    "sg:postcode":"77020",
    "sg:province":"TX",
    "sg:tags":[
        "contractor"
    ],
    "wof:name":"American Roofing Service",
    "wof:placetype":"venue"
},
  "geometry": {"coordinates":[-95.299836,29.76864],"type":"Point"}
}