{
  "type": "Feature",
  "properties": {
    "iso:country":"US",
    "sg:address":"1716 Briarcrest Dr # 300",
    "sg:city":"Bryan",
    "sg:classifiers":[
        {
            "category":"Wholesale",
            "subcategory":"Jewelry",
            "type":"Manufacturing & Wholesale Goods"
        },
        {
            "category":"Shopping",
            "subcategory":"Jewelry",
            "type":"Retail Goods"
        },
        {
            "category":"Manufacturing",
            "subcategory":"Jewelry",
            "type":"Manufacturing & Wholesale Goods"
        }
    ],
    "sg:phone":"+1 979 774 5794",
    "sg:postcode":"77802",
    "sg:province":"TX",
    "sg:tags":[
        "stone",
        "designer",
        "jewelers-wholesale",
        "supply",
        "jeweler",
        "finding",
        "precious",
        "semi-precious",
        "manufacturer"
    ],
    "wof:name":"Fifthcfinejewelry.Com",
    "wof:placetype":"venue"
},
  "geometry": {"coordinates":[-96.34004899999999,30.652122],"type":"Point"}
}