{
  "type": "Feature",
  "properties": {
    "iso:country":"US",
    "sg:address":"1390 Trophy Ct W",
    "sg:city":"Midlothian",
    "sg:classifiers":[
        {
            "category":"Shopping",
            "subcategory":"Catalog Store",
            "type":"Retail Goods"
        }
    ],
    "sg:phone":"+1 972 775 6217",
    "sg:postcode":"76065",
    "sg:province":"TX",
    "sg:tags":[
        "mail",
        "house"
    ],
    "wof:name":"Harborworks LLC",
    "wof:placetype":"venue"
},
  "geometry": {"coordinates":[-97.015981,32.403876],"type":"Point"}
}