{
  "type": "Feature",
  "properties": {
    "iso:country":"US",
    "sg:address":"10606 Hirsch Rd",
    "sg:city":"Houston",
    "sg:classifiers":[
        {
            "category":"Arts & Performance",
            "subcategory":"Theater",
            "type":"Entertainment"
        }
    ],
    "sg:phone":"+1 713 631 0878",
    "sg:postcode":"77016",
    "sg:province":"TX",
    "sg:tags":[
        "music"
    ],
    "wof:name":"Arthur Entertainment Ctr",
    "wof:placetype":"venue"
},
  "geometry": {"coordinates":[-95.31487300000001,29.869814],"type":"Point"}
}