{
  "type": "Feature",
  "properties": {
    "iso:country":"US",
    "sg:address":"3302 Boca Chica Blvd",
    "sg:city":"Brownsville",
    "sg:classifiers":[
        {
            "category":"Banks & Credit Unions",
            "subcategory":"Bank",
            "type":"Services"
        }
    ],
    "sg:phone":"+1 956 546 4528",
    "sg:postcode":"78521",
    "sg:province":"TX",
    "wof:name":"Hibernia National Bank",
    "wof:placetype":"venue"
},
  "geometry": {"coordinates":[-97.47170800000001,25.920916],"type":"Point"}
}