{
  "type": "Feature",
  "properties": {
    "iso:country":"US",
    "sg:address":"4600 Bunny Ln",
    "sg:city":"Wylie",
    "sg:classifiers":[
        {
            "category":"Shopping",
            "subcategory":"Gifts & Souvenirs",
            "type":"Retail Goods"
        }
    ],
    "sg:phone":"+1 972 475 7485",
    "sg:postcode":"75098",
    "sg:province":"TX",
    "wof:name":"My Grandmas House",
    "wof:placetype":"venue"
},
  "geometry": {"coordinates":[-96.51896000000001,32.960847],"type":"Point"}
}