{
  "type": "Feature",
  "properties": {
    "iso:country":"US",
    "sg:address":"2215 Victoria Ln",
    "sg:city":"Richardson",
    "sg:classifiers":[
        {
            "category":"Professional",
            "subcategory":"Management & Consulting",
            "type":"Services"
        }
    ],
    "sg:phone":"+1 972 437 1305",
    "sg:postcode":"75082",
    "sg:province":"TX",
    "wof:name":"Shamus Industries",
    "wof:placetype":"venue"
},
  "geometry": {"coordinates":[-96.69399199999999,32.979285],"type":"Point"}
}