{
  "type": "Feature",
  "properties": {
    "iso:country":"US",
    "sg:address":"3225 Woodland Park Dr",
    "sg:city":"Houston",
    "sg:classifiers":[
        {
            "category":"Banks & Credit Unions",
            "subcategory":"Investment Brokerage",
            "type":"Services"
        },
        {
            "category":"Real Estate",
            "subcategory":"Developer",
            "type":"Services"
        }
    ],
    "sg:phone":"+1 866 614 8289",
    "sg:postcode":"77082",
    "sg:province":"TX",
    "sg:tags":[
        "investing"
    ],
    "sg:website":"http://www.trailsapts.com",
    "wof:name":"Equity Residential",
    "wof:placetype":"venue"
},
  "geometry": {"coordinates":[-95.580142,29.728236],"type":"Point"}
}