{
  "type": "Feature",
  "properties": {
    "iso:country":"US",
    "sg:address":"12400 Amherst Drive",
    "sg:city":"Austin",
    "sg:classifiers":[
        {
            "category":"Social Services",
            "subcategory":"Child Care",
            "type":"Services"
        },
        {
            "category":"Education",
            "subcategory":"Preschool",
            "type":"Public Place"
        },
        {
            "category":"Education",
            "subcategory":"School",
            "type":"Public Place"
        }
    ],
    "sg:phone":"+1 512 833 8877",
    "sg:postcode":"78727",
    "sg:province":"TX",
    "sg:tags":[
        "elementary",
        "day"
    ],
    "sg:website":"www.nams-ami.com",
    "wof:name":"North Austin Montessori School",
    "wof:placetype":"venue"
},
  "geometry": {"coordinates":[-97.71598299999999,30.426799],"type":"Point"}
}