{
  "type": "Feature",
  "properties": {
    "iso:country":"US",
    "sg:address":"13727 Grand Prairie Dr",
    "sg:city":"Humble",
    "sg:classifiers":[
        {
            "category":"Wholesale",
            "subcategory":"Machinery & Supplies",
            "type":"Manufacturing & Wholesale Goods"
        }
    ],
    "sg:phone":"+1 281 590 9119",
    "sg:postcode":"77396",
    "sg:province":"TX",
    "sg:tags":[
        "valve"
    ],
    "wof:name":"Pipe Works",
    "wof:placetype":"venue"
},
  "geometry": {"coordinates":[-95.281312,29.916912],"type":"Point"}
}