{
  "type": "Feature",
  "properties": {
    "iso:country":"US",
    "sg:address":"605 W 4th St",
    "sg:city":"Post",
    "sg:classifiers":[
        {
            "category":"Professional",
            "subcategory":"Research",
            "type":"Services"
        }
    ],
    "sg:phone":"+1 806 495 1265",
    "sg:postcode":"79356",
    "sg:province":"TX",
    "sg:tags":[
        "laboratory"
    ],
    "wof:name":"AME Laboratories",
    "wof:placetype":"venue"
},
  "geometry": {"coordinates":[-101.384818,33.18476],"type":"Point"}
}