{
  "type": "Feature",
  "properties": {
    "iso:country":"US",
    "sg:address":"407 Evans Dr",
    "sg:city":"Euless",
    "sg:classifiers":[
        {
            "category":"Professional",
            "subcategory":"Management & Consulting",
            "type":"Services"
        }
    ],
    "sg:phone":"+1 817 868 0669",
    "sg:postcode":"76040",
    "sg:province":"TX",
    "sg:tags":[
        "business"
    ],
    "wof:name":"Total Leadership Consulting",
    "wof:placetype":"venue"
},
  "geometry": {"coordinates":[-97.117508,32.832785],"type":"Point"}
}