{
  "type": "Feature",
  "properties": {
    "iso:country":"US",
    "sg:address":"11915 Sandler Bend",
    "sg:city":"Cypress",
    "sg:classifiers":[
        {
            "category":"Building & Trades",
            "subcategory":"Construction",
            "type":"Services"
        }
    ],
    "sg:phone":"+1 281 379 5126",
    "sg:postcode":"77429",
    "sg:province":"TX",
    "sg:tags":[
        "house"
    ],
    "wof:name":"Kimball Hill Homes Texas  Inc",
    "wof:placetype":"venue"
},
  "geometry": {"coordinates":[-95.63462,29.989575],"type":"Point"}
}