{
  "type": "Feature",
  "properties": {
    "iso:country":"US",
    "sg:address":"3813 E 29th St",
    "sg:city":"Bryan",
    "sg:classifiers":[
        {
            "category":"Retail",
            "subcategory":"Repair Shop",
            "type":"Services"
        }
    ],
    "sg:phone":"+1 979 260 9810",
    "sg:postcode":"77802",
    "sg:province":"TX",
    "sg:tags":[
        "lock",
        "safe",
        "locksmith"
    ],
    "wof:name":"Couch Lock & Safe Inc",
    "wof:placetype":"venue"
},
  "geometry": {"coordinates":[-96.334053,30.648363],"type":"Point"}
}