{
  "type": "Feature",
  "properties": {
    "iso:country":"US",
    "sg:address":"6513 West Park",
    "sg:city":"Plano",
    "sg:classifiers":[
        {
            "category":"Fast Food",
            "type":"Food & Drink"
        }
    ],
    "sg:phone":"+1 972 473 2019",
    "sg:postcode":"75093",
    "sg:province":"TX",
    "sg:website":"www.raisingcanes.com/",
    "wof:name":"Raising Canes Chicken Fingers",
    "wof:placetype":"venue"
},
  "geometry": {"coordinates":[-96.842733,33.026408],"type":"Point"}
}