{
  "type": "Feature",
  "properties": {
    "iso:country":"US",
    "sg:address":"1410 W 13th St",
    "sg:city":"Austin",
    "sg:classifiers":[
        {
            "category":"Shopping",
            "type":"Retail Goods"
        }
    ],
    "sg:phone":"+1 512 477 4911",
    "sg:postcode":"78703",
    "sg:province":"TX",
    "sg:tags":[
        "merchandise"
    ],
    "wof:name":"Robert Barnstone",
    "wof:placetype":"venue"
},
  "geometry": {"coordinates":[-97.756916,30.280489],"type":"Point"}
}