{
  "type": "Feature",
  "properties": {
    "iso:country":"US",
    "sg:address":"160 S 8th St",
    "sg:city":"Slaton",
    "sg:classifiers":[
        {
            "category":"Building & Trades",
            "subcategory":"Plumbing",
            "type":"Services"
        }
    ],
    "sg:phone":"+1 806 828 6751",
    "sg:postcode":"79364",
    "sg:province":"TX",
    "sg:tags":[
        "plumber"
    ],
    "wof:name":"Dabila Plumbing Services",
    "wof:placetype":"venue"
},
  "geometry": {"coordinates":[-101.64268199999999,33.437393],"type":"Point"}
}