{
  "type": "Feature",
  "properties": {
    "iso:country":"US",
    "sg:address":"2654 W Oaks Blvd",
    "sg:city":"Pearland",
    "sg:classifiers":[
        {
            "category":"Social Services",
            "subcategory":"Child Care",
            "type":"Services"
        }
    ],
    "sg:phone":"+1 281 485 2891",
    "sg:postcode":"77584",
    "sg:province":"TX",
    "sg:tags":[
        "day"
    ],
    "wof:name":"Stepping Stones Learning Ctr",
    "wof:placetype":"venue"
},
  "geometry": {"coordinates":[-95.317926,29.558654],"type":"Point"}
}