{
  "type": "Feature",
  "properties": {
    "iso:country":"US",
    "sg:address":"7907 Kathryn Rd",
    "sg:city":"Needville",
    "sg:classifiers":[
        {
            "category":"Personal",
            "subcategory":"Beauty Salon",
            "type":"Services"
        }
    ],
    "sg:phone":"+1 979 793 5931",
    "sg:postcode":"77461",
    "sg:province":"TX",
    "sg:tags":[
        "shop"
    ],
    "wof:name":"Treats Texas Tan N Salon",
    "wof:placetype":"venue"
},
  "geometry": {"coordinates":[-95.870549,29.448614],"type":"Point"}
}