{
  "type": "Feature",
  "properties": {
    "iso:country":"US",
    "sg:address":"223 Woodhaven Blvd",
    "sg:city":"Duncanville",
    "sg:classifiers":[
        {
            "category":"Retail",
            "subcategory":"Auto Repair",
            "type":"Services"
        }
    ],
    "sg:phone":"+1 972 298 9932",
    "sg:postcode":"75116",
    "sg:province":"TX",
    "sg:tags":[
        "towing"
    ],
    "wof:name":"Duncanville Auto Pound",
    "wof:placetype":"venue"
},
  "geometry": {"coordinates":[-96.89997200000001,32.674229],"type":"Point"}
}