{
  "type": "Feature",
  "properties": {
    "iso:country":"US",
    "sg:address":"5705 4th St",
    "sg:city":"Katy",
    "sg:classifiers":[
        {
            "category":"Manufacturing",
            "subcategory":"Glass & Minerals",
            "type":"Manufacturing & Wholesale Goods"
        },
        {
            "category":"Wholesale",
            "subcategory":"Metals & Minerals",
            "type":"Manufacturing & Wholesale Goods"
        }
    ],
    "sg:phone":"+1 281 391 6688",
    "sg:postcode":"77493",
    "sg:province":"TX",
    "sg:tags":[
        "steel",
        "pipe",
        "drain"
    ],
    "wof:name":"B & W Pipe & Tube Inc",
    "wof:placetype":"venue"
},
  "geometry": {"coordinates":[-95.823258,29.788971],"type":"Point"}
}