{
  "type": "Feature",
  "properties": {
    "iso:country":"US",
    "sg:address":"2710 Devonshire",
    "sg:city":"Grapevine",
    "sg:classifiers":[
        {
            "category":"Professional",
            "subcategory":"Art Services",
            "type":"Services"
        }
    ],
    "sg:phone":"+1 817 329 5110",
    "sg:postcode":"76051",
    "sg:province":"TX",
    "sg:tags":[
        "commercial",
        "design"
    ],
    "wof:name":"Vetro Glass Glowing Glass",
    "wof:placetype":"venue"
},
  "geometry": {"coordinates":[-97.107876,32.895336],"type":"Point"}
}