{
  "type": "Feature",
  "properties": {
    "iso:country":"US",
    "sg:address":"4940 Sinclair Rd",
    "sg:city":"San Antonio",
    "sg:classifiers":[
        {
            "category":"Building & Trades",
            "subcategory":"Electrical",
            "type":"Services"
        }
    ],
    "sg:phone":"+1 210 648 5553",
    "sg:postcode":"78222",
    "sg:province":"TX",
    "sg:tags":[
        "electric",
        "contractor"
    ],
    "wof:name":"Red Simpson Inc",
    "wof:placetype":"venue"
},
  "geometry": {"coordinates":[-98.39290800000001,29.386323],"type":"Point"}
}