{
  "type": "Feature",
  "properties": {
    "iso:country":"US",
    "sg:address":"20012 Thurman Bend Rd",
    "sg:city":"Spicewood",
    "sg:classifiers":[
        {
            "category":"Farming",
            "subcategory":"Farm",
            "type":"Manufacturing & Wholesale Goods"
        }
    ],
    "sg:phone":"+1 512 264 9081",
    "sg:postcode":"78669",
    "sg:province":"TX",
    "sg:tags":[
        "crop",
        "general"
    ],
    "wof:name":"Donahue Farms",
    "wof:placetype":"venue"
},
  "geometry": {"coordinates":[-98.014128,30.407816],"type":"Point"}
}