{
  "type": "Feature",
  "properties": {
    "iso:country":"US",
    "sg:address":"6221 Pebble Beach Dr",
    "sg:city":"Corpus Christi",
    "sg:classifiers":[
        {
            "category":"Building & Trades",
            "subcategory":"Plumbing",
            "type":"Services"
        }
    ],
    "sg:phone":"+1 361 992 3379",
    "sg:postcode":"78413",
    "sg:province":"TX",
    "sg:tags":[
        "contractor"
    ],
    "wof:name":"Hughes Can Do AC & Htg",
    "wof:placetype":"venue"
},
  "geometry": {"coordinates":[-97.3994,27.69735],"type":"Point"}
}