{
  "type": "Feature",
  "properties": {
    "iso:country":"US",
    "sg:address":"630 Wade St",
    "sg:city":"Beaumont",
    "sg:classifiers":[
        {
            "category":"Shopping",
            "type":"Retail Goods"
        },
        {
            "category":"Building & Trades",
            "subcategory":"Equipment Rental",
            "type":"Services"
        }
    ],
    "sg:phone":"+1 409 899 4303",
    "sg:postcode":"77706",
    "sg:province":"TX",
    "sg:tags":[
        "party",
        "merchandise",
        "supply"
    ],
    "wof:name":"ABC Discount Rentals LLC",
    "wof:placetype":"venue"
},
  "geometry": {"coordinates":[-94.160923,30.087006],"type":"Point"}
}