{
  "type": "Feature",
  "properties": {
    "iso:country":"US",
    "sg:address":"8900 Independence Pkwy",
    "sg:city":"Plano",
    "sg:phone":"+1 469 241 9930",
    "sg:postcode":"75025",
    "sg:province":"TX",
    "sg:tags":[
        "food",
        "equipment",
        "processing"
    ],
    "wof:name":"Berkel Inc",
    "wof:placetype":"venue"
},
  "geometry": {"coordinates":[-96.750137,33.099818],"type":"Point"}
}