{
  "type": "Feature",
  "properties": {
    "iso:country":"US",
    "sg:address":"865 E Main St",
    "sg:city":"Lewisville",
    "sg:classifiers":[
        {
            "category":"Autos & Motor Vehicles",
            "subcategory":"Automobile Sales",
            "type":"Retail Goods"
        }
    ],
    "sg:phone":"+1 972 436 1089",
    "sg:postcode":"75057",
    "sg:province":"TX",
    "sg:tags":[
        "dealers-used",
        "car",
        "used",
        "cars-wholesale"
    ],
    "wof:name":"N & I Auto Sales",
    "wof:placetype":"venue"
},
  "geometry": {"coordinates":[-96.978943,33.04181],"type":"Point"}
}