{
  "type": "Feature",
  "properties": {
    "iso:country":"US",
    "sg:address":"7551 Fm 1960 Rd E",
    "sg:city":"Humble",
    "sg:classifiers":[
        {
            "category":"Food & Beverages",
            "subcategory":"Specialty",
            "type":"Retail Goods"
        },
        {
            "category":"Food & Beverages",
            "subcategory":"Fruits & Vegetables",
            "type":"Retail Goods"
        },
        {
            "category":"Shopping",
            "subcategory":"Pharmacy",
            "type":"Retail Goods"
        }
    ],
    "sg:phone":"+1 281 852 7099",
    "sg:postcode":"77346",
    "sg:province":"TX",
    "sg:tags":[
        "product",
        "wellness",
        "vitamin",
        "diet",
        "supplement",
        "health",
        "herb"
    ],
    "sg:website":"http://www.gnc.com",
    "wof:name":"GNC",
    "wof:placetype":"venue"
},
  "geometry": {"coordinates":[-95.16122,29.998923],"type":"Point"}
}