{
  "type": "Feature",
  "properties": {
    "iso:country":"US",
    "sg:address":"2409 Parkcrest Dr",
    "sg:city":"Garland",
    "sg:classifiers":[
        {
            "category":"Building & Trades",
            "subcategory":"Plumbing",
            "type":"Services"
        }
    ],
    "sg:phone":"+1 972 278 6386",
    "sg:postcode":"75041",
    "sg:province":"TX",
    "sg:tags":[
        "air",
        "repair",
        "heating",
        "conditioning",
        "contractor"
    ],
    "wof:name":"Kens Air Conditioning & Appl",
    "wof:placetype":"venue"
},
  "geometry": {"coordinates":[-96.664663,32.891134],"type":"Point"}
}