{
  "type": "Feature",
  "properties": {
    "iso:country":"US",
    "sg:address":"2644 Derby Ln",
    "sg:city":"Madisonville",
    "sg:classifiers":[
        {
            "category":"Wholesale",
            "subcategory":"Machinery & Supplies",
            "type":"Manufacturing & Wholesale Goods"
        }
    ],
    "sg:phone":"+1 979 218 4964",
    "sg:postcode":"77864",
    "sg:province":"TX",
    "sg:tags":[
        "contractor"
    ],
    "wof:name":"Chennault Rentals",
    "wof:placetype":"venue"
},
  "geometry": {"coordinates":[-95.858822,30.974196],"type":"Point"}
}