{
  "type": "Feature",
  "properties": {
    "iso:country":"US",
    "sg:address":"12032 Green River Dr",
    "sg:city":"Houston",
    "sg:classifiers":[
        {
            "category":"Retail",
            "subcategory":"Repair Shop",
            "type":"Services"
        }
    ],
    "sg:phone":"+1 281 458 9975",
    "sg:postcode":"77044",
    "sg:province":"TX",
    "wof:name":"Rons Taxidermy",
    "wof:placetype":"venue"
},
  "geometry": {"coordinates":[-95.219572,29.838713],"type":"Point"}
}