{
  "type": "Feature",
  "properties": {
    "iso:country":"US",
    "sg:address":"13211 N Stemmons Fwy",
    "sg:city":"Dallas",
    "sg:classifiers":[
        {
            "category":"Food & Beverages",
            "subcategory":"Groceries & Convenience Stores",
            "type":"Retail Goods"
        }
    ],
    "sg:phone":"+1 972 247 3885",
    "sg:postcode":"75234",
    "sg:province":"TX",
    "wof:name":"Valley View Mobil",
    "wof:placetype":"venue"
},
  "geometry": {"coordinates":[-96.90149700000001,32.922501],"type":"Point"}
}