{
  "type": "Feature",
  "properties": {
    "iso:country":"US",
    "sg:address":"3407 Trinity Mills Rd",
    "sg:city":"Dallas",
    "sg:classifiers":[
        {
            "category":"Professional",
            "type":"Services"
        }
    ],
    "sg:phone":"+1 972 662 3402",
    "sg:postcode":"75287",
    "sg:province":"TX",
    "sg:tags":[
        "establishment"
    ],
    "wof:name":"Mj Designs",
    "wof:placetype":"venue"
},
  "geometry": {"coordinates":[-96.839595,32.987537],"type":"Point"}
}