{
  "type": "Feature",
  "properties": {
    "iso:country":"US",
    "sg:address":"2630 Exposition Boulevard",
    "sg:city":"Austin",
    "sg:classifiers":[
        {
            "category":"Professional",
            "subcategory":"Lawyer & Legal Services",
            "type":"Services"
        }
    ],
    "sg:phone":"+1 512 472 7111",
    "sg:postcode":"78703",
    "sg:province":"TX",
    "wof:name":"Saunders C Stephen Atty",
    "wof:placetype":"venue"
},
  "geometry": {"coordinates":[-97.765119,30.301646],"type":"Point"}
}