{
  "type": "Feature",
  "properties": {
    "iso:country":"US",
    "sg:address":"110 N 8th St",
    "sg:city":"Gatesville",
    "sg:classifiers":[
        {
            "category":"Government",
            "subcategory":"Office",
            "type":"Public Place"
        }
    ],
    "sg:phone":"+1 254 865 8951",
    "sg:postcode":"76528",
    "sg:province":"TX",
    "sg:tags":[
        "executive"
    ],
    "wof:name":"City Hall",
    "wof:placetype":"venue"
},
  "geometry": {"coordinates":[-97.748434,31.43576],"type":"Point"}
}