{
  "type": "Feature",
  "properties": {
    "iso:country":"US",
    "sg:address":"321 E Buckingham Rd",
    "sg:city":"Garland",
    "sg:classifiers":[
        {
            "category":"Retail",
            "subcategory":"Storage",
            "type":"Services"
        }
    ],
    "sg:phone":"+1 972 530 6288",
    "sg:postcode":"75040",
    "sg:province":"TX",
    "sg:tags":[
        "self"
    ],
    "wof:name":"Storage Trust",
    "wof:placetype":"venue"
},
  "geometry": {"coordinates":[-96.62750200000001,32.931099],"type":"Point"}
}