{
  "type": "Feature",
  "properties": {
    "iso:country":"US",
    "sg:address":"3132 Saint Lo Dr",
    "sg:city":"Irving",
    "sg:classifiers":[
        {
            "category":"Building & Trades",
            "subcategory":"Plumbing",
            "type":"Services"
        }
    ],
    "sg:phone":"+1 972 790 5370",
    "sg:postcode":"75060",
    "sg:province":"TX",
    "sg:tags":[
        "contractor"
    ],
    "wof:name":"McAbees Heating & Air Conditio",
    "wof:placetype":"venue"
},
  "geometry": {"coordinates":[-96.986705,32.810278],"type":"Point"}
}