{
  "type": "Feature",
  "properties": {
    "iso:country":"US",
    "sg:address":"2010 Wilson Rd",
    "sg:city":"Humble",
    "sg:classifiers":[
        {
            "category":"Freight",
            "type":"Transportation"
        }
    ],
    "sg:phone":"+1 281 540 7585",
    "sg:postcode":"77396",
    "sg:province":"TX",
    "sg:tags":[
        "trucking"
    ],
    "wof:name":"Mayfield Trucking Inc",
    "wof:placetype":"venue"
},
  "geometry": {"coordinates":[-95.248424,29.975035],"type":"Point"}
}