{
  "type": "Feature",
  "properties": {
    "iso:country":"US",
    "sg:address":"4323 N Josey Ln Ste 302",
    "sg:city":"Carrollton",
    "sg:classifiers":[
        {
            "category":"Health Services",
            "subcategory":"Doctor",
            "type":"Services"
        }
    ],
    "sg:phone":"+1 972 939 2121",
    "sg:postcode":"75010",
    "sg:province":"TX",
    "sg:tags":[
        "medicine",
        "internal"
    ],
    "wof:name":"Adnan Nadir, MD",
    "wof:placetype":"venue"
},
  "geometry": {"coordinates":[-96.88477,33.034077],"type":"Point"}
}