{
  "type": "Feature",
  "properties": {
    "iso:country":"US",
    "sg:address":"1518 W Main St",
    "sg:city":"Rio Grande City",
    "sg:classifiers":[
        {
            "category":"Shopping",
            "subcategory":"Used Merchandise",
            "type":"Retail Goods"
        }
    ],
    "sg:phone":"+1 956 487 8887",
    "sg:postcode":"78582",
    "sg:province":"TX",
    "sg:tags":[
        "pawnbroker",
        "pawnshop"
    ],
    "wof:name":"First Cash Pawn 93",
    "wof:placetype":"venue"
},
  "geometry": {"coordinates":[-98.836665,26.378341],"type":"Point"}
}