{
  "type": "Feature",
  "properties": {
    "iso:country":"US",
    "sg:address":"1900 Preston Park Blvd",
    "sg:city":"Plano",
    "sg:classifiers":[
        {
            "category":"Social Services",
            "subcategory":"Child Care",
            "type":"Services"
        }
    ],
    "sg:phone":"+1 972 964 7275",
    "sg:postcode":"75093",
    "sg:province":"TX",
    "sg:tags":[
        "day"
    ],
    "wof:name":"Preston Park Children's Academy",
    "wof:placetype":"venue"
},
  "geometry": {"coordinates":[-96.788399,33.0261],"type":"Point"}
}