{
  "type": "Feature",
  "properties": {
    "iso:country":"US",
    "sg:address":"18601 Lyndon B Johnson Fwy Ste 625",
    "sg:city":"Mesquite",
    "sg:classifiers":[
        {
            "category":"Health Services",
            "subcategory":"Doctor",
            "type":"Services"
        }
    ],
    "sg:phone":"+1 972 270 6533",
    "sg:postcode":"75150",
    "sg:province":"TX",
    "sg:tags":[
        "surgeon",
        "oral"
    ],
    "wof:name":"Langston William B III DDS",
    "wof:placetype":"venue"
},
  "geometry": {"coordinates":[-96.627602,32.8027],"type":"Point"}
}