{
  "type": "Feature",
  "properties": {
    "iso:country":"US",
    "sg:address":"1115 Tolar Cemetery Rd",
    "sg:city":"Tolar",
    "sg:classifiers":[
        {
            "category":"Shopping",
            "subcategory":"Clothing, Apparel, & Fashions",
            "type":"Retail Goods"
        }
    ],
    "sg:phone":"+1 254 835 4109",
    "sg:postcode":"76476",
    "sg:province":"TX",
    "sg:tags":[
        "sporting"
    ],
    "wof:name":"Gold Buckle Rodeo Co",
    "wof:placetype":"venue"
},
  "geometry": {"coordinates":[-97.91545499999999,32.378445],"type":"Point"}
}