{
  "type": "Feature",
  "properties": {
    "iso:country":"US",
    "sg:address":"1411 N Lamesa Rd",
    "sg:city":"Midland",
    "sg:classifiers":[
        {
            "category":"Food & Beverages",
            "subcategory":"Groceries & Convenience Stores",
            "type":"Retail Goods"
        }
    ],
    "sg:phone":"+1 432 683 7552",
    "sg:postcode":"79701",
    "sg:province":"TX",
    "sg:tags":[
        "grocer"
    ],
    "wof:name":"Smitty's Grocery & Market",
    "wof:placetype":"venue"
},
  "geometry": {"coordinates":[-102.06948800000001,32.013364],"type":"Point"}
}