{
  "type": "Feature",
  "properties": {
    "iso:country":"US",
    "sg:address":"2312 Western Trails Blvd",
    "sg:city":"Austin",
    "sg:phone":"+1 512 212 4234",
    "sg:postcode":"78745",
    "sg:province":"TX",
    "sg:website":"http://austin.citysearch.com/profile/external/652185230/austin_tx/western_trails_dental.html?publisher=yellowpages&reference_id=7&placement=ypwebsitemip",
    "wof:name":"Western Trails Dental",
    "wof:placetype":"venue"
},
  "geometry": {"coordinates":[-97.794168,30.23044],"type":"Point"}
}