{
  "type": "Feature",
  "properties": {
    "iso:country":"US",
    "sg:address":"3701 Airport Blvd",
    "sg:city":"Austin",
    "sg:classifiers":[
        {
            "category":"Bars & Pubs",
            "type":"Food & Drink"
        }
    ],
    "sg:phone":"+1 512 708 1911",
    "sg:postcode":"78722",
    "sg:province":"TX",
    "sg:tags":[
        "club",
        "drinking",
        "nightlife",
        "night"
    ],
    "wof:name":"El Sentenario",
    "wof:placetype":"venue"
},
  "geometry": {"coordinates":[-97.706497,30.2864],"type":"Point"}
}