{
  "type": "Feature",
  "properties": {
    "iso:country":"US",
    "sg:address":"2330 61st St",
    "sg:city":"Lubbock",
    "sg:classifiers":[
        {
            "category":"Recreation",
            "subcategory":"Campground",
            "type":"Entertainment"
        }
    ],
    "sg:phone":"+1 806 799 1093",
    "sg:postcode":"79412",
    "sg:province":"TX",
    "sg:tags":[
        "recreational",
        "park",
        "vehicle"
    ],
    "wof:name":"Jacobs Sleepy Valley Inc",
    "wof:placetype":"venue"
},
  "geometry": {"coordinates":[-101.867349,33.538843],"type":"Point"}
}