{
  "type": "Feature",
  "properties": {
    "iso:country":"US",
    "sg:address":"825 W Wintergreen Rd",
    "sg:city":"Desoto",
    "sg:classifiers":[
        {
            "category":"Recreation",
            "type":"Entertainment"
        }
    ],
    "sg:phone":"+1 972 296 2146",
    "sg:postcode":"75115",
    "sg:province":"TX",
    "sg:tags":[
        "club",
        "country",
        "golf",
        "course"
    ],
    "wof:name":"Thorntree Country Club",
    "wof:placetype":"venue"
},
  "geometry": {"coordinates":[-96.87499800000001,32.618694],"type":"Point"}
}