{
  "type": "Feature",
  "properties": {
    "iso:country":"US",
    "sg:address":"11126 Jollyville Road Suite B",
    "sg:city":"Austin",
    "sg:classifiers":[
        {
            "category":"Personal",
            "type":"Services"
        }
    ],
    "sg:phone":"+1 512 338 4288",
    "sg:postcode":"78759",
    "sg:province":"TX",
    "sg:tags":[
        "sewing",
        "alteration"
    ],
    "sg:website":"www.tailoredbydesign.com",
    "wof:name":"Tailored by Design",
    "wof:placetype":"venue"
},
  "geometry": {"coordinates":[-97.753311,30.40119],"type":"Point"}
}