{
  "type": "Feature",
  "properties": {
    "iso:country":"US",
    "sg:address":"22002 Franz Rd",
    "sg:city":"Katy",
    "sg:classifiers":[
        {
            "category":"Autos & Motor Vehicles",
            "subcategory":"Auto Supplies",
            "type":"Retail Goods"
        },
        {
            "category":"Retail",
            "subcategory":"Auto Repair",
            "type":"Services"
        }
    ],
    "sg:phone":"+1 281 579 8526",
    "sg:postcode":"77449",
    "sg:province":"TX",
    "sg:tags":[
        "automobile",
        "part",
        "truck"
    ],
    "sg:website":"http://clickserve.dartsearch.net/link/click?lid=43000000313869162&ds_s_kwgid=58000000006820725&ds_e_matchtype={MatchType}&ds_e_kwdid={OrderItemId}&ds_e_adid={AdId}&ds_url_v=2",
    "wof:name":"Mission Car Care",
    "wof:placetype":"venue"
},
  "geometry": {"coordinates":[-95.75500700000001,29.802131],"type":"Point"}
}