{
  "type": "Feature",
  "properties": {
    "iso:country":"US",
    "sg:address":"6410 Weber Rd",
    "sg:city":"Corpus Christi",
    "sg:classifiers":[
        {
            "category":"Restaurant",
            "type":"Food & Drink"
        }
    ],
    "sg:phone":"+1 361 814 8847",
    "sg:postcode":"78413",
    "sg:province":"TX",
    "sg:tags":[
        "eating"
    ],
    "wof:name":"Moodys Mexican Food",
    "wof:placetype":"venue"
},
  "geometry": {"coordinates":[-97.412212,27.6998],"type":"Point"}
}