{
  "type": "Feature",
  "properties": {
    "iso:country":"US",
    "sg:address":"11500 Metric Blvd Ste 320",
    "sg:city":"Austin",
    "sg:classifiers":[
        {
            "category":"Professional",
            "type":"Services"
        },
        {
            "category":"Professional",
            "subcategory":"Computer Services",
            "type":"Services"
        }
    ],
    "sg:phone":"+1 512 637 1684",
    "sg:postcode":"78758",
    "sg:province":"TX",
    "sg:tags":[
        "repair"
    ],
    "sg:website":"www.completetablet.com",
    "wof:name":"CTS",
    "wof:placetype":"venue"
},
  "geometry": {"coordinates":[-97.70803600000001,30.394579],"type":"Point"}
}