{
  "type": "Feature",
  "properties": {
    "iso:country":"US",
    "sg:address":"809 Texas Ave",
    "sg:city":"League City",
    "sg:classifiers":[
        {
            "category":"Retail",
            "subcategory":"Repair Shop",
            "type":"Services"
        }
    ],
    "sg:phone":"+1 281 332 5288",
    "sg:postcode":"77573",
    "sg:province":"TX",
    "sg:tags":[
        "heavy",
        "equipment"
    ],
    "wof:name":"Beveridge Engine & Equipment",
    "wof:placetype":"venue"
},
  "geometry": {"coordinates":[-95.076633,29.510479],"type":"Point"}
}