{
  "type": "Feature",
  "properties": {
    "iso:country":"US",
    "sg:address":"2302 Haltom Rd",
    "sg:city":"Fort Worth",
    "sg:classifiers":[
        {
            "category":"Food & Beverages",
            "subcategory":"Groceries & Convenience Stores",
            "type":"Retail Goods"
        }
    ],
    "sg:phone":"+1 817 831 0250",
    "sg:postcode":"76117",
    "sg:province":"TX",
    "wof:name":"Family Mart",
    "wof:placetype":"venue"
},
  "geometry": {"coordinates":[-97.273078,32.794895],"type":"Point"}
}