{
  "type": "Feature",
  "properties": {
    "iso:country":"US",
    "sg:address":"3940 Saint Francis Ave",
    "sg:city":"Dallas",
    "sg:classifiers":[
        {
            "category":"Autos & Motor Vehicles",
            "subcategory":"Fuel & Gas Station",
            "type":"Retail Goods"
        }
    ],
    "sg:phone":"+1 214 324 5173",
    "sg:postcode":"75227",
    "sg:province":"TX",
    "sg:tags":[
        "station",
        "gasoline"
    ],
    "wof:name":"Murphy USA 5774",
    "wof:placetype":"venue"
},
  "geometry": {"coordinates":[-96.69152200000001,32.794774],"type":"Point"}
}