{
  "type": "Feature",
  "properties": {
    "iso:country":"US",
    "sg:address":"301 W 6th Ave",
    "sg:city":"Corsicana",
    "sg:classifiers":[
        {
            "category":"Retail",
            "subcategory":"Auto Repair",
            "type":"Services"
        }
    ],
    "sg:phone":"+1 903 872 2951",
    "sg:postcode":"75110",
    "sg:province":"TX",
    "sg:tags":[
        "body",
        "automobile",
        "painting"
    ],
    "wof:name":"Manuel's Paint & Body",
    "wof:placetype":"venue"
},
  "geometry": {"coordinates":[-96.46534800000001,32.091679],"type":"Point"}
}