{
  "type": "Feature",
  "properties": {
    "iso:country":"US",
    "sg:address":"2300 San Juan Dr",
    "sg:city":"Austin",
    "sg:classifiers":[
        {
            "category":"Autos & Motor Vehicles",
            "subcategory":"Motorcycle Sales",
            "type":"Retail Goods"
        }
    ],
    "sg:phone":"+1 512 263 5337",
    "sg:postcode":"78733",
    "sg:province":"TX",
    "sg:tags":[
        "parts-wholesale",
        "scooters-supplies",
        "manufacturer"
    ],
    "sg:website":"http://www.krummsindian.com",
    "wof:name":"Krumm's Indian",
    "wof:placetype":"venue"
},
  "geometry": {"coordinates":[-97.859802,30.344351],"type":"Point"}
}