{
  "type": "Feature",
  "properties": {
    "iso:country":"US",
    "sg:address":"1701 Greenville Ave",
    "sg:city":"Dallas",
    "sg:classifiers":[
        {
            "category":"Health Services",
            "subcategory":"Health Practitioner",
            "type":"Services"
        }
    ],
    "sg:phone":"+1 214 575 4888",
    "sg:postcode":"75206",
    "sg:province":"TX",
    "sg:tags":[
        "acupuncture"
    ],
    "wof:name":"Mellina Acupressure & Rlxtn",
    "wof:placetype":"venue"
},
  "geometry": {"coordinates":[-96.770208,32.812199],"type":"Point"}
}