{
  "type": "Feature",
  "properties": {
    "iso:country":"US",
    "sg:address":"604 W Alabama St",
    "sg:city":"Houston",
    "sg:classifiers":[
        {
            "category":"Food & Beverages",
            "subcategory":"Bakery",
            "type":"Retail Goods"
        }
    ],
    "sg:phone":"+1 713 520 1484",
    "sg:postcode":"77006",
    "sg:province":"TX",
    "sg:tags":[
        "baker"
    ],
    "sg:website":"www.acadianbakers.com",
    "wof:name":"Acadian Bakery",
    "wof:placetype":"venue"
},
  "geometry": {"coordinates":[-95.38659699999999,29.739],"type":"Point"}
}