{
  "type": "Feature",
  "properties": {
    "iso:country":"US",
    "sg:address":"301 M B Industrial",
    "sg:city":"Woodway",
    "sg:classifiers":[
        {
            "category":"Utilities",
            "subcategory":"Water",
            "type":"Services"
        },
        {
            "category":"Wholesale",
            "subcategory":"Machinery & Supplies",
            "type":"Manufacturing & Wholesale Goods"
        },
        {
            "category":"Retail",
            "subcategory":"Repair Shop",
            "type":"Services"
        },
        {
            "category":"Manufacturing",
            "subcategory":"Motor Vehicles & Parts",
            "type":"Manufacturing & Wholesale Goods"
        }
    ],
    "sg:phone":"+1 254 776 0377",
    "sg:postcode":"76712",
    "sg:province":"TX",
    "sg:tags":[
        "electric",
        "well",
        "contractor",
        "pump",
        "drilling",
        "pumps-service"
    ],
    "sg:website":"http://www.smithpump.com",
    "wof:name":"Smith Pump Company Inc",
    "wof:placetype":"venue"
},
  "geometry": {"coordinates":[-97.229634,31.492155],"type":"Point"}
}