{
  "type": "Feature",
  "properties": {
    "iso:country":"US",
    "sg:address":"18 Brandenberry Ct",
    "sg:city":"Spring",
    "sg:classifiers":[
        {
            "category":"Professional",
            "type":"Services"
        }
    ],
    "sg:phone":"+1 281 419 9799",
    "sg:postcode":"77381",
    "sg:province":"TX",
    "sg:tags":[
        "establishment"
    ],
    "wof:name":"Genetench Inc",
    "wof:placetype":"venue"
},
  "geometry": {"coordinates":[-95.50604800000001,30.188407],"type":"Point"}
}