{
  "type": "Feature",
  "properties": {
    "iso:country":"US",
    "sg:address":"26520 Clay Rd",
    "sg:city":"Katy",
    "sg:classifiers":[
        {
            "category":"Home & Garden",
            "subcategory":"Garden Supply",
            "type":"Retail Goods"
        }
    ],
    "sg:phone":"+1 281 371 7246",
    "sg:postcode":"77493",
    "sg:province":"TX",
    "wof:name":"Houston Landscape Service",
    "wof:placetype":"venue"
},
  "geometry": {"coordinates":[-95.836125,29.831215],"type":"Point"}
}