{
  "type": "Feature",
  "properties": {
    "iso:country":"US",
    "sg:address":"1201 W Malone",
    "sg:city":"San Antonio",
    "sg:classifiers":[
        {
            "category":"Recreation",
            "type":"Entertainment"
        }
    ],
    "sg:phone":"+1 210 922 1034",
    "sg:postcode":"78225",
    "sg:province":"TX",
    "sg:tags":[
        "executive",
        "center"
    ],
    "wof:name":"Palm Heights Center",
    "wof:placetype":"venue"
},
  "geometry": {"coordinates":[-98.52722900000001,29.387511],"type":"Point"}
}