{
  "type": "Feature",
  "properties": {
    "iso:country":"US",
    "sg:address":"211 Executive Way",
    "sg:city":"Desoto",
    "sg:classifiers":[
        {
            "category":"Professional",
            "subcategory":"Lawyer & Legal Services",
            "type":"Services"
        }
    ],
    "sg:phone":"+1 972 298 6111",
    "sg:postcode":"75115",
    "sg:province":"TX",
    "wof:name":"Boyanton Janet",
    "wof:placetype":"venue"
},
  "geometry": {"coordinates":[-96.859497,32.622398],"type":"Point"}
}