{
  "type": "Feature",
  "properties": {
    "iso:country":"US",
    "sg:address":"2307 Manor Rd",
    "sg:city":"Austin",
    "sg:classifiers":[
        {
            "category":"Arts & Performance",
            "subcategory":"Theater",
            "type":"Entertainment"
        }
    ],
    "sg:phone":"+1 512 478 5282",
    "sg:postcode":"78722",
    "sg:province":"TX",
    "sg:website":"www.vortexrep.org",
    "wof:name":"Vortex",
    "wof:placetype":"venue"
},
  "geometry": {"coordinates":[-97.717185,30.284522],"type":"Point"}
}