{
  "type": "Feature",
  "properties": {
    "iso:country":"US",
    "sg:address":"1010 Houston St",
    "sg:city":"Fort Worth",
    "sg:classifiers":[
        {
            "category":"Travel",
            "subcategory":"Hotels & Motels",
            "type":"Entertainment"
        }
    ],
    "sg:phone":"+1 817 336 2011",
    "sg:postcode":"76102",
    "sg:province":"TX",
    "sg:website":"www.parkcentralhotel.com",
    "wof:name":"Park Central Hotel",
    "wof:placetype":"venue"
},
  "geometry": {"coordinates":[-97.329044,32.749784],"type":"Point"}
}