{
  "type": "Feature",
  "properties": {
    "iso:country":"US",
    "sg:address":"823 Dora St",
    "sg:city":"Bedford",
    "sg:classifiers":[
        {
            "category":"Professional",
            "subcategory":"Art Services",
            "type":"Services"
        }
    ],
    "sg:phone":"+1 817 285 8910",
    "sg:postcode":"76022",
    "sg:province":"TX",
    "sg:tags":[
        "design",
        "graphic",
        "commercial",
        "designer"
    ],
    "wof:name":"N Giles Art",
    "wof:placetype":"venue"
},
  "geometry": {"coordinates":[-97.160765,32.824911],"type":"Point"}
}