{
  "type": "Feature",
  "properties": {
    "iso:country":"US",
    "sg:address":"608 Ridge View Cove",
    "sg:city":"Georgetown",
    "sg:classifiers":[
        {
            "category":"Manufacturing",
            "subcategory":"Retail Goods",
            "type":"Manufacturing & Wholesale Goods"
        }
    ],
    "sg:phone":"+1 512 930 5646",
    "sg:postcode":"78628",
    "sg:province":"TX",
    "sg:tags":[
        "product",
        "mfg"
    ],
    "wof:name":"PS Promotions",
    "wof:placetype":"venue"
},
  "geometry": {"coordinates":[-97.805114,30.620599],"type":"Point"}
}