{
  "type": "Feature",
  "properties": {
    "iso:country":"US",
    "sg:address":"605 Driftwood Pl",
    "sg:city":"Corpus Christi",
    "sg:classifiers":[
        {
            "category":"Building & Trades",
            "subcategory":"Construction",
            "type":"Services"
        }
    ],
    "sg:phone":"+1 361 851 9123",
    "sg:postcode":"78411",
    "sg:province":"TX",
    "sg:tags":[
        "planning",
        "remodeling",
        "kitchen"
    ],
    "wof:name":"Autry Wright Construction",
    "wof:placetype":"venue"
},
  "geometry": {"coordinates":[-97.378922,27.736137],"type":"Point"}
}