{
  "type": "Feature",
  "properties": {
    "iso:country":"US",
    "sg:address":"2260 State Hwy 217",
    "sg:city":"Canyon",
    "sg:classifiers":[
        {
            "category":"Shopping",
            "subcategory":"Jewelry",
            "type":"Retail Goods"
        }
    ],
    "sg:phone":"+1 806 488 2511",
    "sg:postcode":"79015",
    "sg:province":"TX",
    "wof:name":"Harris Battle",
    "wof:placetype":"venue"
},
  "geometry": {"coordinates":[-101.919698,34.979774],"type":"Point"}
}