{
  "type": "Feature",
  "properties": {
    "iso:country":"US",
    "sg:address":"4440 Cynthia St",
    "sg:city":"Bellaire",
    "sg:classifiers":[
        {
            "category":"Professional",
            "subcategory":"Computer Services",
            "type":"Services"
        }
    ],
    "sg:phone":"+1 713 669 9614",
    "sg:postcode":"77401",
    "sg:province":"TX",
    "sg:tags":[
        "datum"
    ],
    "wof:name":"Tech Data of Texas",
    "wof:placetype":"venue"
},
  "geometry": {"coordinates":[-95.45044900000001,29.693596],"type":"Point"}
}