{
  "type": "Feature",
  "properties": {
    "iso:country":"US",
    "sg:address":"4165 Eagle Dr",
    "sg:city":"Corpus Christi",
    "sg:classifiers":[
        {
            "category":"Recreation",
            "type":"Entertainment"
        }
    ],
    "sg:phone":"+1 361 853 2713",
    "sg:postcode":"78413",
    "sg:province":"TX",
    "sg:tags":[
        "charter",
        "fishing",
        "bay"
    ],
    "wof:name":"Capt Paul Eccleston",
    "wof:placetype":"venue"
},
  "geometry": {"coordinates":[-97.413178,27.694554],"type":"Point"}
}