{
  "type": "Feature",
  "properties": {
    "iso:country":"US",
    "sg:address":"5954 Southseas St",
    "sg:city":"Houston",
    "sg:classifiers":[
        {
            "category":"Health Services",
            "subcategory":"Clinic",
            "type":"Services"
        }
    ],
    "sg:phone":"+1 713 649 0934",
    "sg:postcode":"77033",
    "sg:province":"TX",
    "sg:tags":[
        "home"
    ],
    "wof:name":"Just Business",
    "wof:placetype":"venue"
},
  "geometry": {"coordinates":[-95.330719,29.676295],"type":"Point"}
}