{
  "type": "Feature",
  "properties": {
    "iso:country":"US",
    "sg:address":"1809 Palma Plz",
    "sg:city":"Austin",
    "sg:classifiers":[
        {
            "category":"Government",
            "subcategory":"Office",
            "type":"Public Place"
        }
    ],
    "sg:phone":"+1 512 477 6816",
    "sg:postcode":"78703",
    "sg:province":"TX",
    "sg:tags":[
        "conservation"
    ],
    "wof:name":"Creating Common Ground",
    "wof:placetype":"venue"
},
  "geometry": {"coordinates":[-97.76386599999999,30.284186],"type":"Point"}
}