{
  "type": "Feature",
  "properties": {
    "iso:country":"US",
    "sg:address":"1609 Shoal Creek Blvd",
    "sg:city":"Austin",
    "sg:classifiers":[
        {
            "category":"Professional",
            "subcategory":"Management & Consulting",
            "type":"Services"
        },
        {
            "category":"Banks & Credit Unions",
            "subcategory":"Financial Services",
            "type":"Services"
        }
    ],
    "sg:phone":"+1 512 440 1900",
    "sg:postcode":"78701",
    "sg:province":"TX",
    "sg:tags":[
        "consultant",
        "financing",
        "planning"
    ],
    "wof:name":"Equipment Finance Service",
    "wof:placetype":"venue"
},
  "geometry": {"coordinates":[-97.750169,30.281682],"type":"Point"}
}