{
  "type": "Feature",
  "properties": {
    "iso:country":"US",
    "sg:address":"8925 Rio Grande Dr",
    "sg:city":"Houston",
    "sg:classifiers":[
        {
            "category":"Recreation",
            "type":"Entertainment"
        }
    ],
    "sg:phone":"+1 281 890 9099",
    "sg:postcode":"77064",
    "sg:province":"TX",
    "wof:name":"Winchster Cntry Trils Clbhouse",
    "wof:placetype":"venue"
},
  "geometry": {"coordinates":[-95.57419,29.901701],"type":"Point"}
}