{
  "type": "Feature",
  "properties": {
    "iso:country":"US",
    "sg:address":"5 Circle E St",
    "sg:city":"Orange",
    "sg:classifiers":[
        {
            "category":"Shopping",
            "type":"Retail Goods"
        }
    ],
    "sg:phone":"+1 409 670 1970",
    "sg:postcode":"77630",
    "sg:province":"TX",
    "sg:tags":[
        "equipment",
        "safety",
        "supply"
    ],
    "wof:name":"Robert L Hebert",
    "wof:placetype":"venue"
},
  "geometry": {"coordinates":[-93.77087899999999,30.093777],"type":"Point"}
}