{
  "type": "Feature",
  "properties": {
    "iso:country":"US",
    "sg:address":"6836 Bee Cave Rd Ste 112",
    "sg:city":"Austin",
    "sg:classifiers":[
        {
            "category":"Health Services",
            "subcategory":"Doctor",
            "type":"Services"
        }
    ],
    "sg:phone":"+1 512 327 4243",
    "sg:postcode":"78746",
    "sg:province":"TX",
    "sg:tags":[
        "practice",
        "family"
    ],
    "sg:website":"www.beecavesmedical.com/",
    "wof:name":"Bee Caves Medical",
    "wof:placetype":"venue"
},
  "geometry": {"coordinates":[-97.838402,30.300371],"type":"Point"}
}