{
  "type": "Feature",
  "properties": {
    "iso:country":"US",
    "sg:address":"105 E Ferguson Ave",
    "sg:city":"Pharr",
    "sg:classifiers":[
        {
            "category":"Autos & Motor Vehicles",
            "subcategory":"Auto Supplies",
            "type":"Retail Goods"
        }
    ],
    "sg:phone":"+1 956 781 6772",
    "sg:postcode":"78577",
    "sg:province":"TX",
    "wof:name":"Universal Tires & Service",
    "wof:placetype":"venue"
},
  "geometry": {"coordinates":[-98.181331,26.21175],"type":"Point"}
}