{
  "type": "Feature",
  "properties": {
    "iso:country":"US",
    "sg:address":"707 N Shepherd Dr",
    "sg:city":"Houston",
    "sg:classifiers":[
        {
            "category":"Shopping",
            "type":"Retail Goods"
        }
    ],
    "sg:phone":"+1 713 622 3100",
    "sg:postcode":"77007",
    "sg:province":"TX",
    "sg:tags":[
        "packaging",
        "material"
    ],
    "sg:website":"http://www.crpkg.com",
    "wof:name":"Creative Retail Packaging",
    "wof:placetype":"venue"
},
  "geometry": {"coordinates":[-95.409739,29.7836],"type":"Point"}
}