{
  "type": "Feature",
  "properties": {
    "iso:country":"US",
    "sg:address":"834 W Hidalgo Ave",
    "sg:city":"Raymondville",
    "sg:classifiers":[
        {
            "category":"Shopping",
            "subcategory":"Clothing, Apparel, & Fashions",
            "type":"Retail Goods"
        }
    ],
    "sg:phone":"+1 956 689 9885",
    "sg:postcode":"78580",
    "sg:province":"TX",
    "wof:name":"Holy Cross Ministry Net Work",
    "wof:placetype":"venue"
},
  "geometry": {"coordinates":[-97.791595,26.481898],"type":"Point"}
}