{
  "type": "Feature",
  "properties": {
    "iso:country":"US",
    "sg:address":"1300 E 6th Ave",
    "sg:city":"Belton",
    "sg:classifiers":[
        {
            "category":"Health Services",
            "subcategory":"Doctor",
            "type":"Services"
        },
        {
            "category":"Health Services",
            "subcategory":"Clinic",
            "type":"Services"
        }
    ],
    "sg:phone":"+1 254 939 3715",
    "sg:postcode":"76513",
    "sg:province":"TX",
    "sg:tags":[
        "physician",
        "family",
        "medical",
        "practice",
        "surgeons",
        "medicine"
    ],
    "wof:name":"King's Daughters Clinic",
    "wof:placetype":"venue"
},
  "geometry": {"coordinates":[-97.448853,31.05817],"type":"Point"}
}