{
  "type": "Feature",
  "properties": {
    "iso:country":"US",
    "sg:address":"12406 Ledger Ln",
    "sg:city":"Houston",
    "sg:classifiers":[
        {
            "category":"Shopping",
            "subcategory":"Gifts & Souvenirs",
            "type":"Retail Goods"
        }
    ],
    "sg:phone":"+1 713 455 4369",
    "sg:postcode":"77015",
    "sg:province":"TX",
    "wof:name":"Thomas Latham Collectibles",
    "wof:placetype":"venue"
},
  "geometry": {"coordinates":[-95.21403599999999,29.7552],"type":"Point"}
}