{
  "type": "Feature",
  "properties": {
    "iso:country":"US",
    "sg:address":"9001 Markville Dr",
    "sg:city":"Dallas",
    "sg:classifiers":[
        {
            "category":"Professional",
            "type":"Services"
        }
    ],
    "sg:phone":"+1 972 680 2386",
    "sg:postcode":"75243",
    "sg:province":"TX",
    "sg:tags":[
        "establishment"
    ],
    "wof:name":"Multitechnology",
    "wof:placetype":"venue"
},
  "geometry": {"coordinates":[-96.749933,32.915425],"type":"Point"}
}