{
  "type": "Feature",
  "properties": {
    "iso:country":"US",
    "sg:address":"9423 Rentur Dr",
    "sg:city":"Houston",
    "sg:classifiers":[
        {
            "category":"Professional",
            "type":"Services"
        }
    ],
    "sg:phone":"+1 713 484 5765",
    "sg:postcode":"77031",
    "sg:province":"TX",
    "wof:name":"Karen Dollahon",
    "wof:placetype":"venue"
},
  "geometry": {"coordinates":[-95.54256100000001,29.663551],"type":"Point"}
}