{
  "type": "Feature",
  "properties": {
    "iso:country":"US",
    "sg:address":"867 Stoddard Rd",
    "sg:city":"Mc Kinney",
    "sg:classifiers":[
        {
            "category":"Building & Trades",
            "subcategory":"Construction",
            "type":"Services"
        }
    ],
    "sg:phone":"+1 972 562 2302",
    "sg:postcode":"75069",
    "sg:province":"TX",
    "sg:tags":[
        "excavating",
        "contractor"
    ],
    "wof:name":"Scott Mc Croskey Tractor Svc",
    "wof:placetype":"venue"
},
  "geometry": {"coordinates":[-96.626149,33.153032],"type":"Point"}
}