{
  "type": "Feature",
  "properties": {
    "iso:country":"US",
    "sg:address":"7603 Dillon St",
    "sg:city":"Houston",
    "sg:classifiers":[
        {
            "category":"Food & Beverages",
            "subcategory":"Specialty",
            "type":"Retail Goods"
        }
    ],
    "sg:phone":"+1 713 643 5215",
    "sg:postcode":"77061",
    "sg:province":"TX",
    "sg:tags":[
        "merchandise"
    ],
    "wof:name":"Lawson Associate",
    "wof:placetype":"venue"
},
  "geometry": {"coordinates":[-95.281313,29.662358],"type":"Point"}
}