{
  "type": "Feature",
  "properties": {
    "iso:country":"US",
    "sg:address":"223 SW 4th Ave",
    "sg:city":"Amarillo",
    "sg:classifiers":[
        {
            "category":"Professional",
            "subcategory":"Lawyer & Legal Services",
            "type":"Services"
        }
    ],
    "sg:phone":"+1 806 322 7777",
    "sg:postcode":"79101",
    "sg:province":"AR",
    "sg:tags":[
        "attorney"
    ],
    "wof:name":"Janis Alexander Law Office",
    "wof:placetype":"venue"
},
  "geometry": {"coordinates":[-101.839033,35.209914],"type":"Point"}
}