{
  "type": "Feature",
  "properties": {
    "iso:country":"US",
    "sg:address":"727 Old Underwood Rd",
    "sg:city":"La Porte",
    "sg:classifiers":[
        {
            "category":"Wholesale",
            "subcategory":"Petroleum",
            "type":"Manufacturing & Wholesale Goods"
        }
    ],
    "sg:phone":"+1 281 471 9440",
    "sg:postcode":"77571",
    "sg:province":"TX",
    "sg:tags":[
        "pipe",
        "refined",
        "pipeline",
        "line",
        "company"
    ],
    "wof:name":"Dow Pipeline Company",
    "wof:placetype":"venue"
},
  "geometry": {"coordinates":[-95.088129,29.693827],"type":"Point"}
}