{
  "type": "Feature",
  "properties": {
    "iso:country":"US",
    "sg:address":"513 S Guadalupe St",
    "sg:city":"San Marcos",
    "sg:classifiers":[
        {
            "category":"Retail",
            "subcategory":"Repair Shop",
            "type":"Services"
        }
    ],
    "sg:phone":"+1 512 392 9732",
    "sg:postcode":"78666",
    "sg:province":"TX",
    "sg:tags":[
        "upholsterer"
    ],
    "wof:name":"Pete's Upholstery Shop",
    "wof:placetype":"venue"
},
  "geometry": {"coordinates":[-97.94006299999999,29.875351],"type":"Point"}
}