{
  "type": "Feature",
  "properties": {
    "iso:country":"US",
    "sg:address":"2937 W Anderson Ln",
    "sg:city":"Austin",
    "sg:classifiers":[
        {
            "category":"Deli",
            "type":"Food & Drink"
        }
    ],
    "sg:menulink":"http://www.allmenus.com/tx/austin/126729-blimpie-subs--sandwiches/menu/",
    "sg:phone":"+1 512 452 5011",
    "sg:postcode":"78757",
    "sg:province":"TX",
    "sg:tags":[
        "wrap",
        "american",
        "sandwich"
    ],
    "wof:name":"Blimpie Subs & Sandwiches",
    "wof:placetype":"venue"
},
  "geometry": {"coordinates":[-97.738851,30.35977],"type":"Point"}
}