{
  "type": "Feature",
  "properties": {
    "iso:country":"US",
    "sg:address":"415 E College St",
    "sg:city":"Grapevine",
    "sg:classifiers":[
        {
            "category":"Professional",
            "subcategory":"Computer Services",
            "type":"Services"
        }
    ],
    "sg:phone":"+1 817 421 4413",
    "sg:postcode":"76051",
    "sg:province":"TX",
    "sg:tags":[
        "consultant",
        "designer",
        "systems-consultants",
        "system",
        "data"
    ],
    "wof:name":"Co In Motion Inc",
    "wof:placetype":"venue"
},
  "geometry": {"coordinates":[-97.074206,32.935551],"type":"Point"}
}