{
  "type": "Feature",
  "properties": {
    "iso:country":"US",
    "sg:address":"1103 Dallas St",
    "sg:city":"Waco",
    "sg:classifiers":[
        {
            "category":"Building & Trades",
            "subcategory":"Construction",
            "type":"Services"
        }
    ],
    "sg:phone":"+1 254 754 1363",
    "sg:postcode":"76704",
    "sg:province":"TX",
    "sg:tags":[
        "house"
    ],
    "wof:name":"W G Clark Construction Company",
    "wof:placetype":"venue"
},
  "geometry": {"coordinates":[-97.133343,31.571392],"type":"Point"}
}