{
  "type": "Feature",
  "properties": {
    "iso:country":"US",
    "sg:address":"4255 Old Highway 77",
    "sg:city":"Brownsville",
    "sg:phone":"+1 956 350 2822",
    "sg:postcode":"78520",
    "sg:province":"TX",
    "wof:name":"Mardel Souza Inc",
    "wof:placetype":"venue"
},
  "geometry": {"coordinates":[-97.51237500000001,25.964279],"type":"Point"}
}