{
  "type": "Feature",
  "properties": {
    "iso:country":"US",
    "sg:address":"8500 Beatton Ct",
    "sg:city":"Plano",
    "sg:classifiers":[
        {
            "category":"Wholesale",
            "subcategory":"Non-durable Goods",
            "type":"Manufacturing & Wholesale Goods"
        }
    ],
    "sg:phone":"+1 972 335 0325",
    "sg:postcode":"75025",
    "sg:province":"TX",
    "wof:name":"Be Mine Treasures",
    "wof:placetype":"venue"
},
  "geometry": {"coordinates":[-96.76874599999999,33.09323],"type":"Point"}
}