{
  "type": "Feature",
  "properties": {
    "iso:country":"US",
    "sg:address":"34 Greenview Cir",
    "sg:city":"Richardson",
    "sg:classifiers":[
        {
            "category":"Building & Trades",
            "subcategory":"Construction",
            "type":"Services"
        }
    ],
    "sg:phone":"+1 972 918 9240",
    "sg:postcode":"75081",
    "sg:province":"TX",
    "sg:tags":[
        "house"
    ],
    "wof:name":"Rmp Service",
    "wof:placetype":"venue"
},
  "geometry": {"coordinates":[-96.687083,32.937378],"type":"Point"}
}