{
  "type": "Feature",
  "properties": {
    "iso:country":"US",
    "sg:address":"1600 Coit Rd",
    "sg:city":"Plano",
    "sg:classifiers":[
        {
            "category":"Health Services",
            "subcategory":"Doctor",
            "type":"Services"
        }
    ],
    "sg:phone":"+1 972 599 9600",
    "sg:postcode":"75075",
    "sg:province":"TX",
    "sg:tags":[
        "medical"
    ],
    "wof:name":"Family Med Spcalists Texas LLP",
    "wof:placetype":"venue"
},
  "geometry": {"coordinates":[-96.76830699999999,33.021602],"type":"Point"}
}