{
  "type": "Feature",
  "properties": {
    "iso:country":"US",
    "sg:address":"7051 Alameda Ave",
    "sg:city":"El Paso",
    "sg:classifiers":[
        {
            "category":"Personal",
            "subcategory":"Beauty Salon",
            "type":"Services"
        }
    ],
    "sg:phone":"+1 915 778 6616",
    "sg:postcode":"79915",
    "sg:province":"TX",
    "sg:tags":[
        "shop"
    ],
    "wof:name":"Velsoned Hairstylists",
    "wof:placetype":"venue"
},
  "geometry": {"coordinates":[-106.395174,31.756174],"type":"Point"}
}