{
  "type": "Feature",
  "properties": {
    "iso:country":"US",
    "sg:address":"3008 Sandage Ave",
    "sg:city":"Fort Worth",
    "sg:classifiers":[
        {
            "category":"Personal",
            "type":"Services"
        }
    ],
    "sg:phone":"+1 817 921 4781",
    "sg:postcode":"76109",
    "sg:province":"TX",
    "sg:tags":[
        "electrologist"
    ],
    "wof:name":"Lady M Of London Facial Salon",
    "wof:placetype":"venue"
},
  "geometry": {"coordinates":[-97.35451500000001,32.706197],"type":"Point"}
}