{
  "type": "Feature",
  "properties": {
    "iso:country":"US",
    "sg:address":"13802 Diplomat Dr",
    "sg:city":"Dallas",
    "sg:classifiers":[
        {
            "category":"Professional",
            "subcategory":"Management & Consulting",
            "type":"Services"
        }
    ],
    "sg:phone":"+1 214 459 9970",
    "sg:postcode":"75234",
    "sg:province":"TX",
    "sg:tags":[
        "communications",
        "business",
        "consultant"
    ],
    "wof:name":"R M S Communications Group",
    "wof:placetype":"venue"
},
  "geometry": {"coordinates":[-96.906575,32.936503],"type":"Point"}
}