{
  "type": "Feature",
  "properties": {
    "iso:country":"US",
    "sg:address":"16051 Addison Rd",
    "sg:city":"Addison",
    "sg:classifiers":[
        {
            "category":"Real Estate",
            "subcategory":"Real Estate Services",
            "type":"Services"
        },
        {
            "category":"Real Estate",
            "subcategory":"Real Estate Agent",
            "type":"Services"
        }
    ],
    "sg:phone":"+1 972 233 3498",
    "sg:postcode":"75001",
    "sg:province":"TX",
    "sg:tags":[
        "buyer",
        "broker"
    ],
    "wof:name":"Tapp Company",
    "wof:placetype":"venue"
},
  "geometry": {"coordinates":[-96.82989000000001,32.968111],"type":"Point"}
}