{
  "type": "Feature",
  "properties": {
    "iso:country":"US",
    "sg:address":"19209 Sunken Creek Pass",
    "sg:city":"Pflugerville",
    "sg:classifiers":[
        {
            "category":"Banks & Credit Unions",
            "subcategory":"Financial Services",
            "type":"Services"
        }
    ],
    "sg:phone":"+1 512 415 1103",
    "sg:postcode":"78660",
    "sg:province":"TX",
    "wof:name":"Strategic Financial Svc.",
    "wof:placetype":"venue"
},
  "geometry": {"coordinates":[-97.58971699999999,30.471774],"type":"Point"}
}