{
  "type": "Feature",
  "properties": {
    "iso:country":"US",
    "sg:address":"1918 Shawnee Trl",
    "sg:city":"Dalhart",
    "sg:classifiers":[
        {
            "category":"Airline",
            "type":"Transportation"
        }
    ],
    "sg:phone":"+1 806 244 5765",
    "sg:postcode":"79022",
    "sg:province":"TX",
    "sg:tags":[
        "nonscheduled",
        "air"
    ],
    "wof:name":"Outlaw Air Inc",
    "wof:placetype":"venue"
},
  "geometry": {"coordinates":[-102.503338,36.046264],"type":"Point"}
}