{
  "type": "Feature",
  "properties": {
    "iso:country":"US",
    "sg:address":"201 NE",
    "sg:city":"Edgewood",
    "sg:classifiers":[
        {
            "category":"Home & Garden",
            "subcategory":"Carpets & Floor Coverings",
            "type":"Retail Goods"
        }
    ],
    "sg:phone":"+1 903 896 4914",
    "sg:postcode":"75117",
    "sg:province":"TX",
    "sg:tags":[
        "carpeting"
    ],
    "wof:name":"J K's Carpet",
    "wof:placetype":"venue"
},
  "geometry": {"coordinates":[-95.322688,29.744414],"type":"Point"}
}