{
  "type": "Feature",
  "properties": {
    "iso:country":"US",
    "sg:address":"1915 Augusta Dr Apt 7",
    "sg:city":"Houston",
    "sg:classifiers":[
        {
            "category":"Home & Garden",
            "subcategory":"Garden Supply",
            "type":"Retail Goods"
        },
        {
            "category":"Shopping",
            "subcategory":"Florist",
            "type":"Retail Goods"
        }
    ],
    "sg:phone":"+1 281 217 7323",
    "sg:postcode":"77057",
    "sg:province":"TX",
    "sg:tags":[
        "plant"
    ],
    "sg:website":"http://www.tropicaexotica.com",
    "wof:name":"Tropica Exotica",
    "wof:placetype":"venue"
},
  "geometry": {"coordinates":[-95.482597,29.747559],"type":"Point"}
}