{
  "type": "Feature",
  "properties": {
    "iso:country":"US",
    "sg:address":"297 W Campbell Rd",
    "sg:city":"Richardson",
    "sg:classifiers":[
        {
            "category":"Shopping",
            "subcategory":"Jewelry",
            "type":"Retail Goods"
        }
    ],
    "sg:phone":"+1 972 231 4100",
    "sg:postcode":"75080",
    "sg:province":"TX",
    "sg:website":"silverartsjewelry.com/",
    "wof:name":"Silver Arts Jewelry Co",
    "wof:placetype":"venue"
},
  "geometry": {"coordinates":[-96.72441600000001,32.975353],"type":"Point"}
}