{
  "type": "Feature",
  "properties": {
    "iso:country":"US",
    "sg:address":"4329 Loma de Luna Dr",
    "sg:city":"El Paso",
    "sg:classifiers":[
        {
            "category":"Professional",
            "subcategory":"Accounting & Tax Preparation",
            "type":"Services"
        }
    ],
    "sg:phone":"+1 915 821 2828",
    "sg:postcode":"79934",
    "sg:province":"TX",
    "wof:name":"Certified Public Accountant",
    "wof:placetype":"venue"
},
  "geometry": {"coordinates":[-106.44605900000001,31.935136],"type":"Point"}
}