{
  "type": "Feature",
  "properties": {
    "iso:country":"US",
    "sg:address":"621 Briar Ct",
    "sg:city":"Kennedale",
    "sg:classifiers":[
        {
            "category":"Health Services",
            "subcategory":"Doctor",
            "type":"Services"
        }
    ],
    "sg:phone":"+1 817 561 1229",
    "sg:postcode":"76060",
    "sg:province":"TX",
    "sg:tags":[
        "physician",
        "surgeon"
    ],
    "wof:name":"David Allen",
    "wof:placetype":"venue"
},
  "geometry": {"coordinates":[-97.217364,32.651735],"type":"Point"}
}