{
  "type": "Feature",
  "properties": {
    "iso:country":"US",
    "sg:address":"215 Williamsburg Ave",
    "sg:city":"Victoria",
    "sg:classifiers":[
        {
            "category":"Retail",
            "subcategory":"Portrait Studio",
            "type":"Services"
        }
    ],
    "sg:phone":"+1 361 570 7060",
    "sg:postcode":"77904",
    "sg:province":"TX",
    "sg:tags":[
        "photo"
    ],
    "wof:name":"Images By Miguel Gonzalez",
    "wof:placetype":"venue"
},
  "geometry": {"coordinates":[-96.974957,28.851114],"type":"Point"}
}