{
  "type": "Feature",
  "properties": {
    "iso:country":"US",
    "sg:address":"529 W Rock Island Rd",
    "sg:city":"Grand Prairie",
    "sg:classifiers":[
        {
            "category":"Wholesale",
            "subcategory":"Apparel",
            "type":"Manufacturing & Wholesale Goods"
        }
    ],
    "sg:phone":"+1 972 313 0044",
    "sg:postcode":"75050",
    "sg:province":"TX",
    "sg:tags":[
        "distributor",
        "machine",
        "milling",
        "repair"
    ],
    "wof:name":"Eagle Machine Services",
    "wof:placetype":"venue"
},
  "geometry": {"coordinates":[-97.00593000000001,32.815661],"type":"Point"}
}