{
  "type": "Feature",
  "properties": {
    "iso:country":"US",
    "sg:address":"5921 Fm 2920 Rd",
    "sg:city":"Spring",
    "sg:classifiers":[
        {
            "category":"Personal",
            "subcategory":"Beauty Salon",
            "type":"Services"
        },
        {
            "category":"Personal",
            "subcategory":"Tanning Parlor",
            "type":"Services"
        }
    ],
    "sg:phone":"+1 281 907 0999",
    "sg:postcode":"77388",
    "sg:province":"TX",
    "wof:name":"Malibu Tan",
    "wof:placetype":"venue"
},
  "geometry": {"coordinates":[-95.510981,30.074069],"type":"Point"}
}