{
  "type": "Feature",
  "properties": {
    "iso:country":"US",
    "sg:address":"2200 Canyon Valley Trl",
    "sg:city":"Plano",
    "sg:classifiers":[
        {
            "category":"Retail",
            "subcategory":"Animal Services",
            "type":"Services"
        }
    ],
    "sg:phone":"+1 972 964 3816",
    "sg:postcode":"75023",
    "sg:province":"TX",
    "wof:name":"K9 Corp",
    "wof:placetype":"venue"
},
  "geometry": {"coordinates":[-96.733451,33.045249],"type":"Point"}
}