{
  "type": "Feature",
  "properties": {
    "iso:country":"US",
    "sg:address":"117 E Main St",
    "sg:city":"Olney",
    "sg:classifiers":[
        {
            "category":"Health Services",
            "subcategory":"Clinic",
            "type":"Services"
        }
    ],
    "sg:phone":"+1 940 564 4046",
    "sg:postcode":"76374",
    "sg:province":"TX",
    "wof:name":"Outreach Health Svc",
    "wof:placetype":"venue"
},
  "geometry": {"coordinates":[-98.753873,33.370693],"type":"Point"}
}