{
  "type": "Feature",
  "properties": {
    "iso:country":"US",
    "sg:address":"1026 Radio Ln",
    "sg:city":"Rosenberg",
    "sg:classifiers":[
        {
            "category":"Organizations",
            "subcategory":"Religious Organization",
            "type":"Services"
        }
    ],
    "sg:phone":"+1 281 342 8800",
    "sg:postcode":"77471",
    "sg:province":"TX",
    "sg:tags":[
        "church"
    ],
    "wof:name":"Peace Lutheran Church",
    "wof:placetype":"venue"
},
  "geometry": {"coordinates":[-95.78357099999999,29.559067],"type":"Point"}
}