{
  "type": "Feature",
  "properties": {
    "iso:country":"US",
    "sg:address":"723 Hill Country Dr Ste C",
    "sg:city":"Kerrville",
    "sg:classifiers":[
        {
            "category":"Health Services",
            "subcategory":"Doctor",
            "type":"Services"
        },
        {
            "category":"Health Services",
            "subcategory":"Clinic",
            "type":"Services"
        }
    ],
    "sg:phone":"+1 830 792 5800",
    "sg:postcode":"78028",
    "sg:province":"TX",
    "sg:tags":[
        "physician",
        "family",
        "medical",
        "practice",
        "surgeons",
        "osteopathic",
        "medicine"
    ],
    "wof:name":"Franklin Clinic",
    "wof:placetype":"venue"
},
  "geometry": {"coordinates":[-99.147138,30.040818],"type":"Point"}
}