{
  "type": "Feature",
  "properties": {
    "iso:country":"US",
    "sg:address":"3318 Wildcandle Dr",
    "sg:city":"Spring",
    "sg:classifiers":[
        {
            "category":"Professional",
            "subcategory":"Advertising",
            "type":"Services"
        }
    ],
    "sg:phone":"+1 281 353 7335",
    "sg:postcode":"77388",
    "sg:province":"TX",
    "sg:tags":[
        "distribution"
    ],
    "wof:name":"Espresso Partners",
    "wof:placetype":"venue"
},
  "geometry": {"coordinates":[-95.46186899999999,30.049129],"type":"Point"}
}