{
  "type": "Feature",
  "properties": {
    "iso:country":"US",
    "sg:address":"2331 Gus Thomasson Rd",
    "sg:city":"Dallas",
    "sg:classifiers":[
        {
            "category":"Building & Trades",
            "subcategory":"Construction",
            "type":"Services"
        }
    ],
    "sg:phone":"+1 214 327 7273",
    "sg:postcode":"75228",
    "sg:province":"TX",
    "sg:tags":[
        "hanging",
        "contractor"
    ],
    "wof:name":"Grace Amazing Painters",
    "wof:placetype":"venue"
},
  "geometry": {"coordinates":[-96.67448400000001,32.834834],"type":"Point"}
}