{
  "type": "Feature",
  "properties": {
    "iso:country":"US",
    "sg:address":"206 Royston Ave",
    "sg:city":"San Antonio",
    "sg:classifiers":[
        {
            "category":"Personal",
            "subcategory":"Beauty Salon",
            "type":"Services"
        }
    ],
    "sg:phone":"+1 210 927 2366",
    "sg:postcode":"78225",
    "sg:province":"TX",
    "sg:tags":[
        "shop"
    ],
    "wof:name":"Rickies Wigs",
    "wof:placetype":"venue"
},
  "geometry": {"coordinates":[-98.527214,29.386613],"type":"Point"}
}