{
  "type": "Feature",
  "properties": {
    "iso:country":"US",
    "sg:address":"16310 Quail Nest Ct",
    "sg:city":"Missouri City",
    "sg:classifiers":[
        {
            "category":"Building & Trades",
            "subcategory":"Construction",
            "type":"Services"
        }
    ],
    "sg:phone":"+1 281 835 3159",
    "sg:postcode":"77489",
    "sg:province":"TX",
    "sg:tags":[
        "house"
    ],
    "wof:name":"Whites Home Building & R",
    "wof:placetype":"venue"
},
  "geometry": {"coordinates":[-95.51127099999999,29.590726],"type":"Point"}
}