{
  "type": "Feature",
  "properties": {
    "iso:country":"US",
    "sg:address":"9611 Oregano Cir",
    "sg:city":"Houston",
    "sg:classifiers":[
        {
            "category":"Restaurant",
            "type":"Food & Drink"
        }
    ],
    "sg:phone":"+1 713 779 6580",
    "sg:postcode":"77036",
    "sg:province":"TX",
    "sg:tags":[
        "eating"
    ],
    "wof:name":"Empire Catered Events",
    "wof:placetype":"venue"
},
  "geometry": {"coordinates":[-95.551259,29.694731],"type":"Point"}
}