{
  "type": "Feature",
  "properties": {
    "iso:country":"US",
    "sg:address":"2801 Nogalitos St",
    "sg:city":"San Antonio",
    "sg:classifiers":[
        {
            "category":"Food & Beverages",
            "subcategory":"Groceries & Convenience Stores",
            "type":"Retail Goods"
        }
    ],
    "sg:phone":"+1 210 923 7531",
    "sg:postcode":"78225",
    "sg:province":"TX",
    "sg:tags":[
        "grocer"
    ],
    "wof:name":"Handy Andy Supermarkets",
    "wof:placetype":"venue"
},
  "geometry": {"coordinates":[-98.523304,29.387141],"type":"Point"}
}