{
  "type": "Feature",
  "properties": {
    "iso:country":"US",
    "sg:address":"226 FM 813 W",
    "sg:city":"Palmer",
    "sg:phone":"+1 972 845 2150",
    "sg:postcode":"75152",
    "sg:province":"TX",
    "sg:tags":[
        "farm",
        "field",
        "crop"
    ],
    "wof:name":"Charles Prude",
    "wof:placetype":"venue"
},
  "geometry": {"coordinates":[-96.681811,32.431081],"type":"Point"}
}