{
  "type": "Feature",
  "properties": {
    "iso:country":"US",
    "sg:address":"1102 Scott St",
    "sg:city":"Laredo",
    "sg:classifiers":[
        {
            "category":"Insurance",
            "subcategory":"Insurance Agent",
            "type":"Services"
        }
    ],
    "sg:phone":"+1 956 724 4047",
    "sg:postcode":"78040",
    "sg:province":"TX",
    "sg:tags":[
        "adjuster"
    ],
    "wof:name":"Universal Claims Svc",
    "wof:placetype":"venue"
},
  "geometry": {"coordinates":[-99.507447,27.510729],"type":"Point"}
}