{
  "type": "Feature",
  "properties": {
    "iso:country":"US",
    "sg:address":"4226 Rosa Ct",
    "sg:city":"Dallas",
    "sg:classifiers":[
        {
            "category":"Mining & Drilling",
            "type":"Manufacturing & Wholesale Goods"
        }
    ],
    "sg:phone":"+1 214 902 0540",
    "sg:postcode":"75220",
    "sg:province":"TX",
    "sg:tags":[
        "exploration"
    ],
    "wof:name":"Thomas Operating Ltd Company",
    "wof:placetype":"venue"
},
  "geometry": {"coordinates":[-96.836386,32.866599],"type":"Point"}
}