{
  "type": "Feature",
  "properties": {
    "iso:country":"US",
    "sg:address":"812 W Madison St",
    "sg:city":"Ennis",
    "sg:classifiers":[
        {
            "category":"Personal",
            "type":"Services"
        }
    ],
    "sg:phone":"+1 972 878 1067",
    "sg:postcode":"75119",
    "sg:province":"TX",
    "wof:name":"Lisa Schumacher",
    "wof:placetype":"venue"
},
  "geometry": {"coordinates":[-96.62902200000001,32.316511],"type":"Point"}
}