{
  "type": "Feature",
  "properties": {
    "iso:country":"US",
    "sg:address":"1100 N 4th St",
    "sg:city":"Uvalde",
    "sg:classifiers":[
        {
            "category":"Farming",
            "subcategory":"Livestock Farm",
            "type":"Manufacturing & Wholesale Goods"
        }
    ],
    "sg:phone":"+1 830 278 6083",
    "sg:postcode":"78801",
    "sg:province":"TX",
    "sg:tags":[
        "beef",
        "feedlot",
        "cattle"
    ],
    "wof:name":"Bracy Ranch Ltd",
    "wof:placetype":"venue"
},
  "geometry": {"coordinates":[-99.781526,29.230005],"type":"Point"}
}