{
  "type": "Feature",
  "properties": {
    "iso:country":"US",
    "sg:address":"8104 Old Hwy 105 W",
    "sg:city":"Conroe",
    "sg:classifiers":[
        {
            "category":"Personal",
            "subcategory":"Beauty Salon",
            "type":"Services"
        }
    ],
    "sg:phone":"+1 936 588 3610",
    "sg:postcode":"77304",
    "sg:province":"TX",
    "sg:tags":[
        "shop"
    ],
    "wof:name":"Marcellas Beauty Shop",
    "wof:placetype":"venue"
},
  "geometry": {"coordinates":[-95.550194,30.318999],"type":"Point"}
}