{
  "type": "Feature",
  "properties": {
    "iso:country":"US",
    "sg:address":"622 Meadowbrook Dr",
    "sg:city":"Longview",
    "sg:classifiers":[
        {
            "category":"Personal",
            "subcategory":"Shoe Repair & Shine",
            "type":"Services"
        }
    ],
    "sg:phone":"+1 903 753 9319",
    "sg:postcode":"75601",
    "sg:province":"TX",
    "sg:tags":[
        "repairing",
        "parlor",
        "boot"
    ],
    "wof:name":"Brookwood Village Shoe Hosp",
    "wof:placetype":"venue"
},
  "geometry": {"coordinates":[-94.749225,32.51151],"type":"Point"}
}