{
  "type": "Feature",
  "properties": {
    "iso:country":"US",
    "sg:address":"1805 Everglade Dr",
    "sg:city":"Deer Park",
    "sg:classifiers":[
        {
            "category":"Professional",
            "subcategory":"Computer Services",
            "type":"Services"
        }
    ],
    "sg:phone":"+1 281 542 5850",
    "sg:postcode":"77502",
    "sg:province":"TX",
    "sg:tags":[
        "prepackaged",
        "software"
    ],
    "wof:name":"D P Technology",
    "wof:placetype":"venue"
},
  "geometry": {"coordinates":[-95.185289,29.672249],"type":"Point"}
}