{
  "type": "Feature",
  "properties": {
    "iso:country":"US",
    "sg:address":"1121 W Pioneer Dr",
    "sg:city":"Irving",
    "sg:classifiers":[
        {
            "category":"Retail",
            "subcategory":"Laundry & Dry Cleaning",
            "type":"Services"
        }
    ],
    "sg:phone":"+1 972 253 6161",
    "sg:postcode":"75061",
    "sg:province":"TX",
    "wof:name":"Ambis Dry Cleaners",
    "wof:placetype":"venue"
},
  "geometry": {"coordinates":[-96.960503,32.821701],"type":"Point"}
}