{
  "type": "Feature",
  "properties": {
    "iso:country":"US",
    "sg:address":"119 Bailey Ave",
    "sg:city":"Dumas",
    "sg:classifiers":[
        {
            "category":"Shopping",
            "subcategory":"Clothing, Apparel, & Fashions",
            "type":"Retail Goods"
        }
    ],
    "sg:phone":"+1 806 935 9010",
    "sg:postcode":"79029",
    "sg:province":"TX",
    "sg:tags":[
        "ready",
        "teenage"
    ],
    "wof:name":"Bright Spot",
    "wof:placetype":"venue"
},
  "geometry": {"coordinates":[-101.953604,35.866246],"type":"Point"}
}