{
  "type": "Feature",
  "properties": {
    "iso:country":"US",
    "sg:address":"3842 Butterfield Rd",
    "sg:city":"San Angelo",
    "sg:classifiers":[
        {
            "category":"Professional",
            "subcategory":"Business Services",
            "type":"Services"
        }
    ],
    "sg:phone":"+1 325 944 1439",
    "sg:postcode":"76904",
    "sg:province":"TX",
    "sg:tags":[
        "building",
        "operator",
        "nonresidential"
    ],
    "wof:name":"Star Promenaders",
    "wof:placetype":"venue"
},
  "geometry": {"coordinates":[-100.490916,31.434856],"type":"Point"}
}