{
  "type": "Feature",
  "properties": {
    "iso:country":"US",
    "sg:address":"12300 Ford Rd",
    "sg:city":"Farmers Branch",
    "sg:classifiers":[
        {
            "category":"Insurance",
            "subcategory":"Insurance Agent",
            "type":"Services"
        }
    ],
    "sg:phone":"+1 972 484 4637",
    "sg:postcode":"75234",
    "sg:province":"TX",
    "wof:name":"Medical Evaluation Specialists",
    "wof:placetype":"venue"
},
  "geometry": {"coordinates":[-96.891424,32.912324],"type":"Point"}
}