{
  "type": "Feature",
  "properties": {
    "iso:country":"US",
    "sg:address":"920 S Mason Rd",
    "sg:city":"Katy",
    "sg:classifiers":[
        {
            "category":"Recreation",
            "type":"Entertainment"
        }
    ],
    "sg:phone":"+1 281 392 6668",
    "sg:postcode":"77450",
    "sg:province":"TX",
    "wof:name":"Katy Uma Taekwondo",
    "wof:placetype":"venue"
},
  "geometry": {"coordinates":[-95.751761,29.768848],"type":"Point"}
}