{
  "type": "Feature",
  "properties": {
    "iso:country":"US",
    "sg:address":"4315 Shenandoah St",
    "sg:city":"Dallas",
    "sg:classifiers":[
        {
            "category":"Professional",
            "subcategory":"Lawyer & Legal Services",
            "type":"Services"
        }
    ],
    "sg:phone":"+1 214 219 1467",
    "sg:postcode":"75205",
    "sg:province":"TX",
    "wof:name":"Keeble Charles C Jr Atty",
    "wof:placetype":"venue"
},
  "geometry": {"coordinates":[-96.80970000000001,32.8405],"type":"Point"}
}