{
  "type": "Feature",
  "properties": {
    "iso:country":"US",
    "sg:address":"11222 Fountain Lake Dr",
    "sg:city":"Stafford",
    "sg:classifiers":[
        {
            "category":"Restaurant",
            "type":"Food & Drink"
        }
    ],
    "sg:phone":"+1 281 313 6886",
    "sg:postcode":"77477",
    "sg:province":"TX",
    "sg:tags":[
        "eating"
    ],
    "wof:name":"Otto's Barbecue",
    "wof:placetype":"venue"
},
  "geometry": {"coordinates":[-95.589448,29.638644],"type":"Point"}
}