{
  "type": "Feature",
  "properties": {
    "iso:country":"US",
    "sg:address":"Oltorf and S 1st",
    "sg:city":"Austin",
    "sg:classifiers":[
        {
            "category":"Autos & Motor Vehicles",
            "subcategory":"Fuel & Gas Station",
            "type":"Retail Goods"
        }
    ],
    "sg:postcode":"78704",
    "sg:province":"TX",
    "wof:name":"Texaco",
    "wof:placetype":"venue"
},
  "geometry": {"coordinates":[-97.75963299999999,30.242119],"type":"Point"}
}