{
  "type": "Feature",
  "properties": {
    "iso:country":"US",
    "sg:address":"404 N Bryant Ave",
    "sg:city":"Sherman",
    "sg:classifiers":[
        {
            "category":"Health Services",
            "subcategory":"Doctor",
            "type":"Services"
        }
    ],
    "sg:phone":"+1 903 893 5757",
    "sg:postcode":"75092",
    "sg:province":"TX",
    "wof:name":"Jerry M Anderson DDS",
    "wof:placetype":"venue"
},
  "geometry": {"coordinates":[-96.624875,33.638112],"type":"Point"}
}