{
  "type": "Feature",
  "properties": {
    "iso:country":"US",
    "sg:address":"932 S Main St",
    "sg:city":"Lumberton",
    "sg:classifiers":[
        {
            "category":"Personal",
            "subcategory":"Beauty Salon",
            "type":"Services"
        }
    ],
    "sg:phone":"+1 409 755 2155",
    "sg:postcode":"77657",
    "sg:province":"TX",
    "wof:name":"Secrets",
    "wof:placetype":"venue"
},
  "geometry": {"coordinates":[-94.195469,30.238929],"type":"Point"}
}