{
  "type": "Feature",
  "properties": {
    "iso:country":"US",
    "sg:address":"16055 Space Center Blvd Suite 700",
    "sg:city":"Houston",
    "sg:classifiers":[
        {
            "category":"Professional",
            "subcategory":"Computer Services",
            "type":"Services"
        }
    ],
    "sg:phone":"+1 713 589 6511",
    "sg:postcode":"77062",
    "sg:province":"TX",
    "sg:tags":[
        "referral-recruitment",
        "online-recruitment-tool",
        "strategic-sourcing",
        "social-networks",
        "cancidate-referrals",
        "employee-referral-programs"
    ],
    "sg:website":"http://www.cachinko.com",
    "wof:name":"Cachinko",
    "wof:placetype":"venue"
},
  "geometry": {"coordinates":[-95.11183699999999,29.573279],"type":"Point"}
}