{
  "type": "Feature",
  "properties": {
    "iso:country":"US",
    "sg:address":"321 N Central Expy",
    "sg:city":"Mc Kinney",
    "sg:classifiers":[
        {
            "category":"Professional",
            "subcategory":"Management & Consulting",
            "type":"Services"
        }
    ],
    "sg:phone":"+1 972 562 5430",
    "sg:postcode":"75070",
    "sg:province":"TX",
    "sg:tags":[
        "development",
        "economic",
        "agency"
    ],
    "wof:name":"Mc Kinney Economic Development",
    "wof:placetype":"venue"
},
  "geometry": {"coordinates":[-96.639105,33.202009],"type":"Point"}
}