{
  "type": "Feature",
  "properties": {
    "iso:country":"US",
    "sg:address":"7207 Garth Rd",
    "sg:city":"Baytown",
    "sg:classifiers":[
        {
            "category":"Restaurant",
            "type":"Food & Drink"
        }
    ],
    "sg:menulink":"http://www.allmenus.com/tx/northeast-harris/11112-dennys/menu/",
    "sg:phone":"+1 281 839 1191",
    "sg:postcode":"77521",
    "sg:province":"TX",
    "sg:tags":[
        "american",
        "diner"
    ],
    "wof:name":"Denny's",
    "wof:placetype":"venue"
},
  "geometry": {"coordinates":[-94.98205799999999,29.806583],"type":"Point"}
}