{
  "type": "Feature",
  "properties": {
    "iso:country":"US",
    "sg:address":"3124 N Houston St",
    "sg:city":"Fort Worth",
    "sg:classifiers":[
        {
            "category":"Organizations",
            "subcategory":"Religious Organization",
            "type":"Services"
        }
    ],
    "sg:phone":"+1 817 624 3883",
    "sg:postcode":"76106",
    "sg:province":"TX",
    "sg:tags":[
        "church"
    ],
    "wof:name":"Mount Nebo Missionary Baptist",
    "wof:placetype":"venue"
},
  "geometry": {"coordinates":[-97.353604,32.802539],"type":"Point"}
}