{
  "type": "Feature",
  "properties": {
    "iso:country":"US",
    "sg:address":"200 Francisco Lemos St",
    "sg:city":"Kerrville",
    "sg:classifiers":[
        {
            "category":"Social Services",
            "subcategory":"Job Training",
            "type":"Services"
        }
    ],
    "sg:phone":"+1 830 896 4606",
    "sg:postcode":"78028",
    "sg:province":"TX",
    "sg:tags":[
        "retardation",
        "disabled",
        "mental",
        "dev"
    ],
    "sg:website":"www.hillcountry.org",
    "wof:name":"Special Opportunity Ctr",
    "wof:placetype":"venue"
},
  "geometry": {"coordinates":[-99.14581200000001,30.052041],"type":"Point"}
}