{
  "type": "Feature",
  "properties": {
    "iso:country":"US",
    "sg:address":"310 W Irving Blvd",
    "sg:city":"Irving",
    "sg:classifiers":[
        {
            "category":"Shopping",
            "subcategory":"Clothing, Apparel, & Fashions",
            "type":"Retail Goods"
        }
    ],
    "sg:phone":"+1 972 255 0997",
    "sg:postcode":"75060",
    "sg:province":"TX",
    "wof:name":"Coed Tee's",
    "wof:placetype":"venue"
},
  "geometry": {"coordinates":[-96.94958099999999,32.813783],"type":"Point"}
}