{
  "type": "Feature",
  "properties": {
    "iso:country":"US",
    "sg:address":"2407 College Hills Blvd",
    "sg:city":"San Angelo",
    "sg:classifiers":[
        {
            "category":"Retail",
            "subcategory":"Repair Shop",
            "type":"Services"
        }
    ],
    "sg:phone":"+1 325 949 4680",
    "sg:postcode":"76904",
    "sg:province":"TX",
    "wof:name":"Frame Up The",
    "wof:placetype":"venue"
},
  "geometry": {"coordinates":[-100.479919,31.436563],"type":"Point"}
}