{
  "type": "Feature",
  "properties": {
    "iso:country":"US",
    "sg:address":"1510 W University Dr",
    "sg:city":"Mc Kinney",
    "sg:classifiers":[
        {
            "category":"Restaurant",
            "type":"Food & Drink"
        }
    ],
    "sg:phone":"+1 972 542 5331",
    "sg:postcode":"75069",
    "sg:province":"TX",
    "sg:tags":[
        "eating"
    ],
    "wof:name":"Bill Smith Cafe",
    "wof:placetype":"venue"
},
  "geometry": {"coordinates":[-96.62888700000001,33.216575],"type":"Point"}
}