{
  "type": "Feature",
  "properties": {
    "iso:country":"US",
    "sg:address":"3965 Phelan Blvd",
    "sg:city":"Beaumont",
    "sg:classifiers":[
        {
            "category":"Manufacturing",
            "subcategory":"Metals",
            "type":"Manufacturing & Wholesale Goods"
        }
    ],
    "sg:phone":"+1 409 896 5554",
    "sg:postcode":"77707",
    "sg:province":"TX",
    "sg:tags":[
        "coating"
    ],
    "wof:name":"Chandelle Co",
    "wof:placetype":"venue"
},
  "geometry": {"coordinates":[-94.143833,30.084536],"type":"Point"}
}