{
  "type": "Feature",
  "properties": {
    "iso:country":"US",
    "sg:address":"1826 Green Tree Ln",
    "sg:city":"Duncanville",
    "sg:classifiers":[
        {
            "category":"Professional",
            "subcategory":"Business Services",
            "type":"Services"
        }
    ],
    "sg:phone":"+1 972 780 7315",
    "sg:postcode":"75137",
    "sg:province":"TX",
    "wof:name":"Business Brokers Consulta",
    "wof:placetype":"venue"
},
  "geometry": {"coordinates":[-96.937392,32.626462],"type":"Point"}
}