{
  "type": "Feature",
  "properties": {
    "iso:country":"US",
    "sg:address":"3739 Commercial Ave",
    "sg:city":"San Antonio",
    "sg:classifiers":[
        {
            "category":"Education",
            "subcategory":"Dance Studio",
            "type":"Public Place"
        }
    ],
    "sg:phone":"+1 210 923 5362",
    "sg:postcode":"78221",
    "sg:province":"TX",
    "wof:name":"Saritas Dance/Exercise Studio",
    "wof:placetype":"venue"
},
  "geometry": {"coordinates":[-98.516288,29.337059],"type":"Point"}
}