{
  "type": "Feature",
  "properties": {
    "iso:country":"US",
    "sg:address":"448 Crown Rd",
    "sg:city":"Willow Park",
    "sg:classifiers":[
        {
            "category":"Building & Trades",
            "subcategory":"Plumbing",
            "type":"Services"
        }
    ],
    "sg:phone":"+1 817 441 7041",
    "sg:postcode":"76087",
    "sg:province":"TX",
    "sg:tags":[
        "plumbing",
        "contractor"
    ],
    "wof:name":"One Way Plumbing Co",
    "wof:placetype":"venue"
},
  "geometry": {"coordinates":[-97.659485,32.782278],"type":"Point"}
}