{
  "type": "Feature",
  "properties": {
    "iso:country":"US",
    "sg:address":"9415 Burnet Rd",
    "sg:city":"Austin",
    "sg:classifiers":[
        {
            "category":"Building & Trades",
            "subcategory":"Construction",
            "type":"Services"
        }
    ],
    "sg:phone":"+1 512 458 4353",
    "sg:postcode":"78757",
    "sg:province":"TX",
    "sg:tags":[
        "roofing",
        "contractor"
    ],
    "wof:name":"AGR Roofing",
    "wof:placetype":"venue"
},
  "geometry": {"coordinates":[-97.724915,30.379415],"type":"Point"}
}