{
  "type": "Feature",
  "properties": {
    "iso:country":"US",
    "sg:address":"16018 Glen Mar Dr",
    "sg:city":"Houston",
    "sg:classifiers":[
        {
            "category":"Freight",
            "type":"Transportation"
        }
    ],
    "sg:phone":"+1 281 531 5510",
    "sg:postcode":"77082",
    "sg:province":"TX",
    "sg:tags":[
        "operator",
        "local",
        "trucking"
    ],
    "wof:name":"Edwards Trash Hauling",
    "wof:placetype":"venue"
},
  "geometry": {"coordinates":[-95.66761,29.718532],"type":"Point"}
}