{
  "type": "Feature",
  "properties": {
    "iso:country":"US",
    "sg:address":"1106 Caplin St",
    "sg:city":"Houston",
    "sg:classifiers":[
        {
            "category":"Professional",
            "type":"Services"
        }
    ],
    "sg:phone":"+1 713 695 9938",
    "sg:postcode":"77022",
    "sg:province":"TX",
    "wof:name":"Lucky Hat",
    "wof:placetype":"venue"
},
  "geometry": {"coordinates":[-95.356754,29.815607],"type":"Point"}
}