{
  "type": "Feature",
  "properties": {
    "iso:country":"US",
    "sg:address":"1013 S Mays St",
    "sg:city":"Round Rock",
    "sg:classifiers":[
        {
            "category":"Personal",
            "subcategory":"Beauty Salon",
            "type":"Services"
        }
    ],
    "sg:phone":"+1 512 388 1771",
    "sg:postcode":"78664",
    "sg:province":"TX",
    "sg:tags":[
        "manicuring"
    ],
    "wof:name":"Nail It",
    "wof:placetype":"venue"
},
  "geometry": {"coordinates":[-97.675962,30.499109],"type":"Point"}
}