{
  "type": "Feature",
  "properties": {
    "iso:country":"US",
    "sg:address":"718 W University Dr",
    "sg:city":"Edinburg",
    "sg:classifiers":[
        {
            "category":"Autos & Motor Vehicles",
            "subcategory":"Automobile Sales",
            "type":"Retail Goods"
        }
    ],
    "sg:phone":"+1 956 381 8188",
    "sg:postcode":"78539",
    "sg:province":"TX",
    "sg:tags":[
        "car",
        "dealer"
    ],
    "wof:name":"Hacienda Ford",
    "wof:placetype":"venue"
},
  "geometry": {"coordinates":[-98.169944,26.302374],"type":"Point"}
}