{
  "type": "Feature",
  "properties": {
    "iso:country":"US",
    "sg:address":"2800 Texas Blvd",
    "sg:city":"Texarkana",
    "sg:classifiers":[
        {
            "category":"Health Services",
            "subcategory":"Doctor",
            "type":"Services"
        }
    ],
    "sg:phone":"+1 903 794 2826",
    "sg:postcode":"75503",
    "sg:province":"TX",
    "sg:tags":[
        "dentist"
    ],
    "wof:name":"Albert R Mc Williams Jr DDS",
    "wof:placetype":"venue"
},
  "geometry": {"coordinates":[-94.05307999999999,33.443779],"type":"Point"}
}