{
  "type": "Feature",
  "properties": {
    "iso:country":"US",
    "sg:address":"15730 Tammany Ln",
    "sg:city":"Houston",
    "sg:classifiers":[
        {
            "category":"Professional",
            "subcategory":"Business Services",
            "type":"Services"
        }
    ],
    "sg:phone":"+1 281 920 2043",
    "sg:postcode":"77082",
    "sg:province":"TX",
    "wof:name":"Dlh & Associates",
    "wof:placetype":"venue"
},
  "geometry": {"coordinates":[-95.661627,29.716728],"type":"Point"}
}