{
  "type": "Feature",
  "properties": {
    "iso:country":"US",
    "sg:address":"1210 S Fm 51",
    "sg:city":"Decatur",
    "sg:classifiers":[
        {
            "category":"Autos & Motor Vehicles",
            "subcategory":"Fuel & Gas Station",
            "type":"Retail Goods"
        },
        {
            "category":"Food & Beverages",
            "subcategory":"Groceries & Convenience Stores",
            "type":"Retail Goods"
        }
    ],
    "sg:phone":"+1 940 627 3637",
    "sg:postcode":"76234",
    "sg:province":"TX",
    "sg:website":"http://www.phillips66.com",
    "wof:name":"Phillips 66",
    "wof:placetype":"venue"
},
  "geometry": {"coordinates":[-97.594388,33.223835],"type":"Point"}
}