{
  "type": "Feature",
  "properties": {
    "iso:country":"US",
    "sg:address":"14901 Dino Rd",
    "sg:city":"Clint",
    "sg:classifiers":[
        {
            "category":"Shopping",
            "subcategory":"Florist",
            "type":"Retail Goods"
        }
    ],
    "sg:phone":"+1 915 764 4390",
    "sg:postcode":"79836",
    "sg:province":"TX",
    "wof:name":"Photography By Ron Coffey",
    "wof:placetype":"venue"
},
  "geometry": {"coordinates":[-106.188193,31.542531],"type":"Point"}
}