{
  "type": "Feature",
  "properties": {
    "iso:country":"US",
    "sg:address":"508 Lindberg Ave",
    "sg:city":"El Paso",
    "sg:classifiers":[
        {
            "category":"Professional",
            "subcategory":"Management & Consulting",
            "type":"Services"
        }
    ],
    "sg:phone":"+1 915 373 9190",
    "sg:postcode":"79932",
    "sg:province":"TX",
    "sg:tags":[
        "business"
    ],
    "wof:name":"Adolfo R Telles Consultant",
    "wof:placetype":"venue"
},
  "geometry": {"coordinates":[-106.59514900000001,31.848732],"type":"Point"}
}