{
  "type": "Feature",
  "properties": {
    "iso:country":"US",
    "sg:address":"10200 Harwin Dr",
    "sg:city":"Houston",
    "sg:classifiers":[
        {
            "category":"Wholesale",
            "subcategory":"Machinery & Supplies",
            "type":"Manufacturing & Wholesale Goods"
        }
    ],
    "sg:phone":"+1 713 995 7650",
    "sg:postcode":"77036",
    "sg:province":"TX",
    "sg:tags":[
        "field",
        "oil",
        "equipment"
    ],
    "wof:name":"Indel-Davis Inc",
    "wof:placetype":"venue"
},
  "geometry": {"coordinates":[-95.546086,29.717316],"type":"Point"}
}