{
  "type": "Feature",
  "properties": {
    "iso:country":"US",
    "sg:address":"3608 Audubon Pl",
    "sg:city":"Houston",
    "sg:classifiers":[
        {
            "category":"Real Estate",
            "subcategory":"Real Estate Agent",
            "type":"Services"
        }
    ],
    "sg:phone":"+1 281 451 6920",
    "sg:postcode":"77006",
    "sg:province":"TX",
    "wof:name":"Shires Heart Property Co",
    "wof:placetype":"venue"
},
  "geometry": {"coordinates":[-95.38657000000001,29.739754],"type":"Point"}
}