{
  "type": "Feature",
  "properties": {
    "iso:country":"US",
    "sg:address":"1100 Holcombe Blvd",
    "sg:city":"Houston",
    "sg:classifiers":[
        {
            "category":"Health Services",
            "subcategory":"Health Practitioner",
            "type":"Services"
        }
    ],
    "sg:phone":"+1 713 704 6025",
    "sg:postcode":"77030",
    "sg:province":"TX",
    "sg:tags":[
        "physician",
        "assistant"
    ],
    "wof:name":"Javier Alaniz",
    "wof:placetype":"venue"
},
  "geometry": {"coordinates":[-95.400458,29.706228],"type":"Point"}
}