{
  "type": "Feature",
  "properties": {
    "iso:country":"US",
    "sg:address":"1019 E Main St",
    "sg:city":"Alice",
    "sg:classifiers":[
        {
            "category":"Bars & Pubs",
            "type":"Food & Drink"
        }
    ],
    "sg:phone":"+1 361 664 7024",
    "sg:postcode":"78332",
    "sg:province":"TX",
    "sg:tags":[
        "drinking"
    ],
    "wof:name":"T JS Place",
    "wof:placetype":"venue"
},
  "geometry": {"coordinates":[-98.065634,27.750683],"type":"Point"}
}