{
  "type": "Feature",
  "properties": {
    "iso:country":"US",
    "sg:address":"1309 Paluxy Rd",
    "sg:city":"Granbury",
    "sg:classifiers":[
        {
            "category":"Shopping",
            "subcategory":"Catalog Store",
            "type":"Retail Goods"
        }
    ],
    "sg:phone":"+1 817 573 3762",
    "sg:postcode":"76048",
    "sg:province":"TX",
    "sg:tags":[
        "mail",
        "order",
        "online"
    ],
    "wof:name":"Simple Dental Concepts Inc",
    "wof:placetype":"venue"
},
  "geometry": {"coordinates":[-97.803663,32.431098],"type":"Point"}
}