{
  "type": "Feature",
  "properties": {
    "iso:country":"US",
    "sg:address":"1802 N Loop 1604 E",
    "sg:city":"San Antonio",
    "sg:classifiers":[
        {
            "category":"Restaurant",
            "type":"Food & Drink"
        }
    ],
    "sg:menulink":"http://www.allmenus.com/tx/san-antonio/95688-pei-wei/menu/",
    "sg:phone":"+1 210 507 9160",
    "sg:postcode":"78232",
    "sg:province":"TX",
    "sg:tags":[
        "chinese",
        "vietnamese",
        "japanese",
        "asian",
        "korean",
        "thai"
    ],
    "wof:name":"Pei Wei",
    "wof:placetype":"venue"
},
  "geometry": {"coordinates":[-98.46262299999999,29.607387],"type":"Point"}
}