{
  "type": "Feature",
  "properties": {
    "iso:country":"US",
    "sg:address":"11539 Gun Fight Ln",
    "sg:city":"Austin",
    "sg:classifiers":[
        {
            "category":"Social Services",
            "type":"Services"
        },
        {
            "category":"Professional",
            "subcategory":"Employment Agencies",
            "type":"Services"
        }
    ],
    "sg:phone":"+1 512 589 3921",
    "sg:postcode":"78748",
    "sg:province":"TX",
    "sg:tags":[
        "workers'",
        "placement",
        "volunteer"
    ],
    "wof:name":"Ponheary Ly Foundation",
    "wof:placetype":"venue"
},
  "geometry": {"coordinates":[-97.85328699999999,30.159349],"type":"Point"}
}