{
  "type": "Feature",
  "properties": {
    "iso:country":"US",
    "sg:address":"1546 Tuley St",
    "sg:city":"Cedar Hill",
    "sg:classifiers":[
        {
            "category":"Professional",
            "type":"Services"
        }
    ],
    "sg:phone":"+1 972 291 1713",
    "sg:postcode":"75104",
    "sg:province":"TX",
    "wof:name":"Forward Notions",
    "wof:placetype":"venue"
},
  "geometry": {"coordinates":[-96.95326799999999,32.624603],"type":"Point"}
}