{
  "type": "Feature",
  "properties": {
    "iso:country":"US",
    "sg:address":"2335 Old Mill Rd",
    "sg:city":"Sugar Land",
    "sg:classifiers":[
        {
            "category":"Retail",
            "subcategory":"Auto Repair",
            "type":"Services"
        }
    ],
    "sg:phone":"+1 281 242 2228",
    "sg:postcode":"77478",
    "sg:province":"TX",
    "sg:tags":[
        "automotive"
    ],
    "wof:name":"Ep Unlimited LLC",
    "wof:placetype":"venue"
},
  "geometry": {"coordinates":[-95.59486699999999,29.589458],"type":"Point"}
}