{
  "type": "Feature",
  "properties": {
    "iso:country":"US",
    "sg:address":"13062 W Highway 290",
    "sg:city":"Austin",
    "sg:classifiers":[
        {
            "category":"Professional",
            "subcategory":"Lawyer & Legal Services",
            "type":"Services"
        }
    ],
    "sg:phone":"+1 512 477 4707",
    "sg:postcode":"78737",
    "sg:province":"TX",
    "sg:tags":[
        "attorney"
    ],
    "wof:name":"Brandon, Sarah K.",
    "wof:placetype":"venue"
},
  "geometry": {"coordinates":[-97.99732299999999,30.196808],"type":"Point"}
}