{
  "type": "Feature",
  "properties": {
    "iso:country":"US",
    "sg:address":"3801 24th St",
    "sg:city":"Lubbock",
    "sg:classifiers":[
        {
            "category":"Health Services",
            "subcategory":"Doctor",
            "type":"Services"
        }
    ],
    "sg:phone":"+1 806 793 0421",
    "sg:postcode":"79410",
    "sg:province":"TX",
    "sg:tags":[
        "dentist"
    ],
    "wof:name":"William A Nash DDS",
    "wof:placetype":"venue"
},
  "geometry": {"coordinates":[-101.898624,33.572281],"type":"Point"}
}