{
  "type": "Feature",
  "properties": {
    "iso:country":"US",
    "sg:address":"305 Los Nietos Ct",
    "sg:city":"El Paso",
    "sg:classifiers":[
        {
            "category":"Manufacturing",
            "subcategory":"Toys & Sporting Goods",
            "type":"Manufacturing & Wholesale Goods"
        }
    ],
    "sg:phone":"+1 915 585 6440",
    "sg:postcode":"79932",
    "sg:province":"TX",
    "sg:tags":[
        "repair",
        "mfg",
        "pool",
        "swimming"
    ],
    "wof:name":"Paul Dlgado Fbrgls Fabrication",
    "wof:placetype":"venue"
},
  "geometry": {"coordinates":[-106.591086,31.857402],"type":"Point"}
}