{
  "type": "Feature",
  "properties": {
    "iso:country":"US",
    "sg:address":"240 State Hwy 243",
    "sg:city":"Canton",
    "sg:classifiers":[
        {
            "category":"Health Services",
            "subcategory":"Doctor",
            "type":"Services"
        }
    ],
    "sg:phone":"+1 903 567 4881",
    "sg:postcode":"75103",
    "sg:province":"TX",
    "sg:tags":[
        "dentist"
    ],
    "wof:name":"Family Cosmetic Dentistry",
    "wof:placetype":"venue"
},
  "geometry": {"coordinates":[-95.866049,32.544248],"type":"Point"}
}