{
  "type": "Feature",
  "properties": {
    "iso:country":"US",
    "sg:address":"13310 Oak Ledge Dr",
    "sg:city":"Houston",
    "sg:classifiers":[
        {
            "category":"Wholesale",
            "subcategory":"Sporting Goods",
            "type":"Manufacturing & Wholesale Goods"
        }
    ],
    "sg:phone":"+1 281 807 1922",
    "sg:postcode":"77065",
    "sg:province":"TX",
    "wof:name":"Wwwconradsbicyclescom",
    "wof:placetype":"venue"
},
  "geometry": {"coordinates":[-95.62073599999999,29.92879],"type":"Point"}
}