{
  "type": "Feature",
  "properties": {
    "iso:country":"US",
    "sg:address":"10103 Fondren Rd",
    "sg:city":"Houston",
    "sg:classifiers":[
        {
            "category":"Health Services",
            "subcategory":"Clinic",
            "type":"Services"
        }
    ],
    "sg:phone":"+1 713 777 9600",
    "sg:postcode":"77096",
    "sg:province":"TX",
    "sg:tags":[
        "home",
        "care"
    ],
    "wof:name":"Metro Healh Services",
    "wof:placetype":"venue"
},
  "geometry": {"coordinates":[-95.508499,29.670684],"type":"Point"}
}