{
  "type": "Feature",
  "properties": {
    "iso:country":"US",
    "sg:address":"225 Junction Hwy",
    "sg:city":"Kerrville",
    "sg:classifiers":[
        {
            "category":"Retail",
            "subcategory":"Repair Shop",
            "type":"Services"
        }
    ],
    "sg:phone":"+1 830 257 1234",
    "sg:postcode":"78028",
    "sg:province":"TX",
    "sg:tags":[
        "sporting"
    ],
    "wof:name":"Precisionfit Golf",
    "wof:placetype":"venue"
},
  "geometry": {"coordinates":[-99.149424,30.054101],"type":"Point"}
}