{
  "type": "Feature",
  "properties": {
    "iso:country":"US",
    "sg:address":"211 Lombardy Dr",
    "sg:city":"Sugar Land",
    "sg:classifiers":[
        {
            "category":"Building & Trades",
            "subcategory":"Construction",
            "type":"Services"
        }
    ],
    "sg:phone":"+1 281 491 1608",
    "sg:postcode":"77478",
    "sg:province":"TX",
    "sg:tags":[
        "consulting",
        "management",
        "contractor"
    ],
    "wof:name":"American Acoustics Corporation",
    "wof:placetype":"venue"
},
  "geometry": {"coordinates":[-95.61818700000001,29.621167],"type":"Point"}
}