{
  "type": "Feature",
  "properties": {
    "iso:country":"US",
    "sg:address":"6302 31st St",
    "sg:city":"Lubbock",
    "sg:classifiers":[
        {
            "category":"Building & Trades",
            "subcategory":"Cleaning & Sanitation",
            "type":"Services"
        }
    ],
    "sg:phone":"+1 806 793 3915",
    "sg:postcode":"79407",
    "sg:province":"TX",
    "sg:tags":[
        "window",
        "maintenance"
    ],
    "wof:name":"JD Window Cleaning",
    "wof:placetype":"venue"
},
  "geometry": {"coordinates":[-101.95470299999999,33.566071],"type":"Point"}
}