{
  "type": "Feature",
  "properties": {
    "iso:country":"US",
    "sg:address":"248 Addie Roy Rd",
    "sg:city":"Austin",
    "sg:classifiers":[
        {
            "category":"Building & Trades",
            "subcategory":"Construction",
            "type":"Services"
        }
    ],
    "sg:phone":"+1 512 328 7374",
    "sg:postcode":"78746",
    "sg:province":"TX",
    "sg:tags":[
        "house",
        "builder",
        "home"
    ],
    "sg:website":"www.serenohomes.com",
    "wof:name":"Sereno Homes",
    "wof:placetype":"venue"
},
  "geometry": {"coordinates":[-97.84176100000001,30.307796],"type":"Point"}
}