{
  "type": "Feature",
  "properties": {
    "iso:country":"US",
    "sg:address":"1407 Ave P",
    "sg:city":"Del Rio",
    "sg:classifiers":[
        {
            "category":"Professional",
            "type":"Services"
        }
    ],
    "sg:phone":"+1 830 774 6086",
    "sg:postcode":"78840",
    "sg:province":"TX",
    "sg:tags":[
        "establishment"
    ],
    "wof:name":"City Of Del Rio",
    "wof:placetype":"venue"
},
  "geometry": {"coordinates":[-100.91068199999999,29.375169],"type":"Point"}
}