{
  "type": "Feature",
  "properties": {
    "iso:country":"US",
    "sg:address":"527 Steart St",
    "sg:city":"Rockport",
    "sg:classifiers":[
        {
            "category":"Building & Trades",
            "subcategory":"Construction",
            "type":"Services"
        }
    ],
    "sg:phone":"+1 361 790 8742",
    "sg:postcode":"78382",
    "sg:province":"TX",
    "sg:tags":[
        "roofing",
        "industrial",
        "contractors-commercial",
        "contractor"
    ],
    "wof:name":"Peterson Roofing Systems",
    "wof:placetype":"venue"
},
  "geometry": {"coordinates":[-97.070714,28.036152],"type":"Point"}
}