{
  "type": "Feature",
  "properties": {
    "iso:country":"US",
    "sg:address":"110 Inwood Trail",
    "sg:city":"Azle",
    "sg:classifiers":[
        {
            "category":"Building & Trades",
            "subcategory":"Locksmith",
            "type":"Services"
        }
    ],
    "sg:phone":"+1 817 989 6400",
    "sg:postcode":"76020",
    "sg:province":"TX",
    "sg:tags":[
        "lock"
    ],
    "sg:website":"http://capronenterprise.com",
    "wof:name":"Capron Enterprise",
    "wof:placetype":"venue"
},
  "geometry": {"coordinates":[-97.55750999999999,32.828036],"type":"Point"}
}