{
  "type": "Feature",
  "properties": {
    "iso:country":"US",
    "sg:address":"11003 Hidden Lake Ln",
    "sg:city":"Richmond",
    "sg:classifiers":[
        {
            "category":"Professional",
            "subcategory":"Business Services",
            "type":"Services"
        }
    ],
    "sg:phone":"+1 281 341 1727",
    "sg:postcode":"77469",
    "sg:province":"TX",
    "wof:name":"Wbf Enterprises Inc",
    "wof:placetype":"venue"
},
  "geometry": {"coordinates":[-95.821083,29.684086],"type":"Point"}
}