{
  "type": "Feature",
  "properties": {
    "iso:country":"US",
    "sg:address":"2511 6th Ave",
    "sg:city":"Amarillo",
    "sg:classifiers":[
        {
            "category":"Bars & Pubs",
            "type":"Food & Drink"
        }
    ],
    "sg:phone":"+1 806 374 8404",
    "sg:postcode":"79106",
    "sg:province":"TX",
    "sg:tags":[
        "drinking"
    ],
    "wof:name":"Lsd Inc",
    "wof:placetype":"venue"
},
  "geometry": {"coordinates":[-101.86577,35.211329],"type":"Point"}
}