{
  "type": "Feature",
  "properties": {
    "iso:country":"US",
    "sg:address":"129 River Trl",
    "sg:city":"Castroville",
    "sg:classifiers":[
        {
            "category":"Health Services",
            "subcategory":"Health Practitioner",
            "type":"Services"
        }
    ],
    "sg:phone":"+1 830 538 9393",
    "sg:postcode":"78009",
    "sg:province":"TX",
    "sg:tags":[
        "nutritionist"
    ],
    "wof:name":"Nature & Nutrition",
    "wof:placetype":"venue"
},
  "geometry": {"coordinates":[-98.89412799999999,29.356883],"type":"Point"}
}