{
  "type": "Feature",
  "properties": {
    "iso:country":"US",
    "sg:address":"1700 Gallagher Dr",
    "sg:city":"Sherman",
    "sg:classifiers":[
        {
            "category":"Health Services",
            "subcategory":"Doctor",
            "type":"Services"
        }
    ],
    "sg:phone":"+1 903 893 1399",
    "sg:postcode":"75090",
    "sg:province":"TX",
    "sg:tags":[
        "physician",
        "family",
        "practice",
        "surgeons",
        "medicine"
    ],
    "wof:name":"Millmann, Paul R",
    "wof:placetype":"venue"
},
  "geometry": {"coordinates":[-96.597588,33.672649],"type":"Point"}
}