{
  "type": "Feature",
  "properties": {
    "iso:country":"US",
    "sg:address":"510 Petroleum Dr",
    "sg:city":"San Antonio",
    "sg:phone":"+1 210 226 0110",
    "sg:postcode":"78218",
    "sg:province":"TX",
    "sg:tags":[
        "product",
        "petroleum"
    ],
    "wof:name":"Flint Hills Resources",
    "wof:placetype":"venue"
},
  "geometry": {"coordinates":[-98.407404,29.458973],"type":"Point"}
}