{
  "type": "Feature",
  "properties": {
    "iso:country":"US",
    "sg:address":"2707 Metropolitan Ave",
    "sg:city":"Dallas",
    "sg:classifiers":[
        {
            "category":"Professional",
            "subcategory":"Accounting & Tax Preparation",
            "type":"Services"
        }
    ],
    "sg:phone":"+1 214 928 9902",
    "sg:postcode":"75215",
    "sg:province":"TX",
    "sg:tags":[
        "billing"
    ],
    "wof:name":"Barlowco",
    "wof:placetype":"venue"
},
  "geometry": {"coordinates":[-96.76212200000001,32.763721],"type":"Point"}
}