{
  "type": "Feature",
  "properties": {
    "iso:country":"US",
    "sg:address":"1700 S Lamar Blvd Ste 200",
    "sg:city":"Austin",
    "sg:classifiers":[
        {
            "category":"Real Estate",
            "subcategory":"Real Estate Services",
            "type":"Services"
        },
        {
            "category":"Real Estate",
            "subcategory":"Real Estate Operator",
            "type":"Services"
        }
    ],
    "sg:phone":"+1 512 416 8100",
    "sg:postcode":"78704",
    "sg:province":"TX",
    "sg:tags":[
        "apartment"
    ],
    "sg:website":"www.apartmentexperts.org",
    "wof:name":"Apartment Experts",
    "wof:placetype":"venue"
},
  "geometry": {"coordinates":[-97.766496,30.251662],"type":"Point"}
}