{
  "type": "Feature",
  "properties": {
    "iso:country":"US",
    "sg:address":"119 Chestnut Dr",
    "sg:city":"Copperas Cove",
    "sg:classifiers":[
        {
            "category":"Food & Beverages",
            "subcategory":"Candy",
            "type":"Retail Goods"
        }
    ],
    "sg:phone":"+1 254 542 2106",
    "sg:postcode":"76522",
    "sg:province":"TX",
    "sg:tags":[
        "confectionery"
    ],
    "wof:name":"Sweet Occasions",
    "wof:placetype":"venue"
},
  "geometry": {"coordinates":[-97.925702,31.146255],"type":"Point"}
}