{
  "type": "Feature",
  "properties": {
    "iso:country":"US",
    "sg:address":"13438 Forum Rd",
    "sg:city":"Universal City",
    "sg:classifiers":[
        {
            "category":"Professional",
            "subcategory":"Management & Consulting",
            "type":"Services"
        }
    ],
    "sg:phone":"+1 210 658 6361",
    "sg:postcode":"78148",
    "sg:province":"TX",
    "sg:tags":[
        "consultant",
        "designer",
        "bank"
    ],
    "wof:name":"James E Smith Jr",
    "wof:placetype":"venue"
},
  "geometry": {"coordinates":[-98.316638,29.562869],"type":"Point"}
}