{
  "type": "Feature",
  "properties": {
    "iso:country":"US",
    "sg:address":"13923 Schmidt Rd",
    "sg:city":"Cypress",
    "sg:classifiers":[
        {
            "category":"Building & Trades",
            "subcategory":"Cleaning & Sanitation",
            "type":"Services"
        }
    ],
    "sg:phone":"+1 281 469 2140",
    "sg:postcode":"77429",
    "sg:province":"TX",
    "sg:tags":[
        "maintenance"
    ],
    "wof:name":"M I R Enterprises",
    "wof:placetype":"venue"
},
  "geometry": {"coordinates":[-95.631052,29.939582],"type":"Point"}
}