{
  "type": "Feature",
  "properties": {
    "iso:country":"US",
    "sg:address":"1520 Blackburn Rd",
    "sg:city":"Garland",
    "sg:classifiers":[
        {
            "category":"Organizations",
            "subcategory":"Religious Organization",
            "type":"Services"
        }
    ],
    "sg:phone":"+1 972 530 1005",
    "sg:postcode":"75048",
    "sg:province":"TX",
    "wof:name":"First Untd Mthdst Chrch Sachse",
    "wof:placetype":"venue"
},
  "geometry": {"coordinates":[-96.60931600000001,32.982134],"type":"Point"}
}