{
  "type": "Feature",
  "properties": {
    "iso:country":"US",
    "sg:address":"400 Inglewood Dr",
    "sg:city":"Socorro",
    "sg:classifiers":[
        {
            "category":"Utilities",
            "subcategory":"Refuse",
            "type":"Services"
        }
    ],
    "sg:phone":"+1 915 860 7011",
    "sg:postcode":"79927",
    "sg:province":"TX",
    "sg:tags":[
        "disposal",
        "waste"
    ],
    "wof:name":"Rimsa Vivendi Sarp Ind",
    "wof:placetype":"venue"
},
  "geometry": {"coordinates":[-106.297882,31.676669],"type":"Point"}
}