{
  "type": "Feature",
  "properties": {
    "iso:country":"US",
    "sg:address":"1153 Calvert Dr",
    "sg:city":"Cedar Hill",
    "sg:classifiers":[
        {
            "category":"Professional",
            "subcategory":"Business Services",
            "type":"Services"
        }
    ],
    "sg:phone":"+1 972 291 4219",
    "sg:postcode":"75104",
    "sg:province":"TX",
    "wof:name":"Network Venture Capital",
    "wof:placetype":"venue"
},
  "geometry": {"coordinates":[-96.919325,32.594228],"type":"Point"}
}