{
  "type": "Feature",
  "properties": {
    "iso:country":"US",
    "sg:address":"6394 Kiwanis Club Rd",
    "sg:city":"Silsbee",
    "sg:classifiers":[
        {
            "category":"Shopping",
            "subcategory":"Antiques",
            "type":"Retail Goods"
        }
    ],
    "sg:phone":"+1 409 385 4620",
    "sg:postcode":"77656",
    "sg:province":"TX",
    "wof:name":"Nancy Nickersons Collectibles",
    "wof:placetype":"venue"
},
  "geometry": {"coordinates":[-94.21178500000001,30.34594],"type":"Point"}
}