{
  "type": "Feature",
  "properties": {
    "iso:country":"US",
    "sg:address":"6801 Bell St",
    "sg:city":"Amarillo",
    "sg:classifiers":[
        {
            "category":"Restaurant",
            "type":"Food & Drink"
        }
    ],
    "sg:phone":"+1 806 352 6666",
    "sg:postcode":"79109",
    "sg:province":"TX",
    "sg:tags":[
        "eating"
    ],
    "wof:name":"Pizza Planet",
    "wof:placetype":"venue"
},
  "geometry": {"coordinates":[-101.90186799999999,35.138811],"type":"Point"}
}