{
  "type": "Feature",
  "properties": {
    "iso:country":"US",
    "sg:address":"4380 S Wayside Dr",
    "sg:city":"Houston",
    "sg:classifiers":[
        {
            "category":"Wholesale",
            "subcategory":"Machinery & Supplies",
            "type":"Manufacturing & Wholesale Goods"
        }
    ],
    "sg:phone":"+1 713 641 2288",
    "sg:postcode":"77087",
    "sg:province":"TX",
    "sg:tags":[
        "industrial",
        "coupling",
        "fitting",
        "belting",
        "pa",
        "hose",
        "distributor",
        "marine"
    ],
    "wof:name":"Accord International Inc",
    "wof:placetype":"venue"
},
  "geometry": {"coordinates":[-95.321018,29.699029],"type":"Point"}
}