{
  "type": "Feature",
  "properties": {
    "iso:country":"US",
    "sg:address":"247 E Rainbow Ridge Cir",
    "sg:city":"Spring",
    "sg:classifiers":[
        {
            "category":"Building & Trades",
            "subcategory":"Construction",
            "type":"Services"
        }
    ],
    "sg:phone":"+1 281 292 7667",
    "sg:postcode":"77381",
    "sg:province":"TX",
    "sg:tags":[
        "roofing",
        "contractor"
    ],
    "wof:name":"Classic Roofing",
    "wof:placetype":"venue"
},
  "geometry": {"coordinates":[-95.50621700000001,30.174573],"type":"Point"}
}