{
  "type": "Feature",
  "properties": {
    "iso:country":"US",
    "sg:address":"217 N Henderson Blvd",
    "sg:city":"Kilgore",
    "sg:classifiers":[
        {
            "category":"Restaurant",
            "type":"Food & Drink"
        }
    ],
    "sg:menulink":"http://www.allmenus.com/tx/kilgore/204158-sonic/menu/",
    "sg:phone":"+1 903 984 7331",
    "sg:postcode":"75662",
    "sg:province":"TX",
    "sg:tags":[
        "burger",
        "american"
    ],
    "wof:name":"Sonic",
    "wof:placetype":"venue"
},
  "geometry": {"coordinates":[-94.868967,32.39708],"type":"Point"}
}