{
  "type": "Feature",
  "properties": {
    "iso:country":"US",
    "sg:address":"747 Yellowstone Dr",
    "sg:city":"Allen",
    "sg:classifiers":[
        {
            "category":"Real Estate",
            "subcategory":"Real Estate Services",
            "type":"Services"
        }
    ],
    "sg:phone":"+1 214 316 5904",
    "sg:postcode":"75002",
    "sg:province":"TX",
    "sg:tags":[
        "consultant"
    ],
    "wof:name":"Taru Properties",
    "wof:placetype":"venue"
},
  "geometry": {"coordinates":[-96.633411,33.087512],"type":"Point"}
}