{
  "type": "Feature",
  "properties": {
    "iso:country":"US",
    "sg:address":"18105 Deer Trl",
    "sg:city":"Flint",
    "sg:classifiers":[
        {
            "category":"Restaurant",
            "type":"Food & Drink"
        }
    ],
    "sg:phone":"+1 903 521 0427",
    "sg:postcode":"75762",
    "sg:province":"TX",
    "wof:name":"Reliable Restaurant Repair",
    "wof:placetype":"venue"
},
  "geometry": {"coordinates":[-95.332122,32.21928],"type":"Point"}
}