{
  "type": "Feature",
  "properties": {
    "iso:country":"US",
    "sg:address":"503 Pena St",
    "sg:city":"Carrizo Springs",
    "sg:classifiers":[
        {
            "category":"Insurance",
            "subcategory":"Insurance Agent",
            "type":"Services"
        }
    ],
    "sg:phone":"+1 830 876 3539",
    "sg:postcode":"78834",
    "sg:province":"TX",
    "wof:name":"Farmers Insurance Group",
    "wof:placetype":"venue"
},
  "geometry": {"coordinates":[-99.860462,28.521781],"type":"Point"}
}