{
  "type": "Feature",
  "properties": {
    "iso:country":"US",
    "sg:address":"3001 Sherwood Ln",
    "sg:city":"Colleyville",
    "sg:classifiers":[
        {
            "category":"Real Estate",
            "subcategory":"Real Estate Operator",
            "type":"Services"
        }
    ],
    "sg:phone":"+1 817 283 4340",
    "sg:postcode":"76034",
    "sg:province":"TX",
    "sg:tags":[
        "property",
        "lessor"
    ],
    "wof:name":"JD Tack Corp",
    "wof:placetype":"venue"
},
  "geometry": {"coordinates":[-97.120458,32.872723],"type":"Point"}
}