{
  "type": "Feature",
  "properties": {
    "iso:country":"US",
    "sg:address":"3205 W Davis St",
    "sg:city":"Conroe",
    "sg:classifiers":[
        {
            "category":"Banks & Credit Unions",
            "subcategory":"Investment Brokerage",
            "type":"Services"
        }
    ],
    "sg:phone":"+1 936 760 7600",
    "sg:postcode":"77304",
    "sg:province":"TX",
    "wof:name":"Edward Jones Investments",
    "wof:placetype":"venue"
},
  "geometry": {"coordinates":[-95.486327,30.321218],"type":"Point"}
}