{
  "type": "Feature",
  "properties": {
    "iso:country":"US",
    "sg:address":"2206 Albans Rd",
    "sg:city":"Houston",
    "sg:classifiers":[
        {
            "category":"Professional",
            "subcategory":"Lawyer & Legal Services",
            "type":"Services"
        }
    ],
    "sg:phone":"+1 713 524 5959",
    "sg:postcode":"77005",
    "sg:province":"TX",
    "sg:website":"www.deguerin.com",
    "wof:name":"WARD TODD",
    "wof:placetype":"venue"
},
  "geometry": {"coordinates":[-95.410631,29.724024],"type":"Point"}
}