{
  "type": "Feature",
  "properties": {
    "iso:country":"US",
    "sg:address":"5315 Ed Bluestein Blvd",
    "sg:city":"Austin",
    "sg:classifiers":[
        {
            "category":"Organizations",
            "subcategory":"Community Association",
            "type":"Services"
        }
    ],
    "sg:phone":"+1 512 933 9622",
    "sg:postcode":"78723",
    "sg:province":"TX",
    "wof:name":"Y M C A Ed Bluestein",
    "wof:placetype":"venue"
},
  "geometry": {"coordinates":[-97.663562,30.291723],"type":"Point"}
}