{
  "type": "Feature",
  "properties": {
    "iso:country":"US",
    "sg:address":"2729 Madrid Ave",
    "sg:city":"Brownsville",
    "sg:classifiers":[
        {
            "category":"Personal",
            "subcategory":"Beauty Salon",
            "type":"Services"
        }
    ],
    "sg:phone":"+1 956 350 6979",
    "sg:postcode":"78520",
    "sg:province":"TX",
    "wof:name":"Yolanda Estrada Hairstylist",
    "wof:placetype":"venue"
},
  "geometry": {"coordinates":[-97.537966,25.964968],"type":"Point"}
}