{
  "type": "Feature",
  "properties": {
    "iso:country":"US",
    "sg:address":"4102 Bar Harbor Ct",
    "sg:city":"Granbury",
    "sg:classifiers":[
        {
            "category":"Real Estate",
            "subcategory":"Real Estate Agent",
            "type":"Services"
        }
    ],
    "sg:phone":"+1 817 326 5875",
    "sg:postcode":"76049",
    "sg:province":"TX",
    "wof:name":"Dee Trammel",
    "wof:placetype":"venue"
},
  "geometry": {"coordinates":[-97.71575900000001,32.410875],"type":"Point"}
}