{
  "type": "Feature",
  "properties": {
    "iso:country":"US",
    "sg:address":"4332 Grassmere Ln",
    "sg:city":"Dallas",
    "sg:classifiers":[
        {
            "category":"Restaurant",
            "type":"Food & Drink"
        }
    ],
    "sg:phone":"+1 214 521 8974",
    "sg:postcode":"75205",
    "sg:province":"TX",
    "sg:tags":[
        "eating"
    ],
    "wof:name":"Let Them Eat Cookies LLC",
    "wof:placetype":"venue"
},
  "geometry": {"coordinates":[-96.809798,32.849309],"type":"Point"}
}