{
  "type": "Feature",
  "properties": {
    "iso:country":"US",
    "sg:address":"25 Summer Sun Cv",
    "sg:city":"Kyle",
    "sg:classifiers":[
        {
            "category":"Retail",
            "subcategory":"Repair Shop",
            "type":"Services"
        },
        {
            "category":"Building & Trades",
            "subcategory":"Construction",
            "type":"Services"
        }
    ],
    "sg:phone":"+1 512 573 0055",
    "sg:postcode":"78640",
    "sg:province":"TX",
    "sg:tags":[
        "home",
        "fix-it",
        "maintenance"
    ],
    "wof:name":"Jen Pro Roofing",
    "wof:placetype":"venue"
},
  "geometry": {"coordinates":[-97.789514,29.961072],"type":"Point"}
}