{
  "type": "Feature",
  "properties": {
    "iso:country":"US",
    "sg:address":"111 Red Oak Creek Rd",
    "sg:city":"Red Oak",
    "sg:classifiers":[
        {
            "category":"Professional",
            "subcategory":"Accounting & Tax Preparation",
            "type":"Services"
        }
    ],
    "sg:phone":"+1 972 617 5734",
    "sg:postcode":"75154",
    "sg:province":"TX",
    "sg:tags":[
        "return"
    ],
    "wof:name":"Ron Genzer",
    "wof:placetype":"venue"
},
  "geometry": {"coordinates":[-96.858811,32.51742],"type":"Point"}
}