{
  "type": "Feature",
  "properties": {
    "iso:country":"US",
    "sg:address":"14445 US Hwy 290",
    "sg:city":"Stonewall",
    "sg:classifiers":[
        {
            "category":"Retail",
            "subcategory":"Auto Repair",
            "type":"Services"
        }
    ],
    "sg:phone":"+1 830 644 2388",
    "sg:postcode":"78671",
    "sg:province":"TX",
    "sg:tags":[
        "wrecker"
    ],
    "wof:name":"Eckert & Son Wrecking Inc",
    "wof:placetype":"venue"
},
  "geometry": {"coordinates":[-98.678783,30.230124],"type":"Point"}
}