{
  "type": "Feature",
  "properties": {
    "iso:country":"US",
    "sg:address":"606 Patchester Dr",
    "sg:city":"Houston",
    "sg:classifiers":[
        {
            "category":"Farming",
            "subcategory":"Livestock Farm",
            "type":"Manufacturing & Wholesale Goods"
        }
    ],
    "sg:phone":"+1 713 468 0832",
    "sg:postcode":"77079",
    "sg:province":"TX",
    "sg:tags":[
        "equine",
        "animal",
        "general"
    ],
    "wof:name":"Lometa Paint Co",
    "wof:placetype":"venue"
},
  "geometry": {"coordinates":[-95.58480299999999,29.775997],"type":"Point"}
}