{
  "type": "Feature",
  "properties": {
    "iso:country":"US",
    "sg:address":"2415 Juniper Dr",
    "sg:city":"Amarillo",
    "sg:classifiers":[
        {
            "category":"Retail",
            "subcategory":"Repair Shop",
            "type":"Services"
        }
    ],
    "sg:phone":"+1 806 358 2548",
    "sg:postcode":"79109",
    "sg:province":"TX",
    "sg:tags":[
        "welding"
    ],
    "wof:name":"Sawhorse Custom Welding",
    "wof:placetype":"venue"
},
  "geometry": {"coordinates":[-101.86337,35.184393],"type":"Point"}
}