{
  "type": "Feature",
  "properties": {
    "iso:country":"US",
    "sg:address":"7414 Nickle St",
    "sg:city":"San Antonio",
    "sg:classifiers":[
        {
            "category":"Professional",
            "type":"Services"
        }
    ],
    "sg:phone":"+1 210 877 2487",
    "sg:postcode":"78249",
    "sg:province":"TX",
    "wof:name":"Bens Service",
    "wof:placetype":"venue"
},
  "geometry": {"coordinates":[-98.6331,29.567824],"type":"Point"}
}