{
  "type": "Feature",
  "properties": {
    "iso:country":"US",
    "sg:address":"905 Clover Hill Ln",
    "sg:city":"Cedar Hill",
    "sg:classifiers":[
        {
            "category":"Freight",
            "type":"Transportation"
        }
    ],
    "sg:phone":"+1 972 299 9282",
    "sg:postcode":"75104",
    "sg:province":"TX",
    "sg:tags":[
        "operator",
        "local",
        "trucking"
    ],
    "wof:name":"Lb Collier Trucking Co",
    "wof:placetype":"venue"
},
  "geometry": {"coordinates":[-96.92561000000001,32.612995],"type":"Point"}
}