{
  "type": "Feature",
  "properties": {
    "iso:country":"US",
    "sg:address":"3730 FM 1960 W",
    "sg:city":"Houston",
    "sg:classifiers":[
        {
            "category":"Freight",
            "type":"Transportation"
        }
    ],
    "sg:phone":"+1 281 587 2021",
    "sg:postcode":"77068",
    "sg:province":"TX",
    "sg:tags":[
        "operator",
        "trucking"
    ],
    "wof:name":"Tdt Logistics",
    "wof:placetype":"venue"
},
  "geometry": {"coordinates":[-95.480638,29.997738],"type":"Point"}
}