{
  "type": "Feature",
  "properties": {
    "iso:country":"US",
    "sg:address":"405 E Border St",
    "sg:city":"Arlington",
    "sg:classifiers":[
        {
            "category":"Wholesale",
            "subcategory":"Chemicals & Plastics",
            "type":"Manufacturing & Wholesale Goods"
        }
    ],
    "sg:phone":"+1 817 313 3933",
    "sg:postcode":"76010",
    "sg:province":"TX",
    "wof:name":"A & R Plastics & Tooling",
    "wof:placetype":"venue"
},
  "geometry": {"coordinates":[-97.10286499999999,32.733742],"type":"Point"}
}