{
  "type": "Feature",
  "properties": {
    "iso:country":"US",
    "sg:address":"5249 Garfield Ave",
    "sg:city":"Groves",
    "sg:classifiers":[
        {
            "category":"Professional",
            "subcategory":"Art Services",
            "type":"Services"
        }
    ],
    "sg:phone":"+1 409 962 2929",
    "sg:postcode":"77619",
    "sg:province":"TX",
    "sg:tags":[
        "commercial",
        "design"
    ],
    "wof:name":"Brushstrokes",
    "wof:placetype":"venue"
},
  "geometry": {"coordinates":[-93.92768700000001,29.956753],"type":"Point"}
}