{
  "type": "Feature",
  "properties": {
    "iso:country":"US",
    "sg:address":"15707 Walkwood Dr",
    "sg:city":"Houston",
    "sg:classifiers":[
        {
            "category":"Building & Trades",
            "subcategory":"Construction",
            "type":"Services"
        }
    ],
    "sg:phone":"+1 281 497 0628",
    "sg:postcode":"77079",
    "sg:province":"TX",
    "sg:tags":[
        "water",
        "well",
        "drilling"
    ],
    "wof:name":"Nell Oconnor",
    "wof:placetype":"venue"
},
  "geometry": {"coordinates":[-95.633228,29.774808],"type":"Point"}
}