{
  "type": "Feature",
  "properties": {
    "iso:country":"US",
    "sg:address":"106 Belaire Dr",
    "sg:city":"Laredo",
    "sg:classifiers":[
        {
            "category":"Freight",
            "type":"Transportation"
        }
    ],
    "sg:phone":"+1 956 251 3433",
    "sg:postcode":"78041",
    "sg:province":"TX",
    "sg:tags":[
        "arrangement"
    ],
    "wof:name":"South Texas Logistics",
    "wof:placetype":"venue"
},
  "geometry": {"coordinates":[-99.487661,27.56733],"type":"Point"}
}