{
  "type": "Feature",
  "properties": {
    "iso:country":"US",
    "sg:address":"8339 C E King Pkwy",
    "sg:city":"Houston",
    "sg:classifiers":[
        {
            "category":"Home & Garden",
            "subcategory":"Household Appliances",
            "type":"Retail Goods"
        }
    ],
    "sg:phone":"+1 281 458 0050",
    "sg:postcode":"77044",
    "sg:province":"TX",
    "wof:name":"Mobile Merchandise",
    "wof:placetype":"venue"
},
  "geometry": {"coordinates":[-95.214136,29.845164],"type":"Point"}
}