{
  "type": "Feature",
  "properties": {
    "iso:country":"US",
    "sg:address":"120 W Main St",
    "sg:city":"Lewisville",
    "sg:phone":"+1 972 420 0600",
    "sg:postcode":"75057",
    "sg:province":"TX",
    "wof:name":"A Living Canvas Tatoo",
    "wof:placetype":"venue"
},
  "geometry": {"coordinates":[-96.994618,33.046311],"type":"Point"}
}