{
  "type": "Feature",
  "properties": {
    "iso:country":"US",
    "sg:address":"5201 el Paso Dr",
    "sg:city":"El Paso",
    "sg:classifiers":[
        {
            "category":"Wholesale",
            "subcategory":"Apparel",
            "type":"Manufacturing & Wholesale Goods"
        },
        {
            "category":"Manufacturing",
            "subcategory":"Apparel",
            "type":"Manufacturing & Wholesale Goods"
        }
    ],
    "sg:phone":"+1 915 772 9861",
    "sg:postcode":"79905",
    "sg:province":"TX",
    "sg:tags":[
        "trouser",
        "clothing",
        "mfg"
    ],
    "wof:name":"Inter Wash Garment Finishing",
    "wof:placetype":"venue"
},
  "geometry": {"coordinates":[-106.42765,31.770613],"type":"Point"}
}