{
  "type": "Feature",
  "properties": {
    "iso:country":"US",
    "sg:address":"913 Old Barn Ln",
    "sg:city":"Mesquite",
    "sg:classifiers":[
        {
            "category":"Manufacturing",
            "subcategory":"Glass & Minerals",
            "type":"Manufacturing & Wholesale Goods"
        }
    ],
    "sg:phone":"+1 972 288 5661",
    "sg:postcode":"75149",
    "sg:province":"TX",
    "sg:tags":[
        "wall",
        "mfg",
        "mirror"
    ],
    "wof:name":"Baxley Contemporary Acc",
    "wof:placetype":"venue"
},
  "geometry": {"coordinates":[-96.57091,32.774711],"type":"Point"}
}