{
  "type": "Feature",
  "properties": {
    "iso:country":"US",
    "sg:address":"6101 Patton Ranch Rd",
    "sg:city":"Austin",
    "sg:classifiers":[
        {
            "category":"Education",
            "subcategory":"School",
            "type":"Public Place"
        }
    ],
    "sg:phone":"+1 512 414 4413",
    "sg:postcode":"78735",
    "sg:province":"TX",
    "wof:name":"Oak Hill Elementary School",
    "wof:placetype":"venue"
},
  "geometry": {"coordinates":[-97.859619,30.237103],"type":"Point"}
}