{
  "type": "Feature",
  "properties": {
    "iso:country":"US",
    "sg:address":"6101 Jensen Dr",
    "sg:city":"Houston",
    "sg:classifiers":[
        {
            "category":"Retail",
            "subcategory":"Auto Repair",
            "type":"Services"
        }
    ],
    "sg:phone":"+1 713 692 4987",
    "sg:postcode":"77026",
    "sg:province":"TX",
    "sg:tags":[
        "repairing",
        "automobile",
        "general"
    ],
    "wof:name":"Joe's Garage",
    "wof:placetype":"venue"
},
  "geometry": {"coordinates":[-95.342428,29.81532],"type":"Point"}
}