{
  "type": "Feature",
  "properties": {
    "iso:country":"US",
    "sg:address":"11106 Spicewood Club Dr",
    "sg:city":"Austin",
    "sg:classifiers":[
        {
            "category":"Social Services",
            "subcategory":"Child Care",
            "type":"Services"
        }
    ],
    "sg:phone":"+1 512 258 3976",
    "sg:postcode":"78750",
    "sg:province":"TX",
    "sg:tags":[
        "day"
    ],
    "wof:name":"Barbara Ann Matteson",
    "wof:placetype":"venue"
},
  "geometry": {"coordinates":[-97.806742,30.437109],"type":"Point"}
}