{
  "type": "Feature",
  "properties": {
    "iso:country":"US",
    "sg:address":"2400 Chisholm Trl",
    "sg:city":"Round Rock",
    "sg:classifiers":[
        {
            "category":"Wholesale",
            "subcategory":"Construction Materials",
            "type":"Manufacturing & Wholesale Goods"
        },
        {
            "category":"Home & Garden",
            "subcategory":"Building Materials",
            "type":"Retail Goods"
        }
    ],
    "sg:phone":"+1 512 310 9469",
    "sg:postcode":"78681",
    "sg:province":"TX",
    "sg:tags":[
        "lumber"
    ],
    "sg:website":"www.stocklumber.com",
    "wof:name":"Stock Building Supply Texas LP",
    "wof:placetype":"venue"
},
  "geometry": {"coordinates":[-97.695047,30.536006],"type":"Point"}
}