{
  "type": "Feature",
  "properties": {
    "iso:country":"US",
    "sg:address":"13607 Amsbury Ln",
    "sg:city":"Cypress",
    "sg:classifiers":[
        {
            "category":"Professional",
            "subcategory":"Computer Services",
            "type":"Services"
        }
    ],
    "sg:phone":"+1 281 256 6135",
    "sg:postcode":"77429",
    "sg:province":"TX",
    "sg:tags":[
        "management",
        "facility"
    ],
    "wof:name":"Virtual Compute Corporation",
    "wof:placetype":"venue"
},
  "geometry": {"coordinates":[-95.642777,29.978435],"type":"Point"}
}