{
  "type": "Feature",
  "properties": {
    "iso:country":"US",
    "sg:address":"10111 Richmond Ave",
    "sg:city":"Houston",
    "sg:classifiers":[
        {
            "category":"Insurance",
            "subcategory":"Insurance Agent",
            "type":"Services"
        }
    ],
    "sg:phone":"+1 713 789 3366",
    "sg:postcode":"77042",
    "sg:province":"TX",
    "wof:name":"St Paul Travelers",
    "wof:placetype":"venue"
},
  "geometry": {"coordinates":[-95.552486,29.727944],"type":"Point"}
}