{
  "type": "Feature",
  "properties": {
    "iso:country":"US",
    "sg:address":"10233 E Northwest Hwy",
    "sg:city":"Dallas",
    "sg:classifiers":[
        {
            "category":"Real Estate",
            "subcategory":"Real Estate Agent",
            "type":"Services"
        }
    ],
    "sg:phone":"+1 214 341 0330",
    "sg:postcode":"75238",
    "sg:province":"TX",
    "sg:website":"www.ebby.com",
    "wof:name":"Ebby Halliday Realtors",
    "wof:placetype":"venue"
},
  "geometry": {"coordinates":[-96.709429,32.864397],"type":"Point"}
}