{
  "type": "Feature",
  "properties": {
    "iso:country":"US",
    "sg:address":"628 Hambrick Rd",
    "sg:city":"Dallas",
    "sg:classifiers":[
        {
            "category":"Manufacturing",
            "subcategory":"Food",
            "type":"Manufacturing & Wholesale Goods"
        }
    ],
    "sg:phone":"+1 214 348 2325",
    "sg:postcode":"75218",
    "sg:province":"TX",
    "sg:tags":[
        "canned",
        "specialty",
        "mfg"
    ],
    "wof:name":"Adobe House",
    "wof:placetype":"venue"
},
  "geometry": {"coordinates":[-96.705347,32.852387],"type":"Point"}
}