{
  "type": "Feature",
  "properties": {
    "iso:country":"US",
    "sg:address":"1509 S Medina St",
    "sg:city":"Lockhart",
    "sg:classifiers":[
        {
            "category":"Professional",
            "subcategory":"Computer Services",
            "type":"Services"
        }
    ],
    "sg:phone":"+1 512 620 0533",
    "sg:postcode":"78644",
    "sg:province":"TX",
    "wof:name":"Incremental Computers",
    "wof:placetype":"venue"
},
  "geometry": {"coordinates":[-97.684167,29.882889],"type":"Point"}
}