{
  "type": "Feature",
  "properties": {
    "iso:country":"US",
    "sg:address":"1218 E Yandell Dr",
    "sg:city":"El Paso",
    "sg:classifiers":[
        {
            "category":"Real Estate",
            "subcategory":"Real Estate Operator",
            "type":"Services"
        }
    ],
    "sg:phone":"+1 915 545 1180",
    "sg:postcode":"79902",
    "sg:province":"TX",
    "sg:tags":[
        "commercial"
    ],
    "wof:name":"Great River Corp",
    "wof:placetype":"venue"
},
  "geometry": {"coordinates":[-106.48072500000001,31.769676],"type":"Point"}
}