{
  "type": "Feature",
  "properties": {
    "iso:country":"US",
    "sg:address":"2000 E Highway 199",
    "sg:city":"Springtown",
    "sg:classifiers":[
        {
            "category":"Insurance",
            "subcategory":"Hazard Insurance",
            "type":"Services"
        }
    ],
    "sg:phone":"+1 817 221 2640",
    "sg:postcode":"76082",
    "sg:province":"TX",
    "sg:tags":[
        "commercial",
        "business"
    ],
    "wof:name":"Wendall Wood Insurance",
    "wof:placetype":"venue"
},
  "geometry": {"coordinates":[-97.64389,32.943467],"type":"Point"}
}