{
  "type": "Feature",
  "properties": {
    "iso:country":"US",
    "sg:address":"5225 S Loop 289",
    "sg:city":"Lubbock",
    "sg:classifiers":[
        {
            "category":"Insurance",
            "subcategory":"Insurance Agent",
            "type":"Services"
        }
    ],
    "sg:phone":"+1 806 783 9024",
    "sg:postcode":"79424",
    "sg:province":"TX",
    "wof:name":"Kathy Mc Intosh",
    "wof:placetype":"venue"
},
  "geometry": {"coordinates":[-101.92630699999999,33.535766],"type":"Point"}
}