{
  "type": "Feature",
  "properties": {
    "iso:country":"US",
    "sg:address":"2725 23rd St",
    "sg:city":"Orange",
    "sg:classifiers":[
        {
            "category":"Education",
            "subcategory":"Vocational School",
            "type":"Public Place"
        }
    ],
    "sg:phone":"+1 409 886 0242",
    "sg:postcode":"77630",
    "sg:province":"TX",
    "sg:tags":[
        "business"
    ],
    "sg:website":"http://www.sohobizsolutions.com",
    "wof:name":"Soho Business Solutions",
    "wof:placetype":"venue"
},
  "geometry": {"coordinates":[-93.754181,30.11611],"type":"Point"}
}