{
  "type": "Feature",
  "properties": {
    "iso:country":"US",
    "sg:address":"5120 Woodway Dr",
    "sg:city":"Houston",
    "sg:classifiers":[
        {
            "category":"Professional",
            "subcategory":"Lawyer & Legal Services",
            "type":"Services"
        }
    ],
    "sg:phone":"+1 713 840 1300",
    "sg:postcode":"77056",
    "sg:province":"TX",
    "sg:tags":[
        "divorce",
        "law",
        "family"
    ],
    "wof:name":"Emmott Jack H III Associates PC",
    "wof:placetype":"venue"
},
  "geometry": {"coordinates":[-95.466103,29.7623],"type":"Point"}
}