{
  "type": "Feature",
  "properties": {
    "iso:country":"US",
    "sg:address":"510 N Washington Ave",
    "sg:city":"Marshall",
    "sg:classifiers":[
        {
            "category":"Social Services",
            "type":"Services"
        }
    ],
    "sg:phone":"+1 903 938 6605",
    "sg:postcode":"75670",
    "sg:province":"TX",
    "sg:tags":[
        "individual",
        "family"
    ],
    "wof:name":"East Texas Human Development",
    "wof:placetype":"venue"
},
  "geometry": {"coordinates":[-94.36727999999999,32.549115],"type":"Point"}
}