{
  "type": "Feature",
  "properties": {
    "iso:country":"US",
    "sg:address":"16063 Longvista Dr",
    "sg:city":"Dallas",
    "sg:classifiers":[
        {
            "category":"Travel",
            "subcategory":"Campground",
            "type":"Entertainment"
        }
    ],
    "sg:phone":"+1 972 233 3146",
    "sg:postcode":"75248",
    "sg:province":"TX",
    "sg:tags":[
        "camp"
    ],
    "wof:name":"Smudgers Soccer Camp",
    "wof:placetype":"venue"
},
  "geometry": {"coordinates":[-96.78555,32.967769],"type":"Point"}
}