{
  "type": "Feature",
  "properties": {
    "iso:country":"US",
    "sg:address":"4904 Hackney Ln",
    "sg:city":"Lewisville",
    "sg:classifiers":[
        {
            "category":"Professional",
            "subcategory":"Computer Services",
            "type":"Services"
        },
        {
            "category":"Shopping",
            "subcategory":"Computers & Home Electronics",
            "type":"Retail Goods"
        }
    ],
    "sg:phone":"+1 972 370 1807",
    "sg:postcode":"75056",
    "sg:province":"TX",
    "sg:tags":[
        "software",
        "writing"
    ],
    "sg:website":"www.pcfss.com",
    "wof:name":"P C F Software Solutions",
    "wof:placetype":"venue"
},
  "geometry": {"coordinates":[-96.887182,33.083115],"type":"Point"}
}