{
  "type": "Feature",
  "properties": {
    "iso:country":"US",
    "sg:address":"2520 Airline Dr",
    "sg:city":"Houston",
    "sg:classifiers":[
        {
            "category":"Food & Beverages",
            "subcategory":"Fruits & Vegetables",
            "type":"Retail Goods"
        }
    ],
    "sg:phone":"+1 713 862 4027",
    "sg:postcode":"77009",
    "sg:province":"TX",
    "sg:tags":[
        "plant",
        "flower",
        "produce"
    ],
    "wof:name":"Canino Produce Co Inc",
    "wof:placetype":"venue"
},
  "geometry": {"coordinates":[-95.38193800000001,29.810156],"type":"Point"}
}