{
  "type": "Feature",
  "properties": {
    "iso:country":"US",
    "sg:address":"2204 Louisiana St",
    "sg:city":"Houston",
    "sg:classifiers":[
        {
            "category":"Professional",
            "type":"Services"
        }
    ],
    "sg:phone":"+1 713 529 7416",
    "sg:postcode":"77002",
    "sg:province":"TX",
    "wof:name":"Mbps Inc",
    "wof:placetype":"venue"
},
  "geometry": {"coordinates":[-95.37522800000001,29.748898],"type":"Point"}
}