{
  "type": "Feature",
  "properties": {
    "iso:country":"US",
    "sg:address":"101 Industrial Blvd",
    "sg:city":"Lufkin",
    "sg:classifiers":[
        {
            "category":"Utilities",
            "subcategory":"Telephone",
            "type":"Services"
        }
    ],
    "sg:phone":"+1 936 634 4375",
    "sg:postcode":"75904",
    "sg:province":"TX",
    "sg:tags":[
        "communications"
    ],
    "wof:name":"East Texas Dsl",
    "wof:placetype":"venue"
},
  "geometry": {"coordinates":[-94.758658,31.336864],"type":"Point"}
}