{
  "type": "Feature",
  "properties": {
    "iso:country":"US",
    "sg:address":"8308 Riverwalk Ln",
    "sg:city":"Mc Kinney",
    "sg:classifiers":[
        {
            "category":"Retail",
            "subcategory":"Portrait Studio",
            "type":"Services"
        }
    ],
    "sg:phone":"+1 972 369 1118",
    "sg:postcode":"75063",
    "sg:province":"TX",
    "sg:tags":[
        "photo"
    ],
    "wof:name":"Brandon Garner Photography",
    "wof:placetype":"venue"
},
  "geometry": {"coordinates":[-96.947503,32.935607],"type":"Point"}
}