{
  "type": "Feature",
  "properties": {
    "iso:country":"US",
    "sg:address":"7319 Barton Oaks Dr",
    "sg:city":"Houston",
    "sg:classifiers":[
        {
            "category":"Building & Trades",
            "subcategory":"Construction",
            "type":"Services"
        }
    ],
    "sg:phone":"+1 281 550 7437",
    "sg:postcode":"77095",
    "sg:province":"TX",
    "sg:tags":[
        "house"
    ],
    "wof:name":"Rauls Remodeling",
    "wof:placetype":"venue"
},
  "geometry": {"coordinates":[-95.66465700000001,29.886725],"type":"Point"}
}