{
  "type": "Feature",
  "properties": {
    "iso:country":"US",
    "sg:address":"2310 Heather Ridge Ln",
    "sg:city":"Garland",
    "sg:classifiers":[
        {
            "category":"Communications",
            "subcategory":"Film & Video Production",
            "type":"Services"
        }
    ],
    "sg:phone":"+1 972 494 5860",
    "sg:postcode":"75040",
    "sg:province":"TX",
    "sg:tags":[
        "audio"
    ],
    "wof:name":"Kerry Garrett Audio & Video",
    "wof:placetype":"venue"
},
  "geometry": {"coordinates":[-96.598131,32.915011],"type":"Point"}
}