{
  "type": "Feature",
  "properties": {
    "iso:country":"US",
    "sg:address":"2900 N Loop Fwy",
    "sg:city":"Houston",
    "sg:classifiers":[
        {
            "category":"Professional",
            "subcategory":"Employment Agencies",
            "type":"Services"
        }
    ],
    "sg:phone":"+1 713 688 0686",
    "sg:postcode":"77092",
    "sg:province":"TX",
    "sg:tags":[
        "opportunity"
    ],
    "wof:name":"Bob Rule Enterprises",
    "wof:placetype":"venue"
},
  "geometry": {"coordinates":[-95.448407,29.804539],"type":"Point"}
}