{
  "type": "Feature",
  "properties": {
    "iso:country":"US",
    "sg:address":"710 N Bell Blvd,",
    "sg:city":"Cedar Park",
    "sg:classifiers":[
        {
            "category":"Health Services",
            "subcategory":"Clinic",
            "type":"Services"
        }
    ],
    "sg:phone":"+1 512 250 0867",
    "sg:postcode":"78613",
    "sg:province":"TX",
    "sg:tags":[
        "medical"
    ],
    "sg:website":"www.walgreens.com/",
    "wof:name":"Walgreens",
    "wof:placetype":"venue"
},
  "geometry": {"coordinates":[-97.827938,30.517541],"type":"Point"}
}