{
  "type": "Feature",
  "properties": {
    "iso:country":"US",
    "sg:address":"3802 Cedar Valley Dr",
    "sg:city":"Missouri City",
    "sg:classifiers":[
        {
            "category":"Professional",
            "subcategory":"Lawyer & Legal Services",
            "type":"Services"
        }
    ],
    "sg:phone":"+1 281 416 9699",
    "sg:postcode":"77459",
    "sg:province":"TX",
    "wof:name":"John Farra Attorney At Law PC",
    "wof:placetype":"venue"
},
  "geometry": {"coordinates":[-95.548017,29.563636],"type":"Point"}
}