{
  "type": "Feature",
  "properties": {
    "iso:country":"US",
    "sg:address":"2525 Murworth Dr Ste 300",
    "sg:city":"Houston",
    "sg:classifiers":[
        {
            "category":"Government",
            "subcategory":"Office",
            "type":"Public Place"
        }
    ],
    "sg:phone":"+1 713 394 4067",
    "sg:postcode":"77054",
    "sg:province":"TX",
    "sg:tags":[
        "government-united",
        "state"
    ],
    "sg:website":"http://www.hcpl.net",
    "wof:name":"County Attorney",
    "wof:placetype":"venue"
},
  "geometry": {"coordinates":[-95.41570900000001,29.685118],"type":"Point"}
}