{
  "type": "Feature",
  "properties": {
    "iso:country":"US",
    "sg:address":"5925 Forest Ln",
    "sg:city":"Dallas",
    "sg:classifiers":[
        {
            "category":"Professional",
            "subcategory":"Lawyer & Legal Services",
            "type":"Services"
        }
    ],
    "sg:phone":"+1 972 233 2975",
    "sg:postcode":"75230",
    "sg:province":"TX",
    "sg:tags":[
        "attorney"
    ],
    "wof:name":"Charles Marcus",
    "wof:placetype":"venue"
},
  "geometry": {"coordinates":[-96.80473000000001,32.909613],"type":"Point"}
}