{
  "type": "Feature",
  "properties": {
    "iso:country":"US",
    "sg:address":"8403 Hanbridge Ln",
    "sg:city":"Austin",
    "sg:classifiers":[
        {
            "category":"Building & Trades",
            "subcategory":"Construction",
            "type":"Services"
        }
    ],
    "sg:phone":"+1 512 288 3757",
    "sg:postcode":"78736",
    "sg:province":"TX",
    "sg:tags":[
        "contractor"
    ],
    "wof:name":"Austin Custom Tile",
    "wof:placetype":"venue"
},
  "geometry": {"coordinates":[-97.896276,30.238465],"type":"Point"}
}