{
  "type": "Feature",
  "properties": {
    "iso:country":"US",
    "sg:address":"509 Riverview Dr",
    "sg:city":"Georgetown",
    "sg:classifiers":[
        {
            "category":"Shopping",
            "type":"Retail Goods"
        }
    ],
    "sg:phone":"+1 512 863 9788",
    "sg:postcode":"78628",
    "sg:province":"TX",
    "sg:tags":[
        "merchandise"
    ],
    "wof:name":"Kimberly Ann Giese and Gay Pet",
    "wof:placetype":"venue"
},
  "geometry": {"coordinates":[-97.710466,30.616189],"type":"Point"}
}