{
  "type": "Feature",
  "properties": {
    "iso:country":"US",
    "sg:address":"117 E California St",
    "sg:city":"Sulphur Springs",
    "sg:classifiers":[
        {
            "category":"Organizations",
            "subcategory":"Community Association",
            "type":"Services"
        }
    ],
    "sg:phone":"+1 903 885 4024",
    "sg:postcode":"75482",
    "sg:province":"TX",
    "wof:name":"Disabled American Veteran",
    "wof:placetype":"venue"
},
  "geometry": {"coordinates":[-95.59960599999999,33.146933],"type":"Point"}
}