{
  "type": "Feature",
  "properties": {
    "iso:country":"US",
    "sg:address":"125 W 6th St",
    "sg:city":"Aspermont",
    "sg:classifiers":[
        {
            "category":"Personal",
            "subcategory":"Shoe Repair & Shine",
            "type":"Services"
        }
    ],
    "sg:phone":"+1 940 989 3180",
    "sg:postcode":"79556",
    "sg:province":"TX",
    "sg:tags":[
        "repairing",
        "boot"
    ],
    "wof:name":"Rodeo & Roper Supply",
    "wof:placetype":"venue"
},
  "geometry": {"coordinates":[-100.411044,32.47354],"type":"Point"}
}