{
  "type": "Feature",
  "properties": {
    "iso:country":"US",
    "sg:address":"503 Mallard Ln",
    "sg:city":"Taylor",
    "sg:classifiers":[
        {
            "category":"Social Services",
            "type":"Services"
        }
    ],
    "sg:phone":"+1 512 365 2699",
    "sg:postcode":"76574",
    "sg:province":"TX",
    "sg:tags":[
        "organization",
        "welfare"
    ],
    "sg:website":"www.propertyrights.org",
    "wof:name":"American Land Foundation",
    "wof:placetype":"venue"
},
  "geometry": {"coordinates":[-97.417985,30.591002],"type":"Point"}
}