{
  "type": "Feature",
  "properties": {
    "iso:country":"US",
    "sg:address":"5555 W Loop S",
    "sg:city":"Houston",
    "sg:classifiers":[
        {
            "category":"Professional",
            "subcategory":"Lawyer & Legal Services",
            "type":"Services"
        }
    ],
    "sg:phone":"+1 713 662 3115",
    "sg:postcode":"77002",
    "sg:province":"TX",
    "wof:name":"Nguyen & Delcid PC",
    "wof:placetype":"venue"
},
  "geometry": {"coordinates":[-95.336085,29.687646],"type":"Point"}
}