{
  "type": "Feature",
  "properties": {
    "iso:country":"US",
    "sg:address":"510 E Lantrip St",
    "sg:city":"Kilgore",
    "sg:classifiers":[
        {
            "category":"Banks & Credit Unions",
            "subcategory":"Bank",
            "type":"Services"
        }
    ],
    "sg:phone":"+1 903 984 5654",
    "sg:postcode":"75662",
    "sg:province":"TX",
    "wof:name":"Kilgore Shell Employees Federal Credit",
    "wof:placetype":"venue"
},
  "geometry": {"coordinates":[-94.870519,32.387238],"type":"Point"}
}