{
  "type": "Feature",
  "properties": {
    "iso:country":"US",
    "sg:address":"1527 Hemphill St",
    "sg:city":"Fort Worth",
    "sg:classifiers":[
        {
            "category":"Health Services",
            "subcategory":"Hospital",
            "type":"Services"
        }
    ],
    "sg:phone":"+1 817 569 4200",
    "sg:postcode":"76104",
    "sg:province":"TX",
    "sg:tags":[
        "program",
        "mental"
    ],
    "wof:name":"Telecare Tarrant Act I",
    "wof:placetype":"venue"
},
  "geometry": {"coordinates":[-97.331467,32.727417],"type":"Point"}
}