{
  "type": "Feature",
  "properties": {
    "iso:country":"US",
    "sg:address":"875 Twin Oaks Dr",
    "sg:city":"New Braunfels",
    "sg:classifiers":[
        {
            "category":"Shopping",
            "type":"Retail Goods"
        }
    ],
    "sg:phone":"+1 830 608 0443",
    "sg:postcode":"78130",
    "sg:province":"TX",
    "sg:tags":[
        "merchandise"
    ],
    "wof:name":"Ronald Rychel",
    "wof:placetype":"venue"
},
  "geometry": {"coordinates":[-98.15756399999999,29.706673],"type":"Point"}
}