{
  "type": "Feature",
  "properties": {
    "iso:country":"US",
    "sg:address":"1847 State Hwy 46",
    "sg:city":"New Braunfels",
    "sg:classifiers":[
        {
            "category":"Banks & Credit Unions",
            "subcategory":"Investment Brokerage",
            "type":"Services"
        }
    ],
    "sg:phone":"+1 830 643 1046",
    "sg:postcode":"78132",
    "sg:province":"TX",
    "sg:tags":[
        "stock",
        "bond"
    ],
    "wof:name":"Edward Jones Co",
    "wof:placetype":"venue"
},
  "geometry": {"coordinates":[-98.162381,29.718458],"type":"Point"}
}