{
  "type": "Feature",
  "properties": {
    "iso:country":"US",
    "sg:address":"420 W Main St",
    "sg:city":"Nacogdoches",
    "sg:classifiers":[
        {
            "category":"Utilities",
            "subcategory":"Fuel Oil & Lpg",
            "type":"Services"
        }
    ],
    "sg:phone":"+1 936 564 4453",
    "sg:postcode":"75961",
    "sg:province":"TX",
    "sg:tags":[
        "liquefied",
        "household",
        "gas",
        "appliance",
        "petroleum"
    ],
    "wof:name":"Greenville Automatic Gas",
    "wof:placetype":"venue"
},
  "geometry": {"coordinates":[-94.658855,31.604979],"type":"Point"}
}