{
  "type": "Feature",
  "properties": {
    "iso:country":"US",
    "sg:address":"2506 Tierra Dr",
    "sg:city":"Irving",
    "sg:classifiers":[
        {
            "category":"Building & Trades",
            "subcategory":"Landscaping Services",
            "type":"Services"
        }
    ],
    "sg:phone":"+1 972 594 7119",
    "sg:postcode":"75038",
    "sg:province":"TX",
    "wof:name":"Tender Lawn Care Services TLC",
    "wof:placetype":"venue"
},
  "geometry": {"coordinates":[-96.980801,32.860701],"type":"Point"}
}