{
  "type": "Feature",
  "properties": {
    "iso:country":"US",
    "sg:address":"14943 Royal Birkdale St",
    "sg:city":"Houston",
    "sg:classifiers":[
        {
            "category":"Communications",
            "subcategory":"Film & Video Production",
            "type":"Services"
        }
    ],
    "sg:phone":"+1 281 463 2505",
    "sg:postcode":"77095",
    "sg:province":"TX",
    "sg:tags":[
        "motion",
        "picture"
    ],
    "wof:name":"Bakcrafts",
    "wof:placetype":"venue"
},
  "geometry": {"coordinates":[-95.63082900000001,29.892476],"type":"Point"}
}