{
  "type": "Feature",
  "properties": {
    "iso:country":"US",
    "sg:address":"716 High St",
    "sg:city":"Comfort",
    "sg:classifiers":[
        {
            "category":"Professional",
            "type":"Services"
        }
    ],
    "sg:phone":"+1 830 995 2599",
    "sg:postcode":"78013",
    "sg:province":"TX",
    "wof:name":"Rita A Harmon",
    "wof:placetype":"venue"
},
  "geometry": {"coordinates":[-98.907668,29.967033],"type":"Point"}
}