{
  "type": "Feature",
  "properties": {
    "iso:country":"US",
    "sg:address":"201 Linda Dr",
    "sg:city":"Sulphur Springs",
    "sg:classifiers":[
        {
            "category":"Home & Garden",
            "subcategory":"Furniture",
            "type":"Retail Goods"
        }
    ],
    "sg:phone":"+1 903 885 5667",
    "sg:postcode":"75482",
    "sg:province":"TX",
    "wof:name":"Furniture Barn Inc",
    "wof:placetype":"venue"
},
  "geometry": {"coordinates":[-95.59780600000001,33.122116],"type":"Point"}
}