{
  "type": "Feature",
  "properties": {
    "iso:country":"US",
    "sg:address":"1409 Ardmore Dr",
    "sg:city":"Arlington",
    "sg:classifiers":[
        {
            "category":"Health Services",
            "subcategory":"Clinic",
            "type":"Services"
        }
    ],
    "sg:phone":"+1 817 557 1861",
    "sg:postcode":"76018",
    "sg:province":"TX",
    "wof:name":"Lactations Support Services",
    "wof:placetype":"venue"
},
  "geometry": {"coordinates":[-97.08396500000001,32.656226],"type":"Point"}
}