{
  "type": "Feature",
  "properties": {
    "iso:country":"US",
    "sg:address":"8109 Dunn St",
    "sg:city":"Austin",
    "sg:classifiers":[
        {
            "category":"Building & Trades",
            "subcategory":"Construction",
            "type":"Services"
        }
    ],
    "sg:phone":"+1 512 263 1673",
    "sg:postcode":"78745",
    "sg:province":"TX",
    "sg:tags":[
        "repairing",
        "remodeling",
        "contractor"
    ],
    "wof:name":"Home Tec Svc",
    "wof:placetype":"venue"
},
  "geometry": {"coordinates":[-97.834566,30.199816],"type":"Point"}
}