{
  "type": "Feature",
  "properties": {
    "iso:country":"US",
    "sg:address":"2617 NW 17th St",
    "sg:city":"Fort Worth",
    "sg:classifiers":[
        {
            "category":"Retail",
            "subcategory":"Auto Repair",
            "type":"Services"
        }
    ],
    "sg:phone":"+1 817 624 0643",
    "sg:postcode":"76106",
    "sg:province":"TX",
    "sg:tags":[
        "repairing",
        "automobile"
    ],
    "wof:name":"Mario's Auto Svc",
    "wof:placetype":"venue"
},
  "geometry": {"coordinates":[-97.385085,32.789577],"type":"Point"}
}