{
  "type": "Feature",
  "properties": {
    "iso:country":"US",
    "sg:address":"6342 Jacksboro Hwy",
    "sg:city":"Fort Worth",
    "sg:classifiers":[
        {
            "category":"Home & Garden",
            "subcategory":"Building Materials",
            "type":"Retail Goods"
        }
    ],
    "sg:phone":"+1 817 237 0204",
    "sg:postcode":"76135",
    "sg:province":"TX",
    "sg:tags":[
        "paint",
        "floor",
        "covering"
    ],
    "wof:name":"Sherwin-Williams Paints",
    "wof:placetype":"venue"
},
  "geometry": {"coordinates":[-97.426934,32.810669],"type":"Point"}
}