{
  "type": "Feature",
  "properties": {
    "iso:country":"US",
    "sg:address":"401 E Interstate 20 Svc Rd",
    "sg:city":"Weatherford",
    "sg:classifiers":[
        {
            "category":"Organizations",
            "subcategory":"Religious Organization",
            "type":"Services"
        }
    ],
    "sg:phone":"+1 817 594 0589",
    "sg:postcode":"76087",
    "sg:province":"TX",
    "sg:tags":[
        "church"
    ],
    "wof:name":"Church Of The Nazarene",
    "wof:placetype":"venue"
},
  "geometry": {"coordinates":[-97.66042899999999,32.742213],"type":"Point"}
}