{
  "type": "Feature",
  "properties": {
    "iso:country":"US",
    "sg:address":"612 W 11th St",
    "sg:city":"Cisco",
    "sg:classifiers":[
        {
            "category":"Restaurant",
            "type":"Food & Drink"
        }
    ],
    "sg:phone":"+1 254 631 8612",
    "sg:postcode":"76437",
    "sg:province":"TX",
    "wof:name":"Barry's Bar B Q",
    "wof:placetype":"venue"
},
  "geometry": {"coordinates":[-98.98278500000001,32.383321],"type":"Point"}
}