{
  "type": "Feature",
  "properties": {
    "iso:country":"US",
    "sg:address":"1310 Turtle Creek Dr",
    "sg:city":"Missouri City",
    "sg:classifiers":[
        {
            "category":"Professional",
            "type":"Services"
        }
    ],
    "sg:phone":"+1 281 416 3997",
    "sg:postcode":"77489",
    "sg:province":"TX",
    "sg:tags":[
        "establishment"
    ],
    "wof:name":"Ft Bend County Democratic Prty",
    "wof:placetype":"venue"
},
  "geometry": {"coordinates":[-95.521404,29.579597],"type":"Point"}
}