{
  "type": "Feature",
  "properties": {
    "iso:country":"US",
    "sg:address":"1423 Yucca Dr",
    "sg:city":"Dalhart",
    "sg:classifiers":[
        {
            "category":"Professional",
            "type":"Services"
        }
    ],
    "sg:phone":"+1 806 244 2341",
    "sg:postcode":"79022",
    "sg:province":"TX",
    "wof:name":"Golden Spread Millers Inc",
    "wof:placetype":"venue"
},
  "geometry": {"coordinates":[-102.523331,36.050869],"type":"Point"}
}