{
  "type": "Feature",
  "properties": {
    "iso:country":"US",
    "sg:address":"15 N 33rd St",
    "sg:city":"Temple",
    "sg:classifiers":[
        {
            "category":"Utilities",
            "subcategory":"Cable",
            "type":"Services"
        }
    ],
    "sg:phone":"+1 254 778 4201",
    "sg:postcode":"76504",
    "sg:province":"TX",
    "sg:tags":[
        "provides"
    ],
    "wof:name":"Cablevision Investors Inc",
    "wof:placetype":"venue"
},
  "geometry": {"coordinates":[-97.358396,31.102274],"type":"Point"}
}