{
  "type": "Feature",
  "properties": {
    "iso:country":"US",
    "sg:address":"116 E Main St",
    "sg:city":"Richardson",
    "sg:classifiers":[
        {
            "category":"Retail",
            "subcategory":"Repair Shop",
            "type":"Services"
        }
    ],
    "sg:phone":"+1 972 233 2442",
    "sg:postcode":"75081",
    "sg:province":"TX",
    "wof:name":"Ace Key & Lock",
    "wof:placetype":"venue"
},
  "geometry": {"coordinates":[-96.73098899999999,32.948755],"type":"Point"}
}