{
  "type": "Feature",
  "properties": {
    "iso:country":"US",
    "sg:address":"607 Antler Dr",
    "sg:city":"San Antonio",
    "sg:classifiers":[
        {
            "category":"Building & Trades",
            "subcategory":"Construction",
            "type":"Services"
        }
    ],
    "sg:phone":"+1 210 342 8070",
    "sg:postcode":"78213",
    "sg:province":"TX",
    "sg:tags":[
        "carport"
    ],
    "wof:name":"Precision Home Exteriors Co",
    "wof:placetype":"venue"
},
  "geometry": {"coordinates":[-98.50699,29.511351],"type":"Point"}
}