{
  "type": "Feature",
  "properties": {
    "iso:country":"US",
    "sg:address":"10625 Newkirk St",
    "sg:city":"Dallas",
    "sg:classifiers":[
        {
            "category":"Manufacturing",
            "subcategory":"Motor Vehicles & Parts",
            "type":"Manufacturing & Wholesale Goods"
        }
    ],
    "sg:phone":"+1 972 556 0030",
    "sg:postcode":"75220",
    "sg:province":"TX",
    "sg:tags":[
        "automobile",
        "supply"
    ],
    "wof:name":"Tune Up Warehouse",
    "wof:placetype":"venue"
},
  "geometry": {"coordinates":[-96.90785,32.871206],"type":"Point"}
}