{
  "type": "Feature",
  "properties": {
    "iso:country":"US",
    "sg:address":"1926 W 18th St",
    "sg:city":"Houston",
    "sg:classifiers":[
        {
            "category":"Professional",
            "subcategory":"Accounting & Tax Preparation",
            "type":"Services"
        }
    ],
    "sg:phone":"+1 832 242 0123",
    "sg:postcode":"77008",
    "sg:province":"TX",
    "wof:name":"ABS Financial Services",
    "wof:placetype":"venue"
},
  "geometry": {"coordinates":[-95.43354100000001,29.801541],"type":"Point"}
}