{
  "type": "Feature",
  "properties": {
    "iso:country":"US",
    "sg:address":"1704 Bomar St",
    "sg:city":"Marshall",
    "sg:classifiers":[
        {
            "category":"Personal",
            "subcategory":"Beauty Salon",
            "type":"Services"
        }
    ],
    "sg:phone":"+1 903 934 9777",
    "sg:postcode":"75670",
    "sg:province":"TX",
    "sg:tags":[
        "shop"
    ],
    "wof:name":"Yulanda's Hair Salon",
    "wof:placetype":"venue"
},
  "geometry": {"coordinates":[-94.371274,32.530167],"type":"Point"}
}