{
  "type": "Feature",
  "properties": {
    "iso:country":"US",
    "sg:address":"9800 Pagewood Ln Apt 3001",
    "sg:city":"Houston",
    "sg:classifiers":[
        {
            "category":"Social Services",
            "subcategory":"Job Training",
            "type":"Services"
        }
    ],
    "sg:phone":"+1 713 266 1730",
    "sg:postcode":"77042",
    "sg:province":"TX",
    "sg:tags":[
        "consultant"
    ],
    "wof:name":"Hobbs Motivational Messages",
    "wof:placetype":"venue"
},
  "geometry": {"coordinates":[-95.542225,29.72543],"type":"Point"}
}