{
  "type": "Feature",
  "properties": {
    "iso:country":"US",
    "sg:address":"11209 Fuqua St",
    "sg:city":"Houston",
    "sg:classifiers":[
        {
            "category":"Travel",
            "subcategory":"Travel Agent",
            "type":"Entertainment"
        }
    ],
    "sg:phone":"+1 713 944 5200",
    "sg:postcode":"77089",
    "sg:province":"TX",
    "sg:tags":[
        "agency",
        "bureau"
    ],
    "wof:name":"Express Travel Svc",
    "wof:placetype":"venue"
},
  "geometry": {"coordinates":[-95.22062200000001,29.613073],"type":"Point"}
}