{
  "type": "Feature",
  "properties": {
    "iso:country":"US",
    "sg:address":"3152 Major St",
    "sg:city":"Fort Worth",
    "sg:classifiers":[
        {
            "category":"Building & Trades",
            "subcategory":"Construction",
            "type":"Services"
        }
    ],
    "sg:phone":"+1 817 451 5522",
    "sg:postcode":"76112",
    "sg:province":"TX",
    "sg:tags":[
        "maker",
        "cabinet"
    ],
    "wof:name":"Dimension One",
    "wof:placetype":"venue"
},
  "geometry": {"coordinates":[-97.209023,32.731904],"type":"Point"}
}