{
  "type": "Feature",
  "properties": {
    "iso:country":"US",
    "sg:address":"3025 Webb Chapel Ext",
    "sg:city":"Dallas",
    "sg:classifiers":[
        {
            "category":"Restaurant",
            "type":"Food & Drink"
        }
    ],
    "sg:phone":"+1 214 956 9112",
    "sg:postcode":"75220",
    "sg:province":"TX",
    "wof:name":"Terry's Supermarket",
    "wof:placetype":"venue"
},
  "geometry": {"coordinates":[-96.86900300000001,32.858299],"type":"Point"}
}