{
  "type": "Feature",
  "properties": {
    "iso:country":"US",
    "sg:address":"2900 Longmire Dr",
    "sg:city":"College Station",
    "sg:classifiers":[
        {
            "category":"Shopping",
            "subcategory":"Clothing, Apparel, & Fashions",
            "type":"Retail Goods"
        }
    ],
    "sg:phone":"+1 979 695 1856",
    "sg:postcode":"77845",
    "sg:province":"TX",
    "sg:tags":[
        "item",
        "boutique"
    ],
    "wof:name":"Monogram Boutique",
    "wof:placetype":"venue"
},
  "geometry": {"coordinates":[-96.292374,30.590204],"type":"Point"}
}