{
  "type": "Feature",
  "properties": {
    "iso:country":"US",
    "sg:address":"6410 Gulf Fwy",
    "sg:city":"Houston",
    "sg:classifiers":[
        {
            "category":"Personal",
            "subcategory":"Beauty Salon",
            "type":"Services"
        }
    ],
    "sg:phone":"+1 409 986 9333",
    "sg:postcode":"77023",
    "sg:province":"TX",
    "sg:tags":[
        "manicuring"
    ],
    "wof:name":"California Nails USA",
    "wof:placetype":"venue"
},
  "geometry": {"coordinates":[-95.31093199999999,29.711812],"type":"Point"}
}