{
  "type": "Feature",
  "properties": {
    "iso:country":"US",
    "sg:address":"204 W Trinity St",
    "sg:city":"Groesbeck",
    "sg:classifiers":[
        {
            "category":"Health Services",
            "subcategory":"Clinic",
            "type":"Services"
        }
    ],
    "sg:phone":"+1 866 985 3908",
    "sg:postcode":"76642",
    "sg:province":"TX",
    "sg:tags":[
        "welfare"
    ],
    "wof:name":"Rettig Family Health Care",
    "wof:placetype":"venue"
},
  "geometry": {"coordinates":[-96.533062,31.524034],"type":"Point"}
}