{
  "type": "Feature",
  "properties": {
    "iso:country":"US",
    "sg:address":"3740 Galena Hills Loop",
    "sg:city":"Round Rock",
    "sg:classifiers":[
        {
            "category":"Banks & Credit Unions",
            "subcategory":"Financial Services",
            "type":"Services"
        }
    ],
    "sg:phone":"+1 512 716 1145",
    "sg:postcode":"78681",
    "sg:province":"TX",
    "sg:tags":[
        "investor"
    ],
    "wof:name":"AFA Investments Inc",
    "wof:placetype":"venue"
},
  "geometry": {"coordinates":[-97.753501,30.547616],"type":"Point"}
}