{
  "type": "Feature",
  "properties": {
    "iso:country":"US",
    "sg:address":"704 Hood Rd",
    "sg:city":"Mineral Wells",
    "sg:classifiers":[
        {
            "category":"Education",
            "subcategory":"College",
            "type":"Public Place"
        }
    ],
    "sg:phone":"+1 940 325 6101",
    "sg:postcode":"76067",
    "sg:province":"TX",
    "wof:name":"Weatherford College",
    "wof:placetype":"venue"
},
  "geometry": {"coordinates":[-98.054159,32.81888],"type":"Point"}
}