{
  "type": "Feature",
  "properties": {
    "iso:country":"US",
    "sg:address":"5980 Sam Houston Pkwy",
    "sg:city":"Humble",
    "sg:classifiers":[
        {
            "category":"Retail",
            "subcategory":"Auto Repair",
            "type":"Services"
        }
    ],
    "sg:phone":"+1 281 441 3300",
    "sg:postcode":"77396",
    "sg:province":"TX",
    "sg:tags":[
        "automobile",
        "customizing"
    ],
    "wof:name":"Hot Rods Ink",
    "wof:placetype":"venue"
},
  "geometry": {"coordinates":[-95.300082,29.939486],"type":"Point"}
}