{
  "type": "Feature",
  "properties": {
    "iso:country":"US",
    "sg:address":"2900 Walnut Hill Ln",
    "sg:city":"Dallas",
    "sg:classifiers":[
        {
            "category":"Recreation",
            "type":"Entertainment"
        }
    ],
    "sg:phone":"+1 214 902 9305",
    "sg:postcode":"75229",
    "sg:province":"TX",
    "sg:tags":[
        "parlor",
        "billiard"
    ],
    "wof:name":"Billardes Puebla",
    "wof:placetype":"venue"
},
  "geometry": {"coordinates":[-96.883235,32.88084],"type":"Point"}
}