{
  "type": "Feature",
  "properties": {
    "iso:country":"US",
    "sg:address":"3314 Greenbriar St",
    "sg:city":"Houston",
    "sg:classifiers":[
        {
            "category":"Wholesale",
            "subcategory":"Machinery & Supplies",
            "type":"Manufacturing & Wholesale Goods"
        }
    ],
    "sg:phone":"+1 713 526 5601",
    "sg:postcode":"77098",
    "sg:province":"TX",
    "sg:tags":[
        "spray",
        "booth"
    ],
    "wof:name":"Apollo Sprayers",
    "wof:placetype":"venue"
},
  "geometry": {"coordinates":[-95.41296699999999,29.736133],"type":"Point"}
}