{
  "type": "Feature",
  "properties": {
    "iso:country":"US",
    "sg:address":"1164 E Oaklawn Dr",
    "sg:city":"Terrell",
    "sg:classifiers":[
        {
            "category":"Building & Trades",
            "subcategory":"Landscaping Services",
            "type":"Services"
        }
    ],
    "sg:phone":"+1 972 564 5800",
    "sg:postcode":"75160",
    "sg:province":"TX",
    "wof:name":"Parkway Lawn Service",
    "wof:placetype":"venue"
},
  "geometry": {"coordinates":[-96.39855799999999,32.687047],"type":"Point"}
}