{
  "type": "Feature",
  "properties": {
    "iso:country":"US",
    "sg:address":"8225 Valencia Ave",
    "sg:city":"Lubbock",
    "sg:classifiers":[
        {
            "category":"Wholesale",
            "subcategory":"Machinery & Supplies",
            "type":"Manufacturing & Wholesale Goods"
        }
    ],
    "sg:phone":"+1 806 741 0919",
    "sg:postcode":"79424",
    "sg:province":"TX",
    "sg:tags":[
        "equipment",
        "steam",
        "cleaning"
    ],
    "wof:name":"Nelco Equipment Svc",
    "wof:placetype":"venue"
},
  "geometry": {"coordinates":[-101.978667,33.516634],"type":"Point"}
}