{
  "type": "Feature",
  "properties": {
    "iso:country":"US",
    "sg:address":"417 N Austin St",
    "sg:city":"Seguin",
    "sg:classifiers":[
        {
            "category":"Personal",
            "subcategory":"Beauty Salon",
            "type":"Services"
        }
    ],
    "sg:phone":"+1 830 372 3609",
    "sg:postcode":"78155",
    "sg:province":"TX",
    "wof:name":"Haircut Store",
    "wof:placetype":"venue"
},
  "geometry": {"coordinates":[-97.96457599999999,29.5712],"type":"Point"}
}