{
  "type": "Feature",
  "properties": {
    "iso:country":"US",
    "sg:address":"2431 Heather Hill Ln",
    "sg:city":"Plano",
    "sg:classifiers":[
        {
            "category":"Wholesale",
            "subcategory":"Vending Machines",
            "type":"Manufacturing & Wholesale Goods"
        }
    ],
    "sg:phone":"+1 972 596 0285",
    "sg:postcode":"75075",
    "sg:province":"TX",
    "sg:tags":[
        "operator"
    ],
    "wof:name":"Munch Time Vending",
    "wof:placetype":"venue"
},
  "geometry": {"coordinates":[-96.740965,33.034063],"type":"Point"}
}