{
  "type": "Feature",
  "properties": {
    "iso:country":"US",
    "sg:address":"14405 Sandy Side Dr",
    "sg:city":"Austin",
    "sg:classifiers":[
        {
            "category":"Retail",
            "subcategory":"Portrait Studio",
            "type":"Services"
        }
    ],
    "sg:phone":"+1 512 990 2816",
    "sg:postcode":"78728",
    "sg:province":"TX",
    "sg:tags":[
        "photo",
        "photographer",
        "wedding"
    ],
    "wof:name":"Gene Henderson Photography",
    "wof:placetype":"venue"
},
  "geometry": {"coordinates":[-97.67929599999999,30.43943],"type":"Point"}
}