{
  "type": "Feature",
  "properties": {
    "iso:country":"US",
    "sg:address":"982 E Kingsbury St",
    "sg:city":"Seguin",
    "sg:classifiers":[
        {
            "category":"Travel",
            "subcategory":"Hotels & Motels",
            "type":"Entertainment"
        }
    ],
    "sg:phone":"+1 830 401 0907",
    "sg:postcode":"78155",
    "sg:province":"TX",
    "sg:tags":[
        "operation"
    ],
    "wof:name":"Seguin Motel",
    "wof:placetype":"venue"
},
  "geometry": {"coordinates":[-97.953574,29.581037],"type":"Point"}
}