{
  "type": "Feature",
  "properties": {
    "iso:country":"US",
    "sg:address":"1435 Slocum St",
    "sg:city":"Dallas",
    "sg:classifiers":[
        {
            "category":"Home & Garden",
            "subcategory":"Building Materials",
            "type":"Retail Goods"
        }
    ],
    "sg:phone":"+1 214 651 1937",
    "sg:postcode":"75207",
    "sg:province":"TX",
    "sg:tags":[
        "equipment",
        "fixture",
        "lighting"
    ],
    "wof:name":"Thomas Grant Chandeliers",
    "wof:placetype":"venue"
},
  "geometry": {"coordinates":[-96.818631,32.792469],"type":"Point"}
}