{
  "type": "Feature",
  "properties": {
    "iso:country":"US",
    "sg:address":"11882 Greenville Ave Ste 127",
    "sg:city":"Dallas",
    "sg:classifiers":[
        {
            "category":"Professional",
            "subcategory":"Employment Agencies",
            "type":"Services"
        }
    ],
    "sg:phone":"+1 972 699 7740",
    "sg:postcode":"75243",
    "sg:province":"TX",
    "wof:name":"Sterling Personnel Services-Clerical Division",
    "wof:placetype":"venue"
},
  "geometry": {"coordinates":[-96.746399,32.910198],"type":"Point"}
}