{
  "type": "Feature",
  "properties": {
    "iso:country":"US",
    "sg:address":"9201 S Padre Island Dr",
    "sg:city":"Corpus Christi",
    "sg:classifiers":[
        {
            "category":"Professional",
            "type":"Services"
        }
    ],
    "sg:phone":"+1 361 937 1590",
    "sg:postcode":"78418",
    "sg:province":"TX",
    "wof:name":"South Texas Truck & Tract",
    "wof:placetype":"venue"
},
  "geometry": {"coordinates":[-97.30379000000001,27.676811],"type":"Point"}
}