{
  "type": "Feature",
  "properties": {
    "iso:country":"US",
    "sg:address":"2107 Kings Dr",
    "sg:city":"Brookston",
    "sg:classifiers":[
        {
            "category":"Banks & Credit Unions",
            "subcategory":"Financial Services",
            "type":"Services"
        }
    ],
    "sg:phone":"+1 903 785 5881",
    "sg:postcode":"75421",
    "sg:province":"TX",
    "sg:tags":[
        "trust",
        "investment",
        "real estate"
    ],
    "wof:name":"B&B Properties",
    "wof:placetype":"venue"
},
  "geometry": {"coordinates":[-95.647386,33.654937],"type":"Point"}
}