{
  "type": "Feature",
  "properties": {
    "iso:country":"US",
    "sg:address":"5005 Congressional Ct",
    "sg:city":"College Station",
    "sg:classifiers":[
        {
            "category":"Personal",
            "subcategory":"Beauty Salon",
            "type":"Services"
        }
    ],
    "sg:phone":"+1 979 690 7421",
    "sg:postcode":"77845",
    "sg:province":"TX",
    "sg:tags":[
        "shop"
    ],
    "wof:name":"Great Cuts",
    "wof:placetype":"venue"
},
  "geometry": {"coordinates":[-96.237343,30.561359],"type":"Point"}
}