{
  "type": "Feature",
  "properties": {
    "iso:country":"US",
    "sg:address":"4420 Oleander Trl",
    "sg:city":"Mesquite",
    "sg:classifiers":[
        {
            "category":"Shopping",
            "subcategory":"Gifts & Souvenirs",
            "type":"Retail Goods"
        }
    ],
    "sg:phone":"+1 972 270 2255",
    "sg:postcode":"75150",
    "sg:province":"TX",
    "sg:tags":[
        "shop",
        "novelty"
    ],
    "wof:name":"Magnolias & Dreams",
    "wof:placetype":"venue"
},
  "geometry": {"coordinates":[-96.64118499999999,32.822054],"type":"Point"}
}