{
  "type": "Feature",
  "properties": {
    "iso:country":"US",
    "sg:address":"3763 W 6th St",
    "sg:city":"Fort Worth",
    "sg:classifiers":[
        {
            "category":"Manufacturing",
            "subcategory":"Food",
            "type":"Manufacturing & Wholesale Goods"
        }
    ],
    "sg:phone":"+1 817 735 8168",
    "sg:postcode":"76107",
    "sg:province":"TX",
    "sg:tags":[
        "brewer"
    ],
    "wof:name":"Sandidge & Lopez Inc",
    "wof:placetype":"venue"
},
  "geometry": {"coordinates":[-97.37369099999999,32.752302],"type":"Point"}
}