{
  "type": "Feature",
  "properties": {
    "iso:country":"US",
    "sg:address":"402 Arthur Dr",
    "sg:city":"Alamo",
    "sg:classifiers":[
        {
            "category":"Building & Trades",
            "subcategory":"Pest Control",
            "type":"Services"
        }
    ],
    "sg:phone":"+1 956 702 7655",
    "sg:postcode":"78516",
    "sg:province":"TX",
    "wof:name":"Bug Meister Pest Control Co",
    "wof:placetype":"venue"
},
  "geometry": {"coordinates":[-98.11054799999999,26.168045],"type":"Point"}
}