{
  "type": "Feature",
  "properties": {
    "iso:country":"US",
    "sg:address":"10404 Grassbur Rd Apt 7",
    "sg:city":"Bryan",
    "sg:classifiers":[
        {
            "category":"Building & Trades",
            "subcategory":"Construction",
            "type":"Services"
        }
    ],
    "sg:phone":"+1 979 595 6390",
    "sg:postcode":"77808",
    "sg:province":"TX",
    "sg:tags":[
        "wallcoverings-installation",
        "wallpaper",
        "painting",
        "contractor"
    ],
    "wof:name":"Alfa Omega Painting",
    "wof:placetype":"venue"
},
  "geometry": {"coordinates":[-96.212361,30.711715],"type":"Point"}
}