{
  "type": "Feature",
  "properties": {
    "iso:country":"US",
    "sg:address":"5117 April Ln",
    "sg:city":"Houston",
    "sg:classifiers":[
        {
            "category":"Building & Trades",
            "subcategory":"Construction",
            "type":"Services"
        }
    ],
    "sg:phone":"+1 713 681 9458",
    "sg:postcode":"77092",
    "sg:province":"TX",
    "sg:tags":[
        "contractor"
    ],
    "wof:name":"D C D Corp",
    "wof:placetype":"venue"
},
  "geometry": {"coordinates":[-95.471161,29.840096],"type":"Point"}
}