{
  "type": "Feature",
  "properties": {
    "iso:country":"US",
    "sg:address":"5809 Hartman Rd",
    "sg:city":"Fort Worth",
    "sg:classifiers":[
        {
            "category":"Organizations",
            "subcategory":"Religious Organization",
            "type":"Services"
        }
    ],
    "sg:phone":"+1 817 534 1779",
    "sg:postcode":"76119",
    "sg:province":"TX",
    "sg:tags":[
        "church"
    ],
    "wof:name":"True Love Missionary Baptist",
    "wof:placetype":"venue"
},
  "geometry": {"coordinates":[-97.259703,32.676531],"type":"Point"}
}