{
  "type": "Feature",
  "properties": {
    "iso:country":"US",
    "sg:address":"3826 Helmsford Dr",
    "sg:city":"Arlington",
    "sg:classifiers":[
        {
            "category":"Professional",
            "subcategory":"Management & Consulting",
            "type":"Services"
        }
    ],
    "sg:phone":"+1 817 457 7003",
    "sg:postcode":"76016",
    "sg:province":"TX",
    "wof:name":"D&D Marketing Assoc Inc",
    "wof:placetype":"venue"
},
  "geometry": {"coordinates":[-97.19631699999999,32.687894],"type":"Point"}
}