{
  "type": "Feature",
  "properties": {
    "iso:country":"US",
    "sg:address":"1600 Quincy St",
    "sg:city":"Plainview",
    "sg:classifiers":[
        {
            "category":"Shopping",
            "subcategory":"Department Store",
            "type":"Retail Goods"
        }
    ],
    "sg:phone":"+1 806 291 6877",
    "sg:postcode":"79072",
    "sg:province":"TX",
    "sg:tags":[
        "variety"
    ],
    "wof:name":"J M Variety Accessories",
    "wof:placetype":"venue"
},
  "geometry": {"coordinates":[-101.72466300000001,34.197769],"type":"Point"}
}