{
  "type": "Feature",
  "properties": {
    "iso:country":"US",
    "sg:address":"9600 Forest Ln",
    "sg:city":"Dallas",
    "sg:classifiers":[
        {
            "category":"Real Estate",
            "subcategory":"Real Estate Agent",
            "type":"Services"
        }
    ],
    "sg:phone":"+1 214 340 6163",
    "sg:postcode":"75243",
    "sg:province":"TX",
    "wof:name":"Cal West USA Inc",
    "wof:placetype":"venue"
},
  "geometry": {"coordinates":[-96.724963,32.909641],"type":"Point"}
}