{
  "type": "Feature",
  "properties": {
    "iso:country":"US",
    "sg:address":"5200 Keller Springs Rd",
    "sg:city":"Dallas",
    "sg:classifiers":[
        {
            "category":"Real Estate",
            "subcategory":"Real Estate Agent",
            "type":"Services"
        }
    ],
    "sg:phone":"+1 972 503 4497",
    "sg:postcode":"75248",
    "sg:province":"TX",
    "wof:name":"D & F Investment Co",
    "wof:placetype":"venue"
},
  "geometry": {"coordinates":[-96.814606,32.968426],"type":"Point"}
}