{
  "type": "Feature",
  "properties": {
    "iso:country":"US",
    "sg:address":"1621 E Robert St",
    "sg:city":"Fort Worth",
    "sg:classifiers":[
        {
            "category":"Retail",
            "subcategory":"Auto Repair",
            "type":"Services"
        }
    ],
    "sg:phone":"+1 817 531 7284",
    "sg:postcode":"76104",
    "sg:province":"TX",
    "sg:tags":[
        "repairing",
        "automobile"
    ],
    "wof:name":"Charles Automotive",
    "wof:placetype":"venue"
},
  "geometry": {"coordinates":[-97.30008100000001,32.715466],"type":"Point"}
}