{
  "type": "Feature",
  "properties": {
    "iso:country":"US",
    "sg:address":"8830 Storm Wood St",
    "sg:city":"Houston",
    "sg:classifiers":[
        {
            "category":"Professional",
            "type":"Services"
        }
    ],
    "sg:phone":"+1 713 937 3205",
    "sg:postcode":"77040",
    "sg:province":"TX",
    "wof:name":"Reed Services",
    "wof:placetype":"venue"
},
  "geometry": {"coordinates":[-95.530607,29.881077],"type":"Point"}
}