{
  "type": "Feature",
  "properties": {
    "iso:country":"US",
    "sg:address":"1316 Timbercreek Ct",
    "sg:city":"Allen",
    "sg:classifiers":[
        {
            "category":"Shopping",
            "type":"Retail Goods"
        }
    ],
    "sg:phone":"+1 972 727 6313",
    "sg:postcode":"75002",
    "sg:province":"TX",
    "sg:tags":[
        "merchandise"
    ],
    "wof:name":"Addington Enterprises",
    "wof:placetype":"venue"
},
  "geometry": {"coordinates":[-96.639222,33.106254],"type":"Point"}
}