{
  "type": "Feature",
  "properties": {
    "iso:country":"US",
    "sg:address":"4309 N Central Expy",
    "sg:city":"Dallas",
    "sg:classifiers":[
        {
            "category":"Building & Trades",
            "subcategory":"Construction",
            "type":"Services"
        }
    ],
    "sg:phone":"+1 214 559 0000",
    "sg:postcode":"75205",
    "sg:province":"TX",
    "sg:tags":[
        "property",
        "management"
    ],
    "wof:name":"Total Services Co",
    "wof:placetype":"venue"
},
  "geometry": {"coordinates":[-96.788145,32.818787],"type":"Point"}
}