{
  "type": "Feature",
  "properties": {
    "iso:country":"US",
    "sg:address":"202 E Broadway St",
    "sg:city":"Eden",
    "sg:classifiers":[
        {
            "category":"Autos & Motor Vehicles",
            "subcategory":"Fuel & Gas Station",
            "type":"Retail Goods"
        },
        {
            "category":"Food & Beverages",
            "subcategory":"Groceries & Convenience Stores",
            "type":"Retail Goods"
        }
    ],
    "sg:phone":"+1 325 869 8210",
    "sg:postcode":"76837",
    "sg:province":"TX",
    "wof:name":"Star Stop Food Mart",
    "wof:placetype":"venue"
},
  "geometry": {"coordinates":[-99.839935,31.216316],"type":"Point"}
}