{
  "type": "Feature",
  "properties": {
    "iso:country":"US",
    "sg:address":"1231 Safari",
    "sg:city":"San Antonio",
    "sg:classifiers":[
        {
            "category":"Building & Trades",
            "subcategory":"Construction",
            "type":"Services"
        }
    ],
    "sg:phone":"+1 210 402 1248",
    "sg:postcode":"78216",
    "sg:province":"TX",
    "sg:tags":[
        "dry wall",
        "contractor"
    ],
    "wof:name":"King & Co Inc",
    "wof:placetype":"venue"
},
  "geometry": {"coordinates":[-98.474524,29.543874],"type":"Point"}
}