{
  "type": "Feature",
  "properties": {
    "iso:country":"US",
    "sg:address":"2410 Roundabout Ln",
    "sg:city":"Round Rock",
    "sg:classifiers":[
        {
            "category":"Professional",
            "subcategory":"Management & Consulting",
            "type":"Services"
        }
    ],
    "sg:phone":"+1 512 388 7700",
    "sg:postcode":"78664",
    "sg:province":"TX",
    "sg:tags":[
        "business"
    ],
    "wof:name":"Safety Net Consulting",
    "wof:placetype":"venue"
},
  "geometry": {"coordinates":[-97.617587,30.496093],"type":"Point"}
}