{
  "type": "Feature",
  "properties": {
    "iso:country":"US",
    "sg:address":"6616 FM 1488",
    "sg:city":"Magnolia",
    "sg:classifiers":[
        {
            "category":"Professional",
            "type":"Services"
        }
    ],
    "sg:phone":"+1 936 321 9870",
    "sg:postcode":"77384",
    "sg:province":"TX",
    "sg:tags":[
        "establishment"
    ],
    "wof:name":"Krogers",
    "wof:placetype":"venue"
},
  "geometry": {"coordinates":[-95.499028,30.231552],"type":"Point"}
}