{
  "type": "Feature",
  "properties": {
    "iso:country":"US",
    "sg:address":"6600 Lyndon B Johnson Fwy",
    "sg:city":"Dallas",
    "sg:classifiers":[
        {
            "category":"Manufacturing",
            "subcategory":"Paper Products",
            "type":"Manufacturing & Wholesale Goods"
        }
    ],
    "sg:phone":"+1 972 934 6000",
    "sg:postcode":"75240",
    "sg:province":"TX",
    "wof:name":"International Paper Co",
    "wof:placetype":"venue"
},
  "geometry": {"coordinates":[-96.791141,32.924412],"type":"Point"}
}