{
  "type": "Feature",
  "properties": {
    "iso:country":"US",
    "sg:address":"10435 Circle Dr",
    "sg:city":"Austin",
    "sg:classifiers":[
        {
            "category":"Wholesale",
            "subcategory":"Farm Supplies",
            "type":"Manufacturing & Wholesale Goods"
        }
    ],
    "sg:phone":"+1 512 288 5448",
    "sg:postcode":"78736",
    "sg:province":"TX",
    "sg:tags":[
        "livestock"
    ],
    "wof:name":"Summers End",
    "wof:placetype":"venue"
},
  "geometry": {"coordinates":[-97.946172,30.233628],"type":"Point"}
}