{
  "type": "Feature",
  "properties": {
    "iso:country":"US",
    "sg:address":"4855 Fredericksburg Rd",
    "sg:city":"San Antonio",
    "sg:classifiers":[
        {
            "category":"Professional",
            "subcategory":"Accounting & Tax Preparation",
            "type":"Services"
        }
    ],
    "sg:phone":"+1 210 366 4328",
    "sg:postcode":"78229",
    "sg:province":"TX",
    "wof:name":"Sharon E Williamson CPA",
    "wof:placetype":"venue"
},
  "geometry": {"coordinates":[-98.555931,29.496642],"type":"Point"}
}