{
  "type": "Feature",
  "properties": {
    "iso:country":"US",
    "sg:address":"726 Baltic Ln",
    "sg:city":"Houston",
    "sg:classifiers":[
        {
            "category":"Professional",
            "subcategory":"Management & Consulting",
            "type":"Services"
        }
    ],
    "sg:phone":"+1 281 440 6762",
    "sg:postcode":"77090",
    "sg:province":"TX",
    "sg:tags":[
        "business"
    ],
    "wof:name":"Streidl Services Inc",
    "wof:placetype":"venue"
},
  "geometry": {"coordinates":[-95.448943,30.03089],"type":"Point"}
}