{
  "type": "Feature",
  "properties": {
    "iso:country":"US",
    "sg:address":"1425 Nettleton Dr",
    "sg:city":"Desoto",
    "sg:classifiers":[
        {
            "category":"Shopping",
            "type":"Retail Goods"
        }
    ],
    "sg:phone":"+1 972 296 6879",
    "sg:postcode":"75115",
    "sg:province":"TX",
    "sg:tags":[
        "art",
        "merchandise"
    ],
    "wof:name":"Eva Navarro Longaberger",
    "wof:placetype":"venue"
},
  "geometry": {"coordinates":[-96.89549,32.616321],"type":"Point"}
}