{
  "type": "Feature",
  "properties": {
    "iso:country":"US",
    "sg:address":"1101 Clemson Cove",
    "sg:city":"Pflugerville",
    "sg:classifiers":[
        {
            "category":"Professional",
            "subcategory":"Employment Agencies",
            "type":"Services"
        }
    ],
    "sg:phone":"+1 512 990 0747",
    "sg:postcode":"78660",
    "sg:province":"TX",
    "wof:name":"Employment Matters Consulting",
    "wof:placetype":"venue"
},
  "geometry": {"coordinates":[-97.631513,30.431669],"type":"Point"}
}