{
  "type": "Feature",
  "properties": {
    "iso:country":"US",
    "sg:address":"1808 Baird Farm Rd",
    "sg:city":"Arlington",
    "sg:classifiers":[
        {
            "category":"Food & Beverages",
            "subcategory":"Bakery",
            "type":"Retail Goods"
        }
    ],
    "sg:phone":"+1 817 548 8400",
    "sg:postcode":"76006",
    "sg:province":"TX",
    "sg:tags":[
        "product",
        "mfg"
    ],
    "wof:name":"D VS Homemade Donuts",
    "wof:placetype":"venue"
},
  "geometry": {"coordinates":[-97.085421,32.764426],"type":"Point"}
}