{
  "type": "Feature",
  "properties": {
    "iso:country":"US",
    "sg:address":"5706 Reicher Dr",
    "sg:city":"Austin",
    "sg:classifiers":[
        {
            "category":"Professional",
            "subcategory":"Business Services",
            "type":"Services"
        }
    ],
    "sg:phone":"+1 512 926 3311",
    "sg:postcode":"78723",
    "sg:province":"TX",
    "wof:name":"Business Concepts Unlimited",
    "wof:placetype":"venue"
},
  "geometry": {"coordinates":[-97.676306,30.3048],"type":"Point"}
}