{
  "type": "Feature",
  "properties": {
    "iso:country":"US",
    "sg:address":"1527 Windy Meadow Dr",
    "sg:city":"Plano",
    "sg:classifiers":[
        {
            "category":"Building & Trades",
            "subcategory":"Construction",
            "type":"Services"
        }
    ],
    "sg:phone":"+1 972 423 6018",
    "sg:postcode":"75023",
    "sg:province":"TX",
    "sg:tags":[
        "hanging",
        "contractor"
    ],
    "wof:name":"Blasdell Mark",
    "wof:placetype":"venue"
},
  "geometry": {"coordinates":[-96.721339,33.055318],"type":"Point"}
}