{
  "type": "Feature",
  "properties": {
    "iso:country":"US",
    "sg:address":"2920 San Simeon Way",
    "sg:city":"Plano",
    "sg:classifiers":[
        {
            "category":"Professional",
            "type":"Services"
        }
    ],
    "sg:phone":"+1 972 208 1325",
    "sg:postcode":"75023",
    "sg:province":"TX",
    "wof:name":"Telespace Resources Inc",
    "wof:placetype":"venue"
},
  "geometry": {"coordinates":[-96.75018300000001,33.065469],"type":"Point"}
}