{
  "type": "Feature",
  "properties": {
    "iso:country":"US",
    "sg:address":"9027 Northgate Blvd",
    "sg:city":"Austin",
    "sg:classifiers":[
        {
            "category":"Personal",
            "type":"Services"
        }
    ],
    "sg:phone":"+1 512 832 9908",
    "sg:postcode":"78758",
    "sg:province":"TX",
    "sg:tags":[
        "merchandise"
    ],
    "wof:name":"Medical Prof Massage Group",
    "wof:placetype":"venue"
},
  "geometry": {"coordinates":[-97.717341,30.368985],"type":"Point"}
}