{
  "type": "Feature",
  "properties": {
    "iso:country":"US",
    "sg:address":"4414 Concho St",
    "sg:city":"Dallas",
    "sg:classifiers":[
        {
            "category":"Recreation",
            "subcategory":"Picnic Area",
            "type":"Entertainment"
        },
        {
            "category":"Community Center",
            "type":"Public Place"
        }
    ],
    "sg:phone":"+1 214 893 1223",
    "sg:postcode":"75206",
    "sg:province":"TX",
    "sg:tags":[
        "amusement",
        "arcade"
    ],
    "wof:name":"Ask Ace",
    "wof:placetype":"venue"
},
  "geometry": {"coordinates":[-96.76445,32.840205],"type":"Point"}
}