{
  "type": "Feature",
  "properties": {
    "iso:country":"US",
    "sg:address":"7984 Night Fall Pl",
    "sg:city":"El Paso",
    "sg:classifiers":[
        {
            "category":"Banks & Credit Unions",
            "subcategory":"Investment Brokerage",
            "type":"Services"
        }
    ],
    "sg:phone":"+1 214 774 4570",
    "sg:postcode":"79932",
    "sg:province":"TX",
    "sg:tags":[
        "banker"
    ],
    "wof:name":"Logreli Group Inc",
    "wof:placetype":"venue"
},
  "geometry": {"coordinates":[-106.586198,31.878979],"type":"Point"}
}