{
  "type": "Feature",
  "properties": {
    "iso:country":"US",
    "sg:address":"2455 Briarwest Blvd",
    "sg:city":"Houston",
    "sg:classifiers":[
        {
            "category":"Professional",
            "subcategory":"Business Services",
            "type":"Services"
        }
    ],
    "sg:phone":"+1 281 556 5451",
    "sg:postcode":"77077",
    "sg:province":"TX",
    "wof:name":"James G Matujec",
    "wof:placetype":"venue"
},
  "geometry": {"coordinates":[-95.613478,29.737012],"type":"Point"}
}