{
  "type": "Feature",
  "properties": {
    "iso:country":"US",
    "sg:address":"8246 Howard Dr",
    "sg:city":"Houston",
    "sg:classifiers":[
        {
            "category":"Retail",
            "subcategory":"Portrait Studio",
            "type":"Services"
        },
        {
            "category":"Professional",
            "subcategory":"Art Services",
            "type":"Services"
        }
    ],
    "sg:phone":"+1 713 644 9803",
    "sg:postcode":"77017",
    "sg:province":"TX",
    "sg:tags":[
        "photo",
        "photography",
        "commercial",
        "photographer"
    ],
    "sg:website":"www.bejaysphotography.com",
    "wof:name":"Bejay's Photography",
    "wof:placetype":"venue"
},
  "geometry": {"coordinates":[-95.26053899999999,29.680956],"type":"Point"}
}