{
  "type": "Feature",
  "properties": {
    "iso:country":"US",
    "sg:address":"1009 N Jackson St",
    "sg:city":"Jacksonville",
    "sg:classifiers":[
        {
            "category":"Banks & Credit Unions",
            "subcategory":"Bank",
            "type":"Services"
        }
    ],
    "sg:phone":"+1 903 589 0303",
    "sg:postcode":"75766",
    "sg:province":"TX",
    "wof:name":"Southside Bank",
    "wof:placetype":"venue"
},
  "geometry": {"coordinates":[-95.27355799999999,31.979554],"type":"Point"}
}