{
  "type": "Feature",
  "properties": {
    "iso:country":"US",
    "sg:address":"1215 Piedmont Ave",
    "sg:city":"Austin",
    "sg:classifiers":[
        {
            "category":"Social Services",
            "subcategory":"Job Training",
            "type":"Services"
        }
    ],
    "sg:phone":"+1 512 323 5561",
    "sg:postcode":"78757",
    "sg:province":"TX",
    "sg:tags":[
        "sale"
    ],
    "wof:name":"Roulain, Julie Party By Julie",
    "wof:placetype":"venue"
},
  "geometry": {"coordinates":[-97.722317,30.341715],"type":"Point"}
}