{
  "type": "Feature",
  "properties": {
    "iso:country":"US",
    "sg:address":"2901 Barton Skwy Apt 2905",
    "sg:city":"Austin",
    "sg:classifiers":[
        {
            "category":"Health Services",
            "subcategory":"Health Practitioner",
            "type":"Services"
        }
    ],
    "sg:phone":"+1 512 695 4578",
    "sg:postcode":"78746",
    "sg:province":"TX",
    "sg:tags":[
        "nutritionist"
    ],
    "wof:name":"Alive And Well Nutrition Club",
    "wof:placetype":"venue"
},
  "geometry": {"coordinates":[-97.78865999999999,30.259383],"type":"Point"}
}