{
  "type": "Feature",
  "properties": {
    "iso:country":"US",
    "sg:address":"2211 Santa Rita St",
    "sg:city":"Austin",
    "sg:classifiers":[
        {
            "category":"Building & Trades",
            "subcategory":"Cleaning & Sanitation",
            "type":"Services"
        },
        {
            "category":"Building & Trades",
            "subcategory":"Construction",
            "type":"Services"
        }
    ],
    "sg:phone":"+1 512 552 0281",
    "sg:postcode":"78702",
    "sg:province":"TX",
    "sg:tags":[
        "home",
        "painter",
        "contractor"
    ],
    "sg:website":"www.austinqualityfencestaining.com",
    "wof:name":"Austin Quality Fence Staining",
    "wof:placetype":"venue"
},
  "geometry": {"coordinates":[-97.719122,30.257388],"type":"Point"}
}