{
  "type": "Feature",
  "properties": {
    "iso:country":"US",
    "sg:address":"3130 Hilltop Dr",
    "sg:city":"Southlake",
    "sg:classifiers":[
        {
            "category":"Home & Garden",
            "subcategory":"Furniture",
            "type":"Retail Goods"
        }
    ],
    "sg:phone":"+1 817 481 1107",
    "sg:postcode":"76092",
    "sg:province":"TX",
    "sg:tags":[
        "store"
    ],
    "wof:name":"Chaplin Otis",
    "wof:placetype":"venue"
},
  "geometry": {"coordinates":[-97.149788,32.985268],"type":"Point"}
}