{
  "type": "Feature",
  "properties": {
    "iso:country":"US",
    "sg:address":"8051 LBJ Fwy",
    "sg:city":"Dallas",
    "sg:classifiers":[
        {
            "category":"Travel",
            "subcategory":"Hotels & Motels",
            "type":"Entertainment"
        }
    ],
    "sg:phone":"+1 972 680 3000",
    "sg:postcode":"75251",
    "sg:province":"TX",
    "sg:website":"www.bestwestern.com",
    "wof:name":"Best Western Dallas Hotel and Conference Center",
    "wof:placetype":"venue"
},
  "geometry": {"coordinates":[-96.767528,32.924887],"type":"Point"}
}