{
  "type": "Feature",
  "properties": {
    "iso:country":"US",
    "sg:address":"100 S Main St",
    "sg:city":"Shamrock",
    "sg:classifiers":[
        {
            "category":"Restaurant",
            "type":"Food & Drink"
        }
    ],
    "sg:phone":"+1 806 256 1828",
    "sg:postcode":"79079",
    "sg:province":"TX",
    "sg:tags":[
        "used",
        "eating",
        "merchandise"
    ],
    "wof:name":"Olde Station Antiques",
    "wof:placetype":"venue"
},
  "geometry": {"coordinates":[-100.249139,35.214148],"type":"Point"}
}