{
  "type": "Feature",
  "properties": {
    "iso:country":"US",
    "sg:address":"101 Redd Rd",
    "sg:city":"Sulphur Springs",
    "sg:classifiers":[
        {
            "category":"Shopping",
            "subcategory":"Clothing, Apparel, & Fashions",
            "type":"Retail Goods"
        }
    ],
    "sg:phone":"+1 903 438 0320",
    "sg:postcode":"75459",
    "sg:province":"TX",
    "wof:name":"Say I Just Do",
    "wof:placetype":"venue"
},
  "geometry": {"coordinates":[-96.539609,33.515279],"type":"Point"}
}