{
  "type": "Feature",
  "properties": {
    "iso:country":"US",
    "sg:address":"104 Munford St",
    "sg:city":"Houston",
    "sg:classifiers":[
        {
            "category":"Health Services",
            "subcategory":"Doctor",
            "type":"Services"
        }
    ],
    "sg:phone":"+1 713 442 7300",
    "sg:postcode":"77008",
    "sg:province":"TX",
    "sg:tags":[
        "medical"
    ],
    "wof:name":"Cathy Women Center Clinic",
    "wof:placetype":"venue"
},
  "geometry": {"coordinates":[-95.397532,29.808301],"type":"Point"}
}