{
  "type": "Feature",
  "properties": {
    "iso:country":"US",
    "sg:address":"301 S Carpenter St",
    "sg:city":"Mart",
    "sg:classifiers":[
        {
            "category":"Building & Trades",
            "subcategory":"Electrical",
            "type":"Services"
        }
    ],
    "sg:phone":"+1 254 876 2339",
    "sg:postcode":"76664",
    "sg:province":"TX",
    "sg:tags":[
        "electrical",
        "contractor"
    ],
    "wof:name":"McCullough Electric",
    "wof:placetype":"venue"
},
  "geometry": {"coordinates":[-96.826995,31.542513],"type":"Point"}
}