{
  "type": "Feature",
  "properties": {
    "iso:country":"US",
    "sg:address":"1015 22nd St",
    "sg:city":"Galveston",
    "sg:classifiers":[
        {
            "category":"Shopping",
            "subcategory":"Used Merchandise",
            "type":"Retail Goods"
        }
    ],
    "sg:phone":"+1 409 765 6407",
    "sg:postcode":"77550",
    "sg:province":"TX",
    "wof:name":"Saint Vincent De Paul Society",
    "wof:placetype":"venue"
},
  "geometry": {"coordinates":[-94.790751,29.299954],"type":"Point"}
}