{
  "type": "Feature",
  "properties": {
    "iso:country":"US",
    "sg:address":"1600 10th St",
    "sg:city":"Plano",
    "sg:classifiers":[
        {
            "category":"Building & Trades",
            "subcategory":"Equipment Rental",
            "type":"Services"
        }
    ],
    "sg:phone":"+1 972 234 2422",
    "sg:postcode":"75074",
    "sg:province":"TX",
    "wof:name":"Rentelco",
    "wof:placetype":"venue"
},
  "geometry": {"coordinates":[-96.68486300000001,33.012993],"type":"Point"}
}