{
  "type": "Feature",
  "properties": {
    "iso:country":"US",
    "sg:address":"121 Brazosport Blvd N",
    "sg:city":"Clute",
    "sg:classifiers":[
        {
            "category":"Shopping",
            "subcategory":"Computers & Home Electronics",
            "type":"Retail Goods"
        }
    ],
    "sg:phone":"+1 979 265 1588",
    "sg:postcode":"77531",
    "sg:province":"TX",
    "sg:tags":[
        "game",
        "video"
    ],
    "wof:name":"Jokers Wild Game Room",
    "wof:placetype":"venue"
},
  "geometry": {"coordinates":[-95.396258,29.026651],"type":"Point"}
}