{
  "type": "Feature",
  "properties": {
    "iso:country":"US",
    "sg:address":"330 Phelps Dr",
    "sg:city":"Irving",
    "sg:classifiers":[
        {
            "category":"Autos & Motor Vehicles",
            "subcategory":"Auto Supplies",
            "type":"Retail Goods"
        }
    ],
    "sg:phone":"+1 972 717 3488",
    "sg:postcode":"75038",
    "sg:province":"TX",
    "sg:tags":[
        "glass"
    ],
    "wof:name":"Guaranteed Auto Glass The",
    "wof:placetype":"venue"
},
  "geometry": {"coordinates":[-96.948697,32.868686],"type":"Point"}
}