{
  "type": "Feature",
  "properties": {
    "iso:country":"US",
    "sg:address":"705 N Washington Ave",
    "sg:city":"Livingston",
    "sg:classifiers":[
        {
            "category":"Restaurant",
            "type":"Food & Drink"
        }
    ],
    "sg:phone":"+1 936 327 5650",
    "sg:postcode":"77351",
    "sg:province":"TX",
    "sg:tags":[
        "eating"
    ],
    "wof:name":"Cassity's Cafe",
    "wof:placetype":"venue"
},
  "geometry": {"coordinates":[-94.933111,30.714227],"type":"Point"}
}