{
  "type": "Feature",
  "properties": {
    "iso:country":"US",
    "sg:address":"2720 N Belt Line Rd",
    "sg:city":"Irving",
    "sg:classifiers":[
        {
            "category":"Autos & Motor Vehicles",
            "subcategory":"Auto Supplies",
            "type":"Retail Goods"
        }
    ],
    "sg:phone":"+1 972 252 8465",
    "sg:postcode":"75062",
    "sg:province":"TX",
    "sg:tags":[
        "repair",
        "general"
    ],
    "wof:name":"Goodyear",
    "wof:placetype":"venue"
},
  "geometry": {"coordinates":[-96.992272,32.844577],"type":"Point"}
}