{
  "type": "Feature",
  "properties": {
    "iso:country":"US",
    "sg:address":"726 N Great Southwest Pkwy",
    "sg:city":"Arlington",
    "sg:classifiers":[
        {
            "category":"Professional",
            "subcategory":"Business Services",
            "type":"Services"
        },
        {
            "category":"Manufacturing",
            "subcategory":"Motor Vehicles & Parts",
            "type":"Manufacturing & Wholesale Goods"
        }
    ],
    "sg:phone":"+1 817 695 7788",
    "sg:postcode":"76011",
    "sg:province":"TX",
    "sg:tags":[
        "mfg",
        "embroidery",
        "trimming"
    ],
    "wof:name":"K & B Productions",
    "wof:placetype":"venue"
},
  "geometry": {"coordinates":[-97.045796,32.753213],"type":"Point"}
}