{
  "type": "Feature",
  "properties": {
    "iso:country":"US",
    "sg:address":"262 Cline Rd",
    "sg:city":"Waco",
    "sg:classifiers":[
        {
            "category":"Professional",
            "subcategory":"Business Services",
            "type":"Services"
        }
    ],
    "sg:phone":"+1 254 662 6173",
    "sg:postcode":"76706",
    "sg:province":"TX",
    "wof:name":"Kf Enterprise",
    "wof:placetype":"venue"
},
  "geometry": {"coordinates":[-97.106977,31.459608],"type":"Point"}
}