{
  "type": "Feature",
  "properties": {
    "iso:country":"US",
    "sg:address":"4106 Sea Meadow Ct",
    "sg:city":"Katy",
    "sg:classifiers":[
        {
            "category":"Building & Trades",
            "subcategory":"Electrical",
            "type":"Services"
        }
    ],
    "sg:phone":"+1 281 856 7933",
    "sg:postcode":"77449",
    "sg:province":"TX",
    "sg:tags":[
        "electrical",
        "contractor"
    ],
    "wof:name":"Mlcak Electric Inc",
    "wof:placetype":"venue"
},
  "geometry": {"coordinates":[-95.706,29.832711],"type":"Point"}
}