{
  "type": "Feature",
  "properties": {
    "iso:country":"US",
    "sg:address":"4906 Fairmont Pkwy",
    "sg:city":"Pasadena",
    "sg:classifiers":[
        {
            "category":"Health Services",
            "subcategory":"Optometrist",
            "type":"Services"
        }
    ],
    "sg:phone":"+1 713 946 2020",
    "sg:postcode":"77505",
    "sg:province":"TX",
    "wof:name":"Marvin L Baza Jr OD",
    "wof:placetype":"venue"
},
  "geometry": {"coordinates":[-95.16754400000001,29.649479],"type":"Point"}
}