{
  "type": "Feature",
  "properties": {
    "iso:country":"US",
    "sg:address":"536 Herring Ave",
    "sg:city":"Waco",
    "sg:classifiers":[
        {
            "category":"Arts & Performance",
            "subcategory":"Theater",
            "type":"Entertainment"
        }
    ],
    "sg:phone":"+1 254 754 3955",
    "sg:postcode":"76708",
    "sg:province":"TX",
    "sg:tags":[
        "group"
    ],
    "wof:name":"Marcus Howze",
    "wof:placetype":"venue"
},
  "geometry": {"coordinates":[-97.15136099999999,31.570841],"type":"Point"}
}