{
  "type": "Feature",
  "properties": {
    "iso:country":"US",
    "sg:address":"13500 Midway Rd",
    "sg:city":"Dallas",
    "sg:classifiers":[
        {
            "category":"Home & Garden",
            "subcategory":"Furniture",
            "type":"Retail Goods"
        }
    ],
    "sg:phone":"+1 972 239 9221",
    "sg:postcode":"75244",
    "sg:province":"TX",
    "sg:tags":[
        "store"
    ],
    "wof:name":"Opus Contemporary Furniture",
    "wof:placetype":"venue"
},
  "geometry": {"coordinates":[-96.83871600000001,32.932057],"type":"Point"}
}