{
  "type": "Feature",
  "properties": {
    "iso:country":"US",
    "sg:address":"408 Fairview St",
    "sg:city":"Garland",
    "sg:classifiers":[
        {
            "category":"Organizations",
            "subcategory":"Religious Organization",
            "type":"Services"
        }
    ],
    "sg:phone":"+1 972 272 3725",
    "sg:postcode":"75040",
    "sg:province":"TX",
    "wof:name":"House Of God Church",
    "wof:placetype":"venue"
},
  "geometry": {"coordinates":[-96.63431,32.904106],"type":"Point"}
}