{
  "type": "Feature",
  "properties": {
    "iso:country":"US",
    "sg:address":"1300 Guadalupe St",
    "sg:city":"Austin",
    "sg:classifiers":[
        {
            "category":"Professional",
            "subcategory":"Employment Agencies",
            "type":"Services"
        },
        {
            "category":"Organizations",
            "subcategory":"Professional Association",
            "type":"Services"
        }
    ],
    "sg:phone":"+1 512 477 4431",
    "sg:postcode":"78701",
    "sg:province":"TX",
    "sg:tags":[
        "employer"
    ],
    "wof:name":"Consumers Union Southwest Regional Office",
    "wof:placetype":"venue"
},
  "geometry": {"coordinates":[-97.743729,30.276011],"type":"Point"}
}