{
  "type": "Feature",
  "properties": {
    "iso:country":"US",
    "sg:address":"2929 Briarpark Dr",
    "sg:city":"Houston",
    "sg:classifiers":[
        {
            "category":"Real Estate",
            "subcategory":"Real Estate Operator",
            "type":"Services"
        }
    ],
    "sg:phone":"+1 713 621 8000",
    "sg:postcode":"77042",
    "sg:province":"TX",
    "sg:tags":[
        "owner",
        "property",
        "commercial"
    ],
    "wof:name":"Reifpark Corp",
    "wof:placetype":"venue"
},
  "geometry": {"coordinates":[-95.54899,29.733633],"type":"Point"}
}