{
  "type": "Feature",
  "properties": {
    "iso:country":"US",
    "sg:address":"448 Co Rd 310",
    "sg:city":"Port Lavaca",
    "sg:classifiers":[
        {
            "category":"Manufacturing",
            "subcategory":"Tools & Machinery",
            "type":"Manufacturing & Wholesale Goods"
        }
    ],
    "sg:phone":"+1 361 987 2275",
    "sg:postcode":"77979",
    "sg:province":"TX",
    "sg:tags":[
        "terminal",
        "computer",
        "mfg"
    ],
    "wof:name":"Dixie Computers",
    "wof:placetype":"venue"
},
  "geometry": {"coordinates":[-96.4609,28.682295],"type":"Point"}
}