{
  "type": "Feature",
  "properties": {
    "iso:country":"US",
    "sg:address":"8 Chisholm Trl",
    "sg:city":"Round Rock",
    "sg:classifiers":[
        {
            "category":"Professional",
            "subcategory":"Lawyer & Legal Services",
            "type":"Services"
        }
    ],
    "sg:phone":"+1 512 407 8228",
    "sg:postcode":"78681",
    "sg:province":"TX",
    "sg:tags":[
        "attorney"
    ],
    "wof:name":"Jennifer Scates",
    "wof:placetype":"venue"
},
  "geometry": {"coordinates":[-97.68976499999999,30.514982],"type":"Point"}
}