{
  "type": "Feature",
  "properties": {
    "iso:country":"US",
    "sg:address":"1795 N Zaragoza Rd",
    "sg:city":"El Paso",
    "sg:classifiers":[
        {
            "category":"Shopping",
            "subcategory":"Used Merchandise",
            "type":"Retail Goods"
        }
    ],
    "sg:phone":"+1 915 857 7711",
    "sg:postcode":"79936",
    "sg:province":"TX",
    "sg:tags":[
        "pawnbroker"
    ],
    "wof:name":"Benny's Pawn Shop",
    "wof:placetype":"venue"
},
  "geometry": {"coordinates":[-106.274445,31.755913],"type":"Point"}
}