{
  "type": "Feature",
  "properties": {
    "iso:country":"US",
    "sg:address":"300 S Bowser Rd",
    "sg:city":"Richardson",
    "sg:classifiers":[
        {
            "category":"Social Services",
            "subcategory":"Child Care",
            "type":"Services"
        }
    ],
    "sg:phone":"+1 972 690 8351",
    "sg:postcode":"75081",
    "sg:province":"TX",
    "sg:tags":[
        "day"
    ],
    "wof:name":"Montessori at Bowser",
    "wof:placetype":"venue"
},
  "geometry": {"coordinates":[-96.713773,32.945569],"type":"Point"}
}