{
  "type": "Feature",
  "properties": {
    "iso:country":"US",
    "sg:address":"15 Corona Cir",
    "sg:city":"Odessa",
    "sg:classifiers":[
        {
            "category":"Professional",
            "subcategory":"Management & Consulting",
            "type":"Services"
        }
    ],
    "sg:phone":"+1 432 332 3723",
    "sg:postcode":"79763",
    "sg:province":"TX",
    "wof:name":"R W Interprizes",
    "wof:placetype":"venue"
},
  "geometry": {"coordinates":[-102.407318,31.858206],"type":"Point"}
}