{
  "type": "Feature",
  "properties": {
    "iso:country":"US",
    "sg:address":"3309 Dallas Pkwy",
    "sg:city":"Plano",
    "sg:classifiers":[
        {
            "category":"Restaurant",
            "type":"Food & Drink"
        }
    ],
    "sg:phone":"+1 972 378 1522",
    "sg:postcode":"75093",
    "sg:province":"TX",
    "sg:tags":[
        "eating"
    ],
    "wof:name":"Roly Poly",
    "wof:placetype":"venue"
},
  "geometry": {"coordinates":[-96.83013,33.045304],"type":"Point"}
}