{
  "type": "Feature",
  "properties": {
    "iso:country":"US",
    "sg:address":"5029 West Lovers Ln",
    "sg:city":"Dallas",
    "sg:classifiers":[
        {
            "category":"Shopping",
            "subcategory":"Antiques",
            "type":"Retail Goods"
        }
    ],
    "sg:phone":"+1 469 335 9978",
    "sg:postcode":"75209",
    "sg:province":"TX",
    "sg:website":"www.LondonMarketAntiques.com",
    "wof:name":"London Market Antiques",
    "wof:placetype":"venue"
},
  "geometry": {"coordinates":[-96.82401,32.85121],"type":"Point"}
}