{
  "type": "Feature",
  "properties": {
    "iso:country":"US",
    "sg:address":"21915 SE H K Dodgen Loop",
    "sg:city":"Temple",
    "sg:classifiers":[
        {
            "category":"Organizations",
            "subcategory":"Community Association",
            "type":"Services"
        }
    ],
    "sg:phone":"+1 254 771 0145",
    "sg:postcode":"76502",
    "sg:province":"TX",
    "sg:tags":[
        "military"
    ],
    "wof:name":"Disabled American Veterans",
    "wof:placetype":"venue"
},
  "geometry": {"coordinates":[-97.331479,31.053789],"type":"Point"}
}