{
  "type": "Feature",
  "properties": {
    "iso:country":"US",
    "sg:address":"5945 Teague Rd",
    "sg:city":"Fort Worth",
    "sg:classifiers":[
        {
            "category":"Restaurant",
            "type":"Food & Drink"
        }
    ],
    "sg:phone":"+1 817 483 6686",
    "sg:postcode":"76140",
    "sg:province":"TX",
    "sg:tags":[
        "eating"
    ],
    "wof:name":"Korean Jindo Dogs",
    "wof:placetype":"venue"
},
  "geometry": {"coordinates":[-97.224835,32.595148],"type":"Point"}
}