{
  "type": "Feature",
  "properties": {
    "iso:country":"US",
    "sg:address":"19202 Stone Oak Pkwy",
    "sg:city":"San Antonio",
    "sg:classifiers":[
        {
            "category":"Personal",
            "subcategory":"Beauty Salon",
            "type":"Services"
        }
    ],
    "sg:phone":"+1 210 404 2600",
    "sg:postcode":"78258",
    "sg:province":"TX",
    "sg:tags":[
        "shop"
    ],
    "wof:name":"Precision Kuts Inc",
    "wof:placetype":"venue"
},
  "geometry": {"coordinates":[-98.495052,29.626817],"type":"Point"}
}