{
  "type": "Feature",
  "properties": {
    "iso:country":"US",
    "sg:address":"24115 FM 1485",
    "sg:city":"New Caney",
    "sg:classifiers":[
        {
            "category":"Shopping",
            "type":"Retail Goods"
        }
    ],
    "sg:phone":"+1 281 399 3241",
    "sg:postcode":"77357",
    "sg:province":"TX",
    "sg:tags":[
        "merchandise"
    ],
    "wof:name":"Latham Fireworks",
    "wof:placetype":"venue"
},
  "geometry": {"coordinates":[-95.20065099999999,30.150284],"type":"Point"}
}