{
  "type": "Feature",
  "properties": {
    "iso:country":"US",
    "sg:address":"9301 Bissonnet St",
    "sg:city":"Houston",
    "sg:classifiers":[
        {
            "category":"Communications",
            "subcategory":"Film & Video Production",
            "type":"Services"
        }
    ],
    "sg:phone":"+1 713 981 6971",
    "sg:postcode":"77074",
    "sg:province":"TX",
    "sg:tags":[
        "motion",
        "picture"
    ],
    "wof:name":"R&R Video Productions",
    "wof:placetype":"venue"
},
  "geometry": {"coordinates":[-95.541319,29.675946],"type":"Point"}
}