{
  "type": "Feature",
  "properties": {
    "iso:country":"US",
    "sg:address":"758 Gilpin St",
    "sg:city":"Houston",
    "sg:classifiers":[
        {
            "category":"Professional",
            "subcategory":"Art Services",
            "type":"Services"
        }
    ],
    "sg:phone":"+1 713 941 8856",
    "sg:postcode":"77034",
    "sg:province":"TX",
    "sg:tags":[
        "web",
        "graphic",
        "design"
    ],
    "wof:name":"Cielo Designs",
    "wof:placetype":"venue"
},
  "geometry": {"coordinates":[-95.232045,29.642763],"type":"Point"}
}