{
  "type": "Feature",
  "properties": {
    "iso:country":"US",
    "sg:address":"2611 S Austin Ave",
    "sg:city":"Georgetown",
    "sg:classifiers":[
        {
            "category":"Home & Garden",
            "subcategory":"Building Materials",
            "type":"Retail Goods"
        }
    ],
    "sg:phone":"+1 512 863 4527",
    "sg:postcode":"78626",
    "sg:province":"TX",
    "sg:tags":[
        "house",
        "plate",
        "window",
        "construct",
        "glass"
    ],
    "wof:name":"Aaction Russell Glass & Mirror",
    "wof:placetype":"venue"
},
  "geometry": {"coordinates":[-97.680553,30.620877],"type":"Point"}
}