{
  "type": "Feature",
  "properties": {
    "iso:country":"US",
    "sg:address":"12110 Rebel Rd",
    "sg:city":"Cleveland",
    "sg:classifiers":[
        {
            "category":"Building & Trades",
            "subcategory":"Construction",
            "type":"Services"
        }
    ],
    "sg:phone":"+1 281 659 1260",
    "sg:postcode":"77327",
    "sg:province":"TX",
    "sg:tags":[
        "system",
        "contractor",
        "air conditioning"
    ],
    "wof:name":"Md Air Conditioning & Heating",
    "wof:placetype":"venue"
},
  "geometry": {"coordinates":[-95.135333,30.266505],"type":"Point"}
}