{
  "type": "Feature",
  "properties": {
    "iso:country":"US",
    "sg:address":"102 E Colonial Pkwy",
    "sg:city":"Devine",
    "sg:classifiers":[
        {
            "category":"Personal",
            "subcategory":"Beauty Salon",
            "type":"Services"
        },
        {
            "category":"Personal",
            "subcategory":"Barber",
            "type":"Services"
        }
    ],
    "sg:phone":"+1 830 663 5151",
    "sg:postcode":"78016",
    "sg:province":"TX",
    "sg:tags":[
        "hair",
        "stylist"
    ],
    "wof:name":"Hair By Gema",
    "wof:placetype":"venue"
},
  "geometry": {"coordinates":[-98.893314,29.152015],"type":"Point"}
}