{
  "type": "Feature",
  "properties": {
    "iso:country":"US",
    "sg:address":"518 N Hampton Rd",
    "sg:city":"Desoto",
    "sg:classifiers":[
        {
            "category":"Building & Trades",
            "subcategory":"Landscaping Services",
            "type":"Services"
        }
    ],
    "sg:phone":"+1 972 274 1760",
    "sg:postcode":"75115",
    "sg:province":"TX",
    "sg:tags":[
        "lawn",
        "maintenance",
        "grounds"
    ],
    "wof:name":"Stephens Lawn Svc",
    "wof:placetype":"venue"
},
  "geometry": {"coordinates":[-96.85696,32.597878],"type":"Point"}
}