{
  "type": "Feature",
  "properties": {
    "iso:country":"US",
    "sg:address":"2214 W Euless Blvd",
    "sg:city":"Euless",
    "sg:classifiers":[
        {
            "category":"Manufacturing",
            "subcategory":"Tools & Machinery",
            "type":"Manufacturing & Wholesale Goods"
        },
        {
            "category":"Utilities",
            "subcategory":"Fuel Oil & Lpg",
            "type":"Services"
        }
    ],
    "sg:phone":"+1 817 545 8677",
    "sg:postcode":"76040",
    "sg:province":"TX",
    "sg:tags":[
        "building",
        "supply",
        "boring",
        "equipment",
        "construction",
        "drilling"
    ],
    "sg:website":"http://www.vossparts.com",
    "wof:name":"Voss Parts & Supply Co Inc",
    "wof:placetype":"venue"
},
  "geometry": {"coordinates":[-97.119193,32.82193],"type":"Point"}
}