{
  "type": "Feature",
  "properties": {
    "iso:country":"US",
    "sg:address":"7498 Co Rd 215A",
    "sg:city":"Alvin",
    "sg:classifiers":[
        {
            "category":"Shopping",
            "subcategory":"Gifts & Souvenirs",
            "type":"Retail Goods"
        }
    ],
    "sg:phone":"+1 281 692 1207",
    "sg:postcode":"77511",
    "sg:province":"TX",
    "wof:name":"Gift Solution",
    "wof:placetype":"venue"
},
  "geometry": {"coordinates":[-95.309827,29.488578],"type":"Point"}
}