{
  "type": "Feature",
  "properties": {
    "iso:country":"US",
    "sg:address":"8109 Fredericksburg Rd",
    "sg:city":"San Antonio",
    "sg:classifiers":[
        {
            "category":"Professional",
            "subcategory":"Management & Consulting",
            "type":"Services"
        }
    ],
    "sg:phone":"+1 210 593 0570",
    "sg:postcode":"78229",
    "sg:province":"TX",
    "sg:tags":[
        "personnel",
        "consultant"
    ],
    "wof:name":"All About Staffing",
    "wof:placetype":"venue"
},
  "geometry": {"coordinates":[-98.572422,29.517143],"type":"Point"}
}