{
  "type": "Feature",
  "properties": {
    "iso:country":"US",
    "sg:address":"3406 Lankmore Ave",
    "sg:city":"El Paso",
    "sg:classifiers":[
        {
            "category":"Professional",
            "type":"Services"
        }
    ],
    "sg:phone":"+1 915 755 1472",
    "sg:postcode":"79904",
    "sg:province":"TX",
    "wof:name":"Joint Heirs",
    "wof:placetype":"venue"
},
  "geometry": {"coordinates":[-106.45165799999999,31.867489],"type":"Point"}
}