{
  "type": "Feature",
  "properties": {
    "iso:country":"US",
    "sg:address":"1726 W Crosby Rd",
    "sg:city":"Carrollton",
    "sg:classifiers":[
        {
            "category":"Building & Trades",
            "subcategory":"Construction",
            "type":"Services"
        }
    ],
    "sg:phone":"+1 972 242 8322",
    "sg:postcode":"75006",
    "sg:province":"TX",
    "sg:tags":[
        "contractor"
    ],
    "wof:name":"M P I",
    "wof:placetype":"venue"
},
  "geometry": {"coordinates":[-96.928566,32.941391],"type":"Point"}
}