{
  "type": "Feature",
  "properties": {
    "iso:country":"US",
    "sg:address":"6950 Sulphur Dr",
    "sg:city":"Beaumont",
    "sg:classifiers":[
        {
            "category":"Wholesale",
            "subcategory":"Petroleum",
            "type":"Manufacturing & Wholesale Goods"
        },
        {
            "category":"Utilities",
            "subcategory":"Natural Gas",
            "type":"Services"
        }
    ],
    "sg:phone":"+1 409 839 4400",
    "sg:postcode":"77705",
    "sg:province":"TX",
    "sg:tags":[
        "pipe",
        "line",
        "company"
    ],
    "wof:name":"Sabine Gas Transmission Co",
    "wof:placetype":"venue"
},
  "geometry": {"coordinates":[-94.080307,30.029622],"type":"Point"}
}