{
  "type": "Feature",
  "properties": {
    "iso:country":"US",
    "sg:address":"702 Center St",
    "sg:city":"Deer Park",
    "sg:classifiers":[
        {
            "category":"Retail",
            "subcategory":"Laundry & Dry Cleaning",
            "type":"Services"
        }
    ],
    "sg:phone":"+1 281 479 0540",
    "sg:postcode":"77536",
    "sg:province":"TX",
    "sg:tags":[
        "cleaners"
    ],
    "wof:name":"Boot Barn",
    "wof:placetype":"venue"
},
  "geometry": {"coordinates":[-95.123988,29.705772],"type":"Point"}
}