{
  "type": "Feature",
  "properties": {
    "iso:country":"US",
    "sg:address":"2901 Martin Blvd",
    "sg:city":"Wichita Falls",
    "sg:classifiers":[
        {
            "category":"Banks & Credit Unions",
            "subcategory":"Financial Services",
            "type":"Services"
        }
    ],
    "sg:phone":"+1 940 761 1519",
    "sg:postcode":"76308",
    "sg:province":"TX",
    "sg:tags":[
        "investor"
    ],
    "wof:name":"Ozier Investments LLC",
    "wof:placetype":"venue"
},
  "geometry": {"coordinates":[-98.514512,33.883893],"type":"Point"}
}