{
  "type": "Feature",
  "properties": {
    "iso:country":"US",
    "sg:address":"11600 Peters Rd",
    "sg:city":"El Paso",
    "sg:classifiers":[
        {
            "category":"Retail",
            "subcategory":"Repair Shop",
            "type":"Services"
        }
    ],
    "sg:phone":"+1 915 851 6979",
    "sg:postcode":"79927",
    "sg:province":"TX",
    "sg:tags":[
        "armature",
        "rewinding"
    ],
    "wof:name":"Electric Motor Services",
    "wof:placetype":"venue"
},
  "geometry": {"coordinates":[-106.273843,31.617167],"type":"Point"}
}