{
  "type": "Feature",
  "properties": {
    "iso:country":"US",
    "sg:address":"128 Scenic Oak Dr",
    "sg:city":"Floresville",
    "sg:classifiers":[
        {
            "category":"Government",
            "subcategory":"Office",
            "type":"Public Place"
        }
    ],
    "sg:phone":"+1 830 216 9165",
    "sg:postcode":"78114",
    "sg:province":"TX",
    "wof:name":"Lee",
    "wof:placetype":"venue"
},
  "geometry": {"coordinates":[-98.180134,29.274457],"type":"Point"}
}