{
  "type": "Feature",
  "properties": {
    "iso:country":"US",
    "sg:address":"521 Alice St",
    "sg:city":"Ranger",
    "sg:classifiers":[
        {
            "category":"Insurance",
            "subcategory":"Hazard Insurance",
            "type":"Services"
        }
    ],
    "sg:phone":"+1 254 647 3006",
    "sg:postcode":"76470",
    "sg:province":"TX",
    "wof:name":"Carmen Torres",
    "wof:placetype":"venue"
},
  "geometry": {"coordinates":[-98.686784,32.468669],"type":"Point"}
}