{
  "type": "Feature",
  "properties": {
    "iso:country":"US",
    "sg:address":"6228 Glenview Dr",
    "sg:city":"Fort Worth",
    "sg:classifiers":[
        {
            "category":"Real Estate",
            "subcategory":"Real Estate Operator",
            "type":"Services"
        }
    ],
    "sg:phone":"+1 817 656 9550",
    "sg:postcode":"76180",
    "sg:province":"TX",
    "sg:tags":[
        "apartment",
        "complex"
    ],
    "wof:name":"Waterford On The Green",
    "wof:placetype":"venue"
},
  "geometry": {"coordinates":[-97.24934500000001,32.826796],"type":"Point"}
}