{
  "type": "Feature",
  "properties": {
    "iso:country":"US",
    "sg:address":"165 S Forest Ln",
    "sg:city":"Lewisville",
    "sg:classifiers":[
        {
            "category":"Professional",
            "subcategory":"Art Services",
            "type":"Services"
        }
    ],
    "sg:phone":"+1 817 430 3210",
    "sg:postcode":"75077",
    "sg:province":"TX",
    "sg:tags":[
        "commercial",
        "design"
    ],
    "wof:name":"Caseys Creations",
    "wof:placetype":"venue"
},
  "geometry": {"coordinates":[-97.115604,33.055861],"type":"Point"}
}