{
  "type": "Feature",
  "properties": {
    "iso:country":"US",
    "sg:address":"2046 6th St",
    "sg:city":"Port Arthur",
    "sg:classifiers":[
        {
            "category":"Retail",
            "subcategory":"Repair Shop",
            "type":"Services"
        }
    ],
    "sg:phone":"+1 409 983 6174",
    "sg:postcode":"77640",
    "sg:province":"TX",
    "sg:tags":[
        "lock",
        "locksmith"
    ],
    "wof:name":"Low Price Locksmith",
    "wof:placetype":"venue"
},
  "geometry": {"coordinates":[-93.925099,29.885115],"type":"Point"}
}