{
  "type": "Feature",
  "properties": {
    "iso:country":"US",
    "sg:address":"25329 I- 45",
    "sg:city":"Spring",
    "sg:classifiers":[
        {
            "category":"Banks & Credit Unions",
            "subcategory":"Bank",
            "type":"Services"
        }
    ],
    "sg:phone":"+1 281 363 9320",
    "sg:postcode":"77380",
    "sg:province":"TX",
    "sg:tags":[
        "loan",
        "real estate"
    ],
    "wof:name":"GDR Financial Group",
    "wof:placetype":"venue"
},
  "geometry": {"coordinates":[-95.443826,30.126752],"type":"Point"}
}