{
  "type": "Feature",
  "properties": {
    "iso:country":"US",
    "sg:address":"2028 Co Rd 4720",
    "sg:city":"Leonard",
    "sg:classifiers":[
        {
            "category":"Professional",
            "subcategory":"Art Services",
            "type":"Services"
        }
    ],
    "sg:phone":"+1 903 587 3610",
    "sg:postcode":"75452",
    "sg:province":"TX",
    "sg:tags":[
        "commercial",
        "design"
    ],
    "wof:name":"James Ingram",
    "wof:placetype":"venue"
},
  "geometry": {"coordinates":[-96.245649,33.394423],"type":"Point"}
}