{
  "type": "Feature",
  "properties": {
    "iso:country":"US",
    "sg:address":"1219 Morning Mist Ct",
    "sg:city":"Sugar Land",
    "sg:classifiers":[
        {
            "category":"Building & Trades",
            "subcategory":"Construction",
            "type":"Services"
        }
    ],
    "sg:phone":"+1 281 491 4674",
    "sg:postcode":"77478",
    "sg:province":"TX",
    "sg:tags":[
        "house"
    ],
    "wof:name":"Seablue Construction Co Inc",
    "wof:placetype":"venue"
},
  "geometry": {"coordinates":[-95.635465,29.635736],"type":"Point"}
}