{
  "type": "Feature",
  "properties": {
    "iso:country":"US",
    "sg:address":"12600 Exchange Dr",
    "sg:city":"Stafford",
    "sg:classifiers":[
        {
            "category":"Utilities",
            "subcategory":"Telephone",
            "type":"Services"
        },
        {
            "category":"Professional",
            "subcategory":"Business Services",
            "type":"Services"
        }
    ],
    "sg:phone":"+1 281 265 7243",
    "sg:postcode":"77477",
    "sg:province":"TX",
    "sg:tags":[
        "telecommunication"
    ],
    "wof:name":"Mobile Telecom",
    "wof:placetype":"venue"
},
  "geometry": {"coordinates":[-95.593013,29.634148],"type":"Point"}
}