{
  "type": "Feature",
  "properties": {
    "iso:country":"US",
    "sg:address":"5900 Greens Rd",
    "sg:city":"Humble",
    "sg:classifiers":[
        {
            "category":"Government",
            "subcategory":"Office",
            "type":"Public Place"
        }
    ],
    "sg:phone":"+1 281 441 2256",
    "sg:postcode":"77396",
    "sg:province":"TX",
    "wof:name":"Credit Determination",
    "wof:placetype":"venue"
},
  "geometry": {"coordinates":[-95.294422,29.952213],"type":"Point"}
}