{
  "type": "Feature",
  "properties": {
    "iso:country":"US",
    "sg:address":"780 Gatewood Rd Apt 264",
    "sg:city":"Garland",
    "sg:classifiers":[
        {
            "category":"Real Estate",
            "subcategory":"Real Estate Services",
            "type":"Services"
        }
    ],
    "sg:phone":"+1 972 693 3956",
    "sg:postcode":"75043",
    "sg:province":"TX",
    "sg:tags":[
        "buyer",
        "broker"
    ],
    "wof:name":"Tammie Codwell",
    "wof:placetype":"venue"
},
  "geometry": {"coordinates":[-96.602762,32.862175],"type":"Point"}
}