{
  "type": "Feature",
  "properties": {
    "iso:country":"US",
    "sg:address":"3509 S Co Rd 1210",
    "sg:city":"Midland",
    "sg:classifiers":[
        {
            "category":"Manufacturing",
            "subcategory":"Tools & Machinery",
            "type":"Manufacturing & Wholesale Goods"
        }
    ],
    "sg:phone":"+1 432 520 5431",
    "sg:postcode":"79706",
    "sg:province":"TX",
    "sg:tags":[
        "machine",
        "shop"
    ],
    "wof:name":"Texas Machine & Fabrication",
    "wof:placetype":"venue"
},
  "geometry": {"coordinates":[-102.10144200000001,31.946928],"type":"Point"}
}