{
  "type": "Feature",
  "properties": {
    "iso:country":"US",
    "sg:address":"600 N Shepherd Dr",
    "sg:city":"Houston",
    "sg:classifiers":[
        {
            "category":"Professional",
            "subcategory":"Business Services",
            "type":"Services"
        }
    ],
    "sg:phone":"+1 713 861 8273",
    "sg:postcode":"77007",
    "sg:province":"TX",
    "sg:tags":[
        "delivery",
        "courier"
    ],
    "wof:name":"Freight Savers",
    "wof:placetype":"venue"
},
  "geometry": {"coordinates":[-95.408798,29.7813],"type":"Point"}
}