{
  "type": "Feature",
  "properties": {
    "iso:country":"US",
    "sg:address":"608 Florence St",
    "sg:city":"Kerrville",
    "sg:classifiers":[
        {
            "category":"Professional",
            "subcategory":"Management & Consulting",
            "type":"Services"
        }
    ],
    "sg:phone":"+1 830 896 6345",
    "sg:postcode":"78028",
    "sg:province":"TX",
    "sg:tags":[
        "computer",
        "related"
    ],
    "wof:name":"Benjamin Bolin Consultant",
    "wof:placetype":"venue"
},
  "geometry": {"coordinates":[-99.157524,30.057889],"type":"Point"}
}