{
  "type": "Feature",
  "properties": {
    "iso:country":"US",
    "sg:address":"1111 Fannin St",
    "sg:city":"Houston",
    "sg:classifiers":[
        {
            "category":"Professional",
            "subcategory":"Employment Agencies",
            "type":"Services"
        }
    ],
    "sg:phone":"+1 713 571 8565",
    "sg:postcode":"77002",
    "sg:province":"TX",
    "wof:name":"Randstad",
    "wof:placetype":"venue"
},
  "geometry": {"coordinates":[-95.3647,29.7556],"type":"Point"}
}