{
  "type": "Feature",
  "properties": {
    "iso:country":"US",
    "sg:address":"426 Haney St",
    "sg:city":"Spearman",
    "sg:phone":"+1 806 659 3508",
    "sg:postcode":"79081",
    "sg:province":"TX",
    "sg:tags":[
        "farm",
        "corn",
        "wheat"
    ],
    "wof:name":"Craig Schumann",
    "wof:placetype":"venue"
},
  "geometry": {"coordinates":[-101.193399,36.193745],"type":"Point"}
}