{
  "type": "Feature",
  "properties": {
    "iso:country":"US",
    "sg:address":"1421 Northpark Dr",
    "sg:city":"Humble",
    "sg:classifiers":[
        {
            "category":"Retail",
            "subcategory":"Car Wash",
            "type":"Services"
        }
    ],
    "sg:phone":"+1 281 354 2399",
    "sg:postcode":"77339",
    "sg:province":"TX",
    "sg:tags":[
        "carwash",
        "automobile",
        "used"
    ],
    "wof:name":"Tommy Toms",
    "wof:placetype":"venue"
},
  "geometry": {"coordinates":[-95.232873,30.068683],"type":"Point"}
}