{
  "type": "Feature",
  "properties": {
    "iso:country":"US",
    "sg:address":"9818 Fitzroy Dr",
    "sg:city":"Dallas",
    "sg:classifiers":[
        {
            "category":"Health Services",
            "subcategory":"Health Practitioner",
            "type":"Services"
        }
    ],
    "sg:phone":"+1 214 343 5742",
    "sg:postcode":"75238",
    "sg:province":"TX",
    "wof:name":"Bogan Audio Visual",
    "wof:placetype":"venue"
},
  "geometry": {"coordinates":[-96.716447,32.865939],"type":"Point"}
}