{
  "type": "Feature",
  "properties": {
    "iso:country":"US",
    "sg:address":"1720 Lake Woodlands Dr",
    "sg:city":"Spring",
    "sg:classifiers":[
        {
            "category":"Restaurant",
            "type":"Food & Drink"
        }
    ],
    "sg:phone":"+1 281 292 0061",
    "sg:postcode":"77380",
    "sg:province":"TX",
    "sg:tags":[
        "japanese"
    ],
    "wof:name":"Benihana Restaurant",
    "wof:placetype":"venue"
},
  "geometry": {"coordinates":[-95.45904400000001,30.167179],"type":"Point"}
}