{
  "type": "Feature",
  "properties": {
    "iso:country":"US",
    "sg:address":"108 E West St",
    "sg:city":"Livingston",
    "sg:classifiers":[
        {
            "category":"Organizations",
            "subcategory":"Religious Organization",
            "type":"Services"
        }
    ],
    "sg:phone":"+1 936 327 5308",
    "sg:postcode":"77351",
    "sg:province":"TX",
    "wof:name":"Anderson Baptist Chapel Church",
    "wof:placetype":"venue"
},
  "geometry": {"coordinates":[-94.932985,30.720889],"type":"Point"}
}