{
  "type": "Feature",
  "properties": {
    "iso:country":"US",
    "sg:address":"6746 Forest Hill Dr",
    "sg:city":"Fort Worth",
    "sg:classifiers":[
        {
            "category":"Retail",
            "subcategory":"Laundry & Dry Cleaning",
            "type":"Services"
        }
    ],
    "sg:phone":"+1 817 551 6131",
    "sg:postcode":"76119",
    "sg:province":"TX",
    "sg:tags":[
        "drycleaning",
        "plant"
    ],
    "wof:name":"Macy Cleaners",
    "wof:placetype":"venue"
},
  "geometry": {"coordinates":[-97.269975,32.657254],"type":"Point"}
}