{
  "type": "Feature",
  "properties": {
    "iso:country":"US",
    "sg:address":"2311 Williams Trace Blvd",
    "sg:city":"Sugar Land",
    "sg:classifiers":[
        {
            "category":"Shopping",
            "type":"Retail Goods"
        }
    ],
    "sg:phone":"+1 281 242 0088",
    "sg:postcode":"77478",
    "sg:province":"TX",
    "sg:tags":[
        "cosmetic",
        "perfume"
    ],
    "wof:name":"Beauty Essentials",
    "wof:placetype":"venue"
},
  "geometry": {"coordinates":[-95.60422699999999,29.59317],"type":"Point"}
}