{
  "type": "Feature",
  "properties": {
    "iso:country":"US",
    "sg:address":"949 Plum St",
    "sg:city":"Abilene",
    "sg:classifiers":[
        {
            "category":"Education",
            "subcategory":"School",
            "type":"Public Place"
        }
    ],
    "sg:phone":"+1 325 671 4613",
    "sg:postcode":"79601",
    "sg:province":"TX",
    "wof:name":"Abilene Headstart",
    "wof:placetype":"venue"
},
  "geometry": {"coordinates":[-99.728086,32.4597],"type":"Point"}
}