{
  "type": "Feature",
  "properties": {
    "iso:country":"US",
    "sg:address":"815 S Main St",
    "sg:city":"Duncanville",
    "sg:classifiers":[
        {
            "category":"Shopping",
            "type":"Retail Goods"
        },
        {
            "category":"Recreation",
            "type":"Entertainment"
        }
    ],
    "sg:phone":"+1 972 296 6565",
    "sg:postcode":"75137",
    "sg:province":"TX",
    "sg:tags":[
        "picture",
        "farm",
        "frame",
        "mi",
        "crop",
        "general"
    ],
    "wof:name":"Art & Frames",
    "wof:placetype":"venue"
},
  "geometry": {"coordinates":[-96.908494,32.643933],"type":"Point"}
}