{
  "type": "Feature",
  "properties": {
    "iso:country":"US",
    "sg:address":"411 Coronado St",
    "sg:city":"Houston",
    "sg:classifiers":[
        {
            "category":"Government",
            "subcategory":"Fire Station",
            "type":"Public Place"
        }
    ],
    "sg:phone":"+1 254 442 2111",
    "sg:postcode":"77009",
    "sg:province":"TX",
    "sg:tags":[
        "department"
    ],
    "wof:name":"Fire Department",
    "wof:placetype":"venue"
},
  "geometry": {"coordinates":[-95.371287,29.799962],"type":"Point"}
}