{
  "type": "Feature",
  "properties": {
    "iso:country":"US",
    "sg:address":"6511 88th St",
    "sg:city":"Lubbock",
    "sg:classifiers":[
        {
            "category":"Retail",
            "subcategory":"Auto Repair",
            "type":"Services"
        }
    ],
    "sg:phone":"+1 806 798 3314",
    "sg:postcode":"79424",
    "sg:province":"TX",
    "sg:tags":[
        "body",
        "painting",
        "repairing",
        "automobile"
    ],
    "wof:name":"Cnd Body Works",
    "wof:placetype":"venue"
},
  "geometry": {"coordinates":[-101.95829500000001,33.514061],"type":"Point"}
}