{
  "type": "Feature",
  "properties": {
    "iso:country":"US",
    "sg:address":"610 Lanark Dr",
    "sg:city":"San Antonio",
    "sg:classifiers":[
        {
            "category":"Building & Trades",
            "subcategory":"Construction",
            "type":"Services"
        }
    ],
    "sg:phone":"+1 210 590 6442",
    "sg:postcode":"78218",
    "sg:province":"TX",
    "sg:tags":[
        "window",
        "replacement"
    ],
    "wof:name":"Cameron Ashley Building Prods",
    "wof:placetype":"venue"
},
  "geometry": {"coordinates":[-98.401652,29.503214],"type":"Point"}
}