{
  "type": "Feature",
  "properties": {
    "iso:country":"US",
    "sg:address":"3701 Country Vista Dr",
    "sg:city":"Burleson",
    "sg:classifiers":[
        {
            "category":"Real Estate",
            "subcategory":"Real Estate Operator",
            "type":"Services"
        }
    ],
    "sg:phone":"+1 817 261 9557",
    "sg:postcode":"76028",
    "sg:province":"TX",
    "sg:tags":[
        "building",
        "apartment"
    ],
    "wof:name":"Oxford Apartments",
    "wof:placetype":"venue"
},
  "geometry": {"coordinates":[-97.257671,32.548739],"type":"Point"}
}