{
  "type": "Feature",
  "properties": {
    "iso:country":"US",
    "sg:address":"2505 Turtle Creek Blvd",
    "sg:city":"Dallas",
    "sg:classifiers":[
        {
            "category":"Real Estate",
            "subcategory":"Architect",
            "type":"Services"
        }
    ],
    "sg:phone":"+1 214 521 8500",
    "sg:postcode":"75219",
    "sg:province":"TX",
    "sg:website":"www.bensonhlavaty.com",
    "wof:name":"Bha Architects",
    "wof:placetype":"venue"
},
  "geometry": {"coordinates":[-96.807922,32.802661],"type":"Point"}
}