{
  "type": "Feature",
  "properties": {
    "iso:country":"US",
    "sg:address":"2112 S Hughes St",
    "sg:city":"Amarillo",
    "sg:classifiers":[
        {
            "category":"Shopping",
            "subcategory":"Books",
            "type":"Retail Goods"
        }
    ],
    "sg:phone":"+1 806 342 4834",
    "sg:postcode":"79109",
    "sg:province":"TX",
    "wof:name":"Book Protector",
    "wof:placetype":"venue"
},
  "geometry": {"coordinates":[-101.849794,35.189435],"type":"Point"}
}