{
  "type": "Feature",
  "properties": {
    "iso:country":"US",
    "sg:address":"6203 Pokealong Path",
    "sg:city":"Leander",
    "sg:classifiers":[
        {
            "category":"Manufacturing",
            "subcategory":"Paper Products",
            "type":"Manufacturing & Wholesale Goods"
        }
    ],
    "sg:phone":"+1 512 267 4243",
    "sg:postcode":"78645",
    "sg:province":"TX",
    "sg:tags":[
        "mill"
    ],
    "wof:name":"Burns & Haley Inc",
    "wof:placetype":"venue"
},
  "geometry": {"coordinates":[-97.981906,30.454735],"type":"Point"}
}