{
  "type": "Feature",
  "properties": {
    "iso:country":"US",
    "sg:address":"701 S Sylvania Ave",
    "sg:city":"Fort Worth",
    "sg:classifiers":[
        {
            "category":"Professional",
            "subcategory":"Art Services",
            "type":"Services"
        }
    ],
    "sg:phone":"+1 817 237 4801",
    "sg:postcode":"76111",
    "sg:province":"TX",
    "sg:tags":[
        "graphic"
    ],
    "wof:name":"Zebra Graphics",
    "wof:placetype":"venue"
},
  "geometry": {"coordinates":[-97.308984,32.758519],"type":"Point"}
}