{
  "type": "Feature",
  "properties": {
    "iso:country":"US",
    "sg:address":"10211 Sam-Neil Ln",
    "sg:city":"Salado",
    "sg:classifiers":[
        {
            "category":"Shopping",
            "subcategory":"Hobbies, Toys, & Games",
            "type":"Retail Goods"
        }
    ],
    "sg:phone":"+1 254 947 4477",
    "sg:postcode":"76571",
    "sg:province":"TX",
    "sg:tags":[
        "supply"
    ],
    "wof:name":"PM Crafts",
    "wof:placetype":"venue"
},
  "geometry": {"coordinates":[-97.562876,30.979969],"type":"Point"}
}