{
  "type": "Feature",
  "properties": {
    "iso:country":"US",
    "sg:address":"2725 Green Oaks Dr",
    "sg:city":"Garland",
    "sg:classifiers":[
        {
            "category":"Building & Trades",
            "subcategory":"Construction",
            "type":"Services"
        }
    ],
    "sg:phone":"+1 972 495 8690",
    "sg:postcode":"75040",
    "sg:province":"TX",
    "sg:tags":[
        "house"
    ],
    "wof:name":"Lone Star Homes & Construction",
    "wof:placetype":"venue"
},
  "geometry": {"coordinates":[-96.641779,32.947501],"type":"Point"}
}