{
  "type": "Feature",
  "properties": {
    "iso:country":"US",
    "sg:address":"11817 Judd Ct",
    "sg:city":"Dallas",
    "sg:classifiers":[
        {
            "category":"Manufacturing",
            "subcategory":"Apparel",
            "type":"Manufacturing & Wholesale Goods"
        }
    ],
    "sg:phone":"+1 214 575 5878",
    "sg:postcode":"75243",
    "sg:province":"TX",
    "sg:tags":[
        "sewing",
        "contractor"
    ],
    "wof:name":"Gentex Design & Custom Sewing",
    "wof:placetype":"venue"
},
  "geometry": {"coordinates":[-96.743157,32.910718],"type":"Point"}
}