{
  "type": "Feature",
  "properties": {
    "iso:country":"US",
    "sg:address":"865 Sayles Blvd",
    "sg:city":"Abilene",
    "sg:classifiers":[
        {
            "category":"Professional",
            "type":"Services"
        }
    ],
    "sg:phone":"+1 325 676 3617",
    "sg:postcode":"79605",
    "sg:province":"TX",
    "wof:name":"CM Designs",
    "wof:placetype":"venue"
},
  "geometry": {"coordinates":[-99.747891,32.440118],"type":"Point"}
}