{
  "type": "Feature",
  "properties": {
    "iso:country":"US",
    "sg:address":"8899 Andrews Hwy",
    "sg:city":"Odessa",
    "sg:classifiers":[
        {
            "category":"Retail",
            "subcategory":"Repair Shop",
            "type":"Services"
        }
    ],
    "sg:phone":"+1 432 367 0513",
    "sg:postcode":"79765",
    "sg:province":"TX",
    "sg:tags":[
        "welding"
    ],
    "wof:name":"Nordman Welding",
    "wof:placetype":"venue"
},
  "geometry": {"coordinates":[-102.403975,31.940614],"type":"Point"}
}