{
  "type": "Feature",
  "properties": {
    "iso:country":"US",
    "sg:address":"1122 Meriwood Dr",
    "sg:city":"Lewisville",
    "sg:classifiers":[
        {
            "category":"Professional",
            "subcategory":"Art Services",
            "type":"Services"
        }
    ],
    "sg:phone":"+1 972 221 7572",
    "sg:postcode":"75067",
    "sg:province":"TX",
    "sg:tags":[
        "commercial",
        "design"
    ],
    "wof:name":"Grafx",
    "wof:placetype":"venue"
},
  "geometry": {"coordinates":[-97.021326,33.029691],"type":"Point"}
}