{
  "type": "Feature",
  "properties": {
    "iso:country":"US",
    "sg:address":"12769 Co Rd 1131",
    "sg:city":"Flint",
    "sg:classifiers":[
        {
            "category":"Manufacturing",
            "subcategory":"Printing",
            "type":"Manufacturing & Wholesale Goods"
        }
    ],
    "sg:phone":"+1 903 534 5859",
    "sg:postcode":"75762",
    "sg:province":"TX",
    "sg:tags":[
        "publishing"
    ],
    "wof:name":"A Plus Resources",
    "wof:placetype":"venue"
},
  "geometry": {"coordinates":[-95.43662399999999,32.296296],"type":"Point"}
}