{
  "type": "Feature",
  "properties": {
    "iso:country":"US",
    "sg:address":"901 Victoria St",
    "sg:city":"Laredo",
    "sg:classifiers":[
        {
            "category":"Professional",
            "subcategory":"Lawyer & Legal Services",
            "type":"Services"
        }
    ],
    "sg:phone":"+1 956 722 8063",
    "sg:postcode":"78040",
    "sg:province":"TX",
    "sg:tags":[
        "attorney"
    ],
    "wof:name":"Leticia L Martinez",
    "wof:placetype":"venue"
},
  "geometry": {"coordinates":[-99.50560299999999,27.507854],"type":"Point"}
}