{
  "type": "Feature",
  "properties": {
    "iso:country":"US",
    "sg:address":"4675 Oakwood Dr",
    "sg:city":"Odessa",
    "sg:classifiers":[
        {
            "category":"Real Estate",
            "subcategory":"Real Estate Operator",
            "type":"Services"
        }
    ],
    "sg:phone":"+1 432 362 0497",
    "sg:postcode":"79761",
    "sg:province":"TX",
    "sg:tags":[
        "building",
        "apartment"
    ],
    "wof:name":"Fairgreen Apartments",
    "wof:placetype":"venue"
},
  "geometry": {"coordinates":[-102.32729399999999,31.876719],"type":"Point"}
}