{
  "type": "Feature",
  "properties": {
    "iso:country":"US",
    "sg:address":"2661 Midway Rd",
    "sg:city":"Carrollton",
    "sg:classifiers":[
        {
            "category":"Restaurant",
            "type":"Food & Drink"
        }
    ],
    "sg:phone":"+1 972 250 3664",
    "sg:postcode":"75006",
    "sg:province":"TX",
    "sg:tags":[
        "eating"
    ],
    "wof:name":"Bennys Bagels",
    "wof:placetype":"venue"
},
  "geometry": {"coordinates":[-96.84227199999999,32.986274],"type":"Point"}
}