{
  "type": "Feature",
  "properties": {
    "iso:country":"US",
    "sg:address":"207 E 2nd St",
    "sg:city":"Rio Grande City",
    "sg:classifiers":[
        {
            "category":"Real Estate",
            "subcategory":"Real Estate Agent",
            "type":"Services"
        }
    ],
    "sg:phone":"+1 956 487 0381",
    "sg:postcode":"78582",
    "sg:province":"TX",
    "wof:name":"West Hill Realty Services LLC",
    "wof:placetype":"venue"
},
  "geometry": {"coordinates":[-98.819222,26.379613],"type":"Point"}
}