{
  "type": "Feature",
  "properties": {
    "iso:country":"US",
    "sg:address":"13936 Montfort Dr",
    "sg:city":"Dallas",
    "sg:classifiers":[
        {
            "category":"Retail",
            "subcategory":"Laundry & Dry Cleaning",
            "type":"Services"
        }
    ],
    "sg:phone":"+1 972 661 2198",
    "sg:postcode":"75240",
    "sg:province":"TX",
    "sg:tags":[
        "cleaner"
    ],
    "wof:name":"Johnson's Cleaners",
    "wof:placetype":"venue"
},
  "geometry": {"coordinates":[-96.813698,32.937599],"type":"Point"}
}