{
  "type": "Feature",
  "properties": {
    "iso:country":"US",
    "sg:address":"2513 Chippewa Trl",
    "sg:city":"Sanger",
    "sg:classifiers":[
        {
            "category":"Freight",
            "type":"Transportation"
        }
    ],
    "sg:phone":"+1 940 458 3704",
    "sg:postcode":"76266",
    "sg:province":"TX",
    "sg:tags":[
        "operator",
        "trucking"
    ],
    "wof:name":"Yakel Broc",
    "wof:placetype":"venue"
},
  "geometry": {"coordinates":[-97.195869,33.35983],"type":"Point"}
}