{
  "type": "Feature",
  "properties": {
    "iso:country":"US",
    "sg:address":"4835 N O Connor Rd Ste 204",
    "sg:city":"Irving",
    "sg:classifiers":[
        {
            "category":"Banks & Credit Unions",
            "subcategory":"Bank",
            "type":"Services"
        }
    ],
    "sg:phone":"+1 972 717 1516",
    "sg:postcode":"75062",
    "sg:province":"TX",
    "wof:name":"Barbara Schmidt Insurance",
    "wof:placetype":"venue"
},
  "geometry": {"coordinates":[-96.9496,32.864799],"type":"Point"}
}