{
  "type": "Feature",
  "properties": {
    "iso:country":"US",
    "sg:address":"2200 Stanolind Ave",
    "sg:city":"Midland",
    "sg:classifiers":[
        {
            "category":"Travel",
            "subcategory":"Campground",
            "type":"Entertainment"
        }
    ],
    "sg:phone":"+1 432 685 3550",
    "sg:postcode":"79705",
    "sg:province":"TX",
    "sg:tags":[
        "camp"
    ],
    "wof:name":"Five S Game Ranch",
    "wof:placetype":"venue"
},
  "geometry": {"coordinates":[-102.105514,32.014811],"type":"Point"}
}