{
  "type": "Feature",
  "properties": {
    "iso:country":"US",
    "sg:address":"2105 Waterway Bend",
    "sg:city":"Austin",
    "sg:classifiers":[
        {
            "category":"Professional",
            "subcategory":"Management & Consulting",
            "type":"Services"
        }
    ],
    "sg:phone":"+1 512 251 8578",
    "sg:postcode":"78728",
    "sg:province":"TX",
    "sg:tags":[
        "business"
    ],
    "wof:name":"Mohammad Ghanonparvar",
    "wof:placetype":"venue"
},
  "geometry": {"coordinates":[-97.678355,30.447725],"type":"Point"}
}