{
  "type": "Feature",
  "properties": {
    "iso:country":"US",
    "sg:address":"7915 Westglen Dr",
    "sg:city":"Houston",
    "sg:classifiers":[
        {
            "category":"Professional",
            "subcategory":"Engineering",
            "type":"Services"
        }
    ],
    "sg:phone":"+1 713 278 9300",
    "sg:postcode":"77063",
    "sg:province":"TX",
    "wof:name":"Wlb & Associates",
    "wof:placetype":"venue"
},
  "geometry": {"coordinates":[-95.505802,29.7247],"type":"Point"}
}