{
  "type": "Feature",
  "properties": {
    "iso:country":"US",
    "sg:address":"1815 Enclave Pkwy",
    "sg:city":"Houston",
    "sg:classifiers":[
        {
            "category":"Real Estate",
            "subcategory":"Real Estate Operator",
            "type":"Services"
        }
    ],
    "sg:phone":"+1 281 531 1905",
    "sg:postcode":"77077",
    "sg:province":"TX",
    "sg:tags":[
        "building",
        "apartment"
    ],
    "wof:name":"Tarrytowne Estates Retirement",
    "wof:placetype":"venue"
},
  "geometry": {"coordinates":[-95.618736,29.750569],"type":"Point"}
}