{
  "type": "Feature",
  "properties": {
    "iso:country":"US",
    "sg:address":"9540 Loma Vista Dr",
    "sg:city":"Dallas",
    "sg:classifiers":[
        {
            "category":"Restaurant",
            "type":"Food & Drink"
        }
    ],
    "sg:phone":"+1 214 221 8152",
    "sg:postcode":"75243",
    "sg:province":"TX",
    "sg:tags":[
        "eating"
    ],
    "wof:name":"T Tates World Famous",
    "wof:placetype":"venue"
},
  "geometry": {"coordinates":[-96.737212,32.896786],"type":"Point"}
}