{
  "type": "Feature",
  "properties": {
    "iso:country":"US",
    "sg:address":"5720 Glenmont Dr",
    "sg:city":"Houston",
    "sg:classifiers":[
        {
            "category":"Building & Trades",
            "subcategory":"Cleaning & Sanitation",
            "type":"Services"
        }
    ],
    "sg:phone":"+1 713 668 6913",
    "sg:postcode":"77081",
    "sg:province":"TX",
    "sg:tags":[
        "maintenance"
    ],
    "wof:name":"Polos Maintenance",
    "wof:placetype":"venue"
},
  "geometry": {"coordinates":[-95.481562,29.720177],"type":"Point"}
}