{
  "type": "Feature",
  "properties": {
    "iso:country":"US",
    "sg:address":"26901 W Brooks Rd",
    "sg:city":"Waller",
    "sg:classifiers":[
        {
            "category":"Farming",
            "subcategory":"Livestock Farm",
            "type":"Manufacturing & Wholesale Goods"
        },
        {
            "category":"Arena",
            "subcategory":"Horse Racetrack",
            "type":"Entertainment"
        }
    ],
    "sg:phone":"+1 281 924 6579",
    "sg:postcode":"77484",
    "sg:province":"TX",
    "sg:tags":[
        "breeder"
    ],
    "wof:name":"Britannia Farms",
    "wof:placetype":"venue"
},
  "geometry": {"coordinates":[-95.90256599999999,30.214185],"type":"Point"}
}