{
  "type": "Feature",
  "properties": {
    "iso:country":"US",
    "sg:address":"20715 Youpon Ln",
    "sg:city":"Porter",
    "sg:classifiers":[
        {
            "category":"Professional",
            "subcategory":"Management & Consulting",
            "type":"Services"
        }
    ],
    "sg:phone":"+1 281 572 4778",
    "sg:postcode":"77365",
    "sg:province":"TX",
    "wof:name":"Prohealth Group The",
    "wof:placetype":"venue"
},
  "geometry": {"coordinates":[-95.325067,30.149038],"type":"Point"}
}