{
  "type": "Feature",
  "properties": {
    "iso:country":"US",
    "sg:address":"12271 Coit Rd",
    "sg:city":"Dallas",
    "sg:classifiers":[
        {
            "category":"Real Estate",
            "subcategory":"Real Estate Operator",
            "type":"Services"
        }
    ],
    "sg:phone":"+1 972 866 7575",
    "sg:postcode":"75251",
    "sg:province":"TX",
    "sg:tags":[
        "building",
        "apartment"
    ],
    "wof:name":"Town Village North",
    "wof:placetype":"venue"
},
  "geometry": {"coordinates":[-96.769341,32.91631],"type":"Point"}
}