{
  "type": "Feature",
  "properties": {
    "iso:country":"US",
    "sg:address":"1331 E Main St",
    "sg:city":"Eastland",
    "sg:classifiers":[
        {
            "category":"Shopping",
            "type":"Retail Goods"
        }
    ],
    "sg:phone":"+1 254 629 8662",
    "sg:postcode":"76448",
    "sg:province":"TX",
    "sg:tags":[
        "telephone",
        "cellular"
    ],
    "wof:name":"Western Cellular",
    "wof:placetype":"venue"
},
  "geometry": {"coordinates":[-98.79418699999999,32.401575],"type":"Point"}
}