{
  "type": "Feature",
  "properties": {
    "iso:country":"US",
    "sg:address":"5802 Southseas St",
    "sg:city":"Houston",
    "sg:classifiers":[
        {
            "category":"Restaurant",
            "type":"Food & Drink"
        }
    ],
    "sg:phone":"+1 713 644 5216",
    "sg:postcode":"77033",
    "sg:province":"TX",
    "sg:tags":[
        "caterer"
    ],
    "wof:name":"Creative Choices Catering",
    "wof:placetype":"venue"
},
  "geometry": {"coordinates":[-95.334463,29.676275],"type":"Point"}
}