{
  "type": "Feature",
  "properties": {
    "iso:country":"US",
    "sg:address":"5105 N Colony Blvd",
    "sg:city":"Lewisville",
    "sg:classifiers":[
        {
            "category":"Education",
            "subcategory":"School",
            "type":"Public Place"
        }
    ],
    "sg:phone":"+1 972 625 9030",
    "sg:postcode":"75056",
    "sg:province":"TX",
    "sg:tags":[
        "middle"
    ],
    "wof:name":"Griffin Middle School",
    "wof:placetype":"venue"
},
  "geometry": {"coordinates":[-96.881343,33.097328],"type":"Point"}
}