{
  "type": "Feature",
  "properties": {
    "iso:country":"US",
    "sg:address":"3519 Pease St",
    "sg:city":"Vernon",
    "sg:classifiers":[
        {
            "category":"Professional",
            "type":"Services"
        }
    ],
    "sg:phone":"+1 940 553 4918",
    "sg:postcode":"76384",
    "sg:province":"TX",
    "wof:name":"Dorris Service Co",
    "wof:placetype":"venue"
},
  "geometry": {"coordinates":[-99.30496599999999,34.153348],"type":"Point"}
}