{
  "type": "Feature",
  "properties": {
    "iso:country":"US",
    "sg:address":"1925 E Main St",
    "sg:city":"Nacogdoches",
    "sg:classifiers":[
        {
            "category":"Food & Beverages",
            "subcategory":"Liquor & Beverages",
            "type":"Retail Goods"
        }
    ],
    "sg:phone":"+1 936 564 3087",
    "sg:postcode":"75961",
    "sg:province":"TX",
    "sg:tags":[
        "grocery",
        "alcoholic",
        "sup"
    ],
    "wof:name":"Dyer's Liquor Store",
    "wof:placetype":"venue"
},
  "geometry": {"coordinates":[-94.637917,31.597263],"type":"Point"}
}