{
  "type": "Feature",
  "properties": {
    "iso:country":"US",
    "sg:address":"36690 Marshall Hutts Rd",
    "sg:city":"Rio Hondo",
    "sg:classifiers":[
        {
            "category":"Professional",
            "subcategory":"Business Services",
            "type":"Services"
        }
    ],
    "sg:phone":"+1 956 748 0006",
    "sg:postcode":"78583",
    "sg:province":"TX",
    "wof:name":"Bait Shop",
    "wof:placetype":"venue"
},
  "geometry": {"coordinates":[-97.423384,26.342912],"type":"Point"}
}