{
  "type": "Feature",
  "properties": {
    "iso:country":"US",
    "sg:address":"301 Wells Fargo Dr Suite C-5",
    "sg:city":"Houston",
    "sg:classifiers":[
        {
            "category":"Shopping",
            "subcategory":"Catalog Store",
            "type":"Retail Goods"
        }
    ],
    "sg:phone":"+1 713 589 9523",
    "sg:postcode":"77090",
    "sg:province":"TX",
    "sg:tags":[
        "mail",
        "order",
        "online"
    ],
    "sg:website":"http://www.texascandlesupply.net",
    "wof:name":"Texas Candle Supply",
    "wof:placetype":"venue"
},
  "geometry": {"coordinates":[-95.43240900000001,30.015639],"type":"Point"}
}