{
  "type": "Feature",
  "properties": {
    "iso:country":"US",
    "sg:address":"12699 Memorial Dr",
    "sg:city":"Houston",
    "sg:classifiers":[
        {
            "category":"Food & Beverages",
            "subcategory":"Groceries & Convenience Stores",
            "type":"Retail Goods"
        }
    ],
    "sg:phone":"+1 713 973 2078",
    "sg:postcode":"77024",
    "sg:province":"TX",
    "sg:tags":[
        "independent"
    ],
    "wof:name":"Memorial Convenience Store",
    "wof:placetype":"venue"
},
  "geometry": {"coordinates":[-95.557999,29.767799],"type":"Point"}
}