{
  "type": "Feature",
  "properties": {
    "iso:country":"US",
    "sg:address":"2433 N 3rd St",
    "sg:city":"Abilene",
    "sg:classifiers":[
        {
            "category":"Real Estate",
            "subcategory":"Real Estate Operator",
            "type":"Services"
        }
    ],
    "sg:phone":"+1 325 673 8448",
    "sg:postcode":"79603",
    "sg:province":"TX",
    "sg:tags":[
        "building",
        "apartment"
    ],
    "wof:name":"Fontaine Apartments",
    "wof:placetype":"venue"
},
  "geometry": {"coordinates":[-99.75234500000001,32.452913],"type":"Point"}
}