{
  "type": "Feature",
  "properties": {
    "iso:country":"US",
    "sg:address":"319 E Rio Grande St",
    "sg:city":"Victoria",
    "sg:classifiers":[
        {
            "category":"Shopping",
            "subcategory":"Musical Instruments",
            "type":"Retail Goods"
        }
    ],
    "sg:phone":"+1 361 575 1351",
    "sg:postcode":"77901",
    "sg:province":"TX",
    "sg:tags":[
        "store"
    ],
    "wof:name":"Navratil Music Co Inc",
    "wof:placetype":"venue"
},
  "geometry": {"coordinates":[-97.000579,28.805524],"type":"Point"}
}