{
  "type": "Feature",
  "properties": {
    "iso:country":"US",
    "sg:address":"610 N Sycamore St",
    "sg:city":"Palestine",
    "sg:classifiers":[
        {
            "category":"Utilities",
            "subcategory":"Telephone",
            "type":"Services"
        }
    ],
    "sg:phone":"+1 903 729 8855",
    "sg:postcode":"75801",
    "sg:province":"TX",
    "sg:tags":[
        "company"
    ],
    "wof:name":"Gulf States United Phone Co",
    "wof:placetype":"venue"
},
  "geometry": {"coordinates":[-95.63195899999999,31.765207],"type":"Point"}
}