{
  "type": "Feature",
  "properties": {
    "iso:country":"US",
    "sg:address":"12920 Steeple Way Blvd",
    "sg:city":"Houston",
    "sg:classifiers":[
        {
            "category":"Professional",
            "subcategory":"Business Services",
            "type":"Services"
        }
    ],
    "sg:phone":"+1 281 970 3563",
    "sg:postcode":"77065",
    "sg:province":"TX",
    "wof:name":"All Cash Flow Solutions",
    "wof:placetype":"venue"
},
  "geometry": {"coordinates":[-95.58866999999999,29.898785],"type":"Point"}
}