{
  "type": "Feature",
  "properties": {
    "iso:country":"US",
    "sg:address":"2242 Walnut Grove Ln",
    "sg:city":"Garland",
    "sg:classifiers":[
        {
            "category":"Food & Beverages",
            "subcategory":"Groceries & Convenience Stores",
            "type":"Retail Goods"
        }
    ],
    "sg:phone":"+1 972 675 4715",
    "sg:postcode":"75044",
    "sg:province":"TX",
    "sg:tags":[
        "market"
    ],
    "wof:name":"Dovecourt Market",
    "wof:placetype":"venue"
},
  "geometry": {"coordinates":[-96.66189300000001,32.959827],"type":"Point"}
}