{
  "type": "Feature",
  "properties": {
    "iso:country":"US",
    "sg:address":"3706 20th St",
    "sg:city":"Lubbock",
    "sg:classifiers":[
        {
            "category":"Health Services",
            "subcategory":"Doctor",
            "type":"Services"
        }
    ],
    "sg:phone":"+1 806 771 4327",
    "sg:postcode":"79410",
    "sg:province":"TX",
    "sg:tags":[
        "physician",
        "surgeon"
    ],
    "wof:name":"Kids' Hearts & Family Heart",
    "wof:placetype":"venue"
},
  "geometry": {"coordinates":[-101.896331,33.57693],"type":"Point"}
}