{
  "type": "Feature",
  "properties": {
    "iso:country":"US",
    "sg:address":"468 McDonald Ln W",
    "sg:city":"Cedar Creek",
    "sg:classifiers":[
        {
            "category":"Organizations",
            "subcategory":"Religious Organization",
            "type":"Services"
        }
    ],
    "sg:phone":"+1 512 332 0132",
    "sg:postcode":"78612",
    "sg:province":"TX",
    "wof:name":"Mt Pleasant Primitive Baptist",
    "wof:placetype":"venue"
},
  "geometry": {"coordinates":[-97.480926,30.112883],"type":"Point"}
}