{
  "type": "Feature",
  "properties": {
    "iso:country":"US",
    "sg:address":"2210 Hammerwood Dr",
    "sg:city":"Missouri City",
    "sg:classifiers":[
        {
            "category":"Social Services",
            "subcategory":"Child Care",
            "type":"Services"
        }
    ],
    "sg:phone":"+1 281 438 8176",
    "sg:postcode":"77489",
    "sg:province":"TX",
    "sg:tags":[
        "day"
    ],
    "wof:name":"Youth Enrichment Services",
    "wof:placetype":"venue"
},
  "geometry": {"coordinates":[-95.51721999999999,29.596665],"type":"Point"}
}