{
  "type": "Feature",
  "properties": {
    "iso:country":"US",
    "sg:address":"9300 Prairieview Dr",
    "sg:city":"Fort Worth",
    "sg:classifiers":[
        {
            "category":"Building & Trades",
            "subcategory":"Landscaping Services",
            "type":"Services"
        }
    ],
    "sg:phone":"+1 817 615 8815",
    "sg:postcode":"76134",
    "sg:province":"TX",
    "sg:tags":[
        "tree"
    ],
    "wof:name":"Merkwan Tree Svc",
    "wof:placetype":"venue"
},
  "geometry": {"coordinates":[-97.34561600000001,32.619491],"type":"Point"}
}