{
  "type": "Feature",
  "properties": {
    "iso:country":"US",
    "sg:address":"12303 Ecksminster St",
    "sg:city":"San Antonio",
    "sg:classifiers":[
        {
            "category":"Building & Trades",
            "subcategory":"Landscaping Services",
            "type":"Services"
        }
    ],
    "sg:phone":"+1 210 494 3915",
    "sg:postcode":"78216",
    "sg:province":"TX",
    "wof:name":"Plant Life",
    "wof:placetype":"venue"
},
  "geometry": {"coordinates":[-98.469686,29.552958],"type":"Point"}
}