{
  "type": "Feature",
  "properties": {
    "iso:country":"US",
    "sg:address":"2355 W Longhorn Dr",
    "sg:city":"Lancaster",
    "sg:classifiers":[
        {
            "category":"Manufacturing",
            "subcategory":"Chemicals & Compounds",
            "type":"Manufacturing & Wholesale Goods"
        }
    ],
    "sg:phone":"+1 972 224 8231",
    "sg:postcode":"75134",
    "sg:province":"TX",
    "sg:tags":[
        "paint"
    ],
    "wof:name":"Degussa Construction Chemicals",
    "wof:placetype":"venue"
},
  "geometry": {"coordinates":[-96.81601999999999,32.616135],"type":"Point"}
}