{
  "type": "Feature",
  "properties": {
    "iso:country":"US",
    "sg:address":"2910 Bluebonnet Ln",
    "sg:city":"San Angelo",
    "sg:classifiers":[
        {
            "category":"Wholesale",
            "subcategory":"Vending Machines",
            "type":"Manufacturing & Wholesale Goods"
        }
    ],
    "sg:phone":"+1 325 949 4744",
    "sg:postcode":"76904",
    "sg:province":"TX",
    "sg:tags":[
        "operator"
    ],
    "wof:name":"Straight Way Vending",
    "wof:placetype":"venue"
},
  "geometry": {"coordinates":[-100.487765,31.431767],"type":"Point"}
}