{
  "type": "Feature",
  "properties": {
    "iso:country":"US",
    "sg:address":"2556 Broadway St",
    "sg:city":"Houston",
    "sg:classifiers":[
        {
            "category":"Retail",
            "subcategory":"Veterinary Services",
            "type":"Services"
        }
    ],
    "sg:phone":"+1 281 997 1426",
    "sg:postcode":"77012",
    "sg:province":"TX",
    "wof:name":"Paula Ramsey Dvm",
    "wof:placetype":"venue"
},
  "geometry": {"coordinates":[-95.278026,29.704251],"type":"Point"}
}