{
  "type": "Feature",
  "properties": {
    "iso:country":"US",
    "sg:address":"5116 Tesoro Plz",
    "sg:city":"Laredo",
    "sg:classifiers":[
        {
            "category":"Professional",
            "subcategory":"Advertising",
            "type":"Services"
        }
    ],
    "sg:phone":"+1 956 725 5253",
    "sg:postcode":"78041",
    "sg:province":"TX",
    "sg:website":"www.timewarnercable.com",
    "wof:name":"Time Warner Communications",
    "wof:placetype":"venue"
},
  "geometry": {"coordinates":[-99.505076,27.549714],"type":"Point"}
}