{
  "type": "Feature",
  "properties": {
    "iso:country":"US",
    "sg:address":"5000 Westheimer Rd",
    "sg:city":"Houston",
    "sg:classifiers":[
        {
            "category":"Restaurant",
            "type":"Food & Drink"
        }
    ],
    "sg:menulink":"http://www.allmenus.com/tx/houston/26097-antones/menu/",
    "sg:phone":"+1 713 877 1222",
    "sg:postcode":"77056",
    "sg:province":"TX",
    "sg:tags":[
        "wrap",
        "american",
        "sandwich"
    ],
    "wof:name":"Antone's",
    "wof:placetype":"venue"
},
  "geometry": {"coordinates":[-95.462678,29.741928],"type":"Point"}
}