{
  "type": "Feature",
  "properties": {
    "iso:country":"US",
    "sg:address":"286 Co Rd 1160",
    "sg:city":"Decatur",
    "sg:classifiers":[
        {
            "category":"Professional",
            "subcategory":"Accounting & Tax Preparation",
            "type":"Services"
        }
    ],
    "sg:phone":"+1 940 627 6627",
    "sg:postcode":"76234",
    "sg:province":"TX",
    "sg:tags":[
        "return"
    ],
    "wof:name":"Sk Brazile & Associate",
    "wof:placetype":"venue"
},
  "geometry": {"coordinates":[-97.615965,33.256094],"type":"Point"}
}