{
  "type": "Feature",
  "properties": {
    "iso:country":"US",
    "sg:address":"2501 Scripture St",
    "sg:city":"Denton",
    "sg:classifiers":[
        {
            "category":"Health Services",
            "subcategory":"Doctor",
            "type":"Services"
        }
    ],
    "sg:phone":"+1 940 591 8447",
    "sg:postcode":"76201",
    "sg:province":"TX",
    "sg:tags":[
        "medical"
    ],
    "wof:name":"Suzanne E Mack MD",
    "wof:placetype":"venue"
},
  "geometry": {"coordinates":[-97.163905,33.21896],"type":"Point"}
}