{
  "type": "Feature",
  "properties": {
    "iso:country":"US",
    "sg:address":"801 Longridge Dr",
    "sg:city":"Denton",
    "sg:classifiers":[
        {
            "category":"Real Estate",
            "subcategory":"Real Estate Agent",
            "type":"Services"
        }
    ],
    "sg:phone":"+1 940 383 3180",
    "sg:postcode":"76205",
    "sg:province":"TX",
    "wof:name":"Gmss Inc",
    "wof:placetype":"venue"
},
  "geometry": {"coordinates":[-97.12380899999999,33.18267],"type":"Point"}
}