{
  "type": "Feature",
  "properties": {
    "iso:country":"US",
    "sg:address":"2408 Fairway Dr",
    "sg:city":"Fort Worth",
    "sg:classifiers":[
        {
            "category":"Shopping",
            "type":"Retail Goods"
        }
    ],
    "sg:phone":"+1 817 536 8312",
    "sg:postcode":"76119",
    "sg:province":"TX",
    "sg:tags":[
        "cosmetic",
        "perfume"
    ],
    "wof:name":"Bettye's",
    "wof:placetype":"venue"
},
  "geometry": {"coordinates":[-97.295304,32.697018],"type":"Point"}
}