{
  "type": "Feature",
  "properties": {
    "iso:country":"US",
    "sg:address":"2017 Lamar St",
    "sg:city":"Houston",
    "sg:classifiers":[
        {
            "category":"Personal",
            "type":"Services"
        }
    ],
    "sg:phone":"+1 713 223 2257",
    "sg:postcode":"77003",
    "sg:province":"TX",
    "sg:tags":[
        "florist",
        "consultant",
        "wedding"
    ],
    "wof:name":"Lim's Florist & Gift Shop",
    "wof:placetype":"venue"
},
  "geometry": {"coordinates":[-95.3563,29.750799],"type":"Point"}
}