{
  "type": "Feature",
  "properties": {
    "iso:country":"US",
    "sg:address":"2901 N Main St",
    "sg:city":"Fort Worth",
    "sg:classifiers":[
        {
            "category":"Banks & Credit Unions",
            "subcategory":"Bank",
            "type":"Services"
        }
    ],
    "sg:phone":"+1 817 624 6162",
    "sg:postcode":"76106",
    "sg:province":"TX",
    "sg:tags":[
        "money",
        "order"
    ],
    "wof:name":"Tex Mex Transfers Corp",
    "wof:placetype":"venue"
},
  "geometry": {"coordinates":[-97.350325,32.799338],"type":"Point"}
}