{
  "type": "Feature",
  "properties": {
    "iso:country":"US",
    "sg:address":"306 E 18th St",
    "sg:city":"Big Spring",
    "sg:classifiers":[
        {
            "category":"Personal",
            "subcategory":"Beauty Salon",
            "type":"Services"
        }
    ],
    "sg:phone":"+1 432 263 8100",
    "sg:postcode":"79720",
    "sg:province":"TX",
    "sg:tags":[
        "shop"
    ],
    "wof:name":"Beauty Realm",
    "wof:placetype":"venue"
},
  "geometry": {"coordinates":[-101.466814,32.238285],"type":"Point"}
}