{
  "type": "Feature",
  "properties": {
    "iso:country":"US",
    "sg:address":"124 Birnam Wood Ct",
    "sg:city":"Austin",
    "sg:classifiers":[
        {
            "category":"Building & Trades",
            "subcategory":"Construction",
            "type":"Services"
        }
    ],
    "sg:phone":"+1 512 306 1123",
    "sg:postcode":"78746",
    "sg:province":"TX",
    "sg:tags":[
        "house"
    ],
    "wof:name":"Number 1 Custom Homes",
    "wof:placetype":"venue"
},
  "geometry": {"coordinates":[-97.79292700000001,30.285369],"type":"Point"}
}