{
  "type": "Feature",
  "properties": {
    "iso:country":"US",
    "sg:address":"315 W Shadowbend Ave",
    "sg:city":"Friendswood",
    "sg:classifiers":[
        {
            "category":"Organizations",
            "subcategory":"Religious Organization",
            "type":"Services"
        }
    ],
    "sg:phone":"+1 281 996 6880",
    "sg:postcode":"77546",
    "sg:province":"TX",
    "sg:tags":[
        "baptist",
        "church"
    ],
    "wof:name":"Friendswood Baptist Church",
    "wof:placetype":"venue"
},
  "geometry": {"coordinates":[-95.20702900000001,29.527243],"type":"Point"}
}