{
  "type": "Feature",
  "properties": {
    "iso:country":"US",
    "sg:address":"1705 S Bryant Blvd",
    "sg:city":"San Angelo",
    "sg:classifiers":[
        {
            "category":"Restaurant",
            "type":"Food & Drink"
        }
    ],
    "sg:menulink":"http://www.allmenus.com/tx/san-angelo/130481-subway/menu/",
    "sg:phone":"+1 325 486 2097",
    "sg:postcode":"76903",
    "sg:province":"TX",
    "sg:tags":[
        "american",
        "sandwich"
    ],
    "wof:name":"Subway",
    "wof:placetype":"venue"
},
  "geometry": {"coordinates":[-100.442227,31.443827],"type":"Point"}
}