{
  "type": "Feature",
  "properties": {
    "iso:country":"US",
    "sg:address":"611 Santa Ana St",
    "sg:city":"Weslaco",
    "sg:classifiers":[
        {
            "category":"Building & Trades",
            "subcategory":"Construction",
            "type":"Services"
        }
    ],
    "sg:phone":"+1 956 968 7130",
    "sg:postcode":"78596",
    "sg:province":"TX",
    "sg:tags":[
        "fence",
        "contractor"
    ],
    "wof:name":"D Cyclone Fence Co",
    "wof:placetype":"venue"
},
  "geometry": {"coordinates":[-97.99641,26.170567],"type":"Point"}
}