{
  "type": "Feature",
  "properties": {
    "iso:country":"US",
    "sg:address":"2714 Country Club Pkwy",
    "sg:city":"Garland",
    "sg:classifiers":[
        {
            "category":"Real Estate",
            "subcategory":"Surveying",
            "type":"Services"
        }
    ],
    "sg:phone":"+1 972 271 1131",
    "sg:postcode":"75043",
    "sg:province":"TX",
    "sg:tags":[
        "geophysicist"
    ],
    "wof:name":"Seismic Diagnostic Inc",
    "wof:placetype":"venue"
},
  "geometry": {"coordinates":[-96.606233,32.887852],"type":"Point"}
}