{
  "type": "Feature",
  "properties": {
    "iso:country":"US",
    "sg:address":"1821 S Main St",
    "sg:city":"Keller",
    "sg:phone":"+1 817 337 1695",
    "sg:postcode":"76248",
    "sg:province":"TX",
    "sg:website":"http://www.tgifridays.com",
    "wof:name":"T.G.I. Friday's",
    "wof:placetype":"venue"
},
  "geometry": {"coordinates":[-97.254339,32.955605],"type":"Point"}
}