{
  "type": "Feature",
  "properties": {
    "iso:country":"US",
    "sg:address":"1007 W Randol Mill Rd",
    "sg:city":"Arlington",
    "sg:classifiers":[
        {
            "category":"Health Services",
            "subcategory":"Doctor",
            "type":"Services"
        }
    ],
    "sg:phone":"+1 817 861 3937",
    "sg:postcode":"76012",
    "sg:province":"TX",
    "sg:tags":[
        "physician",
        "surgeon"
    ],
    "wof:name":"Texas Eye Physicians",
    "wof:placetype":"venue"
},
  "geometry": {"coordinates":[-97.116522,32.750214],"type":"Point"}
}