{
  "type": "Feature",
  "properties": {
    "iso:country":"US",
    "sg:address":"1302 Quail Run",
    "sg:city":"Burkburnett",
    "sg:classifiers":[
        {
            "category":"Shopping",
            "subcategory":"Used Merchandise",
            "type":"Retail Goods"
        }
    ],
    "sg:phone":"+1 940 569 1078",
    "sg:postcode":"76354",
    "sg:province":"TX",
    "wof:name":"Blachniks Antq & Collectibles",
    "wof:placetype":"venue"
},
  "geometry": {"coordinates":[-98.591987,34.073921],"type":"Point"}
}