{
  "type": "Feature",
  "properties": {
    "iso:country":"US",
    "sg:address":"1350 Colonial Ct",
    "sg:city":"Rockwall",
    "sg:classifiers":[
        {
            "category":"Building & Trades",
            "subcategory":"Construction",
            "type":"Services"
        }
    ],
    "sg:phone":"+1 214 741 1157",
    "sg:postcode":"75087",
    "sg:province":"TX",
    "sg:tags":[
        "layer",
        "carpet"
    ],
    "wof:name":"Custom Installation Artists",
    "wof:placetype":"venue"
},
  "geometry": {"coordinates":[-96.47727399999999,32.945195],"type":"Point"}
}