{
  "type": "Feature",
  "properties": {
    "iso:country":"US",
    "sg:address":"200 S Mcgee St Ste 100",
    "sg:city":"Borger",
    "sg:classifiers":[
        {
            "category":"Health Services",
            "subcategory":"Doctor",
            "type":"Services"
        }
    ],
    "sg:phone":"+1 806 273 1100",
    "sg:postcode":"79007",
    "sg:province":"TX",
    "sg:tags":[
        "physician",
        "surgeon"
    ],
    "wof:name":"Specialty Physicians Clinic",
    "wof:placetype":"venue"
},
  "geometry": {"coordinates":[-101.39424099999999,35.664639],"type":"Point"}
}