{
  "type": "Feature",
  "properties": {
    "iso:country":"US",
    "sg:address":"3118 Frick Rd",
    "sg:city":"Houston",
    "sg:classifiers":[
        {
            "category":"Retail",
            "subcategory":"Auto Repair",
            "type":"Services"
        }
    ],
    "sg:phone":"+1 281 448 2533",
    "sg:postcode":"77038",
    "sg:province":"TX",
    "sg:tags":[
        "automotive"
    ],
    "wof:name":"45 North Towing",
    "wof:placetype":"venue"
},
  "geometry": {"coordinates":[-95.468279,29.923037],"type":"Point"}
}