{
  "type": "Feature",
  "properties": {
    "iso:country":"US",
    "sg:address":"410 Plantation Dr",
    "sg:city":"Lake Jackson",
    "sg:classifiers":[
        {
            "category":"Food & Beverages",
            "subcategory":"Groceries & Convenience Stores",
            "type":"Retail Goods"
        }
    ],
    "sg:phone":"+1 979 297 1288",
    "sg:postcode":"77566",
    "sg:province":"TX",
    "sg:tags":[
        "grocer"
    ],
    "sg:website":"www.heb.com",
    "wof:name":"H E B Foods",
    "wof:placetype":"venue"
},
  "geometry": {"coordinates":[-95.433263,29.021724],"type":"Point"}
}