{
  "type": "Feature",
  "properties": {
    "iso:country":"US",
    "sg:address":"2855 Gramercy St.",
    "sg:city":"Houston",
    "sg:classifiers":[
        {
            "category":"Health Services",
            "subcategory":"Optometrist",
            "type":"Services"
        }
    ],
    "sg:phone":"+1 713 668 1828",
    "sg:postcode":"77025",
    "sg:province":"TX",
    "sg:tags":[
        "ophthalmologist"
    ],
    "sg:website":"www.thehoustoneyecenter.com",
    "wof:name":"Houston Eye Associates",
    "wof:placetype":"venue"
},
  "geometry": {"coordinates":[-95.422195,29.703934],"type":"Point"}
}