{
  "type": "Feature",
  "properties": {
    "iso:country":"US",
    "sg:address":"7997 US Hwy 59",
    "sg:city":"Diboll",
    "sg:classifiers":[
        {
            "category":"Building & Trades",
            "subcategory":"Construction",
            "type":"Services"
        }
    ],
    "sg:phone":"+1 936 637 2415",
    "sg:postcode":"75941",
    "sg:province":"TX",
    "sg:tags":[
        "roofing",
        "contractor"
    ],
    "wof:name":"Bonner Roofing & Metal Inc",
    "wof:placetype":"venue"
},
  "geometry": {"coordinates":[-94.766217,31.231404],"type":"Point"}
}