{
  "type": "Feature",
  "properties": {
    "iso:country":"US",
    "sg:address":"16223 Moon Rock Dr",
    "sg:city":"Houston",
    "sg:phone":"+1 281 480 2255",
    "sg:postcode":"77062",
    "sg:province":"TX",
    "wof:name":"Lobo Sports Club",
    "wof:placetype":"venue"
},
  "geometry": {"coordinates":[-95.10856,29.575838],"type":"Point"}
}