{
  "type": "Feature",
  "properties": {
    "iso:country":"US",
    "sg:address":"22015 Buescher Rd",
    "sg:city":"Tomball",
    "sg:classifiers":[
        {
            "category":"Animal Shelter",
            "type":"Public Place"
        },
        {
            "category":"Retail",
            "subcategory":"Pet Boarding",
            "type":"Services"
        }
    ],
    "sg:phone":"+1 281 451 8781",
    "sg:postcode":"77377",
    "sg:province":"TX",
    "sg:tags":[
        "kennel"
    ],
    "wof:name":"Dogwood Kennel, Inc",
    "wof:placetype":"venue"
},
  "geometry": {"coordinates":[-95.67652099999999,30.079492],"type":"Point"}
}