{
  "type": "Feature",
  "properties": {
    "iso:country":"US",
    "sg:address":"8145 Long Point Rd",
    "sg:city":"Houston",
    "sg:classifiers":[
        {
            "category":"Wholesale",
            "subcategory":"Machinery & Supplies",
            "type":"Manufacturing & Wholesale Goods"
        }
    ],
    "sg:phone":"+1 713 465 9066",
    "sg:postcode":"77055",
    "sg:province":"TX",
    "sg:tags":[
        "shop",
        "salon",
        "beauty",
        "suppl",
        "equipment",
        "barber"
    ],
    "wof:name":"Sally Beauty Supply 104",
    "wof:placetype":"venue"
},
  "geometry": {"coordinates":[-95.491905,29.802877],"type":"Point"}
}