{
  "type": "Feature",
  "properties": {
    "iso:country":"US",
    "sg:address":"9795 Beechnut St Ste A",
    "sg:city":"Houston",
    "sg:classifiers":[
        {
            "category":"Restaurant",
            "type":"Food & Drink"
        },
        {
            "category":"Food & Beverages",
            "subcategory":"Meat & Fish",
            "type":"Retail Goods"
        }
    ],
    "sg:phone":"+1 713 981 7410",
    "sg:postcode":"77036",
    "sg:province":"TX",
    "sg:tags":[
        "seafood",
        "market"
    ],
    "wof:name":"Les New Orleans Seafood",
    "wof:placetype":"venue"
},
  "geometry": {"coordinates":[-95.55439800000001,29.6891],"type":"Point"}
}