{
  "type": "Feature",
  "properties": {
    "iso:country":"US",
    "sg:address":"1222 Caledonia Ct",
    "sg:city":"Allen",
    "sg:classifiers":[
        {
            "category":"Professional",
            "type":"Services"
        }
    ],
    "sg:phone":"+1 972 359 6393",
    "sg:postcode":"75013",
    "sg:province":"TX",
    "wof:name":"Legacy Designs",
    "wof:placetype":"venue"
},
  "geometry": {"coordinates":[-96.697517,33.106603],"type":"Point"}
}