{
  "type": "Feature",
  "properties": {
    "iso:country":"US",
    "sg:address":"1107 Summit Hill",
    "sg:city":"San Antonio",
    "sg:classifiers":[
        {
            "category":"Professional",
            "type":"Services"
        }
    ],
    "sg:phone":"+1 210 497 2082",
    "sg:postcode":"78258",
    "sg:province":"TX",
    "wof:name":"Kids Klassics",
    "wof:placetype":"venue"
},
  "geometry": {"coordinates":[-98.499112,29.648857],"type":"Point"}
}