{
  "type": "Feature",
  "properties": {
    "iso:country":"US",
    "sg:address":"20319 Timberline Trl",
    "sg:city":"Cypress",
    "sg:classifiers":[
        {
            "category":"Restaurant",
            "type":"Food & Drink"
        }
    ],
    "sg:phone":"+1 281 213 3324",
    "sg:postcode":"77433",
    "sg:province":"TX",
    "sg:tags":[
        "eating"
    ],
    "wof:name":"Piltzmaker Enterprises Inc",
    "wof:placetype":"venue"
},
  "geometry": {"coordinates":[-95.73425,30.009506],"type":"Point"}
}