{
  "type": "Feature",
  "properties": {
    "iso:country":"US",
    "sg:address":"1300 W Walnut Hill Ln",
    "sg:city":"Irving",
    "sg:classifiers":[
        {
            "category":"Professional",
            "subcategory":"Computer Services",
            "type":"Services"
        }
    ],
    "sg:phone":"+1 972 550 9061",
    "sg:postcode":"75038",
    "sg:province":"TX",
    "sg:tags":[
        "programming"
    ],
    "wof:name":"Visionary Concepts Inc",
    "wof:placetype":"venue"
},
  "geometry": {"coordinates":[-96.968256,32.88497],"type":"Point"}
}