{
  "type": "Feature",
  "properties": {
    "iso:country":"US",
    "sg:address":"713 Red Oak Dr",
    "sg:city":"Orange",
    "sg:classifiers":[
        {
            "category":"Professional",
            "subcategory":"Business Services",
            "type":"Services"
        }
    ],
    "sg:phone":"+1 409 883 7438",
    "sg:postcode":"77632",
    "sg:province":"TX",
    "wof:name":"Tech Plus Solutions",
    "wof:placetype":"venue"
},
  "geometry": {"coordinates":[-93.74197100000001,30.157711],"type":"Point"}
}