{
  "type": "Feature",
  "properties": {
    "iso:country":"US",
    "sg:address":"10233 E Northwest Hwy",
    "sg:city":"Dallas",
    "sg:classifiers":[
        {
            "category":"Restaurant",
            "type":"Food & Drink"
        }
    ],
    "sg:phone":"+1 214 503 0388",
    "sg:postcode":"75238",
    "sg:province":"TX",
    "wof:name":"Tony's Pizza & Pasta",
    "wof:placetype":"venue"
},
  "geometry": {"coordinates":[-96.709429,32.864397],"type":"Point"}
}