{
  "type": "Feature",
  "properties": {
    "iso:country":"US",
    "sg:address":"120 South Alexander",
    "sg:city":"Baytown",
    "sg:classifiers":[
        {
            "category":"Professional",
            "subcategory":"Advertising",
            "type":"Services"
        }
    ],
    "sg:phone":"+1 888 308 0946",
    "sg:postcode":"77521",
    "sg:province":"TX",
    "sg:tags":[
        "demand-generation",
        "cold-calling",
        "lead-generation",
        "business-to-business-marketing"
    ],
    "sg:website":"http://www.demandlogix.com",
    "wof:name":"DemandLogix",
    "wof:placetype":"venue"
},
  "geometry": {"coordinates":[-94.955246,29.736794],"type":"Point"}
}