{
  "type": "Feature",
  "properties": {
    "iso:country":"US",
    "sg:address":"9700 Court Glen Dr # 803",
    "sg:city":"Houston",
    "sg:classifiers":[
        {
            "category":"Insurance",
            "subcategory":"Title Insurance",
            "type":"Services"
        }
    ],
    "sg:phone":"+1 281 933 0760",
    "sg:postcode":"77099",
    "sg:province":"TX",
    "sg:tags":[
        "mortgage"
    ],
    "wof:name":"Mutual Mortgage Insurance",
    "wof:placetype":"venue"
},
  "geometry": {"coordinates":[-95.583023,29.67141],"type":"Point"}
}