{
  "type": "Feature",
  "properties": {
    "iso:country":"US",
    "sg:address":"10815 N Fm 620",
    "sg:city":"Austin",
    "sg:classifiers":[
        {
            "category":"Autos & Motor Vehicles",
            "subcategory":"Automobile Sales",
            "type":"Retail Goods"
        },
        {
            "category":"Retail",
            "subcategory":"Auto Repair",
            "type":"Services"
        }
    ],
    "sg:phone":"+1 512 335 6043",
    "sg:postcode":"78726",
    "sg:province":"TX",
    "sg:tags":[
        "electric",
        "equipment",
        "brake",
        "diagnostic",
        "air conditioning"
    ],
    "wof:name":"Qualtech Automotive",
    "wof:placetype":"venue"
},
  "geometry": {"coordinates":[-97.830792,30.448104],"type":"Point"}
}