{
  "type": "Feature",
  "properties": {
    "iso:country":"US",
    "sg:address":"44 Rogers Wood",
    "sg:city":"San Antonio",
    "sg:classifiers":[
        {
            "category":"Organizations",
            "subcategory":"Membership Organization",
            "type":"Services"
        }
    ],
    "sg:phone":"+1 210 492 6270",
    "sg:postcode":"78248",
    "sg:province":"TX",
    "wof:name":"Inwood",
    "wof:placetype":"venue"
},
  "geometry": {"coordinates":[-98.536598,29.585958],"type":"Point"}
}