{
  "type": "Feature",
  "properties": {
    "iso:country":"US",
    "sg:address":"13418 Bradbridge Ln",
    "sg:city":"Houston",
    "sg:classifiers":[
        {
            "category":"Professional",
            "subcategory":"Business Services",
            "type":"Services"
        }
    ],
    "sg:phone":"+1 281 531 0654",
    "sg:postcode":"77082",
    "sg:province":"TX",
    "wof:name":"Planetour Group",
    "wof:placetype":"venue"
},
  "geometry": {"coordinates":[-95.62239099999999,29.717463],"type":"Point"}
}