{
  "type": "Feature",
  "properties": {
    "iso:country":"US",
    "sg:address":"3603 S Braeswood Blvd",
    "sg:city":"Houston",
    "sg:classifiers":[
        {
            "category":"Health Services",
            "subcategory":"Doctor",
            "type":"Services"
        }
    ],
    "sg:phone":"+1 713 666 5522",
    "sg:postcode":"77025",
    "sg:province":"TX",
    "sg:tags":[
        "medical"
    ],
    "wof:name":"Agnes M Guthrie",
    "wof:placetype":"venue"
},
  "geometry": {"coordinates":[-95.433449,29.690809],"type":"Point"}
}