{
  "type": "Feature",
  "properties": {
    "iso:country":"US",
    "sg:address":"2240 Royal Ln",
    "sg:city":"Dallas",
    "sg:classifiers":[
        {
            "category":"Personal",
            "subcategory":"Beauty Salon",
            "type":"Services"
        }
    ],
    "sg:phone":"+1 972 406 0667",
    "sg:postcode":"75229",
    "sg:province":"TX",
    "sg:tags":[
        "shop"
    ],
    "wof:name":"Yuns Haircuts",
    "wof:placetype":"venue"
},
  "geometry": {"coordinates":[-96.901337,32.895635],"type":"Point"}
}