{
  "type": "Feature",
  "properties": {
    "iso:country":"US",
    "sg:address":"6818 Snider Plaza",
    "sg:city":"Dallas",
    "sg:classifiers":[
        {
            "category":"Shopping",
            "subcategory":"Clothing, Apparel, & Fashions",
            "type":"Retail Goods"
        }
    ],
    "sg:phone":"+1 214 369 1700",
    "sg:postcode":"75205",
    "sg:province":"TX",
    "sg:tags":[
        "clothing",
        "women's"
    ],
    "sg:website":"www.melaniegayle.com",
    "wof:name":"Melanie Gayle",
    "wof:placetype":"venue"
},
  "geometry": {"coordinates":[-96.78750100000001,32.848663],"type":"Point"}
}