{
  "type": "Feature",
  "properties": {
    "iso:country":"US",
    "sg:address":"3720 State Highway 121",
    "sg:city":"Plano",
    "sg:classifiers":[
        {
            "category":"Banks & Credit Unions",
            "subcategory":"Bank",
            "type":"Services"
        },
        {
            "category":"Banks & Credit Unions",
            "subcategory":"Financial Services",
            "type":"Services"
        }
    ],
    "sg:phone":"+1 469 633 9707",
    "sg:postcode":"75025",
    "sg:province":"TX",
    "sg:tags":[
        "saving",
        "loan",
        "commercial"
    ],
    "sg:website":"https://www.chase.com/",
    "wof:name":"CHASE Bank",
    "wof:placetype":"venue"
},
  "geometry": {"coordinates":[-96.76714699999999,33.111945],"type":"Point"}
}