{
  "type": "Feature",
  "properties": {
    "iso:country":"US",
    "sg:address":"611 I- 20",
    "sg:city":"Duncanville",
    "sg:classifiers":[
        {
            "category":"Autos & Motor Vehicles",
            "subcategory":"Auto Supplies",
            "type":"Retail Goods"
        }
    ],
    "sg:phone":"+1 972 296 0978",
    "sg:postcode":"75116",
    "sg:province":"TX",
    "sg:tags":[
        "body",
        "used"
    ],
    "wof:name":"Urban Nissan",
    "wof:placetype":"venue"
},
  "geometry": {"coordinates":[-96.920233,32.667513],"type":"Point"}
}