{
  "type": "Feature",
  "properties": {
    "iso:country":"US",
    "sg:address":"140 S Heights Blvd",
    "sg:city":"Houston",
    "sg:classifiers":[
        {
            "category":"Restaurant",
            "type":"Food & Drink"
        }
    ],
    "sg:phone":"+1 713 864 8080",
    "sg:postcode":"77007",
    "sg:province":"TX",
    "sg:tags":[
        "new",
        "american",
        "eating"
    ],
    "sg:website":"www.chatterscafe.com",
    "wof:name":"Chatter's Cafe & Bistro",
    "wof:placetype":"venue"
},
  "geometry": {"coordinates":[-95.397447,29.768107],"type":"Point"}
}