{
  "type": "Feature",
  "properties": {
    "iso:country":"US",
    "sg:address":"908 E 32nd St",
    "sg:city":"Houston",
    "sg:classifiers":[
        {
            "category":"Organizations",
            "subcategory":"Religious Organization",
            "type":"Services"
        }
    ],
    "sg:phone":"+1 713 864 4504",
    "sg:postcode":"77022",
    "sg:province":"TX",
    "sg:tags":[
        "church"
    ],
    "wof:name":"Mt Pilgrim Missionary Baptist",
    "wof:placetype":"venue"
},
  "geometry": {"coordinates":[-95.385992,29.815222],"type":"Point"}
}