{
  "type": "Feature",
  "properties": {
    "iso:country":"US",
    "sg:address":"3988 N Central Expy",
    "sg:city":"Dallas",
    "sg:classifiers":[
        {
            "category":"Insurance",
            "subcategory":"Insurance Agent",
            "type":"Services"
        }
    ],
    "sg:phone":"+1 214 821 7130",
    "sg:postcode":"75204",
    "sg:province":"TX",
    "wof:name":"American General Life Ins Co",
    "wof:placetype":"venue"
},
  "geometry": {"coordinates":[-96.792091,32.809497],"type":"Point"}
}