{
  "type": "Feature",
  "properties": {
    "iso:country":"US",
    "sg:address":"1713 Kingsbridge Dr",
    "sg:city":"Garland",
    "sg:classifiers":[
        {
            "category":"Building & Trades",
            "subcategory":"Electrical",
            "type":"Services"
        }
    ],
    "sg:phone":"+1 214 912 0827",
    "sg:postcode":"75044",
    "sg:province":"TX",
    "sg:tags":[
        "electric",
        "contractor"
    ],
    "wof:name":"Mahlon Randall Allen Electric",
    "wof:placetype":"venue"
},
  "geometry": {"coordinates":[-96.65595399999999,32.934855],"type":"Point"}
}