{
  "type": "Feature",
  "properties": {
    "iso:country":"US",
    "sg:address":"1240 Shiloh Rd",
    "sg:city":"Plano",
    "sg:classifiers":[
        {
            "category":"Building & Trades",
            "subcategory":"Construction",
            "type":"Services"
        }
    ],
    "sg:phone":"+1 972 754 8905",
    "sg:postcode":"75074",
    "sg:province":"TX",
    "sg:tags":[
        "bathroom",
        "remodeling"
    ],
    "wof:name":"Dallas Bath Systems",
    "wof:placetype":"venue"
},
  "geometry": {"coordinates":[-96.664637,33.012944],"type":"Point"}
}