{
  "type": "Feature",
  "properties": {
    "iso:country":"US",
    "sg:address":"3700 Buffalo Speedway",
    "sg:city":"Houston",
    "sg:classifiers":[
        {
            "category":"Mining & Drilling",
            "type":"Manufacturing & Wholesale Goods"
        }
    ],
    "sg:phone":"+1 713 871 1946",
    "sg:postcode":"77005",
    "sg:province":"TX",
    "sg:tags":[
        "natural",
        "gas"
    ],
    "wof:name":"South Shore Pipeline LP",
    "wof:placetype":"venue"
},
  "geometry": {"coordinates":[-95.42882,29.732392],"type":"Point"}
}