{
  "type": "Feature",
  "properties": {
    "iso:country":"US",
    "sg:address":"2400 E Oltorf St Ste 16",
    "sg:city":"Austin",
    "sg:classifiers":[
        {
            "category":"Personal",
            "subcategory":"Nail Salon",
            "type":"Services"
        }
    ],
    "sg:phone":"+1 512 326 3625",
    "sg:postcode":"78741",
    "sg:province":"TX",
    "wof:name":"Sally Nails",
    "wof:placetype":"venue"
},
  "geometry": {"coordinates":[-97.729624,30.229399],"type":"Point"}
}