{
  "type": "Feature",
  "properties": {
    "iso:country":"US",
    "sg:address":"1220 E Commerce St",
    "sg:city":"San Antonio",
    "sg:classifiers":[
        {
            "category":"Professional",
            "type":"Services"
        }
    ],
    "sg:phone":"+1 210 227 1922",
    "sg:postcode":"78205",
    "sg:province":"TX",
    "sg:tags":[
        "establishment"
    ],
    "wof:name":"Presidio Plaza Conference Ctr",
    "wof:placetype":"venue"
},
  "geometry": {"coordinates":[-98.47639599999999,29.421114],"type":"Point"}
}