{
  "type": "Feature",
  "properties": {
    "iso:country":"US",
    "sg:address":"4401 Garth Rd",
    "sg:city":"Baytown",
    "sg:classifiers":[
        {
            "category":"Shopping",
            "subcategory":"Gifts & Souvenirs",
            "type":"Retail Goods"
        }
    ],
    "sg:phone":"+1 281 420 8976",
    "sg:postcode":"77521",
    "sg:province":"TX",
    "sg:tags":[
        "shop"
    ],
    "sg:website":"http://www.lorishospitalgiftshops.com",
    "wof:name":"Lori's Hospital Gift Shop",
    "wof:placetype":"venue"
},
  "geometry": {"coordinates":[-94.97757,29.769171],"type":"Point"}
}