{
  "type": "Feature",
  "properties": {
    "iso:country":"US",
    "sg:address":"4207 Driscoll St",
    "sg:city":"Houston",
    "sg:classifiers":[
        {
            "category":"Manufacturing",
            "subcategory":"Tools & Machinery",
            "type":"Manufacturing & Wholesale Goods"
        }
    ],
    "sg:phone":"+1 713 545 9054",
    "sg:postcode":"77098",
    "sg:province":"TX",
    "sg:tags":[
        "wholesaler",
        "filter",
        "order",
        "mfg"
    ],
    "wof:name":"A1 Oder Control of Houston",
    "wof:placetype":"venue"
},
  "geometry": {"coordinates":[-95.406159,29.734316],"type":"Point"}
}