{
  "type": "Feature",
  "properties": {
    "iso:country":"US",
    "sg:address":"4433 Hannigan Dr",
    "sg:city":"Corpus Christi",
    "sg:classifiers":[
        {
            "category":"Building & Trades",
            "subcategory":"Construction",
            "type":"Services"
        }
    ],
    "sg:phone":"+1 361 980 0311",
    "sg:postcode":"78413",
    "sg:province":"TX",
    "sg:tags":[
        "builder",
        "deck"
    ],
    "wof:name":"Overall Fence & Deck",
    "wof:placetype":"venue"
},
  "geometry": {"coordinates":[-97.399197,27.700995],"type":"Point"}
}