{
  "type": "Feature",
  "properties": {
    "iso:country":"US",
    "sg:address":"5601 Brodie Ln Ste 920",
    "sg:city":"Sunset Valley",
    "sg:classifiers":[
        {
            "category":"Insurance",
            "subcategory":"Health Insurance",
            "type":"Services"
        }
    ],
    "sg:phone":"+1 512 892 0938",
    "sg:postcode":"78745",
    "sg:province":"TX",
    "sg:tags":[
        "market"
    ],
    "sg:website":"www.gnc.com/home/index.jsp",
    "wof:name":"GNC",
    "wof:placetype":"venue"
},
  "geometry": {"coordinates":[-97.82048500000001,30.228778],"type":"Point"}
}