{
  "type": "Feature",
  "properties": {
    "iso:country":"US",
    "sg:address":"4970 Sentry Woods Ln",
    "sg:city":"Pearland",
    "sg:classifiers":[
        {
            "category":"Utilities",
            "subcategory":"Mobile Phone",
            "type":"Services"
        }
    ],
    "sg:phone":"+1 281 412 9298",
    "sg:postcode":"77584",
    "sg:province":"TX",
    "sg:tags":[
        "communication",
        "radiotelephone"
    ],
    "wof:name":"Galaxy Wireless LLC",
    "wof:placetype":"venue"
},
  "geometry": {"coordinates":[-95.340824,29.544538],"type":"Point"}
}