{
  "type": "Feature",
  "properties": {
    "iso:country":"US",
    "sg:address":"5801 Wimbleton Way",
    "sg:city":"Fort Worth",
    "sg:classifiers":[
        {
            "category":"Professional",
            "type":"Services"
        }
    ],
    "sg:phone":"+1 817 370 2310",
    "sg:postcode":"76133",
    "sg:province":"TX",
    "wof:name":"Atlantic & Pacific Transp",
    "wof:placetype":"venue"
},
  "geometry": {"coordinates":[-97.38590600000001,32.656774],"type":"Point"}
}