{
  "type": "Feature",
  "properties": {
    "iso:country":"US",
    "sg:address":"782 Pine St",
    "sg:city":"Abilene",
    "sg:classifiers":[
        {
            "category":"Retail",
            "subcategory":"Laundry & Dry Cleaning",
            "type":"Services"
        }
    ],
    "sg:phone":"+1 325 673 8685",
    "sg:postcode":"79601",
    "sg:province":"TX",
    "sg:tags":[
        "cleaners"
    ],
    "wof:name":"Master Cleaners",
    "wof:placetype":"venue"
},
  "geometry": {"coordinates":[-99.732451,32.455973],"type":"Point"}
}