{
  "type": "Feature",
  "properties": {
    "iso:country":"US",
    "sg:address":"2118 Ethel Ave",
    "sg:city":"Waco",
    "sg:classifiers":[
        {
            "category":"Shopping",
            "type":"Retail Goods"
        }
    ],
    "sg:phone":"+1 254 755 7680",
    "sg:postcode":"76707",
    "sg:province":"TX",
    "sg:tags":[
        "merchandise"
    ],
    "wof:name":"Rickey R Thompson",
    "wof:placetype":"venue"
},
  "geometry": {"coordinates":[-97.157938,31.553695],"type":"Point"}
}