{
  "type": "Feature",
  "properties": {
    "iso:country":"US",
    "sg:address":"655 Town Square Blvd",
    "sg:city":"Garland",
    "sg:classifiers":[
        {
            "category":"Shopping",
            "subcategory":"Clothing, Apparel, & Fashions",
            "type":"Retail Goods"
        }
    ],
    "sg:phone":"+1 972 675 2030",
    "sg:postcode":"75040",
    "sg:province":"TX",
    "sg:tags":[
        "children's",
        "clothing"
    ],
    "wof:name":"Carters Retail Inc",
    "wof:placetype":"venue"
},
  "geometry": {"coordinates":[-96.61173599999999,32.954362],"type":"Point"}
}