{
  "type": "Feature",
  "properties": {
    "iso:country":"US",
    "sg:address":"6350 US Hwy 90 Alt",
    "sg:city":"Sugar Land",
    "sg:classifiers":[
        {
            "category":"Restaurant",
            "type":"Food & Drink"
        }
    ],
    "sg:phone":"+1 281 565 3354",
    "sg:postcode":"77478",
    "sg:province":"TX",
    "wof:name":"Cafe Natalie Catering & Dining",
    "wof:placetype":"venue"
},
  "geometry": {"coordinates":[-95.655447,29.610449],"type":"Point"}
}