{
  "type": "Feature",
  "properties": {
    "iso:country":"US",
    "sg:address":"4518 Erie Dr",
    "sg:city":"Midland",
    "sg:classifiers":[
        {
            "category":"Manufacturing",
            "subcategory":"Toys & Sporting Goods",
            "type":"Manufacturing & Wholesale Goods"
        }
    ],
    "sg:phone":"+1 432 689 9533",
    "sg:postcode":"79703",
    "sg:province":"TX",
    "sg:tags":[
        "mfg"
    ],
    "wof:name":"Rock Forever",
    "wof:placetype":"venue"
},
  "geometry": {"coordinates":[-102.133184,31.977995],"type":"Point"}
}