{
  "type": "Feature",
  "properties": {
    "iso:country":"US",
    "sg:address":"2333 Gulf Terminal Dr",
    "sg:city":"Houston",
    "sg:classifiers":[
        {
            "category":"Wholesale",
            "subcategory":"Metals & Minerals",
            "type":"Manufacturing & Wholesale Goods"
        }
    ],
    "sg:phone":"+1 713 923 6111",
    "sg:postcode":"77023",
    "sg:province":"TX",
    "sg:tags":[
        "import",
        "ductile",
        "casting",
        "iron",
        "cast"
    ],
    "wof:name":"Serampore Industries Inc",
    "wof:placetype":"venue"
},
  "geometry": {"coordinates":[-95.322906,29.718035],"type":"Point"}
}