{
  "type": "Feature",
  "properties": {
    "iso:country":"US",
    "sg:address":"416 Lochridge Dr",
    "sg:city":"Azle",
    "sg:classifiers":[
        {
            "category":"Arts & Performance",
            "subcategory":"Theater",
            "type":"Entertainment"
        }
    ],
    "sg:phone":"+1 817 444 4678",
    "sg:postcode":"76020",
    "sg:province":"TX",
    "sg:tags":[
        "group"
    ],
    "wof:name":"Story Patch Players",
    "wof:placetype":"venue"
},
  "geometry": {"coordinates":[-97.539978,32.908751],"type":"Point"}
}