{
  "type": "Feature",
  "properties": {
    "iso:country":"US",
    "sg:address":"1623 Farola Dr",
    "sg:city":"Dallas",
    "sg:classifiers":[
        {
            "category":"Freight",
            "type":"Transportation"
        }
    ],
    "sg:phone":"+1 214 660 4060",
    "sg:postcode":"75228",
    "sg:province":"TX",
    "sg:tags":[
        "operator",
        "local",
        "trucking"
    ],
    "wof:name":"Dwe Trucking",
    "wof:placetype":"venue"
},
  "geometry": {"coordinates":[-96.68236899999999,32.844094],"type":"Point"}
}