{
  "type": "Feature",
  "properties": {
    "iso:country":"US",
    "sg:address":"2250 William D Tate Ave",
    "sg:city":"Grapevine",
    "sg:classifiers":[
        {
            "category":"Shopping",
            "subcategory":"Catalog Store",
            "type":"Retail Goods"
        }
    ],
    "sg:phone":"+1 817 424 2000",
    "sg:postcode":"76051",
    "sg:province":"TX",
    "sg:tags":[
        "used",
        "related",
        "hardware",
        "game",
        "video",
        "new"
    ],
    "wof:name":"FUNCOLAND",
    "wof:placetype":"venue"
},
  "geometry": {"coordinates":[-97.09603799999999,32.91648],"type":"Point"}
}