{
  "type": "Feature",
  "properties": {
    "iso:country":"US",
    "sg:address":"7229 Ferguson Rd",
    "sg:city":"Dallas",
    "sg:classifiers":[
        {
            "category":"Utilities",
            "subcategory":"Natural Gas",
            "type":"Services"
        }
    ],
    "sg:phone":"+1 214 874 3567",
    "sg:postcode":"75228",
    "sg:province":"TX",
    "sg:tags":[
        "stone"
    ],
    "sg:website":"http://www.ayyastonework.com",
    "wof:name":"Ayya Stone",
    "wof:placetype":"venue"
},
  "geometry": {"coordinates":[-96.72132499999999,32.795816],"type":"Point"}
}