{
  "type": "Feature",
  "properties": {
    "iso:country":"US",
    "sg:address":"9801 Fondren Rd",
    "sg:city":"Houston",
    "sg:classifiers":[
        {
            "category":"Building & Trades",
            "subcategory":"Pest Control",
            "type":"Services"
        }
    ],
    "sg:phone":"+1 713 988 4757",
    "sg:postcode":"77096",
    "sg:province":"TX",
    "wof:name":"Texas Pest Solutions",
    "wof:placetype":"venue"
},
  "geometry": {"coordinates":[-95.508527,29.673842],"type":"Point"}
}