{
  "type": "Feature",
  "properties": {
    "iso:country":"US",
    "sg:address":"35 Lucky Leaf Ct",
    "sg:city":"Spring",
    "sg:classifiers":[
        {
            "category":"Manufacturing",
            "subcategory":"Printing",
            "type":"Manufacturing & Wholesale Goods"
        }
    ],
    "sg:phone":"+1 281 367 4487",
    "sg:postcode":"77381",
    "sg:province":"TX",
    "sg:tags":[
        "lithographic",
        "commercial"
    ],
    "wof:name":"Specialty Printing & Grap",
    "wof:placetype":"venue"
},
  "geometry": {"coordinates":[-95.491876,30.180472],"type":"Point"}
}