{
  "type": "Feature",
  "properties": {
    "iso:country":"US",
    "sg:address":"616 Fort Worth Dr",
    "sg:city":"Denton",
    "sg:classifiers":[
        {
            "category":"Professional",
            "subcategory":"Research",
            "type":"Services"
        }
    ],
    "sg:phone":"+1 940 591 6904",
    "sg:postcode":"76201",
    "sg:province":"TX",
    "sg:tags":[
        "laboratory"
    ],
    "wof:name":"Laboratory Corp Of America",
    "wof:placetype":"venue"
},
  "geometry": {"coordinates":[-97.13755399999999,33.199965],"type":"Point"}
}