{
  "type": "Feature",
  "properties": {
    "iso:country":"US",
    "sg:address":"103 N Moody St",
    "sg:city":"Victoria",
    "sg:classifiers":[
        {
            "category":"Retail",
            "subcategory":"Repair Shop",
            "type":"Services"
        }
    ],
    "sg:phone":"+1 361 575 5362",
    "sg:postcode":"77901",
    "sg:province":"TX",
    "sg:tags":[
        "upholsterer"
    ],
    "wof:name":"Carmona's Custom Upholstering",
    "wof:placetype":"venue"
},
  "geometry": {"coordinates":[-97.008702,28.800988],"type":"Point"}
}