{
  "type": "Feature",
  "properties": {
    "iso:country":"US",
    "sg:address":"5347 N Mesa St",
    "sg:city":"El Paso",
    "sg:classifiers":[
        {
            "category":"Retail",
            "subcategory":"Auto Repair",
            "type":"Services"
        }
    ],
    "sg:phone":"+1 915 833 2082",
    "sg:postcode":"79912",
    "sg:province":"TX",
    "sg:tags":[
        "repairing",
        "automobile"
    ],
    "wof:name":"Abcom Inc",
    "wof:placetype":"venue"
},
  "geometry": {"coordinates":[-106.51472,31.816908],"type":"Point"}
}