{
  "type": "Feature",
  "properties": {
    "iso:country":"US",
    "sg:address":"5014 Queen's Ct",
    "sg:city":"Corpus Christi",
    "sg:classifiers":[
        {
            "category":"Building & Trades",
            "subcategory":"Construction",
            "type":"Services"
        }
    ],
    "sg:phone":"+1 361 991 4636",
    "sg:postcode":"78413",
    "sg:province":"TX",
    "sg:tags":[
        "contractor"
    ],
    "wof:name":"South Texas Home Remodeling",
    "wof:placetype":"venue"
},
  "geometry": {"coordinates":[-97.403132,27.675842],"type":"Point"}
}