{
  "type": "Feature",
  "properties": {
    "iso:country":"US",
    "sg:address":"1401 Preston Rd",
    "sg:city":"Plano",
    "sg:classifiers":[
        {
            "category":"Restaurant",
            "type":"Food & Drink"
        }
    ],
    "sg:phone":"+1 214 818 8537",
    "sg:postcode":"75093",
    "sg:province":"TX",
    "wof:name":"Mattitos Cafe Mexicano",
    "wof:placetype":"venue"
},
  "geometry": {"coordinates":[-96.795406,33.018541],"type":"Point"}
}