{
  "type": "Feature",
  "properties": {
    "iso:country":"US",
    "sg:address":"200 S Robinson Dr",
    "sg:city":"Waco",
    "sg:classifiers":[
        {
            "category":"Restaurant",
            "type":"Food & Drink"
        }
    ],
    "sg:phone":"+1 254 662 2490",
    "sg:postcode":"76706",
    "sg:province":"TX",
    "sg:tags":[
        "eating"
    ],
    "wof:name":"Jays Deli",
    "wof:placetype":"venue"
},
  "geometry": {"coordinates":[-97.11541800000001,31.468774],"type":"Point"}
}