{
  "type": "Feature",
  "properties": {
    "iso:country":"US",
    "sg:address":"10900 Kingspoint Rd",
    "sg:city":"Houston",
    "sg:classifiers":[
        {
            "category":"Personal",
            "subcategory":"Beauty Salon",
            "type":"Services"
        }
    ],
    "sg:phone":"+1 713 947 0100",
    "sg:postcode":"77075",
    "sg:province":"TX",
    "sg:tags":[
        "shop"
    ],
    "wof:name":"2000 Hair Design",
    "wof:placetype":"venue"
},
  "geometry": {"coordinates":[-95.227507,29.620365],"type":"Point"}
}