{
  "type": "Feature",
  "properties": {
    "iso:country":"US",
    "sg:address":"2813 Knollwood Dr",
    "sg:city":"Plano",
    "sg:classifiers":[
        {
            "category":"Real Estate",
            "subcategory":"Real Estate Agent",
            "type":"Services"
        }
    ],
    "sg:phone":"+1 972 373 4963",
    "sg:postcode":"75075",
    "sg:province":"TX",
    "wof:name":"Rominger Real Estate",
    "wof:placetype":"venue"
},
  "geometry": {"coordinates":[-96.75004199999999,33.02454],"type":"Point"}
}