{
  "type": "Feature",
  "properties": {
    "iso:country":"US",
    "sg:address":"3102 Kiowa St",
    "sg:city":"San Antonio",
    "sg:classifiers":[
        {
            "category":"Freight",
            "type":"Transportation"
        }
    ],
    "sg:phone":"+1 210 924 3259",
    "sg:postcode":"78211",
    "sg:province":"TX",
    "sg:tags":[
        "operator",
        "local",
        "trucking"
    ],
    "wof:name":"J P Molina Trucking",
    "wof:placetype":"venue"
},
  "geometry": {"coordinates":[-98.557675,29.342667],"type":"Point"}
}