{
  "type": "Feature",
  "properties": {
    "iso:country":"US",
    "sg:address":"870 San Jacinto Dr",
    "sg:city":"Grand Prairie",
    "sg:classifiers":[
        {
            "category":"Restaurant",
            "type":"Food & Drink"
        }
    ],
    "sg:phone":"+1 972 264 6030",
    "sg:postcode":"75052",
    "sg:province":"TX",
    "sg:tags":[
        "eating"
    ],
    "wof:name":"Wreaths At Your Door",
    "wof:placetype":"venue"
},
  "geometry": {"coordinates":[-96.99355799999999,32.665183],"type":"Point"}
}