{
  "type": "Feature",
  "properties": {
    "iso:country":"US",
    "sg:address":"11110 Ballet Dr",
    "sg:city":"San Antonio",
    "sg:classifiers":[
        {
            "category":"Organizations",
            "subcategory":"Membership Organization",
            "type":"Services"
        }
    ],
    "sg:phone":"+1 210 820 0652",
    "sg:postcode":"78216",
    "sg:province":"TX",
    "wof:name":"Olmos Kiwanis Club",
    "wof:placetype":"venue"
},
  "geometry": {"coordinates":[-98.501687,29.542031],"type":"Point"}
}