{
  "type": "Feature",
  "properties": {
    "iso:country":"US",
    "sg:address":"2722 Ridge View Rd",
    "sg:city":"Frisco",
    "sg:classifiers":[
        {
            "category":"Professional",
            "subcategory":"Management & Consulting",
            "type":"Services"
        },
        {
            "category":"Professional",
            "subcategory":"Business Services",
            "type":"Services"
        }
    ],
    "sg:phone":"+1 972 625 3893",
    "sg:postcode":"75034",
    "sg:province":"TX",
    "sg:tags":[
        "consultant",
        "coach"
    ],
    "sg:website":"http://www.christhrash.com",
    "wof:name":"Thrash Chris & Associates",
    "wof:placetype":"venue"
},
  "geometry": {"coordinates":[-96.866608,33.126311],"type":"Point"}
}