{
  "type": "Feature",
  "properties": {
    "iso:country":"US",
    "sg:address":"4055 Valley View Ln",
    "sg:city":"Dallas",
    "sg:classifiers":[
        {
            "category":"Professional",
            "subcategory":"Engineering",
            "type":"Services"
        }
    ],
    "sg:phone":"+1 972 385 8630",
    "sg:postcode":"75244",
    "sg:province":"TX",
    "wof:name":"Mobile Field Engineer Inc",
    "wof:placetype":"venue"
},
  "geometry": {"coordinates":[-96.840721,32.925327],"type":"Point"}
}