{
  "type": "Feature",
  "properties": {
    "iso:country":"US",
    "sg:address":"414 Main St",
    "sg:city":"Marble Falls",
    "sg:classifiers":[
        {
            "category":"Retail",
            "subcategory":"Repair Shop",
            "type":"Services"
        }
    ],
    "sg:phone":"+1 830 693 4818",
    "sg:postcode":"78654",
    "sg:province":"TX",
    "wof:name":"Lock & Key Shop",
    "wof:placetype":"venue"
},
  "geometry": {"coordinates":[-98.27631,30.573746],"type":"Point"}
}