{
  "type": "Feature",
  "properties": {
    "iso:country":"US",
    "sg:address":"230 Faircrest Dr",
    "sg:city":"Arlington",
    "sg:classifiers":[
        {
            "category":"Shopping",
            "subcategory":"Used Merchandise",
            "type":"Retail Goods"
        }
    ],
    "sg:phone":"+1 817 472 5649",
    "sg:postcode":"76018",
    "sg:province":"TX",
    "sg:tags":[
        "antique"
    ],
    "wof:name":"Belle Rive Antqs & Collectible",
    "wof:placetype":"venue"
},
  "geometry": {"coordinates":[-97.112527,32.648091],"type":"Point"}
}