{
  "type": "Feature",
  "properties": {
    "iso:country":"US",
    "sg:address":"770 Rd To Six Flags E",
    "sg:city":"Arlington",
    "sg:classifiers":[
        {
            "category":"Restaurant",
            "type":"Food & Drink"
        }
    ],
    "sg:phone":"+1 817 226 7468",
    "sg:postcode":"76011",
    "sg:province":"TX",
    "sg:tags":[
        "eating"
    ],
    "wof:name":"Flying Saucer Arlington",
    "wof:placetype":"venue"
},
  "geometry": {"coordinates":[-97.10075000000001,32.755986],"type":"Point"}
}