{
  "type": "Feature",
  "properties": {
    "iso:country":"US",
    "sg:address":"3600 E Sam Houston Pkwy S",
    "sg:city":"Pasadena",
    "sg:classifiers":[
        {
            "category":"Home & Garden",
            "subcategory":"Garden Supply",
            "type":"Retail Goods"
        },
        {
            "category":"Manufacturing",
            "subcategory":"Paper Products",
            "type":"Manufacturing & Wholesale Goods"
        }
    ],
    "sg:phone":"+1 281 487 4830",
    "sg:postcode":"77505",
    "sg:province":"TX",
    "sg:tags":[
        "bamboo"
    ],
    "wof:name":"Houston Garden Center",
    "wof:placetype":"venue"
},
  "geometry": {"coordinates":[-95.156578,29.657974],"type":"Point"}
}