{
  "type": "Feature",
  "properties": {
    "iso:country":"US",
    "sg:address":"1076 Calder Ave",
    "sg:city":"Beaumont",
    "sg:classifiers":[
        {
            "category":"Professional",
            "type":"Services"
        }
    ],
    "sg:phone":"+1 409 899 3366",
    "sg:postcode":"77701",
    "sg:province":"TX",
    "wof:name":"Enhouse America Inc",
    "wof:placetype":"venue"
},
  "geometry": {"coordinates":[-94.104733,30.086162],"type":"Point"}
}