{
  "type": "Feature",
  "properties": {
    "iso:country":"US",
    "sg:address":"924 Clear Springs Dr",
    "sg:city":"Desoto",
    "sg:classifiers":[
        {
            "category":"Wholesale",
            "subcategory":"Durable Goods & Equipment",
            "type":"Manufacturing & Wholesale Goods"
        }
    ],
    "sg:phone":"+1 972 223 6767",
    "sg:postcode":"75115",
    "sg:province":"TX",
    "sg:tags":[
        "representative",
        "manufacturer"
    ],
    "wof:name":"Walker & Assoc",
    "wof:placetype":"venue"
},
  "geometry": {"coordinates":[-96.836775,32.601816],"type":"Point"}
}