{
  "type": "Feature",
  "properties": {
    "iso:country":"US",
    "sg:address":"1512 Michigan St",
    "sg:city":"Houston",
    "sg:classifiers":[
        {
            "category":"Shopping",
            "subcategory":"Gifts & Souvenirs",
            "type":"Retail Goods"
        }
    ],
    "sg:phone":"+1 713 774 2918",
    "sg:postcode":"77006",
    "sg:province":"TX",
    "wof:name":"Nancy Kottwitz Craft Serv",
    "wof:placetype":"venue"
},
  "geometry": {"coordinates":[-95.39861500000001,29.748],"type":"Point"}
}