{
  "type": "Feature",
  "properties": {
    "iso:country":"US",
    "sg:address":"4445 N Braeswood Blvd",
    "sg:city":"Houston",
    "sg:classifiers":[
        {
            "category":"Health Services",
            "subcategory":"Hospital",
            "type":"Services"
        }
    ],
    "sg:phone":"+1 713 592 9294",
    "sg:postcode":"77096",
    "sg:province":"TX",
    "sg:tags":[
        "mental"
    ],
    "sg:website":"www.innerwisdom.com",
    "wof:name":"Innerwisdom Counseling Ctr",
    "wof:placetype":"venue"
},
  "geometry": {"coordinates":[-95.451064,29.684596],"type":"Point"}
}