{
  "type": "Feature",
  "properties": {
    "iso:country":"US",
    "sg:address":"6110 E Riverside Dr",
    "sg:city":"Austin",
    "sg:classifiers":[
        {
            "category":"Retail",
            "subcategory":"Laundry & Dry Cleaning",
            "type":"Services"
        }
    ],
    "sg:phone":"+1 512 385 7568",
    "sg:postcode":"78741",
    "sg:province":"TX",
    "sg:tags":[
        "garment",
        "plant",
        "agent",
        "drycleaning"
    ],
    "wof:name":"Atlas Cleaners",
    "wof:placetype":"venue"
},
  "geometry": {"coordinates":[-97.70484399999999,30.225744],"type":"Point"}
}