{
  "type": "Feature",
  "properties": {
    "iso:country":"US",
    "sg:address":"2511 Ackerman Rd",
    "sg:city":"San Antonio",
    "sg:classifiers":[
        {
            "category":"Restaurant",
            "type":"Food & Drink"
        }
    ],
    "sg:phone":"+1 210 666 6151",
    "sg:postcode":"78219",
    "sg:province":"TX",
    "sg:tags":[
        "eating"
    ],
    "wof:name":"El Rincon De Maria",
    "wof:placetype":"venue"
},
  "geometry": {"coordinates":[-98.381299,29.451911],"type":"Point"}
}