{
  "type": "Feature",
  "properties": {
    "iso:country":"US",
    "sg:address":"2305 Texas Ave S",
    "sg:city":"College Station",
    "sg:classifiers":[
        {
            "category":"Shopping",
            "subcategory":"Used Merchandise",
            "type":"Retail Goods"
        }
    ],
    "sg:phone":"+1 979 696 7296",
    "sg:postcode":"77840",
    "sg:province":"TX",
    "sg:tags":[
        "pawnbroker",
        "pawnshop"
    ],
    "wof:name":"College Station Pawn Shop",
    "wof:placetype":"venue"
},
  "geometry": {"coordinates":[-96.31178300000001,30.609586],"type":"Point"}
}