{
  "type": "Feature",
  "properties": {
    "iso:country":"US",
    "sg:address":"700 Paredes Ave",
    "sg:city":"Brownsville",
    "sg:classifiers":[
        {
            "category":"Health Services",
            "subcategory":"Clinic",
            "type":"Services"
        }
    ],
    "sg:phone":"+1 956 541 4410",
    "sg:postcode":"78521",
    "sg:province":"TX",
    "sg:tags":[
        "home",
        "care"
    ],
    "wof:name":"Interim Services",
    "wof:placetype":"venue"
},
  "geometry": {"coordinates":[-97.490163,25.915671],"type":"Point"}
}