{
  "type": "Feature",
  "properties": {
    "iso:country":"US",
    "sg:address":"911 Rosario St",
    "sg:city":"Laredo",
    "sg:classifiers":[
        {
            "category":"Wholesale",
            "subcategory":"Groceries",
            "type":"Manufacturing & Wholesale Goods"
        }
    ],
    "sg:phone":"+1 956 724 6430",
    "sg:postcode":"78040",
    "sg:province":"TX",
    "sg:tags":[
        "confectionery",
        "candy"
    ],
    "wof:name":"M & S Candy & Party Supplies",
    "wof:placetype":"venue"
},
  "geometry": {"coordinates":[-99.48665099999999,27.504661],"type":"Point"}
}