{
  "type": "Feature",
  "properties": {
    "iso:country":"US",
    "sg:address":"9918 Catlett Ln",
    "sg:city":"La Porte",
    "sg:classifiers":[
        {
            "category":"Professional",
            "subcategory":"Computer Services",
            "type":"Services"
        }
    ],
    "sg:phone":"+1 281 471 0255",
    "sg:postcode":"77571",
    "sg:province":"TX",
    "sg:tags":[
        "related"
    ],
    "wof:name":"Edtronics",
    "wof:placetype":"venue"
},
  "geometry": {"coordinates":[-95.08211,29.662087],"type":"Point"}
}