{
  "type": "Feature",
  "properties": {
    "iso:country":"US",
    "sg:address":"6509 N Shepherd Dr",
    "sg:city":"Houston",
    "sg:classifiers":[
        {
            "category":"Retail",
            "subcategory":"Auto Repair",
            "type":"Services"
        }
    ],
    "sg:phone":"+1 713 697 7015",
    "sg:postcode":"77091",
    "sg:province":"TX",
    "sg:tags":[
        "muffler",
        "exhaust",
        "system"
    ],
    "wof:name":"New Star Muffler",
    "wof:placetype":"venue"
},
  "geometry": {"coordinates":[-95.41266299999999,29.859651],"type":"Point"}
}