{
  "type": "Feature",
  "properties": {
    "iso:country":"US",
    "sg:address":"3550 SW H K Dodgen Loop",
    "sg:city":"Temple",
    "sg:classifiers":[
        {
            "category":"Professional",
            "type":"Services"
        }
    ],
    "sg:phone":"+1 254 770 0076",
    "sg:postcode":"76504",
    "sg:province":"TX",
    "wof:name":"Dees Place",
    "wof:placetype":"venue"
},
  "geometry": {"coordinates":[-97.385756,31.08784],"type":"Point"}
}