{
  "type": "Feature",
  "properties": {
    "iso:country":"US",
    "sg:address":"4833 Spicewood Springs Rd",
    "sg:city":"Austin",
    "sg:classifiers":[
        {
            "category":"Health Services",
            "subcategory":"Health Practitioner",
            "type":"Services"
        }
    ],
    "sg:phone":"+1 512 658 2674",
    "sg:postcode":"78759",
    "sg:province":"TX",
    "sg:tags":[
        "psychotherapist"
    ],
    "sg:website":"http://www.kilcrease.com",
    "wof:name":"J Worth Kilcrease LPC FT",
    "wof:placetype":"venue"
},
  "geometry": {"coordinates":[-97.762699,30.375794],"type":"Point"}
}