{
  "type": "Feature",
  "properties": {
    "iso:country":"US",
    "sg:address":"1857 Crestridge Dr",
    "sg:city":"Stephenville",
    "sg:classifiers":[
        {
            "category":"Shopping",
            "subcategory":"Used Merchandise",
            "type":"Retail Goods"
        },
        {
            "category":"Professional",
            "type":"Services"
        }
    ],
    "sg:phone":"+1 254 968 6543",
    "sg:postcode":"76401",
    "sg:province":"TX",
    "sg:tags":[
        "antique"
    ],
    "wof:name":"Nana's Nook",
    "wof:placetype":"venue"
},
  "geometry": {"coordinates":[-98.22488300000001,32.219231],"type":"Point"}
}