{
  "type": "Feature",
  "properties": {
    "iso:country":"US",
    "sg:address":"1000 E 41st St",
    "sg:city":"Austin",
    "sg:classifiers":[
        {
            "category":"Shopping",
            "subcategory":"Beauty & Cosmetics",
            "type":"Retail Goods"
        }
    ],
    "sg:phone":"+1 512 451 4522",
    "sg:postcode":"78751",
    "sg:province":"TX",
    "sg:tags":[
        "equipment",
        "perfume",
        "salons-equipment",
        "supply"
    ],
    "sg:website":"http://www.merlenorman.com",
    "wof:name":"Merle Norman Cosmetic Studio",
    "wof:placetype":"venue"
},
  "geometry": {"coordinates":[-97.718964,30.29805],"type":"Point"}
}