{
  "type": "Feature",
  "properties": {
    "iso:country":"US",
    "sg:address":"3312 Leopard St",
    "sg:city":"Corpus Christi",
    "sg:classifiers":[
        {
            "category":"Government",
            "subcategory":"Fire Station",
            "type":"Public Place"
        }
    ],
    "sg:phone":"+1 361 884 5158",
    "sg:postcode":"78408",
    "sg:province":"TX",
    "sg:tags":[
        "department"
    ],
    "wof:name":"Corpus Christi Fire Station",
    "wof:placetype":"venue"
},
  "geometry": {"coordinates":[-97.42713999999999,27.796835],"type":"Point"}
}