{
  "type": "Feature",
  "properties": {
    "iso:country":"US",
    "sg:address":"1228 W Scyene Rd",
    "sg:city":"Mesquite",
    "sg:classifiers":[
        {
            "category":"Building & Trades",
            "subcategory":"Plumbing",
            "type":"Services"
        }
    ],
    "sg:phone":"+1 972 329 2400",
    "sg:postcode":"75149",
    "sg:province":"TX",
    "sg:tags":[
        "contractor"
    ],
    "wof:name":"Lamb Heating & AC",
    "wof:placetype":"venue"
},
  "geometry": {"coordinates":[-96.61724700000001,32.769552],"type":"Point"}
}