{
  "type": "Feature",
  "properties": {
    "iso:country":"US",
    "sg:address":"701 E Shady Grove Rd",
    "sg:city":"Grand Prairie",
    "sg:classifiers":[
        {
            "category":"Real Estate",
            "subcategory":"Real Estate Operator",
            "type":"Services"
        }
    ],
    "sg:phone":"+1 972 790 0625",
    "sg:postcode":"75050",
    "sg:province":"TX",
    "sg:tags":[
        "mobile",
        "home",
        "site",
        "community"
    ],
    "wof:name":"Bush Mobile Home & Rv Park",
    "wof:placetype":"venue"
},
  "geometry": {"coordinates":[-96.99835299999999,32.804862],"type":"Point"}
}