{
  "type": "Feature",
  "properties": {
    "iso:country":"US",
    "sg:address":"6107 Old Sherman Rd",
    "sg:city":"Whitesboro",
    "sg:classifiers":[
        {
            "category":"Shopping",
            "type":"Retail Goods"
        }
    ],
    "sg:phone":"+1 214 682 4191",
    "sg:postcode":"76273",
    "sg:province":"TX",
    "sg:tags":[
        "merchandise"
    ],
    "wof:name":"Tiff's Cowgirl Bling",
    "wof:placetype":"venue"
},
  "geometry": {"coordinates":[-96.88089100000001,33.650441],"type":"Point"}
}