{
  "type": "Feature",
  "properties": {
    "iso:country":"US",
    "sg:address":"11903 Atwell Dr",
    "sg:city":"Houston",
    "sg:classifiers":[
        {
            "category":"Shopping",
            "subcategory":"Crafts & Fabrics",
            "type":"Retail Goods"
        }
    ],
    "sg:phone":"+1 713 721 4050",
    "sg:postcode":"77035",
    "sg:province":"TX",
    "sg:tags":[
        "sewing"
    ],
    "wof:name":"Turrentine Needlecraft",
    "wof:placetype":"venue"
},
  "geometry": {"coordinates":[-95.483206,29.648891],"type":"Point"}
}