{
  "type": "Feature",
  "properties": {
    "iso:country":"US",
    "sg:address":"2409 45th St",
    "sg:city":"Galveston",
    "sg:classifiers":[
        {
            "category":"Personal",
            "subcategory":"Barber",
            "type":"Services"
        }
    ],
    "sg:phone":"+1 409 762 7887",
    "sg:postcode":"77550",
    "sg:province":"TX",
    "wof:name":"Chris's The Shop",
    "wof:placetype":"venue"
},
  "geometry": {"coordinates":[-94.81298200000001,29.280791],"type":"Point"}
}