{
  "type": "Feature",
  "properties": {
    "iso:country":"US",
    "sg:address":"225 School Ave",
    "sg:city":"Waskom",
    "sg:classifiers":[
        {
            "category":"Education",
            "subcategory":"School",
            "type":"Public Place"
        }
    ],
    "sg:phone":"+1 903 687 3638",
    "sg:postcode":"75692",
    "sg:province":"TX",
    "sg:website":"www.waskomisd.net",
    "wof:name":"Waskom Elementary School",
    "wof:placetype":"venue"
},
  "geometry": {"coordinates":[-94.073581,32.475249],"type":"Point"}
}