{
  "type": "Feature",
  "properties": {
    "iso:country":"US",
    "sg:address":"2504 Cobre Valle Ln",
    "sg:city":"Plano",
    "sg:classifiers":[
        {
            "category":"Wholesale",
            "subcategory":"Machinery & Supplies",
            "type":"Manufacturing & Wholesale Goods"
        }
    ],
    "sg:phone":"+1 214 808 4740",
    "sg:postcode":"75023",
    "sg:province":"TX",
    "sg:tags":[
        "equipment",
        "material",
        "handling"
    ],
    "wof:name":"Warehousing Solutions",
    "wof:placetype":"venue"
},
  "geometry": {"coordinates":[-96.745732,33.055201],"type":"Point"}
}