{
  "type": "Feature",
  "properties": {
    "iso:country":"US",
    "sg:address":"3163 State Hwy 6",
    "sg:city":"Sugar Land",
    "sg:classifiers":[
        {
            "category":"Restaurant",
            "type":"Food & Drink"
        }
    ],
    "sg:phone":"+1 281 494 2800",
    "sg:postcode":"77478",
    "sg:province":"TX",
    "sg:tags":[
        "caterer"
    ],
    "wof:name":"Droubi's International Imports",
    "wof:placetype":"venue"
},
  "geometry": {"coordinates":[-95.60647899999999,29.592647],"type":"Point"}
}