{
  "type": "Feature",
  "properties": {
    "iso:country":"US",
    "sg:address":"16000 Katy Fwy",
    "sg:city":"Houston",
    "sg:classifiers":[
        {
            "category":"Health Services",
            "subcategory":"Health Practitioner",
            "type":"Services"
        }
    ],
    "sg:phone":"+1 281 870 9111",
    "sg:postcode":"77094",
    "sg:province":"TX",
    "wof:name":"Annette McMurrey",
    "wof:placetype":"venue"
},
  "geometry": {"coordinates":[-95.665888,29.784426],"type":"Point"}
}