{
  "type": "Feature",
  "properties": {
    "iso:country":"US",
    "sg:address":"921 Holly Hills Ct",
    "sg:city":"Keller",
    "sg:classifiers":[
        {
            "category":"Retail",
            "subcategory":"Laundry & Dry Cleaning",
            "type":"Services"
        }
    ],
    "sg:phone":"+1 817 428 5893",
    "sg:postcode":"76248",
    "sg:province":"TX",
    "sg:tags":[
        "drycleaning",
        "plant"
    ],
    "wof:name":"Dry Clean Super Center",
    "wof:placetype":"venue"
},
  "geometry": {"coordinates":[-97.22989699999999,32.90282],"type":"Point"}
}