{
  "type": "Feature",
  "properties": {
    "iso:country":"US",
    "sg:address":"108 W Grauwyler Rd",
    "sg:city":"Irving",
    "sg:classifiers":[
        {
            "category":"Organizations",
            "subcategory":"Religious Organization",
            "type":"Services"
        }
    ],
    "sg:phone":"+1 972 554 1962",
    "sg:postcode":"75061",
    "sg:province":"TX",
    "wof:name":"Irving Church Of Christ",
    "wof:placetype":"venue"
},
  "geometry": {"coordinates":[-96.94767899999999,32.829307],"type":"Point"}
}