{
  "type": "Feature",
  "properties": {
    "iso:country":"US",
    "sg:address":"415 Carby Rd",
    "sg:city":"Houston",
    "sg:classifiers":[
        {
            "category":"Real Estate",
            "subcategory":"Real Estate Operator",
            "type":"Services"
        }
    ],
    "sg:phone":"+1 281 447 4500",
    "sg:postcode":"77037",
    "sg:province":"TX",
    "sg:tags":[
        "mobile",
        "home",
        "site",
        "community"
    ],
    "wof:name":"Melrose Mobile Home Park",
    "wof:placetype":"venue"
},
  "geometry": {"coordinates":[-95.383494,29.878185],"type":"Point"}
}