{
  "type": "Feature",
  "properties": {
    "iso:country":"US",
    "sg:address":"1873 Boca Chica Blvd",
    "sg:city":"Brownsville",
    "sg:classifiers":[
        {
            "category":"Food & Beverages",
            "subcategory":"Groceries & Convenience Stores",
            "type":"Retail Goods"
        }
    ],
    "sg:phone":"+1 956 548 0145",
    "sg:postcode":"78520",
    "sg:province":"TX",
    "wof:name":"Tejano Mart 407",
    "wof:placetype":"venue"
},
  "geometry": {"coordinates":[-97.491252,25.922336],"type":"Point"}
}