{
  "type": "Feature",
  "properties": {
    "iso:country":"US",
    "sg:address":"4000 10th St",
    "sg:city":"Bridgeport",
    "sg:classifiers":[
        {
            "category":"Government",
            "subcategory":"Jail",
            "type":"Public Place"
        }
    ],
    "sg:phone":"+1 940 683 3010",
    "sg:postcode":"76426",
    "sg:province":"TX",
    "sg:tags":[
        "govt",
        "state",
        "institution"
    ],
    "sg:website":"www.thegeo.net",
    "wof:name":"Bridgeport Correctional Ctr",
    "wof:placetype":"venue"
},
  "geometry": {"coordinates":[-97.757408,33.223267],"type":"Point"}
}