{
  "type": "Feature",
  "properties": {
    "iso:country":"US",
    "sg:address":"6363 Woodway Dr",
    "sg:city":"Houston",
    "sg:classifiers":[
        {
            "category":"Professional",
            "type":"Services"
        }
    ],
    "sg:phone":"+1 713 333 2002",
    "sg:postcode":"77057",
    "sg:province":"TX",
    "sg:tags":[
        "establishment"
    ],
    "wof:name":"Fdlc LLC",
    "wof:placetype":"venue"
},
  "geometry": {"coordinates":[-95.49775,29.755648],"type":"Point"}
}