{
  "type": "Feature",
  "properties": {
    "iso:country":"US",
    "sg:address":"4513 Treaschwig Rd",
    "sg:city":"Spring",
    "sg:classifiers":[
        {
            "category":"Health Services",
            "subcategory":"Doctor",
            "type":"Services"
        }
    ],
    "sg:phone":"+1 281 443 0366",
    "sg:postcode":"77373",
    "sg:province":"TX",
    "wof:name":"Richard A Halling DDS",
    "wof:placetype":"venue"
},
  "geometry": {"coordinates":[-95.361278,30.037159],"type":"Point"}
}