{
  "type": "Feature",
  "properties": {
    "iso:country":"US",
    "sg:address":"3205 Tamarack Ave",
    "sg:city":"Mcallen",
    "sg:classifiers":[
        {
            "category":"Building & Trades",
            "subcategory":"Plumbing",
            "type":"Services"
        }
    ],
    "sg:phone":"+1 956 627 2370",
    "sg:postcode":"78501",
    "sg:province":"TX",
    "sg:tags":[
        "plumber",
        "industrial",
        "contractors-commercial"
    ],
    "wof:name":"Masters Plumbing",
    "wof:placetype":"venue"
},
  "geometry": {"coordinates":[-98.253266,26.225193],"type":"Point"}
}