{
  "type": "Feature",
  "properties": {
    "iso:country":"US",
    "sg:address":"2101 Co Rd 24",
    "sg:city":"Lamesa",
    "sg:phone":"+1 806 497 6395",
    "sg:postcode":"79331",
    "sg:province":"TX",
    "sg:tags":[
        "farm",
        "live",
        "cotton",
        "grain",
        "stock"
    ],
    "wof:name":"Donald & Jeanna Love Prtnrshp",
    "wof:placetype":"venue"
},
  "geometry": {"coordinates":[-101.76946100000001,32.689501],"type":"Point"}
}