{
  "type": "Feature",
  "properties": {
    "iso:country":"US",
    "sg:address":"2031 Crockett Rd",
    "sg:city":"Palestine",
    "sg:classifiers":[
        {
            "category":"Professional",
            "subcategory":"Business Services",
            "type":"Services"
        },
        {
            "category":"Health Services",
            "subcategory":"Doctor",
            "type":"Services"
        }
    ],
    "sg:phone":"+1 903 729 3896",
    "sg:postcode":"75803",
    "sg:province":"TX",
    "sg:tags":[
        "physician",
        "surgeon"
    ],
    "wof:name":"Palestine Women's Clinic",
    "wof:placetype":"venue"
},
  "geometry": {"coordinates":[-95.61090900000001,31.738189],"type":"Point"}
}