{
  "type": "Feature",
  "properties": {
    "iso:country":"US",
    "sg:address":"3739 N 16th St",
    "sg:city":"Orange",
    "sg:classifiers":[
        {
            "category":"Shopping",
            "subcategory":"Gifts & Souvenirs",
            "type":"Retail Goods"
        }
    ],
    "sg:phone":"+1 409 883 8560",
    "sg:postcode":"77632",
    "sg:province":"TX",
    "sg:tags":[
        "shop"
    ],
    "wof:name":"Gala Hallmark",
    "wof:placetype":"venue"
},
  "geometry": {"coordinates":[-93.74768899999999,30.122748],"type":"Point"}
}