{
  "type": "Feature",
  "properties": {
    "iso:country":"US",
    "sg:address":"1630 E US Hwy 83",
    "sg:city":"Weslaco",
    "sg:classifiers":[
        {
            "category":"Autos & Motor Vehicles",
            "subcategory":"Auto Supplies",
            "type":"Retail Goods"
        }
    ],
    "sg:phone":"+1 956 968 8851",
    "sg:postcode":"78596",
    "sg:province":"TX",
    "sg:tags":[
        "radiator"
    ],
    "wof:name":"Anthony's Fuel Injection Svc",
    "wof:placetype":"venue"
},
  "geometry": {"coordinates":[-97.973596,26.156318],"type":"Point"}
}