{
  "type": "Feature",
  "properties": {
    "iso:country":"US",
    "sg:address":"5500 Kirby Dr",
    "sg:city":"Houston",
    "sg:classifiers":[
        {
            "category":"Banks & Credit Unions",
            "subcategory":"Bank",
            "type":"Services"
        }
    ],
    "sg:phone":"+1 713 218 2240",
    "sg:postcode":"77005",
    "sg:province":"TX",
    "sg:website":"www.bokf.com",
    "wof:name":"Bank of Texas Na",
    "wof:placetype":"venue"
},
  "geometry": {"coordinates":[-95.41860200000001,29.722799],"type":"Point"}
}