{
  "type": "Feature",
  "properties": {
    "iso:country":"US",
    "sg:address":"5610 E Central Texas Expy",
    "sg:city":"Killeen",
    "sg:classifiers":[
        {
            "category":"Health Services",
            "subcategory":"Doctor",
            "type":"Services"
        }
    ],
    "sg:phone":"+1 254 690 8887",
    "sg:postcode":"76543",
    "sg:province":"TX",
    "sg:tags":[
        "medicine",
        "physician",
        "practice",
        "surgeons",
        "family"
    ],
    "wof:name":"Webster Dave E DO",
    "wof:placetype":"venue"
},
  "geometry": {"coordinates":[-97.687107,31.075328],"type":"Point"}
}