{
  "type": "Feature",
  "properties": {
    "iso:country":"US",
    "sg:address":"305 W Houston St",
    "sg:city":"Beeville",
    "sg:classifiers":[
        {
            "category":"Building & Trades",
            "subcategory":"Construction",
            "type":"Services"
        }
    ],
    "sg:phone":"+1 361 358 1366",
    "sg:postcode":"78102",
    "sg:province":"TX",
    "sg:tags":[
        "contractor"
    ],
    "wof:name":"A Welding Shop",
    "wof:placetype":"venue"
},
  "geometry": {"coordinates":[-97.74982,28.40021],"type":"Point"}
}