{
  "type": "Feature",
  "properties": {
    "iso:country":"US",
    "sg:address":"3408 Preston Rd",
    "sg:city":"Plano",
    "sg:classifiers":[
        {
            "category":"Restaurant",
            "type":"Food & Drink"
        }
    ],
    "sg:menulink":"http://www.allmenus.com/tx/plano/15671-kirbys-steakhouse/menu/",
    "sg:phone":"+1 972 867 2122",
    "sg:postcode":"75093",
    "sg:province":"TX",
    "sg:tags":[
        "american",
        "steakhouse"
    ],
    "wof:name":"Kirby's Steakhouse",
    "wof:placetype":"venue"
},
  "geometry": {"coordinates":[-96.79432,33.044395],"type":"Point"}
}