{
  "type": "Feature",
  "properties": {
    "iso:country":"US",
    "sg:address":"2111 Blindlake Dr",
    "sg:city":"Houston",
    "sg:classifiers":[
        {
            "category":"Professional",
            "type":"Services"
        }
    ],
    "sg:phone":"+1 281 578 7210",
    "sg:postcode":"77084",
    "sg:province":"TX",
    "wof:name":"Familygrocerycom",
    "wof:placetype":"venue"
},
  "geometry": {"coordinates":[-95.70902700000001,29.795914],"type":"Point"}
}