{
  "type": "Feature",
  "properties": {
    "iso:country":"US",
    "sg:address":"613 Kelly Dr",
    "sg:city":"Fort Worth",
    "sg:classifiers":[
        {
            "category":"Professional",
            "type":"Services"
        }
    ],
    "sg:phone":"+1 817 293 5709",
    "sg:postcode":"76140",
    "sg:province":"TX",
    "wof:name":"Sun Moon & Stars",
    "wof:placetype":"venue"
},
  "geometry": {"coordinates":[-97.287792,32.626486],"type":"Point"}
}