{
  "type": "Feature",
  "properties": {
    "iso:country":"US",
    "sg:address":"1300 Sarah Brooks Dr",
    "sg:city":"Keller",
    "sg:classifiers":[
        {
            "category":"Organizations",
            "subcategory":"Religious Organization",
            "type":"Services"
        }
    ],
    "sg:phone":"+1 817 428 6775",
    "sg:postcode":"76248",
    "sg:province":"TX",
    "wof:name":"Westwind Church",
    "wof:placetype":"venue"
},
  "geometry": {"coordinates":[-97.216702,32.910168],"type":"Point"}
}