{
  "type": "Feature",
  "properties": {
    "iso:country":"US",
    "sg:address":"2902 W Main St",
    "sg:city":"Atlanta",
    "sg:classifiers":[
        {
            "category":"Retail",
            "subcategory":"Auto Repair",
            "type":"Services"
        }
    ],
    "sg:phone":"+1 903 796 8398",
    "sg:postcode":"75551",
    "sg:province":"TX",
    "sg:tags":[
        "body",
        "automobile",
        "painting",
        "repairing"
    ],
    "wof:name":"Texas T Paint & Body",
    "wof:placetype":"venue"
},
  "geometry": {"coordinates":[-94.21243800000001,33.101735],"type":"Point"}
}