{
  "type": "Feature",
  "properties": {
    "iso:country":"US",
    "sg:address":"501 S Adams Ave",
    "sg:city":"Mc Gregor",
    "sg:classifiers":[
        {
            "category":"Banks & Credit Unions",
            "subcategory":"Bank",
            "type":"Services"
        }
    ],
    "sg:phone":"+1 254 840 2847",
    "sg:postcode":"76657",
    "sg:province":"TX",
    "sg:tags":[
        "mortgage"
    ],
    "wof:name":"Vinelife Fellowship",
    "wof:placetype":"venue"
},
  "geometry": {"coordinates":[-97.40815000000001,31.436563],"type":"Point"}
}