{
  "type": "Feature",
  "properties": {
    "iso:country":"US",
    "sg:address":"3410 98th St Ste 4",
    "sg:city":"Lubbock",
    "sg:classifiers":[
        {
            "category":"Building & Trades",
            "subcategory":"Landscaping Services",
            "type":"Services"
        }
    ],
    "sg:phone":"+1 806 445 0321",
    "sg:postcode":"79423",
    "sg:province":"TX",
    "sg:tags":[
        "lawn",
        "landscape",
        "contractor"
    ],
    "wof:name":"J S L Landscaping Inc",
    "wof:placetype":"venue"
},
  "geometry": {"coordinates":[-101.887929,33.505259],"type":"Point"}
}