{
  "type": "Feature",
  "properties": {
    "iso:country":"US",
    "sg:address":"5213 Parker St",
    "sg:city":"Amarillo",
    "sg:classifiers":[
        {
            "category":"Building & Trades",
            "subcategory":"Equipment Rental",
            "type":"Services"
        }
    ],
    "sg:phone":"+1 806 356 9518",
    "sg:postcode":"79110",
    "sg:province":"TX",
    "wof:name":"Gary L Leimer",
    "wof:placetype":"venue"
},
  "geometry": {"coordinates":[-101.854283,35.152048],"type":"Point"}
}