{
  "type": "Feature",
  "properties": {
    "iso:country":"US",
    "sg:address":"4106 Walnut Hill Ln",
    "sg:city":"Dallas",
    "sg:classifiers":[
        {
            "category":"Shopping",
            "subcategory":"Books",
            "type":"Retail Goods"
        }
    ],
    "sg:phone":"+1 214 351 5075",
    "sg:postcode":"75229",
    "sg:province":"TX",
    "sg:tags":[
        "organization",
        "membership"
    ],
    "wof:name":"Betty Wlsh Great Bks Fundation",
    "wof:placetype":"venue"
},
  "geometry": {"coordinates":[-96.84158600000001,32.88028],"type":"Point"}
}