{
  "type": "Feature",
  "properties": {
    "iso:country":"US",
    "sg:address":"1105 Marine Dr",
    "sg:city":"Galveston",
    "sg:classifiers":[
        {
            "category":"Building & Trades",
            "subcategory":"Equipment Rental",
            "type":"Services"
        }
    ],
    "sg:phone":"+1 409 763 6865",
    "sg:postcode":"77550",
    "sg:province":"TX",
    "sg:tags":[
        "heavy",
        "company"
    ],
    "wof:name":"Rex Erectors Inc",
    "wof:placetype":"venue"
},
  "geometry": {"coordinates":[-94.77280500000001,29.322309],"type":"Point"}
}