{
  "type": "Feature",
  "properties": {
    "iso:country":"US",
    "sg:address":"200 N State Highway 16",
    "sg:city":"Graford",
    "sg:classifiers":[
        {
            "category":"Place Of Worship",
            "subcategory":"Church",
            "type":"Public Place"
        },
        {
            "category":"Place Of Worship",
            "type":"Public Place"
        }
    ],
    "sg:phone":"+1 940 779 2395",
    "sg:postcode":"76449",
    "sg:province":"TX",
    "sg:tags":[
        "churches-baptist-general",
        "churches-baptist"
    ],
    "wof:name":"First Baptist Church Of Possum Kingdom Lake",
    "wof:placetype":"venue"
},
  "geometry": {"coordinates":[-98.388616,32.935639],"type":"Point"}
}