{
  "type": "Feature",
  "properties": {
    "iso:country":"US",
    "sg:address":"1056 Churchill Dr",
    "sg:city":"Frisco",
    "sg:classifiers":[
        {
            "category":"Personal",
            "subcategory":"Barber",
            "type":"Services"
        }
    ],
    "sg:phone":"+1 972 668 0589",
    "sg:postcode":"75034",
    "sg:province":"TX",
    "sg:tags":[
        "shop"
    ],
    "wof:name":"Barber Wood Working",
    "wof:placetype":"venue"
},
  "geometry": {"coordinates":[-96.884159,33.15025],"type":"Point"}
}