{
  "type": "Feature",
  "properties": {
    "iso:country":"US",
    "sg:address":"16818 City View Pl",
    "sg:city":"Houston",
    "sg:classifiers":[
        {
            "category":"Real Estate",
            "subcategory":"Real Estate Services",
            "type":"Services"
        },
        {
            "category":"Real Estate",
            "subcategory":"Real Estate Operator",
            "type":"Services"
        }
    ],
    "sg:phone":"+1 281 820 9342",
    "sg:postcode":"77060",
    "sg:province":"TX",
    "sg:tags":[
        "vacancy",
        "apartment",
        "rental",
        "listing"
    ],
    "wof:name":"Cityview Place Apartments",
    "wof:placetype":"venue"
},
  "geometry": {"coordinates":[-95.399844,29.944909],"type":"Point"}
}