{
  "type": "Feature",
  "properties": {
    "iso:country":"US",
    "sg:address":"110 Oryan Ct",
    "sg:city":"Houston",
    "sg:classifiers":[
        {
            "category":"Freight",
            "type":"Transportation"
        }
    ],
    "sg:phone":"+1 713 330 1877",
    "sg:postcode":"77015",
    "sg:province":"TX",
    "sg:tags":[
        "operator",
        "trucking"
    ],
    "wof:name":"Silva Erasma",
    "wof:placetype":"venue"
},
  "geometry": {"coordinates":[-95.17643700000001,29.800222],"type":"Point"}
}