{
  "type": "Feature",
  "properties": {
    "iso:country":"US",
    "sg:address":"3 Davis Loop",
    "sg:city":"Rockport",
    "sg:classifiers":[
        {
            "category":"Professional",
            "type":"Services"
        }
    ],
    "sg:phone":"+1 361 729 2912",
    "sg:postcode":"78382",
    "sg:province":"TX",
    "wof:name":"Poppin Reelin Guide Service",
    "wof:placetype":"venue"
},
  "geometry": {"coordinates":[-97.04286500000001,28.093684],"type":"Point"}
}