{
  "type": "Feature",
  "properties": {
    "iso:country":"US",
    "sg:address":"910 W Commerce St",
    "sg:city":"San Antonio",
    "sg:classifiers":[
        {
            "category":"Government",
            "subcategory":"Office",
            "type":"Public Place"
        }
    ],
    "sg:phone":"+1 210 224 5838",
    "sg:postcode":"78207",
    "sg:province":"TX",
    "wof:name":"Samm SHELTER",
    "wof:placetype":"venue"
},
  "geometry": {"coordinates":[-98.50508600000001,29.426229],"type":"Point"}
}