{
  "type": "Feature",
  "properties": {
    "iso:country":"US",
    "sg:address":"117 E Crockett St",
    "sg:city":"Luling",
    "sg:classifiers":[
        {
            "category":"Professional",
            "subcategory":"Accounting & Tax Preparation",
            "type":"Services"
        }
    ],
    "sg:phone":"+1 830 875 3721",
    "sg:postcode":"78648",
    "sg:province":"TX",
    "sg:tags":[
        "accountant"
    ],
    "wof:name":"James E Rougeou CPA",
    "wof:placetype":"venue"
},
  "geometry": {"coordinates":[-97.655744,29.680398],"type":"Point"}
}