{
  "type": "Feature",
  "properties": {
    "iso:country":"US",
    "sg:address":"7111 Bosque Blvd Suite 200",
    "sg:city":"Waco",
    "sg:classifiers":[
        {
            "category":"Food & Beverages",
            "subcategory":"Specialty",
            "type":"Retail Goods"
        },
        {
            "category":"Health Services",
            "subcategory":"Health Practitioner",
            "type":"Services"
        },
        {
            "category":"Food & Beverages",
            "subcategory":"Fruits & Vegetables",
            "type":"Retail Goods"
        }
    ],
    "sg:phone":"+1 254 759 8050",
    "sg:postcode":"76710",
    "sg:province":"TX",
    "sg:tags":[
        "acupuncture",
        "herb",
        "alternative",
        "medicine",
        "spice"
    ],
    "sg:website":"http://www.healingtouchacupuncture.com",
    "wof:name":"Healing Touch Acupuncture And Herbal",
    "wof:placetype":"venue"
},
  "geometry": {"coordinates":[-97.208893,31.525431],"type":"Point"}
}