{
  "type": "Feature",
  "properties": {
    "iso:country":"US",
    "sg:address":"2106 Southwood Dr",
    "sg:city":"College Station",
    "sg:classifiers":[
        {
            "category":"Shopping",
            "type":"Retail Goods"
        }
    ],
    "sg:phone":"+1 979 696 2500",
    "sg:postcode":"77840",
    "sg:province":"TX",
    "sg:tags":[
        "equipment",
        "telephone",
        "supply"
    ],
    "wof:name":"Brazos Valley Design",
    "wof:placetype":"venue"
},
  "geometry": {"coordinates":[-96.307282,30.595512],"type":"Point"}
}