{
  "type": "Feature",
  "properties": {
    "iso:country":"US",
    "sg:address":"3419 la Salle Ave",
    "sg:city":"Lubbock",
    "sg:classifiers":[
        {
            "category":"Place Of Worship",
            "subcategory":"Church",
            "type":"Public Place"
        },
        {
            "category":"Place Of Worship",
            "type":"Public Place"
        }
    ],
    "sg:phone":"+1 806 797 8026",
    "sg:postcode":"79407",
    "sg:province":"TX",
    "sg:tags":[
        "churches-interdenominational",
        "churches-various",
        "denomination"
    ],
    "wof:name":"Islamic Center Of South Plains",
    "wof:placetype":"venue"
},
  "geometry": {"coordinates":[-101.95440600000001,33.56253],"type":"Point"}
}