{
  "type": "Feature",
  "properties": {
    "iso:country":"US",
    "sg:address":"1303 McCullough Ave",
    "sg:city":"San Antonio",
    "sg:classifiers":[
        {
            "category":"Shopping",
            "subcategory":"Optical Goods",
            "type":"Retail Goods"
        }
    ],
    "sg:phone":"+1 210 222 0760",
    "sg:postcode":"78212",
    "sg:province":"TX",
    "wof:name":"Sharp Eye Optical",
    "wof:placetype":"venue"
},
  "geometry": {"coordinates":[-98.491908,29.441684],"type":"Point"}
}