{
  "type": "Feature",
  "properties": {
    "iso:country":"US",
    "sg:address":"1501 E Main St",
    "sg:city":"Alice",
    "sg:classifiers":[
        {
            "category":"Personal",
            "subcategory":"Beauty Salon",
            "type":"Services"
        }
    ],
    "sg:phone":"+1 361 661 1882",
    "sg:postcode":"78332",
    "sg:province":"TX",
    "sg:tags":[
        "shop"
    ],
    "wof:name":"De Arte Salon",
    "wof:placetype":"venue"
},
  "geometry": {"coordinates":[-98.056358,27.756721],"type":"Point"}
}