{
  "type": "Feature",
  "properties": {
    "iso:country":"US",
    "sg:address":"8912 Turks Cap Ct",
    "sg:city":"Austin",
    "sg:classifiers":[
        {
            "category":"Wholesale",
            "subcategory":"Durable Goods & Equipment",
            "type":"Manufacturing & Wholesale Goods"
        }
    ],
    "sg:phone":"+1 512 336 8811",
    "sg:postcode":"78750",
    "sg:province":"TX",
    "wof:name":"Sun Plus",
    "wof:placetype":"venue"
},
  "geometry": {"coordinates":[-97.789019,30.433887],"type":"Point"}
}