{
  "type": "Feature",
  "properties": {
    "iso:country":"US",
    "sg:address":"4510 Garth Rd",
    "sg:city":"Baytown",
    "sg:classifiers":[
        {
            "category":"Retail",
            "subcategory":"Photofinishing",
            "type":"Services"
        }
    ],
    "sg:phone":"+1 281 420 9585",
    "sg:postcode":"77521",
    "sg:province":"TX",
    "sg:tags":[
        "laboratory"
    ],
    "wof:name":"Qualex 1 Hour Photo Lab",
    "wof:placetype":"venue"
},
  "geometry": {"coordinates":[-94.977475,29.769838],"type":"Point"}
}