{
  "type": "Feature",
  "properties": {
    "iso:country":"US",
    "sg:address":"309 E 6th St",
    "sg:city":"Hereford",
    "sg:classifiers":[
        {
            "category":"Organizations",
            "subcategory":"Community Association",
            "type":"Services"
        }
    ],
    "sg:phone":"+1 806 364 4445",
    "sg:postcode":"79045",
    "sg:province":"TX",
    "wof:name":"CASA Del Llano",
    "wof:placetype":"venue"
},
  "geometry": {"coordinates":[-102.398144,34.820993],"type":"Point"}
}