{
  "type": "Feature",
  "properties": {
    "iso:country":"US",
    "sg:address":"1 Nature Pl",
    "sg:city":"Mckinney",
    "sg:classifiers":[
        {
            "category":"Museum",
            "type":"Entertainment"
        }
    ],
    "sg:phone":"+1 972 562 5566",
    "sg:postcode":"75069",
    "sg:province":"TX",
    "wof:name":"The Heard Natural Science Museum",
    "wof:placetype":"venue"
},
  "geometry": {"coordinates":[-96.61628,33.159279],"type":"Point"}
}