{
  "type": "Feature",
  "properties": {
    "iso:country":"US",
    "sg:address":"200 S 3rd St",
    "sg:city":"Mabank",
    "sg:classifiers":[
        {
            "category":"Food & Beverages",
            "subcategory":"Groceries & Convenience Stores",
            "type":"Retail Goods"
        }
    ],
    "sg:phone":"+1 903 887 7218",
    "sg:postcode":"75147",
    "sg:province":"TX",
    "wof:name":"Food-Fast Convenience Store",
    "wof:placetype":"venue"
},
  "geometry": {"coordinates":[-96.101286,32.365538],"type":"Point"}
}