{
  "type": "Feature",
  "properties": {
    "iso:country":"US",
    "sg:address":"1925 Milam St",
    "sg:city":"Fort Worth",
    "sg:classifiers":[
        {
            "category":"Retail",
            "subcategory":"Laundry & Dry Cleaning",
            "type":"Services"
        }
    ],
    "sg:phone":"+1 817 429 1086",
    "sg:postcode":"76112",
    "sg:province":"TX",
    "sg:tags":[
        "cleaners",
        "rug",
        "carpet"
    ],
    "wof:name":"Craig's Carpet Cleaning",
    "wof:placetype":"venue"
},
  "geometry": {"coordinates":[-97.21133500000001,32.751066],"type":"Point"}
}