{
  "type": "Feature",
  "properties": {
    "iso:country":"US",
    "sg:address":"905 E 22nd St",
    "sg:city":"San Angelo",
    "sg:classifiers":[
        {
            "category":"Building & Trades",
            "subcategory":"Plumbing",
            "type":"Services"
        }
    ],
    "sg:phone":"+1 325 653 0264",
    "sg:postcode":"76903",
    "sg:province":"TX",
    "sg:tags":[
        "plumbing",
        "contractor"
    ],
    "wof:name":"Garcia Plumbing",
    "wof:placetype":"venue"
},
  "geometry": {"coordinates":[-100.434096,31.485279],"type":"Point"}
}