{
  "type": "Feature",
  "properties": {
    "iso:country":"US",
    "sg:address":"111 W Lipan Dr",
    "sg:city":"Lipan",
    "sg:classifiers":[
        {
            "category":"Autos & Motor Vehicles",
            "subcategory":"Fuel & Gas Station",
            "type":"Retail Goods"
        }
    ],
    "sg:phone":"+1 254 646 2476",
    "sg:postcode":"76462",
    "sg:province":"TX",
    "sg:tags":[
        "grocery",
        "station",
        "gasoline",
        "general"
    ],
    "wof:name":"Harmon & Creed Corporation",
    "wof:placetype":"venue"
},
  "geometry": {"coordinates":[-98.052162,32.52149],"type":"Point"}
}