{
  "type": "Feature",
  "properties": {
    "iso:country":"US",
    "sg:address":"6302 Broadway St",
    "sg:city":"Pearland",
    "sg:classifiers":[
        {
            "category":"Insurance",
            "subcategory":"Insurance Agent",
            "type":"Services"
        }
    ],
    "sg:phone":"+1 281 997 0008",
    "sg:postcode":"77581",
    "sg:province":"TX",
    "wof:name":"Kevin Childers",
    "wof:placetype":"venue"
},
  "geometry": {"coordinates":[-95.31639800000001,29.559345],"type":"Point"}
}