{
  "type": "Feature",
  "properties": {
    "iso:country":"US",
    "sg:address":"5431 Pine Arbor Dr",
    "sg:city":"Houston",
    "sg:classifiers":[
        {
            "category":"Professional",
            "subcategory":"Advertising",
            "type":"Services"
        }
    ],
    "sg:phone":"+1 281 583 2806",
    "sg:postcode":"77066",
    "sg:province":"TX",
    "wof:name":"Hitech ADS LLC",
    "wof:placetype":"venue"
},
  "geometry": {"coordinates":[-95.503553,29.972864],"type":"Point"}
}