{
  "type": "Feature",
  "properties": {
    "iso:country":"US",
    "sg:address":"1601 Bonanza Dr",
    "sg:city":"Garland",
    "sg:classifiers":[
        {
            "category":"Building & Trades",
            "subcategory":"Construction",
            "type":"Services"
        }
    ],
    "sg:phone":"+1 972 495 4690",
    "sg:postcode":"75048",
    "sg:province":"TX",
    "sg:tags":[
        "contractor"
    ],
    "wof:name":"Gutter Craft",
    "wof:placetype":"venue"
},
  "geometry": {"coordinates":[-96.60757700000001,32.97862],"type":"Point"}
}