{
  "type": "Feature",
  "properties": {
    "iso:country":"US",
    "sg:address":"3103 Canyon Creek Dr",
    "sg:city":"Richardson",
    "sg:classifiers":[
        {
            "category":"Professional",
            "type":"Services"
        }
    ],
    "sg:phone":"+1 972 680 0173",
    "sg:postcode":"75080",
    "sg:province":"TX",
    "wof:name":"Thomas A Weeks L L C",
    "wof:placetype":"venue"
},
  "geometry": {"coordinates":[-96.740764,32.994257],"type":"Point"}
}