{
  "type": "Feature",
  "properties": {
    "iso:country":"US",
    "sg:address":"209 Applewood Ct",
    "sg:city":"Mc Kinney",
    "sg:classifiers":[
        {
            "category":"Personal",
            "subcategory":"Beauty Salon",
            "type":"Services"
        }
    ],
    "sg:phone":"+1 214 544 2057",
    "sg:postcode":"75071",
    "sg:province":"TX",
    "sg:tags":[
        "shop"
    ],
    "wof:name":"Beas Zora Boutique",
    "wof:placetype":"venue"
},
  "geometry": {"coordinates":[-96.652314,33.200582],"type":"Point"}
}