{
  "type": "Feature",
  "properties": {
    "iso:country":"US",
    "sg:address":"30700 I- 10 W",
    "sg:city":"Boerne",
    "sg:classifiers":[
        {
            "category":"Autos & Motor Vehicles",
            "subcategory":"Automobile Sales",
            "type":"Retail Goods"
        }
    ],
    "sg:phone":"+1 830 755 8243",
    "sg:postcode":"78006",
    "sg:province":"TX",
    "sg:tags":[
        "car",
        "dealer"
    ],
    "wof:name":"Cavender Chevrolet Oldsmobile",
    "wof:placetype":"venue"
},
  "geometry": {"coordinates":[-98.69944,29.748984],"type":"Point"}
}