{
  "type": "Feature",
  "properties": {
    "iso:country":"US",
    "sg:address":"9003 Hammerly Blvd",
    "sg:city":"Houston",
    "sg:classifiers":[
        {
            "category":"Building & Trades",
            "subcategory":"Cleaning & Sanitation",
            "type":"Services"
        }
    ],
    "sg:phone":"+1 713 722 9849",
    "sg:postcode":"77080",
    "sg:province":"TX",
    "sg:tags":[
        "maintenance"
    ],
    "wof:name":"T JS Office Service",
    "wof:placetype":"venue"
},
  "geometry": {"coordinates":[-95.516657,29.810436],"type":"Point"}
}