{
  "type": "Feature",
  "properties": {
    "iso:country":"US",
    "sg:address":"5828 Balcones Dr",
    "sg:city":"Austin",
    "sg:classifiers":[
        {
            "category":"Insurance",
            "subcategory":"Insurance Agent",
            "type":"Services"
        }
    ],
    "sg:phone":"+1 512 380 9850",
    "sg:postcode":"78731",
    "sg:province":"TX",
    "wof:name":"Rodney A Gamble Insurance",
    "wof:placetype":"venue"
},
  "geometry": {"coordinates":[-97.752972,30.34379],"type":"Point"}
}