{
  "type": "Feature",
  "properties": {
    "iso:country":"US",
    "sg:address":"6526 Hidden Bluff",
    "sg:city":"San Antonio",
    "sg:classifiers":[
        {
            "category":"Social Services",
            "subcategory":"Child Care",
            "type":"Services"
        }
    ],
    "sg:phone":"+1 210 946 8909",
    "sg:postcode":"78218",
    "sg:province":"TX",
    "sg:tags":[
        "day"
    ],
    "wof:name":"Earlie Birds Daycare",
    "wof:placetype":"venue"
},
  "geometry": {"coordinates":[-98.41193800000001,29.488208],"type":"Point"}
}