{
  "type": "Feature",
  "properties": {
    "iso:country":"US",
    "sg:address":"5915 Cannon Mountain Dr",
    "sg:city":"Austin",
    "sg:classifiers":[
        {
            "category":"Professional",
            "subcategory":"Management & Consulting",
            "type":"Services"
        }
    ],
    "sg:phone":"+1 512 394 9578",
    "sg:postcode":"78749",
    "sg:province":"TX",
    "sg:tags":[
        "retail",
        "direct",
        "sales"
    ],
    "wof:name":"Barbara E Parker",
    "wof:placetype":"venue"
},
  "geometry": {"coordinates":[-97.867476,30.222367],"type":"Point"}
}