{
  "type": "Feature",
  "properties": {
    "iso:country":"US",
    "sg:address":"110 S Bolivar St",
    "sg:city":"Marshall",
    "sg:classifiers":[
        {
            "category":"Insurance",
            "subcategory":"Insurance Agent",
            "type":"Services"
        }
    ],
    "sg:phone":"+1 903 938 4000",
    "sg:postcode":"75670",
    "sg:province":"TX",
    "wof:name":"Physical Damage Specialists",
    "wof:placetype":"venue"
},
  "geometry": {"coordinates":[-94.36622300000001,32.54493],"type":"Point"}
}