{
  "type": "Feature",
  "properties": {
    "iso:country":"US",
    "sg:address":"4239 Windhaven Ln",
    "sg:city":"Dallas",
    "sg:classifiers":[
        {
            "category":"Professional",
            "type":"Services"
        }
    ],
    "sg:phone":"+1 972 248 0665",
    "sg:postcode":"75287",
    "sg:province":"TX",
    "wof:name":"Poshe Etc",
    "wof:placetype":"venue"
},
  "geometry": {"coordinates":[-96.838545,33.007757],"type":"Point"}
}