{
  "type": "Feature",
  "properties": {
    "iso:country":"US",
    "sg:address":"3604 Tamarack Trl",
    "sg:city":"Austin",
    "sg:classifiers":[
        {
            "category":"Personal",
            "subcategory":"Day Spa",
            "type":"Services"
        }
    ],
    "sg:phone":"+1 512 244 6931",
    "sg:postcode":"78727",
    "sg:province":"TX",
    "sg:tags":[
        "hot",
        "tub"
    ],
    "wof:name":"Simov Spas",
    "wof:placetype":"venue"
},
  "geometry": {"coordinates":[-97.71222299999999,30.424441],"type":"Point"}
}