{
  "type": "Feature",
  "properties": {
    "iso:country":"US",
    "sg:address":"17 Richardson Hts Ctr",
    "sg:city":"Richardson",
    "sg:classifiers":[
        {
            "category":"Restaurant",
            "type":"Food & Drink"
        }
    ],
    "sg:phone":"+1 972 808 9990",
    "sg:postcode":"75080",
    "sg:province":"TX",
    "sg:tags":[
        "chinese"
    ],
    "wof:name":"Bombay Chinese Restaurant",
    "wof:placetype":"venue"
},
  "geometry": {"coordinates":[-96.73580200000001,32.950901],"type":"Point"}
}