{
  "type": "Feature",
  "properties": {
    "iso:country":"US",
    "sg:address":"8315 Manchester St",
    "sg:city":"Houston",
    "sg:classifiers":[
        {
            "category":"Wholesale",
            "subcategory":"Metals & Minerals",
            "type":"Manufacturing & Wholesale Goods"
        }
    ],
    "sg:phone":"+1 713 928 5611",
    "sg:postcode":"77012",
    "sg:province":"TX",
    "sg:tags":[
        "steel",
        "warehouse"
    ],
    "wof:name":"Ameritech Inc",
    "wof:placetype":"venue"
},
  "geometry": {"coordinates":[-95.27466099999999,29.71826],"type":"Point"}
}