{
  "type": "Feature",
  "properties": {
    "iso:country":"US",
    "sg:address":"1005 W Bitters Rd",
    "sg:city":"San Antonio",
    "sg:classifiers":[
        {
            "category":"Retail",
            "subcategory":"Laundry & Dry Cleaning",
            "type":"Services"
        },
        {
            "category":"Autos & Motor Vehicles",
            "subcategory":"Fuel & Gas Station",
            "type":"Retail Goods"
        }
    ],
    "sg:phone":"+1 210 490 1392",
    "sg:postcode":"78216",
    "sg:province":"TX",
    "sg:tags":[
        "drycleaning",
        "plant",
        "oil"
    ],
    "wof:name":"Express Grocery & Budget Dry C",
    "wof:placetype":"venue"
},
  "geometry": {"coordinates":[-98.505296,29.581547],"type":"Point"}
}