{
  "type": "Feature",
  "properties": {
    "iso:country":"US",
    "sg:address":"2122 Pine Dr",
    "sg:city":"Dickinson",
    "sg:classifiers":[
        {
            "category":"Shopping",
            "subcategory":"Used Merchandise",
            "type":"Retail Goods"
        }
    ],
    "sg:phone":"+1 281 534 2812",
    "sg:postcode":"77539",
    "sg:province":"TX",
    "sg:tags":[
        "shop",
        "thrift"
    ],
    "wof:name":"Thrift Shop",
    "wof:placetype":"venue"
},
  "geometry": {"coordinates":[-95.05972800000001,29.459686],"type":"Point"}
}