{
  "type": "Feature",
  "properties": {
    "iso:country":"US",
    "sg:address":"1201 Co Rd 3390",
    "sg:city":"Paradise",
    "sg:classifiers":[
        {
            "category":"Professional",
            "type":"Services"
        }
    ],
    "sg:phone":"+1 940 969 6101",
    "sg:postcode":"76073",
    "sg:province":"TX",
    "wof:name":"Ronny D Holt",
    "wof:placetype":"venue"
},
  "geometry": {"coordinates":[-97.664862,33.138244],"type":"Point"}
}