{
  "type": "Feature",
  "properties": {
    "iso:country":"US",
    "sg:address":"171 Fawn Ridge Dr",
    "sg:city":"Waxahachie",
    "sg:classifiers":[
        {
            "category":"Manufacturing",
            "subcategory":"Retail Goods",
            "type":"Manufacturing & Wholesale Goods"
        }
    ],
    "sg:phone":"+1 972 642 6626",
    "sg:postcode":"75165",
    "sg:province":"TX",
    "sg:tags":[
        "product",
        "mfg"
    ],
    "wof:name":"Candles By Annette",
    "wof:placetype":"venue"
},
  "geometry": {"coordinates":[-96.82216699999999,32.484841],"type":"Point"}
}