{
  "type": "Feature",
  "properties": {
    "iso:country":"US",
    "sg:address":"518 N Estrella St",
    "sg:city":"El Paso",
    "sg:classifiers":[
        {
            "category":"Organizations",
            "subcategory":"Religious Organization",
            "type":"Services"
        }
    ],
    "sg:phone":"+1 915 565 2370",
    "sg:postcode":"79903",
    "sg:province":"TX",
    "sg:tags":[
        "episcopal",
        "african",
        "methodist",
        "church"
    ],
    "wof:name":"Visitors Chapel African Meth",
    "wof:placetype":"venue"
},
  "geometry": {"coordinates":[-106.45685400000001,31.77947],"type":"Point"}
}