{
  "type": "Feature",
  "properties": {
    "iso:country":"US",
    "sg:address":"42 Sunnygrove Dr",
    "sg:city":"Odessa",
    "sg:classifiers":[
        {
            "category":"Health Services",
            "subcategory":"Doctor",
            "type":"Services"
        }
    ],
    "sg:phone":"+1 432 368 7555",
    "sg:postcode":"79761",
    "sg:province":"TX",
    "sg:tags":[
        "physician",
        "surgeon",
        "medical"
    ],
    "wof:name":"Steven P Wiehle MD",
    "wof:placetype":"venue"
},
  "geometry": {"coordinates":[-102.317898,31.878058],"type":"Point"}
}