{
  "type": "Feature",
  "properties": {
    "iso:country":"US",
    "sg:address":"9670 Old Corpus Christi Hwy",
    "sg:city":"San Antonio",
    "sg:classifiers":[
        {
            "category":"Arts & Performance",
            "subcategory":"Theater",
            "type":"Entertainment"
        }
    ],
    "sg:phone":"+1 210 633 3774",
    "sg:postcode":"78223",
    "sg:province":"TX",
    "sg:tags":[
        "entertainer",
        "business"
    ],
    "wof:name":"All Pro C & W Singing DJ",
    "wof:placetype":"venue"
},
  "geometry": {"coordinates":[-98.41299600000001,29.325224],"type":"Point"}
}