{
  "type": "Feature",
  "properties": {
    "iso:country":"US",
    "sg:address":"2312 Blalock Dr",
    "sg:city":"Austin",
    "sg:classifiers":[
        {
            "category":"Banks & Credit Unions",
            "subcategory":"Investment Brokerage",
            "type":"Services"
        }
    ],
    "sg:phone":"+1 512 833 8007",
    "sg:postcode":"78758",
    "sg:province":"TX",
    "wof:name":"Gray Capital Partners LLC",
    "wof:placetype":"venue"
},
  "geometry": {"coordinates":[-97.702067,30.416662],"type":"Point"}
}