{
  "type": "Feature",
  "properties": {
    "iso:country":"US",
    "sg:address":"9569 Grape Creek Rd",
    "sg:city":"San Angelo",
    "sg:classifiers":[
        {
            "category":"Shopping",
            "subcategory":"Jewelry",
            "type":"Retail Goods"
        }
    ],
    "sg:phone":"+1 325 655 1494",
    "sg:postcode":"76901",
    "sg:province":"TX",
    "wof:name":"Treasure Chest",
    "wof:placetype":"venue"
},
  "geometry": {"coordinates":[-100.54736,31.57696],"type":"Point"}
}