{
  "type": "Feature",
  "properties": {
    "iso:country":"US",
    "sg:address":"16345 Judson Rd",
    "sg:city":"San Antonio",
    "sg:classifiers":[
        {
            "category":"Social Services",
            "subcategory":"Child Care",
            "type":"Services"
        }
    ],
    "sg:phone":"+1 210 654 8618",
    "sg:postcode":"78233",
    "sg:province":"TX",
    "wof:name":"LA Petite Academy",
    "wof:placetype":"venue"
},
  "geometry": {"coordinates":[-98.378992,29.589503],"type":"Point"}
}