{
  "type": "Feature",
  "properties": {
    "iso:country":"US",
    "sg:address":"1405 US Hwy 271",
    "sg:city":"Gilmer",
    "sg:classifiers":[
        {
            "category":"Building & Trades",
            "subcategory":"Construction",
            "type":"Services"
        }
    ],
    "sg:phone":"+1 903 790 1551",
    "sg:postcode":"75644",
    "sg:province":"TX",
    "sg:tags":[
        "hanging",
        "contractor"
    ],
    "wof:name":"Watson Painting",
    "wof:placetype":"venue"
},
  "geometry": {"coordinates":[-94.941406,32.742584],"type":"Point"}
}