{
  "type": "Feature",
  "properties": {
    "iso:country":"US",
    "sg:address":"108 N Broadway St",
    "sg:city":"Ballinger",
    "sg:classifiers":[
        {
            "category":"Restaurant",
            "type":"Food & Drink"
        }
    ],
    "sg:phone":"+1 325 365 2481",
    "sg:postcode":"76821",
    "sg:province":"TX",
    "sg:tags":[
        "eating"
    ],
    "wof:name":"Ballinger Burger Hut",
    "wof:placetype":"venue"
},
  "geometry": {"coordinates":[-99.947374,31.73997],"type":"Point"}
}