{
  "type": "Feature",
  "properties": {
    "iso:country":"US",
    "sg:address":"917 J Pl",
    "sg:city":"Plano",
    "sg:classifiers":[
        {
            "category":"Building & Trades",
            "subcategory":"Construction",
            "type":"Services"
        }
    ],
    "sg:phone":"+1 972 424 5790",
    "sg:postcode":"75074",
    "sg:province":"TX",
    "sg:tags":[
        "concrete",
        "contractor"
    ],
    "wof:name":"Espinosa Concrete Brothers",
    "wof:placetype":"venue"
},
  "geometry": {"coordinates":[-96.700185,33.010313],"type":"Point"}
}