{
  "type": "Feature",
  "properties": {
    "iso:country":"US",
    "sg:address":"2330 Rock Island Rd",
    "sg:city":"Irving",
    "sg:classifiers":[
        {
            "category":"Professional",
            "subcategory":"Accounting & Tax Preparation",
            "type":"Services"
        }
    ],
    "sg:phone":"+1 972 253 1999",
    "sg:postcode":"75060",
    "sg:province":"TX",
    "sg:tags":[
        "return",
        "filing"
    ],
    "wof:name":"Luceros Income Tax Svc",
    "wof:placetype":"venue"
},
  "geometry": {"coordinates":[-96.97485,32.815222],"type":"Point"}
}