{
  "type": "Feature",
  "properties": {
    "iso:country":"US",
    "sg:address":"2435 Stillmeadow Dr",
    "sg:city":"Missouri City",
    "sg:classifiers":[
        {
            "category":"Professional",
            "subcategory":"Business Services",
            "type":"Services"
        }
    ],
    "sg:phone":"+1 281 437 0442",
    "sg:postcode":"77489",
    "sg:province":"TX",
    "wof:name":"Starting Point Recovery C",
    "wof:placetype":"venue"
},
  "geometry": {"coordinates":[-95.540513,29.579274],"type":"Point"}
}