{
  "type": "Feature",
  "properties": {
    "iso:country":"US",
    "sg:address":"407 E 2nd St",
    "sg:city":"Rio Grande City",
    "sg:classifiers":[
        {
            "category":"Shopping",
            "subcategory":"Discount & Variety Stores",
            "type":"Retail Goods"
        }
    ],
    "sg:phone":"+1 956 488 9433",
    "sg:postcode":"78582",
    "sg:province":"TX",
    "sg:tags":[
        "merchandise",
        "general"
    ],
    "wof:name":"99 Cent Store",
    "wof:placetype":"venue"
},
  "geometry": {"coordinates":[-98.817381,26.379052],"type":"Point"}
}