{
  "type": "Feature",
  "properties": {
    "iso:country":"US",
    "sg:address":"54 Glen Knoll Dr",
    "sg:city":"Wylie",
    "sg:classifiers":[
        {
            "category":"Organizations",
            "subcategory":"Labor Organization",
            "type":"Services"
        }
    ],
    "sg:phone":"+1 972 442 0603",
    "sg:postcode":"75098",
    "sg:province":"TX",
    "wof:name":"Allied Trades Co",
    "wof:placetype":"venue"
},
  "geometry": {"coordinates":[-96.55680700000001,32.99399],"type":"Point"}
}