{
  "type": "Feature",
  "properties": {
    "iso:country":"US",
    "sg:address":"506 State Hwy 214",
    "sg:city":"Denver City",
    "sg:classifiers":[
        {
            "category":"Recreation",
            "type":"Entertainment"
        }
    ],
    "sg:phone":"+1 806 592 9128",
    "sg:postcode":"79323",
    "sg:province":"TX",
    "sg:tags":[
        "pool",
        "swimming"
    ],
    "wof:name":"Pool Co Texas LTD",
    "wof:placetype":"venue"
},
  "geometry": {"coordinates":[-102.819007,32.969838],"type":"Point"}
}