{
  "type": "Feature",
  "properties": {
    "iso:country":"US",
    "sg:address":"6105 Nunn St",
    "sg:city":"Houston",
    "sg:classifiers":[
        {
            "category":"Manufacturing",
            "subcategory":"Metals",
            "type":"Manufacturing & Wholesale Goods"
        },
        {
            "category":"Building & Trades",
            "subcategory":"Construction",
            "type":"Services"
        }
    ],
    "sg:phone":"+1 713 644 4900",
    "sg:postcode":"77087",
    "sg:province":"TX",
    "sg:tags":[
        "steel",
        "detailers",
        "warehouse",
        "fabricator",
        "distributor",
        "metal-wholesale",
        "mill",
        "manufacturer",
        "structural"
    ],
    "sg:website":"http://www.jarcosteel.com",
    "wof:name":"Jarco Steel Inc",
    "wof:placetype":"venue"
},
  "geometry": {"coordinates":[-95.311279,29.676665],"type":"Point"}
}