{
  "type": "Feature",
  "properties": {
    "iso:country":"US",
    "sg:address":"495 Medical Center Blvd",
    "sg:city":"Webster",
    "sg:classifiers":[
        {
            "category":"Building & Trades",
            "subcategory":"Electrical",
            "type":"Services"
        }
    ],
    "sg:phone":"+1 281 316 3662",
    "sg:postcode":"77598",
    "sg:province":"TX",
    "sg:tags":[
        "electrical",
        "contractor"
    ],
    "wof:name":"Kenmor Electric Co L P",
    "wof:placetype":"venue"
},
  "geometry": {"coordinates":[-95.1268,29.54065],"type":"Point"}
}