{
  "type": "Feature",
  "properties": {
    "iso:country":"US",
    "sg:address":"6411 Fannin St",
    "sg:city":"Houston",
    "sg:classifiers":[
        {
            "category":"Health Services",
            "subcategory":"Doctor",
            "type":"Services"
        }
    ],
    "sg:phone":"+1 713 704 4000",
    "sg:postcode":"77030",
    "sg:province":"TX",
    "wof:name":"Flores Maria Md",
    "wof:placetype":"venue"
},
  "geometry": {"coordinates":[-95.39625599999999,29.715184],"type":"Point"}
}