{
  "type": "Feature",
  "properties": {
    "iso:country":"US",
    "sg:address":"11918 Swan Dr",
    "sg:city":"Austin",
    "sg:classifiers":[
        {
            "category":"Retail",
            "subcategory":"Car Wash",
            "type":"Services"
        }
    ],
    "sg:phone":"+1 512 918 3996",
    "sg:postcode":"78750",
    "sg:province":"TX",
    "sg:tags":[
        "carwash"
    ],
    "wof:name":"Mr Suds Wash Tear Inc",
    "wof:placetype":"venue"
},
  "geometry": {"coordinates":[-97.80007500000001,30.449293],"type":"Point"}
}