{
  "type": "Feature",
  "properties": {
    "iso:country":"US",
    "sg:address":"4513 Hogan Dr",
    "sg:city":"Corpus Christi",
    "sg:classifiers":[
        {
            "category":"Manufacturing",
            "subcategory":"Paper Products",
            "type":"Manufacturing & Wholesale Goods"
        }
    ],
    "sg:phone":"+1 361 854 0156",
    "sg:postcode":"78413",
    "sg:province":"TX",
    "sg:tags":[
        "converted",
        "mfg"
    ],
    "wof:name":"Janet Ungerer",
    "wof:placetype":"venue"
},
  "geometry": {"coordinates":[-97.40467599999999,27.690477],"type":"Point"}
}