{
  "type": "Feature",
  "properties": {
    "iso:country":"US",
    "sg:address":"3300 E Park Row Dr",
    "sg:city":"Arlington",
    "sg:classifiers":[
        {
            "category":"Freight",
            "type":"Transportation"
        }
    ],
    "sg:phone":"+1 817 652 4710",
    "sg:postcode":"76010",
    "sg:province":"TX",
    "sg:tags":[
        "trucking"
    ],
    "wof:name":"Refrigerated Transport Inc",
    "wof:placetype":"venue"
},
  "geometry": {"coordinates":[-97.04927000000001,32.720563],"type":"Point"}
}