{
  "type": "Feature",
  "properties": {
    "iso:country":"US",
    "sg:address":"1777 S Avondale St",
    "sg:city":"Amarillo",
    "sg:classifiers":[
        {
            "category":"Retail",
            "subcategory":"Animal Services",
            "type":"Services"
        }
    ],
    "sg:phone":"+1 806 353 1798",
    "sg:postcode":"79106",
    "sg:province":"TX",
    "sg:tags":[
        "breeder",
        "dog"
    ],
    "wof:name":"Dog Spa Self Serve Dog Wash",
    "wof:placetype":"venue"
},
  "geometry": {"coordinates":[-101.893247,35.195972],"type":"Point"}
}