{
  "type": "Feature",
  "properties": {
    "iso:country":"US",
    "sg:address":"803 N Frazier St",
    "sg:city":"Conroe",
    "sg:classifiers":[
        {
            "category":"Retail",
            "subcategory":"Auto Repair",
            "type":"Services"
        }
    ],
    "sg:phone":"+1 936 588 2888",
    "sg:postcode":"77301",
    "sg:province":"TX",
    "sg:tags":[
        "glass",
        "coating",
        "tinting"
    ],
    "wof:name":"Texan Tinters",
    "wof:placetype":"venue"
},
  "geometry": {"coordinates":[-95.46332200000001,30.31656],"type":"Point"}
}