{
  "type": "Feature",
  "properties": {
    "iso:country":"US",
    "sg:address":"8214 Westchester Dr",
    "sg:city":"Dallas",
    "sg:classifiers":[
        {
            "category":"Banks & Credit Unions",
            "subcategory":"Investment Brokerage",
            "type":"Services"
        },
        {
            "category":"Professional",
            "subcategory":"Research",
            "type":"Services"
        }
    ],
    "sg:phone":"+1 214 692 3592",
    "sg:postcode":"75225",
    "sg:province":"TX",
    "sg:tags":[
        "merger",
        "banker",
        "acquisition"
    ],
    "wof:name":"Corporate Finance Associates",
    "wof:placetype":"venue"
},
  "geometry": {"coordinates":[-96.806494,32.863415],"type":"Point"}
}