{
  "type": "Feature",
  "properties": {
    "iso:country":"US",
    "sg:address":"530 Canada St",
    "sg:city":"Jacksonville",
    "sg:classifiers":[
        {
            "category":"Social Services",
            "subcategory":"Child Care",
            "type":"Services"
        }
    ],
    "sg:phone":"+1 903 586 8542",
    "sg:postcode":"75766",
    "sg:province":"TX",
    "sg:tags":[
        "nursery",
        "day"
    ],
    "wof:name":"Hi Knee Village",
    "wof:placetype":"venue"
},
  "geometry": {"coordinates":[-95.265799,31.956558],"type":"Point"}
}