{
  "type": "Feature",
  "properties": {
    "iso:country":"US",
    "sg:address":"2211 N Fry Rd",
    "sg:city":"Katy",
    "sg:classifiers":[
        {
            "category":"Shopping",
            "subcategory":"Florist",
            "type":"Retail Goods"
        }
    ],
    "sg:phone":"+1 281 859 6656",
    "sg:postcode":"77449",
    "sg:province":"TX",
    "wof:name":"Absolute Bliss Flowers & Gifts",
    "wof:placetype":"venue"
},
  "geometry": {"coordinates":[-95.719086,29.798448],"type":"Point"}
}