{
  "type": "Feature",
  "properties": {
    "iso:country":"US",
    "sg:address":"3615 Reveille St",
    "sg:city":"Houston",
    "sg:classifiers":[
        {
            "category":"Personal",
            "subcategory":"Beauty Salon",
            "type":"Services"
        }
    ],
    "sg:phone":"+1 713 645 7510",
    "sg:postcode":"77087",
    "sg:province":"TX",
    "wof:name":"Elsa's Hair Salon",
    "wof:placetype":"venue"
},
  "geometry": {"coordinates":[-95.29031500000001,29.690014],"type":"Point"}
}