{
  "type": "Feature",
  "properties": {
    "iso:country":"US",
    "sg:address":"4005 Dogwood Ln",
    "sg:city":"Fort Worth",
    "sg:classifiers":[
        {
            "category":"Farming",
            "subcategory":"Livestock Farm",
            "type":"Manufacturing & Wholesale Goods"
        }
    ],
    "sg:phone":"+1 817 306 0041",
    "sg:postcode":"76137",
    "sg:province":"TX",
    "sg:tags":[
        "specialty",
        "animal"
    ],
    "wof:name":"Ramblin Maxx Retrievers",
    "wof:placetype":"venue"
},
  "geometry": {"coordinates":[-97.293504,32.869605],"type":"Point"}
}