{
  "type": "Feature",
  "properties": {
    "iso:country":"US",
    "sg:address":"702 W Moore Ave",
    "sg:city":"Terrell",
    "sg:classifiers":[
        {
            "category":"Professional",
            "type":"Services"
        }
    ],
    "sg:phone":"+1 972 563 2445",
    "sg:postcode":"75160",
    "sg:province":"TX",
    "sg:tags":[
        "organizing",
        "business",
        "services-household"
    ],
    "wof:name":"Beans Creek Inc",
    "wof:placetype":"venue"
},
  "geometry": {"coordinates":[-96.28479799999999,32.73732],"type":"Point"}
}