{
  "type": "Feature",
  "properties": {
    "iso:country":"US",
    "sg:address":"3903 Red River St",
    "sg:city":"Austin",
    "sg:classifiers":[
        {
            "category":"Real Estate",
            "subcategory":"Real Estate Agent",
            "type":"Services"
        }
    ],
    "sg:phone":"+1 512 454 6934",
    "sg:postcode":"78751",
    "sg:province":"TX",
    "wof:name":"Husbands Co Real Estate Svc",
    "wof:placetype":"venue"
},
  "geometry": {"coordinates":[-97.722568,30.298539],"type":"Point"}
}