{
  "type": "Feature",
  "properties": {
    "iso:country":"US",
    "sg:address":"11608 Cameron Rd",
    "sg:city":"Austin",
    "sg:classifiers":[
        {
            "category":"Utilities",
            "subcategory":"Refuse",
            "type":"Services"
        }
    ],
    "sg:phone":"+1 512 784 7645",
    "sg:postcode":"78754",
    "sg:province":"TX",
    "sg:tags":[
        "garbage",
        "collection"
    ],
    "wof:name":"Alley Cat Hauling & Trailer",
    "wof:placetype":"venue"
},
  "geometry": {"coordinates":[-97.635773,30.355672],"type":"Point"}
}