{
  "type": "Feature",
  "properties": {
    "iso:country":"US",
    "sg:address":"4000 Parkside Center Blvd",
    "sg:city":"Farmers Branch",
    "sg:classifiers":[
        {
            "category":"Building & Trades",
            "subcategory":"Cleaning & Sanitation",
            "type":"Services"
        }
    ],
    "sg:phone":"+1 972 247 0332",
    "sg:postcode":"75244",
    "sg:province":"TX",
    "sg:tags":[
        "janitor"
    ],
    "wof:name":"Rowland Building Svc",
    "wof:placetype":"venue"
},
  "geometry": {"coordinates":[-96.83981900000001,32.939178],"type":"Point"}
}