{
  "type": "Feature",
  "properties": {
    "iso:country":"US",
    "sg:address":"2641 US Hwy 70",
    "sg:city":"Plainview",
    "sg:classifiers":[
        {
            "category":"Farming",
            "subcategory":"Farm & Veterinary Services",
            "type":"Manufacturing & Wholesale Goods"
        }
    ],
    "sg:phone":"+1 806 296 6965",
    "sg:postcode":"79072",
    "sg:province":"TX",
    "sg:tags":[
        "business",
        "crop",
        "harvesting"
    ],
    "wof:name":"Hale County Spraying Inc",
    "wof:placetype":"venue"
},
  "geometry": {"coordinates":[-101.66003600000001,34.184016],"type":"Point"}
}