{
  "type": "Feature",
  "properties": {
    "iso:country":"US",
    "sg:address":"303 S Dogwood St",
    "sg:city":"Pharr",
    "sg:classifiers":[
        {
            "category":"Education",
            "subcategory":"School",
            "type":"Public Place"
        }
    ],
    "sg:phone":"+1 956 702 5808",
    "sg:postcode":"78577",
    "sg:province":"TX",
    "wof:name":"Computer Lab Central High Schl",
    "wof:placetype":"venue"
},
  "geometry": {"coordinates":[-98.178847,26.190626],"type":"Point"}
}