{
  "type": "Feature",
  "properties": {
    "iso:country":"US",
    "sg:address":"1515 State Hwy 1604",
    "sg:city":"San Antonio",
    "sg:classifiers":[
        {
            "category":"Health Services",
            "subcategory":"Doctor",
            "type":"Services"
        }
    ],
    "sg:phone":"+1 210 545 1680",
    "sg:postcode":"78232",
    "sg:province":"TX",
    "sg:tags":[
        "physician",
        "surgeon"
    ],
    "wof:name":"Jeff Elkins MD",
    "wof:placetype":"venue"
},
  "geometry": {"coordinates":[-98.473848,29.610312],"type":"Point"}
}