{
  "type": "Feature",
  "properties": {
    "iso:country":"US",
    "sg:address":"12129 Ranch Rd 620 N",
    "sg:city":"Austin",
    "sg:classifiers":[
        {
            "category":"Social Services",
            "subcategory":"Child Care",
            "type":"Services"
        }
    ],
    "sg:phone":"+1 512 336 2986",
    "sg:postcode":"78750",
    "sg:province":"TX",
    "sg:tags":[
        "day"
    ],
    "wof:name":"Seton Health Partners",
    "wof:placetype":"venue"
},
  "geometry": {"coordinates":[-97.81843600000001,30.461314],"type":"Point"}
}