{
  "type": "Feature",
  "properties": {
    "iso:country":"US",
    "sg:address":"256 N Collins St",
    "sg:city":"Arlington",
    "sg:classifiers":[
        {
            "category":"Manufacturing",
            "subcategory":"Food",
            "type":"Manufacturing & Wholesale Goods"
        }
    ],
    "sg:phone":"+1 817 860 6558",
    "sg:postcode":"76011",
    "sg:province":"TX",
    "sg:tags":[
        "product",
        "retail",
        "bakery",
        "mfg"
    ],
    "wof:name":"Collins Donuts",
    "wof:placetype":"venue"
},
  "geometry": {"coordinates":[-97.097443,32.738495],"type":"Point"}
}