{
  "type": "Feature",
  "properties": {
    "iso:country":"US",
    "sg:address":"1813 Island View Dr",
    "sg:city":"Mesquite",
    "sg:classifiers":[
        {
            "category":"Insurance",
            "subcategory":"Insurance Agent",
            "type":"Services"
        }
    ],
    "sg:phone":"+1 972 216 7017",
    "sg:postcode":"75149",
    "sg:province":"TX",
    "wof:name":"Dlg Insurance Agency",
    "wof:placetype":"venue"
},
  "geometry": {"coordinates":[-96.57196,32.76014],"type":"Point"}
}