{
  "type": "Feature",
  "properties": {
    "iso:country":"US",
    "sg:address":"1422 E Highway 377",
    "sg:city":"Granbury",
    "sg:classifiers":[
        {
            "category":"Food & Beverages",
            "subcategory":"Liquor & Beverages",
            "type":"Retail Goods"
        }
    ],
    "sg:phone":"+1 817 579 8511",
    "sg:postcode":"76048",
    "sg:province":"TX",
    "sg:tags":[
        "store"
    ],
    "wof:name":"Larry's Liquor",
    "wof:placetype":"venue"
},
  "geometry": {"coordinates":[-97.76563899999999,32.437972],"type":"Point"}
}