{
  "type": "Feature",
  "properties": {
    "iso:country":"US",
    "sg:address":"4125 Broadway Blvd",
    "sg:city":"Garland",
    "sg:classifiers":[
        {
            "category":"Banks & Credit Unions",
            "subcategory":"Bank",
            "type":"Services"
        }
    ],
    "sg:phone":"+1 972 303 9161",
    "sg:postcode":"75043",
    "sg:province":"TX",
    "sg:tags":[
        "loan",
        "mortgage",
        "real estate"
    ],
    "wof:name":"Banksource Mortgage",
    "wof:placetype":"venue"
},
  "geometry": {"coordinates":[-96.603988,32.863346],"type":"Point"}
}