{
  "type": "Feature",
  "properties": {
    "iso:country":"US",
    "sg:address":"319 E Spruce St",
    "sg:city":"Whitewright",
    "sg:classifiers":[
        {
            "category":"Retail",
            "subcategory":"Portrait Studio",
            "type":"Services"
        }
    ],
    "sg:phone":"+1 903 364 9117",
    "sg:postcode":"75491",
    "sg:province":"TX",
    "sg:tags":[
        "photo"
    ],
    "wof:name":"Jennys Hometown Photography",
    "wof:placetype":"venue"
},
  "geometry": {"coordinates":[-96.389516,33.510496],"type":"Point"}
}