{
  "type": "Feature",
  "properties": {
    "iso:country":"US",
    "sg:address":"1821 Bingle Rd",
    "sg:city":"Houston",
    "sg:classifiers":[
        {
            "category":"Travel",
            "subcategory":"Travel Agent",
            "type":"Entertainment"
        }
    ],
    "sg:phone":"+1 713 788 2447",
    "sg:postcode":"77055",
    "sg:province":"TX",
    "sg:tags":[
        "agency"
    ],
    "wof:name":"Envios Atencingo & Travel",
    "wof:placetype":"venue"
},
  "geometry": {"coordinates":[-95.50097100000001,29.803652],"type":"Point"}
}