{
  "type": "Feature",
  "properties": {
    "iso:country":"US",
    "sg:address":"7909 Owl Creek Ln",
    "sg:city":"Mc Kinney",
    "sg:classifiers":[
        {
            "category":"Professional",
            "subcategory":"Management & Consulting",
            "type":"Services"
        }
    ],
    "sg:phone":"+1 972 562 1427",
    "sg:postcode":"75070",
    "sg:province":"TX",
    "wof:name":"Prather Marketing Communicatio",
    "wof:placetype":"venue"
},
  "geometry": {"coordinates":[-96.720643,33.180746],"type":"Point"}
}