{
  "type": "Feature",
  "properties": {
    "iso:country":"US",
    "sg:address":"6129 W Main St",
    "sg:city":"Frisco",
    "sg:classifiers":[
        {
            "category":"Professional",
            "type":"Services"
        },
        {
            "category":"Restaurant",
            "type":"Food & Drink"
        }
    ],
    "sg:phone":"+1 214 872 3411",
    "sg:postcode":"75034",
    "sg:province":"TX",
    "sg:tags":[
        "mexican",
        "caterer"
    ],
    "sg:website":"http://www.mattitos.com/locations/frisco-location/",
    "wof:name":"Mattito's Cafe Mexicano",
    "wof:placetype":"venue"
},
  "geometry": {"coordinates":[-96.83475799999999,33.152817],"type":"Point"}
}