{
  "type": "Feature",
  "properties": {
    "iso:country":"US",
    "sg:address":"9600 Bellaire Blvd Ste 229",
    "sg:city":"Houston",
    "sg:classifiers":[
        {
            "category":"Organizations",
            "subcategory":"Religious Organization",
            "type":"Services"
        }
    ],
    "sg:phone":"+1 713 778 1144",
    "sg:postcode":"77036",
    "sg:province":"TX",
    "wof:name":"Christian Communications Inc of USA",
    "wof:placetype":"venue"
},
  "geometry": {"coordinates":[-95.550848,29.706033],"type":"Point"}
}