{
  "type": "Feature",
  "properties": {
    "iso:country":"US",
    "sg:address":"218 Connally St",
    "sg:city":"Sulphur Springs",
    "sg:classifiers":[
        {
            "category":"Organizations",
            "subcategory":"Non-profit Organization",
            "type":"Services"
        }
    ],
    "sg:phone":"+1 903 885 1173",
    "sg:postcode":"75482",
    "sg:province":"TX",
    "sg:tags":[
        "special",
        "court",
        "appointed",
        "advocacy",
        "for"
    ],
    "wof:name":"Lake Country CASA",
    "wof:placetype":"venue"
},
  "geometry": {"coordinates":[-95.602165,33.1383],"type":"Point"}
}