{
  "type": "Feature",
  "properties": {
    "iso:country":"US",
    "sg:address":"12801 Lexington St",
    "sg:city":"Manor",
    "sg:classifiers":[
        {
            "category":"Sports & Exercise",
            "subcategory":"Golf",
            "type":"Entertainment"
        }
    ],
    "sg:phone":"+1 512 278 1304",
    "sg:postcode":"78653",
    "sg:province":"TX",
    "wof:name":"Shadowglen Golf Club",
    "wof:placetype":"venue"
},
  "geometry": {"coordinates":[-97.569,30.369801],"type":"Point"}
}