{
  "type": "Feature",
  "properties": {
    "iso:country":"US",
    "sg:address":"801 E 9th St",
    "sg:city":"Del Rio",
    "sg:classifiers":[
        {
            "category":"Real Estate",
            "subcategory":"Real Estate Operator",
            "type":"Services"
        }
    ],
    "sg:phone":"+1 830 775 5366",
    "sg:postcode":"78840",
    "sg:province":"TX",
    "sg:tags":[
        "apartment"
    ],
    "wof:name":"English Village Apartments",
    "wof:placetype":"venue"
},
  "geometry": {"coordinates":[-100.897458,29.375524],"type":"Point"}
}