{
  "type": "Feature",
  "properties": {
    "iso:country":"US",
    "sg:address":"1502 Pine Knoll Drive",
    "sg:city":"Austin",
    "sg:classifiers":[
        {
            "category":"Building & Trades",
            "subcategory":"Landscaping Services",
            "type":"Services"
        }
    ],
    "sg:phone":"+1 512 293 0651",
    "sg:postcode":"78758",
    "sg:province":"TX",
    "wof:name":"Austin Landscaping & More",
    "wof:placetype":"venue"
},
  "geometry": {"coordinates":[-97.70277400000001,30.380341],"type":"Point"}
}