{
  "type": "Feature",
  "properties": {
    "iso:country":"US",
    "sg:address":"505 N Big Spring St",
    "sg:city":"Midland",
    "sg:classifiers":[
        {
            "category":"Real Estate",
            "subcategory":"Real Estate Operator",
            "type":"Services"
        }
    ],
    "sg:phone":"+1 432 682 5219",
    "sg:postcode":"79701",
    "sg:province":"TX",
    "sg:tags":[
        "building",
        "parks"
    ],
    "wof:name":"Energy Square Building",
    "wof:placetype":"venue"
},
  "geometry": {"coordinates":[-102.07829700000001,32.002609],"type":"Point"}
}