{
  "type": "Feature",
  "properties": {
    "iso:country":"US",
    "sg:address":"3920 Kirby Dr",
    "sg:city":"Denton",
    "sg:classifiers":[
        {
            "category":"Professional",
            "subcategory":"Management & Consulting",
            "type":"Services"
        }
    ],
    "sg:phone":"+1 940 387 2785",
    "sg:postcode":"76210",
    "sg:province":"TX",
    "wof:name":"Smart Alliance LLC",
    "wof:placetype":"venue"
},
  "geometry": {"coordinates":[-97.10198099999999,33.163975],"type":"Point"}
}