{
  "type": "Feature",
  "properties": {
    "iso:country":"US",
    "sg:address":"8604 Chisholm Trl",
    "sg:city":"Crossroads",
    "sg:classifiers":[
        {
            "category":"Structure",
            "subcategory":"Office Building",
            "type":"Public Place"
        }
    ],
    "sg:phone":"+1 940 206 0633",
    "sg:postcode":"76227",
    "sg:province":"TX",
    "sg:tags":[
        "park"
    ],
    "wof:name":"Curry Properties",
    "wof:placetype":"venue"
},
  "geometry": {"coordinates":[-96.98286400000001,33.206247],"type":"Point"}
}