{
  "type": "Feature",
  "properties": {
    "iso:country":"US",
    "sg:address":"115 Warden Ln",
    "sg:city":"San Marcos",
    "sg:classifiers":[
        {
            "category":"Health Services",
            "subcategory":"Doctor",
            "type":"Services"
        }
    ],
    "sg:phone":"+1 512 754 3408",
    "sg:postcode":"78666",
    "sg:province":"TX",
    "sg:tags":[
        "medical"
    ],
    "wof:name":"Dr Stuart Damore",
    "wof:placetype":"venue"
},
  "geometry": {"coordinates":[-97.920344,29.89159],"type":"Point"}
}