{
  "type": "Feature",
  "properties": {
    "iso:country":"US",
    "sg:address":"22823 Bucktrout Ln",
    "sg:city":"Katy",
    "sg:classifiers":[
        {
            "category":"Insurance",
            "subcategory":"Insurance Agent",
            "type":"Services"
        }
    ],
    "sg:phone":"+1 281 347 9307",
    "sg:postcode":"77449",
    "sg:province":"TX",
    "wof:name":"Stll Fnncl Plnng Svc",
    "wof:placetype":"venue"
},
  "geometry": {"coordinates":[-95.767921,29.797736],"type":"Point"}
}