{
  "type": "Feature",
  "properties": {
    "iso:country":"US",
    "sg:address":"1023 E Main St",
    "sg:city":"Mexia",
    "sg:classifiers":[
        {
            "category":"Social Services",
            "type":"Services"
        }
    ],
    "sg:phone":"+1 254 562 2610",
    "sg:postcode":"76667",
    "sg:province":"TX",
    "sg:tags":[
        "organization",
        "welfare"
    ],
    "wof:name":"HCCAA Inc",
    "wof:placetype":"venue"
},
  "geometry": {"coordinates":[-96.470614,31.681216],"type":"Point"}
}