{
  "type": "Feature",
  "properties": {
    "iso:country":"US",
    "sg:address":"11455 Bissonnet St",
    "sg:city":"Houston",
    "sg:classifiers":[
        {
            "category":"Professional",
            "subcategory":"Business Services",
            "type":"Services"
        }
    ],
    "sg:phone":"+1 281 568 4267",
    "sg:postcode":"77099",
    "sg:province":"TX",
    "wof:name":"Global Business Mktng Sltns",
    "wof:placetype":"venue"
},
  "geometry": {"coordinates":[-95.581881,29.674827],"type":"Point"}
}