{
  "type": "Feature",
  "properties": {
    "iso:country":"US",
    "sg:address":"2020 W Houston Ave",
    "sg:city":"Mcallen",
    "sg:classifiers":[
        {
            "category":"Manufacturing",
            "subcategory":"Printing",
            "type":"Manufacturing & Wholesale Goods"
        }
    ],
    "sg:phone":"+1 956 631 9884",
    "sg:postcode":"78501",
    "sg:province":"TX",
    "sg:tags":[
        "publishing"
    ],
    "wof:name":"Ser CA Entertainment Inc",
    "wof:placetype":"venue"
},
  "geometry": {"coordinates":[-98.243123,26.197751],"type":"Point"}
}