{
  "type": "Feature",
  "properties": {
    "iso:country":"US",
    "sg:address":"1105 S Gabriel Dr",
    "sg:city":"Leander",
    "sg:classifiers":[
        {
            "category":"Building & Trades",
            "subcategory":"Construction",
            "type":"Services"
        }
    ],
    "sg:phone":"+1 512 249 5595",
    "sg:postcode":"78641",
    "sg:province":"TX",
    "sg:tags":[
        "concrete",
        "contractor"
    ],
    "wof:name":"Austin Capitol Concrete Inc",
    "wof:placetype":"venue"
},
  "geometry": {"coordinates":[-97.84993,30.616343],"type":"Point"}
}