{
  "type": "Feature",
  "properties": {
    "iso:country":"US",
    "sg:address":"8200 John W Carpenter Fwy",
    "sg:city":"Dallas",
    "sg:classifiers":[
        {
            "category":"Autos & Motor Vehicles",
            "subcategory":"Automobile Sales",
            "type":"Retail Goods"
        }
    ],
    "sg:phone":"+1 214 688 0900",
    "sg:postcode":"75247",
    "sg:province":"TX",
    "sg:tags":[
        "car"
    ],
    "sg:website":"www.enterprise.com",
    "wof:name":"Enterprise 1 800 Car Sales",
    "wof:placetype":"venue"
},
  "geometry": {"coordinates":[-96.876801,32.821999],"type":"Point"}
}