{
  "type": "Feature",
  "properties": {
    "iso:country":"US",
    "sg:address":"11218 Jade Green",
    "sg:city":"San Antonio",
    "sg:classifiers":[
        {
            "category":"Education",
            "subcategory":"School",
            "type":"Public Place"
        }
    ],
    "sg:phone":"+1 210 694 0991",
    "sg:postcode":"78249",
    "sg:province":"TX",
    "wof:name":"Lawton International",
    "wof:placetype":"venue"
},
  "geometry": {"coordinates":[-98.60877499999999,29.54554],"type":"Point"}
}