{
  "type": "Feature",
  "properties": {
    "iso:country":"US",
    "sg:address":"11643 Research Boulevard",
    "sg:city":"Austin",
    "sg:classifiers":[
        {
            "category":"Food & Beverages",
            "subcategory":"Groceries & Convenience Stores",
            "type":"Retail Goods"
        }
    ],
    "sg:phone":"+1 512 338 0326",
    "sg:postcode":"78759",
    "sg:province":"TX",
    "wof:name":"Speedy Stop",
    "wof:placetype":"venue"
},
  "geometry": {"coordinates":[-97.74612999999999,30.416548],"type":"Point"}
}