{
  "type": "Feature",
  "properties": {
    "iso:country":"US",
    "sg:address":"1801 Ocean Dr",
    "sg:city":"Corpus Christi",
    "sg:classifiers":[
        {
            "category":"Wholesale",
            "subcategory":"Durable Goods & Equipment",
            "type":"Manufacturing & Wholesale Goods"
        }
    ],
    "sg:phone":"+1 361 888 8729",
    "sg:postcode":"78404",
    "sg:province":"TX",
    "wof:name":"Gromark International",
    "wof:placetype":"venue"
},
  "geometry": {"coordinates":[-97.390829,27.772432],"type":"Point"}
}