{
  "type": "Feature",
  "properties": {
    "iso:country":"US",
    "sg:address":"908 Southmore Ave Ste 380",
    "sg:city":"Pasadena",
    "sg:classifiers":[
        {
            "category":"Health Services",
            "subcategory":"Doctor",
            "type":"Services"
        }
    ],
    "sg:phone":"+1 713 477 8600",
    "sg:postcode":"77502",
    "sg:province":"TX",
    "wof:name":"Hampel Ori MD PA",
    "wof:placetype":"venue"
},
  "geometry": {"coordinates":[-95.202698,29.6908],"type":"Point"}
}