{
  "type": "Feature",
  "properties": {
    "iso:country":"US",
    "sg:address":"1607 Troup Hwy",
    "sg:city":"Tyler",
    "sg:classifiers":[
        {
            "category":"Organizations",
            "subcategory":"Religious Organization",
            "type":"Services"
        }
    ],
    "sg:phone":"+1 903 593 9424",
    "sg:postcode":"75701",
    "sg:province":"TX",
    "sg:tags":[
        "child",
        "center",
        "care"
    ],
    "wof:name":"Green Acres Baptist Church",
    "wof:placetype":"venue"
},
  "geometry": {"coordinates":[-95.28097,32.319315],"type":"Point"}
}