{
  "type": "Feature",
  "properties": {
    "iso:country":"US",
    "sg:address":"1136 State Hwy 34",
    "sg:city":"Terrell",
    "sg:classifiers":[
        {
            "category":"Travel",
            "subcategory":"Hotels & Motels",
            "type":"Entertainment"
        }
    ],
    "sg:phone":"+1 972 524 2808",
    "sg:postcode":"75160",
    "sg:province":"TX",
    "sg:tags":[
        "operation"
    ],
    "wof:name":"Calverts Drive Inn",
    "wof:placetype":"venue"
},
  "geometry": {"coordinates":[-96.27695799999999,32.726345],"type":"Point"}
}