{
  "type": "Feature",
  "properties": {
    "iso:country":"US",
    "sg:address":"1832 Dunagan St",
    "sg:city":"Toyahvale",
    "sg:classifiers":[
        {
            "category":"Farming",
            "subcategory":"Livestock Farm",
            "type":"Manufacturing & Wholesale Goods"
        }
    ],
    "sg:phone":"+1 432 426 9004",
    "sg:postcode":"79706",
    "sg:province":"TX",
    "sg:tags":[
        "ranch"
    ],
    "wof:name":"Mc Coy Land & Cattle Manager",
    "wof:placetype":"venue"
},
  "geometry": {"coordinates":[-102.08213499999999,31.961887],"type":"Point"}
}