{
  "type": "Feature",
  "properties": {
    "iso:country":"US",
    "sg:address":"516 9th St",
    "sg:city":"Port Aransas",
    "sg:classifiers":[
        {
            "category":"Freight",
            "type":"Transportation"
        }
    ],
    "sg:phone":"+1 361 749 6609",
    "sg:postcode":"78373",
    "sg:province":"TX",
    "sg:tags":[
        "storage"
    ],
    "wof:name":"Port Aransas Mini Storage",
    "wof:placetype":"venue"
},
  "geometry": {"coordinates":[-97.06504099999999,27.82878],"type":"Point"}
}