{
  "type": "Feature",
  "properties": {
    "iso:country":"US",
    "sg:address":"250 E Arapaho Rd",
    "sg:city":"Richardson",
    "sg:classifiers":[
        {
            "category":"Wholesale",
            "subcategory":"Chemicals & Plastics",
            "type":"Manufacturing & Wholesale Goods"
        }
    ],
    "sg:phone":"+1 972 238 6800",
    "sg:postcode":"75081",
    "sg:province":"TX",
    "sg:tags":[
        "explosive"
    ],
    "wof:name":"Siemens Explosive Detection",
    "wof:placetype":"venue"
},
  "geometry": {"coordinates":[-96.719053,32.960573],"type":"Point"}
}