{
  "type": "Feature",
  "properties": {
    "iso:country":"US",
    "sg:address":"835 Texas Ave",
    "sg:city":"Bridge City",
    "sg:classifiers":[
        {
            "category":"Restaurant",
            "type":"Food & Drink"
        }
    ],
    "sg:menulink":"http://www.allmenus.com/tx/bridge-city-orangefield/193304-taco-bell/menu/",
    "sg:postcode":"77611",
    "sg:province":"TX",
    "sg:tags":[
        "mexican"
    ],
    "wof:name":"Taco Bell",
    "wof:placetype":"venue"
},
  "geometry": {"coordinates":[-93.843028,30.023985],"type":"Point"}
}