{
  "type": "Feature",
  "properties": {
    "iso:country":"US",
    "sg:address":"2224 Bayberry Dr",
    "sg:city":"Mesquite",
    "sg:classifiers":[
        {
            "category":"Shopping",
            "type":"Retail Goods"
        }
    ],
    "sg:phone":"+1 972 288 9613",
    "sg:postcode":"75149",
    "sg:province":"TX",
    "sg:tags":[
        "merchandise"
    ],
    "wof:name":"Innerresource Analysis",
    "wof:placetype":"venue"
},
  "geometry": {"coordinates":[-96.635079,32.769012],"type":"Point"}
}