{
  "type": "Feature",
  "properties": {
    "iso:country":"US",
    "sg:address":"422 Sailmaster St",
    "sg:city":"Austin",
    "sg:classifiers":[
        {
            "category":"Professional",
            "subcategory":"Advertising",
            "type":"Services"
        }
    ],
    "sg:phone":"+1 512 261 0991",
    "sg:postcode":"78734",
    "sg:province":"TX",
    "wof:name":"Turner New Media",
    "wof:placetype":"venue"
},
  "geometry": {"coordinates":[-97.968935,30.369084],"type":"Point"}
}