{
  "type": "Feature",
  "properties": {
    "iso:country":"US",
    "sg:address":"527 W Fordyce Ave",
    "sg:city":"Kingsville",
    "sg:classifiers":[
        {
            "category":"Organizations",
            "subcategory":"Religious Organization",
            "type":"Services"
        }
    ],
    "sg:phone":"+1 361 592 0594",
    "sg:postcode":"78363",
    "sg:province":"TX",
    "sg:tags":[
        "church"
    ],
    "wof:name":"Friendship Baptist Church",
    "wof:placetype":"venue"
},
  "geometry": {"coordinates":[-97.87375299999999,27.51145],"type":"Point"}
}