{
  "type": "Feature",
  "properties": {
    "iso:country":"US",
    "sg:address":"1141 Larry Mahan Dr",
    "sg:city":"El Paso",
    "sg:classifiers":[
        {
            "category":"Manufacturing",
            "subcategory":"Jewelry",
            "type":"Manufacturing & Wholesale Goods"
        }
    ],
    "sg:phone":"+1 915 593 5777",
    "sg:postcode":"79925",
    "sg:province":"TX",
    "sg:tags":[
        "rings",
        "graduation",
        "mfg"
    ],
    "wof:name":"Herff Jones Class Rings",
    "wof:placetype":"venue"
},
  "geometry": {"coordinates":[-106.367205,31.767011],"type":"Point"}
}