{
  "type": "Feature",
  "properties": {
    "iso:country":"US",
    "sg:address":"353 Charles Rd",
    "sg:city":"Houston",
    "sg:classifiers":[
        {
            "category":"Education",
            "subcategory":"College",
            "type":"Public Place"
        }
    ],
    "sg:phone":"+1 713 910 2510",
    "sg:postcode":"77076",
    "sg:province":"TX",
    "wof:name":"Yes College Preperatory School",
    "wof:placetype":"venue"
},
  "geometry": {"coordinates":[-95.371566,29.862419],"type":"Point"}
}