{
  "type": "Feature",
  "properties": {
    "iso:country":"US",
    "sg:address":"918 Crestmeade Dr",
    "sg:city":"Garland",
    "sg:classifiers":[
        {
            "category":"Real Estate",
            "subcategory":"Real Estate Agent",
            "type":"Services"
        }
    ],
    "sg:phone":"+1 972 495 6659",
    "sg:postcode":"75040",
    "sg:province":"TX",
    "sg:tags":[
        "appraiser"
    ],
    "wof:name":"Russell Isbell RE Appraisal",
    "wof:placetype":"venue"
},
  "geometry": {"coordinates":[-96.641429,32.93991],"type":"Point"}
}