{
  "type": "Feature",
  "properties": {
    "iso:country":"US",
    "sg:address":"7400 Fannin St Ste 1200",
    "sg:city":"Houston",
    "sg:classifiers":[
        {
            "category":"Health Services",
            "subcategory":"Clinic",
            "type":"Services"
        },
        {
            "category":"Organizations",
            "subcategory":"Non-profit Organization",
            "type":"Services"
        }
    ],
    "sg:phone":"+1 888 840 8688",
    "sg:postcode":"77054",
    "sg:province":"TX",
    "sg:tags":[
        "counseling",
        "community",
        "mental",
        "service/non-profit"
    ],
    "sg:website":"www.NonProfitSTDTesting.org",
    "wof:name":"Houston Non Profit HIV/STD Testing Center",
    "wof:placetype":"venue"
},
  "geometry": {"coordinates":[-95.401188,29.694702],"type":"Point"}
}