{
  "type": "Feature",
  "properties": {
    "iso:country":"US",
    "sg:address":"22334 Prince George Ln",
    "sg:city":"Katy",
    "sg:classifiers":[
        {
            "category":"Wholesale",
            "subcategory":"Electrical",
            "type":"Manufacturing & Wholesale Goods"
        }
    ],
    "sg:phone":"+1 281 347 3655",
    "sg:postcode":"77449",
    "sg:province":"TX",
    "sg:tags":[
        "equipment",
        "alarm",
        "burglar",
        "system"
    ],
    "wof:name":"Intercept Security",
    "wof:placetype":"venue"
},
  "geometry": {"coordinates":[-95.75675099999999,29.799066],"type":"Point"}
}