{
  "type": "Feature",
  "properties": {
    "iso:country":"US",
    "sg:address":"2120 Post Office St",
    "sg:city":"Galveston",
    "sg:classifiers":[
        {
            "category":"Professional",
            "subcategory":"Art Services",
            "type":"Services"
        }
    ],
    "sg:phone":"+1 409 766 7030",
    "sg:postcode":"77550",
    "sg:province":"TX",
    "sg:tags":[
        "interior",
        "designer",
        "decorator"
    ],
    "wof:name":"Hamrock Interiors",
    "wof:placetype":"venue"
},
  "geometry": {"coordinates":[-94.791417,29.30508],"type":"Point"}
}