{
  "type": "Feature",
  "properties": {
    "iso:country":"US",
    "sg:address":"137 W Bay Area Blvd",
    "sg:city":"Webster",
    "sg:classifiers":[
        {
            "category":"Wholesale",
            "subcategory":"Photographic Equipment",
            "type":"Manufacturing & Wholesale Goods"
        }
    ],
    "sg:phone":"+1 281 332 1222",
    "sg:postcode":"77598",
    "sg:province":"TX",
    "sg:tags":[
        "photo",
        "repair"
    ],
    "wof:name":"Vintec Camera and Repairs",
    "wof:placetype":"venue"
},
  "geometry": {"coordinates":[-95.12891500000001,29.548652],"type":"Point"}
}