{
  "type": "Feature",
  "properties": {
    "iso:country":"US",
    "sg:address":"8000 Harwin Dr",
    "sg:city":"Houston",
    "sg:classifiers":[
        {
            "category":"Shopping",
            "subcategory":"Clothing, Apparel, & Fashions",
            "type":"Retail Goods"
        }
    ],
    "sg:phone":"+1 713 780 8687",
    "sg:postcode":"77036",
    "sg:province":"TX",
    "wof:name":"J K Intl Inc",
    "wof:placetype":"venue"
},
  "geometry": {"coordinates":[-95.52646,29.717928],"type":"Point"}
}