{
  "type": "Feature",
  "properties": {
    "iso:country":"US",
    "sg:address":"1110 Victoria St",
    "sg:city":"Laredo",
    "sg:classifiers":[
        {
            "category":"Government",
            "subcategory":"Office",
            "type":"Public Place"
        }
    ],
    "sg:phone":"+1 956 523 4954",
    "sg:postcode":"78040",
    "sg:province":"TX",
    "wof:name":"Honorable Andres Reyes",
    "wof:placetype":"venue"
},
  "geometry": {"coordinates":[-99.50739799999999,27.507958],"type":"Point"}
}