{
  "type": "Feature",
  "properties": {
    "iso:country":"US",
    "sg:address":"128 Colley Dr",
    "sg:city":"Palestine",
    "sg:classifiers":[
        {
            "category":"Manufacturing",
            "subcategory":"Tools & Machinery",
            "type":"Manufacturing & Wholesale Goods"
        }
    ],
    "sg:phone":"+1 903 723 1894",
    "sg:postcode":"75803",
    "sg:province":"TX",
    "sg:tags":[
        "equipment",
        "mfg"
    ],
    "wof:name":"Gardens Gate",
    "wof:placetype":"venue"
},
  "geometry": {"coordinates":[-95.63042900000001,31.786901],"type":"Point"}
}