{
  "type": "Feature",
  "properties": {
    "iso:country":"US",
    "sg:address":"613 Jupiter Rd",
    "sg:city":"Plano",
    "sg:classifiers":[
        {
            "category":"Restaurant",
            "type":"Food & Drink"
        }
    ],
    "sg:menulink":"http://www.allmenus.com/tx/plano/142001-waffle-house/menu/",
    "sg:phone":"+1 972 633 0234",
    "sg:postcode":"75074",
    "sg:province":"TX",
    "sg:tags":[
        "american"
    ],
    "wof:name":"Waffle House",
    "wof:placetype":"venue"
},
  "geometry": {"coordinates":[-96.682963,33.006298],"type":"Point"}
}