{
  "type": "Feature",
  "properties": {
    "iso:country":"US",
    "sg:address":"400 State Highway 78",
    "sg:city":"Lavon",
    "sg:classifiers":[
        {
            "category":"Shopping",
            "type":"Retail Goods"
        }
    ],
    "sg:phone":"+1 972 843 4523",
    "sg:postcode":"75166",
    "sg:province":"TX",
    "sg:tags":[
        "merchandise"
    ],
    "wof:name":"Community Spirit Shop",
    "wof:placetype":"venue"
},
  "geometry": {"coordinates":[-96.446169,33.022222],"type":"Point"}
}