{
  "type": "Feature",
  "properties": {
    "iso:country":"US",
    "sg:address":"3209 Commercial Dr",
    "sg:city":"Midland",
    "sg:classifiers":[
        {
            "category":"Manufacturing",
            "subcategory":"Signs",
            "type":"Manufacturing & Wholesale Goods"
        }
    ],
    "sg:phone":"+1 432 682 8770",
    "sg:postcode":"79701",
    "sg:province":"TX",
    "wof:name":"All Star Signs",
    "wof:placetype":"venue"
},
  "geometry": {"coordinates":[-102.110032,31.974032],"type":"Point"}
}