{
  "type": "Feature",
  "properties": {
    "iso:country":"US",
    "sg:address":"1215 I- 30",
    "sg:city":"Greenville",
    "sg:classifiers":[
        {
            "category":"Travel",
            "subcategory":"Hotels & Motels",
            "type":"Entertainment"
        }
    ],
    "sg:phone":"+1 903 454 7000",
    "sg:postcode":"75402",
    "sg:province":"TX",
    "wof:name":"Ramada Inn",
    "wof:placetype":"venue"
},
  "geometry": {"coordinates":[-96.069062,33.13585],"type":"Point"}
}