{
  "type": "Feature",
  "properties": {
    "iso:country":"US",
    "sg:address":"621 9th St",
    "sg:city":"Huntsville",
    "sg:classifiers":[
        {
            "category":"Restaurant",
            "type":"Food & Drink"
        }
    ],
    "sg:phone":"+1 936 439 9559",
    "sg:postcode":"77320",
    "sg:province":"TX",
    "wof:name":"Bennie J's Smoke Pit",
    "wof:placetype":"venue"
},
  "geometry": {"coordinates":[-95.54356300000001,30.726358],"type":"Point"}
}