{
  "type": "Feature",
  "properties": {
    "iso:country":"US",
    "sg:address":"3200 Broadway Blvd",
    "sg:city":"Garland",
    "sg:classifiers":[
        {
            "category":"Real Estate",
            "subcategory":"Real Estate Services",
            "type":"Services"
        }
    ],
    "sg:phone":"+1 972 278 0300",
    "sg:postcode":"75043",
    "sg:province":"TX",
    "sg:tags":[
        "management",
        "property"
    ],
    "wof:name":"Gullion Properties",
    "wof:placetype":"venue"
},
  "geometry": {"coordinates":[-96.620052,32.877943],"type":"Point"}
}