{
  "type": "Feature",
  "properties": {
    "iso:country":"US",
    "sg:address":"3535 N Buckner Blvd",
    "sg:city":"Dallas",
    "sg:classifiers":[
        {
            "category":"Health Services",
            "subcategory":"Doctor",
            "type":"Services"
        }
    ],
    "sg:phone":"+1 214 660 1011",
    "sg:postcode":"75228",
    "sg:province":"TX",
    "sg:tags":[
        "physician",
        "family",
        "practice",
        "surgeons",
        "medicine",
        "surgeon"
    ],
    "wof:name":"Priority Health Center",
    "wof:placetype":"venue"
},
  "geometry": {"coordinates":[-96.682587,32.802769],"type":"Point"}
}