{
  "type": "Feature",
  "properties": {
    "iso:country":"US",
    "sg:address":"2517 Ella Lee Ln",
    "sg:city":"Houston",
    "sg:classifiers":[
        {
            "category":"Professional",
            "type":"Services"
        }
    ],
    "sg:phone":"+1 713 529 1003",
    "sg:postcode":"77019",
    "sg:province":"TX",
    "wof:name":"Janet R Bodin",
    "wof:placetype":"venue"
},
  "geometry": {"coordinates":[-95.417683,29.745466],"type":"Point"}
}