{
  "type": "Feature",
  "properties": {
    "iso:country":"US",
    "sg:address":"1135 E 9th St",
    "sg:city":"Mission",
    "sg:classifiers":[
        {
            "category":"Sports & Exercise",
            "subcategory":"Gym",
            "type":"Entertainment"
        }
    ],
    "sg:phone":"+1 956 581 1444",
    "sg:postcode":"78572",
    "sg:province":"TX",
    "sg:tags":[
        "fitness",
        "physical",
        "facility"
    ],
    "wof:name":"World Fitness Center",
    "wof:placetype":"venue"
},
  "geometry": {"coordinates":[-98.312431,26.213127],"type":"Point"}
}