{
  "type": "Feature",
  "properties": {
    "iso:country":"US",
    "sg:address":"222 W Jefferson Blvd",
    "sg:city":"Dallas",
    "sg:classifiers":[
        {
            "category":"Professional",
            "type":"Services"
        }
    ],
    "sg:phone":"+1 214 946 2304",
    "sg:postcode":"75208",
    "sg:province":"TX",
    "wof:name":"Lone Star Credit Co Inc",
    "wof:placetype":"venue"
},
  "geometry": {"coordinates":[-96.826131,32.743186],"type":"Point"}
}