{
  "type": "Feature",
  "properties": {
    "iso:country":"US",
    "sg:address":"3914 Lost Oak Dr",
    "sg:city":"Spring",
    "sg:classifiers":[
        {
            "category":"Shopping",
            "type":"Retail Goods"
        }
    ],
    "sg:phone":"+1 281 353 6551",
    "sg:postcode":"77388",
    "sg:province":"TX",
    "sg:tags":[
        "merchandise"
    ],
    "wof:name":"Instant Graphics & Design",
    "wof:placetype":"venue"
},
  "geometry": {"coordinates":[-95.47791599999999,30.040798],"type":"Point"}
}