{
  "type": "Feature",
  "properties": {
    "iso:country":"US",
    "sg:address":"1200 McKinney St Ste 391",
    "sg:city":"Houston",
    "sg:classifiers":[
        {
            "category":"Shopping",
            "subcategory":"Mobile Phones",
            "type":"Retail Goods"
        }
    ],
    "sg:phone":"+1 713 652 9070",
    "sg:postcode":"77010",
    "sg:province":"TX",
    "wof:name":"RadioShack",
    "wof:placetype":"venue"
},
  "geometry": {"coordinates":[-95.363263,29.755773],"type":"Point"}
}