{
  "type": "Feature",
  "properties": {
    "iso:country":"US",
    "sg:address":"2020 Washington Ave",
    "sg:city":"Houston",
    "sg:classifiers":[
        {
            "category":"Shopping",
            "subcategory":"Used Merchandise",
            "type":"Retail Goods"
        }
    ],
    "sg:phone":"+1 713 862 2605",
    "sg:postcode":"77007",
    "sg:province":"TX",
    "wof:name":"Saint Vincent De Paul Stores",
    "wof:placetype":"venue"
},
  "geometry": {"coordinates":[-95.379212,29.768077],"type":"Point"}
}