{
  "type": "Feature",
  "properties": {
    "iso:country":"US",
    "sg:address":"1701 19th St",
    "sg:city":"Hondo",
    "sg:classifiers":[
        {
            "category":"Real Estate",
            "subcategory":"Real Estate Agent",
            "type":"Services"
        }
    ],
    "sg:phone":"+1 512 426 2022",
    "sg:postcode":"78861",
    "sg:province":"TX",
    "wof:name":"Claude Schuehle Realty Inc",
    "wof:placetype":"venue"
},
  "geometry": {"coordinates":[-99.14733099999999,29.34708],"type":"Point"}
}