{
  "type": "Feature",
  "properties": {
    "iso:country":"US",
    "sg:address":"821 Central Ave",
    "sg:city":"Elgin",
    "sg:classifiers":[
        {
            "category":"Professional",
            "subcategory":"Management & Consulting",
            "type":"Services"
        }
    ],
    "sg:phone":"+1 512 285 4866",
    "sg:postcode":"78621",
    "sg:province":"TX",
    "wof:name":"Graham Cw Management Co",
    "wof:placetype":"venue"
},
  "geometry": {"coordinates":[-97.381952,30.344777],"type":"Point"}
}