{
  "type": "Feature",
  "properties": {
    "iso:country":"US",
    "sg:address":"1807 Falcon Dr",
    "sg:city":"Portland",
    "sg:classifiers":[
        {
            "category":"Wholesale",
            "subcategory":"Home Furnishings",
            "type":"Manufacturing & Wholesale Goods"
        }
    ],
    "sg:phone":"+1 361 221 9129",
    "sg:postcode":"78374",
    "sg:province":"TX",
    "wof:name":"Suavehousebiz",
    "wof:placetype":"venue"
},
  "geometry": {"coordinates":[-97.32465999999999,27.892861],"type":"Point"}
}