{
  "type": "Feature",
  "properties": {
    "iso:country":"US",
    "sg:address":"526 Mockingbird Ln",
    "sg:city":"Clute",
    "sg:classifiers":[
        {
            "category":"Wholesale",
            "subcategory":"Metals & Minerals",
            "type":"Manufacturing & Wholesale Goods"
        }
    ],
    "sg:phone":"+1 979 265 2566",
    "sg:postcode":"77531",
    "sg:province":"TX",
    "sg:tags":[
        "center"
    ],
    "wof:name":"MSC Management Inc",
    "wof:placetype":"venue"
},
  "geometry": {"coordinates":[-95.388959,29.017474],"type":"Point"}
}