{
  "type": "Feature",
  "properties": {
    "iso:country":"US",
    "sg:address":"11427 Radford Ln",
    "sg:city":"Houston",
    "sg:classifiers":[
        {
            "category":"Education",
            "subcategory":"Special Training",
            "type":"Public Place"
        }
    ],
    "sg:phone":"+1 281 933 5327",
    "sg:postcode":"77099",
    "sg:province":"TX",
    "wof:name":"Behind Wheel Driving Course",
    "wof:placetype":"venue"
},
  "geometry": {"coordinates":[-95.575731,29.651499],"type":"Point"}
}