{
  "type": "Feature",
  "properties": {
    "iso:country":"US",
    "sg:address":"220 Oregon Ave",
    "sg:city":"Dallas",
    "sg:classifiers":[
        {
            "category":"Real Estate",
            "subcategory":"Real Estate Operator",
            "type":"Services"
        }
    ],
    "sg:phone":"+1 214 372 7157",
    "sg:postcode":"75203",
    "sg:province":"TX",
    "sg:tags":[
        "apartment"
    ],
    "wof:name":"Madison Point Apartments",
    "wof:placetype":"venue"
},
  "geometry": {"coordinates":[-96.82123199999999,32.766856],"type":"Point"}
}