{
  "type": "Feature",
  "properties": {
    "iso:country":"US",
    "sg:address":"300 Lynch Bend Rd",
    "sg:city":"Springtown",
    "sg:classifiers":[
        {
            "category":"Building & Trades",
            "subcategory":"Electrical",
            "type":"Services"
        }
    ],
    "sg:phone":"+1 817 220 0002",
    "sg:postcode":"76082",
    "sg:province":"TX",
    "sg:tags":[
        "electric",
        "contractor"
    ],
    "wof:name":"CMS Construction",
    "wof:placetype":"venue"
},
  "geometry": {"coordinates":[-97.693575,32.948914],"type":"Point"}
}