{
  "type": "Feature",
  "properties": {
    "iso:country":"US",
    "sg:address":"13527 Durbridge Trail Dr",
    "sg:city":"Houston",
    "sg:classifiers":[
        {
            "category":"Professional",
            "subcategory":"Computer Services",
            "type":"Services"
        }
    ],
    "sg:phone":"+1 281 970 9177",
    "sg:postcode":"77065",
    "sg:province":"TX",
    "sg:tags":[
        "consulting",
        "upgrade"
    ],
    "wof:name":"MicroAge Integration Co",
    "wof:placetype":"venue"
},
  "geometry": {"coordinates":[-95.61975,29.923081],"type":"Point"}
}