{
  "type": "Feature",
  "properties": {
    "iso:country":"US",
    "sg:address":"3521 Oak Lawn Ave",
    "sg:city":"Dallas",
    "sg:classifiers":[
        {
            "category":"Shopping",
            "subcategory":"Gifts & Souvenirs",
            "type":"Retail Goods"
        }
    ],
    "sg:phone":"+1 214 522 1617",
    "sg:postcode":"75219",
    "sg:province":"TX",
    "sg:tags":[
        "florist",
        "basket",
        "parcel"
    ],
    "sg:website":"www.bouquetsthatstay.com",
    "wof:name":"Bouquets That Stay",
    "wof:placetype":"venue"
},
  "geometry": {"coordinates":[-96.80552400000001,32.812223],"type":"Point"}
}