{
  "type": "Feature",
  "properties": {
    "iso:country":"US",
    "sg:address":"9627 Bayou Brook St",
    "sg:city":"Houston",
    "sg:classifiers":[
        {
            "category":"Professional",
            "subcategory":"Business Services",
            "type":"Services"
        }
    ],
    "sg:phone":"+1 713 789 4956",
    "sg:postcode":"77063",
    "sg:province":"TX",
    "wof:name":"Bonneau Enterprises LLC",
    "wof:placetype":"venue"
},
  "geometry": {"coordinates":[-95.53413500000001,29.748164],"type":"Point"}
}