{
  "type": "Feature",
  "properties": {
    "iso:country":"US",
    "sg:address":"11613 FM 620",
    "sg:city":"Austin",
    "sg:classifiers":[
        {
            "category":"Autos & Motor Vehicles",
            "subcategory":"Fuel & Gas Station",
            "type":"Retail Goods"
        }
    ],
    "sg:phone":"+1 512 336 2160",
    "sg:postcode":"78750",
    "sg:province":"TX",
    "sg:tags":[
        "oil"
    ],
    "wof:name":"Exxon On The Run",
    "wof:placetype":"venue"
},
  "geometry": {"coordinates":[-97.823454,30.457794],"type":"Point"}
}