{
  "type": "Feature",
  "properties": {
    "iso:country":"US",
    "sg:address":"800 US Hwy 77",
    "sg:city":"Waxahachie",
    "sg:classifiers":[
        {
            "category":"Retail",
            "subcategory":"Laundry & Dry Cleaning",
            "type":"Services"
        }
    ],
    "sg:phone":"+1 972 923 2359",
    "sg:postcode":"75165",
    "sg:province":"TX",
    "sg:tags":[
        "cleaners"
    ],
    "wof:name":"HEB Cleaners",
    "wof:placetype":"venue"
},
  "geometry": {"coordinates":[-96.845957,32.395415],"type":"Point"}
}