{
  "type": "Feature",
  "properties": {
    "iso:country":"US",
    "sg:address":"1605 George Dieter Dr",
    "sg:city":"El Paso",
    "sg:classifiers":[
        {
            "category":"Personal",
            "subcategory":"Shoe Repair & Shine",
            "type":"Services"
        }
    ],
    "sg:phone":"+1 915 594 1582",
    "sg:postcode":"79936",
    "sg:province":"TX",
    "sg:tags":[
        "repairing",
        "boot"
    ],
    "wof:name":"Juarez Boots & Shoe Repair",
    "wof:placetype":"venue"
},
  "geometry": {"coordinates":[-106.301931,31.753859],"type":"Point"}
}