{
  "type": "Feature",
  "properties": {
    "iso:country":"US",
    "sg:address":"3737 S Cooper St",
    "sg:city":"Arlington",
    "sg:classifiers":[
        {
            "category":"Restaurant",
            "type":"Food & Drink"
        }
    ],
    "sg:menulink":"http://www.allmenus.com/tx/arlington/177277-jack-in-the-box/menu/",
    "sg:phone":"+1 817 472 9462",
    "sg:postcode":"76015",
    "sg:province":"TX",
    "sg:tags":[
        "burger",
        "american"
    ],
    "wof:name":"Jack in the Box",
    "wof:placetype":"venue"
},
  "geometry": {"coordinates":[-97.131857,32.685423],"type":"Point"}
}