{
  "type": "Feature",
  "properties": {
    "iso:country":"US",
    "sg:address":"21926 Kingsland Blvd",
    "sg:city":"Katy",
    "sg:classifiers":[
        {
            "category":"Food & Beverages",
            "subcategory":"Specialty",
            "type":"Retail Goods"
        }
    ],
    "sg:phone":"+1 281 693 4800",
    "sg:postcode":"77450",
    "sg:province":"TX",
    "wof:name":"Discount Nutrition Warehouse",
    "wof:placetype":"venue"
},
  "geometry": {"coordinates":[-95.75241800000001,29.774825],"type":"Point"}
}