{
  "type": "Feature",
  "properties": {
    "iso:country":"US",
    "sg:address":"1146 W Main St",
    "sg:city":"Lewisville",
    "sg:classifiers":[
        {
            "category":"Retail",
            "subcategory":"Laundry & Dry Cleaning",
            "type":"Services"
        }
    ],
    "sg:phone":"+1 972 221 9052",
    "sg:postcode":"75067",
    "sg:province":"TX",
    "wof:name":"Roseys Alterations",
    "wof:placetype":"venue"
},
  "geometry": {"coordinates":[-97.0227,33.041953],"type":"Point"}
}