{
  "type": "Feature",
  "properties": {
    "iso:country":"US",
    "sg:address":"2248 E Lancaster Ave",
    "sg:city":"Fort Worth",
    "sg:classifiers":[
        {
            "category":"Manufacturing",
            "subcategory":"Metals",
            "type":"Manufacturing & Wholesale Goods"
        }
    ],
    "sg:phone":"+1 817 535 2127",
    "sg:postcode":"76103",
    "sg:province":"TX",
    "sg:tags":[
        "ornamental",
        "product",
        "work",
        "iron",
        "mfg"
    ],
    "wof:name":"Rodgers Ornamental Iron Inc",
    "wof:placetype":"venue"
},
  "geometry": {"coordinates":[-97.294693,32.745507],"type":"Point"}
}