{
  "type": "Feature",
  "properties": {
    "iso:country":"US",
    "sg:address":"9826 Faircrest Dr",
    "sg:city":"Dallas",
    "sg:classifiers":[
        {
            "category":"Shopping",
            "subcategory":"Computers & Home Electronics",
            "type":"Retail Goods"
        }
    ],
    "sg:phone":"+1 214 393 0689",
    "sg:postcode":"75238",
    "sg:province":"TX",
    "sg:tags":[
        "equipment",
        "dealer"
    ],
    "wof:name":"Teach Me Mac",
    "wof:placetype":"venue"
},
  "geometry": {"coordinates":[-96.713965,32.889551],"type":"Point"}
}