{
  "type": "Feature",
  "properties": {
    "iso:country":"US",
    "sg:address":"1002 Meadow Ridge Dr",
    "sg:city":"Dripping Springs",
    "sg:classifiers":[
        {
            "category":"Wholesale",
            "subcategory":"Construction Materials",
            "type":"Manufacturing & Wholesale Goods"
        }
    ],
    "sg:phone":"+1 512 894 3659",
    "sg:postcode":"78620",
    "sg:province":"TX",
    "wof:name":"Atlanta Steel Buildings",
    "wof:placetype":"venue"
},
  "geometry": {"coordinates":[-98.013452,30.1675],"type":"Point"}
}