{
  "type": "Feature",
  "properties": {
    "iso:country":"US",
    "sg:address":"4102 Woodlawn Ave Ste 110",
    "sg:city":"Pasadena",
    "sg:classifiers":[
        {
            "category":"Health Services",
            "subcategory":"Doctor",
            "type":"Services"
        }
    ],
    "sg:phone":"+1 713 946 6081",
    "sg:postcode":"77504",
    "sg:province":"TX",
    "sg:tags":[
        "physician",
        "surgeons",
        "medicine",
        "surgeon",
        "rehabilitation",
        "physical"
    ],
    "wof:name":"Peri Vaduganathan",
    "wof:placetype":"venue"
},
  "geometry": {"coordinates":[-95.182986,29.66018],"type":"Point"}
}