{
  "type": "Feature",
  "properties": {
    "iso:country":"US",
    "sg:address":"707 W Marshall Ave",
    "sg:city":"Longview",
    "sg:classifiers":[
        {
            "category":"Restaurant",
            "type":"Food & Drink"
        }
    ],
    "sg:phone":"+1 903 234 8594",
    "sg:postcode":"75601",
    "sg:province":"TX",
    "sg:tags":[
        "eating"
    ],
    "wof:name":"Waffle Shop The",
    "wof:placetype":"venue"
},
  "geometry": {"coordinates":[-94.74995199999999,32.49916],"type":"Point"}
}