{
  "type": "Feature",
  "properties": {
    "iso:country":"US",
    "sg:address":"116 E Reiman St",
    "sg:city":"Seymour",
    "sg:classifiers":[
        {
            "category":"Professional",
            "type":"Services"
        }
    ],
    "sg:phone":"+1 940 888 3429",
    "sg:postcode":"76380",
    "sg:province":"TX",
    "sg:tags":[
        "establishment"
    ],
    "wof:name":"Confetti's",
    "wof:placetype":"venue"
},
  "geometry": {"coordinates":[-99.26038,33.58677],"type":"Point"}
}