{
  "type": "Feature",
  "properties": {
    "iso:country":"US",
    "sg:address":"26511 State Hwy 75",
    "sg:city":"Spring",
    "sg:classifiers":[
        {
            "category":"Personal",
            "subcategory":"Beauty Salon",
            "type":"Services"
        }
    ],
    "sg:phone":"+1 281 367 9210",
    "sg:postcode":"77340",
    "sg:province":"TX",
    "wof:name":"Jamilet Beauty Salon",
    "wof:placetype":"venue"
},
  "geometry": {"coordinates":[-95.520188,30.678235],"type":"Point"}
}