{
  "type": "Feature",
  "properties": {
    "iso:country":"US",
    "sg:address":"4575 Westgrove Dr",
    "sg:city":"Addison",
    "sg:classifiers":[
        {
            "category":"Local Transit",
            "type":"Transportation"
        }
    ],
    "sg:phone":"+1 972 250 0555",
    "sg:postcode":"75001",
    "sg:province":"TX",
    "sg:tags":[
        "limousine"
    ],
    "wof:name":"Addison Express Limo & Car Svc",
    "wof:placetype":"venue"
},
  "geometry": {"coordinates":[-96.831667,32.975891],"type":"Point"}
}