{
  "type": "Feature",
  "properties": {
    "iso:country":"US",
    "sg:address":"5100 E 7th St",
    "sg:city":"Austin",
    "sg:classifiers":[
        {
            "category":"Restaurant",
            "type":"Food & Drink"
        }
    ],
    "sg:phone":"+1 512 247 3333",
    "sg:postcode":"78702",
    "sg:province":"TX",
    "wof:name":"Taco Sabroso",
    "wof:placetype":"venue"
},
  "geometry": {"coordinates":[-97.69583299999999,30.252269],"type":"Point"}
}