{
  "type": "Feature",
  "properties": {
    "iso:country":"US",
    "sg:address":"4603 Cypresswood Dr",
    "sg:city":"Spring",
    "sg:classifiers":[
        {
            "category":"Cinema",
            "subcategory":"Movie Rental",
            "type":"Entertainment"
        }
    ],
    "sg:phone":"+1 281 376 2118",
    "sg:postcode":"77379",
    "sg:province":"TX",
    "sg:tags":[
        "video",
        "tape"
    ],
    "wof:name":"Omega Legal Video",
    "wof:placetype":"venue"
},
  "geometry": {"coordinates":[-95.481999,30.028278],"type":"Point"}
}