{
  "type": "Feature",
  "properties": {
    "iso:country":"US",
    "sg:address":"2102 Cavitt Ave",
    "sg:city":"Bryan",
    "sg:classifiers":[
        {
            "category":"Retail",
            "subcategory":"Repair Shop",
            "type":"Services"
        }
    ],
    "sg:phone":"+1 979 822 4071",
    "sg:postcode":"77801",
    "sg:province":"TX",
    "wof:name":"Ambrose Furniture Works",
    "wof:placetype":"venue"
},
  "geometry": {"coordinates":[-96.363201,30.649681],"type":"Point"}
}