{
  "type": "Feature",
  "properties": {
    "iso:country":"US",
    "sg:address":"328 Windrose Pl",
    "sg:city":"El Paso",
    "sg:classifiers":[
        {
            "category":"Professional",
            "type":"Services"
        }
    ],
    "sg:phone":"+1 915 581 0893",
    "sg:postcode":"79912",
    "sg:province":"TX",
    "wof:name":"El Pincel",
    "wof:placetype":"venue"
},
  "geometry": {"coordinates":[-106.53630099999999,31.841679],"type":"Point"}
}