{
  "type": "Feature",
  "properties": {
    "iso:country":"US",
    "sg:address":"2323 San Antonio St",
    "sg:city":"Austin",
    "sg:classifiers":[
        {
            "category":"Professional",
            "type":"Services"
        }
    ],
    "sg:phone":"+1 512 478 1732",
    "sg:postcode":"78705",
    "sg:province":"TX",
    "sg:tags":[
        "caterer"
    ],
    "wof:name":"College Park-the Castilian Inc",
    "wof:placetype":"venue"
},
  "geometry": {"coordinates":[-97.742699,30.2868],"type":"Point"}
}