{
  "type": "Feature",
  "properties": {
    "iso:country":"US",
    "sg:address":"2921 Boca Chica Blvd",
    "sg:city":"Brownsville",
    "sg:classifiers":[
        {
            "category":"Insurance",
            "subcategory":"Insurance Agent",
            "type":"Services"
        },
        {
            "category":"Banks & Credit Unions",
            "subcategory":"Investment Brokerage",
            "type":"Services"
        },
        {
            "category":"Insurance",
            "subcategory":"Hazard Insurance",
            "type":"Services"
        }
    ],
    "sg:phone":"+1 956 546 8100",
    "sg:postcode":"78521",
    "sg:province":"TX",
    "sg:tags":[
        "auto",
        "motorcycle",
        "resume"
    ],
    "sg:website":"http://www.directgeneral.com",
    "wof:name":"Direct Auto Insurance",
    "wof:placetype":"venue"
},
  "geometry": {"coordinates":[-97.47790500000001,25.921489],"type":"Point"}
}