{
  "type": "Feature",
  "properties": {
    "iso:country":"US",
    "sg:address":"14030 US Hwy 181",
    "sg:city":"San Antonio",
    "sg:classifiers":[
        {
            "category":"Wholesale",
            "subcategory":"Machinery & Supplies",
            "type":"Manufacturing & Wholesale Goods"
        }
    ],
    "sg:phone":"+1 210 635 8065",
    "sg:postcode":"78223",
    "sg:province":"TX",
    "sg:tags":[
        "equipment",
        "industrial"
    ],
    "wof:name":"Caldwell Equip Co Inc",
    "wof:placetype":"venue"
},
  "geometry": {"coordinates":[-98.335365,29.281506],"type":"Point"}
}