{
  "type": "Feature",
  "properties": {
    "iso:country":"US",
    "sg:address":"13447 Bridgepath Ln",
    "sg:city":"Houston",
    "sg:classifiers":[
        {
            "category":"Professional",
            "subcategory":"Management & Consulting",
            "type":"Services"
        }
    ],
    "sg:phone":"+1 713 856 6881",
    "sg:postcode":"77041",
    "sg:province":"TX",
    "wof:name":"Transamerica Data Management",
    "wof:placetype":"venue"
},
  "geometry": {"coordinates":[-95.612458,29.856871],"type":"Point"}
}