{
  "type": "Feature",
  "properties": {
    "iso:country":"US",
    "sg:address":"2910 Ferndale St",
    "sg:city":"Houston",
    "sg:classifiers":[
        {
            "category":"Shopping",
            "subcategory":"Antiques",
            "type":"Retail Goods"
        }
    ],
    "sg:phone":"+1 713 524 6622",
    "sg:postcode":"77098",
    "sg:province":"TX",
    "wof:name":"Gundry Jas A Inc",
    "wof:placetype":"venue"
},
  "geometry": {"coordinates":[-95.421997,29.7393],"type":"Point"}
}