{
  "type": "Feature",
  "properties": {
    "iso:country":"US",
    "sg:address":"4000 S Medford Dr",
    "sg:city":"Lufkin",
    "sg:classifiers":[
        {
            "category":"Professional",
            "type":"Services"
        }
    ],
    "sg:phone":"+1 936 632 4226",
    "sg:postcode":"75901",
    "sg:province":"TX",
    "sg:tags":[
        "establishment"
    ],
    "wof:name":"Weston Geophysical",
    "wof:placetype":"venue"
},
  "geometry": {"coordinates":[-94.717547,31.313632],"type":"Point"}
}