{
  "type": "Feature",
  "properties": {
    "iso:country":"US",
    "sg:address":"OGA Physician Group 7900 Fannin St, Ste 1350",
    "sg:city":"Houston",
    "sg:classifiers":[
        {
            "category":"Shopping",
            "subcategory":"Pharmacy",
            "type":"Retail Goods"
        }
    ],
    "sg:phone":"+1 713 791 9426",
    "sg:postcode":"77054",
    "sg:province":"TX",
    "sg:tags":[
        "drugstore"
    ],
    "sg:website":"www.walgreens.com",
    "wof:name":"Walgreens",
    "wof:placetype":"venue"
},
  "geometry": {"coordinates":[-95.402964,29.693367],"type":"Point"}
}