{
  "type": "Feature",
  "properties": {
    "iso:country":"US",
    "sg:address":"5414 Crown Colony St",
    "sg:city":"Houston",
    "sg:classifiers":[
        {
            "category":"Building & Trades",
            "subcategory":"Construction",
            "type":"Services"
        }
    ],
    "sg:phone":"+1 281 580 8898",
    "sg:postcode":"77069",
    "sg:province":"TX",
    "sg:tags":[
        "contractor"
    ],
    "wof:name":"CE Hearn Enterprises Inc",
    "wof:placetype":"venue"
},
  "geometry": {"coordinates":[-95.51417499999999,29.982808],"type":"Point"}
}