{
  "type": "Feature",
  "properties": {
    "iso:country":"US",
    "sg:address":"7402 Neuhaus St",
    "sg:city":"Houston",
    "sg:classifiers":[
        {
            "category":"Freight",
            "type":"Transportation"
        }
    ],
    "sg:phone":"+1 713 466 1000",
    "sg:postcode":"77061",
    "sg:province":"TX",
    "sg:tags":[
        "warehouse",
        "alloy",
        "wire",
        "for",
        "special"
    ],
    "wof:name":"Techalloy Company Inc",
    "wof:placetype":"venue"
},
  "geometry": {"coordinates":[-95.291387,29.647939],"type":"Point"}
}