{
  "type": "Feature",
  "properties": {
    "iso:country":"US",
    "sg:address":"430 W Mable St",
    "sg:city":"Odessa",
    "sg:classifiers":[
        {
            "category":"Organizations",
            "subcategory":"Religious Organization",
            "type":"Services"
        }
    ],
    "sg:phone":"+1 432 335 9021",
    "sg:postcode":"79761",
    "sg:province":"TX",
    "wof:name":"Iglesia De Cristo",
    "wof:placetype":"venue"
},
  "geometry": {"coordinates":[-102.368854,31.839358],"type":"Point"}
}