{
  "type": "Feature",
  "properties": {
    "iso:country":"US",
    "sg:address":"463 Co Rd 199",
    "sg:city":"Nacogdoches",
    "sg:classifiers":[
        {
            "category":"Professional",
            "subcategory":"Management & Consulting",
            "type":"Services"
        }
    ],
    "sg:phone":"+1 936 569 2038",
    "sg:postcode":"75961",
    "sg:province":"TX",
    "wof:name":"Vonallmen Agency",
    "wof:placetype":"venue"
},
  "geometry": {"coordinates":[-94.60995800000001,31.701137],"type":"Point"}
}