{
  "type": "Feature",
  "properties": {
    "iso:country":"US",
    "sg:address":"7419 Ashcroft Dr",
    "sg:city":"Houston",
    "sg:classifiers":[
        {
            "category":"Recreation",
            "subcategory":"Marina",
            "type":"Entertainment"
        }
    ],
    "sg:phone":"+1 713 774 2255",
    "sg:postcode":"77081",
    "sg:province":"TX",
    "sg:tags":[
        "operation"
    ],
    "wof:name":"Tidelands Boat Car & Rv Stor",
    "wof:placetype":"venue"
},
  "geometry": {"coordinates":[-95.49071000000001,29.696944],"type":"Point"}
}