{
  "type": "Feature",
  "properties": {
    "iso:country":"US",
    "sg:address":"711 Lowell St",
    "sg:city":"Dallas",
    "sg:classifiers":[
        {
            "category":"Professional",
            "subcategory":"Advertising",
            "type":"Services"
        }
    ],
    "sg:phone":"+1 214 827 0620",
    "sg:postcode":"75214",
    "sg:province":"TX",
    "sg:tags":[
        "agency"
    ],
    "wof:name":"Vision Makers",
    "wof:placetype":"venue"
},
  "geometry": {"coordinates":[-96.75951999999999,32.808164],"type":"Point"}
}