{
  "type": "Feature",
  "properties": {
    "iso:country":"US",
    "sg:address":"5102 Kirby Dr",
    "sg:city":"Houston",
    "sg:classifiers":[
        {
            "category":"Retail",
            "subcategory":"Car Wash",
            "type":"Services"
        }
    ],
    "sg:phone":"+1 713 227 9274",
    "sg:postcode":"77098",
    "sg:province":"TX",
    "sg:website":"www.bubblescarwash.com/",
    "wof:name":"Bubbles Car Wash",
    "wof:placetype":"venue"
},
  "geometry": {"coordinates":[-95.418701,29.726999],"type":"Point"}
}