{
  "type": "Feature",
  "properties": {
    "iso:country":"US",
    "sg:address":"409 16th St",
    "sg:city":"Canyon",
    "sg:classifiers":[
        {
            "category":"Personal",
            "subcategory":"Beauty Salon",
            "type":"Services"
        }
    ],
    "sg:phone":"+1 806 655 3738",
    "sg:postcode":"79015",
    "sg:province":"TX",
    "sg:tags":[
        "hair",
        "shop"
    ],
    "wof:name":"For You Lady Beauty Shop",
    "wof:placetype":"venue"
},
  "geometry": {"coordinates":[-101.92800099999999,34.979301],"type":"Point"}
}