{
  "type": "Feature",
  "properties": {
    "iso:country":"US",
    "sg:address":"905 W Main St",
    "sg:city":"League City",
    "sg:classifiers":[
        {
            "category":"Health Services",
            "subcategory":"Health Practitioner",
            "type":"Services"
        }
    ],
    "sg:phone":"+1 281 332 4515",
    "sg:postcode":"77573",
    "sg:province":"TX",
    "wof:name":"Mary/Massage Therapist Hill",
    "wof:placetype":"venue"
},
  "geometry": {"coordinates":[-95.102829,29.505843],"type":"Point"}
}