{
  "type": "Feature",
  "properties": {
    "iso:country":"US",
    "sg:address":"2990 Richmond Ave Ste 420",
    "sg:city":"Houston",
    "sg:classifiers":[
        {
            "category":"Education",
            "subcategory":"Kindergarten",
            "type":"Public Place"
        }
    ],
    "sg:phone":"+1 713 524 7444",
    "sg:postcode":"77098",
    "sg:province":"TX",
    "sg:tags":[
        "school",
        "driving"
    ],
    "wof:name":"Broussard Enterprise",
    "wof:placetype":"venue"
},
  "geometry": {"coordinates":[-95.414101,29.7351],"type":"Point"}
}