{
  "type": "Feature",
  "properties": {
    "iso:country":"US",
    "sg:address":"9319 Anderson Mill Rd",
    "sg:city":"Austin",
    "sg:classifiers":[
        {
            "category":"Professional",
            "subcategory":"Accounting & Tax Preparation",
            "type":"Services"
        }
    ],
    "sg:phone":"+1 512 331 9944",
    "sg:postcode":"78729",
    "sg:province":"TX",
    "sg:tags":[
        "consultant"
    ],
    "wof:name":"E D Walp & Assoc",
    "wof:placetype":"venue"
},
  "geometry": {"coordinates":[-97.787885,30.449493],"type":"Point"}
}