{
  "type": "Feature",
  "properties": {
    "iso:country":"US",
    "sg:address":"18225 Co Rd 322",
    "sg:city":"Terrell",
    "sg:classifiers":[
        {
            "category":"Shopping",
            "subcategory":"Hobbies, Toys, & Games",
            "type":"Retail Goods"
        }
    ],
    "sg:phone":"+1 972 524 1461",
    "sg:postcode":"75160",
    "sg:province":"TX",
    "wof:name":"Rich's Vw Toys",
    "wof:placetype":"venue"
},
  "geometry": {"coordinates":[-96.24415,32.811336],"type":"Point"}
}