{
  "type": "Feature",
  "properties": {
    "iso:country":"US",
    "sg:address":"5200 Mitchelldale St",
    "sg:city":"Houston",
    "sg:classifiers":[
        {
            "category":"Building & Trades",
            "subcategory":"Construction",
            "type":"Services"
        },
        {
            "category":"Home & Garden",
            "subcategory":"Carpets & Floor Coverings",
            "type":"Retail Goods"
        }
    ],
    "sg:phone":"+1 713 862 6552",
    "sg:postcode":"77092",
    "sg:province":"TX",
    "sg:tags":[
        "material",
        "laying",
        "contractor"
    ],
    "wof:name":"Innovative Flooring Solutions",
    "wof:placetype":"venue"
},
  "geometry": {"coordinates":[-95.46625400000001,29.813839],"type":"Point"}
}