{
  "type": "Feature",
  "properties": {
    "iso:country":"US",
    "sg:address":"2400 E Amarillo Blvd",
    "sg:city":"Amarillo",
    "sg:classifiers":[
        {
            "category":"Retail",
            "subcategory":"Auto Repair",
            "type":"Services"
        }
    ],
    "sg:phone":"+1 806 373 3825",
    "sg:postcode":"79107",
    "sg:province":"TX",
    "sg:tags":[
        "automotive",
        "exhaust"
    ],
    "wof:name":"Custom Exhaust",
    "wof:placetype":"venue"
},
  "geometry": {"coordinates":[-101.81057300000001,35.221828],"type":"Point"}
}