{
  "type": "Feature",
  "properties": {
    "iso:country":"US",
    "sg:address":"301 W Tyler Ave",
    "sg:city":"Longview",
    "sg:classifiers":[
        {
            "category":"Manufacturing",
            "subcategory":"Rubber & Plastics",
            "type":"Manufacturing & Wholesale Goods"
        }
    ],
    "sg:phone":"+1 903 753 5764",
    "sg:postcode":"75601",
    "sg:province":"TX",
    "sg:tags":[
        "tube",
        "mfg",
        "supply"
    ],
    "wof:name":"Big 5 Tire and Auto",
    "wof:placetype":"venue"
},
  "geometry": {"coordinates":[-94.744778,32.496733],"type":"Point"}
}