{
  "type": "Feature",
  "properties": {
    "iso:country":"US",
    "sg:address":"9010 W Little York Rd",
    "sg:city":"Houston",
    "sg:classifiers":[
        {
            "category":"Wholesale",
            "subcategory":"Stationery",
            "type":"Manufacturing & Wholesale Goods"
        }
    ],
    "sg:phone":"+1 713 290 8600",
    "sg:postcode":"77040",
    "sg:province":"TX",
    "sg:tags":[
        "box",
        "fiber"
    ],
    "wof:name":"Golden State Container Inc",
    "wof:placetype":"venue"
},
  "geometry": {"coordinates":[-95.533974,29.86754],"type":"Point"}
}