{
  "type": "Feature",
  "properties": {
    "iso:country":"US",
    "sg:address":"2009 Big Canyon Dr",
    "sg:city":"Austin",
    "sg:classifiers":[
        {
            "category":"Professional",
            "type":"Services"
        }
    ],
    "sg:phone":"+1 512 732 0624",
    "sg:postcode":"78746",
    "sg:province":"TX",
    "wof:name":"Audiographic Instruments",
    "wof:placetype":"venue"
},
  "geometry": {"coordinates":[-97.839759,30.27853],"type":"Point"}
}