{
  "type": "Feature",
  "properties": {
    "iso:country":"US",
    "sg:address":"322 N Glenwood Blvd",
    "sg:city":"Tyler",
    "sg:classifiers":[
        {
            "category":"Utilities",
            "subcategory":"Cable",
            "type":"Services"
        }
    ],
    "sg:phone":"+1 903 595 4321",
    "sg:postcode":"75702",
    "sg:province":"TX",
    "sg:tags":[
        "communications",
        "television",
        "telephone"
    ],
    "wof:name":"Cox Communications",
    "wof:placetype":"venue"
},
  "geometry": {"coordinates":[-95.31934800000001,32.354034],"type":"Point"}
}