{
  "type": "Feature",
  "properties": {
    "iso:country":"US",
    "sg:address":"3001 Fountainwood Dr",
    "sg:city":"Georgetown",
    "sg:classifiers":[
        {
            "category":"Building & Trades",
            "subcategory":"Landscaping Services",
            "type":"Services"
        }
    ],
    "sg:phone":"+1 512 863 7303",
    "sg:postcode":"78633",
    "sg:province":"TX",
    "sg:tags":[
        "landscape",
        "contractor"
    ],
    "wof:name":"Reliance Lawn & Maintenance",
    "wof:placetype":"venue"
},
  "geometry": {"coordinates":[-97.75265899999999,30.697357],"type":"Point"}
}