{
  "type": "Feature",
  "properties": {
    "iso:country":"US",
    "sg:address":"441 E Pioneer Dr Ste 104",
    "sg:city":"Irving",
    "sg:classifiers":[
        {
            "category":"Retail",
            "subcategory":"Auto Repair",
            "type":"Services"
        }
    ],
    "sg:phone":"+1 972 721 0215",
    "sg:postcode":"75061",
    "sg:province":"TX",
    "wof:name":"Nick Car Repair",
    "wof:placetype":"venue"
},
  "geometry": {"coordinates":[-96.941498,32.817699],"type":"Point"}
}