{
  "type": "Feature",
  "properties": {
    "iso:country":"US",
    "sg:address":"5020 Collinwood Ave",
    "sg:city":"Fort Worth",
    "sg:classifiers":[
        {
            "category":"Real Estate",
            "subcategory":"Real Estate Agent",
            "type":"Services"
        }
    ],
    "sg:phone":"+1 817 737 7701",
    "sg:postcode":"76107",
    "sg:province":"TX",
    "sg:tags":[
        "a",
        "legal",
        "title"
    ],
    "wof:name":"Rattikin Exchange Services",
    "wof:placetype":"venue"
},
  "geometry": {"coordinates":[-97.39643599999999,32.737743],"type":"Point"}
}