{
  "type": "Feature",
  "properties": {
    "iso:country":"US",
    "sg:address":"18038 Golden Ridge Dr",
    "sg:city":"Houston",
    "sg:classifiers":[
        {
            "category":"Building & Trades",
            "subcategory":"Cleaning & Sanitation",
            "type":"Services"
        }
    ],
    "sg:phone":"+1 281 855 0279",
    "sg:postcode":"77084",
    "sg:province":"TX",
    "sg:tags":[
        "maintenance"
    ],
    "wof:name":"Personal Touch Maid Services",
    "wof:placetype":"venue"
},
  "geometry": {"coordinates":[-95.675871,29.858247],"type":"Point"}
}