{
  "type": "Feature",
  "properties": {
    "iso:country":"US",
    "sg:address":"8006 Parkglen",
    "sg:city":"Houston",
    "sg:classifiers":[
        {
            "category":"Professional",
            "type":"Services"
        }
    ],
    "sg:phone":"+1 281 458 0774",
    "sg:postcode":"77049",
    "sg:province":"TX",
    "wof:name":"Apple Patch Inc",
    "wof:placetype":"venue"
},
  "geometry": {"coordinates":[-95.189376,29.84027],"type":"Point"}
}