{
  "type": "Feature",
  "properties": {
    "iso:country":"US",
    "sg:address":"108 Industrial Blvd",
    "sg:city":"Cedar Park",
    "sg:classifiers":[
        {
            "category":"Food & Beverages",
            "subcategory":"Specialty",
            "type":"Retail Goods"
        },
        {
            "category":"Professional",
            "type":"Services"
        }
    ],
    "sg:phone":"+1 512 528 1825",
    "sg:postcode":"78613",
    "sg:province":"TX",
    "sg:tags":[
        "establishment",
        "transportation",
        "local"
    ],
    "wof:name":"Chinatown Water Works Inc",
    "wof:placetype":"venue"
},
  "geometry": {"coordinates":[-97.83361600000001,30.52859],"type":"Point"}
}