{
  "type": "Feature",
  "properties": {
    "iso:country":"US",
    "sg:address":"9012 Research Blvd",
    "sg:city":"Austin",
    "sg:classifiers":[
        {
            "category":"Home & Garden",
            "subcategory":"Carpets & Floor Coverings",
            "type":"Retail Goods"
        }
    ],
    "sg:phone":"+1 512 453 9962",
    "sg:postcode":"78758",
    "sg:province":"TX",
    "sg:tags":[
        "mattress"
    ],
    "wof:name":"Big Sur Waterbeds",
    "wof:placetype":"venue"
},
  "geometry": {"coordinates":[-97.728302,30.373699],"type":"Point"}
}