{
  "type": "Feature",
  "properties": {
    "iso:country":"US",
    "sg:address":"507 Avondale St",
    "sg:city":"Lufkin",
    "sg:classifiers":[
        {
            "category":"Building & Trades",
            "subcategory":"Cleaning & Sanitation",
            "type":"Services"
        }
    ],
    "sg:phone":"+1 936 639 9370",
    "sg:postcode":"75904",
    "sg:province":"TX",
    "sg:tags":[
        "maintenance"
    ],
    "wof:name":"Busy Bee Cleaning Service",
    "wof:placetype":"venue"
},
  "geometry": {"coordinates":[-94.73866700000001,31.332131],"type":"Point"}
}