{
  "type": "Feature",
  "properties": {
    "iso:country":"US",
    "sg:address":"7501 Fannin St",
    "sg:city":"Houston",
    "sg:classifiers":[
        {
            "category":"Health Services",
            "subcategory":"Doctor",
            "type":"Services"
        }
    ],
    "sg:phone":"+1 713 796 1300",
    "sg:postcode":"77004",
    "sg:province":"TX",
    "sg:tags":[
        "physician",
        "surgeon"
    ],
    "wof:name":"Becky Mc Graw-Wall MD",
    "wof:placetype":"venue"
},
  "geometry": {"coordinates":[-95.401697,29.6923],"type":"Point"}
}