{
  "type": "Feature",
  "properties": {
    "iso:country":"US",
    "sg:address":"7005 S Gessner Rd",
    "sg:city":"Houston",
    "sg:classifiers":[
        {
            "category":"Wholesale",
            "subcategory":"Non-durable Goods",
            "type":"Manufacturing & Wholesale Goods"
        }
    ],
    "sg:phone":"+1 713 392 5340",
    "sg:postcode":"77036",
    "sg:province":"TX",
    "wof:name":"Falcon Trading Falcon I",
    "wof:placetype":"venue"
},
  "geometry": {"coordinates":[-95.537863,29.701441],"type":"Point"}
}