{
  "type": "Feature",
  "properties": {
    "iso:country":"US",
    "sg:address":"4205 Edgemont Dr",
    "sg:city":"Austin",
    "sg:classifiers":[
        {
            "category":"Health Services",
            "subcategory":"Health Practitioner",
            "type":"Services"
        }
    ],
    "sg:phone":"+1 512 472 6238",
    "sg:postcode":"78731",
    "sg:province":"TX",
    "wof:name":"Austin Physical Therapy Clinic",
    "wof:placetype":"venue"
},
  "geometry": {"coordinates":[-97.76725999999999,30.323642],"type":"Point"}
}