{
  "type": "Feature",
  "properties": {
    "iso:country":"US",
    "sg:address":"16555 Fir Rd",
    "sg:city":"Santa Fe",
    "sg:classifiers":[
        {
            "category":"Retail",
            "subcategory":"Repair Shop",
            "type":"Services"
        }
    ],
    "sg:phone":"+1 409 925 2662",
    "sg:postcode":"77517",
    "sg:province":"TX",
    "sg:tags":[
        "taxidermist"
    ],
    "wof:name":"Buck's Taxidermy",
    "wof:placetype":"venue"
},
  "geometry": {"coordinates":[-95.166094,29.391227],"type":"Point"}
}