{
  "type": "Feature",
  "properties": {
    "iso:country":"US",
    "sg:address":"401 W Main St",
    "sg:city":"Nacogdoches",
    "sg:classifiers":[
        {
            "category":"Recreation",
            "type":"Entertainment"
        }
    ],
    "sg:phone":"+1 936 462 8000",
    "sg:postcode":"75964",
    "sg:province":"TX",
    "sg:tags":[
        "hall",
        "auditorium"
    ],
    "wof:name":"Banita Creek Hall",
    "wof:placetype":"venue"
},
  "geometry": {"coordinates":[-94.657749,31.604751],"type":"Point"}
}