{
  "type": "Feature",
  "properties": {
    "iso:country":"US",
    "sg:address":"731 W Wadley Ave",
    "sg:city":"Midland",
    "sg:classifiers":[
        {
            "category":"Professional",
            "subcategory":"Accounting & Tax Preparation",
            "type":"Services"
        }
    ],
    "sg:phone":"+1 432 686 7638",
    "sg:postcode":"79705",
    "sg:province":"TX",
    "sg:tags":[
        "bookkeeping",
        "general"
    ],
    "wof:name":"Staton Professional Svc",
    "wof:placetype":"venue"
},
  "geometry": {"coordinates":[-102.090676,32.027699],"type":"Point"}
}