{
  "type": "Feature",
  "properties": {
    "iso:country":"US",
    "sg:address":"6328 FM 1179",
    "sg:city":"Bryan",
    "sg:classifiers":[
        {
            "category":"Manufacturing",
            "subcategory":"Tools & Machinery",
            "type":"Manufacturing & Wholesale Goods"
        }
    ],
    "sg:phone":"+1 979 776 4310",
    "sg:postcode":"77808",
    "sg:province":"TX",
    "sg:tags":[
        "oil",
        "gas"
    ],
    "wof:name":"Petroleum Electronic Instrs",
    "wof:placetype":"venue"
},
  "geometry": {"coordinates":[-96.291837,30.695299],"type":"Point"}
}