{
  "type": "Feature",
  "properties": {
    "iso:country":"US",
    "sg:address":"1510 N Bowie Dr",
    "sg:city":"Abilene",
    "sg:classifiers":[
        {
            "category":"Building & Trades",
            "subcategory":"Construction",
            "type":"Services"
        }
    ],
    "sg:phone":"+1 325 675 6567",
    "sg:postcode":"79603",
    "sg:province":"TX",
    "sg:tags":[
        "house"
    ],
    "wof:name":"Bob Dean Construction",
    "wof:placetype":"venue"
},
  "geometry": {"coordinates":[-99.77998599999999,32.467595],"type":"Point"}
}