{
  "type": "Feature",
  "properties": {
    "iso:country":"US",
    "sg:address":"2415 Texas Blvd",
    "sg:city":"Texarkana",
    "sg:classifiers":[
        {
            "category":"Real Estate",
            "subcategory":"Real Estate Agent",
            "type":"Services"
        }
    ],
    "sg:phone":"+1 903 793 8139",
    "sg:postcode":"75503",
    "sg:province":"TX",
    "sg:tags":[
        "appraiser"
    ],
    "wof:name":"Pam Bonds Real Estate",
    "wof:placetype":"venue"
},
  "geometry": {"coordinates":[-94.053196,33.440711],"type":"Point"}
}