{
  "type": "Feature",
  "properties": {
    "iso:country":"US",
    "sg:address":"300 Shepherd Hill Rd",
    "sg:city":"Shepherd",
    "sg:classifiers":[
        {
            "category":"Professional",
            "subcategory":"Business Services",
            "type":"Services"
        }
    ],
    "sg:phone":"+1 936 628 3154",
    "sg:postcode":"77371",
    "sg:province":"TX",
    "wof:name":"CJ Enterprise",
    "wof:placetype":"venue"
},
  "geometry": {"coordinates":[-95.008539,30.544933],"type":"Point"}
}