{
  "type": "Feature",
  "properties": {
    "iso:country":"US",
    "sg:address":"10400 Harwin Dr",
    "sg:city":"Houston",
    "sg:classifiers":[
        {
            "category":"Restaurant",
            "type":"Food & Drink"
        },
        {
            "category":"Coffee & Tea",
            "type":"Food & Drink"
        },
        {
            "category":"Food & Beverages",
            "subcategory":"Liquor & Beverages",
            "type":"Retail Goods"
        },
        {
            "category":"Deli",
            "type":"Food & Drink"
        },
        {
            "category":"Food & Beverages",
            "subcategory":"Groceries & Convenience Stores",
            "type":"Retail Goods"
        }
    ],
    "sg:phone":"+1 713 773 0800",
    "sg:postcode":"77036",
    "sg:province":"TX",
    "sg:tags":[
        "shop",
        "delicatessen",
        "espresso"
    ],
    "wof:name":"Dnr Turkish Grill",
    "wof:placetype":"venue"
},
  "geometry": {"coordinates":[-95.551582,29.716631],"type":"Point"}
}