{
  "type": "Feature",
  "properties": {
    "iso:country":"US",
    "sg:address":"6014 Green Terrace Ln",
    "sg:city":"Houston",
    "sg:classifiers":[
        {
            "category":"Home & Garden",
            "subcategory":"Building Materials",
            "type":"Retail Goods"
        }
    ],
    "sg:phone":"+1 713 683 9139",
    "sg:postcode":"77088",
    "sg:province":"TX",
    "wof:name":"Gilberts Custom Screens",
    "wof:placetype":"venue"
},
  "geometry": {"coordinates":[-95.477988,29.874097],"type":"Point"}
}