{
  "type": "Feature",
  "properties": {
    "iso:country":"US",
    "sg:address":"2241 N Center St",
    "sg:city":"Bonham",
    "sg:classifiers":[
        {
            "category":"Restaurant",
            "type":"Food & Drink"
        }
    ],
    "sg:menulink":"http://www.allmenus.com/tx/bonham/202336-mcdonalds/menu/",
    "sg:postcode":"75418",
    "sg:province":"TX",
    "sg:tags":[
        "burger",
        "american"
    ],
    "wof:name":"McDonald's",
    "wof:placetype":"venue"
},
  "geometry": {"coordinates":[-96.175529,33.602017],"type":"Point"}
}