{
  "type": "Feature",
  "properties": {
    "iso:country":"US",
    "sg:address":"1402 E Hacienda St",
    "sg:city":"Bellville",
    "sg:classifiers":[
        {
            "category":"Wholesale",
            "subcategory":"Stationery",
            "type":"Manufacturing & Wholesale Goods"
        }
    ],
    "sg:phone":"+1 979 865 9181",
    "sg:postcode":"77418",
    "sg:province":"TX",
    "sg:tags":[
        "business",
        "form",
        "system"
    ],
    "wof:name":"Crabar BUSINESS System",
    "wof:placetype":"venue"
},
  "geometry": {"coordinates":[-96.246927,29.932306],"type":"Point"}
}