{
  "type": "Feature",
  "properties": {
    "iso:country":"US",
    "sg:address":"2710 Kingswood Blvd",
    "sg:city":"Grand Prairie",
    "sg:classifiers":[
        {
            "category":"Personal",
            "subcategory":"Beauty Salon",
            "type":"Services"
        }
    ],
    "sg:phone":"+1 972 641 6502",
    "sg:postcode":"75052",
    "sg:province":"TX",
    "sg:tags":[
        "shop"
    ],
    "wof:name":"Event Market Direct",
    "wof:placetype":"venue"
},
  "geometry": {"coordinates":[-97.04894899999999,32.654237],"type":"Point"}
}