{
  "type": "Feature",
  "properties": {
    "iso:country":"US",
    "sg:address":"804 Stimson",
    "sg:city":"Rockwall",
    "sg:classifiers":[
        {
            "category":"Real Estate",
            "subcategory":"Architect",
            "type":"Services"
        }
    ],
    "sg:phone":"+1 972 771 2624",
    "sg:postcode":"75087",
    "sg:province":"TX",
    "sg:tags":[
        "architectural"
    ],
    "wof:name":"J Carroll Architects",
    "wof:placetype":"venue"
},
  "geometry": {"coordinates":[-96.45384300000001,32.94058],"type":"Point"}
}