{
  "type": "Feature",
  "properties": {
    "iso:country":"US",
    "sg:address":"403 Small Hill Dr",
    "sg:city":"Grand Prairie",
    "sg:classifiers":[
        {
            "category":"Real Estate",
            "subcategory":"Real Estate Operator",
            "type":"Services"
        }
    ],
    "sg:phone":"+1 972 262 3663",
    "sg:postcode":"75050",
    "sg:province":"TX",
    "sg:tags":[
        "apartment"
    ],
    "wof:name":"Greenhill Apartments",
    "wof:placetype":"venue"
},
  "geometry": {"coordinates":[-96.998221,32.748828],"type":"Point"}
}