{
  "type": "Feature",
  "properties": {
    "iso:country":"US",
    "sg:address":"802 Juarez Ave",
    "sg:city":"Laredo",
    "sg:classifiers":[
        {
            "category":"Restaurant",
            "type":"Food & Drink"
        }
    ],
    "sg:phone":"+1 956 724 3185",
    "sg:postcode":"78040",
    "sg:province":"TX",
    "wof:name":"Danny's Restaurant",
    "wof:placetype":"venue"
},
  "geometry": {"coordinates":[-99.50947600000001,27.507128],"type":"Point"}
}