{
  "type": "Feature",
  "properties": {
    "iso:country":"US",
    "sg:address":"1103 State Hwy 46",
    "sg:city":"Seguin",
    "sg:classifiers":[
        {
            "category":"Wholesale",
            "subcategory":"Hardware",
            "type":"Manufacturing & Wholesale Goods"
        }
    ],
    "sg:phone":"+1 830 372 3660",
    "sg:postcode":"78155",
    "sg:province":"TX",
    "sg:tags":[
        "plumbing",
        "equipment",
        "fixture",
        "supply"
    ],
    "wof:name":"A & L Supply",
    "wof:placetype":"venue"
},
  "geometry": {"coordinates":[-97.99207800000001,29.581974],"type":"Point"}
}