{
  "type": "Feature",
  "properties": {
    "iso:country":"US",
    "sg:address":"2015 S I- 35",
    "sg:city":"Austin",
    "sg:classifiers":[
        {
            "category":"Building & Trades",
            "subcategory":"Cleaning & Sanitation",
            "type":"Services"
        }
    ],
    "sg:phone":"+1 512 796 8291",
    "sg:postcode":"78741",
    "sg:province":"TX",
    "sg:tags":[
        "janitor"
    ],
    "wof:name":"Compete Service Solutions",
    "wof:placetype":"venue"
},
  "geometry": {"coordinates":[-97.738281,30.237938],"type":"Point"}
}