{
  "type": "Feature",
  "properties": {
    "iso:country":"US",
    "sg:address":"939 E Irving Blvd",
    "sg:city":"Irving",
    "sg:classifiers":[
        {
            "category":"Restaurant",
            "type":"Food & Drink"
        }
    ],
    "sg:phone":"+1 972 438 4805",
    "sg:postcode":"75060",
    "sg:province":"TX",
    "wof:name":"Adam's Restaurant",
    "wof:placetype":"venue"
},
  "geometry": {"coordinates":[-96.935097,32.812099],"type":"Point"}
}