{
  "type": "Feature",
  "properties": {
    "iso:country":"US",
    "sg:address":"214 Kristine Ln",
    "sg:city":"Kingsbury",
    "sg:classifiers":[
        {
            "category":"Professional",
            "subcategory":"Engineering",
            "type":"Services"
        }
    ],
    "sg:phone":"+1 512 913 0667",
    "sg:postcode":"78638",
    "sg:province":"TX",
    "sg:tags":[
        "mini",
        "construction",
        "storage"
    ],
    "wof:name":"R R Installers",
    "wof:placetype":"venue"
},
  "geometry": {"coordinates":[-97.822168,29.65563],"type":"Point"}
}