{
  "type": "Feature",
  "properties": {
    "iso:country":"US",
    "sg:address":"2401 E 6th St",
    "sg:city":"Austin",
    "sg:classifiers":[
        {
            "category":"Organizations",
            "subcategory":"Professional Association",
            "type":"Services"
        }
    ],
    "sg:phone":"+1 512 495 9190",
    "sg:postcode":"78702",
    "sg:province":"TX",
    "wof:name":"Pedernales Owners Assn",
    "wof:placetype":"venue"
},
  "geometry": {"coordinates":[-97.71548799999999,30.259201],"type":"Point"}
}