{
  "type": "Feature",
  "properties": {
    "iso:country":"US",
    "sg:address":"10600 Six Pines Rd",
    "sg:city":"Spring",
    "sg:classifiers":[
        {
            "category":"Freight",
            "type":"Transportation"
        }
    ],
    "sg:phone":"+1 281 367 5299",
    "sg:postcode":"77380",
    "sg:province":"TX",
    "sg:tags":[
        "mover"
    ],
    "wof:name":"AMMCS",
    "wof:placetype":"venue"
},
  "geometry": {"coordinates":[-95.46126599999999,30.153436],"type":"Point"}
}