{
  "type": "Feature",
  "properties": {
    "iso:country":"US",
    "sg:address":"625 Fairway View Ter",
    "sg:city":"Grapevine",
    "sg:classifiers":[
        {
            "category":"Professional",
            "subcategory":"Management & Consulting",
            "type":"Services"
        }
    ],
    "sg:phone":"+1 817 410 9688",
    "sg:postcode":"76092",
    "sg:province":"TX",
    "sg:tags":[
        "course",
        "golf",
        "consultant"
    ],
    "wof:name":"Sports Turf Svc",
    "wof:placetype":"venue"
},
  "geometry": {"coordinates":[-97.14491200000001,32.923015],"type":"Point"}
}