{
  "type": "Feature",
  "properties": {
    "iso:country":"US",
    "sg:address":"9341 N Green River Dr",
    "sg:city":"Houston",
    "sg:classifiers":[
        {
            "category":"Building & Trades",
            "subcategory":"Plumbing",
            "type":"Services"
        }
    ],
    "sg:phone":"+1 713 631 7738",
    "sg:postcode":"77078",
    "sg:province":"TX",
    "sg:tags":[
        "conditioning",
        "air",
        "system",
        "contractor"
    ],
    "wof:name":"Big Tex Air Conditioning",
    "wof:placetype":"venue"
},
  "geometry": {"coordinates":[-95.239496,29.835856],"type":"Point"}
}