{
  "type": "Feature",
  "properties": {
    "iso:country":"US",
    "sg:address":"405 US Hwy 290 Bus",
    "sg:city":"Elgin",
    "sg:classifiers":[
        {
            "category":"Autos & Motor Vehicles",
            "subcategory":"Auto Supplies",
            "type":"Retail Goods"
        }
    ],
    "sg:phone":"+1 512 285 3301",
    "sg:postcode":"78621",
    "sg:province":"TX",
    "sg:tags":[
        "automobile",
        "parts"
    ],
    "wof:name":"A-Line Auto Parts",
    "wof:placetype":"venue"
},
  "geometry": {"coordinates":[-97.36864199999999,30.343314],"type":"Point"}
}