{
  "type": "Feature",
  "properties": {
    "iso:country":"US",
    "sg:address":"24 N 11th St",
    "sg:city":"Beaumont",
    "sg:classifiers":[
        {
            "category":"Autos & Motor Vehicles",
            "subcategory":"Boat Sales",
            "type":"Retail Goods"
        }
    ],
    "sg:phone":"+1 409 212 1005",
    "sg:postcode":"77702",
    "sg:province":"TX",
    "wof:name":"Pete Jorgensen Marine",
    "wof:placetype":"venue"
},
  "geometry": {"coordinates":[-94.129677,30.078537],"type":"Point"}
}