{
  "type": "Feature",
  "properties": {
    "iso:country":"US",
    "sg:address":"501 Liberty St",
    "sg:city":"Dublin",
    "sg:classifiers":[
        {
            "category":"Organizations",
            "subcategory":"Religious Organization",
            "type":"Services"
        }
    ],
    "sg:phone":"+1 254 445 2049",
    "sg:postcode":"76446",
    "sg:province":"TX",
    "sg:tags":[
        "church"
    ],
    "wof:name":"Southside Church Of Christ",
    "wof:placetype":"venue"
},
  "geometry": {"coordinates":[-98.336319,32.078222],"type":"Point"}
}