{
  "type": "Feature",
  "properties": {
    "iso:country":"US",
    "sg:address":"3333 Naaman School Rd",
    "sg:city":"Garland",
    "sg:classifiers":[
        {
            "category":"Wholesale",
            "subcategory":"Electrical",
            "type":"Manufacturing & Wholesale Goods"
        }
    ],
    "sg:phone":"+1 972 414 8188",
    "sg:postcode":"75040",
    "sg:province":"TX",
    "sg:tags":[
        "electronic",
        "representative"
    ],
    "sg:website":"www.cmatex.com",
    "wof:name":"Centra Mark America Inc",
    "wof:placetype":"venue"
},
  "geometry": {"coordinates":[-96.622411,32.949039],"type":"Point"}
}