{
  "type": "Feature",
  "properties": {
    "iso:country":"US",
    "sg:address":"2907 Claremont Dr",
    "sg:city":"Mansfield",
    "sg:classifiers":[
        {
            "category":"Professional",
            "subcategory":"Management & Consulting",
            "type":"Services"
        }
    ],
    "sg:phone":"+1 817 477 4710",
    "sg:postcode":"76063",
    "sg:province":"TX",
    "sg:tags":[
        "public",
        "relations"
    ],
    "wof:name":"CK Promotions & Graphics",
    "wof:placetype":"venue"
},
  "geometry": {"coordinates":[-97.120125,32.607045],"type":"Point"}
}