{
  "type": "Feature",
  "properties": {
    "iso:country":"US",
    "sg:address":"934 New Laredo Hwy",
    "sg:city":"San Antonio",
    "sg:classifiers":[
        {
            "category":"Travel",
            "subcategory":"Hotels & Motels",
            "type":"Entertainment"
        }
    ],
    "sg:phone":"+1 210 923 7193",
    "sg:postcode":"78211",
    "sg:province":"TX",
    "sg:tags":[
        "operation"
    ],
    "wof:name":"Mayfield Motel",
    "wof:placetype":"venue"
},
  "geometry": {"coordinates":[-98.553414,29.362436],"type":"Point"}
}