{
  "type": "Feature",
  "properties": {
    "iso:country":"US",
    "sg:address":"7454 Spicewood Springs Rd",
    "sg:city":"Austin",
    "sg:classifiers":[
        {
            "category":"Building & Trades",
            "subcategory":"Construction",
            "type":"Services"
        }
    ],
    "sg:phone":"+1 512 736 3732",
    "sg:postcode":"78759",
    "sg:province":"TX",
    "sg:tags":[
        "residential"
    ],
    "wof:name":"Jay Barstow",
    "wof:placetype":"venue"
},
  "geometry": {"coordinates":[-97.793655,30.420517],"type":"Point"}
}