{
  "type": "Feature",
  "properties": {
    "iso:country":"US",
    "sg:address":"2601 Scott Ave",
    "sg:city":"Fort Worth",
    "sg:classifiers":[
        {
            "category":"Shopping",
            "subcategory":"Computers & Home Electronics",
            "type":"Retail Goods"
        }
    ],
    "sg:phone":"+1 817 531 8992",
    "sg:postcode":"76103",
    "sg:province":"TX",
    "sg:tags":[
        "software"
    ],
    "sg:website":"www.hcc-care.com",
    "wof:name":"Healthcare Computer Corp",
    "wof:placetype":"venue"
},
  "geometry": {"coordinates":[-97.287527,32.74771],"type":"Point"}
}