{
  "type": "Feature",
  "properties": {
    "iso:country":"US",
    "sg:address":"6801 Viewing Pl",
    "sg:city":"Austin",
    "sg:classifiers":[
        {
            "category":"Manufacturing",
            "subcategory":"Signs",
            "type":"Manufacturing & Wholesale Goods"
        }
    ],
    "sg:phone":"+1 512 243 2210",
    "sg:postcode":"78719",
    "sg:province":"TX",
    "wof:name":"K & M Signs",
    "wof:placetype":"venue"
},
  "geometry": {"coordinates":[-97.69204499999999,30.160741],"type":"Point"}
}