{
  "type": "Feature",
  "properties": {
    "iso:country":"US",
    "sg:address":"131 Teal Ridge",
    "sg:city":"New Braunfels",
    "sg:classifiers":[
        {
            "category":"Professional",
            "subcategory":"Business Services",
            "type":"Services"
        }
    ],
    "sg:phone":"+1 830 964 3263",
    "sg:postcode":"78133",
    "sg:province":"TX",
    "wof:name":"Esque Teal Enterprises",
    "wof:placetype":"venue"
},
  "geometry": {"coordinates":[-98.11903,29.857949],"type":"Point"}
}