{
  "type": "Feature",
  "properties": {
    "iso:country":"US",
    "sg:address":"530 N Main St",
    "sg:city":"Beaumont",
    "sg:classifiers":[
        {
            "category":"Organizations",
            "subcategory":"Religious Organization",
            "type":"Services"
        }
    ],
    "sg:phone":"+1 409 838 6308",
    "sg:postcode":"77701",
    "sg:province":"TX",
    "sg:tags":[
        "church"
    ],
    "wof:name":"Westminister Presbyterian Chr",
    "wof:placetype":"venue"
},
  "geometry": {"coordinates":[-94.099726,30.087414],"type":"Point"}
}