{
  "type": "Feature",
  "properties": {
    "iso:country":"US",
    "sg:address":"5711 Sugar Hill Dr",
    "sg:city":"Houston",
    "sg:classifiers":[
        {
            "category":"Freight",
            "type":"Transportation"
        }
    ],
    "sg:phone":"+1 713 953 7301",
    "sg:postcode":"77057",
    "sg:province":"TX",
    "sg:tags":[
        "operator",
        "packing",
        "crating",
        "local",
        "trucking"
    ],
    "wof:name":"Advantage Moving & Storage Inc",
    "wof:placetype":"venue"
},
  "geometry": {"coordinates":[-95.47831600000001,29.756857],"type":"Point"}
}