{
  "type": "Feature",
  "properties": {
    "iso:country":"US",
    "sg:address":"3801 S Collins St",
    "sg:city":"Arlington",
    "sg:classifiers":[
        {
            "category":"Banks & Credit Unions",
            "subcategory":"Bank",
            "type":"Services"
        }
    ],
    "sg:phone":"+1 817 276 5900",
    "sg:postcode":"76014",
    "sg:province":"TX",
    "sg:tags":[
        "financing"
    ],
    "wof:name":"Providian Financial Co",
    "wof:placetype":"venue"
},
  "geometry": {"coordinates":[-97.093436,32.680755],"type":"Point"}
}