{
  "type": "Feature",
  "properties": {
    "iso:country":"US",
    "sg:address":"707 W 10th St",
    "sg:city":"Austin",
    "sg:classifiers":[
        {
            "category":"Social Services",
            "type":"Services"
        }
    ],
    "sg:phone":"+1 512 322 0006",
    "sg:postcode":"78701",
    "sg:province":"TX",
    "sg:tags":[
        "counselor",
        "marriage",
        "family"
    ],
    "wof:name":"Marchetta Ramirez",
    "wof:placetype":"venue"
},
  "geometry": {"coordinates":[-97.749183,30.273872],"type":"Point"}
}