{
  "type": "Feature",
  "properties": {
    "iso:country":"US",
    "sg:address":"2251 N Main St",
    "sg:city":"Fort Worth",
    "sg:classifiers":[
        {
            "category":"Banks & Credit Unions",
            "subcategory":"Bank",
            "type":"Services"
        }
    ],
    "sg:phone":"+1 817 624 1635",
    "sg:postcode":"76164",
    "sg:province":"TX",
    "sg:tags":[
        "money",
        "order"
    ],
    "wof:name":"America Transfers Inc",
    "wof:placetype":"venue"
},
  "geometry": {"coordinates":[-97.34916,32.786277],"type":"Point"}
}