{
  "type": "Feature",
  "properties": {
    "iso:country":"US",
    "sg:address":"650 Uptown Blvd",
    "sg:city":"Cedar Hill",
    "sg:classifiers":[
        {
            "category":"Ice Cream",
            "type":"Food & Drink"
        }
    ],
    "sg:menulink":"http://www.allmenus.com/tx/southwest/255461-sheridans-frozen-custard/menu/",
    "sg:phone":"+1 469 272 5495",
    "sg:postcode":"75104",
    "sg:province":"TX",
    "sg:tags":[
        "american"
    ],
    "wof:name":"Sheridan's Frozen Custard",
    "wof:placetype":"venue"
},
  "geometry": {"coordinates":[-96.945047,32.599251],"type":"Point"}
}