{
  "type": "Feature",
  "properties": {
    "iso:country":"US",
    "sg:address":"1710 S Dairy Ashford St",
    "sg:city":"Houston",
    "sg:classifiers":[
        {
            "category":"Insurance",
            "subcategory":"Title Insurance",
            "type":"Services"
        }
    ],
    "sg:phone":"+1 281 504 1580",
    "sg:postcode":"77077",
    "sg:province":"TX",
    "sg:tags":[
        "loan",
        "company"
    ],
    "wof:name":"First American Equity Ln Svcs",
    "wof:placetype":"venue"
},
  "geometry": {"coordinates":[-95.606061,29.750172],"type":"Point"}
}