{
  "type": "Feature",
  "properties": {
    "iso:country":"US",
    "sg:address":"3627 Inwood Dr",
    "sg:city":"Houston",
    "sg:classifiers":[
        {
            "category":"Banks & Credit Unions",
            "subcategory":"Financial Services",
            "type":"Services"
        }
    ],
    "sg:phone":"+1 713 622 9982",
    "sg:postcode":"77019",
    "sg:province":"TX",
    "sg:tags":[
        "trust",
        "management"
    ],
    "wof:name":"Lcgw Family Partners Ltd",
    "wof:placetype":"venue"
},
  "geometry": {"coordinates":[-95.436778,29.751106],"type":"Point"}
}