{
  "type": "Feature",
  "properties": {
    "iso:country":"US",
    "sg:address":"804 Jackson St",
    "sg:city":"Marlin",
    "sg:classifiers":[
        {
            "category":"Organizations",
            "subcategory":"Religious Organization",
            "type":"Services"
        }
    ],
    "sg:phone":"+1 254 803 5093",
    "sg:postcode":"76661",
    "sg:province":"TX",
    "sg:tags":[
        "church"
    ],
    "wof:name":"Pentecostal Bibleway Holiness",
    "wof:placetype":"venue"
},
  "geometry": {"coordinates":[-96.883487,31.301773],"type":"Point"}
}