{
  "type": "Feature",
  "properties": {
    "iso:country":"US",
    "sg:address":"617 Blessing Ranch Rd",
    "sg:city":"Liberty Hill",
    "sg:classifiers":[
        {
            "category":"Building & Trades",
            "subcategory":"Construction",
            "type":"Services"
        }
    ],
    "sg:phone":"+1 512 515 5688",
    "sg:postcode":"78642",
    "sg:province":"TX",
    "sg:tags":[
        "excavating",
        "contractor"
    ],
    "wof:name":"Liberty Hill Tractor & Backhoe",
    "wof:placetype":"venue"
},
  "geometry": {"coordinates":[-97.92271700000001,30.727862],"type":"Point"}
}