{
  "type": "Feature",
  "properties": {
    "iso:country":"US",
    "sg:address":"2717 Larkin Ave",
    "sg:city":"Fort Worth",
    "sg:classifiers":[
        {
            "category":"Insurance",
            "subcategory":"Insurance Agent",
            "type":"Services"
        }
    ],
    "sg:phone":"+1 817 370 6095",
    "sg:postcode":"76133",
    "sg:province":"TX",
    "wof:name":"Gristina Chris Prdential Insur",
    "wof:placetype":"venue"
},
  "geometry": {"coordinates":[-97.357519,32.665462],"type":"Point"}
}