{
  "type": "Feature",
  "properties": {
    "iso:country":"US",
    "sg:address":"2615 Sunnybrook Dr",
    "sg:city":"Tyler",
    "sg:classifiers":[
        {
            "category":"Professional",
            "subcategory":"Business Services",
            "type":"Services"
        }
    ],
    "sg:phone":"+1 903 597 5881",
    "sg:postcode":"75701",
    "sg:province":"TX",
    "sg:tags":[
        "translator",
        "interpreter"
    ],
    "wof:name":"Urbina Support Svc",
    "wof:placetype":"venue"
},
  "geometry": {"coordinates":[-95.309416,32.322238],"type":"Point"}
}