{
  "type": "Feature",
  "properties": {
    "iso:country":"US",
    "sg:address":"1900 Preston Rd",
    "sg:city":"Plano",
    "sg:classifiers":[
        {
            "category":"Health Services",
            "subcategory":"Doctor",
            "type":"Services"
        }
    ],
    "sg:phone":"+1 972 867 3177",
    "sg:postcode":"75093",
    "sg:province":"TX",
    "wof:name":"Ozier Mark DDS Ms PC",
    "wof:placetype":"venue"
},
  "geometry": {"coordinates":[-96.794837,33.025921],"type":"Point"}
}