{
  "type": "Feature",
  "properties": {
    "iso:country":"US",
    "sg:address":"901 N McDonald St",
    "sg:city":"Mc Kinney",
    "sg:classifiers":[
        {
            "category":"Shopping",
            "type":"Retail Goods"
        }
    ],
    "sg:phone":"+1 214 544 3894",
    "sg:postcode":"75069",
    "sg:province":"TX",
    "sg:tags":[
        "merchandise"
    ],
    "wof:name":"Cellular Too",
    "wof:placetype":"venue"
},
  "geometry": {"coordinates":[-96.612584,33.2102],"type":"Point"}
}