{
  "type": "Feature",
  "properties": {
    "iso:country":"US",
    "sg:address":"6519 Gaston Ave",
    "sg:city":"Dallas",
    "sg:classifiers":[
        {
            "category":"Professional",
            "subcategory":"Business Services",
            "type":"Services"
        }
    ],
    "sg:phone":"+1 214 827 1264",
    "sg:postcode":"75214",
    "sg:province":"TX",
    "wof:name":"Intrepid Partners Inc",
    "wof:placetype":"venue"
},
  "geometry": {"coordinates":[-96.750518,32.816437],"type":"Point"}
}