{
  "type": "Feature",
  "properties": {
    "iso:country":"US",
    "sg:address":"1014 Spanish Cove Dr",
    "sg:city":"Crosby",
    "sg:classifiers":[
        {
            "category":"Social Services",
            "subcategory":"Child Care",
            "type":"Services"
        }
    ],
    "sg:phone":"+1 281 324 1255",
    "sg:postcode":"77532",
    "sg:province":"TX",
    "wof:name":"Judds Child Care Center",
    "wof:placetype":"venue"
},
  "geometry": {"coordinates":[-95.103082,29.995639],"type":"Point"}
}