{
  "type": "Feature",
  "properties": {
    "iso:country":"US",
    "sg:address":"6175 E Yandell Dr",
    "sg:city":"El Paso",
    "sg:classifiers":[
        {
            "category":"Food & Beverages",
            "subcategory":"Groceries & Convenience Stores",
            "type":"Retail Goods"
        }
    ],
    "sg:phone":"+1 915 774 9897",
    "sg:postcode":"79905",
    "sg:province":"TX",
    "wof:name":"Gloria Parga Flea Mkt",
    "wof:placetype":"venue"
},
  "geometry": {"coordinates":[-106.412953,31.775211],"type":"Point"}
}