{
  "type": "Feature",
  "properties": {
    "iso:country":"US",
    "sg:address":"9023 E County Road 5300",
    "sg:city":"Idalou",
    "sg:classifiers":[
        {
            "category":"Transit Center",
            "subcategory":"Freight",
            "type":"Transportation"
        },
        {
            "category":"Freight",
            "type":"Transportation"
        }
    ],
    "sg:phone":"+1 806 892 2215",
    "sg:postcode":"79329",
    "sg:province":"TX",
    "sg:tags":[
        "local",
        "trucking-motor",
        "trucking"
    ],
    "wof:name":"Windmill Trucking Inc",
    "wof:placetype":"venue"
},
  "geometry": {"coordinates":[-101.68179499999999,33.783505],"type":"Point"}
}