{
  "type": "Feature",
  "properties": {
    "iso:country":"US",
    "sg:address":"708 Littlewood St",
    "sg:city":"Baytown",
    "sg:classifiers":[
        {
            "category":"Professional",
            "type":"Services"
        }
    ],
    "sg:phone":"+1 281 428 2262",
    "sg:postcode":"77521",
    "sg:province":"TX",
    "wof:name":"Dreams & More",
    "wof:placetype":"venue"
},
  "geometry": {"coordinates":[-94.955782,29.7553],"type":"Point"}
}