{
  "type": "Feature",
  "properties": {
    "iso:country":"US",
    "sg:address":"1201 Bacon Ranch Rd",
    "sg:city":"Killeen",
    "sg:classifiers":[
        {
            "category":"Real Estate",
            "subcategory":"Real Estate Operator",
            "type":"Services"
        }
    ],
    "sg:phone":"+1 254 526 9707",
    "sg:postcode":"76542",
    "sg:province":"TX",
    "sg:tags":[
        "building",
        "apartment"
    ],
    "wof:name":"Hunter's Glen Village Apts",
    "wof:placetype":"venue"
},
  "geometry": {"coordinates":[-97.731453,31.089088],"type":"Point"}
}