{
  "type": "Feature",
  "properties": {
    "iso:country":"US",
    "sg:address":"6608 Estados Dr",
    "sg:city":"Allen",
    "sg:classifiers":[
        {
            "category":"Freight",
            "type":"Transportation"
        }
    ],
    "sg:phone":"+1 972 429 5125",
    "sg:postcode":"75002",
    "sg:province":"TX",
    "sg:tags":[
        "operator",
        "local",
        "trucking"
    ],
    "wof:name":"Frank Easterling Trucking",
    "wof:placetype":"venue"
},
  "geometry": {"coordinates":[-96.601208,33.057252],"type":"Point"}
}