{
  "type": "Feature",
  "properties": {
    "iso:country":"US",
    "sg:address":"3699 McKinney Ave Ste 104-B",
    "sg:city":"Dallas",
    "sg:classifiers":[
        {
            "category":"Food & Beverages",
            "subcategory":"Specialty",
            "type":"Retail Goods"
        }
    ],
    "sg:phone":"+1 214 528 7900",
    "sg:postcode":"75204",
    "sg:province":"TX",
    "sg:website":"www.spiceandtea.com",
    "wof:name":"The Spice and Tea Exchange",
    "wof:placetype":"venue"
},
  "geometry": {"coordinates":[-96.79691099999999,32.808959],"type":"Point"}
}