{
  "type": "Feature",
  "properties": {
    "iso:country":"US",
    "sg:address":"310 N Texas Blvd",
    "sg:city":"Weslaco",
    "sg:classifiers":[
        {
            "category":"Building & Trades",
            "subcategory":"Construction",
            "type":"Services"
        }
    ],
    "sg:phone":"+1 956 969 2839",
    "sg:postcode":"78596",
    "sg:province":"TX",
    "sg:tags":[
        "house"
    ],
    "wof:name":"Center Line Construction",
    "wof:placetype":"venue"
},
  "geometry": {"coordinates":[-97.99085700000001,26.165332],"type":"Point"}
}