{
  "type": "Feature",
  "properties": {
    "iso:country":"US",
    "sg:address":"41 N Copperknoll Cir",
    "sg:city":"Spring",
    "sg:classifiers":[
        {
            "category":"Professional",
            "subcategory":"Management & Consulting",
            "type":"Services"
        }
    ],
    "sg:phone":"+1 281 296 0607",
    "sg:postcode":"77381",
    "sg:province":"TX",
    "sg:tags":[
        "consultant"
    ],
    "wof:name":"IAM Consulting Inc",
    "wof:placetype":"venue"
},
  "geometry": {"coordinates":[-95.51396,30.180964],"type":"Point"}
}