{
  "type": "Feature",
  "properties": {
    "iso:country":"US",
    "sg:address":"6130 Westview Dr",
    "sg:city":"Houston",
    "sg:classifiers":[
        {
            "category":"Home & Garden",
            "subcategory":"Furniture",
            "type":"Retail Goods"
        }
    ],
    "sg:phone":"+1 713 252 9800",
    "sg:postcode":"77055",
    "sg:province":"TX",
    "wof:name":"Bdc Furniture Group",
    "wof:placetype":"venue"
},
  "geometry": {"coordinates":[-95.45901600000001,29.793998],"type":"Point"}
}