{
  "type": "Feature",
  "properties": {
    "iso:country":"US",
    "sg:address":"3508 University Blvd",
    "sg:city":"Dallas",
    "sg:classifiers":[
        {
            "category":"Professional",
            "subcategory":"Lawyer & Legal Services",
            "type":"Services"
        }
    ],
    "sg:phone":"+1 214 373 7161",
    "sg:postcode":"75205",
    "sg:province":"TX",
    "sg:tags":[
        "attorney"
    ],
    "wof:name":"Robert N Virden PC",
    "wof:placetype":"venue"
},
  "geometry": {"coordinates":[-96.792581,32.845102],"type":"Point"}
}