{
  "type": "Feature",
  "properties": {
    "iso:country":"US",
    "sg:address":"4365 S Eden Rd",
    "sg:city":"Kennedale",
    "sg:classifiers":[
        {
            "category":"Banks & Credit Unions",
            "subcategory":"Financial Services",
            "type":"Services"
        }
    ],
    "sg:phone":"+1 817 561 0414",
    "sg:postcode":"76060",
    "sg:province":"TX",
    "sg:tags":[
        "investor"
    ],
    "wof:name":"Jordan Investments",
    "wof:placetype":"venue"
},
  "geometry": {"coordinates":[-97.20163599999999,32.623358],"type":"Point"}
}