{
  "type": "Feature",
  "properties": {
    "iso:country":"US",
    "sg:address":"200 E Sarah Ave",
    "sg:city":"Longview",
    "sg:classifiers":[
        {
            "category":"Building & Trades",
            "subcategory":"Plumbing",
            "type":"Services"
        }
    ],
    "sg:phone":"+1 903 297 2696",
    "sg:postcode":"75604",
    "sg:province":"TX",
    "sg:tags":[
        "contractor"
    ],
    "wof:name":"Superior AC & Htg",
    "wof:placetype":"venue"
},
  "geometry": {"coordinates":[-94.804878,32.528735],"type":"Point"}
}