{
  "type": "Feature",
  "properties": {
    "iso:country":"US",
    "sg:address":"1212 W Palestine Ave",
    "sg:city":"Palestine",
    "sg:classifiers":[
        {
            "category":"Manufacturing",
            "subcategory":"Tools & Machinery",
            "type":"Manufacturing & Wholesale Goods"
        }
    ],
    "sg:phone":"+1 903 729 2730",
    "sg:postcode":"75801",
    "sg:province":"TX",
    "sg:tags":[
        "steel"
    ],
    "wof:name":"Palestine Imported Metals Co",
    "wof:placetype":"venue"
},
  "geometry": {"coordinates":[-95.64630699999999,31.764118],"type":"Point"}
}