{
  "type": "Feature",
  "properties": {
    "iso:country":"US",
    "sg:address":"605 W Brentwood St",
    "sg:city":"Channelview",
    "sg:classifiers":[
        {
            "category":"Shopping",
            "subcategory":"Gifts & Souvenirs",
            "type":"Retail Goods"
        }
    ],
    "sg:phone":"+1 281 452 6227",
    "sg:postcode":"77530",
    "sg:province":"TX",
    "wof:name":"Fancy That E Gifts",
    "wof:placetype":"venue"
},
  "geometry": {"coordinates":[-95.145365,29.781423],"type":"Point"}
}