{
  "type": "Feature",
  "properties": {
    "iso:country":"US",
    "sg:address":"4403 Three Rivers Dr",
    "sg:city":"Sugar Land",
    "sg:classifiers":[
        {
            "category":"Recreation",
            "type":"Entertainment"
        }
    ],
    "sg:phone":"+1 281 265 6843",
    "sg:postcode":"77478",
    "sg:province":"TX",
    "wof:name":"Coastal Guide Service",
    "wof:placetype":"venue"
},
  "geometry": {"coordinates":[-95.58785899999999,29.60445],"type":"Point"}
}