{
  "type": "Feature",
  "properties": {
    "iso:country":"US",
    "sg:address":"400 Memorial City Way",
    "sg:city":"Houston",
    "sg:classifiers":[
        {
            "category":"Health Services",
            "subcategory":"Optometrist",
            "type":"Services"
        },
        {
            "category":"Shopping",
            "subcategory":"Optician",
            "type":"Retail Goods"
        }
    ],
    "sg:phone":"+1 713 467 5047",
    "sg:postcode":"77024",
    "sg:province":"TX",
    "sg:tags":[
        "eyewear"
    ],
    "sg:website":"www.primaryeyecare.com",
    "wof:name":"Primary Eye Care",
    "wof:placetype":"venue"
},
  "geometry": {"coordinates":[-95.535912,29.779763],"type":"Point"}
}