{
  "type": "Feature",
  "properties": {
    "iso:country":"US",
    "sg:address":"3042 S Port Ave",
    "sg:city":"Corpus Christi",
    "sg:classifiers":[
        {
            "category":"Banks & Credit Unions",
            "subcategory":"Bank",
            "type":"Services"
        }
    ],
    "sg:phone":"+1 361 882 4522",
    "sg:postcode":"78405",
    "sg:province":"TX",
    "sg:tags":[
        "cashing",
        "check"
    ],
    "wof:name":"Cash & Go",
    "wof:placetype":"venue"
},
  "geometry": {"coordinates":[-97.42014399999999,27.765787],"type":"Point"}
}