{
  "type": "Feature",
  "properties": {
    "iso:country":"US",
    "sg:address":"1849 Carson Ln",
    "sg:city":"Frisco",
    "sg:classifiers":[
        {
            "category":"Shopping",
            "subcategory":"Computers & Home Electronics",
            "type":"Retail Goods"
        }
    ],
    "sg:phone":"+1 972 712 8016",
    "sg:postcode":"75034",
    "sg:province":"TX",
    "sg:tags":[
        "equipment",
        "dealer"
    ],
    "wof:name":"Mendenhall Enterprises",
    "wof:placetype":"venue"
},
  "geometry": {"coordinates":[-96.874915,33.153884],"type":"Point"}
}