{
  "type": "Feature",
  "properties": {
    "iso:country":"US",
    "sg:address":"310 Ingram Rd",
    "sg:city":"Devine",
    "sg:classifiers":[
        {
            "category":"Professional",
            "subcategory":"Advertising",
            "type":"Services"
        }
    ],
    "sg:phone":"+1 830 665 3287",
    "sg:postcode":"78016",
    "sg:province":"TX",
    "sg:tags":[
        "agency"
    ],
    "wof:name":"Ponce Advertising",
    "wof:placetype":"venue"
},
  "geometry": {"coordinates":[-98.902053,29.159318],"type":"Point"}
}