{
  "type": "Feature",
  "properties": {
    "iso:country":"US",
    "sg:address":"3900 Hemphill St",
    "sg:city":"Fort Worth",
    "sg:classifiers":[
        {
            "category":"Food & Beverages",
            "subcategory":"Groceries & Convenience Stores",
            "type":"Retail Goods"
        }
    ],
    "sg:phone":"+1 817 924 9342",
    "sg:postcode":"76110",
    "sg:province":"TX",
    "sg:tags":[
        "grocer"
    ],
    "wof:name":"Terrys Supermarket",
    "wof:placetype":"venue"
},
  "geometry": {"coordinates":[-97.331734,32.689977],"type":"Point"}
}