{
  "type": "Feature",
  "properties": {
    "iso:country":"US",
    "sg:address":"819 Water St",
    "sg:city":"Kerrville",
    "sg:classifiers":[
        {
            "category":"Social Services",
            "type":"Services"
        }
    ],
    "sg:phone":"+1 830 896 7643",
    "sg:postcode":"78028",
    "sg:province":"TX",
    "sg:tags":[
        "organization",
        "welfare"
    ],
    "sg:website":"www.twc.state.tx.us",
    "wof:name":"Alamo Workforce Development",
    "wof:placetype":"venue"
},
  "geometry": {"coordinates":[-99.140423,30.045341],"type":"Point"}
}