{
  "type": "Feature",
  "properties": {
    "iso:country":"US",
    "sg:address":"695 Normandy St",
    "sg:city":"Houston",
    "sg:classifiers":[
        {
            "category":"Organizations",
            "subcategory":"Religious Organization",
            "type":"Services"
        }
    ],
    "sg:phone":"+1 713 455 3088",
    "sg:postcode":"77015",
    "sg:province":"TX",
    "sg:tags":[
        "church"
    ],
    "wof:name":"Church Of Jesus Christ Lds",
    "wof:placetype":"venue"
},
  "geometry": {"coordinates":[-95.203233,29.786047],"type":"Point"}
}