{
  "type": "Feature",
  "properties": {
    "iso:country":"US",
    "sg:address":"901 Zauk Ave",
    "sg:city":"Dumas",
    "sg:classifiers":[
        {
            "category":"Organizations",
            "subcategory":"Religious Organization",
            "type":"Services"
        }
    ],
    "sg:phone":"+1 806 935 5003",
    "sg:postcode":"79029",
    "sg:province":"TX",
    "wof:name":"Hispana Mission",
    "wof:placetype":"venue"
},
  "geometry": {"coordinates":[-101.96637200000001,35.85639],"type":"Point"}
}