{
  "type": "Feature",
  "properties": {
    "iso:country":"US",
    "sg:address":"2810B Karnack Hwy",
    "sg:city":"Marshall",
    "sg:classifiers":[
        {
            "category":"Coffee & Tea",
            "type":"Food & Drink"
        },
        {
            "category":"Restaurant",
            "type":"Food & Drink"
        }
    ],
    "sg:phone":"+1 903 938 2133",
    "sg:postcode":"75672",
    "sg:province":"TX",
    "sg:tags":[
        "shop",
        "espresso"
    ],
    "wof:name":"Lady Tremaine Coffee Shop",
    "wof:placetype":"venue"
},
  "geometry": {"coordinates":[-94.336281,32.55373],"type":"Point"}
}