{
  "type": "Feature",
  "properties": {
    "iso:country":"US",
    "sg:address":"3203 Carol Ann St",
    "sg:city":"Wichita Falls",
    "sg:classifiers":[
        {
            "category":"Manufacturing",
            "subcategory":"Tools & Machinery",
            "type":"Manufacturing & Wholesale Goods"
        }
    ],
    "sg:phone":"+1 940 763 0183",
    "sg:postcode":"76309",
    "sg:province":"TX",
    "sg:tags":[
        "computer",
        "electronic",
        "mfg"
    ],
    "wof:name":"Ffmy Computing",
    "wof:placetype":"venue"
},
  "geometry": {"coordinates":[-98.532726,33.901039],"type":"Point"}
}