{
  "type": "Feature",
  "properties": {
    "iso:country":"US",
    "sg:address":"3200 Ave F",
    "sg:city":"Bay City",
    "sg:classifiers":[
        {
            "category":"Manufacturing",
            "subcategory":"Tools & Machinery",
            "type":"Manufacturing & Wholesale Goods"
        },
        {
            "category":"Retail",
            "subcategory":"Auto Repair",
            "type":"Services"
        }
    ],
    "sg:phone":"+1 979 244 4217",
    "sg:postcode":"77414",
    "sg:province":"TX",
    "sg:tags":[
        "machine",
        "automotive",
        "shop"
    ],
    "wof:name":"Johs Automotive Machine Svcs",
    "wof:placetype":"venue"
},
  "geometry": {"coordinates":[-95.96966500000001,28.971164],"type":"Point"}
}