{
  "type": "Feature",
  "properties": {
    "iso:country":"US",
    "sg:address":"522 W Live Oak St",
    "sg:city":"Dublin",
    "sg:classifiers":[
        {
            "category":"Freight",
            "type":"Transportation"
        }
    ],
    "sg:phone":"+1 254 445 2132",
    "sg:postcode":"76446",
    "sg:province":"TX",
    "sg:tags":[
        "operator",
        "local",
        "trucking"
    ],
    "wof:name":"Gonzales Trucking",
    "wof:placetype":"venue"
},
  "geometry": {"coordinates":[-98.347385,32.087325],"type":"Point"}
}