{
  "type": "Feature",
  "properties": {
    "iso:country":"US",
    "sg:address":"1010 W Jasper Dr Ste 12",
    "sg:city":"Killeen",
    "sg:classifiers":[
        {
            "category":"Restaurant",
            "type":"Food & Drink"
        },
        {
            "category":"Bakery",
            "type":"Food & Drink"
        }
    ],
    "sg:phone":"+1 254 628 0497",
    "sg:postcode":"76542",
    "sg:province":"TX",
    "wof:name":"Sweet Eats",
    "wof:placetype":"venue"
},
  "geometry": {"coordinates":[-97.746484,31.10229],"type":"Point"}
}