{
  "type": "Feature",
  "properties": {
    "iso:country":"US",
    "sg:address":"1203 W Cameron Ave",
    "sg:city":"Rockdale",
    "sg:classifiers":[
        {
            "category":"Organizations",
            "subcategory":"Professional Association",
            "type":"Services"
        }
    ],
    "sg:phone":"+1 512 446 2030",
    "sg:postcode":"76567",
    "sg:province":"TX",
    "sg:tags":[
        "chamber",
        "commerce"
    ],
    "sg:website":"www.rockdalechamber.com",
    "wof:name":"Chamber of Commerce",
    "wof:placetype":"venue"
},
  "geometry": {"coordinates":[-97.014685,30.649458],"type":"Point"}
}