{
  "type": "Feature",
  "properties": {
    "iso:country":"US",
    "sg:address":"1805 Ouida Dr",
    "sg:city":"Austin",
    "sg:classifiers":[
        {
            "category":"Real Estate",
            "subcategory":"Surveying",
            "type":"Services"
        }
    ],
    "sg:phone":"+1 512 267 7430",
    "sg:postcode":"78728",
    "sg:province":"TX",
    "sg:tags":[
        "surveyor",
        "land",
        "engineer"
    ],
    "wof:name":"G & R Surveying",
    "wof:placetype":"venue"
},
  "geometry": {"coordinates":[-97.66902399999999,30.447615],"type":"Point"}
}