{
  "type": "Feature",
  "properties": {
    "iso:country":"US",
    "sg:address":"117 S Front St",
    "sg:city":"Cotulla",
    "sg:classifiers":[
        {
            "category":"Organizations",
            "subcategory":"Community Association",
            "type":"Services"
        }
    ],
    "sg:phone":"+1 830 879 3774",
    "sg:postcode":"78014",
    "sg:province":"TX",
    "sg:tags":[
        "club"
    ],
    "wof:name":"Cotulla Social Club",
    "wof:placetype":"venue"
},
  "geometry": {"coordinates":[-99.233774,28.435767],"type":"Point"}
}