{
  "type": "Feature",
  "properties": {
    "iso:country":"US",
    "sg:address":"1319 State Hwy 114L Bus",
    "sg:city":"Grapevine",
    "sg:classifiers":[
        {
            "category":"Banks & Credit Unions",
            "subcategory":"Bank",
            "type":"Services"
        }
    ],
    "sg:phone":"+1 817 488 0775",
    "sg:postcode":"76051",
    "sg:province":"TX",
    "wof:name":"Washington Mutual",
    "wof:placetype":"venue"
},
  "geometry": {"coordinates":[-97.09038,32.941015],"type":"Point"}
}