{
  "type": "Feature",
  "properties": {
    "iso:country":"US",
    "sg:address":"2567 Valley View Ln",
    "sg:city":"Dallas",
    "sg:classifiers":[
        {
            "category":"Social Services",
            "subcategory":"Child Care",
            "type":"Services"
        },
        {
            "category":"Education",
            "subcategory":"Preschool",
            "type":"Public Place"
        },
        {
            "category":"Education",
            "subcategory":"School",
            "type":"Public Place"
        }
    ],
    "sg:phone":"+1 972 243 7209",
    "sg:postcode":"75234",
    "sg:province":"TX",
    "sg:tags":[
        "elementary",
        "day"
    ],
    "wof:name":"Kiddie Castle Learning",
    "wof:placetype":"venue"
},
  "geometry": {"coordinates":[-96.8946,32.924099],"type":"Point"}
}