{
  "type": "Feature",
  "properties": {
    "iso:country":"US",
    "sg:address":"1207 Grand Junction Dr",
    "sg:city":"Katy",
    "sg:classifiers":[
        {
            "category":"Professional",
            "type":"Services"
        }
    ],
    "sg:phone":"+1 281 395 3741",
    "sg:postcode":"77450",
    "sg:province":"TX",
    "wof:name":"Mikes Master Pieces La",
    "wof:placetype":"venue"
},
  "geometry": {"coordinates":[-95.753685,29.763672],"type":"Point"}
}