{
  "type": "Feature",
  "properties": {
    "iso:country":"US",
    "sg:address":"2401 Comburg Castle Way",
    "sg:city":"Austin",
    "sg:classifiers":[
        {
            "category":"Organizations",
            "subcategory":"Religious Organization",
            "type":"Services"
        }
    ],
    "sg:phone":"+1 512 292 1814",
    "sg:postcode":"78748",
    "sg:province":"TX",
    "wof:name":"Faith Knowlton",
    "wof:placetype":"venue"
},
  "geometry": {"coordinates":[-97.823885,30.184707],"type":"Point"}
}