{
  "type": "Feature",
  "properties": {
    "iso:country":"US",
    "sg:address":"9815 FM 1952",
    "sg:city":"Wallis",
    "sg:classifiers":[
        {
            "category":"Retail",
            "subcategory":"Repair Shop",
            "type":"Services"
        }
    ],
    "sg:phone":"+1 979 478 6730",
    "sg:postcode":"77485",
    "sg:province":"TX",
    "wof:name":"C&L Cleaning",
    "wof:placetype":"venue"
},
  "geometry": {"coordinates":[-96.05438100000001,29.60092],"type":"Point"}
}