{
  "type": "Feature",
  "properties": {
    "iso:country":"US",
    "sg:address":"3815 21st St",
    "sg:city":"Lubbock",
    "sg:classifiers":[
        {
            "category":"Travel",
            "subcategory":"Hotels & Motels",
            "type":"Entertainment"
        }
    ],
    "sg:phone":"+1 806 791 0433",
    "sg:postcode":"79410",
    "sg:province":"TX",
    "wof:name":"Guesthouse Inn",
    "wof:placetype":"venue"
},
  "geometry": {"coordinates":[-101.897414,33.575858],"type":"Point"}
}