{
  "type": "Feature",
  "properties": {
    "iso:country":"US",
    "sg:address":"216 S Leggett Dr",
    "sg:city":"Abilene",
    "sg:classifiers":[
        {
            "category":"Personal",
            "subcategory":"Beauty Salon",
            "type":"Services"
        }
    ],
    "sg:phone":"+1 325 676 2661",
    "sg:postcode":"79605",
    "sg:province":"TX",
    "sg:tags":[
        "shop"
    ],
    "wof:name":"Still Salon",
    "wof:placetype":"venue"
},
  "geometry": {"coordinates":[-99.770526,32.450122],"type":"Point"}
}