{
  "type": "Feature",
  "properties": {
    "iso:country":"US",
    "sg:address":"18485 Summer Hills Blvd",
    "sg:city":"Porter",
    "sg:classifiers":[
        {
            "category":"Building & Trades",
            "subcategory":"Construction",
            "type":"Services"
        }
    ],
    "sg:phone":"+1 281 354 7186",
    "sg:postcode":"77365",
    "sg:province":"TX",
    "sg:tags":[
        "contractor"
    ],
    "wof:name":"Complete Drywall",
    "wof:placetype":"venue"
},
  "geometry": {"coordinates":[-95.293796,30.09656],"type":"Point"}
}