{
  "type": "Feature",
  "properties": {
    "iso:country":"US",
    "sg:address":"205 W Avenue G",
    "sg:city":"Temple",
    "sg:classifiers":[
        {
            "category":"Travel",
            "subcategory":"Hotels & Motels",
            "type":"Entertainment"
        }
    ],
    "sg:phone":"+1 254 773 9043",
    "sg:postcode":"76504",
    "sg:province":"TX",
    "sg:tags":[
        "lodging"
    ],
    "sg:website":"http://www.economyinnflorence.com",
    "wof:name":"Economy Inn",
    "wof:placetype":"venue"
},
  "geometry": {"coordinates":[-97.345782,31.090249],"type":"Point"}
}