{
  "type": "Feature",
  "properties": {
    "iso:country":"US",
    "sg:address":"7190 Alameda Ave",
    "sg:city":"El Paso",
    "sg:classifiers":[
        {
            "category":"Home & Garden",
            "subcategory":"Mobile Homes",
            "type":"Retail Goods"
        }
    ],
    "sg:phone":"+1 915 779 5266",
    "sg:postcode":"79915",
    "sg:province":"TX",
    "wof:name":"E & S Mobile Homes",
    "wof:placetype":"venue"
},
  "geometry": {"coordinates":[-106.387457,31.749718],"type":"Point"}
}