{
  "type": "Feature",
  "properties": {
    "iso:country":"US",
    "sg:address":"2020 Hollystone Dr",
    "sg:city":"Tyler",
    "sg:classifiers":[
        {
            "category":"Insurance",
            "subcategory":"Hazard Insurance",
            "type":"Services"
        }
    ],
    "sg:phone":"+1 903 561 7668",
    "sg:postcode":"75703",
    "sg:province":"TX",
    "sg:tags":[
        "commercial",
        "business"
    ],
    "wof:name":"Denson Insurance Group",
    "wof:placetype":"venue"
},
  "geometry": {"coordinates":[-95.33107800000001,32.266862],"type":"Point"}
}