{
  "type": "Feature",
  "properties": {
    "iso:country":"US",
    "sg:address":"101 Western Ave",
    "sg:city":"Robstown",
    "sg:classifiers":[
        {
            "category":"Shopping",
            "subcategory":"Gifts & Souvenirs",
            "type":"Retail Goods"
        }
    ],
    "sg:phone":"+1 361 767 0676",
    "sg:postcode":"78380",
    "sg:province":"TX",
    "wof:name":"From Me To You",
    "wof:placetype":"venue"
},
  "geometry": {"coordinates":[-97.67752299999999,27.791641],"type":"Point"}
}