{
  "type": "Feature",
  "properties": {
    "iso:country":"US",
    "sg:address":"611 S 22nd St",
    "sg:city":"Temple",
    "sg:classifiers":[
        {
            "category":"Personal",
            "subcategory":"Barber",
            "type":"Services"
        }
    ],
    "sg:phone":"+1 254 773 7868",
    "sg:postcode":"76501",
    "sg:province":"TX",
    "wof:name":"Odessa's Barber & Beauty Salon",
    "wof:placetype":"venue"
},
  "geometry": {"coordinates":[-97.331541,31.086407],"type":"Point"}
}