{
  "type": "Feature",
  "properties": {
    "iso:country":"US",
    "sg:address":"1220 Fairmont Pkwy",
    "sg:city":"La Porte",
    "sg:classifiers":[
        {
            "category":"Cinema",
            "subcategory":"Movie Rental",
            "type":"Entertainment"
        }
    ],
    "sg:phone":"+1 281 842 9366",
    "sg:postcode":"77571",
    "sg:province":"TX",
    "sg:tags":[
        "leasing",
        "video",
        "disc",
        "tape"
    ],
    "sg:website":"www.blockbuster.com",
    "wof:name":"Blockbuster Video",
    "wof:placetype":"venue"
},
  "geometry": {"coordinates":[-95.031277,29.652235],"type":"Point"}
}