{
  "type": "Feature",
  "properties": {
    "iso:country":"US",
    "sg:address":"2218 Jensen Dr",
    "sg:city":"Houston",
    "sg:classifiers":[
        {
            "category":"Personal",
            "subcategory":"Beauty Salon",
            "type":"Services"
        }
    ],
    "sg:phone":"+1 832 423 5171",
    "sg:postcode":"77026",
    "sg:province":"TX",
    "sg:tags":[
        "shop"
    ],
    "wof:name":"Family Affair Dollar Plus",
    "wof:placetype":"venue"
},
  "geometry": {"coordinates":[-95.34181700000001,29.782179],"type":"Point"}
}