{
  "type": "Feature",
  "properties": {
    "iso:country":"US",
    "sg:address":"2842 Blystone Ln",
    "sg:city":"Dallas",
    "sg:classifiers":[
        {
            "category":"Professional",
            "type":"Services"
        },
        {
            "category":"Airport",
            "type":"Transportation"
        }
    ],
    "sg:phone":"+1 214 654 9927",
    "sg:postcode":"75220",
    "sg:province":"TX",
    "wof:name":"Franklin Products Inc",
    "wof:placetype":"venue"
},
  "geometry": {"coordinates":[-96.87862699999999,32.873769],"type":"Point"}
}