{
  "type": "Feature",
  "properties": {
    "iso:country":"US",
    "sg:address":"5201 Bonham St",
    "sg:city":"Corpus Christi",
    "sg:classifiers":[
        {
            "category":"Social Services",
            "subcategory":"Child Care",
            "type":"Services"
        }
    ],
    "sg:phone":"+1 361 857 5720",
    "sg:postcode":"78415",
    "sg:province":"TX",
    "sg:tags":[
        "day"
    ],
    "wof:name":"Ana Breseno S Childcare",
    "wof:placetype":"venue"
},
  "geometry": {"coordinates":[-97.416208,27.728246],"type":"Point"}
}