{
  "type": "Feature",
  "properties": {
    "iso:country":"US",
    "sg:address":"1346 N Lee Trevino Dr",
    "sg:city":"El Paso",
    "sg:classifiers":[
        {
            "category":"Insurance",
            "subcategory":"Insurance Agent",
            "type":"Services"
        }
    ],
    "sg:phone":"+1 915 593 1346",
    "sg:postcode":"79936",
    "sg:province":"TX",
    "wof:name":"Andrus Virginia",
    "wof:placetype":"venue"
},
  "geometry": {"coordinates":[-106.32038799999999,31.74458],"type":"Point"}
}