{
  "type": "Feature",
  "properties": {
    "iso:country":"US",
    "sg:address":"16746 Sky Blue Ln",
    "sg:city":"Houston",
    "sg:classifiers":[
        {
            "category":"Retail",
            "subcategory":"Auto Repair",
            "type":"Services"
        }
    ],
    "sg:phone":"+1 281 859 3551",
    "sg:postcode":"77095",
    "sg:province":"TX",
    "sg:tags":[
        "general"
    ],
    "wof:name":"Morillon Mobile Auto Repair",
    "wof:placetype":"venue"
},
  "geometry": {"coordinates":[-95.66287800000001,29.880967],"type":"Point"}
}