{
  "type": "Feature",
  "properties": {
    "iso:country":"US",
    "sg:address":"1809 County Loop Rd",
    "sg:city":"Fort Worth",
    "sg:classifiers":[
        {
            "category":"Banks & Credit Unions",
            "subcategory":"Financial Services",
            "type":"Services"
        }
    ],
    "sg:phone":"+1 817 236 2030",
    "sg:postcode":"76179",
    "sg:province":"TX",
    "sg:tags":[
        "company",
        "holding"
    ],
    "wof:name":"Jmh 2 Holdings LLC",
    "wof:placetype":"venue"
},
  "geometry": {"coordinates":[-97.403097,32.89579],"type":"Point"}
}