{
  "type": "Feature",
  "properties": {
    "iso:country":"US",
    "sg:address":"325 Paul St",
    "sg:city":"San Antonio",
    "sg:classifiers":[
        {
            "category":"Government",
            "subcategory":"Police Station",
            "type":"Public Place"
        }
    ],
    "sg:phone":"+1 210 533 8004",
    "sg:postcode":"78203",
    "sg:province":"TX",
    "sg:tags":[
        "sheriff"
    ],
    "wof:name":"Sammy D Thomas",
    "wof:placetype":"venue"
},
  "geometry": {"coordinates":[-98.465672,29.415347],"type":"Point"}
}