{
  "type": "Feature",
  "properties": {
    "iso:country":"US",
    "sg:address":"11246 Timber Tech Ave",
    "sg:city":"Tomball",
    "sg:classifiers":[
        {
            "category":"Manufacturing",
            "subcategory":"Printing",
            "type":"Manufacturing & Wholesale Goods"
        }
    ],
    "sg:phone":"+1 281 351 9011",
    "sg:postcode":"77375",
    "sg:province":"TX",
    "sg:tags":[
        "newspaper"
    ],
    "wof:name":"Favro Terry L",
    "wof:placetype":"venue"
},
  "geometry": {"coordinates":[-95.601187,30.033022],"type":"Point"}
}