{
  "type": "Feature",
  "properties": {
    "iso:country":"US",
    "sg:address":"1321 Regal Row",
    "sg:city":"Dallas",
    "sg:classifiers":[
        {
            "category":"Shopping",
            "subcategory":"Clothing, Apparel, & Fashions",
            "type":"Retail Goods"
        }
    ],
    "sg:phone":"+1 214 634 4181",
    "sg:postcode":"75247",
    "sg:province":"TX",
    "wof:name":"Fast Fashion",
    "wof:placetype":"venue"
},
  "geometry": {"coordinates":[-96.88062499999999,32.832166],"type":"Point"}
}