{
  "type": "Feature",
  "properties": {
    "iso:country":"US",
    "sg:address":"293 Sunset Ridge Dr",
    "sg:city":"League City",
    "sg:classifiers":[
        {
            "category":"Retail",
            "subcategory":"Portrait Studio",
            "type":"Services"
        }
    ],
    "sg:phone":"+1 254 793 4236",
    "sg:postcode":"77573",
    "sg:province":"TX",
    "sg:tags":[
        "photographer"
    ],
    "wof:name":"Liz Parker Photography",
    "wof:placetype":"venue"
},
  "geometry": {"coordinates":[-95.041348,29.537789],"type":"Point"}
}