{
  "type": "Feature",
  "properties": {
    "iso:country":"US",
    "sg:address":"3415 Petite Cir",
    "sg:city":"Galveston",
    "sg:classifiers":[
        {
            "category":"Wholesale",
            "subcategory":"Machinery & Supplies",
            "type":"Manufacturing & Wholesale Goods"
        }
    ],
    "sg:phone":"+1 409 737 5204",
    "sg:postcode":"77554",
    "sg:province":"TX",
    "sg:tags":[
        "pump"
    ],
    "wof:name":"Afton Pumps Inc",
    "wof:placetype":"venue"
},
  "geometry": {"coordinates":[-94.949922,29.215346],"type":"Point"}
}