{
  "type": "Feature",
  "properties": {
    "iso:country":"US",
    "sg:address":"434 Diana Dr",
    "sg:city":"Converse",
    "sg:classifiers":[
        {
            "category":"Shopping",
            "subcategory":"Clothing, Apparel, & Fashions",
            "type":"Retail Goods"
        }
    ],
    "sg:phone":"+1 210 319 9955",
    "sg:postcode":"78109",
    "sg:province":"TX",
    "sg:tags":[
        "uniforms-accessories",
        "uniform"
    ],
    "wof:name":"Uniform Fitness",
    "wof:placetype":"venue"
},
  "geometry": {"coordinates":[-98.302688,29.499231],"type":"Point"}
}