{
  "type": "Feature",
  "properties": {
    "iso:country":"US",
    "sg:address":"4777 S Main St",
    "sg:city":"Stafford",
    "sg:classifiers":[
        {
            "category":"Building & Trades",
            "subcategory":"Plumbing",
            "type":"Services"
        }
    ],
    "sg:phone":"+1 281 980 9300",
    "sg:postcode":"77477",
    "sg:province":"TX",
    "sg:tags":[
        "plumbing",
        "contractor"
    ],
    "wof:name":"Doug Turner Plumbing Co Inc",
    "wof:placetype":"venue"
},
  "geometry": {"coordinates":[-95.586055,29.628202],"type":"Point"}
}