{
  "type": "Feature",
  "properties": {
    "iso:country":"US",
    "sg:address":"7019 Wyoma Trl",
    "sg:city":"Spring",
    "sg:classifiers":[
        {
            "category":"Shopping",
            "subcategory":"Discount & Variety Stores",
            "type":"Retail Goods"
        }
    ],
    "sg:phone":"+1 281 370 7818",
    "sg:postcode":"77379",
    "sg:province":"TX",
    "sg:tags":[
        "merchandise",
        "general"
    ],
    "wof:name":"Canyon Lake Soap Company",
    "wof:placetype":"venue"
},
  "geometry": {"coordinates":[-95.528319,30.034231],"type":"Point"}
}