{
  "type": "Feature",
  "properties": {
    "iso:country":"US",
    "sg:address":"13549 Raytel St",
    "sg:city":"San Antonio",
    "sg:classifiers":[
        {
            "category":"Building & Trades",
            "subcategory":"Construction",
            "type":"Services"
        }
    ],
    "sg:phone":"+1 210 823 6029",
    "sg:postcode":"78253",
    "sg:province":"TX",
    "sg:tags":[
        "resurfacing",
        "laying",
        "refinishing",
        "floor"
    ],
    "wof:name":"Sandoval Ramiro Tile Works",
    "wof:placetype":"venue"
},
  "geometry": {"coordinates":[-98.762047,29.458351],"type":"Point"}
}