{
  "type": "Feature",
  "properties": {
    "iso:country":"US",
    "sg:address":"295 Ward Rd",
    "sg:city":"Midlothian",
    "sg:classifiers":[
        {
            "category":"Freight",
            "type":"Transportation"
        }
    ],
    "sg:phone":"+1 972 775 1195",
    "sg:postcode":"76065",
    "sg:province":"TX",
    "sg:tags":[
        "hauling",
        "trucking"
    ],
    "sg:website":"www.team-america.com",
    "wof:name":"America Steel Transport",
    "wof:placetype":"venue"
},
  "geometry": {"coordinates":[-97.028524,32.463307],"type":"Point"}
}