{
  "type": "Feature",
  "properties": {
    "iso:country":"US",
    "sg:address":"3393 Thousand Oaks Dr",
    "sg:city":"San Antonio",
    "sg:classifiers":[
        {
            "category":"Real Estate",
            "subcategory":"Real Estate Agent",
            "type":"Services"
        }
    ],
    "sg:phone":"+1 210 494 1300",
    "sg:postcode":"78247",
    "sg:province":"TX",
    "sg:website":"www.besthomesgmac.com",
    "wof:name":"Best Homes GMAC Real Estate",
    "wof:placetype":"venue"
},
  "geometry": {"coordinates":[-98.432536,29.569727],"type":"Point"}
}