{
  "type": "Feature",
  "properties": {
    "iso:country":"US",
    "sg:address":"701 E Grand Ave",
    "sg:city":"Marshall",
    "sg:classifiers":[
        {
            "category":"Building & Trades",
            "subcategory":"Construction",
            "type":"Services"
        }
    ],
    "sg:phone":"+1 903 938 6131",
    "sg:postcode":"75672",
    "sg:province":"TX",
    "sg:tags":[
        "roofing",
        "contractor"
    ],
    "wof:name":"Marshall Roofing",
    "wof:placetype":"venue"
},
  "geometry": {"coordinates":[-94.36103,32.548462],"type":"Point"}
}