{
  "type": "Feature",
  "properties": {
    "iso:country":"US",
    "sg:address":"602 S Main St",
    "sg:city":"Weatherford",
    "sg:classifiers":[
        {
            "category":"Insurance",
            "subcategory":"Insurance Agent",
            "type":"Services"
        }
    ],
    "sg:phone":"+1 817 594 0230",
    "sg:postcode":"76086",
    "sg:province":"TX",
    "wof:name":"Mader Bagley Insurance",
    "wof:placetype":"venue"
},
  "geometry": {"coordinates":[-97.797504,32.75293],"type":"Point"}
}