{
  "type": "Feature",
  "properties": {
    "iso:country":"US",
    "sg:address":"4138 Allison Rd",
    "sg:city":"Houston",
    "sg:classifiers":[
        {
            "category":"Building & Trades",
            "subcategory":"Landscaping Services",
            "type":"Services"
        }
    ],
    "sg:phone":"+1 832 519 7163",
    "sg:postcode":"77048",
    "sg:province":"TX",
    "sg:tags":[
        "tree",
        "stump",
        "grinding",
        "removal"
    ],
    "wof:name":"James Cornish",
    "wof:placetype":"venue"
},
  "geometry": {"coordinates":[-95.354176,29.616624],"type":"Point"}
}