{
  "type": "Feature",
  "properties": {
    "iso:country":"US",
    "sg:address":"3211 Brown Trl",
    "sg:city":"Bedford",
    "sg:classifiers":[
        {
            "category":"Education",
            "subcategory":"Dance Studio",
            "type":"Public Place"
        }
    ],
    "sg:phone":"+1 817 485 8665",
    "sg:postcode":"76021",
    "sg:province":"TX",
    "wof:name":"Texas Assoc of Single Squ",
    "wof:placetype":"venue"
},
  "geometry": {"coordinates":[-97.159865,32.8581],"type":"Point"}
}