{
  "type": "Feature",
  "properties": {
    "iso:country":"US",
    "sg:address":"6311 N O Connor Blvd",
    "sg:city":"Irving",
    "sg:classifiers":[
        {
            "category":"Professional",
            "subcategory":"Art Services",
            "type":"Services"
        }
    ],
    "sg:phone":"+1 972 432 0900",
    "sg:postcode":"75039",
    "sg:province":"TX",
    "sg:tags":[
        "commercial",
        "design"
    ],
    "wof:name":"Wingate R Quentan Graphic",
    "wof:placetype":"venue"
},
  "geometry": {"coordinates":[-96.937028,32.893078],"type":"Point"}
}