{
  "type": "Feature",
  "properties": {
    "iso:country":"US",
    "sg:address":"105 W 7th Ave",
    "sg:city":"Corsicana",
    "sg:classifiers":[
        {
            "category":"Utilities",
            "subcategory":"Mobile Phone",
            "type":"Services"
        }
    ],
    "sg:phone":"+1 903 872 5540",
    "sg:postcode":"75110",
    "sg:province":"TX",
    "sg:tags":[
        "telephone",
        "cellular"
    ],
    "wof:name":"Cellular One",
    "wof:placetype":"venue"
},
  "geometry": {"coordinates":[-96.462811,32.091801],"type":"Point"}
}