{
  "type": "Feature",
  "properties": {
    "iso:country":"US",
    "sg:address":"1400 E 5th St",
    "sg:city":"Austin",
    "sg:classifiers":[
        {
            "category":"Building & Trades",
            "subcategory":"Locksmith",
            "type":"Services"
        }
    ],
    "sg:phone":"+1 512 623 1363",
    "sg:postcode":"78702",
    "sg:province":"TX",
    "sg:tags":[
        "lock"
    ],
    "wof:name":"5th St. Locksmith",
    "wof:placetype":"venue"
},
  "geometry": {"coordinates":[-97.728897,30.26284],"type":"Point"}
}