{
  "type": "Feature",
  "properties": {
    "iso:country":"US",
    "sg:address":"12300 North Fwy",
    "sg:city":"Houston",
    "sg:classifiers":[
        {
            "category":"Shopping",
            "subcategory":"Shoes",
            "type":"Retail Goods"
        }
    ],
    "sg:phone":"+1 281 874 9290",
    "sg:postcode":"77060",
    "sg:province":"TX",
    "sg:website":"www.footaction.com",
    "wof:name":"Footaction",
    "wof:placetype":"venue"
},
  "geometry": {"coordinates":[-95.417018,29.949033],"type":"Point"}
}