{
  "type": "Feature",
  "properties": {
    "iso:country":"US",
    "sg:address":"1620 E Arapaho Rd",
    "sg:city":"Richardson",
    "sg:classifiers":[
        {
            "category":"Organizations",
            "subcategory":"Religious Organization",
            "type":"Services"
        }
    ],
    "sg:phone":"+1 972 235 1133",
    "sg:postcode":"75081",
    "sg:province":"TX",
    "sg:tags":[
        "church"
    ],
    "wof:name":"First Assembly Of God",
    "wof:placetype":"venue"
},
  "geometry": {"coordinates":[-96.695548,32.960476],"type":"Point"}
}