{
  "type": "Feature",
  "properties": {
    "iso:country":"US",
    "sg:address":"2293 State Hwy 21",
    "sg:city":"Dale",
    "sg:classifiers":[
        {
            "category":"Shopping",
            "subcategory":"Bicycles & Sporting Goods",
            "type":"Retail Goods"
        }
    ],
    "sg:phone":"+1 512 303 2841",
    "sg:postcode":"78616",
    "sg:province":"TX",
    "sg:tags":[
        "firearm"
    ],
    "wof:name":"Allan Yoast Firearms",
    "wof:placetype":"venue"
},
  "geometry": {"coordinates":[-97.60157,30.060791],"type":"Point"}
}