{
  "type": "Feature",
  "properties": {
    "iso:country":"US",
    "sg:address":"3535 Worth St",
    "sg:city":"Dallas",
    "sg:classifiers":[
        {
            "category":"Shopping",
            "type":"Retail Goods"
        }
    ],
    "sg:phone":"+1 214 820 8282",
    "sg:postcode":"75246",
    "sg:province":"TX",
    "sg:tags":[
        "merchandise"
    ],
    "wof:name":"Baylor-Charles A Sammons Ctr",
    "wof:placetype":"venue"
},
  "geometry": {"coordinates":[-96.779667,32.788041],"type":"Point"}
}