{
  "type": "Feature",
  "properties": {
    "iso:country":"US",
    "sg:address":"2701 Turner Warnell Rd",
    "sg:city":"Arlington",
    "sg:classifiers":[
        {
            "category":"Real Estate",
            "subcategory":"Architect",
            "type":"Services"
        }
    ],
    "sg:phone":"+1 817 483 5080",
    "sg:postcode":"76001",
    "sg:province":"TX",
    "sg:tags":[
        "home",
        "planning",
        "design"
    ],
    "wof:name":"Jeff Payne Home Design",
    "wof:placetype":"venue"
},
  "geometry": {"coordinates":[-97.15841,32.61407],"type":"Point"}
}