{
  "type": "Feature",
  "properties": {
    "iso:country":"US",
    "sg:address":"1909 Copper Creek Dr",
    "sg:city":"Plano",
    "sg:classifiers":[
        {
            "category":"Retail",
            "subcategory":"Repair Shop",
            "type":"Services"
        }
    ],
    "sg:phone":"+1 972 985 1588",
    "sg:postcode":"75075",
    "sg:province":"TX",
    "wof:name":"New Era Upholstery",
    "wof:placetype":"venue"
},
  "geometry": {"coordinates":[-96.73083,33.04068],"type":"Point"}
}