{
  "type": "Feature",
  "properties": {
    "iso:country":"US",
    "sg:address":"1021 University Dr E",
    "sg:city":"College Station",
    "sg:classifiers":[
        {
            "category":"Farming",
            "subcategory":"Livestock Farm",
            "type":"Manufacturing & Wholesale Goods"
        }
    ],
    "sg:phone":"+1 979 846 4726",
    "sg:postcode":"77840",
    "sg:province":"TX",
    "sg:tags":[
        "animal",
        "general"
    ],
    "wof:name":"Lochow Ranch Inc",
    "wof:placetype":"venue"
},
  "geometry": {"coordinates":[-96.32145300000001,30.636251],"type":"Point"}
}