{
  "type": "Feature",
  "properties": {
    "iso:country":"US",
    "sg:address":"4949 Everhart Rd",
    "sg:city":"Corpus Christi",
    "sg:classifiers":[
        {
            "category":"Personal",
            "type":"Services"
        }
    ],
    "sg:phone":"+1 361 857 8885",
    "sg:postcode":"78411",
    "sg:province":"TX",
    "sg:tags":[
        "therapist",
        "massage"
    ],
    "wof:name":"Vital Touch Healthy Massage",
    "wof:placetype":"venue"
},
  "geometry": {"coordinates":[-97.382853,27.717182],"type":"Point"}
}