{
  "type": "Feature",
  "properties": {
    "iso:country":"US",
    "sg:address":"6300 Ridglea Pl",
    "sg:city":"Fort Worth",
    "sg:classifiers":[
        {
            "category":"Professional",
            "type":"Services"
        }
    ],
    "sg:phone":"+1 817 738 8648",
    "sg:postcode":"76116",
    "sg:province":"TX",
    "wof:name":"Petroleum Research",
    "wof:placetype":"venue"
},
  "geometry": {"coordinates":[-97.41809499999999,32.724086],"type":"Point"}
}