{
  "type": "Feature",
  "properties": {
    "iso:country":"US",
    "sg:address":"19811 Summerset Way",
    "sg:city":"Houston",
    "sg:classifiers":[
        {
            "category":"Professional",
            "subcategory":"Management & Consulting",
            "type":"Services"
        }
    ],
    "sg:phone":"+1 281 492 0727",
    "sg:postcode":"77094",
    "sg:province":"TX",
    "sg:tags":[
        "engineering"
    ],
    "wof:name":"Diehl Enterprises LLC",
    "wof:placetype":"venue"
},
  "geometry": {"coordinates":[-95.717043,29.767698],"type":"Point"}
}