{
  "type": "Feature",
  "properties": {
    "iso:country":"US",
    "sg:address":"3220 Clearview Dr",
    "sg:city":"Austin",
    "sg:classifiers":[
        {
            "category":"Professional",
            "subcategory":"Business Services",
            "type":"Services"
        }
    ],
    "sg:phone":"+1 512 477 8645",
    "sg:postcode":"78703",
    "sg:province":"TX",
    "wof:name":"Jarrett Juno Ranch Partnership",
    "wof:placetype":"venue"
},
  "geometry": {"coordinates":[-97.775288,30.296395],"type":"Point"}
}