{
  "type": "Feature",
  "properties": {
    "iso:country":"US",
    "sg:address":"13521 Nacogdoches Rd",
    "sg:city":"San Antonio",
    "sg:classifiers":[
        {
            "category":"Shopping",
            "subcategory":"Computers & Home Electronics",
            "type":"Retail Goods"
        }
    ],
    "sg:phone":"+1 210 599 3002",
    "sg:postcode":"78217",
    "sg:province":"TX",
    "wof:name":"Computer 547",
    "wof:placetype":"venue"
},
  "geometry": {"coordinates":[-98.38972099999999,29.564421],"type":"Point"}
}