{
  "type": "Feature",
  "properties": {
    "iso:country":"US",
    "sg:address":"1023 Ave B",
    "sg:city":"Nederland",
    "sg:classifiers":[
        {
            "category":"Professional",
            "subcategory":"Business Services",
            "type":"Services"
        }
    ],
    "sg:phone":"+1 409 729 5438",
    "sg:postcode":"77627",
    "sg:province":"TX",
    "wof:name":"Truth Hurts Recording",
    "wof:placetype":"venue"
},
  "geometry": {"coordinates":[-93.98672999999999,29.974452],"type":"Point"}
}