{
  "type": "Feature",
  "properties": {
    "iso:country":"US",
    "sg:address":"1617 N 25th St",
    "sg:city":"Corsicana",
    "sg:classifiers":[
        {
            "category":"Professional",
            "subcategory":"Accounting & Tax Preparation",
            "type":"Services"
        }
    ],
    "sg:phone":"+1 903 872 7813",
    "sg:postcode":"75110",
    "sg:province":"TX",
    "wof:name":"Funderburk Business Services",
    "wof:placetype":"venue"
},
  "geometry": {"coordinates":[-96.489565,32.099326],"type":"Point"}
}