{
  "type": "Feature",
  "properties": {
    "iso:country":"US",
    "sg:address":"1800 N New Braunfels Ave",
    "sg:city":"San Antonio",
    "sg:classifiers":[
        {
            "category":"Food & Beverages",
            "subcategory":"Groceries & Convenience Stores",
            "type":"Retail Goods"
        }
    ],
    "sg:phone":"+1 210 223 5511",
    "sg:postcode":"78208",
    "sg:province":"TX",
    "sg:tags":[
        "grocer"
    ],
    "wof:name":"Lupe's Market",
    "wof:placetype":"venue"
},
  "geometry": {"coordinates":[-98.460948,29.440792],"type":"Point"}
}