{
  "type": "Feature",
  "properties": {
    "iso:country":"US",
    "sg:address":"1681 Spur St",
    "sg:city":"New Braunfels",
    "sg:classifiers":[
        {
            "category":"Restaurant",
            "type":"Food & Drink"
        }
    ],
    "sg:phone":"+1 830 625 0217",
    "sg:postcode":"78130",
    "sg:province":"TX",
    "sg:tags":[
        "eating"
    ],
    "wof:name":"New Braunfels Tortilleria",
    "wof:placetype":"venue"
},
  "geometry": {"coordinates":[-98.138131,29.688933],"type":"Point"}
}