{
  "type": "Feature",
  "properties": {
    "iso:country":"US",
    "sg:address":"12525 Jones Rd",
    "sg:city":"Houston",
    "sg:classifiers":[
        {
            "category":"Organizations",
            "subcategory":"Religious Organization",
            "type":"Services"
        }
    ],
    "sg:phone":"+1 281 856 8172",
    "sg:postcode":"77070",
    "sg:province":"TX",
    "wof:name":"Phillippine American Good New",
    "wof:placetype":"venue"
},
  "geometry": {"coordinates":[-95.585027,29.955643],"type":"Point"}
}