{
  "type": "Feature",
  "properties": {
    "iso:country":"US",
    "sg:address":"2505 N Forty Cir",
    "sg:city":"Arlington",
    "sg:classifiers":[
        {
            "category":"Professional",
            "subcategory":"Management & Consulting",
            "type":"Services"
        }
    ],
    "sg:phone":"+1 817 385 0080",
    "sg:postcode":"76006",
    "sg:province":"TX",
    "wof:name":"Magnolia Fields",
    "wof:placetype":"venue"
},
  "geometry": {"coordinates":[-97.06434299999999,32.775661],"type":"Point"}
}