{
  "type": "Feature",
  "properties": {
    "iso:country":"US",
    "sg:address":"710 E Main Ave",
    "sg:city":"Robstown",
    "sg:classifiers":[
        {
            "category":"Farming",
            "subcategory":"Farm & Veterinary Services",
            "type":"Manufacturing & Wholesale Goods"
        }
    ],
    "sg:phone":"+1 361 767 5223",
    "sg:postcode":"78380",
    "sg:province":"TX",
    "sg:tags":[
        "management"
    ],
    "wof:name":"Texas Coop Extnsons Neces Cnty",
    "wof:placetype":"venue"
},
  "geometry": {"coordinates":[-97.658869,27.788615],"type":"Point"}
}