{
  "type": "Feature",
  "properties": {
    "iso:country":"US",
    "sg:address":"106 Tribble Rd",
    "sg:city":"Sherman",
    "sg:classifiers":[
        {
            "category":"Autos & Motor Vehicles",
            "subcategory":"Automobile Sales",
            "type":"Retail Goods"
        }
    ],
    "sg:phone":"+1 903 813 0883",
    "sg:postcode":"75090",
    "sg:province":"TX",
    "sg:tags":[
        "used"
    ],
    "wof:name":"Silverado Auto Sales",
    "wof:placetype":"venue"
},
  "geometry": {"coordinates":[-96.519555,33.572161],"type":"Point"}
}