{
  "type": "Feature",
  "properties": {
    "iso:country":"US",
    "sg:address":"104 Swisher Rd",
    "sg:city":"Lake Dallas",
    "sg:classifiers":[
        {
            "category":"Education",
            "subcategory":"School",
            "type":"Public Place"
        }
    ],
    "sg:phone":"+1 940 497 2222",
    "sg:postcode":"75065",
    "sg:province":"TX",
    "sg:website":"www.ldisd.net",
    "wof:name":"Lake Dallas Primary School",
    "wof:placetype":"venue"
},
  "geometry": {"coordinates":[-97.030356,33.12983],"type":"Point"}
}