{
  "type": "Feature",
  "properties": {
    "iso:country":"US",
    "sg:address":"5907 W Marshall Ave",
    "sg:city":"Longview",
    "sg:phone":"+1 903 295 3120",
    "sg:postcode":"75604",
    "sg:province":"TX",
    "sg:tags":[
        "oil",
        "gasoline"
    ],
    "wof:name":"Gregg County Oil Co",
    "wof:placetype":"venue"
},
  "geometry": {"coordinates":[-94.81382499999999,32.509558],"type":"Point"}
}