{
  "type": "Feature",
  "properties": {
    "iso:country":"US",
    "sg:address":"14018 Taco Ct",
    "sg:city":"Sugar Land",
    "sg:classifiers":[
        {
            "category":"Professional",
            "subcategory":"Art Services",
            "type":"Services"
        }
    ],
    "sg:phone":"+1 281 494 8016",
    "sg:postcode":"77478",
    "sg:province":"TX",
    "sg:tags":[
        "graphic",
        "designer"
    ],
    "wof:name":"Land Graphic",
    "wof:placetype":"venue"
},
  "geometry": {"coordinates":[-95.633212,29.64186],"type":"Point"}
}