{
  "type": "Feature",
  "properties": {
    "iso:country":"US",
    "sg:address":"5208 Village Creek Dr Ste 101",
    "sg:city":"Plano",
    "sg:classifiers":[
        {
            "category":"Health Services",
            "subcategory":"Health Practitioner",
            "type":"Services"
        }
    ],
    "sg:phone":"+1 972 732 7804",
    "sg:postcode":"75093",
    "sg:province":"TX",
    "sg:tags":[
        "acupuncture"
    ],
    "sg:website":"www.greatwallacupuncture.com",
    "wof:name":"Great Wall Medical Center",
    "wof:placetype":"venue"
},
  "geometry": {"coordinates":[-96.80485,33.013916],"type":"Point"}
}