{
  "type": "Feature",
  "properties": {
    "iso:country":"US",
    "sg:address":"3817 Parkdale St",
    "sg:city":"San Antonio",
    "sg:classifiers":[
        {
            "category":"Manufacturing",
            "subcategory":"Metals",
            "type":"Manufacturing & Wholesale Goods"
        }
    ],
    "sg:phone":"+1 210 624 9800",
    "sg:postcode":"78229",
    "sg:province":"TX",
    "sg:tags":[
        "metalwork",
        "architectural",
        "mfg"
    ],
    "wof:name":"M W Structural",
    "wof:placetype":"venue"
},
  "geometry": {"coordinates":[-98.561182,29.525996],"type":"Point"}
}