{
  "type": "Feature",
  "properties": {
    "iso:country":"US",
    "sg:address":"415 Harbor St",
    "sg:city":"Houston",
    "sg:classifiers":[
        {
            "category":"Building & Trades",
            "subcategory":"Construction",
            "type":"Services"
        }
    ],
    "sg:phone":"+1 713 671 0951",
    "sg:postcode":"77020",
    "sg:province":"TX",
    "sg:tags":[
        "house"
    ],
    "wof:name":"Tgmc Const Service",
    "wof:placetype":"venue"
},
  "geometry": {"coordinates":[-95.29485099999999,29.782175],"type":"Point"}
}