{
  "type": "Feature",
  "properties": {
    "iso:country":"US",
    "sg:address":"2820 Park Dr",
    "sg:city":"Arlington",
    "sg:classifiers":[
        {
            "category":"Place Of Worship",
            "type":"Public Place"
        }
    ],
    "sg:phone":"+1 817 277 4254",
    "sg:postcode":"76016",
    "sg:province":"TX",
    "sg:tags":[
        "church"
    ],
    "wof:name":"Mehlmann Joseph Etux Chri",
    "wof:placetype":"venue"
},
  "geometry": {"coordinates":[-97.158664,32.6992],"type":"Point"}
}