{
  "type": "Feature",
  "properties": {
    "iso:country":"US",
    "sg:address":"3015 6th Ave",
    "sg:city":"Amarillo",
    "sg:classifiers":[
        {
            "category":"Organizations",
            "subcategory":"Community Association",
            "type":"Services"
        }
    ],
    "sg:phone":"+1 806 374 6100",
    "sg:postcode":"79106",
    "sg:province":"TX",
    "sg:tags":[
        "fraternal"
    ],
    "wof:name":"Masonic Lodge",
    "wof:placetype":"venue"
},
  "geometry": {"coordinates":[-101.870879,35.211227],"type":"Point"}
}