{
  "type": "Feature",
  "properties": {
    "iso:country":"US",
    "sg:address":"4410 E Saunders St",
    "sg:city":"Laredo",
    "sg:classifiers":[
        {
            "category":"Retail",
            "subcategory":"Auto Repair",
            "type":"Services"
        }
    ],
    "sg:phone":"+1 956 722 9291",
    "sg:postcode":"78041",
    "sg:province":"TX",
    "sg:tags":[
        "road"
    ],
    "wof:name":"Martinez Wrecker Svc",
    "wof:placetype":"venue"
},
  "geometry": {"coordinates":[-99.451741,27.528645],"type":"Point"}
}