{
  "type": "Feature",
  "properties": {
    "iso:country":"US",
    "sg:address":"5114 Montclair Dr",
    "sg:city":"Colleyville",
    "sg:classifiers":[
        {
            "category":"Professional",
            "type":"Services"
        }
    ],
    "sg:phone":"+1 817 283 3634",
    "sg:postcode":"76034",
    "sg:province":"TX",
    "sg:tags":[
        "writer"
    ],
    "wof:name":"Goebel Music Pub",
    "wof:placetype":"venue"
},
  "geometry": {"coordinates":[-97.134883,32.884136],"type":"Point"}
}