{
  "type": "Feature",
  "properties": {
    "iso:country":"US",
    "sg:address":"2500 N Mesa St",
    "sg:city":"El Paso",
    "sg:classifiers":[
        {
            "category":"Shopping",
            "type":"Retail Goods"
        }
    ],
    "sg:phone":"+1 915 544 1927",
    "sg:postcode":"79902",
    "sg:province":"TX",
    "sg:tags":[
        "telephone",
        "cellular"
    ],
    "wof:name":"Global Tech Wireless",
    "wof:placetype":"venue"
},
  "geometry": {"coordinates":[-106.502487,31.776225],"type":"Point"}
}