{
  "type": "Feature",
  "properties": {
    "iso:country":"US",
    "sg:address":"812 Bryant St",
    "sg:city":"Bryan",
    "sg:classifiers":[
        {
            "category":"Wholesale",
            "subcategory":"Machinery & Supplies",
            "type":"Manufacturing & Wholesale Goods"
        }
    ],
    "sg:phone":"+1 979 779 7154",
    "sg:postcode":"77803",
    "sg:province":"TX",
    "sg:tags":[
        "equipment",
        "welding"
    ],
    "wof:name":"Botco",
    "wof:placetype":"venue"
},
  "geometry": {"coordinates":[-96.378516,30.666886],"type":"Point"}
}