{
  "type": "Feature",
  "properties": {
    "iso:country":"US",
    "sg:address":"2603 Upland Ave",
    "sg:city":"Lubbock",
    "sg:classifiers":[
        {
            "category":"Professional",
            "subcategory":"Business Services",
            "type":"Services"
        }
    ],
    "sg:phone":"+1 806 792 9797",
    "sg:postcode":"79407",
    "sg:province":"TX",
    "wof:name":"Greenkeepers",
    "wof:placetype":"venue"
},
  "geometry": {"coordinates":[-101.974358,33.570512],"type":"Point"}
}