{
  "type": "Feature",
  "properties": {
    "iso:country":"US",
    "sg:address":"290 Todd St",
    "sg:city":"Beaumont",
    "sg:classifiers":[
        {
            "category":"Professional",
            "subcategory":"Business Services",
            "type":"Services"
        }
    ],
    "sg:phone":"+1 409 866 6574",
    "sg:postcode":"77707",
    "sg:province":"TX",
    "wof:name":"Eagle Business Services",
    "wof:placetype":"venue"
},
  "geometry": {"coordinates":[-94.20911,30.068058],"type":"Point"}
}