{
  "type": "Feature",
  "properties": {
    "iso:country":"US",
    "sg:address":"208 Settlers Valley Dr",
    "sg:city":"Pflugerville",
    "sg:classifiers":[
        {
            "category":"Shopping",
            "subcategory":"Gifts & Souvenirs",
            "type":"Retail Goods"
        }
    ],
    "sg:phone":"+1 512 989 0654",
    "sg:postcode":"78660",
    "sg:province":"TX",
    "wof:name":"This N That",
    "wof:placetype":"venue"
},
  "geometry": {"coordinates":[-97.627078,30.433541],"type":"Point"}
}