{
  "type": "Feature",
  "properties": {
    "iso:country":"US",
    "sg:address":"4212 N Frankford Ave",
    "sg:city":"Lubbock",
    "sg:classifiers":[
        {
            "category":"Shopping",
            "subcategory":"Used Merchandise",
            "type":"Retail Goods"
        }
    ],
    "sg:phone":"+1 806 741 1986",
    "sg:postcode":"79416",
    "sg:province":"TX",
    "sg:tags":[
        "shop",
        "consignment"
    ],
    "wof:name":"Consignment Sales",
    "wof:placetype":"venue"
},
  "geometry": {"coordinates":[-101.93979,33.638346],"type":"Point"}
}