{
  "type": "Feature",
  "properties": {
    "iso:country":"US",
    "sg:address":"15906 Moon Rock Dr",
    "sg:city":"Houston",
    "sg:classifiers":[
        {
            "category":"Professional",
            "subcategory":"Management & Consulting",
            "type":"Services"
        }
    ],
    "sg:phone":"+1 281 280 8208",
    "sg:postcode":"77062",
    "sg:province":"TX",
    "sg:tags":[
        "business"
    ],
    "wof:name":"J R Main Consulting",
    "wof:placetype":"venue"
},
  "geometry": {"coordinates":[-95.112771,29.577624],"type":"Point"}
}