{
  "type": "Feature",
  "properties": {
    "iso:country":"US",
    "sg:address":"5538 Beth View Dr",
    "sg:city":"El Paso",
    "sg:classifiers":[
        {
            "category":"Professional",
            "subcategory":"Business Services",
            "type":"Services"
        }
    ],
    "sg:phone":"+1 915 585 0125",
    "sg:postcode":"79932",
    "sg:province":"TX",
    "wof:name":"Leonel G Rodarte",
    "wof:placetype":"venue"
},
  "geometry": {"coordinates":[-106.58335099999999,31.860598],"type":"Point"}
}