{
  "type": "Feature",
  "properties": {
    "iso:country":"US",
    "sg:address":"1226 Beech Creek Rd",
    "sg:city":"Livingston",
    "sg:classifiers":[
        {
            "category":"Retail",
            "subcategory":"Repair Shop",
            "type":"Services"
        }
    ],
    "sg:phone":"+1 936 327 4080",
    "sg:postcode":"77351",
    "sg:province":"TX",
    "wof:name":"City T V & V C R Repair",
    "wof:placetype":"venue"
},
  "geometry": {"coordinates":[-94.855407,30.701518],"type":"Point"}
}