{
  "type": "Feature",
  "properties": {
    "iso:country":"US",
    "sg:address":"3508 FM 528",
    "sg:city":"Alvin",
    "sg:classifiers":[
        {
            "category":"Shopping",
            "subcategory":"Gifts & Souvenirs",
            "type":"Retail Goods"
        }
    ],
    "sg:phone":"+1 281 331 6100",
    "sg:postcode":"77511",
    "sg:province":"TX",
    "wof:name":"Gifts 3 Go",
    "wof:placetype":"venue"
},
  "geometry": {"coordinates":[-95.233678,29.45487],"type":"Point"}
}