{
  "type": "Feature",
  "properties": {
    "iso:country":"US",
    "sg:address":"12002 Veterans Memorial Dr",
    "sg:city":"Houston",
    "sg:classifiers":[
        {
            "category":"Retail",
            "subcategory":"Laundry & Dry Cleaning",
            "type":"Services"
        }
    ],
    "sg:phone":"+1 281 880 8768",
    "sg:postcode":"77067",
    "sg:province":"TX",
    "sg:tags":[
        "cleaners",
        "plant",
        "drycleaning"
    ],
    "wof:name":"H & H Cleaner & Tailoring",
    "wof:placetype":"venue"
},
  "geometry": {"coordinates":[-95.47548500000001,29.957953],"type":"Point"}
}