{
  "type": "Feature",
  "properties": {
    "iso:country":"US",
    "sg:address":"309 S Robinson Dr",
    "sg:city":"Robinson",
    "sg:classifiers":[
        {
            "category":"Cinema",
            "subcategory":"Movie Rental",
            "type":"Entertainment"
        }
    ],
    "sg:phone":"+1 254 662 4870",
    "sg:postcode":"76706",
    "sg:province":"TX",
    "sg:tags":[
        "leasing",
        "video",
        "disc",
        "tape"
    ],
    "wof:name":"Rocket Video",
    "wof:placetype":"venue"
},
  "geometry": {"coordinates":[-97.114817,31.46778],"type":"Point"}
}