{
  "type": "Feature",
  "properties": {
    "iso:country":"US",
    "sg:address":"4028 N Story Rd",
    "sg:city":"Irving",
    "sg:classifiers":[
        {
            "category":"Building & Trades",
            "subcategory":"Construction",
            "type":"Services"
        }
    ],
    "sg:phone":"+1 972 870 0554",
    "sg:postcode":"75038",
    "sg:province":"TX",
    "sg:tags":[
        "painter"
    ],
    "wof:name":"WCR Painting",
    "wof:placetype":"venue"
},
  "geometry": {"coordinates":[-96.976536,32.861664],"type":"Point"}
}