{
  "type": "Feature",
  "properties": {
    "iso:country":"US",
    "sg:address":"10923 Jones Rd",
    "sg:city":"Houston",
    "sg:classifiers":[
        {
            "category":"Shopping",
            "subcategory":"Clothing, Apparel, & Fashions",
            "type":"Retail Goods"
        }
    ],
    "sg:phone":"+1 281 897 8071",
    "sg:postcode":"77065",
    "sg:province":"TX",
    "sg:tags":[
        "tailoring",
        "tailor",
        "alteration",
        "wedding"
    ],
    "wof:name":"M's Tailor",
    "wof:placetype":"venue"
},
  "geometry": {"coordinates":[-95.584962,29.931051],"type":"Point"}
}