{
  "type": "Feature",
  "properties": {
    "iso:country":"US",
    "sg:address":"424 Burlington Ave",
    "sg:city":"Spur",
    "sg:classifiers":[
        {
            "category":"Shopping",
            "subcategory":"Florist",
            "type":"Retail Goods"
        }
    ],
    "sg:phone":"+1 806 271 3382",
    "sg:postcode":"79370",
    "sg:province":"TX",
    "wof:name":"Spur Florist",
    "wof:placetype":"venue"
},
  "geometry": {"coordinates":[-100.854934,33.477227],"type":"Point"}
}