{
  "type": "Feature",
  "properties": {
    "iso:country":"US",
    "sg:address":"5711 Hillcroft St #A8",
    "sg:city":"Houston",
    "sg:classifiers":[
        {
            "category":"Shopping",
            "subcategory":"Clothing, Apparel, & Fashions",
            "type":"Retail Goods"
        },
        {
            "category":"Shopping",
            "subcategory":"Shoes",
            "type":"Retail Goods"
        }
    ],
    "sg:phone":"+1 713 789 2322",
    "sg:postcode":"77036",
    "sg:province":"TX",
    "sg:tags":[
        "accessory",
        "clothing",
        "store",
        "women's"
    ],
    "wof:name":"Just In",
    "wof:placetype":"venue"
},
  "geometry": {"coordinates":[-95.50058799999999,29.720017],"type":"Point"}
}