{
  "type": "Feature",
  "properties": {
    "iso:country":"US",
    "sg:address":"609 S Bois D Arc Ave",
    "sg:city":"Tyler",
    "sg:classifiers":[
        {
            "category":"Retail",
            "subcategory":"Repair Shop",
            "type":"Services"
        }
    ],
    "sg:phone":"+1 903 593 4822",
    "sg:postcode":"75701",
    "sg:province":"TX",
    "sg:tags":[
        "equipment",
        "telephone",
        "system"
    ],
    "wof:name":"B-H Telecom",
    "wof:placetype":"venue"
},
  "geometry": {"coordinates":[-95.303436,32.343421],"type":"Point"}
}