{
  "type": "Feature",
  "properties": {
    "iso:country":"US",
    "sg:address":"905 Nebraska St",
    "sg:city":"South Houston",
    "sg:classifiers":[
        {
            "category":"Restaurant",
            "type":"Food & Drink"
        }
    ],
    "sg:phone":"+1 713 946 3353",
    "sg:postcode":"77587",
    "sg:province":"TX",
    "sg:tags":[
        "eating"
    ],
    "wof:name":"Rios Food Market",
    "wof:placetype":"venue"
},
  "geometry": {"coordinates":[-95.246381,29.664393],"type":"Point"}
}