{
  "type": "Feature",
  "properties": {
    "iso:country":"US",
    "sg:address":"5702 Ponderosa Dr",
    "sg:city":"San Antonio",
    "sg:classifiers":[
        {
            "category":"Organizations",
            "subcategory":"Professional Association",
            "type":"Services"
        }
    ],
    "sg:phone":"+1 210 684 2194",
    "sg:postcode":"78240",
    "sg:province":"TX",
    "wof:name":"American Assoc of Univers",
    "wof:placetype":"venue"
},
  "geometry": {"coordinates":[-98.59854799999999,29.496872],"type":"Point"}
}