{
  "type": "Feature",
  "properties": {
    "iso:country":"US",
    "sg:address":"1313 Scott Ave",
    "sg:city":"Wichita Falls",
    "sg:classifiers":[
        {
            "category":"Autos & Motor Vehicles",
            "subcategory":"Automobile Sales",
            "type":"Retail Goods"
        }
    ],
    "sg:phone":"+1 940 322 3168",
    "sg:postcode":"76301",
    "sg:province":"TX",
    "sg:tags":[
        "car",
        "dealer"
    ],
    "wof:name":"Freedom Motors",
    "wof:placetype":"venue"
},
  "geometry": {"coordinates":[-98.4873,33.906193],"type":"Point"}
}