{
  "type": "Feature",
  "properties": {
    "iso:country":"US",
    "sg:address":"3308 Fairfield Ave",
    "sg:city":"Fort Worth",
    "sg:classifiers":[
        {
            "category":"Restaurant",
            "type":"Food & Drink"
        }
    ],
    "sg:phone":"+1 817 731 6961",
    "sg:postcode":"76116",
    "sg:province":"TX",
    "sg:tags":[
        "drinking",
        "eating"
    ],
    "wof:name":"Hedarys Restaurant",
    "wof:placetype":"venue"
},
  "geometry": {"coordinates":[-97.416713,32.727051],"type":"Point"}
}