{
  "type": "Feature",
  "properties": {
    "iso:country":"US",
    "sg:address":"18351 Kuykendahl Rd",
    "sg:city":"Spring",
    "sg:classifiers":[
        {
            "category":"Shopping",
            "type":"Retail Goods"
        }
    ],
    "sg:phone":"+1 281 528 5777",
    "sg:postcode":"77379",
    "sg:province":"TX",
    "sg:tags":[
        "cosmetic",
        "perfume"
    ],
    "sg:website":"www.allurebeautysupply.com",
    "wof:name":"Allure Beauty Supply",
    "wof:placetype":"venue"
},
  "geometry": {"coordinates":[-95.486923,30.037929],"type":"Point"}
}