{
  "type": "Feature",
  "properties": {
    "iso:country":"US",
    "sg:address":"106 S Lee St",
    "sg:city":"Midland",
    "sg:classifiers":[
        {
            "category":"Building & Trades",
            "subcategory":"Construction",
            "type":"Services"
        }
    ],
    "sg:phone":"+1 432 570 9951",
    "sg:postcode":"79701",
    "sg:province":"TX",
    "sg:tags":[
        "contractor"
    ],
    "wof:name":"Allied Services",
    "wof:placetype":"venue"
},
  "geometry": {"coordinates":[-102.06288600000001,31.996955],"type":"Point"}
}