{
  "type": "Feature",
  "properties": {
    "iso:country":"US",
    "sg:address":"1810 Commerce St",
    "sg:city":"Garland",
    "sg:classifiers":[
        {
            "category":"Shopping",
            "subcategory":"Hobbies, Toys, & Games",
            "type":"Retail Goods"
        }
    ],
    "sg:phone":"+1 972 487 5921",
    "sg:postcode":"75040",
    "sg:province":"TX",
    "wof:name":"Yuletide Yards",
    "wof:placetype":"venue"
},
  "geometry": {"coordinates":[-96.601883,32.908772],"type":"Point"}
}