{
  "type": "Feature",
  "properties": {
    "iso:country":"US",
    "sg:address":"760 TX-337",
    "sg:city":"New Braunfels",
    "sg:classifiers":[
        {
            "category":"Restaurant",
            "type":"Food & Drink"
        }
    ],
    "sg:menulink":"http://www.allmenus.com/tx/new-braunfels/223715-chicken-express/menu/",
    "sg:phone":"+1 830 625 3800",
    "sg:postcode":"78130",
    "sg:province":"TX",
    "sg:tags":[
        "american"
    ],
    "wof:name":"Chicken Express",
    "wof:placetype":"venue"
},
  "geometry": {"coordinates":[-98.10537600000001,29.722198],"type":"Point"}
}