{
  "type": "Feature",
  "properties": {
    "iso:country":"US",
    "sg:address":"1709 Benbow Way",
    "sg:city":"Houston",
    "sg:classifiers":[
        {
            "category":"Real Estate",
            "subcategory":"Real Estate Agent",
            "type":"Services"
        }
    ],
    "sg:phone":"+1 713 932 9122",
    "sg:postcode":"77080",
    "sg:province":"TX",
    "wof:name":"Oscar Sanchez",
    "wof:placetype":"venue"
},
  "geometry": {"coordinates":[-95.522436,29.800463],"type":"Point"}
}