{
  "type": "Feature",
  "properties": {
    "iso:country":"US",
    "sg:address":"10534 Cradlerock Dr",
    "sg:city":"Dallas",
    "sg:classifiers":[
        {
            "category":"Food & Beverages",
            "subcategory":"Specialty",
            "type":"Retail Goods"
        }
    ],
    "sg:phone":"+1 972 289 6969",
    "sg:postcode":"75217",
    "sg:province":"TX",
    "wof:name":"Majel Intl",
    "wof:placetype":"venue"
},
  "geometry": {"coordinates":[-96.6452,32.74159],"type":"Point"}
}