{
  "type": "Feature",
  "properties": {
    "iso:country":"US",
    "sg:address":"2339 Dunstan Rd",
    "sg:city":"Houston",
    "sg:classifiers":[
        {
            "category":"Professional",
            "subcategory":"Advertising",
            "type":"Services"
        }
    ],
    "sg:phone":"+1 713 807 9000",
    "sg:postcode":"77005",
    "sg:province":"TX",
    "sg:tags":[
        "counselor"
    ],
    "wof:name":"Brownchild LTD",
    "wof:placetype":"venue"
},
  "geometry": {"coordinates":[-95.41462900000001,29.719261],"type":"Point"}
}