{
  "type": "Feature",
  "properties": {
    "iso:country":"US",
    "sg:address":"3302 Red Cliff Cir",
    "sg:city":"Temple",
    "sg:classifiers":[
        {
            "category":"Real Estate",
            "subcategory":"Real Estate Services",
            "type":"Services"
        }
    ],
    "sg:phone":"+1 254 770 1005",
    "sg:postcode":"76502",
    "sg:province":"TX",
    "sg:tags":[
        "company",
        "title"
    ],
    "wof:name":"Lone Star Vechile Title Svc",
    "wof:placetype":"venue"
},
  "geometry": {"coordinates":[-97.39663299999999,31.076263],"type":"Point"}
}