{
  "type": "Feature",
  "properties": {
    "iso:country":"US",
    "sg:address":"2398 W Highway 199",
    "sg:city":"Springtown",
    "sg:classifiers":[
        {
            "category":"Building & Trades",
            "subcategory":"Electrical",
            "type":"Services"
        }
    ],
    "sg:phone":"+1 817 948 1936",
    "sg:postcode":"76082",
    "sg:province":"TX",
    "sg:tags":[
        "electrician"
    ],
    "wof:name":"North Star Oilfield Electrical Company Inc.",
    "wof:placetype":"venue"
},
  "geometry": {"coordinates":[-97.71991300000001,32.972194],"type":"Point"}
}