{
  "type": "Feature",
  "properties": {
    "iso:country":"US",
    "sg:address":"600 W. 13th St.",
    "sg:city":"Austin",
    "sg:classifiers":[
        {
            "category":"Professional",
            "subcategory":"Lawyer & Legal Services",
            "type":"Services"
        }
    ],
    "sg:phone":"+1 512 963 8855",
    "sg:postcode":"78701",
    "sg:province":"TX",
    "sg:tags":[
        "litigation",
        "personal",
        "injury"
    ],
    "sg:website":"www.harronlaw.com",
    "wof:name":"Law Office Of Eric Harron",
    "wof:placetype":"venue"
},
  "geometry": {"coordinates":[-97.745853,30.276623],"type":"Point"}
}