{
  "type": "Feature",
  "properties": {
    "iso:country":"US",
    "sg:address":"2175 Co Rd 108",
    "sg:city":"Hutto",
    "sg:classifiers":[
        {
            "category":"Autos & Motor Vehicles",
            "subcategory":"Automobile Sales",
            "type":"Retail Goods"
        }
    ],
    "sg:phone":"+1 512 846 1568",
    "sg:postcode":"78634",
    "sg:province":"TX",
    "sg:tags":[
        "car",
        "dealer"
    ],
    "wof:name":"Affordable Auto Sales",
    "wof:placetype":"venue"
},
  "geometry": {"coordinates":[-97.573409,30.542577],"type":"Point"}
}