{
  "type": "Feature",
  "properties": {
    "iso:country":"US",
    "sg:address":"13525 Denton Dr",
    "sg:city":"Dallas",
    "sg:classifiers":[
        {
            "category":"Manufacturing",
            "subcategory":"Chemicals & Compounds",
            "type":"Manufacturing & Wholesale Goods"
        }
    ],
    "sg:phone":"+1 972 241 9665",
    "sg:postcode":"75234",
    "sg:province":"TX",
    "sg:tags":[
        "preparation",
        "toilet",
        "mfg"
    ],
    "wof:name":"Naterra International Inc",
    "wof:placetype":"venue"
},
  "geometry": {"coordinates":[-96.898687,32.928868],"type":"Point"}
}