{
  "type": "Feature",
  "properties": {
    "iso:country":"US",
    "sg:address":"147 Alamo St",
    "sg:city":"Lone Star",
    "sg:classifiers":[
        {
            "category":"Real Estate",
            "subcategory":"Real Estate Operator",
            "type":"Services"
        }
    ],
    "sg:phone":"+1 903 656 2995",
    "sg:postcode":"75668",
    "sg:province":"TX",
    "sg:tags":[
        "building",
        "apartment"
    ],
    "wof:name":"Lone Star Senior Apartments",
    "wof:placetype":"venue"
},
  "geometry": {"coordinates":[-94.711393,32.940639],"type":"Point"}
}