{
  "type": "Feature",
  "properties": {
    "iso:country":"US",
    "sg:address":"7042 Coral Tree Ln",
    "sg:city":"San Antonio",
    "sg:classifiers":[
        {
            "category":"Social Services",
            "subcategory":"Adult Care",
            "type":"Services"
        }
    ],
    "sg:phone":"+1 210 675 4021",
    "sg:postcode":"78227",
    "sg:province":"TX",
    "sg:tags":[
        "residential"
    ],
    "wof:name":"Lettys Loved Ones",
    "wof:placetype":"venue"
},
  "geometry": {"coordinates":[-98.62955599999999,29.43097],"type":"Point"}
}