{
  "type": "Feature",
  "properties": {
    "iso:country":"US",
    "sg:address":"199 N Belknap St",
    "sg:city":"Stephenville",
    "sg:classifiers":[
        {
            "category":"Retail",
            "subcategory":"Portrait Studio",
            "type":"Services"
        }
    ],
    "sg:phone":"+1 254 968 0088",
    "sg:postcode":"76401",
    "sg:province":"TX",
    "sg:tags":[
        "photographer"
    ],
    "wof:name":"Julie Jacques Lueck Phtgrphy",
    "wof:placetype":"venue"
},
  "geometry": {"coordinates":[-98.202862,32.220295],"type":"Point"}
}