{
  "type": "Feature",
  "properties": {
    "iso:country":"US",
    "sg:address":"705 Gallant Fox Dr",
    "sg:city":"Dallas",
    "sg:classifiers":[
        {
            "category":"Organizations",
            "subcategory":"Religious Organization",
            "type":"Services"
        }
    ],
    "sg:phone":"+1 214 337 8170",
    "sg:postcode":"75211",
    "sg:province":"TX",
    "wof:name":"Jesus V Ortega",
    "wof:placetype":"venue"
},
  "geometry": {"coordinates":[-96.927975,32.739682],"type":"Point"}
}