{
  "type": "Feature",
  "properties": {
    "iso:country":"US",
    "sg:address":"19110 Amoco Dr S",
    "sg:city":"Alvin",
    "sg:classifiers":[
        {
            "category":"Retail",
            "subcategory":"Auto Repair",
            "type":"Services"
        }
    ],
    "sg:phone":"+1 281 489 7038",
    "sg:postcode":"77511",
    "sg:province":"TX",
    "sg:tags":[
        "general"
    ],
    "wof:name":"Ahuac Auto Repair",
    "wof:placetype":"venue"
},
  "geometry": {"coordinates":[-95.267522,29.494963],"type":"Point"}
}