{
  "type": "Feature",
  "properties": {
    "iso:country":"US",
    "sg:address":"3120 Sherwood Ln",
    "sg:city":"Wichita Falls",
    "sg:classifiers":[
        {
            "category":"Building & Trades",
            "subcategory":"Construction",
            "type":"Services"
        }
    ],
    "sg:phone":"+1 940 696 3818",
    "sg:postcode":"76308",
    "sg:province":"TX",
    "sg:tags":[
        "contractor"
    ],
    "wof:name":"Cantrell Tile Co",
    "wof:placetype":"venue"
},
  "geometry": {"coordinates":[-98.52802699999999,33.878245],"type":"Point"}
}