{
  "type": "Feature",
  "properties": {
    "iso:country":"US",
    "sg:address":"921 Ronald Dr",
    "sg:city":"Corpus Christi",
    "sg:classifiers":[
        {
            "category":"Building & Trades",
            "subcategory":"Landscaping Services",
            "type":"Services"
        }
    ],
    "sg:phone":"+1 361 993 2878",
    "sg:postcode":"78412",
    "sg:province":"TX",
    "wof:name":"Als Lawn Care",
    "wof:placetype":"venue"
},
  "geometry": {"coordinates":[-97.35489699999999,27.708925],"type":"Point"}
}