{
  "type": "Feature",
  "properties": {
    "iso:country":"US",
    "sg:address":"9220 Ferguson Rd",
    "sg:city":"Dallas",
    "sg:classifiers":[
        {
            "category":"Organizations",
            "subcategory":"Religious Organization",
            "type":"Services"
        }
    ],
    "sg:phone":"+1 214 328 2747",
    "sg:postcode":"75228",
    "sg:province":"TX",
    "sg:tags":[
        "church"
    ],
    "wof:name":"White Rock Church Of Christ",
    "wof:placetype":"venue"
},
  "geometry": {"coordinates":[-96.693794,32.815186],"type":"Point"}
}