{
  "type": "Feature",
  "properties": {
    "iso:country":"US",
    "sg:address":"1800 Gerault Rd",
    "sg:city":"Flower Mound",
    "sg:classifiers":[
        {
            "category":"Arts & Performance",
            "subcategory":"Theater",
            "type":"Entertainment"
        }
    ],
    "sg:phone":"+1 972 724 2147",
    "sg:postcode":"75028",
    "sg:province":"TX",
    "wof:name":"Performing Arts Theatre",
    "wof:placetype":"venue"
},
  "geometry": {"coordinates":[-97.04494200000001,33.0095],"type":"Point"}
}