{
  "type": "Feature",
  "properties": {
    "iso:country":"US",
    "sg:address":"5900 S Hulen St",
    "sg:city":"Fort Worth",
    "sg:classifiers":[
        {
            "category":"Restaurant",
            "type":"Food & Drink"
        }
    ],
    "sg:menulink":"http://www.allmenus.com/tx/fort-worth/105075-carinos-italian-grill/menu/",
    "sg:phone":"+1 817 346 4456",
    "sg:postcode":"76132",
    "sg:province":"TX",
    "sg:tags":[
        "american",
        "italian"
    ],
    "wof:name":"Carino's Italian Grill",
    "wof:placetype":"venue"
},
  "geometry": {"coordinates":[-97.402308,32.664169],"type":"Point"}
}