{
  "type": "Feature",
  "properties": {
    "iso:country":"US",
    "sg:address":"301 N Allen Dr",
    "sg:city":"Allen",
    "sg:classifiers":[
        {
            "category":"Insurance",
            "subcategory":"Insurance Agent",
            "type":"Services"
        }
    ],
    "sg:phone":"+1 972 727 5145",
    "sg:postcode":"75013",
    "sg:province":"TX",
    "wof:name":"Farmers Insurance Group",
    "wof:placetype":"venue"
},
  "geometry": {"coordinates":[-96.672089,33.10859],"type":"Point"}
}