{
  "type": "Feature",
  "properties": {
    "iso:country":"US",
    "sg:address":"1101 N Business 45",
    "sg:city":"Corsicana",
    "sg:classifiers":[
        {
            "category":"Manufacturing",
            "subcategory":"Apparel",
            "type":"Manufacturing & Wholesale Goods"
        }
    ],
    "sg:phone":"+1 903 874 7446",
    "sg:postcode":"75110",
    "sg:province":"TX",
    "sg:tags":[
        "cap",
        "hat",
        "millinery"
    ],
    "wof:name":"Hat Brands Inc",
    "wof:placetype":"venue"
},
  "geometry": {"coordinates":[-96.46343299999999,32.105006],"type":"Point"}
}