{
  "type": "Feature",
  "properties": {
    "iso:country":"US",
    "sg:address":"7501 Lockheed Dr",
    "sg:city":"El Paso",
    "sg:classifiers":[
        {
            "category":"Real Estate",
            "subcategory":"Real Estate Agent",
            "type":"Services"
        }
    ],
    "sg:phone":"+1 915 774 0962",
    "sg:postcode":"79925",
    "sg:province":"TX",
    "sg:tags":[
        "management"
    ],
    "wof:name":"Ed Walsh Property Management",
    "wof:placetype":"venue"
},
  "geometry": {"coordinates":[-106.389548,31.790853],"type":"Point"}
}