{
  "type": "Feature",
  "properties": {
    "iso:country":"US",
    "sg:address":"855 Delmar Dr",
    "sg:city":"Beaumont",
    "sg:classifiers":[
        {
            "category":"Autos & Motor Vehicles",
            "subcategory":"Auto Supplies",
            "type":"Retail Goods"
        },
        {
            "category":"Manufacturing",
            "subcategory":"Motor Vehicles & Parts",
            "type":"Manufacturing & Wholesale Goods"
        },
        {
            "category":"Retail",
            "subcategory":"Auto Repair",
            "type":"Services"
        }
    ],
    "sg:phone":"+1 409 842 1700",
    "sg:postcode":"77707",
    "sg:province":"TX",
    "sg:tags":[
        "automobile",
        "driveshaft",
        "accessory"
    ],
    "wof:name":"Driveshaft Specialties Inc",
    "wof:placetype":"venue"
},
  "geometry": {"coordinates":[-94.149573,30.068433],"type":"Point"}
}