{
  "type": "Feature",
  "properties": {
    "iso:country":"US",
    "sg:address":"14075 Dublin Sq",
    "sg:city":"San Antonio",
    "sg:classifiers":[
        {
            "category":"Professional",
            "type":"Services"
        }
    ],
    "sg:phone":"+1 210 599 9666",
    "sg:postcode":"78217",
    "sg:province":"TX",
    "wof:name":"American Multi Coat",
    "wof:placetype":"venue"
},
  "geometry": {"coordinates":[-98.412882,29.568093],"type":"Point"}
}