{
  "type": "Feature",
  "properties": {
    "iso:country":"US",
    "sg:address":"2435 6th Ave",
    "sg:city":"Port Arthur",
    "sg:classifiers":[
        {
            "category":"Personal",
            "subcategory":"Barber",
            "type":"Services"
        }
    ],
    "sg:phone":"+1 409 736 2846",
    "sg:postcode":"77642",
    "sg:province":"TX",
    "sg:tags":[
        "shop",
        "beauty"
    ],
    "wof:name":"Tomplaits Nelda Hair Designers",
    "wof:placetype":"venue"
},
  "geometry": {"coordinates":[-93.93079,29.908665],"type":"Point"}
}