{
  "type": "Feature",
  "properties": {
    "iso:country":"US",
    "sg:address":"9800 N Lamar Blvd., Ste 218",
    "sg:city":"Austin",
    "sg:classifiers":[
        {
            "category":"Professional",
            "subcategory":"Detective & Security Services",
            "type":"Services"
        }
    ],
    "sg:phone":"+1 512 490 1572",
    "sg:postcode":"78753",
    "sg:province":"TX",
    "sg:tags":[
        "control",
        "monitoring",
        "consultant",
        "system",
        "access",
        "equipment",
        "guard",
        "patrol"
    ],
    "wof:name":"Applied Network Security, LLC",
    "wof:placetype":"venue"
},
  "geometry": {"coordinates":[-97.694603,30.367399],"type":"Point"}
}