{
  "type": "Feature",
  "properties": {
    "iso:country":"US",
    "sg:address":"1319 Iberis Rd S",
    "sg:city":"Tuscola",
    "sg:classifiers":[
        {
            "category":"Manufacturing",
            "subcategory":"Toys & Sporting Goods",
            "type":"Manufacturing & Wholesale Goods"
        }
    ],
    "sg:phone":"+1 325 698 8151",
    "sg:postcode":"79562",
    "sg:province":"TX",
    "sg:tags":[
        "equipment",
        "playground"
    ],
    "wof:name":"Custom Machine & Mfg",
    "wof:placetype":"venue"
},
  "geometry": {"coordinates":[-99.75874,32.308988],"type":"Point"}
}