{
  "type": "Feature",
  "properties": {
    "iso:country":"US",
    "sg:address":"4926 FM 3012",
    "sg:city":"Wharton",
    "sg:classifiers":[
        {
            "category":"Retail",
            "subcategory":"Auto Repair",
            "type":"Services"
        }
    ],
    "sg:phone":"+1 979 532 5139",
    "sg:postcode":"77488",
    "sg:province":"TX",
    "sg:tags":[
        "repairing",
        "automobile"
    ],
    "wof:name":"Macek's Garage",
    "wof:placetype":"venue"
},
  "geometry": {"coordinates":[-96.041714,29.289043],"type":"Point"}
}