{
  "type": "Feature",
  "properties": {
    "iso:country":"US",
    "sg:address":"221 US Hwy 77",
    "sg:city":"Waxahachie",
    "sg:classifiers":[
        {
            "category":"Shopping",
            "type":"Retail Goods"
        }
    ],
    "sg:phone":"+1 972 923 4486",
    "sg:postcode":"75165",
    "sg:province":"TX",
    "sg:tags":[
        "craft",
        "gallery",
        "dealer"
    ],
    "wof:name":"Texas Inspirations",
    "wof:placetype":"venue"
},
  "geometry": {"coordinates":[-96.849441,32.385115],"type":"Point"}
}