{
  "type": "Feature",
  "properties": {
    "iso:country":"US",
    "sg:address":"8787 S Lancaster Rd",
    "sg:city":"Dallas",
    "sg:classifiers":[
        {
            "category":"Restaurant",
            "type":"Food & Drink"
        }
    ],
    "sg:phone":"+1 972 228 9105",
    "sg:postcode":"75241",
    "sg:province":"TX",
    "wof:name":"Main Street Cafe",
    "wof:placetype":"venue"
},
  "geometry": {"coordinates":[-96.779701,32.6432],"type":"Point"}
}