{
  "type": "Feature",
  "properties": {
    "iso:country":"US",
    "sg:address":"7017 N 10th St",
    "sg:city":"Mcallen",
    "sg:classifiers":[
        {
            "category":"Social Services",
            "subcategory":"Child Care",
            "type":"Services"
        }
    ],
    "sg:phone":"+1 956 928 1440",
    "sg:postcode":"78504",
    "sg:province":"TX",
    "sg:tags":[
        "toy",
        "store"
    ],
    "wof:name":"Learning Express McAllen",
    "wof:placetype":"venue"
},
  "geometry": {"coordinates":[-98.219055,26.267854],"type":"Point"}
}