{
  "type": "Feature",
  "properties": {
    "iso:country":"US",
    "sg:address":"120 Pecan Valley Ln",
    "sg:city":"Waxahachie",
    "sg:classifiers":[
        {
            "category":"Professional",
            "subcategory":"Business Services",
            "type":"Services"
        }
    ],
    "sg:phone":"+1 972 935 9090",
    "sg:postcode":"75165",
    "sg:province":"TX",
    "sg:tags":[
        "appraiser"
    ],
    "wof:name":"Kirby Harper Appraisals",
    "wof:placetype":"venue"
},
  "geometry": {"coordinates":[-96.807942,32.34944],"type":"Point"}
}