{
  "type": "Feature",
  "properties": {
    "iso:country":"US",
    "sg:address":"913 N I- 35",
    "sg:city":"San Marcos",
    "sg:classifiers":[
        {
            "category":"Restaurant",
            "type":"Food & Drink"
        }
    ],
    "sg:phone":"+1 512 392 5211",
    "sg:postcode":"78666",
    "sg:province":"TX",
    "sg:tags":[
        "eating"
    ],
    "wof:name":"KFC",
    "wof:placetype":"venue"
},
  "geometry": {"coordinates":[-97.926885,29.878014],"type":"Point"}
}