{
  "type": "Feature",
  "properties": {
    "iso:country":"US",
    "sg:address":"10611 Gold Point Dr",
    "sg:city":"Houston",
    "sg:classifiers":[
        {
            "category":"Professional",
            "subcategory":"Business Services",
            "type":"Services"
        }
    ],
    "sg:phone":"+1 281 469 9006",
    "sg:postcode":"77064",
    "sg:province":"TX",
    "wof:name":"2 Floozies",
    "wof:placetype":"venue"
},
  "geometry": {"coordinates":[-95.575987,29.90682],"type":"Point"}
}