{
  "type": "Feature",
  "properties": {
    "iso:country":"US",
    "sg:address":"101 Cemetary Rd",
    "sg:city":"Stamford",
    "sg:classifiers":[
        {
            "category":"Utilities",
            "subcategory":"Water",
            "type":"Services"
        }
    ],
    "sg:phone":"+1 325 773 3319",
    "sg:postcode":"79545",
    "sg:province":"TX",
    "sg:tags":[
        "system",
        "supply"
    ],
    "wof:name":"Paint Creek Water Supply",
    "wof:placetype":"venue"
},
  "geometry": {"coordinates":[-100.50897000000001,32.403021],"type":"Point"}
}