{
  "type": "Feature",
  "properties": {
    "iso:country":"US",
    "sg:address":"231 Aston Dr",
    "sg:city":"Bridgeport",
    "sg:classifiers":[
        {
            "category":"Professional",
            "type":"Services"
        }
    ],
    "sg:phone":"+1 940 683 1744",
    "sg:postcode":"76426",
    "sg:province":"TX",
    "wof:name":"Active Voice LLC",
    "wof:placetype":"venue"
},
  "geometry": {"coordinates":[-97.8323,33.223415],"type":"Point"}
}