{
  "type": "Feature",
  "properties": {
    "iso:country":"US",
    "sg:address":"12210 Montego Plz",
    "sg:city":"Dallas",
    "sg:classifiers":[
        {
            "category":"Manufacturing",
            "subcategory":"Textiles",
            "type":"Manufacturing & Wholesale Goods"
        }
    ],
    "sg:phone":"+1 972 392 4441",
    "sg:postcode":"75230",
    "sg:province":"TX",
    "sg:tags":[
        "business",
        "mfg"
    ],
    "wof:name":"Cheryl Berman Textiles",
    "wof:placetype":"venue"
},
  "geometry": {"coordinates":[-96.815252,32.920108],"type":"Point"}
}