{
  "type": "Feature",
  "properties": {
    "iso:country":"US",
    "sg:address":"11425 Homestead Rd",
    "sg:city":"Houston",
    "sg:classifiers":[
        {
            "category":"Retail",
            "subcategory":"Auto Repair",
            "type":"Services"
        }
    ],
    "sg:phone":"+1 281 987 8210",
    "sg:postcode":"77016",
    "sg:province":"TX",
    "sg:tags":[
        "repairing",
        "automobile",
        "radiator"
    ],
    "wof:name":"J R's Radiator Shop",
    "wof:placetype":"venue"
},
  "geometry": {"coordinates":[-95.300926,29.887124],"type":"Point"}
}