{
  "type": "Feature",
  "properties": {
    "iso:country":"US",
    "sg:address":"781 Cypress St",
    "sg:city":"Abilene",
    "sg:classifiers":[
        {
            "category":"Wholesale",
            "subcategory":"Office Equipment",
            "type":"Manufacturing & Wholesale Goods"
        }
    ],
    "sg:phone":"+1 325 673 7383",
    "sg:postcode":"79601",
    "sg:province":"TX",
    "sg:tags":[
        "machine",
        "photocopy",
        "duplicating",
        "copying"
    ],
    "wof:name":"Copy Machines Co",
    "wof:placetype":"venue"
},
  "geometry": {"coordinates":[-99.73343800000001,32.457266],"type":"Point"}
}