{
  "type": "Feature",
  "properties": {
    "iso:country":"US",
    "sg:address":"313 E Tom Landry St",
    "sg:city":"Mission",
    "sg:classifiers":[
        {
            "category":"Banks & Credit Unions",
            "subcategory":"Financial Services",
            "type":"Services"
        }
    ],
    "sg:phone":"+1 956 519 1313",
    "sg:postcode":"78572",
    "sg:province":"TX",
    "sg:tags":[
        "loan"
    ],
    "wof:name":"C & G Company",
    "wof:placetype":"venue"
},
  "geometry": {"coordinates":[-98.32326,26.215602],"type":"Point"}
}