{
  "type": "Feature",
  "properties": {
    "iso:country":"US",
    "sg:address":"1202 E del Mar Blvd",
    "sg:city":"Laredo",
    "sg:classifiers":[
        {
            "category":"Restaurant",
            "type":"Food & Drink"
        }
    ],
    "sg:phone":"+1 956 717 4999",
    "sg:postcode":"78041",
    "sg:province":"TX",
    "sg:tags":[
        "eating"
    ],
    "wof:name":"Tonos Bar & Grill Inc",
    "wof:placetype":"venue"
},
  "geometry": {"coordinates":[-99.47314,27.574215],"type":"Point"}
}