{
  "type": "Feature",
  "properties": {
    "iso:country":"US",
    "sg:address":"508 S Macarthur Blvd",
    "sg:city":"Irving",
    "sg:classifiers":[
        {
            "category":"Social Services",
            "type":"Services"
        },
        {
            "category":"Health Services",
            "subcategory":"Doctor",
            "type":"Services"
        }
    ],
    "sg:phone":"+1 972 259 6900",
    "sg:postcode":"75060",
    "sg:province":"TX",
    "sg:tags":[
        "clinic",
        "medical"
    ],
    "wof:name":"Molina Medical Surgical Center",
    "wof:placetype":"venue"
},
  "geometry": {"coordinates":[-96.959923,32.809787],"type":"Point"}
}