{
  "type": "Feature",
  "properties": {
    "iso:country":"US",
    "sg:address":"2410 E Riverside Drive Suite A3",
    "sg:city":"Austin",
    "sg:classifiers":[
        {
            "category":"Shopping",
            "subcategory":"Computers & Home Electronics",
            "type":"Retail Goods"
        }
    ],
    "sg:phone":"+1 512 441 2433",
    "sg:postcode":"78741",
    "sg:province":"TX",
    "wof:name":"Blockbuster Video",
    "wof:placetype":"venue"
},
  "geometry": {"coordinates":[-97.725004,30.236557],"type":"Point"}
}