{
  "type": "Feature",
  "properties": {
    "iso:country":"US",
    "sg:address":"383 Valley Hi Dr",
    "sg:city":"San Antonio",
    "sg:classifiers":[
        {
            "category":"Personal",
            "subcategory":"Barber",
            "type":"Services"
        }
    ],
    "sg:phone":"+1 210 673 5533",
    "sg:postcode":"78227",
    "sg:province":"TX",
    "wof:name":"Magic Clippers",
    "wof:placetype":"venue"
},
  "geometry": {"coordinates":[-98.64010399999999,29.381213],"type":"Point"}
}