{
  "type": "Feature",
  "properties": {
    "iso:country":"US",
    "sg:address":"525 E Walker St",
    "sg:city":"League City",
    "sg:classifiers":[
        {
            "category":"Building & Trades",
            "subcategory":"Plumbing",
            "type":"Services"
        }
    ],
    "sg:phone":"+1 281 338 2005",
    "sg:postcode":"77573",
    "sg:province":"TX",
    "sg:tags":[
        "contractor"
    ],
    "wof:name":"Gibbs Interprise",
    "wof:placetype":"venue"
},
  "geometry": {"coordinates":[-95.087569,29.508114],"type":"Point"}
}