{
  "type": "Feature",
  "properties": {
    "iso:country":"US",
    "sg:address":"319 Neches St",
    "sg:city":"Jacksonville",
    "sg:classifiers":[
        {
            "category":"Building & Trades",
            "subcategory":"Electrical",
            "type":"Services"
        }
    ],
    "sg:phone":"+1 903 586 1670",
    "sg:postcode":"75766",
    "sg:province":"TX",
    "sg:tags":[
        "electric",
        "contractor"
    ],
    "wof:name":"Inter-County Electric Co",
    "wof:placetype":"venue"
},
  "geometry": {"coordinates":[-95.26936600000001,31.963424],"type":"Point"}
}