{
  "type": "Feature",
  "properties": {
    "iso:country":"US",
    "sg:address":"2208 Routh St",
    "sg:city":"Dallas",
    "sg:classifiers":[
        {
            "category":"Government",
            "subcategory":"Office",
            "type":"Public Place"
        }
    ],
    "sg:phone":"+1 214 303 1100",
    "sg:postcode":"75201",
    "sg:province":"TX",
    "sg:website":"www.johncarona.net",
    "wof:name":"John J Carona State Senator",
    "wof:placetype":"venue"
},
  "geometry": {"coordinates":[-96.79951800000001,32.794495],"type":"Point"}
}