{
  "type": "Feature",
  "properties": {
    "iso:country":"US",
    "sg:address":"17160 Pop Mckenzie Rd",
    "sg:city":"Flint",
    "sg:classifiers":[
        {
            "category":"Restaurant",
            "type":"Food & Drink"
        },
        {
            "category":"Exhibition Hall",
            "type":"Public Place"
        }
    ],
    "sg:phone":"+1 903 534 6599",
    "sg:postcode":"75762",
    "sg:province":"TX",
    "sg:tags":[
        "halls",
        "ballroom",
        "auditorium"
    ],
    "wof:name":"Pine Cove Ranch Dining Hall",
    "wof:placetype":"venue"
},
  "geometry": {"coordinates":[-95.46010800000001,32.24437],"type":"Point"}
}