{
  "type": "Feature",
  "properties": {
    "iso:country":"US",
    "sg:address":"4403 Shoal Creek Blvd",
    "sg:city":"Austin",
    "sg:classifiers":[
        {
            "category":"Social Services",
            "subcategory":"Child Care",
            "type":"Services"
        }
    ],
    "sg:phone":"+1 512 374 9646",
    "sg:postcode":"78756",
    "sg:province":"TX",
    "sg:tags":[
        "day"
    ],
    "wof:name":"Tot Tot",
    "wof:placetype":"venue"
},
  "geometry": {"coordinates":[-97.747758,30.314263],"type":"Point"}
}