{
  "type": "Feature",
  "properties": {
    "iso:country":"US",
    "sg:address":"1114 Crescent Hill",
    "sg:city":"San Antonio",
    "sg:classifiers":[
        {
            "category":"Building & Trades",
            "subcategory":"Construction",
            "type":"Services"
        }
    ],
    "sg:phone":"+1 210 674 4795",
    "sg:postcode":"78253",
    "sg:province":"TX",
    "sg:tags":[
        "contractor"
    ],
    "wof:name":"D&D Tile Inc",
    "wof:placetype":"venue"
},
  "geometry": {"coordinates":[-98.764843,29.448809],"type":"Point"}
}