{
  "type": "Feature",
  "properties": {
    "iso:country":"US",
    "sg:address":"432 E Mulberry St",
    "sg:city":"Angleton",
    "sg:classifiers":[
        {
            "category":"Government",
            "subcategory":"Office",
            "type":"Public Place"
        }
    ],
    "sg:phone":"+1 979 864 1484",
    "sg:postcode":"77515",
    "sg:province":"TX",
    "sg:tags":[
        "county",
        "program",
        "health"
    ],
    "wof:name":"Brazoria County Health Unit",
    "wof:placetype":"venue"
},
  "geometry": {"coordinates":[-95.428237,29.164415],"type":"Point"}
}