{
  "type": "Feature",
  "properties": {
    "iso:country":"US",
    "sg:address":"18539 Keenan Cut Off Rd",
    "sg:city":"Montgomery",
    "sg:classifiers":[
        {
            "category":"Building & Trades",
            "subcategory":"Construction",
            "type":"Services"
        }
    ],
    "sg:phone":"+1 936 449 4860",
    "sg:postcode":"77316",
    "sg:province":"TX",
    "sg:tags":[
        "contractor"
    ],
    "wof:name":"Complete Masonry",
    "wof:placetype":"venue"
},
  "geometry": {"coordinates":[-95.65210999999999,30.325187],"type":"Point"}
}