{
  "type": "Feature",
  "properties": {
    "iso:country":"US",
    "sg:address":"12606 Hunters Chase Dr",
    "sg:city":"Austin",
    "sg:classifiers":[
        {
            "category":"Arts & Performance",
            "subcategory":"Theater",
            "type":"Entertainment"
        }
    ],
    "sg:phone":"+1 512 257 7755",
    "sg:postcode":"78729",
    "sg:province":"TX",
    "sg:tags":[
        "balloon",
        "painting",
        "face"
    ],
    "wof:name":"Rosey Curly & Co",
    "wof:placetype":"venue"
},
  "geometry": {"coordinates":[-97.769189,30.448153],"type":"Point"}
}