{
  "type": "Feature",
  "properties": {
    "iso:country":"US",
    "sg:address":"5870 Ranchester Dr",
    "sg:city":"Houston",
    "sg:classifiers":[
        {
            "category":"Professional",
            "subcategory":"Management & Consulting",
            "type":"Services"
        }
    ],
    "sg:phone":"+1 713 772 1181",
    "sg:postcode":"77036",
    "sg:province":"TX",
    "wof:name":"Spa Goez Healthy Center",
    "wof:placetype":"venue"
},
  "geometry": {"coordinates":[-95.54812,29.715184],"type":"Point"}
}