{
  "type": "Feature",
  "properties": {
    "iso:country":"US",
    "sg:address":"301 Hooks Ave",
    "sg:city":"Donna",
    "sg:classifiers":[
        {
            "category":"Food & Beverages",
            "subcategory":"Bakery",
            "type":"Retail Goods"
        }
    ],
    "sg:phone":"+1 956 464 7012",
    "sg:postcode":"78537",
    "sg:province":"TX",
    "wof:name":"Donna Tortilleria & Bakery",
    "wof:placetype":"venue"
},
  "geometry": {"coordinates":[-98.059933,26.171892],"type":"Point"}
}