{
  "type": "Feature",
  "properties": {
    "iso:country":"US",
    "sg:address":"2007 Rice Dr",
    "sg:city":"Levelland",
    "sg:classifiers":[
        {
            "category":"Personal",
            "type":"Services"
        }
    ],
    "sg:phone":"+1 806 894 4445",
    "sg:postcode":"79336",
    "sg:province":"TX",
    "wof:name":"Womans Intuition",
    "wof:placetype":"venue"
},
  "geometry": {"coordinates":[-102.36648700000001,33.571989],"type":"Point"}
}