{
  "type": "Feature",
  "properties": {
    "iso:country":"US",
    "sg:address":"2616 Chalk Hill Rd",
    "sg:city":"Dallas",
    "sg:classifiers":[
        {
            "category":"Government",
            "subcategory":"Fire Station",
            "type":"Public Place"
        }
    ],
    "sg:phone":"+1 214 670 5085",
    "sg:postcode":"75212",
    "sg:province":"TX",
    "sg:tags":[
        "protection"
    ],
    "wof:name":"Fire Station 16",
    "wof:placetype":"venue"
},
  "geometry": {"coordinates":[-96.904166,32.773886],"type":"Point"}
}