{
  "type": "Feature",
  "properties": {
    "iso:country":"US",
    "sg:address":"316 E 7th St",
    "sg:city":"Kemp",
    "sg:classifiers":[
        {
            "category":"Autos & Motor Vehicles",
            "subcategory":"Auto Supplies",
            "type":"Retail Goods"
        },
        {
            "category":"Shopping",
            "subcategory":"Computers & Home Electronics",
            "type":"Retail Goods"
        }
    ],
    "sg:phone":"+1 903 432 2115",
    "sg:postcode":"75143",
    "sg:province":"TX",
    "sg:tags":[
        "automobile",
        "stereo",
        "radio",
        "product",
        "mfg"
    ],
    "wof:name":"Durham's Car Audio",
    "wof:placetype":"venue"
},
  "geometry": {"coordinates":[-96.23018399999999,32.444407],"type":"Point"}
}