{
  "type": "Feature",
  "properties": {
    "iso:country":"US",
    "sg:address":"817 Fairview St",
    "sg:city":"Houston",
    "sg:classifiers":[
        {
            "category":"Bars & Pubs",
            "type":"Food & Drink"
        }
    ],
    "sg:phone":"+1 713 528 9204",
    "sg:postcode":"77006",
    "sg:province":"TX",
    "sg:tags":[
        "drinking"
    ],
    "wof:name":"Cousins Subs",
    "wof:placetype":"venue"
},
  "geometry": {"coordinates":[-95.39032400000001,29.748046],"type":"Point"}
}