{
  "type": "Feature",
  "properties": {
    "iso:country":"US",
    "sg:address":"606 S 23rd St",
    "sg:city":"Donna",
    "sg:classifiers":[
        {
            "category":"Retail",
            "subcategory":"Repair Shop",
            "type":"Services"
        }
    ],
    "sg:phone":"+1 956 464 3131",
    "sg:postcode":"78537",
    "sg:province":"TX",
    "sg:tags":[
        "upholsterer"
    ],
    "wof:name":"Gus's Upholstery",
    "wof:placetype":"venue"
},
  "geometry": {"coordinates":[-98.040509,26.160877],"type":"Point"}
}