{
  "type": "Feature",
  "properties": {
    "iso:country":"US",
    "sg:address":"3641 Holmes St",
    "sg:city":"Dallas",
    "sg:classifiers":[
        {
            "category":"Shopping",
            "subcategory":"Mobile Phones",
            "type":"Retail Goods"
        }
    ],
    "sg:phone":"+1 214 437 2549",
    "sg:postcode":"75215",
    "sg:province":"TX",
    "wof:name":"Dfw Wireless",
    "wof:placetype":"venue"
},
  "geometry": {"coordinates":[-96.77267999999999,32.755765],"type":"Point"}
}