{
  "type": "Feature",
  "properties": {
    "iso:country":"US",
    "sg:address":"13330 Duke of York Ln",
    "sg:city":"Houston",
    "sg:classifiers":[
        {
            "category":"Social Services",
            "subcategory":"Child Care",
            "type":"Services"
        }
    ],
    "sg:phone":"+1 281 894 2917",
    "sg:postcode":"77070",
    "sg:province":"TX",
    "wof:name":"Linda Jo Lazenby",
    "wof:placetype":"venue"
},
  "geometry": {"coordinates":[-95.578779,29.967966],"type":"Point"}
}