{
  "type": "Feature",
  "properties": {
    "iso:country":"US",
    "sg:address":"1330 E 8th St",
    "sg:city":"Odessa",
    "sg:classifiers":[
        {
            "category":"Insurance",
            "subcategory":"Insurance Agent",
            "type":"Services"
        }
    ],
    "sg:phone":"+1 432 332 8226",
    "sg:postcode":"79761",
    "sg:province":"TX",
    "wof:name":"American National Insurance Co",
    "wof:placetype":"venue"
},
  "geometry": {"coordinates":[-102.35762699999999,31.858095],"type":"Point"}
}