{
  "type": "Feature",
  "properties": {
    "iso:country":"US",
    "sg:address":"5103 Oak Tree Cir",
    "sg:city":"Dallas",
    "sg:classifiers":[
        {
            "category":"Professional",
            "type":"Services"
        }
    ],
    "sg:phone":"+1 972 381 8288",
    "sg:postcode":"75287",
    "sg:province":"TX",
    "wof:name":"Gabriel Goncalves",
    "wof:placetype":"venue"
},
  "geometry": {"coordinates":[-96.818798,32.996755],"type":"Point"}
}