{
  "type": "Feature",
  "properties": {
    "iso:country":"US",
    "sg:address":"605 Avalon Dr",
    "sg:city":"Seagoville",
    "sg:classifiers":[
        {
            "category":"Health Services",
            "subcategory":"Dentist",
            "type":"Services"
        }
    ],
    "sg:phone":"+1 972 287 5513",
    "sg:postcode":"75159",
    "sg:province":"TX",
    "wof:name":"Seagoville Dental Clinic",
    "wof:placetype":"venue"
},
  "geometry": {"coordinates":[-96.541067,32.64645],"type":"Point"}
}