{
  "type": "Feature",
  "properties": {
    "iso:country":"US",
    "sg:address":"489 Lincolnshire Dr",
    "sg:city":"San Antonio",
    "sg:classifiers":[
        {
            "category":"Organizations",
            "subcategory":"Religious Organization",
            "type":"Services"
        }
    ],
    "sg:phone":"+1 210 337 4634",
    "sg:postcode":"78220",
    "sg:province":"TX",
    "sg:tags":[
        "church"
    ],
    "wof:name":"Living Waters Baptist Church",
    "wof:placetype":"venue"
},
  "geometry": {"coordinates":[-98.431904,29.411246],"type":"Point"}
}