{
  "type": "Feature",
  "properties": {
    "iso:country":"US",
    "sg:address":"1416 Co Rd 930",
    "sg:city":"Mexia",
    "sg:classifiers":[
        {
            "category":"Personal",
            "subcategory":"Beauty Salon",
            "type":"Services"
        }
    ],
    "sg:phone":"+1 254 562 5809",
    "sg:postcode":"76667",
    "sg:province":"TX",
    "sg:tags":[
        "shop"
    ],
    "wof:name":"Nail Masters",
    "wof:placetype":"venue"
},
  "geometry": {"coordinates":[-96.392684,31.684103],"type":"Point"}
}