{
  "type": "Feature",
  "properties": {
    "iso:country":"US",
    "sg:address":"110 Hwy 332",
    "sg:city":"Lake Jackson",
    "sg:classifiers":[
        {
            "category":"Restaurant",
            "type":"Food & Drink"
        }
    ],
    "sg:phone":"+1 979 297 6330",
    "sg:postcode":"77566",
    "sg:province":"TX",
    "sg:tags":[
        "eating"
    ],
    "wof:name":"Ptex Enterprises",
    "wof:placetype":"venue"
},
  "geometry": {"coordinates":[-95.420895,29.010621],"type":"Point"}
}