{
  "type": "Feature",
  "properties": {
    "iso:country":"US",
    "sg:address":"1120 Harbor Haven St",
    "sg:city":"Southlake",
    "sg:classifiers":[
        {
            "category":"Organizations",
            "subcategory":"Non-profit Organization",
            "type":"Services"
        }
    ],
    "sg:phone":"+1 817 416 9000",
    "sg:postcode":"76092",
    "sg:province":"TX",
    "sg:tags":[
        "charitable",
        "institution"
    ],
    "wof:name":"Hoap Foundation",
    "wof:placetype":"venue"
},
  "geometry": {"coordinates":[-97.133743,32.983992],"type":"Point"}
}