{
  "type": "Feature",
  "properties": {
    "iso:country":"US",
    "sg:address":"2419 Haggar Ave",
    "sg:city":"Weslaco",
    "sg:classifiers":[
        {
            "category":"Education",
            "subcategory":"Junior College",
            "type":"Public Place"
        }
    ],
    "sg:phone":"+1 956 969 1564",
    "sg:postcode":"78596",
    "sg:province":"TX",
    "sg:tags":[
        "technical",
        "institute"
    ],
    "sg:website":"www.stvt.net",
    "wof:name":"South Tech Vo Tech School",
    "wof:placetype":"venue"
},
  "geometry": {"coordinates":[-97.967905,26.172229],"type":"Point"}
}