{
  "type": "Feature",
  "properties": {
    "iso:country":"US",
    "sg:address":"10828 Dennis Rd",
    "sg:city":"Dallas",
    "sg:classifiers":[
        {
            "category":"Professional",
            "subcategory":"Business Services",
            "type":"Services"
        }
    ],
    "sg:phone":"+1 972 481 9732",
    "sg:postcode":"75229",
    "sg:province":"TX",
    "sg:tags":[
        "translator",
        "interpreter"
    ],
    "wof:name":"Dolex Dollar Express",
    "wof:placetype":"venue"
},
  "geometry": {"coordinates":[-96.88130200000001,32.899159],"type":"Point"}
}