{
  "type": "Feature",
  "properties": {
    "iso:country":"US",
    "sg:address":"701 Hwy 288B",
    "sg:city":"Clute",
    "sg:classifiers":[
        {
            "category":"Freight",
            "type":"Transportation"
        }
    ],
    "sg:phone":"+1 979 265 2563",
    "sg:postcode":"77531",
    "sg:province":"TX",
    "sg:tags":[
        "operator",
        "trucking"
    ],
    "wof:name":"Service Lines",
    "wof:placetype":"venue"
},
  "geometry": {"coordinates":[-95.39826100000001,29.032768],"type":"Point"}
}