{
  "type": "Feature",
  "properties": {
    "iso:country":"US",
    "sg:address":"1400 Rock Island Rd",
    "sg:city":"Irving",
    "sg:classifiers":[
        {
            "category":"Food & Beverages",
            "subcategory":"Groceries & Convenience Stores",
            "type":"Retail Goods"
        }
    ],
    "sg:phone":"+1 972 254 7846",
    "sg:postcode":"75060",
    "sg:province":"TX",
    "wof:name":"Circle S Food Stop 1",
    "wof:placetype":"venue"
},
  "geometry": {"coordinates":[-96.962799,32.815201],"type":"Point"}
}