{
  "type": "Feature",
  "properties": {
    "iso:country":"US",
    "sg:address":"405 Lewis Ln",
    "sg:city":"Keene",
    "sg:classifiers":[
        {
            "category":"Home & Garden",
            "subcategory":"Household Appliances",
            "type":"Retail Goods"
        },
        {
            "category":"Building & Trades",
            "subcategory":"Construction",
            "type":"Services"
        },
        {
            "category":"Building & Trades",
            "subcategory":"Electrical",
            "type":"Services"
        }
    ],
    "sg:phone":"+1 817 645 8011",
    "sg:postcode":"76059",
    "sg:province":"TX",
    "sg:tags":[
        "major",
        "industrial",
        "electrician",
        "electric",
        "specialty",
        "system",
        "appliances-small",
        "heating",
        "contractors-commercial",
        "contractor",
        "air conditioning"
    ],
    "sg:website":"http://www.putnamservice.com",
    "wof:name":"Putnam Service",
    "wof:placetype":"venue"
},
  "geometry": {"coordinates":[-97.332595,32.399264],"type":"Point"}
}