{
  "type": "Feature",
  "properties": {
    "iso:country":"US",
    "sg:address":"1401 Royal Pkwy",
    "sg:city":"Euless",
    "sg:classifiers":[
        {
            "category":"Shopping",
            "type":"Retail Goods"
        }
    ],
    "sg:phone":"+1 817 358 6800",
    "sg:postcode":"76040",
    "sg:province":"TX",
    "sg:tags":[
        "merchandise"
    ],
    "wof:name":"Brace Yourself",
    "wof:placetype":"venue"
},
  "geometry": {"coordinates":[-97.11884999999999,32.821912],"type":"Point"}
}