{
  "type": "Feature",
  "properties": {
    "iso:country":"US",
    "sg:address":"4408 Rittiman Rd",
    "sg:city":"San Antonio",
    "sg:classifiers":[
        {
            "category":"Insurance",
            "subcategory":"Insurance Agent",
            "type":"Services"
        }
    ],
    "sg:phone":"+1 210 824 0360",
    "sg:postcode":"78209",
    "sg:province":"TX",
    "wof:name":"Rick Cantara State Farm",
    "wof:placetype":"venue"
},
  "geometry": {"coordinates":[-98.407067,29.484002],"type":"Point"}
}