{
  "type": "Feature",
  "properties": {
    "iso:country":"US",
    "sg:address":"128 Fairview St",
    "sg:city":"Arlington",
    "sg:classifiers":[
        {
            "category":"Professional",
            "subcategory":"Engineering",
            "type":"Services"
        },
        {
            "category":"Home & Garden",
            "subcategory":"Building Materials",
            "type":"Retail Goods"
        },
        {
            "category":"Building & Trades",
            "subcategory":"Construction",
            "type":"Services"
        }
    ],
    "sg:phone":"+1 817 265 1191",
    "sg:postcode":"76010",
    "sg:province":"TX",
    "sg:tags":[
        "system",
        "specialty",
        "heating",
        "contractor",
        "equipment",
        "air conditioning"
    ],
    "sg:website":"http://find.trane.com/tcs-dealer-402350?utm_source=YP&utm_medium=banner&utm_campaign=TL",
    "wof:name":"Houk Air Conditioning, Inc.",
    "wof:placetype":"venue"
},
  "geometry": {"coordinates":[-97.08547,32.737359],"type":"Point"}
}