{
  "type": "Feature",
  "properties": {
    "iso:country":"US",
    "sg:address":"12719 Pathfinder Ln",
    "sg:city":"San Antonio",
    "sg:classifiers":[
        {
            "category":"Professional",
            "subcategory":"Business Services",
            "type":"Services"
        }
    ],
    "sg:phone":"+1 210 493 5359",
    "sg:postcode":"78230",
    "sg:province":"TX",
    "wof:name":"Progressive Sales & Service",
    "wof:placetype":"venue"
},
  "geometry": {"coordinates":[-98.56249699999999,29.559404],"type":"Point"}
}