{
  "type": "Feature",
  "properties": {
    "iso:country":"US",
    "sg:address":"7175 Fair Oaks Ave",
    "sg:city":"Dallas",
    "sg:classifiers":[
        {
            "category":"Professional",
            "subcategory":"Detective & Security Services",
            "type":"Services"
        }
    ],
    "sg:phone":"+1 214 891 0206",
    "sg:postcode":"75231",
    "sg:province":"TX",
    "sg:tags":[
        "system"
    ],
    "wof:name":"Lakewood Alarm",
    "wof:placetype":"venue"
},
  "geometry": {"coordinates":[-96.75753400000001,32.873399],"type":"Point"}
}