{
  "type": "Feature",
  "properties": {
    "iso:country":"US",
    "sg:address":"4101 Dauphine Dr",
    "sg:city":"Austin",
    "sg:classifiers":[
        {
            "category":"Professional",
            "subcategory":"Business Services",
            "type":"Services"
        }
    ],
    "sg:phone":"+1 512 833 7972",
    "sg:postcode":"78727",
    "sg:province":"TX",
    "wof:name":"Three & ASAP",
    "wof:placetype":"venue"
},
  "geometry": {"coordinates":[-97.72138099999999,30.420999],"type":"Point"}
}