{
  "type": "Feature",
  "properties": {
    "iso:country":"US",
    "sg:address":"8201 Lemmon Ave",
    "sg:city":"Dallas",
    "sg:classifiers":[
        {
            "category":"Professional",
            "type":"Services"
        }
    ],
    "sg:phone":"+1 972 559 7000",
    "sg:postcode":"75209",
    "sg:province":"TX",
    "sg:tags":[
        "cargo",
        "package",
        "express",
        "air"
    ],
    "wof:name":"Associated Air Center",
    "wof:placetype":"venue"
},
  "geometry": {"coordinates":[-96.844521,32.852901],"type":"Point"}
}