{
  "type": "Feature",
  "properties": {
    "iso:country":"US",
    "sg:address":"1510 W 35th St Cutoff",
    "sg:city":"Austin",
    "sg:classifiers":[
        {
            "category":"Personal",
            "subcategory":"Beauty Salon",
            "type":"Services"
        }
    ],
    "sg:phone":"+1 512 371 1818",
    "sg:postcode":"78731",
    "sg:province":"TX",
    "wof:name":"Bradz Beauty Merchant",
    "wof:placetype":"venue"
},
  "geometry": {"coordinates":[-97.750376,30.307112],"type":"Point"}
}