{
  "type": "Feature",
  "properties": {
    "iso:country":"US",
    "sg:address":"704 Pasadena Blvd",
    "sg:city":"Pasadena",
    "sg:classifiers":[
        {
            "category":"Insurance",
            "subcategory":"Hazard Insurance",
            "type":"Services"
        },
        {
            "category":"Professional",
            "subcategory":"Business Services",
            "type":"Services"
        }
    ],
    "sg:phone":"+1 713 941 2000",
    "sg:postcode":"77506",
    "sg:province":"TX",
    "sg:tags":[
        "bond"
    ],
    "wof:name":"Claude Thompson Bonding Co",
    "wof:placetype":"venue"
},
  "geometry": {"coordinates":[-95.20106199999999,29.701812],"type":"Point"}
}