{
  "type": "Feature",
  "properties": {
    "iso:country":"US",
    "sg:address":"5005 Sycene Ct",
    "sg:city":"El Paso",
    "sg:classifiers":[
        {
            "category":"Communications",
            "type":"Services"
        }
    ],
    "sg:phone":"+1 915 821 3929",
    "sg:postcode":"79924",
    "sg:province":"TX",
    "wof:name":"Orbiting Communications",
    "wof:placetype":"venue"
},
  "geometry": {"coordinates":[-106.42351499999999,31.918556],"type":"Point"}
}