{
  "type": "Feature",
  "properties": {
    "iso:country":"US",
    "sg:address":"3315 Cherrywood Rd",
    "sg:city":"Austin",
    "sg:classifiers":[
        {
            "category":"Wholesale",
            "subcategory":"Non-durable Goods",
            "type":"Manufacturing & Wholesale Goods"
        }
    ],
    "sg:phone":"+1 512 632 6970",
    "sg:postcode":"78722",
    "sg:province":"TX",
    "wof:name":"Twin Feathers Trading Co",
    "wof:placetype":"venue"
},
  "geometry": {"coordinates":[-97.715086,30.289308],"type":"Point"}
}