{
  "type": "Feature",
  "properties": {
    "iso:country":"US",
    "sg:address":"15714 Brook Forest Dr",
    "sg:city":"Houston",
    "sg:classifiers":[
        {
            "category":"Organizations",
            "subcategory":"Membership Organization",
            "type":"Services"
        }
    ],
    "sg:phone":"+1 281 488 5977",
    "sg:postcode":"77059",
    "sg:province":"TX",
    "wof:name":"Jaggi Hardevi Foundation",
    "wof:placetype":"venue"
},
  "geometry": {"coordinates":[-95.11420200000001,29.585769],"type":"Point"}
}