{
  "type": "Feature",
  "properties": {
    "iso:country":"US",
    "sg:address":"119 Savanah Dr",
    "sg:city":"Victoria",
    "sg:classifiers":[
        {
            "category":"Shopping",
            "subcategory":"Crafts & Fabrics",
            "type":"Retail Goods"
        }
    ],
    "sg:phone":"+1 361 575 4702",
    "sg:postcode":"77904",
    "sg:province":"TX",
    "sg:tags":[
        "sewing"
    ],
    "wof:name":"Dancing Needle Designs",
    "wof:placetype":"venue"
},
  "geometry": {"coordinates":[-96.983378,28.847321],"type":"Point"}
}