{
  "type": "Feature",
  "properties": {
    "iso:country":"US",
    "sg:address":"3400 W Marshall Ave",
    "sg:city":"Longview",
    "sg:classifiers":[
        {
            "category":"Place Of Worship",
            "subcategory":"Church",
            "type":"Public Place"
        },
        {
            "category":"Place Of Worship",
            "type":"Public Place"
        }
    ],
    "sg:phone":"+1 903 212 7770",
    "sg:postcode":"75604",
    "sg:province":"TX",
    "sg:tags":[
        "churches-full",
        "denomination",
        "churches-interdenominational",
        "gospel",
        "churches-charismatic",
        "churches-various",
        "interdenominational"
    ],
    "sg:website":"http://pathwaylongview.com",
    "wof:name":"Pathway Church",
    "wof:placetype":"venue"
},
  "geometry": {"coordinates":[-94.79097,32.506882],"type":"Point"}
}