{
  "type": "Feature",
  "properties": {
    "iso:country":"US",
    "sg:address":"2319 Clover Ridge Dr",
    "sg:city":"Cedar Park",
    "sg:classifiers":[
        {
            "category":"Professional",
            "subcategory":"Management & Consulting",
            "type":"Services"
        }
    ],
    "sg:phone":"+1 512 250 1341",
    "sg:postcode":"78613",
    "sg:province":"TX",
    "sg:tags":[
        "retail",
        "direct",
        "sales"
    ],
    "wof:name":"Huff & Puff Creations",
    "wof:placetype":"venue"
},
  "geometry": {"coordinates":[-97.82961299999999,30.474595],"type":"Point"}
}