{
  "type": "Feature",
  "properties": {
    "iso:country":"US",
    "sg:address":"9555 Callaghan Rd",
    "sg:city":"San Antonio",
    "sg:classifiers":[
        {
            "category":"Professional",
            "subcategory":"Management & Consulting",
            "type":"Services"
        }
    ],
    "sg:phone":"+1 210 342 1208",
    "sg:postcode":"78230",
    "sg:province":"TX",
    "sg:tags":[
        "retail",
        "direct",
        "sales"
    ],
    "wof:name":"Hal Martin Studios",
    "wof:placetype":"venue"
},
  "geometry": {"coordinates":[-98.53760800000001,29.526118],"type":"Point"}
}