{
  "type": "Feature",
  "properties": {
    "iso:country":"US",
    "sg:address":"1513 Ave H",
    "sg:city":"Levelland",
    "sg:classifiers":[
        {
            "category":"Restaurant",
            "type":"Food & Drink"
        }
    ],
    "sg:phone":"+1 806 894 9177",
    "sg:postcode":"79336",
    "sg:province":"TX",
    "sg:tags":[
        "bakery",
        "retail",
        "eating"
    ],
    "wof:name":"Kemps Mr Treat Doughnut No 2",
    "wof:placetype":"venue"
},
  "geometry": {"coordinates":[-102.377414,33.576761],"type":"Point"}
}