{
  "type": "Feature",
  "properties": {
    "iso:country":"US",
    "sg:address":"1007 E Lee St",
    "sg:city":"Rotan",
    "sg:classifiers":[
        {
            "category":"Personal",
            "subcategory":"Beauty Salon",
            "type":"Services"
        }
    ],
    "sg:phone":"+1 325 735 1100",
    "sg:postcode":"79546",
    "sg:province":"TX",
    "wof:name":"Southern Touch Salon",
    "wof:placetype":"venue"
},
  "geometry": {"coordinates":[-100.457324,32.86041],"type":"Point"}
}