{
  "type": "Feature",
  "properties": {
    "iso:country":"US",
    "sg:address":"4810 Landrun Ln",
    "sg:city":"Arlington",
    "sg:classifiers":[
        {
            "category":"Shopping",
            "subcategory":"Hobbies, Toys, & Games",
            "type":"Retail Goods"
        }
    ],
    "sg:phone":"+1 817 483 2259",
    "sg:postcode":"76017",
    "sg:province":"TX",
    "wof:name":"Waigand Trains",
    "wof:placetype":"venue"
},
  "geometry": {"coordinates":[-97.18469,32.65755],"type":"Point"}
}