{
  "type": "Feature",
  "properties": {
    "iso:country":"US",
    "sg:address":"10107 Inwood Shadows St",
    "sg:city":"Houston",
    "sg:classifiers":[
        {
            "category":"Social Services",
            "subcategory":"Child Care",
            "type":"Services"
        }
    ],
    "sg:phone":"+1 281 448 7522",
    "sg:postcode":"77088",
    "sg:province":"TX",
    "wof:name":"For Kids Daycare",
    "wof:placetype":"venue"
},
  "geometry": {"coordinates":[-95.485766,29.887419],"type":"Point"}
}