{
  "type": "Feature",
  "properties": {
    "iso:country":"US",
    "sg:address":"801 S 1st St",
    "sg:city":"Crockett",
    "sg:classifiers":[
        {
            "category":"Home & Garden",
            "subcategory":"Building Materials",
            "type":"Retail Goods"
        }
    ],
    "sg:phone":"+1 936 544 2138",
    "sg:postcode":"75835",
    "sg:province":"TX",
    "sg:tags":[
        "lumber"
    ],
    "wof:name":"Stowe Lumber Co",
    "wof:placetype":"venue"
},
  "geometry": {"coordinates":[-95.46372599999999,31.305021],"type":"Point"}
}