{
  "type": "Feature",
  "properties": {
    "iso:country":"US",
    "sg:address":"1647 Co Rd 229",
    "sg:city":"Schulenburg",
    "sg:classifiers":[
        {
            "category":"Building & Trades",
            "subcategory":"Landscaping Services",
            "type":"Services"
        }
    ],
    "sg:phone":"+1 713 829 0879",
    "sg:postcode":"78956",
    "sg:province":"TX",
    "sg:tags":[
        "landscape"
    ],
    "wof:name":"Canadas Tractor Inc",
    "wof:placetype":"venue"
},
  "geometry": {"coordinates":[-96.965942,29.59022],"type":"Point"}
}