{
  "type": "Feature",
  "properties": {
    "iso:country":"US",
    "sg:address":"17530 Henderson Pass",
    "sg:city":"San Antonio",
    "sg:classifiers":[
        {
            "category":"Recreation",
            "type":"Entertainment"
        }
    ],
    "sg:phone":"+1 210 490 9550",
    "sg:postcode":"78232",
    "sg:province":"TX",
    "sg:tags":[
        "skating",
        "rink"
    ],
    "wof:name":"Northwoods Ice LLC",
    "wof:placetype":"venue"
},
  "geometry": {"coordinates":[-98.465547,29.603717],"type":"Point"}
}