{
  "type": "Feature",
  "properties": {
    "iso:country":"US",
    "sg:address":"100 Houston St",
    "sg:city":"Barry",
    "sg:classifiers":[
        {
            "category":"Utilities",
            "subcategory":"Fuel Oil & Lpg",
            "type":"Services"
        }
    ],
    "sg:phone":"+1 903 695 4352",
    "sg:postcode":"75102",
    "sg:province":"TX",
    "sg:tags":[
        "liquefied",
        "gas",
        "petroleum"
    ],
    "wof:name":"Longhorn Propane Gas Service",
    "wof:placetype":"venue"
},
  "geometry": {"coordinates":[-96.636393,32.099818],"type":"Point"}
}