{
  "type": "Feature",
  "properties": {
    "iso:country":"US",
    "sg:address":"4840 W Panther Creek Dr",
    "sg:city":"Spring",
    "sg:classifiers":[
        {
            "category":"Health Services",
            "subcategory":"Doctor",
            "type":"Services"
        }
    ],
    "sg:phone":"+1 281 364 8130",
    "sg:postcode":"77381",
    "sg:province":"TX",
    "sg:tags":[
        "physician",
        "family",
        "practice",
        "surgeons",
        "medicine",
        "surgeon"
    ],
    "wof:name":"Robert, J Moore",
    "wof:placetype":"venue"
},
  "geometry": {"coordinates":[-95.501885,30.166835],"type":"Point"}
}