{
  "type": "Feature",
  "properties": {
    "iso:country":"US",
    "sg:address":"5307 US Hwy 69",
    "sg:city":"Pollok",
    "sg:classifiers":[
        {
            "category":"Utilities",
            "subcategory":"Water",
            "type":"Services"
        }
    ],
    "sg:phone":"+1 936 853 2354",
    "sg:postcode":"75969",
    "sg:province":"TX",
    "sg:tags":[
        "company",
        "sewage"
    ],
    "wof:name":"Central Water Works",
    "wof:placetype":"venue"
},
  "geometry": {"coordinates":[-94.794235,31.402153],"type":"Point"}
}