{
  "type": "Feature",
  "properties": {
    "iso:country":"US",
    "sg:address":"800 W 4th St",
    "sg:city":"Odessa",
    "sg:classifiers":[
        {
            "category":"Education",
            "subcategory":"Library",
            "type":"Public Place"
        }
    ],
    "sg:phone":"+1 432 335 5130",
    "sg:postcode":"79763",
    "sg:province":"TX",
    "wof:name":"Ttuhsc Medical Library",
    "wof:placetype":"venue"
},
  "geometry": {"coordinates":[-102.37629699999999,31.843691],"type":"Point"}
}