{
  "type": "Feature",
  "properties": {
    "iso:country":"US",
    "sg:address":"113 Bess St",
    "sg:city":"New Braunfels",
    "sg:classifiers":[
        {
            "category":"Food & Beverages",
            "subcategory":"Bakery",
            "type":"Retail Goods"
        }
    ],
    "sg:phone":"+1 830 625 9797",
    "sg:postcode":"78130",
    "sg:province":"TX",
    "sg:tags":[
        "doughnut"
    ],
    "wof:name":"Donut Palace",
    "wof:placetype":"venue"
},
  "geometry": {"coordinates":[-98.049942,29.65383],"type":"Point"}
}