{
  "type": "Feature",
  "properties": {
    "iso:country":"US",
    "sg:address":"780 Porter St",
    "sg:city":"Beaumont",
    "sg:classifiers":[
        {
            "category":"Organizations",
            "subcategory":"Religious Organization",
            "type":"Services"
        }
    ],
    "sg:phone":"+1 409 833 6089",
    "sg:postcode":"77701",
    "sg:province":"TX",
    "sg:tags":[
        "church"
    ],
    "wof:name":"Blessed Sacrament Church",
    "wof:placetype":"venue"
},
  "geometry": {"coordinates":[-94.087625,30.064869],"type":"Point"}
}