{
  "type": "Feature",
  "properties": {
    "iso:country":"US",
    "sg:address":"1503 Giddings St",
    "sg:city":"Wichita Falls",
    "sg:classifiers":[
        {
            "category":"Retail",
            "subcategory":"Repair Shop",
            "type":"Services"
        }
    ],
    "sg:phone":"+1 940 767 4802",
    "sg:postcode":"76309",
    "sg:province":"TX",
    "wof:name":"Dill Microwave Clinic",
    "wof:placetype":"venue"
},
  "geometry": {"coordinates":[-98.51390600000001,33.896283],"type":"Point"}
}