{
  "type": "Feature",
  "properties": {
    "iso:country":"US",
    "sg:address":"4107 Bay Shore Dr",
    "sg:city":"Missouri City",
    "sg:classifiers":[
        {
            "category":"Building & Trades",
            "subcategory":"Construction",
            "type":"Services"
        }
    ],
    "sg:phone":"+1 281 499 2484",
    "sg:postcode":"77459",
    "sg:province":"TX",
    "sg:tags":[
        "home",
        "builder"
    ],
    "wof:name":"Perry Homes Bright Water Cnstr",
    "wof:placetype":"venue"
},
  "geometry": {"coordinates":[-95.56811999999999,29.588058],"type":"Point"}
}