{
  "type": "Feature",
  "properties": {
    "iso:country":"US",
    "sg:address":"9205 Skillman St Ste 112",
    "sg:city":"Dallas",
    "sg:classifiers":[
        {
            "category":"Real Estate",
            "subcategory":"Real Estate Services",
            "type":"Services"
        }
    ],
    "sg:phone":"+1 214 363 9184",
    "sg:postcode":"75243",
    "sg:province":"TX",
    "sg:tags":[
        "management",
        "property"
    ],
    "wof:name":"Teel Enterprises Inc",
    "wof:placetype":"venue"
},
  "geometry": {"coordinates":[-96.71630500000001,32.904108],"type":"Point"}
}