{
  "type": "Feature",
  "properties": {
    "iso:country":"US",
    "sg:address":"3110 Founders Green Cir",
    "sg:city":"Pearland",
    "sg:classifiers":[
        {
            "category":"Retail",
            "subcategory":"Auto Repair",
            "type":"Services"
        }
    ],
    "sg:phone":"+1 281 485 1949",
    "sg:postcode":"77581",
    "sg:province":"TX",
    "sg:tags":[
        "body",
        "automobile",
        "painting",
        "repairing"
    ],
    "wof:name":"Bow Glass",
    "wof:placetype":"venue"
},
  "geometry": {"coordinates":[-95.26818,29.567256],"type":"Point"}
}