{
  "type": "Feature",
  "properties": {
    "iso:country":"US",
    "sg:address":"505 Bedford Rd",
    "sg:city":"Bedford",
    "sg:classifiers":[
        {
            "category":"Recreation",
            "type":"Entertainment"
        }
    ],
    "sg:phone":"+1 972 751 1152",
    "sg:postcode":"76022",
    "sg:province":"TX",
    "sg:tags":[
        "charter",
        "boat"
    ],
    "wof:name":"Longhorn Yacht Club Inc",
    "wof:placetype":"venue"
},
  "geometry": {"coordinates":[-97.159628,32.8349],"type":"Point"}
}