{
  "type": "Feature",
  "properties": {
    "iso:country":"US",
    "sg:address":"17530 Sorrel Ridge Dr",
    "sg:city":"Spring",
    "sg:classifiers":[
        {
            "category":"Professional",
            "subcategory":"Computer Services",
            "type":"Services"
        }
    ],
    "sg:phone":"+1 281 651 0969",
    "sg:postcode":"77388",
    "sg:province":"TX",
    "sg:tags":[
        "datum",
        "related"
    ],
    "wof:name":"K H Consulting",
    "wof:placetype":"venue"
},
  "geometry": {"coordinates":[-95.472319,30.033835],"type":"Point"}
}