{
  "type": "Feature",
  "properties": {
    "iso:country":"US",
    "sg:address":"6621 McCallum Blvd",
    "sg:city":"Dallas",
    "sg:classifiers":[
        {
            "category":"Health Services",
            "subcategory":"Health Practitioner",
            "type":"Services"
        }
    ],
    "sg:phone":"+1 972 250 2217",
    "sg:postcode":"75252",
    "sg:province":"TX",
    "wof:name":"Irene Johnson Crna",
    "wof:placetype":"venue"
},
  "geometry": {"coordinates":[-96.786968,32.98802],"type":"Point"}
}