{
  "type": "Feature",
  "properties": {
    "iso:country":"US",
    "sg:address":"1912 Lamplight Ln",
    "sg:city":"Tyler",
    "sg:classifiers":[
        {
            "category":"Building & Trades",
            "subcategory":"Landscaping Services",
            "type":"Services"
        }
    ],
    "sg:phone":"+1 903 597 4900",
    "sg:postcode":"75701",
    "sg:province":"TX",
    "sg:tags":[
        "landscape",
        "contractor"
    ],
    "wof:name":"Southern Caspian Irrigation",
    "wof:placetype":"venue"
},
  "geometry": {"coordinates":[-95.27554000000001,32.323685],"type":"Point"}
}