{
  "type": "Feature",
  "properties": {
    "iso:country":"US",
    "sg:address":"7557 Annemasse St",
    "sg:city":"Corpus Christi",
    "sg:classifiers":[
        {
            "category":"Health Services",
            "subcategory":"Optometrist",
            "type":"Services"
        }
    ],
    "sg:phone":"+1 361 993 2015",
    "sg:postcode":"78414",
    "sg:province":"TX",
    "wof:name":"McIntyer Garza Assoc",
    "wof:placetype":"venue"
},
  "geometry": {"coordinates":[-97.384528,27.660765],"type":"Point"}
}