{
  "type": "Feature",
  "properties": {
    "iso:country":"US",
    "sg:address":"16820 Oak Ln",
    "sg:city":"Channelview",
    "sg:classifiers":[
        {
            "category":"Building & Trades",
            "subcategory":"Construction",
            "type":"Services"
        }
    ],
    "sg:phone":"+1 281 452 4469",
    "sg:postcode":"77530",
    "sg:province":"TX",
    "sg:tags":[
        "contractor"
    ],
    "wof:name":"Joe Gandy Backhoe & Dozer Service",
    "wof:placetype":"venue"
},
  "geometry": {"coordinates":[-95.09699999999999,29.8025],"type":"Point"}
}