{
  "type": "Feature",
  "properties": {
    "iso:country":"US",
    "sg:address":"5018 Heritage Cir",
    "sg:city":"Garland",
    "sg:classifiers":[
        {
            "category":"Manufacturing",
            "subcategory":"Jewelry",
            "type":"Manufacturing & Wholesale Goods"
        }
    ],
    "sg:phone":"+1 972 495 0569",
    "sg:postcode":"75048",
    "sg:province":"TX",
    "sg:tags":[
        "costume",
        "mfg"
    ],
    "wof:name":"Sherry Cowlings",
    "wof:placetype":"venue"
},
  "geometry": {"coordinates":[-96.57156999999999,32.970072],"type":"Point"}
}