{
  "type": "Feature",
  "properties": {
    "iso:country":"US",
    "sg:address":"13497 N US Hwy 183",
    "sg:city":"Austin",
    "sg:classifiers":[
        {
            "category":"Shopping",
            "subcategory":"Bicycles & Sporting Goods",
            "type":"Retail Goods"
        }
    ],
    "sg:phone":"+1 512 219 1122",
    "sg:postcode":"78750",
    "sg:province":"TX",
    "sg:tags":[
        "gun",
        "gunsmith"
    ],
    "wof:name":"Heritage Firearms",
    "wof:placetype":"venue"
},
  "geometry": {"coordinates":[-97.791298,30.452387],"type":"Point"}
}