{
  "type": "Feature",
  "properties": {
    "iso:country":"US",
    "sg:address":"701 Edinburg Ave",
    "sg:city":"Elsa",
    "sg:classifiers":[
        {
            "category":"Health Services",
            "subcategory":"Doctor",
            "type":"Services"
        }
    ],
    "sg:phone":"+1 956 262 1888",
    "sg:postcode":"78543",
    "sg:province":"TX",
    "sg:tags":[
        "dentist"
    ],
    "wof:name":"Rodriguez Dental Group",
    "wof:placetype":"venue"
},
  "geometry": {"coordinates":[-97.979294,26.293584],"type":"Point"}
}