{
  "type": "Feature",
  "properties": {
    "iso:country":"US",
    "sg:address":"6919 Jeb Stuart Dr",
    "sg:city":"Richmond",
    "sg:classifiers":[
        {
            "category":"Building & Trades",
            "subcategory":"Construction",
            "type":"Services"
        }
    ],
    "sg:phone":"+1 281 937 9370",
    "sg:postcode":"77469",
    "sg:province":"TX",
    "sg:tags":[
        "contractor"
    ],
    "wof:name":"McLaughlin Remodeling",
    "wof:placetype":"venue"
},
  "geometry": {"coordinates":[-95.69073400000001,29.546648],"type":"Point"}
}