{
  "type": "Feature",
  "properties": {
    "iso:country":"US",
    "sg:address":"1505 Harroun Ave",
    "sg:city":"Mckinney",
    "sg:classifiers":[
        {
            "category":"Health Services",
            "subcategory":"Podiatrist",
            "type":"Services"
        }
    ],
    "sg:phone":"+1 972 542 3668",
    "sg:postcode":"75069",
    "sg:province":"TX",
    "sg:tags":[
        "physician",
        "referral",
        "surgeons",
        "podiatrists'",
        "information"
    ],
    "sg:website":"http://www.mckinneyfootcare.com",
    "wof:name":"McKinney Foot Care",
    "wof:placetype":"venue"
},
  "geometry": {"coordinates":[-96.627272,33.21452],"type":"Point"}
}