{
  "type": "Feature",
  "properties": {
    "iso:country":"US",
    "sg:address":"328 Goldfinch Dr",
    "sg:city":"White Settlement",
    "sg:classifiers":[
        {
            "category":"Building & Trades",
            "subcategory":"Landscaping Services",
            "type":"Services"
        }
    ],
    "sg:phone":"+1 817 246 4221",
    "sg:postcode":"76108",
    "sg:province":"TX",
    "sg:tags":[
        "spraying"
    ],
    "wof:name":"Bob's Tree Svc",
    "wof:placetype":"venue"
},
  "geometry": {"coordinates":[-97.493844,32.754824],"type":"Point"}
}