{
  "type": "Feature",
  "properties": {
    "iso:country":"US",
    "sg:address":"104 E 31st St",
    "sg:city":"Austin",
    "sg:classifiers":[
        {
            "category":"Food & Beverages",
            "subcategory":"Groceries & Convenience Stores",
            "type":"Retail Goods"
        }
    ],
    "sg:phone":"+1 512 478 1320",
    "sg:postcode":"78705",
    "sg:province":"TX",
    "wof:name":"Peernath Inc",
    "wof:placetype":"venue"
},
  "geometry": {"coordinates":[-97.736633,30.295208],"type":"Point"}
}