{
  "type": "Feature",
  "properties": {
    "iso:country":"US",
    "sg:address":"224 W 3rd St",
    "sg:city":"Texarkana",
    "sg:classifiers":[
        {
            "category":"Banks & Credit Unions",
            "subcategory":"Financial Services",
            "type":"Services"
        }
    ],
    "sg:phone":"+1 903 793 5624",
    "sg:postcode":"75501",
    "sg:province":"TX",
    "sg:tags":[
        "loan"
    ],
    "wof:name":"E-Z Loan Co",
    "wof:placetype":"venue"
},
  "geometry": {"coordinates":[-94.043785,33.422247],"type":"Point"}
}