{
  "type": "Feature",
  "properties": {
    "iso:country":"US",
    "sg:address":"5234 Elm St",
    "sg:city":"Houston",
    "sg:classifiers":[
        {
            "category":"Manufacturing",
            "subcategory":"Printing",
            "type":"Manufacturing & Wholesale Goods"
        }
    ],
    "sg:phone":"+1 713 610 0770",
    "sg:postcode":"77081",
    "sg:province":"TX",
    "sg:tags":[
        "multimedia"
    ],
    "wof:name":"Apt Communications",
    "wof:placetype":"venue"
},
  "geometry": {"coordinates":[-95.471643,29.713012],"type":"Point"}
}