{
  "type": "Feature",
  "properties": {
    "iso:country":"US",
    "sg:address":"133 Broiles St",
    "sg:city":"Jacksonville",
    "sg:classifiers":[
        {
            "category":"Restaurant",
            "type":"Food & Drink"
        }
    ],
    "sg:phone":"+1 903 586 9577",
    "sg:postcode":"75766",
    "sg:province":"TX",
    "wof:name":"Plaza Dine Inc",
    "wof:placetype":"venue"
},
  "geometry": {"coordinates":[-95.266068,31.938432],"type":"Point"}
}