{
  "type": "Feature",
  "properties": {
    "iso:country":"US",
    "sg:address":"3400 Duke Rd",
    "sg:city":"Austin",
    "sg:classifiers":[
        {
            "category":"Home & Garden",
            "subcategory":"Home Furnishings",
            "type":"Retail Goods"
        }
    ],
    "sg:phone":"+1 512 926 7700",
    "sg:postcode":"78724",
    "sg:province":"TX",
    "sg:tags":[
        "venetian",
        "blind"
    ],
    "wof:name":"Classic Blind & Drapery Co",
    "wof:placetype":"venue"
},
  "geometry": {"coordinates":[-97.65977100000001,30.321144],"type":"Point"}
}