{
  "type": "Feature",
  "properties": {
    "iso:country":"US",
    "sg:address":"403 N Kirkwood Rd",
    "sg:city":"Houston",
    "sg:classifiers":[
        {
            "category":"Food & Beverages",
            "subcategory":"Candy",
            "type":"Retail Goods"
        }
    ],
    "sg:phone":"+1 281 564 1808",
    "sg:postcode":"77079",
    "sg:province":"TX",
    "wof:name":"Action Snacks & Candies",
    "wof:placetype":"venue"
},
  "geometry": {"coordinates":[-95.589896,29.764671],"type":"Point"}
}