{
  "type": "Feature",
  "properties": {
    "iso:country":"US",
    "sg:address":"3346 Walnut Bend Ln",
    "sg:city":"Houston",
    "sg:classifiers":[
        {
            "category":"Wholesale",
            "subcategory":"Machinery & Supplies",
            "type":"Manufacturing & Wholesale Goods"
        }
    ],
    "sg:phone":"+1 713 278 7790",
    "sg:postcode":"77042",
    "sg:province":"TX",
    "sg:tags":[
        "truck"
    ],
    "wof:name":"E Z Loader",
    "wof:placetype":"venue"
},
  "geometry": {"coordinates":[-95.568043,29.725519],"type":"Point"}
}