{
  "type": "Feature",
  "properties": {
    "iso:country":"US",
    "sg:address":"4526 Co Rd 12",
    "sg:city":"Hereford",
    "sg:classifiers":[
        {
            "category":"Farming",
            "subcategory":"Farm",
            "type":"Manufacturing & Wholesale Goods"
        }
    ],
    "sg:phone":"+1 806 258 7569",
    "sg:postcode":"79045",
    "sg:province":"TX",
    "sg:tags":[
        "general"
    ],
    "wof:name":"Wayne Betzen Farms Inc",
    "wof:placetype":"venue"
},
  "geometry": {"coordinates":[-102.254503,34.913279],"type":"Point"}
}