{
  "type": "Feature",
  "properties": {
    "iso:country":"US",
    "sg:address":"2210 S Washington St",
    "sg:city":"Kaufman",
    "sg:classifiers":[
        {
            "category":"Manufacturing",
            "subcategory":"Glass & Minerals",
            "type":"Manufacturing & Wholesale Goods"
        }
    ],
    "sg:phone":"+1 972 932 3072",
    "sg:postcode":"75142",
    "sg:province":"TX",
    "sg:tags":[
        "glass-wholesale",
        "shape",
        "circle",
        "special",
        "manufacturer"
    ],
    "wof:name":"Glass Service Specialist",
    "wof:placetype":"venue"
},
  "geometry": {"coordinates":[-96.30914300000001,32.575504],"type":"Point"}
}