{
  "type": "Feature",
  "properties": {
    "iso:country":"US",
    "sg:address":"723 N 4th St",
    "sg:city":"Longview",
    "sg:classifiers":[
        {
            "category":"Health Services",
            "subcategory":"Doctor",
            "type":"Services"
        }
    ],
    "sg:phone":"+1 903 753 7515",
    "sg:postcode":"75601",
    "sg:province":"TX",
    "wof:name":"Brenda Copeland DDS",
    "wof:placetype":"venue"
},
  "geometry": {"coordinates":[-94.731537,32.501807],"type":"Point"}
}