{
  "type": "Feature",
  "properties": {
    "iso:country":"US",
    "sg:address":"15 Harmony Hollow Ct",
    "sg:city":"Conroe",
    "sg:classifiers":[
        {
            "category":"Professional",
            "subcategory":"Computer Services",
            "type":"Services"
        }
    ],
    "sg:phone":"+1 936 271 4629",
    "sg:postcode":"77385",
    "sg:province":"TX",
    "sg:tags":[
        "related"
    ],
    "wof:name":"Hidden Attributes",
    "wof:placetype":"venue"
},
  "geometry": {"coordinates":[-95.438158,30.215477],"type":"Point"}
}