{
  "type": "Feature",
  "properties": {
    "iso:country":"US",
    "sg:address":"25534 Hickory Valley Ln",
    "sg:city":"Spring",
    "sg:classifiers":[
        {
            "category":"Home & Garden",
            "subcategory":"Hardware",
            "type":"Retail Goods"
        }
    ],
    "sg:phone":"+1 281 353 0780",
    "sg:postcode":"77373",
    "sg:province":"TX",
    "wof:name":"RR Tools",
    "wof:placetype":"venue"
},
  "geometry": {"coordinates":[-95.40692900000001,30.072065],"type":"Point"}
}