{
  "type": "Feature",
  "properties": {
    "iso:country":"US",
    "sg:address":"113 E Houston St",
    "sg:city":"Tyler",
    "sg:classifiers":[
        {
            "category":"Organizations",
            "subcategory":"Non-profit Organization",
            "type":"Services"
        },
        {
            "category":"Government",
            "subcategory":"Office",
            "type":"Public Place"
        }
    ],
    "sg:phone":"+1 903 592 0582",
    "sg:postcode":"75702",
    "sg:province":"TX",
    "sg:tags":[
        "administrative",
        "program",
        "health"
    ],
    "wof:name":"Big Brothers and Big Sisters",
    "wof:placetype":"venue"
},
  "geometry": {"coordinates":[-95.299654,32.343666],"type":"Point"}
}