{
  "type": "Feature",
  "properties": {
    "iso:country":"US",
    "sg:address":"4801 Woodway Dr",
    "sg:city":"Houston",
    "sg:classifiers":[
        {
            "category":"Professional",
            "subcategory":"Management & Consulting",
            "type":"Services"
        }
    ],
    "sg:phone":"+1 713 964 2664",
    "sg:postcode":"77056",
    "sg:province":"TX",
    "sg:tags":[
        "training",
        "sales"
    ],
    "wof:name":"Leadership Management Dynamics",
    "wof:placetype":"venue"
},
  "geometry": {"coordinates":[-95.45839599999999,29.764477],"type":"Point"}
}