{
  "type": "Feature",
  "properties": {
    "iso:country":"US",
    "sg:address":"4128 Creekmont Dr",
    "sg:city":"Houston",
    "sg:classifiers":[
        {
            "category":"Retail",
            "subcategory":"Repair Shop",
            "type":"Services"
        }
    ],
    "sg:phone":"+1 713 957 2724",
    "sg:postcode":"77091",
    "sg:province":"TX",
    "sg:tags":[
        "welding",
        "contractor"
    ],
    "wof:name":"Premium Welding Inc",
    "wof:placetype":"venue"
},
  "geometry": {"coordinates":[-95.454615,29.842377],"type":"Point"}
}