{
  "type": "Feature",
  "properties": {
    "iso:country":"US",
    "sg:address":"5155 River Oaks Blvd",
    "sg:city":"Fort Worth",
    "sg:classifiers":[
        {
            "category":"Restaurant",
            "type":"Food & Drink"
        }
    ],
    "sg:phone":"+1 817 624 1641",
    "sg:postcode":"76114",
    "sg:province":"TX",
    "sg:tags":[
        "eating"
    ],
    "wof:name":"Gershom El Cafe",
    "wof:placetype":"venue"
},
  "geometry": {"coordinates":[-97.398636,32.773995],"type":"Point"}
}