{
  "type": "Feature",
  "properties": {
    "iso:country":"US",
    "sg:address":"14452 Midway Rd",
    "sg:city":"Dallas",
    "sg:classifiers":[
        {
            "category":"Wholesale",
            "subcategory":"Home Furnishings",
            "type":"Manufacturing & Wholesale Goods"
        }
    ],
    "sg:phone":"+1 972 934 1114",
    "sg:postcode":"75244",
    "sg:province":"TX",
    "sg:tags":[
        "blind",
        "shade"
    ],
    "wof:name":"Sun Masters of Farmers Branch",
    "wof:placetype":"venue"
},
  "geometry": {"coordinates":[-96.83869900000001,32.946999],"type":"Point"}
}