{
  "type": "Feature",
  "properties": {
    "iso:country":"US",
    "sg:address":"16037 E State Hwy 29",
    "sg:city":"Buchanan Dam",
    "sg:classifiers":[
        {
            "category":"Retail",
            "subcategory":"Auto Repair",
            "type":"Services"
        }
    ],
    "sg:phone":"+1 512 793 2164",
    "sg:postcode":"78609",
    "sg:province":"TX",
    "sg:tags":[
        "automotive",
        "general"
    ],
    "wof:name":"Charlies Car Care",
    "wof:placetype":"venue"
},
  "geometry": {"coordinates":[-98.449753,30.736108],"type":"Point"}
}