{
  "type": "Feature",
  "properties": {
    "iso:country":"US",
    "sg:address":"1150 Federal Rd",
    "sg:city":"Houston",
    "sg:classifiers":[
        {
            "category":"Restaurant",
            "type":"Food & Drink"
        }
    ],
    "sg:phone":"+1 713 451 2221",
    "sg:postcode":"77015",
    "sg:province":"TX",
    "wof:name":"Taqueria Refresqueria Los Reyes",
    "wof:placetype":"venue"
},
  "geometry": {"coordinates":[-95.21489699999999,29.771999],"type":"Point"}
}