{
  "type": "Feature",
  "properties": {
    "iso:country":"US",
    "sg:address":"14006 FM 2920",
    "sg:city":"Tomball",
    "sg:classifiers":[
        {
            "category":"Utilities",
            "subcategory":"Telephone",
            "type":"Services"
        }
    ],
    "sg:phone":"+1 281 255 2058",
    "sg:postcode":"77377",
    "sg:province":"TX",
    "sg:tags":[
        "company"
    ],
    "wof:name":"National Telephone Co",
    "wof:placetype":"venue"
},
  "geometry": {"coordinates":[-95.63442499999999,30.089402],"type":"Point"}
}