{
  "type": "Feature",
  "properties": {
    "iso:country":"US",
    "sg:address":"6005 Dalrock Rd",
    "sg:city":"Rowlett",
    "sg:classifiers":[
        {
            "category":"Social Services",
            "subcategory":"Child Care",
            "type":"Services"
        }
    ],
    "sg:phone":"+1 972 463 3698",
    "sg:postcode":"75088",
    "sg:province":"TX",
    "sg:tags":[
        "day"
    ],
    "wof:name":"Treasures Learning Center",
    "wof:placetype":"venue"
},
  "geometry": {"coordinates":[-96.518047,32.912538],"type":"Point"}
}