{
  "type": "Feature",
  "properties": {
    "iso:country":"US",
    "sg:address":"95 Oak Dr",
    "sg:city":"Lake Jackson",
    "sg:classifiers":[
        {
            "category":"Food & Beverages",
            "subcategory":"Groceries & Convenience Stores",
            "type":"Retail Goods"
        }
    ],
    "sg:phone":"+1 979 297 2977",
    "sg:postcode":"77566",
    "sg:province":"TX",
    "wof:name":"Wag-A-Bag",
    "wof:placetype":"venue"
},
  "geometry": {"coordinates":[-95.446811,29.043891],"type":"Point"}
}