{
  "type": "Feature",
  "properties": {
    "iso:country":"US",
    "sg:address":"4951 Walzem Rd",
    "sg:city":"San Antonio",
    "sg:classifiers":[
        {
            "category":"Travel",
            "subcategory":"Travel Agent",
            "type":"Entertainment"
        }
    ],
    "sg:phone":"+1 210 654 6310",
    "sg:postcode":"78218",
    "sg:province":"TX",
    "sg:tags":[
        "agency"
    ],
    "wof:name":"Rennert Cruise & Tour",
    "wof:placetype":"venue"
},
  "geometry": {"coordinates":[-98.39355999999999,29.510206],"type":"Point"}
}