{
  "type": "Feature",
  "properties": {
    "iso:country":"US",
    "sg:address":"611 E FM 78",
    "sg:city":"Cibolo",
    "sg:classifiers":[
        {
            "category":"Personal",
            "subcategory":"Beauty Salon",
            "type":"Services"
        }
    ],
    "sg:phone":"+1 210 659 9311",
    "sg:postcode":"78108",
    "sg:province":"TX",
    "sg:tags":[
        "shop"
    ],
    "wof:name":"Hair Designs By Helen",
    "wof:placetype":"venue"
},
  "geometry": {"coordinates":[-98.20767499999999,29.562908],"type":"Point"}
}