{
  "type": "Feature",
  "properties": {
    "iso:country":"US",
    "sg:address":"1290 S Willis St",
    "sg:city":"Abilene",
    "sg:classifiers":[
        {
            "category":"Insurance",
            "subcategory":"Insurance Agent",
            "type":"Services"
        }
    ],
    "sg:phone":"+1 325 698 3511",
    "sg:postcode":"79605",
    "sg:province":"TX",
    "sg:tags":[
        "planning",
        "financial"
    ],
    "wof:name":"Equitable Life Assurance",
    "wof:placetype":"venue"
},
  "geometry": {"coordinates":[-99.76415900000001,32.434449],"type":"Point"}
}