{
  "type": "Feature",
  "properties": {
    "iso:country":"US",
    "sg:address":"5112 Lincolnshire Ct",
    "sg:city":"Dallas",
    "sg:classifiers":[
        {
            "category":"Shopping",
            "type":"Retail Goods"
        },
        {
            "category":"Professional",
            "subcategory":"Management & Consulting",
            "type":"Services"
        }
    ],
    "sg:phone":"+1 972 234 2267",
    "sg:postcode":"75287",
    "sg:province":"TX",
    "sg:tags":[
        "direct",
        "sales",
        "cosmetic",
        "perfume"
    ],
    "wof:name":"Mary Kay Cosmestics",
    "wof:placetype":"venue"
},
  "geometry": {"coordinates":[-96.82196399999999,33.002171],"type":"Point"}
}