{
  "type": "Feature",
  "properties": {
    "iso:country":"US",
    "sg:address":"6838 Middlefield Dr",
    "sg:city":"Pasadena",
    "sg:classifiers":[
        {
            "category":"Home & Garden",
            "subcategory":"Building Materials",
            "type":"Retail Goods"
        },
        {
            "category":"Building & Trades",
            "subcategory":"Construction",
            "type":"Services"
        }
    ],
    "sg:phone":"+1 281 998 8556",
    "sg:postcode":"77505",
    "sg:province":"TX",
    "sg:tags":[
        "concrete",
        "staining",
        "contractor"
    ],
    "wof:name":"Creative Outdoor Designs",
    "wof:placetype":"venue"
},
  "geometry": {"coordinates":[-95.134928,29.642233],"type":"Point"}
}