{
  "type": "Feature",
  "properties": {
    "iso:country":"US",
    "sg:address":"3800 Main St Ste B",
    "sg:city":"Dallas",
    "sg:classifiers":[
        {
            "category":"Real Estate",
            "subcategory":"Architect",
            "type":"Services"
        }
    ],
    "sg:phone":"+1 214 823 3300",
    "sg:postcode":"75226",
    "sg:province":"TX",
    "wof:name":"Z E R O 3",
    "wof:placetype":"venue"
},
  "geometry": {"coordinates":[-96.77310199999999,32.786201],"type":"Point"}
}