{
  "type": "Feature",
  "properties": {
    "iso:country":"US",
    "sg:address":"418 E Main St",
    "sg:city":"Fredericksburg",
    "sg:classifiers":[
        {
            "category":"Shopping",
            "subcategory":"Used Merchandise",
            "type":"Retail Goods"
        }
    ],
    "sg:phone":"+1 830 990 0185",
    "sg:postcode":"78624",
    "sg:province":"TX",
    "wof:name":"Just Antiques",
    "wof:placetype":"venue"
},
  "geometry": {"coordinates":[-98.86696600000001,30.271337],"type":"Point"}
}