{
  "type": "Feature",
  "properties": {
    "iso:country":"US",
    "sg:address":"809 E Galbraith St",
    "sg:city":"Hebbronville",
    "sg:classifiers":[
        {
            "category":"Mining & Drilling",
            "type":"Manufacturing & Wholesale Goods"
        }
    ],
    "sg:phone":"+1 361 527 4421",
    "sg:postcode":"78361",
    "sg:province":"TX",
    "sg:tags":[
        "field",
        "oil"
    ],
    "wof:name":"Katco Vacuum Truck Svc Inc",
    "wof:placetype":"venue"
},
  "geometry": {"coordinates":[-98.66876600000001,27.305835],"type":"Point"}
}