{
  "type": "Feature",
  "properties": {
    "iso:country":"US",
    "sg:address":"10250 Osburn Rd",
    "sg:city":"Aubrey",
    "sg:classifiers":[
        {
            "category":"Building & Trades",
            "subcategory":"Construction",
            "type":"Services"
        }
    ],
    "sg:phone":"+1 940 365 1900",
    "sg:postcode":"76258",
    "sg:province":"TX",
    "sg:tags":[
        "roofing",
        "contractor"
    ],
    "wof:name":"Classic Roofing",
    "wof:placetype":"venue"
},
  "geometry": {"coordinates":[-96.949636,33.340926],"type":"Point"}
}