{
  "type": "Feature",
  "properties": {
    "iso:country":"US",
    "sg:address":"1905 Ave R",
    "sg:city":"Hondo",
    "sg:classifiers":[
        {
            "category":"Retail",
            "subcategory":"Repair Shop",
            "type":"Services"
        }
    ],
    "sg:phone":"+1 830 741 5686",
    "sg:postcode":"78861",
    "sg:province":"TX",
    "wof:name":"Tonnes Towing",
    "wof:placetype":"venue"
},
  "geometry": {"coordinates":[-99.147254,29.347079],"type":"Point"}
}