{
  "type": "Feature",
  "properties": {
    "iso:country":"US",
    "sg:address":"906 N 6th St",
    "sg:city":"Longview",
    "sg:classifiers":[
        {
            "category":"Health Services",
            "subcategory":"Doctor",
            "type":"Services"
        }
    ],
    "sg:phone":"+1 903 753 2246",
    "sg:postcode":"75601",
    "sg:province":"TX",
    "sg:tags":[
        "medical"
    ],
    "wof:name":"Stephen Lee Womack MD",
    "wof:placetype":"venue"
},
  "geometry": {"coordinates":[-94.729179,32.503492],"type":"Point"}
}