{
  "type": "Feature",
  "properties": {
    "iso:country":"US",
    "sg:address":"3772 Hickory St",
    "sg:city":"Abilene",
    "sg:classifiers":[
        {
            "category":"Retail",
            "subcategory":"Car Wash",
            "type":"Services"
        }
    ],
    "sg:phone":"+1 325 672 4826",
    "sg:postcode":"79601",
    "sg:province":"TX",
    "sg:tags":[
        "automobile",
        "detail",
        "clean"
    ],
    "wof:name":"Verastequi Body Shop",
    "wof:placetype":"venue"
},
  "geometry": {"coordinates":[-99.734977,32.497096],"type":"Point"}
}