{
  "type": "Feature",
  "properties": {
    "iso:country":"US",
    "sg:address":"12317 Main St",
    "sg:city":"Houston",
    "sg:classifiers":[
        {
            "category":"Shopping",
            "subcategory":"Clothing, Apparel, & Fashions",
            "type":"Retail Goods"
        }
    ],
    "sg:phone":"+1 713 283 8446",
    "sg:postcode":"77035",
    "sg:province":"TX",
    "sg:tags":[
        "accessory",
        "clothing",
        "women's"
    ],
    "wof:name":"Rainbow Apparel Companies",
    "wof:placetype":"venue"
},
  "geometry": {"coordinates":[-95.452904,29.651501],"type":"Point"}
}