{
  "type": "Feature",
  "properties": {
    "iso:country":"US",
    "sg:address":"401 E Mayfield Rd",
    "sg:city":"Arlington",
    "sg:classifiers":[
        {
            "category":"Education",
            "subcategory":"School",
            "type":"Public Place"
        }
    ],
    "sg:phone":"+1 817 419 1300",
    "sg:postcode":"76014",
    "sg:province":"TX",
    "sg:tags":[
        "elementary"
    ],
    "wof:name":"Burgin Elementary School",
    "wof:placetype":"venue"
},
  "geometry": {"coordinates":[-97.104556,32.691795],"type":"Point"}
}