{
  "type": "Feature",
  "properties": {
    "iso:country":"US",
    "sg:address":"1907 Aduanales Ln",
    "sg:city":"Laredo",
    "sg:classifiers":[
        {
            "category":"Wholesale",
            "subcategory":"Computers",
            "type":"Manufacturing & Wholesale Goods"
        }
    ],
    "sg:phone":"+1 956 728 7777",
    "sg:postcode":"78041",
    "sg:province":"TX",
    "wof:name":"Internet Club",
    "wof:placetype":"venue"
},
  "geometry": {"coordinates":[-99.51518900000001,27.542534],"type":"Point"}
}