{
  "type": "Feature",
  "properties": {
    "iso:country":"US",
    "sg:address":"1207 E University Dr",
    "sg:city":"Edinburg",
    "sg:classifiers":[
        {
            "category":"Restaurant",
            "type":"Food & Drink"
        }
    ],
    "sg:phone":"+1 956 316 4949",
    "sg:postcode":"78539",
    "sg:province":"TX",
    "wof:name":"Taqueria El Zarape",
    "wof:placetype":"venue"
},
  "geometry": {"coordinates":[-98.15042099999999,26.299746],"type":"Point"}
}