{
  "type": "Feature",
  "properties": {
    "iso:country":"US",
    "sg:address":"2415 E 8th St",
    "sg:city":"Austin",
    "sg:classifiers":[
        {
            "category":"Shopping",
            "subcategory":"Clothing, Apparel, & Fashions",
            "type":"Retail Goods"
        }
    ],
    "sg:phone":"+1 512 294 2334",
    "sg:postcode":"78702",
    "sg:province":"TX",
    "sg:tags":[
        "designer"
    ],
    "wof:name":"Helms",
    "wof:placetype":"venue"
},
  "geometry": {"coordinates":[-97.71511099999999,30.263575],"type":"Point"}
}