{
  "type": "Feature",
  "properties": {
    "iso:country":"US",
    "sg:address":"5034 Libbey Ln",
    "sg:city":"Houston",
    "sg:classifiers":[
        {
            "category":"Professional",
            "type":"Services"
        }
    ],
    "sg:phone":"+1 281 630 0755",
    "sg:postcode":"77092",
    "sg:province":"TX",
    "sg:tags":[
        "artist"
    ],
    "wof:name":"Monolithic Art & Design",
    "wof:placetype":"venue"
},
  "geometry": {"coordinates":[-95.464027,29.83091],"type":"Point"}
}