{
  "type": "Feature",
  "properties": {
    "iso:country":"US",
    "sg:address":"6566 Kiwanis Club Rd",
    "sg:city":"Silsbee",
    "sg:classifiers":[
        {
            "category":"Insurance",
            "subcategory":"Insurance Agent",
            "type":"Services"
        }
    ],
    "sg:phone":"+1 409 385 7354",
    "sg:postcode":"77656",
    "sg:province":"TX",
    "wof:name":"Farmers Mutual Protective Agcy",
    "wof:placetype":"venue"
},
  "geometry": {"coordinates":[-94.210551,30.341759],"type":"Point"}
}