{
  "type": "Feature",
  "properties": {
    "iso:country":"US",
    "sg:address":"2750 McCree Rd",
    "sg:city":"Garland",
    "sg:classifiers":[
        {
            "category":"Building & Trades",
            "subcategory":"Construction",
            "type":"Services"
        }
    ],
    "sg:phone":"+1 972 271 0187",
    "sg:postcode":"75041",
    "sg:province":"TX",
    "sg:tags":[
        "home",
        "improvement"
    ],
    "wof:name":"West Star Builders",
    "wof:placetype":"venue"
},
  "geometry": {"coordinates":[-96.671432,32.871456],"type":"Point"}
}