{
  "type": "Feature",
  "properties": {
    "iso:country":"US",
    "sg:address":"6907 FM 1488",
    "sg:city":"Magnolia",
    "sg:classifiers":[
        {
            "category":"Manufacturing",
            "subcategory":"Apparel",
            "type":"Manufacturing & Wholesale Goods"
        }
    ],
    "sg:phone":"+1 281 356 1941",
    "sg:postcode":"77354",
    "sg:province":"TX",
    "sg:tags":[
        "textile",
        "bag"
    ],
    "sg:website":"www.filterall.com",
    "wof:name":"Sewn-Weld Industries",
    "wof:placetype":"venue"
},
  "geometry": {"coordinates":[-95.57394499999999,30.220674],"type":"Point"}
}