{
  "type": "Feature",
  "properties": {
    "iso:country":"US",
    "sg:address":"2330 Jett St",
    "sg:city":"Farmers Branch",
    "sg:classifiers":[
        {
            "category":"Professional",
            "subcategory":"Advertising",
            "type":"Services"
        }
    ],
    "sg:phone":"+1 972 243 7326",
    "sg:postcode":"75234",
    "sg:province":"TX",
    "sg:tags":[
        "mailing",
        "shipping"
    ],
    "wof:name":"Dallas Mailing Svc",
    "wof:placetype":"venue"
},
  "geometry": {"coordinates":[-96.89842,32.92442],"type":"Point"}
}