{
  "type": "Feature",
  "properties": {
    "iso:country":"US",
    "sg:address":"1410 Calais Ct",
    "sg:city":"Euless",
    "sg:classifiers":[
        {
            "category":"Shopping",
            "type":"Retail Goods"
        }
    ],
    "sg:phone":"+1 817 545 7662",
    "sg:postcode":"76040",
    "sg:province":"TX",
    "sg:tags":[
        "trophy",
        "medal",
        "award"
    ],
    "wof:name":"Andrea's Trophy Shoppe",
    "wof:placetype":"venue"
},
  "geometry": {"coordinates":[-97.104849,32.835254],"type":"Point"}
}