{
  "type": "Feature",
  "properties": {
    "iso:country":"US",
    "sg:address":"950 Longfellow Dr",
    "sg:city":"Beaumont",
    "sg:classifiers":[
        {
            "category":"Personal",
            "type":"Services"
        }
    ],
    "sg:phone":"+1 409 898 4247",
    "sg:postcode":"77706",
    "sg:province":"TX",
    "wof:name":"Hair Restoration Club",
    "wof:placetype":"venue"
},
  "geometry": {"coordinates":[-94.13701500000001,30.092337],"type":"Point"}
}