{
  "type": "Feature",
  "properties": {
    "iso:country":"US",
    "sg:address":"8408 Shady Oaks Dr",
    "sg:city":"Fort Worth",
    "sg:classifiers":[
        {
            "category":"Building & Trades",
            "subcategory":"Equipment Rental",
            "type":"Services"
        },
        {
            "category":"Banks & Credit Unions",
            "subcategory":"Bank",
            "type":"Services"
        }
    ],
    "sg:phone":"+1 817 498 4334",
    "sg:postcode":"76180",
    "sg:province":"TX",
    "sg:tags":[
        "leasing",
        "institution",
        "business"
    ],
    "wof:name":"Center Capital Corporation",
    "wof:placetype":"venue"
},
  "geometry": {"coordinates":[-97.20370699999999,32.903611],"type":"Point"}
}