{
  "type": "Feature",
  "properties": {
    "iso:country":"US",
    "sg:address":"10830 N Central Expy",
    "sg:city":"Dallas",
    "sg:classifiers":[
        {
            "category":"Professional",
            "subcategory":"Lawyer & Legal Services",
            "type":"Services"
        }
    ],
    "sg:phone":"+1 214 369 7761",
    "sg:postcode":"75231",
    "sg:province":"TX",
    "wof:name":"Corman Jack Atty",
    "wof:placetype":"venue"
},
  "geometry": {"coordinates":[-96.7687,32.895199],"type":"Point"}
}