{
  "type": "Feature",
  "properties": {
    "iso:country":"US",
    "sg:address":"2534 Shoreline Dr",
    "sg:city":"Abilene",
    "sg:classifiers":[
        {
            "category":"Banks & Credit Unions",
            "subcategory":"Financial Services",
            "type":"Services"
        }
    ],
    "sg:phone":"+1 325 672 7012",
    "sg:postcode":"79602",
    "sg:province":"TX",
    "sg:tags":[
        "investor"
    ],
    "wof:name":"Kilaru Investment Managem",
    "wof:placetype":"venue"
},
  "geometry": {"coordinates":[-99.702298,32.416262],"type":"Point"}
}