{
  "type": "Feature",
  "properties": {
    "iso:country":"US",
    "sg:address":"1883 Winchester Dr",
    "sg:city":"Moody",
    "sg:classifiers":[
        {
            "category":"Wholesale",
            "subcategory":"Electrical",
            "type":"Manufacturing & Wholesale Goods"
        }
    ],
    "sg:phone":"+1 254 853 9095",
    "sg:postcode":"76557",
    "sg:province":"TX",
    "sg:tags":[
        "battery",
        "industrial",
        "maintenance"
    ],
    "wof:name":"Fred Roberts",
    "wof:placetype":"venue"
},
  "geometry": {"coordinates":[-97.314649,31.318754],"type":"Point"}
}