{
  "type": "Feature",
  "properties": {
    "iso:country":"US",
    "sg:address":"2625 Hartwood Dr",
    "sg:city":"Fort Worth",
    "sg:classifiers":[
        {
            "category":"Real Estate",
            "subcategory":"Real Estate Agent",
            "type":"Services"
        }
    ],
    "sg:phone":"+1 817 926 1803",
    "sg:postcode":"76109",
    "sg:province":"TX",
    "wof:name":"Ordile Sealy Estate Sale Svc",
    "wof:placetype":"venue"
},
  "geometry": {"coordinates":[-97.375542,32.71244],"type":"Point"}
}