{
  "type": "Feature",
  "properties": {
    "iso:country":"US",
    "sg:address":"635 Cross Fence Dr",
    "sg:city":"Mc Kinney",
    "sg:classifiers":[
        {
            "category":"Building & Trades",
            "subcategory":"Landscaping Services",
            "type":"Services"
        }
    ],
    "sg:phone":"+1 972 548 2546",
    "sg:postcode":"75069",
    "sg:province":"TX",
    "sg:tags":[
        "landscape"
    ],
    "wof:name":"Weave Lawn & Landscaping",
    "wof:placetype":"venue"
},
  "geometry": {"coordinates":[-96.533675,33.160122],"type":"Point"}
}