{
  "type": "Feature",
  "properties": {
    "iso:country":"US",
    "sg:address":"3220 Dalworth St",
    "sg:city":"Arlington",
    "sg:classifiers":[
        {
            "category":"Wholesale",
            "subcategory":"Medical Equipment & Supplies",
            "type":"Manufacturing & Wholesale Goods"
        }
    ],
    "sg:phone":"+1 817 877 3227",
    "sg:postcode":"76011",
    "sg:province":"TX",
    "sg:tags":[
        "physician",
        "surgeon"
    ],
    "sg:website":"www.hcs.com",
    "wof:name":"Cornerstone Medical",
    "wof:placetype":"venue"
},
  "geometry": {"coordinates":[-97.046999,32.744753],"type":"Point"}
}