{
  "type": "Feature",
  "properties": {
    "iso:country":"US",
    "sg:address":"1105 Travis Heights Blvd",
    "sg:city":"Austin",
    "sg:classifiers":[
        {
            "category":"Shopping",
            "subcategory":"Computers & Home Electronics",
            "type":"Retail Goods"
        }
    ],
    "sg:phone":"+1 512 912 1302",
    "sg:postcode":"78704",
    "sg:province":"TX",
    "sg:tags":[
        "recorder",
        "time",
        "clock"
    ],
    "sg:website":"http://www.silenttimer.com",
    "wof:name":"Silent Technology",
    "wof:placetype":"venue"
},
  "geometry": {"coordinates":[-97.739047,30.249171],"type":"Point"}
}