{
  "type": "Feature",
  "properties": {
    "iso:country":"US",
    "sg:address":"4817 Reginald Dr",
    "sg:city":"Wichita Falls",
    "sg:classifiers":[
        {
            "category":"Freight",
            "type":"Transportation"
        }
    ],
    "sg:phone":"+1 940 691 1902",
    "sg:postcode":"76308",
    "sg:province":"TX",
    "sg:tags":[
        "operator",
        "trucking"
    ],
    "wof:name":"T C Trux Inc",
    "wof:placetype":"venue"
},
  "geometry": {"coordinates":[-98.540409,33.851984],"type":"Point"}
}