{
  "type": "Feature",
  "properties": {
    "iso:country":"US",
    "sg:address":"3105 Sunlite St",
    "sg:city":"Amarillo",
    "sg:classifiers":[
        {
            "category":"Wholesale",
            "subcategory":"Jewelry",
            "type":"Manufacturing & Wholesale Goods"
        }
    ],
    "sg:phone":"+1 806 358 4871",
    "sg:postcode":"79106",
    "sg:province":"TX",
    "sg:tags":[
        "jeweler"
    ],
    "wof:name":"American Gold & Jewelry",
    "wof:placetype":"venue"
},
  "geometry": {"coordinates":[-101.889467,35.178432],"type":"Point"}
}