{
  "type": "Feature",
  "properties": {
    "iso:country":"US",
    "sg:address":"6000 Craig St",
    "sg:city":"Fort Worth",
    "sg:classifiers":[
        {
            "category":"Shopping",
            "subcategory":"Computers & Home Electronics",
            "type":"Retail Goods"
        }
    ],
    "sg:phone":"+1 817 451 4242",
    "sg:postcode":"76112",
    "sg:province":"TX",
    "sg:tags":[
        "equipment",
        "satellite",
        "system"
    ],
    "wof:name":"DIRECTV",
    "wof:placetype":"venue"
},
  "geometry": {"coordinates":[-97.22748199999999,32.737795],"type":"Point"}
}