{
  "type": "Feature",
  "properties": {
    "iso:country":"US",
    "sg:address":"15444 Tradesman",
    "sg:city":"San Antonio",
    "sg:classifiers":[
        {
            "category":"Utilities",
            "subcategory":"Mobile Phone",
            "type":"Services"
        }
    ],
    "sg:phone":"+1 210 764 2588",
    "sg:postcode":"78249",
    "sg:province":"TX",
    "sg:tags":[
        "communication",
        "radiotelephone"
    ],
    "wof:name":"R-Cellular Inc",
    "wof:placetype":"venue"
},
  "geometry": {"coordinates":[-98.585303,29.58929],"type":"Point"}
}