{
  "type": "Feature",
  "properties": {
    "iso:country":"US",
    "sg:address":"1616 W 6th St Ste 100",
    "sg:city":"Austin",
    "sg:classifiers":[
        {
            "category":"Real Estate",
            "subcategory":"Real Estate Services",
            "type":"Services"
        }
    ],
    "sg:phone":"+1 512 499 8013",
    "sg:postcode":"78703",
    "sg:province":"TX",
    "sg:website":"www.wsgaustin.com",
    "wof:name":"West Side Group",
    "wof:placetype":"venue"
},
  "geometry": {"coordinates":[-97.763563,30.275376],"type":"Point"}
}