{
  "type": "Feature",
  "properties": {
    "iso:country":"US",
    "sg:address":"326 County Road 4160",
    "sg:city":"Bonham",
    "sg:classifiers":[
        {
            "category":"Shopping",
            "subcategory":"Crafts & Fabrics",
            "type":"Retail Goods"
        }
    ],
    "sg:phone":"+1 903 640 0459",
    "sg:postcode":"75418",
    "sg:province":"TX",
    "sg:tags":[
        "shop"
    ],
    "wof:name":"Linda Call Designs",
    "wof:placetype":"venue"
},
  "geometry": {"coordinates":[-96.24979500000001,33.500979],"type":"Point"}
}