{
  "type": "Feature",
  "properties": {
    "iso:country":"US",
    "sg:address":"203 Stillwater",
    "sg:city":"Wimberley",
    "sg:classifiers":[
        {
            "category":"Health Services",
            "subcategory":"Clinic",
            "type":"Services"
        }
    ],
    "sg:phone":"+1 512 847 5678",
    "sg:postcode":"78676",
    "sg:province":"TX",
    "sg:tags":[
        "spa",
        "medical"
    ],
    "wof:name":"Wimberley Medi Spa",
    "wof:placetype":"venue"
},
  "geometry": {"coordinates":[-98.089136,29.990092],"type":"Point"}
}