{
  "type": "Feature",
  "properties": {
    "iso:country":"US",
    "sg:address":"15 Remington Run",
    "sg:city":"San Antonio",
    "sg:classifiers":[
        {
            "category":"Building & Trades",
            "subcategory":"Construction",
            "type":"Services"
        }
    ],
    "sg:phone":"+1 210 497 3676",
    "sg:postcode":"78258",
    "sg:province":"TX",
    "sg:tags":[
        "hanging",
        "contractor"
    ],
    "wof:name":"RPS Painting Inc",
    "wof:placetype":"venue"
},
  "geometry": {"coordinates":[-98.478162,29.654138],"type":"Point"}
}