{
  "type": "Feature",
  "properties": {
    "iso:country":"US",
    "sg:address":"9210 State Hwy 6",
    "sg:city":"Houston",
    "sg:classifiers":[
        {
            "category":"Manufacturing",
            "subcategory":"Retail Goods",
            "type":"Manufacturing & Wholesale Goods"
        }
    ],
    "sg:phone":"+1 281 328 1971",
    "sg:postcode":"77083",
    "sg:province":"TX",
    "sg:tags":[
        "product",
        "mfg"
    ],
    "wof:name":"Stanbridge Eye Center",
    "wof:placetype":"venue"
},
  "geometry": {"coordinates":[-95.643467,29.678988],"type":"Point"}
}