{
  "type": "Feature",
  "properties": {
    "iso:country":"US",
    "sg:address":"1155 US Hwy 380",
    "sg:city":"Bridgeport",
    "sg:classifiers":[
        {
            "category":"Shopping",
            "subcategory":"Stationery & Office Supplies",
            "type":"Retail Goods"
        }
    ],
    "sg:phone":"+1 940 482 7949",
    "sg:postcode":"76426",
    "sg:province":"TX",
    "wof:name":"Sharp Supply Co",
    "wof:placetype":"venue"
},
  "geometry": {"coordinates":[-97.755988,33.222833],"type":"Point"}
}