{
  "type": "Feature",
  "properties": {
    "iso:country":"US",
    "sg:address":"8646 Old Hwy",
    "sg:city":"Calvert",
    "sg:classifiers":[
        {
            "category":"Government",
            "subcategory":"Fire Station",
            "type":"Public Place"
        }
    ],
    "sg:phone":"+1 979 422 5659",
    "sg:postcode":"77837",
    "sg:province":"TX",
    "sg:tags":[
        "department"
    ],
    "wof:name":"Se Falls County Reagen Volunteer Fire Dept",
    "wof:placetype":"venue"
},
  "geometry": {"coordinates":[-96.72917,31.087567],"type":"Point"}
}