{
  "type": "Feature",
  "properties": {
    "iso:country":"US",
    "sg:address":"1010 Oak Grove Ct S",
    "sg:city":"Fort Worth",
    "sg:classifiers":[
        {
            "category":"Shopping",
            "type":"Retail Goods"
        }
    ],
    "sg:phone":"+1 817 921 3895",
    "sg:postcode":"76115",
    "sg:province":"TX",
    "sg:tags":[
        "merchandise"
    ],
    "wof:name":"A&E Resale Shop",
    "wof:placetype":"venue"
},
  "geometry": {"coordinates":[-97.312899,32.670083],"type":"Point"}
}