{
  "type": "Feature",
  "properties": {
    "iso:country":"US",
    "sg:address":"2740 Dallas Pkwy Ste. 280",
    "sg:city":"Plano",
    "sg:phone":"+1 877 237 4790",
    "sg:postcode":"75093",
    "sg:province":"TX",
    "sg:website":"http://www-aerotek-com.netsolads.com/?LEC-6UM982376821&_nsag=33207",
    "wof:name":"Aerotek",
    "wof:placetype":"venue"
},
  "geometry": {"coordinates":[-96.829232,33.036392],"type":"Point"}
}