{
  "type": "Feature",
  "properties": {
    "iso:country":"US",
    "sg:address":"708 McBride Pkwy",
    "sg:city":"Angleton",
    "sg:classifiers":[
        {
            "category":"Retail",
            "subcategory":"Auto Repair",
            "type":"Services"
        }
    ],
    "sg:phone":"+1 979 848 8455",
    "sg:postcode":"77515",
    "sg:province":"TX",
    "sg:tags":[
        "general"
    ],
    "wof:name":"Kruegers Kuston Auto Works",
    "wof:placetype":"venue"
},
  "geometry": {"coordinates":[-95.422438,29.170771],"type":"Point"}
}