{
  "type": "Feature",
  "properties": {
    "iso:country":"US",
    "sg:address":"635 S Main Ave",
    "sg:city":"San Antonio",
    "sg:classifiers":[
        {
            "category":"Government",
            "subcategory":"Office",
            "type":"Public Place"
        }
    ],
    "sg:phone":"+1 210 472 6119",
    "sg:postcode":"78204",
    "sg:province":"TX",
    "sg:tags":[
        "federal"
    ],
    "wof:name":"US General Svc Adm",
    "wof:placetype":"venue"
},
  "geometry": {"coordinates":[-98.49593299999999,29.417939],"type":"Point"}
}