{
  "type": "Feature",
  "properties": {
    "iso:country":"US",
    "sg:address":"800 Stella Mae Dr",
    "sg:city":"Burleson",
    "sg:classifiers":[
        {
            "category":"Building & Trades",
            "subcategory":"Construction",
            "type":"Services"
        }
    ],
    "sg:phone":"+1 817 721 6304",
    "sg:postcode":"76028",
    "sg:province":"TX",
    "sg:tags":[
        "repairing",
        "remodeling",
        "contractor"
    ],
    "wof:name":"All-Star Builders",
    "wof:placetype":"venue"
},
  "geometry": {"coordinates":[-97.30869199999999,32.594794],"type":"Point"}
}