{
  "type": "Feature",
  "properties": {
    "iso:country":"US",
    "sg:address":"8004 Bottlebrush Dr",
    "sg:city":"Austin",
    "sg:classifiers":[
        {
            "category":"Professional",
            "subcategory":"Computer Services",
            "type":"Services"
        }
    ],
    "sg:phone":"+1 512 342 2232",
    "sg:postcode":"78750",
    "sg:province":"TX",
    "sg:tags":[
        "software",
        "retail",
        "developer"
    ],
    "wof:name":"Critical Tools Inc",
    "wof:placetype":"venue"
},
  "geometry": {"coordinates":[-97.800483,30.392565],"type":"Point"}
}