{
  "type": "Feature",
  "properties": {
    "iso:country":"US",
    "sg:address":"4426 Falls Dr",
    "sg:city":"Dallas",
    "sg:classifiers":[
        {
            "category":"Restaurant",
            "type":"Food & Drink"
        }
    ],
    "sg:phone":"+1 214 352 6874",
    "sg:postcode":"75211",
    "sg:province":"TX",
    "sg:tags":[
        "eating"
    ],
    "wof:name":"La Cabana West",
    "wof:placetype":"venue"
},
  "geometry": {"coordinates":[-96.894887,32.726434],"type":"Point"}
}