{
  "type": "Feature",
  "properties": {
    "iso:country":"US",
    "sg:address":"11363 Mathis Ave",
    "sg:city":"Dallas",
    "sg:classifiers":[
        {
            "category":"Recreation",
            "subcategory":"Marina",
            "type":"Entertainment"
        },
        {
            "category":"Manufacturing",
            "subcategory":"Watercraft",
            "type":"Manufacturing & Wholesale Goods"
        }
    ],
    "sg:phone":"+1 972 869 3218",
    "sg:postcode":"75229",
    "sg:province":"TX",
    "sg:tags":[
        "repairing",
        "repair",
        "boat"
    ],
    "wof:name":"Performance Jet Boats Co",
    "wof:placetype":"venue"
},
  "geometry": {"coordinates":[-96.91447700000001,32.894835],"type":"Point"}
}