{
  "type": "Feature",
  "properties": {
    "iso:country":"US",
    "sg:address":"307 W Loop 281",
    "sg:city":"Longview",
    "sg:classifiers":[
        {
            "category":"Shopping",
            "subcategory":"Department Store",
            "type":"Retail Goods"
        }
    ],
    "sg:phone":"+1 903 663 3966",
    "sg:postcode":"75605",
    "sg:province":"TX",
    "sg:tags":[
        "shop"
    ],
    "wof:name":"Pier 1 Imports",
    "wof:placetype":"venue"
},
  "geometry": {"coordinates":[-94.75192300000001,32.541963],"type":"Point"}
}