{
  "type": "Feature",
  "properties": {
    "iso:country":"US",
    "sg:address":"8303 N Mo Pac Expy",
    "sg:city":"Austin",
    "sg:classifiers":[
        {
            "category":"Professional",
            "subcategory":"Employment Agencies",
            "type":"Services"
        }
    ],
    "sg:phone":"+1 512 343 2141",
    "sg:postcode":"78759",
    "sg:province":"TX",
    "sg:tags":[
        "help",
        "contractor"
    ],
    "wof:name":"Manpower Temporary Svc",
    "wof:placetype":"venue"
},
  "geometry": {"coordinates":[-97.74144099999999,30.372032],"type":"Point"}
}