{
  "type": "Feature",
  "properties": {
    "iso:country":"US",
    "sg:address":"4200 Amherst Ave",
    "sg:city":"Dallas",
    "sg:classifiers":[
        {
            "category":"Shopping",
            "subcategory":"Used Merchandise",
            "type":"Retail Goods"
        }
    ],
    "sg:phone":"+1 214 363 7150",
    "sg:postcode":"75225",
    "sg:province":"TX",
    "wof:name":"Acquisitions Two Inc",
    "wof:placetype":"venue"
},
  "geometry": {"coordinates":[-96.808662,32.852112],"type":"Point"}
}