{
  "type": "Feature",
  "properties": {
    "iso:country":"US",
    "sg:address":"603 S May St",
    "sg:city":"Madisonville",
    "sg:classifiers":[
        {
            "category":"Building & Trades",
            "subcategory":"Electrical",
            "type":"Services"
        }
    ],
    "sg:phone":"+1 936 348 9624",
    "sg:postcode":"77864",
    "sg:province":"TX",
    "sg:tags":[
        "electric",
        "contractor"
    ],
    "wof:name":"Ace Electric & Air Cond",
    "wof:placetype":"venue"
},
  "geometry": {"coordinates":[-95.909385,30.946283],"type":"Point"}
}