{
  "type": "Feature",
  "properties": {
    "iso:country":"US",
    "sg:address":"1524 11th St",
    "sg:city":"Huntsville",
    "sg:classifiers":[
        {
            "category":"Professional",
            "subcategory":"Credit Reporting & Collection",
            "type":"Services"
        }
    ],
    "sg:phone":"+1 281 931 5050",
    "sg:postcode":"77320",
    "sg:province":"TX",
    "sg:tags":[
        "agency"
    ],
    "wof:name":"Fma Alliance Ltd",
    "wof:placetype":"venue"
},
  "geometry": {"coordinates":[-95.556152,30.723623],"type":"Point"}
}