{
  "type": "Feature",
  "properties": {
    "iso:country":"US",
    "sg:address":"1203 N Main St",
    "sg:city":"Victoria",
    "sg:classifiers":[
        {
            "category":"Professional",
            "subcategory":"Business Services",
            "type":"Services"
        }
    ],
    "sg:phone":"+1 361 578 5057",
    "sg:postcode":"77901",
    "sg:province":"TX",
    "wof:name":"Clegg Home",
    "wof:placetype":"venue"
},
  "geometry": {"coordinates":[-97.00360000000001,28.80549],"type":"Point"}
}