{
  "type": "Feature",
  "properties": {
    "iso:country":"US",
    "sg:address":"2610 Collard Rd",
    "sg:city":"Arlington",
    "sg:classifiers":[
        {
            "category":"Professional",
            "subcategory":"Engineering",
            "type":"Services"
        }
    ],
    "sg:phone":"+1 817 465 7552",
    "sg:postcode":"76017",
    "sg:province":"TX",
    "wof:name":"Engineering Support Services",
    "wof:placetype":"venue"
},
  "geometry": {"coordinates":[-97.153441,32.656305],"type":"Point"}
}