{
  "type": "Feature",
  "properties": {
    "iso:country":"US",
    "sg:address":"112 S 8th St",
    "sg:city":"Waco",
    "sg:classifiers":[
        {
            "category":"Banks & Credit Unions",
            "subcategory":"Bank",
            "type":"Services"
        }
    ],
    "sg:phone":"+1 254 753 5368",
    "sg:postcode":"76701",
    "sg:province":"TX",
    "sg:tags":[
        "personal",
        "institution"
    ],
    "wof:name":"Lane Finance Service",
    "wof:placetype":"venue"
},
  "geometry": {"coordinates":[-97.133557,31.553809],"type":"Point"}
}