{
  "type": "Feature",
  "properties": {
    "iso:country":"US",
    "sg:address":"119 Greenwich Blvd",
    "sg:city":"San Antonio",
    "sg:classifiers":[
        {
            "category":"Insurance",
            "subcategory":"Insurance Agent",
            "type":"Services"
        }
    ],
    "sg:phone":"+1 210 828 8436",
    "sg:postcode":"78209",
    "sg:province":"TX",
    "wof:name":"Risk MGT Analytical Servicces",
    "wof:placetype":"venue"
},
  "geometry": {"coordinates":[-98.45421899999999,29.48888],"type":"Point"}
}