{
  "type": "Feature",
  "properties": {
    "iso:country":"US",
    "sg:address":"2730 S Brahma Blvd",
    "sg:city":"Kingsville",
    "sg:classifiers":[
        {
            "category":"Professional",
            "type":"Services"
        }
    ],
    "sg:phone":"+1 361 595 1500",
    "sg:postcode":"78363",
    "sg:province":"TX",
    "wof:name":"Cigarettes Cheaper 1456",
    "wof:placetype":"venue"
},
  "geometry": {"coordinates":[-97.85571,27.491078],"type":"Point"}
}