{
  "type": "Feature",
  "properties": {
    "iso:country":"US",
    "sg:address":"301 W Parker Rd",
    "sg:city":"Plano",
    "sg:classifiers":[
        {
            "category":"Banks & Credit Unions",
            "subcategory":"Bank",
            "type":"Services"
        }
    ],
    "sg:phone":"+1 972 424 8577",
    "sg:postcode":"75023",
    "sg:province":"TX",
    "sg:tags":[
        "loan"
    ],
    "wof:name":"Wells Fargo Financial Accptnce",
    "wof:placetype":"venue"
},
  "geometry": {"coordinates":[-96.70710699999999,33.038899],"type":"Point"}
}