{
  "type": "Feature",
  "properties": {
    "iso:country":"US",
    "sg:address":"150 Acorn Path",
    "sg:city":"San Marcos",
    "sg:classifiers":[
        {
            "category":"Personal",
            "subcategory":"Beauty Salon",
            "type":"Services"
        }
    ],
    "sg:phone":"+1 512 452 1844",
    "sg:postcode":"78666",
    "sg:province":"TX",
    "sg:tags":[
        "shop"
    ],
    "wof:name":"Salon E",
    "wof:placetype":"venue"
},
  "geometry": {"coordinates":[-97.96856200000001,29.969743],"type":"Point"}
}