{
  "type": "Feature",
  "properties": {
    "iso:country":"US",
    "sg:address":"4220 Pinemont Dr",
    "sg:city":"Houston",
    "sg:classifiers":[
        {
            "category":"Retail",
            "subcategory":"Laundry & Dry Cleaning",
            "type":"Services"
        },
        {
            "category":"Food & Beverages",
            "subcategory":"Meat & Fish",
            "type":"Retail Goods"
        }
    ],
    "sg:phone":"+1 713 862 2299",
    "sg:postcode":"77018",
    "sg:province":"TX",
    "sg:tags":[
        "shop"
    ],
    "wof:name":"Frenchy's Sausage Co",
    "wof:placetype":"venue"
},
  "geometry": {"coordinates":[-95.449203,29.841101],"type":"Point"}
}