{
  "type": "Feature",
  "properties": {
    "iso:country":"US",
    "sg:address":"1223 W Mcdermott Dr",
    "sg:city":"Allen",
    "sg:classifiers":[
        {
            "category":"Restaurant",
            "type":"Food & Drink"
        }
    ],
    "sg:menulink":"http://www.allmenus.com/tx/plano/34771-thai-pan-restaurant/menu/",
    "sg:phone":"+1 972 747 0057",
    "sg:postcode":"75013",
    "sg:province":"TX",
    "sg:tags":[
        "thai",
        "asian"
    ],
    "wof:name":"Thai Pan Restaurant",
    "wof:placetype":"venue"
},
  "geometry": {"coordinates":[-96.695168,33.100685],"type":"Point"}
}