{
  "type": "Feature",
  "properties": {
    "iso:country":"US",
    "sg:address":"2215 Co Rd 7110",
    "sg:city":"Lubbock",
    "sg:classifiers":[
        {
            "category":"Manufacturing",
            "subcategory":"Metals",
            "type":"Manufacturing & Wholesale Goods"
        }
    ],
    "sg:phone":"+1 806 748 0835",
    "sg:postcode":"79404",
    "sg:province":"TX",
    "sg:tags":[
        "steel",
        "building",
        "mfg",
        "component",
        "structural"
    ],
    "wof:name":"South Plains Steel Inc",
    "wof:placetype":"venue"
},
  "geometry": {"coordinates":[-101.813947,33.517934],"type":"Point"}
}