{
  "type": "Feature",
  "properties": {
    "iso:country":"US",
    "sg:address":"327 W Page Ave",
    "sg:city":"Dallas",
    "sg:classifiers":[
        {
            "category":"Restaurant",
            "type":"Food & Drink"
        }
    ],
    "sg:phone":"+1 214 941 0320",
    "sg:postcode":"75208",
    "sg:province":"TX",
    "sg:tags":[
        "eating"
    ],
    "wof:name":"Rob All Aobut Ribs",
    "wof:placetype":"venue"
},
  "geometry": {"coordinates":[-96.82787,32.740229],"type":"Point"}
}