{
  "type": "Feature",
  "properties": {
    "iso:country":"US",
    "sg:address":"213 S Madison St",
    "sg:city":"Amarillo",
    "sg:classifiers":[
        {
            "category":"Organizations",
            "subcategory":"Religious Organization",
            "type":"Services"
        }
    ],
    "sg:phone":"+1 806 374 3684",
    "sg:postcode":"79101",
    "sg:province":"AR",
    "sg:tags":[
        "church"
    ],
    "wof:name":"Langston Memorial Church-God",
    "wof:placetype":"venue"
},
  "geometry": {"coordinates":[-101.843779,35.211811],"type":"Point"}
}