{
  "type": "Feature",
  "properties": {
    "iso:country":"US",
    "sg:address":"3514 Lindenwood Ave",
    "sg:city":"Dallas",
    "sg:classifiers":[
        {
            "category":"Health Services",
            "subcategory":"Doctor",
            "type":"Services"
        }
    ],
    "sg:phone":"+1 214 528 4713",
    "sg:postcode":"75205",
    "sg:province":"TX",
    "wof:name":"Stephen L Crane",
    "wof:placetype":"venue"
},
  "geometry": {"coordinates":[-96.79080500000001,32.828199],"type":"Point"}
}