{
  "type": "Feature",
  "properties": {
    "iso:country":"US",
    "sg:address":"3312 Kerbey Ln",
    "sg:city":"Austin",
    "sg:classifiers":[
        {
            "category":"Social Services",
            "type":"Services"
        },
        {
            "category":"Professional",
            "subcategory":"Employment Agencies",
            "type":"Services"
        }
    ],
    "sg:phone":"+1 512 482 9260",
    "sg:postcode":"78703",
    "sg:province":"TX",
    "sg:tags":[
        "workers'",
        "placement",
        "volunteer"
    ],
    "wof:name":"Davis Global Foundation",
    "wof:placetype":"venue"
},
  "geometry": {"coordinates":[-97.751785,30.304808],"type":"Point"}
}