{
  "type": "Feature",
  "properties": {
    "iso:country":"US",
    "sg:address":"7209 Golden Hawk Dr",
    "sg:city":"El Paso",
    "sg:classifiers":[
        {
            "category":"Professional",
            "subcategory":"Management & Consulting",
            "type":"Services"
        }
    ],
    "sg:phone":"+1 915 587 5172",
    "sg:postcode":"79912",
    "sg:province":"TX",
    "sg:tags":[
        "business"
    ],
    "wof:name":"Iluminacion Y Potencia LLC",
    "wof:placetype":"venue"
},
  "geometry": {"coordinates":[-106.55450399999999,31.870392],"type":"Point"}
}