{
  "type": "Feature",
  "properties": {
    "iso:country":"US",
    "sg:address":"428 Northwest Mall",
    "sg:city":"Houston",
    "sg:classifiers":[
        {
            "category":"Shopping",
            "subcategory":"Clothing, Apparel, & Fashions",
            "type":"Retail Goods"
        }
    ],
    "sg:phone":"+1 713 957 1180",
    "sg:postcode":"77092",
    "sg:province":"TX",
    "sg:tags":[
        "accessory",
        "clothing",
        "women's"
    ],
    "wof:name":"Melrose No 13",
    "wof:placetype":"venue"
},
  "geometry": {"coordinates":[-95.45259900000001,29.7974],"type":"Point"}
}