{
  "type": "Feature",
  "properties": {
    "iso:country":"US",
    "sg:address":"1614 Cranford Dr",
    "sg:city":"Garland",
    "sg:classifiers":[
        {
            "category":"Professional",
            "type":"Services"
        }
    ],
    "sg:phone":"+1 972 926 8324",
    "sg:postcode":"75041",
    "sg:province":"TX",
    "wof:name":"Mtz Street Machines",
    "wof:placetype":"venue"
},
  "geometry": {"coordinates":[-96.65228,32.877056],"type":"Point"}
}