{
  "type": "Feature",
  "properties": {
    "iso:country":"US",
    "sg:address":"2813 School St",
    "sg:city":"Needville",
    "sg:classifiers":[
        {
            "category":"Donuts",
            "subcategory":"None",
            "type":"Food & Drink"
        }
    ],
    "sg:phone":"+1 979 793 3131",
    "sg:postcode":"77461",
    "sg:province":"TX",
    "sg:tags":[
        "shop"
    ],
    "wof:name":"The Donut Shop",
    "wof:placetype":"venue"
},
  "geometry": {"coordinates":[-95.834875,29.402097],"type":"Point"}
}