{
  "type": "Feature",
  "properties": {
    "iso:country":"US",
    "sg:address":"1530 E Main St",
    "sg:city":"League City",
    "sg:classifiers":[
        {
            "category":"Food & Beverages",
            "subcategory":"Groceries & Convenience Stores",
            "type":"Retail Goods"
        }
    ],
    "sg:phone":"+1 281 554 2886",
    "sg:postcode":"77573",
    "sg:province":"TX",
    "wof:name":"Handy Stop 42",
    "wof:placetype":"venue"
},
  "geometry": {"coordinates":[-95.082076,29.517644],"type":"Point"}
}