{
  "type": "Feature",
  "properties": {
    "iso:country":"US",
    "sg:address":"317 W Concho Ave",
    "sg:city":"San Angelo",
    "sg:classifiers":[
        {
            "category":"Professional",
            "subcategory":"Lawyer & Legal Services",
            "type":"Services"
        }
    ],
    "sg:phone":"+1 325 655 8176",
    "sg:postcode":"76903",
    "sg:province":"TX",
    "sg:tags":[
        "attorney"
    ],
    "wof:name":"Symes Law Firm",
    "wof:placetype":"venue"
},
  "geometry": {"coordinates":[-100.44171,31.458028],"type":"Point"}
}