{
  "type": "Feature",
  "properties": {
    "iso:country":"US",
    "sg:address":"1644 N Main St",
    "sg:city":"Paris",
    "sg:classifiers":[
        {
            "category":"Autos & Motor Vehicles",
            "subcategory":"Automobile Sales",
            "type":"Retail Goods"
        }
    ],
    "sg:phone":"+1 903 737 1969",
    "sg:postcode":"75460",
    "sg:province":"TX",
    "sg:tags":[
        "used"
    ],
    "wof:name":"Hometown Jam Auto Sales",
    "wof:placetype":"venue"
},
  "geometry": {"coordinates":[-95.555623,33.67712],"type":"Point"}
}