{
  "type": "Feature",
  "properties": {
    "iso:country":"US",
    "sg:address":"6035 Derek Trl",
    "sg:city":"Dallas",
    "sg:classifiers":[
        {
            "category":"Organizations",
            "subcategory":"Religious Organization",
            "type":"Services"
        }
    ],
    "sg:phone":"+1 972 931 1545",
    "sg:postcode":"75252",
    "sg:province":"TX",
    "wof:name":"Wang Shih Chu",
    "wof:placetype":"venue"
},
  "geometry": {"coordinates":[-96.80189900000001,33.008208],"type":"Point"}
}