{
  "type": "Feature",
  "properties": {
    "iso:country":"US",
    "sg:address":"2406 Junction Hwy",
    "sg:city":"Kerrville",
    "sg:phone":"+1 830 895 5331",
    "sg:postcode":"78028",
    "sg:province":"TX",
    "sg:tags":[
        "petroleum",
        "product",
        "gas"
    ],
    "wof:name":"Hunt Ingram Gas Co",
    "wof:placetype":"venue"
},
  "geometry": {"coordinates":[-99.195531,30.073698],"type":"Point"}
}