{
  "type": "Feature",
  "properties": {
    "iso:country":"US",
    "sg:address":"10511 Salt Mill Holw",
    "sg:city":"Austin",
    "sg:classifiers":[
        {
            "category":"Place Of Worship",
            "subcategory":"Church",
            "type":"Public Place"
        },
        {
            "category":"Place Of Worship",
            "type":"Public Place"
        }
    ],
    "sg:phone":"+1 512 258 3096",
    "sg:postcode":"78750",
    "sg:province":"TX",
    "sg:tags":[
        "christ",
        "churches-community"
    ],
    "sg:website":"http://www.gcc-am.org",
    "wof:name":"Grace Community Church",
    "wof:placetype":"venue"
},
  "geometry": {"coordinates":[-97.803584,30.454039],"type":"Point"}
}