{
  "type": "Feature",
  "properties": {
    "iso:country":"US",
    "sg:address":"701 Buchanan Dr",
    "sg:city":"Burnet",
    "sg:classifiers":[
        {
            "category":"Restaurant",
            "type":"Food & Drink"
        }
    ],
    "sg:menulink":"http://www.allmenus.com/tx/burnet/70062-pizza-hut/menu/",
    "sg:phone":"+1 512 756 6918",
    "sg:postcode":"78611",
    "sg:province":"TX",
    "sg:tags":[
        "american",
        "pizza"
    ],
    "wof:name":"Pizza Hut",
    "wof:placetype":"venue"
},
  "geometry": {"coordinates":[-98.236602,30.758044],"type":"Point"}
}