{
  "type": "Feature",
  "properties": {
    "iso:country":"US",
    "sg:address":"302 Priest Dr",
    "sg:city":"Killeen",
    "sg:classifiers":[
        {
            "category":"Professional",
            "subcategory":"Detective & Security Services",
            "type":"Services"
        }
    ],
    "sg:phone":"+1 254 634 1919",
    "sg:postcode":"76541",
    "sg:province":"TX",
    "sg:tags":[
        "information",
        "bureau"
    ],
    "wof:name":"Drivers License Service",
    "wof:placetype":"venue"
},
  "geometry": {"coordinates":[-97.735193,31.115141],"type":"Point"}
}