{
  "type": "Feature",
  "properties": {
    "iso:country":"US",
    "sg:address":"615 E Abram St",
    "sg:city":"Arlington",
    "sg:classifiers":[
        {
            "category":"Building & Trades",
            "subcategory":"Cleaning & Sanitation",
            "type":"Services"
        }
    ],
    "sg:phone":"+1 817 366 8400",
    "sg:postcode":"76010",
    "sg:province":"TX",
    "sg:tags":[
        "upholstery",
        "janitor",
        "clean",
        "maintenance",
        "carpet"
    ],
    "wof:name":"Griffin Cleaning Systems",
    "wof:placetype":"venue"
},
  "geometry": {"coordinates":[-97.10028800000001,32.73564],"type":"Point"}
}