{
  "type": "Feature",
  "properties": {
    "iso:country":"US",
    "sg:address":"1516 E Sam Houston Pkwy S Ofc",
    "sg:city":"Pasadena",
    "sg:classifiers":[
        {
            "category":"Real Estate",
            "subcategory":"Real Estate Operator",
            "type":"Services"
        }
    ],
    "sg:phone":"+1 713 472 0300",
    "sg:postcode":"77503",
    "sg:province":"TX",
    "sg:tags":[
        "apartment"
    ],
    "wof:name":"San Agstine Aprtments Phase Ii",
    "wof:placetype":"venue"
},
  "geometry": {"coordinates":[-95.153983,29.687194],"type":"Point"}
}