{
  "type": "Feature",
  "properties": {
    "iso:country":"US",
    "sg:address":"10250 Katy Fwy",
    "sg:city":"Houston",
    "sg:classifiers":[
        {
            "category":"Retail",
            "subcategory":"Auto Rental",
            "type":"Services"
        }
    ],
    "sg:phone":"+1 713 468 2335",
    "sg:postcode":"77043",
    "sg:province":"TX",
    "sg:tags":[
        "car"
    ],
    "sg:website":"www.hertz.com",
    "wof:name":"Hertz Rent-A-Car",
    "wof:placetype":"venue"
},
  "geometry": {"coordinates":[-95.552885,29.784917],"type":"Point"}
}