{
  "type": "Feature",
  "properties": {
    "iso:country":"US",
    "sg:address":"1504 109th St",
    "sg:city":"Grand Prairie",
    "sg:phone":"+1 972 660 6040",
    "sg:postcode":"75050",
    "sg:province":"TX",
    "sg:tags":[
        "equipment",
        "station"
    ],
    "sg:website":"www.rice-christ.com",
    "wof:name":"Rice-Christ Inc",
    "wof:placetype":"venue"
},
  "geometry": {"coordinates":[-97.05308599999999,32.774906],"type":"Point"}
}