{
  "type": "Feature",
  "properties": {
    "iso:country":"US",
    "sg:address":"2 Ambrosia Pl",
    "sg:city":"Spring",
    "sg:classifiers":[
        {
            "category":"Professional",
            "subcategory":"Management & Consulting",
            "type":"Services"
        }
    ],
    "sg:phone":"+1 281 364 4046",
    "sg:postcode":"77381",
    "sg:province":"TX",
    "sg:tags":[
        "fuel"
    ],
    "wof:name":"Guardian Compliance Management",
    "wof:placetype":"venue"
},
  "geometry": {"coordinates":[-95.533193,30.177384],"type":"Point"}
}