{
  "type": "Feature",
  "properties": {
    "iso:country":"US",
    "sg:address":"524 Sellmeyer Ln",
    "sg:city":"Lewisville",
    "sg:classifiers":[
        {
            "category":"Wholesale",
            "subcategory":"Durable Goods & Equipment",
            "type":"Manufacturing & Wholesale Goods"
        }
    ],
    "sg:phone":"+1 972 317 1840",
    "sg:postcode":"75077",
    "sg:province":"TX",
    "sg:tags":[
        "professional"
    ],
    "wof:name":"Telecom Engineering Enter",
    "wof:placetype":"venue"
},
  "geometry": {"coordinates":[-97.04510999999999,33.08126],"type":"Point"}
}