{
  "type": "Feature",
  "properties": {
    "iso:country":"US",
    "sg:address":"2021 Mall Dr",
    "sg:city":"Texarkana",
    "sg:classifiers":[
        {
            "category":"Fast Food",
            "type":"Food & Drink"
        },
        {
            "category":"Restaurant",
            "type":"Food & Drink"
        }
    ],
    "sg:phone":"+1 903 792 1522",
    "sg:postcode":"75503",
    "sg:province":"TX",
    "sg:tags":[
        "cafeteria",
        "home",
        "american",
        "cooking",
        "take"
    ],
    "wof:name":"Bryce's Cafeteria",
    "wof:placetype":"venue"
},
  "geometry": {"coordinates":[-94.068015,33.46372],"type":"Point"}
}