{
  "type": "Feature",
  "properties": {
    "iso:country":"US",
    "sg:address":"301 Hesters Crossing Rd",
    "sg:city":"Round Rock",
    "sg:classifiers":[
        {
            "category":"Health Services",
            "subcategory":"Chiropractor",
            "type":"Services"
        }
    ],
    "sg:phone":"+1 512 388 3880",
    "sg:postcode":"78681",
    "sg:province":"TX",
    "wof:name":"Round Rock Chiropractic",
    "wof:placetype":"venue"
},
  "geometry": {"coordinates":[-97.67775899999999,30.488528],"type":"Point"}
}