{
  "type": "Feature",
  "properties": {
    "iso:country":"US",
    "sg:address":"4406 Lilac Ln",
    "sg:city":"Victoria",
    "sg:classifiers":[
        {
            "category":"Personal",
            "subcategory":"Beauty Salon",
            "type":"Services"
        }
    ],
    "sg:phone":"+1 361 570 4468",
    "sg:postcode":"77901",
    "sg:province":"TX",
    "sg:tags":[
        "manicuring"
    ],
    "wof:name":"It's A Nail Thing",
    "wof:placetype":"venue"
},
  "geometry": {"coordinates":[-96.99868499999999,28.835444],"type":"Point"}
}