{
  "type": "Feature",
  "properties": {
    "iso:country":"US",
    "sg:address":"3814 Cypress Grove Ln",
    "sg:city":"Houston",
    "sg:classifiers":[
        {
            "category":"Retail",
            "subcategory":"Car Wash",
            "type":"Services"
        }
    ],
    "sg:phone":"+1 281 999 8472",
    "sg:postcode":"77088",
    "sg:province":"TX",
    "sg:tags":[
        "carwash"
    ],
    "wof:name":"Dream Wash LLC",
    "wof:placetype":"venue"
},
  "geometry": {"coordinates":[-95.460955,29.865691],"type":"Point"}
}