{
  "type": "Feature",
  "properties": {
    "iso:country":"US",
    "sg:address":"502 Gregory St",
    "sg:city":"Taft",
    "sg:classifiers":[
        {
            "category":"Education",
            "subcategory":"School",
            "type":"Public Place"
        }
    ],
    "sg:phone":"+1 361 643 9568",
    "sg:postcode":"78390",
    "sg:province":"TX",
    "wof:name":"Stephen F Austin Elementary",
    "wof:placetype":"venue"
},
  "geometry": {"coordinates":[-97.39340799999999,27.978943],"type":"Point"}
}