{
  "type": "Feature",
  "properties": {
    "iso:country":"US",
    "sg:address":"217 N Oxford Dr",
    "sg:city":"San Angelo",
    "sg:classifiers":[
        {
            "category":"Building & Trades",
            "subcategory":"Electrical",
            "type":"Services"
        }
    ],
    "sg:phone":"+1 325 944 3713",
    "sg:postcode":"76901",
    "sg:province":"TX",
    "sg:tags":[
        "communications",
        "line",
        "electrical",
        "telephone",
        "contractor"
    ],
    "wof:name":"Electra-Com Services",
    "wof:placetype":"venue"
},
  "geometry": {"coordinates":[-100.485119,31.446368],"type":"Point"}
}