{
  "type": "Feature",
  "properties": {
    "iso:country":"US",
    "sg:address":"11120 Elam Rd",
    "sg:city":"Mesquite",
    "sg:classifiers":[
        {
            "category":"Shopping",
            "subcategory":"Used Merchandise",
            "type":"Retail Goods"
        }
    ],
    "sg:phone":"+1 972 913 1688",
    "sg:postcode":"75180",
    "sg:province":"TX",
    "wof:name":"David Vess",
    "wof:placetype":"venue"
},
  "geometry": {"coordinates":[-96.634837,32.719408],"type":"Point"}
}