{
  "type": "Feature",
  "properties": {
    "iso:country":"US",
    "sg:address":"8504 del Carmen Cove",
    "sg:city":"Austin",
    "sg:classifiers":[
        {
            "category":"Professional",
            "subcategory":"Management & Consulting",
            "type":"Services"
        }
    ],
    "sg:phone":"+1 512 918 3464",
    "sg:postcode":"78759",
    "sg:province":"TX",
    "wof:name":"Sabins Associates",
    "wof:placetype":"venue"
},
  "geometry": {"coordinates":[-97.792281,30.417367],"type":"Point"}
}