{
  "type": "Feature",
  "properties": {
    "iso:country":"US",
    "sg:address":"17141 East Fwy",
    "sg:city":"Channelview",
    "sg:classifiers":[
        {
            "category":"Food & Beverages",
            "subcategory":"Groceries & Convenience Stores",
            "type":"Retail Goods"
        }
    ],
    "sg:phone":"+1 281 457 1817",
    "sg:postcode":"77530",
    "sg:province":"TX",
    "wof:name":"Cobra Truck Stop",
    "wof:placetype":"venue"
},
  "geometry": {"coordinates":[-95.091599,29.790501],"type":"Point"}
}