{
  "type": "Feature",
  "properties": {
    "iso:country":"US",
    "sg:address":"993 E Southcross Blvd",
    "sg:city":"San Antonio",
    "sg:classifiers":[
        {
            "category":"Manufacturing",
            "subcategory":"Signs",
            "type":"Manufacturing & Wholesale Goods"
        }
    ],
    "sg:phone":"+1 210 924 5556",
    "sg:postcode":"78214",
    "sg:province":"TX",
    "sg:tags":[
        "specialty",
        "mfg"
    ],
    "wof:name":"Bratton Brothers Sign Co",
    "wof:placetype":"venue"
},
  "geometry": {"coordinates":[-98.48348300000001,29.371169],"type":"Point"}
}