{
  "type": "Feature",
  "properties": {
    "iso:country":"US",
    "sg:address":"1601 E Alton Gloor Blvd",
    "sg:city":"Brownsville",
    "sg:classifiers":[
        {
            "category":"Restaurant",
            "type":"Food & Drink"
        },
        {
            "category":"Shopping",
            "subcategory":"Books",
            "type":"Retail Goods"
        }
    ],
    "sg:phone":"+1 956 986 2665",
    "sg:postcode":"78521",
    "sg:province":"TX",
    "sg:tags":[
        "eating",
        "dealer"
    ],
    "wof:name":"Last Chapter Books & Coffee Hs",
    "wof:placetype":"venue"
},
  "geometry": {"coordinates":[-97.48504200000001,25.982217],"type":"Point"}
}