{
  "type": "Feature",
  "properties": {
    "iso:country":"US",
    "sg:address":"6832 Northwood Rd",
    "sg:city":"Dallas",
    "sg:classifiers":[
        {
            "category":"Professional",
            "subcategory":"Employment Agencies",
            "type":"Services"
        }
    ],
    "sg:phone":"+1 214 265 1200",
    "sg:postcode":"75225",
    "sg:province":"TX",
    "sg:tags":[
        "consultant",
        "search",
        "executive"
    ],
    "wof:name":"Luby & Assoc",
    "wof:placetype":"venue"
},
  "geometry": {"coordinates":[-96.789973,32.86955],"type":"Point"}
}