{
  "type": "Feature",
  "properties": {
    "iso:country":"US",
    "sg:address":"904 N Grand St",
    "sg:city":"Amarillo",
    "sg:classifiers":[
        {
            "category":"Organizations",
            "subcategory":"Religious Organization",
            "type":"Services"
        }
    ],
    "sg:phone":"+1 806 383 7388",
    "sg:postcode":"79107",
    "sg:province":"TX",
    "wof:name":"Grand Avenue Baptist Church",
    "wof:placetype":"venue"
},
  "geometry": {"coordinates":[-101.79528500000001,35.223732],"type":"Point"}
}