{
  "type": "Feature",
  "properties": {
    "iso:country":"US",
    "sg:address":"1914 E 6th St",
    "sg:city":"Austin",
    "sg:classifiers":[
        {
            "category":"Government",
            "subcategory":"Post Office",
            "type":"Public Place"
        }
    ],
    "sg:phone":"+1 512 472 2644",
    "sg:postcode":"78702",
    "sg:province":"TX",
    "sg:tags":[
        "postal",
        "us"
    ],
    "wof:name":"East Austin Station",
    "wof:placetype":"venue"
},
  "geometry": {"coordinates":[-97.71875199999999,30.260453],"type":"Point"}
}