{
  "type": "Feature",
  "properties": {
    "iso:country":"US",
    "sg:address":"203 Colorado St",
    "sg:city":"Austin",
    "sg:classifiers":[
        {
            "category":"Banks & Credit Unions",
            "subcategory":"Financial Services",
            "type":"Services"
        }
    ],
    "sg:phone":"+1 512 236 3800",
    "sg:postcode":"78701",
    "sg:province":"TX",
    "sg:tags":[
        "shop",
        "sandwich",
        "restaurant"
    ],
    "wof:name":"Schlotzskys Deli",
    "wof:placetype":"venue"
},
  "geometry": {"coordinates":[-97.74539900000001,30.265301],"type":"Point"}
}