{
  "type": "Feature",
  "properties": {
    "iso:country":"US",
    "sg:address":"8204 N Lamar Blvd",
    "sg:city":"Austin",
    "sg:classifiers":[
        {
            "category":"Professional",
            "subcategory":"Research",
            "type":"Services"
        }
    ],
    "sg:phone":"+1 713 941 5335",
    "sg:postcode":"78753",
    "sg:province":"TX",
    "sg:tags":[
        "environmental",
        "ecological"
    ],
    "wof:name":"Cam Environment Svc",
    "wof:placetype":"venue"
},
  "geometry": {"coordinates":[-97.707382,30.352116],"type":"Point"}
}