{
  "type": "Feature",
  "properties": {
    "iso:country":"US",
    "sg:address":"909 E 8th St",
    "sg:city":"Odessa",
    "sg:classifiers":[
        {
            "category":"Autos & Motor Vehicles",
            "subcategory":"Automobile Sales",
            "type":"Retail Goods"
        },
        {
            "category":"Banks & Credit Unions",
            "subcategory":"Bank",
            "type":"Services"
        }
    ],
    "sg:phone":"+1 432 580 3855",
    "sg:postcode":"79761",
    "sg:province":"TX",
    "sg:tags":[
        "financing"
    ],
    "wof:name":"Don Sauls Auto Sale Inc",
    "wof:placetype":"venue"
},
  "geometry": {"coordinates":[-102.362741,31.855566],"type":"Point"}
}