{
  "type": "Feature",
  "properties": {
    "iso:country":"US",
    "sg:address":"6101 E Oltorf St",
    "sg:city":"Austin",
    "sg:classifiers":[
        {
            "category":"Banks & Credit Unions",
            "subcategory":"Bank",
            "type":"Services"
        },
        {
            "category":"Banks & Credit Unions",
            "subcategory":"Financial Services",
            "type":"Services"
        }
    ],
    "sg:phone":"+1 512 389 1543",
    "sg:postcode":"78741",
    "sg:province":"TX",
    "sg:tags":[
        "financing"
    ],
    "wof:name":"Public Employees Credit Union",
    "wof:placetype":"venue"
},
  "geometry": {"coordinates":[-97.71339999999999,30.216583],"type":"Point"}
}