{
  "type": "Feature",
  "properties": {
    "iso:country":"US",
    "sg:address":"3109 Olton Rd",
    "sg:city":"Plainview",
    "sg:classifiers":[
        {
            "category":"Professional",
            "subcategory":"Accounting & Tax Preparation",
            "type":"Services"
        }
    ],
    "sg:phone":"+1 806 293 0564",
    "sg:postcode":"79072",
    "sg:province":"TX",
    "sg:tags":[
        "equipment",
        "accountant"
    ],
    "wof:name":"Barbara G Strain CPA",
    "wof:placetype":"venue"
},
  "geometry": {"coordinates":[-101.741776,34.185227],"type":"Point"}
}