{
  "type": "Feature",
  "properties": {
    "iso:country":"US",
    "sg:address":"1617 Enid St",
    "sg:city":"Houston",
    "sg:classifiers":[
        {
            "category":"Building & Trades",
            "subcategory":"Equipment Rental",
            "type":"Services"
        }
    ],
    "sg:phone":"+1 713 869 3491",
    "sg:postcode":"77009",
    "sg:province":"TX",
    "sg:tags":[
        "scaffolding"
    ],
    "sg:website":"www.scaffold.com",
    "wof:name":"Betco Scaffold",
    "wof:placetype":"venue"
},
  "geometry": {"coordinates":[-95.375643,29.80754],"type":"Point"}
}