{
  "type": "Feature",
  "properties": {
    "iso:country":"US",
    "sg:address":"9800 Brockbank Dr",
    "sg:city":"Dallas",
    "sg:classifiers":[
        {
            "category":"Retail",
            "subcategory":"Auto Repair",
            "type":"Services"
        }
    ],
    "sg:phone":"+1 214 357 1841",
    "sg:postcode":"75220",
    "sg:province":"TX",
    "sg:tags":[
        "repairing",
        "automobile",
        "general"
    ],
    "wof:name":"Cartwrights Motorcar Services",
    "wof:placetype":"venue"
},
  "geometry": {"coordinates":[-96.87535,32.873371],"type":"Point"}
}