{
  "type": "Feature",
  "properties": {
    "iso:country":"US",
    "sg:address":"7335 82nd St",
    "sg:city":"Lubbock",
    "sg:classifiers":[
        {
            "category":"Shopping",
            "type":"Retail Goods"
        }
    ],
    "sg:phone":"+1 806 866 2541",
    "sg:postcode":"79424",
    "sg:province":"TX",
    "sg:tags":[
        "art",
        "gallery",
        "dealer"
    ],
    "wof:name":"Art & Doodles Visual Arts Std",
    "wof:placetype":"venue"
},
  "geometry": {"coordinates":[-101.975781,33.519625],"type":"Point"}
}