{
  "type": "Feature",
  "properties": {
    "iso:country":"US",
    "sg:address":"2997 I- 45 N",
    "sg:city":"New Waverly",
    "sg:classifiers":[
        {
            "category":"Professional",
            "type":"Services"
        }
    ],
    "sg:phone":"+1 936 344 2639",
    "sg:postcode":"77358",
    "sg:province":"TX",
    "sg:tags":[
        "establishment"
    ],
    "wof:name":"Wildwood Shores",
    "wof:placetype":"venue"
},
  "geometry": {"coordinates":[-95.4943,30.486729],"type":"Point"}
}