{
  "type": "Feature",
  "properties": {
    "iso:country":"US",
    "sg:address":"2704 David St",
    "sg:city":"Rosenberg",
    "sg:classifiers":[
        {
            "category":"Professional",
            "type":"Services"
        }
    ],
    "sg:phone":"+1 281 232 3312",
    "sg:postcode":"77471",
    "sg:province":"TX",
    "wof:name":"Schultz Virginia L",
    "wof:placetype":"venue"
},
  "geometry": {"coordinates":[-95.799825,29.539678],"type":"Point"}
}