{
  "type": "Feature",
  "properties": {
    "iso:country":"US",
    "sg:address":"11923 McAuliffe Dr",
    "sg:city":"El Paso",
    "sg:classifiers":[
        {
            "category":"Food & Beverages",
            "subcategory":"Groceries & Convenience Stores",
            "type":"Retail Goods"
        }
    ],
    "sg:phone":"+1 915 593 3554",
    "sg:postcode":"79936",
    "sg:province":"TX",
    "wof:name":"Jj Market Arts & Crafts",
    "wof:placetype":"venue"
},
  "geometry": {"coordinates":[-106.28015600000001,31.756764],"type":"Point"}
}