{
  "type": "Feature",
  "properties": {
    "iso:country":"US",
    "sg:address":"5870 Beldart St",
    "sg:city":"Houston",
    "sg:classifiers":[
        {
            "category":"Social Services",
            "subcategory":"Child Care",
            "type":"Services"
        }
    ],
    "sg:phone":"+1 713 738 0160",
    "sg:postcode":"77033",
    "sg:province":"TX",
    "wof:name":"Rosa Lee Harris",
    "wof:placetype":"venue"
},
  "geometry": {"coordinates":[-95.33141500000001,29.661726],"type":"Point"}
}