{
  "type": "Feature",
  "properties": {
    "iso:country":"US",
    "sg:address":"7963 Bellfort St",
    "sg:city":"Houston",
    "sg:classifiers":[
        {
            "category":"Autos & Motor Vehicles",
            "subcategory":"Automobile Sales",
            "type":"Retail Goods"
        }
    ],
    "sg:phone":"+1 713 242 0955",
    "sg:postcode":"77061",
    "sg:province":"TX",
    "sg:tags":[
        "car",
        "dealer"
    ],
    "wof:name":"Amigo's Cars & Trucks",
    "wof:placetype":"venue"
},
  "geometry": {"coordinates":[-95.27127,29.673106],"type":"Point"}
}