{
  "type": "Feature",
  "properties": {
    "iso:country":"US",
    "sg:address":"144 Bonham Dr",
    "sg:city":"Hewitt",
    "sg:classifiers":[
        {
            "category":"Shopping",
            "type":"Retail Goods"
        }
    ],
    "sg:phone":"+1 254 420 1286",
    "sg:postcode":"76643",
    "sg:province":"TX",
    "sg:tags":[
        "merchandise"
    ],
    "wof:name":"Pet Pride",
    "wof:placetype":"venue"
},
  "geometry": {"coordinates":[-97.207144,31.460195],"type":"Point"}
}