{
  "type": "Feature",
  "properties": {
    "iso:country":"US",
    "sg:address":"430 N Main St",
    "sg:city":"Borger",
    "sg:classifiers":[
        {
            "category":"Home & Garden",
            "subcategory":"Furniture",
            "type":"Retail Goods"
        }
    ],
    "sg:phone":"+1 806 273 5676",
    "sg:postcode":"79007",
    "sg:province":"TX",
    "wof:name":"Smitty's Furniture Mart",
    "wof:placetype":"venue"
},
  "geometry": {"coordinates":[-101.38976700000001,35.670036],"type":"Point"}
}