{
  "type": "Feature",
  "properties": {
    "iso:country":"US",
    "sg:address":"2700 E 29th St Ste 330",
    "sg:city":"Bryan",
    "sg:classifiers":[
        {
            "category":"Health Services",
            "subcategory":"Doctor",
            "type":"Services"
        }
    ],
    "sg:phone":"+1 979 776 5602",
    "sg:postcode":"77802",
    "sg:province":"TX",
    "sg:tags":[
        "gynecology",
        "physician",
        "surgeon",
        "surgeons",
        "obstetrics"
    ],
    "sg:website":"http://www.bvwc.com/",
    "wof:name":"Brazos Valley Women's Center",
    "wof:placetype":"venue"
},
  "geometry": {"coordinates":[-96.346474,30.657061],"type":"Point"}
}