{
  "type": "Feature",
  "properties": {
    "iso:country":"US",
    "sg:address":"1417 W Arkansas Ln",
    "sg:city":"Arlington",
    "sg:classifiers":[
        {
            "category":"Personal",
            "subcategory":"Beauty Salon",
            "type":"Services"
        }
    ],
    "sg:phone":"+1 817 795 1295",
    "sg:postcode":"76013",
    "sg:province":"TX",
    "wof:name":"Christopher Blair Salon",
    "wof:placetype":"venue"
},
  "geometry": {"coordinates":[-97.13195899999999,32.706621],"type":"Point"}
}