{
  "type": "Feature",
  "properties": {
    "iso:country":"US",
    "sg:address":"5302 Stillbrooke Dr",
    "sg:city":"Houston",
    "sg:classifiers":[
        {
            "category":"Professional",
            "type":"Services"
        }
    ],
    "sg:phone":"+1 713 723 2494",
    "sg:postcode":"77096",
    "sg:province":"TX",
    "wof:name":"Tom Kister Inc",
    "wof:placetype":"venue"
},
  "geometry": {"coordinates":[-95.475281,29.664929],"type":"Point"}
}