{
  "type": "Feature",
  "properties": {
    "iso:country":"US",
    "sg:address":"3200 Bonniebrook Dr",
    "sg:city":"Plano",
    "sg:classifiers":[
        {
            "category":"Professional",
            "type":"Services"
        }
    ],
    "sg:phone":"+1 972 596 3838",
    "sg:postcode":"75075",
    "sg:province":"TX",
    "wof:name":"Swpha Inc",
    "wof:placetype":"venue"
},
  "geometry": {"coordinates":[-96.7567,33.017792],"type":"Point"}
}