{
  "type": "Feature",
  "properties": {
    "iso:country":"US",
    "sg:address":"3000 S Belt Line Rd",
    "sg:city":"Dallas",
    "sg:classifiers":[
        {
            "category":"Food & Beverages",
            "subcategory":"Groceries & Convenience Stores",
            "type":"Retail Goods"
        }
    ],
    "sg:phone":"+1 972 286 8700",
    "sg:postcode":"75253",
    "sg:province":"TX",
    "wof:name":"Five Points Grocery Inc",
    "wof:placetype":"venue"
},
  "geometry": {"coordinates":[-96.61769200000001,32.660684],"type":"Point"}
}