{
  "type": "Feature",
  "properties": {
    "iso:country":"US",
    "sg:address":"1010 N Center St",
    "sg:city":"Arlington",
    "sg:classifiers":[
        {
            "category":"Insurance",
            "subcategory":"Insurance Agent",
            "type":"Services"
        }
    ],
    "sg:phone":"+1 817 794 5144",
    "sg:postcode":"76011",
    "sg:province":"TX",
    "wof:name":"Centerpointe Insurance Agency",
    "wof:placetype":"venue"
},
  "geometry": {"coordinates":[-97.10569,32.751583],"type":"Point"}
}