{
  "type": "Feature",
  "properties": {
    "iso:country":"US",
    "sg:address":"508 Westheimer Rd",
    "sg:city":"Houston",
    "sg:classifiers":[
        {
            "category":"Shopping",
            "subcategory":"Shoes",
            "type":"Retail Goods"
        }
    ],
    "sg:phone":"+1 713 877 1867",
    "sg:postcode":"77006",
    "sg:province":"TX",
    "wof:name":"Lady Foot Locker",
    "wof:placetype":"venue"
},
  "geometry": {"coordinates":[-95.38873,29.744587],"type":"Point"}
}