{
  "type": "Feature",
  "properties": {
    "iso:country":"US",
    "sg:address":"577 Rocky Branch Ln",
    "sg:city":"Coppell",
    "sg:classifiers":[
        {
            "category":"Building & Trades",
            "subcategory":"Plumbing",
            "type":"Services"
        }
    ],
    "sg:phone":"+1 972 462 1811",
    "sg:postcode":"75019",
    "sg:province":"TX",
    "sg:tags":[
        "conditioning",
        "air",
        "system",
        "contractor"
    ],
    "wof:name":"Matco Services",
    "wof:placetype":"venue"
},
  "geometry": {"coordinates":[-96.983975,32.956075],"type":"Point"}
}