{
  "type": "Feature",
  "properties": {
    "iso:country":"US",
    "sg:address":"3939 Issacks Way",
    "sg:city":"Sugar Land",
    "sg:classifiers":[
        {
            "category":"Professional",
            "subcategory":"Business Services",
            "type":"Services"
        }
    ],
    "sg:phone":"+1 281 265 7650",
    "sg:postcode":"77479",
    "sg:province":"TX",
    "wof:name":"Tell Tale Design",
    "wof:placetype":"venue"
},
  "geometry": {"coordinates":[-95.594793,29.586834],"type":"Point"}
}