{
  "type": "Feature",
  "properties": {
    "iso:country":"US",
    "sg:address":"1709 San Antonio Street",
    "sg:city":"Austin",
    "sg:classifiers":[
        {
            "category":"Professional",
            "subcategory":"Lawyer & Legal Services",
            "type":"Services"
        }
    ],
    "sg:phone":"+1 512 478 1990",
    "sg:postcode":"78701",
    "sg:province":"TX",
    "wof:name":"Matthews James B Atty",
    "wof:placetype":"venue"
},
  "geometry": {"coordinates":[-97.743347,30.280094],"type":"Point"}
}