{
  "type": "Feature",
  "properties": {
    "iso:country":"US",
    "sg:address":"130 Briarwood",
    "sg:city":"Sulphur Springs",
    "sg:classifiers":[
        {
            "category":"Manufacturing",
            "subcategory":"Apparel",
            "type":"Manufacturing & Wholesale Goods"
        }
    ],
    "sg:phone":"+1 903 885 4814",
    "sg:postcode":"75482",
    "sg:province":"TX",
    "sg:tags":[
        "outerwear",
        "mfg"
    ],
    "wof:name":"Sweet Home Creations",
    "wof:placetype":"venue"
},
  "geometry": {"coordinates":[-95.611074,33.079546],"type":"Point"}
}