{
  "type": "Feature",
  "properties": {
    "iso:country":"US",
    "sg:address":"2219 Par Ln",
    "sg:city":"Richmond",
    "sg:classifiers":[
        {
            "category":"Personal",
            "subcategory":"Beauty Salon",
            "type":"Services"
        }
    ],
    "sg:phone":"+1 281 341 7171",
    "sg:postcode":"77469",
    "sg:province":"TX",
    "wof:name":"Photographic Artistry",
    "wof:placetype":"venue"
},
  "geometry": {"coordinates":[-95.75408299999999,29.566851],"type":"Point"}
}