{
  "type": "Feature",
  "properties": {
    "iso:country":"US",
    "sg:address":"4213 Ramsey Ave",
    "sg:city":"Austin",
    "sg:classifiers":[
        {
            "category":"Professional",
            "subcategory":"Advertising",
            "type":"Services"
        }
    ],
    "sg:phone":"+1 512 680 9575",
    "sg:postcode":"78756",
    "sg:province":"TX",
    "sg:tags":[
        "outdoor"
    ],
    "wof:name":"Capital Outdoors Inc",
    "wof:placetype":"venue"
},
  "geometry": {"coordinates":[-97.745538,30.312823],"type":"Point"}
}