{
  "type": "Feature",
  "properties": {
    "iso:country":"US",
    "sg:address":"11549 Nettie Rose Cir",
    "sg:city":"El Paso",
    "sg:classifiers":[
        {
            "category":"Retail",
            "subcategory":"Auto Repair",
            "type":"Services"
        }
    ],
    "sg:phone":"+1 915 857 0862",
    "sg:postcode":"79936",
    "sg:province":"TX",
    "sg:tags":[
        "body"
    ],
    "wof:name":"Hector C Figueroa",
    "wof:placetype":"venue"
},
  "geometry": {"coordinates":[-106.28992599999999,31.78726],"type":"Point"}
}