{
  "type": "Feature",
  "properties": {
    "iso:country":"US",
    "sg:address":"2111 Kennedy Ln",
    "sg:city":"Texarkana",
    "sg:classifiers":[
        {
            "category":"Social Services",
            "subcategory":"Child Care",
            "type":"Services"
        }
    ],
    "sg:phone":"+1 903 792 8754",
    "sg:postcode":"75503",
    "sg:province":"TX",
    "sg:tags":[
        "day"
    ],
    "wof:name":"Texarkana Tisd Texas",
    "wof:placetype":"venue"
},
  "geometry": {"coordinates":[-94.06784500000001,33.453707],"type":"Point"}
}