{
  "type": "Feature",
  "properties": {
    "iso:country":"US",
    "sg:address":"11981 Memorial Dr",
    "sg:city":"Houston",
    "sg:classifiers":[
        {
            "category":"Government",
            "subcategory":"Police Station",
            "type":"Public Place"
        }
    ],
    "sg:phone":"+1 713 365 3700",
    "sg:postcode":"77024",
    "sg:province":"TX",
    "sg:tags":[
        "department"
    ],
    "sg:website":"http://www.cityofhunterscreek.com",
    "wof:name":"Memorial Villages Police Dept",
    "wof:placetype":"venue"
},
  "geometry": {"coordinates":[-95.53795599999999,29.761999],"type":"Point"}
}