{
  "type": "Feature",
  "properties": {
    "iso:country":"US",
    "sg:address":"1729 Weston Brent Ln",
    "sg:city":"El Paso",
    "sg:classifiers":[
        {
            "category":"Health Services",
            "subcategory":"Doctor",
            "type":"Services"
        }
    ],
    "sg:phone":"+1 915 594 8275",
    "sg:postcode":"79935",
    "sg:province":"TX",
    "sg:tags":[
        "physician",
        "surgeon"
    ],
    "wof:name":"Rio Grande Obgyn Group Pa",
    "wof:placetype":"venue"
},
  "geometry": {"coordinates":[-106.320106,31.763237],"type":"Point"}
}