{
  "type": "Feature",
  "properties": {
    "iso:country":"US",
    "sg:address":"10707 Co Rd 2426",
    "sg:city":"Terrell",
    "sg:classifiers":[
        {
            "category":"Building & Trades",
            "subcategory":"Plumbing",
            "type":"Services"
        }
    ],
    "sg:phone":"+1 972 442 0085",
    "sg:postcode":"75160",
    "sg:province":"TX",
    "sg:tags":[
        "contractor"
    ],
    "wof:name":"Arrow Mechanical",
    "wof:placetype":"venue"
},
  "geometry": {"coordinates":[-96.254468,32.869201],"type":"Point"}
}