{
  "type": "Feature",
  "properties": {
    "iso:country":"US",
    "sg:address":"1427 Grinnell St",
    "sg:city":"Dallas",
    "sg:classifiers":[
        {
            "category":"Professional",
            "subcategory":"Management & Consulting",
            "type":"Services"
        }
    ],
    "sg:phone":"+1 214 376 0819",
    "sg:postcode":"75216",
    "sg:province":"TX",
    "sg:tags":[
        "business"
    ],
    "wof:name":"Financial Systems Consulting",
    "wof:placetype":"venue"
},
  "geometry": {"coordinates":[-96.803669,32.697048],"type":"Point"}
}