{
  "type": "Feature",
  "properties": {
    "iso:country":"US",
    "sg:address":"4600 Applewood Dr",
    "sg:city":"Odessa",
    "sg:classifiers":[
        {
            "category":"Banks & Credit Unions",
            "subcategory":"Financial Services",
            "type":"Services"
        }
    ],
    "sg:phone":"+1 432 950 7306",
    "sg:postcode":"79761",
    "sg:province":"TX",
    "sg:tags":[
        "co",
        "holding"
    ],
    "wof:name":"Scribner Industries Inc",
    "wof:placetype":"venue"
},
  "geometry": {"coordinates":[-102.32185800000001,31.871931],"type":"Point"}
}