{
  "type": "Feature",
  "properties": {
    "iso:country":"US",
    "sg:address":"3818 Copper Mtn",
    "sg:city":"Montgomery",
    "sg:phone":"+1 936 582 4227",
    "sg:postcode":"77356",
    "sg:province":"TX",
    "wof:name":"Z Best",
    "wof:placetype":"venue"
},
  "geometry": {"coordinates":[-95.63170100000001,30.405381],"type":"Point"}
}