{
  "type": "Feature",
  "properties": {
    "iso:country":"US",
    "sg:address":"4233 Mccullough Ave",
    "sg:city":"San Antonio",
    "sg:classifiers":[
        {
            "category":"Restaurant",
            "type":"Food & Drink"
        }
    ],
    "sg:menulink":"http://www.allmenus.com/tx/san-antonio/61658-subway/menu/",
    "sg:phone":"+1 210 826 6215",
    "sg:postcode":"78212",
    "sg:province":"TX",
    "sg:tags":[
        "american",
        "sandwich"
    ],
    "wof:name":"Subway",
    "wof:placetype":"venue"
},
  "geometry": {"coordinates":[-98.49171200000001,29.470399],"type":"Point"}
}