{
  "type": "Feature",
  "properties": {
    "iso:country":"US",
    "sg:address":"1540 State Hwy 46",
    "sg:city":"Seguin",
    "sg:classifiers":[
        {
            "category":"Restaurant",
            "type":"Food & Drink"
        }
    ],
    "sg:phone":"+1 830 401 0195",
    "sg:postcode":"78155",
    "sg:province":"TX",
    "sg:tags":[
        "eating"
    ],
    "wof:name":"Soilita's Cocina Mexicana Inc",
    "wof:placetype":"venue"
},
  "geometry": {"coordinates":[-97.994494,29.587627],"type":"Point"}
}