{
  "type": "Feature",
  "properties": {
    "iso:country":"US",
    "sg:address":"1438 Texas Ave",
    "sg:city":"Texas City",
    "sg:classifiers":[
        {
            "category":"Professional",
            "subcategory":"Employment Agencies",
            "type":"Services"
        }
    ],
    "sg:phone":"+1 409 941 0081",
    "sg:postcode":"77590",
    "sg:province":"TX",
    "sg:tags":[
        "opportunity"
    ],
    "wof:name":"Labor Ready Inc",
    "wof:placetype":"venue"
},
  "geometry": {"coordinates":[-94.915712,29.384013],"type":"Point"}
}