{
  "type": "Feature",
  "properties": {
    "iso:country":"US",
    "sg:address":"151 W Rowson St",
    "sg:city":"San Benito",
    "sg:classifiers":[
        {
            "category":"Professional",
            "subcategory":"Accounting & Tax Preparation",
            "type":"Services"
        }
    ],
    "sg:phone":"+1 956 399 5396",
    "sg:postcode":"78586",
    "sg:province":"TX",
    "sg:tags":[
        "return",
        "filing"
    ],
    "wof:name":"Jordan & Garcia",
    "wof:placetype":"venue"
},
  "geometry": {"coordinates":[-97.632569,26.132011],"type":"Point"}
}