{
  "type": "Feature",
  "properties": {
    "iso:country":"US",
    "sg:address":"620 W 19th St",
    "sg:city":"Houston",
    "sg:classifiers":[
        {
            "category":"Retail",
            "subcategory":"Repair Shop",
            "type":"Services"
        }
    ],
    "sg:phone":"+1 713 864 9269",
    "sg:postcode":"77008",
    "sg:province":"TX",
    "sg:tags":[
        "lawn",
        "chainsaw",
        "mower"
    ],
    "wof:name":"Houston Lawnmower & Saw Works",
    "wof:placetype":"venue"
},
  "geometry": {"coordinates":[-95.40974799999999,29.802712],"type":"Point"}
}