{
  "type": "Feature",
  "properties": {
    "iso:country":"US",
    "sg:address":"1822 S Manhattan St",
    "sg:city":"Amarillo",
    "sg:classifiers":[
        {
            "category":"Organizations",
            "subcategory":"Religious Organization",
            "type":"Services"
        }
    ],
    "sg:phone":"+1 806 376 6828",
    "sg:postcode":"79103",
    "sg:province":"TX",
    "wof:name":"Reorganized Ch LDS",
    "wof:placetype":"venue"
},
  "geometry": {"coordinates":[-101.804261,35.192178],"type":"Point"}
}