{
  "type": "Feature",
  "properties": {
    "iso:country":"US",
    "sg:address":"4111 S 1st Street",
    "sg:city":"Austin",
    "sg:classifiers":[
        {
            "category":"Autos & Motor Vehicles",
            "subcategory":"Fuel & Gas Station",
            "type":"Retail Goods"
        },
        {
            "category":"Food & Beverages",
            "subcategory":"Groceries & Convenience Stores",
            "type":"Retail Goods"
        }
    ],
    "sg:phone":"+1 512 444 2005",
    "sg:postcode":"78745",
    "sg:province":"TX",
    "wof:name":"Diamond Shamrock",
    "wof:placetype":"venue"
},
  "geometry": {"coordinates":[-97.770349,30.224911],"type":"Point"}
}