{
  "type": "Feature",
  "properties": {
    "iso:country":"US",
    "sg:address":"10910 Munn St",
    "sg:city":"Houston",
    "sg:classifiers":[
        {
            "category":"Organizations",
            "subcategory":"Religious Organization",
            "type":"Services"
        }
    ],
    "sg:phone":"+1 713 455 4340",
    "sg:postcode":"77029",
    "sg:province":"TX",
    "wof:name":"Munn Street Baptist Church",
    "wof:placetype":"venue"
},
  "geometry": {"coordinates":[-95.234095,29.763202],"type":"Point"}
}