{
  "type": "Feature",
  "properties": {
    "iso:country":"US",
    "sg:address":"8631 Beechnut St",
    "sg:city":"Houston",
    "sg:classifiers":[
        {
            "category":"Food & Beverages",
            "subcategory":"Liquor & Beverages",
            "type":"Retail Goods"
        }
    ],
    "sg:phone":"+1 713 270 5347",
    "sg:postcode":"77036",
    "sg:province":"TX",
    "sg:tags":[
        "beer",
        "spirit",
        "wine"
    ],
    "wof:name":"Lulu Liquor Store",
    "wof:placetype":"venue"
},
  "geometry": {"coordinates":[-95.53673000000001,29.690555],"type":"Point"}
}