{
  "type": "Feature",
  "properties": {
    "iso:country":"US",
    "sg:address":"141 Red Oaks Dr",
    "sg:city":"Dale",
    "sg:classifiers":[
        {
            "category":"Building & Trades",
            "subcategory":"Construction",
            "type":"Services"
        }
    ],
    "sg:phone":"+1 512 601 1443",
    "sg:postcode":"78616",
    "sg:province":"TX",
    "sg:tags":[
        "carpentry",
        "contractor"
    ],
    "wof:name":"Dyer Inc",
    "wof:placetype":"venue"
},
  "geometry": {"coordinates":[-97.557171,30.036979],"type":"Point"}
}