{
  "type": "Feature",
  "properties": {
    "iso:country":"US",
    "sg:address":"1120 N 20th St",
    "sg:city":"Slaton",
    "sg:classifiers":[
        {
            "category":"Personal",
            "subcategory":"Beauty Salon",
            "type":"Services"
        }
    ],
    "sg:phone":"+1 806 828 5481",
    "sg:postcode":"79364",
    "sg:province":"TX",
    "sg:tags":[
        "shop"
    ],
    "wof:name":"Karlas Kut Up",
    "wof:placetype":"venue"
},
  "geometry": {"coordinates":[-101.657386,33.450166],"type":"Point"}
}