{
  "type": "Feature",
  "properties": {
    "iso:country":"US",
    "sg:address":"6060 Richmond Ave Ste 210",
    "sg:city":"Houston",
    "sg:classifiers":[
        {
            "category":"Health Services",
            "subcategory":"Dentist",
            "type":"Services"
        }
    ],
    "sg:phone":"+1 713 785 0234",
    "sg:postcode":"77057",
    "sg:province":"TX",
    "wof:name":"Salha Fadi C Dds",
    "wof:placetype":"venue"
},
  "geometry": {"coordinates":[-95.486419,29.731965],"type":"Point"}
}