{
  "type": "Feature",
  "properties": {
    "iso:country":"US",
    "sg:address":"1608 Barton Springs Rd",
    "sg:city":"Austin",
    "sg:classifiers":[
        {
            "category":"Food & Beverages",
            "subcategory":"Candy",
            "type":"Retail Goods"
        },
        {
            "category":"Coffee & Tea",
            "type":"Food & Drink"
        },
        {
            "category":"Restaurant",
            "type":"Food & Drink"
        },
        {
            "category":"Food & Beverages",
            "subcategory":"Bakery",
            "type":"Retail Goods"
        }
    ],
    "sg:phone":"+1 512 482 9450",
    "sg:postcode":"78704",
    "sg:province":"TX",
    "sg:tags":[
        "style",
        "sandwich",
        "family",
        "dessert",
        "vegetarian",
        "espresso",
        "traditional",
        "lunch",
        "american",
        "brunch",
        "breakfast"
    ],
    "sg:website":"www.austinjava.com",
    "wof:name":"Austin Java",
    "wof:placetype":"venue"
},
  "geometry": {"coordinates":[-97.761616,30.262012],"type":"Point"}
}