{
  "type": "Feature",
  "properties": {
    "iso:country":"US",
    "sg:address":"5111 N 10th St",
    "sg:city":"Mcallen",
    "sg:classifiers":[
        {
            "category":"Shopping",
            "subcategory":"Computers & Home Electronics",
            "type":"Retail Goods"
        }
    ],
    "sg:phone":"+1 956 682 5137",
    "sg:postcode":"78504",
    "sg:province":"TX",
    "sg:tags":[
        "publishing"
    ],
    "wof:name":"Impact-Research & Publication",
    "wof:placetype":"venue"
},
  "geometry": {"coordinates":[-98.22238299999999,26.248303],"type":"Point"}
}