{
  "type": "Feature",
  "properties": {
    "iso:country":"US",
    "sg:address":"5806 Berkeley Rd",
    "sg:city":"San Angelo",
    "sg:classifiers":[
        {
            "category":"Shopping",
            "subcategory":"Gifts & Souvenirs",
            "type":"Retail Goods"
        }
    ],
    "sg:phone":"+1 325 947 5361",
    "sg:postcode":"76901",
    "sg:province":"TX",
    "wof:name":"Brennas Baskets",
    "wof:placetype":"venue"
},
  "geometry": {"coordinates":[-100.509252,31.443677],"type":"Point"}
}