{
  "type": "Feature",
  "properties": {
    "iso:country":"US",
    "sg:address":"6320 Meadowbrook Dr",
    "sg:city":"Fort Worth",
    "sg:classifiers":[
        {
            "category":"Professional",
            "subcategory":"Accounting & Tax Preparation",
            "type":"Services"
        }
    ],
    "sg:phone":"+1 817 446 5222",
    "sg:postcode":"76112",
    "sg:province":"TX",
    "sg:tags":[
        "return",
        "filing"
    ],
    "wof:name":"Compuquick Tax",
    "wof:placetype":"venue"
},
  "geometry": {"coordinates":[-97.221547,32.746011],"type":"Point"}
}