{
  "type": "Feature",
  "properties": {
    "iso:country":"US",
    "sg:address":"4628 College Park Dr",
    "sg:city":"Dallas",
    "sg:classifiers":[
        {
            "category":"Professional",
            "type":"Services"
        }
    ],
    "sg:phone":"+1 214 739 0306",
    "sg:postcode":"75229",
    "sg:province":"TX",
    "wof:name":"Promobiz Co",
    "wof:placetype":"venue"
},
  "geometry": {"coordinates":[-96.82690100000001,32.903558],"type":"Point"}
}