{
  "type": "Feature",
  "properties": {
    "iso:country":"US",
    "sg:address":"2319 114th St",
    "sg:city":"Lubbock",
    "sg:classifiers":[
        {
            "category":"Wholesale",
            "subcategory":"Durable Goods & Equipment",
            "type":"Manufacturing & Wholesale Goods"
        }
    ],
    "sg:phone":"+1 806 745 6333",
    "sg:postcode":"79423",
    "sg:province":"TX",
    "sg:tags":[
        "representative",
        "manufacturer"
    ],
    "wof:name":"Simpson Technical Sales Co",
    "wof:placetype":"venue"
},
  "geometry": {"coordinates":[-101.86776399999999,33.490716],"type":"Point"}
}