{
  "type": "Feature",
  "properties": {
    "iso:country":"US",
    "sg:address":"3601 Mimosa",
    "sg:city":"Cibolo",
    "sg:classifiers":[
        {
            "category":"Professional",
            "subcategory":"Business Services",
            "type":"Services"
        }
    ],
    "sg:phone":"+1 830 627 3930",
    "sg:postcode":"78108",
    "sg:province":"TX",
    "wof:name":"Strategic Answers",
    "wof:placetype":"venue"
},
  "geometry": {"coordinates":[-98.22583,29.623687],"type":"Point"}
}