{
  "type": "Feature",
  "properties": {
    "iso:country":"US",
    "sg:address":"3601 Sunnypark Dr",
    "sg:city":"Arlington",
    "sg:classifiers":[
        {
            "category":"Home & Garden",
            "subcategory":"Furniture",
            "type":"Retail Goods"
        }
    ],
    "sg:phone":"+1 817 375 1411",
    "sg:postcode":"76014",
    "sg:province":"TX",
    "sg:tags":[
        "store"
    ],
    "wof:name":"I Bex Collection Inc",
    "wof:placetype":"venue"
},
  "geometry": {"coordinates":[-97.107071,32.686131],"type":"Point"}
}