{
  "type": "Feature",
  "properties": {
    "iso:country":"US",
    "sg:address":"1812 Centre Creek Dr. Suite 110",
    "sg:city":"Austin",
    "sg:classifiers":[
        {
            "category":"Building & Trades",
            "subcategory":"Landscaping Services",
            "type":"Services"
        }
    ],
    "sg:phone":"+1 512 506 1360",
    "sg:postcode":"78754",
    "sg:province":"TX",
    "sg:website":"www.lonestarlanddesign.com",
    "wof:name":"Lone Star Land Design",
    "wof:placetype":"venue"
},
  "geometry": {"coordinates":[-97.67702,30.337107],"type":"Point"}
}