{
  "type": "Feature",
  "properties": {
    "iso:country":"US",
    "sg:address":"3050 Little York Rd",
    "sg:city":"Houston",
    "sg:classifiers":[
        {
            "category":"Restaurant",
            "type":"Food & Drink"
        }
    ],
    "sg:phone":"+1 713 695 1208",
    "sg:postcode":"77093",
    "sg:province":"TX",
    "sg:tags":[
        "eating"
    ],
    "wof:name":"Vincents Seafood",
    "wof:placetype":"venue"
},
  "geometry": {"coordinates":[-95.336641,29.871012],"type":"Point"}
}