{
  "type": "Feature",
  "properties": {
    "iso:country":"US",
    "sg:address":"1105 N 5th St",
    "sg:city":"Silsbee",
    "sg:classifiers":[
        {
            "category":"Health Services",
            "subcategory":"Clinic",
            "type":"Services"
        }
    ],
    "sg:phone":"+1 409 385 3352",
    "sg:postcode":"77656",
    "sg:province":"TX",
    "sg:tags":[
        "home"
    ],
    "wof:name":"Texas Home Health",
    "wof:placetype":"venue"
},
  "geometry": {"coordinates":[-94.173897,30.359821],"type":"Point"}
}