{
  "type": "Feature",
  "properties": {
    "iso:country":"US",
    "sg:address":"12824 Carrera Dr",
    "sg:city":"Austin",
    "sg:classifiers":[
        {
            "category":"Professional",
            "subcategory":"Employment Agencies",
            "type":"Services"
        }
    ],
    "sg:phone":"+1 512 918 8725",
    "sg:postcode":"78727",
    "sg:province":"TX",
    "sg:tags":[
        "help",
        "supply"
    ],
    "wof:name":"Bear Backs Productions",
    "wof:placetype":"venue"
},
  "geometry": {"coordinates":[-97.74315799999999,30.437125],"type":"Point"}
}