{
  "type": "Feature",
  "properties": {
    "iso:country":"US",
    "sg:address":"9848 Harwin Dr",
    "sg:city":"Houston",
    "sg:classifiers":[
        {
            "category":"Home & Garden",
            "subcategory":"Home Furnishings",
            "type":"Retail Goods"
        }
    ],
    "sg:phone":"+1 713 787 9848",
    "sg:postcode":"77036",
    "sg:province":"TX",
    "sg:tags":[
        "linen"
    ],
    "wof:name":"Neighbor's Linens",
    "wof:placetype":"venue"
},
  "geometry": {"coordinates":[-95.53656599999999,29.71781],"type":"Point"}
}