{
  "type": "Feature",
  "properties": {
    "iso:country":"US",
    "sg:address":"608 N Union St",
    "sg:city":"Whitesboro",
    "sg:classifiers":[
        {
            "category":"Coffee & Tea",
            "type":"Food & Drink"
        },
        {
            "category":"Bakery",
            "type":"Food & Drink"
        },
        {
            "category":"Donuts",
            "type":"Food & Drink"
        }
    ],
    "sg:menulink":"http://www.allmenus.com/tx/northwest-grayson/231136-daylight-donuts/menu/",
    "sg:phone":"+1 903 564 3411",
    "sg:postcode":"76273",
    "sg:province":"TX",
    "sg:tags":[
        "american",
        "pastry"
    ],
    "wof:name":"Daylight Donuts",
    "wof:placetype":"venue"
},
  "geometry": {"coordinates":[-96.906407,33.66566],"type":"Point"}
}