{
  "type": "Feature",
  "properties": {
    "iso:country":"US",
    "sg:address":"101 W Goodwin Ave",
    "sg:city":"Victoria",
    "sg:classifiers":[
        {
            "category":"Professional",
            "subcategory":"Lawyer & Legal Services",
            "type":"Services"
        }
    ],
    "sg:phone":"+1 361 580 2400",
    "sg:postcode":"77901",
    "sg:province":"TX",
    "sg:tags":[
        "attorney",
        "practice",
        "plan"
    ],
    "wof:name":"Law Office Of Paul A Romano Atty",
    "wof:placetype":"venue"
},
  "geometry": {"coordinates":[-97.005437,28.800821],"type":"Point"}
}