{
  "type": "Feature",
  "properties": {
    "iso:country":"US",
    "sg:address":"7303 Antoine Dr",
    "sg:city":"Houston",
    "sg:classifiers":[
        {
            "category":"Autos & Motor Vehicles",
            "subcategory":"Auto Supplies",
            "type":"Retail Goods"
        }
    ],
    "sg:phone":"+1 281 272 2887",
    "sg:postcode":"77088",
    "sg:province":"TX",
    "sg:tags":[
        "tire"
    ],
    "wof:name":"Monterrey Wheels & Tire",
    "wof:placetype":"venue"
},
  "geometry": {"coordinates":[-95.473018,29.86692],"type":"Point"}
}