{
  "type": "Feature",
  "properties": {
    "iso:country":"US",
    "sg:address":"1635 W Lucas Dr",
    "sg:city":"Beaumont",
    "sg:classifiers":[
        {
            "category":"Building & Trades",
            "subcategory":"Plumbing",
            "type":"Services"
        }
    ],
    "sg:phone":"+1 409 898 2528",
    "sg:postcode":"77706",
    "sg:province":"TX",
    "sg:tags":[
        "plumber",
        "industrial",
        "contractors-commercial"
    ],
    "wof:name":"Beaumont Plumbing",
    "wof:placetype":"venue"
},
  "geometry": {"coordinates":[-94.14747800000001,30.09676],"type":"Point"}
}