{
  "type": "Feature",
  "properties": {
    "iso:country":"US",
    "sg:address":"3234 Clay Ave",
    "sg:city":"Waco",
    "sg:classifiers":[
        {
            "category":"Wholesale",
            "subcategory":"Hardware",
            "type":"Manufacturing & Wholesale Goods"
        }
    ],
    "sg:phone":"+1 254 296 1119",
    "sg:postcode":"76711",
    "sg:province":"TX",
    "sg:tags":[
        "air",
        "parts",
        "conditioning",
        "supply"
    ],
    "wof:name":"Climatic Corp",
    "wof:placetype":"venue"
},
  "geometry": {"coordinates":[-97.151983,31.530553],"type":"Point"}
}