{
  "type": "Feature",
  "properties": {
    "iso:country":"US",
    "sg:address":"125 Baywood Blvd",
    "sg:city":"Mabank",
    "sg:classifiers":[
        {
            "category":"Personal",
            "subcategory":"Barber",
            "type":"Services"
        }
    ],
    "sg:phone":"+1 903 451 4564",
    "sg:postcode":"75156",
    "sg:province":"TX",
    "wof:name":"Barefoot Barber Shop",
    "wof:placetype":"venue"
},
  "geometry": {"coordinates":[-96.11305299999999,32.296791],"type":"Point"}
}