{
  "type": "Feature",
  "properties": {
    "iso:country":"US",
    "sg:address":"1218 Herndon Dr",
    "sg:city":"Rosenberg",
    "sg:classifiers":[
        {
            "category":"Retail",
            "subcategory":"Veterinary Services",
            "type":"Services"
        }
    ],
    "sg:phone":"+1 281 342 6618",
    "sg:postcode":"77471",
    "sg:province":"TX",
    "sg:tags":[
        "veterinarian"
    ],
    "wof:name":"Rosenberg Veterinary Clinic",
    "wof:placetype":"venue"
},
  "geometry": {"coordinates":[-95.780417,29.562249],"type":"Point"}
}