{
  "type": "Feature",
  "properties": {
    "iso:country":"US",
    "sg:address":"333 E Cedar Creek Pkwy",
    "sg:city":"Kemp",
    "sg:classifiers":[
        {
            "category":"Restaurant",
            "type":"Food & Drink"
        }
    ],
    "sg:phone":"+1 903 432 9711",
    "sg:postcode":"75143",
    "sg:province":"TX",
    "sg:tags":[
        "house",
        "steak",
        "barbecue"
    ],
    "wof:name":"Xtreme Bbq",
    "wof:placetype":"venue"
},
  "geometry": {"coordinates":[-96.19501099999999,32.326022],"type":"Point"}
}