{
  "type": "Feature",
  "properties": {
    "iso:country":"US",
    "sg:address":"3350 Harwood Rd",
    "sg:city":"Bedford",
    "sg:classifiers":[
        {
            "category":"Restaurant",
            "type":"Food & Drink"
        }
    ],
    "sg:phone":"+1 817 283 5645",
    "sg:postcode":"76021",
    "sg:province":"TX",
    "sg:tags":[
        "eating"
    ],
    "wof:name":"McDonalds",
    "wof:placetype":"venue"
},
  "geometry": {"coordinates":[-97.11296900000001,32.851733],"type":"Point"}
}