{
  "type": "Feature",
  "properties": {
    "iso:country":"US",
    "sg:address":"100 Jackson St",
    "sg:city":"Houston",
    "sg:classifiers":[
        {
            "category":"Professional",
            "type":"Services"
        }
    ],
    "sg:phone":"+1 713 225 1846",
    "sg:postcode":"77002",
    "sg:province":"TX",
    "wof:name":"Barron Studios",
    "wof:placetype":"venue"
},
  "geometry": {"coordinates":[-95.353931,29.759823],"type":"Point"}
}