{
  "type": "Feature",
  "properties": {
    "iso:country":"US",
    "sg:address":"580 N Pierce St",
    "sg:city":"Quemado",
    "sg:classifiers":[
        {
            "category":"Building & Trades",
            "subcategory":"Equipment Rental",
            "type":"Services"
        }
    ],
    "sg:phone":"+1 830 757 2500",
    "sg:postcode":"78852",
    "sg:province":"TX",
    "sg:tags":[
        "leasing",
        "furniture"
    ],
    "wof:name":"Rent To Own Furniture",
    "wof:placetype":"venue"
},
  "geometry": {"coordinates":[-100.497744,28.712334],"type":"Point"}
}