{
  "type": "Feature",
  "properties": {
    "iso:country":"US",
    "sg:address":"2419 S Market St",
    "sg:city":"Odessa",
    "sg:classifiers":[
        {
            "category":"Retail",
            "subcategory":"Repair Shop",
            "type":"Services"
        },
        {
            "category":"Mining & Drilling",
            "type":"Manufacturing & Wholesale Goods"
        }
    ],
    "sg:phone":"+1 432 580 3887",
    "sg:postcode":"79766",
    "sg:province":"TX",
    "sg:tags":[
        "field",
        "oil",
        "center",
        "equipment"
    ],
    "wof:name":"S P M Flow Control Inc",
    "wof:placetype":"venue"
},
  "geometry": {"coordinates":[-102.323725,31.844835],"type":"Point"}
}