{
  "type": "Feature",
  "properties": {
    "iso:country":"US",
    "sg:address":"5314 Bransford Rd",
    "sg:city":"Colleyville",
    "sg:classifiers":[
        {
            "category":"Social Services",
            "subcategory":"Adult Care",
            "type":"Services"
        }
    ],
    "sg:phone":"+1 817 427 2273",
    "sg:postcode":"76034",
    "sg:province":"TX",
    "sg:tags":[
        "residential"
    ],
    "wof:name":"Colleyville Place",
    "wof:placetype":"venue"
},
  "geometry": {"coordinates":[-97.161525,32.886015],"type":"Point"}
}