{
  "type": "Feature",
  "properties": {
    "iso:country":"US",
    "sg:address":"13738 Tajamar St",
    "sg:city":"Corpus Christi",
    "sg:classifiers":[
        {
            "category":"Building & Trades",
            "subcategory":"Construction",
            "type":"Services"
        }
    ],
    "sg:phone":"+1 361 949 8679",
    "sg:postcode":"78418",
    "sg:province":"TX",
    "sg:tags":[
        "house"
    ],
    "wof:name":"T&G Builders",
    "wof:placetype":"venue"
},
  "geometry": {"coordinates":[-97.234568,27.624989],"type":"Point"}
}