{
  "type": "Feature",
  "properties": {
    "iso:country":"US",
    "sg:address":"5875 Mountain Valley Ln",
    "sg:city":"Dallas",
    "sg:classifiers":[
        {
            "category":"Real Estate",
            "subcategory":"Real Estate Operator",
            "type":"Services"
        }
    ],
    "sg:phone":"+1 214 331 5426",
    "sg:postcode":"75211",
    "sg:province":"TX",
    "sg:tags":[
        "apartment"
    ],
    "wof:name":"Mountain Valley Apartments",
    "wof:placetype":"venue"
},
  "geometry": {"coordinates":[-96.920782,32.734335],"type":"Point"}
}