{
  "type": "Feature",
  "properties": {
    "iso:country":"US",
    "sg:address":"805 S Main St",
    "sg:city":"Kemp",
    "sg:classifiers":[
        {
            "category":"Recreation",
            "type":"Entertainment"
        }
    ],
    "sg:phone":"+1 903 498 7500",
    "sg:postcode":"75143",
    "sg:province":"TX",
    "sg:tags":[
        "instruction",
        "gymnastic"
    ],
    "wof:name":"For My Team Studio & Gym",
    "wof:placetype":"venue"
},
  "geometry": {"coordinates":[-96.228792,32.437181],"type":"Point"}
}