{
  "type": "Feature",
  "properties": {
    "iso:country":"US",
    "sg:address":"5142 Richter St",
    "sg:city":"Corpus Christi",
    "sg:classifiers":[
        {
            "category":"Retail",
            "subcategory":"Auto Repair",
            "type":"Services"
        }
    ],
    "sg:phone":"+1 361 852 2148",
    "sg:postcode":"78415",
    "sg:province":"TX",
    "sg:tags":[
        "glass",
        "coating",
        "tinting"
    ],
    "wof:name":"Auto Trim Of North America",
    "wof:placetype":"venue"
},
  "geometry": {"coordinates":[-97.421027,27.730522],"type":"Point"}
}