{
  "type": "Feature",
  "properties": {
    "iso:country":"US",
    "sg:address":"615 Westwood Cir",
    "sg:city":"La Marque",
    "sg:classifiers":[
        {
            "category":"Building & Trades",
            "subcategory":"Construction",
            "type":"Services"
        }
    ],
    "sg:phone":"+1 409 986 6811",
    "sg:postcode":"77568",
    "sg:province":"TX",
    "sg:tags":[
        "industrial",
        "nonresidential"
    ],
    "wof:name":"RGI",
    "wof:placetype":"venue"
},
  "geometry": {"coordinates":[-95.048456,29.395048],"type":"Point"}
}