{
  "type": "Feature",
  "properties": {
    "iso:country":"US",
    "sg:address":"1440 Le May Dr",
    "sg:city":"Carrollton",
    "sg:classifiers":[
        {
            "category":"Professional",
            "subcategory":"Business Services",
            "type":"Services"
        },
        {
            "category":"Manufacturing",
            "subcategory":"Printing",
            "type":"Manufacturing & Wholesale Goods"
        }
    ],
    "sg:phone":"+1 972 245 7585",
    "sg:postcode":"75007",
    "sg:province":"TX",
    "sg:tags":[
        "commercial",
        "design",
        "broker"
    ],
    "wof:name":"Graphix N More",
    "wof:placetype":"venue"
},
  "geometry": {"coordinates":[-96.923993,32.989222],"type":"Point"}
}