{
  "type": "Feature",
  "properties": {
    "iso:country":"US",
    "sg:address":"1315 Riverchase Dr # 1414",
    "sg:city":"Coppell",
    "sg:classifiers":[
        {
            "category":"Utilities",
            "subcategory":"Water",
            "type":"Services"
        }
    ],
    "sg:phone":"+1 713 534 3866",
    "sg:postcode":"75019",
    "sg:province":"TX",
    "sg:tags":[
        "bulk",
        "companies-bottled"
    ],
    "wof:name":"Where Water Comes Down",
    "wof:placetype":"venue"
},
  "geometry": {"coordinates":[-96.95697,32.954994],"type":"Point"}
}