{
  "type": "Feature",
  "properties": {
    "iso:country":"US",
    "sg:address":"22018 Knoll Lake Ln",
    "sg:city":"Katy",
    "sg:classifiers":[
        {
            "category":"Wholesale",
            "subcategory":"Non-durable Goods",
            "type":"Manufacturing & Wholesale Goods"
        }
    ],
    "sg:phone":"+1 281 395 2939",
    "sg:postcode":"77450",
    "sg:province":"TX",
    "wof:name":"Wam Distributing",
    "wof:placetype":"venue"
},
  "geometry": {"coordinates":[-95.753851,29.760913],"type":"Point"}
}