{
  "type": "Feature",
  "properties": {
    "iso:country":"US",
    "sg:address":"806 N Loop 336 E",
    "sg:city":"Conroe",
    "sg:classifiers":[
        {
            "category":"Shopping",
            "subcategory":"Florist",
            "type":"Retail Goods"
        }
    ],
    "sg:phone":"+1 936 760 3499",
    "sg:postcode":"77301",
    "sg:province":"TX",
    "wof:name":"Flower World-Conroe",
    "wof:placetype":"venue"
},
  "geometry": {"coordinates":[-95.437724,30.339939],"type":"Point"}
}