{
  "type": "Feature",
  "properties": {
    "iso:country":"US",
    "sg:address":"105 W Burleson St",
    "sg:city":"Wharton",
    "sg:classifiers":[
        {
            "category":"Professional",
            "subcategory":"Lawyer & Legal Services",
            "type":"Services"
        }
    ],
    "sg:phone":"+1 979 532 3871",
    "sg:postcode":"77488",
    "sg:province":"TX",
    "sg:tags":[
        "attorney"
    ],
    "wof:name":"Wadler & Perches",
    "wof:placetype":"venue"
},
  "geometry": {"coordinates":[-96.101529,29.310155],"type":"Point"}
}