{
  "type": "Feature",
  "properties": {
    "iso:country":"US",
    "sg:address":"1649 W Northwest Hwy",
    "sg:city":"Grapevine",
    "sg:classifiers":[
        {
            "category":"Shopping",
            "subcategory":"Used Merchandise",
            "type":"Retail Goods"
        }
    ],
    "sg:phone":"+1 817 416 2953",
    "sg:postcode":"76051",
    "sg:province":"TX",
    "wof:name":"Second Glance CL & Furn Resal",
    "wof:placetype":"venue"
},
  "geometry": {"coordinates":[-97.092821,32.941036],"type":"Point"}
}