{
  "type": "Feature",
  "properties": {
    "iso:country":"US",
    "sg:address":"1500 Co Rd 705",
    "sg:city":"Joshua",
    "sg:classifiers":[
        {
            "category":"Building & Trades",
            "subcategory":"Plumbing",
            "type":"Services"
        }
    ],
    "sg:phone":"+1 817 558 0403",
    "sg:postcode":"76058",
    "sg:province":"TX",
    "sg:tags":[
        "septic"
    ],
    "wof:name":"Johnson County Septic Svc",
    "wof:placetype":"venue"
},
  "geometry": {"coordinates":[-97.354784,32.433187],"type":"Point"}
}