{
  "type": "Feature",
  "properties": {
    "iso:country":"US",
    "sg:address":"5420 Hwy 78",
    "sg:city":"Sachse",
    "sg:classifiers":[
        {
            "category":"Autos & Motor Vehicles",
            "subcategory":"Auto Supplies",
            "type":"Retail Goods"
        }
    ],
    "sg:phone":"+1 972 675 4012",
    "sg:postcode":"75048",
    "sg:province":"TX",
    "sg:tags":[
        "tire"
    ],
    "sg:website":"www.ntb.com/default.aspx",
    "wof:name":"NTB",
    "wof:placetype":"venue"
},
  "geometry": {"coordinates":[-96.602148,32.971414],"type":"Point"}
}