{
  "type": "Feature",
  "properties": {
    "iso:country":"US",
    "sg:address":"1105 Lloyd Ave",
    "sg:city":"Big Spring",
    "sg:classifiers":[
        {
            "category":"Professional",
            "subcategory":"Business Services",
            "type":"Services"
        }
    ],
    "sg:phone":"+1 432 263 4005",
    "sg:postcode":"79720",
    "sg:province":"TX",
    "wof:name":"Fgs Sales & Service",
    "wof:placetype":"venue"
},
  "geometry": {"coordinates":[-101.459883,32.252896],"type":"Point"}
}