{
  "type": "Feature",
  "properties": {
    "iso:country":"US",
    "sg:address":"3905 Vangie Ln",
    "sg:city":"Harlingen",
    "sg:classifiers":[
        {
            "category":"Shopping",
            "subcategory":"Florist",
            "type":"Retail Goods"
        }
    ],
    "sg:phone":"+1 956 425 2507",
    "sg:postcode":"78552",
    "sg:province":"TX",
    "wof:name":"Homes By Ron Carroll",
    "wof:placetype":"venue"
},
  "geometry": {"coordinates":[-97.73635299999999,26.198803],"type":"Point"}
}