{
  "type": "Feature",
  "properties": {
    "iso:country":"US",
    "sg:address":"812 Hawthorne St",
    "sg:city":"Houston",
    "sg:classifiers":[
        {
            "category":"Health Services",
            "subcategory":"Health Practitioner",
            "type":"Services"
        }
    ],
    "sg:phone":"+1 713 529 5800",
    "sg:postcode":"77006",
    "sg:province":"TX",
    "sg:tags":[
        "psychologist"
    ],
    "wof:name":"Montrose Psychotherapy PC",
    "wof:placetype":"venue"
},
  "geometry": {"coordinates":[-95.38981099999999,29.742453],"type":"Point"}
}