{
  "type": "Feature",
  "properties": {
    "iso:country":"US",
    "sg:address":"1301 Main St",
    "sg:city":"Dallas",
    "sg:classifiers":[
        {
            "category":"Professional",
            "subcategory":"Management & Consulting",
            "type":"Services"
        }
    ],
    "sg:phone":"+1 214 752 7110",
    "sg:postcode":"75202",
    "sg:province":"TX",
    "sg:tags":[
        "consultant",
        "educational"
    ],
    "wof:name":"Chambers Of Knowledge",
    "wof:placetype":"venue"
},
  "geometry": {"coordinates":[-96.800184,32.780425],"type":"Point"}
}