{
  "type": "Feature",
  "properties": {
    "iso:country":"US",
    "sg:address":"3600 Waketon Rd",
    "sg:city":"Flower Mound",
    "sg:classifiers":[
        {
            "category":"Building & Trades",
            "subcategory":"Construction",
            "type":"Services"
        }
    ],
    "sg:phone":"+1 972 539 7026",
    "sg:postcode":"75028",
    "sg:province":"TX",
    "sg:tags":[
        "restoration",
        "cleaning",
        "patio",
        "deck"
    ],
    "wof:name":"Jim's Pressure Washing",
    "wof:placetype":"venue"
},
  "geometry": {"coordinates":[-97.08170800000001,33.062645],"type":"Point"}
}