{
  "type": "Feature",
  "properties": {
    "iso:country":"US",
    "sg:address":"3350 Wedgewood Dr",
    "sg:city":"El Paso",
    "sg:classifiers":[
        {
            "category":"Food & Beverages",
            "subcategory":"Groceries & Convenience Stores",
            "type":"Retail Goods"
        }
    ],
    "sg:phone":"+1 915 591 7573",
    "sg:postcode":"79925",
    "sg:province":"TX",
    "sg:tags":[
        "grocer"
    ],
    "wof:name":"Duran Brothers Inc",
    "wof:placetype":"venue"
},
  "geometry": {"coordinates":[-106.348417,31.794114],"type":"Point"}
}