{
  "type": "Feature",
  "properties": {
    "iso:country":"US",
    "sg:address":"7932 Mariann Rd",
    "sg:city":"Ore City",
    "sg:classifiers":[
        {
            "category":"Autos & Motor Vehicles",
            "subcategory":"Auto Supplies",
            "type":"Retail Goods"
        }
    ],
    "sg:phone":"+1 903 968 4807",
    "sg:postcode":"75683",
    "sg:province":"TX",
    "wof:name":"Lakeside Enterprises",
    "wof:placetype":"venue"
},
  "geometry": {"coordinates":[-94.716872,32.843479],"type":"Point"}
}