{
  "type": "Feature",
  "properties": {
    "iso:country":"US",
    "sg:address":"120 N Victoria St",
    "sg:city":"Victoria",
    "sg:classifiers":[
        {
            "category":"Professional",
            "subcategory":"Computer Services",
            "type":"Services"
        }
    ],
    "sg:phone":"+1 361 572 3230",
    "sg:postcode":"77901",
    "sg:province":"TX",
    "sg:tags":[
        "internet"
    ],
    "sg:website":"www.victoriatexas.net",
    "wof:name":"Victoria Internet Providers",
    "wof:placetype":"venue"
},
  "geometry": {"coordinates":[-97.01052199999999,28.801397],"type":"Point"}
}