{
  "type": "Feature",
  "properties": {
    "iso:country":"US",
    "sg:address":"9224 Markville Dr",
    "sg:city":"Dallas",
    "sg:classifiers":[
        {
            "category":"Social Services",
            "type":"Services"
        }
    ],
    "sg:phone":"+1 972 907 0284",
    "sg:postcode":"75243",
    "sg:province":"TX",
    "wof:name":"Operating Rescue Dfw",
    "wof:placetype":"venue"
},
  "geometry": {"coordinates":[-96.74021399999999,32.913633],"type":"Point"}
}