{
  "type": "Feature",
  "properties": {
    "iso:country":"US",
    "sg:address":"411 W US Hwy 83",
    "sg:city":"Mcallen",
    "sg:classifiers":[
        {
            "category":"Autos & Motor Vehicles",
            "subcategory":"Auto Supplies",
            "type":"Retail Goods"
        }
    ],
    "sg:phone":"+1 956 687 8697",
    "sg:postcode":"78501",
    "sg:province":"TX",
    "sg:tags":[
        "automobile",
        "accessory"
    ],
    "wof:name":"Car Toys Inc",
    "wof:placetype":"venue"
},
  "geometry": {"coordinates":[-98.224226,26.202224],"type":"Point"}
}