{
  "type": "Feature",
  "properties": {
    "iso:country":"US",
    "sg:address":"1055 Co Rd 237",
    "sg:city":"Giddings",
    "sg:classifiers":[
        {
            "category":"Mining & Drilling",
            "type":"Manufacturing & Wholesale Goods"
        }
    ],
    "sg:phone":"+1 979 778 5420",
    "sg:postcode":"78942",
    "sg:province":"TX",
    "sg:tags":[
        "field"
    ],
    "wof:name":"Computalog USA Inc",
    "wof:placetype":"venue"
},
  "geometry": {"coordinates":[-96.857885,30.167979],"type":"Point"}
}