{
  "type": "Feature",
  "properties": {
    "iso:country":"US",
    "sg:address":"5010 W Loop 250 N",
    "sg:city":"Midland",
    "sg:classifiers":[
        {
            "category":"Building & Trades",
            "subcategory":"Cleaning & Sanitation",
            "type":"Services"
        }
    ],
    "sg:phone":"+1 432 425 9765",
    "sg:postcode":"79707",
    "sg:province":"TX",
    "sg:tags":[
        "window"
    ],
    "wof:name":"Elite Window Washing",
    "wof:placetype":"venue"
},
  "geometry": {"coordinates":[-102.15325300000001,32.021712],"type":"Point"}
}