{
  "type": "Feature",
  "properties": {
    "iso:country":"US",
    "sg:address":"2538 Crenshaw Dr",
    "sg:city":"Round Rock",
    "sg:classifiers":[
        {
            "category":"Real Estate",
            "subcategory":"Real Estate Agent",
            "type":"Services"
        }
    ],
    "sg:phone":"+1 512 388 9657",
    "sg:postcode":"78664",
    "sg:province":"TX",
    "wof:name":"Sorensen Properties",
    "wof:placetype":"venue"
},
  "geometry": {"coordinates":[-97.601383,30.516553],"type":"Point"}
}