{
  "type": "Feature",
  "properties": {
    "iso:country":"US",
    "sg:address":"6259 Granbury Rd",
    "sg:city":"Fort Worth",
    "sg:classifiers":[
        {
            "category":"Shopping",
            "type":"Retail Goods"
        }
    ],
    "sg:phone":"+1 817 263 6881",
    "sg:postcode":"76133",
    "sg:province":"TX",
    "sg:tags":[
        "cosmetic",
        "perfume"
    ],
    "wof:name":"Beauty Ware",
    "wof:placetype":"venue"
},
  "geometry": {"coordinates":[-97.40087800000001,32.658455],"type":"Point"}
}