{
  "type": "Feature",
  "properties": {
    "iso:country":"US",
    "sg:address":"902 Bandera Ct",
    "sg:city":"Allen",
    "sg:classifiers":[
        {
            "category":"Building & Trades",
            "subcategory":"Construction",
            "type":"Services"
        }
    ],
    "sg:phone":"+1 214 495 7377",
    "sg:postcode":"75013",
    "sg:province":"TX",
    "sg:tags":[
        "nonresidential"
    ],
    "wof:name":"Mega Wraps Dfw",
    "wof:placetype":"venue"
},
  "geometry": {"coordinates":[-96.710855,33.111874],"type":"Point"}
}