{
  "type": "Feature",
  "properties": {
    "iso:country":"US",
    "sg:address":"2525 Wallingwood Bldg. 1 Suite 211",
    "sg:city":"Austin",
    "sg:classifiers":[
        {
            "category":"Health Services",
            "subcategory":"Clinic",
            "type":"Services"
        }
    ],
    "sg:phone":"+1 206 612 3651",
    "sg:postcode":"78746",
    "sg:province":"TX",
    "sg:tags":[
        "counseling",
        "mental"
    ],
    "wof:name":"Dawn Grace, CCHt",
    "wof:placetype":"venue"
},
  "geometry": {"coordinates":[-97.782854,30.264913],"type":"Point"}
}