{
  "type": "Feature",
  "properties": {
    "iso:country":"US",
    "sg:address":"7800 Emmett F Lowry Expy",
    "sg:city":"Texas City",
    "sg:classifiers":[
        {
            "category":"Manufacturing",
            "subcategory":"Printing",
            "type":"Manufacturing & Wholesale Goods"
        }
    ],
    "sg:phone":"+1 409 935 2108",
    "sg:postcode":"77591",
    "sg:province":"TX",
    "sg:tags":[
        "newspaper"
    ],
    "sg:website":"www.texascitysun.com",
    "wof:name":"Texas City Sun",
    "wof:placetype":"venue"
},
  "geometry": {"coordinates":[-95.00008099999999,29.398207],"type":"Point"}
}