{
  "type": "Feature",
  "properties": {
    "iso:country":"US",
    "sg:address":"11114 Rendezvous Dr",
    "sg:city":"San Antonio",
    "sg:classifiers":[
        {
            "category":"Shopping",
            "type":"Retail Goods"
        }
    ],
    "sg:phone":"+1 210 341 6393",
    "sg:postcode":"78216",
    "sg:province":"TX",
    "sg:tags":[
        "merchandise"
    ],
    "wof:name":"Square Bear Crafts",
    "wof:placetype":"venue"
},
  "geometry": {"coordinates":[-98.494727,29.542385],"type":"Point"}
}