{
  "type": "Feature",
  "properties": {
    "iso:country":"US",
    "sg:address":"904 Industrial Blvd",
    "sg:city":"Robstown",
    "sg:classifiers":[
        {
            "category":"Building & Trades",
            "subcategory":"Construction",
            "type":"Services"
        }
    ],
    "sg:phone":"+1 361 387 2795",
    "sg:postcode":"78380",
    "sg:province":"TX",
    "sg:tags":[
        "paving",
        "contractor"
    ],
    "wof:name":"Ram-Bro Contracting Inc",
    "wof:placetype":"venue"
},
  "geometry": {"coordinates":[-97.655922,27.785942],"type":"Point"}
}