{
  "type": "Feature",
  "properties": {
    "iso:country":"US",
    "sg:address":"11401 Century Oaks Ter Ste 200",
    "sg:city":"Austin",
    "sg:classifiers":[
        {
            "category":"Professional",
            "subcategory":"Art Services",
            "type":"Services"
        },
        {
            "category":"Professional",
            "subcategory":"Business Services",
            "type":"Services"
        }
    ],
    "sg:phone":"+1 512 977 0520",
    "sg:postcode":"78758",
    "sg:province":"TX",
    "sg:tags":[
        "development",
        "product",
        "designer",
        "designers-industrial",
        "marketing",
        "commercial",
        "design",
        "interior",
        "decorator"
    ],
    "sg:website":"http://www.computerrenditions.com",
    "wof:name":"Carson Design Associates",
    "wof:placetype":"venue"
},
  "geometry": {"coordinates":[-97.72673,30.400539],"type":"Point"}
}