{
  "type": "Feature",
  "properties": {
    "iso:country":"US",
    "sg:address":"2917 W Industrial Ave",
    "sg:city":"Midland",
    "sg:classifiers":[
        {
            "category":"Retail",
            "subcategory":"Repair Shop",
            "type":"Services"
        }
    ],
    "sg:phone":"+1 432 570 1117",
    "sg:postcode":"79701",
    "sg:province":"TX",
    "sg:tags":[
        "equipment",
        "conditioning",
        "air"
    ],
    "wof:name":"Pure Air Cond & Refrigeration",
    "wof:placetype":"venue"
},
  "geometry": {"coordinates":[-102.09903,31.982686],"type":"Point"}
}