{
  "type": "Feature",
  "properties": {
    "iso:country":"US",
    "sg:address":"519 Mission Viejo",
    "sg:city":"San Antonio",
    "sg:classifiers":[
        {
            "category":"Shopping",
            "subcategory":"Gifts & Souvenirs",
            "type":"Retail Goods"
        }
    ],
    "sg:phone":"+1 210 496 6732",
    "sg:postcode":"78232",
    "sg:province":"TX",
    "sg:tags":[
        "collectible"
    ],
    "wof:name":"Corinthian Collection",
    "wof:placetype":"venue"
},
  "geometry": {"coordinates":[-98.504953,29.590369],"type":"Point"}
}