{
  "type": "Feature",
  "properties": {
    "iso:country":"US",
    "sg:address":"3930 Cobblestone Dr",
    "sg:city":"Dallas",
    "sg:classifiers":[
        {
            "category":"Professional",
            "subcategory":"Management & Consulting",
            "type":"Services"
        }
    ],
    "sg:phone":"+1 214 676 1556",
    "sg:postcode":"75229",
    "sg:province":"TX",
    "sg:tags":[
        "consultant"
    ],
    "wof:name":"Hilltop Consulting Svc",
    "wof:placetype":"venue"
},
  "geometry": {"coordinates":[-96.84750699999999,32.889259],"type":"Point"}
}