{
  "type": "Feature",
  "properties": {
    "iso:country":"US",
    "sg:address":"4212 Medical Pkwy",
    "sg:city":"Austin",
    "sg:classifiers":[
        {
            "category":"Health Services",
            "subcategory":"Health Practitioner",
            "type":"Services"
        }
    ],
    "sg:phone":"+1 512 323 9253",
    "sg:postcode":"78756",
    "sg:province":"TX",
    "sg:tags":[
        "psychologist"
    ],
    "wof:name":"Austin American Sleep Dgnstc",
    "wof:placetype":"venue"
},
  "geometry": {"coordinates":[-97.74240899999999,30.312337],"type":"Point"}
}