{
  "type": "Feature",
  "properties": {
    "iso:country":"US",
    "sg:address":"810 18th St",
    "sg:city":"Hondo",
    "sg:classifiers":[
        {
            "category":"Freight",
            "type":"Transportation"
        }
    ],
    "sg:phone":"+1 830 741 4485",
    "sg:postcode":"78861",
    "sg:province":"TX",
    "sg:tags":[
        "commercial",
        "storage"
    ],
    "wof:name":"Hondo Attic Self Storage",
    "wof:placetype":"venue"
},
  "geometry": {"coordinates":[-99.137072,29.348595],"type":"Point"}
}