{
  "type": "Feature",
  "properties": {
    "iso:country":"US",
    "sg:address":"149 W Kingsley Rd Ste 226",
    "sg:city":"Garland",
    "sg:classifiers":[
        {
            "category":"Shopping",
            "subcategory":"Clothing, Apparel, & Fashions",
            "type":"Retail Goods"
        },
        {
            "category":"Shopping",
            "subcategory":"Department Store",
            "type":"Retail Goods"
        }
    ],
    "sg:phone":"+1 972 926 9201",
    "sg:postcode":"75041",
    "sg:province":"TX",
    "sg:tags":[
        "apparel",
        "clothing",
        "women's"
    ],
    "wof:name":"Levine's Department Store",
    "wof:placetype":"venue"
},
  "geometry": {"coordinates":[-96.63152599999999,32.878819],"type":"Point"}
}