{
  "type": "Feature",
  "properties": {
    "iso:country":"US",
    "sg:address":"9653 Olive Dr",
    "sg:city":"Princeton",
    "sg:classifiers":[
        {
            "category":"Building & Trades",
            "subcategory":"Construction",
            "type":"Services"
        }
    ],
    "sg:phone":"+1 972 736 3144",
    "sg:postcode":"75407",
    "sg:province":"TX",
    "sg:tags":[
        "excavating",
        "contractor"
    ],
    "wof:name":"Ace Trenching",
    "wof:placetype":"venue"
},
  "geometry": {"coordinates":[-96.516983,33.108277],"type":"Point"}
}