{
  "type": "Feature",
  "properties": {
    "iso:country":"US",
    "sg:address":"408 W College St",
    "sg:city":"Carthage",
    "sg:classifiers":[
        {
            "category":"Professional",
            "subcategory":"Business Services",
            "type":"Services"
        }
    ],
    "sg:phone":"+1 903 693 4444",
    "sg:postcode":"75633",
    "sg:province":"TX",
    "wof:name":"Time and Temperature Carthage",
    "wof:placetype":"venue"
},
  "geometry": {"coordinates":[-94.34433,32.158254],"type":"Point"}
}