{
  "type": "Feature",
  "properties": {
    "iso:country":"US",
    "sg:address":"602 W Main St",
    "sg:city":"Olney",
    "sg:classifiers":[
        {
            "category":"Personal",
            "subcategory":"Beauty Salon",
            "type":"Services"
        }
    ],
    "sg:phone":"+1 940 564 2062",
    "sg:postcode":"76374",
    "sg:province":"TX",
    "sg:tags":[
        "shop"
    ],
    "wof:name":"Style Beauty Shop",
    "wof:placetype":"venue"
},
  "geometry": {"coordinates":[-98.761296,33.370705],"type":"Point"}
}