{
  "type": "Feature",
  "properties": {
    "iso:country":"US",
    "sg:address":"1801 Idaho Ave",
    "sg:city":"Dallas",
    "sg:classifiers":[
        {
            "category":"Organizations",
            "subcategory":"Religious Organization",
            "type":"Services"
        }
    ],
    "sg:phone":"+1 214 941 7367",
    "sg:postcode":"75216",
    "sg:province":"TX",
    "sg:tags":[
        "church"
    ],
    "wof:name":"New Canaan Missionary Baptist",
    "wof:placetype":"venue"
},
  "geometry": {"coordinates":[-96.81201299999999,32.725031],"type":"Point"}
}