{
  "type": "Feature",
  "properties": {
    "iso:country":"US",
    "sg:address":"8710 Puerto Marques",
    "sg:city":"Laredo",
    "sg:classifiers":[
        {
            "category":"Building & Trades",
            "subcategory":"Plumbing",
            "type":"Services"
        }
    ],
    "sg:phone":"+1 956 725 6601",
    "sg:postcode":"78045",
    "sg:province":"TX",
    "sg:tags":[
        "plumbing",
        "heating",
        "air"
    ],
    "wof:name":"Smith Brothers AC",
    "wof:placetype":"venue"
},
  "geometry": {"coordinates":[-99.47942,27.587242],"type":"Point"}
}