{
  "type": "Feature",
  "properties": {
    "iso:country":"US",
    "sg:address":"3030 Nacogdoches Rd",
    "sg:city":"San Antonio",
    "sg:classifiers":[
        {
            "category":"Professional",
            "subcategory":"Detective & Security Services",
            "type":"Services"
        }
    ],
    "sg:phone":"+1 210 227 6485",
    "sg:postcode":"78217",
    "sg:province":"TX",
    "sg:tags":[
        "guard"
    ],
    "wof:name":"Smith Legacy Security",
    "wof:placetype":"venue"
},
  "geometry": {"coordinates":[-98.439801,29.525891],"type":"Point"}
}