{
  "type": "Feature",
  "properties": {
    "iso:country":"US",
    "sg:address":"2709 Woodland Dr",
    "sg:city":"Waco",
    "sg:classifiers":[
        {
            "category":"Professional",
            "subcategory":"Computer Services",
            "type":"Services"
        }
    ],
    "sg:phone":"+1 512 657 9691",
    "sg:postcode":"76710",
    "sg:province":"TX",
    "sg:tags":[
        "related"
    ],
    "wof:name":"Pomatics",
    "wof:placetype":"venue"
},
  "geometry": {"coordinates":[-97.192908,31.557326],"type":"Point"}
}