{
  "type": "Feature",
  "properties": {
    "iso:country":"US",
    "sg:address":"3601 N Hwy 35 Byp",
    "sg:city":"Alvin",
    "sg:classifiers":[
        {
            "category":"Manufacturing",
            "subcategory":"Metals",
            "type":"Manufacturing & Wholesale Goods"
        }
    ],
    "sg:phone":"+1 281 756 8676",
    "sg:postcode":"77511",
    "sg:province":"TX",
    "sg:tags":[
        "fluid",
        "power",
        "mfg"
    ],
    "wof:name":"Custom Hose",
    "wof:placetype":"venue"
},
  "geometry": {"coordinates":[-95.24462800000001,29.455052],"type":"Point"}
}