{
  "type": "Feature",
  "properties": {
    "iso:country":"US",
    "sg:address":"5020 Foster Ave",
    "sg:city":"Groves",
    "sg:classifiers":[
        {
            "category":"Professional",
            "subcategory":"Business Services",
            "type":"Services"
        }
    ],
    "sg:phone":"+1 409 962 9758",
    "sg:postcode":"77619",
    "sg:province":"TX",
    "wof:name":"Devries & Trahan Enterprises",
    "wof:placetype":"venue"
},
  "geometry": {"coordinates":[-93.93844900000001,29.942366],"type":"Point"}
}