{
  "type": "Feature",
  "properties": {
    "iso:country":"US",
    "sg:address":"11335 Oakcenter Dr",
    "sg:city":"Houston",
    "sg:classifiers":[
        {
            "category":"Professional",
            "type":"Services"
        }
    ],
    "sg:phone":"+1 281 561 7961",
    "sg:postcode":"77072",
    "sg:province":"TX",
    "wof:name":"Okkin Inc",
    "wof:placetype":"venue"
},
  "geometry": {"coordinates":[-95.57878700000001,29.706827],"type":"Point"}
}