{
  "type": "Feature",
  "properties": {
    "iso:country":"US",
    "sg:address":"404 S Main Ave",
    "sg:city":"Monahans",
    "sg:classifiers":[
        {
            "category":"Retail",
            "subcategory":"Laundry & Dry Cleaning",
            "type":"Services"
        }
    ],
    "sg:phone":"+1 432 943 5692",
    "sg:postcode":"79756",
    "sg:province":"TX",
    "sg:tags":[
        "garment",
        "plant",
        "drycleaning",
        "agent",
        "cleaners"
    ],
    "wof:name":"A-1 Cleaners",
    "wof:placetype":"venue"
},
  "geometry": {"coordinates":[-102.891993,31.591688],"type":"Point"}
}