{
  "type": "Feature",
  "properties": {
    "iso:country":"US",
    "sg:address":"617 Slaughter Lane W",
    "sg:city":"Austin",
    "sg:classifiers":[
        {
            "category":"Personal",
            "subcategory":"Beauty Salon",
            "type":"Services"
        },
        {
            "category":"Personal",
            "subcategory":"Day Spa",
            "type":"Services"
        }
    ],
    "sg:phone":"+1 512 282 2211",
    "sg:postcode":"78748",
    "sg:province":"TX",
    "wof:name":"Venus Day Spa",
    "wof:placetype":"venue"
},
  "geometry": {"coordinates":[-97.799999,30.172753],"type":"Point"}
}