{
  "type": "Feature",
  "properties": {
    "iso:country":"US",
    "sg:address":"10835 Shady Trl",
    "sg:city":"Dallas",
    "sg:classifiers":[
        {
            "category":"Shopping",
            "subcategory":"Mobile Phones",
            "type":"Retail Goods"
        }
    ],
    "sg:phone":"+1 214 654 9924",
    "sg:postcode":"75220",
    "sg:province":"TX",
    "wof:name":"Texas Semiconductor",
    "wof:placetype":"venue"
},
  "geometry": {"coordinates":[-96.890389,32.876658],"type":"Point"}
}