{
  "type": "Feature",
  "properties": {
    "iso:country":"US",
    "sg:address":"1502 Calder Ave",
    "sg:city":"Beaumont",
    "sg:classifiers":[
        {
            "category":"Autos & Motor Vehicles",
            "subcategory":"Automobile Sales",
            "type":"Retail Goods"
        }
    ],
    "sg:phone":"+1 409 839 4700",
    "sg:postcode":"77701",
    "sg:province":"TX",
    "sg:tags":[
        "used"
    ],
    "wof:name":"Triangle Motor Co",
    "wof:placetype":"venue"
},
  "geometry": {"coordinates":[-94.11187099999999,30.086018],"type":"Point"}
}