{
  "type": "Feature",
  "properties": {
    "iso:country":"US",
    "sg:address":"208 Houston St",
    "sg:city":"Cedar Hill",
    "sg:classifiers":[
        {
            "category":"Shopping",
            "subcategory":"Clothing, Apparel, & Fashions",
            "type":"Retail Goods"
        }
    ],
    "sg:phone":"+1 972 293 6883",
    "sg:postcode":"75104",
    "sg:province":"TX",
    "wof:name":"Houston Street Outfitters",
    "wof:placetype":"venue"
},
  "geometry": {"coordinates":[-96.95644799999999,32.588045],"type":"Point"}
}