{
  "type": "Feature",
  "properties": {
    "iso:country":"US",
    "sg:address":"800 Airport Rd",
    "sg:city":"Terrell",
    "sg:classifiers":[
        {
            "category":"Manufacturing",
            "subcategory":"Tools & Machinery",
            "type":"Manufacturing & Wholesale Goods"
        }
    ],
    "sg:phone":"+1 972 563 2605",
    "sg:postcode":"75160",
    "sg:province":"TX",
    "sg:tags":[
        "equipment",
        "metalwork",
        "sheet",
        "mfg"
    ],
    "wof:name":"Air System Components",
    "wof:placetype":"venue"
},
  "geometry": {"coordinates":[-96.266094,32.716678],"type":"Point"}
}