{
  "type": "Feature",
  "properties": {
    "iso:country":"US",
    "sg:address":"7150 Greenville Ave",
    "sg:city":"Dallas",
    "sg:classifiers":[
        {
            "category":"Health Services",
            "subcategory":"Doctor",
            "type":"Services"
        }
    ],
    "sg:phone":"+1 214 360 0869",
    "sg:postcode":"75231",
    "sg:province":"TX",
    "sg:tags":[
        "physician",
        "surgeon"
    ],
    "wof:name":"Cardiovascular Research",
    "wof:placetype":"venue"
},
  "geometry": {"coordinates":[-96.759962,32.879728],"type":"Point"}
}