{
  "type": "Feature",
  "properties": {
    "iso:country":"US",
    "sg:address":"11246 S Post Oak Rd",
    "sg:city":"Houston",
    "sg:classifiers":[
        {
            "category":"Organizations",
            "subcategory":"Religious Organization",
            "type":"Services"
        }
    ],
    "sg:phone":"+1 713 723 2949",
    "sg:postcode":"77035",
    "sg:province":"TX",
    "sg:tags":[
        "church"
    ],
    "wof:name":"Excellence-N-Ministries",
    "wof:placetype":"venue"
},
  "geometry": {"coordinates":[-95.463921,29.655295],"type":"Point"}
}