{
  "type": "Feature",
  "properties": {
    "iso:country":"US",
    "sg:address":"4601 Ridgemont Rd",
    "sg:city":"Fort Worth",
    "sg:classifiers":[
        {
            "category":"Professional",
            "subcategory":"Art Services",
            "type":"Services"
        }
    ],
    "sg:phone":"+1 817 849 1484",
    "sg:postcode":"76117",
    "sg:province":"TX",
    "sg:tags":[
        "commercial",
        "design"
    ],
    "wof:name":"Susan L Dawson-Backer",
    "wof:placetype":"venue"
},
  "geometry": {"coordinates":[-97.25881200000001,32.831958],"type":"Point"}
}