{
  "type": "Feature",
  "properties": {
    "iso:country":"US",
    "sg:address":"3349 W Parkway St",
    "sg:city":"Groves",
    "sg:classifiers":[
        {
            "category":"Autos & Motor Vehicles",
            "subcategory":"Automobile Sales",
            "type":"Retail Goods"
        },
        {
            "category":"Retail",
            "subcategory":"Auto Rental",
            "type":"Services"
        }
    ],
    "sg:phone":"+1 409 962 3234",
    "sg:postcode":"77619",
    "sg:province":"TX",
    "sg:tags":[
        "car",
        "leasing",
        "truck"
    ],
    "sg:website":"http://www.enterprise.com/car_rental/deeplinkmap.do?gpbr=06R8&bid=004&cnty=US&arc=YPTRL01&cm_mmc=Yellowpages.com-_-IYP-_-Tradelisting-_-branch",
    "wof:name":"Enterprise Rent-A-Car",
    "wof:placetype":"venue"
},
  "geometry": {"coordinates":[-93.914787,29.94031],"type":"Point"}
}