{
  "type": "Feature",
  "properties": {
    "iso:country":"US",
    "sg:address":"108 Lander St",
    "sg:city":"Cuero",
    "sg:classifiers":[
        {
            "category":"Freight",
            "type":"Transportation"
        }
    ],
    "sg:phone":"+1 361 277 8509",
    "sg:postcode":"77995",
    "sg:province":"TX",
    "sg:tags":[
        "operator",
        "local",
        "trucking"
    ],
    "wof:name":"Wimbish Trucking Co",
    "wof:placetype":"venue"
},
  "geometry": {"coordinates":[-97.146126,29.278601],"type":"Point"}
}