{
  "type": "Feature",
  "properties": {
    "iso:country":"US",
    "sg:address":"304 Cargill St",
    "sg:city":"El Paso",
    "sg:classifiers":[
        {
            "category":"Shopping",
            "subcategory":"Used Merchandise",
            "type":"Retail Goods"
        }
    ],
    "sg:phone":"+1 915 779 1867",
    "sg:postcode":"79905",
    "sg:province":"TX",
    "wof:name":"Elena Rodriquez Luz",
    "wof:placetype":"venue"
},
  "geometry": {"coordinates":[-106.41157,31.759712],"type":"Point"}
}