{
  "type": "Feature",
  "properties": {
    "iso:country":"US",
    "sg:address":"2608 S FM 116",
    "sg:city":"Copperas Cove",
    "sg:classifiers":[
        {
            "category":"Organizations",
            "subcategory":"Religious Organization",
            "type":"Services"
        }
    ],
    "sg:phone":"+1 254 547 4013",
    "sg:postcode":"76522",
    "sg:province":"TX",
    "sg:tags":[
        "church"
    ],
    "wof:name":"Crestview Christian Church",
    "wof:placetype":"venue"
},
  "geometry": {"coordinates":[-97.90264000000001,31.092592],"type":"Point"}
}