{
  "type": "Feature",
  "properties": {
    "iso:country":"US",
    "sg:address":"620 N Grant Ave",
    "sg:city":"Odessa",
    "sg:classifiers":[
        {
            "category":"Professional",
            "type":"Services"
        }
    ],
    "sg:phone":"+1 432 333 5090",
    "sg:postcode":"79761",
    "sg:province":"TX",
    "sg:tags":[
        "establishment"
    ],
    "wof:name":"Craig Terrill Hale & Grantham",
    "wof:placetype":"venue"
},
  "geometry": {"coordinates":[-102.37066299999999,31.850011],"type":"Point"}
}