{
  "type": "Feature",
  "properties": {
    "iso:country":"US",
    "sg:address":"4123 Drowsy Ln",
    "sg:city":"Dallas",
    "sg:classifiers":[
        {
            "category":"Shopping",
            "subcategory":"Computers & Home Electronics",
            "type":"Retail Goods"
        }
    ],
    "sg:phone":"+1 214 337 5966",
    "sg:postcode":"75233",
    "sg:province":"TX",
    "wof:name":"Icaon Upgrade",
    "wof:placetype":"venue"
},
  "geometry": {"coordinates":[-96.882014,32.692815],"type":"Point"}
}