{
  "type": "Feature",
  "properties": {
    "iso:country":"US",
    "sg:address":"5011 Trowbridge Dr",
    "sg:city":"El Paso",
    "sg:classifiers":[
        {
            "category":"Retail",
            "subcategory":"Self-service Laundry",
            "type":"Services"
        }
    ],
    "sg:phone":"+1 915 566 6400",
    "sg:postcode":"79903",
    "sg:province":"TX",
    "sg:tags":[
        "garment",
        "coin",
        "agent"
    ],
    "wof:name":"Speed Queen Laundry",
    "wof:placetype":"venue"
},
  "geometry": {"coordinates":[-106.430853,31.788539],"type":"Point"}
}