{
  "type": "Feature",
  "properties": {
    "iso:country":"US",
    "sg:address":"1110 Evergreen Dr",
    "sg:city":"Houston",
    "sg:classifiers":[
        {
            "category":"Shopping",
            "subcategory":"Crafts & Fabrics",
            "type":"Retail Goods"
        }
    ],
    "sg:phone":"+1 713 921 2045",
    "sg:postcode":"77087",
    "sg:province":"TX",
    "sg:tags":[
        "art",
        "supply"
    ],
    "wof:name":"Webb Jerry Ceramc",
    "wof:placetype":"venue"
},
  "geometry": {"coordinates":[-95.290398,29.715401],"type":"Point"}
}