{
  "type": "Feature",
  "properties": {
    "iso:country":"US",
    "sg:address":"1929 W Dallas St",
    "sg:city":"Houston",
    "sg:classifiers":[
        {
            "category":"Professional",
            "subcategory":"Business Services",
            "type":"Services"
        },
        {
            "category":"Shopping",
            "subcategory":"Clothing, Apparel, & Fashions",
            "type":"Retail Goods"
        }
    ],
    "sg:phone":"+1 713 526 0691",
    "sg:postcode":"77019",
    "sg:province":"TX",
    "sg:tags":[
        "designer"
    ],
    "wof:name":"Azrael's Accomplice Designs",
    "wof:placetype":"venue"
},
  "geometry": {"coordinates":[-95.388142,29.757491],"type":"Point"}
}