{
  "type": "Feature",
  "properties": {
    "iso:country":"US",
    "sg:address":"115 W Davis St",
    "sg:city":"Conroe",
    "sg:classifiers":[
        {
            "category":"Manufacturing",
            "subcategory":"Retail Goods",
            "type":"Manufacturing & Wholesale Goods"
        }
    ],
    "sg:phone":"+1 936 647 4330",
    "sg:postcode":"77301",
    "sg:province":"TX",
    "sg:tags":[
        "oils-essential"
    ],
    "wof:name":"Extravagant Oils",
    "wof:placetype":"venue"
},
  "geometry": {"coordinates":[-95.456155,30.31214],"type":"Point"}
}