{
  "type": "Feature",
  "properties": {
    "iso:country":"US",
    "sg:address":"3361 Boyington Dr",
    "sg:city":"Carrollton",
    "sg:classifiers":[
        {
            "category":"Wholesale",
            "subcategory":"Hardware",
            "type":"Manufacturing & Wholesale Goods"
        }
    ],
    "sg:phone":"+1 972 869 1200",
    "sg:postcode":"75006",
    "sg:province":"TX",
    "sg:tags":[
        "equipment",
        "refrigeration",
        "conditioning",
        "air"
    ],
    "wof:name":"Hale Engineering",
    "wof:placetype":"venue"
},
  "geometry": {"coordinates":[-96.842174,32.965143],"type":"Point"}
}