{
  "type": "Feature",
  "properties": {
    "iso:country":"US",
    "sg:address":"955 Co Rd 156",
    "sg:city":"Granger",
    "sg:classifiers":[
        {
            "category":"Shopping",
            "subcategory":"Computers & Home Electronics",
            "type":"Retail Goods"
        }
    ],
    "sg:phone":"+1 512 863 0181",
    "sg:postcode":"76530",
    "sg:province":"TX",
    "wof:name":"Computers In Motion Inc",
    "wof:placetype":"venue"
},
  "geometry": {"coordinates":[-97.547214,30.686374],"type":"Point"}
}