{
  "type": "Feature",
  "properties": {
    "iso:country":"US",
    "sg:address":"6715 Pleasant Stream Dr",
    "sg:city":"Katy",
    "sg:classifiers":[
        {
            "category":"Building & Trades",
            "subcategory":"Electrical",
            "type":"Services"
        }
    ],
    "sg:phone":"+1 281 463 8809",
    "sg:postcode":"77449",
    "sg:province":"TX",
    "sg:tags":[
        "home",
        "system",
        "automation"
    ],
    "wof:name":"Interactive Technologies",
    "wof:placetype":"venue"
},
  "geometry": {"coordinates":[-95.734386,29.873555],"type":"Point"}
}