{
  "type": "Feature",
  "properties": {
    "iso:country":"US",
    "sg:address":"1014 N Washington Ave",
    "sg:city":"Odessa",
    "sg:classifiers":[
        {
            "category":"Organizations",
            "subcategory":"Religious Organization",
            "type":"Services"
        }
    ],
    "sg:phone":"+1 432 337 1804",
    "sg:postcode":"79761",
    "sg:province":"TX",
    "sg:tags":[
        "church"
    ],
    "wof:name":"Washington Avenue Chr",
    "wof:placetype":"venue"
},
  "geometry": {"coordinates":[-102.377494,31.851527],"type":"Point"}
}