{
  "type": "Feature",
  "properties": {
    "iso:country":"US",
    "sg:address":"4600 Behrens Rd",
    "sg:city":"Colleyville",
    "sg:classifiers":[
        {
            "category":"Building & Trades",
            "subcategory":"Construction",
            "type":"Services"
        }
    ],
    "sg:phone":"+1 817 354 7922",
    "sg:postcode":"76034",
    "sg:province":"TX",
    "sg:tags":[
        "house"
    ],
    "wof:name":"Kevin Walker Custom Homes",
    "wof:placetype":"venue"
},
  "geometry": {"coordinates":[-97.14220299999999,32.876272],"type":"Point"}
}