{
  "type": "Feature",
  "properties": {
    "iso:country":"US",
    "sg:address":"803 Pampa St",
    "sg:city":"Pasadena",
    "sg:phone":"+1 713 946 4133",
    "sg:postcode":"77504",
    "sg:province":"TX",
    "sg:tags":[
        "farm",
        "grain",
        "cash"
    ],
    "wof:name":"Dusek Farm",
    "wof:placetype":"venue"
},
  "geometry": {"coordinates":[-95.19479,29.65655],"type":"Point"}
}