{
  "type": "Feature",
  "properties": {
    "iso:country":"US",
    "sg:address":"1013 Ronald Dr",
    "sg:city":"Corpus Christi",
    "sg:classifiers":[
        {
            "category":"Retail",
            "subcategory":"Repair Shop",
            "type":"Services"
        }
    ],
    "sg:phone":"+1 361 985 1000",
    "sg:postcode":"78412",
    "sg:province":"TX",
    "wof:name":"Laura Skrobarczyk Piano Servi",
    "wof:placetype":"venue"
},
  "geometry": {"coordinates":[-97.35439599999999,27.710071],"type":"Point"}
}