{
  "type": "Feature",
  "properties": {
    "iso:country":"US",
    "sg:address":"5250 Gulfton St",
    "sg:city":"Houston",
    "sg:classifiers":[
        {
            "category":"Retail",
            "subcategory":"Photofinishing",
            "type":"Services"
        }
    ],
    "sg:phone":"+1 713 666 0282",
    "sg:postcode":"77081",
    "sg:province":"TX",
    "sg:tags":[
        "laboratory",
        "finishing",
        "custom",
        "photo"
    ],
    "sg:website":"www.houstonphotoimaging.com",
    "wof:name":"Houston Photo Imaging",
    "wof:placetype":"venue"
},
  "geometry": {"coordinates":[-95.47085199999999,29.716647],"type":"Point"}
}