{
  "type": "Feature",
  "properties": {
    "iso:country":"US",
    "sg:address":"9035 Vinewood Dr",
    "sg:city":"Dallas",
    "sg:classifiers":[
        {
            "category":"Professional",
            "subcategory":"Advertising",
            "type":"Services"
        }
    ],
    "sg:phone":"+1 214 327 9600",
    "sg:postcode":"75228",
    "sg:province":"TX",
    "sg:tags":[
        "agency",
        "specialty"
    ],
    "wof:name":"Better Business Productions",
    "wof:placetype":"venue"
},
  "geometry": {"coordinates":[-96.69982,32.816849],"type":"Point"}
}