{
  "type": "Feature",
  "properties": {
    "iso:country":"US",
    "sg:address":"8860 Old Agnes Rd",
    "sg:city":"Poolville",
    "sg:classifiers":[
        {
            "category":"Professional",
            "type":"Services"
        },
        {
            "category":"Retail",
            "subcategory":"Repair Shop",
            "type":"Services"
        }
    ],
    "sg:phone":"+1 817 220 5055",
    "sg:postcode":"76487",
    "sg:province":"TX",
    "sg:tags":[
        "welding"
    ],
    "wof:name":"J & B Metal Works",
    "wof:placetype":"venue"
},
  "geometry": {"coordinates":[-97.792725,32.9586],"type":"Point"}
}