{
  "type": "Feature",
  "properties": {
    "iso:country":"US",
    "sg:address":"1001 Crestwood Dr",
    "sg:city":"Cleburne",
    "sg:classifiers":[
        {
            "category":"Building & Trades",
            "subcategory":"Cleaning & Sanitation",
            "type":"Services"
        }
    ],
    "sg:phone":"+1 817 641 8579",
    "sg:postcode":"76033",
    "sg:province":"TX",
    "sg:tags":[
        "maintenance"
    ],
    "wof:name":"Meticulous Maintenance/Cleburn",
    "wof:placetype":"venue"
},
  "geometry": {"coordinates":[-97.40190699999999,32.337432],"type":"Point"}
}