{
  "type": "Feature",
  "properties": {
    "iso:country":"US",
    "sg:address":"8500 Long Point Rd",
    "sg:city":"Houston",
    "sg:classifiers":[
        {
            "category":"Autos & Motor Vehicles",
            "subcategory":"Fuel & Gas Station",
            "type":"Retail Goods"
        }
    ],
    "sg:phone":"+1 713 465 6699",
    "sg:postcode":"77055",
    "sg:province":"TX",
    "sg:website":"www.texaco.com",
    "wof:name":"Dan's Long Point Texaco",
    "wof:placetype":"venue"
},
  "geometry": {"coordinates":[-95.49700199999999,29.803101],"type":"Point"}
}