{
  "type": "Feature",
  "properties": {
    "iso:country":"US",
    "sg:address":"330 Main St",
    "sg:city":"Sealy",
    "sg:classifiers":[
        {
            "category":"Professional",
            "subcategory":"Lawyer & Legal Services",
            "type":"Services"
        }
    ],
    "sg:phone":"+1 979 885 3533",
    "sg:postcode":"77474",
    "sg:province":"TX",
    "sg:tags":[
        "attorney"
    ],
    "sg:website":"www.cccwlaw.com",
    "wof:name":"Conner Cantey & Clover",
    "wof:placetype":"venue"
},
  "geometry": {"coordinates":[-96.15558,29.781386],"type":"Point"}
}