{
  "type": "Feature",
  "properties": {
    "iso:country":"US",
    "sg:address":"2924 Sweet Briar",
    "sg:city":"Grapevine",
    "sg:classifiers":[
        {
            "category":"Building & Trades",
            "subcategory":"Construction",
            "type":"Services"
        }
    ],
    "sg:phone":"+1 817 329 4328",
    "sg:postcode":"76051",
    "sg:province":"TX",
    "sg:tags":[
        "concrete",
        "contractor"
    ],
    "wof:name":"SD Ponder Concrete Inc",
    "wof:placetype":"venue"
},
  "geometry": {"coordinates":[-97.111176,32.966787],"type":"Point"}
}