{
  "type": "Feature",
  "properties": {
    "iso:country":"US",
    "sg:address":"604 Highway 79",
    "sg:city":"Hutto",
    "sg:classifiers":[
        {
            "category":"Banks & Credit Unions",
            "subcategory":"Bank",
            "type":"Services"
        },
        {
            "category":"Banks & Credit Unions",
            "subcategory":"Financial Services",
            "type":"Services"
        }
    ],
    "sg:phone":"+1 512 846 2816",
    "sg:postcode":"78634",
    "sg:province":"TX",
    "sg:tags":[
        "commercial",
        "loan",
        "saving",
        "mortgage"
    ],
    "sg:website":"https://www.wellsfargo.com/wfonline/",
    "wof:name":"Wells Fargo Bank",
    "wof:placetype":"venue"
},
  "geometry": {"coordinates":[-97.557137,30.541176],"type":"Point"}
}