{
  "type": "Feature",
  "properties": {
    "iso:country":"US",
    "sg:address":"4904 Airline Dr",
    "sg:city":"Houston",
    "sg:classifiers":[
        {
            "category":"Food & Beverages",
            "subcategory":"Groceries & Convenience Stores",
            "type":"Retail Goods"
        }
    ],
    "sg:phone":"+1 713 694 1455",
    "sg:postcode":"77022",
    "sg:province":"TX",
    "wof:name":"Handi Plus Food Store",
    "wof:placetype":"venue"
},
  "geometry": {"coordinates":[-95.384102,29.8377],"type":"Point"}
}