{
  "type": "Feature",
  "properties": {
    "iso:country":"US",
    "sg:address":"7624 Grapevine Hwy",
    "sg:city":"Fort Worth",
    "sg:classifiers":[
        {
            "category":"Shopping",
            "subcategory":"Shoes",
            "type":"Retail Goods"
        }
    ],
    "sg:phone":"+1 817 284 4471",
    "sg:postcode":"76180",
    "sg:province":"TX",
    "wof:name":"Payless Shoesource",
    "wof:placetype":"venue"
},
  "geometry": {"coordinates":[-97.21867,32.830469],"type":"Point"}
}