{
  "type": "Feature",
  "properties": {
    "iso:country":"US",
    "sg:address":"3301 Hamilton Ave",
    "sg:city":"Fort Worth",
    "sg:classifiers":[
        {
            "category":"Real Estate",
            "subcategory":"Real Estate Agent",
            "type":"Services"
        }
    ],
    "sg:phone":"+1 817 810 9912",
    "sg:postcode":"76107",
    "sg:province":"TX",
    "wof:name":"Laredo Real Estate Services",
    "wof:placetype":"venue"
},
  "geometry": {"coordinates":[-97.36658300000001,32.754832],"type":"Point"}
}