{
  "type": "Feature",
  "properties": {
    "iso:country":"US",
    "sg:address":"5014 Oak Ave",
    "sg:city":"Pasadena",
    "sg:classifiers":[
        {
            "category":"Building & Trades",
            "subcategory":"Construction",
            "type":"Services"
        }
    ],
    "sg:phone":"+1 281 487 6884",
    "sg:postcode":"77503",
    "sg:province":"TX",
    "sg:tags":[
        "contractor"
    ],
    "wof:name":"Olc Co Contractor",
    "wof:placetype":"venue"
},
  "geometry": {"coordinates":[-95.16330000000001,29.672254],"type":"Point"}
}