{
  "type": "Feature",
  "properties": {
    "iso:country":"US",
    "sg:address":"64 Bristol Green",
    "sg:city":"San Antonio",
    "sg:classifiers":[
        {
            "category":"Building & Trades",
            "subcategory":"Electrical",
            "type":"Services"
        }
    ],
    "sg:phone":"+1 210 826 5889",
    "sg:postcode":"78209",
    "sg:province":"TX",
    "sg:tags":[
        "electrical",
        "contractor"
    ],
    "wof:name":"Beth W Eidelberg",
    "wof:placetype":"venue"
},
  "geometry": {"coordinates":[-98.47606,29.501931],"type":"Point"}
}