{
  "type": "Feature",
  "properties": {
    "iso:country":"US",
    "sg:address":"5809 East Dr",
    "sg:city":"Laredo",
    "sg:classifiers":[
        {
            "category":"Wholesale",
            "subcategory":"Electrical",
            "type":"Manufacturing & Wholesale Goods"
        }
    ],
    "sg:phone":"+1 956 722 1171",
    "sg:postcode":"78041",
    "sg:province":"TX",
    "sg:tags":[
        "equipment",
        "telephone",
        "system"
    ],
    "wof:name":"Carr Sales Inc",
    "wof:placetype":"venue"
},
  "geometry": {"coordinates":[-99.474891,27.551348],"type":"Point"}
}