{
  "type": "Feature",
  "properties": {
    "iso:country":"US",
    "sg:address":"1507 W 18th St",
    "sg:city":"Houston",
    "sg:classifiers":[
        {
            "category":"Health Services",
            "subcategory":"Dentist",
            "type":"Services"
        }
    ],
    "sg:phone":"+1 713 861 7078",
    "sg:postcode":"77008",
    "sg:province":"TX",
    "wof:name":"Northwest Family Dentistry",
    "wof:placetype":"venue"
},
  "geometry": {"coordinates":[-95.426903,29.8015],"type":"Point"}
}