{
  "type": "Feature",
  "properties": {
    "iso:country":"US",
    "sg:address":"209 Stirrup Rd",
    "sg:city":"Victoria",
    "sg:classifiers":[
        {
            "category":"Shopping",
            "subcategory":"Jewelry",
            "type":"Retail Goods"
        }
    ],
    "sg:phone":"+1 361 575 0440",
    "sg:postcode":"77905",
    "sg:province":"TX",
    "sg:tags":[
        "repair"
    ],
    "wof:name":"Victoria Mfg",
    "wof:placetype":"venue"
},
  "geometry": {"coordinates":[-97.172618,28.892799],"type":"Point"}
}