{
  "type": "Feature",
  "properties": {
    "iso:country":"US",
    "sg:address":"415 W 24th St",
    "sg:city":"Austin",
    "sg:classifiers":[
        {
            "category":"Restaurant",
            "type":"Food & Drink"
        }
    ],
    "sg:menulink":"http://www.allmenus.com/tx/austin/284942-big-bite-pizza-/menu/",
    "sg:phone":"+1 512 457 4992",
    "sg:postcode":"78705",
    "sg:province":"TX",
    "sg:tags":[
        "american",
        "sandwich",
        "pizza"
    ],
    "wof:name":"Big Bite Pizza",
    "wof:placetype":"venue"
},
  "geometry": {"coordinates":[-97.742346,30.287632],"type":"Point"}
}