{
  "type": "Feature",
  "properties": {
    "iso:country":"US",
    "sg:address":"1617 27th St",
    "sg:city":"Lubbock",
    "sg:classifiers":[
        {
            "category":"Social Services",
            "type":"Services"
        }
    ],
    "sg:phone":"+1 806 762 6348",
    "sg:postcode":"79411",
    "sg:province":"TX",
    "sg:tags":[
        "family",
        "specialty",
        "outpatient",
        "clinic",
        "marriage",
        "counselor"
    ],
    "wof:name":"Waldren Group",
    "wof:placetype":"venue"
},
  "geometry": {"coordinates":[-101.854545,33.569982],"type":"Point"}
}