{
  "type": "Feature",
  "properties": {
    "iso:country":"US",
    "sg:address":"15913 Singapore Ln",
    "sg:city":"Houston",
    "sg:classifiers":[
        {
            "category":"Real Estate",
            "subcategory":"Real Estate Operator",
            "type":"Services"
        }
    ],
    "sg:phone":"+1 713 937 1380",
    "sg:postcode":"77040",
    "sg:province":"TX",
    "sg:tags":[
        "building",
        "nonresidential"
    ],
    "wof:name":"Advanced Properties Inc",
    "wof:placetype":"venue"
},
  "geometry": {"coordinates":[-95.560648,29.882237],"type":"Point"}
}