{
  "type": "Feature",
  "properties": {
    "iso:country":"US",
    "sg:address":"605 20th St",
    "sg:city":"Hondo",
    "sg:classifiers":[
        {
            "category":"Health Services",
            "subcategory":"Podiatrist",
            "type":"Services"
        }
    ],
    "sg:phone":"+1 830 741 3909",
    "sg:postcode":"78861",
    "sg:province":"TX",
    "wof:name":"Robinson Donald E",
    "wof:placetype":"venue"
},
  "geometry": {"coordinates":[-99.134929,29.346829],"type":"Point"}
}