{
  "type": "Feature",
  "properties": {
    "iso:country":"US",
    "sg:address":"3301 W Co Rd 180",
    "sg:city":"Midland",
    "sg:classifiers":[
        {
            "category":"Freight",
            "type":"Transportation"
        }
    ],
    "sg:phone":"+1 432 685 1248",
    "sg:postcode":"79706",
    "sg:province":"TX",
    "sg:tags":[
        "warehouse"
    ],
    "wof:name":"Aero Mod Services Inc",
    "wof:placetype":"venue"
},
  "geometry": {"coordinates":[-102.06796,31.866408],"type":"Point"}
}