{
  "type": "Feature",
  "properties": {
    "iso:country":"US",
    "sg:address":"4201 Ramsey Ave",
    "sg:city":"Austin",
    "sg:classifiers":[
        {
            "category":"Shopping",
            "subcategory":"Gifts & Souvenirs",
            "type":"Retail Goods"
        }
    ],
    "sg:phone":"+1 512 468 4567",
    "sg:postcode":"78756",
    "sg:province":"TX",
    "sg:tags":[
        "shop"
    ],
    "wof:name":"A Little Something",
    "wof:placetype":"venue"
},
  "geometry": {"coordinates":[-97.745621,30.312691],"type":"Point"}
}