{
  "type": "Feature",
  "properties": {
    "iso:country":"US",
    "sg:address":"524 Spruce St",
    "sg:city":"Texarkana",
    "sg:classifiers":[
        {
            "category":"Shopping",
            "subcategory":"Used Merchandise",
            "type":"Retail Goods"
        }
    ],
    "sg:phone":"+1 903 794 3309",
    "sg:postcode":"75501",
    "sg:province":"TX",
    "wof:name":"Barns & Yards Antiques Inc",
    "wof:placetype":"venue"
},
  "geometry": {"coordinates":[-94.048269,33.423527],"type":"Point"}
}