{
  "type": "Feature",
  "properties": {
    "iso:country":"US",
    "sg:address":"3010 W Park Row Dr",
    "sg:city":"Arlington",
    "sg:classifiers":[
        {
            "category":"Real Estate",
            "subcategory":"Real Estate Services",
            "type":"Services"
        }
    ],
    "sg:phone":"+1 817 461 4494",
    "sg:postcode":"76013",
    "sg:province":"TX",
    "sg:tags":[
        "company",
        "abstract",
        "title"
    ],
    "wof:name":"American Title Company",
    "wof:placetype":"venue"
},
  "geometry": {"coordinates":[-97.159261,32.721342],"type":"Point"}
}