{
  "type": "Feature",
  "properties": {
    "iso:country":"US",
    "sg:address":"1002 E Gibbs St",
    "sg:city":"Del Rio",
    "sg:classifiers":[
        {
            "category":"Personal",
            "subcategory":"Beauty Salon",
            "type":"Services"
        }
    ],
    "sg:phone":"+1 830 775 9589",
    "sg:postcode":"78840",
    "sg:province":"TX",
    "wof:name":"Norma's Hair & Nail Salon",
    "wof:placetype":"venue"
},
  "geometry": {"coordinates":[-100.891631,29.368006],"type":"Point"}
}