{
  "type": "Feature",
  "properties": {
    "iso:country":"US",
    "sg:address":"483 E Commerce St",
    "sg:city":"San Antonio",
    "sg:classifiers":[
        {
            "category":"Cinema",
            "subcategory":"Movie Theater",
            "type":"Entertainment"
        }
    ],
    "sg:phone":"+1 210 247 0230",
    "sg:postcode":"78205",
    "sg:province":"TX",
    "wof:name":"Theatre Rivercenter Mall",
    "wof:placetype":"venue"
},
  "geometry": {"coordinates":[-98.488254,29.423922],"type":"Point"}
}