{
  "type": "Feature",
  "properties": {
    "iso:country":"US",
    "sg:address":"556 Pace Park Rd",
    "sg:city":"Salado",
    "sg:classifiers":[
        {
            "category":"Shopping",
            "subcategory":"Gifts & Souvenirs",
            "type":"Retail Goods"
        }
    ],
    "sg:phone":"+1 254 947 3182",
    "sg:postcode":"76571",
    "sg:province":"TX",
    "sg:tags":[
        "shop"
    ],
    "wof:name":"Essengee's",
    "wof:placetype":"venue"
},
  "geometry": {"coordinates":[-97.53624000000001,30.944496],"type":"Point"}
}