{
  "type": "Feature",
  "properties": {
    "iso:country":"US",
    "sg:address":"626 Flintstone Dr",
    "sg:city":"New Braunfels",
    "sg:classifiers":[
        {
            "category":"Building & Trades",
            "subcategory":"Construction",
            "type":"Services"
        }
    ],
    "sg:phone":"+1 210 657 5693",
    "sg:postcode":"78133",
    "sg:province":"TX",
    "sg:tags":[
        "contractor"
    ],
    "wof:name":"A & R Lath & Plaster",
    "wof:placetype":"venue"
},
  "geometry": {"coordinates":[-98.296902,29.860273],"type":"Point"}
}