{
  "type": "Feature",
  "properties": {
    "iso:country":"US",
    "sg:address":"11104 Fondren Rd",
    "sg:city":"Houston",
    "sg:classifiers":[
        {
            "category":"Shopping",
            "subcategory":"Clothing, Apparel, & Fashions",
            "type":"Retail Goods"
        },
        {
            "category":"Shopping",
            "subcategory":"Used Merchandise",
            "type":"Retail Goods"
        }
    ],
    "sg:phone":"+1 713 272 0180",
    "sg:postcode":"77096",
    "sg:province":"TX",
    "sg:tags":[
        "vintage",
        "clothing",
        "accessory",
        "consignment",
        "women's"
    ],
    "sg:website":"www.dots.com",
    "wof:name":"Dots",
    "wof:placetype":"venue"
},
  "geometry": {"coordinates":[-95.50868699999999,29.658719],"type":"Point"}
}