{
  "type": "Feature",
  "properties": {
    "iso:country":"US",
    "sg:address":"1444 Southern Hills Dr",
    "sg:city":"Mansfield",
    "sg:classifiers":[
        {
            "category":"Professional",
            "subcategory":"Art Services",
            "type":"Services"
        }
    ],
    "sg:phone":"+1 817 473 3783",
    "sg:postcode":"76063",
    "sg:province":"TX",
    "sg:tags":[
        "commercial",
        "design"
    ],
    "wof:name":"Creative Touch",
    "wof:placetype":"venue"
},
  "geometry": {"coordinates":[-97.112357,32.581721],"type":"Point"}
}