{
  "type": "Feature",
  "properties": {
    "iso:country":"US",
    "sg:address":"1627 W Terra Alta Rd",
    "sg:city":"San Antonio",
    "sg:classifiers":[
        {
            "category":"Banks & Credit Unions",
            "subcategory":"Financial Services",
            "type":"Services"
        }
    ],
    "sg:phone":"+1 210 822 0969",
    "sg:postcode":"78209",
    "sg:province":"TX",
    "sg:tags":[
        "company",
        "holding"
    ],
    "wof:name":"Purple Pines &A Pond Inc",
    "wof:placetype":"venue"
},
  "geometry": {"coordinates":[-98.466669,29.505489],"type":"Point"}
}