{
  "type": "Feature",
  "properties": {
    "iso:country":"US",
    "sg:address":"1501 Tech Centre Pkwy",
    "sg:city":"Arlington",
    "sg:classifiers":[
        {
            "category":"Autos & Motor Vehicles",
            "subcategory":"Automobile Sales",
            "type":"Retail Goods"
        }
    ],
    "sg:phone":"+1 817 557 9256",
    "sg:postcode":"76014",
    "sg:province":"TX",
    "sg:tags":[
        "dealers-used",
        "car",
        "used",
        "cars-wholesale",
        "new"
    ],
    "wof:name":"Manuel Auto Group",
    "wof:placetype":"venue"
},
  "geometry": {"coordinates":[-97.088707,32.680931],"type":"Point"}
}