{
  "type": "Feature",
  "properties": {
    "iso:country":"US",
    "sg:address":"103 Professional Park Dr",
    "sg:city":"Victoria",
    "sg:classifiers":[
        {
            "category":"Health Services",
            "subcategory":"Doctor",
            "type":"Services"
        }
    ],
    "sg:phone":"+1 361 576 1235",
    "sg:postcode":"77904",
    "sg:province":"TX",
    "sg:tags":[
        "dentist"
    ],
    "wof:name":"Norman M Sawyers DDS",
    "wof:placetype":"venue"
},
  "geometry": {"coordinates":[-96.987008,28.84139],"type":"Point"}
}