{
  "type": "Feature",
  "properties": {
    "iso:country":"US",
    "sg:address":"11345 Avering Ln",
    "sg:city":"Austin",
    "sg:classifiers":[
        {
            "category":"Retail",
            "subcategory":"Laundry & Dry Cleaning",
            "type":"Services"
        }
    ],
    "sg:phone":"+1 512 577 3715",
    "sg:postcode":"78754",
    "sg:province":"TX",
    "sg:tags":[
        "laundries-self"
    ],
    "wof:name":"It All Comes Naturally Corporation",
    "wof:placetype":"venue"
},
  "geometry": {"coordinates":[-97.61109,30.346771],"type":"Point"}
}