{
  "type": "Feature",
  "properties": {
    "iso:country":"US",
    "sg:address":"1028 Ellingson Ln",
    "sg:city":"Austin",
    "sg:classifiers":[
        {
            "category":"Shopping",
            "subcategory":"Bicycles & Sporting Goods",
            "type":"Retail Goods"
        }
    ],
    "sg:phone":"+1 512 453 5842",
    "sg:postcode":"78751",
    "sg:province":"TX",
    "sg:tags":[
        "gun",
        "gunsmith"
    ],
    "wof:name":"Robert's Gun Shop",
    "wof:placetype":"venue"
},
  "geometry": {"coordinates":[-97.71677200000001,30.302665],"type":"Point"}
}