{
  "type": "Feature",
  "properties": {
    "iso:country":"US",
    "sg:address":"104 S Gauntt St",
    "sg:city":"Athens",
    "sg:classifiers":[
        {
            "category":"Real Estate",
            "subcategory":"Real Estate Agent",
            "type":"Services"
        }
    ],
    "sg:phone":"+1 903 675 8660",
    "sg:postcode":"75751",
    "sg:province":"TX",
    "sg:tags":[
        "body",
        "house",
        "auto"
    ],
    "wof:name":"Straw Hat Beauty Salon",
    "wof:placetype":"venue"
},
  "geometry": {"coordinates":[-95.86774800000001,32.204385],"type":"Point"}
}