{
  "type": "Feature",
  "properties": {
    "iso:country":"US",
    "sg:address":"385 Landa St",
    "sg:city":"New Braunfels",
    "sg:classifiers":[
        {
            "category":"Retail",
            "subcategory":"Car Wash",
            "type":"Services"
        }
    ],
    "sg:phone":"+1 830 625 7969",
    "sg:postcode":"78130",
    "sg:province":"TX",
    "sg:tags":[
        "carwash"
    ],
    "wof:name":"Custom Auto Care & Sales",
    "wof:placetype":"venue"
},
  "geometry": {"coordinates":[-98.129216,29.70488],"type":"Point"}
}