{
  "type": "Feature",
  "properties": {
    "iso:country":"US",
    "sg:address":"4733 Samuell Blvd",
    "sg:city":"Mesquite",
    "sg:classifiers":[
        {
            "category":"Recreation",
            "type":"Entertainment"
        }
    ],
    "sg:phone":"+1 972 320 0042",
    "sg:postcode":"75149",
    "sg:province":"TX",
    "sg:tags":[
        "club",
        "membership"
    ],
    "wof:name":"Millionaire Club",
    "wof:placetype":"venue"
},
  "geometry": {"coordinates":[-96.672467,32.792318],"type":"Point"}
}