{
  "type": "Feature",
  "properties": {
    "iso:country":"US",
    "sg:address":"664 Trenckmann Rd",
    "sg:city":"Sealy",
    "sg:classifiers":[
        {
            "category":"Personal",
            "subcategory":"Barber",
            "type":"Services"
        }
    ],
    "sg:phone":"+1 979 885 6102",
    "sg:postcode":"77474",
    "sg:province":"TX",
    "sg:tags":[
        "shop"
    ],
    "wof:name":"Pinoak Barbershop",
    "wof:placetype":"venue"
},
  "geometry": {"coordinates":[-96.18799199999999,29.852623],"type":"Point"}
}