{
  "type": "Feature",
  "properties": {
    "iso:country":"US",
    "sg:address":"500 W Southlake Blvd",
    "sg:city":"Southlake",
    "sg:classifiers":[
        {
            "category":"Personal",
            "subcategory":"Beauty Salon",
            "type":"Services"
        }
    ],
    "sg:phone":"+1 817 488 7702",
    "sg:postcode":"76092",
    "sg:province":"TX",
    "sg:tags":[
        "shop",
        "manicuring"
    ],
    "wof:name":"Nail Elite",
    "wof:placetype":"venue"
},
  "geometry": {"coordinates":[-97.157189,32.94115],"type":"Point"}
}