{
  "type": "Feature",
  "properties": {
    "iso:country":"US",
    "sg:address":"1201 Industrial Blvd",
    "sg:city":"Temple",
    "sg:classifiers":[
        {
            "category":"Building & Trades",
            "subcategory":"Construction",
            "type":"Services"
        }
    ],
    "sg:phone":"+1 254 774 7302",
    "sg:postcode":"76504",
    "sg:province":"TX",
    "sg:tags":[
        "siding",
        "contractor"
    ],
    "wof:name":"Quality Builders",
    "wof:placetype":"venue"
},
  "geometry": {"coordinates":[-97.343757,31.126972],"type":"Point"}
}