{
  "type": "Feature",
  "properties": {
    "iso:country":"US",
    "sg:address":"9726 Rockbrook Dr",
    "sg:city":"Dallas",
    "sg:classifiers":[
        {
            "category":"Banks & Credit Unions",
            "subcategory":"Financial Services",
            "type":"Services"
        }
    ],
    "sg:phone":"+1 214 353 2692",
    "sg:postcode":"75220",
    "sg:province":"TX",
    "sg:tags":[
        "investor"
    ],
    "wof:name":"Wwet Investment Management Co",
    "wof:placetype":"venue"
},
  "geometry": {"coordinates":[-96.83204600000001,32.875024],"type":"Point"}
}