{
  "type": "Feature",
  "properties": {
    "iso:country":"US",
    "sg:address":"4813 Gallagher Ave",
    "sg:city":"Laredo",
    "sg:classifiers":[
        {
            "category":"Autos & Motor Vehicles",
            "subcategory":"Auto Supplies",
            "type":"Retail Goods"
        },
        {
            "category":"Retail",
            "subcategory":"Auto Repair",
            "type":"Services"
        }
    ],
    "sg:phone":"+1 956 726 9098",
    "sg:postcode":"78041",
    "sg:province":"TX",
    "sg:tags":[
        "body",
        "lettering",
        "automobile",
        "truck",
        "customizing",
        "painting",
        "repairing"
    ],
    "wof:name":"Westside Collision",
    "wof:placetype":"venue"
},
  "geometry": {"coordinates":[-99.49717,27.542515],"type":"Point"}
}