{
  "type": "Feature",
  "properties": {
    "iso:country":"US",
    "sg:address":"1228 E 8th St",
    "sg:city":"Odessa",
    "sg:classifiers":[
        {
            "category":"Banks & Credit Unions",
            "subcategory":"Bank",
            "type":"Services"
        }
    ],
    "sg:phone":"+1 432 337 1400",
    "sg:postcode":"79761",
    "sg:province":"TX",
    "sg:tags":[
        "cashing",
        "check"
    ],
    "wof:name":"Pronto Check Cashing",
    "wof:placetype":"venue"
},
  "geometry": {"coordinates":[-102.35961399999999,31.857051],"type":"Point"}
}