{
  "type": "Feature",
  "properties": {
    "iso:country":"US",
    "sg:address":"1116 Commerce Dr",
    "sg:city":"Richardson",
    "sg:classifiers":[
        {
            "category":"Manufacturing",
            "subcategory":"Printing",
            "type":"Manufacturing & Wholesale Goods"
        }
    ],
    "sg:phone":"+1 972 699 8693",
    "sg:postcode":"75081",
    "sg:province":"TX",
    "sg:tags":[
        "printer"
    ],
    "wof:name":"Color Magic",
    "wof:placetype":"venue"
},
  "geometry": {"coordinates":[-96.70571700000001,32.965863],"type":"Point"}
}