{
  "type": "Feature",
  "properties": {
    "iso:country":"US",
    "sg:address":"220 Winding Way Rd",
    "sg:city":"Marble Falls",
    "sg:classifiers":[
        {
            "category":"Manufacturing",
            "subcategory":"Tools & Machinery",
            "type":"Manufacturing & Wholesale Goods"
        }
    ],
    "sg:phone":"+1 830 693 3565",
    "sg:postcode":"78654",
    "sg:province":"TX",
    "sg:tags":[
        "machine",
        "shop"
    ],
    "wof:name":"Rock Solid Machining",
    "wof:placetype":"venue"
},
  "geometry": {"coordinates":[-98.283079,30.633395],"type":"Point"}
}