{
  "type": "Feature",
  "properties": {
    "iso:country":"US",
    "sg:address":"2314 9th St",
    "sg:city":"Wichita Falls",
    "sg:classifiers":[
        {
            "category":"Personal",
            "subcategory":"Barber",
            "type":"Services"
        }
    ],
    "sg:phone":"+1 940 723 5077",
    "sg:postcode":"76301",
    "sg:province":"TX",
    "sg:tags":[
        "shop",
        "beauty"
    ],
    "wof:name":"Nathans Mens Hair Styling",
    "wof:placetype":"venue"
},
  "geometry": {"coordinates":[-98.516347,33.903929],"type":"Point"}
}