{
  "type": "Feature",
  "properties": {
    "iso:country":"US",
    "sg:address":"310 W Belt Line Rd",
    "sg:city":"Cedar Hill",
    "sg:classifiers":[
        {
            "category":"Social Services",
            "subcategory":"Child Care",
            "type":"Services"
        },
        {
            "category":"Education",
            "subcategory":"Preschool",
            "type":"Public Place"
        },
        {
            "category":"Education",
            "subcategory":"School",
            "type":"Public Place"
        }
    ],
    "sg:phone":"+1 972 291 1313",
    "sg:postcode":"75104",
    "sg:province":"TX",
    "sg:tags":[
        "elementary",
        "day"
    ],
    "sg:website":"www.ashleysprivateschool.net",
    "wof:name":"Ashleys Private School",
    "wof:placetype":"venue"
},
  "geometry": {"coordinates":[-96.951302,32.59],"type":"Point"}
}