{
  "type": "Feature",
  "properties": {
    "iso:country":"US",
    "sg:address":"271 E Summit Ave",
    "sg:city":"San Antonio",
    "sg:classifiers":[
        {
            "category":"Professional",
            "type":"Services"
        }
    ],
    "sg:phone":"+1 210 734 0302",
    "sg:postcode":"78212",
    "sg:province":"TX",
    "wof:name":"AAA Armory",
    "wof:placetype":"venue"
},
  "geometry": {"coordinates":[-98.49150299999999,29.458571],"type":"Point"}
}