{
  "type": "Feature",
  "properties": {
    "iso:country":"US",
    "sg:address":"280 Thompson Dr",
    "sg:city":"Kerrville",
    "sg:classifiers":[
        {
            "category":"Banks & Credit Unions",
            "subcategory":"Bank",
            "type":"Services"
        }
    ],
    "sg:phone":"+1 830 792 5626",
    "sg:postcode":"78028",
    "sg:province":"TX",
    "sg:tags":[
        "sell",
        "ranch",
        "commercial",
        "mortgage"
    ],
    "wof:name":"First American Mortgage",
    "wof:placetype":"venue"
},
  "geometry": {"coordinates":[-99.145404,30.045366],"type":"Point"}
}