{
  "type": "Feature",
  "properties": {
    "iso:country":"US",
    "sg:address":"3500 Doniphan Dr",
    "sg:city":"El Paso",
    "sg:classifiers":[
        {
            "category":"Wholesale",
            "subcategory":"Farm Supplies",
            "type":"Manufacturing & Wholesale Goods"
        }
    ],
    "sg:phone":"+1 915 833 6107",
    "sg:postcode":"79922",
    "sg:province":"TX",
    "sg:tags":[
        "feed"
    ],
    "wof:name":"Amrail Services Inc",
    "wof:placetype":"venue"
},
  "geometry": {"coordinates":[-106.545413,31.806004],"type":"Point"}
}