{
  "type": "Feature",
  "properties": {
    "iso:country":"US",
    "sg:address":"1712 Howard Ln",
    "sg:city":"Austin",
    "sg:classifiers":[
        {
            "category":"Building & Trades",
            "subcategory":"Construction",
            "type":"Services"
        }
    ],
    "sg:phone":"+1 512 252 9636",
    "sg:postcode":"78728",
    "sg:province":"TX",
    "sg:tags":[
        "excavation",
        "foundation",
        "contractor"
    ],
    "wof:name":"Dickey & Son Concrete Inc",
    "wof:placetype":"venue"
},
  "geometry": {"coordinates":[-97.678432,30.427795],"type":"Point"}
}