{
  "type": "Feature",
  "properties": {
    "iso:country":"US",
    "sg:address":"411 N Avenue N",
    "sg:city":"Clifton",
    "sg:classifiers":[
        {
            "category":"Retail",
            "subcategory":"Laundry & Dry Cleaning",
            "type":"Services"
        }
    ],
    "sg:phone":"+1 254 675 8056",
    "sg:postcode":"76634",
    "sg:province":"TX",
    "sg:tags":[
        "cleaner",
        "rug",
        "carpet"
    ],
    "wof:name":"Carl's Carpet Cleaning",
    "wof:placetype":"venue"
},
  "geometry": {"coordinates":[-97.585132,31.783066],"type":"Point"}
}