{
  "type": "Feature",
  "properties": {
    "iso:country":"US",
    "sg:address":"3251 Garden Brook Dr",
    "sg:city":"Dallas",
    "sg:classifiers":[
        {
            "category":"Professional",
            "subcategory":"Advertising",
            "type":"Services"
        }
    ],
    "sg:phone":"+1 972 620 0368",
    "sg:postcode":"75234",
    "sg:province":"TX",
    "sg:tags":[
        "mail",
        "direct"
    ],
    "wof:name":"Total Fulfillment",
    "wof:placetype":"venue"
},
  "geometry": {"coordinates":[-96.866455,32.950365],"type":"Point"}
}