{
  "type": "Feature",
  "properties": {
    "iso:country":"US",
    "sg:address":"281 Cornstalk Ln",
    "sg:city":"Rockwall",
    "sg:classifiers":[
        {
            "category":"Building & Trades",
            "subcategory":"Construction",
            "type":"Services"
        }
    ],
    "sg:phone":"+1 972 564 4184",
    "sg:postcode":"75032",
    "sg:province":"TX",
    "sg:tags":[
        "home",
        "builder"
    ],
    "wof:name":"Ben Garrett Construction Co",
    "wof:placetype":"venue"
},
  "geometry": {"coordinates":[-96.422369,32.817188],"type":"Point"}
}