{
  "type": "Feature",
  "properties": {
    "iso:country":"US",
    "sg:address":"176 Applewhite Dr",
    "sg:city":"Katy",
    "sg:classifiers":[
        {
            "category":"Personal",
            "subcategory":"Beauty Salon",
            "type":"Services"
        }
    ],
    "sg:phone":"+1 281 347 1444",
    "sg:postcode":"77450",
    "sg:province":"TX",
    "wof:name":"Hair Miracles By Daphne",
    "wof:placetype":"venue"
},
  "geometry": {"coordinates":[-95.75457,29.783483],"type":"Point"}
}