{
  "type": "Feature",
  "properties": {
    "iso:country":"US",
    "sg:address":"3500 Jefferson St",
    "sg:city":"Austin",
    "sg:classifiers":[
        {
            "category":"Banks & Credit Unions",
            "subcategory":"Investment Brokerage",
            "type":"Services"
        }
    ],
    "sg:phone":"+1 512 380 9174",
    "sg:postcode":"78731",
    "sg:province":"TX",
    "sg:tags":[
        "security"
    ],
    "wof:name":"Morgan Stanley",
    "wof:placetype":"venue"
},
  "geometry": {"coordinates":[-97.750664,30.309185],"type":"Point"}
}