{
  "type": "Feature",
  "properties": {
    "iso:country":"US",
    "sg:address":"2602 Ave K",
    "sg:city":"Galveston",
    "sg:classifiers":[
        {
            "category":"Shopping",
            "subcategory":"Discount & Variety Stores",
            "type":"Retail Goods"
        }
    ],
    "sg:phone":"+1 409 762 1328",
    "sg:postcode":"77550",
    "sg:province":"TX",
    "sg:tags":[
        "merchandise",
        "general"
    ],
    "wof:name":"McMahon Imports",
    "wof:placetype":"venue"
},
  "geometry": {"coordinates":[-94.79633200000001,29.297961],"type":"Point"}
}