{
  "type": "Feature",
  "properties": {
    "iso:country":"US",
    "sg:address":"12315 Blue River Dr",
    "sg:city":"Houston",
    "sg:classifiers":[
        {
            "category":"Building & Trades",
            "subcategory":"Electrical",
            "type":"Services"
        }
    ],
    "sg:phone":"+1 281 590 7110",
    "sg:postcode":"77050",
    "sg:province":"TX",
    "sg:tags":[
        "electrical",
        "contractor"
    ],
    "wof:name":"Hampton Electrical Servic",
    "wof:placetype":"venue"
},
  "geometry": {"coordinates":[-95.291483,29.901365],"type":"Point"}
}