{
  "type": "Feature",
  "properties": {
    "iso:country":"US",
    "sg:address":"8126 Bottlebrush Dr",
    "sg:city":"Austin",
    "sg:classifiers":[
        {
            "category":"Shopping",
            "subcategory":"Clothing, Apparel, & Fashions",
            "type":"Retail Goods"
        }
    ],
    "sg:phone":"+1 512 349 0311",
    "sg:postcode":"78750",
    "sg:province":"TX",
    "wof:name":"Imperial Sales LLC",
    "wof:placetype":"venue"
},
  "geometry": {"coordinates":[-97.799509,30.394371],"type":"Point"}
}