{
  "type": "Feature",
  "properties": {
    "iso:country":"US",
    "sg:address":"4665 Sweetwater Blvd",
    "sg:city":"Sugar Land",
    "sg:classifiers":[
        {
            "category":"Banks & Credit Unions",
            "subcategory":"Bank",
            "type":"Services"
        }
    ],
    "sg:phone":"+1 281 565 5626",
    "sg:postcode":"77479",
    "sg:province":"TX",
    "sg:tags":[
        "mortgage"
    ],
    "wof:name":"Hometown America Mortgage Co",
    "wof:placetype":"venue"
},
  "geometry": {"coordinates":[-95.631002,29.583402],"type":"Point"}
}