{
  "type": "Feature",
  "properties": {
    "iso:country":"US",
    "sg:address":"11484 Moran Rd",
    "sg:city":"Azle",
    "sg:phone":"+1 817 270 5497",
    "sg:postcode":"76020",
    "sg:province":"TX",
    "sg:tags":[
        "equipment",
        "supply"
    ],
    "wof:name":"Raleigh W Johnson & Co",
    "wof:placetype":"venue"
},
  "geometry": {"coordinates":[-97.515867,32.936521],"type":"Point"}
}