{
  "type": "Feature",
  "properties": {
    "iso:country":"US",
    "sg:address":"13101 Northwest Fwy",
    "sg:city":"Houston",
    "sg:classifiers":[
        {
            "category":"Banks & Credit Unions",
            "subcategory":"Bank",
            "type":"Services"
        }
    ],
    "sg:phone":"+1 713 690 1529",
    "sg:postcode":"77040",
    "sg:province":"TX",
    "wof:name":"Guaranty Bank",
    "wof:placetype":"venue"
},
  "geometry": {"coordinates":[-95.501198,29.8461],"type":"Point"}
}