{
  "type": "Feature",
  "properties": {
    "iso:country":"US",
    "sg:address":"13010 Rudys Way",
    "sg:city":"Streetman",
    "sg:classifiers":[
        {
            "category":"Building & Trades",
            "subcategory":"Landscaping Services",
            "type":"Services"
        }
    ],
    "sg:phone":"+1 903 599 2240",
    "sg:postcode":"75859",
    "sg:province":"TX",
    "sg:tags":[
        "consultant",
        "lawn",
        "designer",
        "landscape",
        "maintenance"
    ],
    "wof:name":"Metroplex Services/Richland Chambers Lawn Mainten",
    "wof:placetype":"venue"
},
  "geometry": {"coordinates":[-96.268113,31.952421],"type":"Point"}
}