{
  "type": "Feature",
  "properties": {
    "iso:country":"US",
    "sg:address":"1618 Greenview Ct",
    "sg:city":"Aledo",
    "sg:classifiers":[
        {
            "category":"Professional",
            "subcategory":"Management & Consulting",
            "type":"Services"
        }
    ],
    "sg:phone":"+1 817 596 7865",
    "sg:postcode":"76008",
    "sg:province":"TX",
    "sg:tags":[
        "business"
    ],
    "wof:name":"Jnc Consulting Inc",
    "wof:placetype":"venue"
},
  "geometry": {"coordinates":[-97.66240000000001,32.730202],"type":"Point"}
}