{
  "type": "Feature",
  "properties": {
    "iso:country":"US",
    "sg:address":"4901 Daffodil Ave",
    "sg:city":"Mcallen",
    "sg:classifiers":[
        {
            "category":"Social Services",
            "type":"Services"
        },
        {
            "category":"Professional",
            "subcategory":"Employment Agencies",
            "type":"Services"
        }
    ],
    "sg:phone":"+1 956 668 9740",
    "sg:postcode":"78501",
    "sg:province":"TX",
    "sg:tags":[
        "workers'",
        "placement",
        "volunteer"
    ],
    "sg:website":"http://www.mcallentownband.com",
    "wof:name":"Mcallen Town Band",
    "wof:placetype":"venue"
},
  "geometry": {"coordinates":[-98.270392,26.237044],"type":"Point"}
}