{
  "type": "Feature",
  "properties": {
    "iso:country":"US",
    "sg:address":"1110 Cottonwood Ln",
    "sg:city":"Irving",
    "sg:classifiers":[
        {
            "category":"Health Services",
            "subcategory":"Doctor",
            "type":"Services"
        }
    ],
    "sg:phone":"+1 972 258 7499",
    "sg:postcode":"75038",
    "sg:province":"TX",
    "sg:tags":[
        "physician",
        "surgeon"
    ],
    "wof:name":"J Mark Anderson MD",
    "wof:placetype":"venue"
},
  "geometry": {"coordinates":[-96.961568,32.865514],"type":"Point"}
}