{
  "type": "Feature",
  "properties": {
    "iso:country":"US",
    "sg:address":"9285 State Hwy 6",
    "sg:city":"Meridian",
    "sg:classifiers":[
        {
            "category":"Restaurant",
            "type":"Food & Drink"
        }
    ],
    "sg:phone":"+1 254 435 9782",
    "sg:postcode":"76638",
    "sg:province":"TX",
    "wof:name":"Subway Sandwiches & Salads",
    "wof:placetype":"venue"
},
  "geometry": {"coordinates":[-97.33688100000001,31.592599],"type":"Point"}
}