{
  "type": "Feature",
  "properties": {
    "iso:country":"US",
    "sg:address":"3233 Pagosa Ct",
    "sg:city":"El Paso",
    "sg:classifiers":[
        {
            "category":"Manufacturing",
            "subcategory":"Electronics",
            "type":"Manufacturing & Wholesale Goods"
        }
    ],
    "sg:phone":"+1 915 751 3222",
    "sg:postcode":"79904",
    "sg:province":"TX",
    "sg:tags":[
        "whole",
        "component",
        "electronic",
        "mfg"
    ],
    "wof:name":"Zeli Systems",
    "wof:placetype":"venue"
},
  "geometry": {"coordinates":[-106.459377,31.847443],"type":"Point"}
}