{
  "type": "Feature",
  "properties": {
    "iso:country":"US",
    "sg:address":"416 Hampshire Ave",
    "sg:city":"San Antonio",
    "sg:classifiers":[
        {
            "category":"Professional",
            "subcategory":"Business Services",
            "type":"Services"
        }
    ],
    "sg:phone":"+1 210 216 4499",
    "sg:postcode":"78210",
    "sg:province":"TX",
    "wof:name":"Edge Tech Enterprises",
    "wof:placetype":"venue"
},
  "geometry": {"coordinates":[-98.475408,29.394403],"type":"Point"}
}