{
  "type": "Feature",
  "properties": {
    "iso:country":"US",
    "sg:address":"3223 S Loop 289",
    "sg:city":"Lubbock",
    "sg:classifiers":[
        {
            "category":"Insurance",
            "subcategory":"Hazard Insurance",
            "type":"Services"
        }
    ],
    "sg:phone":"+1 806 793 3210",
    "sg:postcode":"79423",
    "sg:province":"TX",
    "sg:tags":[
        "warranty",
        "program"
    ],
    "wof:name":"America's Best Warranty Co Inc",
    "wof:placetype":"venue"
},
  "geometry": {"coordinates":[-101.87907800000001,33.528957],"type":"Point"}
}