{
  "type": "Feature",
  "properties": {
    "iso:country":"US",
    "sg:address":"3735 Country Club Cir",
    "sg:city":"Fort Worth",
    "sg:classifiers":[
        {
            "category":"Recreation",
            "type":"Entertainment"
        }
    ],
    "sg:phone":"+1 817 927 4200",
    "sg:postcode":"76109",
    "sg:province":"TX",
    "sg:tags":[
        "golf",
        "club",
        "course",
        "membership",
        "sport",
        "public",
        "physical"
    ],
    "wof:name":"Colonial Country Club",
    "wof:placetype":"venue"
},
  "geometry": {"coordinates":[-97.37115799999999,32.71813],"type":"Point"}
}