{
  "type": "Feature",
  "properties": {
    "iso:country":"US",
    "sg:address":"2100 Ridgmar Blvd",
    "sg:city":"Fort Worth",
    "sg:classifiers":[
        {
            "category":"Food & Beverages",
            "subcategory":"Groceries & Convenience Stores",
            "type":"Retail Goods"
        }
    ],
    "sg:phone":"+1 817 731 1882",
    "sg:postcode":"76116",
    "sg:province":"TX",
    "wof:name":"Q Mart",
    "wof:placetype":"venue"
},
  "geometry": {"coordinates":[-97.42496199999999,32.739173],"type":"Point"}
}