{
  "type": "Feature",
  "properties": {
    "iso:country":"US",
    "sg:address":"1138 Silver Lake Dr",
    "sg:city":"Grapevine",
    "sg:classifiers":[
        {
            "category":"Building & Trades",
            "subcategory":"Landscaping Services",
            "type":"Services"
        }
    ],
    "sg:phone":"+1 817 421 1300",
    "sg:postcode":"76051",
    "sg:province":"TX",
    "wof:name":"Fleur Delis Landscape & Lawn",
    "wof:placetype":"venue"
},
  "geometry": {"coordinates":[-97.07128899999999,32.94858],"type":"Point"}
}