{
  "type": "Feature",
  "properties": {
    "iso:country":"US",
    "sg:address":"700 W Harwood Rd",
    "sg:city":"Hurst",
    "sg:classifiers":[
        {
            "category":"Professional",
            "subcategory":"Accounting & Tax Preparation",
            "type":"Services"
        }
    ],
    "sg:phone":"+1 325 247 1445",
    "sg:postcode":"76054",
    "sg:province":"TX",
    "wof:name":"Karon G Targonski PC",
    "wof:placetype":"venue"
},
  "geometry": {"coordinates":[-97.183504,32.845788],"type":"Point"}
}