{
  "type": "Feature",
  "properties": {
    "iso:country":"US",
    "sg:address":"406 Harvey St",
    "sg:city":"San Marcos",
    "sg:classifiers":[
        {
            "category":"Social Services",
            "subcategory":"Child Care",
            "type":"Services"
        }
    ],
    "sg:phone":"+1 512 353 8340",
    "sg:postcode":"78666",
    "sg:province":"TX",
    "sg:tags":[
        "school",
        "day"
    ],
    "wof:name":"San Marcos Montessori School",
    "wof:placetype":"venue"
},
  "geometry": {"coordinates":[-97.944517,29.881828],"type":"Point"}
}