{
  "type": "Feature",
  "properties": {
    "iso:country":"US",
    "sg:address":"11042 S Post Oak Rd",
    "sg:city":"Houston",
    "sg:classifiers":[
        {
            "category":"Wholesale",
            "subcategory":"Auto Parts",
            "type":"Manufacturing & Wholesale Goods"
        }
    ],
    "sg:phone":"+1 713 726 9502",
    "sg:postcode":"77035",
    "sg:province":"TX",
    "sg:tags":[
        "supply"
    ],
    "wof:name":"Niam Tire Co",
    "wof:placetype":"venue"
},
  "geometry": {"coordinates":[-95.46408099999999,29.66003],"type":"Point"}
}