{
  "type": "Feature",
  "properties": {
    "iso:country":"US",
    "sg:address":"835 W Davis St",
    "sg:city":"Dallas",
    "sg:classifiers":[
        {
            "category":"Shopping",
            "subcategory":"Jewelry",
            "type":"Retail Goods"
        },
        {
            "category":"Home & Garden",
            "subcategory":"Home Furnishings",
            "type":"Retail Goods"
        }
    ],
    "sg:phone":"+1 214 942 1030",
    "sg:postcode":"75208",
    "sg:province":"TX",
    "sg:tags":[
        "decor"
    ],
    "sg:website":"www.fromtheendsoftheearth.com",
    "wof:name":"From The Ends Of The Earth",
    "wof:placetype":"venue"
},
  "geometry": {"coordinates":[-96.83720700000001,32.749503],"type":"Point"}
}