{
  "type": "Feature",
  "properties": {
    "iso:country":"US",
    "sg:address":"425 Round Rock West Dr",
    "sg:city":"Round Rock",
    "sg:classifiers":[
        {
            "category":"Wholesale",
            "subcategory":"Electrical",
            "type":"Manufacturing & Wholesale Goods"
        }
    ],
    "sg:phone":"+1 512 759 2325",
    "sg:postcode":"78681",
    "sg:province":"TX",
    "sg:tags":[
        "equipment",
        "electronic",
        "supply"
    ],
    "sg:website":"www.electronicprecision.com",
    "wof:name":"Electronic Precision Materials",
    "wof:placetype":"venue"
},
  "geometry": {"coordinates":[-97.69403,30.503632],"type":"Point"}
}