{
  "type": "Feature",
  "properties": {
    "iso:country":"US",
    "sg:address":"7652 Bellfort St",
    "sg:city":"Houston",
    "sg:classifiers":[
        {
            "category":"Shopping",
            "subcategory":"Pharmacy",
            "type":"Retail Goods"
        }
    ],
    "sg:phone":"+1 713 644 1343",
    "sg:postcode":"77061",
    "sg:province":"TX",
    "sg:tags":[
        "drugstore"
    ],
    "wof:name":"Medicine Man Pharmacy the",
    "wof:placetype":"venue"
},
  "geometry": {"coordinates":[-95.282402,29.6721],"type":"Point"}
}