{
  "type": "Feature",
  "properties": {
    "iso:country":"US",
    "sg:address":"205 N Gray St",
    "sg:city":"Killeen",
    "sg:classifiers":[
        {
            "category":"Real Estate",
            "subcategory":"Real Estate Agent",
            "type":"Services"
        }
    ],
    "sg:phone":"+1 254 200 2525",
    "sg:postcode":"76541",
    "sg:province":"TX",
    "wof:name":"Sun Properties",
    "wof:placetype":"venue"
},
  "geometry": {"coordinates":[-97.727954,31.120086],"type":"Point"}
}