{
  "type": "Feature",
  "properties": {
    "iso:country":"US",
    "sg:address":"1202 S Alamo St",
    "sg:city":"San Antonio",
    "sg:classifiers":[
        {
            "category":"Professional",
            "subcategory":"Lawyer & Legal Services",
            "type":"Services"
        }
    ],
    "sg:phone":"+1 210 226 6808",
    "sg:postcode":"78210",
    "sg:province":"TX",
    "sg:tags":[
        "law"
    ],
    "wof:name":"Guyer Law Office",
    "wof:placetype":"venue"
},
  "geometry": {"coordinates":[-98.494214,29.410897],"type":"Point"}
}