{
  "type": "Feature",
  "properties": {
    "iso:country":"US",
    "sg:address":"1011 Halsell Ave",
    "sg:city":"Bridgeport",
    "sg:classifiers":[
        {
            "category":"Professional",
            "type":"Services"
        }
    ],
    "sg:phone":"+1 940 683 3827",
    "sg:postcode":"76426",
    "sg:province":"TX",
    "sg:tags":[
        "establishment"
    ],
    "wof:name":"Top Of The Line",
    "wof:placetype":"venue"
},
  "geometry": {"coordinates":[-97.75786100000001,33.210341],"type":"Point"}
}