{
  "type": "Feature",
  "properties": {
    "iso:country":"US",
    "sg:address":"307 Baylor St",
    "sg:city":"Texarkana",
    "sg:classifiers":[
        {
            "category":"Building & Trades",
            "subcategory":"Plumbing",
            "type":"Services"
        }
    ],
    "sg:phone":"+1 903 838 8525",
    "sg:postcode":"75501",
    "sg:province":"TX",
    "sg:tags":[
        "nursery",
        "installation",
        "landscape",
        "maintenance"
    ],
    "wof:name":"Bunch Gardens",
    "wof:placetype":"venue"
},
  "geometry": {"coordinates":[-94.082538,33.438504],"type":"Point"}
}