{
  "type": "Feature",
  "properties": {
    "iso:country":"US",
    "sg:address":"309 Rye St",
    "sg:city":"Round Rock",
    "sg:classifiers":[
        {
            "category":"Wholesale",
            "subcategory":"Non-durable Goods",
            "type":"Manufacturing & Wholesale Goods"
        }
    ],
    "sg:phone":"+1 512 255 4721",
    "sg:postcode":"78664",
    "sg:province":"TX",
    "sg:tags":[
        "advertising",
        "specialty"
    ],
    "wof:name":"J M Promotion",
    "wof:placetype":"venue"
},
  "geometry": {"coordinates":[-97.669248,30.513672],"type":"Point"}
}