{
  "type": "Feature",
  "properties": {
    "iso:country":"US",
    "sg:address":"1805 Clinton St",
    "sg:city":"Longview",
    "sg:classifiers":[
        {
            "category":"Professional",
            "type":"Services"
        }
    ],
    "sg:phone":"+1 903 297 9679",
    "sg:postcode":"75604",
    "sg:province":"TX",
    "wof:name":"Arthur K Bobbitt",
    "wof:placetype":"venue"
},
  "geometry": {"coordinates":[-94.79903299999999,32.528938],"type":"Point"}
}