{
  "type": "Feature",
  "properties": {
    "iso:country":"US",
    "sg:address":"5501 Independence Pkwy",
    "sg:city":"Plano",
    "sg:classifiers":[
        {
            "category":"Health Services",
            "subcategory":"Doctor",
            "type":"Services"
        }
    ],
    "sg:phone":"+1 972 596 1747",
    "sg:postcode":"75023",
    "sg:province":"TX",
    "sg:tags":[
        "medical"
    ],
    "wof:name":"Kenneth A Shore",
    "wof:placetype":"venue"
},
  "geometry": {"coordinates":[-96.750714,33.054279],"type":"Point"}
}