{
  "type": "Feature",
  "properties": {
    "iso:country":"US",
    "sg:address":"3338 US Hwy 90",
    "sg:city":"Seguin",
    "sg:classifiers":[
        {
            "category":"Retail",
            "subcategory":"Animal Services",
            "type":"Services"
        }
    ],
    "sg:phone":"+1 830 379 7792",
    "sg:postcode":"78155",
    "sg:province":"TX",
    "sg:tags":[
        "merchandise"
    ],
    "wof:name":"Wagging Works Grooming",
    "wof:placetype":"venue"
},
  "geometry": {"coordinates":[-98.037187,29.552284],"type":"Point"}
}