{
  "type": "Feature",
  "properties": {
    "iso:country":"US",
    "sg:address":"101 Westbrook Drive",
    "sg:city":"West Lake Hills",
    "sg:classifiers":[
        {
            "category":"Professional",
            "subcategory":"Employment Agencies",
            "type":"Services"
        }
    ],
    "sg:phone":"+1 512 327 3375",
    "sg:postcode":"78746",
    "sg:province":"TX",
    "wof:name":"John Dunlap & Company",
    "wof:placetype":"venue"
},
  "geometry": {"coordinates":[-97.804239,30.278015],"type":"Point"}
}