{
  "type": "Feature",
  "properties": {
    "iso:country":"US",
    "sg:address":"1009 E University Dr",
    "sg:city":"Edinburg",
    "sg:classifiers":[
        {
            "category":"Health Services",
            "subcategory":"Doctor",
            "type":"Services"
        }
    ],
    "sg:phone":"+1 956 316 3533",
    "sg:postcode":"78539",
    "sg:province":"TX",
    "sg:tags":[
        "dentist"
    ],
    "wof:name":"Pecan Dental",
    "wof:placetype":"venue"
},
  "geometry": {"coordinates":[-98.15149700000001,26.299893],"type":"Point"}
}