{
  "type": "Feature",
  "properties": {
    "iso:country":"US",
    "sg:address":"5911 Bellaire Blvd",
    "sg:city":"Houston",
    "sg:classifiers":[
        {
            "category":"Retail",
            "subcategory":"Auto Repair",
            "type":"Services"
        }
    ],
    "sg:phone":"+1 713 432 9688",
    "sg:postcode":"77081",
    "sg:province":"TX",
    "sg:tags":[
        "general"
    ],
    "wof:name":"Performance Collision",
    "wof:placetype":"venue"
},
  "geometry": {"coordinates":[-95.48570100000001,29.705455],"type":"Point"}
}