{
  "type": "Feature",
  "properties": {
    "iso:country":"US",
    "sg:address":"5330 Logston Ln",
    "sg:city":"Spring",
    "sg:classifiers":[
        {
            "category":"Home & Garden",
            "subcategory":"Household Appliances",
            "type":"Retail Goods"
        },
        {
            "category":"Building & Trades",
            "subcategory":"Construction",
            "type":"Services"
        }
    ],
    "sg:phone":"+1 281 353 7608",
    "sg:postcode":"77389",
    "sg:province":"TX",
    "sg:tags":[
        "repair",
        "major",
        "dishwashing",
        "system",
        "machine",
        "contractor",
        "air conditioning"
    ],
    "wof:name":"Viking Air Conditioning",
    "wof:placetype":"venue"
},
  "geometry": {"coordinates":[-95.50073500000001,30.091764],"type":"Point"}
}