{
  "type": "Feature",
  "properties": {
    "iso:country":"US",
    "sg:address":"10609 Valley Vista Rd",
    "sg:city":"Austin",
    "sg:classifiers":[
        {
            "category":"Real Estate",
            "subcategory":"Real Estate Agent",
            "type":"Services"
        }
    ],
    "sg:phone":"+1 512 288 3102",
    "sg:postcode":"78737",
    "sg:province":"TX",
    "wof:name":"Fisher Properties",
    "wof:placetype":"venue"
},
  "geometry": {"coordinates":[-97.949624,30.222788],"type":"Point"}
}