{
  "type": "Feature",
  "properties": {
    "iso:country":"US",
    "sg:address":"2224 Nyssa Ave",
    "sg:city":"Mcallen",
    "sg:classifiers":[
        {
            "category":"Shopping",
            "subcategory":"Florist",
            "type":"Retail Goods"
        }
    ],
    "sg:phone":"+1 956 682 0218",
    "sg:postcode":"78501",
    "sg:province":"TX",
    "wof:name":"Lisa's Creations",
    "wof:placetype":"venue"
},
  "geometry": {"coordinates":[-98.242683,26.217765],"type":"Point"}
}