{
  "type": "Feature",
  "properties": {
    "iso:country":"US",
    "sg:address":"1800 N Texas Blvd Ofc",
    "sg:city":"Weslaco",
    "sg:classifiers":[
        {
            "category":"Real Estate",
            "subcategory":"Real Estate Services",
            "type":"Services"
        },
        {
            "category":"Real Estate",
            "subcategory":"Real Estate Operator",
            "type":"Services"
        }
    ],
    "sg:phone":"+1 956 968 2567",
    "sg:postcode":"78596",
    "sg:province":"TX",
    "sg:tags":[
        "vacancy",
        "apartment",
        "rental",
        "finder",
        "listing"
    ],
    "wof:name":"Northside Apartments",
    "wof:placetype":"venue"
},
  "geometry": {"coordinates":[-97.99099699999999,26.17762],"type":"Point"}
}