{
  "type": "Feature",
  "properties": {
    "iso:country":"US",
    "sg:address":"7002 Tall Oaks Dr",
    "sg:city":"Texarkana",
    "sg:classifiers":[
        {
            "category":"Building & Trades",
            "subcategory":"Construction",
            "type":"Services"
        }
    ],
    "sg:phone":"+1 870 774 6416",
    "sg:postcode":"71854",
    "sg:province":"TX",
    "sg:tags":[
        "hanging",
        "contractor"
    ],
    "wof:name":"Williams Commercial Painting",
    "wof:placetype":"venue"
},
  "geometry": {"coordinates":[-94.00587400000001,33.490921],"type":"Point"}
}