{
  "type": "Feature",
  "properties": {
    "iso:country":"US",
    "sg:address":"4923 Louetta Rd",
    "sg:city":"Spring",
    "sg:classifiers":[
        {
            "category":"Food & Beverages",
            "subcategory":"Bakery",
            "type":"Retail Goods"
        }
    ],
    "sg:phone":"+1 281 320 9517",
    "sg:postcode":"77379",
    "sg:province":"TX",
    "wof:name":"Top Donuts",
    "wof:placetype":"venue"
},
  "geometry": {"coordinates":[-95.489043,30.039991],"type":"Point"}
}