{
  "type": "Feature",
  "properties": {
    "iso:country":"US",
    "sg:address":"118 Crawford Dr",
    "sg:city":"Victoria",
    "sg:classifiers":[
        {
            "category":"Mining & Drilling",
            "type":"Manufacturing & Wholesale Goods"
        }
    ],
    "sg:phone":"+1 361 575 2310",
    "sg:postcode":"77904",
    "sg:province":"TX",
    "sg:tags":[
        "report",
        "oil"
    ],
    "wof:name":"4 K Resources",
    "wof:placetype":"venue"
},
  "geometry": {"coordinates":[-97.08883299999999,28.895333],"type":"Point"}
}