{
  "type": "Feature",
  "properties": {
    "iso:country":"US",
    "sg:address":"205 Pecan St",
    "sg:city":"Fort Worth",
    "sg:classifiers":[
        {
            "category":"Banks & Credit Unions",
            "subcategory":"Financial Services",
            "type":"Services"
        }
    ],
    "sg:phone":"+1 817 980 3834",
    "sg:postcode":"76102",
    "sg:province":"TX",
    "sg:tags":[
        "trust",
        "management"
    ],
    "wof:name":"Testarossa Inc",
    "wof:placetype":"venue"
},
  "geometry": {"coordinates":[-97.32822299999999,32.757696],"type":"Point"}
}