{
  "type": "Feature",
  "properties": {
    "iso:country":"US",
    "sg:address":"1410 Glourie Dr",
    "sg:city":"Houston",
    "sg:classifiers":[
        {
            "category":"Professional",
            "subcategory":"Business Services",
            "type":"Services"
        }
    ],
    "sg:phone":"+1 713 935 0099",
    "sg:postcode":"77055",
    "sg:province":"TX",
    "wof:name":"Calyx Design Concepts",
    "wof:placetype":"venue"
},
  "geometry": {"coordinates":[-95.48794599999999,29.796895],"type":"Point"}
}