{
  "type": "Feature",
  "properties": {
    "iso:country":"US",
    "sg:address":"10201 S Western St",
    "sg:city":"Amarillo",
    "sg:classifiers":[
        {
            "category":"Autos & Motor Vehicles",
            "subcategory":"Automobile Sales",
            "type":"Retail Goods"
        }
    ],
    "sg:phone":"+1 806 622 0341",
    "sg:postcode":"79118",
    "sg:province":"TX",
    "sg:tags":[
        "dealers-used",
        "car",
        "used",
        "cars-wholesale",
        "new"
    ],
    "wof:name":"Sample Auto Sales",
    "wof:placetype":"venue"
},
  "geometry": {"coordinates":[-101.88368199999999,35.103642],"type":"Point"}
}