{
  "type": "Feature",
  "properties": {
    "iso:country":"US",
    "sg:address":"6802 Bellfort St",
    "sg:city":"Houston",
    "sg:classifiers":[
        {
            "category":"Organizations",
            "subcategory":"Religious Organization",
            "type":"Services"
        }
    ],
    "sg:phone":"+1 713 645 1817",
    "sg:postcode":"77087",
    "sg:province":"TX",
    "wof:name":"Foster Place Baptist Church",
    "wof:placetype":"venue"
},
  "geometry": {"coordinates":[-95.308728,29.668031],"type":"Point"}
}