{
  "type": "Feature",
  "properties": {
    "iso:country":"US",
    "sg:address":"1522 Spring Cypress Rd",
    "sg:city":"Spring",
    "sg:classifiers":[
        {
            "category":"Professional",
            "subcategory":"Lawyer & Legal Services",
            "type":"Services"
        }
    ],
    "sg:phone":"+1 281 355 8833",
    "sg:postcode":"77388",
    "sg:province":"TX",
    "sg:tags":[
        "attorney"
    ],
    "wof:name":"Duckworth & Ray",
    "wof:placetype":"venue"
},
  "geometry": {"coordinates":[-95.437349,30.074367],"type":"Point"}
}