{
  "type": "Feature",
  "properties": {
    "iso:country":"US",
    "sg:address":"706 Wisdom Dr",
    "sg:city":"Deer Park",
    "sg:classifiers":[
        {
            "category":"Autos & Motor Vehicles",
            "subcategory":"Fuel & Gas Station",
            "type":"Retail Goods"
        }
    ],
    "sg:phone":"+1 281 476 9786",
    "sg:postcode":"77536",
    "sg:province":"TX",
    "sg:tags":[
        "convenience",
        "station",
        "store"
    ],
    "wof:name":"M & M Food Mart",
    "wof:placetype":"venue"
},
  "geometry": {"coordinates":[-95.131636,29.674596],"type":"Point"}
}