{
  "type": "Feature",
  "properties": {
    "iso:country":"US",
    "sg:address":"13526 George Rd",
    "sg:city":"San Antonio",
    "sg:classifiers":[
        {
            "category":"Real Estate",
            "subcategory":"Real Estate Agent",
            "type":"Services"
        }
    ],
    "sg:phone":"+1 210 493 3999",
    "sg:postcode":"78230",
    "sg:province":"TX",
    "sg:tags":[
        "appraiser"
    ],
    "wof:name":"SUMMIT Appraisals",
    "wof:placetype":"venue"
},
  "geometry": {"coordinates":[-98.539652,29.562264],"type":"Point"}
}