{
  "type": "Feature",
  "properties": {
    "iso:country":"US",
    "sg:address":"1018 Preston St Ste 700",
    "sg:city":"Houston",
    "sg:classifiers":[
        {
            "category":"Professional",
            "subcategory":"Lawyer & Legal Services",
            "type":"Services"
        }
    ],
    "sg:phone":"+1 713 223 5959",
    "sg:postcode":"77002",
    "sg:province":"TX",
    "wof:name":"Deguerin Dickson & Hennessy",
    "wof:placetype":"venue"
},
  "geometry": {"coordinates":[-95.361198,29.7614],"type":"Point"}
}