{
  "type": "Feature",
  "properties": {
    "iso:country":"US",
    "sg:address":"24 Sunset Rd",
    "sg:city":"Gainesville",
    "sg:classifiers":[
        {
            "category":"Real Estate",
            "subcategory":"Real Estate Operator",
            "type":"Services"
        }
    ],
    "sg:phone":"+1 940 665 3836",
    "sg:postcode":"76240",
    "sg:province":"TX",
    "sg:tags":[
        "mobile",
        "home",
        "site"
    ],
    "wof:name":"Sunset Village",
    "wof:placetype":"venue"
},
  "geometry": {"coordinates":[-97.15957,33.647408],"type":"Point"}
}