{
  "type": "Feature",
  "properties": {
    "iso:country":"US",
    "sg:address":"1201 W Presidio St",
    "sg:city":"Fort Worth",
    "sg:classifiers":[
        {
            "category":"Real Estate",
            "subcategory":"Developer",
            "type":"Services"
        },
        {
            "category":"Farming",
            "subcategory":"Farm & Veterinary Services",
            "type":"Manufacturing & Wholesale Goods"
        }
    ],
    "sg:phone":"+1 817 878 4278",
    "sg:postcode":"76102",
    "sg:province":"TX",
    "sg:tags":[
        "breeder",
        "livestock"
    ],
    "wof:name":"Harper Land and Cattle",
    "wof:placetype":"venue"
},
  "geometry": {"coordinates":[-97.34050000000001,32.746026],"type":"Point"}
}