{
  "type": "Feature",
  "properties": {
    "iso:country":"US",
    "sg:address":"415 S 1st St",
    "sg:city":"Lufkin",
    "sg:classifiers":[
        {
            "category":"Professional",
            "type":"Services"
        }
    ],
    "sg:phone":"+1 936 633 6417",
    "sg:postcode":"75901",
    "sg:province":"TX",
    "sg:tags":[
        "establishment"
    ],
    "wof:name":"Imaginet",
    "wof:placetype":"venue"
},
  "geometry": {"coordinates":[-94.729992,31.33611],"type":"Point"}
}