{
  "type": "Feature",
  "properties": {
    "iso:country":"US",
    "sg:address":"12444 Research Blvd",
    "sg:city":"Austin",
    "sg:classifiers":[
        {
            "category":"Real Estate",
            "subcategory":"Real Estate Agent",
            "type":"Services"
        }
    ],
    "sg:phone":"+1 512 219 3030",
    "sg:postcode":"78759",
    "sg:province":"TX",
    "wof:name":"Re Max Austin Advantage",
    "wof:placetype":"venue"
},
  "geometry": {"coordinates":[-97.756299,30.427212],"type":"Point"}
}