{
  "type": "Feature",
  "properties": {
    "iso:country":"US",
    "sg:address":"13999 Old Blanco Rd",
    "sg:city":"San Antonio",
    "sg:classifiers":[
        {
            "category":"Real Estate",
            "subcategory":"Real Estate Operator",
            "type":"Services"
        }
    ],
    "sg:phone":"+1 210 479 4900",
    "sg:postcode":"78216",
    "sg:province":"TX",
    "sg:tags":[
        "apartment"
    ],
    "wof:name":"Blanco Crossing Apartments",
    "wof:placetype":"venue"
},
  "geometry": {"coordinates":[-98.52107599999999,29.566328],"type":"Point"}
}