{
  "type": "Feature",
  "properties": {
    "iso:country":"US",
    "sg:address":"6927 Paso del Sol Dr",
    "sg:city":"Houston",
    "sg:classifiers":[
        {
            "category":"Shopping",
            "subcategory":"Gifts & Souvenirs",
            "type":"Retail Goods"
        }
    ],
    "sg:phone":"+1 281 530 9726",
    "sg:postcode":"77083",
    "sg:province":"TX",
    "wof:name":"Compu-Artz",
    "wof:placetype":"venue"
},
  "geometry": {"coordinates":[-95.673153,29.701721],"type":"Point"}
}