{
  "type": "Feature",
  "properties": {
    "iso:country":"US",
    "sg:address":"7671 Ronnie Dr",
    "sg:city":"Dallas",
    "sg:classifiers":[
        {
            "category":"Professional",
            "subcategory":"Engineering",
            "type":"Services"
        },
        {
            "category":"Building & Trades",
            "subcategory":"Construction",
            "type":"Services"
        }
    ],
    "sg:phone":"+1 972 931 1653",
    "sg:postcode":"75252",
    "sg:province":"TX",
    "sg:tags":[
        "concrete",
        "contractor",
        "engineer"
    ],
    "wof:name":"Parrent Concrete Inc",
    "wof:placetype":"venue"
},
  "geometry": {"coordinates":[-96.77545000000001,32.98993],"type":"Point"}
}