{
  "type": "Feature",
  "properties": {
    "iso:country":"US",
    "sg:address":"1275 E Southlake Blvd",
    "sg:city":"Southlake",
    "sg:classifiers":[
        {
            "category":"Professional",
            "subcategory":"Management & Consulting",
            "type":"Services"
        },
        {
            "category":"Professional",
            "subcategory":"Advertising",
            "type":"Services"
        }
    ],
    "sg:phone":"+1 817 310 0882",
    "sg:postcode":"76092",
    "sg:province":"TX",
    "sg:tags":[
        "marketing",
        "program",
        "consultant"
    ],
    "wof:name":"Jake's Loft",
    "wof:placetype":"venue"
},
  "geometry": {"coordinates":[-97.13217400000001,32.94102],"type":"Point"}
}