{
  "type": "Feature",
  "properties": {
    "iso:country":"US",
    "sg:address":"6830 Mykawa Rd",
    "sg:city":"Houston",
    "sg:classifiers":[
        {
            "category":"Wholesale",
            "subcategory":"Auto Parts",
            "type":"Manufacturing & Wholesale Goods"
        }
    ],
    "sg:phone":"+1 713 641 3100",
    "sg:postcode":"77033",
    "sg:province":"TX",
    "sg:tags":[
        "car",
        "used"
    ],
    "wof:name":"Asian Auto Salvage",
    "wof:placetype":"venue"
},
  "geometry": {"coordinates":[-95.32207699999999,29.67893],"type":"Point"}
}