{
  "type": "Feature",
  "properties": {
    "iso:country":"US",
    "sg:address":"7430 Stone Pine Ln",
    "sg:city":"Houston",
    "sg:classifiers":[
        {
            "category":"Shopping",
            "subcategory":"Hobbies, Toys, & Games",
            "type":"Retail Goods"
        }
    ],
    "sg:phone":"+1 713 858 0571",
    "sg:postcode":"77041",
    "sg:province":"TX",
    "wof:name":"Fun Shine Crafts",
    "wof:placetype":"venue"
},
  "geometry": {"coordinates":[-95.615619,29.884327],"type":"Point"}
}