{
  "type": "Feature",
  "properties": {
    "iso:country":"US",
    "sg:address":"1216 Palm Valley Blvd",
    "sg:city":"Round Rock",
    "sg:classifiers":[
        {
            "category":"Retail",
            "subcategory":"Laundry & Dry Cleaning",
            "type":"Services"
        }
    ],
    "sg:phone":"+1 512 733 5664",
    "sg:postcode":"78664",
    "sg:province":"TX",
    "sg:tags":[
        "drycleaning",
        "plant"
    ],
    "wof:name":"X Press Cleaners Inc",
    "wof:placetype":"venue"
},
  "geometry": {"coordinates":[-97.667531,30.518076],"type":"Point"}
}