{
  "type": "Feature",
  "properties": {
    "iso:country":"US",
    "sg:address":"1436 Marlene Pl",
    "sg:city":"De Soto",
    "sg:classifiers":[
        {
            "category":"Building & Trades",
            "subcategory":"Cleaning & Sanitation",
            "type":"Services"
        }
    ],
    "sg:phone":"+1 972 223 4301",
    "sg:postcode":"75115",
    "sg:province":"TX",
    "sg:tags":[
        "maintenance"
    ],
    "wof:name":"General Aviation Maintenance",
    "wof:placetype":"venue"
},
  "geometry": {"coordinates":[-96.86451599999999,32.618072],"type":"Point"}
}