{
  "type": "Feature",
  "properties": {
    "iso:country":"US",
    "sg:address":"1616 W San Antonio St",
    "sg:city":"Lockhart",
    "sg:classifiers":[
        {
            "category":"Retail",
            "subcategory":"Auto Repair",
            "type":"Services"
        }
    ],
    "sg:phone":"+1 512 398 4334",
    "sg:postcode":"78644",
    "sg:province":"TX",
    "sg:tags":[
        "general"
    ],
    "wof:name":"Angels Auto Service",
    "wof:placetype":"venue"
},
  "geometry": {"coordinates":[-97.69279,29.882814],"type":"Point"}
}