{
  "type": "Feature",
  "properties": {
    "iso:country":"US",
    "sg:address":"599 McAllister Rd",
    "sg:city":"Bastrop",
    "sg:classifiers":[
        {
            "category":"Building & Trades",
            "subcategory":"Landscaping Services",
            "type":"Services"
        }
    ],
    "sg:phone":"+1 512 303 4703",
    "sg:postcode":"78602",
    "sg:province":"TX",
    "sg:tags":[
        "landscape"
    ],
    "wof:name":"Houston Landscape",
    "wof:placetype":"venue"
},
  "geometry": {"coordinates":[-97.25787699999999,30.054496],"type":"Point"}
}