{
  "type": "Feature",
  "properties": {
    "iso:country":"US",
    "sg:address":"5711 Duval St",
    "sg:city":"Austin",
    "sg:classifiers":[
        {
            "category":"Manufacturing",
            "subcategory":"Retail Goods",
            "type":"Manufacturing & Wholesale Goods"
        }
    ],
    "sg:phone":"+1 512 451 1217",
    "sg:postcode":"78752",
    "sg:province":"TX",
    "sg:tags":[
        "product",
        "mfg"
    ],
    "wof:name":"Soy Delites",
    "wof:placetype":"venue"
},
  "geometry": {"coordinates":[-97.71668099999999,30.32376],"type":"Point"}
}