{
  "type": "Feature",
  "properties": {
    "iso:country":"US",
    "sg:address":"10455 N Central Expy",
    "sg:city":"Dallas",
    "sg:classifiers":[
        {
            "category":"Professional",
            "subcategory":"Employment Agencies",
            "type":"Services"
        }
    ],
    "sg:phone":"+1 214 891 1555",
    "sg:postcode":"75231",
    "sg:province":"TX",
    "sg:tags":[
        "consultant",
        "search",
        "executive"
    ],
    "wof:name":"KERR & Co Executive Search",
    "wof:placetype":"venue"
},
  "geometry": {"coordinates":[-96.770321,32.88798],"type":"Point"}
}