{
  "type": "Feature",
  "properties": {
    "iso:country":"US",
    "sg:address":"1200 Stinnet Pl",
    "sg:city":"Desoto",
    "sg:classifiers":[
        {
            "category":"Professional",
            "subcategory":"Business Services",
            "type":"Services"
        }
    ],
    "sg:phone":"+1 832 593 8622",
    "sg:postcode":"75115",
    "sg:province":"TX",
    "wof:name":"Runt Rods",
    "wof:placetype":"venue"
},
  "geometry": {"coordinates":[-96.891227,32.60176],"type":"Point"}
}