{
  "type": "Feature",
  "properties": {
    "iso:country":"US",
    "sg:address":"365 W King Ave",
    "sg:city":"Kingsville",
    "sg:classifiers":[
        {
            "category":"Banks & Credit Unions",
            "subcategory":"Investment Brokerage",
            "type":"Services"
        }
    ],
    "sg:phone":"+1 361 592 7746",
    "sg:postcode":"78363",
    "sg:province":"TX",
    "sg:tags":[
        "advisory"
    ],
    "wof:name":"Waddell & Reed Inc",
    "wof:placetype":"venue"
},
  "geometry": {"coordinates":[-97.871178,27.515464],"type":"Point"}
}