{
  "type": "Feature",
  "properties": {
    "iso:country":"US",
    "sg:address":"3814 Farmington Dr",
    "sg:city":"Richardson",
    "sg:classifiers":[
        {
            "category":"Personal",
            "type":"Services"
        }
    ],
    "sg:phone":"+1 972 768 8246",
    "sg:postcode":"75082",
    "sg:province":"TX",
    "wof:name":"Jordan Enterprises",
    "wof:placetype":"venue"
},
  "geometry": {"coordinates":[-96.616287,33.004181],"type":"Point"}
}