{
  "type": "Feature",
  "properties": {
    "iso:country":"US",
    "sg:address":"421 Jefferson St",
    "sg:city":"Clarendon",
    "sg:classifiers":[
        {
            "category":"Retail",
            "subcategory":"Repair Shop",
            "type":"Services"
        }
    ],
    "sg:phone":"+1 806 874 3477",
    "sg:postcode":"79226",
    "sg:province":"TX",
    "sg:tags":[
        "upholsterer"
    ],
    "wof:name":"Simpson Upholstery",
    "wof:placetype":"venue"
},
  "geometry": {"coordinates":[-100.891909,34.936268],"type":"Point"}
}