{
  "type": "Feature",
  "properties": {
    "iso:country":"US",
    "sg:address":"241 S FM 270",
    "sg:city":"League City",
    "sg:classifiers":[
        {
            "category":"Restaurant",
            "type":"Food & Drink"
        }
    ],
    "sg:phone":"+1 281 332 7511",
    "sg:postcode":"77573",
    "sg:province":"TX",
    "sg:tags":[
        "parlor",
        "ice",
        "cream"
    ],
    "wof:name":"Shakes Frozen Custard",
    "wof:placetype":"venue"
},
  "geometry": {"coordinates":[-95.074979,29.52004],"type":"Point"}
}