{
  "type": "Feature",
  "properties": {
    "iso:country":"US",
    "sg:address":"8148 San Cristobal Dr",
    "sg:city":"Dallas",
    "sg:classifiers":[
        {
            "category":"Professional",
            "subcategory":"Business Services",
            "type":"Services"
        }
    ],
    "sg:phone":"+1 214 320 7247",
    "sg:postcode":"75218",
    "sg:province":"TX",
    "wof:name":"Clark & Assoc",
    "wof:placetype":"venue"
},
  "geometry": {"coordinates":[-96.716269,32.808251],"type":"Point"}
}