{
  "type": "Feature",
  "properties": {
    "iso:country":"US",
    "sg:address":"4444 Vandervoort Dr",
    "sg:city":"Dallas",
    "sg:classifiers":[
        {
            "category":"Organizations",
            "subcategory":"Religious Organization",
            "type":"Services"
        }
    ],
    "sg:phone":"+1 214 371 9939",
    "sg:postcode":"75216",
    "sg:province":"TX",
    "sg:tags":[
        "church"
    ],
    "wof:name":"Oliver Hill Baptist Church",
    "wof:placetype":"venue"
},
  "geometry": {"coordinates":[-96.760344,32.708267],"type":"Point"}
}