{
  "type": "Feature",
  "properties": {
    "iso:country":"US",
    "sg:address":"1810 Effie Ln",
    "sg:city":"Pasadena",
    "sg:classifiers":[
        {
            "category":"Building & Trades",
            "subcategory":"Landscaping Services",
            "type":"Services"
        }
    ],
    "sg:phone":"+1 713 477 4986",
    "sg:postcode":"77502",
    "sg:province":"TX",
    "wof:name":"Andrades Lawn Service",
    "wof:placetype":"venue"
},
  "geometry": {"coordinates":[-95.18373699999999,29.684407],"type":"Point"}
}