{
  "type": "Feature",
  "properties": {
    "iso:country":"US",
    "sg:address":"2804 Tophill Ln",
    "sg:city":"Flower Mound",
    "sg:classifiers":[
        {
            "category":"Professional",
            "subcategory":"Business Services",
            "type":"Services"
        },
        {
            "category":"Shopping",
            "subcategory":"Gifts & Souvenirs",
            "type":"Retail Goods"
        }
    ],
    "sg:phone":"+1 972 317 1965",
    "sg:postcode":"75022",
    "sg:province":"TX",
    "sg:tags":[
        "decorating",
        "contractor"
    ],
    "wof:name":"Balloon House Design Studio",
    "wof:placetype":"venue"
},
  "geometry": {"coordinates":[-97.075669,33.013201],"type":"Point"}
}