{
  "type": "Feature",
  "properties": {
    "iso:country":"US",
    "sg:address":"2123 S Eastman Rd",
    "sg:city":"Longview",
    "sg:classifiers":[
        {
            "category":"Personal",
            "subcategory":"Barber",
            "type":"Services"
        }
    ],
    "sg:phone":"+1 903 757 9908",
    "sg:postcode":"75602",
    "sg:province":"TX",
    "sg:tags":[
        "shop"
    ],
    "wof:name":"Your Barber Shop",
    "wof:placetype":"venue"
},
  "geometry": {"coordinates":[-94.707483,32.469521],"type":"Point"}
}