{
  "type": "Feature",
  "properties": {
    "iso:country":"US",
    "sg:address":"801 Telephone Rd",
    "sg:city":"Houston",
    "sg:classifiers":[
        {
            "category":"Restaurant",
            "type":"Food & Drink"
        }
    ],
    "sg:menulink":"http://www.allmenus.com/tx/houston/177570-jack-in-the-box/menu/",
    "sg:phone":"+1 713 926 6437",
    "sg:postcode":"77023",
    "sg:province":"TX",
    "sg:tags":[
        "burger",
        "american"
    ],
    "wof:name":"Jack in the Box",
    "wof:placetype":"venue"
},
  "geometry": {"coordinates":[-95.32923700000001,29.734363],"type":"Point"}
}