{
  "type": "Feature",
  "properties": {
    "iso:country":"US",
    "sg:address":"6616 Missy Dr",
    "sg:city":"Dallas",
    "sg:classifiers":[
        {
            "category":"Professional",
            "subcategory":"Management & Consulting",
            "type":"Services"
        }
    ],
    "sg:phone":"+1 972 964 1123",
    "sg:postcode":"75252",
    "sg:province":"TX",
    "sg:tags":[
        "public",
        "relations"
    ],
    "wof:name":"Ensite Hosting Inc",
    "wof:placetype":"venue"
},
  "geometry": {"coordinates":[-96.78943099999999,32.999142],"type":"Point"}
}