{
  "type": "Feature",
  "properties": {
    "iso:country":"US",
    "sg:address":"2615 Routh St",
    "sg:city":"Dallas",
    "sg:classifiers":[
        {
            "category":"Shopping",
            "subcategory":"Florist",
            "type":"Retail Goods"
        }
    ],
    "sg:phone":"+1 214 220 1272",
    "sg:postcode":"75201",
    "sg:province":"TX",
    "wof:name":"Garden Gate Floral Design",
    "wof:placetype":"venue"
},
  "geometry": {"coordinates":[-96.80239899999999,32.7967],"type":"Point"}
}