{
  "type": "Feature",
  "properties": {
    "iso:country":"US",
    "sg:address":"209 E Greenbriar Ln",
    "sg:city":"Dallas",
    "sg:classifiers":[
        {
            "category":"Professional",
            "subcategory":"Management & Consulting",
            "type":"Services"
        }
    ],
    "sg:phone":"+1 214 231 7000",
    "sg:postcode":"75203",
    "sg:province":"TX",
    "sg:tags":[
        "business"
    ],
    "wof:name":"Evalutech Services LLC",
    "wof:placetype":"venue"
},
  "geometry": {"coordinates":[-96.819924,32.76422],"type":"Point"}
}