{
  "type": "Feature",
  "properties": {
    "iso:country":"US",
    "sg:address":"7500 Bellaire Blvd",
    "sg:city":"Houston",
    "sg:classifiers":[
        {
            "category":"Shopping",
            "subcategory":"Clothing, Apparel, & Fashions",
            "type":"Retail Goods"
        }
    ],
    "sg:phone":"+1 713 271 2727",
    "sg:postcode":"77036",
    "sg:province":"TX",
    "sg:tags":[
        "furnishing"
    ],
    "wof:name":"Harold Pener Man Of Fashion",
    "wof:placetype":"venue"
},
  "geometry": {"coordinates":[-95.51733400000001,29.705264],"type":"Point"}
}