{
  "type": "Feature",
  "properties": {
    "iso:country":"US",
    "sg:address":"1202 Morning Dove Dr",
    "sg:city":"Duncanville",
    "sg:classifiers":[
        {
            "category":"Professional",
            "subcategory":"Business Services",
            "type":"Services"
        }
    ],
    "sg:phone":"+1 972 283 9208",
    "sg:postcode":"75137",
    "sg:province":"TX",
    "wof:name":"Tipco Enterprise",
    "wof:placetype":"venue"
},
  "geometry": {"coordinates":[-96.91324899999999,32.638922],"type":"Point"}
}