{
  "type": "Feature",
  "properties": {
    "iso:country":"US",
    "sg:address":"4110 Goddard Rd",
    "sg:city":"Fort Worth",
    "sg:classifiers":[
        {
            "category":"Professional",
            "type":"Services"
        }
    ],
    "sg:phone":"+1 817 838 6224",
    "sg:postcode":"76111",
    "sg:province":"TX",
    "sg:tags":[
        "personal",
        "interest"
    ],
    "wof:name":"David F Brady",
    "wof:placetype":"venue"
},
  "geometry": {"coordinates":[-97.285865,32.767083],"type":"Point"}
}