{
  "type": "Feature",
  "properties": {
    "iso:country":"US",
    "sg:address":"5301 S 2nd Ave",
    "sg:city":"Dallas",
    "sg:classifiers":[
        {
            "category":"Autos & Motor Vehicles",
            "subcategory":"Automobile Sales",
            "type":"Retail Goods"
        }
    ],
    "sg:phone":"+1 866 647 9620",
    "sg:postcode":"75210",
    "sg:province":"TX",
    "sg:tags":[
        "automotive"
    ],
    "sg:website":"cashforjunkcars.aitrk.com",
    "wof:name":"Dallas South Pick-n-Pull",
    "wof:placetype":"venue"
},
  "geometry": {"coordinates":[-96.739576,32.752568],"type":"Point"}
}