{
  "type": "Feature",
  "properties": {
    "iso:country":"US",
    "sg:address":"2425 Gateway Dr Ste 106",
    "sg:city":"Irving",
    "sg:classifiers":[
        {
            "category":"Utilities",
            "subcategory":"Telephone",
            "type":"Services"
        }
    ],
    "sg:phone":"+1 972 582 6000",
    "sg:postcode":"75063",
    "sg:province":"TX",
    "sg:tags":[
        "systems-wholesale",
        "equipment",
        "system",
        "manufacturer"
    ],
    "sg:website":"http://www.necam.com",
    "wof:name":"N E C Public Switching Group",
    "wof:placetype":"venue"
},
  "geometry": {"coordinates":[-96.984739,32.893145],"type":"Point"}
}