{
  "type": "Feature",
  "properties": {
    "iso:country":"US",
    "sg:address":"10420 Refinery Rd",
    "sg:city":"Iowa Park",
    "sg:classifiers":[
        {
            "category":"Manufacturing",
            "subcategory":"Petroleum Products",
            "type":"Manufacturing & Wholesale Goods"
        }
    ],
    "sg:phone":"+1 940 438 2204",
    "sg:postcode":"76367",
    "sg:province":"TX",
    "sg:tags":[
        "refiner"
    ],
    "wof:name":"B B Oil Company",
    "wof:placetype":"venue"
},
  "geometry": {"coordinates":[-98.763598,33.894423],"type":"Point"}
}