{
  "type": "Feature",
  "properties": {
    "iso:country":"US",
    "sg:address":"2200 San Pedro Ave",
    "sg:city":"San Antonio",
    "sg:classifiers":[
        {
            "category":"Food & Beverages",
            "subcategory":"Groceries & Convenience Stores",
            "type":"Retail Goods"
        }
    ],
    "sg:phone":"+1 210 734 2697",
    "sg:postcode":"78212",
    "sg:province":"TX",
    "wof:name":"Corner C Mart",
    "wof:placetype":"venue"
},
  "geometry": {"coordinates":[-98.499296,29.455781],"type":"Point"}
}