{
  "type": "Feature",
  "properties": {
    "iso:country":"US",
    "sg:address":"7680 US Hwy 190",
    "sg:city":"Temple",
    "sg:classifiers":[
        {
            "category":"Autos & Motor Vehicles",
            "subcategory":"Auto Supplies",
            "type":"Retail Goods"
        }
    ],
    "sg:phone":"+1 254 983 2321",
    "sg:postcode":"76501",
    "sg:province":"TX",
    "sg:tags":[
        "tire"
    ],
    "wof:name":"Eastbell County Tire",
    "wof:placetype":"venue"
},
  "geometry": {"coordinates":[-97.28873299999999,30.999073],"type":"Point"}
}