{
  "type": "Feature",
  "properties": {
    "iso:country":"US",
    "sg:address":"531 Londonderry Ln # 100",
    "sg:city":"Denton",
    "sg:classifiers":[
        {
            "category":"Health Services",
            "subcategory":"Clinic",
            "type":"Services"
        }
    ],
    "sg:phone":"+1 940 387 7121",
    "sg:postcode":"76205",
    "sg:province":"TX",
    "sg:tags":[
        "information",
        "mental"
    ],
    "wof:name":"Daybreak Mhmr",
    "wof:placetype":"venue"
},
  "geometry": {"coordinates":[-97.128072,33.189953],"type":"Point"}
}