{
  "type": "Feature",
  "properties": {
    "iso:country":"US",
    "sg:address":"100 N Houston St",
    "sg:city":"Granbury",
    "sg:classifiers":[
        {
            "category":"Shopping",
            "subcategory":"Gifts & Souvenirs",
            "type":"Retail Goods"
        }
    ],
    "sg:phone":"+1 817 573 8008",
    "sg:postcode":"76048",
    "sg:province":"TX",
    "wof:name":"Cooldues",
    "wof:placetype":"venue"
},
  "geometry": {"coordinates":[-97.78765,32.443151],"type":"Point"}
}