{
  "type": "Feature",
  "properties": {
    "iso:country":"US",
    "sg:address":"1510 N Garfield St",
    "sg:city":"San Angelo",
    "sg:classifiers":[
        {
            "category":"Shopping",
            "subcategory":"Clothing, Apparel, & Fashions",
            "type":"Retail Goods"
        }
    ],
    "sg:phone":"+1 325 947 4976",
    "sg:postcode":"76901",
    "sg:province":"TX",
    "wof:name":"Trinkums",
    "wof:placetype":"venue"
},
  "geometry": {"coordinates":[-100.48187299999999,31.46114],"type":"Point"}
}