{
  "type": "Feature",
  "properties": {
    "iso:country":"US",
    "sg:address":"1011 N Shepherd Dr",
    "sg:city":"Houston",
    "sg:classifiers":[
        {
            "category":"Health Services",
            "subcategory":"Optometrist",
            "type":"Services"
        }
    ],
    "sg:phone":"+1 713 862 3195",
    "sg:postcode":"77008",
    "sg:province":"TX",
    "wof:name":"Rivera Aurea I Optmtrst",
    "wof:placetype":"venue"
},
  "geometry": {"coordinates":[-95.410004,29.7892],"type":"Point"}
}