{
  "type": "Feature",
  "properties": {
    "iso:country":"US",
    "sg:address":"3205 Oakview Dr",
    "sg:city":"Temple",
    "sg:classifiers":[
        {
            "category":"Education",
            "subcategory":"School",
            "type":"Public Place"
        }
    ],
    "sg:phone":"+1 254 771 5771",
    "sg:postcode":"76502",
    "sg:province":"TX",
    "wof:name":"Central Texas Christian School",
    "wof:placetype":"venue"
},
  "geometry": {"coordinates":[-97.38090200000001,31.073188],"type":"Point"}
}