{
  "type": "Feature",
  "properties": {
    "iso:country":"US",
    "sg:address":"1509 Lynn Dr",
    "sg:city":"Garland",
    "sg:classifiers":[
        {
            "category":"Manufacturing",
            "subcategory":"Printing",
            "type":"Manufacturing & Wholesale Goods"
        }
    ],
    "sg:phone":"+1 972 494 2656",
    "sg:postcode":"75040",
    "sg:province":"TX",
    "sg:tags":[
        "lithographic",
        "commercial"
    ],
    "wof:name":"Litho Electronics Inc",
    "wof:placetype":"venue"
},
  "geometry": {"coordinates":[-96.6322,32.89881],"type":"Point"}
}