{
  "type": "Feature",
  "properties": {
    "iso:country":"US",
    "sg:address":"1010 S Cage Blvd",
    "sg:city":"Pharr",
    "sg:classifiers":[
        {
            "category":"Professional",
            "type":"Services"
        }
    ],
    "sg:phone":"+1 956 782 5757",
    "sg:postcode":"78577",
    "sg:province":"TX",
    "wof:name":"Lan Stone Co",
    "wof:placetype":"venue"
},
  "geometry": {"coordinates":[-98.18566800000001,26.185643],"type":"Point"}
}