{
  "type": "Feature",
  "properties": {
    "iso:country":"US",
    "sg:address":"8501 S Loop Fwy",
    "sg:city":"Houston",
    "sg:classifiers":[
        {
            "category":"Building & Trades",
            "subcategory":"Construction",
            "type":"Services"
        }
    ],
    "sg:phone":"+1 713 923 8691",
    "sg:postcode":"77017",
    "sg:province":"TX",
    "sg:tags":[
        "petroleum",
        "storage",
        "cleaning",
        "tank"
    ],
    "wof:name":"Midwestern Services Inc",
    "wof:placetype":"venue"
},
  "geometry": {"coordinates":[-95.27097500000001,29.708367],"type":"Point"}
}