{
  "type": "Feature",
  "properties": {
    "iso:country":"US",
    "sg:address":"2525 Seagler Rd",
    "sg:city":"Houston",
    "sg:classifiers":[
        {
            "category":"Education",
            "subcategory":"Preschool",
            "type":"Public Place"
        },
        {
            "category":"Education",
            "subcategory":"School",
            "type":"Public Place"
        }
    ],
    "sg:phone":"+1 713 783 0260",
    "sg:postcode":"77042",
    "sg:province":"TX",
    "sg:tags":[
        "elementary"
    ],
    "wof:name":"Church of the Ascension Episcopal School",
    "wof:placetype":"venue"
},
  "geometry": {"coordinates":[-95.553101,29.738701],"type":"Point"}
}