{
  "type": "Feature",
  "properties": {
    "iso:country":"US",
    "sg:address":"2710 Metcalfe Rd",
    "sg:city":"Austin",
    "sg:classifiers":[
        {
            "category":"Wholesale",
            "subcategory":"Electrical",
            "type":"Manufacturing & Wholesale Goods"
        },
        {
            "category":"Shopping",
            "subcategory":"Computers & Home Electronics",
            "type":"Retail Goods"
        }
    ],
    "sg:phone":"+1 512 445 4750",
    "sg:postcode":"78741",
    "sg:province":"TX",
    "sg:tags":[
        "equipment",
        "consumer",
        "electric",
        "supply"
    ],
    "wof:name":"Grokking Electro-Fix",
    "wof:placetype":"venue"
},
  "geometry": {"coordinates":[-97.73659600000001,30.226127],"type":"Point"}
}