{
  "type": "Feature",
  "properties": {
    "iso:country":"US",
    "sg:address":"1520 Clark Blvd",
    "sg:city":"Laredo",
    "sg:classifiers":[
        {
            "category":"Banks & Credit Unions",
            "subcategory":"Bank",
            "type":"Services"
        }
    ],
    "sg:phone":"+1 956 791 8877",
    "sg:postcode":"78040",
    "sg:province":"TX",
    "sg:tags":[
        "loan"
    ],
    "wof:name":"Laredo Loans",
    "wof:placetype":"venue"
},
  "geometry": {"coordinates":[-99.480558,27.516734],"type":"Point"}
}