{
  "type": "Feature",
  "properties": {
    "iso:country":"US",
    "sg:address":"905 Taft St",
    "sg:city":"Houston",
    "sg:classifiers":[
        {
            "category":"Restaurant",
            "type":"Food & Drink"
        }
    ],
    "sg:phone":"+1 713 528 9689",
    "sg:postcode":"77019",
    "sg:province":"TX",
    "wof:name":"Cafe Zorro",
    "wof:placetype":"venue"
},
  "geometry": {"coordinates":[-95.385637,29.757649],"type":"Point"}
}