{
  "type": "Feature",
  "properties": {
    "iso:country":"US",
    "sg:address":"2903 Richmond Rd",
    "sg:city":"Texarkana",
    "sg:classifiers":[
        {
            "category":"Restaurant",
            "type":"Food & Drink"
        }
    ],
    "sg:menulink":"http://www.allmenus.com/tx/texarkana/70641-pizza-hut/menu/",
    "sg:phone":"+1 903 831 5252",
    "sg:postcode":"75503",
    "sg:province":"TX",
    "sg:tags":[
        "american",
        "pizza"
    ],
    "wof:name":"PIZZA HUT",
    "wof:placetype":"venue"
},
  "geometry": {"coordinates":[-94.09169900000001,33.461366],"type":"Point"}
}