{
  "type": "Feature",
  "properties": {
    "iso:country":"US",
    "sg:address":"6702 Hondo Bend",
    "sg:city":"Austin",
    "sg:classifiers":[
        {
            "category":"Professional",
            "type":"Services"
        }
    ],
    "sg:phone":"+1 512 472 3774",
    "sg:postcode":"78729",
    "sg:province":"TX",
    "wof:name":"Blossom Foundation",
    "wof:placetype":"venue"
},
  "geometry": {"coordinates":[-97.746863,30.446508],"type":"Point"}
}