{
  "type": "Feature",
  "properties": {
    "iso:country":"US",
    "sg:address":"8305 Jones Rd",
    "sg:city":"Texas City",
    "sg:classifiers":[
        {
            "category":"Communications",
            "subcategory":"Film & Video Production",
            "type":"Services"
        }
    ],
    "sg:phone":"+1 409 948 1336",
    "sg:postcode":"77591",
    "sg:province":"TX",
    "sg:tags":[
        "freelance",
        "cameraman"
    ],
    "wof:name":"Empire Video Superstore",
    "wof:placetype":"venue"
},
  "geometry": {"coordinates":[-95.003883,29.384385],"type":"Point"}
}