{
  "type": "Feature",
  "properties": {
    "iso:country":"US",
    "sg:address":"2119 Via Estrada",
    "sg:city":"Carrollton",
    "sg:classifiers":[
        {
            "category":"Wholesale",
            "subcategory":"Electrical",
            "type":"Manufacturing & Wholesale Goods"
        }
    ],
    "sg:phone":"+1 972 416 7579",
    "sg:postcode":"75006",
    "sg:province":"TX",
    "sg:tags":[
        "test",
        "electronic",
        "mechanical"
    ],
    "wof:name":"J M Holleman & Associates",
    "wof:placetype":"venue"
},
  "geometry": {"coordinates":[-96.86914400000001,32.969666],"type":"Point"}
}