{
  "type": "Feature",
  "properties": {
    "iso:country":"US",
    "sg:address":"1310 W Main St",
    "sg:city":"Lewisville",
    "sg:classifiers":[
        {
            "category":"Health Services",
            "subcategory":"Health Practitioner",
            "type":"Services"
        }
    ],
    "sg:phone":"+1 972 434 6024",
    "sg:postcode":"75067",
    "sg:province":"TX",
    "wof:name":"Advanced Physical Therapy Inc",
    "wof:placetype":"venue"
},
  "geometry": {"coordinates":[-97.03196699999999,33.042093],"type":"Point"}
}