{
  "type": "Feature",
  "properties": {
    "iso:country":"US",
    "sg:address":"306 Kessler Ave",
    "sg:city":"Schulenburg",
    "sg:classifiers":[
        {
            "category":"Food & Beverages",
            "subcategory":"Liquor & Beverages",
            "type":"Retail Goods"
        }
    ],
    "sg:phone":"+1 979 743 4042",
    "sg:postcode":"78956",
    "sg:province":"TX",
    "sg:tags":[
        "alcoholic"
    ],
    "wof:name":"Schulenburg Liquor Store",
    "wof:placetype":"venue"
},
  "geometry": {"coordinates":[-96.90290899999999,29.683687],"type":"Point"}
}