{
  "type": "Feature",
  "properties": {
    "iso:country":"US",
    "sg:address":"2508 Forest Point Dr",
    "sg:city":"Arlington",
    "sg:classifiers":[
        {
            "category":"Real Estate",
            "subcategory":"Real Estate Operator",
            "type":"Services"
        }
    ],
    "sg:phone":"+1 972 988 3505",
    "sg:postcode":"76006",
    "sg:province":"TX",
    "sg:tags":[
        "apartment"
    ],
    "sg:website":"www.equityapartments.com",
    "wof:name":"Forest Ridge Apartments",
    "wof:placetype":"venue"
},
  "geometry": {"coordinates":[-97.06340899999999,32.785697],"type":"Point"}
}