{
  "type": "Feature",
  "properties": {
    "iso:country":"US",
    "sg:address":"2341 Havard Oak Dr",
    "sg:city":"Plano",
    "sg:classifiers":[
        {
            "category":"Professional",
            "subcategory":"Management & Consulting",
            "type":"Services"
        }
    ],
    "sg:phone":"+1 972 422 6425",
    "sg:postcode":"75074",
    "sg:province":"TX",
    "wof:name":"Business Network Consulting",
    "wof:placetype":"venue"
},
  "geometry": {"coordinates":[-96.65503,33.032265],"type":"Point"}
}