{
  "type": "Feature",
  "properties": {
    "iso:country":"US",
    "sg:address":"301 W Cowan Dr",
    "sg:city":"Houston",
    "sg:classifiers":[
        {
            "category":"Shopping",
            "type":"Retail Goods"
        }
    ],
    "sg:phone":"+1 713 861 6495",
    "sg:postcode":"77007",
    "sg:province":"TX",
    "sg:tags":[
        "merchandise"
    ],
    "wof:name":"R L Pet Mc Kinney",
    "wof:placetype":"venue"
},
  "geometry": {"coordinates":[-95.42637499999999,29.764941],"type":"Point"}
}