{
  "type": "Feature",
  "properties": {
    "iso:country":"US",
    "sg:address":"2001 Bryan St",
    "sg:city":"Dallas",
    "sg:classifiers":[
        {
            "category":"Banks & Credit Unions",
            "subcategory":"Bank",
            "type":"Services"
        }
    ],
    "sg:phone":"+1 972 869 0012",
    "sg:postcode":"75201",
    "sg:province":"TX",
    "sg:tags":[
        "federal",
        "savings",
        "institution"
    ],
    "wof:name":"Fidelity Federal Savings Assn",
    "wof:placetype":"venue"
},
  "geometry": {"coordinates":[-96.795788,32.78539],"type":"Point"}
}