{
  "type": "Feature",
  "properties": {
    "iso:country":"US",
    "sg:address":"8405 Beech Ln",
    "sg:city":"Mc Kinney",
    "sg:classifiers":[
        {
            "category":"Communications",
            "subcategory":"Film & Video Production",
            "type":"Services"
        }
    ],
    "sg:phone":"+1 972 529 2092",
    "sg:postcode":"75070",
    "sg:province":"TX",
    "sg:tags":[
        "motion"
    ],
    "wof:name":"Video Creations & Productions",
    "wof:placetype":"venue"
},
  "geometry": {"coordinates":[-96.726091,33.198557],"type":"Point"}
}