{
  "type": "Feature",
  "properties": {
    "iso:country":"US",
    "sg:address":"3621 Kimberly Ln",
    "sg:city":"Fort Worth",
    "sg:classifiers":[
        {
            "category":"Building & Trades",
            "subcategory":"Construction",
            "type":"Services"
        }
    ],
    "sg:phone":"+1 817 370 1935",
    "sg:postcode":"76133",
    "sg:province":"TX",
    "sg:tags":[
        "contractor"
    ],
    "wof:name":"Brantleys Weathertec",
    "wof:placetype":"venue"
},
  "geometry": {"coordinates":[-97.371773,32.668798],"type":"Point"}
}