{
  "type": "Feature",
  "properties": {
    "iso:country":"US",
    "sg:address":"11311 Harry Hines Blvd",
    "sg:city":"Dallas",
    "sg:classifiers":[
        {
            "category":"Wholesale",
            "subcategory":"Durable Goods & Equipment",
            "type":"Manufacturing & Wholesale Goods"
        }
    ],
    "sg:phone":"+1 972 241 4818",
    "sg:postcode":"75229",
    "sg:province":"TX",
    "sg:tags":[
        "importer"
    ],
    "sg:website":"www.ravisiwi.com",
    "wof:name":"Import Warehouse Inc",
    "wof:placetype":"venue"
},
  "geometry": {"coordinates":[-96.890564,32.893435],"type":"Point"}
}