{
  "type": "Feature",
  "properties": {
    "iso:country":"US",
    "sg:address":"1717 Turning Basin Dr",
    "sg:city":"Houston",
    "sg:classifiers":[
        {
            "category":"Freight",
            "type":"Transportation"
        }
    ],
    "sg:phone":"+1 713 236 0902",
    "sg:postcode":"77029",
    "sg:province":"TX",
    "sg:tags":[
        "trucking"
    ],
    "wof:name":"Gem Delivery Svc",
    "wof:placetype":"venue"
},
  "geometry": {"coordinates":[-95.265479,29.749837],"type":"Point"}
}