{
  "type": "Feature",
  "properties": {
    "iso:country":"US",
    "sg:address":"4691 FM 1516 N",
    "sg:city":"Converse",
    "sg:classifiers":[
        {
            "category":"Retail",
            "subcategory":"Auto Repair",
            "type":"Services"
        }
    ],
    "sg:phone":"+1 210 661 3474",
    "sg:postcode":"78109",
    "sg:province":"TX",
    "sg:tags":[
        "truck"
    ],
    "wof:name":"Quality Truck & Trailer Inc",
    "wof:placetype":"venue"
},
  "geometry": {"coordinates":[-98.31297000000001,29.47212],"type":"Point"}
}