{
  "type": "Feature",
  "properties": {
    "iso:country":"US",
    "sg:address":"11821 28th St",
    "sg:city":"Santa Fe",
    "sg:classifiers":[
        {
            "category":"Building & Trades",
            "subcategory":"Landscaping Services",
            "type":"Services"
        }
    ],
    "sg:phone":"+1 409 925 5125",
    "sg:postcode":"77510",
    "sg:province":"TX",
    "wof:name":"Melvin David and Sons",
    "wof:placetype":"venue"
},
  "geometry": {"coordinates":[-95.07978300000001,29.354318],"type":"Point"}
}