{
  "type": "Feature",
  "properties": {
    "iso:country":"US",
    "sg:address":"2218 Bancroft St",
    "sg:city":"Houston",
    "sg:classifiers":[
        {
            "category":"Professional",
            "subcategory":"Management & Consulting",
            "type":"Services"
        }
    ],
    "sg:phone":"+1 713 622 5419",
    "sg:postcode":"77027",
    "sg:province":"TX",
    "wof:name":"Ssor Management LLC",
    "wof:placetype":"venue"
},
  "geometry": {"coordinates":[-95.45187199999999,29.745899],"type":"Point"}
}