{
  "type": "Feature",
  "properties": {
    "iso:country":"US",
    "sg:address":"524 Salem Dr",
    "sg:city":"Richardson",
    "sg:classifiers":[
        {
            "category":"Personal",
            "type":"Services"
        }
    ],
    "sg:phone":"+1 972 235 5752",
    "sg:postcode":"75080",
    "sg:province":"TX",
    "wof:name":"Crazy Quilter",
    "wof:placetype":"venue"
},
  "geometry": {"coordinates":[-96.737184,32.970535],"type":"Point"}
}