{
  "type": "Feature",
  "properties": {
    "iso:country":"US",
    "sg:address":"317 N Milton St",
    "sg:city":"San Angelo",
    "sg:classifiers":[
        {
            "category":"Building & Trades",
            "subcategory":"Construction",
            "type":"Services"
        }
    ],
    "sg:phone":"+1 325 659 2143",
    "sg:postcode":"76901",
    "sg:province":"TX",
    "sg:tags":[
        "residential"
    ],
    "wof:name":"West Texas Investments",
    "wof:placetype":"venue"
},
  "geometry": {"coordinates":[-100.462695,31.457787],"type":"Point"}
}