{
  "type": "Feature",
  "properties": {
    "iso:country":"US",
    "sg:address":"4211 Mulberry Dr",
    "sg:city":"Carrollton",
    "sg:classifiers":[
        {
            "category":"Professional",
            "type":"Services"
        }
    ],
    "sg:phone":"+1 972 395 0461",
    "sg:postcode":"75010",
    "sg:province":"TX",
    "wof:name":"Ya Corporation Inc",
    "wof:placetype":"venue"
},
  "geometry": {"coordinates":[-96.908477,33.026221],"type":"Point"}
}