{
  "type": "Feature",
  "properties": {
    "iso:country":"US",
    "sg:address":"1316 W Alabama St",
    "sg:city":"Houston",
    "sg:classifiers":[
        {
            "category":"Insurance",
            "subcategory":"Insurance Agent",
            "type":"Services"
        }
    ],
    "sg:phone":"+1 713 522 2792",
    "sg:postcode":"77006",
    "sg:province":"TX",
    "wof:name":"Four Season Insurance Inc",
    "wof:placetype":"venue"
},
  "geometry": {"coordinates":[-95.395578,29.738797],"type":"Point"}
}