{
  "type": "Feature",
  "properties": {
    "iso:country":"US",
    "sg:address":"3619 Parry Ave",
    "sg:city":"Dallas",
    "sg:classifiers":[
        {
            "category":"Professional",
            "subcategory":"Business Services",
            "type":"Services"
        }
    ],
    "sg:phone":"+1 214 827 2220",
    "sg:postcode":"75226",
    "sg:province":"TX",
    "sg:tags":[
        "bureau"
    ],
    "wof:name":"Acme CD Manufacturing Co",
    "wof:placetype":"venue"
},
  "geometry": {"coordinates":[-96.766469,32.78202],"type":"Point"}
}