{
  "type": "Feature",
  "properties": {
    "iso:country":"US",
    "sg:address":"106 E 6th St",
    "sg:city":"Austin",
    "sg:classifiers":[
        {
            "category":"Professional",
            "subcategory":"Lawyer & Legal Services",
            "type":"Services"
        }
    ],
    "sg:phone":"+1 512 322 5775",
    "sg:postcode":"78701",
    "sg:province":"TX",
    "sg:tags":[
        "attorney"
    ],
    "wof:name":"Linda Robinson",
    "wof:placetype":"venue"
},
  "geometry": {"coordinates":[-97.741502,30.267777],"type":"Point"}
}