{
  "type": "Feature",
  "properties": {
    "iso:country":"US",
    "sg:address":"1612 Hart St",
    "sg:city":"Southlake",
    "sg:classifiers":[
        {
            "category":"Professional",
            "subcategory":"Business Services",
            "type":"Services"
        }
    ],
    "sg:phone":"+1 817 329 7303",
    "sg:postcode":"76092",
    "sg:province":"TX",
    "sg:tags":[
        "interior",
        "design",
        "flooring",
        "drapery"
    ],
    "wof:name":"Primas Design Center",
    "wof:placetype":"venue"
},
  "geometry": {"coordinates":[-97.12634799999999,32.924209],"type":"Point"}
}