{
  "type": "Feature",
  "properties": {
    "iso:country":"US",
    "sg:address":"15601 Dallas Pkwy Ste 500",
    "sg:city":"Addison",
    "sg:classifiers":[
        {
            "category":"Health Services",
            "subcategory":"Doctor",
            "type":"Services"
        }
    ],
    "sg:phone":"+1 214 237 4502",
    "sg:postcode":"75001",
    "sg:province":"TX",
    "wof:name":"Solis Womens Health",
    "wof:placetype":"venue"
},
  "geometry": {"coordinates":[-96.822011,32.962487],"type":"Point"}
}