{
  "type": "Feature",
  "properties": {
    "iso:country":"US",
    "sg:address":"11814 Cordoba Dr",
    "sg:city":"Houston",
    "sg:classifiers":[
        {
            "category":"Professional",
            "subcategory":"Business Services",
            "type":"Services"
        }
    ],
    "sg:phone":"+1 281 820 6344",
    "sg:postcode":"77038",
    "sg:province":"TX",
    "wof:name":"General Inventory Service",
    "wof:placetype":"venue"
},
  "geometry": {"coordinates":[-95.447012,29.905639],"type":"Point"}
}