{
  "type": "Feature",
  "properties": {
    "iso:country":"US",
    "sg:address":"4107 Armistice Dr",
    "sg:city":"Frisco",
    "sg:classifiers":[
        {
            "category":"Professional",
            "subcategory":"Management & Consulting",
            "type":"Services"
        }
    ],
    "sg:phone":"+1 972 668 8002",
    "sg:postcode":"75034",
    "sg:province":"TX",
    "sg:tags":[
        "business"
    ],
    "wof:name":"Windows By Design",
    "wof:placetype":"venue"
},
  "geometry": {"coordinates":[-96.85158199999999,33.113529],"type":"Point"}
}