{
  "type": "Feature",
  "properties": {
    "iso:country":"US",
    "sg:address":"3800 State Hwy 6",
    "sg:city":"College Station",
    "sg:classifiers":[
        {
            "category":"Restaurant",
            "type":"Food & Drink"
        }
    ],
    "sg:menulink":"http://www.allmenus.com/tx/bryan-college-station/70346-pizza-hut/menu/",
    "sg:phone":"+1 979 693 9393",
    "sg:postcode":"77845",
    "sg:province":"TX",
    "sg:tags":[
        "american",
        "pizza"
    ],
    "wof:name":"Pizza Hut",
    "wof:placetype":"venue"
},
  "geometry": {"coordinates":[-96.28751699999999,30.587699],"type":"Point"}
}