{
  "type": "Feature",
  "properties": {
    "iso:country":"US",
    "sg:address":"4600 Guadalupe Ste B-2",
    "sg:city":"Austin",
    "sg:classifiers":[
        {
            "category":"Coffee & Tea",
            "type":"Food & Drink"
        }
    ],
    "sg:phone":"+1 512 467 4365",
    "sg:postcode":"78751",
    "sg:province":"TX",
    "sg:website":"kickbuttcoffee.com",
    "wof:name":"Kick Butt Coffee",
    "wof:placetype":"venue"
},
  "geometry": {"coordinates":[-97.733903,30.314117],"type":"Point"}
}