{
  "type": "Feature",
  "properties": {
    "iso:country":"US",
    "sg:address":"100 Orchard Ln",
    "sg:city":"Rockwall",
    "sg:classifiers":[
        {
            "category":"Professional",
            "subcategory":"Management & Consulting",
            "type":"Services"
        }
    ],
    "sg:phone":"+1 972 771 2712",
    "sg:postcode":"75087",
    "sg:province":"TX",
    "sg:tags":[
        "communications",
        "consultant"
    ],
    "wof:name":"Guardian Consulting & Comm",
    "wof:placetype":"venue"
},
  "geometry": {"coordinates":[-96.430263,32.952806],"type":"Point"}
}