{
  "type": "Feature",
  "properties": {
    "iso:country":"US",
    "sg:address":"243 E Stamford St",
    "sg:city":"Abilene",
    "sg:classifiers":[
        {
            "category":"Food & Beverages",
            "subcategory":"Candy",
            "type":"Retail Goods"
        }
    ],
    "sg:phone":"+1 325 672 1355",
    "sg:postcode":"79601",
    "sg:province":"TX",
    "sg:tags":[
        "confectionery"
    ],
    "wof:name":"Russell Stover 225",
    "wof:placetype":"venue"
},
  "geometry": {"coordinates":[-99.723465,32.489746],"type":"Point"}
}