{
  "type": "Feature",
  "properties": {
    "iso:country":"US",
    "sg:address":"304 Mesquite Hill Dr",
    "sg:city":"Arlington",
    "sg:classifiers":[
        {
            "category":"Manufacturing",
            "subcategory":"Motor Vehicles & Parts",
            "type":"Manufacturing & Wholesale Goods"
        }
    ],
    "sg:phone":"+1 817 417 4250",
    "sg:postcode":"76002",
    "sg:province":"TX",
    "sg:tags":[
        "mfg"
    ],
    "wof:name":"Purvis Equipment Corporation",
    "wof:placetype":"venue"
},
  "geometry": {"coordinates":[-97.113851,32.615049],"type":"Point"}
}