{
  "type": "Feature",
  "properties": {
    "iso:country":"US",
    "sg:address":"16988 County Road 476",
    "sg:city":"Lindale",
    "sg:classifiers":[
        {
            "category":"Home & Garden",
            "subcategory":"Building Materials",
            "type":"Retail Goods"
        }
    ],
    "sg:phone":"+1 903 882 4839",
    "sg:postcode":"75771",
    "sg:province":"TX",
    "sg:tags":[
        "sand",
        "gravel"
    ],
    "wof:name":"Lindale Sand & Gravel",
    "wof:placetype":"venue"
},
  "geometry": {"coordinates":[-95.447469,32.517771],"type":"Point"}
}