{
  "type": "Feature",
  "properties": {
    "iso:country":"US",
    "sg:address":"1612 W Randol Mill Rd",
    "sg:city":"Arlington",
    "sg:classifiers":[
        {
            "category":"Banks & Credit Unions",
            "subcategory":"Investment Brokerage",
            "type":"Services"
        }
    ],
    "sg:phone":"+1 817 276 1684",
    "sg:postcode":"76012",
    "sg:province":"TX",
    "sg:tags":[
        "advisory",
        "financial"
    ],
    "wof:name":"Q C Financial",
    "wof:placetype":"venue"
},
  "geometry": {"coordinates":[-97.131508,32.750139],"type":"Point"}
}