{
  "type": "Feature",
  "properties": {
    "iso:country":"US",
    "sg:address":"16007 Upshire St",
    "sg:city":"Channelview",
    "sg:classifiers":[
        {
            "category":"Manufacturing",
            "subcategory":"Printing",
            "type":"Manufacturing & Wholesale Goods"
        }
    ],
    "sg:phone":"+1 281 457 1483",
    "sg:postcode":"77530",
    "sg:province":"TX",
    "sg:tags":[
        "printer"
    ],
    "wof:name":"Kiru Office Help",
    "wof:placetype":"venue"
},
  "geometry": {"coordinates":[-95.11673999999999,29.797856],"type":"Point"}
}