{
  "type": "Feature",
  "properties": {
    "iso:country":"US",
    "sg:address":"115 Caldwell St",
    "sg:city":"Baytown",
    "sg:classifiers":[
        {
            "category":"Arts & Performance",
            "subcategory":"Theater",
            "type":"Entertainment"
        }
    ],
    "sg:phone":"+1 281 424 9763",
    "sg:postcode":"77520",
    "sg:province":"TX",
    "sg:tags":[
        "group"
    ],
    "wof:name":"Smooth Groove Productions",
    "wof:placetype":"venue"
},
  "geometry": {"coordinates":[-95.037361,29.777594],"type":"Point"}
}