{
  "type": "Feature",
  "properties": {
    "iso:country":"US",
    "sg:address":"15330 Poplar Grove Dr",
    "sg:city":"Houston",
    "sg:classifiers":[
        {
            "category":"Professional",
            "subcategory":"Management & Consulting",
            "type":"Services"
        }
    ],
    "sg:phone":"+1 281 586 0192",
    "sg:postcode":"77068",
    "sg:province":"TX",
    "wof:name":"Bowles Ventures Inc",
    "wof:placetype":"venue"
},
  "geometry": {"coordinates":[-95.495803,30.0027],"type":"Point"}
}