{
  "type": "Feature",
  "properties": {
    "iso:country":"US",
    "sg:address":"8026 Vantage Dr",
    "sg:city":"San Antonio",
    "sg:classifiers":[
        {
            "category":"Health Services",
            "subcategory":"Health Practitioner",
            "type":"Services"
        }
    ],
    "sg:phone":"+1 210 979 0802",
    "sg:postcode":"78230",
    "sg:province":"TX",
    "sg:tags":[
        "physician"
    ],
    "wof:name":"Ruth Rojo",
    "wof:placetype":"venue"
},
  "geometry": {"coordinates":[-98.55143099999999,29.510447],"type":"Point"}
}