{
  "type": "Feature",
  "properties": {
    "iso:country":"US",
    "sg:address":"511 S Patrick St",
    "sg:city":"Gonzales",
    "sg:classifiers":[
        {
            "category":"Insurance",
            "subcategory":"Insurance Agent",
            "type":"Services"
        }
    ],
    "sg:phone":"+1 830 672 6177",
    "sg:postcode":"78629",
    "sg:province":"TX",
    "wof:name":"Jackie L Mills Insurance Agcy",
    "wof:placetype":"venue"
},
  "geometry": {"coordinates":[-97.435614,29.497422],"type":"Point"}
}