{
  "type": "Feature",
  "properties": {
    "iso:country":"US",
    "sg:address":"613 Clearwood Dr",
    "sg:city":"Richardson",
    "sg:classifiers":[
        {
            "category":"Real Estate",
            "subcategory":"Real Estate Operator",
            "type":"Services"
        }
    ],
    "sg:phone":"+1 972 238 9188",
    "sg:postcode":"75081",
    "sg:province":"TX",
    "sg:tags":[
        "apartment",
        "complex"
    ],
    "wof:name":"Falls On Clearwood",
    "wof:placetype":"venue"
},
  "geometry": {"coordinates":[-96.746453,32.936542],"type":"Point"}
}