{
  "type": "Feature",
  "properties": {
    "iso:country":"US",
    "sg:address":"1200 FM 1462",
    "sg:city":"Alvin",
    "sg:classifiers":[
        {
            "category":"Shopping",
            "subcategory":"Gifts & Souvenirs",
            "type":"Retail Goods"
        }
    ],
    "sg:phone":"+1 281 331 0032",
    "sg:postcode":"77511",
    "sg:province":"TX",
    "sg:tags":[
        "collectible"
    ],
    "wof:name":"Bene's Closet",
    "wof:placetype":"venue"
},
  "geometry": {"coordinates":[-95.247929,29.401238],"type":"Point"}
}