{
  "type": "Feature",
  "properties": {
    "iso:country":"US",
    "sg:address":"76 Shiloh Rd",
    "sg:city":"Odessa",
    "sg:classifiers":[
        {
            "category":"Professional",
            "subcategory":"Business Services",
            "type":"Services"
        }
    ],
    "sg:phone":"+1 432 368 0818",
    "sg:postcode":"79762",
    "sg:province":"TX",
    "wof:name":"ABB Equipment Inc",
    "wof:placetype":"venue"
},
  "geometry": {"coordinates":[-102.30289399999999,31.894242],"type":"Point"}
}