{
  "type": "Feature",
  "properties": {
    "iso:country":"US",
    "sg:address":"416 N 1st St",
    "sg:city":"Lamesa",
    "sg:classifiers":[
        {
            "category":"Banks & Credit Unions",
            "subcategory":"Bank",
            "type":"Services"
        }
    ],
    "sg:phone":"+1 806 872 3568",
    "sg:postcode":"79331",
    "sg:province":"TX",
    "sg:tags":[
        "personal",
        "institution"
    ],
    "wof:name":"Delta Loans",
    "wof:placetype":"venue"
},
  "geometry": {"coordinates":[-101.951988,32.73323],"type":"Point"}
}