{
  "type": "Feature",
  "properties": {
    "iso:country":"US",
    "sg:address":"3413 Lariat Ln",
    "sg:city":"Corpus Christi",
    "sg:classifiers":[
        {
            "category":"Retail",
            "subcategory":"Repair Shop",
            "type":"Services"
        }
    ],
    "sg:phone":"+1 361 853 4034",
    "sg:postcode":"78415",
    "sg:province":"TX",
    "sg:tags":[
        "equipment",
        "conditioning",
        "air"
    ],
    "wof:name":"Harris Air Conditioning & Htg",
    "wof:placetype":"venue"
},
  "geometry": {"coordinates":[-97.40922,27.719917],"type":"Point"}
}