{
  "type": "Feature",
  "properties": {
    "iso:country":"US",
    "sg:address":"8001 Bayside St",
    "sg:city":"Galveston",
    "sg:classifiers":[
        {
            "category":"Building & Trades",
            "subcategory":"Construction",
            "type":"Services"
        }
    ],
    "sg:phone":"+1 409 740 6988",
    "sg:postcode":"77554",
    "sg:province":"TX",
    "sg:tags":[
        "contractor"
    ],
    "wof:name":"R L H Construction Inc",
    "wof:placetype":"venue"
},
  "geometry": {"coordinates":[-94.861593,29.289613],"type":"Point"}
}