{
  "type": "Feature",
  "properties": {
    "iso:country":"US",
    "sg:address":"1424 Woodland Trl",
    "sg:city":"Abilene",
    "sg:classifiers":[
        {
            "category":"Real Estate",
            "subcategory":"Real Estate Operator",
            "type":"Services"
        }
    ],
    "sg:phone":"+1 325 698 8887",
    "sg:postcode":"79605",
    "sg:province":"TX",
    "sg:tags":[
        "building",
        "nonresidential"
    ],
    "wof:name":"J Hamil Properties LLC",
    "wof:placetype":"venue"
},
  "geometry": {"coordinates":[-99.777558,32.432105],"type":"Point"}
}