{
  "type": "Feature",
  "properties": {
    "iso:country":"US",
    "sg:address":"12117 FM 853",
    "sg:city":"San Angelo",
    "sg:classifiers":[
        {
            "category":"Building & Trades",
            "subcategory":"Equipment Rental",
            "type":"Services"
        }
    ],
    "sg:phone":"+1 325 949 8188",
    "sg:postcode":"76901",
    "sg:province":"TX",
    "sg:tags":[
        "heavy",
        "construction"
    ],
    "wof:name":"Mp Cattle Co",
    "wof:placetype":"venue"
},
  "geometry": {"coordinates":[-100.618101,31.439673],"type":"Point"}
}