{
  "type": "Feature",
  "properties": {
    "iso:country":"US",
    "sg:address":"1850 FM 359",
    "sg:city":"Richmond",
    "sg:classifiers":[
        {
            "category":"Cinema",
            "subcategory":"Movie Rental",
            "type":"Entertainment"
        }
    ],
    "sg:phone":"+1 281 238 5646",
    "sg:postcode":"77469",
    "sg:province":"TX",
    "sg:tags":[
        "video",
        "tape"
    ],
    "wof:name":"Silver Screen Video",
    "wof:placetype":"venue"
},
  "geometry": {"coordinates":[-95.743567,29.621527],"type":"Point"}
}