{
  "type": "Feature",
  "properties": {
    "iso:country":"US",
    "sg:address":"3210 S Main St",
    "sg:city":"Lindale",
    "sg:classifiers":[
        {
            "category":"Restaurant",
            "type":"Food & Drink"
        }
    ],
    "sg:phone":"+1 903 882 3227",
    "sg:postcode":"75771",
    "sg:province":"TX",
    "sg:tags":[
        "american"
    ],
    "sg:website":"http://www.chilis.com",
    "wof:name":"Chili's Grill & Bar",
    "wof:placetype":"venue"
},
  "geometry": {"coordinates":[-95.39103900000001,32.474516],"type":"Point"}
}