{
  "type": "Feature",
  "properties": {
    "iso:country":"US",
    "sg:address":"1241 N Creek Cir",
    "sg:city":"Waxahachie",
    "sg:classifiers":[
        {
            "category":"Building & Trades",
            "subcategory":"Construction",
            "type":"Services"
        }
    ],
    "sg:phone":"+1 972 938 0224",
    "sg:postcode":"75165",
    "sg:province":"TX",
    "sg:tags":[
        "home",
        "builder"
    ],
    "wof:name":"Don Schmerse Custom Homes",
    "wof:placetype":"venue"
},
  "geometry": {"coordinates":[-96.811888,32.469712],"type":"Point"}
}