{
  "type": "Feature",
  "properties": {
    "iso:country":"US",
    "sg:address":"7910 Gateway Blvd E",
    "sg:city":"El Paso",
    "sg:classifiers":[
        {
            "category":"Real Estate",
            "subcategory":"Real Estate Agent",
            "type":"Services"
        }
    ],
    "sg:phone":"+1 915 594 7855",
    "sg:postcode":"79915",
    "sg:province":"TX",
    "wof:name":"Century 21 Your Neighborhood",
    "wof:placetype":"venue"
},
  "geometry": {"coordinates":[-106.349825,31.754929],"type":"Point"}
}