{
  "type": "Feature",
  "properties": {
    "iso:country":"US",
    "sg:address":"1810 Summit Rd E",
    "sg:city":"Abilene",
    "sg:classifiers":[
        {
            "category":"Retail",
            "subcategory":"Repair Shop",
            "type":"Services"
        }
    ],
    "sg:phone":"+1 325 672 1551",
    "sg:postcode":"79601",
    "sg:province":"TX",
    "wof:name":"Anything Fiberglass",
    "wof:placetype":"venue"
},
  "geometry": {"coordinates":[-99.743996,32.511192],"type":"Point"}
}