{
  "type": "Feature",
  "properties": {
    "iso:country":"US",
    "sg:address":"2601 Miori Ln",
    "sg:city":"Victoria",
    "sg:classifiers":[
        {
            "category":"Autos & Motor Vehicles",
            "subcategory":"Auto Supplies",
            "type":"Retail Goods"
        }
    ],
    "sg:phone":"+1 361 580 1569",
    "sg:postcode":"77901",
    "sg:province":"TX",
    "sg:tags":[
        "repair",
        "general"
    ],
    "wof:name":"Cirilo Auto Service",
    "wof:placetype":"venue"
},
  "geometry": {"coordinates":[-96.978207,28.824309],"type":"Point"}
}