{
  "type": "Feature",
  "properties": {
    "iso:country":"US",
    "sg:address":"5910 Grace Ln",
    "sg:city":"Houston",
    "sg:classifiers":[
        {
            "category":"Real Estate",
            "subcategory":"Architect",
            "type":"Services"
        }
    ],
    "sg:phone":"+1 713 440 0083",
    "sg:postcode":"77021",
    "sg:province":"TX",
    "sg:website":"www.maarchitecturestudio.com",
    "wof:name":"M A Architecture Studio",
    "wof:placetype":"venue"
},
  "geometry": {"coordinates":[-95.342877,29.698542],"type":"Point"}
}