{
  "type": "Feature",
  "properties": {
    "iso:country":"US",
    "sg:address":"100 Grand Fairway",
    "sg:city":"Spring",
    "sg:classifiers":[
        {
            "category":"Shopping",
            "subcategory":"Bicycles & Sporting Goods",
            "type":"Retail Goods"
        },
        {
            "category":"Organizations",
            "subcategory":"Membership Organization",
            "type":"Services"
        },
        {
            "category":"Sports & Exercise",
            "subcategory":"Golf",
            "type":"Entertainment"
        }
    ],
    "sg:phone":"+1 281 863 1440",
    "sg:postcode":"77381",
    "sg:province":"TX",
    "sg:tags":[
        "course",
        "club",
        "supply",
        "private",
        "equipment",
        "courses-private"
    ],
    "wof:name":"Woodlands Country Club The Palmer Pro. Shop",
    "wof:placetype":"venue"
},
  "geometry": {"coordinates":[-95.51937100000001,30.188829],"type":"Point"}
}