{
  "type": "Feature",
  "properties": {
    "iso:country":"US",
    "sg:address":"308 S Ragsdale St",
    "sg:city":"Jacksonville",
    "sg:classifiers":[
        {
            "category":"Professional",
            "subcategory":"Accounting & Tax Preparation",
            "type":"Services"
        }
    ],
    "sg:phone":"+1 903 586 2275",
    "sg:postcode":"75766",
    "sg:province":"TX",
    "sg:tags":[
        "accountant"
    ],
    "wof:name":"Hugh L Goodpasture CPA",
    "wof:placetype":"venue"
},
  "geometry": {"coordinates":[-95.271309,31.963053],"type":"Point"}
}