{
  "type": "Feature",
  "properties": {
    "iso:country":"US",
    "sg:address":"5820 Annapolis St",
    "sg:city":"Houston",
    "sg:classifiers":[
        {
            "category":"Communications",
            "type":"Services"
        }
    ],
    "sg:phone":"+1 713 666 5780",
    "sg:postcode":"77005",
    "sg:province":"TX",
    "sg:tags":[
        "communication"
    ],
    "wof:name":"Media Communications Plus",
    "wof:placetype":"venue"
},
  "geometry": {"coordinates":[-95.420957,29.719533],"type":"Point"}
}