{
  "type": "Feature",
  "properties": {
    "iso:country":"US",
    "sg:address":"29 Borondo Stretch",
    "sg:city":"La Marque",
    "sg:classifiers":[
        {
            "category":"Building & Trades",
            "subcategory":"Construction",
            "type":"Services"
        }
    ],
    "sg:phone":"+1 409 935 2656",
    "sg:postcode":"77568",
    "sg:province":"TX",
    "sg:tags":[
        "home",
        "builder"
    ],
    "wof:name":"Kebbel Homes",
    "wof:placetype":"venue"
},
  "geometry": {"coordinates":[-94.992175,29.356626],"type":"Point"}
}