{
  "type": "Feature",
  "properties": {
    "iso:country":"US",
    "sg:address":"10418 Shayna Dr",
    "sg:city":"Dallas",
    "sg:classifiers":[
        {
            "category":"Building & Trades",
            "subcategory":"Construction",
            "type":"Services"
        }
    ],
    "sg:phone":"+1 972 285 3194",
    "sg:postcode":"75217",
    "sg:province":"TX",
    "sg:tags":[
        "contractor"
    ],
    "wof:name":"Metal Fences Barandales Aposto",
    "wof:placetype":"venue"
},
  "geometry": {"coordinates":[-96.644605,32.743919],"type":"Point"}
}