{
  "type": "Feature",
  "properties": {
    "iso:country":"US",
    "sg:address":"1424 Fm 1092 Rd",
    "sg:city":"Missouri City",
    "sg:classifiers":[
        {
            "category":"Organizations",
            "subcategory":"Religious Organization",
            "type":"Services"
        }
    ],
    "sg:phone":"+1 281 499 7611",
    "sg:postcode":"77459",
    "sg:province":"TX",
    "wof:name":"New Hope Lutheran Church-Elca",
    "wof:placetype":"venue"
},
  "geometry": {"coordinates":[-95.56440000000001,29.598801],"type":"Point"}
}