{
  "type": "Feature",
  "properties": {
    "iso:country":"US",
    "sg:address":"308 W Main St",
    "sg:city":"Eagle Lake",
    "sg:classifiers":[
        {
            "category":"Retail",
            "subcategory":"Auto Repair",
            "type":"Services"
        }
    ],
    "sg:phone":"+1 979 234 3773",
    "sg:postcode":"77434",
    "sg:province":"TX",
    "sg:tags":[
        "repairing",
        "automobile",
        "radiator"
    ],
    "wof:name":"Way Out West Ind Radiator Svc",
    "wof:placetype":"venue"
},
  "geometry": {"coordinates":[-96.33653700000001,29.590788],"type":"Point"}
}