{
  "type": "Feature",
  "properties": {
    "iso:country":"US",
    "sg:address":"1051 N Jefferson St",
    "sg:city":"La Grange",
    "sg:classifiers":[
        {
            "category":"Professional",
            "type":"Services"
        }
    ],
    "sg:phone":"+1 979 968 9944",
    "sg:postcode":"78945",
    "sg:province":"TX",
    "sg:tags":[
        "establishment"
    ],
    "wof:name":"Bugle Boy",
    "wof:placetype":"venue"
},
  "geometry": {"coordinates":[-96.88166,29.91291],"type":"Point"}
}