{
  "type": "Feature",
  "properties": {
    "iso:country":"US",
    "sg:address":"5221 S Zapata Hwy",
    "sg:city":"Laredo",
    "sg:classifiers":[
        {
            "category":"Home & Garden",
            "subcategory":"Mobile Homes",
            "type":"Retail Goods"
        }
    ],
    "sg:phone":"+1 956 724 1607",
    "sg:postcode":"78046",
    "sg:province":"TX",
    "wof:name":"Juan Navraez Mfg Homes",
    "wof:placetype":"venue"
},
  "geometry": {"coordinates":[-99.47777000000001,27.448657],"type":"Point"}
}