{
  "type": "Feature",
  "properties": {
    "iso:country":"US",
    "sg:address":"24688 Sorters Rd",
    "sg:city":"Porter",
    "sg:classifiers":[
        {
            "category":"Retail",
            "subcategory":"Auto Repair",
            "type":"Services"
        }
    ],
    "sg:phone":"+1 281 354 7448",
    "sg:postcode":"77365",
    "sg:province":"TX",
    "sg:tags":[
        "body"
    ],
    "wof:name":"Paint Body Works",
    "wof:placetype":"venue"
},
  "geometry": {"coordinates":[-95.274974,30.090317],"type":"Point"}
}