{
  "type": "Feature",
  "properties": {
    "iso:country":"US",
    "sg:address":"1331 Gemini St",
    "sg:city":"Houston",
    "sg:classifiers":[
        {
            "category":"Professional",
            "subcategory":"Lawyer & Legal Services",
            "type":"Services"
        }
    ],
    "sg:phone":"+1 281 486 9461",
    "sg:postcode":"77058",
    "sg:province":"TX",
    "wof:name":"Billy R Smith PC",
    "wof:placetype":"venue"
},
  "geometry": {"coordinates":[-95.113249,29.557529],"type":"Point"}
}