{
  "type": "Feature",
  "properties": {
    "iso:country":"US",
    "sg:address":"3600 San Bernardo Ave",
    "sg:city":"Laredo",
    "sg:classifiers":[
        {
            "category":"Professional",
            "type":"Services"
        }
    ],
    "sg:phone":"+1 956 753 9032",
    "sg:postcode":"78041",
    "sg:province":"TX",
    "sg:tags":[
        "establishment"
    ],
    "wof:name":"Cibsa",
    "wof:placetype":"venue"
},
  "geometry": {"coordinates":[-99.50439,27.532747],"type":"Point"}
}