{
  "type": "Feature",
  "properties": {
    "iso:country":"US",
    "sg:address":"14520 Memorial Dr",
    "sg:city":"Houston",
    "sg:classifiers":[
        {
            "category":"Education",
            "subcategory":"Dance Studio",
            "type":"Public Place"
        }
    ],
    "sg:phone":"+1 281 558 0369",
    "sg:postcode":"77079",
    "sg:province":"TX",
    "wof:name":"Adagio Intl Dance Studios",
    "wof:placetype":"venue"
},
  "geometry": {"coordinates":[-95.6032,29.770219],"type":"Point"}
}