{
  "type": "Feature",
  "properties": {
    "iso:country":"US",
    "sg:address":"236 Marina Dr",
    "sg:city":"Montgomery",
    "sg:classifiers":[
        {
            "category":"Professional",
            "type":"Services"
        }
    ],
    "sg:phone":"+1 936 588 1004",
    "sg:postcode":"77356",
    "sg:province":"TX",
    "sg:tags":[
        "establishment"
    ],
    "wof:name":"April Harbor Hoa Pool",
    "wof:placetype":"venue"
},
  "geometry": {"coordinates":[-95.595018,30.363676],"type":"Point"}
}