{
  "type": "Feature",
  "properties": {
    "iso:country":"US",
    "sg:address":"6380 Phelan Blvd",
    "sg:city":"Beaumont",
    "sg:classifiers":[
        {
            "category":"Restaurant",
            "type":"Food & Drink"
        }
    ],
    "sg:phone":"+1 409 866 7272",
    "sg:postcode":"77706",
    "sg:province":"TX",
    "wof:name":"Mc Donald's",
    "wof:placetype":"venue"
},
  "geometry": {"coordinates":[-94.167975,30.078729],"type":"Point"}
}