{
  "type": "Feature",
  "properties": {
    "iso:country":"US",
    "sg:address":"621 Jefferson St",
    "sg:city":"Santa Anna",
    "sg:classifiers":[
        {
            "category":"Real Estate",
            "subcategory":"Real Estate Operator",
            "type":"Services"
        }
    ],
    "sg:phone":"+1 325 348 9350",
    "sg:postcode":"76878",
    "sg:province":"TX",
    "sg:tags":[
        "building",
        "apartment"
    ],
    "wof:name":"Mira Vista Apts",
    "wof:placetype":"venue"
},
  "geometry": {"coordinates":[-99.322705,31.735937],"type":"Point"}
}