{
  "type": "Feature",
  "properties": {
    "iso:country":"US",
    "sg:address":"1105 Arbor Gate Dr",
    "sg:city":"Garland",
    "sg:classifiers":[
        {
            "category":"Health Services",
            "subcategory":"Clinic",
            "type":"Services"
        }
    ],
    "sg:phone":"+1 214 549 3894",
    "sg:postcode":"75040",
    "sg:province":"TX",
    "sg:tags":[
        "welfare"
    ],
    "wof:name":"Francis Michael Dba-Triple F Home Healthcare Agency",
    "wof:placetype":"venue"
},
  "geometry": {"coordinates":[-96.620158,32.93874],"type":"Point"}
}