{
  "type": "Feature",
  "properties": {
    "iso:country":"US",
    "sg:address":"4211 Interstate Dr",
    "sg:city":"Amarillo",
    "sg:classifiers":[
        {
            "category":"Real Estate",
            "subcategory":"Real Estate Agent",
            "type":"Services"
        }
    ],
    "sg:phone":"+1 806 373 3111",
    "sg:postcode":"79106",
    "sg:province":"TX",
    "sg:website":"www.jgaut.com",
    "wof:name":"J Gaut & Assoc",
    "wof:placetype":"venue"
},
  "geometry": {"coordinates":[-101.884028,35.191137],"type":"Point"}
}