{
  "type": "Feature",
  "properties": {
    "iso:country":"US",
    "sg:address":"594 E FM 120",
    "sg:city":"Denison",
    "sg:classifiers":[
        {
            "category":"Food & Beverages",
            "subcategory":"Groceries & Convenience Stores",
            "type":"Retail Goods"
        }
    ],
    "sg:phone":"+1 903 465 2045",
    "sg:postcode":"75021",
    "sg:province":"TX",
    "sg:tags":[
        "grocer"
    ],
    "wof:name":"Patti's Grocery & Svc Station",
    "wof:placetype":"venue"
},
  "geometry": {"coordinates":[-96.51552,33.755325],"type":"Point"}
}