{
  "type": "Feature",
  "properties": {
    "iso:country":"US",
    "sg:address":"1008 US Hwy 77X Bus",
    "sg:city":"Harlingen",
    "sg:classifiers":[
        {
            "category":"Travel",
            "subcategory":"Travel Agent",
            "type":"Entertainment"
        }
    ],
    "sg:phone":"+1 956 428 0217",
    "sg:postcode":"78550",
    "sg:province":"TX",
    "sg:tags":[
        "agency"
    ],
    "wof:name":"Adventures In Travel",
    "wof:placetype":"venue"
},
  "geometry": {"coordinates":[-97.685901,26.203798],"type":"Point"}
}