{
  "type": "Feature",
  "properties": {
    "iso:country":"US",
    "sg:address":"415 N Main St",
    "sg:city":"Jacksonville",
    "sg:classifiers":[
        {
            "category":"Retail",
            "subcategory":"Funeral Services",
            "type":"Services"
        }
    ],
    "sg:phone":"+1 903 586 4698",
    "sg:postcode":"75766",
    "sg:province":"TX",
    "wof:name":"Mercy Funeral Home",
    "wof:placetype":"venue"
},
  "geometry": {"coordinates":[-95.275036,31.96755],"type":"Point"}
}