{
  "type": "Feature",
  "properties": {
    "iso:country":"US",
    "sg:address":"2515 W Jefferson Blvd",
    "sg:city":"Dallas",
    "sg:classifiers":[
        {
            "category":"Restaurant",
            "type":"Food & Drink"
        }
    ],
    "sg:phone":"+1 214 948 3969",
    "sg:postcode":"75211",
    "sg:province":"TX",
    "sg:tags":[
        "eating"
    ],
    "wof:name":"Starbucks",
    "wof:placetype":"venue"
},
  "geometry": {"coordinates":[-96.858228,32.748147],"type":"Point"}
}