{
  "type": "Feature",
  "properties": {
    "iso:country":"US",
    "sg:address":"3224 Modella Ave",
    "sg:city":"Dallas",
    "sg:classifiers":[
        {
            "category":"Building & Trades",
            "subcategory":"Construction",
            "type":"Services"
        }
    ],
    "sg:phone":"+1 972 406 9102",
    "sg:postcode":"75229",
    "sg:province":"TX",
    "sg:tags":[
        "carpentry",
        "contractor"
    ],
    "wof:name":"J R Trim",
    "wof:placetype":"venue"
},
  "geometry": {"coordinates":[-96.868568,32.906513],"type":"Point"}
}