{
  "type": "Feature",
  "properties": {
    "iso:country":"US",
    "sg:address":"3701 N Main St",
    "sg:city":"Taylor",
    "sg:classifiers":[
        {
            "category":"Personal",
            "subcategory":"Beauty Salon",
            "type":"Services"
        }
    ],
    "sg:phone":"+1 512 352 5003",
    "sg:postcode":"76574",
    "sg:province":"TX",
    "wof:name":"Smart Style Family Hair Salon",
    "wof:placetype":"venue"
},
  "geometry": {"coordinates":[-97.41626599999999,30.599798],"type":"Point"}
}