{
  "type": "Feature",
  "properties": {
    "iso:country":"US",
    "sg:address":"135 Arapahoe Ridge",
    "sg:city":"Weatherford",
    "sg:classifiers":[
        {
            "category":"Professional",
            "subcategory":"Business Services",
            "type":"Services"
        }
    ],
    "sg:phone":"+1 817 598 0522",
    "sg:postcode":"76087",
    "sg:province":"TX",
    "wof:name":"Building Innovations Group",
    "wof:placetype":"venue"
},
  "geometry": {"coordinates":[-97.743081,32.718083],"type":"Point"}
}