{
  "type": "Feature",
  "properties": {
    "iso:country":"US",
    "sg:address":"2216 S Soncy Rd",
    "sg:city":"Amarillo",
    "sg:classifiers":[
        {
            "category":"Banks & Credit Unions",
            "subcategory":"Bank",
            "type":"Services"
        }
    ],
    "sg:phone":"+1 806 342 4456",
    "sg:postcode":"79124",
    "sg:province":"TX",
    "wof:name":"First National Bank Building",
    "wof:placetype":"venue"
},
  "geometry": {"coordinates":[-101.938373,35.188537],"type":"Point"}
}