{
  "type": "Feature",
  "properties": {
    "iso:country":"US",
    "sg:address":"1490 E Whitestone Blvd",
    "sg:city":"Cedar Park",
    "sg:classifiers":[
        {
            "category":"Professional",
            "subcategory":"Employment Agencies",
            "type":"Services"
        }
    ],
    "sg:phone":"+1 512 260 9065",
    "sg:postcode":"78613",
    "sg:province":"TX",
    "wof:name":"Advance Med Llc",
    "wof:placetype":"venue"
},
  "geometry": {"coordinates":[-97.810799,30.5268],"type":"Point"}
}