{
  "type": "Feature",
  "properties": {
    "iso:country":"US",
    "sg:address":"510 el Paso St",
    "sg:city":"Mason",
    "sg:classifiers":[
        {
            "category":"Travel",
            "subcategory":"Hotels & Motels",
            "type":"Entertainment"
        }
    ],
    "sg:phone":"+1 325 347 6477",
    "sg:postcode":"76856",
    "sg:province":"TX",
    "sg:tags":[
        "breakfast",
        "accommodation",
        "bed"
    ],
    "wof:name":"Oma's & Opa's Bed & Breakfast",
    "wof:placetype":"venue"
},
  "geometry": {"coordinates":[-99.236277,30.749127],"type":"Point"}
}