{
  "type": "Feature",
  "properties": {
    "iso:country":"US",
    "sg:address":"8702 Crest Ridge Cir",
    "sg:city":"Austin",
    "sg:classifiers":[
        {
            "category":"Personal",
            "type":"Services"
        }
    ],
    "sg:phone":"+1 512 258 6662",
    "sg:postcode":"78750",
    "sg:province":"TX",
    "sg:tags":[
        "merchandise"
    ],
    "wof:name":"Beautcntrol By Jmmy Sue Coburn",
    "wof:placetype":"venue"
},
  "geometry": {"coordinates":[-97.786818,30.437403],"type":"Point"}
}