{
  "type": "Feature",
  "properties": {
    "iso:country":"US",
    "sg:address":"14930 Walters Rd",
    "sg:city":"Houston",
    "sg:classifiers":[
        {
            "category":"Shopping",
            "subcategory":"Catalog Store",
            "type":"Retail Goods"
        }
    ],
    "sg:phone":"+1 281 397 7120",
    "sg:postcode":"77068",
    "sg:province":"TX",
    "sg:tags":[
        "mail",
        "house"
    ],
    "wof:name":"Artful Nature",
    "wof:placetype":"venue"
},
  "geometry": {"coordinates":[-95.488193,30.000455],"type":"Point"}
}