{
  "type": "Feature",
  "properties": {
    "iso:country":"US",
    "sg:address":"1291 County Road 1150",
    "sg:city":"Ravenna",
    "sg:classifiers":[
        {
            "category":"Building & Trades",
            "subcategory":"Landscaping Services",
            "type":"Services"
        }
    ],
    "sg:phone":"+1 903 640 9096",
    "sg:postcode":"75476",
    "sg:province":"TX",
    "sg:tags":[
        "lawn",
        "maintenance"
    ],
    "wof:name":"Matt Gibbs Mowing Services",
    "wof:placetype":"venue"
},
  "geometry": {"coordinates":[-96.20061699999999,33.698055],"type":"Point"}
}