{
  "type": "Feature",
  "properties": {
    "iso:country":"US",
    "sg:address":"8514 Pines Place Dr",
    "sg:city":"Humble",
    "sg:classifiers":[
        {
            "category":"Manufacturing",
            "subcategory":"Tools & Machinery",
            "type":"Manufacturing & Wholesale Goods"
        }
    ],
    "sg:phone":"+1 281 852 9517",
    "sg:postcode":"77346",
    "sg:province":"TX",
    "sg:tags":[
        "building",
        "equipment",
        "construction"
    ],
    "wof:name":"A1 Backhoe & Clearing Corp.",
    "wof:placetype":"venue"
},
  "geometry": {"coordinates":[-95.148374,30.003816],"type":"Point"}
}