{
  "type": "Feature",
  "properties": {
    "iso:country":"US",
    "sg:address":"18718 Timbers Dr",
    "sg:city":"Humble",
    "sg:classifiers":[
        {
            "category":"Professional",
            "type":"Services"
        }
    ],
    "sg:phone":"+1 281 852 2174",
    "sg:postcode":"77346",
    "sg:province":"TX",
    "wof:name":"Ewts Inc",
    "wof:placetype":"venue"
},
  "geometry": {"coordinates":[-95.190184,29.993688],"type":"Point"}
}