{
  "type": "Feature",
  "properties": {
    "iso:country":"US",
    "sg:address":"3009 Houston Hwy",
    "sg:city":"Victoria",
    "sg:classifiers":[
        {
            "category":"Travel",
            "subcategory":"Hotels & Motels",
            "type":"Entertainment"
        }
    ],
    "sg:phone":"+1 361 575 0278",
    "sg:postcode":"77901",
    "sg:province":"TX",
    "sg:tags":[
        "building",
        "operator",
        "operation",
        "apartment"
    ],
    "wof:name":"Six Flags Motel Inc",
    "wof:placetype":"venue"
},
  "geometry": {"coordinates":[-96.971761,28.81307],"type":"Point"}
}