{
  "type": "Feature",
  "properties": {
    "iso:country":"US",
    "sg:address":"112 S Seaman St",
    "sg:city":"Eastland",
    "sg:classifiers":[
        {
            "category":"Real Estate",
            "subcategory":"Real Estate Agent",
            "type":"Services"
        }
    ],
    "sg:phone":"+1 254 629 3600",
    "sg:postcode":"76448",
    "sg:province":"TX",
    "sg:tags":[
        "desk",
        "space"
    ],
    "wof:name":"Old Rip Plaza",
    "wof:placetype":"venue"
},
  "geometry": {"coordinates":[-98.81804099999999,32.401676],"type":"Point"}
}