{
  "type": "Feature",
  "properties": {
    "iso:country":"US",
    "sg:address":"3014 Bellmead Dr",
    "sg:city":"Waco",
    "sg:classifiers":[
        {
            "category":"Shopping",
            "subcategory":"Florist",
            "type":"Retail Goods"
        }
    ],
    "sg:phone":"+1 254 799 3483",
    "sg:postcode":"76705",
    "sg:province":"TX",
    "wof:name":"Flower Paradise Inc",
    "wof:placetype":"venue"
},
  "geometry": {"coordinates":[-97.099842,31.590735],"type":"Point"}
}