{
  "type": "Feature",
  "properties": {
    "iso:country":"US",
    "sg:address":"403 S Bosque St",
    "sg:city":"Whitney",
    "sg:classifiers":[
        {
            "category":"Sports & Exercise",
            "subcategory":"Gym",
            "type":"Entertainment"
        }
    ],
    "sg:phone":"+1 254 694 1424",
    "sg:postcode":"76692",
    "sg:province":"TX",
    "sg:tags":[
        "club",
        "health",
        "studio",
        "gymnasium"
    ],
    "wof:name":"Curves Of Whitney",
    "wof:placetype":"venue"
},
  "geometry": {"coordinates":[-97.316873,31.940828],"type":"Point"}
}