{
  "type": "Feature",
  "properties": {
    "iso:country":"US",
    "sg:address":"1335 N Cowan Ave",
    "sg:city":"Lewisville",
    "sg:classifiers":[
        {
            "category":"Autos & Motor Vehicles",
            "subcategory":"Automobile Sales",
            "type":"Retail Goods"
        }
    ],
    "sg:phone":"+1 972 219 9703",
    "sg:postcode":"75057",
    "sg:province":"TX",
    "sg:tags":[
        "car",
        "dealer"
    ],
    "wof:name":"B & M Auto",
    "wof:placetype":"venue"
},
  "geometry": {"coordinates":[-97.00126899999999,33.061444],"type":"Point"}
}