{
  "type": "Feature",
  "properties": {
    "iso:country":"US",
    "sg:address":"807 Brazos Park Dr",
    "sg:city":"Clute",
    "sg:classifiers":[
        {
            "category":"Freight",
            "type":"Transportation"
        }
    ],
    "sg:phone":"+1 979 265 7471",
    "sg:postcode":"77531",
    "sg:province":"TX",
    "sg:tags":[
        "commercial",
        "storage"
    ],
    "wof:name":"Storage USA",
    "wof:placetype":"venue"
},
  "geometry": {"coordinates":[-95.419045,29.013278],"type":"Point"}
}