{
  "type": "Feature",
  "properties": {
    "iso:country":"US",
    "sg:address":"1 S 1st St",
    "sg:city":"Temple",
    "sg:classifiers":[
        {
            "category":"Real Estate",
            "subcategory":"Real Estate Operator",
            "type":"Services"
        }
    ],
    "sg:phone":"+1 254 773 7778",
    "sg:postcode":"76501",
    "sg:province":"TX",
    "sg:tags":[
        "property",
        "oil"
    ],
    "wof:name":"Joe T Shepperd Oil & Gas",
    "wof:placetype":"venue"
},
  "geometry": {"coordinates":[-97.342553,31.095926],"type":"Point"}
}