{
  "type": "Feature",
  "properties": {
    "iso:country":"US",
    "sg:address":"2187 Danville Rd",
    "sg:city":"Kilgore",
    "sg:classifiers":[
        {
            "category":"Organizations",
            "subcategory":"Religious Organization",
            "type":"Services"
        }
    ],
    "sg:phone":"+1 903 984 4683",
    "sg:postcode":"75662",
    "sg:province":"TX",
    "sg:tags":[
        "church"
    ],
    "wof:name":"Danville United Meth Church",
    "wof:placetype":"venue"
},
  "geometry": {"coordinates":[-94.826859,32.401273],"type":"Point"}
}