{
  "type": "Feature",
  "properties": {
    "iso:country":"US",
    "sg:address":"1212 Wyoming Ave",
    "sg:city":"El Paso",
    "sg:classifiers":[
        {
            "category":"Building & Trades",
            "subcategory":"Construction",
            "type":"Services"
        }
    ],
    "sg:phone":"+1 915 532 1810",
    "sg:postcode":"79902",
    "sg:province":"TX",
    "sg:tags":[
        "tile",
        "dealer"
    ],
    "wof:name":"Flores Tile Svc",
    "wof:placetype":"venue"
},
  "geometry": {"coordinates":[-106.480029,31.769001],"type":"Point"}
}