{
  "type": "Feature",
  "properties": {
    "iso:country":"US",
    "sg:address":"1210 Taylor Ave",
    "sg:city":"Victoria",
    "sg:classifiers":[
        {
            "category":"Insurance",
            "subcategory":"Insurance Agent",
            "type":"Services"
        }
    ],
    "sg:phone":"+1 361 576 1852",
    "sg:postcode":"77901",
    "sg:province":"TX",
    "wof:name":"Borrego Insurance Co",
    "wof:placetype":"venue"
},
  "geometry": {"coordinates":[-96.99394700000001,28.832655],"type":"Point"}
}