{
  "type": "Feature",
  "properties": {
    "iso:country":"US",
    "sg:address":"625 Corn Products Rd",
    "sg:city":"Corpus Christi",
    "sg:classifiers":[
        {
            "category":"Professional",
            "subcategory":"Business Services",
            "type":"Services"
        }
    ],
    "sg:phone":"+1 361 289 5300",
    "sg:postcode":"78409",
    "sg:province":"TX",
    "sg:tags":[
        "barricade"
    ],
    "sg:website":"www.ur.com",
    "wof:name":"United Rentals Highway Tech",
    "wof:placetype":"venue"
},
  "geometry": {"coordinates":[-97.4862,27.796942],"type":"Point"}
}