{
  "type": "Feature",
  "properties": {
    "iso:country":"US",
    "sg:address":"7901 el Rio St",
    "sg:city":"Houston",
    "sg:classifiers":[
        {
            "category":"Government",
            "subcategory":"Office",
            "type":"Public Place"
        }
    ],
    "sg:phone":"+1 713 991 6881",
    "sg:postcode":"77054",
    "sg:province":"TX",
    "sg:website":"www.co.harris.tx.us",
    "wof:name":"Harris County Svc Ctr",
    "wof:placetype":"venue"
},
  "geometry": {"coordinates":[-95.388668,29.686465],"type":"Point"}
}