{
  "type": "Feature",
  "properties": {
    "iso:country":"US",
    "sg:address":"1031 W Crawford St",
    "sg:city":"Denison",
    "sg:classifiers":[
        {
            "category":"Manufacturing",
            "subcategory":"Apparel",
            "type":"Manufacturing & Wholesale Goods"
        }
    ],
    "sg:phone":"+1 903 465 8686",
    "sg:postcode":"75020",
    "sg:province":"TX",
    "sg:tags":[
        "clothing",
        "mfg"
    ],
    "wof:name":"K Trading",
    "wof:placetype":"venue"
},
  "geometry": {"coordinates":[-96.55044700000001,33.753965],"type":"Point"}
}