{
  "type": "Feature",
  "properties": {
    "iso:country":"US",
    "sg:address":"4408 Tahoe Dr",
    "sg:city":"Fort Worth",
    "sg:classifiers":[
        {
            "category":"Social Services",
            "subcategory":"Child Care",
            "type":"Services"
        }
    ],
    "sg:phone":"+1 817 531 4564",
    "sg:postcode":"76119",
    "sg:province":"TX",
    "wof:name":"Linda's Daycare",
    "wof:placetype":"venue"
},
  "geometry": {"coordinates":[-97.25744299999999,32.700074],"type":"Point"}
}