{
  "type": "Feature",
  "properties": {
    "iso:country":"US",
    "sg:address":"310 Rock Island Ave Ste B",
    "sg:city":"Dalhart",
    "sg:classifiers":[
        {
            "category":"Insurance",
            "subcategory":"Insurance Agent",
            "type":"Services"
        },
        {
            "category":"Insurance",
            "subcategory":"Hazard Insurance",
            "type":"Services"
        },
        {
            "category":"Insurance",
            "subcategory":"Health Insurance",
            "type":"Services"
        }
    ],
    "sg:phone":"+1 806 244 9813",
    "sg:postcode":"79022",
    "sg:province":"TX",
    "sg:tags":[
        "employee",
        "auto",
        "benefit",
        "commercial",
        "business"
    ],
    "sg:website":"http://www.farmersagent.com/lmontgomery1",
    "wof:name":"Farmers Insurance",
    "wof:placetype":"venue"
},
  "geometry": {"coordinates":[-102.52449,36.062814],"type":"Point"}
}