{
  "type": "Feature",
  "properties": {
    "iso:country":"US",
    "sg:address":"23054 FM 1093",
    "sg:city":"Richmond",
    "sg:classifiers":[
        {
            "category":"Freight",
            "type":"Transportation"
        }
    ],
    "sg:phone":"+1 281 392 3988",
    "sg:postcode":"77469",
    "sg:province":"TX",
    "sg:tags":[
        "commercial",
        "storage"
    ],
    "wof:name":"House It Storage",
    "wof:placetype":"venue"
},
  "geometry": {"coordinates":[-95.779612,29.70045],"type":"Point"}
}