{
  "type": "Feature",
  "properties": {
    "iso:country":"US",
    "sg:address":"500 S Main St",
    "sg:city":"Carbon",
    "sg:classifiers":[
        {
            "category":"Freight",
            "type":"Transportation"
        }
    ],
    "sg:phone":"+1 254 639 2071",
    "sg:postcode":"76435",
    "sg:province":"TX",
    "sg:tags":[
        "trucking"
    ],
    "wof:name":"Triple T Transport",
    "wof:placetype":"venue"
},
  "geometry": {"coordinates":[-98.830691,32.267995],"type":"Point"}
}