{
  "type": "Feature",
  "properties": {
    "iso:country":"US",
    "sg:address":"2528 Spring Rain Dr",
    "sg:city":"Mesquite",
    "sg:classifiers":[
        {
            "category":"Real Estate",
            "subcategory":"Real Estate Agent",
            "type":"Services"
        }
    ],
    "sg:phone":"+1 972 222 9195",
    "sg:postcode":"75181",
    "sg:province":"TX",
    "sg:tags":[
        "inspection"
    ],
    "wof:name":"A Total Home Inspection",
    "wof:placetype":"venue"
},
  "geometry": {"coordinates":[-96.541321,32.739693],"type":"Point"}
}