{
  "type": "Feature",
  "properties": {
    "iso:country":"US",
    "sg:address":"1314 Kemp Blvd",
    "sg:city":"Wichita Falls",
    "sg:classifiers":[
        {
            "category":"Professional",
            "type":"Services"
        }
    ],
    "sg:phone":"+1 940 716 0280",
    "sg:postcode":"76309",
    "sg:province":"TX",
    "wof:name":"American Power Washing SE",
    "wof:placetype":"venue"
},
  "geometry": {"coordinates":[-98.52100799999999,33.90076],"type":"Point"}
}