{
  "type": "Feature",
  "properties": {
    "iso:country":"US",
    "sg:address":"10911 FM 2728",
    "sg:city":"Terrell",
    "sg:classifiers":[
        {
            "category":"Retail",
            "subcategory":"Repair Shop",
            "type":"Services"
        }
    ],
    "sg:phone":"+1 972 524 0346",
    "sg:postcode":"75161",
    "sg:province":"TX",
    "sg:tags":[
        "plant",
        "packing",
        "meat"
    ],
    "wof:name":"American Taxidermy",
    "wof:placetype":"venue"
},
  "geometry": {"coordinates":[-96.184456,32.696724],"type":"Point"}
}