{
  "type": "Feature",
  "properties": {
    "iso:country":"US",
    "sg:address":"1597 Acacia Pkwy",
    "sg:city":"Spring Branch",
    "sg:classifiers":[
        {
            "category":"Building & Trades",
            "subcategory":"Construction",
            "type":"Services"
        }
    ],
    "sg:phone":"+1 830 885 6884",
    "sg:postcode":"78070",
    "sg:province":"TX",
    "sg:tags":[
        "contractor"
    ],
    "wof:name":"Comal Roofing",
    "wof:placetype":"venue"
},
  "geometry": {"coordinates":[-98.427179,29.849081],"type":"Point"}
}