{
  "type": "Feature",
  "properties": {
    "iso:country":"US",
    "sg:address":"131 Lamar St",
    "sg:city":"Mathis",
    "sg:classifiers":[
        {
            "category":"Manufacturing",
            "subcategory":"Buildings",
            "type":"Manufacturing & Wholesale Goods"
        },
        {
            "category":"Building & Trades",
            "subcategory":"Construction",
            "type":"Services"
        }
    ],
    "sg:phone":"+1 361 678 4152",
    "sg:postcode":"78368",
    "sg:province":"TX",
    "sg:tags":[
        "home",
        "builder",
        "contractor"
    ],
    "wof:name":"Ovalle Construction",
    "wof:placetype":"venue"
},
  "geometry": {"coordinates":[-97.81591299999999,28.086172],"type":"Point"}
}