{
  "type": "Feature",
  "properties": {
    "iso:country":"US",
    "sg:address":"4215 Navajo St",
    "sg:city":"Pasadena",
    "sg:classifiers":[
        {
            "category":"Professional",
            "type":"Services"
        }
    ],
    "sg:phone":"+1 281 487 3857",
    "sg:postcode":"77504",
    "sg:province":"TX",
    "wof:name":"Vectair Aviation LLC",
    "wof:placetype":"venue"
},
  "geometry": {"coordinates":[-95.17843499999999,29.64438],"type":"Point"}
}