{
  "type": "Feature",
  "properties": {
    "iso:country":"US",
    "sg:address":"4105 Buckingham Pl",
    "sg:city":"Colleyville",
    "sg:classifiers":[
        {
            "category":"Health Services",
            "subcategory":"Clinic",
            "type":"Services"
        }
    ],
    "sg:phone":"+1 817 571 0378",
    "sg:postcode":"76034",
    "sg:province":"TX",
    "wof:name":"Accu Stat Med Transcription Co",
    "wof:placetype":"venue"
},
  "geometry": {"coordinates":[-97.126687,32.868019],"type":"Point"}
}