{
  "type": "Feature",
  "properties": {
    "iso:country":"US",
    "sg:address":"800 Washington Ave",
    "sg:city":"Waco",
    "sg:classifiers":[
        {
            "category":"Banks & Credit Unions",
            "subcategory":"Bank",
            "type":"Services"
        }
    ],
    "sg:phone":"+1 254 757 1455",
    "sg:postcode":"76701",
    "sg:province":"TX",
    "sg:tags":[
        "financing",
        "company",
        "mortgage"
    ],
    "wof:name":"First Preference Holdings",
    "wof:placetype":"venue"
},
  "geometry": {"coordinates":[-97.136335,31.554503],"type":"Point"}
}