{
  "type": "Feature",
  "properties": {
    "iso:country":"US",
    "sg:address":"10714 Mount Tipton St",
    "sg:city":"San Antonio",
    "sg:classifiers":[
        {
            "category":"Real Estate",
            "subcategory":"Real Estate Agent",
            "type":"Services"
        }
    ],
    "sg:phone":"+1 210 341 8445",
    "sg:postcode":"78213",
    "sg:province":"TX",
    "sg:tags":[
        "a",
        "as",
        "manager"
    ],
    "wof:name":"Focolare Movement",
    "wof:placetype":"venue"
},
  "geometry": {"coordinates":[-98.513645,29.538192],"type":"Point"}
}