{
  "type": "Feature",
  "properties": {
    "iso:country":"US",
    "sg:address":"835 Tower Dr",
    "sg:city":"Odessa",
    "sg:classifiers":[
        {
            "category":"Professional",
            "subcategory":"Management & Consulting",
            "type":"Services"
        },
        {
            "category":"Professional",
            "subcategory":"Employment Agencies",
            "type":"Services"
        }
    ],
    "sg:phone":"+1 432 337 0440",
    "sg:postcode":"79761",
    "sg:province":"TX",
    "sg:tags":[
        "opportunity"
    ],
    "wof:name":"Energi Personnel",
    "wof:placetype":"venue"
},
  "geometry": {"coordinates":[-102.342412,31.863946],"type":"Point"}
}