{
  "type": "Feature",
  "properties": {
    "iso:country":"US",
    "sg:address":"5214 Marcillus Ave",
    "sg:city":"El Paso",
    "sg:classifiers":[
        {
            "category":"Shopping",
            "subcategory":"Jewelry",
            "type":"Retail Goods"
        }
    ],
    "sg:phone":"+1 915 751 8407",
    "sg:postcode":"79924",
    "sg:province":"TX",
    "wof:name":"Leganna Jewelry",
    "wof:placetype":"venue"
},
  "geometry": {"coordinates":[-106.417468,31.891967],"type":"Point"}
}