{
  "type": "Feature",
  "properties": {
    "iso:country":"US",
    "sg:address":"12924 Willow Chase Dr",
    "sg:city":"Houston",
    "sg:classifiers":[
        {
            "category":"Shopping",
            "subcategory":"Gifts & Souvenirs",
            "type":"Retail Goods"
        }
    ],
    "sg:phone":"+1 281 894 2825",
    "sg:postcode":"77070",
    "sg:province":"TX",
    "sg:tags":[
        "shop"
    ],
    "wof:name":"Tuesday Morning 160",
    "wof:placetype":"venue"
},
  "geometry": {"coordinates":[-95.552227,29.960334],"type":"Point"}
}