{
  "type": "Feature",
  "properties": {
    "iso:country":"US",
    "sg:address":"113 Wilson Ranch Rd",
    "sg:city":"Round Mountain",
    "sg:classifiers":[
        {
            "category":"Manufacturing",
            "subcategory":"Musical Instruments",
            "type":"Manufacturing & Wholesale Goods"
        }
    ],
    "sg:phone":"+1 830 825 2112",
    "sg:postcode":"78663",
    "sg:province":"TX",
    "sg:tags":[
        "mfg"
    ],
    "wof:name":"Hill Country Violins",
    "wof:placetype":"venue"
},
  "geometry": {"coordinates":[-98.20815399999999,30.366542],"type":"Point"}
}