{
  "type": "Feature",
  "properties": {
    "iso:country":"US",
    "sg:address":"1901 Agnes St",
    "sg:city":"Corpus Christi",
    "sg:classifiers":[
        {
            "category":"Home & Garden",
            "subcategory":"Furniture",
            "type":"Retail Goods"
        }
    ],
    "sg:phone":"+1 361 884 0912",
    "sg:postcode":"78405",
    "sg:province":"TX",
    "sg:tags":[
        "bed"
    ],
    "wof:name":"Mattress Firm The",
    "wof:placetype":"venue"
},
  "geometry": {"coordinates":[-97.411135,27.78692],"type":"Point"}
}