{
  "type": "Feature",
  "properties": {
    "iso:country":"US",
    "sg:address":"1926 Banks St",
    "sg:city":"Houston",
    "sg:classifiers":[
        {
            "category":"Professional",
            "type":"Services"
        }
    ],
    "sg:phone":"+1 713 522 7532",
    "sg:postcode":"77098",
    "sg:province":"TX",
    "wof:name":"Lctft L L C",
    "wof:placetype":"venue"
},
  "geometry": {"coordinates":[-95.405567,29.72966],"type":"Point"}
}