{
  "type": "Feature",
  "properties": {
    "iso:country":"US",
    "sg:address":"3925 Market St.",
    "sg:city":"Austin",
    "sg:classifiers":[
        {
            "category":"Food & Beverages",
            "subcategory":"Specialty",
            "type":"Retail Goods"
        }
    ],
    "sg:phone":"+1 512 402 0060",
    "sg:postcode":"78738",
    "sg:province":"TX",
    "sg:website":"www.twinliquors.com/",
    "wof:name":"Twin Liquors Marketplace Galleria",
    "wof:placetype":"venue"
},
  "geometry": {"coordinates":[-97.76723800000001,30.340452],"type":"Point"}
}