{
  "type": "Feature",
  "properties": {
    "iso:country":"US",
    "sg:address":"13505 FM 620 N",
    "sg:city":"Austin",
    "sg:classifiers":[
        {
            "category":"Retail",
            "subcategory":"Auto Repair",
            "type":"Services"
        }
    ],
    "sg:phone":"+1 512 335 6900",
    "sg:postcode":"78717",
    "sg:province":"TX",
    "sg:tags":[
        "automobile",
        "lubrication"
    ],
    "wof:name":"Lube Pitstop",
    "wof:placetype":"venue"
},
  "geometry": {"coordinates":[-97.780632,30.473091],"type":"Point"}
}