{
  "type": "Feature",
  "properties": {
    "iso:country":"US",
    "sg:address":"1918 Round Wind Trl",
    "sg:city":"Crosby",
    "sg:classifiers":[
        {
            "category":"Professional",
            "subcategory":"Business Services",
            "type":"Services"
        }
    ],
    "sg:phone":"+1 281 324 6794",
    "sg:postcode":"77532",
    "sg:province":"TX",
    "wof:name":"Live Oak Technologies",
    "wof:placetype":"venue"
},
  "geometry": {"coordinates":[-95.118392,29.977195],"type":"Point"}
}