{
  "type": "Feature",
  "properties": {
    "iso:country":"US",
    "sg:address":"2215 N Carroll Ave",
    "sg:city":"Dallas",
    "sg:classifiers":[
        {
            "category":"Banks & Credit Unions",
            "subcategory":"Bank",
            "type":"Services"
        }
    ],
    "sg:phone":"+1 214 826 6336",
    "sg:postcode":"75204",
    "sg:province":"TX",
    "wof:name":"United Texas Bank",
    "wof:placetype":"venue"
},
  "geometry": {"coordinates":[-96.784284,32.80594],"type":"Point"}
}