{
  "type": "Feature",
  "properties": {
    "iso:country":"US",
    "sg:address":"1510 Creekside Ct",
    "sg:city":"Mansfield",
    "sg:classifiers":[
        {
            "category":"Shopping",
            "subcategory":"Clothing, Apparel, & Fashions",
            "type":"Retail Goods"
        }
    ],
    "sg:phone":"+1 817 473 1494",
    "sg:postcode":"76063",
    "sg:province":"TX",
    "sg:tags":[
        "wear"
    ],
    "wof:name":"My Nap Pak",
    "wof:placetype":"venue"
},
  "geometry": {"coordinates":[-97.095456,32.584645],"type":"Point"}
}