{
  "type": "Feature",
  "properties": {
    "iso:country":"US",
    "sg:address":"215 N Masters Dr",
    "sg:city":"Dallas",
    "sg:classifiers":[
        {
            "category":"Organizations",
            "subcategory":"Religious Organization",
            "type":"Services"
        }
    ],
    "sg:phone":"+1 972 557 8383",
    "sg:postcode":"75217",
    "sg:province":"TX",
    "sg:tags":[
        "church"
    ],
    "sg:website":"www.kingdomharvestcogic.org",
    "wof:name":"Kingdom Harvest Church of God In Christ",
    "wof:placetype":"venue"
},
  "geometry": {"coordinates":[-96.648697,32.713799],"type":"Point"}
}