{
  "type": "Feature",
  "properties": {
    "iso:country":"US",
    "sg:address":"815 Loma St",
    "sg:city":"Alice",
    "sg:classifiers":[
        {
            "category":"Wholesale",
            "subcategory":"Non-durable Goods",
            "type":"Manufacturing & Wholesale Goods"
        }
    ],
    "sg:phone":"+1 361 668 4661",
    "sg:postcode":"78332",
    "sg:province":"TX",
    "wof:name":"Jack of All Trade",
    "wof:placetype":"venue"
},
  "geometry": {"coordinates":[-98.068213,27.744685],"type":"Point"}
}