{
  "type": "Feature",
  "properties": {
    "iso:country":"US",
    "sg:address":"1306 FM 1092",
    "sg:city":"Missouri City",
    "sg:classifiers":[
        {
            "category":"Home & Garden",
            "subcategory":"Building Materials",
            "type":"Retail Goods"
        }
    ],
    "sg:phone":"+1 281 208 8667",
    "sg:postcode":"77459",
    "sg:province":"TX",
    "sg:tags":[
        "mixed",
        "concrete"
    ],
    "wof:name":"Rodriguez Redi Mix",
    "wof:placetype":"venue"
},
  "geometry": {"coordinates":[-95.564381,29.600722],"type":"Point"}
}