{
  "type": "Feature",
  "properties": {
    "iso:country":"US",
    "sg:address":"4250 W 10th Ave",
    "sg:city":"Amarillo",
    "sg:classifiers":[
        {
            "category":"Retail",
            "subcategory":"Repair Shop",
            "type":"Services"
        }
    ],
    "sg:phone":"+1 806 353 4821",
    "sg:postcode":"79106",
    "sg:province":"TX",
    "wof:name":"Budget Drain Service",
    "wof:placetype":"venue"
},
  "geometry": {"coordinates":[-101.887687,35.205008],"type":"Point"}
}