{
  "type": "Feature",
  "properties": {
    "iso:country":"US",
    "sg:address":"4499 Medical Dr",
    "sg:city":"San Antonio",
    "sg:classifiers":[
        {
            "category":"Health Services",
            "subcategory":"Medical Lab",
            "type":"Services"
        }
    ],
    "sg:phone":"+1 210 614 3777",
    "sg:postcode":"78229",
    "sg:province":"TX",
    "sg:tags":[
        "laboratory"
    ],
    "wof:name":"Quest Diagnostics Inc",
    "wof:placetype":"venue"
},
  "geometry": {"coordinates":[-98.571399,29.510522],"type":"Point"}
}