{
  "type": "Feature",
  "properties": {
    "iso:country":"US",
    "sg:address":"18607 Cape Charles Ln",
    "sg:city":"Houston",
    "sg:classifiers":[
        {
            "category":"Recreation",
            "type":"Entertainment"
        }
    ],
    "sg:phone":"+1 281 333 1408",
    "sg:postcode":"77058",
    "sg:province":"TX",
    "wof:name":"Glaze Gallery",
    "wof:placetype":"venue"
},
  "geometry": {"coordinates":[-95.08727399999999,29.541841],"type":"Point"}
}