{
  "type": "Feature",
  "properties": {
    "iso:country":"US",
    "sg:address":"706 Gresham St",
    "sg:city":"Baytown",
    "sg:classifiers":[
        {
            "category":"Building & Trades",
            "subcategory":"Construction",
            "type":"Services"
        }
    ],
    "sg:phone":"+1 713 530 6852",
    "sg:postcode":"77520",
    "sg:province":"TX",
    "sg:tags":[
        "house"
    ],
    "wof:name":"Lasting Impressions",
    "wof:placetype":"venue"
},
  "geometry": {"coordinates":[-94.975031,29.748024],"type":"Point"}
}