{
  "type": "Feature",
  "properties": {
    "iso:country":"US",
    "sg:address":"415 E Main St",
    "sg:city":"Alice",
    "sg:classifiers":[
        {
            "category":"Government",
            "subcategory":"Office",
            "type":"Public Place"
        }
    ],
    "sg:phone":"+1 361 668 7209",
    "sg:postcode":"78332",
    "sg:province":"TX",
    "sg:tags":[
        "city"
    ],
    "wof:name":"City Mayor's Office",
    "wof:placetype":"venue"
},
  "geometry": {"coordinates":[-98.072351,27.750223],"type":"Point"}
}