{
  "type": "Feature",
  "properties": {
    "iso:country":"US",
    "sg:address":"2030 Nogalus Dr",
    "sg:city":"Crosby",
    "sg:classifiers":[
        {
            "category":"Building & Trades",
            "subcategory":"Construction",
            "type":"Services"
        }
    ],
    "sg:phone":"+1 281 324 6826",
    "sg:postcode":"77532",
    "sg:province":"TX",
    "sg:tags":[
        "house"
    ],
    "wof:name":"Amethyst TLC",
    "wof:placetype":"venue"
},
  "geometry": {"coordinates":[-95.121714,29.99314],"type":"Point"}
}