{
  "type": "Feature",
  "properties": {
    "iso:country":"US",
    "sg:address":"3702 Royal Coach Ln",
    "sg:city":"Irving",
    "sg:classifiers":[
        {
            "category":"Professional",
            "subcategory":"Management & Consulting",
            "type":"Services"
        }
    ],
    "sg:phone":"+1 972 790 9545",
    "sg:postcode":"75060",
    "sg:province":"TX",
    "wof:name":"Red Star Marketing",
    "wof:placetype":"venue"
},
  "geometry": {"coordinates":[-97.00054900000001,32.809285],"type":"Point"}
}