{
  "type": "Feature",
  "properties": {
    "iso:country":"US",
    "sg:address":"1925 Moser Ave",
    "sg:city":"Dallas",
    "sg:classifiers":[
        {
            "category":"Real Estate",
            "subcategory":"Real Estate Operator",
            "type":"Services"
        }
    ],
    "sg:phone":"+1 214 823 6800",
    "sg:postcode":"75206",
    "sg:province":"TX",
    "sg:tags":[
        "apartment"
    ],
    "wof:name":"Avalon Apartments",
    "wof:placetype":"venue"
},
  "geometry": {"coordinates":[-96.775597,32.810799],"type":"Point"}
}