{
  "type": "Feature",
  "properties": {
    "iso:country":"US",
    "sg:address":"9108 Bellaire Blvd Ste H",
    "sg:city":"Houston",
    "sg:classifiers":[
        {
            "category":"Personal",
            "subcategory":"Beauty Salon",
            "type":"Services"
        }
    ],
    "sg:phone":"+1 713 779 1678",
    "sg:postcode":"77036",
    "sg:province":"TX",
    "sg:tags":[
        "hair"
    ],
    "wof:name":"Susan Hair Styling",
    "wof:placetype":"venue"
},
  "geometry": {"coordinates":[-95.54435599999999,29.706591],"type":"Point"}
}