{
  "type": "Feature",
  "properties": {
    "iso:country":"US",
    "sg:address":"1309 Sandy Creek Dr",
    "sg:city":"Allen",
    "sg:classifiers":[
        {
            "category":"Restaurant",
            "type":"Food & Drink"
        }
    ],
    "sg:phone":"+1 972 429 8771",
    "sg:postcode":"75002",
    "sg:province":"TX",
    "sg:tags":[
        "eating"
    ],
    "wof:name":"Delassus Eating Adventures",
    "wof:placetype":"venue"
},
  "geometry": {"coordinates":[-96.641059,33.114106],"type":"Point"}
}