{
  "type": "Feature",
  "properties": {
    "iso:country":"US",
    "sg:address":"1060 Witte Rd",
    "sg:city":"Houston",
    "sg:classifiers":[
        {
            "category":"Wholesale",
            "subcategory":"Machinery & Supplies",
            "type":"Manufacturing & Wholesale Goods"
        }
    ],
    "sg:phone":"+1 713 464 7446",
    "sg:postcode":"77055",
    "sg:province":"TX",
    "sg:tags":[
        "industrial"
    ],
    "wof:name":"Riley Corporation Sales Inc",
    "wof:placetype":"venue"
},
  "geometry": {"coordinates":[-95.54001100000001,29.785963],"type":"Point"}
}