{
  "type": "Feature",
  "properties": {
    "iso:country":"US",
    "sg:address":"1775 Saint James Pl",
    "sg:city":"Houston",
    "sg:classifiers":[
        {
            "category":"Shopping",
            "subcategory":"Computers & Home Electronics",
            "type":"Retail Goods"
        }
    ],
    "sg:phone":"+1 713 623 8394",
    "sg:postcode":"77056",
    "sg:province":"TX",
    "sg:tags":[
        "software"
    ],
    "wof:name":"Fyimed",
    "wof:placetype":"venue"
},
  "geometry": {"coordinates":[-95.472735,29.749347],"type":"Point"}
}