{
  "type": "Feature",
  "properties": {
    "iso:country":"US",
    "sg:address":"2620 Carson St",
    "sg:city":"Fort Worth",
    "sg:classifiers":[
        {
            "category":"Building & Trades",
            "subcategory":"Construction",
            "type":"Services"
        }
    ],
    "sg:phone":"+1 817 246 3632",
    "sg:postcode":"76117",
    "sg:province":"TX",
    "sg:tags":[
        "downspouts",
        "gutter"
    ],
    "wof:name":"AAA Gutter Co",
    "wof:placetype":"venue"
},
  "geometry": {"coordinates":[-97.25569900000001,32.799538],"type":"Point"}
}