{
  "type": "Feature",
  "properties": {
    "iso:country":"US",
    "sg:address":"3499 Mission Rd",
    "sg:city":"San Antonio",
    "sg:classifiers":[
        {
            "category":"Freight",
            "type":"Transportation"
        }
    ],
    "sg:phone":"+1 210 922 1600",
    "sg:postcode":"78214",
    "sg:province":"TX",
    "sg:tags":[
        "storage"
    ],
    "wof:name":"Mission Rd Mini Storage",
    "wof:placetype":"venue"
},
  "geometry": {"coordinates":[-98.47431899999999,29.352961],"type":"Point"}
}