{
  "type": "Feature",
  "properties": {
    "iso:country":"US",
    "sg:address":"7966 Dawnridge Dr",
    "sg:city":"Houston",
    "sg:classifiers":[
        {
            "category":"Professional",
            "subcategory":"Accounting & Tax Preparation",
            "type":"Services"
        }
    ],
    "sg:phone":"+1 713 283 7981",
    "sg:postcode":"77071",
    "sg:province":"TX",
    "wof:name":"Ms Moes Services",
    "wof:placetype":"venue"
},
  "geometry": {"coordinates":[-95.517461,29.64804],"type":"Point"}
}