{
  "type": "Feature",
  "properties": {
    "iso:country":"US",
    "sg:address":"11151 Sam Snead Dr",
    "sg:city":"El Paso",
    "sg:classifiers":[
        {
            "category":"Professional",
            "subcategory":"Business Services",
            "type":"Services"
        }
    ],
    "sg:phone":"+1 915 593 7025",
    "sg:postcode":"79936",
    "sg:province":"TX",
    "wof:name":"Computer Net Solution",
    "wof:placetype":"venue"
},
  "geometry": {"coordinates":[-106.308744,31.777151],"type":"Point"}
}