{
  "type": "Feature",
  "properties": {
    "iso:country":"US",
    "sg:address":"1171 Holmes Ct",
    "sg:city":"Austin",
    "sg:classifiers":[
        {
            "category":"Real Estate",
            "subcategory":"Real Estate Agent",
            "type":"Services"
        }
    ],
    "sg:phone":"+1 512 469 9672",
    "sg:postcode":"78702",
    "sg:province":"TX",
    "wof:name":"Alegors Realty",
    "wof:placetype":"venue"
},
  "geometry": {"coordinates":[-97.71098600000001,30.272908],"type":"Point"}
}