{
  "type": "Feature",
  "properties": {
    "iso:country":"US",
    "sg:address":"601 Ogletree Dr Ste A",
    "sg:city":"Livingston",
    "sg:classifiers":[
        {
            "category":"Health Services",
            "subcategory":"Doctor",
            "type":"Services"
        }
    ],
    "sg:phone":"+1 936 328 8080",
    "sg:postcode":"77351",
    "sg:province":"TX",
    "sg:tags":[
        "physician",
        "family",
        "practice",
        "surgeons",
        "medicine"
    ],
    "wof:name":"Timothy Shane Shaw, M.D.,",
    "wof:placetype":"venue"
},
  "geometry": {"coordinates":[-94.936607,30.70491],"type":"Point"}
}