{
  "type": "Feature",
  "properties": {
    "iso:country":"US",
    "sg:address":"5234 Spencer Hwy",
    "sg:city":"Pasadena",
    "sg:classifiers":[
        {
            "category":"Fast Food",
            "type":"Food & Drink"
        }
    ],
    "sg:phone":"+1 281 998 8398",
    "sg:postcode":"77505",
    "sg:province":"TX",
    "sg:tags":[
        "chicken",
        "wing"
    ],
    "sg:website":"www.churchs.com",
    "wof:name":"Church's Chicken",
    "wof:placetype":"venue"
},
  "geometry": {"coordinates":[-95.16216900000001,29.665403],"type":"Point"}
}