{
  "type": "Feature",
  "properties": {
    "iso:country":"US",
    "sg:address":"5319 Forest Timbers Dr",
    "sg:city":"Humble",
    "sg:classifiers":[
        {
            "category":"Retail",
            "subcategory":"Auto Repair",
            "type":"Services"
        }
    ],
    "sg:phone":"+1 281 353 5131",
    "sg:postcode":"77346",
    "sg:province":"TX",
    "sg:tags":[
        "general"
    ],
    "wof:name":"All Tex Garage Doors",
    "wof:placetype":"venue"
},
  "geometry": {"coordinates":[-95.195981,30.003913],"type":"Point"}
}