{
  "type": "Feature",
  "properties": {
    "iso:country":"US",
    "sg:address":"1734 S 20th St",
    "sg:city":"Abilene",
    "sg:classifiers":[
        {
            "category":"Retail",
            "subcategory":"Auto Repair",
            "type":"Services"
        }
    ],
    "sg:phone":"+1 325 672 4400",
    "sg:postcode":"79602",
    "sg:province":"TX",
    "sg:tags":[
        "repairing",
        "automobile"
    ],
    "wof:name":"R L Bailey Automotive",
    "wof:placetype":"venue"
},
  "geometry": {"coordinates":[-99.744542,32.424859],"type":"Point"}
}