{
  "type": "Feature",
  "properties": {
    "iso:country":"US",
    "sg:address":"1001 Ave K",
    "sg:city":"Brownwood",
    "sg:classifiers":[
        {
            "category":"Health Services",
            "subcategory":"Doctor",
            "type":"Services"
        }
    ],
    "sg:phone":"+1 325 643 2551",
    "sg:postcode":"76801",
    "sg:province":"TX",
    "sg:tags":[
        "dentist"
    ],
    "wof:name":"Kennon Mc Lean DDS",
    "wof:placetype":"venue"
},
  "geometry": {"coordinates":[-98.97319299999999,31.704393],"type":"Point"}
}