{
  "type": "Feature",
  "properties": {
    "iso:country":"US",
    "sg:address":"901 Main St Ste C118",
    "sg:city":"Dallas",
    "sg:classifiers":[
        {
            "category":"Shopping",
            "subcategory":"Pharmacy",
            "type":"Retail Goods"
        }
    ],
    "sg:phone":"+1 214 742 1044",
    "sg:postcode":"75202",
    "sg:province":"TX",
    "sg:tags":[
        "drugstore"
    ],
    "sg:website":"www.cvs.com",
    "wof:name":"CVS",
    "wof:placetype":"venue"
},
  "geometry": {"coordinates":[-96.80375600000001,32.780022],"type":"Point"}
}