{
  "type": "Feature",
  "properties": {
    "iso:country":"US",
    "sg:address":"15911 Old Richmond Rd",
    "sg:city":"Sugar Land",
    "sg:classifiers":[
        {
            "category":"Wholesale",
            "subcategory":"Toys & Hobbies",
            "type":"Manufacturing & Wholesale Goods"
        }
    ],
    "sg:phone":"+1 281 495 3227",
    "sg:postcode":"77478",
    "sg:province":"TX",
    "sg:tags":[
        "firework"
    ],
    "wof:name":"Martinez Fireworks Stand",
    "wof:placetype":"venue"
},
  "geometry": {"coordinates":[-95.65647800000001,29.668536],"type":"Point"}
}