{
  "type": "Feature",
  "properties": {
    "iso:country":"US",
    "sg:address":"1230 W Arkansas Ln",
    "sg:city":"Arlington",
    "sg:classifiers":[
        {
            "category":"Retail",
            "subcategory":"Auto Repair",
            "type":"Services"
        }
    ],
    "sg:phone":"+1 817 469 8878",
    "sg:postcode":"76013",
    "sg:province":"TX",
    "sg:tags":[
        "repairing",
        "automobile"
    ],
    "wof:name":"Hon Body Shop",
    "wof:placetype":"venue"
},
  "geometry": {"coordinates":[-97.124593,32.706424],"type":"Point"}
}