{
  "type": "Feature",
  "properties": {
    "iso:country":"US",
    "sg:address":"4937 Broadmoor Dr",
    "sg:city":"Garland",
    "sg:classifiers":[
        {
            "category":"Wholesale",
            "subcategory":"Medical Equipment & Supplies",
            "type":"Manufacturing & Wholesale Goods"
        }
    ],
    "sg:phone":"+1 972 681 5661",
    "sg:postcode":"75043",
    "sg:province":"TX",
    "wof:name":"Texas Medical Supply",
    "wof:placetype":"venue"
},
  "geometry": {"coordinates":[-96.643879,32.858019],"type":"Point"}
}