{
  "type": "Feature",
  "properties": {
    "iso:country":"US",
    "sg:address":"703 Willow Ridge Ct",
    "sg:city":"Coppell",
    "sg:classifiers":[
        {
            "category":"Professional",
            "subcategory":"Management & Consulting",
            "type":"Services"
        }
    ],
    "sg:phone":"+1 972 459 2583",
    "sg:postcode":"75019",
    "sg:province":"TX",
    "sg:tags":[
        "business"
    ],
    "wof:name":"Adventure Marketing",
    "wof:placetype":"venue"
},
  "geometry": {"coordinates":[-96.98316,32.986871],"type":"Point"}
}