{
  "type": "Feature",
  "properties": {
    "iso:country":"US",
    "sg:address":"106 Mountain Laurel Way",
    "sg:city":"Georgetown",
    "sg:classifiers":[
        {
            "category":"Real Estate",
            "subcategory":"Real Estate Agent",
            "type":"Services"
        }
    ],
    "sg:phone":"+1 512 931 0628",
    "sg:postcode":"78602",
    "sg:province":"TX",
    "wof:name":"Autumn Property Management",
    "wof:placetype":"venue"
},
  "geometry": {"coordinates":[-97.26331500000001,30.052689],"type":"Point"}
}