{
  "type": "Feature",
  "properties": {
    "iso:country":"US",
    "sg:address":"302 N Houston Ave",
    "sg:city":"Humble",
    "sg:classifiers":[
        {
            "category":"Insurance",
            "subcategory":"Insurance Agent",
            "type":"Services"
        }
    ],
    "sg:phone":"+1 281 446 8655",
    "sg:postcode":"77338",
    "sg:province":"TX",
    "wof:name":"Insurance Agency-Sw",
    "wof:placetype":"venue"
},
  "geometry": {"coordinates":[-95.257307,29.998109],"type":"Point"}
}