{
  "type": "Feature",
  "properties": {
    "iso:country":"US",
    "sg:address":"6400 Burnet Rd",
    "sg:city":"Austin",
    "sg:classifiers":[
        {
            "category":"Real Estate",
            "subcategory":"Real Estate Agent",
            "type":"Services"
        }
    ],
    "sg:phone":"+1 512 302 3111",
    "sg:postcode":"78757",
    "sg:province":"TX",
    "sg:tags":[
        "management"
    ],
    "wof:name":"Michael Stevens Interests Inc",
    "wof:placetype":"venue"
},
  "geometry": {"coordinates":[-97.739307,30.338512],"type":"Point"}
}