{
  "type": "Feature",
  "properties": {
    "iso:country":"US",
    "sg:address":"3906 Alsace St",
    "sg:city":"Houston",
    "sg:classifiers":[
        {
            "category":"Education",
            "subcategory":"Special Training",
            "type":"Public Place"
        }
    ],
    "sg:phone":"+1 713 741 7180",
    "sg:postcode":"77021",
    "sg:province":"TX",
    "wof:name":"Freddie As Esl & Mus Tutoring",
    "wof:placetype":"venue"
},
  "geometry": {"coordinates":[-95.357792,29.697349],"type":"Point"}
}