{
  "type": "Feature",
  "properties": {
    "iso:country":"US",
    "sg:address":"2400 N Guadalupe St",
    "sg:city":"Seguin",
    "sg:classifiers":[
        {
            "category":"Professional",
            "type":"Services"
        }
    ],
    "sg:phone":"+1 830 379 7825",
    "sg:postcode":"78155",
    "sg:province":"TX",
    "sg:tags":[
        "establishment"
    ],
    "wof:name":"BVZ-Power Partners-Seguin",
    "wof:placetype":"venue"
},
  "geometry": {"coordinates":[-97.96982300000001,29.59331],"type":"Point"}
}