{
  "type": "Feature",
  "properties": {
    "iso:country":"US",
    "sg:address":"144 Fairway Dr",
    "sg:city":"Kerrville",
    "sg:classifiers":[
        {
            "category":"Health Services",
            "subcategory":"Clinic",
            "type":"Services"
        }
    ],
    "sg:phone":"+1 830 895 4585",
    "sg:postcode":"78028",
    "sg:province":"TX",
    "wof:name":"Juahan Skin Clinic",
    "wof:placetype":"venue"
},
  "geometry": {"coordinates":[-99.142387,30.023709],"type":"Point"}
}