{
  "type": "Feature",
  "properties": {
    "iso:country":"US",
    "sg:address":"7905 Burgess Rd",
    "sg:city":"Hitchcock",
    "sg:classifiers":[
        {
            "category":"Recreation",
            "type":"Entertainment"
        }
    ],
    "sg:phone":"+1 409 986 6830",
    "sg:postcode":"77563",
    "sg:province":"TX",
    "sg:tags":[
        "amusement"
    ],
    "wof:name":"D & D Moonwalk Rentals",
    "wof:placetype":"venue"
},
  "geometry": {"coordinates":[-95.016582,29.350789],"type":"Point"}
}