{
  "type": "Feature",
  "properties": {
    "iso:country":"US",
    "sg:address":"11550 Chimney Rock Rd",
    "sg:city":"Houston",
    "sg:classifiers":[
        {
            "category":"Retail",
            "subcategory":"Repair Shop",
            "type":"Services"
        }
    ],
    "sg:phone":"+1 713 721 2099",
    "sg:postcode":"77035",
    "sg:province":"TX",
    "wof:name":"Bills Picture Framing",
    "wof:placetype":"venue"
},
  "geometry": {"coordinates":[-95.47774099999999,29.656252],"type":"Point"}
}