{
  "type": "Feature",
  "properties": {
    "iso:country":"US",
    "sg:address":"1204 W River Oaks Dr",
    "sg:city":"Longview",
    "sg:classifiers":[
        {
            "category":"Building & Trades",
            "subcategory":"Pest Control",
            "type":"Services"
        }
    ],
    "sg:phone":"+1 903 553 1585",
    "sg:postcode":"75604",
    "sg:province":"TX",
    "sg:tags":[
        "mothproofing"
    ],
    "wof:name":"Economy",
    "wof:placetype":"venue"
},
  "geometry": {"coordinates":[-94.765404,32.49585],"type":"Point"}
}