{
  "type": "Feature",
  "properties": {
    "iso:country":"US",
    "sg:address":"1618 Seagate Ln",
    "sg:city":"Houston",
    "sg:classifiers":[
        {
            "category":"Professional",
            "subcategory":"Art Services",
            "type":"Services"
        }
    ],
    "sg:phone":"+1 281 488 4134",
    "sg:postcode":"77062",
    "sg:province":"TX",
    "sg:tags":[
        "commercial",
        "design"
    ],
    "wof:name":"Lisa Deming",
    "wof:placetype":"venue"
},
  "geometry": {"coordinates":[-95.11929000000001,29.570975],"type":"Point"}
}