{
  "type": "Feature",
  "properties": {
    "iso:country":"US",
    "sg:address":"1418 Pleasanton Rd",
    "sg:city":"San Antonio",
    "sg:classifiers":[
        {
            "category":"Restaurant",
            "type":"Food & Drink"
        }
    ],
    "sg:menulink":"http://www.allmenus.com/tx/san-antonio/217136-bill-miller-bbq/menu/",
    "sg:phone":"+1 210 924 6491",
    "sg:postcode":"78221",
    "sg:province":"TX",
    "sg:tags":[
        "barbecue",
        "american"
    ],
    "wof:name":"Bill Miller BBQ",
    "wof:placetype":"venue"
},
  "geometry": {"coordinates":[-98.50373399999999,29.368753],"type":"Point"}
}