{
  "type": "Feature",
  "properties": {
    "iso:country":"US",
    "sg:address":"828 Elmwood Ave",
    "sg:city":"Fort Worth",
    "sg:classifiers":[
        {
            "category":"Farming",
            "subcategory":"Livestock Farm",
            "type":"Manufacturing & Wholesale Goods"
        }
    ],
    "sg:phone":"+1 817 207 9147",
    "sg:postcode":"76104",
    "sg:province":"TX",
    "sg:tags":[
        "animal",
        "general"
    ],
    "wof:name":"Hadleys Sunshine Ranch",
    "wof:placetype":"venue"
},
  "geometry": {"coordinates":[-97.319525,32.725178],"type":"Point"}
}