{
  "type": "Feature",
  "properties": {
    "iso:country":"US",
    "sg:address":"22911 Hausworth Ct",
    "sg:city":"Spring",
    "sg:classifiers":[
        {
            "category":"Freight",
            "type":"Transportation"
        }
    ],
    "sg:phone":"+1 281 353 6150",
    "sg:postcode":"77373",
    "sg:province":"TX",
    "wof:name":"Heritage Transportation Svcs",
    "wof:placetype":"venue"
},
  "geometry": {"coordinates":[-95.424464,30.095126],"type":"Point"}
}