{
  "type": "Feature",
  "properties": {
    "iso:country":"US",
    "sg:address":"2970 Dowlen Rd",
    "sg:city":"Beaumont",
    "sg:classifiers":[
        {
            "category":"Restaurant",
            "type":"Food & Drink"
        }
    ],
    "sg:menulink":"http://www.allmenus.com/tx/beaumont/203735-sonic/menu/",
    "sg:phone":"+1 409 860 3930",
    "sg:postcode":"77706",
    "sg:province":"TX",
    "sg:tags":[
        "burger",
        "american"
    ],
    "wof:name":"Sonic",
    "wof:placetype":"venue"
},
  "geometry": {"coordinates":[-94.168367,30.105491],"type":"Point"}
}