{
  "type": "Feature",
  "properties": {
    "iso:country":"US",
    "sg:address":"928 E Tidwell Rd",
    "sg:city":"Houston",
    "sg:classifiers":[
        {
            "category":"Food & Beverages",
            "subcategory":"Groceries & Convenience Stores",
            "type":"Retail Goods"
        }
    ],
    "sg:phone":"+1 713 691 4699",
    "sg:postcode":"77022",
    "sg:province":"TX",
    "wof:name":"Quick Stop",
    "wof:placetype":"venue"
},
  "geometry": {"coordinates":[-95.385288,29.845335],"type":"Point"}
}