{
  "type": "Feature",
  "properties": {
    "iso:country":"US",
    "sg:address":"718 Huff St",
    "sg:city":"Taylor",
    "sg:classifiers":[
        {
            "category":"Professional",
            "type":"Services"
        }
    ],
    "sg:phone":"+1 512 365 8411",
    "sg:postcode":"76574",
    "sg:province":"TX",
    "sg:tags":[
        "establishment"
    ],
    "wof:name":"Brushycreek Wcid",
    "wof:placetype":"venue"
},
  "geometry": {"coordinates":[-97.41883799999999,30.579329],"type":"Point"}
}