{
  "type": "Feature",
  "properties": {
    "iso:country":"US",
    "sg:address":"4709 N Main St",
    "sg:city":"Liberty",
    "sg:classifiers":[
        {
            "category":"Place Of Worship",
            "subcategory":"Church",
            "type":"Public Place"
        },
        {
            "category":"Place Of Worship",
            "type":"Public Place"
        }
    ],
    "sg:phone":"+1 936 336 6362",
    "sg:postcode":"77575",
    "sg:province":"TX",
    "sg:tags":[
        "churches-baptist-general",
        "churches-baptist"
    ],
    "wof:name":"North Main Baptist Church Inc",
    "wof:placetype":"venue"
},
  "geometry": {"coordinates":[-94.74852300000001,30.101159],"type":"Point"}
}