{
  "type": "Feature",
  "properties": {
    "iso:country":"US",
    "sg:address":"3605 Cadena Dr",
    "sg:city":"Pasadena",
    "sg:classifiers":[
        {
            "category":"Home & Garden",
            "subcategory":"Building Materials",
            "type":"Retail Goods"
        }
    ],
    "sg:phone":"+1 713 987 9557",
    "sg:postcode":"77504",
    "sg:province":"TX",
    "sg:tags":[
        "soil",
        "sand",
        "gravel"
    ],
    "wof:name":"Dallas Enterprises",
    "wof:placetype":"venue"
},
  "geometry": {"coordinates":[-95.189819,29.657892],"type":"Point"}
}