{
  "type": "Feature",
  "properties": {
    "iso:country":"US",
    "sg:address":"10026 Sagegate Dr",
    "sg:city":"Houston",
    "sg:classifiers":[
        {
            "category":"Professional",
            "type":"Services"
        }
    ],
    "sg:phone":"+1 281 481 8710",
    "sg:postcode":"77089",
    "sg:province":"TX",
    "wof:name":"Heritage Millwork Co",
    "wof:placetype":"venue"
},
  "geometry": {"coordinates":[-95.228908,29.576904],"type":"Point"}
}