{
  "type": "Feature",
  "properties": {
    "iso:country":"US",
    "sg:address":"3006 Lotus Ln",
    "sg:city":"Pearland",
    "sg:classifiers":[
        {
            "category":"Utilities",
            "subcategory":"Mobile Phone",
            "type":"Services"
        }
    ],
    "sg:phone":"+1 281 412 3421",
    "sg:postcode":"77584",
    "sg:province":"TX",
    "sg:tags":[
        "communication",
        "radiotelephone"
    ],
    "wof:name":"Coptel",
    "wof:placetype":"venue"
},
  "geometry": {"coordinates":[-95.356095,29.542885],"type":"Point"}
}