{
  "type": "Feature",
  "properties": {
    "iso:country":"US",
    "sg:address":"3024 Hebron Pkwy E",
    "sg:city":"Carrollton",
    "sg:classifiers":[
        {
            "category":"Real Estate",
            "subcategory":"Real Estate Services",
            "type":"Services"
        }
    ],
    "sg:phone":"+1 972 418 8400",
    "sg:postcode":"75010",
    "sg:province":"TX",
    "sg:tags":[
        "company",
        "title"
    ],
    "wof:name":"Republic Title Of Texas Inc",
    "wof:placetype":"venue"
},
  "geometry": {"coordinates":[-96.86214,33.0242],"type":"Point"}
}