{
  "type": "Feature",
  "properties": {
    "iso:country":"US",
    "sg:address":"318 Wildbriar Dr",
    "sg:city":"Garland",
    "sg:classifiers":[
        {
            "category":"Banks & Credit Unions",
            "subcategory":"Financial Services",
            "type":"Services"
        }
    ],
    "sg:phone":"+1 972 270 1086",
    "sg:postcode":"75043",
    "sg:province":"TX",
    "sg:tags":[
        "patent"
    ],
    "wof:name":"Conaway Sales & Le",
    "wof:placetype":"venue"
},
  "geometry": {"coordinates":[-96.630684,32.862238],"type":"Point"}
}