{
  "type": "Feature",
  "properties": {
    "iso:country":"US",
    "sg:address":"8145 Howard Dr",
    "sg:city":"Houston",
    "sg:classifiers":[
        {
            "category":"Retail",
            "subcategory":"Repair Shop",
            "type":"Services"
        }
    ],
    "sg:phone":"+1 713 946 2468",
    "sg:postcode":"77017",
    "sg:province":"TX",
    "wof:name":"Central Lock & Safe Co",
    "wof:placetype":"venue"
},
  "geometry": {"coordinates":[-95.26273,29.679484],"type":"Point"}
}