{
  "type": "Feature",
  "properties": {
    "iso:country":"US",
    "sg:address":"4128 Fairlakes Ct",
    "sg:city":"Dallas",
    "sg:classifiers":[
        {
            "category":"Professional",
            "subcategory":"Art Services",
            "type":"Services"
        }
    ],
    "sg:phone":"+1 214 321 2416",
    "sg:postcode":"75228",
    "sg:province":"TX",
    "sg:tags":[
        "graphic",
        "designer"
    ],
    "wof:name":"Digital Innovations",
    "wof:placetype":"venue"
},
  "geometry": {"coordinates":[-96.63825799999999,32.841528],"type":"Point"}
}