{
  "type": "Feature",
  "properties": {
    "iso:country":"US",
    "sg:address":"1019 Brooksy St",
    "sg:city":"Gilmer",
    "sg:classifiers":[
        {
            "category":"Professional",
            "subcategory":"Business Services",
            "type":"Services"
        }
    ],
    "sg:phone":"+1 903 843 2469",
    "sg:postcode":"75644",
    "sg:province":"TX",
    "wof:name":"National Assoc of Letter",
    "wof:placetype":"venue"
},
  "geometry": {"coordinates":[-94.956536,32.738971],"type":"Point"}
}