{
  "type": "Feature",
  "properties": {
    "iso:country":"US",
    "sg:address":"508 N Elm St",
    "sg:city":"Palestine",
    "sg:classifiers":[
        {
            "category":"Autos & Motor Vehicles",
            "subcategory":"Auto Supplies",
            "type":"Retail Goods"
        }
    ],
    "sg:phone":"+1 903 729 0121",
    "sg:postcode":"75801",
    "sg:province":"TX",
    "sg:tags":[
        "repair",
        "tire",
        "general"
    ],
    "wof:name":"Bratz Uniroyal Tire Co",
    "wof:placetype":"venue"
},
  "geometry": {"coordinates":[-95.628259,31.765347],"type":"Point"}
}