{
  "type": "Feature",
  "properties": {
    "iso:country":"US",
    "sg:address":"289 Fish Rd",
    "sg:city":"Jasper",
    "sg:classifiers":[
        {
            "category":"Recreation",
            "type":"Entertainment"
        }
    ],
    "sg:phone":"+1 409 384 2221",
    "sg:postcode":"75901",
    "sg:province":"TX",
    "sg:tags":[
        "parks"
    ],
    "wof:name":"Parks & Wildlife Dept",
    "wof:placetype":"venue"
},
  "geometry": {"coordinates":[-94.655643,31.305384],"type":"Point"}
}