{
  "type": "Feature",
  "properties": {
    "iso:country":"US",
    "sg:address":"716 E I- 30",
    "sg:city":"Garland",
    "sg:classifiers":[
        {
            "category":"Manufacturing",
            "subcategory":"Metals",
            "type":"Manufacturing & Wholesale Goods"
        }
    ],
    "sg:phone":"+1 972 226 1981",
    "sg:postcode":"75043",
    "sg:province":"TX",
    "sg:tags":[
        "fence"
    ],
    "sg:website":"www.sunnyvale.com",
    "wof:name":"Sunnyvale Fence & Ironworks",
    "wof:placetype":"venue"
},
  "geometry": {"coordinates":[-96.564736,32.852648],"type":"Point"}
}