{
  "type": "Feature",
  "properties": {
    "iso:country":"US",
    "sg:address":"712 Bermuda St",
    "sg:city":"Lakeway",
    "sg:classifiers":[
        {
            "category":"Building & Trades",
            "subcategory":"Construction",
            "type":"Services"
        }
    ],
    "sg:phone":"+1 512 451 4500",
    "sg:postcode":"78734",
    "sg:province":"TX",
    "sg:tags":[
        "contractor"
    ],
    "wof:name":"KDL Construction",
    "wof:placetype":"venue"
},
  "geometry": {"coordinates":[-97.98730500000001,30.37023],"type":"Point"}
}