{
  "type": "Feature",
  "properties": {
    "iso:country":"US",
    "sg:address":"4131 N Story Rd",
    "sg:city":"Irving",
    "sg:classifiers":[
        {
            "category":"Organizations",
            "subcategory":"Membership Organization",
            "type":"Services"
        }
    ],
    "sg:phone":"+1 972 257 0002",
    "sg:postcode":"75038",
    "sg:province":"TX",
    "wof:name":"Buena Vista Animal Clinic",
    "wof:placetype":"venue"
},
  "geometry": {"coordinates":[-96.977366,32.864131],"type":"Point"}
}