{
  "type": "Feature",
  "properties": {
    "iso:country":"US",
    "sg:address":"7707 N Macarthur Blvd",
    "sg:city":"Irving",
    "sg:classifiers":[
        {
            "category":"Restaurant",
            "type":"Food & Drink"
        }
    ],
    "sg:menulink":"http://www.allmenus.com/tx/southwest/136872-smoothie-king/menu/",
    "sg:phone":"+1 972 556 2900",
    "sg:postcode":"75063",
    "sg:province":"TX",
    "sg:tags":[
        "smoothy",
        "juice",
        "american"
    ],
    "wof:name":"Smoothie King",
    "wof:placetype":"venue"
},
  "geometry": {"coordinates":[-96.959431,32.911834],"type":"Point"}
}