{
  "type": "Feature",
  "properties": {
    "iso:country":"US",
    "sg:address":"5848 W Airport Blvd",
    "sg:city":"Houston",
    "sg:classifiers":[
        {
            "category":"Food & Beverages",
            "subcategory":"Bakery",
            "type":"Retail Goods"
        }
    ],
    "sg:phone":"+1 713 729 2381",
    "sg:postcode":"77035",
    "sg:province":"TX",
    "sg:tags":[
        "product",
        "mfg"
    ],
    "wof:name":"Shipley Donut Shops",
    "wof:placetype":"venue"
},
  "geometry": {"coordinates":[-95.49169500000001,29.64457],"type":"Point"}
}