{
  "type": "Feature",
  "properties": {
    "iso:country":"US",
    "sg:address":"11510 Galbreath Dr",
    "sg:city":"Houston",
    "sg:classifiers":[
        {
            "category":"Building & Trades",
            "subcategory":"Construction",
            "type":"Services"
        }
    ],
    "sg:phone":"+1 281 893 3812",
    "sg:postcode":"77066",
    "sg:province":"TX",
    "sg:tags":[
        "house"
    ],
    "wof:name":"Snommah Construction & RE",
    "wof:placetype":"venue"
},
  "geometry": {"coordinates":[-95.508546,29.954109],"type":"Point"}
}