{
  "type": "Feature",
  "properties": {
    "iso:country":"US",
    "sg:address":"3740 W Northwest Hwy",
    "sg:city":"Dallas",
    "sg:classifiers":[
        {
            "category":"Professional",
            "subcategory":"Accounting & Tax Preparation",
            "type":"Services"
        }
    ],
    "sg:phone":"+1 214 351 1384",
    "sg:postcode":"75220",
    "sg:province":"TX",
    "sg:tags":[
        "return"
    ],
    "wof:name":"Martinez Multi-Service",
    "wof:placetype":"venue"
},
  "geometry": {"coordinates":[-96.856824,32.8604],"type":"Point"}
}