{
  "type": "Feature",
  "properties": {
    "iso:country":"US",
    "sg:address":"601 Shaver St",
    "sg:city":"Pasadena",
    "sg:classifiers":[
        {
            "category":"Building & Trades",
            "subcategory":"Plumbing",
            "type":"Services"
        }
    ],
    "sg:phone":"+1 713 472 0721",
    "sg:postcode":"77506",
    "sg:province":"TX",
    "sg:tags":[
        "heating",
        "contractor"
    ],
    "wof:name":"Bolton Air Conditioning Svc",
    "wof:placetype":"venue"
},
  "geometry": {"coordinates":[-95.21153700000001,29.701698],"type":"Point"}
}