{
  "type": "Feature",
  "properties": {
    "iso:country":"US",
    "sg:address":"1017 Birchwood Ln",
    "sg:city":"Mansfield",
    "sg:classifiers":[
        {
            "category":"Building & Trades",
            "subcategory":"Plumbing",
            "type":"Services"
        }
    ],
    "sg:phone":"+1 972 877 3311",
    "sg:postcode":"76063",
    "sg:province":"TX",
    "sg:tags":[
        "plumbing",
        "contractor"
    ],
    "wof:name":"Orlando Escobar",
    "wof:placetype":"venue"
},
  "geometry": {"coordinates":[-97.12684900000001,32.588313],"type":"Point"}
}