{
  "type": "Feature",
  "properties": {
    "iso:country":"US",
    "sg:address":"24122 Spring Gum Dr",
    "sg:city":"Spring",
    "sg:classifiers":[
        {
            "category":"Shopping",
            "subcategory":"Hobbies, Toys, & Games",
            "type":"Retail Goods"
        }
    ],
    "sg:phone":"+1 281 355 7670",
    "sg:postcode":"77373",
    "sg:province":"TX",
    "sg:tags":[
        "craft"
    ],
    "wof:name":"Darleen F Hunold Crafts",
    "wof:placetype":"venue"
},
  "geometry": {"coordinates":[-95.38846599999999,30.062854],"type":"Point"}
}