{
  "type": "Feature",
  "properties": {
    "iso:country":"US",
    "sg:address":"11936 Bellaire Blvd",
    "sg:city":"Houston",
    "sg:classifiers":[
        {
            "category":"Restaurant",
            "type":"Food & Drink"
        }
    ],
    "sg:menulink":"http://www.allmenus.com/tx/houston/62613-subway/menu/",
    "sg:phone":"+1 281 933 2343",
    "sg:postcode":"77072",
    "sg:province":"TX",
    "sg:tags":[
        "american",
        "sandwich"
    ],
    "wof:name":"Subway",
    "wof:placetype":"venue"
},
  "geometry": {"coordinates":[-95.58869,29.703782],"type":"Point"}
}