{
  "type": "Feature",
  "properties": {
    "iso:country":"US",
    "sg:address":"2481 Peel Rd",
    "sg:city":"Springtown",
    "sg:classifiers":[
        {
            "category":"Wholesale",
            "subcategory":"Farm Supplies",
            "type":"Manufacturing & Wholesale Goods"
        }
    ],
    "sg:phone":"+1 817 220 8126",
    "sg:postcode":"76082",
    "sg:province":"TX",
    "sg:tags":[
        "livestock"
    ],
    "wof:name":"Hasty Ranch",
    "wof:placetype":"venue"
},
  "geometry": {"coordinates":[-97.71929799999999,32.996852],"type":"Point"}
}