{
  "type": "Feature",
  "properties": {
    "iso:country":"US",
    "sg:address":"2432 Chew St",
    "sg:city":"Houston",
    "sg:classifiers":[
        {
            "category":"Social Services",
            "type":"Services"
        }
    ],
    "sg:phone":"+1 713 672 1563",
    "sg:postcode":"77020",
    "sg:province":"TX",
    "sg:tags":[
        "organization",
        "welfare"
    ],
    "wof:name":"Macedonia Outreach Ctr",
    "wof:placetype":"venue"
},
  "geometry": {"coordinates":[-95.315009,29.783996],"type":"Point"}
}