{
  "type": "Feature",
  "properties": {
    "iso:country":"US",
    "sg:address":"806 34th St",
    "sg:city":"Lubbock",
    "sg:classifiers":[
        {
            "category":"Food & Beverages",
            "subcategory":"Groceries & Convenience Stores",
            "type":"Retail Goods"
        }
    ],
    "sg:phone":"+1 806 767 9135",
    "sg:postcode":"79404",
    "sg:province":"TX",
    "wof:name":"Town & Country Food Store 202",
    "wof:placetype":"venue"
},
  "geometry": {"coordinates":[-101.844317,33.563358],"type":"Point"}
}