{
  "type": "Feature",
  "properties": {
    "iso:country":"US",
    "sg:address":"6987 San Pedro Ave",
    "sg:city":"San Antonio",
    "sg:classifiers":[
        {
            "category":"Retail",
            "subcategory":"Auto Repair",
            "type":"Services"
        }
    ],
    "sg:phone":"+1 210 340 1441",
    "sg:postcode":"78216",
    "sg:province":"TX",
    "sg:tags":[
        "repairing",
        "automobile"
    ],
    "wof:name":"All Tune & Lube",
    "wof:placetype":"venue"
},
  "geometry": {"coordinates":[-98.499341,29.505404],"type":"Point"}
}