{
  "type": "Feature",
  "properties": {
    "iso:country":"US",
    "sg:address":"211 State Hwy 110",
    "sg:city":"Grand Saline",
    "sg:classifiers":[
        {
            "category":"Autos & Motor Vehicles",
            "subcategory":"Automobile Sales",
            "type":"Retail Goods"
        }
    ],
    "sg:phone":"+1 903 962 4858",
    "sg:postcode":"75140",
    "sg:province":"TX",
    "sg:tags":[
        "used"
    ],
    "wof:name":"R & S New & Used",
    "wof:placetype":"venue"
},
  "geometry": {"coordinates":[-95.709667,32.674451],"type":"Point"}
}