{
  "type": "Feature",
  "properties": {
    "iso:country":"US",
    "sg:address":"6292 Trowbridge Dr",
    "sg:city":"El Paso",
    "sg:classifiers":[
        {
            "category":"Government",
            "subcategory":"Office",
            "type":"Public Place"
        }
    ],
    "sg:phone":"+1 915 778 2072",
    "sg:postcode":"79905",
    "sg:province":"TX",
    "sg:tags":[
        "city",
        "program",
        "health"
    ],
    "wof:name":"San Juan Health Ctr",
    "wof:placetype":"venue"
},
  "geometry": {"coordinates":[-106.409462,31.775025],"type":"Point"}
}