{
  "type": "Feature",
  "properties": {
    "iso:country":"US",
    "sg:address":"1904 N Washington Ave",
    "sg:city":"Livingston",
    "sg:classifiers":[
        {
            "category":"Freight",
            "type":"Transportation"
        }
    ],
    "sg:phone":"+1 936 327 3052",
    "sg:postcode":"77351",
    "sg:province":"TX",
    "sg:tags":[
        "commercial",
        "storage"
    ],
    "wof:name":"J & H Storage",
    "wof:placetype":"venue"
},
  "geometry": {"coordinates":[-94.932306,30.726059],"type":"Point"}
}