{
  "type": "Feature",
  "properties": {
    "iso:country":"US",
    "sg:address":"7332 Scout Dr",
    "sg:city":"Plano",
    "sg:classifiers":[
        {
            "category":"Professional",
            "subcategory":"Business Services",
            "type":"Services"
        }
    ],
    "sg:phone":"+1 972 491 0252",
    "sg:postcode":"75025",
    "sg:province":"TX",
    "wof:name":"Rodolfo R Palacios Group",
    "wof:placetype":"venue"
},
  "geometry": {"coordinates":[-96.74261300000001,33.07759],"type":"Point"}
}