{
  "type": "Feature",
  "properties": {
    "iso:country":"US",
    "sg:address":"2111 Kramer Ln",
    "sg:city":"Austin",
    "sg:classifiers":[
        {
            "category":"Manufacturing",
            "subcategory":"Electronics",
            "type":"Manufacturing & Wholesale Goods"
        }
    ],
    "sg:phone":"+1 512 719 9088",
    "sg:postcode":"78758",
    "sg:province":"TX",
    "sg:tags":[
        "contract"
    ],
    "wof:name":"Svtronics Manufacturing Inc",
    "wof:placetype":"venue"
},
  "geometry": {"coordinates":[-97.71303899999999,30.389896],"type":"Point"}
}