{
  "type": "Feature",
  "properties": {
    "iso:country":"US",
    "sg:address":"1604 N Main St",
    "sg:city":"Paris",
    "sg:classifiers":[
        {
            "category":"Food & Beverages",
            "subcategory":"Groceries & Convenience Stores",
            "type":"Retail Goods"
        }
    ],
    "sg:phone":"+1 903 737 8600",
    "sg:postcode":"75460",
    "sg:province":"TX",
    "wof:name":"Wagabag",
    "wof:placetype":"venue"
},
  "geometry": {"coordinates":[-95.55559100000001,33.677513],"type":"Point"}
}