{
  "type": "Feature",
  "properties": {
    "iso:country":"US",
    "sg:address":"9304 N Lamar Blvd",
    "sg:city":"Austin",
    "sg:classifiers":[
        {
            "category":"Arts & Performance",
            "subcategory":"Music",
            "type":"Entertainment"
        }
    ],
    "sg:phone":"+1 512 339 9795",
    "sg:postcode":"78753",
    "sg:province":"TX",
    "sg:tags":[
        "musician"
    ],
    "wof:name":"Latino Discoteca",
    "wof:placetype":"venue"
},
  "geometry": {"coordinates":[-97.69761699999999,30.362035],"type":"Point"}
}