{
  "type": "Feature",
  "properties": {
    "iso:country":"US",
    "sg:address":"3925 Caruth Blvd",
    "sg:city":"Dallas",
    "sg:classifiers":[
        {
            "category":"Professional",
            "type":"Services"
        }
    ],
    "sg:phone":"+1 214 692 6486",
    "sg:postcode":"75225",
    "sg:province":"TX",
    "wof:name":"Multi View Inc",
    "wof:placetype":"venue"
},
  "geometry": {"coordinates":[-96.80135900000001,32.858896],"type":"Point"}
}