{
  "type": "Feature",
  "properties": {
    "iso:country":"US",
    "sg:address":"707 N Zang Blvd",
    "sg:city":"Dallas",
    "sg:classifiers":[
        {
            "category":"Wholesale",
            "subcategory":"Medical Equipment & Supplies",
            "type":"Manufacturing & Wholesale Goods"
        }
    ],
    "sg:phone":"+1 214 943 3600",
    "sg:postcode":"75208",
    "sg:province":"TX",
    "sg:tags":[
        "physician",
        "surgeon"
    ],
    "wof:name":"Gatesco Medical Supplies",
    "wof:placetype":"venue"
},
  "geometry": {"coordinates":[-96.824217,32.752141],"type":"Point"}
}