{
  "type": "Feature",
  "properties": {
    "iso:country":"US",
    "sg:address":"1200 E Mansfield Hwy",
    "sg:city":"Kennedale",
    "sg:classifiers":[
        {
            "category":"Building & Trades",
            "subcategory":"Construction",
            "type":"Services"
        }
    ],
    "sg:phone":"+1 817 563 6881",
    "sg:postcode":"76060",
    "sg:province":"TX",
    "sg:tags":[
        "painter"
    ],
    "wof:name":"Marcos Painting",
    "wof:placetype":"venue"
},
  "geometry": {"coordinates":[-97.207414,32.633226],"type":"Point"}
}