{
  "type": "Feature",
  "properties": {
    "iso:country":"US",
    "sg:address":"4400 Buffalo Gap Rd",
    "sg:city":"Abilene",
    "sg:classifiers":[
        {
            "category":"Health Services",
            "subcategory":"Doctor",
            "type":"Services"
        }
    ],
    "sg:phone":"+1 325 793 5375",
    "sg:postcode":"79606",
    "sg:province":"TX",
    "sg:tags":[
        "clinic"
    ],
    "wof:name":"Abilene Diagnostic Clinic",
    "wof:placetype":"venue"
},
  "geometry": {"coordinates":[-99.760077,32.398146],"type":"Point"}
}