{
  "type": "Feature",
  "properties": {
    "iso:country":"US",
    "sg:address":"111 W Ovilla Rd",
    "sg:city":"Red Oak",
    "sg:classifiers":[
        {
            "category":"Shopping",
            "subcategory":"Musical Instruments",
            "type":"Retail Goods"
        }
    ],
    "sg:phone":"+1 972 223 0133",
    "sg:postcode":"75154",
    "sg:province":"TX",
    "wof:name":"Guitar Focus",
    "wof:placetype":"venue"
},
  "geometry": {"coordinates":[-96.856139,32.531949],"type":"Point"}
}