{
  "type": "Feature",
  "properties": {
    "iso:country":"US",
    "sg:address":"13144 Malinowski Ln",
    "sg:city":"Chappell Hill",
    "sg:classifiers":[
        {
            "category":"Autos & Motor Vehicles",
            "subcategory":"Recreational Vehicle Sales",
            "type":"Retail Goods"
        }
    ],
    "sg:phone":"+1 979 836 3438",
    "sg:postcode":"77426",
    "sg:province":"TX",
    "wof:name":"Dim-It Sunscreen",
    "wof:placetype":"venue"
},
  "geometry": {"coordinates":[-96.191542,30.124589],"type":"Point"}
}