{
  "type": "Feature",
  "properties": {
    "iso:country":"US",
    "sg:address":"1201 West Loop N Ste 170",
    "sg:city":"Houston",
    "sg:classifiers":[
        {
            "category":"Professional",
            "subcategory":"Business Services",
            "type":"Services"
        }
    ],
    "sg:phone":"+1 713 686 5252",
    "sg:postcode":"77055",
    "sg:province":"TX",
    "sg:tags":[
        "delivery",
        "courier"
    ],
    "sg:website":"www.datarush.com",
    "wof:name":"Data Rush Couriers",
    "wof:placetype":"venue"
},
  "geometry": {"coordinates":[-95.453577,29.78877],"type":"Point"}
}