{
  "type": "Feature",
  "properties": {
    "iso:country":"US",
    "sg:address":"1614 W Cameron Ave",
    "sg:city":"Rockdale",
    "sg:classifiers":[
        {
            "category":"Shopping",
            "subcategory":"Gifts & Souvenirs",
            "type":"Retail Goods"
        }
    ],
    "sg:phone":"+1 512 446 0649",
    "sg:postcode":"76567",
    "sg:province":"TX",
    "wof:name":"Tisket A Tasket",
    "wof:placetype":"venue"
},
  "geometry": {"coordinates":[-97.02090200000001,30.646691],"type":"Point"}
}