{
  "type": "Feature",
  "properties": {
    "iso:country":"US",
    "sg:address":"206 Main St",
    "sg:city":"Bandera",
    "sg:classifiers":[
        {
            "category":"Shopping",
            "subcategory":"Stationery & Office Supplies",
            "type":"Retail Goods"
        },
        {
            "category":"Shopping",
            "subcategory":"Gifts & Souvenirs",
            "type":"Retail Goods"
        }
    ],
    "sg:phone":"+1 830 796 7386",
    "sg:postcode":"78003",
    "sg:province":"TX",
    "sg:tags":[
        "shop",
        "store"
    ],
    "wof:name":"Old West Imports",
    "wof:placetype":"venue"
},
  "geometry": {"coordinates":[-99.06988699999999,29.723647],"type":"Point"}
}