{
  "type": "Feature",
  "properties": {
    "iso:country":"US",
    "sg:address":"2405 Terrace Ave",
    "sg:city":"Victoria",
    "sg:classifiers":[
        {
            "category":"Wholesale",
            "subcategory":"Farm Supplies",
            "type":"Manufacturing & Wholesale Goods"
        }
    ],
    "sg:phone":"+1 361 575 1288",
    "sg:postcode":"77901",
    "sg:province":"TX",
    "sg:tags":[
        "livestock"
    ],
    "wof:name":"Buffaloe Cattle Co",
    "wof:placetype":"venue"
},
  "geometry": {"coordinates":[-96.982529,28.820473],"type":"Point"}
}