{
  "type": "Feature",
  "properties": {
    "iso:country":"US",
    "sg:address":"7609 Carothers St",
    "sg:city":"Houston",
    "sg:classifiers":[
        {
            "category":"Organizations",
            "subcategory":"Religious Organization",
            "type":"Services"
        }
    ],
    "sg:phone":"+1 713 633 1100",
    "sg:postcode":"77028",
    "sg:province":"TX",
    "wof:name":"Come To The Cross Prison",
    "wof:placetype":"venue"
},
  "geometry": {"coordinates":[-95.289086,29.834149],"type":"Point"}
}