{
  "type": "Feature",
  "properties": {
    "iso:country":"US",
    "sg:address":"321 Topeka Dr",
    "sg:city":"Waco",
    "sg:classifiers":[
        {
            "category":"Personal",
            "type":"Services"
        }
    ],
    "sg:phone":"+1 254 399 0922",
    "sg:postcode":"76712",
    "sg:province":"TX",
    "wof:name":"Billy R Holtkamp",
    "wof:placetype":"venue"
},
  "geometry": {"coordinates":[-97.204886,31.509317],"type":"Point"}
}