{
  "type": "Feature",
  "properties": {
    "iso:country":"US",
    "sg:address":"114 Greenwood Dr",
    "sg:city":"Beaumont",
    "sg:classifiers":[
        {
            "category":"Professional",
            "subcategory":"Business Services",
            "type":"Services"
        }
    ],
    "sg:phone":"+1 409 796 2008",
    "sg:postcode":"77705",
    "sg:province":"TX",
    "wof:name":"Hl Gilmore Enterprises Inc",
    "wof:placetype":"venue"
},
  "geometry": {"coordinates":[-94.141302,29.873617],"type":"Point"}
}