{
  "type": "Feature",
  "properties": {
    "iso:country":"US",
    "sg:address":"4019 John Ben Shepperd Pkwy",
    "sg:city":"Odessa",
    "sg:classifiers":[
        {
            "category":"Restaurant",
            "type":"Food & Drink"
        }
    ],
    "sg:phone":"+1 432 550 0691",
    "sg:postcode":"79762",
    "sg:province":"TX",
    "sg:tags":[
        "eating"
    ],
    "wof:name":"Dos Compadres Mexican Rest",
    "wof:placetype":"venue"
},
  "geometry": {"coordinates":[-102.332965,31.889655],"type":"Point"}
}