{
  "type": "Feature",
  "properties": {
    "iso:country":"US",
    "sg:address":"22758 Westheimer Pkwy",
    "sg:city":"Katy",
    "sg:classifiers":[
        {
            "category":"Restaurant",
            "type":"Food & Drink"
        }
    ],
    "sg:phone":"+1 281 395 3473",
    "sg:postcode":"77450",
    "sg:province":"TX",
    "sg:website":"http://thepublichousekaty.com",
    "wof:name":"The Public House",
    "wof:placetype":"venue"
},
  "geometry": {"coordinates":[-95.763542,29.734594],"type":"Point"}
}