{
  "type": "Feature",
  "properties": {
    "iso:country":"US",
    "sg:address":"906 Western Ave",
    "sg:city":"Orange",
    "sg:classifiers":[
        {
            "category":"Personal",
            "type":"Services"
        },
        {
            "category":"Restaurant",
            "type":"Food & Drink"
        }
    ],
    "sg:phone":"+1 409 886 1902",
    "sg:postcode":"77630",
    "sg:province":"TX",
    "sg:tags":[
        "banquet",
        "rooms"
    ],
    "wof:name":"Shirley's Table Covering",
    "wof:placetype":"venue"
},
  "geometry": {"coordinates":[-93.737949,30.084483],"type":"Point"}
}