{
  "type": "Feature",
  "properties": {
    "iso:country":"US",
    "sg:address":"902 S Allen Genoa Rd Ste A",
    "sg:city":"South Houston",
    "sg:classifiers":[
        {
            "category":"Food & Beverages",
            "subcategory":"Groceries & Convenience Stores",
            "type":"Retail Goods"
        }
    ],
    "sg:phone":"+1 713 910 1800",
    "sg:postcode":"77587",
    "sg:province":"TX",
    "wof:name":"Allen Genoa Food Store",
    "wof:placetype":"venue"
},
  "geometry": {"coordinates":[-95.21004499999999,29.657238],"type":"Point"}
}