{
  "type": "Feature",
  "properties": {
    "iso:country":"US",
    "sg:address":"5600 W Lovers Ln",
    "sg:city":"Dallas",
    "sg:classifiers":[
        {
            "category":"Shopping",
            "subcategory":"Clothing, Apparel, & Fashions",
            "type":"Retail Goods"
        }
    ],
    "sg:phone":"+1 214 353 9671",
    "sg:postcode":"75209",
    "sg:province":"TX",
    "sg:tags":[
        "wear",
        "shoes"
    ],
    "wof:name":"Childrens Collection",
    "wof:placetype":"venue"
},
  "geometry": {"coordinates":[-96.815361,32.851161],"type":"Point"}
}