{
  "type": "Feature",
  "properties": {
    "iso:country":"US",
    "sg:address":"14025 Northwest Freeway",
    "sg:city":"Houston",
    "sg:classifiers":[
        {
            "category":"Retail",
            "subcategory":"Auto Repair",
            "type":"Services"
        }
    ],
    "sg:phone":"+1 713 460 8444",
    "sg:postcode":"77040",
    "sg:province":"TX",
    "sg:website":"www.justbrakes.com",
    "wof:name":"Just Brakes",
    "wof:placetype":"venue"
},
  "geometry": {"coordinates":[-95.51830699999999,29.855357],"type":"Point"}
}