{
  "type": "Feature",
  "properties": {
    "iso:country":"US",
    "sg:address":"431 Candlelight Ave",
    "sg:city":"Duncanville",
    "sg:classifiers":[
        {
            "category":"Retail",
            "subcategory":"Portrait Studio",
            "type":"Services"
        }
    ],
    "sg:phone":"+1 972 709 6414",
    "sg:postcode":"75137",
    "sg:province":"TX",
    "sg:tags":[
        "photo"
    ],
    "wof:name":"C&C Photography & Graphic",
    "wof:placetype":"venue"
},
  "geometry": {"coordinates":[-96.90315200000001,32.638919],"type":"Point"}
}