{
  "type": "Feature",
  "properties": {
    "iso:country":"US",
    "sg:address":"3520 E Gilbert Rd",
    "sg:city":"Grand Prairie",
    "sg:classifiers":[
        {
            "category":"Bus Charters",
            "type":"Transportation"
        }
    ],
    "sg:phone":"+1 972 986 2071",
    "sg:postcode":"75050",
    "sg:province":"TX",
    "sg:tags":[
        "rental"
    ],
    "sg:website":"www.midnightcoach.com",
    "wof:name":"Midnight Coaches Inc",
    "wof:placetype":"venue"
},
  "geometry": {"coordinates":[-97.002352,32.81365],"type":"Point"}
}