{
  "type": "Feature",
  "properties": {
    "iso:country":"US",
    "sg:address":"301 W Hall Acres Rd",
    "sg:city":"Pharr",
    "sg:classifiers":[
        {
            "category":"Professional",
            "type":"Services"
        }
    ],
    "sg:phone":"+1 956 787 0312",
    "sg:postcode":"78577",
    "sg:province":"TX",
    "wof:name":"Marlenes Water Colors",
    "wof:placetype":"venue"
},
  "geometry": {"coordinates":[-98.19166,26.166676],"type":"Point"}
}