{
  "type": "Feature",
  "properties": {
    "iso:country":"US",
    "sg:address":"1615 Hines Rd",
    "sg:city":"Cleburne",
    "sg:classifiers":[
        {
            "category":"Autos & Motor Vehicles",
            "subcategory":"Auto Supplies",
            "type":"Retail Goods"
        },
        {
            "category":"Retail",
            "subcategory":"Auto Repair",
            "type":"Services"
        }
    ],
    "sg:phone":"+1 817 641 0039",
    "sg:postcode":"76031",
    "sg:province":"TX",
    "sg:tags":[
        "body",
        "lettering",
        "automobile",
        "truck",
        "painting",
        "repairing"
    ],
    "wof:name":"Edmonds Bill & Son Paint & Body Shop",
    "wof:placetype":"venue"
},
  "geometry": {"coordinates":[-97.38174100000001,32.330073],"type":"Point"}
}