{
  "type": "Feature",
  "properties": {
    "iso:country":"US",
    "sg:address":"8610 Broadway",
    "sg:city":"San Antonio",
    "sg:classifiers":[
        {
            "category":"Social Services",
            "type":"Services"
        }
    ],
    "sg:phone":"+1 210 805 2200",
    "sg:postcode":"78217",
    "sg:province":"TX",
    "sg:tags":[
        "rehabilitation",
        "center"
    ],
    "wof:name":"Dept Assistive Rehabilitative",
    "wof:placetype":"venue"
},
  "geometry": {"coordinates":[-98.461595,29.519651],"type":"Point"}
}