{
  "type": "Feature",
  "properties": {
    "iso:country":"US",
    "sg:address":"1160 Airway Blvd",
    "sg:city":"El Paso",
    "sg:classifiers":[
        {
            "category":"Retail",
            "subcategory":"Portrait Studio",
            "type":"Services"
        }
    ],
    "sg:phone":"+1 915 775 3517",
    "sg:postcode":"79925",
    "sg:province":"TX",
    "sg:tags":[
        "school",
        "photography"
    ],
    "wof:name":"Lifetouch",
    "wof:placetype":"venue"
},
  "geometry": {"coordinates":[-106.39527699999999,31.783515],"type":"Point"}
}