{
  "type": "Feature",
  "properties": {
    "iso:country":"US",
    "sg:address":"1500 Hearthstone Dr",
    "sg:city":"Plano",
    "sg:classifiers":[
        {
            "category":"Retail",
            "subcategory":"Animal Services",
            "type":"Services"
        }
    ],
    "sg:phone":"+1 972 596 4037",
    "sg:postcode":"75023",
    "sg:province":"TX",
    "sg:tags":[
        "pet",
        "boarding",
        "sitting"
    ],
    "wof:name":"Teacher's Pets",
    "wof:placetype":"venue"
},
  "geometry": {"coordinates":[-96.725543,33.042339],"type":"Point"}
}