{
  "type": "Feature",
  "properties": {
    "iso:country":"US",
    "sg:address":"6324 Custer Rd",
    "sg:city":"Plano",
    "sg:classifiers":[
        {
            "category":"Cinema",
            "subcategory":"Movie Rental",
            "type":"Entertainment"
        }
    ],
    "sg:phone":"+1 972 575 9181",
    "sg:postcode":"75023",
    "sg:province":"TX",
    "sg:tags":[
        "leasing",
        "video",
        "disc",
        "tape"
    ],
    "wof:name":"Blockbuster Video",
    "wof:placetype":"venue"
},
  "geometry": {"coordinates":[-96.733121,33.059067],"type":"Point"}
}