{
  "type": "Feature",
  "properties": {
    "iso:country":"US",
    "sg:address":"901 N Orange St",
    "sg:city":"Alpine",
    "sg:classifiers":[
        {
            "category":"Real Estate",
            "subcategory":"Real Estate Operator",
            "type":"Services"
        },
        {
            "category":"Health Services",
            "subcategory":"Nursing And Care Facility",
            "type":"Services"
        },
        {
            "category":"Social Services",
            "subcategory":"Adult Care",
            "type":"Services"
        }
    ],
    "sg:phone":"+1 432 837 2259",
    "sg:postcode":"79830",
    "sg:province":"TX",
    "sg:tags":[
        "living",
        "apartment",
        "assisted",
        "rest",
        "elder",
        "home"
    ],
    "wof:name":"Alpine Retirement Community",
    "wof:placetype":"venue"
},
  "geometry": {"coordinates":[-103.678753,30.35612],"type":"Point"}
}