{
  "type": "Feature",
  "properties": {
    "iso:country":"US",
    "sg:address":"1714 54th St",
    "sg:city":"Galveston",
    "sg:classifiers":[
        {
            "category":"Social Services",
            "type":"Services"
        }
    ],
    "sg:phone":"+1 409 744 1289",
    "sg:postcode":"77551",
    "sg:province":"TX",
    "wof:name":"Clutterless Recovery Groups",
    "wof:placetype":"venue"
},
  "geometry": {"coordinates":[-94.82520700000001,29.284283],"type":"Point"}
}