{
  "type": "Feature",
  "properties": {
    "iso:country":"US",
    "sg:address":"5003 Oates Rd",
    "sg:city":"Houston",
    "sg:classifiers":[
        {
            "category":"Freight",
            "type":"Transportation"
        }
    ],
    "sg:phone":"+1 713 672 0100",
    "sg:postcode":"77013",
    "sg:province":"TX",
    "sg:tags":[
        "operator",
        "trucking"
    ],
    "wof:name":"Road Master Trucking Inc",
    "wof:placetype":"venue"
},
  "geometry": {"coordinates":[-95.240607,29.80933],"type":"Point"}
}