{
  "type": "Feature",
  "properties": {
    "iso:country":"US",
    "sg:address":"11321 Chaucer Dr",
    "sg:city":"Frisco",
    "sg:classifiers":[
        {
            "category":"Professional",
            "subcategory":"Management & Consulting",
            "type":"Services"
        }
    ],
    "sg:phone":"+1 972 240 7614",
    "sg:postcode":"75035",
    "sg:province":"TX",
    "wof:name":"Smart Employee Benefits Inc",
    "wof:placetype":"venue"
},
  "geometry": {"coordinates":[-96.781673,33.137552],"type":"Point"}
}