{
  "type": "Feature",
  "properties": {
    "iso:country":"US",
    "sg:address":"300 W Bitters Rd",
    "sg:city":"San Antonio",
    "sg:classifiers":[
        {
            "category":"Retail",
            "subcategory":"Laundry & Dry Cleaning",
            "type":"Services"
        }
    ],
    "sg:phone":"+1 210 494 3183",
    "sg:postcode":"78216",
    "sg:province":"TX",
    "sg:tags":[
        "cleaners"
    ],
    "wof:name":"Slater-White Cleaners",
    "wof:placetype":"venue"
},
  "geometry": {"coordinates":[-98.49014099999999,29.570854],"type":"Point"}
}