{
  "type": "Feature",
  "properties": {
    "iso:country":"US",
    "sg:address":"15227 Garett Green Cir",
    "sg:city":"Houston",
    "sg:classifiers":[
        {
            "category":"Professional",
            "subcategory":"Engineering",
            "type":"Services"
        }
    ],
    "sg:phone":"+1 281 858 1014",
    "sg:postcode":"77095",
    "sg:province":"TX",
    "sg:tags":[
        "engineer"
    ],
    "wof:name":"Ardoin Engineering",
    "wof:placetype":"venue"
},
  "geometry": {"coordinates":[-95.633745,29.913393],"type":"Point"}
}