{
  "type": "Feature",
  "properties": {
    "iso:country":"US",
    "sg:address":"2712 Edenwood Dr",
    "sg:city":"Austin",
    "sg:classifiers":[
        {
            "category":"Professional",
            "type":"Services"
        }
    ],
    "sg:phone":"+1 512 445 4576",
    "sg:postcode":"78745",
    "sg:province":"TX",
    "sg:tags":[
        "establishment"
    ],
    "wof:name":"Amd-Michael Hillis",
    "wof:placetype":"venue"
},
  "geometry": {"coordinates":[-97.818924,30.203786],"type":"Point"}
}