{
  "type": "Feature",
  "properties": {
    "iso:country":"US",
    "sg:address":"9100 Southwest Fwy",
    "sg:city":"Houston",
    "sg:classifiers":[
        {
            "category":"Banks & Credit Unions",
            "subcategory":"Investment Brokerage",
            "type":"Services"
        }
    ],
    "sg:phone":"+1 713 270 0000",
    "sg:postcode":"77074",
    "sg:province":"TX",
    "sg:tags":[
        "advisory",
        "financial"
    ],
    "wof:name":"Victory Financial Group",
    "wof:placetype":"venue"
},
  "geometry": {"coordinates":[-95.534329,29.683871],"type":"Point"}
}