{
  "type": "Feature",
  "properties": {
    "iso:country":"US",
    "sg:address":"1220 E Commerce St",
    "sg:city":"San Antonio",
    "sg:classifiers":[
        {
            "category":"Restaurant",
            "type":"Food & Drink"
        }
    ],
    "sg:phone":"+1 210 223 2680",
    "sg:postcode":"78205",
    "sg:province":"TX",
    "sg:tags":[
        "caterer"
    ],
    "wof:name":"Catering By Rosemary Inc",
    "wof:placetype":"venue"
},
  "geometry": {"coordinates":[-98.47639599999999,29.421114],"type":"Point"}
}