{
  "type": "Feature",
  "properties": {
    "iso:country":"US",
    "sg:address":"707 Widener Ln",
    "sg:city":"Laredo",
    "sg:classifiers":[
        {
            "category":"Wholesale",
            "subcategory":"Durable Goods & Equipment",
            "type":"Manufacturing & Wholesale Goods"
        }
    ],
    "sg:phone":"+1 956 726 1431",
    "sg:postcode":"78041",
    "sg:province":"TX",
    "sg:tags":[
        "exporter"
    ],
    "wof:name":"Valle Trade Co",
    "wof:placetype":"venue"
},
  "geometry": {"coordinates":[-99.477036,27.568854],"type":"Point"}
}