{
  "type": "Feature",
  "properties": {
    "iso:country":"US",
    "sg:address":"4702 Pecan Grove Dr",
    "sg:city":"Pearland",
    "sg:classifiers":[
        {
            "category":"Social Services",
            "subcategory":"Child Care",
            "type":"Services"
        }
    ],
    "sg:phone":"+1 281 485 0298",
    "sg:postcode":"77584",
    "sg:province":"TX",
    "wof:name":"Day Care",
    "wof:placetype":"venue"
},
  "geometry": {"coordinates":[-95.345089,29.550539],"type":"Point"}
}