{
  "type": "Feature",
  "properties": {
    "iso:country":"US",
    "sg:address":"9208 Johns Rd",
    "sg:city":"Houston",
    "sg:classifiers":[
        {
            "category":"Building & Trades",
            "subcategory":"Electrical",
            "type":"Services"
        }
    ],
    "sg:phone":"+1 281 830 1446",
    "sg:postcode":"77049",
    "sg:province":"TX",
    "sg:tags":[
        "electrical",
        "electric",
        "contractor"
    ],
    "wof:name":"Anderson Electrical Svcs L L C",
    "wof:placetype":"venue"
},
  "geometry": {"coordinates":[-95.13869,29.859659],"type":"Point"}
}