{
  "type": "Feature",
  "properties": {
    "iso:country":"US",
    "sg:address":"3604 Teal Ln",
    "sg:city":"Bedford",
    "sg:classifiers":[
        {
            "category":"Building & Trades",
            "subcategory":"Construction",
            "type":"Services"
        }
    ],
    "sg:phone":"+1 817 354 4459",
    "sg:postcode":"76021",
    "sg:province":"TX",
    "sg:tags":[
        "house"
    ],
    "wof:name":"Jess Jones Construction",
    "wof:placetype":"venue"
},
  "geometry": {"coordinates":[-97.123689,32.864241],"type":"Point"}
}