{
  "type": "Feature",
  "properties": {
    "iso:country":"US",
    "sg:address":"8401 Gateway Blvd W",
    "sg:city":"El Paso",
    "sg:classifiers":[
        {
            "category":"Shopping",
            "subcategory":"Computers & Home Electronics",
            "type":"Retail Goods"
        }
    ],
    "sg:phone":"+1 915 779 7275",
    "sg:postcode":"79935",
    "sg:province":"TX",
    "sg:tags":[
        "game",
        "video",
        "software"
    ],
    "wof:name":"Electronics Boutique",
    "wof:placetype":"venue"
},
  "geometry": {"coordinates":[-106.382199,31.774207],"type":"Point"}
}