{
  "type": "Feature",
  "properties": {
    "iso:country":"US",
    "sg:address":"4601 Granny Dr",
    "sg:city":"Del Valle",
    "sg:classifiers":[
        {
            "category":"Building & Trades",
            "subcategory":"Construction",
            "type":"Services"
        }
    ],
    "sg:phone":"+1 512 247 4871",
    "sg:postcode":"78617",
    "sg:province":"TX",
    "sg:tags":[
        "heavy"
    ],
    "wof:name":"B & B Land Clearing Co Inc",
    "wof:placetype":"venue"
},
  "geometry": {"coordinates":[-97.553624,30.182641],"type":"Point"}
}