{
  "type": "Feature",
  "properties": {
    "iso:country":"US",
    "sg:address":"4209 Rosemary Ln",
    "sg:city":"Houston",
    "sg:classifiers":[
        {
            "category":"Organizations",
            "subcategory":"Religious Organization",
            "type":"Services"
        }
    ],
    "sg:phone":"+1 832 922 0374",
    "sg:postcode":"77093",
    "sg:province":"TX",
    "sg:tags":[
        "community",
        "church"
    ],
    "sg:website":"http://www.churchoflordjesuschrist.org",
    "wof:name":"The Church of the Lord Jesus Christ",
    "wof:placetype":"venue"
},
  "geometry": {"coordinates":[-95.324724,29.877069],"type":"Point"}
}