{
  "type": "Feature",
  "properties": {
    "iso:country":"US",
    "sg:address":"410 Blue Valley Dr",
    "sg:city":"Austin",
    "sg:classifiers":[
        {
            "category":"Restaurant",
            "type":"Food & Drink"
        }
    ],
    "sg:phone":"+1 512 280 0740",
    "sg:postcode":"78748",
    "sg:province":"TX",
    "sg:tags":[
        "eating"
    ],
    "wof:name":"Kathryn E Burger",
    "wof:placetype":"venue"
},
  "geometry": {"coordinates":[-97.78980300000001,30.181624],"type":"Point"}
}