{
  "type": "Feature",
  "properties": {
    "iso:country":"US",
    "sg:address":"951 E Bitters Rd",
    "sg:city":"San Antonio",
    "sg:classifiers":[
        {
            "category":"Retail",
            "subcategory":"Auto Repair",
            "type":"Services"
        }
    ],
    "sg:phone":"+1 210 495 7400",
    "sg:postcode":"78216",
    "sg:province":"TX",
    "sg:tags":[
        "transmission"
    ],
    "wof:name":"AAMCO Transmissions",
    "wof:placetype":"venue"
},
  "geometry": {"coordinates":[-98.479074,29.562388],"type":"Point"}
}