{
  "type": "Feature",
  "properties": {
    "iso:country":"US",
    "sg:address":"7617 Stony Brook Dr",
    "sg:city":"Corpus Christi",
    "sg:classifiers":[
        {
            "category":"Building & Trades",
            "subcategory":"Construction",
            "type":"Services"
        }
    ],
    "sg:phone":"+1 361 334 4160",
    "sg:postcode":"78413",
    "sg:province":"TX",
    "sg:tags":[
        "house"
    ],
    "wof:name":"C & M Homestead Inc",
    "wof:placetype":"venue"
},
  "geometry": {"coordinates":[-97.40186,27.666871],"type":"Point"}
}