{
  "type": "Feature",
  "properties": {
    "iso:country":"US",
    "sg:address":"3416 Enterprise Dr",
    "sg:city":"Rowlett",
    "sg:classifiers":[
        {
            "category":"Shopping",
            "subcategory":"Computers & Home Electronics",
            "type":"Retail Goods"
        }
    ],
    "sg:phone":"+1 972 412 2290",
    "sg:postcode":"75088",
    "sg:province":"TX",
    "sg:tags":[
        "software"
    ],
    "wof:name":"Scott's Systems",
    "wof:placetype":"venue"
},
  "geometry": {"coordinates":[-96.570645,32.905374],"type":"Point"}
}