{
  "type": "Feature",
  "properties": {
    "iso:country":"US",
    "sg:address":"229 Dowlen Rd",
    "sg:city":"Beaumont",
    "sg:classifiers":[
        {
            "category":"Food & Beverages",
            "subcategory":"Specialty",
            "type":"Retail Goods"
        }
    ],
    "sg:phone":"+1 409 861 4424",
    "sg:postcode":"77706",
    "sg:province":"TX",
    "sg:tags":[
        "supplement",
        "health",
        "vitamin",
        "diet"
    ],
    "sg:website":"http://www.basicfoodsmarket.com",
    "wof:name":"Basic Foods",
    "wof:placetype":"venue"
},
  "geometry": {"coordinates":[-94.17227800000001,30.075023],"type":"Point"}
}