{
  "type": "Feature",
  "properties": {
    "iso:country":"US",
    "sg:address":"202 N Texas Blvd",
    "sg:city":"Alice",
    "sg:classifiers":[
        {
            "category":"Shopping",
            "type":"Retail Goods"
        }
    ],
    "sg:phone":"+1 361 396 0000",
    "sg:postcode":"78332",
    "sg:province":"TX",
    "sg:tags":[
        "merchandise"
    ],
    "wof:name":"Coast To Coast Wireless",
    "wof:placetype":"venue"
},
  "geometry": {"coordinates":[-98.064672,27.753139],"type":"Point"}
}