{
  "type": "Feature",
  "properties": {
    "iso:country":"US",
    "sg:address":"302 S Clark St",
    "sg:city":"Rockwall",
    "sg:classifiers":[
        {
            "category":"Social Services",
            "subcategory":"Child Care",
            "type":"Services"
        }
    ],
    "sg:phone":"+1 972 771 4537",
    "sg:postcode":"75087",
    "sg:province":"TX",
    "sg:tags":[
        "day"
    ],
    "wof:name":"Burgess Day Care",
    "wof:placetype":"venue"
},
  "geometry": {"coordinates":[-96.454463,32.929097],"type":"Point"}
}