{
  "type": "Feature",
  "properties": {
    "iso:country":"US",
    "sg:address":"9101 Old McGregor Rd",
    "sg:city":"Waco",
    "sg:classifiers":[
        {
            "category":"Retail",
            "subcategory":"Auto Repair",
            "type":"Services"
        }
    ],
    "sg:phone":"+1 254 772 0760",
    "sg:postcode":"76712",
    "sg:province":"TX",
    "sg:tags":[
        "automotive",
        "supply",
        "general"
    ],
    "wof:name":"Midway Auto Parts & Supply",
    "wof:placetype":"venue"
},
  "geometry": {"coordinates":[-97.221148,31.492452],"type":"Point"}
}