{
  "type": "Feature",
  "properties": {
    "iso:country":"US",
    "sg:address":"2200 Post Oak Blvd",
    "sg:city":"Houston",
    "sg:classifiers":[
        {
            "category":"Insurance",
            "subcategory":"Hazard Insurance",
            "type":"Services"
        },
        {
            "category":"Insurance",
            "subcategory":"Insurance Agent",
            "type":"Services"
        }
    ],
    "sg:phone":"+1 713 622 4867",
    "sg:postcode":"77056",
    "sg:province":"TX",
    "sg:tags":[
        "employee",
        "benefit",
        "plan",
        "compensation"
    ],
    "wof:name":"M J Murray R H U & Assoc",
    "wof:placetype":"venue"
},
  "geometry": {"coordinates":[-95.461074,29.74494],"type":"Point"}
}