{
  "type": "Feature",
  "properties": {
    "iso:country":"US",
    "sg:address":"22711 Mines Rd",
    "sg:city":"Laredo",
    "sg:classifiers":[
        {
            "category":"Autos & Motor Vehicles",
            "subcategory":"Recreational Vehicle Sales",
            "type":"Retail Goods"
        },
        {
            "category":"Retail",
            "subcategory":"Auto Repair",
            "type":"Services"
        }
    ],
    "sg:phone":"+1 956 796 1605",
    "sg:postcode":"78045",
    "sg:province":"TX",
    "sg:tags":[
        "automotive",
        "travel",
        "trailer"
    ],
    "wof:name":"Trailer Connection of Laredo",
    "wof:placetype":"venue"
},
  "geometry": {"coordinates":[-99.604091,27.655577],"type":"Point"}
}