{
  "type": "Feature",
  "properties": {
    "iso:country":"US",
    "sg:address":"445 Walnut St Ste 115",
    "sg:city":"Richardson",
    "sg:classifiers":[
        {
            "category":"Personal",
            "subcategory":"Massage",
            "type":"Services"
        }
    ],
    "sg:phone":"+1 214 476 7213",
    "sg:postcode":"75081",
    "sg:province":"TX",
    "wof:name":"Philippa Dodson, LMT",
    "wof:placetype":"venue"
},
  "geometry": {"coordinates":[-96.731454,32.925563],"type":"Point"}
}