{
  "type": "Feature",
  "properties": {
    "iso:country":"US",
    "sg:address":"581 W Campbell Rd",
    "sg:city":"Richardson",
    "sg:classifiers":[
        {
            "category":"Organizations",
            "subcategory":"Religious Organization",
            "type":"Services"
        }
    ],
    "sg:phone":"+1 972 644 4737",
    "sg:postcode":"75080",
    "sg:province":"TX",
    "wof:name":"Canyon Creek Community Church",
    "wof:placetype":"venue"
},
  "geometry": {"coordinates":[-96.737459,32.976726],"type":"Point"}
}