{
  "type": "Feature",
  "properties": {
    "iso:country":"US",
    "sg:address":"7030 Tokalon Dr",
    "sg:city":"Dallas",
    "sg:classifiers":[
        {
            "category":"Health Services",
            "subcategory":"Doctor",
            "type":"Services"
        }
    ],
    "sg:phone":"+1 214 328 3898",
    "sg:postcode":"75214",
    "sg:province":"TX",
    "sg:tags":[
        "physician",
        "surgeon",
        "medical"
    ],
    "wof:name":"Steinbach Sandra MD",
    "wof:placetype":"venue"
},
  "geometry": {"coordinates":[-96.736198,32.819401],"type":"Point"}
}