{
  "type": "Feature",
  "properties": {
    "iso:country":"US",
    "sg:address":"11111 Plano Rd",
    "sg:city":"Dallas",
    "sg:classifiers":[
        {
            "category":"Building & Trades",
            "subcategory":"Construction",
            "type":"Services"
        }
    ],
    "sg:phone":"+1 214 341 0668",
    "sg:postcode":"75238",
    "sg:province":"TX",
    "sg:tags":[
        "insulation",
        "heat",
        "contractor"
    ],
    "sg:website":"www.nasco.com",
    "wof:name":"Williams Insulation",
    "wof:placetype":"venue"
},
  "geometry": {"coordinates":[-96.70068999999999,32.900561],"type":"Point"}
}