{
  "type": "Feature",
  "properties": {
    "iso:country":"US",
    "sg:address":"5620 Volder Dr",
    "sg:city":"Fort Worth",
    "sg:classifiers":[
        {
            "category":"Personal",
            "type":"Services"
        }
    ],
    "sg:phone":"+1 817 731 3912",
    "sg:postcode":"76114",
    "sg:province":"TX",
    "wof:name":"Dunavant Patrick Tux Carl",
    "wof:placetype":"venue"
},
  "geometry": {"coordinates":[-97.407725,32.751253],"type":"Point"}
}