{
  "type": "Feature",
  "properties": {
    "iso:country":"US",
    "sg:address":"2101 Clubview Dr",
    "sg:city":"Tyler",
    "sg:classifiers":[
        {
            "category":"Professional",
            "subcategory":"Computer Services",
            "type":"Services"
        }
    ],
    "sg:phone":"+1 903 597 7656",
    "sg:postcode":"75701",
    "sg:province":"TX",
    "sg:tags":[
        "related"
    ],
    "wof:name":"Jim Wills",
    "wof:placetype":"venue"
},
  "geometry": {"coordinates":[-95.27262399999999,32.325699],"type":"Point"}
}