{
  "type": "Feature",
  "properties": {
    "iso:country":"US",
    "sg:address":"211 W American Blvd",
    "sg:city":"Muleshoe",
    "sg:classifiers":[
        {
            "category":"Food & Beverages",
            "subcategory":"Groceries & Convenience Stores",
            "type":"Retail Goods"
        }
    ],
    "sg:phone":"+1 806 272 6880",
    "sg:postcode":"79347",
    "sg:province":"TX",
    "wof:name":"All Star Convenience Store",
    "wof:placetype":"venue"
},
  "geometry": {"coordinates":[-102.725877,34.227383],"type":"Point"}
}