{
  "type": "Feature",
  "properties": {
    "iso:country":"US",
    "sg:address":"714 High St",
    "sg:city":"Comfort",
    "sg:classifiers":[
        {
            "category":"Restaurant",
            "type":"Food & Drink"
        }
    ],
    "sg:phone":"+1 830 995 3470",
    "sg:postcode":"78013",
    "sg:province":"TX",
    "sg:website":"http://www.mimiscafe.com/",
    "wof:name":"Mimi's Cafe",
    "wof:placetype":"venue"
},
  "geometry": {"coordinates":[-98.907667,29.967001],"type":"Point"}
}