{
  "type": "Feature",
  "properties": {
    "iso:country":"US",
    "sg:address":"920 Frostwood Dr",
    "sg:city":"Houston",
    "sg:classifiers":[
        {
            "category":"Health Services",
            "subcategory":"Doctor",
            "type":"Services"
        }
    ],
    "sg:phone":"+1 713 467 4883",
    "sg:postcode":"77024",
    "sg:province":"TX",
    "sg:tags":[
        "medical"
    ],
    "wof:name":"Christopherson M Bruce",
    "wof:placetype":"venue"
},
  "geometry": {"coordinates":[-95.54777900000001,29.779169],"type":"Point"}
}