{
  "type": "Feature",
  "properties": {
    "iso:country":"US",
    "sg:address":"1300 Holman St",
    "sg:city":"Houston",
    "sg:classifiers":[
        {
            "category":"Education",
            "subcategory":"Junior College",
            "type":"Public Place"
        }
    ],
    "sg:phone":"+1 713 718 6000",
    "sg:postcode":"77004",
    "sg:province":"TX",
    "wof:name":"Central College",
    "wof:placetype":"venue"
},
  "geometry": {"coordinates":[-95.375067,29.737703],"type":"Point"}
}