{
  "type": "Feature",
  "properties": {
    "iso:country":"US",
    "sg:address":"4739 Lucky Ln",
    "sg:city":"Dallas",
    "sg:classifiers":[
        {
            "category":"Retail",
            "subcategory":"Auto Repair",
            "type":"Services"
        }
    ],
    "sg:phone":"+1 214 637 0565",
    "sg:postcode":"75247",
    "sg:province":"TX",
    "sg:tags":[
        "truck",
        "semi",
        "general"
    ],
    "wof:name":"Longhorn Alignment",
    "wof:placetype":"venue"
},
  "geometry": {"coordinates":[-96.874318,32.805333],"type":"Point"}
}