{
  "type": "Feature",
  "properties": {
    "iso:country":"US",
    "sg:address":"1919 Jefferson Dr",
    "sg:city":"Port Arthur",
    "sg:classifiers":[
        {
            "category":"Organizations",
            "subcategory":"Religious Organization",
            "type":"Services"
        }
    ],
    "sg:phone":"+1 409 963 2961",
    "sg:postcode":"77642",
    "sg:province":"TX",
    "wof:name":"Paul Anderson",
    "wof:placetype":"venue"
},
  "geometry": {"coordinates":[-93.91546200000001,29.923004],"type":"Point"}
}