{
  "type": "Feature",
  "properties": {
    "iso:country":"US",
    "sg:address":"115 Morrill Ave",
    "sg:city":"San Antonio",
    "sg:classifiers":[
        {
            "category":"Shopping",
            "subcategory":"Gifts & Souvenirs",
            "type":"Retail Goods"
        }
    ],
    "sg:phone":"+1 210 977 9215",
    "sg:postcode":"78214",
    "sg:province":"TX",
    "wof:name":"Baby Pillow Talk",
    "wof:placetype":"venue"
},
  "geometry": {"coordinates":[-98.498375,29.37942],"type":"Point"}
}