{
  "type": "Feature",
  "properties": {
    "iso:country":"US",
    "sg:address":"518 E Texas Ave",
    "sg:city":"Mart",
    "sg:classifiers":[
        {
            "category":"Banks & Credit Unions",
            "subcategory":"Bank",
            "type":"Services"
        }
    ],
    "sg:phone":"+1 254 876 3600",
    "sg:postcode":"76664",
    "sg:province":"TX",
    "sg:tags":[
        "loan",
        "real estate"
    ],
    "wof:name":"CSI Mortgage Corp",
    "wof:placetype":"venue"
},
  "geometry": {"coordinates":[-96.83255200000001,31.5428],"type":"Point"}
}