{
  "type": "Feature",
  "properties": {
    "iso:country":"US",
    "sg:address":"1900 Ben Ave",
    "sg:city":"Fort Worth",
    "sg:classifiers":[
        {
            "category":"Restaurant",
            "type":"Food & Drink"
        }
    ],
    "sg:phone":"+1 817 534 4908",
    "sg:postcode":"76103",
    "sg:province":"TX",
    "sg:tags":[
        "eating"
    ],
    "wof:name":"Fort Worth Cattle Drive Rstrnt",
    "wof:placetype":"venue"
},
  "geometry": {"coordinates":[-97.279354,32.745126],"type":"Point"}
}