{
  "type": "Feature",
  "properties": {
    "iso:country":"US",
    "sg:address":"1000 5th St",
    "sg:city":"Wichita Falls",
    "sg:classifiers":[
        {
            "category":"Professional",
            "type":"Services"
        }
    ],
    "sg:phone":"+1 940 763 2201",
    "sg:postcode":"76301",
    "sg:province":"TX",
    "sg:tags":[
        "establishment"
    ],
    "wof:name":"Parkside Cycle",
    "wof:placetype":"venue"
},
  "geometry": {"coordinates":[-98.497832,33.912997],"type":"Point"}
}