{
  "type": "Feature",
  "properties": {
    "iso:country":"US",
    "sg:address":"4706 W Orange St",
    "sg:city":"Pearland",
    "sg:classifiers":[
        {
            "category":"Food & Beverages",
            "subcategory":"Groceries & Convenience Stores",
            "type":"Retail Goods"
        }
    ],
    "sg:phone":"+1 281 485 1171",
    "sg:postcode":"77581",
    "sg:province":"TX",
    "sg:tags":[
        "station",
        "gas"
    ],
    "wof:name":"Spin & Market",
    "wof:placetype":"venue"
},
  "geometry": {"coordinates":[-95.295338,29.569034],"type":"Point"}
}