{
  "type": "Feature",
  "properties": {
    "iso:country":"US",
    "sg:address":"2280 E Garrison St",
    "sg:city":"Eagle Pass",
    "sg:classifiers":[
        {
            "category":"Restaurant",
            "type":"Food & Drink"
        }
    ],
    "sg:phone":"+1 830 773 7232",
    "sg:postcode":"78852",
    "sg:province":"TX",
    "sg:tags":[
        "eating"
    ],
    "wof:name":"Burger King",
    "wof:placetype":"venue"
},
  "geometry": {"coordinates":[-100.483647,28.705717],"type":"Point"}
}