{
  "type": "Feature",
  "properties": {
    "iso:country":"US",
    "sg:address":"1815 Coombs St",
    "sg:city":"Dallas",
    "sg:classifiers":[
        {
            "category":"Manufacturing",
            "subcategory":"Metals",
            "type":"Manufacturing & Wholesale Goods"
        }
    ],
    "sg:phone":"+1 214 421 2141",
    "sg:postcode":"75215",
    "sg:province":"TX",
    "sg:tags":[
        "steel"
    ],
    "wof:name":"Steel Boss Intl",
    "wof:placetype":"venue"
},
  "geometry": {"coordinates":[-96.780784,32.767458],"type":"Point"}
}