{
  "type": "Feature",
  "properties": {
    "iso:country":"US",
    "sg:address":"900 Hollow Trail Ct",
    "sg:city":"Round Rock",
    "sg:classifiers":[
        {
            "category":"Personal",
            "type":"Services"
        }
    ],
    "sg:phone":"+1 210 223 8433",
    "sg:postcode":"78664",
    "sg:province":"TX",
    "wof:name":"Latina Bodas",
    "wof:placetype":"venue"
},
  "geometry": {"coordinates":[-97.652552,30.497628],"type":"Point"}
}