{
  "type": "Feature",
  "properties": {
    "iso:country":"US",
    "sg:address":"299 Coble Rd",
    "sg:city":"Poteet",
    "sg:classifiers":[
        {
            "category":"Farming",
            "subcategory":"Farm",
            "type":"Manufacturing & Wholesale Goods"
        }
    ],
    "sg:phone":"+1 830 742 3682",
    "sg:postcode":"78065",
    "sg:province":"TX",
    "sg:tags":[
        "crop",
        "general"
    ],
    "wof:name":"S & C Farms Inc",
    "wof:placetype":"venue"
},
  "geometry": {"coordinates":[-98.539688,29.088942],"type":"Point"}
}