{
  "type": "Feature",
  "properties": {
    "iso:country":"US",
    "sg:address":"4509 50th St",
    "sg:city":"Lubbock",
    "sg:classifiers":[
        {
            "category":"Shopping",
            "subcategory":"Crafts & Fabrics",
            "type":"Retail Goods"
        }
    ],
    "sg:phone":"+1 806 799 2411",
    "sg:postcode":"79414",
    "sg:province":"TX",
    "sg:tags":[
        "designer"
    ],
    "wof:name":"Swatches Decorative Fabrics",
    "wof:placetype":"venue"
},
  "geometry": {"coordinates":[-101.90926399999999,33.548688],"type":"Point"}
}