{
  "type": "Feature",
  "properties": {
    "iso:country":"US",
    "sg:address":"110 Bolles Cir",
    "sg:city":"Austin",
    "sg:classifiers":[
        {
            "category":"Government",
            "subcategory":"Office",
            "type":"Public Place"
        }
    ],
    "sg:phone":"+1 512 837 2550",
    "sg:postcode":"78753",
    "sg:province":"TX",
    "sg:tags":[
        "housing",
        "agency"
    ],
    "wof:name":"Georgian Manor",
    "wof:placetype":"venue"
},
  "geometry": {"coordinates":[-97.70312300000001,30.35071],"type":"Point"}
}