{
  "type": "Feature",
  "properties": {
    "iso:country":"US",
    "sg:address":"610 N Franklin St",
    "sg:city":"Bronte",
    "sg:classifiers":[
        {
            "category":"Shopping",
            "type":"Retail Goods"
        }
    ],
    "sg:phone":"+1 325 473 2402",
    "sg:postcode":"76933",
    "sg:province":"TX",
    "sg:tags":[
        "monument"
    ],
    "wof:name":"Shaffer Monuments",
    "wof:placetype":"venue"
},
  "geometry": {"coordinates":[-100.29059100000001,31.89164],"type":"Point"}
}