{
  "type": "Feature",
  "properties": {
    "iso:country":"US",
    "sg:address":"16400 Ledgemont Ln",
    "sg:city":"Addison",
    "sg:classifiers":[
        {
            "category":"Professional",
            "subcategory":"Management & Consulting",
            "type":"Services"
        }
    ],
    "sg:phone":"+1 972 931 5020",
    "sg:postcode":"75001",
    "sg:province":"TX",
    "wof:name":"Haffar Marketing",
    "wof:placetype":"venue"
},
  "geometry": {"coordinates":[-96.827676,32.969945],"type":"Point"}
}