{
  "type": "Feature",
  "properties": {
    "iso:country":"US",
    "sg:address":"526 S Treadaway Blvd",
    "sg:city":"Abilene",
    "sg:classifiers":[
        {
            "category":"Retail",
            "subcategory":"Car Wash",
            "type":"Services"
        }
    ],
    "sg:phone":"+1 325 672 2005",
    "sg:postcode":"79602",
    "sg:province":"TX",
    "sg:tags":[
        "carwash"
    ],
    "wof:name":"Carry-On Detail Shop",
    "wof:placetype":"venue"
},
  "geometry": {"coordinates":[-99.72786000000001,32.443685],"type":"Point"}
}