{
  "type": "Feature",
  "properties": {
    "iso:country":"US",
    "sg:address":"240 E Renfro St Ste 207",
    "sg:city":"Burleson",
    "sg:classifiers":[
        {
            "category":"Farming",
            "subcategory":"Fish & Marine Products",
            "type":"Manufacturing & Wholesale Goods"
        }
    ],
    "sg:phone":"+1 817 426 8000",
    "sg:postcode":"76028",
    "sg:province":"TX",
    "wof:name":"Essl",
    "wof:placetype":"venue"
},
  "geometry": {"coordinates":[-97.316914,32.543388],"type":"Point"}
}