{
  "type": "Feature",
  "properties": {
    "iso:country":"US",
    "sg:address":"308 W Main St",
    "sg:city":"Rio Grande City",
    "sg:classifiers":[
        {
            "category":"Shopping",
            "subcategory":"Jewelry",
            "type":"Retail Goods"
        }
    ],
    "sg:phone":"+1 956 487 7431",
    "sg:postcode":"78582",
    "sg:province":"TX",
    "wof:name":"S & A Jewelry",
    "wof:placetype":"venue"
},
  "geometry": {"coordinates":[-98.823476,26.379852],"type":"Point"}
}