{
  "type": "Feature",
  "properties": {
    "iso:country":"US",
    "sg:address":"201 E Saint Elmo Rd",
    "sg:city":"Austin",
    "sg:classifiers":[
        {
            "category":"Organizations",
            "subcategory":"Community Association",
            "type":"Services"
        }
    ],
    "sg:phone":"+1 512 445 0105",
    "sg:postcode":"78745",
    "sg:province":"TX",
    "wof:name":"Sierra Ridge Comm Ctr",
    "wof:placetype":"venue"
},
  "geometry": {"coordinates":[-97.757318,30.214988],"type":"Point"}
}