{
  "type": "Feature",
  "properties": {
    "iso:country":"US",
    "sg:address":"2838 Alaska Ave",
    "sg:city":"Dallas",
    "sg:classifiers":[
        {
            "category":"Retail",
            "subcategory":"Auto Repair",
            "type":"Services"
        }
    ],
    "sg:phone":"+1 214 943 8538",
    "sg:postcode":"75216",
    "sg:province":"TX",
    "sg:tags":[
        "general"
    ],
    "wof:name":"Marcos Auto Repair & Sales",
    "wof:placetype":"venue"
},
  "geometry": {"coordinates":[-96.815754,32.712064],"type":"Point"}
}