{
  "type": "Feature",
  "properties": {
    "iso:country":"US",
    "sg:address":"510 N River St",
    "sg:city":"Seguin",
    "sg:classifiers":[
        {
            "category":"Health Services",
            "subcategory":"Chiropractor",
            "type":"Services"
        }
    ],
    "sg:phone":"+1 830 379 1111",
    "sg:postcode":"78155",
    "sg:province":"TX",
    "wof:name":"Long John",
    "wof:placetype":"venue"
},
  "geometry": {"coordinates":[-97.963903,29.572582],"type":"Point"}
}