{
  "type": "Feature",
  "properties": {
    "iso:country":"US",
    "sg:address":"2910 Kemp Blvd",
    "sg:city":"Wichita Falls",
    "sg:classifiers":[
        {
            "category":"Shopping",
            "subcategory":"Clothing, Apparel, & Fashions",
            "type":"Retail Goods"
        }
    ],
    "sg:phone":"+1 972 315 2554",
    "sg:postcode":"76308",
    "sg:province":"TX",
    "sg:tags":[
        "furnishing"
    ],
    "wof:name":"Casual Male Big & Tall",
    "wof:placetype":"venue"
},
  "geometry": {"coordinates":[-98.528588,33.883402],"type":"Point"}
}