{
  "type": "Feature",
  "properties": {
    "iso:country":"US",
    "sg:address":"1119 Grove St",
    "sg:city":"Houston",
    "sg:classifiers":[
        {
            "category":"Government",
            "subcategory":"Office",
            "type":"Public Place"
        }
    ],
    "sg:phone":"+1 713 228 2461",
    "sg:postcode":"77020",
    "sg:province":"TX",
    "sg:tags":[
        "housing",
        "authority"
    ],
    "wof:name":"Kelly Village",
    "wof:placetype":"venue"
},
  "geometry": {"coordinates":[-95.336713,29.771762],"type":"Point"}
}