{
  "type": "Feature",
  "properties": {
    "iso:country":"US",
    "sg:address":"9009 N FM 620 Ste 705",
    "sg:city":"Austin",
    "sg:classifiers":[
        {
            "category":"Building & Trades",
            "subcategory":"Construction",
            "type":"Services"
        }
    ],
    "sg:phone":"+1 512 695 2081",
    "sg:postcode":"78726",
    "sg:province":"TX",
    "sg:tags":[
        "roofing",
        "contractor"
    ],
    "sg:website":"accentroofingcompany.com/",
    "wof:name":"Accent Roofing Company",
    "wof:placetype":"venue"
},
  "geometry": {"coordinates":[-97.841712,30.431409],"type":"Point"}
}