{
  "type": "Feature",
  "properties": {
    "iso:country":"US",
    "sg:address":"1415 N Dallas Ave",
    "sg:city":"Lancaster",
    "sg:classifiers":[
        {
            "category":"Food & Beverages",
            "subcategory":"Groceries & Convenience Stores",
            "type":"Retail Goods"
        }
    ],
    "sg:phone":"+1 972 227 6990",
    "sg:postcode":"75134",
    "sg:province":"TX",
    "wof:name":"Lancaster Supermarket",
    "wof:placetype":"venue"
},
  "geometry": {"coordinates":[-96.75949199999999,32.605731],"type":"Point"}
}