{
  "type": "Feature",
  "properties": {
    "iso:country":"US",
    "sg:address":"9739 Cobb St",
    "sg:city":"San Antonio",
    "sg:classifiers":[
        {
            "category":"Building & Trades",
            "subcategory":"Construction",
            "type":"Services"
        }
    ],
    "sg:phone":"+1 210 657 5467",
    "sg:postcode":"78217",
    "sg:province":"TX",
    "sg:tags":[
        "interior",
        "renovation",
        "exterior"
    ],
    "wof:name":"OBriens Tile Incorporated",
    "wof:placetype":"venue"
},
  "geometry": {"coordinates":[-98.399811,29.527369],"type":"Point"}
}