{
  "type": "Feature",
  "properties": {
    "iso:country":"US",
    "sg:address":"3307 Hickory Brook Ln",
    "sg:city":"Humble",
    "sg:classifiers":[
        {
            "category":"Organizations",
            "subcategory":"Religious Organization",
            "type":"Services"
        }
    ],
    "sg:phone":"+1 281 360 8287",
    "sg:postcode":"77345",
    "sg:province":"TX",
    "wof:name":"Glad Tidings",
    "wof:placetype":"venue"
},
  "geometry": {"coordinates":[-95.184872,30.060338],"type":"Point"}
}