{
  "type": "Feature",
  "properties": {
    "iso:country":"US",
    "sg:address":"6904 Colleyville Blvd",
    "sg:city":"Colleyville",
    "sg:classifiers":[
        {
            "category":"Personal",
            "subcategory":"Beauty Salon",
            "type":"Services"
        }
    ],
    "sg:phone":"+1 817 552 6398",
    "sg:postcode":"76034",
    "sg:province":"TX",
    "sg:tags":[
        "shop"
    ],
    "wof:name":"Aesthetique",
    "wof:placetype":"venue"
},
  "geometry": {"coordinates":[-97.13526899999999,32.910828],"type":"Point"}
}