{
  "type": "Feature",
  "properties": {
    "iso:country":"US",
    "sg:address":"305 S Archie St",
    "sg:city":"Vidor",
    "sg:classifiers":[
        {
            "category":"Shopping",
            "subcategory":"Pharmacy",
            "type":"Retail Goods"
        }
    ],
    "sg:phone":"+1 409 769 2406",
    "sg:postcode":"77662",
    "sg:province":"TX",
    "wof:name":"Family Pharmacy",
    "wof:placetype":"venue"
},
  "geometry": {"coordinates":[-94.015186,30.126492],"type":"Point"}
}