{
  "type": "Feature",
  "properties": {
    "iso:country":"US",
    "sg:address":"1220 Rock Island Rd",
    "sg:city":"Irving",
    "sg:classifiers":[
        {
            "category":"Autos & Motor Vehicles",
            "subcategory":"Auto Supplies",
            "type":"Retail Goods"
        },
        {
            "category":"Manufacturing",
            "subcategory":"Building Materials",
            "type":"Manufacturing & Wholesale Goods"
        },
        {
            "category":"Manufacturing",
            "subcategory":"Glass & Minerals",
            "type":"Manufacturing & Wholesale Goods"
        },
        {
            "category":"Retail",
            "subcategory":"Auto Repair",
            "type":"Services"
        },
        {
            "category":"Manufacturing",
            "subcategory":"Apparel",
            "type":"Manufacturing & Wholesale Goods"
        }
    ],
    "sg:phone":"+1 972 579 1631",
    "sg:postcode":"75060",
    "sg:province":"TX",
    "sg:tags":[
        "plate",
        "automobile",
        "doors-glass",
        "glass-auto",
        "accessory",
        "window",
        "part",
        "doors",
        "frames",
        "glass-broken",
        "windshield"
    ],
    "sg:website":"http://www.kelleysglass.com",
    "wof:name":"Kelley's Glass & Mirror Inc",
    "wof:placetype":"venue"
},
  "geometry": {"coordinates":[-96.960645,32.814935],"type":"Point"}
}