{
  "type": "Feature",
  "properties": {
    "iso:country":"US",
    "sg:address":"11931 Spring Cypress Rd",
    "sg:city":"Tomball",
    "sg:classifiers":[
        {
            "category":"Food & Beverages",
            "subcategory":"Groceries & Convenience Stores",
            "type":"Retail Goods"
        }
    ],
    "sg:phone":"+1 281 655 0050",
    "sg:postcode":"77377",
    "sg:province":"TX",
    "wof:name":"Handi Stop",
    "wof:placetype":"venue"
},
  "geometry": {"coordinates":[-95.609168,30.012699],"type":"Point"}
}