{
  "type": "Feature",
  "properties": {
    "iso:country":"US",
    "sg:address":"1501 Valleyridge Dr",
    "sg:city":"Austin",
    "sg:classifiers":[
        {
            "category":"Restaurant",
            "type":"Food & Drink"
        }
    ],
    "sg:phone":"+1 512 447 4839",
    "sg:postcode":"78704",
    "sg:province":"TX",
    "sg:tags":[
        "grocery",
        "eating"
    ],
    "wof:name":"Maynards Deli",
    "wof:placetype":"venue"
},
  "geometry": {"coordinates":[-97.77577100000001,30.23608],"type":"Point"}
}