{
  "type": "Feature",
  "properties": {
    "iso:country":"US",
    "sg:address":"1833 Lauder Rd",
    "sg:city":"Houston",
    "sg:classifiers":[
        {
            "category":"Manufacturing",
            "subcategory":"Aerospace",
            "type":"Manufacturing & Wholesale Goods"
        }
    ],
    "sg:phone":"+1 281 442 7791",
    "sg:postcode":"77039",
    "sg:province":"TX",
    "sg:tags":[
        "aircraft",
        "mfg"
    ],
    "wof:name":"Prime Forge Tech Inc",
    "wof:placetype":"venue"
},
  "geometry": {"coordinates":[-95.357913,29.913254],"type":"Point"}
}