{
  "type": "Feature",
  "properties": {
    "iso:country":"US",
    "sg:address":"15221 Berry Trl",
    "sg:city":"Dallas",
    "sg:classifiers":[
        {
            "category":"Manufacturing",
            "subcategory":"Apparel",
            "type":"Manufacturing & Wholesale Goods"
        }
    ],
    "sg:phone":"+1 972 980 7046",
    "sg:postcode":"75248",
    "sg:province":"TX",
    "sg:tags":[
        "mfg"
    ],
    "wof:name":"Mollie Magpie",
    "wof:placetype":"venue"
},
  "geometry": {"coordinates":[-96.803541,32.956077],"type":"Point"}
}