{
  "type": "Feature",
  "properties": {
    "iso:country":"US",
    "sg:address":"501 Clark Blvd",
    "sg:city":"Laredo",
    "sg:classifiers":[
        {
            "category":"Retail",
            "subcategory":"Auto Rental",
            "type":"Services"
        }
    ],
    "sg:phone":"+1 956 718 9915",
    "sg:postcode":"78040",
    "sg:province":"TX",
    "sg:tags":[
        "passenger",
        "car"
    ],
    "wof:name":"Rent A Husband Handyman Svc",
    "wof:placetype":"venue"
},
  "geometry": {"coordinates":[-99.490736,27.516669],"type":"Point"}
}