{
  "type": "Feature",
  "properties": {
    "iso:country":"US",
    "sg:address":"2803 Shady Ln",
    "sg:city":"Webster",
    "sg:classifiers":[
        {
            "category":"Professional",
            "type":"Services"
        }
    ],
    "sg:phone":"+1 281 332 4609",
    "sg:postcode":"77598",
    "sg:province":"TX",
    "wof:name":"Brad Bylund",
    "wof:placetype":"venue"
},
  "geometry": {"coordinates":[-95.144531,29.510218],"type":"Point"}
}