{
  "type": "Feature",
  "properties": {
    "iso:country":"US",
    "sg:address":"2139 Nectar Dr",
    "sg:city":"Mesquite",
    "sg:classifiers":[
        {
            "category":"Retail",
            "subcategory":"Laundry & Dry Cleaning",
            "type":"Services"
        },
        {
            "category":"Building & Trades",
            "subcategory":"Cleaning & Sanitation",
            "type":"Services"
        }
    ],
    "sg:phone":"+1 972 489 8078",
    "sg:postcode":"75149",
    "sg:province":"TX",
    "sg:tags":[
        "cleaner",
        "house"
    ],
    "wof:name":"Oracce Cleaners",
    "wof:placetype":"venue"
},
  "geometry": {"coordinates":[-96.62795300000001,32.75583],"type":"Point"}
}