{
  "type": "Feature",
  "properties": {
    "iso:country":"US",
    "sg:address":"5219 Bayou Glen Rd",
    "sg:city":"Houston",
    "sg:classifiers":[
        {
            "category":"Organizations",
            "subcategory":"Membership Organization",
            "type":"Services"
        }
    ],
    "sg:phone":"+1 713 622 8598",
    "sg:postcode":"77056",
    "sg:province":"TX",
    "wof:name":"March For Life Education",
    "wof:placetype":"venue"
},
  "geometry": {"coordinates":[-95.470705,29.766266],"type":"Point"}
}