{
  "type": "Feature",
  "properties": {
    "iso:country":"US",
    "sg:address":"6821 Old Quarry Ln",
    "sg:city":"Austin",
    "sg:classifiers":[
        {
            "category":"Professional",
            "type":"Services"
        }
    ],
    "sg:phone":"+1 512 231 0634",
    "sg:postcode":"78731",
    "sg:province":"TX",
    "wof:name":"Strangeways",
    "wof:placetype":"venue"
},
  "geometry": {"coordinates":[-97.757481,30.351489],"type":"Point"}
}