{
  "type": "Feature",
  "properties": {
    "iso:country":"US",
    "sg:address":"428 French Pl",
    "sg:city":"El Paso",
    "sg:classifiers":[
        {
            "category":"Social Services",
            "subcategory":"Child Care",
            "type":"Services"
        }
    ],
    "sg:phone":"+1 915 544 7202",
    "sg:postcode":"79905",
    "sg:province":"TX",
    "sg:tags":[
        "day"
    ],
    "wof:name":"Pablin Day Care",
    "wof:placetype":"venue"
},
  "geometry": {"coordinates":[-106.43703499999999,31.762804],"type":"Point"}
}