{
  "type": "Feature",
  "properties": {
    "iso:country":"US",
    "sg:address":"1613 W 6th St Ste C",
    "sg:city":"Austin",
    "sg:classifiers":[
        {
            "category":"Professional",
            "subcategory":"Detective & Security Services",
            "type":"Services"
        }
    ],
    "sg:phone":"+1 512 771 8530",
    "sg:postcode":"78703",
    "sg:province":"TX",
    "sg:tags":[
        "information",
        "bureau"
    ],
    "wof:name":"Curry Organizing Services",
    "wof:placetype":"venue"
},
  "geometry": {"coordinates":[-97.76370199999999,30.275339],"type":"Point"}
}