{
  "type": "Feature",
  "properties": {
    "iso:country":"US",
    "sg:address":"10315 Cliffwood Dr",
    "sg:city":"Houston",
    "sg:classifiers":[
        {
            "category":"Professional",
            "subcategory":"Business Services",
            "type":"Services"
        },
        {
            "category":"Professional",
            "subcategory":"Printing & Photocopies",
            "type":"Services"
        }
    ],
    "sg:phone":"+1 713 721 5275",
    "sg:postcode":"77035",
    "sg:province":"TX",
    "sg:tags":[
        "system",
        "form",
        "printers-business"
    ],
    "wof:name":"Forms Doc",
    "wof:placetype":"venue"
},
  "geometry": {"coordinates":[-95.45495200000001,29.669975],"type":"Point"}
}