{
  "type": "Feature",
  "properties": {
    "iso:country":"US",
    "sg:address":"5220 W Parkway St",
    "sg:city":"Groves",
    "sg:classifiers":[
        {
            "category":"Home & Garden",
            "subcategory":"Building Materials",
            "type":"Retail Goods"
        }
    ],
    "sg:phone":"+1 409 963 1105",
    "sg:postcode":"77619",
    "sg:province":"TX",
    "sg:tags":[
        "glass",
        "window",
        "plate"
    ],
    "wof:name":"Alamo Glass Company",
    "wof:placetype":"venue"
},
  "geometry": {"coordinates":[-93.92897600000001,29.93773],"type":"Point"}
}