{
  "type": "Feature",
  "properties": {
    "iso:country":"US",
    "sg:address":"4017 Dakota Trl",
    "sg:city":"Granbury",
    "sg:classifiers":[
        {
            "category":"Wholesale",
            "subcategory":"Non-durable Goods",
            "type":"Manufacturing & Wholesale Goods"
        }
    ],
    "sg:phone":"+1 817 573 8251",
    "sg:postcode":"76048",
    "sg:province":"TX",
    "wof:name":"Earth Treasures Wholesale",
    "wof:placetype":"venue"
},
  "geometry": {"coordinates":[-97.75877800000001,32.408118],"type":"Point"}
}