{
  "type": "Feature",
  "properties": {
    "iso:country":"US",
    "sg:address":"5619 Babcock Rd",
    "sg:city":"San Antonio",
    "sg:classifiers":[
        {
            "category":"Retail",
            "subcategory":"Auto Repair",
            "type":"Services"
        }
    ],
    "sg:phone":"+1 210 690 8385",
    "sg:postcode":"78240",
    "sg:province":"TX",
    "sg:tags":[
        "exhaust"
    ],
    "wof:name":"American Muffler & Engines",
    "wof:placetype":"venue"
},
  "geometry": {"coordinates":[-98.59641999999999,29.519146],"type":"Point"}
}