{
  "type": "Feature",
  "properties": {
    "iso:country":"US",
    "sg:address":"201 Lincoln St",
    "sg:city":"Deer Park",
    "sg:classifiers":[
        {
            "category":"Bars & Pubs",
            "type":"Food & Drink"
        }
    ],
    "sg:phone":"+1 281 478 5437",
    "sg:postcode":"77536",
    "sg:province":"TX",
    "sg:tags":[
        "drinking"
    ],
    "wof:name":"Best Little Ice House In Texas",
    "wof:placetype":"venue"
},
  "geometry": {"coordinates":[-95.119496,29.671647],"type":"Point"}
}