{
  "type": "Feature",
  "properties": {
    "iso:country":"US",
    "sg:address":"2542 Widgeon Dr",
    "sg:city":"Corpus Christi",
    "sg:classifiers":[
        {
            "category":"Building & Trades",
            "subcategory":"Cleaning & Sanitation",
            "type":"Services"
        }
    ],
    "sg:phone":"+1 361 241 0033",
    "sg:postcode":"78410",
    "sg:province":"TX",
    "sg:tags":[
        "janitor"
    ],
    "wof:name":"Best Quality Office Cleaning",
    "wof:placetype":"venue"
},
  "geometry": {"coordinates":[-97.593259,27.829657],"type":"Point"}
}