{
  "type": "Feature",
  "properties": {
    "iso:country":"US",
    "sg:address":"138 Waxwood Ln",
    "sg:city":"San Antonio",
    "sg:classifiers":[
        {
            "category":"Arts & Performance",
            "subcategory":"Theater",
            "type":"Entertainment"
        }
    ],
    "sg:phone":"+1 210 348 6640",
    "sg:postcode":"78216",
    "sg:province":"TX",
    "sg:tags":[
        "entertainer",
        "business"
    ],
    "wof:name":"Alamo City Paranormal",
    "wof:placetype":"venue"
},
  "geometry": {"coordinates":[-98.48791,29.506753],"type":"Point"}
}