{
  "type": "Feature",
  "properties": {
    "iso:country":"US",
    "sg:address":"4107 Somerset Ct",
    "sg:city":"Grapevine",
    "sg:classifiers":[
        {
            "category":"Professional",
            "subcategory":"Business Services",
            "type":"Services"
        }
    ],
    "sg:phone":"+1 817 481 8577",
    "sg:postcode":"76051",
    "sg:province":"TX",
    "wof:name":"Shoot Out Partners LLC",
    "wof:placetype":"venue"
},
  "geometry": {"coordinates":[-97.118555,32.895786],"type":"Point"}
}