{
  "type": "Feature",
  "properties": {
    "iso:country":"US",
    "sg:address":"112 W Dilley Ave",
    "sg:city":"Laredo",
    "sg:classifiers":[
        {
            "category":"Building & Trades",
            "subcategory":"Construction",
            "type":"Services"
        }
    ],
    "sg:phone":"+1 956 727 2870",
    "sg:postcode":"78016",
    "sg:province":"TX",
    "sg:tags":[
        "contractor"
    ],
    "wof:name":"Cobalt Construction Co",
    "wof:placetype":"venue"
},
  "geometry": {"coordinates":[-98.903779,29.144718],"type":"Point"}
}