{
  "type": "Feature",
  "properties": {
    "iso:country":"US",
    "sg:address":"805 Quitman St",
    "sg:city":"Houston",
    "sg:classifiers":[
        {
            "category":"Shopping",
            "subcategory":"Clothing, Apparel, & Fashions",
            "type":"Retail Goods"
        }
    ],
    "sg:phone":"+1 713 426 0529",
    "sg:postcode":"77009",
    "sg:province":"TX",
    "sg:tags":[
        "shop",
        "bridal"
    ],
    "wof:name":"Dina's Bridal Shop",
    "wof:placetype":"venue"
},
  "geometry": {"coordinates":[-95.36156,29.781688],"type":"Point"}
}