{
  "type": "Feature",
  "properties": {
    "iso:country":"US",
    "sg:address":"7315 Oak Shores Drive",
    "sg:city":"Austin",
    "sg:classifiers":[
        {
            "category":"Insurance",
            "subcategory":"Hazard Insurance",
            "type":"Services"
        }
    ],
    "sg:phone":"+1 512 918 9095",
    "sg:postcode":"78730",
    "sg:province":"TX",
    "wof:name":"Perryman Melissa Jankoski Insurance",
    "wof:placetype":"venue"
},
  "geometry": {"coordinates":[-97.82423300000001,30.341748],"type":"Point"}
}