{
  "type": "Feature",
  "properties": {
    "iso:country":"US",
    "sg:address":"4122 Broadway Blvd",
    "sg:city":"Garland",
    "sg:classifiers":[
        {
            "category":"Restaurant",
            "type":"Food & Drink"
        }
    ],
    "sg:phone":"+1 972 240 6798",
    "sg:postcode":"75043",
    "sg:province":"TX",
    "wof:name":"Sonic Drive-In",
    "wof:placetype":"venue"
},
  "geometry": {"coordinates":[-96.603857,32.863422],"type":"Point"}
}