{
  "type": "Feature",
  "properties": {
    "iso:country":"US",
    "sg:address":"316 Jim Wright Fwy N",
    "sg:city":"Fort Worth",
    "sg:classifiers":[
        {
            "category":"Sports & Exercise",
            "subcategory":"Gym",
            "type":"Entertainment"
        }
    ],
    "sg:phone":"+1 817 246 7855",
    "sg:postcode":"76108",
    "sg:province":"TX",
    "sg:tags":[
        "fitness",
        "physical",
        "facility"
    ],
    "wof:name":"Curves For Women",
    "wof:placetype":"venue"
},
  "geometry": {"coordinates":[-97.47615399999999,32.764094],"type":"Point"}
}