{
  "type": "Feature",
  "properties": {
    "iso:country":"US",
    "sg:address":"2723 81st St",
    "sg:city":"Lubbock",
    "sg:classifiers":[
        {
            "category":"Building & Trades",
            "subcategory":"Construction",
            "type":"Services"
        }
    ],
    "sg:phone":"+1 806 745 9450",
    "sg:postcode":"79423",
    "sg:province":"TX",
    "sg:tags":[
        "nonresidential"
    ],
    "wof:name":"Sandia Construction Inc",
    "wof:placetype":"venue"
},
  "geometry": {"coordinates":[-101.874653,33.520574],"type":"Point"}
}