{
  "type": "Feature",
  "properties": {
    "iso:country":"US",
    "sg:address":"3315 E Lancaster Ave",
    "sg:city":"Fort Worth",
    "sg:classifiers":[
        {
            "category":"Food & Beverages",
            "subcategory":"Groceries & Convenience Stores",
            "type":"Retail Goods"
        }
    ],
    "sg:phone":"+1 817 536 6749",
    "sg:postcode":"76103",
    "sg:province":"TX",
    "wof:name":"E Z Stop Grocery Store",
    "wof:placetype":"venue"
},
  "geometry": {"coordinates":[-97.276659,32.740295],"type":"Point"}
}