{
  "type": "Feature",
  "properties": {
    "iso:country":"US",
    "sg:address":"920 Sandalwood Ave",
    "sg:city":"Richardson",
    "sg:classifiers":[
        {
            "category":"Professional",
            "subcategory":"Management & Consulting",
            "type":"Services"
        }
    ],
    "sg:phone":"+1 972 235 6154",
    "sg:postcode":"75080",
    "sg:province":"TX",
    "sg:tags":[
        "consultant",
        "business"
    ],
    "wof:name":"Sharper Enterprises",
    "wof:placetype":"venue"
},
  "geometry": {"coordinates":[-96.75479199999999,32.975826],"type":"Point"}
}