{
  "type": "Feature",
  "properties": {
    "iso:country":"US",
    "sg:address":"1400 Presidential Dr",
    "sg:city":"Richardson",
    "sg:classifiers":[
        {
            "category":"Utilities",
            "subcategory":"Cable",
            "type":"Services"
        }
    ],
    "sg:phone":"+1 972 480 9600",
    "sg:postcode":"75081",
    "sg:province":"TX",
    "sg:tags":[
        "television"
    ],
    "wof:name":"Cable Plus Inc",
    "wof:placetype":"venue"
},
  "geometry": {"coordinates":[-96.70299900000001,32.964821],"type":"Point"}
}