{
  "type": "Feature",
  "properties": {
    "iso:country":"US",
    "sg:address":"1213 Bunratty Cir",
    "sg:city":"Pflugerville",
    "sg:classifiers":[
        {
            "category":"Home & Garden",
            "subcategory":"Home Furnishings",
            "type":"Retail Goods"
        }
    ],
    "sg:phone":"+1 512 251 7770",
    "sg:postcode":"78660",
    "sg:province":"TX",
    "wof:name":"Ceramic Empire",
    "wof:placetype":"venue"
},
  "geometry": {"coordinates":[-97.639156,30.473221],"type":"Point"}
}