{
  "type": "Feature",
  "properties": {
    "iso:country":"US",
    "sg:address":"2957 Shadow Wood Dr",
    "sg:city":"Dallas",
    "sg:classifiers":[
        {
            "category":"Wholesale",
            "subcategory":"Meat",
            "type":"Manufacturing & Wholesale Goods"
        }
    ],
    "sg:phone":"+1 214 943 0128",
    "sg:postcode":"75224",
    "sg:province":"TX",
    "wof:name":"Freedman Distributors Inc",
    "wof:placetype":"venue"
},
  "geometry": {"coordinates":[-96.835196,32.712231],"type":"Point"}
}