{
  "type": "Feature",
  "properties": {
    "iso:country":"US",
    "sg:address":"3200 S 1st St",
    "sg:city":"Austin",
    "sg:classifiers":[
        {
            "category":"Building & Trades",
            "subcategory":"Equipment Rental",
            "type":"Services"
        }
    ],
    "sg:phone":"+1 512 416 8323",
    "sg:postcode":"78704",
    "sg:province":"TX",
    "sg:tags":[
        "yard"
    ],
    "wof:name":"Universal Trench Shoring",
    "wof:placetype":"venue"
},
  "geometry": {"coordinates":[-97.76573399999999,30.232409],"type":"Point"}
}