{
  "type": "Feature",
  "properties": {
    "iso:country":"US",
    "sg:address":"14740 US Hwy 59",
    "sg:city":"Humble",
    "sg:classifiers":[
        {
            "category":"Wholesale",
            "subcategory":"Machinery & Supplies",
            "type":"Manufacturing & Wholesale Goods"
        }
    ],
    "sg:phone":"+1 281 441 8991",
    "sg:postcode":"77396",
    "sg:province":"TX",
    "sg:tags":[
        "equipment",
        "industrial"
    ],
    "wof:name":"Schiller Service Corporation",
    "wof:placetype":"venue"
},
  "geometry": {"coordinates":[-95.29907,29.932708],"type":"Point"}
}