{
  "type": "Feature",
  "properties": {
    "iso:country":"US",
    "sg:address":"2312 Long Ridge Ln",
    "sg:city":"Arlington",
    "sg:classifiers":[
        {
            "category":"Shopping",
            "subcategory":"Discount & Variety Stores",
            "type":"Retail Goods"
        }
    ],
    "sg:phone":"+1 817 275 3503",
    "sg:postcode":"76014",
    "sg:province":"TX",
    "sg:tags":[
        "merchandise",
        "general"
    ],
    "wof:name":"Randy Brown",
    "wof:placetype":"venue"
},
  "geometry": {"coordinates":[-97.110028,32.705871],"type":"Point"}
}