{
  "type": "Feature",
  "properties": {
    "iso:country":"US",
    "sg:address":"6724 Eastridge Dr",
    "sg:city":"Dallas",
    "sg:classifiers":[
        {
            "category":"Health Services",
            "subcategory":"Clinic",
            "type":"Services"
        }
    ],
    "sg:phone":"+1 214 692 1948",
    "sg:postcode":"75231",
    "sg:province":"TX",
    "wof:name":"So Medical",
    "wof:placetype":"venue"
},
  "geometry": {"coordinates":[-96.75058199999999,32.86719],"type":"Point"}
}