{
  "type": "Feature",
  "properties": {
    "iso:country":"US",
    "sg:address":"900 N Grand Ave",
    "sg:city":"Sherman",
    "sg:classifiers":[
        {
            "category":"Education",
            "subcategory":"Library",
            "type":"Public Place"
        }
    ],
    "sg:phone":"+1 903 813 2556",
    "sg:postcode":"75090",
    "sg:province":"TX",
    "wof:name":"Abell Library",
    "wof:placetype":"venue"
},
  "geometry": {"coordinates":[-96.59524500000001,33.648761],"type":"Point"}
}