{
  "type": "Feature",
  "properties": {
    "iso:country":"US",
    "sg:address":"3105 Clearview Dr",
    "sg:city":"San Angelo",
    "sg:classifiers":[
        {
            "category":"Manufacturing",
            "subcategory":"Signs",
            "type":"Manufacturing & Wholesale Goods"
        }
    ],
    "sg:phone":"+1 325 949 0953",
    "sg:postcode":"76904",
    "sg:province":"TX",
    "wof:name":"Stork For Rent",
    "wof:placetype":"venue"
},
  "geometry": {"coordinates":[-100.491004,31.409272],"type":"Point"}
}