{
  "type": "Feature",
  "properties": {
    "iso:country":"US",
    "sg:address":"5090 Richmond Ave",
    "sg:city":"Houston",
    "sg:classifiers":[
        {
            "category":"Professional",
            "subcategory":"Management & Consulting",
            "type":"Services"
        }
    ],
    "sg:phone":"+1 713 478 6367",
    "sg:postcode":"77056",
    "sg:province":"TX",
    "sg:tags":[
        "technology",
        "holding"
    ],
    "wof:name":"Invenire Inc",
    "wof:placetype":"venue"
},
  "geometry": {"coordinates":[-95.463949,29.731866],"type":"Point"}
}