{
  "type": "Feature",
  "properties": {
    "iso:country":"US",
    "sg:address":"1620 S Zapata Hwy",
    "sg:city":"Laredo",
    "sg:classifiers":[
        {
            "category":"Autos & Motor Vehicles",
            "subcategory":"Auto Supplies",
            "type":"Retail Goods"
        }
    ],
    "sg:phone":"+1 956 726 3701",
    "sg:postcode":"78046",
    "sg:province":"TX",
    "sg:tags":[
        "automobile",
        "parts"
    ],
    "wof:name":"Gonzalez Auto Parts Inc",
    "wof:placetype":"venue"
},
  "geometry": {"coordinates":[-99.47255800000001,27.482475],"type":"Point"}
}