{
  "type": "Feature",
  "properties": {
    "iso:country":"US",
    "sg:address":"2255 Ridge Rd",
    "sg:city":"Rockwall",
    "sg:classifiers":[
        {
            "category":"Banks & Credit Unions",
            "subcategory":"Investment Brokerage",
            "type":"Services"
        }
    ],
    "sg:phone":"+1 469 698 8500",
    "sg:postcode":"75032",
    "sg:province":"TX",
    "wof:name":"RRG Investments",
    "wof:placetype":"venue"
},
  "geometry": {"coordinates":[-96.467923,32.900192],"type":"Point"}
}