{
  "type": "Feature",
  "properties": {
    "iso:country":"US",
    "sg:address":"1428 W Alabama St",
    "sg:city":"Houston",
    "sg:classifiers":[
        {
            "category":"Professional",
            "type":"Services"
        }
    ],
    "sg:phone":"+1 713 942 7337",
    "sg:postcode":"77006",
    "sg:province":"TX",
    "wof:name":"Focus Inside",
    "wof:placetype":"venue"
},
  "geometry": {"coordinates":[-95.397052,29.738791],"type":"Point"}
}