{
  "type": "Feature",
  "properties": {
    "iso:country":"US",
    "sg:address":"7920 San Felipe Blvd",
    "sg:city":"Austin",
    "sg:classifiers":[
        {
            "category":"Professional",
            "subcategory":"Art Services",
            "type":"Services"
        }
    ],
    "sg:phone":"+1 512 335 3705",
    "sg:postcode":"78729",
    "sg:province":"TX",
    "sg:tags":[
        "graphic",
        "designer"
    ],
    "wof:name":"Glendenning Design",
    "wof:placetype":"venue"
},
  "geometry": {"coordinates":[-97.769865,30.438352],"type":"Point"}
}