{
  "type": "Feature",
  "properties": {
    "iso:country":"US",
    "sg:address":"1601 Weyland Dr",
    "sg:city":"Fort Worth",
    "sg:classifiers":[
        {
            "category":"Real Estate",
            "subcategory":"Real Estate Operator",
            "type":"Services"
        }
    ],
    "sg:phone":"+1 817 498 8000",
    "sg:postcode":"76180",
    "sg:province":"TX",
    "sg:tags":[
        "building",
        "apartment"
    ],
    "wof:name":"Remington Oaks Apartments",
    "wof:placetype":"venue"
},
  "geometry": {"coordinates":[-97.19502199999999,32.839968],"type":"Point"}
}