{
  "type": "Feature",
  "properties": {
    "iso:country":"US",
    "sg:address":"6520 Tyree St",
    "sg:city":"Dallas",
    "sg:classifiers":[
        {
            "category":"Local Transit",
            "type":"Transportation"
        }
    ],
    "sg:phone":"+1 214 435 7508",
    "sg:postcode":"75209",
    "sg:province":"TX",
    "wof:name":"Benjamin Knox",
    "wof:placetype":"venue"
},
  "geometry": {"coordinates":[-96.832165,32.838068],"type":"Point"}
}