{
  "type": "Feature",
  "properties": {
    "iso:country":"US",
    "sg:address":"2400 Perryland Dr",
    "sg:city":"Arlington",
    "sg:classifiers":[
        {
            "category":"Farming",
            "subcategory":"Livestock Farm",
            "type":"Manufacturing & Wholesale Goods"
        }
    ],
    "sg:phone":"+1 817 303 1300",
    "sg:postcode":"76013",
    "sg:province":"TX",
    "sg:tags":[
        "animal",
        "general"
    ],
    "wof:name":"Double R Bar Ranch Inc",
    "wof:placetype":"venue"
},
  "geometry": {"coordinates":[-97.148488,32.713507],"type":"Point"}
}