{
  "type": "Feature",
  "properties": {
    "iso:country":"US",
    "sg:address":"1800 Bomar St",
    "sg:city":"Marshall",
    "sg:classifiers":[
        {
            "category":"Personal",
            "subcategory":"Beauty Salon",
            "type":"Services"
        }
    ],
    "sg:phone":"+1 903 927 2742",
    "sg:postcode":"75670",
    "sg:province":"TX",
    "sg:tags":[
        "shop"
    ],
    "wof:name":"Athenas Hair Salon",
    "wof:placetype":"venue"
},
  "geometry": {"coordinates":[-94.371268,32.52947],"type":"Point"}
}