{
  "type": "Feature",
  "properties": {
    "iso:country":"US",
    "sg:address":"2607 Finney Vallet Rd",
    "sg:city":"Rosenberg",
    "sg:classifiers":[
        {
            "category":"Farming",
            "subcategory":"Farm",
            "type":"Manufacturing & Wholesale Goods"
        }
    ],
    "sg:phone":"+1 281 344 9349",
    "sg:postcode":"77471",
    "sg:province":"TX",
    "sg:tags":[
        "crop",
        "general"
    ],
    "wof:name":"Angelina Farms",
    "wof:placetype":"venue"
},
  "geometry": {"coordinates":[-95.853723,29.486843],"type":"Point"}
}