{
  "type": "Feature",
  "properties": {
    "iso:country":"US",
    "sg:address":"6410 Fannin St Ste 450",
    "sg:city":"Houston",
    "sg:classifiers":[
        {
            "category":"Health Services",
            "subcategory":"Doctor",
            "type":"Services"
        }
    ],
    "sg:phone":"+1 832 325 7222",
    "sg:postcode":"77030",
    "sg:province":"TX",
    "wof:name":"Estrada-Y-Martin Rosa MD",
    "wof:placetype":"venue"
},
  "geometry": {"coordinates":[-95.39727499999999,29.714409],"type":"Point"}
}