{
  "type": "Feature",
  "properties": {
    "iso:country":"US",
    "sg:address":"2700 Via Fortuna",
    "sg:city":"Austin",
    "sg:classifiers":[
        {
            "category":"Professional",
            "subcategory":"Engineering",
            "type":"Services"
        }
    ],
    "sg:phone":"+1 512 891 3000",
    "sg:postcode":"78746",
    "sg:province":"TX",
    "sg:tags":[
        "engineer"
    ],
    "wof:name":"CFX LP",
    "wof:placetype":"venue"
},
  "geometry": {"coordinates":[-97.800527,30.255421],"type":"Point"}
}