{
  "type": "Feature",
  "properties": {
    "iso:country":"US",
    "sg:address":"10901 Ranchstone Dr",
    "sg:city":"Houston",
    "sg:classifiers":[
        {
            "category":"Wholesale",
            "subcategory":"Non-durable Goods",
            "type":"Manufacturing & Wholesale Goods"
        }
    ],
    "sg:phone":"+1 281 890 8661",
    "sg:postcode":"77064",
    "sg:province":"TX",
    "wof:name":"Paracas Trading LLC",
    "wof:placetype":"venue"
},
  "geometry": {"coordinates":[-95.58000199999999,29.910793],"type":"Point"}
}