{
  "type": "Feature",
  "properties": {
    "iso:country":"US",
    "sg:address":"833 Co Rd 583",
    "sg:city":"La Coste",
    "sg:classifiers":[
        {
            "category":"Food & Beverages",
            "subcategory":"Meat & Fish",
            "type":"Retail Goods"
        }
    ],
    "sg:phone":"+1 830 762 3200",
    "sg:postcode":"78039",
    "sg:province":"TX",
    "sg:tags":[
        "seafood"
    ],
    "wof:name":"Automated Shrimp Corp",
    "wof:placetype":"venue"
},
  "geometry": {"coordinates":[-98.82719400000001,29.290339],"type":"Point"}
}