{
  "type": "Feature",
  "properties": {
    "iso:country":"US",
    "sg:address":"2916 Bayport Blvd",
    "sg:city":"Seabrook",
    "sg:classifiers":[
        {
            "category":"Home & Garden",
            "subcategory":"Home Furnishings",
            "type":"Retail Goods"
        },
        {
            "category":"Commercial Area",
            "type":"Public Place"
        },
        {
            "category":"Manufacturing",
            "subcategory":"Glass & Minerals",
            "type":"Manufacturing & Wholesale Goods"
        },
        {
            "category":"Manufacturing",
            "subcategory":"Building Materials",
            "type":"Manufacturing & Wholesale Goods"
        },
        {
            "category":"Building & Trades",
            "subcategory":"Construction",
            "type":"Services"
        }
    ],
    "sg:phone":"+1 281 291 8120",
    "sg:postcode":"77586",
    "sg:province":"TX",
    "sg:tags":[
        "plate",
        "installation",
        "repair",
        "windows-repair",
        "top",
        "window",
        "shower",
        "glass-auto",
        "mirror",
        "front",
        "door",
        "replacement",
        "enclosure",
        "store",
        "furniture"
    ],
    "sg:website":"http://www.proglasscompany.com",
    "wof:name":"ProGlass",
    "wof:placetype":"venue"
},
  "geometry": {"coordinates":[-95.028069,29.577435],"type":"Point"}
}