{
  "type": "Feature",
  "properties": {
    "iso:country":"US",
    "sg:address":"5150 Grisham Dr",
    "sg:city":"Rowlett",
    "sg:classifiers":[
        {
            "category":"Home & Garden",
            "subcategory":"Furniture",
            "type":"Retail Goods"
        }
    ],
    "sg:phone":"+1 972 412 0152",
    "sg:postcode":"75088",
    "sg:province":"TX",
    "sg:tags":[
        "store"
    ],
    "wof:name":"Interior Concepts",
    "wof:placetype":"venue"
},
  "geometry": {"coordinates":[-96.58237200000001,32.906292],"type":"Point"}
}