{
  "type": "Feature",
  "properties": {
    "iso:country":"US",
    "sg:address":"6704 Cuesta Trl",
    "sg:city":"Austin",
    "sg:classifiers":[
        {
            "category":"Freight",
            "type":"Transportation"
        }
    ],
    "sg:phone":"+1 512 450 0954",
    "sg:postcode":"78730",
    "sg:province":"TX",
    "sg:tags":[
        "trucking"
    ],
    "wof:name":"James Brooks Newbill",
    "wof:placetype":"venue"
},
  "geometry": {"coordinates":[-97.81488899999999,30.379234],"type":"Point"}
}