{
  "type": "Feature",
  "properties": {
    "iso:country":"US",
    "sg:address":"507 E Sabine St",
    "sg:city":"Victoria",
    "sg:classifiers":[
        {
            "category":"Restaurant",
            "type":"Food & Drink"
        }
    ],
    "sg:phone":"+1 361 578 3032",
    "sg:postcode":"77901",
    "sg:province":"TX",
    "sg:tags":[
        "eating",
        "merchandise"
    ],
    "wof:name":"Reddy Ice",
    "wof:placetype":"venue"
},
  "geometry": {"coordinates":[-96.99881999999999,28.812145],"type":"Point"}
}