{
  "type": "Feature",
  "properties": {
    "iso:country":"US",
    "sg:address":"735 Lum Ave",
    "sg:city":"Corpus Christi",
    "sg:classifiers":[
        {
            "category":"Restaurant",
            "type":"Food & Drink"
        }
    ],
    "sg:phone":"+1 361 992 0626",
    "sg:postcode":"78412",
    "sg:province":"TX",
    "sg:tags":[
        "eating"
    ],
    "wof:name":"Church's Chicken",
    "wof:placetype":"venue"
},
  "geometry": {"coordinates":[-97.36238299999999,27.719108],"type":"Point"}
}