{
  "type": "Feature",
  "properties": {
    "iso:country":"US",
    "sg:address":"8520 Prairie Rose Ln",
    "sg:city":"Fort Worth",
    "sg:classifiers":[
        {
            "category":"Travel",
            "subcategory":"Hotels & Motels",
            "type":"Entertainment"
        }
    ],
    "sg:phone":"+1 817 370 8588",
    "sg:postcode":"76123",
    "sg:province":"TX",
    "sg:website":"www.catchacruise.com",
    "wof:name":"CRUISEONE FORT WORTH",
    "wof:placetype":"venue"
},
  "geometry": {"coordinates":[-97.37186800000001,32.618559],"type":"Point"}
}