{
  "type": "Feature",
  "properties": {
    "iso:country":"US",
    "sg:address":"1726 Commerce St",
    "sg:city":"Garland",
    "sg:classifiers":[
        {
            "category":"Manufacturing",
            "subcategory":"Chemicals & Compounds",
            "type":"Manufacturing & Wholesale Goods"
        }
    ],
    "sg:phone":"+1 972 272 7337",
    "sg:postcode":"75040",
    "sg:province":"TX",
    "sg:tags":[
        "preparation",
        "laboratory",
        "testing",
        "mfg"
    ],
    "wof:name":"Universal Laboratory",
    "wof:placetype":"venue"
},
  "geometry": {"coordinates":[-96.605678,32.908654],"type":"Point"}
}