{
  "type": "Feature",
  "properties": {
    "iso:country":"US",
    "sg:address":"302 S Main St",
    "sg:city":"Henderson",
    "sg:classifiers":[
        {
            "category":"Shopping",
            "subcategory":"Computers & Home Electronics",
            "type":"Retail Goods"
        }
    ],
    "sg:phone":"+1 903 657 5751",
    "sg:postcode":"75654",
    "sg:province":"TX",
    "sg:tags":[
        "equipment",
        "dealer"
    ],
    "wof:name":"Laptops For Less",
    "wof:placetype":"venue"
},
  "geometry": {"coordinates":[-94.79960699999999,32.151074],"type":"Point"}
}