{
  "type": "Feature",
  "properties": {
    "iso:country":"US",
    "sg:address":"7237 San Pedro Ave",
    "sg:city":"San Antonio",
    "sg:classifiers":[
        {
            "category":"Restaurant",
            "type":"Food & Drink"
        }
    ],
    "sg:phone":"+1 210 541 8200",
    "sg:postcode":"78216",
    "sg:province":"TX",
    "wof:name":"El Pollo Loco",
    "wof:placetype":"venue"
},
  "geometry": {"coordinates":[-98.49934,29.514732],"type":"Point"}
}