{
  "type": "Feature",
  "properties": {
    "iso:country":"US",
    "sg:address":"1107 N Meadow Lake Ave",
    "sg:city":"Odessa",
    "sg:classifiers":[
        {
            "category":"Freight",
            "type":"Transportation"
        }
    ],
    "sg:phone":"+1 432 530 2505",
    "sg:postcode":"79763",
    "sg:province":"TX",
    "sg:tags":[
        "local",
        "storage",
        "trucking"
    ],
    "wof:name":"Affordable Movers",
    "wof:placetype":"venue"
},
  "geometry": {"coordinates":[-102.480047,31.827645],"type":"Point"}
}