{
  "type": "Feature",
  "properties": {
    "iso:country":"US",
    "sg:address":"2212 Oceanside Dr",
    "sg:city":"El Paso",
    "sg:classifiers":[
        {
            "category":"Wholesale",
            "subcategory":"Groceries",
            "type":"Manufacturing & Wholesale Goods"
        }
    ],
    "sg:phone":"+1 915 591 0685",
    "sg:postcode":"79936",
    "sg:province":"TX",
    "wof:name":"Danielle M Bengtson",
    "wof:placetype":"venue"
},
  "geometry": {"coordinates":[-106.308261,31.774774],"type":"Point"}
}