{
  "type": "Feature",
  "properties": {
    "iso:country":"US",
    "sg:address":"10800 Roark Rd",
    "sg:city":"Houston",
    "sg:classifiers":[
        {
            "category":"Recreation",
            "subcategory":"Amusement Park",
            "type":"Entertainment"
        },
        {
            "category":"Sports & Exercise",
            "subcategory":"Sports Center",
            "type":"Entertainment"
        }
    ],
    "sg:phone":"+1 281 495 0660",
    "sg:postcode":"77099",
    "sg:province":"TX",
    "sg:tags":[
        "amateur",
        "team"
    ],
    "sg:website":"www.autobanhmotorsports.com",
    "wof:name":"Autobanh Motor Sports",
    "wof:placetype":"venue"
},
  "geometry": {"coordinates":[-95.559814,29.662947],"type":"Point"}
}