{
  "type": "Feature",
  "properties": {
    "iso:country":"US",
    "sg:address":"909 N Jackson Rd",
    "sg:city":"Mcallen",
    "sg:classifiers":[
        {
            "category":"Professional",
            "subcategory":"Credit Reporting & Collection",
            "type":"Services"
        }
    ],
    "sg:phone":"+1 956 668 0332",
    "sg:postcode":"78501",
    "sg:province":"TX",
    "sg:tags":[
        "repair"
    ],
    "wof:name":"Fix Credit U S A",
    "wof:placetype":"venue"
},
  "geometry": {"coordinates":[-98.202522,26.208586],"type":"Point"}
}