{
  "type": "Feature",
  "properties": {
    "iso:country":"US",
    "sg:address":"4965 Co Rd 344",
    "sg:city":"Oglesby",
    "sg:classifiers":[
        {
            "category":"Manufacturing",
            "subcategory":"Tools & Machinery",
            "type":"Manufacturing & Wholesale Goods"
        }
    ],
    "sg:phone":"+1 254 456 2552",
    "sg:postcode":"76561",
    "sg:province":"TX",
    "sg:tags":[
        "machine",
        "shop",
        "jobbing",
        "repair"
    ],
    "wof:name":"McKown Machine & Welding",
    "wof:placetype":"venue"
},
  "geometry": {"coordinates":[-97.53096499999999,31.361623],"type":"Point"}
}