{
  "type": "Feature",
  "properties": {
    "iso:country":"US",
    "sg:address":"2320 Ave K",
    "sg:city":"Bay City",
    "sg:classifiers":[
        {
            "category":"Social Services",
            "type":"Services"
        }
    ],
    "sg:phone":"+1 979 244 4447",
    "sg:postcode":"77414",
    "sg:province":"TX",
    "sg:tags":[
        "youth",
        "organization",
        "center"
    ],
    "wof:name":"Girls In Scouting",
    "wof:placetype":"venue"
},
  "geometry": {"coordinates":[-95.963936,28.980831],"type":"Point"}
}