{
  "type": "Feature",
  "properties": {
    "iso:country":"US",
    "sg:address":"7227 Antoine Dr Ste 5",
    "sg:city":"Houston",
    "sg:classifiers":[
        {
            "category":"Personal",
            "subcategory":"Nail Salon",
            "type":"Services"
        }
    ],
    "sg:phone":"+1 281 445 0922",
    "sg:postcode":"77088",
    "sg:province":"TX",
    "wof:name":"Tee Dee Nail Salon",
    "wof:placetype":"venue"
},
  "geometry": {"coordinates":[-95.473,29.865999],"type":"Point"}
}