{
  "type": "Feature",
  "properties": {
    "iso:country":"US",
    "sg:address":"15903 Morley Dr",
    "sg:city":"Cypress",
    "sg:classifiers":[
        {
            "category":"Retail",
            "subcategory":"Auto Repair",
            "type":"Services"
        }
    ],
    "sg:phone":"+1 281 373 0141",
    "sg:postcode":"77429",
    "sg:province":"TX",
    "sg:tags":[
        "automotive",
        "towing"
    ],
    "wof:name":"Rlp Wrecker Service",
    "wof:placetype":"venue"
},
  "geometry": {"coordinates":[-95.65922999999999,29.948196],"type":"Point"}
}