{
  "type": "Feature",
  "properties": {
    "iso:country":"US",
    "sg:address":"9091 Co Rd 456",
    "sg:city":"Brownwood",
    "sg:classifiers":[
        {
            "category":"Insurance",
            "subcategory":"Insurance Agent",
            "type":"Services"
        }
    ],
    "sg:phone":"+1 325 784 9800",
    "sg:postcode":"76801",
    "sg:province":"TX",
    "wof:name":"Royal Neighbors Of America",
    "wof:placetype":"venue"
},
  "geometry": {"coordinates":[-99.110258,31.835672],"type":"Point"}
}