{
  "type": "Feature",
  "properties": {
    "iso:country":"US",
    "sg:address":"1010 Sycamore St",
    "sg:city":"Lake Jackson",
    "sg:classifiers":[
        {
            "category":"Manufacturing",
            "subcategory":"Metals",
            "type":"Manufacturing & Wholesale Goods"
        },
        {
            "category":"Wholesale",
            "subcategory":"Hardware",
            "type":"Manufacturing & Wholesale Goods"
        }
    ],
    "sg:phone":"+1 979 297 1920",
    "sg:postcode":"77566",
    "sg:province":"TX",
    "sg:tags":[
        "fastener"
    ],
    "wof:name":"Pinnacle Fastener Corp",
    "wof:placetype":"venue"
},
  "geometry": {"coordinates":[-95.427995,29.019913],"type":"Point"}
}