{
  "type": "Feature",
  "properties": {
    "iso:country":"US",
    "sg:address":"7111 S Ww White Rd",
    "sg:city":"San Antonio",
    "sg:classifiers":[
        {
            "category":"Home & Garden",
            "subcategory":"Mobile Homes",
            "type":"Retail Goods"
        }
    ],
    "sg:phone":"+1 210 648 4275",
    "sg:postcode":"78222",
    "sg:province":"TX",
    "wof:name":"Harper Enterprises",
    "wof:placetype":"venue"
},
  "geometry": {"coordinates":[-98.39655399999999,29.34851],"type":"Point"}
}