{
  "type": "Feature",
  "properties": {
    "iso:country":"US",
    "sg:address":"5525 FM 1488",
    "sg:city":"Magnolia",
    "sg:classifiers":[
        {
            "category":"Wholesale",
            "subcategory":"Fruits & Vegetables",
            "type":"Manufacturing & Wholesale Goods"
        }
    ],
    "sg:phone":"+1 281 259 5133",
    "sg:postcode":"77384",
    "sg:province":"TX",
    "wof:name":"Montgomery County Farmers Mark",
    "wof:placetype":"venue"
},
  "geometry": {"coordinates":[-95.489853,30.233082],"type":"Point"}
}