{
  "type": "Feature",
  "properties": {
    "iso:country":"US",
    "sg:address":"3102 S Closner Blvd",
    "sg:city":"Edinburg",
    "sg:classifiers":[
        {
            "category":"Government",
            "subcategory":"Office",
            "type":"Public Place"
        }
    ],
    "sg:phone":"+1 956 292 2133",
    "sg:postcode":"78540",
    "sg:province":"TX",
    "sg:tags":[
        "village"
    ],
    "wof:name":"Edinburg Recycling Ctr",
    "wof:placetype":"venue"
},
  "geometry": {"coordinates":[-98.17148899999999,26.269123],"type":"Point"}
}