{
  "type": "Feature",
  "properties": {
    "iso:country":"US",
    "sg:address":"1417 Nogalitos St",
    "sg:city":"San Antonio",
    "sg:classifiers":[
        {
            "category":"Home & Garden",
            "subcategory":"Furniture",
            "type":"Retail Goods"
        }
    ],
    "sg:phone":"+1 210 299 4700",
    "sg:postcode":"78204",
    "sg:province":"TX",
    "wof:name":"Garza's Furniture",
    "wof:placetype":"venue"
},
  "geometry": {"coordinates":[-98.51272899999999,29.399411],"type":"Point"}
}