{
  "type": "Feature",
  "properties": {
    "iso:country":"US",
    "sg:address":"120 Co Rd 877",
    "sg:city":"Princeton",
    "sg:classifiers":[
        {
            "category":"Professional",
            "subcategory":"Advertising",
            "type":"Services"
        }
    ],
    "sg:phone":"+1 469 667 2553",
    "sg:postcode":"75407",
    "sg:province":"TX",
    "sg:tags":[
        "mobile",
        "billboard"
    ],
    "wof:name":"Mobile Billboards",
    "wof:placetype":"venue"
},
  "geometry": {"coordinates":[-96.48911,33.133249],"type":"Point"}
}