{
  "type": "Feature",
  "properties": {
    "iso:country":"US",
    "sg:address":"1261 N Greenbrier Rd",
    "sg:city":"Nocona",
    "sg:classifiers":[
        {
            "category":"Retail",
            "subcategory":"Auto Repair",
            "type":"Services"
        }
    ],
    "sg:phone":"+1 940 825 6890",
    "sg:postcode":"76255",
    "sg:province":"TX",
    "sg:tags":[
        "body",
        "painting",
        "repairing",
        "automobile"
    ],
    "wof:name":"Kfr Auto Craft",
    "wof:placetype":"venue"
},
  "geometry": {"coordinates":[-97.68888200000001,33.781593],"type":"Point"}
}