{
  "type": "Feature",
  "properties": {
    "iso:country":"US",
    "sg:address":"501 Fuller St",
    "sg:city":"Arlington",
    "sg:classifiers":[
        {
            "category":"Real Estate",
            "subcategory":"Real Estate Operator",
            "type":"Services"
        }
    ],
    "sg:phone":"+1 817 265 1400",
    "sg:postcode":"76011",
    "sg:province":"TX",
    "sg:tags":[
        "apartment"
    ],
    "wof:name":"Sawyer's Mill Apartments",
    "wof:placetype":"venue"
},
  "geometry": {"coordinates":[-97.11403199999999,32.74706],"type":"Point"}
}