{
  "type": "Feature",
  "properties": {
    "iso:country":"US",
    "sg:address":"6727 Fellowood St",
    "sg:city":"San Antonio",
    "sg:classifiers":[
        {
            "category":"Building & Trades",
            "subcategory":"Construction",
            "type":"Services"
        }
    ],
    "sg:phone":"+1 210 767 1228",
    "sg:postcode":"78238",
    "sg:province":"TX",
    "sg:tags":[
        "floor",
        "laying",
        "contractor"
    ],
    "wof:name":"Lifestile Flooring",
    "wof:placetype":"venue"
},
  "geometry": {"coordinates":[-98.63507799999999,29.496955],"type":"Point"}
}