{
  "type": "Feature",
  "properties": {
    "iso:country":"US",
    "sg:address":"4010 W Marshall Ave",
    "sg:city":"Longview",
    "sg:classifiers":[
        {
            "category":"Professional",
            "subcategory":"Accounting & Tax Preparation",
            "type":"Services"
        }
    ],
    "sg:phone":"+1 903 295 9376",
    "sg:postcode":"75604",
    "sg:province":"TX",
    "sg:tags":[
        "bookkeeping",
        "general"
    ],
    "wof:name":"Reeves WEBB & Assoc",
    "wof:placetype":"venue"
},
  "geometry": {"coordinates":[-94.797974,32.507217],"type":"Point"}
}