{
  "type": "Feature",
  "properties": {
    "iso:country":"US",
    "sg:address":"3823 Bee Caves Rd",
    "sg:city":"Austin",
    "sg:classifiers":[
        {
            "category":"Real Estate",
            "subcategory":"Surveying",
            "type":"Services"
        }
    ],
    "sg:phone":"+1 512 328 8373",
    "sg:postcode":"78746",
    "sg:province":"TX",
    "sg:tags":[
        "firm",
        "planning",
        "land"
    ],
    "wof:name":"Terra Firma",
    "wof:placetype":"venue"
},
  "geometry": {"coordinates":[-97.808553,30.281257],"type":"Point"}
}