{
  "type": "Feature",
  "properties": {
    "iso:country":"US",
    "sg:address":"1422 Hampton Rd",
    "sg:city":"Grapevine",
    "sg:classifiers":[
        {
            "category":"Personal",
            "type":"Services"
        }
    ],
    "sg:phone":"+1 817 481 4618",
    "sg:postcode":"76051",
    "sg:province":"TX",
    "wof:name":"Tropical Palms",
    "wof:placetype":"venue"
},
  "geometry": {"coordinates":[-97.092078,32.95152],"type":"Point"}
}