{
  "type": "Feature",
  "properties": {
    "iso:country":"US",
    "sg:address":"204 Chaparral Ct",
    "sg:city":"Southlake",
    "sg:classifiers":[
        {
            "category":"Organizations",
            "subcategory":"Religious Organization",
            "type":"Services"
        }
    ],
    "sg:phone":"+1 817 421 9025",
    "sg:postcode":"76092",
    "sg:province":"TX",
    "wof:name":"Christian Outreach",
    "wof:placetype":"venue"
},
  "geometry": {"coordinates":[-97.12339,32.979763],"type":"Point"}
}