{
  "type": "Feature",
  "properties": {
    "iso:country":"US",
    "sg:address":"14860 Montfort Dr",
    "sg:city":"Dallas",
    "sg:classifiers":[
        {
            "category":"Autos & Motor Vehicles",
            "subcategory":"Auto Supplies",
            "type":"Retail Goods"
        }
    ],
    "sg:phone":"+1 972 960 7944",
    "sg:postcode":"75254",
    "sg:province":"TX",
    "wof:name":"Gunter Ring Inv Partners LP",
    "wof:placetype":"venue"
},
  "geometry": {"coordinates":[-96.81827699999999,32.950804],"type":"Point"}
}