{
  "type": "Feature",
  "properties": {
    "iso:country":"US",
    "sg:address":"906 S Center St",
    "sg:city":"Grand Prairie",
    "sg:classifiers":[
        {
            "category":"Professional",
            "type":"Services"
        }
    ],
    "sg:phone":"+1 972 264 8007",
    "sg:postcode":"75051",
    "sg:province":"TX",
    "wof:name":"Michael Maas",
    "wof:placetype":"venue"
},
  "geometry": {"coordinates":[-97.003801,32.731978],"type":"Point"}
}