{
  "type": "Feature",
  "properties": {
    "iso:country":"US",
    "sg:address":"9207 Stroud Dr",
    "sg:city":"Houston",
    "sg:classifiers":[
        {
            "category":"Social Services",
            "subcategory":"Child Care",
            "type":"Services"
        }
    ],
    "sg:phone":"+1 713 772 9742",
    "sg:postcode":"77036",
    "sg:province":"TX",
    "wof:name":"Huang LI Hua",
    "wof:placetype":"venue"
},
  "geometry": {"coordinates":[-95.54710900000001,29.700368],"type":"Point"}
}