{
  "type": "Feature",
  "properties": {
    "iso:country":"US",
    "sg:address":"141 Live Oak St",
    "sg:city":"Azle",
    "sg:classifiers":[
        {
            "category":"Building & Trades",
            "subcategory":"Landscaping Services",
            "type":"Services"
        }
    ],
    "sg:phone":"+1 817 444 6705",
    "sg:postcode":"76020",
    "sg:province":"TX",
    "sg:tags":[
        "landscape"
    ],
    "wof:name":"Horizon Landscape",
    "wof:placetype":"venue"
},
  "geometry": {"coordinates":[-97.580834,32.909199],"type":"Point"}
}