{
  "type": "Feature",
  "properties": {
    "iso:country":"US",
    "sg:address":"15810 Midway Rd",
    "sg:city":"Addison",
    "sg:classifiers":[
        {
            "category":"Health Services",
            "subcategory":"Health Practitioner",
            "type":"Services"
        }
    ],
    "sg:phone":"+1 972 458 7238",
    "sg:postcode":"75001",
    "sg:province":"TX",
    "sg:tags":[
        "occupational",
        "safety"
    ],
    "wof:name":"Occupational Health Ctr",
    "wof:placetype":"venue"
},
  "geometry": {"coordinates":[-96.83846200000001,32.964559],"type":"Point"}
}