{
  "type": "Feature",
  "properties": {
    "iso:country":"US",
    "sg:address":"805 Park St",
    "sg:city":"Beaumont",
    "sg:classifiers":[
        {
            "category":"Professional",
            "subcategory":"Lawyer & Legal Services",
            "type":"Services"
        }
    ],
    "sg:phone":"+1 409 839 4511",
    "sg:postcode":"77701",
    "sg:province":"TX",
    "sg:tags":[
        "information",
        "attorney",
        "referral",
        "plan"
    ],
    "wof:name":"Charlton P Hornsby Pc",
    "wof:placetype":"venue"
},
  "geometry": {"coordinates":[-94.097741,30.079699],"type":"Point"}
}