{
  "type": "Feature",
  "properties": {
    "iso:country":"US",
    "sg:address":"101 W Airport Fwy",
    "sg:city":"Irving",
    "sg:classifiers":[
        {
            "category":"Restaurant",
            "type":"Food & Drink"
        }
    ],
    "sg:menulink":"http://www.allmenus.com/tx/southwest/193480-taco-bell/menu/",
    "sg:postcode":"75062",
    "sg:province":"TX",
    "sg:tags":[
        "mexican"
    ],
    "wof:name":"Taco Bell",
    "wof:placetype":"venue"
},
  "geometry": {"coordinates":[-96.944451,32.837161],"type":"Point"}
}