{
  "type": "Feature",
  "properties": {
    "iso:country":"US",
    "sg:address":"1701 Carter Dr",
    "sg:city":"Brownfield",
    "sg:phone":"+1 806 637 2664",
    "sg:postcode":"79316",
    "sg:province":"TX",
    "sg:tags":[
        "farm",
        "field",
        "crop"
    ],
    "wof:name":"Martin James",
    "wof:placetype":"venue"
},
  "geometry": {"coordinates":[-102.247473,33.173268],"type":"Point"}
}