{
  "type": "Feature",
  "properties": {
    "iso:country":"US",
    "sg:address":"546 Lindner Ave",
    "sg:city":"Comfort",
    "sg:classifiers":[
        {
            "category":"Retail",
            "subcategory":"Auto Repair",
            "type":"Services"
        }
    ],
    "sg:phone":"+1 830 995 3881",
    "sg:postcode":"78013",
    "sg:province":"TX",
    "sg:tags":[
        "repairing",
        "automobile"
    ],
    "wof:name":"Cook Bro's & Sons",
    "wof:placetype":"venue"
},
  "geometry": {"coordinates":[-98.901366,29.964922],"type":"Point"}
}