{
  "type": "Feature",
  "properties": {
    "iso:country":"US",
    "sg:address":"1908 S Austin Ave Fl 1",
    "sg:city":"Georgetown",
    "sg:classifiers":[
        {
            "category":"Building & Trades",
            "subcategory":"Construction",
            "type":"Services"
        }
    ],
    "sg:phone":"+1 512 863 9091",
    "sg:postcode":"78626",
    "sg:province":"TX",
    "sg:tags":[
        "excavation",
        "sealcoating",
        "paving",
        "asphalt",
        "contractor"
    ],
    "wof:name":"Holmes Excavating & Paving Co",
    "wof:placetype":"venue"
},
  "geometry": {"coordinates":[-97.669239,30.65847],"type":"Point"}
}