{
  "type": "Feature",
  "properties": {
    "iso:country":"US",
    "sg:address":"14015 Park Dr",
    "sg:city":"Tomball",
    "sg:classifiers":[
        {
            "category":"Real Estate",
            "subcategory":"Real Estate Agent",
            "type":"Services"
        }
    ],
    "sg:phone":"+1 281 351 0200",
    "sg:postcode":"77377",
    "sg:province":"TX",
    "wof:name":"Realty Partners Inc",
    "wof:placetype":"venue"
},
  "geometry": {"coordinates":[-95.63236999999999,30.086836],"type":"Point"}
}