{
  "type": "Feature",
  "properties": {
    "iso:country":"US",
    "sg:address":"600 S Hewitt Dr",
    "sg:city":"Hewitt",
    "sg:phone":"+1 254 666 9837",
    "sg:postcode":"76643",
    "sg:province":"TX",
    "sg:website":"http://www.walmart.com",
    "wof:name":"Wal-Mart Supercenter",
    "wof:placetype":"venue"
},
  "geometry": {"coordinates":[-97.200157,31.456921],"type":"Point"}
}