{
  "type": "Feature",
  "properties": {
    "iso:country":"US",
    "sg:address":"4410 Yoakum Blvd",
    "sg:city":"Houston",
    "sg:classifiers":[
        {
            "category":"Education",
            "subcategory":"College",
            "type":"Public Place"
        }
    ],
    "sg:phone":"+1 713 529 0405",
    "sg:postcode":"77006",
    "sg:province":"TX",
    "sg:tags":[
        "school",
        "theological"
    ],
    "wof:name":"Holy Ghost Fathers Seminary",
    "wof:placetype":"venue"
},
  "geometry": {"coordinates":[-95.39255900000001,29.732905],"type":"Point"}
}