{
  "type": "Feature",
  "properties": {
    "iso:country":"US",
    "sg:address":"2928 Bitters Rd",
    "sg:city":"San Antonio",
    "sg:classifiers":[
        {
            "category":"Organizations",
            "subcategory":"Religious Organization",
            "type":"Services"
        }
    ],
    "sg:phone":"+1 210 824 6070",
    "sg:postcode":"78217",
    "sg:province":"TX",
    "sg:tags":[
        "church"
    ],
    "wof:name":"San Antonio Korean Baptist",
    "wof:placetype":"venue"
},
  "geometry": {"coordinates":[-98.440765,29.527506],"type":"Point"}
}