{
  "type": "Feature",
  "properties": {
    "iso:country":"US",
    "sg:address":"1128 Jones Rd",
    "sg:city":"Marshall",
    "sg:classifiers":[
        {
            "category":"Manufacturing",
            "subcategory":"Retail Goods",
            "type":"Manufacturing & Wholesale Goods"
        }
    ],
    "sg:phone":"+1 903 938 8965",
    "sg:postcode":"75670",
    "sg:province":"TX",
    "sg:tags":[
        "product",
        "mfg"
    ],
    "wof:name":"Claudia M Campbell",
    "wof:placetype":"venue"
},
  "geometry": {"coordinates":[-94.412834,32.566006],"type":"Point"}
}