{
  "type": "Feature",
  "properties": {
    "iso:country":"US",
    "sg:address":"5006 Tahoka Dr",
    "sg:city":"Granbury",
    "sg:classifiers":[
        {
            "category":"Building & Trades",
            "subcategory":"Construction",
            "type":"Services"
        }
    ],
    "sg:phone":"+1 817 326 3200",
    "sg:postcode":"76049",
    "sg:province":"TX",
    "sg:tags":[
        "excavation",
        "commercial"
    ],
    "wof:name":"Buzzard Roost Construction",
    "wof:placetype":"venue"
},
  "geometry": {"coordinates":[-97.699482,32.432635],"type":"Point"}
}