{
  "type": "Feature",
  "properties": {
    "iso:country":"US",
    "sg:address":"6803 Lauderwick Ct",
    "sg:city":"Katy",
    "sg:classifiers":[
        {
            "category":"Real Estate",
            "subcategory":"Real Estate Agent",
            "type":"Services"
        }
    ],
    "sg:phone":"+1 281 579 2108",
    "sg:postcode":"77450",
    "sg:province":"TX",
    "sg:tags":[
        "business"
    ],
    "wof:name":"Vision Acquisitions & Mergers",
    "wof:placetype":"venue"
},
  "geometry": {"coordinates":[-95.75335,29.703683],"type":"Point"}
}