{
  "type": "Feature",
  "properties": {
    "iso:country":"US",
    "sg:address":"6200 Savoy Dr Ste 260",
    "sg:city":"Houston",
    "sg:classifiers":[
        {
            "category":"Professional",
            "subcategory":"Lawyer & Legal Services",
            "type":"Services"
        }
    ],
    "sg:phone":"+1 713 981 8600",
    "sg:postcode":"77036",
    "sg:province":"TX",
    "wof:name":"James Floyd Atty",
    "wof:placetype":"venue"
},
  "geometry": {"coordinates":[-95.505746,29.714834],"type":"Point"}
}