{
  "type": "Feature",
  "properties": {
    "iso:country":"US",
    "sg:address":"1912 NE 28th St",
    "sg:city":"Fort Worth",
    "sg:classifiers":[
        {
            "category":"Wholesale",
            "subcategory":"Medical Equipment & Supplies",
            "type":"Manufacturing & Wholesale Goods"
        }
    ],
    "sg:phone":"+1 817 378 0636",
    "sg:postcode":"76106",
    "sg:province":"TX",
    "sg:tags":[
        "massage"
    ],
    "wof:name":"Migun Forth Worth Ctr",
    "wof:placetype":"venue"
},
  "geometry": {"coordinates":[-97.33178700000001,32.795134],"type":"Point"}
}