{
  "type": "Feature",
  "properties": {
    "iso:country":"US",
    "sg:address":"108 S Broadway St",
    "sg:city":"Brownwood",
    "sg:classifiers":[
        {
            "category":"Wholesale",
            "subcategory":"Electrical",
            "type":"Manufacturing & Wholesale Goods"
        }
    ],
    "sg:phone":"+1 325 646 7052",
    "sg:postcode":"76801",
    "sg:province":"TX",
    "sg:tags":[
        "electric",
        "motor"
    ],
    "wof:name":"Harris Motor Supply Co",
    "wof:placetype":"venue"
},
  "geometry": {"coordinates":[-98.98206500000001,31.722818],"type":"Point"}
}