{
  "type": "Feature",
  "properties": {
    "iso:country":"US",
    "sg:address":"1305 Southwood Blvd",
    "sg:city":"Arlington",
    "sg:classifiers":[
        {
            "category":"Professional",
            "type":"Services"
        }
    ],
    "sg:phone":"+1 817 478 8175",
    "sg:postcode":"76013",
    "sg:province":"TX",
    "sg:tags":[
        "establishment"
    ],
    "wof:name":"Kitchenaid",
    "wof:placetype":"venue"
},
  "geometry": {"coordinates":[-97.12703,32.719649],"type":"Point"}
}