{
  "type": "Feature",
  "properties": {
    "iso:country":"US",
    "sg:address":"1894 Co Rd 212",
    "sg:city":"Falls City",
    "sg:classifiers":[
        {
            "category":"Farming",
            "subcategory":"Livestock Farm",
            "type":"Manufacturing & Wholesale Goods"
        }
    ],
    "sg:phone":"+1 830 484 2227",
    "sg:postcode":"78113",
    "sg:province":"TX",
    "sg:tags":[
        "beef",
        "feedlot",
        "cattle"
    ],
    "wof:name":"Rick Dockery",
    "wof:placetype":"venue"
},
  "geometry": {"coordinates":[-98.09532299999999,28.954293],"type":"Point"}
}