{
  "type": "Feature",
  "properties": {
    "iso:country":"US",
    "sg:address":"1107 E Ennis Ave",
    "sg:city":"Ennis",
    "sg:classifiers":[
        {
            "category":"Restaurant",
            "type":"Food & Drink"
        }
    ],
    "sg:menulink":"http://www.allmenus.com/tx/ennis/193387-taco-bell/menu/",
    "sg:postcode":"75119",
    "sg:province":"TX",
    "sg:tags":[
        "mexican"
    ],
    "wof:name":"Taco Bell",
    "wof:placetype":"venue"
},
  "geometry": {"coordinates":[-96.616592,32.333552],"type":"Point"}
}