{
  "type": "Feature",
  "properties": {
    "iso:country":"US",
    "sg:address":"2005 W Wheeler Ave",
    "sg:city":"Aransas Pass",
    "sg:classifiers":[
        {
            "category":"Home & Garden",
            "subcategory":"Building Materials",
            "type":"Retail Goods"
        }
    ],
    "sg:phone":"+1 361 758 7870",
    "sg:postcode":"78336",
    "sg:province":"TX",
    "sg:tags":[
        "glass",
        "window",
        "plate"
    ],
    "wof:name":"Binswanger Glass Co",
    "wof:placetype":"venue"
},
  "geometry": {"coordinates":[-97.165212,27.917813],"type":"Point"}
}