{
  "type": "Feature",
  "properties": {
    "iso:country":"US",
    "sg:address":"8230 Walnut Hill Ln Ste 610",
    "sg:city":"Dallas",
    "sg:classifiers":[
        {
            "category":"Health Services",
            "subcategory":"Doctor",
            "type":"Services"
        }
    ],
    "sg:phone":"+1 214 345 7398",
    "sg:postcode":"75231",
    "sg:province":"TX",
    "wof:name":"Nunez Michael J MD",
    "wof:placetype":"venue"
},
  "geometry": {"coordinates":[-96.76173300000001,32.883142],"type":"Point"}
}