{
  "type": "Feature",
  "properties": {
    "iso:country":"US",
    "sg:address":"5836 Sampley Way",
    "sg:city":"Houston",
    "sg:classifiers":[
        {
            "category":"Home & Garden",
            "subcategory":"Furniture",
            "type":"Retail Goods"
        }
    ],
    "sg:phone":"+1 832 867 5057",
    "sg:postcode":"77092",
    "sg:province":"TX",
    "sg:tags":[
        "renting",
        "leasing"
    ],
    "wof:name":"Myers Furniture Rental",
    "wof:placetype":"venue"
},
  "geometry": {"coordinates":[-95.49920299999999,29.851969],"type":"Point"}
}