{
  "type": "Feature",
  "properties": {
    "iso:country":"US",
    "sg:address":"211 Cherokee St",
    "sg:city":"Longview",
    "sg:classifiers":[
        {
            "category":"Retail",
            "subcategory":"Auto Repair",
            "type":"Services"
        }
    ],
    "sg:phone":"+1 903 295 4848",
    "sg:postcode":"75604",
    "sg:province":"TX",
    "sg:tags":[
        "truck"
    ],
    "wof:name":"Freedom Diesel Svc",
    "wof:placetype":"venue"
},
  "geometry": {"coordinates":[-94.794202,32.504046],"type":"Point"}
}