{
  "type": "Feature",
  "properties": {
    "iso:country":"US",
    "sg:address":"436 FM 1960 W",
    "sg:city":"Houston",
    "sg:classifiers":[
        {
            "category":"Cinema",
            "subcategory":"Movie Rental",
            "type":"Entertainment"
        }
    ],
    "sg:phone":"+1 281 587 8827",
    "sg:postcode":"77090",
    "sg:province":"TX",
    "sg:tags":[
        "video",
        "tape"
    ],
    "wof:name":"Hollywood Video",
    "wof:placetype":"venue"
},
  "geometry": {"coordinates":[-95.43517799999999,30.0194],"type":"Point"}
}