{
  "type": "Feature",
  "properties": {
    "iso:country":"US",
    "sg:address":"1908 Cloisters Dr",
    "sg:city":"Arlington",
    "sg:classifiers":[
        {
            "category":"Banks & Credit Unions",
            "subcategory":"Financial Services",
            "type":"Services"
        }
    ],
    "sg:phone":"+1 817 277 2900",
    "sg:postcode":"76011",
    "sg:province":"TX",
    "sg:tags":[
        "investment",
        "closed"
    ],
    "wof:name":"Petrogroup",
    "wof:placetype":"venue"
},
  "geometry": {"coordinates":[-97.093214,32.764831],"type":"Point"}
}