{
  "type": "Feature",
  "properties": {
    "iso:country":"US",
    "sg:address":"700 Hidalgo Blvd",
    "sg:city":"Zapata",
    "sg:classifiers":[
        {
            "category":"Organizations",
            "subcategory":"Non-profit Organization",
            "type":"Services"
        }
    ],
    "sg:phone":"+1 956 765 9963",
    "sg:postcode":"78076",
    "sg:province":"TX",
    "sg:tags":[
        "program",
        "prevention",
        "crime"
    ],
    "wof:name":"Tips-Crime Prevention",
    "wof:placetype":"venue"
},
  "geometry": {"coordinates":[-99.266301,26.902558],"type":"Point"}
}