{
  "type": "Feature",
  "properties": {
    "iso:country":"US",
    "sg:address":"2915 Greenville Ave",
    "sg:city":"Dallas",
    "sg:classifiers":[
        {
            "category":"Personal",
            "subcategory":"Beauty Salon",
            "type":"Services"
        }
    ],
    "sg:phone":"+1 214 370 9486",
    "sg:postcode":"75206",
    "sg:province":"TX",
    "sg:tags":[
        "hair",
        "shop"
    ],
    "wof:name":"Stinson Studio Salon Inc",
    "wof:placetype":"venue"
},
  "geometry": {"coordinates":[-96.770302,32.823601],"type":"Point"}
}