{
  "type": "Feature",
  "properties": {
    "iso:country":"US",
    "sg:address":"3701 W Alabama St Ste 230",
    "sg:city":"Houston",
    "sg:classifiers":[
        {
            "category":"Social Services",
            "subcategory":"Child Care",
            "type":"Services"
        },
        {
            "category":"Personal",
            "subcategory":"Adult",
            "type":"Services"
        }
    ],
    "sg:phone":"+1 713 963 8880",
    "sg:postcode":"77027",
    "sg:province":"TX",
    "sg:tags":[
        "day",
        "midwife"
    ],
    "sg:website":"www.motherhoodcenter.com",
    "wof:name":"The Motherhood Center",
    "wof:placetype":"venue"
},
  "geometry": {"coordinates":[-95.437163,29.737679],"type":"Point"}
}