{
  "type": "Feature",
  "properties": {
    "iso:country":"US",
    "sg:address":"8700 N Stemmons Fwy",
    "sg:city":"Dallas",
    "sg:classifiers":[
        {
            "category":"Restaurant",
            "type":"Food & Drink"
        }
    ],
    "sg:phone":"+1 214 630 1681",
    "sg:postcode":"75247",
    "sg:province":"TX",
    "sg:tags":[
        "eating"
    ],
    "wof:name":"Park Cafe Inc",
    "wof:placetype":"venue"
},
  "geometry": {"coordinates":[-96.872981,32.829254],"type":"Point"}
}