{
  "type": "Feature",
  "properties": {
    "iso:country":"US",
    "sg:address":"3030 Broadmoor Ln",
    "sg:city":"Flower Mound",
    "sg:classifiers":[
        {
            "category":"Education",
            "subcategory":"Library",
            "type":"Public Place"
        }
    ],
    "sg:phone":"+1 972 874 6200",
    "sg:postcode":"75022",
    "sg:province":"TX",
    "wof:name":"Flower Mound Public Library",
    "wof:placetype":"venue"
},
  "geometry": {"coordinates":[-97.075783,33.033633],"type":"Point"}
}