{
  "type": "Feature",
  "properties": {
    "iso:country":"US",
    "sg:address":"2423 87th St",
    "sg:city":"Lubbock",
    "sg:classifiers":[
        {
            "category":"Social Services",
            "subcategory":"Child Care",
            "type":"Services"
        }
    ],
    "sg:phone":"+1 806 748 4000",
    "sg:postcode":"79423",
    "sg:province":"TX",
    "sg:tags":[
        "day"
    ],
    "wof:name":"Shelby & Friends",
    "wof:placetype":"venue"
},
  "geometry": {"coordinates":[-101.86817000000001,33.515645],"type":"Point"}
}