{
  "type": "Feature",
  "properties": {
    "iso:country":"US",
    "sg:address":"303 S Leonard Ave",
    "sg:city":"Cotulla",
    "sg:classifiers":[
        {
            "category":"Communications",
            "subcategory":"Film & Video Production",
            "type":"Services"
        }
    ],
    "sg:phone":"+1 830 879 6106",
    "sg:postcode":"78014",
    "sg:province":"TX",
    "sg:tags":[
        "motion",
        "picture"
    ],
    "wof:name":"Cesario Medellin Jr",
    "wof:placetype":"venue"
},
  "geometry": {"coordinates":[-99.240393,28.433099],"type":"Point"}
}