{
  "type": "Feature",
  "properties": {
    "iso:country":"US",
    "sg:address":"16840 State Hwy 3",
    "sg:city":"Webster",
    "sg:classifiers":[
        {
            "category":"Wholesale",
            "subcategory":"Construction Materials",
            "type":"Manufacturing & Wholesale Goods"
        }
    ],
    "sg:phone":"+1 281 554 4575",
    "sg:postcode":"77598",
    "sg:province":"TX",
    "sg:tags":[
        "tile"
    ],
    "wof:name":"Dal-Tile",
    "wof:placetype":"venue"
},
  "geometry": {"coordinates":[-95.12830700000001,29.548495],"type":"Point"}
}