{
  "type": "Feature",
  "properties": {
    "iso:country":"US",
    "sg:address":"27 Scenic Loop Rd",
    "sg:city":"Boerne",
    "sg:classifiers":[
        {
            "category":"Professional",
            "subcategory":"Management & Consulting",
            "type":"Services"
        }
    ],
    "sg:phone":"+1 830 981 8980",
    "sg:postcode":"78006",
    "sg:province":"TX",
    "sg:tags":[
        "consultant",
        "business"
    ],
    "sg:website":"www.jdgassociates.com",
    "wof:name":"JDG Assoc",
    "wof:placetype":"venue"
},
  "geometry": {"coordinates":[-98.704939,29.753985],"type":"Point"}
}