{
  "type": "Feature",
  "properties": {
    "iso:country":"US",
    "sg:address":"312 W Leuda St",
    "sg:city":"Fort Worth",
    "sg:classifiers":[
        {
            "category":"Professional",
            "type":"Services"
        }
    ],
    "sg:phone":"+1 817 882 9750",
    "sg:postcode":"76104",
    "sg:province":"TX",
    "wof:name":"Central For Healing Arts",
    "wof:placetype":"venue"
},
  "geometry": {"coordinates":[-97.32900600000001,32.73659],"type":"Point"}
}