{
  "type": "Feature",
  "properties": {
    "iso:country":"US",
    "sg:address":"2201 Arkansas Blvd",
    "sg:city":"Texarkana",
    "sg:classifiers":[
        {
            "category":"Organizations",
            "subcategory":"Religious Organization",
            "type":"Services"
        }
    ],
    "sg:phone":"+1 870 772 4740",
    "sg:postcode":"71854",
    "sg:province":"TX",
    "wof:name":"Baptist Church Mount Grove",
    "wof:placetype":"venue"
},
  "geometry": {"coordinates":[-94.019442,33.460647],"type":"Point"}
}