{
  "type": "Feature",
  "properties": {
    "iso:country":"US",
    "sg:address":"13421 Flagstone Ln",
    "sg:city":"Dallas",
    "sg:classifiers":[
        {
            "category":"Building & Trades",
            "subcategory":"Plumbing",
            "type":"Services"
        }
    ],
    "sg:phone":"+1 972 233 7116",
    "sg:postcode":"75240",
    "sg:province":"TX",
    "sg:tags":[
        "plumbing",
        "contractor"
    ],
    "wof:name":"Wilkey W W Plumbing",
    "wof:placetype":"venue"
},
  "geometry": {"coordinates":[-96.77297,32.929845],"type":"Point"}
}