{
  "type": "Feature",
  "properties": {
    "iso:country":"US",
    "sg:address":"1325 Bellgrove Dr",
    "sg:city":"Seabrook",
    "sg:classifiers":[
        {
            "category":"Retail",
            "subcategory":"Laundry & Dry Cleaning",
            "type":"Services"
        }
    ],
    "sg:phone":"+1 281 326 0988",
    "sg:postcode":"77586",
    "sg:province":"TX",
    "sg:tags":[
        "cleaners",
        "rug",
        "carpet"
    ],
    "wof:name":"Carpet Joy Cleaning Svc",
    "wof:placetype":"venue"
},
  "geometry": {"coordinates":[-95.039845,29.573477],"type":"Point"}
}