{
  "type": "Feature",
  "properties": {
    "iso:country":"US",
    "sg:address":"4828 Caroline St.",
    "sg:city":"Houston",
    "sg:classifiers":[
        {
            "category":"Arts & Performance",
            "subcategory":"Art Gallery",
            "type":"Entertainment"
        }
    ],
    "sg:phone":"+1 713 568 8174",
    "sg:postcode":"77004",
    "sg:province":"TX",
    "wof:name":"ArtStorm",
    "wof:placetype":"venue"
},
  "geometry": {"coordinates":[-95.383402,29.729342],"type":"Point"}
}