{
  "type": "Feature",
  "properties": {
    "iso:country":"US",
    "sg:address":"12959 Jupiter Rd",
    "sg:city":"Dallas",
    "sg:classifiers":[
        {
            "category":"Professional",
            "subcategory":"Detective & Security Services",
            "type":"Services"
        }
    ],
    "sg:phone":"+1 214 521 5811",
    "sg:postcode":"75238",
    "sg:province":"TX",
    "sg:tags":[
        "investigator"
    ],
    "wof:name":"Investigations",
    "wof:placetype":"venue"
},
  "geometry": {"coordinates":[-96.683258,32.873238],"type":"Point"}
}