{
  "type": "Feature",
  "properties": {
    "iso:country":"US",
    "sg:address":"4200 S Hulen St",
    "sg:city":"Fort Worth",
    "sg:classifiers":[
        {
            "category":"Professional",
            "subcategory":"Accounting & Tax Preparation",
            "type":"Services"
        }
    ],
    "sg:phone":"+1 817 570 9773",
    "sg:postcode":"76109",
    "sg:province":"TX",
    "sg:tags":[
        "return",
        "filing"
    ],
    "wof:name":"Lone Star Tax Advisory Group",
    "wof:placetype":"venue"
},
  "geometry": {"coordinates":[-97.39295,32.687701],"type":"Point"}
}