{
  "type": "Feature",
  "properties": {
    "iso:country":"US",
    "sg:address":"20622 Boxridge Ln",
    "sg:city":"Katy",
    "sg:classifiers":[
        {
            "category":"Banks & Credit Unions",
            "subcategory":"Bank",
            "type":"Services"
        }
    ],
    "sg:phone":"+1 281 647 0783",
    "sg:postcode":"77449",
    "sg:province":"TX",
    "sg:tags":[
        "mortgage"
    ],
    "wof:name":"Online Mortgage Service",
    "wof:placetype":"venue"
},
  "geometry": {"coordinates":[-95.73746,29.793795],"type":"Point"}
}