{
  "type": "Feature",
  "properties": {
    "iso:country":"US",
    "sg:address":"16102 Constitution Ln",
    "sg:city":"Friendswood",
    "sg:classifiers":[
        {
            "category":"Personal",
            "subcategory":"Beauty Salon",
            "type":"Services"
        }
    ],
    "sg:phone":"+1 281 996 5111",
    "sg:postcode":"77546",
    "sg:province":"TX",
    "sg:tags":[
        "shop"
    ],
    "wof:name":"Elaines Unique Design In",
    "wof:placetype":"venue"
},
  "geometry": {"coordinates":[-95.179258,29.538857],"type":"Point"}
}