{
  "type": "Feature",
  "properties": {
    "iso:country":"US",
    "sg:address":"1408 NE 23rd St",
    "sg:city":"Mineral Wells",
    "sg:classifiers":[
        {
            "category":"Wholesale",
            "subcategory":"Farm Supplies",
            "type":"Manufacturing & Wholesale Goods"
        }
    ],
    "sg:phone":"+1 940 325 2331",
    "sg:postcode":"76067",
    "sg:province":"TX",
    "wof:name":"Tommy M Yates Enterprises",
    "wof:placetype":"venue"
},
  "geometry": {"coordinates":[-98.091604,32.825207],"type":"Point"}
}