{
  "type": "Feature",
  "properties": {
    "iso:country":"US",
    "sg:address":"15363 FM 849",
    "sg:city":"Lindale",
    "sg:classifiers":[
        {
            "category":"Travel",
            "subcategory":"Campground",
            "type":"Entertainment"
        }
    ],
    "sg:phone":"+1 903 882 3183",
    "sg:postcode":"75771",
    "sg:province":"TX",
    "sg:tags":[
        "camp"
    ],
    "sg:website":"www.timberlinecamp.com",
    "wof:name":"Timberline Baptist Camp",
    "wof:placetype":"venue"
},
  "geometry": {"coordinates":[-95.42198500000001,32.495222],"type":"Point"}
}