{
  "type": "Feature",
  "properties": {
    "iso:country":"US",
    "sg:address":"4268 Co Rd 4803",
    "sg:city":"Athens",
    "sg:classifiers":[
        {
            "category":"Shopping",
            "subcategory":"Gifts & Souvenirs",
            "type":"Retail Goods"
        }
    ],
    "sg:phone":"+1 903 675 2264",
    "sg:postcode":"75752",
    "sg:province":"TX",
    "wof:name":"Brown Bear",
    "wof:placetype":"venue"
},
  "geometry": {"coordinates":[-95.75047600000001,32.20455],"type":"Point"}
}