{
  "type": "Feature",
  "properties": {
    "iso:country":"US",
    "sg:address":"12810 Hillcrest Rd Ste 225",
    "sg:city":"Dallas",
    "sg:classifiers":[
        {
            "category":"Professional",
            "subcategory":"Employment Agencies",
            "type":"Services"
        }
    ],
    "sg:phone":"+1 214 623 5940",
    "sg:postcode":"75230",
    "sg:province":"TX",
    "wof:name":"Wayne Perry & Associates",
    "wof:placetype":"venue"
},
  "geometry": {"coordinates":[-96.78598599999999,32.923153],"type":"Point"}
}