{
  "type": "Feature",
  "properties": {
    "iso:country":"US",
    "sg:address":"920 W 39th St",
    "sg:city":"Odessa",
    "sg:classifiers":[
        {
            "category":"Home & Garden",
            "subcategory":"Furniture",
            "type":"Retail Goods"
        }
    ],
    "sg:phone":"+1 432 368 5816",
    "sg:postcode":"79764",
    "sg:province":"TX",
    "sg:tags":[
        "store"
    ],
    "wof:name":"Furniture Speicialists",
    "wof:placetype":"venue"
},
  "geometry": {"coordinates":[-102.39442699999999,31.876374],"type":"Point"}
}