{
  "type": "Feature",
  "properties": {
    "iso:country":"US",
    "sg:address":"1606 Hard Luck Rd",
    "sg:city":"Marion",
    "sg:classifiers":[
        {
            "category":"Retail",
            "subcategory":"Repair Shop",
            "type":"Services"
        },
        {
            "category":"Building & Trades",
            "subcategory":"Plumbing",
            "type":"Services"
        }
    ],
    "sg:phone":"+1 830 914 2663",
    "sg:postcode":"78124",
    "sg:province":"TX",
    "sg:tags":[
        "contractor"
    ],
    "wof:name":"Samco Septic Tank Cleaning",
    "wof:placetype":"venue"
},
  "geometry": {"coordinates":[-98.11629600000001,29.595016],"type":"Point"}
}