{
  "type": "Feature",
  "properties": {
    "iso:country":"US",
    "sg:address":"1175 N Burleson Blvd",
    "sg:city":"Burleson",
    "sg:classifiers":[
        {
            "category":"Restaurant",
            "type":"Food & Drink"
        }
    ],
    "sg:menulink":"http://www.allmenus.com/tx/fort-worth/127950-red-lobster/menu/",
    "sg:phone":"+1 817 295 7150",
    "sg:postcode":"76028",
    "sg:province":"TX",
    "sg:tags":[
        "seafood",
        "american"
    ],
    "wof:name":"Red Lobster",
    "wof:placetype":"venue"
},
  "geometry": {"coordinates":[-97.31931299999999,32.568833],"type":"Point"}
}