{
  "type": "Feature",
  "properties": {
    "iso:country":"US",
    "sg:address":"1801 Oates Dr",
    "sg:city":"Dallas",
    "sg:classifiers":[
        {
            "category":"Farming",
            "subcategory":"Fish & Marine Products",
            "type":"Manufacturing & Wholesale Goods"
        }
    ],
    "sg:phone":"+1 214 827 4357",
    "sg:postcode":"75228",
    "sg:province":"TX",
    "sg:tags":[
        "relocation",
        "rescue",
        "animal",
        "transporting"
    ],
    "wof:name":"Find A Pet",
    "wof:placetype":"venue"
},
  "geometry": {"coordinates":[-96.681805,32.821664],"type":"Point"}
}