{
  "type": "Feature",
  "properties": {
    "iso:country":"US",
    "sg:address":"10725 N Autumnwood Way",
    "sg:city":"Spring",
    "sg:classifiers":[
        {
            "category":"Professional",
            "subcategory":"Management & Consulting",
            "type":"Services"
        }
    ],
    "sg:phone":"+1 281 367 6266",
    "sg:postcode":"77380",
    "sg:province":"TX",
    "sg:tags":[
        "business"
    ],
    "wof:name":"D2 Consulting Inc",
    "wof:placetype":"venue"
},
  "geometry": {"coordinates":[-95.474216,30.150476],"type":"Point"}
}