{
  "type": "Feature",
  "properties": {
    "iso:country":"US",
    "sg:address":"9507 Town Park Dr",
    "sg:city":"Houston",
    "sg:classifiers":[
        {
            "category":"Professional",
            "subcategory":"Advertising",
            "type":"Services"
        }
    ],
    "sg:phone":"+1 713 774 6330",
    "sg:postcode":"77036",
    "sg:province":"TX",
    "sg:tags":[
        "product",
        "advertising-promotional",
        "specialty"
    ],
    "sg:website":"http://www.agwear.com",
    "wof:name":"Agwear",
    "wof:placetype":"venue"
},
  "geometry": {"coordinates":[-95.549688,29.711847],"type":"Point"}
}