{
  "type": "Feature",
  "properties": {
    "iso:country":"US",
    "sg:address":"7720 N MacArthur Blvd",
    "sg:city":"Irving",
    "sg:classifiers":[
        {
            "category":"Banks & Credit Unions",
            "subcategory":"Bank",
            "type":"Services"
        }
    ],
    "sg:phone":"+1 972 556 2102",
    "sg:postcode":"75063",
    "sg:province":"TX",
    "sg:website":"www.wachovia.com",
    "wof:name":"Wachovia",
    "wof:placetype":"venue"
},
  "geometry": {"coordinates":[-96.958426,32.911416],"type":"Point"}
}