{
  "type": "Feature",
  "properties": {
    "iso:country":"US",
    "sg:address":"200 NW Mustang Dr",
    "sg:city":"Andrews",
    "sg:classifiers":[
        {
            "category":"Autos & Motor Vehicles",
            "subcategory":"Fuel & Gas Station",
            "type":"Retail Goods"
        }
    ],
    "sg:phone":"+1 432 524 9270",
    "sg:postcode":"79714",
    "sg:province":"TX",
    "sg:tags":[
        "station",
        "gasoline"
    ],
    "wof:name":"Exxon",
    "wof:placetype":"venue"
},
  "geometry": {"coordinates":[-102.568309,32.316781],"type":"Point"}
}