{
  "type": "Feature",
  "properties": {
    "iso:country":"US",
    "sg:address":"17330 Candela Dr",
    "sg:city":"Houston",
    "sg:classifiers":[
        {
            "category":"Professional",
            "type":"Services"
        }
    ],
    "sg:phone":"+1 281 265 8651",
    "sg:postcode":"77083",
    "sg:province":"TX",
    "wof:name":"Martir Quality Services",
    "wof:placetype":"venue"
},
  "geometry": {"coordinates":[-95.68555000000001,29.687037],"type":"Point"}
}