{
  "type": "Feature",
  "properties": {
    "iso:country":"US",
    "sg:address":"1101 W Mulberry St",
    "sg:city":"Angleton",
    "sg:classifiers":[
        {
            "category":"Real Estate",
            "subcategory":"Real Estate Agent",
            "type":"Services"
        }
    ],
    "sg:phone":"+1 979 849 8464",
    "sg:postcode":"77515",
    "sg:province":"TX",
    "wof:name":"Cameron Real Estate",
    "wof:placetype":"venue"
},
  "geometry": {"coordinates":[-95.45089,29.163758],"type":"Point"}
}