{
  "type": "Feature",
  "properties": {
    "iso:country":"US",
    "sg:address":"4918 Orange Grove Dr",
    "sg:city":"Houston",
    "sg:classifiers":[
        {
            "category":"Professional",
            "type":"Services"
        },
        {
            "category":"Building & Trades",
            "subcategory":"Construction",
            "type":"Services"
        }
    ],
    "sg:phone":"+1 281 987 8891",
    "sg:postcode":"77039",
    "sg:province":"TX",
    "sg:tags":[
        "utility",
        "contractor"
    ],
    "wof:name":"J & V Utilities",
    "wof:placetype":"venue"
},
  "geometry": {"coordinates":[-95.321534,29.89417],"type":"Point"}
}