{
  "type": "Feature",
  "properties": {
    "iso:country":"US",
    "sg:address":"2000 S Commercial Ave",
    "sg:city":"Coleman",
    "sg:classifiers":[
        {
            "category":"Shopping",
            "subcategory":"Discount & Variety Stores",
            "type":"Retail Goods"
        }
    ],
    "sg:phone":"+1 325 625 1354",
    "sg:postcode":"76834",
    "sg:province":"TX",
    "wof:name":"Dollar General",
    "wof:placetype":"venue"
},
  "geometry": {"coordinates":[-99.42331299999999,31.814633],"type":"Point"}
}