{
  "type": "Feature",
  "properties": {
    "iso:country":"US",
    "sg:address":"2860 Keller Hicks Rd",
    "sg:city":"Keller",
    "sg:classifiers":[
        {
            "category":"Professional",
            "subcategory":"Business Services",
            "type":"Services"
        }
    ],
    "sg:phone":"+1 817 431 3277",
    "sg:postcode":"76248",
    "sg:province":"TX",
    "wof:name":"Rocking R Services",
    "wof:placetype":"venue"
},
  "geometry": {"coordinates":[-97.30504000000001,32.938994],"type":"Point"}
}