{
  "type": "Feature",
  "properties": {
    "iso:country":"US",
    "sg:address":"2501 SW Loop 820",
    "sg:city":"Fort Worth",
    "sg:classifiers":[
        {
            "category":"Government",
            "subcategory":"Office",
            "type":"Public Place"
        }
    ],
    "sg:phone":"+1 817 370 6500",
    "sg:postcode":"76133",
    "sg:province":"TX",
    "sg:tags":[
        "state",
        "program"
    ],
    "sg:website":"www.dot.state.tx.us",
    "wof:name":"Transportation Dept",
    "wof:placetype":"venue"
},
  "geometry": {"coordinates":[-97.355897,32.66766],"type":"Point"}
}