{
  "type": "Feature",
  "properties": {
    "iso:country":"US",
    "sg:address":"3558 Wilhurt Ave",
    "sg:city":"Dallas",
    "sg:classifiers":[
        {
            "category":"Real Estate",
            "subcategory":"Real Estate Operator",
            "type":"Services"
        }
    ],
    "sg:phone":"+1 214 376 0607",
    "sg:postcode":"75216",
    "sg:province":"TX",
    "sg:tags":[
        "building",
        "apartment"
    ],
    "wof:name":"Royal Crest Apartments",
    "wof:placetype":"venue"
},
  "geometry": {"coordinates":[-96.765005,32.71293],"type":"Point"}
}