{
  "type": "Feature",
  "properties": {
    "iso:country":"US",
    "sg:address":"22900 Hardy Oak Blvd",
    "sg:city":"San Antonio",
    "sg:classifiers":[
        {
            "category":"Education",
            "subcategory":"School",
            "type":"Public Place"
        }
    ],
    "sg:phone":"+1 210 481 4000",
    "sg:postcode":"78258",
    "sg:province":"TX",
    "wof:name":"Schools",
    "wof:placetype":"venue"
},
  "geometry": {"coordinates":[-98.49534,29.654774],"type":"Point"}
}