{
  "type": "Feature",
  "properties": {
    "iso:country":"US",
    "sg:address":"228 Westmoreland St",
    "sg:city":"Houston",
    "sg:classifiers":[
        {
            "category":"Real Estate",
            "subcategory":"Real Estate Operator",
            "type":"Services"
        }
    ],
    "sg:phone":"+1 713 528 5218",
    "sg:postcode":"77006",
    "sg:province":"TX",
    "sg:tags":[
        "apartment"
    ],
    "wof:name":"Court Of Charleston Apartments",
    "wof:placetype":"venue"
},
  "geometry": {"coordinates":[-95.384045,29.740594],"type":"Point"}
}