{
  "type": "Feature",
  "properties": {
    "iso:country":"US",
    "sg:address":"204 2nd St",
    "sg:city":"Nazareth",
    "sg:classifiers":[
        {
            "category":"Personal",
            "subcategory":"Beauty Salon",
            "type":"Services"
        }
    ],
    "sg:phone":"+1 806 945 2434",
    "sg:postcode":"79063",
    "sg:province":"TX",
    "wof:name":"Mo's House Of Style",
    "wof:placetype":"venue"
},
  "geometry": {"coordinates":[-102.10187000000001,34.545601],"type":"Point"}
}