{
  "type": "Feature",
  "properties": {
    "iso:country":"US",
    "sg:address":"16304 FM 1488",
    "sg:city":"Magnolia",
    "sg:classifiers":[
        {
            "category":"Social Services",
            "subcategory":"Child Care",
            "type":"Services"
        }
    ],
    "sg:phone":"+1 281 259 7585",
    "sg:postcode":"77354",
    "sg:province":"TX",
    "sg:tags":[
        "day",
        "animal"
    ],
    "wof:name":"Dogs Day Out Grooming",
    "wof:placetype":"venue"
},
  "geometry": {"coordinates":[-95.710874,30.227658],"type":"Point"}
}