{
  "type": "Feature",
  "properties": {
    "iso:country":"US",
    "sg:address":"12700 Northborough Dr",
    "sg:city":"Houston",
    "sg:classifiers":[
        {
            "category":"Professional",
            "subcategory":"Management & Consulting",
            "type":"Services"
        }
    ],
    "sg:phone":"+1 281 874 4950",
    "sg:postcode":"77067",
    "sg:province":"TX",
    "sg:tags":[
        "property"
    ],
    "wof:name":"Pitney Bowes",
    "wof:placetype":"venue"
},
  "geometry": {"coordinates":[-95.42260899999999,29.953847],"type":"Point"}
}