{
  "type": "Feature",
  "properties": {
    "iso:country":"US",
    "sg:address":"1606 E Euless Blvd",
    "sg:city":"Euless",
    "sg:classifiers":[
        {
            "category":"Manufacturing",
            "subcategory":"Tools & Machinery",
            "type":"Manufacturing & Wholesale Goods"
        }
    ],
    "sg:phone":"+1 817 283 2227",
    "sg:postcode":"76040",
    "sg:province":"TX",
    "sg:tags":[
        "industry",
        "aerospace"
    ],
    "sg:website":"www.madisonaerospace.com",
    "wof:name":"Madison Aerospace Inc",
    "wof:placetype":"venue"
},
  "geometry": {"coordinates":[-97.11023900000001,32.824906],"type":"Point"}
}