{
  "type": "Feature",
  "properties": {
    "iso:country":"US",
    "sg:address":"9002 Wurzbach Rd",
    "sg:city":"San Antonio",
    "sg:classifiers":[
        {
            "category":"Professional",
            "subcategory":"Lawyer & Legal Services",
            "type":"Services"
        }
    ],
    "sg:phone":"+1 210 614 4444",
    "sg:postcode":"78240",
    "sg:province":"TX",
    "sg:tags":[
        "attorney"
    ],
    "wof:name":"Law Offices of James R Bass",
    "wof:placetype":"venue"
},
  "geometry": {"coordinates":[-98.56690999999999,29.526254],"type":"Point"}
}