{
  "type": "Feature",
  "properties": {
    "iso:country":"US",
    "sg:address":"611 Jackson St",
    "sg:city":"Richmond",
    "sg:classifiers":[
        {
            "category":"Travel",
            "subcategory":"Travel Agent",
            "type":"Entertainment"
        }
    ],
    "sg:phone":"+1 281 342 6892",
    "sg:postcode":"77469",
    "sg:province":"TX",
    "sg:tags":[
        "agency",
        "bureau"
    ],
    "sg:website":"www.seeweetravel.com",
    "wof:name":"Seewee's Travel",
    "wof:placetype":"venue"
},
  "geometry": {"coordinates":[-95.76308400000001,29.581427],"type":"Point"}
}