{
  "type": "Feature",
  "properties": {
    "iso:country":"US",
    "sg:address":"3506 Darby St",
    "sg:city":"Austin",
    "sg:classifiers":[
        {
            "category":"Autos & Motor Vehicles",
            "subcategory":"Automobile Sales",
            "type":"Retail Goods"
        }
    ],
    "sg:phone":"+1 512 927 1010",
    "sg:postcode":"78721",
    "sg:province":"TX",
    "sg:tags":[
        "car",
        "used",
        "cars-wholesale",
        "dealers-used"
    ],
    "wof:name":"Big Star Motors Inc",
    "wof:placetype":"venue"
},
  "geometry": {"coordinates":[-97.669899,30.270873],"type":"Point"}
}