{
  "type": "Feature",
  "properties": {
    "iso:country":"US",
    "sg:address":"1302 Nance St",
    "sg:city":"Houston",
    "sg:classifiers":[
        {
            "category":"Restaurant",
            "type":"Food & Drink"
        }
    ],
    "sg:phone":"+1 713 229 8369",
    "sg:postcode":"77002",
    "sg:province":"TX",
    "sg:tags":[
        "american",
        "latin"
    ],
    "sg:website":"www.latinbitescafe.com/",
    "wof:name":"Latin Bites Cafe",
    "wof:placetype":"venue"
},
  "geometry": {"coordinates":[-95.35402499999999,29.767778],"type":"Point"}
}