{
  "type": "Feature",
  "properties": {
    "iso:country":"US",
    "sg:address":"2216 Lawnmeadow Dr",
    "sg:city":"Richardson",
    "sg:classifiers":[
        {
            "category":"Wholesale",
            "subcategory":"Non-durable Goods",
            "type":"Manufacturing & Wholesale Goods"
        }
    ],
    "sg:phone":"+1 972 644 0732",
    "sg:postcode":"75080",
    "sg:province":"TX",
    "wof:name":"Mountain Man Distributor",
    "wof:placetype":"venue"
},
  "geometry": {"coordinates":[-96.74017600000001,32.982819],"type":"Point"}
}