{
  "type": "Feature",
  "properties": {
    "iso:country":"US",
    "sg:address":"1716 Mangum Rd",
    "sg:city":"Houston",
    "sg:classifiers":[
        {
            "category":"Banks & Credit Unions",
            "subcategory":"Financial Services",
            "type":"Services"
        }
    ],
    "sg:phone":"+1 866 531 0572",
    "sg:postcode":"77092",
    "sg:province":"TX",
    "sg:tags":[
        "counseling",
        "debt",
        "bankruptcy"
    ],
    "sg:website":"http://www.moneymanagement.org",
    "wof:name":"Consumer Credit Counseling Services",
    "wof:placetype":"venue"
},
  "geometry": {"coordinates":[-95.458555,29.800583],"type":"Point"}
}