{
  "type": "Feature",
  "properties": {
    "iso:country":"US",
    "sg:address":"4230 Almond Lake Dr",
    "sg:city":"Houston",
    "sg:classifiers":[
        {
            "category":"Professional",
            "subcategory":"Computer Services",
            "type":"Services"
        }
    ],
    "sg:phone":"+1 713 738 7430",
    "sg:postcode":"77047",
    "sg:province":"TX",
    "sg:tags":[
        "equipment",
        "rooms-installation"
    ],
    "sg:website":"http://www.hughoshaw.com",
    "wof:name":"Continential Computer Technology",
    "wof:placetype":"venue"
},
  "geometry": {"coordinates":[-95.354226,29.593727],"type":"Point"}
}