{
  "type": "Feature",
  "properties": {
    "iso:country":"US",
    "sg:address":"9002 Shipman St",
    "sg:city":"Rowlett",
    "sg:classifiers":[
        {
            "category":"Restaurant",
            "type":"Food & Drink"
        }
    ],
    "sg:phone":"+1 972 412 4299",
    "sg:postcode":"75088",
    "sg:province":"TX",
    "sg:tags":[
        "eating"
    ],
    "wof:name":"Basic Snacks",
    "wof:placetype":"venue"
},
  "geometry": {"coordinates":[-96.515394,32.915716],"type":"Point"}
}