{
  "type": "Feature",
  "properties": {
    "iso:country":"US",
    "sg:address":"4202 W Walnut St",
    "sg:city":"Pearland",
    "sg:classifiers":[
        {
            "category":"Organizations",
            "subcategory":"Community Association",
            "type":"Services"
        }
    ],
    "sg:phone":"+1 281 997 1097",
    "sg:postcode":"77581",
    "sg:province":"TX",
    "sg:tags":[
        "military"
    ],
    "wof:name":"Veterans Of Foreign Wars 7109",
    "wof:placetype":"venue"
},
  "geometry": {"coordinates":[-95.28827,29.559908],"type":"Point"}
}