{
  "type": "Feature",
  "properties": {
    "iso:country":"US",
    "sg:address":"3758 Ashley Ct",
    "sg:city":"Fort Worth",
    "sg:classifiers":[
        {
            "category":"Professional",
            "subcategory":"Business Services",
            "type":"Services"
        }
    ],
    "sg:phone":"+1 817 370 8415",
    "sg:postcode":"76123",
    "sg:province":"TX",
    "wof:name":"3b Enterprises",
    "wof:placetype":"venue"
},
  "geometry": {"coordinates":[-97.375536,32.626683],"type":"Point"}
}