{
  "type": "Feature",
  "properties": {
    "iso:country":"US",
    "sg:address":"8473 Southwestern Blvd",
    "sg:city":"Dallas",
    "sg:classifiers":[
        {
            "category":"Building & Trades",
            "subcategory":"Construction",
            "type":"Services"
        }
    ],
    "sg:phone":"+1 972 333 7448",
    "sg:postcode":"75206",
    "sg:province":"TX",
    "sg:tags":[
        "house"
    ],
    "wof:name":"Texas Handyman Services",
    "wof:placetype":"venue"
},
  "geometry": {"coordinates":[-96.761005,32.860159],"type":"Point"}
}