{
  "type": "Feature",
  "properties": {
    "iso:country":"US",
    "sg:address":"439 W Mescalero Dr",
    "sg:city":"Odessa",
    "sg:classifiers":[
        {
            "category":"Restaurant",
            "type":"Food & Drink"
        }
    ],
    "sg:phone":"+1 432 333 7053",
    "sg:postcode":"79766",
    "sg:province":"TX",
    "sg:tags":[
        "eating"
    ],
    "wof:name":"Lunch Wagon",
    "wof:placetype":"venue"
},
  "geometry": {"coordinates":[-102.36744400000001,31.760616],"type":"Point"}
}