{
  "type": "Feature",
  "properties": {
    "iso:country":"US",
    "sg:address":"801 S Magnolia St",
    "sg:city":"Palestine",
    "sg:classifiers":[
        {
            "category":"Shopping",
            "subcategory":"Used Merchandise",
            "type":"Retail Goods"
        }
    ],
    "sg:phone":"+1 903 729 1073",
    "sg:postcode":"75801",
    "sg:province":"TX",
    "wof:name":"WL & Caron L Fraser",
    "wof:placetype":"venue"
},
  "geometry": {"coordinates":[-95.631418,31.754911],"type":"Point"}
}