{
  "type": "Feature",
  "properties": {
    "iso:country":"US",
    "sg:address":"2144 Lyman Dutton Cir",
    "sg:city":"El Paso",
    "sg:classifiers":[
        {
            "category":"Personal",
            "subcategory":"Beauty Salon",
            "type":"Services"
        }
    ],
    "sg:phone":"+1 915 856 0953",
    "sg:postcode":"79936",
    "sg:province":"TX",
    "sg:tags":[
        "shop"
    ],
    "wof:name":"European Hair Salon",
    "wof:placetype":"venue"
},
  "geometry": {"coordinates":[-106.269085,31.766365],"type":"Point"}
}