{
  "type": "Feature",
  "properties": {
    "iso:country":"US",
    "sg:address":"11523 Glen Lake Dr",
    "sg:city":"Sugar Land",
    "sg:classifiers":[
        {
            "category":"Professional",
            "type":"Services"
        }
    ],
    "sg:phone":"+1 281 575 7267",
    "sg:postcode":"77478",
    "sg:province":"TX",
    "sg:tags":[
        "establishment"
    ],
    "wof:name":"Electra City Sound Enterprises",
    "wof:placetype":"venue"
},
  "geometry": {"coordinates":[-95.65409,29.647822],"type":"Point"}
}