{
  "type": "Feature",
  "properties": {
    "iso:country":"US",
    "sg:address":"2930 Preston Rd",
    "sg:city":"Frisco",
    "sg:classifiers":[
        {
            "category":"Home & Garden",
            "subcategory":"Furniture",
            "type":"Retail Goods"
        }
    ],
    "sg:phone":"+1 972 731 0999",
    "sg:postcode":"75034",
    "sg:province":"TX",
    "wof:name":"Sleep Experts",
    "wof:placetype":"venue"
},
  "geometry": {"coordinates":[-96.805475,33.1028],"type":"Point"}
}