{
  "type": "Feature",
  "properties": {
    "iso:country":"US",
    "sg:address":"14702 Mystic Bend Dr",
    "sg:city":"Cypress",
    "sg:classifiers":[
        {
            "category":"Wholesale",
            "subcategory":"Machinery & Supplies",
            "type":"Manufacturing & Wholesale Goods"
        }
    ],
    "sg:phone":"+1 281 894 6545",
    "sg:postcode":"77429",
    "sg:province":"TX",
    "sg:tags":[
        "industrial"
    ],
    "wof:name":"C&W Technical Sales Co In",
    "wof:placetype":"venue"
},
  "geometry": {"coordinates":[-95.644006,29.962855],"type":"Point"}
}