{
  "type": "Feature",
  "properties": {
    "iso:country":"US",
    "sg:address":"2310 W Shady Grove Rd",
    "sg:city":"Irving",
    "sg:classifiers":[
        {
            "category":"Professional",
            "subcategory":"Accounting & Tax Preparation",
            "type":"Services"
        }
    ],
    "sg:phone":"+1 972 399 0305",
    "sg:postcode":"75060",
    "sg:province":"TX",
    "sg:tags":[
        "return",
        "filing"
    ],
    "wof:name":"H & R Block Tax Svc",
    "wof:placetype":"venue"
},
  "geometry": {"coordinates":[-96.975357,32.800369],"type":"Point"}
}