{
  "type": "Feature",
  "properties": {
    "iso:country":"US",
    "sg:address":"7260 FM 3405",
    "sg:city":"Liberty Hill",
    "sg:classifiers":[
        {
            "category":"Retail",
            "subcategory":"Auto Repair",
            "type":"Services"
        }
    ],
    "sg:phone":"+1 512 515 6780",
    "sg:postcode":"78642",
    "sg:province":"TX",
    "sg:tags":[
        "general"
    ],
    "wof:name":"James Baker Automotive",
    "wof:placetype":"venue"
},
  "geometry": {"coordinates":[-97.873486,30.705305],"type":"Point"}
}