{
  "type": "Feature",
  "properties": {
    "iso:country":"US",
    "sg:address":"106 S Main St",
    "sg:city":"Borger",
    "sg:classifiers":[
        {
            "category":"Retail",
            "subcategory":"Auto Repair",
            "type":"Services"
        }
    ],
    "sg:phone":"+1 806 273 5911",
    "sg:postcode":"79007",
    "sg:province":"TX",
    "sg:tags":[
        "repairing",
        "automobile"
    ],
    "sg:website":"www.fuzzysradiator.com",
    "wof:name":"Fuzzy's Radiator Sales & Svc",
    "wof:placetype":"venue"
},
  "geometry": {"coordinates":[-101.389881,35.665762],"type":"Point"}
}