{
  "type": "Feature",
  "properties": {
    "iso:country":"US",
    "sg:address":"1716 E Yandell Dr",
    "sg:city":"El Paso",
    "sg:phone":"+1 915 534 0012",
    "sg:postcode":"79902",
    "sg:province":"TX",
    "sg:tags":[
        "communications",
        "telegraph"
    ],
    "wof:name":"Western Union",
    "wof:placetype":"venue"
},
  "geometry": {"coordinates":[-106.474667,31.773586],"type":"Point"}
}