{
  "type": "Feature",
  "properties": {
    "iso:country":"US",
    "sg:address":"3721 Greenstone Dr",
    "sg:city":"Fort Worth",
    "sg:classifiers":[
        {
            "category":"Retail",
            "subcategory":"Repair Shop",
            "type":"Services"
        }
    ],
    "sg:phone":"+1 817 232 8872",
    "sg:postcode":"76137",
    "sg:province":"TX",
    "sg:tags":[
        "related"
    ],
    "wof:name":"Cooling Tower Repair Svc",
    "wof:placetype":"venue"
},
  "geometry": {"coordinates":[-97.300726,32.86926],"type":"Point"}
}