{
  "type": "Feature",
  "properties": {
    "iso:country":"US",
    "sg:address":"11150 Research Blvd #104",
    "sg:city":"Austin",
    "sg:classifiers":[
        {
            "category":"Shopping",
            "subcategory":"Department Store",
            "type":"Retail Goods"
        },
        {
            "category":"Shopping",
            "type":"Retail Goods"
        },
        {
            "category":"Shopping",
            "subcategory":"Discount & Variety Stores",
            "type":"Retail Goods"
        }
    ],
    "sg:phone":"+1 512 340 0635",
    "sg:postcode":"78759",
    "sg:province":"TX",
    "sg:tags":[
        "merchandise"
    ],
    "sg:website":"www.dollartree.com",
    "wof:name":"Dollar Tree",
    "wof:placetype":"venue"
},
  "geometry": {"coordinates":[-97.745654,30.406708],"type":"Point"}
}