{
  "type": "Feature",
  "properties": {
    "iso:country":"US",
    "sg:address":"50 Briar Hollow Ln",
    "sg:city":"Houston",
    "sg:classifiers":[
        {
            "category":"Building & Trades",
            "subcategory":"Construction",
            "type":"Services"
        }
    ],
    "sg:phone":"+1 713 572 3216",
    "sg:postcode":"77027",
    "sg:province":"TX",
    "sg:tags":[
        "contractor"
    ],
    "wof:name":"Manchester Gas Storage",
    "wof:placetype":"venue"
},
  "geometry": {"coordinates":[-95.45195,29.752445],"type":"Point"}
}