{
  "type": "Feature",
  "properties": {
    "iso:country":"US",
    "sg:address":"1170 Katy Rd",
    "sg:city":"Keller",
    "sg:classifiers":[
        {
            "category":"Retail",
            "subcategory":"Auto Repair",
            "type":"Services"
        }
    ],
    "sg:phone":"+1 817 431 8928",
    "sg:postcode":"76248",
    "sg:province":"TX",
    "sg:tags":[
        "general"
    ],
    "wof:name":"Half Price Auto Repair",
    "wof:placetype":"venue"
},
  "geometry": {"coordinates":[-97.255291,32.949495],"type":"Point"}
}