{
  "type": "Feature",
  "properties": {
    "iso:country":"US",
    "sg:address":"2216 Crockett St",
    "sg:city":"Houston",
    "sg:classifiers":[
        {
            "category":"Organizations",
            "subcategory":"Religious Organization",
            "type":"Services"
        }
    ],
    "sg:phone":"+1 713 864 8401",
    "sg:postcode":"77007",
    "sg:province":"TX",
    "wof:name":"Iglesia El Monte Calvario",
    "wof:placetype":"venue"
},
  "geometry": {"coordinates":[-95.381299,29.773721],"type":"Point"}
}