{
  "type": "Feature",
  "properties": {
    "iso:country":"US",
    "sg:address":"3700 Murphy Dr",
    "sg:city":"Bedford",
    "sg:classifiers":[
        {
            "category":"Shopping",
            "subcategory":"Bicycles & Sporting Goods",
            "type":"Retail Goods"
        }
    ],
    "sg:phone":"+1 817 267 3484",
    "sg:postcode":"76021",
    "sg:province":"TX",
    "wof:name":"D H Guns",
    "wof:placetype":"venue"
},
  "geometry": {"coordinates":[-97.124661,32.866378],"type":"Point"}
}