{
  "type": "Feature",
  "properties": {
    "iso:country":"US",
    "sg:address":"4204 Texacana Ln",
    "sg:city":"Mission",
    "sg:classifiers":[
        {
            "category":"Professional",
            "type":"Services"
        }
    ],
    "sg:phone":"+1 956 581 1195",
    "sg:postcode":"78572",
    "sg:province":"TX",
    "wof:name":"Sasktex Inc",
    "wof:placetype":"venue"
},
  "geometry": {"coordinates":[-98.37817800000001,26.213296],"type":"Point"}
}