{
  "type": "Feature",
  "properties": {
    "iso:country":"US",
    "sg:address":"6422 Bosley Ln",
    "sg:city":"Houston",
    "sg:classifiers":[
        {
            "category":"Manufacturing",
            "subcategory":"Tools & Machinery",
            "type":"Manufacturing & Wholesale Goods"
        }
    ],
    "sg:phone":"+1 281 345 6632",
    "sg:postcode":"77084",
    "sg:province":"TX",
    "sg:tags":[
        "industrial",
        "mfg"
    ],
    "wof:name":"I Eloisa Movers",
    "wof:placetype":"venue"
},
  "geometry": {"coordinates":[-95.64116300000001,29.868611],"type":"Point"}
}