{
  "type": "Feature",
  "properties": {
    "iso:country":"US",
    "sg:address":"306 Texas Ave",
    "sg:city":"Kingsland",
    "sg:classifiers":[
        {
            "category":"Professional",
            "subcategory":"Computer Services",
            "type":"Services"
        }
    ],
    "sg:phone":"+1 325 388 9121",
    "sg:postcode":"78639",
    "sg:province":"TX",
    "sg:tags":[
        "datum"
    ],
    "wof:name":"Whites Data Services",
    "wof:placetype":"venue"
},
  "geometry": {"coordinates":[-98.45196799999999,30.676974],"type":"Point"}
}