{
  "type": "Feature",
  "properties": {
    "iso:country":"US",
    "sg:address":"4002 North Main Street",
    "sg:city":"Houston",
    "sg:classifiers":[
        {
            "category":"Restaurant",
            "type":"Food & Drink"
        }
    ],
    "sg:postcode":"77009",
    "sg:province":"TX",
    "sg:tags":[
        "mexican"
    ],
    "sg:website":"www.facebook.com",
    "wof:name":"Rico's Cantina",
    "wof:placetype":"venue"
},
  "geometry": {"coordinates":[-95.37651,29.793523],"type":"Point"}
}