{
  "type": "Feature",
  "properties": {
    "iso:country":"US",
    "sg:address":"191 Palmetto Dr",
    "sg:city":"Jasper",
    "sg:classifiers":[
        {
            "category":"Building & Trades",
            "subcategory":"Landscaping Services",
            "type":"Services"
        }
    ],
    "sg:phone":"+1 409 489 1397",
    "sg:postcode":"75951",
    "sg:province":"TX",
    "wof:name":"Aplus Total Lawn Care",
    "wof:placetype":"venue"
},
  "geometry": {"coordinates":[-93.982991,30.922205],"type":"Point"}
}