{
  "type": "Feature",
  "properties": {
    "iso:country":"US",
    "sg:address":"22657 Nameless Rd",
    "sg:city":"Leander",
    "sg:classifiers":[
        {
            "category":"Food & Beverages",
            "subcategory":"Groceries & Convenience Stores",
            "type":"Retail Goods"
        }
    ],
    "sg:phone":"+1 512 259 3312",
    "sg:postcode":"78641",
    "sg:province":"TX",
    "wof:name":"Calkins Country Store",
    "wof:placetype":"venue"
},
  "geometry": {"coordinates":[-97.942933,30.57051],"type":"Point"}
}