{
  "type": "Feature",
  "properties": {
    "iso:country":"US",
    "sg:address":"6638 State Hwy 114",
    "sg:city":"Haslet",
    "sg:classifiers":[
        {
            "category":"Home & Garden",
            "subcategory":"Garden Supply",
            "type":"Retail Goods"
        }
    ],
    "sg:phone":"+1 817 636 2643",
    "sg:postcode":"76052",
    "sg:province":"TX",
    "sg:tags":[
        "lawn"
    ],
    "wof:name":"Husky Power Of Texas LP",
    "wof:placetype":"venue"
},
  "geometry": {"coordinates":[-97.41056500000001,33.036696],"type":"Point"}
}