{
  "type": "Feature",
  "properties": {
    "iso:country":"US",
    "sg:address":"601 Newmarket Ct",
    "sg:city":"Mc Kinney",
    "sg:classifiers":[
        {
            "category":"Building & Trades",
            "subcategory":"Construction",
            "type":"Services"
        }
    ],
    "sg:phone":"+1 972 347 2940",
    "sg:postcode":"75071",
    "sg:province":"TX",
    "sg:tags":[
        "home",
        "builder"
    ],
    "wof:name":"Beazer Homes",
    "wof:placetype":"venue"
},
  "geometry": {"coordinates":[-96.733487,33.208276],"type":"Point"}
}