{
  "type": "Feature",
  "properties": {
    "iso:country":"US",
    "sg:address":"3540 W Highway 377",
    "sg:city":"Granbury",
    "sg:classifiers":[
        {
            "category":"Building & Trades",
            "subcategory":"Landscaping Services",
            "type":"Services"
        }
    ],
    "sg:phone":"+1 817 579 7929",
    "sg:postcode":"76048",
    "sg:province":"TX",
    "sg:tags":[
        "tree"
    ],
    "wof:name":"Lake Wl Country Tree Farm",
    "wof:placetype":"venue"
},
  "geometry": {"coordinates":[-97.81362300000001,32.436069],"type":"Point"}
}