{
  "type": "Feature",
  "properties": {
    "iso:country":"US",
    "sg:address":"2400 S Hayden St",
    "sg:city":"Amarillo",
    "sg:classifiers":[
        {
            "category":"Health Services",
            "subcategory":"Health Practitioner",
            "type":"Services"
        }
    ],
    "sg:phone":"+1 806 373 3061",
    "sg:postcode":"79109",
    "sg:province":"TX",
    "wof:name":"Barbara F Edd Williams",
    "wof:placetype":"venue"
},
  "geometry": {"coordinates":[-101.850911,35.1856],"type":"Point"}
}