{
  "type": "Feature",
  "properties": {
    "iso:country":"US",
    "sg:address":"8905 Bluff Springs Rd",
    "sg:city":"Austin",
    "sg:classifiers":[
        {
            "category":"Building & Trades",
            "subcategory":"Construction",
            "type":"Services"
        }
    ],
    "sg:phone":"+1 512 445 5388",
    "sg:postcode":"78744",
    "sg:province":"TX",
    "sg:tags":[
        "roofing",
        "contractor"
    ],
    "wof:name":"Caswell Services",
    "wof:placetype":"venue"
},
  "geometry": {"coordinates":[-97.76956199999999,30.159739],"type":"Point"}
}