{
  "type": "Feature",
  "properties": {
    "iso:country":"US",
    "sg:address":"2500 Wilcrest Dr",
    "sg:city":"Houston",
    "sg:classifiers":[
        {
            "category":"Professional",
            "subcategory":"Management & Consulting",
            "type":"Services"
        }
    ],
    "sg:phone":"+1 713 954 7250",
    "sg:postcode":"77042",
    "sg:province":"TX",
    "sg:tags":[
        "consultant",
        "energy",
        "conservation"
    ],
    "wof:name":"Whitworth Resources Inc",
    "wof:placetype":"venue"
},
  "geometry": {"coordinates":[-95.571854,29.737052],"type":"Point"}
}