{
  "type": "Feature",
  "properties": {
    "iso:country":"US",
    "sg:address":"217 W Hickman Ave",
    "sg:city":"Port Isabel",
    "sg:classifiers":[
        {
            "category":"Building & Trades",
            "subcategory":"Construction",
            "type":"Services"
        }
    ],
    "sg:phone":"+1 956 943 6631",
    "sg:postcode":"78578",
    "sg:province":"TX",
    "sg:tags":[
        "marking",
        "maintenance",
        "parking"
    ],
    "wof:name":"Port Isabel Public Works Div",
    "wof:placetype":"venue"
},
  "geometry": {"coordinates":[-97.21024300000001,26.073475],"type":"Point"}
}