{
  "type": "Feature",
  "properties": {
    "iso:country":"US",
    "sg:address":"6114 Faringdon Ln",
    "sg:city":"Rowlett",
    "sg:classifiers":[
        {
            "category":"Real Estate",
            "subcategory":"Architect",
            "type":"Services"
        }
    ],
    "sg:phone":"+1 972 412 2074",
    "sg:postcode":"75089",
    "sg:province":"TX",
    "sg:tags":[
        "architectural"
    ],
    "wof:name":"AB Architects Inc",
    "wof:placetype":"venue"
},
  "geometry": {"coordinates":[-96.577218,32.915807],"type":"Point"}
}