{
  "type": "Feature",
  "properties": {
    "iso:country":"US",
    "sg:address":"2207 Michigan Ave",
    "sg:city":"Arlington",
    "sg:classifiers":[
        {
            "category":"Health Services",
            "subcategory":"Chiropractor",
            "type":"Services"
        }
    ],
    "sg:phone":"+1 817 469 6840",
    "sg:postcode":"76013",
    "sg:province":"TX",
    "wof:name":"Kurban Chiropractic Health",
    "wof:placetype":"venue"
},
  "geometry": {"coordinates":[-97.157155,32.707014],"type":"Point"}
}