{
  "type": "Feature",
  "properties": {
    "iso:country":"US",
    "sg:address":"5933 Gateway Blvd W",
    "sg:city":"El Paso",
    "sg:classifiers":[
        {
            "category":"Shopping",
            "type":"Retail Goods"
        }
    ],
    "sg:phone":"+1 915 775 0113",
    "sg:postcode":"79925",
    "sg:province":"TX",
    "sg:tags":[
        "religious"
    ],
    "wof:name":"Madonna Shop",
    "wof:placetype":"venue"
},
  "geometry": {"coordinates":[-106.41509600000001,31.781639],"type":"Point"}
}