{
  "type": "Feature",
  "properties": {
    "iso:country":"US",
    "sg:address":"2626 NW 18th St",
    "sg:city":"Fort Worth",
    "sg:classifiers":[
        {
            "category":"Real Estate",
            "subcategory":"Real Estate Operator",
            "type":"Services"
        }
    ],
    "sg:phone":"+1 817 625 9921",
    "sg:postcode":"76106",
    "sg:province":"TX",
    "sg:tags":[
        "apartment"
    ],
    "wof:name":"Fossil Ridge Apartments",
    "wof:placetype":"venue"
},
  "geometry": {"coordinates":[-97.38452599999999,32.790806],"type":"Point"}
}