{
  "type": "Feature",
  "properties": {
    "iso:country":"US",
    "sg:address":"4500 Bryan St",
    "sg:city":"Dallas",
    "sg:classifiers":[
        {
            "category":"Food & Beverages",
            "subcategory":"Groceries & Convenience Stores",
            "type":"Retail Goods"
        }
    ],
    "sg:phone":"+1 214 826 0234",
    "sg:postcode":"75204",
    "sg:province":"TX",
    "wof:name":"T Grocery",
    "wof:placetype":"venue"
},
  "geometry": {"coordinates":[-96.77770200000001,32.8004],"type":"Point"}
}