{
  "type": "Feature",
  "properties": {
    "iso:country":"US",
    "sg:address":"107 Wahl St",
    "sg:city":"Crosby",
    "sg:classifiers":[
        {
            "category":"Freight",
            "type":"Transportation"
        }
    ],
    "sg:phone":"+1 281 328 3091",
    "sg:postcode":"77532",
    "sg:province":"TX",
    "sg:tags":[
        "trucking"
    ],
    "wof:name":"Codellite Inc",
    "wof:placetype":"venue"
},
  "geometry": {"coordinates":[-95.06372399999999,29.909105],"type":"Point"}
}