{
  "type": "Feature",
  "properties": {
    "iso:country":"US",
    "sg:address":"8303 Westglen Dr",
    "sg:city":"Houston",
    "sg:classifiers":[
        {
            "category":"Shopping",
            "type":"Retail Goods"
        }
    ],
    "sg:phone":"+1 713 785 4646",
    "sg:postcode":"77063",
    "sg:province":"TX",
    "sg:tags":[
        "repair",
        "register",
        "cash"
    ],
    "wof:name":"Cash Register Sls Svcs Houston",
    "wof:placetype":"venue"
},
  "geometry": {"coordinates":[-95.510757,29.724625],"type":"Point"}
}