{
  "type": "Feature",
  "properties": {
    "iso:country":"US",
    "sg:address":"14306 Moorfield Dr",
    "sg:city":"Houston",
    "sg:classifiers":[
        {
            "category":"Restaurant",
            "type":"Food & Drink"
        }
    ],
    "sg:phone":"+1 713 728 1305",
    "sg:postcode":"77083",
    "sg:province":"TX",
    "sg:tags":[
        "eating"
    ],
    "wof:name":"Tacos Guzman",
    "wof:placetype":"venue"
},
  "geometry": {"coordinates":[-95.636646,29.677899],"type":"Point"}
}