{
  "type": "Feature",
  "properties": {
    "iso:country":"US",
    "sg:address":"400 W Hopkins St",
    "sg:city":"San Marcos",
    "sg:classifiers":[
        {
            "category":"Wholesale",
            "subcategory":"Farm Supplies",
            "type":"Manufacturing & Wholesale Goods"
        }
    ],
    "sg:phone":"+1 512 396 0045",
    "sg:postcode":"78666",
    "sg:province":"TX",
    "sg:tags":[
        "broker",
        "cattle"
    ],
    "wof:name":"Longcope Cattle Company Inc",
    "wof:placetype":"venue"
},
  "geometry": {"coordinates":[-97.94551300000001,29.882531],"type":"Point"}
}