{
  "type": "Feature",
  "properties": {
    "iso:country":"US",
    "sg:address":"2906 Cedar Crest Cir",
    "sg:city":"Round Rock",
    "sg:classifiers":[
        {
            "category":"Wholesale",
            "subcategory":"Non-durable Goods",
            "type":"Manufacturing & Wholesale Goods"
        }
    ],
    "sg:phone":"+1 512 671 3778",
    "sg:postcode":"78665",
    "sg:province":"TX",
    "wof:name":"Twin Lights Distribution Incor",
    "wof:placetype":"venue"
},
  "geometry": {"coordinates":[-97.622883,30.514142],"type":"Point"}
}