{
  "type": "Feature",
  "properties": {
    "iso:country":"US",
    "sg:address":"11930 Tavel Cir",
    "sg:city":"Dallas",
    "sg:classifiers":[
        {
            "category":"Professional",
            "subcategory":"Business Services",
            "type":"Services"
        }
    ],
    "sg:phone":"+1 972 239 6832",
    "sg:postcode":"75230",
    "sg:province":"TX",
    "wof:name":"Joan Nstadt Weil Charitable Tr",
    "wof:placetype":"venue"
},
  "geometry": {"coordinates":[-96.803394,32.911957],"type":"Point"}
}