{
  "type": "Feature",
  "properties": {
    "iso:country":"US",
    "sg:address":"16000 Dallas Pkwy Ste 100",
    "sg:city":"Dallas",
    "sg:classifiers":[
        {
            "category":"Wholesale",
            "subcategory":"Computers",
            "type":"Manufacturing & Wholesale Goods"
        }
    ],
    "sg:phone":"+1 972 726 7200",
    "sg:postcode":"75248",
    "sg:province":"TX",
    "sg:website":"www.technologent.com",
    "wof:name":"Technologent",
    "wof:placetype":"venue"
},
  "geometry": {"coordinates":[-96.821073,32.967103],"type":"Point"}
}