{
  "type": "Feature",
  "properties": {
    "iso:country":"US",
    "sg:address":"1908 Bremen St",
    "sg:city":"Austin",
    "sg:classifiers":[
        {
            "category":"Building & Trades",
            "subcategory":"Construction",
            "type":"Services"
        }
    ],
    "sg:phone":"+1 512 481 1158",
    "sg:postcode":"78703",
    "sg:province":"TX",
    "sg:tags":[
        "remodeling",
        "contractor"
    ],
    "wof:name":"Cooper Construction",
    "wof:placetype":"venue"
},
  "geometry": {"coordinates":[-97.764706,30.292593],"type":"Point"}
}