{
  "type": "Feature",
  "properties": {
    "iso:country":"US",
    "sg:address":"2978 Goliad St",
    "sg:city":"Beaumont",
    "sg:classifiers":[
        {
            "category":"Social Services",
            "subcategory":"Child Care",
            "type":"Services"
        }
    ],
    "sg:phone":"+1 409 835 0042",
    "sg:postcode":"77701",
    "sg:province":"TX",
    "wof:name":"Watkins Day Care",
    "wof:placetype":"venue"
},
  "geometry": {"coordinates":[-94.113343,30.057795],"type":"Point"}
}