{
  "type": "Feature",
  "properties": {
    "iso:country":"US",
    "sg:address":"12100 Melville Dr",
    "sg:city":"Montgomery",
    "sg:classifiers":[
        {
            "category":"Personal",
            "subcategory":"Beauty Salon",
            "type":"Services"
        }
    ],
    "sg:phone":"+1 936 582 6803",
    "sg:postcode":"77356",
    "sg:province":"TX",
    "sg:tags":[
        "shop"
    ],
    "wof:name":"Hammers & Nails",
    "wof:placetype":"venue"
},
  "geometry": {"coordinates":[-95.60367100000001,30.39951],"type":"Point"}
}