{
  "type": "Feature",
  "properties": {
    "iso:country":"US",
    "sg:address":"5037 State Hwy 123",
    "sg:city":"Seguin",
    "sg:classifiers":[
        {
            "category":"Building & Trades",
            "subcategory":"Construction",
            "type":"Services"
        }
    ],
    "sg:phone":"+1 830 303 9640",
    "sg:postcode":"78155",
    "sg:province":"TX",
    "sg:tags":[
        "swimming",
        "designer",
        "dealer",
        "pool",
        "contractor"
    ],
    "wof:name":"Above Ground Pool Pro's",
    "wof:placetype":"venue"
},
  "geometry": {"coordinates":[-97.967136,29.635991],"type":"Point"}
}