{
  "type": "Feature",
  "properties": {
    "iso:country":"US",
    "sg:address":"4293 Pleasant Run Rd",
    "sg:city":"Irving",
    "sg:classifiers":[
        {
            "category":"Shopping",
            "subcategory":"Discount & Variety Stores",
            "type":"Retail Goods"
        }
    ],
    "sg:phone":"+1 972 871 8742",
    "sg:postcode":"75038",
    "sg:province":"TX",
    "sg:tags":[
        "merchandise",
        "general"
    ],
    "wof:name":"Lyons Enterprises",
    "wof:placetype":"venue"
},
  "geometry": {"coordinates":[-96.988603,32.861423],"type":"Point"}
}