{
  "type": "Feature",
  "properties": {
    "iso:country":"US",
    "sg:address":"911 Magnolia Blvd",
    "sg:city":"Odessa",
    "sg:classifiers":[
        {
            "category":"Building & Trades",
            "subcategory":"Construction",
            "type":"Services"
        }
    ],
    "sg:phone":"+1 432 332 0027",
    "sg:postcode":"79761",
    "sg:province":"TX",
    "sg:tags":[
        "water",
        "well",
        "drilling"
    ],
    "wof:name":"Billalba Water Well Svc",
    "wof:placetype":"venue"
},
  "geometry": {"coordinates":[-102.354747,31.840612],"type":"Point"}
}