{
  "type": "Feature",
  "properties": {
    "iso:country":"US",
    "sg:address":"5801 Marvin D Love Fwy",
    "sg:city":"Dallas",
    "sg:classifiers":[
        {
            "category":"Health Services",
            "subcategory":"Clinic",
            "type":"Services"
        }
    ],
    "sg:phone":"+1 214 665 3280",
    "sg:postcode":"75237",
    "sg:province":"TX",
    "sg:tags":[
        "home"
    ],
    "wof:name":"Home Health Svc Of Dallas Inc",
    "wof:placetype":"venue"
},
  "geometry": {"coordinates":[-96.85718,32.676198],"type":"Point"}
}