{
  "type": "Feature",
  "properties": {
    "iso:country":"US",
    "sg:address":"8027 Highway 6",
    "sg:city":"Hitchcock",
    "sg:classifiers":[
        {
            "category":"Autos & Motor Vehicles",
            "subcategory":"Fuel & Gas Station",
            "type":"Retail Goods"
        }
    ],
    "sg:phone":"+1 409 986 7606",
    "sg:postcode":"77563",
    "sg:province":"TX",
    "wof:name":"Williams Arco Serv Statio",
    "wof:placetype":"venue"
},
  "geometry": {"coordinates":[-95.01908,29.349255],"type":"Point"}
}