{
  "type": "Feature",
  "properties": {
    "iso:country":"US",
    "sg:address":"3443 W Campbell Rd",
    "sg:city":"Garland",
    "sg:classifiers":[
        {
            "category":"Personal",
            "subcategory":"Beauty Salon",
            "type":"Services"
        }
    ],
    "sg:phone":"+1 972 675 4446",
    "sg:postcode":"75044",
    "sg:province":"TX",
    "wof:name":"Hair Elite",
    "wof:placetype":"venue"
},
  "geometry": {"coordinates":[-96.680835,32.973193],"type":"Point"}
}