{
  "type": "Feature",
  "properties": {
    "iso:country":"US",
    "sg:address":"404 Sinclair Dr",
    "sg:city":"Spicewood",
    "sg:classifiers":[
        {
            "category":"Real Estate",
            "subcategory":"Architect",
            "type":"Services"
        }
    ],
    "sg:phone":"+1 512 331 5898",
    "sg:postcode":"78669",
    "sg:province":"TX",
    "sg:tags":[
        "architectural"
    ],
    "wof:name":"Ralph A Thibodeau",
    "wof:placetype":"venue"
},
  "geometry": {"coordinates":[-98.039438,30.413061],"type":"Point"}
}