{
  "type": "Feature",
  "properties": {
    "iso:country":"US",
    "sg:address":"1004 Walnut St",
    "sg:city":"Bastrop",
    "sg:classifiers":[
        {
            "category":"Professional",
            "type":"Services"
        }
    ],
    "sg:phone":"+1 512 321 2868",
    "sg:postcode":"78602",
    "sg:province":"TX",
    "wof:name":"Bastrop Cad Services",
    "wof:placetype":"venue"
},
  "geometry": {"coordinates":[-97.316202,30.108508],"type":"Point"}
}