{
  "type": "Feature",
  "properties": {
    "iso:country":"US",
    "sg:address":"7207 Bar K Ranch Rd",
    "sg:city":"Lago Vista",
    "sg:classifiers":[
        {
            "category":"Government",
            "subcategory":"Fire Station",
            "type":"Public Place"
        }
    ],
    "sg:phone":"+1 512 267 1551",
    "sg:postcode":"78645",
    "sg:province":"TX",
    "sg:tags":[
        "department"
    ],
    "wof:name":"Sandy Creek Volunteer Fire",
    "wof:placetype":"venue"
},
  "geometry": {"coordinates":[-97.990897,30.473405],"type":"Point"}
}