{
  "type": "Feature",
  "properties": {
    "iso:country":"US",
    "sg:address":"4301 Memorial Dr",
    "sg:city":"Waco",
    "sg:classifiers":[
        {
            "category":"Education",
            "subcategory":"Special Training",
            "type":"Public Place"
        }
    ],
    "sg:phone":"+1 254 753 2311",
    "sg:postcode":"76711",
    "sg:province":"TX",
    "sg:tags":[
        "instruction",
        "driving"
    ],
    "wof:name":"Affiliated Defensive Driving",
    "wof:placetype":"venue"
},
  "geometry": {"coordinates":[-97.15841899999999,31.517656],"type":"Point"}
}