{
  "type": "Feature",
  "properties": {
    "iso:country":"US",
    "sg:address":"5500 Fall Creek Hwy",
    "sg:city":"Granbury",
    "sg:classifiers":[
        {
            "category":"Professional",
            "subcategory":"Business Services",
            "type":"Services"
        }
    ],
    "sg:phone":"+1 817 326 2185",
    "sg:postcode":"76049",
    "sg:province":"TX",
    "sg:tags":[
        "consultant",
        "coach"
    ],
    "wof:name":"Martin Consulting Eng",
    "wof:placetype":"venue"
},
  "geometry": {"coordinates":[-97.670776,32.421822],"type":"Point"}
}