{
  "type": "Feature",
  "properties": {
    "iso:country":"US",
    "sg:address":"1802 N Main St",
    "sg:city":"Tahoka",
    "sg:classifiers":[
        {
            "category":"Fast Food",
            "type":"Food & Drink"
        },
        {
            "category":"Restaurant",
            "type":"Food & Drink"
        }
    ],
    "sg:phone":"+1 806 998 4850",
    "sg:postcode":"79373",
    "sg:province":"TX",
    "sg:tags":[
        "take"
    ],
    "wof:name":"Dixie Dog Drive Inn",
    "wof:placetype":"venue"
},
  "geometry": {"coordinates":[-101.796097,33.167415],"type":"Point"}
}