{
  "type": "Feature",
  "properties": {
    "iso:country":"US",
    "sg:address":"35407 State Hwy 249",
    "sg:city":"Pinehurst",
    "sg:classifiers":[
        {
            "category":"Restaurant",
            "type":"Food & Drink"
        }
    ],
    "sg:phone":"+1 281 356 7180",
    "sg:postcode":"77362",
    "sg:province":"TX",
    "sg:tags":[
        "barbecue"
    ],
    "wof:name":"P & P Bar-B-Que",
    "wof:placetype":"venue"
},
  "geometry": {"coordinates":[-95.68207700000001,30.170552],"type":"Point"}
}