{
  "type": "Feature",
  "properties": {
    "iso:country":"US",
    "sg:address":"605 E Main St",
    "sg:city":"Madisonville",
    "sg:classifiers":[
        {
            "category":"Real Estate",
            "subcategory":"Real Estate Agent",
            "type":"Services"
        }
    ],
    "sg:phone":"+1 936 348 5554",
    "sg:postcode":"77864",
    "sg:province":"TX",
    "wof:name":"Brogdon Real Estate",
    "wof:placetype":"venue"
},
  "geometry": {"coordinates":[-95.909659,30.950918],"type":"Point"}
}