{
  "type": "Feature",
  "properties": {
    "iso:country":"US",
    "sg:address":"1706 Evergreen St",
    "sg:city":"Amarillo",
    "sg:classifiers":[
        {
            "category":"Organizations",
            "subcategory":"Religious Organization",
            "type":"Services"
        }
    ],
    "sg:phone":"+1 806 383 1345",
    "sg:postcode":"79107",
    "sg:province":"TX",
    "sg:tags":[
        "church"
    ],
    "wof:name":"Iglesia De Cristo",
    "wof:placetype":"venue"
},
  "geometry": {"coordinates":[-101.768055,35.231386],"type":"Point"}
}