{
  "type": "Feature",
  "properties": {
    "iso:country":"US",
    "sg:address":"5511 Parkcrest Dr Ste 207",
    "sg:city":"Austin",
    "sg:classifiers":[
        {
            "category":"Building & Trades",
            "subcategory":"Landscaping Services",
            "type":"Services"
        }
    ],
    "sg:phone":"+1 512 329 9833",
    "sg:postcode":"78731",
    "sg:province":"TX",
    "sg:tags":[
        "consultant",
        "designer",
        "landscape"
    ],
    "wof:name":"Boedy Alexander Associates",
    "wof:placetype":"venue"
},
  "geometry": {"coordinates":[-97.75863200000001,30.336469],"type":"Point"}
}