{
  "type": "Feature",
  "properties": {
    "iso:country":"US",
    "sg:address":"5194 Mitchell-Saxon Rd",
    "sg:city":"Fort Worth",
    "sg:classifiers":[
        {
            "category":"Shopping",
            "subcategory":"Crafts & Fabrics",
            "type":"Retail Goods"
        }
    ],
    "sg:phone":"+1 817 478 8881",
    "sg:postcode":"76140",
    "sg:province":"TX",
    "sg:tags":[
        "sewing"
    ],
    "wof:name":"Rebecca Designs",
    "wof:placetype":"venue"
},
  "geometry": {"coordinates":[-97.246211,32.596312],"type":"Point"}
}