{
  "type": "Feature",
  "properties": {
    "iso:country":"US",
    "sg:address":"713 N Mechanic St",
    "sg:city":"El Campo",
    "sg:classifiers":[
        {
            "category":"Shopping",
            "type":"Retail Goods"
        }
    ],
    "sg:phone":"+1 979 543 4331",
    "sg:postcode":"77437",
    "sg:province":"TX",
    "sg:tags":[
        "picture",
        "frame"
    ],
    "wof:name":"Bishop Enterprises",
    "wof:placetype":"venue"
},
  "geometry": {"coordinates":[-96.271683,29.198825],"type":"Point"}
}