{
  "type": "Feature",
  "properties": {
    "iso:country":"US",
    "sg:address":"4109 Hartford Dr",
    "sg:city":"Garland",
    "sg:classifiers":[
        {
            "category":"Shopping",
            "subcategory":"Used Merchandise",
            "type":"Retail Goods"
        }
    ],
    "sg:phone":"+1 972 864 0965",
    "sg:postcode":"75043",
    "sg:province":"TX",
    "wof:name":"Brokenglass Antiques",
    "wof:placetype":"venue"
},
  "geometry": {"coordinates":[-96.617093,32.861765],"type":"Point"}
}