{
  "type": "Feature",
  "properties": {
    "iso:country":"US",
    "sg:address":"410 Hoover St",
    "sg:city":"Taft",
    "sg:classifiers":[
        {
            "category":"Restaurant",
            "type":"Food & Drink"
        }
    ],
    "sg:phone":"+1 361 528 3200",
    "sg:postcode":"78390",
    "sg:province":"TX",
    "wof:name":"Ruck's Barbecue",
    "wof:placetype":"venue"
},
  "geometry": {"coordinates":[-97.393091,27.98273],"type":"Point"}
}