{
  "type": "Feature",
  "properties": {
    "iso:country":"US",
    "sg:address":"2010 W 44th St",
    "sg:city":"Odessa",
    "sg:classifiers":[
        {
            "category":"Home & Garden",
            "subcategory":"Building Materials",
            "type":"Retail Goods"
        }
    ],
    "sg:phone":"+1 432 368 7911",
    "sg:postcode":"79764",
    "sg:province":"TX",
    "wof:name":"B & B U-Cart Concrete",
    "wof:placetype":"venue"
},
  "geometry": {"coordinates":[-102.403809,31.881393],"type":"Point"}
}