{
  "type": "Feature",
  "properties": {
    "iso:country":"US",
    "sg:address":"103 S Main St",
    "sg:city":"Yantis",
    "sg:classifiers":[
        {
            "category":"Shopping",
            "subcategory":"Bicycles & Sporting Goods",
            "type":"Retail Goods"
        }
    ],
    "sg:phone":"+1 903 383 7293",
    "sg:postcode":"75438",
    "sg:province":"TX",
    "sg:tags":[
        "gun",
        "gunsmith"
    ],
    "wof:name":"Lake Fork Archery Shop",
    "wof:placetype":"venue"
},
  "geometry": {"coordinates":[-96.07589,33.573192],"type":"Point"}
}