{
  "type": "Feature",
  "properties": {
    "iso:country":"US",
    "sg:address":"450 SW Avenue E F F",
    "sg:city":"Hamlin",
    "sg:classifiers":[
        {
            "category":"Education",
            "subcategory":"School",
            "type":"Public Place"
        }
    ],
    "sg:phone":"+1 325 576 3624",
    "sg:postcode":"79520",
    "sg:province":"TX",
    "sg:tags":[
        "high"
    ],
    "wof:name":"Hamlin High School",
    "wof:placetype":"venue"
},
  "geometry": {"coordinates":[-100.130931,32.87823],"type":"Point"}
}