{
  "type": "Feature",
  "properties": {
    "iso:country":"US",
    "sg:address":"7151 Lorna Rd",
    "sg:city":"Montgomery",
    "sg:classifiers":[
        {
            "category":"Mining & Drilling",
            "type":"Manufacturing & Wholesale Goods"
        }
    ],
    "sg:phone":"+1 936 447 3629",
    "sg:postcode":"77316",
    "sg:province":"TX",
    "sg:tags":[
        "field"
    ],
    "wof:name":"Tramel Evaluations Inc",
    "wof:placetype":"venue"
},
  "geometry": {"coordinates":[-95.581919,30.274751],"type":"Point"}
}