{
  "type": "Feature",
  "properties": {
    "iso:country":"US",
    "sg:address":"8505 Sea Ash Cir",
    "sg:city":"Round Rock",
    "sg:classifiers":[
        {
            "category":"Professional",
            "subcategory":"Business Services",
            "type":"Services"
        }
    ],
    "sg:phone":"+1 512 733 8858",
    "sg:postcode":"78681",
    "sg:province":"TX",
    "wof:name":"Antur LLC",
    "wof:placetype":"venue"
},
  "geometry": {"coordinates":[-97.725899,30.522659],"type":"Point"}
}