{
  "type": "Feature",
  "properties": {
    "iso:country":"US",
    "sg:address":"1010 Center St",
    "sg:city":"Deer Park",
    "sg:classifiers":[
        {
            "category":"Wholesale",
            "subcategory":"Durable Goods & Equipment",
            "type":"Manufacturing & Wholesale Goods"
        }
    ],
    "sg:phone":"+1 281 479 5949",
    "sg:postcode":"77536",
    "sg:province":"TX",
    "wof:name":"Mid-Continent Safety LLC",
    "wof:placetype":"venue"
},
  "geometry": {"coordinates":[-95.12388900000001,29.702786],"type":"Point"}
}