{
  "type": "Feature",
  "properties": {
    "iso:country":"US",
    "sg:address":"201 McClellan Cir",
    "sg:city":"Humble",
    "sg:classifiers":[
        {
            "category":"Organizations",
            "subcategory":"Religious Organization",
            "type":"Services"
        }
    ],
    "sg:phone":"+1 281 358 9711",
    "sg:postcode":"77339",
    "sg:province":"TX",
    "sg:tags":[
        "church"
    ],
    "wof:name":"Harvest Church",
    "wof:placetype":"venue"
},
  "geometry": {"coordinates":[-95.262362,30.040247],"type":"Point"}
}