{
  "type": "Feature",
  "properties": {
    "iso:country":"US",
    "sg:address":"13934 Lighthouse Dr",
    "sg:city":"Corpus Christi",
    "sg:classifiers":[
        {
            "category":"Professional",
            "type":"Services"
        }
    ],
    "sg:phone":"+1 361 949 1488",
    "sg:postcode":"78418",
    "sg:province":"TX",
    "wof:name":"Valtel Communications",
    "wof:placetype":"venue"
},
  "geometry": {"coordinates":[-97.229936,27.614313],"type":"Point"}
}