{
  "type": "Feature",
  "properties": {
    "iso:country":"US",
    "sg:address":"602 Katherine Ct",
    "sg:city":"Duncanville",
    "sg:classifiers":[
        {
            "category":"Shopping",
            "subcategory":"Used Merchandise",
            "type":"Retail Goods"
        }
    ],
    "sg:phone":"+1 972 296 1353",
    "sg:postcode":"75137",
    "sg:province":"TX",
    "sg:tags":[
        "antique"
    ],
    "wof:name":"Handy's House",
    "wof:placetype":"venue"
},
  "geometry": {"coordinates":[-96.896497,32.64207],"type":"Point"}
}