{
  "type": "Feature",
  "properties": {
    "iso:country":"US",
    "sg:address":"1533 Austin Hwy",
    "sg:city":"San Antonio",
    "sg:classifiers":[
        {
            "category":"Personal",
            "subcategory":"Beauty Salon",
            "type":"Services"
        }
    ],
    "sg:phone":"+1 210 930 5300",
    "sg:postcode":"78218",
    "sg:province":"TX",
    "wof:name":"Fantastic Sams",
    "wof:placetype":"venue"
},
  "geometry": {"coordinates":[-98.431629,29.494721],"type":"Point"}
}