{
  "type": "Feature",
  "properties": {
    "iso:country":"US",
    "sg:address":"6503 Wanda Ln",
    "sg:city":"Houston",
    "sg:classifiers":[
        {
            "category":"Social Services",
            "subcategory":"Child Care",
            "type":"Services"
        }
    ],
    "sg:phone":"+1 713 779 6391",
    "sg:postcode":"77074",
    "sg:province":"TX",
    "wof:name":"Foster's Playhouse",
    "wof:placetype":"venue"
},
  "geometry": {"coordinates":[-95.50863699999999,29.678629],"type":"Point"}
}