{
  "type": "Feature",
  "properties": {
    "iso:country":"US",
    "sg:address":"5821 Beverlyhill St",
    "sg:city":"Houston",
    "sg:classifiers":[
        {
            "category":"Professional",
            "subcategory":"Testing Lab",
            "type":"Services"
        }
    ],
    "sg:phone":"+1 281 266 1849",
    "sg:postcode":"77057",
    "sg:province":"TX",
    "sg:tags":[
        "laboratory"
    ],
    "wof:name":"Energistics Laboratory",
    "wof:placetype":"venue"
},
  "geometry": {"coordinates":[-95.483853,29.730092],"type":"Point"}
}