{
  "type": "Feature",
  "properties": {
    "iso:country":"US",
    "sg:address":"1125 E Collins Blvd",
    "sg:city":"Richardson",
    "sg:classifiers":[
        {
            "category":"Shopping",
            "subcategory":"Mobile Phones",
            "type":"Retail Goods"
        }
    ],
    "sg:phone":"+1 972 852 6700",
    "sg:postcode":"75081",
    "sg:province":"TX",
    "wof:name":"Spectra Point WireleSS",
    "wof:placetype":"venue"
},
  "geometry": {"coordinates":[-96.705279,32.968177],"type":"Point"}
}