{
  "type": "Feature",
  "properties": {
    "iso:country":"US",
    "sg:address":"5110 Walnut Hills Dr",
    "sg:city":"Humble",
    "sg:classifiers":[
        {
            "category":"Professional",
            "type":"Services"
        }
    ],
    "sg:phone":"+1 281 360 4563",
    "sg:postcode":"77345",
    "sg:province":"TX",
    "wof:name":"Kingwood Shipholding Inc",
    "wof:placetype":"venue"
},
  "geometry": {"coordinates":[-95.17036899999999,30.058888],"type":"Point"}
}