{
  "type": "Feature",
  "properties": {
    "iso:country":"US",
    "sg:address":"511 E 114",
    "sg:city":"Irving",
    "sg:classifiers":[
        {
            "category":"Health Services",
            "subcategory":"Doctor",
            "type":"Services"
        },
        {
            "category":"Health Services",
            "subcategory":"Clinic",
            "type":"Services"
        }
    ],
    "sg:phone":"+1 972 869 2954",
    "sg:postcode":"75039",
    "sg:province":"TX",
    "sg:tags":[
        "counseling",
        "mental"
    ],
    "wof:name":"Abbott Donna PHD",
    "wof:placetype":"venue"
},
  "geometry": {"coordinates":[-96.9496,32.883598],"type":"Point"}
}