{
  "type": "Feature",
  "properties": {
    "iso:country":"US",
    "sg:address":"5307 Mulberry Grove Dr",
    "sg:city":"Humble",
    "sg:classifiers":[
        {
            "category":"Manufacturing",
            "subcategory":"Printing",
            "type":"Manufacturing & Wholesale Goods"
        }
    ],
    "sg:phone":"+1 281 361 4445",
    "sg:postcode":"77345",
    "sg:province":"TX",
    "sg:tags":[
        "mfg"
    ],
    "wof:name":"Nancy D Wallace",
    "wof:placetype":"venue"
},
  "geometry": {"coordinates":[-95.16762900000001,30.05744],"type":"Point"}
}