{
  "type": "Feature",
  "properties": {
    "iso:country":"US",
    "sg:address":"108 N 15th St",
    "sg:city":"Canyon",
    "sg:classifiers":[
        {
            "category":"Retail",
            "subcategory":"Auto Repair",
            "type":"Services"
        }
    ],
    "sg:phone":"+1 806 655 4794",
    "sg:postcode":"79015",
    "sg:province":"TX",
    "sg:tags":[
        "body",
        "shop",
        "painting",
        "repairing",
        "automobile"
    ],
    "wof:name":"Texas Body Shop",
    "wof:placetype":"venue"
},
  "geometry": {"coordinates":[-101.929001,34.983398],"type":"Point"}
}