{
  "type": "Feature",
  "properties": {
    "iso:country":"US",
    "sg:address":"30 Beachcomber Dr",
    "sg:city":"Belton",
    "sg:classifiers":[
        {
            "category":"Professional",
            "subcategory":"Lawyer & Legal Services",
            "type":"Services"
        }
    ],
    "sg:phone":"+1 254 289 9076",
    "sg:postcode":"76513",
    "sg:province":"TX",
    "wof:name":"Ross G Lavin",
    "wof:placetype":"venue"
},
  "geometry": {"coordinates":[-97.470772,31.15042],"type":"Point"}
}