{
  "type": "Feature",
  "properties": {
    "iso:country":"US",
    "sg:address":"2414 Empire Central",
    "sg:city":"Dallas",
    "sg:classifiers":[
        {
            "category":"Building & Trades",
            "subcategory":"Construction",
            "type":"Services"
        }
    ],
    "sg:phone":"+1 214 351 0074",
    "sg:postcode":"75235",
    "sg:province":"TX",
    "sg:tags":[
        "nonresidential"
    ],
    "wof:name":"Re Creations",
    "wof:placetype":"venue"
},
  "geometry": {"coordinates":[-96.848403,32.831285],"type":"Point"}
}