{
  "type": "Feature",
  "properties": {
    "iso:country":"US",
    "sg:address":"5310 Stuyvesant Ln",
    "sg:city":"Houston",
    "sg:classifiers":[
        {
            "category":"Banks & Credit Unions",
            "subcategory":"Financial Services",
            "type":"Services"
        }
    ],
    "sg:phone":"+1 713 649 2574",
    "sg:postcode":"77021",
    "sg:province":"TX",
    "sg:tags":[
        "investing",
        "real estate"
    ],
    "wof:name":"JW Properties",
    "wof:placetype":"venue"
},
  "geometry": {"coordinates":[-95.32985600000001,29.700306],"type":"Point"}
}