{
  "type": "Feature",
  "properties": {
    "iso:country":"US",
    "sg:address":"12915 FM 306",
    "sg:city":"Canyon Lake",
    "sg:classifiers":[
        {
            "category":"Travel",
            "subcategory":"Hotels & Motels",
            "type":"Entertainment"
        }
    ],
    "sg:phone":"+1 830 964 3731",
    "sg:postcode":"78133",
    "sg:province":"TX",
    "sg:website":"www.maricoparesort.com",
    "wof:name":"Maricopa Ranch Resort",
    "wof:placetype":"venue"
},
  "geometry": {"coordinates":[-98.17221600000001,29.865817],"type":"Point"}
}