{
  "type": "Feature",
  "properties": {
    "iso:country":"US",
    "sg:address":"13521 Method St",
    "sg:city":"Dallas",
    "sg:classifiers":[
        {
            "category":"Manufacturing",
            "subcategory":"Chemicals & Compounds",
            "type":"Manufacturing & Wholesale Goods"
        }
    ],
    "sg:phone":"+1 972 437 3642",
    "sg:postcode":"75243",
    "sg:province":"TX",
    "sg:tags":[
        "industrial",
        "gas",
        "mfg"
    ],
    "wof:name":"Air Products",
    "wof:placetype":"venue"
},
  "geometry": {"coordinates":[-96.747213,32.932428],"type":"Point"}
}