{
  "type": "Feature",
  "properties": {
    "iso:country":"US",
    "sg:address":"619 S Fleishel Ave",
    "sg:city":"Tyler",
    "sg:classifiers":[
        {
            "category":"Health Services",
            "subcategory":"Doctor",
            "type":"Services"
        }
    ],
    "sg:phone":"+1 903 510 8782",
    "sg:postcode":"75701",
    "sg:province":"TX",
    "sg:tags":[
        "osteopathic"
    ],
    "wof:name":"J Ross Tanner Do",
    "wof:placetype":"venue"
},
  "geometry": {"coordinates":[-95.288782,32.342488],"type":"Point"}
}