{
  "type": "Feature",
  "properties": {
    "iso:country":"US",
    "sg:address":"420 E 7th St",
    "sg:city":"Dalhart",
    "sg:classifiers":[
        {
            "category":"Health Services",
            "subcategory":"Health Practitioner",
            "type":"Services"
        }
    ],
    "sg:phone":"+1 806 244 2154",
    "sg:postcode":"79022",
    "sg:province":"TX",
    "sg:tags":[
        "nutritionist"
    ],
    "wof:name":"FMA Nutrition",
    "wof:placetype":"venue"
},
  "geometry": {"coordinates":[-102.518326,36.059278],"type":"Point"}
}