{
  "type": "Feature",
  "properties": {
    "iso:country":"US",
    "sg:address":"5445 S Hulen St",
    "sg:city":"Fort Worth",
    "sg:classifiers":[
        {
            "category":"Shopping",
            "subcategory":"Florist",
            "type":"Retail Goods"
        }
    ],
    "sg:phone":"+1 817 924 4206",
    "sg:postcode":"76132",
    "sg:province":"TX",
    "wof:name":"Rothermel Flowers & Gifts",
    "wof:placetype":"venue"
},
  "geometry": {"coordinates":[-97.39992700000001,32.670284],"type":"Point"}
}