{
  "type": "Feature",
  "properties": {
    "iso:country":"US",
    "sg:address":"3301 S Shepherd Dr",
    "sg:city":"Houston",
    "sg:phone":"+1 713 874 0111",
    "sg:postcode":"77098",
    "sg:province":"TX",
    "wof:name":"MRI Central Houston",
    "wof:placetype":"venue"
},
  "geometry": {"coordinates":[-95.41069,29.73682],"type":"Point"}
}