{
  "type": "Feature",
  "properties": {
    "iso:country":"US",
    "sg:address":"6959 Arapaho Rd",
    "sg:city":"Dallas",
    "sg:classifiers":[
        {
            "category":"Personal",
            "subcategory":"Beauty Salon",
            "type":"Services"
        }
    ],
    "sg:phone":"+1 972 991 2492",
    "sg:postcode":"75248",
    "sg:province":"TX",
    "sg:tags":[
        "nail",
        "shop",
        "manicuring"
    ],
    "wof:name":"Nails by Shanaz",
    "wof:placetype":"venue"
},
  "geometry": {"coordinates":[-96.78939800000001,32.9622],"type":"Point"}
}