{
  "type": "Feature",
  "properties": {
    "iso:country":"US",
    "sg:address":"249 E Grange St",
    "sg:city":"La Grange",
    "sg:classifiers":[
        {
            "category":"Insurance",
            "subcategory":"Insurance Agent",
            "type":"Services"
        }
    ],
    "sg:phone":"+1 979 968 8863",
    "sg:postcode":"78962",
    "sg:province":"TX",
    "wof:name":"Germania Farm Mutual Insurance",
    "wof:placetype":"venue"
},
  "geometry": {"coordinates":[-96.77841100000001,29.704525],"type":"Point"}
}