{
  "type": "Feature",
  "properties": {
    "iso:country":"US",
    "sg:address":"1016 La Posada Drive Suite 140",
    "sg:city":"Austin",
    "sg:classifiers":[
        {
            "category":"Professional",
            "subcategory":"Lawyer & Legal Services",
            "type":"Services"
        }
    ],
    "sg:phone":"+1 512 458 4138",
    "sg:postcode":"78752",
    "sg:province":"TX",
    "wof:name":"Hansen & Associates",
    "wof:placetype":"venue"
},
  "geometry": {"coordinates":[-97.702467,30.325662],"type":"Point"}
}