{
  "type": "Feature",
  "properties": {
    "iso:country":"US",
    "sg:address":"755 S Guadalupe St",
    "sg:city":"Seguin",
    "sg:classifiers":[
        {
            "category":"Wholesale",
            "subcategory":"Auto Parts",
            "type":"Manufacturing & Wholesale Goods"
        }
    ],
    "sg:phone":"+1 830 303 7539",
    "sg:postcode":"78155",
    "sg:province":"TX",
    "sg:tags":[
        "tire"
    ],
    "wof:name":"Herman's Tire Shop",
    "wof:placetype":"venue"
},
  "geometry": {"coordinates":[-97.969425,29.562809],"type":"Point"}
}