{
  "type": "Feature",
  "properties": {
    "iso:country":"US",
    "sg:address":"235 Double Oaks Dr",
    "sg:city":"Lewisville",
    "sg:classifiers":[
        {
            "category":"Wholesale",
            "subcategory":"Durable Goods & Equipment",
            "type":"Manufacturing & Wholesale Goods"
        }
    ],
    "sg:phone":"+1 469 948 0081",
    "sg:postcode":"75077",
    "sg:province":"TX",
    "wof:name":"Gayle M Saathoff",
    "wof:placetype":"venue"
},
  "geometry": {"coordinates":[-97.12056800000001,33.062305],"type":"Point"}
}