{
  "type": "Feature",
  "properties": {
    "iso:country":"US",
    "sg:address":"2507 E 11th St",
    "sg:city":"Odessa",
    "sg:phone":"+1 432 333 1016",
    "sg:postcode":"79761",
    "sg:province":"TX",
    "sg:tags":[
        "equipment",
        "commercial",
        "vehicle"
    ],
    "wof:name":"S&K Merchant Services",
    "wof:placetype":"venue"
},
  "geometry": {"coordinates":[-102.34054999999999,31.864848],"type":"Point"}
}