{
  "type": "Feature",
  "properties": {
    "iso:country":"US",
    "sg:address":"1301 E Jasmine Ave",
    "sg:city":"Mcallen",
    "sg:classifiers":[
        {
            "category":"Internet Cafe",
            "subcategory":"None",
            "type":"Food & Drink"
        },
        {
            "category":"Utilities",
            "subcategory":"Telephone",
            "type":"Services"
        },
        {
            "category":"Professional",
            "subcategory":"Computer Services",
            "type":"Services"
        }
    ],
    "sg:phone":"+1 956 739 4392",
    "sg:postcode":"78501",
    "sg:province":"TX",
    "sg:tags":[
        "product",
        "designer",
        "network",
        "consultant",
        "system",
        "equipment",
        "design",
        "software"
    ],
    "wof:name":"Tech Synergy Solutions",
    "wof:placetype":"venue"
},
  "geometry": {"coordinates":[-98.205552,26.20952],"type":"Point"}
}