{
  "type": "Feature",
  "properties": {
    "iso:country":"US",
    "sg:address":"315 Gentry St",
    "sg:city":"Spring",
    "sg:classifiers":[
        {
            "category":"Professional",
            "subcategory":"Advertising",
            "type":"Services"
        }
    ],
    "sg:phone":"+1 281 350 1989",
    "sg:postcode":"77373",
    "sg:province":"TX",
    "sg:website":"www.buzzbuy.com",
    "wof:name":"BUZZBUY.COM",
    "wof:placetype":"venue"
},
  "geometry": {"coordinates":[-95.41981699999999,30.078618],"type":"Point"}
}