{
  "type": "Feature",
  "properties": {
    "iso:country":"US",
    "sg:address":"301 Kirk Rd",
    "sg:city":"Midlothian",
    "sg:classifiers":[
        {
            "category":"Banks & Credit Unions",
            "subcategory":"Bank",
            "type":"Services"
        }
    ],
    "sg:phone":"+1 972 723 3830",
    "sg:postcode":"76065",
    "sg:province":"TX",
    "sg:tags":[
        "mortgage"
    ],
    "wof:name":"First Service Mortgage",
    "wof:placetype":"venue"
},
  "geometry": {"coordinates":[-96.96417700000001,32.484054],"type":"Point"}
}