{
  "type": "Feature",
  "properties": {
    "iso:country":"US",
    "sg:address":"15300 Midway Rd",
    "sg:city":"Addison",
    "sg:classifiers":[
        {
            "category":"Autos & Motor Vehicles",
            "subcategory":"Automobile Sales",
            "type":"Retail Goods"
        }
    ],
    "sg:phone":"+1 972 702 0011",
    "sg:postcode":"75001",
    "sg:province":"TX",
    "sg:tags":[
        "dealers-used",
        "car",
        "used",
        "cars-wholesale",
        "new"
    ],
    "wof:name":"Midway Auto Group",
    "wof:placetype":"venue"
},
  "geometry": {"coordinates":[-96.838463,32.958069],"type":"Point"}
}