{
  "type": "Feature",
  "properties": {
    "iso:country":"US",
    "sg:address":"7630 Pebble Dr",
    "sg:city":"Fort Worth",
    "sg:classifiers":[
        {
            "category":"Professional",
            "type":"Services"
        }
    ],
    "sg:phone":"+1 817 284 8032",
    "sg:postcode":"76118",
    "sg:province":"TX",
    "sg:tags":[
        "establishment"
    ],
    "wof:name":"Airsopure",
    "wof:placetype":"venue"
},
  "geometry": {"coordinates":[-97.216027,32.792848],"type":"Point"}
}