{
  "type": "Feature",
  "properties": {
    "iso:country":"US",
    "sg:address":"166 Jefferson St",
    "sg:city":"Eagle Pass",
    "sg:classifiers":[
        {
            "category":"Home & Garden",
            "subcategory":"Furniture",
            "type":"Retail Goods"
        }
    ],
    "sg:phone":"+1 830 773 9222",
    "sg:postcode":"78852",
    "sg:province":"TX",
    "wof:name":"L F D Home Furnishings",
    "wof:placetype":"venue"
},
  "geometry": {"coordinates":[-100.502662,28.706287],"type":"Point"}
}