{
  "type": "Feature",
  "properties": {
    "iso:country":"US",
    "sg:address":"7451 McCart Ave",
    "sg:city":"Fort Worth",
    "sg:classifiers":[
        {
            "category":"Utilities",
            "subcategory":"Mobile Phone",
            "type":"Services"
        }
    ],
    "sg:phone":"+1 817 370 7584",
    "sg:postcode":"76133",
    "sg:province":"TX",
    "sg:tags":[
        "telephone",
        "cellular"
    ],
    "wof:name":"Cingular Wireless",
    "wof:placetype":"venue"
},
  "geometry": {"coordinates":[-97.369784,32.636732],"type":"Point"}
}