{
  "type": "Feature",
  "properties": {
    "iso:country":"US",
    "sg:address":"7215 Eldridge Meadow Ct",
    "sg:city":"Houston",
    "sg:classifiers":[
        {
            "category":"Professional",
            "subcategory":"Management & Consulting",
            "type":"Services"
        }
    ],
    "sg:phone":"+1 713 459 1340",
    "sg:postcode":"77041",
    "sg:province":"TX",
    "sg:tags":[
        "business"
    ],
    "wof:name":"Accutax",
    "wof:placetype":"venue"
},
  "geometry": {"coordinates":[-95.61329600000001,29.882771],"type":"Point"}
}