{
  "type": "Feature",
  "properties": {
    "iso:country":"US",
    "sg:address":"109 N Reagan St",
    "sg:city":"West",
    "sg:classifiers":[
        {
            "category":"Health Services",
            "subcategory":"Chiropractor",
            "type":"Services"
        }
    ],
    "sg:phone":"+1 254 826 3737",
    "sg:postcode":"76691",
    "sg:province":"TX",
    "wof:name":"Mellgren Chiropractic Clinic",
    "wof:placetype":"venue"
},
  "geometry": {"coordinates":[-97.094052,31.802891],"type":"Point"}
}