{
  "type": "Feature",
  "properties": {
    "iso:country":"US",
    "sg:address":"2706 Wingate Cir",
    "sg:city":"College Station",
    "sg:classifiers":[
        {
            "category":"Building & Trades",
            "subcategory":"Construction",
            "type":"Services"
        }
    ],
    "sg:phone":"+1 979 693 8584",
    "sg:postcode":"77845",
    "sg:province":"TX",
    "sg:tags":[
        "house"
    ],
    "wof:name":"Armatys Construction",
    "wof:placetype":"venue"
},
  "geometry": {"coordinates":[-96.29706899999999,30.629256],"type":"Point"}
}