{
  "type": "Feature",
  "properties": {
    "iso:country":"US",
    "sg:address":"130 Trade Center Dr",
    "sg:city":"New Braunfels",
    "sg:classifiers":[
        {
            "category":"Health Services",
            "subcategory":"Doctor",
            "type":"Services"
        }
    ],
    "sg:phone":"+1 830 624 7410",
    "sg:postcode":"78130",
    "sg:province":"TX",
    "sg:tags":[
        "clinic"
    ],
    "wof:name":"Stenbarr Medical",
    "wof:placetype":"venue"
},
  "geometry": {"coordinates":[-98.10921399999999,29.68798],"type":"Point"}
}