{
  "type": "Feature",
  "properties": {
    "iso:country":"US",
    "sg:address":"1129 Randy Dr",
    "sg:city":"Irving",
    "sg:classifiers":[
        {
            "category":"Building & Trades",
            "subcategory":"Landscaping Services",
            "type":"Services"
        }
    ],
    "sg:phone":"+1 972 986 5812",
    "sg:postcode":"75060",
    "sg:province":"TX",
    "sg:tags":[
        "lawn",
        "maintenance",
        "grounds"
    ],
    "wof:name":"Jay's Enterprise",
    "wof:placetype":"venue"
},
  "geometry": {"coordinates":[-96.973339,32.802554],"type":"Point"}
}