{
  "type": "Feature",
  "properties": {
    "iso:country":"US",
    "sg:address":"11200 Lakeline Mall Dr",
    "sg:city":"Cedar Park",
    "sg:classifiers":[
        {
            "category":"Shopping",
            "subcategory":"Computers & Home Electronics",
            "type":"Retail Goods"
        }
    ],
    "sg:phone":"+1 512 257 7416",
    "sg:postcode":"78613",
    "sg:province":"TX",
    "sg:tags":[
        "game",
        "software"
    ],
    "wof:name":"Electronics Boutique",
    "wof:placetype":"venue"
},
  "geometry": {"coordinates":[-97.793848,30.475206],"type":"Point"}
}