{
  "type": "Feature",
  "properties": {
    "iso:country":"US",
    "sg:address":"5959 W Loop S",
    "sg:city":"Houston",
    "sg:classifiers":[
        {
            "category":"Health Services",
            "subcategory":"Doctor",
            "type":"Services"
        },
        {
            "category":"Health Services",
            "subcategory":"Clinic",
            "type":"Services"
        }
    ],
    "sg:phone":"+1 713 621 7001",
    "sg:postcode":"77002",
    "sg:province":"TX",
    "sg:tags":[
        "counseling",
        "mental"
    ],
    "wof:name":"Anderson Merrill P PHD",
    "wof:placetype":"venue"
},
  "geometry": {"coordinates":[-95.459703,29.717249],"type":"Point"}
}