{
  "type": "Feature",
  "properties": {
    "iso:country":"US",
    "sg:address":"814 Spencer Hwy",
    "sg:city":"South Houston",
    "sg:classifiers":[
        {
            "category":"Recreation",
            "type":"Entertainment"
        }
    ],
    "sg:phone":"+1 713 944 7867",
    "sg:postcode":"77587",
    "sg:province":"TX",
    "sg:tags":[
        "club",
        "membership"
    ],
    "wof:name":"O JS Bar",
    "wof:placetype":"venue"
},
  "geometry": {"coordinates":[-95.22062200000001,29.664503],"type":"Point"}
}