{
  "type": "Feature",
  "properties": {
    "iso:country":"US",
    "sg:address":"9800 Hempstead Rd",
    "sg:city":"Houston",
    "sg:classifiers":[
        {
            "category":"Shopping",
            "subcategory":"Shoes",
            "type":"Retail Goods"
        }
    ],
    "sg:phone":"+1 713 263 7009",
    "sg:postcode":"77092",
    "sg:province":"TX",
    "sg:tags":[
        "store"
    ],
    "wof:name":"Rack Room Shoes",
    "wof:placetype":"venue"
},
  "geometry": {"coordinates":[-95.455704,29.7985],"type":"Point"}
}