{
  "type": "Feature",
  "properties": {
    "iso:country":"US",
    "sg:address":"9012 Co Rd 3114",
    "sg:city":"Snyder",
    "sg:phone":"+1 325 573 4882",
    "sg:postcode":"79549",
    "sg:province":"TX",
    "sg:tags":[
        "farming",
        "cotton"
    ],
    "wof:name":"2 B Farms Inc",
    "wof:placetype":"venue"
},
  "geometry": {"coordinates":[-101.06184500000001,32.641822],"type":"Point"}
}