{
  "type": "Feature",
  "properties": {
    "iso:country":"US",
    "sg:address":"2610 Salem Ave",
    "sg:city":"Lubbock",
    "sg:classifiers":[
        {
            "category":"Shopping",
            "subcategory":"Gifts & Souvenirs",
            "type":"Retail Goods"
        }
    ],
    "sg:phone":"+1 806 722 2430",
    "sg:postcode":"79410",
    "sg:province":"TX",
    "wof:name":"This One Is For You",
    "wof:placetype":"venue"
},
  "geometry": {"coordinates":[-101.909189,33.569729],"type":"Point"}
}