{
  "type": "Feature",
  "properties": {
    "iso:country":"US",
    "sg:address":"3007 N Lamar Boulevard",
    "sg:city":"Austin",
    "sg:classifiers":[
        {
            "category":"Health Services",
            "subcategory":"Health Practitioner",
            "type":"Services"
        }
    ],
    "sg:phone":"+1 512 302 5600",
    "sg:postcode":"78705",
    "sg:province":"TX",
    "sg:tags":[
        "acupuncture"
    ],
    "sg:website":"austinfertilitysolution.com/",
    "wof:name":"Cornerstone Acupuncture Clinic",
    "wof:placetype":"venue"
},
  "geometry": {"coordinates":[-97.746726,30.299735],"type":"Point"}
}