{
  "type": "Feature",
  "properties": {
    "iso:country":"US",
    "sg:address":"835 Hunterwood Dr",
    "sg:city":"Jasper",
    "sg:classifiers":[
        {
            "category":"Health Services",
            "subcategory":"Doctor",
            "type":"Services"
        }
    ],
    "sg:phone":"+1 409 384 8560",
    "sg:postcode":"75951",
    "sg:province":"TX",
    "wof:name":"Ronald H Shamblin DDS",
    "wof:placetype":"venue"
},
  "geometry": {"coordinates":[-94.017056,30.931055],"type":"Point"}
}