{
  "type": "Feature",
  "properties": {
    "iso:country":"US",
    "sg:address":"201 E 14th St",
    "sg:city":"Austin",
    "sg:classifiers":[
        {
            "category":"Health Services",
            "subcategory":"Clinic",
            "type":"Services"
        }
    ],
    "sg:phone":"+1 512 320 8378",
    "sg:postcode":"78701",
    "sg:province":"TX",
    "wof:name":"State Of Tx Ut Health Sci Ctr",
    "wof:placetype":"venue"
},
  "geometry": {"coordinates":[-97.73745099999999,30.275278],"type":"Point"}
}