{
  "type": "Feature",
  "properties": {
    "iso:country":"US",
    "sg:address":"10919 Shawnbrook Dr",
    "sg:city":"Houston",
    "sg:classifiers":[
        {
            "category":"Shopping",
            "type":"Retail Goods"
        }
    ],
    "sg:phone":"+1 713 772 4095",
    "sg:postcode":"77071",
    "sg:province":"TX",
    "sg:tags":[
        "merchandise"
    ],
    "wof:name":"Pet Nannys Pet Sitting",
    "wof:placetype":"venue"
},
  "geometry": {"coordinates":[-95.51958,29.661119],"type":"Point"}
}