{
  "type": "Feature",
  "properties": {
    "iso:country":"US",
    "sg:address":"8633 Funtier Ct",
    "sg:city":"Fort Worth",
    "sg:classifiers":[
        {
            "category":"Wholesale",
            "subcategory":"Vending Machines",
            "type":"Manufacturing & Wholesale Goods"
        }
    ],
    "sg:phone":"+1 817 236 1010",
    "sg:postcode":"76179",
    "sg:province":"TX",
    "sg:tags":[
        "operator"
    ],
    "wof:name":"Penny Vending",
    "wof:placetype":"venue"
},
  "geometry": {"coordinates":[-97.439365,32.884627],"type":"Point"}
}