{
  "type": "Feature",
  "properties": {
    "iso:country":"US",
    "sg:address":"136 Youngs Prairie Rd",
    "sg:city":"Elgin",
    "sg:classifiers":[
        {
            "category":"Autos & Motor Vehicles",
            "subcategory":"Automobile Sales",
            "type":"Retail Goods"
        }
    ],
    "sg:phone":"+1 512 285 3112",
    "sg:postcode":"78621",
    "sg:province":"TX",
    "sg:tags":[
        "car",
        "dealer"
    ],
    "wof:name":"Us Auto Sales",
    "wof:placetype":"venue"
},
  "geometry": {"coordinates":[-97.399458,30.290613],"type":"Point"}
}