{
  "type": "Feature",
  "properties": {
    "iso:country":"US",
    "sg:address":"111 University Dr E",
    "sg:city":"College Station",
    "sg:classifiers":[
        {
            "category":"Professional",
            "subcategory":"Research",
            "type":"Services"
        }
    ],
    "sg:phone":"+1 979 846 0303",
    "sg:postcode":"77840",
    "sg:province":"TX",
    "sg:tags":[
        "economic",
        "analysis"
    ],
    "sg:website":"www.welchcon.com",
    "wof:name":"Welch Consulting In Economics",
    "wof:placetype":"venue"
},
  "geometry": {"coordinates":[-96.333896,30.628822],"type":"Point"}
}