{
  "type": "Feature",
  "properties": {
    "iso:country":"US",
    "sg:address":"4335 Co Rd 105",
    "sg:city":"Agua Dulce",
    "sg:classifiers":[
        {
            "category":"Farming",
            "subcategory":"Livestock Farm",
            "type":"Manufacturing & Wholesale Goods"
        }
    ],
    "sg:phone":"+1 361 998 2299",
    "sg:postcode":"78330",
    "sg:province":"TX",
    "sg:tags":[
        "animal",
        "general"
    ],
    "wof:name":"La Puerta Ranch Outfitters",
    "wof:placetype":"venue"
},
  "geometry": {"coordinates":[-97.932678,27.839315],"type":"Point"}
}