{
  "type": "Feature",
  "properties": {
    "iso:country":"US",
    "sg:address":"500 S 1st St",
    "sg:city":"Lamesa",
    "sg:classifiers":[
        {
            "category":"Real Estate",
            "subcategory":"Real Estate Operator",
            "type":"Services"
        }
    ],
    "sg:phone":"+1 806 872 6337",
    "sg:postcode":"79331",
    "sg:province":"TX",
    "sg:tags":[
        "apartment"
    ],
    "wof:name":"Hillcrest Apartments",
    "wof:placetype":"venue"
},
  "geometry": {"coordinates":[-101.95269999999999,32.731902],"type":"Point"}
}