{
  "type": "Feature",
  "properties": {
    "iso:country":"US",
    "sg:address":"561 Geraldine Ln",
    "sg:city":"Brownsville",
    "sg:classifiers":[
        {
            "category":"Real Estate",
            "subcategory":"Real Estate Agent",
            "type":"Services"
        }
    ],
    "sg:phone":"+1 956 546 6265",
    "sg:postcode":"78526",
    "sg:province":"TX",
    "wof:name":"M A Castro Inc",
    "wof:placetype":"venue"
},
  "geometry": {"coordinates":[-97.49588900000001,25.954196],"type":"Point"}
}