{
  "type": "Feature",
  "properties": {
    "iso:country":"US",
    "sg:address":"15616 FM 973 N",
    "sg:city":"Manor",
    "sg:classifiers":[
        {
            "category":"Wholesale",
            "subcategory":"Chemicals & Plastics",
            "type":"Manufacturing & Wholesale Goods"
        }
    ],
    "sg:phone":"+1 512 278 0801",
    "sg:postcode":"78653",
    "sg:province":"TX",
    "sg:tags":[
        "trade",
        "contractor"
    ],
    "wof:name":"Progressive Coml Aquatics Inc",
    "wof:placetype":"venue"
},
  "geometry": {"coordinates":[-97.52103,30.387215],"type":"Point"}
}