{
  "type": "Feature",
  "properties": {
    "iso:country":"US",
    "sg:address":"3622 Apollo Rd",
    "sg:city":"Corpus Christi",
    "sg:classifiers":[
        {
            "category":"Retail",
            "subcategory":"Auto Repair",
            "type":"Services"
        }
    ],
    "sg:phone":"+1 361 814 2886",
    "sg:postcode":"78413",
    "sg:province":"TX",
    "sg:tags":[
        "repairing",
        "automobile"
    ],
    "wof:name":"Paradise Auto & Towing",
    "wof:placetype":"venue"
},
  "geometry": {"coordinates":[-97.422077,27.697043],"type":"Point"}
}