{
  "type": "Feature",
  "properties": {
    "iso:country":"US",
    "sg:address":"1313 N Navarro St",
    "sg:city":"Victoria",
    "sg:classifiers":[
        {
            "category":"Shopping",
            "subcategory":"Florist",
            "type":"Retail Goods"
        }
    ],
    "sg:phone":"+1 361 573 3246",
    "sg:postcode":"77901",
    "sg:province":"TX",
    "wof:name":"House of Flowers",
    "wof:placetype":"venue"
},
  "geometry": {"coordinates":[-96.999543,28.807488],"type":"Point"}
}