{
  "type": "Feature",
  "properties": {
    "iso:country":"US",
    "sg:address":"2411 S Border Ave",
    "sg:city":"Weslaco",
    "sg:classifiers":[
        {
            "category":"Building & Trades",
            "subcategory":"Construction",
            "type":"Services"
        }
    ],
    "sg:phone":"+1 956 969 3472",
    "sg:postcode":"78596",
    "sg:province":"TX",
    "sg:tags":[
        "home",
        "general",
        "family",
        "contractor"
    ],
    "wof:name":"Vera Leopoldo Leo Bldg Contr",
    "wof:placetype":"venue"
},
  "geometry": {"coordinates":[-97.99814600000001,26.133147],"type":"Point"}
}