{
  "type": "Feature",
  "properties": {
    "iso:country":"US",
    "sg:address":"3400 US Hwy 90",
    "sg:city":"Del Rio",
    "sg:classifiers":[
        {
            "category":"Manufacturing",
            "subcategory":"Metals",
            "type":"Manufacturing & Wholesale Goods"
        }
    ],
    "sg:phone":"+1 830 775 5506",
    "sg:postcode":"78840",
    "sg:province":"TX",
    "sg:tags":[
        "fabricator",
        "sheet"
    ],
    "wof:name":"Oviedo & Segovia Roofing",
    "wof:placetype":"venue"
},
  "geometry": {"coordinates":[-100.85655300000001,29.369373],"type":"Point"}
}