{
  "type": "Feature",
  "properties": {
    "iso:country":"US",
    "sg:address":"5411 Belt Line Rd",
    "sg:city":"Dallas",
    "sg:classifiers":[
        {
            "category":"Shopping",
            "subcategory":"Optical Goods",
            "type":"Retail Goods"
        }
    ],
    "sg:phone":"+1 972 392 3111",
    "sg:postcode":"75254",
    "sg:province":"TX",
    "wof:name":"Reading Glasses To Go",
    "wof:placetype":"venue"
},
  "geometry": {"coordinates":[-96.811843,32.954019],"type":"Point"}
}