{
  "type": "Feature",
  "properties": {
    "iso:country":"US",
    "sg:address":"627 Fonseca Dr",
    "sg:city":"El Paso",
    "sg:classifiers":[
        {
            "category":"Real Estate",
            "subcategory":"Real Estate Operator",
            "type":"Services"
        }
    ],
    "sg:phone":"+1 915 779 6265",
    "sg:postcode":"79905",
    "sg:province":"TX",
    "sg:tags":[
        "apartment"
    ],
    "wof:name":"Fonseca Apartments",
    "wof:placetype":"venue"
},
  "geometry": {"coordinates":[-106.416462,31.754707],"type":"Point"}
}