{
  "type": "Feature",
  "properties": {
    "iso:country":"US",
    "sg:address":"2700 Buttermilk Dr",
    "sg:city":"Arlington",
    "sg:classifiers":[
        {
            "category":"Professional",
            "type":"Services"
        }
    ],
    "sg:phone":"+1 817 461 7704",
    "sg:postcode":"76006",
    "sg:province":"TX",
    "wof:name":"Pombo Ltd",
    "wof:placetype":"venue"
},
  "geometry": {"coordinates":[-97.10387900000001,32.781467],"type":"Point"}
}