{
  "type": "Feature",
  "properties": {
    "iso:country":"US",
    "sg:address":"9330 Cerro Verde Dr",
    "sg:city":"San Antonio",
    "sg:classifiers":[
        {
            "category":"Wholesale",
            "subcategory":"Office Equipment",
            "type":"Manufacturing & Wholesale Goods"
        }
    ],
    "sg:phone":"+1 210 651 5155",
    "sg:postcode":"78224",
    "sg:province":"TX",
    "wof:name":"Sound Communication Systems",
    "wof:placetype":"venue"
},
  "geometry": {"coordinates":[-98.53189500000001,29.328084],"type":"Point"}
}