{
  "type": "Feature",
  "properties": {
    "iso:country":"US",
    "sg:address":"402 E Tyler St",
    "sg:city":"Athens",
    "sg:classifiers":[
        {
            "category":"Retail",
            "subcategory":"Funeral Services",
            "type":"Services"
        }
    ],
    "sg:phone":"+1 903 675 2233",
    "sg:postcode":"75751",
    "sg:province":"TX",
    "sg:tags":[
        "home"
    ],
    "wof:name":"Foster & Brown Funeral Home",
    "wof:placetype":"venue"
},
  "geometry": {"coordinates":[-95.851032,32.205281],"type":"Point"}
}