{
  "type": "Feature",
  "properties": {
    "iso:country":"US",
    "sg:address":"18366 Hollow Oaks Cir",
    "sg:city":"Porter",
    "sg:classifiers":[
        {
            "category":"Shopping",
            "type":"Retail Goods"
        }
    ],
    "sg:phone":"+1 281 354 2250",
    "sg:postcode":"77365",
    "sg:province":"TX",
    "sg:tags":[
        "merchandise"
    ],
    "wof:name":"Denny Ludlow Stamps",
    "wof:placetype":"venue"
},
  "geometry": {"coordinates":[-95.29798599999999,30.130968],"type":"Point"}
}