{
  "type": "Feature",
  "properties": {
    "iso:country":"US",
    "sg:address":"2710 Live Oak St",
    "sg:city":"Dallas",
    "sg:classifiers":[
        {
            "category":"Professional",
            "type":"Services"
        },
        {
            "category":"Personal",
            "type":"Services"
        },
        {
            "category":"Professional",
            "subcategory":"Employment Agencies",
            "type":"Services"
        }
    ],
    "sg:phone":"+1 214 742 4741",
    "sg:postcode":"75204",
    "sg:province":"TX",
    "sg:tags":[
        "planning",
        "local",
        "event"
    ],
    "sg:website":"www.iatse127.org",
    "wof:name":"IATSE Local 127",
    "wof:placetype":"venue"
},
  "geometry": {"coordinates":[-96.788945,32.788771],"type":"Point"}
}