{
  "type": "Feature",
  "properties": {
    "iso:country":"US",
    "sg:address":"1901 S Main St",
    "sg:city":"Keller",
    "sg:classifiers":[
        {
            "category":"Banks & Credit Unions",
            "subcategory":"Bank",
            "type":"Services"
        }
    ],
    "sg:phone":"+1 817 337 1128",
    "sg:postcode":"76248",
    "sg:province":"TX",
    "sg:website":"www.bankone.com",
    "wof:name":"Bank One",
    "wof:placetype":"venue"
},
  "geometry": {"coordinates":[-97.25697700000001,32.90481],"type":"Point"}
}