{
  "type": "Feature",
  "properties": {
    "iso:country":"US",
    "sg:address":"111 State Highway 64 W",
    "sg:city":"Henderson",
    "sg:classifiers":[
        {
            "category":"Home & Garden",
            "subcategory":"Furniture",
            "type":"Retail Goods"
        }
    ],
    "sg:phone":"+1 903 657 4000",
    "sg:postcode":"75652",
    "sg:province":"TX",
    "sg:tags":[
        "store"
    ],
    "wof:name":"Rent 1st",
    "wof:placetype":"venue"
},
  "geometry": {"coordinates":[-94.793477,32.167718],"type":"Point"}
}