{
  "type": "Feature",
  "properties": {
    "iso:country":"US",
    "sg:address":"2015 Coggin Ave",
    "sg:city":"Brownwood",
    "sg:classifiers":[
        {
            "category":"Personal",
            "subcategory":"Beauty Salon",
            "type":"Services"
        }
    ],
    "sg:phone":"+1 325 643 3701",
    "sg:postcode":"76801",
    "sg:province":"TX",
    "sg:tags":[
        "shop"
    ],
    "wof:name":"Looking Good",
    "wof:placetype":"venue"
},
  "geometry": {"coordinates":[-98.985788,31.702488],"type":"Point"}
}