{
  "type": "Feature",
  "properties": {
    "iso:country":"US",
    "sg:address":"218 E North St",
    "sg:city":"Kilgore",
    "sg:classifiers":[
        {
            "category":"Shopping",
            "type":"Retail Goods"
        }
    ],
    "sg:phone":"+1 903 988 8700",
    "sg:postcode":"75662",
    "sg:province":"TX",
    "sg:tags":[
        "pet",
        "shop"
    ],
    "wof:name":"Pet Shop",
    "wof:placetype":"venue"
},
  "geometry": {"coordinates":[-94.874983,32.386891],"type":"Point"}
}