{
  "type": "Feature",
  "properties": {
    "iso:country":"US",
    "sg:address":"4415 Trowbridge Dr",
    "sg:city":"El Paso",
    "sg:classifiers":[
        {
            "category":"Shopping",
            "subcategory":"Computers & Home Electronics",
            "type":"Retail Goods"
        }
    ],
    "sg:phone":"+1 915 565 4592",
    "sg:postcode":"79903",
    "sg:province":"TX",
    "wof:name":"Best Deal Computer Warehouse",
    "wof:placetype":"venue"
},
  "geometry": {"coordinates":[-106.43764299999999,31.788769],"type":"Point"}
}