{
  "type": "Feature",
  "properties": {
    "iso:country":"US",
    "sg:address":"108 Co Rd 221",
    "sg:city":"Breckenridge",
    "sg:classifiers":[
        {
            "category":"Organizations",
            "subcategory":"Religious Organization",
            "type":"Services"
        }
    ],
    "sg:phone":"+1 254 559 3722",
    "sg:postcode":"76424",
    "sg:province":"TX",
    "sg:tags":[
        "church"
    ],
    "wof:name":"Lake Side Baptist Church",
    "wof:placetype":"venue"
},
  "geometry": {"coordinates":[-99.01692799999999,32.765292],"type":"Point"}
}