{
  "type": "Feature",
  "properties": {
    "iso:country":"US",
    "sg:address":"1301 McKinney St",
    "sg:city":"Houston",
    "sg:classifiers":[
        {
            "category":"Professional",
            "subcategory":"Lawyer & Legal Services",
            "type":"Services"
        }
    ],
    "sg:phone":"+1 713 651 5475",
    "sg:postcode":"77010",
    "sg:province":"TX",
    "wof:name":"Gregory Regina L Atty",
    "wof:placetype":"venue"
},
  "geometry": {"coordinates":[-95.362297,29.7554],"type":"Point"}
}