{
  "type": "Feature",
  "properties": {
    "iso:country":"US",
    "sg:address":"4900 Spicewood Springs Rd",
    "sg:city":"Austin",
    "sg:classifiers":[
        {
            "category":"Building & Trades",
            "subcategory":"Construction",
            "type":"Services"
        },
        {
            "category":"Sports & Exercise",
            "subcategory":"Swimming Pool",
            "type":"Entertainment"
        }
    ],
    "sg:phone":"+1 512 477 3700",
    "sg:postcode":"78759",
    "sg:province":"TX",
    "wof:name":"Biscayne Aquaculture",
    "wof:placetype":"venue"
},
  "geometry": {"coordinates":[-97.76365699999999,30.37637],"type":"Point"}
}