{
  "type": "Feature",
  "properties": {
    "iso:country":"US",
    "sg:address":"132 Oyster Creek Dr",
    "sg:city":"Lake Jackson",
    "sg:classifiers":[
        {
            "category":"Real Estate",
            "subcategory":"Real Estate Operator",
            "type":"Services"
        }
    ],
    "sg:phone":"+1 979 297 5308",
    "sg:postcode":"77566",
    "sg:province":"TX",
    "sg:tags":[
        "building",
        "apartment"
    ],
    "wof:name":"Casa Del Lago II",
    "wof:placetype":"venue"
},
  "geometry": {"coordinates":[-95.453508,29.046789],"type":"Point"}
}