{
  "type": "Feature",
  "properties": {
    "iso:country":"US",
    "sg:address":"2655 Walsh Rd",
    "sg:city":"San Antonio",
    "sg:classifiers":[
        {
            "category":"Building & Trades",
            "subcategory":"Construction",
            "type":"Services"
        }
    ],
    "sg:phone":"+1 210 628 4000",
    "sg:postcode":"78224",
    "sg:province":"TX",
    "sg:tags":[
        "contractor"
    ],
    "wof:name":"Wiking Demolition Corp",
    "wof:placetype":"venue"
},
  "geometry": {"coordinates":[-98.553561,29.291917],"type":"Point"}
}