{
  "type": "Feature",
  "properties": {
    "iso:country":"US",
    "sg:address":"1534 E 6th St Ste 105",
    "sg:city":"Brownsville",
    "sg:classifiers":[
        {
            "category":"Professional",
            "subcategory":"Lawyer & Legal Services",
            "type":"Services"
        }
    ],
    "sg:phone":"+1 956 548 9100",
    "sg:postcode":"78520",
    "sg:province":"TX",
    "sg:tags":[
        "attorney",
        "practice"
    ],
    "wof:name":"Kip Johnson Hodge",
    "wof:placetype":"venue"
},
  "geometry": {"coordinates":[-97.494084,25.912414],"type":"Point"}
}