{
  "type": "Feature",
  "properties": {
    "iso:country":"US",
    "sg:address":"510 Cordoba Dr",
    "sg:city":"Universal City",
    "sg:classifiers":[
        {
            "category":"Shopping",
            "subcategory":"Gifts & Souvenirs",
            "type":"Retail Goods"
        }
    ],
    "sg:phone":"+1 210 945 4556",
    "sg:postcode":"78148",
    "sg:province":"TX",
    "wof:name":"Enjoyed Moments",
    "wof:placetype":"venue"
},
  "geometry": {"coordinates":[-98.31568300000001,29.551143],"type":"Point"}
}