{
  "type": "Feature",
  "properties": {
    "iso:country":"US",
    "sg:address":"15592 Wilson Rd",
    "sg:city":"Harlingen",
    "sg:classifiers":[
        {
            "category":"Professional",
            "subcategory":"Advertising",
            "type":"Services"
        },
        {
            "category":"Manufacturing",
            "subcategory":"Printing",
            "type":"Manufacturing & Wholesale Goods"
        }
    ],
    "sg:phone":"+1 956 412 1184",
    "sg:postcode":"78552",
    "sg:province":"TX",
    "sg:tags":[
        "screen",
        "agency"
    ],
    "wof:name":"Advertising By Juno",
    "wof:placetype":"venue"
},
  "geometry": {"coordinates":[-97.776015,26.211314],"type":"Point"}
}