{
  "type": "Feature",
  "properties": {
    "iso:country":"US",
    "sg:address":"2205 Bingle Rd",
    "sg:city":"Houston",
    "sg:classifiers":[
        {
            "category":"Retail",
            "subcategory":"Car Wash",
            "type":"Services"
        }
    ],
    "sg:phone":"+1 713 935 0503",
    "sg:postcode":"77055",
    "sg:province":"TX",
    "sg:tags":[
        "carwash"
    ],
    "wof:name":"Super Carwash",
    "wof:placetype":"venue"
},
  "geometry": {"coordinates":[-95.500923,29.81501],"type":"Point"}
}