{
  "type": "Feature",
  "properties": {
    "iso:country":"US",
    "sg:address":"5101 Oriole Dr",
    "sg:city":"San Angelo",
    "sg:classifiers":[
        {
            "category":"Building & Trades",
            "subcategory":"Construction",
            "type":"Services"
        }
    ],
    "sg:phone":"+1 325 658 3132",
    "sg:postcode":"76903",
    "sg:province":"TX",
    "sg:tags":[
        "painting",
        "drywall",
        "contractor"
    ],
    "wof:name":"Roach Paint Drywall",
    "wof:placetype":"venue"
},
  "geometry": {"coordinates":[-100.454307,31.517644],"type":"Point"}
}