{
  "type": "Feature",
  "properties": {
    "iso:country":"US",
    "sg:address":"16147 FM 521",
    "sg:city":"Rosharon",
    "sg:classifiers":[
        {
            "category":"Wholesale",
            "subcategory":"Farm Supplies",
            "type":"Manufacturing & Wholesale Goods"
        }
    ],
    "sg:phone":"+1 281 595 3057",
    "sg:postcode":"77583",
    "sg:province":"TX",
    "sg:tags":[
        "feed"
    ],
    "wof:name":"Mc Donald Feed & Supply",
    "wof:placetype":"venue"
},
  "geometry": {"coordinates":[-95.462222,29.354049],"type":"Point"}
}