{
  "type": "Feature",
  "properties": {
    "iso:country":"US",
    "sg:address":"320 W Moore Ave",
    "sg:city":"Terrell",
    "sg:classifiers":[
        {
            "category":"Autos & Motor Vehicles",
            "subcategory":"Fuel & Gas Station",
            "type":"Retail Goods"
        }
    ],
    "sg:phone":"+1 972 524 3114",
    "sg:postcode":"75160",
    "sg:province":"TX",
    "sg:tags":[
        "station",
        "gasoline",
        "oil"
    ],
    "wof:name":"Mainstreet Mobile",
    "wof:placetype":"venue"
},
  "geometry": {"coordinates":[-96.27956,32.736846],"type":"Point"}
}