{
  "type": "Feature",
  "properties": {
    "iso:country":"US",
    "sg:address":"18690 Bandera Rd",
    "sg:city":"Helotes",
    "sg:classifiers":[
        {
            "category":"Autos & Motor Vehicles",
            "subcategory":"Automobile Sales",
            "type":"Retail Goods"
        }
    ],
    "sg:phone":"+1 210 695 2299",
    "sg:postcode":"78023",
    "sg:province":"TX",
    "sg:tags":[
        "car",
        "dealer"
    ],
    "wof:name":"Knight Auto Sales",
    "wof:placetype":"venue"
},
  "geometry": {"coordinates":[-98.744293,29.62021],"type":"Point"}
}