{
  "type": "Feature",
  "properties": {
    "iso:country":"US",
    "sg:address":"5346 W Orem Dr",
    "sg:city":"Houston",
    "sg:classifiers":[
        {
            "category":"Retail",
            "subcategory":"Auto Repair",
            "type":"Services"
        }
    ],
    "sg:phone":"+1 713 434 2228",
    "sg:postcode":"77045",
    "sg:province":"TX",
    "sg:tags":[
        "repairing",
        "automobile",
        "radiator"
    ],
    "wof:name":"Anchor Radiator & Air Cond Svc",
    "wof:placetype":"venue"
},
  "geometry": {"coordinates":[-95.462896,29.627369],"type":"Point"}
}