{
  "type": "Feature",
  "properties": {
    "iso:country":"US",
    "sg:address":"6906 Edgewater Dr",
    "sg:city":"Mc Kinney",
    "sg:classifiers":[
        {
            "category":"Shopping",
            "subcategory":"Computers & Home Electronics",
            "type":"Retail Goods"
        }
    ],
    "sg:phone":"+1 972 548 5011",
    "sg:postcode":"75070",
    "sg:province":"TX",
    "sg:tags":[
        "software"
    ],
    "sg:website":"www.creativitysoftware.com",
    "wof:name":"Creativity Software Inc",
    "wof:placetype":"venue"
},
  "geometry": {"coordinates":[-96.70496799999999,33.193433],"type":"Point"}
}