{
  "type": "Feature",
  "properties": {
    "iso:country":"US",
    "sg:address":"5830 Hinman Dr",
    "sg:city":"Corpus Christi",
    "sg:classifiers":[
        {
            "category":"Retail",
            "subcategory":"Portrait Studio",
            "type":"Services"
        }
    ],
    "sg:phone":"+1 361 334 9237",
    "sg:postcode":"78412",
    "sg:province":"TX",
    "sg:tags":[
        "photographer"
    ],
    "wof:name":"New Wave Photography",
    "wof:placetype":"venue"
},
  "geometry": {"coordinates":[-97.33953,27.720117],"type":"Point"}
}