{
  "type": "Feature",
  "properties": {
    "iso:country":"US",
    "sg:address":"625 Royal Ln",
    "sg:city":"Dallas",
    "sg:classifiers":[
        {
            "category":"Professional",
            "subcategory":"Employment Agencies",
            "type":"Services"
        }
    ],
    "sg:phone":"+1 972 373 8826",
    "sg:postcode":"75231",
    "sg:province":"TX",
    "sg:tags":[
        "help",
        "contractor"
    ],
    "wof:name":"TRC Staffing",
    "wof:placetype":"venue"
},
  "geometry": {"coordinates":[-96.72850200000001,32.894568],"type":"Point"}
}