{
  "type": "Feature",
  "properties": {
    "iso:country":"US",
    "sg:address":"120 Liscio Loop",
    "sg:city":"Georgetown",
    "sg:classifiers":[
        {
            "category":"Home & Garden",
            "subcategory":"Building Materials",
            "type":"Retail Goods"
        }
    ],
    "sg:phone":"+1 512 863 2277",
    "sg:postcode":"78628",
    "sg:province":"TX",
    "wof:name":"Palacios Masonry Supply",
    "wof:placetype":"venue"
},
  "geometry": {"coordinates":[-97.685481,30.698074],"type":"Point"}
}