{
  "type": "Feature",
  "properties": {
    "iso:country":"US",
    "sg:address":"1519 Lomita Dr",
    "sg:city":"Richardson",
    "sg:classifiers":[
        {
            "category":"Professional",
            "subcategory":"Computer Services",
            "type":"Services"
        }
    ],
    "sg:phone":"+1 972 669 0047",
    "sg:postcode":"75080",
    "sg:province":"TX",
    "sg:tags":[
        "related"
    ],
    "wof:name":"King & The Assoc",
    "wof:placetype":"venue"
},
  "geometry": {"coordinates":[-96.752157,32.972825],"type":"Point"}
}