{
  "type": "Feature",
  "properties": {
    "iso:country":"US",
    "sg:address":"2910 N Co Rd 1138",
    "sg:city":"Midland",
    "sg:classifiers":[
        {
            "category":"Recreation",
            "type":"Entertainment"
        }
    ],
    "sg:phone":"+1 432 570 5137",
    "sg:postcode":"79705",
    "sg:province":"TX",
    "wof:name":"4 M C Training Stables",
    "wof:placetype":"venue"
},
  "geometry": {"coordinates":[-102.00531100000001,32.044892],"type":"Point"}
}