{
  "type": "Feature",
  "properties": {
    "iso:country":"US",
    "sg:address":"249 Circle Way St",
    "sg:city":"Lake Jackson",
    "sg:classifiers":[
        {
            "category":"Museum",
            "type":"Entertainment"
        }
    ],
    "sg:phone":"+1 979 297 1570",
    "sg:postcode":"77566",
    "sg:province":"TX",
    "sg:website":"www.lakejacksonmuseum.org",
    "wof:name":"Lake Jackson Historical Museum",
    "wof:placetype":"venue"
},
  "geometry": {"coordinates":[-95.447478,29.038568],"type":"Point"}
}