{
  "type": "Feature",
  "properties": {
    "iso:country":"US",
    "sg:address":"3638 Devon St",
    "sg:city":"San Antonio",
    "sg:classifiers":[
        {
            "category":"Building & Trades",
            "subcategory":"Construction",
            "type":"Services"
        }
    ],
    "sg:phone":"+1 210 337 9100",
    "sg:postcode":"78223",
    "sg:province":"TX",
    "sg:tags":[
        "hanging",
        "contractor"
    ],
    "wof:name":"CD Painting",
    "wof:placetype":"venue"
},
  "geometry": {"coordinates":[-98.423593,29.355997],"type":"Point"}
}