{
  "type": "Feature",
  "properties": {
    "iso:country":"US",
    "sg:address":"6431 Fannin St",
    "sg:city":"Houston",
    "sg:classifiers":[
        {
            "category":"Health Services",
            "subcategory":"Doctor",
            "type":"Services"
        }
    ],
    "sg:phone":"+1 832 325 7222",
    "sg:postcode":"77030",
    "sg:province":"TX",
    "wof:name":"Navaneethan Priya Md",
    "wof:placetype":"venue"
},
  "geometry": {"coordinates":[-95.39704399999999,29.714167],"type":"Point"}
}