{
  "type": "Feature",
  "properties": {
    "iso:country":"US",
    "sg:address":"2261 Brookhollow Plaza Dr Suite 100",
    "sg:city":"Arlington",
    "sg:classifiers":[
        {
            "category":"Professional",
            "subcategory":"Accounting & Tax Preparation",
            "type":"Services"
        }
    ],
    "sg:phone":"+1 817 640 7563",
    "sg:postcode":"76006",
    "sg:province":"TX",
    "sg:tags":[
        "bookkeeping",
        "return",
        "public",
        "accountants-certified"
    ],
    "sg:website":"http://www.cgrcpaonline.com",
    "wof:name":"Cole Greene & Ruggeberg",
    "wof:placetype":"venue"
},
  "geometry": {"coordinates":[-97.069935,32.763373],"type":"Point"}
}