{
  "type": "Feature",
  "properties": {
    "iso:country":"US",
    "sg:address":"16512 Boss Gaston Rd",
    "sg:city":"Richmond",
    "sg:classifiers":[
        {
            "category":"Building & Trades",
            "subcategory":"Electrical",
            "type":"Services"
        }
    ],
    "sg:phone":"+1 281 277 0816",
    "sg:postcode":"77469",
    "sg:province":"TX",
    "sg:tags":[
        "electric",
        "contractor"
    ],
    "wof:name":"Southland Electrical Contr",
    "wof:placetype":"venue"
},
  "geometry": {"coordinates":[-95.674915,29.667881],"type":"Point"}
}