{
  "type": "Feature",
  "properties": {
    "iso:country":"US",
    "sg:address":"10333 Denton Dr",
    "sg:city":"Dallas",
    "sg:classifiers":[
        {
            "category":"Restaurant",
            "type":"Food & Drink"
        }
    ],
    "sg:phone":"+1 214 358 0930",
    "sg:postcode":"75220",
    "sg:province":"TX",
    "wof:name":"El Pupuson Restaurant",
    "wof:placetype":"venue"
},
  "geometry": {"coordinates":[-96.87912900000001,32.864497],"type":"Point"}
}