{
  "type": "Feature",
  "properties": {
    "iso:country":"US",
    "sg:address":"1013 Brook Ave",
    "sg:city":"Wichita Falls",
    "sg:classifiers":[
        {
            "category":"Shopping",
            "subcategory":"Pharmacy",
            "type":"Retail Goods"
        }
    ],
    "sg:phone":"+1 940 723 7145",
    "sg:postcode":"76301",
    "sg:province":"TX",
    "sg:tags":[
        "drug",
        "store"
    ],
    "wof:name":"Franklin Pharmacy",
    "wof:placetype":"venue"
},
  "geometry": {"coordinates":[-98.503613,33.901475],"type":"Point"}
}