{
  "type": "Feature",
  "properties": {
    "iso:country":"US",
    "sg:address":"3103 E Park Blvd",
    "sg:city":"Plano",
    "sg:classifiers":[
        {
            "category":"Professional",
            "type":"Services"
        }
    ],
    "sg:phone":"+1 972 423 9151",
    "sg:postcode":"75074",
    "sg:province":"TX",
    "wof:name":"Eva Belonga",
    "wof:placetype":"venue"
},
  "geometry": {"coordinates":[-96.673428,33.031164],"type":"Point"}
}