{
  "type": "Feature",
  "properties": {
    "iso:country":"US",
    "sg:address":"800 10th St",
    "sg:city":"Huntsville",
    "sg:classifiers":[
        {
            "category":"Health Services",
            "subcategory":"Health Practitioner",
            "type":"Services"
        }
    ],
    "sg:phone":"+1 936 294 0660",
    "sg:postcode":"77320",
    "sg:province":"TX",
    "wof:name":"Pat Haynes",
    "wof:placetype":"venue"
},
  "geometry": {"coordinates":[-95.547275,30.725095],"type":"Point"}
}