{
  "type": "Feature",
  "properties": {
    "iso:country":"US",
    "sg:address":"10561 Goodnight Ln",
    "sg:city":"Dallas",
    "sg:classifiers":[
        {
            "category":"Real Estate",
            "subcategory":"Real Estate Agent",
            "type":"Services"
        }
    ],
    "sg:phone":"+1 972 241 7954",
    "sg:postcode":"75220",
    "sg:province":"TX",
    "wof:name":"Rockbrook Realty LTD",
    "wof:placetype":"venue"
},
  "geometry": {"coordinates":[-96.902434,32.869992],"type":"Point"}
}