{
  "type": "Feature",
  "properties": {
    "iso:country":"US",
    "sg:address":"401 E Adams St",
    "sg:city":"Itasca",
    "sg:classifiers":[
        {
            "category":"Professional",
            "type":"Services"
        }
    ],
    "sg:phone":"+1 254 687 2883",
    "sg:postcode":"76055",
    "sg:province":"TX",
    "sg:tags":[
        "establishment"
    ],
    "wof:name":"Methodist Parsonage",
    "wof:placetype":"venue"
},
  "geometry": {"coordinates":[-97.145718,32.160525],"type":"Point"}
}