{
  "type": "Feature",
  "properties": {
    "iso:country":"US",
    "sg:address":"2636 Avenida Loop",
    "sg:city":"Irving",
    "sg:classifiers":[
        {
            "category":"Shopping",
            "subcategory":"Computers & Home Electronics",
            "type":"Retail Goods"
        }
    ],
    "sg:phone":"+1 972 594 7777",
    "sg:postcode":"75062",
    "sg:province":"TX",
    "wof:name":"Ology",
    "wof:placetype":"venue"
},
  "geometry": {"coordinates":[-96.996331,32.842494],"type":"Point"}
}