{
  "type": "Feature",
  "properties": {
    "iso:country":"US",
    "sg:address":"1216 N Velasco St",
    "sg:city":"Angleton",
    "sg:classifiers":[
        {
            "category":"Health Services",
            "subcategory":"Doctor",
            "type":"Services"
        }
    ],
    "sg:phone":"+1 979 848 2228",
    "sg:postcode":"77515",
    "sg:province":"TX",
    "sg:tags":[
        "medical"
    ],
    "wof:name":"David McLendon MD",
    "wof:placetype":"venue"
},
  "geometry": {"coordinates":[-95.433194,29.186862],"type":"Point"}
}