{
  "type": "Feature",
  "properties": {
    "iso:country":"US",
    "sg:address":"2607 Grant St",
    "sg:city":"Houston",
    "sg:classifiers":[
        {
            "category":"Fast Food",
            "type":"Food & Drink"
        },
        {
            "category":"Restaurant",
            "type":"Food & Drink"
        }
    ],
    "sg:phone":"+1 713 522 0042",
    "sg:postcode":"77006",
    "sg:province":"TX",
    "sg:tags":[
        "burger",
        "american",
        "vegetarian",
        "new"
    ],
    "sg:website":"www.babayega.com/",
    "wof:name":"Baba Yega",
    "wof:placetype":"venue"
},
  "geometry": {"coordinates":[-95.390404,29.746099],"type":"Point"}
}