{
  "type": "Feature",
  "properties": {
    "iso:country":"US",
    "sg:address":"213 23rd St",
    "sg:city":"Galveston",
    "sg:classifiers":[
        {
            "category":"Professional",
            "type":"Services"
        }
    ],
    "sg:phone":"+1 409 750 8255",
    "sg:postcode":"77550",
    "sg:province":"TX",
    "wof:name":"Hargrove Comm Inc",
    "wof:placetype":"venue"
},
  "geometry": {"coordinates":[-94.794414,29.30707],"type":"Point"}
}