{
  "type": "Feature",
  "properties": {
    "iso:country":"US",
    "sg:address":"206 Broadmoor St",
    "sg:city":"Victoria",
    "sg:classifiers":[
        {
            "category":"Organizations",
            "subcategory":"Religious Organization",
            "type":"Services"
        }
    ],
    "sg:phone":"+1 361 578 5096",
    "sg:postcode":"77904",
    "sg:province":"TX",
    "sg:tags":[
        "church"
    ],
    "wof:name":"Northgate Church Of God",
    "wof:placetype":"venue"
},
  "geometry": {"coordinates":[-96.99776199999999,28.880965],"type":"Point"}
}