{
  "type": "Feature",
  "properties": {
    "iso:country":"US",
    "sg:address":"9504 Long Point Rd",
    "sg:city":"Houston",
    "sg:classifiers":[
        {
            "category":"Utilities",
            "type":"Services"
        }
    ],
    "sg:phone":"+1 713 979 5555",
    "sg:postcode":"77055",
    "sg:province":"TX",
    "sg:tags":[
        "provider",
        "internet"
    ],
    "wof:name":"G Zone",
    "wof:placetype":"venue"
},
  "geometry": {"coordinates":[-95.525932,29.797419],"type":"Point"}
}