{
  "type": "Feature",
  "properties": {
    "iso:country":"US",
    "sg:address":"1409 W Panola St",
    "sg:city":"Carthage",
    "sg:classifiers":[
        {
            "category":"Cinema",
            "subcategory":"Movie Rental",
            "type":"Entertainment"
        }
    ],
    "sg:phone":"+1 903 693 4333",
    "sg:postcode":"75633",
    "sg:province":"TX",
    "sg:tags":[
        "leasing",
        "video",
        "disc",
        "tape"
    ],
    "sg:website":"www.moviegallery.com",
    "wof:name":"Movie Gallery",
    "wof:placetype":"venue"
},
  "geometry": {"coordinates":[-94.36277,32.159418],"type":"Point"}
}