{
  "type": "Feature",
  "properties": {
    "iso:country":"US",
    "sg:address":"9309 Radio Rd",
    "sg:city":"Houston",
    "sg:classifiers":[
        {
            "category":"Retail",
            "subcategory":"Repair Shop",
            "type":"Services"
        }
    ],
    "sg:phone":"+1 713 944 2659",
    "sg:postcode":"77075",
    "sg:province":"TX",
    "sg:tags":[
        "equipment",
        "electrical"
    ],
    "wof:name":"A/V Specialists",
    "wof:placetype":"venue"
},
  "geometry": {"coordinates":[-95.25658199999999,29.642737],"type":"Point"}
}