{
  "type": "Feature",
  "properties": {
    "iso:country":"US",
    "sg:address":"513 N Interurban St",
    "sg:city":"Richardson",
    "sg:classifiers":[
        {
            "category":"Shopping",
            "subcategory":"Optician",
            "type":"Retail Goods"
        }
    ],
    "sg:phone":"+1 972 231 4923",
    "sg:postcode":"75081",
    "sg:province":"TX",
    "sg:tags":[
        "eyewear"
    ],
    "wof:name":"Nu-Tec Optical Equipment Inc",
    "wof:placetype":"venue"
},
  "geometry": {"coordinates":[-96.727997,32.956799],"type":"Point"}
}