{
  "type": "Feature",
  "properties": {
    "iso:country":"US",
    "sg:address":"600 River Pointe Dr",
    "sg:city":"Conroe",
    "sg:classifiers":[
        {
            "category":"Health Services",
            "subcategory":"Doctor",
            "type":"Services"
        }
    ],
    "sg:phone":"+1 936 756 5866",
    "sg:postcode":"77304",
    "sg:province":"TX",
    "sg:tags":[
        "physician",
        "surgeon"
    ],
    "wof:name":"Alan Mobley MD",
    "wof:placetype":"venue"
},
  "geometry": {"coordinates":[-95.46266199999999,30.280815],"type":"Point"}
}