{
  "type": "Feature",
  "properties": {
    "iso:country":"US",
    "sg:address":"6810 3rd St",
    "sg:city":"Lubbock",
    "sg:classifiers":[
        {
            "category":"Building & Trades",
            "subcategory":"Construction",
            "type":"Services"
        }
    ],
    "sg:phone":"+1 806 788 1614",
    "sg:postcode":"79416",
    "sg:province":"TX",
    "sg:tags":[
        "roofing",
        "contractor"
    ],
    "wof:name":"Midstates Roofing Ltd",
    "wof:placetype":"venue"
},
  "geometry": {"coordinates":[-101.96495,33.593856],"type":"Point"}
}