{
  "type": "Feature",
  "properties": {
    "iso:country":"US",
    "sg:address":"2202 W Adams Ave",
    "sg:city":"Temple",
    "sg:classifiers":[
        {
            "category":"Wholesale",
            "subcategory":"Hardware",
            "type":"Manufacturing & Wholesale Goods"
        }
    ],
    "sg:phone":"+1 254 742 1554",
    "sg:postcode":"76504",
    "sg:province":"TX",
    "sg:tags":[
        "plumbing",
        "equipment",
        "heating",
        "supply"
    ],
    "wof:name":"Moore Supply Co",
    "wof:placetype":"venue"
},
  "geometry": {"coordinates":[-97.364903,31.104229],"type":"Point"}
}