{
  "type": "Feature",
  "properties": {
    "iso:country":"US",
    "sg:address":"9005 Villa Park Cir",
    "sg:city":"Dallas",
    "sg:classifiers":[
        {
            "category":"Travel",
            "subcategory":"Travel Agent",
            "type":"Entertainment"
        }
    ],
    "sg:phone":"+1 214 369 0229",
    "sg:postcode":"75225",
    "sg:province":"TX",
    "sg:tags":[
        "operator",
        "tour",
        "promoter",
        "tours-operators"
    ],
    "wof:name":"Big Country Tours",
    "wof:placetype":"venue"
},
  "geometry": {"coordinates":[-96.77648499999999,32.872421],"type":"Point"}
}