{
  "type": "Feature",
  "properties": {
    "iso:country":"US",
    "sg:address":"5696 Piper Ln",
    "sg:city":"College Station",
    "sg:classifiers":[
        {
            "category":"Manufacturing",
            "subcategory":"Building Materials",
            "type":"Manufacturing & Wholesale Goods"
        }
    ],
    "sg:phone":"+1 979 846 4846",
    "sg:postcode":"77845",
    "sg:province":"TX",
    "sg:tags":[
        "mfg"
    ],
    "wof:name":"Unlimited Services",
    "wof:placetype":"venue"
},
  "geometry": {"coordinates":[-96.40132,30.594286],"type":"Point"}
}