{
  "type": "Feature",
  "properties": {
    "iso:country":"US",
    "sg:address":"4523 34th St",
    "sg:city":"Lubbock",
    "sg:classifiers":[
        {
            "category":"Shopping",
            "subcategory":"Computers & Home Electronics",
            "type":"Retail Goods"
        }
    ],
    "sg:phone":"+1 806 799 4347",
    "sg:postcode":"79410",
    "sg:province":"TX",
    "sg:tags":[
        "television",
        "set",
        "electric",
        "household",
        "appliance",
        "r"
    ],
    "wof:name":"Mullinstv & Appliance",
    "wof:placetype":"venue"
},
  "geometry": {"coordinates":[-101.908057,33.563183],"type":"Point"}
}