{
  "type": "Feature",
  "properties": {
    "iso:country":"US",
    "sg:address":"762 Arvana St",
    "sg:city":"Houston",
    "sg:classifiers":[
        {
            "category":"Building & Trades",
            "subcategory":"Plumbing",
            "type":"Services"
        },
        {
            "category":"Home & Garden",
            "subcategory":"Home Furnishings",
            "type":"Retail Goods"
        },
        {
            "category":"Building & Trades",
            "subcategory":"Construction",
            "type":"Services"
        }
    ],
    "sg:postcode":"77034",
    "sg:province":"TX",
    "sg:tags":[
        "plumber",
        "altering",
        "refinish",
        "bathroom",
        "contractor",
        "planning",
        "sinks-repair",
        "bathtub",
        "remodeling",
        "kitchen"
    ],
    "sg:website":"http://www.eZaccessbathroomS.com",
    "wof:name":"EZ Access Bathrooms.com",
    "wof:placetype":"venue"
},
  "geometry": {"coordinates":[-95.231702,29.643642],"type":"Point"}
}