{
  "type": "Feature",
  "properties": {
    "iso:country":"US",
    "sg:address":"6010 Walker St",
    "sg:city":"Fort Worth",
    "sg:classifiers":[
        {
            "category":"Education",
            "subcategory":"School",
            "type":"Public Place"
        }
    ],
    "sg:phone":"+1 817 547 5400",
    "sg:postcode":"76117",
    "sg:province":"TX",
    "wof:name":"Shannon Education Center",
    "wof:placetype":"venue"
},
  "geometry": {"coordinates":[-97.25376,32.808262],"type":"Point"}
}