{
  "type": "Feature",
  "properties": {
    "iso:country":"US",
    "sg:address":"507 E 4th St",
    "sg:city":"Hallettsville",
    "sg:classifiers":[
        {
            "category":"Insurance",
            "subcategory":"Insurance Agent",
            "type":"Services"
        }
    ],
    "sg:phone":"+1 361 798 3200",
    "sg:postcode":"77964",
    "sg:province":"TX",
    "wof:name":"Bluebonnet Insurance Agency",
    "wof:placetype":"venue"
},
  "geometry": {"coordinates":[-96.93883700000001,29.44456],"type":"Point"}
}