{
  "type": "Feature",
  "properties": {
    "iso:country":"US",
    "sg:address":"2101 Carmel Ct",
    "sg:city":"Arlington",
    "sg:classifiers":[
        {
            "category":"Professional",
            "type":"Services"
        }
    ],
    "sg:phone":"+1 817 705 7545",
    "sg:postcode":"76012",
    "sg:province":"TX",
    "wof:name":"Tejas Worldwide Inc",
    "wof:placetype":"venue"
},
  "geometry": {"coordinates":[-97.137378,32.769261],"type":"Point"}
}