{
  "type": "Feature",
  "properties": {
    "iso:country":"US",
    "sg:address":"311 Elm Forest Loop",
    "sg:city":"Cedar Creek",
    "sg:classifiers":[
        {
            "category":"Shopping",
            "subcategory":"Books",
            "type":"Retail Goods"
        }
    ],
    "sg:phone":"+1 512 321 2089",
    "sg:postcode":"78612",
    "sg:province":"TX",
    "sg:tags":[
        "dealer"
    ],
    "sg:website":"www.naturallycurious.com",
    "wof:name":"Naturally Curious Inc",
    "wof:placetype":"venue"
},
  "geometry": {"coordinates":[-97.55591,30.108238],"type":"Point"}
}