{
  "type": "Feature",
  "properties": {
    "iso:country":"US",
    "sg:address":"2317 Coit Rd",
    "sg:city":"Plano",
    "sg:classifiers":[
        {
            "category":"Professional",
            "subcategory":"Lawyer & Legal Services",
            "type":"Services"
        }
    ],
    "sg:phone":"+1 972 985 4448",
    "sg:postcode":"75075",
    "sg:province":"TX",
    "sg:tags":[
        "attorney"
    ],
    "wof:name":"Power & Virashin Law Office",
    "wof:placetype":"venue"
},
  "geometry": {"coordinates":[-96.77024400000001,33.030072],"type":"Point"}
}