{
  "type": "Feature",
  "properties": {
    "iso:country":"US",
    "sg:address":"1625 Lancaster Dr",
    "sg:city":"Grapevine",
    "sg:classifiers":[
        {
            "category":"Health Services",
            "subcategory":"Doctor",
            "type":"Services"
        }
    ],
    "sg:phone":"+1 817 416 2229",
    "sg:postcode":"76051",
    "sg:province":"TX",
    "sg:tags":[
        "physician",
        "gynecology",
        "surgeons",
        "obstetrics",
        "surgeon",
        "public"
    ],
    "sg:website":"http://www.wih.cc",
    "wof:name":"Women's Integrated Healthcare PA",
    "wof:placetype":"venue"
},
  "geometry": {"coordinates":[-97.091685,32.933067],"type":"Point"}
}