{
  "type": "Feature",
  "properties": {
    "iso:country":"US",
    "sg:address":"713 Emil Rd",
    "sg:city":"La Grange",
    "sg:classifiers":[
        {
            "category":"Education",
            "subcategory":"Special Training",
            "type":"Public Place"
        }
    ],
    "sg:phone":"+1 979 242 4028",
    "sg:postcode":"78945",
    "sg:province":"TX",
    "wof:name":"Sims Education Contractor",
    "wof:placetype":"venue"
},
  "geometry": {"coordinates":[-97.011807,30.015192],"type":"Point"}
}