{
  "type": "Feature",
  "properties": {
    "iso:country":"US",
    "sg:address":"13955 Fm 529 Rd",
    "sg:city":"Houston",
    "sg:classifiers":[
        {
            "category":"Manufacturing",
            "subcategory":"Tools & Machinery",
            "type":"Manufacturing & Wholesale Goods"
        }
    ],
    "sg:phone":"+1 713 466 5888",
    "sg:postcode":"77041",
    "sg:province":"TX",
    "sg:tags":[
        "trailers-equipment",
        "parts-wholesale",
        "manufacturer"
    ],
    "sg:website":"http://www.travistrailers.com",
    "wof:name":"Travis Enterprises",
    "wof:placetype":"venue"
},
  "geometry": {"coordinates":[-95.62054999999999,29.87945],"type":"Point"}
}