{
  "type": "Feature",
  "properties": {
    "iso:country":"US",
    "sg:address":"1507 N Waddill St",
    "sg:city":"Mc Kinney",
    "sg:classifiers":[
        {
            "category":"Professional",
            "subcategory":"Computer Services",
            "type":"Services"
        }
    ],
    "sg:phone":"+1 972 547 4791",
    "sg:postcode":"75069",
    "sg:province":"TX",
    "sg:tags":[
        "internet"
    ],
    "wof:name":"Buyers Connection",
    "wof:placetype":"venue"
},
  "geometry": {"coordinates":[-96.625843,33.212301],"type":"Point"}
}