{
  "type": "Feature",
  "properties": {
    "iso:country":"US",
    "sg:address":"8620 Windswept Ln",
    "sg:city":"Houston",
    "sg:classifiers":[
        {
            "category":"Building & Trades",
            "subcategory":"Construction",
            "type":"Services"
        }
    ],
    "sg:phone":"+1 713 975 6041",
    "sg:postcode":"77063",
    "sg:province":"TX",
    "sg:tags":[
        "contractor"
    ],
    "wof:name":"Ski Systems Inc",
    "wof:placetype":"venue"
},
  "geometry": {"coordinates":[-95.516294,29.725675],"type":"Point"}
}