{
  "type": "Feature",
  "properties": {
    "iso:country":"US",
    "sg:address":"8863 Anderson Mill Road Suite # 104",
    "sg:city":"Austin",
    "sg:classifiers":[
        {
            "category":"Sports & Exercise",
            "subcategory":"Gym",
            "type":"Entertainment"
        },
        {
            "category":"Arena",
            "subcategory":"Sports Club",
            "type":"Entertainment"
        }
    ],
    "sg:phone":"+1 512 257 8552",
    "sg:postcode":"78729",
    "sg:province":"TX",
    "sg:tags":[
        "trainer",
        "martial art"
    ],
    "sg:website":"www.aimandfocus.com",
    "wof:name":"Aim & Focus Karate",
    "wof:placetype":"venue"
},
  "geometry": {"coordinates":[-97.773048,30.453913],"type":"Point"}
}