{
  "type": "Feature",
  "properties": {
    "iso:country":"US",
    "sg:address":"2510 W Expressway 83",
    "sg:city":"Mission",
    "sg:classifiers":[
        {
            "category":"Autos & Motor Vehicles",
            "subcategory":"Auto Supplies",
            "type":"Retail Goods"
        },
        {
            "category":"Retail",
            "subcategory":"Auto Repair",
            "type":"Services"
        }
    ],
    "sg:phone":"+1 956 519 8414",
    "sg:postcode":"78572",
    "sg:province":"TX",
    "sg:tags":[
        "body",
        "lettering",
        "automobile",
        "truck",
        "painting",
        "repairing"
    ],
    "sg:website":"http://www.collisionmastersinc.com",
    "wof:name":"Collision Masters",
    "wof:placetype":"venue"
},
  "geometry": {"coordinates":[-98.35357999999999,26.222437],"type":"Point"}
}