{
  "type": "Feature",
  "properties": {
    "iso:country":"US",
    "sg:address":"6739 Airline Dr",
    "sg:city":"Houston",
    "sg:classifiers":[
        {
            "category":"Banks & Credit Unions",
            "subcategory":"Bank",
            "type":"Services"
        }
    ],
    "sg:phone":"+1 713 695 4280",
    "sg:postcode":"77076",
    "sg:province":"TX",
    "sg:tags":[
        "personal",
        "loan",
        "co",
        "finance"
    ],
    "wof:name":"Banner Finance Co",
    "wof:placetype":"venue"
},
  "geometry": {"coordinates":[-95.38479700000001,29.860578],"type":"Point"}
}