{
  "type": "Feature",
  "properties": {
    "iso:country":"US",
    "sg:address":"4901 Cross Creek Ct",
    "sg:city":"Arlington",
    "sg:classifiers":[
        {
            "category":"Banks & Credit Unions",
            "subcategory":"Financial Services",
            "type":"Services"
        }
    ],
    "sg:phone":"+1 817 467 6015",
    "sg:postcode":"76017",
    "sg:province":"TX",
    "sg:tags":[
        "management",
        "investment"
    ],
    "wof:name":"Lax Investment Llp",
    "wof:placetype":"venue"
},
  "geometry": {"coordinates":[-97.14115099999999,32.66711],"type":"Point"}
}