{
  "type": "Feature",
  "properties": {
    "iso:country":"US",
    "sg:address":"2023 State Hwy 25",
    "sg:city":"Electra",
    "sg:classifiers":[
        {
            "category":"Government",
            "subcategory":"Office",
            "type":"Public Place"
        }
    ],
    "sg:phone":"+1 940 495 2016",
    "sg:postcode":"76360",
    "sg:province":"TX",
    "sg:tags":[
        "executive"
    ],
    "wof:name":"Tax Substations Electra",
    "wof:placetype":"venue"
},
  "geometry": {"coordinates":[-98.917494,34.049977],"type":"Point"}
}