{
  "type": "Feature",
  "properties": {
    "iso:country":"US",
    "sg:address":"1601 N Trade Days Blvd",
    "sg:city":"Canton",
    "sg:classifiers":[
        {
            "category":"Government",
            "subcategory":"Office",
            "type":"Public Place"
        }
    ],
    "sg:phone":"+1 903 567 2301",
    "sg:postcode":"75103",
    "sg:province":"TX",
    "wof:name":"Texas Dept Of Puplic Safety",
    "wof:placetype":"venue"
},
  "geometry": {"coordinates":[-95.855846,32.572209],"type":"Point"}
}