{
  "type": "Feature",
  "properties": {
    "iso:country":"US",
    "sg:address":"1321 Bogard Ln",
    "sg:city":"Lewisville",
    "sg:classifiers":[
        {
            "category":"Freight",
            "type":"Transportation"
        }
    ],
    "sg:phone":"+1 972 317 8777",
    "sg:postcode":"75077",
    "sg:province":"TX",
    "wof:name":"Bill Cross",
    "wof:placetype":"venue"
},
  "geometry": {"coordinates":[-97.029821,33.081135],"type":"Point"}
}