{
  "type": "Feature",
  "properties": {
    "iso:country":"US",
    "sg:address":"5302 Anchor Cove Cir",
    "sg:city":"Garland",
    "sg:classifiers":[
        {
            "category":"Restaurant",
            "type":"Food & Drink"
        }
    ],
    "sg:phone":"+1 214 325 5912",
    "sg:postcode":"75043",
    "sg:province":"TX",
    "sg:tags":[
        "barbecue"
    ],
    "wof:name":"McCoys Soul Fd Tk-Out Barbecue",
    "wof:placetype":"venue"
},
  "geometry": {"coordinates":[-96.552841,32.848891],"type":"Point"}
}