{
  "type": "Feature",
  "properties": {
    "iso:country":"US",
    "sg:address":"115 W Foster Ave",
    "sg:city":"Pampa",
    "sg:classifiers":[
        {
            "category":"Professional",
            "subcategory":"Lawyer & Legal Services",
            "type":"Services"
        }
    ],
    "sg:phone":"+1 806 665 2555",
    "sg:postcode":"79065",
    "sg:province":"TX",
    "sg:tags":[
        "attorney"
    ],
    "wof:name":"John Mann Law Offices",
    "wof:placetype":"venue"
},
  "geometry": {"coordinates":[-100.961533,35.535686],"type":"Point"}
}