{
  "type": "Feature",
  "properties": {
    "iso:country":"US",
    "sg:address":"4324 Highlander Dr",
    "sg:city":"Dallas",
    "sg:classifiers":[
        {
            "category":"Wholesale",
            "subcategory":"Groceries",
            "type":"Manufacturing & Wholesale Goods"
        }
    ],
    "sg:phone":"+1 972 250 2719",
    "sg:postcode":"75287",
    "sg:province":"TX",
    "sg:tags":[
        "wholesaler",
        "syrup"
    ],
    "wof:name":"Fruit Drinks Of Dallas",
    "wof:placetype":"venue"
},
  "geometry": {"coordinates":[-96.837301,32.996296],"type":"Point"}
}