{
  "type": "Feature",
  "properties": {
    "iso:country":"US",
    "sg:address":"1300 Cypress Dr",
    "sg:city":"Richardson",
    "sg:classifiers":[
        {
            "category":"Social Services",
            "type":"Services"
        }
    ],
    "sg:phone":"+1 972 644 5119",
    "sg:postcode":"75080",
    "sg:province":"TX",
    "sg:tags":[
        "organization",
        "welfare"
    ],
    "wof:name":"Richardson Adult Literacy Ctr",
    "wof:placetype":"venue"
},
  "geometry": {"coordinates":[-96.76553199999999,32.960778],"type":"Point"}
}