{
  "type": "Feature",
  "properties": {
    "iso:country":"US",
    "sg:address":"14138 Hempstead Rd",
    "sg:city":"Houston",
    "sg:classifiers":[
        {
            "category":"Wholesale",
            "subcategory":"Farm Supplies",
            "type":"Manufacturing & Wholesale Goods"
        }
    ],
    "sg:phone":"+1 713 462 4444",
    "sg:postcode":"77040",
    "sg:province":"TX",
    "sg:tags":[
        "feed"
    ],
    "wof:name":"A A A Rentals & Supply Inc",
    "wof:placetype":"venue"
},
  "geometry": {"coordinates":[-95.53119599999999,29.852472],"type":"Point"}
}