{
  "type": "Feature",
  "properties": {
    "iso:country":"US",
    "sg:address":"14348 Proton Rd",
    "sg:city":"Dallas",
    "sg:classifiers":[
        {
            "category":"Personal",
            "type":"Services"
        }
    ],
    "sg:phone":"+1 972 361 0633",
    "sg:postcode":"75244",
    "sg:province":"TX",
    "sg:tags":[
        "local"
    ],
    "sg:website":"corporate-amenities.com",
    "wof:name":"Corporate Amenities",
    "wof:placetype":"venue"
},
  "geometry": {"coordinates":[-96.836089,32.945138],"type":"Point"}
}