{
  "type": "Feature",
  "properties": {
    "iso:country":"US",
    "sg:address":"5310 Glenmont Dr",
    "sg:city":"Houston",
    "sg:classifiers":[
        {
            "category":"Building & Trades",
            "subcategory":"Construction",
            "type":"Services"
        }
    ],
    "sg:phone":"+1 713 663 6302",
    "sg:postcode":"77081",
    "sg:province":"TX",
    "sg:tags":[
        "resurfacing",
        "laying",
        "refinishing",
        "floor"
    ],
    "wof:name":"Houston Floors Distribution",
    "wof:placetype":"venue"
},
  "geometry": {"coordinates":[-95.472866,29.720256],"type":"Point"}
}