{
  "type": "Feature",
  "properties": {
    "iso:country":"US",
    "sg:address":"7859 Townsend Rd",
    "sg:city":"Mansfield",
    "sg:classifiers":[
        {
            "category":"Building & Trades",
            "subcategory":"Construction",
            "type":"Services"
        }
    ],
    "sg:phone":"+1 817 572 7559",
    "sg:postcode":"76063",
    "sg:province":"TX",
    "sg:tags":[
        "hanging",
        "contractor"
    ],
    "wof:name":"Taylor Made Painting Co",
    "wof:placetype":"venue"
},
  "geometry": {"coordinates":[-97.192122,32.607052],"type":"Point"}
}