{
  "type": "Feature",
  "properties": {
    "iso:country":"US",
    "sg:address":"900 Ashton Dr",
    "sg:city":"Hewitt",
    "sg:classifiers":[
        {
            "category":"Professional",
            "type":"Services"
        }
    ],
    "sg:phone":"+1 254 857 9575",
    "sg:postcode":"76643",
    "sg:province":"TX",
    "wof:name":"Susan A Wright",
    "wof:placetype":"venue"
},
  "geometry": {"coordinates":[-97.19903600000001,31.432495],"type":"Point"}
}