{
  "type": "Feature",
  "properties": {
    "iso:country":"US",
    "sg:address":"2001 N Collins St",
    "sg:city":"Arlington",
    "sg:classifiers":[
        {
            "category":"Retail",
            "subcategory":"Auto Rental",
            "type":"Services"
        }
    ],
    "sg:phone":"+1 817 801 4909",
    "sg:postcode":"76011",
    "sg:province":"TX",
    "sg:tags":[
        "passenger",
        "car"
    ],
    "wof:name":"Enterprise Rent-A-Car",
    "wof:placetype":"venue"
},
  "geometry": {"coordinates":[-97.09708500000001,32.767128],"type":"Point"}
}