{
  "type": "Feature",
  "properties": {
    "iso:country":"US",
    "sg:address":"2125 E 14th St",
    "sg:city":"Brownsville",
    "sg:classifiers":[
        {
            "category":"Retail",
            "subcategory":"Auto Repair",
            "type":"Services"
        }
    ],
    "sg:phone":"+1 956 544 5014",
    "sg:postcode":"78521",
    "sg:province":"TX",
    "sg:tags":[
        "alternator",
        "generators-automotive"
    ],
    "wof:name":"European Starters & Alternators",
    "wof:placetype":"venue"
},
  "geometry": {"coordinates":[-97.48499700000001,25.909562],"type":"Point"}
}