{
  "type": "Feature",
  "properties": {
    "iso:country":"US",
    "sg:address":"1400 Dapplegrey Ln",
    "sg:city":"Austin",
    "sg:classifiers":[
        {
            "category":"Social Services",
            "type":"Services"
        },
        {
            "category":"Professional",
            "subcategory":"Employment Agencies",
            "type":"Services"
        }
    ],
    "sg:phone":"+1 512 836 4880",
    "sg:postcode":"78727",
    "sg:province":"TX",
    "sg:tags":[
        "workers'",
        "placement",
        "volunteer"
    ],
    "wof:name":"Pfluger Haus Foundation",
    "wof:placetype":"venue"
},
  "geometry": {"coordinates":[-97.682312,30.41234],"type":"Point"}
}