{
  "type": "Feature",
  "properties": {
    "iso:country":"US",
    "sg:address":"51 Thunderbird Dr",
    "sg:city":"May",
    "sg:classifiers":[
        {
            "category":"Building & Trades",
            "subcategory":"Construction",
            "type":"Services"
        }
    ],
    "sg:phone":"+1 325 784 8257",
    "sg:postcode":"76857",
    "sg:province":"TX",
    "sg:tags":[
        "specializing",
        "family",
        "housing",
        "improvement",
        "home",
        "contractor",
        "gen"
    ],
    "wof:name":"A-1 Home Improvements",
    "wof:placetype":"venue"
},
  "geometry": {"coordinates":[-99.02253399999999,31.900295],"type":"Point"}
}