{
  "type": "Feature",
  "properties": {
    "iso:country":"US",
    "sg:address":"6068 Clyde Morgan Rd",
    "sg:city":"Wichita Falls",
    "sg:classifiers":[
        {
            "category":"Building & Trades",
            "subcategory":"Construction",
            "type":"Services"
        }
    ],
    "sg:phone":"+1 940 692 1444",
    "sg:postcode":"76310",
    "sg:province":"TX",
    "sg:tags":[
        "demolition",
        "contractor"
    ],
    "wof:name":"Mote Inc",
    "wof:placetype":"venue"
},
  "geometry": {"coordinates":[-98.632767,33.836707],"type":"Point"}
}