{
  "type": "Feature",
  "properties": {
    "iso:country":"US",
    "sg:address":"200 N 5th St",
    "sg:city":"Garland",
    "sg:classifiers":[
        {
            "category":"Government",
            "subcategory":"Office",
            "type":"Public Place"
        }
    ],
    "sg:phone":"+1 972 205 2404",
    "sg:postcode":"75040",
    "sg:province":"TX",
    "sg:tags":[
        "village"
    ],
    "wof:name":"Garland City Secretary's Ofc",
    "wof:placetype":"venue"
},
  "geometry": {"coordinates":[-96.63655300000001,32.913567],"type":"Point"}
}