{
  "type": "Feature",
  "properties": {
    "iso:country":"US",
    "sg:address":"1421 N Col Rowe Blvd",
    "sg:city":"Mcallen",
    "sg:classifiers":[
        {
            "category":"Professional",
            "type":"Services"
        }
    ],
    "sg:phone":"+1 956 972 1747",
    "sg:postcode":"78501",
    "sg:province":"TX",
    "sg:tags":[
        "establishment"
    ],
    "wof:name":"In Step Therapy",
    "wof:placetype":"venue"
},
  "geometry": {"coordinates":[-98.21901699999999,26.215588],"type":"Point"}
}