{
  "type": "Feature",
  "properties": {
    "iso:country":"US",
    "sg:address":"561 W Campbell Rd",
    "sg:city":"Richardson",
    "sg:classifiers":[
        {
            "category":"Restaurant",
            "type":"Food & Drink"
        }
    ],
    "sg:postcode":"75080",
    "sg:province":"TX",
    "sg:tags":[
        "tex-mex"
    ],
    "sg:website":"www.fuzzystacoshop.com",
    "wof:name":"Fuzzy's Taco Shop",
    "wof:placetype":"venue"
},
  "geometry": {"coordinates":[-96.73899400000001,32.976333],"type":"Point"}
}