{
  "type": "Feature",
  "properties": {
    "iso:country":"US",
    "sg:address":"7022 Midbury Dr",
    "sg:city":"Dallas",
    "sg:classifiers":[
        {
            "category":"Banks & Credit Unions",
            "subcategory":"Investment Brokerage",
            "type":"Services"
        }
    ],
    "sg:phone":"+1 214 373 6448",
    "sg:postcode":"75230",
    "sg:province":"TX",
    "sg:tags":[
        "advisory",
        "financial"
    ],
    "wof:name":"Nort Comm Resources Ctr",
    "wof:placetype":"venue"
},
  "geometry": {"coordinates":[-96.785398,32.900887],"type":"Point"}
}