{
  "type": "Feature",
  "properties": {
    "iso:country":"US",
    "sg:address":"1111 W Airport Fwy Ste 235",
    "sg:city":"Irving",
    "sg:classifiers":[
        {
            "category":"Airline",
            "type":"Transportation"
        }
    ],
    "sg:phone":"+1 972 252 8058",
    "sg:postcode":"75062",
    "sg:province":"TX",
    "sg:tags":[
        "airport"
    ],
    "wof:name":"Globe Airport Security",
    "wof:placetype":"venue"
},
  "geometry": {"coordinates":[-96.95639799999999,32.837299],"type":"Point"}
}