{
  "type": "Feature",
  "properties": {
    "iso:country":"US",
    "sg:address":"1300 W Dumble St",
    "sg:city":"Alvin",
    "sg:classifiers":[
        {
            "category":"Building & Trades",
            "subcategory":"Construction",
            "type":"Services"
        }
    ],
    "sg:phone":"+1 281 756 0613",
    "sg:postcode":"77511",
    "sg:province":"TX",
    "sg:tags":[
        "house"
    ],
    "wof:name":"Catch-All",
    "wof:placetype":"venue"
},
  "geometry": {"coordinates":[-95.255449,29.416518],"type":"Point"}
}