{
  "type": "Feature",
  "properties": {
    "iso:country":"US",
    "sg:address":"650 State Hwy 6",
    "sg:city":"Houston",
    "sg:classifiers":[
        {
            "category":"Banks & Credit Unions",
            "subcategory":"Investment Brokerage",
            "type":"Services"
        }
    ],
    "sg:phone":"+1 281 558 0600",
    "sg:postcode":"77079",
    "sg:province":"TX",
    "sg:tags":[
        "advisory",
        "financial"
    ],
    "wof:name":"LRC-Ride Cycle",
    "wof:placetype":"venue"
},
  "geometry": {"coordinates":[-95.644747,29.778076],"type":"Point"}
}