{
  "type": "Feature",
  "properties": {
    "iso:country":"US",
    "sg:address":"6723 Carrington Ridge Ln",
    "sg:city":"Humble",
    "sg:classifiers":[
        {
            "category":"Retail",
            "subcategory":"Auto Repair",
            "type":"Services"
        }
    ],
    "sg:phone":"+1 281 446 3998",
    "sg:postcode":"77346",
    "sg:province":"TX",
    "sg:tags":[
        "machine",
        "automobile",
        "shop"
    ],
    "wof:name":"Exact Manufacturing Co",
    "wof:placetype":"venue"
},
  "geometry": {"coordinates":[-95.17516500000001,29.982554],"type":"Point"}
}