{
  "type": "Feature",
  "properties": {
    "iso:country":"US",
    "sg:address":"454 Wilson Rd",
    "sg:city":"Waco",
    "sg:classifiers":[
        {
            "category":"Retail",
            "subcategory":"Repair Shop",
            "type":"Services"
        }
    ],
    "sg:phone":"+1 254 799 0695",
    "sg:postcode":"76705",
    "sg:province":"TX",
    "wof:name":"Big Buck Taxadermy",
    "wof:placetype":"venue"
},
  "geometry": {"coordinates":[-97.069819,31.591157],"type":"Point"}
}