{
  "type": "Feature",
  "properties": {
    "iso:country":"US",
    "sg:address":"1432 Richard St",
    "sg:city":"Mesquite",
    "sg:classifiers":[
        {
            "category":"Building & Trades",
            "subcategory":"Construction",
            "type":"Services"
        }
    ],
    "sg:phone":"+1 972 289 9365",
    "sg:postcode":"75149",
    "sg:province":"TX",
    "sg:tags":[
        "repair",
        "system",
        "specialty",
        "heating",
        "contractor",
        "air conditioning"
    ],
    "wof:name":"General Air Conditioning & Heating Inc",
    "wof:placetype":"venue"
},
  "geometry": {"coordinates":[-96.61761199999999,32.786271],"type":"Point"}
}