{
  "type": "Feature",
  "properties": {
    "iso:country":"US",
    "sg:address":"109 Carlton St",
    "sg:city":"Midland",
    "sg:classifiers":[
        {
            "category":"Personal",
            "subcategory":"Beauty Salon",
            "type":"Services"
        }
    ],
    "sg:phone":"+1 432 687 3919",
    "sg:postcode":"79701",
    "sg:province":"TX",
    "sg:tags":[
        "shop"
    ],
    "wof:name":"Hair Cottage",
    "wof:placetype":"venue"
},
  "geometry": {"coordinates":[-102.10110299999999,31.990328],"type":"Point"}
}