{
  "type": "Feature",
  "properties": {
    "iso:country":"US",
    "sg:address":"8219 Waynemer Way",
    "sg:city":"Houston",
    "sg:classifiers":[
        {
            "category":"Wholesale",
            "subcategory":"Home Furnishings",
            "type":"Manufacturing & Wholesale Goods"
        }
    ],
    "sg:phone":"+1 713 896 7229",
    "sg:postcode":"77040",
    "sg:province":"TX",
    "sg:tags":[
        "floor",
        "covering"
    ],
    "wof:name":"Carpet Den",
    "wof:placetype":"venue"
},
  "geometry": {"coordinates":[-95.533283,29.892874],"type":"Point"}
}