{
  "type": "Feature",
  "properties": {
    "iso:country":"US",
    "sg:address":"13775 Higgins Rd",
    "sg:city":"San Antonio",
    "sg:classifiers":[
        {
            "category":"Recreation",
            "type":"Entertainment"
        }
    ],
    "sg:phone":"+1 210 655 7951",
    "sg:postcode":"78217",
    "sg:province":"TX",
    "wof:name":"Flip City Inc",
    "wof:placetype":"venue"
},
  "geometry": {"coordinates":[-98.39179,29.564237],"type":"Point"}
}