{
  "type": "Feature",
  "properties": {
    "iso:country":"US",
    "sg:address":"3151 SE Inner Loop",
    "sg:city":"Georgetown",
    "sg:classifiers":[
        {
            "category":"Government",
            "subcategory":"Office",
            "type":"Public Place"
        }
    ],
    "sg:phone":"+1 512 943 3370",
    "sg:postcode":"78626",
    "sg:province":"TX",
    "wof:name":"Williamson County Commissioner",
    "wof:placetype":"venue"
},
  "geometry": {"coordinates":[-97.64335800000001,30.630644],"type":"Point"}
}