{
  "type": "Feature",
  "properties": {
    "iso:country":"US",
    "sg:address":"33 Waugh Dr",
    "sg:city":"Houston",
    "sg:classifiers":[
        {
            "category":"Bars & Pubs",
            "subcategory":"Lounge",
            "type":"Food & Drink"
        },
        {
            "category":"Bars & Pubs",
            "subcategory":"Sports Bar",
            "type":"Food & Drink"
        }
    ],
    "sg:phone":"+1 713 862 9911",
    "sg:postcode":"77007",
    "sg:province":"TX",
    "sg:website":"www.kobain.net",
    "wof:name":"Kobain",
    "wof:placetype":"venue"
},
  "geometry": {"coordinates":[-95.398149,29.7681],"type":"Point"}
}