{
  "type": "Feature",
  "properties": {
    "iso:country":"US",
    "sg:address":"9075 Co Rd 174",
    "sg:city":"Anderson",
    "sg:classifiers":[
        {
            "category":"Shopping",
            "subcategory":"Gifts & Souvenirs",
            "type":"Retail Goods"
        }
    ],
    "sg:phone":"+1 936 873 2117",
    "sg:postcode":"77830",
    "sg:province":"TX",
    "wof:name":"Simply Scents & Gifts",
    "wof:placetype":"venue"
},
  "geometry": {"coordinates":[-96.116159,30.616281],"type":"Point"}
}