{
  "type": "Feature",
  "properties": {
    "iso:country":"US",
    "sg:address":"2118 Springwood",
    "sg:city":"Carrollton",
    "sg:classifiers":[
        {
            "category":"Retail",
            "subcategory":"Repair Shop",
            "type":"Services"
        }
    ],
    "sg:phone":"+1 972 418 7552",
    "sg:postcode":"75006",
    "sg:province":"TX",
    "wof:name":"Mr Squeegee",
    "wof:placetype":"venue"
},
  "geometry": {"coordinates":[-96.879942,32.972557],"type":"Point"}
}