{
  "type": "Feature",
  "properties": {
    "iso:country":"US",
    "sg:address":"3145 Produce Row",
    "sg:city":"Houston",
    "sg:classifiers":[
        {
            "category":"Wholesale",
            "subcategory":"Fruits & Vegetables",
            "type":"Manufacturing & Wholesale Goods"
        }
    ],
    "sg:phone":"+1 713 924 6992",
    "sg:postcode":"77023",
    "sg:province":"TX",
    "sg:tags":[
        "vegetables-wholesale"
    ],
    "wof:name":"Third Coast Produce Co.",
    "wof:placetype":"venue"
},
  "geometry": {"coordinates":[-95.330755,29.709373],"type":"Point"}
}