{
  "type": "Feature",
  "properties": {
    "iso:country":"US",
    "sg:address":"1530 George Dieter Dr",
    "sg:city":"El Paso",
    "sg:classifiers":[
        {
            "category":"Personal",
            "subcategory":"Beauty Salon",
            "type":"Services"
        }
    ],
    "sg:phone":"+1 915 595 0340",
    "sg:postcode":"79936",
    "sg:province":"TX",
    "sg:tags":[
        "shop"
    ],
    "wof:name":"Salon At Elodia",
    "wof:placetype":"venue"
},
  "geometry": {"coordinates":[-106.3017,31.747366],"type":"Point"}
}