{
  "type": "Feature",
  "properties": {
    "iso:country":"US",
    "sg:address":"998 Tony Lama St",
    "sg:city":"El Paso",
    "sg:classifiers":[
        {
            "category":"Building & Trades",
            "subcategory":"Equipment Rental",
            "type":"Services"
        }
    ],
    "sg:phone":"+1 915 592 5814",
    "sg:postcode":"79915",
    "sg:province":"TX",
    "sg:tags":[
        "scaffolding"
    ],
    "wof:name":"El Paso Scaffolding Leasing",
    "wof:placetype":"venue"
},
  "geometry": {"coordinates":[-106.374449,31.763582],"type":"Point"}
}