{
  "type": "Feature",
  "properties": {
    "iso:country":"US",
    "sg:address":"10308 E Gentry Rd",
    "sg:city":"Silsbee",
    "sg:classifiers":[
        {
            "category":"Banks & Credit Unions",
            "subcategory":"Investment Brokerage",
            "type":"Services"
        }
    ],
    "sg:phone":"+1 409 385 5346",
    "sg:postcode":"77656",
    "sg:province":"TX",
    "wof:name":"Ross Eppes Investments",
    "wof:placetype":"venue"
},
  "geometry": {"coordinates":[-94.151948,30.3248],"type":"Point"}
}