{
  "type": "Feature",
  "properties": {
    "iso:country":"US",
    "sg:address":"1218 Webster St",
    "sg:city":"Houston",
    "sg:classifiers":[
        {
            "category":"Education",
            "subcategory":"Dance Studio",
            "type":"Public Place"
        }
    ],
    "sg:phone":"+1 713 652 3938",
    "sg:postcode":"77002",
    "sg:province":"TX",
    "sg:tags":[
        "school",
        "hall"
    ],
    "wof:name":"Dwdt",
    "wof:placetype":"venue"
},
  "geometry": {"coordinates":[-95.369604,29.74647],"type":"Point"}
}