{
  "type": "Feature",
  "properties": {
    "iso:country":"US",
    "sg:address":"1501 Harry Wurzbach",
    "sg:city":"San Antonio",
    "sg:classifiers":[
        {
            "category":"Retail",
            "subcategory":"Laundry & Dry Cleaning",
            "type":"Services"
        }
    ],
    "sg:phone":"+1 210 822 7775",
    "sg:postcode":"78209",
    "sg:province":"TX",
    "sg:tags":[
        "cleaners"
    ],
    "wof:name":"Lee's Cleaners",
    "wof:placetype":"venue"
},
  "geometry": {"coordinates":[-98.435396,29.475077],"type":"Point"}
}