{
  "type": "Feature",
  "properties": {
    "iso:country":"US",
    "sg:address":"7 Shady Pond Pl",
    "sg:city":"Spring",
    "sg:classifiers":[
        {
            "category":"Manufacturing",
            "subcategory":"Tools & Machinery",
            "type":"Manufacturing & Wholesale Goods"
        }
    ],
    "sg:phone":"+1 832 656 5531",
    "sg:postcode":"77382",
    "sg:province":"TX",
    "sg:tags":[
        "hardware",
        "development",
        "software"
    ],
    "wof:name":"Enameco",
    "wof:placetype":"venue"
},
  "geometry": {"coordinates":[-95.490927,30.202297],"type":"Point"}
}