{
  "type": "Feature",
  "properties": {
    "iso:country":"US",
    "sg:address":"4321 W Sam Houston Pkwy N Ste 100",
    "sg:city":"Houston",
    "sg:classifiers":[
        {
            "category":"Education",
            "subcategory":"Special Training",
            "type":"Public Place"
        }
    ],
    "sg:phone":"+1 713 849 1150",
    "sg:postcode":"77043",
    "sg:province":"TX",
    "sg:tags":[
        "adult"
    ],
    "sg:website":"www.pfsolutions.info/seminars/de...",
    "wof:name":"Pepperl+Fuchs, Inc",
    "wof:placetype":"venue"
},
  "geometry": {"coordinates":[-95.564706,29.828867],"type":"Point"}
}