{
  "type": "Feature",
  "properties": {
    "iso:country":"US",
    "sg:address":"700 Versailles St",
    "sg:city":"Mesquite",
    "sg:classifiers":[
        {
            "category":"Freight",
            "type":"Transportation"
        }
    ],
    "sg:phone":"+1 972 289 9669",
    "sg:postcode":"75149",
    "sg:province":"TX",
    "sg:tags":[
        "operator",
        "local",
        "trucking"
    ],
    "wof:name":"Allen Trucking",
    "wof:placetype":"venue"
},
  "geometry": {"coordinates":[-96.605985,32.772379],"type":"Point"}
}