{
  "type": "Feature",
  "properties": {
    "iso:country":"US",
    "sg:address":"15505 Bradley Rd",
    "sg:city":"Atascosa",
    "sg:classifiers":[
        {
            "category":"Building & Trades",
            "subcategory":"Electrical",
            "type":"Services"
        }
    ],
    "sg:phone":"+1 210 622 9418",
    "sg:postcode":"78002",
    "sg:province":"TX",
    "sg:tags":[
        "electrician"
    ],
    "wof:name":"Ct Electric",
    "wof:placetype":"venue"
},
  "geometry": {"coordinates":[-98.73412399999999,29.268694],"type":"Point"}
}