{
  "type": "Feature",
  "properties": {
    "iso:country":"US",
    "sg:address":"900 E Pecan",
    "sg:city":"Pflugerville",
    "sg:classifiers":[
        {
            "category":"Building & Trades",
            "subcategory":"Plumbing",
            "type":"Services"
        }
    ],
    "sg:phone":"+1 512 371 3615",
    "sg:postcode":"78660",
    "sg:province":"TX",
    "sg:website":"pflugervilletx.rotorooter.com/",
    "wof:name":"Roto-Rooter Plumbing & Drain Services",
    "wof:placetype":"venue"
},
  "geometry": {"coordinates":[-97.627016,30.443399],"type":"Point"}
}