{
  "type": "Feature",
  "properties": {
    "iso:country":"US",
    "sg:address":"1822 W Walker St",
    "sg:city":"Breckenridge",
    "sg:classifiers":[
        {
            "category":"Professional",
            "subcategory":"Accounting & Tax Preparation",
            "type":"Services"
        }
    ],
    "sg:phone":"+1 254 559 3035",
    "sg:postcode":"76424",
    "sg:province":"TX",
    "sg:tags":[
        "accountant"
    ],
    "wof:name":"George J Hart CPA",
    "wof:placetype":"venue"
},
  "geometry": {"coordinates":[-98.924177,32.755428],"type":"Point"}
}