{
  "type": "Feature",
  "properties": {
    "iso:country":"US",
    "sg:address":"4901 Broadway St",
    "sg:city":"Pearland",
    "sg:classifiers":[
        {
            "category":"Insurance",
            "subcategory":"Insurance Agent",
            "type":"Services"
        },
        {
            "category":"Insurance",
            "subcategory":"Hazard Insurance",
            "type":"Services"
        }
    ],
    "sg:phone":"+1 281 485 7283",
    "sg:postcode":"77581",
    "sg:province":"TX",
    "sg:tags":[
        "auto",
        "recreational",
        "motorcycle",
        "vehicle",
        "marine",
        "boat"
    ],
    "wof:name":"INSURANCE PLUS+ AGENCIES",
    "wof:placetype":"venue"
},
  "geometry": {"coordinates":[-95.296997,29.560499],"type":"Point"}
}