{
  "type": "Feature",
  "properties": {
    "iso:country":"US",
    "sg:address":"2938 S Main St",
    "sg:city":"Stafford",
    "sg:classifiers":[
        {
            "category":"Professional",
            "subcategory":"Lawyer & Legal Services",
            "type":"Services"
        }
    ],
    "sg:phone":"+1 713 784 4345",
    "sg:postcode":"77477",
    "sg:province":"TX",
    "wof:name":"Gransberry Law Firm",
    "wof:placetype":"venue"
},
  "geometry": {"coordinates":[-95.559658,29.615847],"type":"Point"}
}