{
  "type": "Feature",
  "properties": {
    "iso:country":"US",
    "sg:address":"1300 26th St",
    "sg:city":"Snyder",
    "sg:classifiers":[
        {
            "category":"Government",
            "subcategory":"Police Station",
            "type":"Public Place"
        }
    ],
    "sg:phone":"+1 325 573 4182",
    "sg:postcode":"79549",
    "sg:province":"TX",
    "sg:tags":[
        "state"
    ],
    "wof:name":"Highway Patrol",
    "wof:placetype":"venue"
},
  "geometry": {"coordinates":[-100.912389,32.716034],"type":"Point"}
}