{
  "type": "Feature",
  "properties": {
    "iso:country":"US",
    "sg:address":"2503 Nightowl Trl",
    "sg:city":"Spring",
    "sg:classifiers":[
        {
            "category":"Shopping",
            "subcategory":"Jewelry",
            "type":"Retail Goods"
        },
        {
            "category":"Manufacturing",
            "subcategory":"Jewelry",
            "type":"Manufacturing & Wholesale Goods"
        }
    ],
    "sg:phone":"+1 281 528 9368",
    "sg:postcode":"77373",
    "sg:province":"TX",
    "sg:tags":[
        "manufacturer",
        "jewelers-wholesale",
        "jeweler"
    ],
    "wof:name":"Laras Lil' Treasures",
    "wof:placetype":"venue"
},
  "geometry": {"coordinates":[-95.392275,30.043724],"type":"Point"}
}