{
  "type": "Feature",
  "properties": {
    "iso:country":"US",
    "sg:address":"600 Round Rock West Dr",
    "sg:city":"Round Rock",
    "sg:classifiers":[
        {
            "category":"Professional",
            "subcategory":"Detective & Security Services",
            "type":"Services"
        }
    ],
    "sg:phone":"+1 512 341 9627",
    "sg:postcode":"78681",
    "sg:province":"TX",
    "sg:tags":[
        "system"
    ],
    "wof:name":"Striker Systems Inc",
    "wof:placetype":"venue"
},
  "geometry": {"coordinates":[-97.694841,30.504686],"type":"Point"}
}