{
  "type": "Feature",
  "properties": {
    "iso:country":"US",
    "sg:address":"1245 Southridge Ct",
    "sg:city":"Hurst",
    "sg:classifiers":[
        {
            "category":"Real Estate",
            "subcategory":"Real Estate Agent",
            "type":"Services"
        }
    ],
    "sg:phone":"+1 817 268 3110",
    "sg:postcode":"76053",
    "sg:province":"TX",
    "sg:tags":[
        "management"
    ],
    "wof:name":"Property Management Etc",
    "wof:placetype":"venue"
},
  "geometry": {"coordinates":[-97.18073200000001,32.833287],"type":"Point"}
}