{
  "type": "Feature",
  "properties": {
    "iso:country":"US",
    "sg:address":"1421 S Wheeler St",
    "sg:city":"Jasper",
    "sg:classifiers":[
        {
            "category":"Health Services",
            "subcategory":"Doctor",
            "type":"Services"
        }
    ],
    "sg:phone":"+1 409 384 8242",
    "sg:postcode":"75951",
    "sg:province":"TX",
    "sg:tags":[
        "physician",
        "surgeon"
    ],
    "wof:name":"William W Wagnon MD",
    "wof:placetype":"venue"
},
  "geometry": {"coordinates":[-93.994086,30.906745],"type":"Point"}
}