{
  "type": "Feature",
  "properties": {
    "iso:country":"US",
    "sg:address":"100 N Robinson Dr",
    "sg:city":"Robinson",
    "sg:classifiers":[
        {
            "category":"Retail",
            "subcategory":"Storage",
            "type":"Services"
        }
    ],
    "sg:phone":"+1 254 662 5693",
    "sg:postcode":"76706",
    "sg:province":"TX",
    "sg:tags":[
        "household",
        "commercial"
    ],
    "sg:website":"http://www.RocketMiniStorage.com",
    "wof:name":"AA1-Stor dba Rocket Mini Storage",
    "wof:placetype":"venue"
},
  "geometry": {"coordinates":[-97.116928,31.470949],"type":"Point"}
}