{
  "type": "Feature",
  "properties": {
    "iso:country":"US",
    "sg:address":"13070 Brandeis Dr",
    "sg:city":"El Paso",
    "sg:classifiers":[
        {
            "category":"Shopping",
            "subcategory":"Jewelry",
            "type":"Retail Goods"
        }
    ],
    "sg:phone":"+1 915 720 3203",
    "sg:postcode":"79928",
    "sg:province":"TX",
    "wof:name":"Jimenez Jewelry",
    "wof:placetype":"venue"
},
  "geometry": {"coordinates":[-106.238187,31.672349],"type":"Point"}
}