{
  "type": "Feature",
  "properties": {
    "iso:country":"US",
    "sg:address":"2551 Texas Ave S",
    "sg:city":"College Station",
    "sg:classifiers":[
        {
            "category":"Personal",
            "subcategory":"Beauty Salon",
            "type":"Services"
        }
    ],
    "sg:phone":"+1 979 764 3000",
    "sg:postcode":"77840",
    "sg:province":"TX",
    "sg:tags":[
        "shop"
    ],
    "wof:name":"Cutler2 Salon & Spa Works",
    "wof:placetype":"venue"
},
  "geometry": {"coordinates":[-96.308048,30.606902],"type":"Point"}
}