{
  "type": "Feature",
  "properties": {
    "iso:country":"US",
    "sg:address":"5855 Fairmont Pkwy",
    "sg:city":"Pasadena",
    "sg:classifiers":[
        {
            "category":"Bakery",
            "type":"Food & Drink"
        }
    ],
    "sg:menulink":"http://www.allmenus.com/tx/pasadena/102925-panera-bread/menu/",
    "sg:phone":"+1 281 991 8111",
    "sg:postcode":"77505",
    "sg:province":"TX",
    "sg:tags":[
        "american",
        "sandwich",
        "pastry"
    ],
    "wof:name":"Panera Bread",
    "wof:placetype":"venue"
},
  "geometry": {"coordinates":[-95.149186,29.650287],"type":"Point"}
}