{
  "type": "Feature",
  "properties": {
    "iso:country":"US",
    "sg:address":"965 Capitol St",
    "sg:city":"Houston",
    "sg:classifiers":[
        {
            "category":"Professional",
            "subcategory":"Lawyer & Legal Services",
            "type":"Services"
        }
    ],
    "sg:phone":"+1 713 224 8380",
    "sg:postcode":"77002",
    "sg:province":"TX",
    "sg:tags":[
        "attorney"
    ],
    "wof:name":"Marilyn T Hebinck",
    "wof:placetype":"venue"
},
  "geometry": {"coordinates":[-95.363598,29.759602],"type":"Point"}
}