{
  "type": "Feature",
  "properties": {
    "iso:country":"US",
    "sg:address":"1109 Ridgeley Dr",
    "sg:city":"Houston",
    "sg:classifiers":[
        {
            "category":"Professional",
            "subcategory":"Business Services",
            "type":"Services"
        }
    ],
    "sg:phone":"+1 713 464 2691",
    "sg:postcode":"77055",
    "sg:province":"TX",
    "wof:name":"Argo Financial Services Inc",
    "wof:placetype":"venue"
},
  "geometry": {"coordinates":[-95.48889200000001,29.787558],"type":"Point"}
}