{
  "type": "Feature",
  "properties": {
    "iso:country":"US",
    "sg:address":"4211 N Grandview Ave",
    "sg:city":"Odessa",
    "sg:classifiers":[
        {
            "category":"Autos & Motor Vehicles",
            "subcategory":"Auto Supplies",
            "type":"Retail Goods"
        }
    ],
    "sg:phone":"+1 432 363 8083",
    "sg:postcode":"79762",
    "sg:province":"TX",
    "sg:tags":[
        "tire"
    ],
    "sg:website":"http://www.goodyear.com",
    "wof:name":"Goodyear",
    "wof:placetype":"venue"
},
  "geometry": {"coordinates":[-102.352385,31.891611],"type":"Point"}
}