{
  "type": "Feature",
  "properties": {
    "iso:country":"US",
    "sg:address":"8151 Almeda-Genoa Rd",
    "sg:city":"Houston",
    "sg:classifiers":[
        {
            "category":"Banks & Credit Unions",
            "subcategory":"Investment Brokerage",
            "type":"Services"
        }
    ],
    "sg:phone":"+1 713 991 0967",
    "sg:postcode":"77075",
    "sg:province":"TX",
    "sg:tags":[
        "advisory"
    ],
    "wof:name":"T E Davis Investments",
    "wof:placetype":"venue"
},
  "geometry": {"coordinates":[-95.27221299999999,29.626277],"type":"Point"}
}