{
  "type": "Feature",
  "properties": {
    "iso:country":"US",
    "sg:address":"8014 C E King Pkwy",
    "sg:city":"Houston",
    "sg:classifiers":[
        {
            "category":"Shopping",
            "subcategory":"Music",
            "type":"Retail Goods"
        },
        {
            "category":"Cinema",
            "subcategory":"Movie Rental",
            "type":"Entertainment"
        }
    ],
    "sg:phone":"+1 281 458 8719",
    "sg:postcode":"77044",
    "sg:province":"TX",
    "sg:tags":[
        "video",
        "disc",
        "tape",
        "cassette"
    ],
    "wof:name":"Kingway Video Inc",
    "wof:placetype":"venue"
},
  "geometry": {"coordinates":[-95.214006,29.83887],"type":"Point"}
}