{
  "type": "Feature",
  "properties": {
    "iso:country":"US",
    "sg:address":"930 Thorton Dr",
    "sg:city":"Cedar Hill",
    "sg:classifiers":[
        {
            "category":"Building & Trades",
            "subcategory":"Construction",
            "type":"Services"
        }
    ],
    "sg:phone":"+1 214 882 6307",
    "sg:postcode":"75104",
    "sg:province":"TX",
    "sg:tags":[
        "roofing",
        "contractor"
    ],
    "wof:name":"Cleantech",
    "wof:placetype":"venue"
},
  "geometry": {"coordinates":[-96.930295,32.577663],"type":"Point"}
}