{
  "type": "Feature",
  "properties": {
    "iso:country":"US",
    "sg:address":"1319 Woodcrest Ln",
    "sg:city":"Sour Lake",
    "sg:classifiers":[
        {
            "category":"Professional",
            "subcategory":"Business Services",
            "type":"Services"
        }
    ],
    "sg:phone":"+1 409 753 1738",
    "sg:postcode":"77659",
    "sg:province":"TX",
    "wof:name":"Rf Browning Enterprises Inc",
    "wof:placetype":"venue"
},
  "geometry": {"coordinates":[-94.315168,30.168325],"type":"Point"}
}