{
  "type": "Feature",
  "properties": {
    "iso:country":"US",
    "sg:address":"2616 Pickett St",
    "sg:city":"Greenville",
    "sg:classifiers":[
        {
            "category":"Building & Trades",
            "subcategory":"Plumbing",
            "type":"Services"
        }
    ],
    "sg:phone":"+1 903 455 1293",
    "sg:postcode":"75401",
    "sg:province":"TX",
    "sg:tags":[
        "plumbing",
        "contractor",
        "heating",
        "conditioning",
        "air"
    ],
    "wof:name":"H & R Plumbing Co",
    "wof:placetype":"venue"
},
  "geometry": {"coordinates":[-96.10800500000001,33.138409],"type":"Point"}
}