{
  "type": "Feature",
  "properties": {
    "iso:country":"US",
    "sg:address":"222 Rs County Road 1219",
    "sg:city":"Emory",
    "sg:classifiers":[
        {
            "category":"Building & Trades",
            "subcategory":"Construction",
            "type":"Services"
        }
    ],
    "sg:phone":"+1 903 473 2877",
    "sg:postcode":"75440",
    "sg:province":"TX",
    "sg:tags":[
        "system",
        "specialty",
        "heating",
        "contractor",
        "air conditioning"
    ],
    "wof:name":"Ron's Plumbing",
    "wof:placetype":"venue"
},
  "geometry": {"coordinates":[-95.79309600000001,32.883057],"type":"Point"}
}