{
  "type": "Feature",
  "properties": {
    "iso:country":"US",
    "sg:address":"5702 Slide Rd",
    "sg:city":"Lubbock",
    "sg:classifiers":[
        {
            "category":"Restaurant",
            "type":"Food & Drink"
        }
    ],
    "sg:menulink":"http://www.allmenus.com/tx/lubbock/14124-olive-garden-italian-restaurant/menu/",
    "sg:phone":"+1 806 791 3575",
    "sg:postcode":"79414",
    "sg:province":"TX",
    "sg:tags":[
        "italian"
    ],
    "wof:name":"Olive Garden Italian Restaurant",
    "wof:placetype":"venue"
},
  "geometry": {"coordinates":[-101.923078,33.541963],"type":"Point"}
}