{
  "type": "Feature",
  "properties": {
    "iso:country":"US",
    "sg:address":"9200 Brodie Ln",
    "sg:city":"Austin",
    "sg:classifiers":[
        {
            "category":"Autos & Motor Vehicles",
            "subcategory":"Automobile Sales",
            "type":"Retail Goods"
        }
    ],
    "sg:phone":"+1 512 282 2886",
    "sg:postcode":"78748",
    "sg:province":"TX",
    "sg:tags":[
        "automotive"
    ],
    "wof:name":"Christian Brothers Automotive",
    "wof:placetype":"venue"
},
  "geometry": {"coordinates":[-97.84417000000001,30.192537],"type":"Point"}
}