{
  "type": "Feature",
  "properties": {
    "iso:country":"US",
    "sg:address":"3404 Lynbrook Dr",
    "sg:city":"Plano",
    "sg:classifiers":[
        {
            "category":"Banks & Credit Unions",
            "subcategory":"Financial Services",
            "type":"Services"
        }
    ],
    "sg:phone":"+1 972 596 7179",
    "sg:postcode":"75075",
    "sg:province":"TX",
    "sg:tags":[
        "investor"
    ],
    "wof:name":"Ebone Seven & Associates",
    "wof:placetype":"venue"
},
  "geometry": {"coordinates":[-96.762305,33.018654],"type":"Point"}
}