{
  "type": "Feature",
  "properties": {
    "iso:country":"US",
    "sg:address":"231 Parkfield",
    "sg:city":"Pleasanton",
    "sg:classifiers":[
        {
            "category":"Retail",
            "subcategory":"Repair Shop",
            "type":"Services"
        }
    ],
    "sg:phone":"+1 830 569 3564",
    "sg:postcode":"78064",
    "sg:province":"TX",
    "wof:name":"Straight Arrw Fndtion Rpair Sr",
    "wof:placetype":"venue"
},
  "geometry": {"coordinates":[-98.413769,29.005052],"type":"Point"}
}