{
  "type": "Feature",
  "properties": {
    "iso:country":"US",
    "sg:address":"1403 Oak Knoll Dr",
    "sg:city":"Fort Worth",
    "sg:classifiers":[
        {
            "category":"Wholesale",
            "subcategory":"Stationery",
            "type":"Manufacturing & Wholesale Goods"
        }
    ],
    "sg:phone":"+1 817 921 6167",
    "sg:postcode":"76117",
    "sg:province":"TX",
    "sg:tags":[
        "business",
        "form"
    ],
    "wof:name":"Hefco",
    "wof:placetype":"venue"
},
  "geometry": {"coordinates":[-97.280793,32.783294],"type":"Point"}
}