{
  "type": "Feature",
  "properties": {
    "iso:country":"US",
    "sg:address":"9058 W Riggs Dr",
    "sg:city":"Odessa",
    "sg:classifiers":[
        {
            "category":"Home & Garden",
            "subcategory":"Furniture",
            "type":"Retail Goods"
        }
    ],
    "sg:phone":"+1 432 559 3524",
    "sg:postcode":"79764",
    "sg:province":"TX",
    "wof:name":"Furniture Medic",
    "wof:placetype":"venue"
},
  "geometry": {"coordinates":[-102.48631899999999,31.852332],"type":"Point"}
}