{
  "type": "Feature",
  "properties": {
    "iso:country":"US",
    "sg:address":"511 E 6th St",
    "sg:city":"Irving",
    "sg:classifiers":[
        {
            "category":"Real Estate",
            "subcategory":"Real Estate Operator",
            "type":"Services"
        }
    ],
    "sg:phone":"+1 972 579 3435",
    "sg:postcode":"75060",
    "sg:province":"TX",
    "sg:tags":[
        "apartment"
    ],
    "wof:name":"Oak Grove Manor Apartments",
    "wof:placetype":"venue"
},
  "geometry": {"coordinates":[-96.940422,32.808693],"type":"Point"}
}