{
  "type": "Feature",
  "properties": {
    "iso:country":"US",
    "sg:address":"1110 N 16th St",
    "sg:city":"Orange",
    "sg:classifiers":[
        {
            "category":"Building & Trades",
            "subcategory":"Equipment Rental",
            "type":"Services"
        }
    ],
    "sg:phone":"+1 409 883 7368",
    "sg:postcode":"77630",
    "sg:province":"TX",
    "sg:tags":[
        "a",
        "retail",
        "store",
        "operates"
    ],
    "wof:name":"Landrys Furniture",
    "wof:placetype":"venue"
},
  "geometry": {"coordinates":[-93.747103,30.10044],"type":"Point"}
}