{
  "type": "Feature",
  "properties": {
    "iso:country":"US",
    "sg:address":"4107 Medical Pkwy Ste 210",
    "sg:city":"Austin",
    "sg:classifiers":[
        {
            "category":"Home & Garden",
            "subcategory":"Furniture",
            "type":"Retail Goods"
        },
        {
            "category":"Wholesale",
            "subcategory":"Home Furnishings",
            "type":"Manufacturing & Wholesale Goods"
        }
    ],
    "sg:phone":"+1 512 451 9706",
    "sg:postcode":"78756",
    "sg:province":"TX",
    "sg:tags":[
        "equipment-wholesale",
        "kitchen",
        "equipment-household",
        "manufacturer",
        "cabinet"
    ],
    "wof:name":"Instapro Cabinets, Inc",
    "wof:placetype":"venue"
},
  "geometry": {"coordinates":[-97.74262,30.30994],"type":"Point"}
}