{
  "type": "Feature",
  "properties": {
    "iso:country":"US",
    "sg:address":"3812 Market St",
    "sg:city":"Denton",
    "sg:classifiers":[
        {
            "category":"Social Services",
            "subcategory":"Child Care",
            "type":"Services"
        },
        {
            "category":"Education",
            "subcategory":"School",
            "type":"Public Place"
        }
    ],
    "sg:phone":"+1 940 484 8337",
    "sg:postcode":"76209",
    "sg:province":"TX",
    "sg:tags":[
        "private",
        "nursery",
        "k-",
        "interest",
        "religious",
        "day"
    ],
    "sg:website":"http://www.alphadenton.com",
    "wof:name":"Alpha Christian Academy",
    "wof:placetype":"venue"
},
  "geometry": {"coordinates":[-97.090311,33.217344],"type":"Point"}
}