{
  "type": "Feature",
  "properties": {
    "iso:country":"US",
    "sg:address":"6739 N Hwy 146",
    "sg:city":"Baytown",
    "sg:classifiers":[
        {
            "category":"Home & Garden",
            "subcategory":"Furniture",
            "type":"Retail Goods"
        }
    ],
    "sg:phone":"+1 281 383 2288",
    "sg:postcode":"77520",
    "sg:province":"TX",
    "wof:name":"De Bruhl Discount Furniture",
    "wof:placetype":"venue"
},
  "geometry": {"coordinates":[-94.906459,29.7972],"type":"Point"}
}