{
  "type": "Feature",
  "properties": {
    "iso:country":"US",
    "sg:address":"102 Houston St",
    "sg:city":"Weatherford",
    "sg:classifiers":[
        {
            "category":"Banks & Credit Unions",
            "subcategory":"Investment Brokerage",
            "type":"Services"
        }
    ],
    "sg:phone":"+1 817 599 7100",
    "sg:postcode":"76086",
    "sg:province":"TX",
    "sg:tags":[
        "consultant",
        "financing"
    ],
    "wof:name":"LNC Financial Corp",
    "wof:placetype":"venue"
},
  "geometry": {"coordinates":[-97.798152,32.758335],"type":"Point"}
}