{
  "type": "Feature",
  "properties": {
    "iso:country":"US",
    "sg:address":"4919 W Lovers Ln",
    "sg:city":"Dallas",
    "sg:classifiers":[
        {
            "category":"Insurance",
            "subcategory":"Insurance Agent",
            "type":"Services"
        }
    ],
    "sg:phone":"+1 214 692 5507",
    "sg:postcode":"75209",
    "sg:province":"TX",
    "wof:name":"Sundance Financial Services",
    "wof:placetype":"venue"
},
  "geometry": {"coordinates":[-96.826797,32.851288],"type":"Point"}
}