{
  "type": "Feature",
  "properties": {
    "iso:country":"US",
    "sg:address":"9040 Viscount Row",
    "sg:city":"Dallas",
    "sg:classifiers":[
        {
            "category":"Manufacturing",
            "subcategory":"Apparel",
            "type":"Manufacturing & Wholesale Goods"
        }
    ],
    "sg:phone":"+1 214 630 2202",
    "sg:postcode":"75247",
    "sg:province":"TX",
    "sg:tags":[
        "specializing",
        "mfg",
        "western",
        "lady",
        "sportswear",
        "wear"
    ],
    "wof:name":"Banjo",
    "wof:placetype":"venue"
},
  "geometry": {"coordinates":[-96.894811,32.815167],"type":"Point"}
}