{
  "type": "Feature",
  "properties": {
    "iso:country":"US",
    "sg:address":"812 W Division St",
    "sg:city":"Arlington",
    "sg:classifiers":[
        {
            "category":"Social Services",
            "subcategory":"Job Training",
            "type":"Services"
        }
    ],
    "sg:phone":"+1 817 801 4868",
    "sg:postcode":"76012",
    "sg:province":"TX",
    "sg:tags":[
        "rehabilitation"
    ],
    "wof:name":"North Texas Inst-Career Dev",
    "wof:placetype":"venue"
},
  "geometry": {"coordinates":[-97.11719100000001,32.739019],"type":"Point"}
}