{
  "type": "Feature",
  "properties": {
    "iso:country":"US",
    "sg:address":"701 Brockman St",
    "sg:city":"Sweeny",
    "sg:classifiers":[
        {
            "category":"Building & Trades",
            "subcategory":"Construction",
            "type":"Services"
        }
    ],
    "sg:phone":"+1 979 548 3973",
    "sg:postcode":"77480",
    "sg:province":"TX",
    "sg:tags":[
        "nonresidential"
    ],
    "wof:name":"Larry Lamb",
    "wof:placetype":"venue"
},
  "geometry": {"coordinates":[-95.69443099999999,29.045121],"type":"Point"}
}