{
  "type": "Feature",
  "properties": {
    "iso:country":"US",
    "sg:address":"1138 Lazar Dr",
    "sg:city":"Eagle Pass",
    "sg:classifiers":[
        {
            "category":"Freight",
            "type":"Transportation"
        }
    ],
    "sg:phone":"+1 830 752 1366",
    "sg:postcode":"78852",
    "sg:province":"TX",
    "sg:tags":[
        "operator",
        "local",
        "trucking"
    ],
    "wof:name":"Dobie A Trucking",
    "wof:placetype":"venue"
},
  "geometry": {"coordinates":[-100.483941,28.691293],"type":"Point"}
}