{
  "type": "Feature",
  "properties": {
    "iso:country":"US",
    "sg:address":"3205 Ave I",
    "sg:city":"Rosenberg",
    "sg:classifiers":[
        {
            "category":"Retail",
            "subcategory":"Self-service Laundry",
            "type":"Services"
        }
    ],
    "sg:phone":"+1 281 344 9222",
    "sg:postcode":"77471",
    "sg:province":"TX",
    "sg:tags":[
        "coin"
    ],
    "wof:name":"Happy Washer",
    "wof:placetype":"venue"
},
  "geometry": {"coordinates":[-95.793812,29.557476],"type":"Point"}
}