{
  "type": "Feature",
  "properties": {
    "iso:country":"US",
    "sg:address":"2012 W Washington St",
    "sg:city":"Stephenville",
    "sg:classifiers":[
        {
            "category":"Restaurant",
            "type":"Food & Drink"
        }
    ],
    "sg:menulink":"http://www.allmenus.com/tx/stephenville/166008-arbys/menu/",
    "sg:phone":"+1 254 965 2729",
    "sg:postcode":"76401",
    "sg:province":"TX",
    "sg:tags":[
        "burger",
        "american"
    ],
    "wof:name":"Arby's",
    "wof:placetype":"venue"
},
  "geometry": {"coordinates":[-98.222266,32.211356],"type":"Point"}
}