{
  "type": "Feature",
  "properties": {
    "iso:country":"US",
    "sg:address":"1838 FM 1331",
    "sg:city":"Thorndale",
    "sg:phone":"+1 512 862 3313",
    "sg:postcode":"76574",
    "sg:province":"TX",
    "sg:tags":[
        "beef",
        "farm",
        "corn",
        "cash",
        "grain",
        "cattle",
        "feedlot"
    ],
    "wof:name":"Randall Unnasch",
    "wof:placetype":"venue"
},
  "geometry": {"coordinates":[-97.406764,30.644396],"type":"Point"}
}