{
  "type": "Feature",
  "properties": {
    "iso:country":"US",
    "sg:address":"10711 Preston Rd",
    "sg:city":"Dallas",
    "sg:classifiers":[
        {
            "category":"Real Estate",
            "subcategory":"Architect",
            "type":"Services"
        }
    ],
    "sg:phone":"+1 214 361 8485",
    "sg:postcode":"75230",
    "sg:province":"TX",
    "wof:name":"Nelson Edward Russell Acrchitects Inc",
    "wof:placetype":"venue"
},
  "geometry": {"coordinates":[-96.804154,32.89288],"type":"Point"}
}