{
  "type": "Feature",
  "properties": {
    "iso:country":"US",
    "sg:address":"14016 Stacey Valley Dr",
    "sg:city":"Azle",
    "sg:classifiers":[
        {
            "category":"Home & Garden",
            "subcategory":"Furniture",
            "type":"Retail Goods"
        }
    ],
    "sg:phone":"+1 817 238 0936",
    "sg:postcode":"76020",
    "sg:province":"TX",
    "sg:tags":[
        "store"
    ],
    "wof:name":"Ruiz Furniture Building And Restoration",
    "wof:placetype":"venue"
},
  "geometry": {"coordinates":[-97.546823,32.85268],"type":"Point"}
}