{
  "type": "Feature",
  "properties": {
    "iso:country":"US",
    "sg:address":"2117 Crawford Dr",
    "sg:city":"Mesquite",
    "sg:classifiers":[
        {
            "category":"Building & Trades",
            "subcategory":"Construction",
            "type":"Services"
        }
    ],
    "sg:phone":"+1 972 222 5602",
    "sg:postcode":"75149",
    "sg:province":"TX",
    "sg:tags":[
        "contractor"
    ],
    "wof:name":"Smittys Acoustical Ceilings",
    "wof:placetype":"venue"
},
  "geometry": {"coordinates":[-96.57018100000001,32.747311],"type":"Point"}
}