{
  "type": "Feature",
  "properties": {
    "iso:country":"US",
    "sg:address":"801 Cherry St",
    "sg:city":"Fort Worth",
    "sg:classifiers":[
        {
            "category":"Cafe",
            "type":"Food & Drink"
        }
    ],
    "sg:menulink":"http://www.allmenus.com/tx/fort-worth/15266-alonti-market-cafe/menu/",
    "sg:phone":"+1 817 877 4022",
    "sg:postcode":"76102",
    "sg:province":"TX",
    "sg:tags":[
        "american"
    ],
    "wof:name":"Alonti Market Cafe",
    "wof:placetype":"venue"
},
  "geometry": {"coordinates":[-97.334782,32.750902],"type":"Point"}
}