{
  "type": "Feature",
  "properties": {
    "iso:country":"US",
    "sg:address":"6200 Bellaire Blvd",
    "sg:city":"Houston",
    "sg:classifiers":[
        {
            "category":"Building & Trades",
            "subcategory":"Locksmith",
            "type":"Services"
        }
    ],
    "sg:phone":"+1 713 779 5397",
    "sg:postcode":"77081",
    "sg:province":"TX",
    "sg:tags":[
        "key"
    ],
    "wof:name":"Super Key Co",
    "wof:placetype":"venue"
},
  "geometry": {"coordinates":[-95.4897,29.7057],"type":"Point"}
}