{
  "type": "Feature",
  "properties": {
    "iso:country":"US",
    "sg:address":"10710 Research Boulevard",
    "sg:city":"Austin",
    "sg:classifiers":[
        {
            "category":"Shopping",
            "subcategory":"Beauty & Cosmetics",
            "type":"Retail Goods"
        }
    ],
    "sg:phone":"+1 512 345 3552",
    "sg:postcode":"78759",
    "sg:province":"TX",
    "sg:tags":[
        "supply"
    ],
    "sg:website":"www.sallybeauty.com",
    "wof:name":"Sally Beauty Supply",
    "wof:placetype":"venue"
},
  "geometry": {"coordinates":[-97.746503,30.398502],"type":"Point"}
}