{
  "type": "Feature",
  "properties": {
    "iso:country":"US",
    "sg:address":"2615 Lory St",
    "sg:city":"Rosenberg",
    "sg:classifiers":[
        {
            "category":"Manufacturing",
            "subcategory":"Jewelry",
            "type":"Manufacturing & Wholesale Goods"
        }
    ],
    "sg:phone":"+1 281 342 7226",
    "sg:postcode":"77471",
    "sg:province":"TX",
    "sg:tags":[
        "precious",
        "metal",
        "mfg"
    ],
    "wof:name":"Southwest Precious Metals",
    "wof:placetype":"venue"
},
  "geometry": {"coordinates":[-95.795227,29.540188],"type":"Point"}
}