{
  "type": "Feature",
  "properties": {
    "iso:country":"US",
    "sg:address":"4602 Summerhill Rd",
    "sg:city":"Texarkana",
    "sg:classifiers":[
        {
            "category":"Insurance",
            "subcategory":"Hazard Insurance",
            "type":"Services"
        }
    ],
    "sg:phone":"+1 903 793 0102",
    "sg:postcode":"75503",
    "sg:province":"TX",
    "sg:tags":[
        "commercial",
        "business"
    ],
    "wof:name":"Axa Equitable",
    "wof:placetype":"venue"
},
  "geometry": {"coordinates":[-94.065834,33.461911],"type":"Point"}
}