{
  "type": "Feature",
  "properties": {
    "iso:country":"US",
    "sg:address":"1120 Cedar Dr",
    "sg:city":"Midlothian",
    "sg:classifiers":[
        {
            "category":"Building & Trades",
            "subcategory":"Construction",
            "type":"Services"
        },
        {
            "category":"Military Area",
            "subcategory":"Armory",
            "type":"Public Place"
        }
    ],
    "sg:phone":"+1 972 723 6532",
    "sg:postcode":"76065",
    "sg:province":"TX",
    "sg:tags":[
        "repair",
        "fence-sales",
        "fence",
        "contractor"
    ],
    "wof:name":"Circle T Enterprises",
    "wof:placetype":"venue"
},
  "geometry": {"coordinates":[-97.006624,32.461213],"type":"Point"}
}