{
  "type": "Feature",
  "properties": {
    "iso:country":"US",
    "sg:address":"402 S Wilhite St",
    "sg:city":"Cleburne",
    "sg:classifiers":[
        {
            "category":"Personal",
            "subcategory":"Beauty Salon",
            "type":"Services"
        }
    ],
    "sg:phone":"+1 817 556 3004",
    "sg:postcode":"76031",
    "sg:province":"TX",
    "wof:name":"Josie's Beauty Salon",
    "wof:placetype":"venue"
},
  "geometry": {"coordinates":[-97.38234,32.344601],"type":"Point"}
}