{
  "type": "Feature",
  "properties": {
    "iso:country":"US",
    "sg:address":"9 Cherokee Trl",
    "sg:city":"Iowa Park",
    "sg:classifiers":[
        {
            "category":"Sports & Exercise",
            "subcategory":"Race Track",
            "type":"Entertainment"
        }
    ],
    "sg:phone":"+1 940 592 1017",
    "sg:postcode":"76367",
    "sg:province":"TX",
    "sg:tags":[
        "operation",
        "racing",
        "or"
    ],
    "wof:name":"Liggett Race Engines",
    "wof:placetype":"venue"
},
  "geometry": {"coordinates":[-98.656834,33.958013],"type":"Point"}
}