{
  "type": "Feature",
  "properties": {
    "iso:country":"US",
    "sg:address":"3436 Indale Rd",
    "sg:city":"Fort Worth",
    "sg:classifiers":[
        {
            "category":"Banks & Credit Unions",
            "subcategory":"Investment Brokerage",
            "type":"Services"
        }
    ],
    "sg:phone":"+1 817 738 9477",
    "sg:postcode":"76116",
    "sg:province":"TX",
    "sg:tags":[
        "advisory"
    ],
    "wof:name":"Indigo International LLC",
    "wof:placetype":"venue"
},
  "geometry": {"coordinates":[-97.42782699999999,32.721549],"type":"Point"}
}