{
  "type": "Feature",
  "properties": {
    "iso:country":"US",
    "sg:address":"113 S Allen St",
    "sg:city":"Boyd",
    "sg:classifiers":[
        {
            "category":"Retail",
            "subcategory":"Repair Shop",
            "type":"Services"
        }
    ],
    "sg:phone":"+1 940 399 9922",
    "sg:postcode":"76023",
    "sg:province":"TX",
    "wof:name":"Magnolia",
    "wof:placetype":"venue"
},
  "geometry": {"coordinates":[-97.565043,33.078402],"type":"Point"}
}