{
  "type": "Feature",
  "properties": {
    "iso:country":"US",
    "sg:address":"3705 E Veterans Memorial Blvd",
    "sg:city":"Killeen",
    "sg:classifiers":[
        {
            "category":"Autos & Motor Vehicles",
            "subcategory":"Auto Supplies",
            "type":"Retail Goods"
        },
        {
            "category":"Retail",
            "subcategory":"Auto Repair",
            "type":"Services"
        }
    ],
    "sg:phone":"+1 254 690 8473",
    "sg:postcode":"76543",
    "sg:province":"TX",
    "sg:tags":[
        "repairing",
        "automobile",
        "custom",
        "tire",
        "accessory"
    ],
    "wof:name":"Caruthers Tire & Service Ctr",
    "wof:placetype":"venue"
},
  "geometry": {"coordinates":[-97.699186,31.101146],"type":"Point"}
}