{
  "type": "Feature",
  "properties": {
    "iso:country":"US",
    "sg:address":"17996 FM 529",
    "sg:city":"Houston",
    "sg:classifiers":[
        {
            "category":"Utilities",
            "subcategory":"Mobile Phone",
            "type":"Services"
        }
    ],
    "sg:phone":"+1 281 345 8295",
    "sg:postcode":"77095",
    "sg:province":"TX",
    "sg:tags":[
        "communication",
        "radiotelephone"
    ],
    "wof:name":"Eckerd",
    "wof:placetype":"venue"
},
  "geometry": {"coordinates":[-95.683229,29.880016],"type":"Point"}
}