{
  "type": "Feature",
  "properties": {
    "iso:country":"US",
    "sg:address":"1 Baybrook Mall",
    "sg:city":"Friendswood",
    "sg:classifiers":[
        {
            "category":"Fast Food",
            "type":"Food & Drink"
        },
        {
            "category":"Restaurant",
            "type":"Food & Drink"
        }
    ],
    "sg:phone":"+1 281 480 7144",
    "sg:postcode":"77546",
    "sg:province":"TX",
    "sg:tags":[
        "chicken"
    ],
    "wof:name":"Chick-fil-A",
    "wof:placetype":"venue"
},
  "geometry": {"coordinates":[-95.146057,29.53952],"type":"Point"}
}