{
  "type": "Feature",
  "properties": {
    "iso:country":"US",
    "sg:address":"1814 N W S Young Dr",
    "sg:city":"Killeen",
    "sg:classifiers":[
        {
            "category":"Banks & Credit Unions",
            "subcategory":"Financial Services",
            "type":"Services"
        },
        {
            "category":"Banks & Credit Unions",
            "subcategory":"Atm",
            "type":"Services"
        },
        {
            "category":"Food & Beverages",
            "subcategory":"Groceries & Convenience Stores",
            "type":"Retail Goods"
        }
    ],
    "sg:phone":"+1 254 634 6073",
    "sg:postcode":"76543",
    "sg:province":"TX",
    "sg:tags":[
        "money",
        "location",
        "order"
    ],
    "sg:website":"http://www.7-eleven.com",
    "wof:name":"7-Eleven",
    "wof:placetype":"venue"
},
  "geometry": {"coordinates":[-97.70657300000001,31.128704],"type":"Point"}
}