{
  "type": "Feature",
  "properties": {
    "iso:country":"US",
    "sg:address":"4252 Armstrong Pkwy",
    "sg:city":"Dallas",
    "sg:classifiers":[
        {
            "category":"Professional",
            "subcategory":"Management & Consulting",
            "type":"Services"
        }
    ],
    "sg:phone":"+1 214 528 5897",
    "sg:postcode":"75205",
    "sg:province":"TX",
    "sg:tags":[
        "business"
    ],
    "wof:name":"Louis F Davis Consultants Inc",
    "wof:placetype":"venue"
},
  "geometry": {"coordinates":[-96.806254,32.824965],"type":"Point"}
}