{
  "type": "Feature",
  "properties": {
    "iso:country":"US",
    "sg:address":"122 Johnston St",
    "sg:city":"Longview",
    "sg:classifiers":[
        {
            "category":"Food & Beverages",
            "subcategory":"Dairy",
            "type":"Retail Goods"
        }
    ],
    "sg:phone":"+1 903 757 7919",
    "sg:postcode":"75601",
    "sg:province":"TX",
    "sg:tags":[
        "product"
    ],
    "wof:name":"Brians Scotts Snowballs Snacks",
    "wof:placetype":"venue"
},
  "geometry": {"coordinates":[-94.741175,32.515473],"type":"Point"}
}