{
  "type": "Feature",
  "properties": {
    "iso:country":"US",
    "sg:address":"555 W Interstate 30",
    "sg:city":"Garland",
    "sg:classifiers":[
        {
            "category":"Personal",
            "subcategory":"Nail Salon",
            "type":"Services"
        }
    ],
    "sg:phone":"+1 972 240 5522",
    "sg:postcode":"75043",
    "sg:province":"TX",
    "wof:name":"California Nails USA",
    "wof:placetype":"venue"
},
  "geometry": {"coordinates":[-96.596497,32.840199],"type":"Point"}
}