{
  "type": "Feature",
  "properties": {
    "iso:country":"US",
    "sg:address":"1304 US Hwy 271",
    "sg:city":"Gilmer",
    "sg:classifiers":[
        {
            "category":"Manufacturing",
            "subcategory":"Tools & Machinery",
            "type":"Manufacturing & Wholesale Goods"
        },
        {
            "category":"Retail",
            "subcategory":"Auto Repair",
            "type":"Services"
        }
    ],
    "sg:phone":"+1 903 797 6490",
    "sg:postcode":"75644",
    "sg:province":"TX",
    "sg:tags":[
        "general"
    ],
    "wof:name":"Steelmans Garage",
    "wof:placetype":"venue"
},
  "geometry": {"coordinates":[-94.941822,32.741342],"type":"Point"}
}