{
  "type": "Feature",
  "properties": {
    "iso:country":"US",
    "sg:address":"8105 Spring Valley Ln",
    "sg:city":"Plano",
    "sg:classifiers":[
        {
            "category":"Wholesale",
            "subcategory":"Home Furnishings",
            "type":"Manufacturing & Wholesale Goods"
        }
    ],
    "sg:phone":"+1 972 377 9306",
    "sg:postcode":"75025",
    "sg:province":"TX",
    "wof:name":"Vintage Designs LLC",
    "wof:placetype":"venue"
},
  "geometry": {"coordinates":[-96.757863,33.090118],"type":"Point"}
}