{
  "type": "Feature",
  "properties": {
    "iso:country":"US",
    "sg:address":"400 Ave F",
    "sg:city":"Bay City",
    "sg:classifiers":[
        {
            "category":"Health Services",
            "subcategory":"Hospital",
            "type":"Services"
        }
    ],
    "sg:phone":"+1 979 245 3806",
    "sg:postcode":"77414",
    "sg:province":"TX",
    "sg:tags":[
        "specialty"
    ],
    "wof:name":"Council On Substance Abuse",
    "wof:placetype":"venue"
},
  "geometry": {"coordinates":[-95.97356600000001,29.009566],"type":"Point"}
}