{
  "type": "Feature",
  "properties": {
    "iso:country":"US",
    "sg:address":"5002 Parkridge Dr",
    "sg:city":"Houston",
    "sg:classifiers":[
        {
            "category":"Wholesale",
            "subcategory":"Non-durable Goods",
            "type":"Manufacturing & Wholesale Goods"
        }
    ],
    "sg:phone":"+1 281 437 5802",
    "sg:postcode":"77053",
    "sg:province":"TX",
    "wof:name":"Lyons Laurent Trading Company",
    "wof:placetype":"venue"
},
  "geometry": {"coordinates":[-95.46240899999999,29.58404],"type":"Point"}
}