{
  "type": "Feature",
  "properties": {
    "iso:country":"US",
    "sg:address":"700 Milam St",
    "sg:city":"Houston",
    "sg:classifiers":[
        {
            "category":"Mining & Drilling",
            "type":"Manufacturing & Wholesale Goods"
        }
    ],
    "sg:phone":"+1 713 546 8907",
    "sg:postcode":"77002",
    "sg:province":"TX",
    "sg:tags":[
        "production",
        "gas",
        "oil"
    ],
    "wof:name":"Savannah Company",
    "wof:placetype":"venue"
},
  "geometry": {"coordinates":[-95.36549100000001,29.759507],"type":"Point"}
}