{
  "type": "Feature",
  "properties": {
    "iso:country":"US",
    "sg:address":"515 Sedberry Ct",
    "sg:city":"San Antonio",
    "sg:classifiers":[
        {
            "category":"Banks & Credit Unions",
            "subcategory":"Financial Services",
            "type":"Services"
        }
    ],
    "sg:phone":"+1 210 497 8551",
    "sg:postcode":"78258",
    "sg:province":"TX",
    "sg:tags":[
        "investor"
    ],
    "wof:name":"Rain Investments Inc",
    "wof:placetype":"venue"
},
  "geometry": {"coordinates":[-98.50340300000001,29.640661],"type":"Point"}
}