{
  "type": "Feature",
  "properties": {
    "iso:country":"US",
    "sg:address":"111 Ramble Ln",
    "sg:city":"Austin",
    "sg:classifiers":[
        {
            "category":"Building & Trades",
            "subcategory":"Construction",
            "type":"Services"
        }
    ],
    "sg:phone":"+1 512 326 2633",
    "sg:postcode":"78745",
    "sg:province":"TX",
    "sg:tags":[
        "fire",
        "restoration",
        "damage"
    ],
    "sg:website":"www.austinhi-tech.com",
    "wof:name":"Austin Hi-Tech Restoration",
    "wof:placetype":"venue"
},
  "geometry": {"coordinates":[-97.774997,30.209921],"type":"Point"}
}