{
  "type": "Feature",
  "properties": {
    "iso:country":"US",
    "sg:address":"3307 W Pleasant Run Rd",
    "sg:city":"Lancaster",
    "sg:classifiers":[
        {
            "category":"Restaurant",
            "type":"Food & Drink"
        }
    ],
    "sg:menulink":"http://www.allmenus.com/tx/southwest/44743-chubbys/menu/",
    "sg:phone":"+1 972 228 4101",
    "sg:postcode":"75146",
    "sg:province":"TX",
    "sg:tags":[
        "american"
    ],
    "wof:name":"Chubby's",
    "wof:placetype":"venue"
},
  "geometry": {"coordinates":[-96.819361,32.604294],"type":"Point"}
}