{
  "type": "Feature",
  "properties": {
    "iso:country":"US",
    "sg:address":"3440 Lockwood Rd",
    "sg:city":"Richmond",
    "sg:classifiers":[
        {
            "category":"Utilities",
            "subcategory":"Electric",
            "type":"Services"
        },
        {
            "category":"Building & Trades",
            "subcategory":"Electrical",
            "type":"Services"
        }
    ],
    "sg:phone":"+1 281 545 8930",
    "sg:postcode":"77469",
    "sg:province":"TX",
    "sg:tags":[
        "industrial",
        "electrician",
        "contractors-commercial"
    ],
    "sg:website":"http://www.calpine.com",
    "wof:name":"Calpine Corporation",
    "wof:placetype":"venue"
},
  "geometry": {"coordinates":[-95.621403,29.469819],"type":"Point"}
}