{
  "type": "Feature",
  "properties": {
    "iso:country":"US",
    "sg:address":"1112 Post Oak Ln",
    "sg:city":"De Soto",
    "sg:classifiers":[
        {
            "category":"Professional",
            "type":"Services"
        }
    ],
    "sg:phone":"+1 972 224 5344",
    "sg:postcode":"75115",
    "sg:province":"TX",
    "wof:name":"Mlp Homehealth Services",
    "wof:placetype":"venue"
},
  "geometry": {"coordinates":[-96.83022800000001,32.614479],"type":"Point"}
}