{
  "type": "Feature",
  "properties": {
    "iso:country":"US",
    "sg:address":"3724 Compton Rd",
    "sg:city":"Valley Mills",
    "sg:classifiers":[
        {
            "category":"Farming",
            "subcategory":"Livestock Farm",
            "type":"Manufacturing & Wholesale Goods"
        }
    ],
    "sg:phone":"+1 254 848 4713",
    "sg:postcode":"76689",
    "sg:province":"TX",
    "sg:tags":[
        "beef",
        "feedlot",
        "cattle"
    ],
    "wof:name":"David Miller",
    "wof:placetype":"venue"
},
  "geometry": {"coordinates":[-97.40715899999999,31.592926],"type":"Point"}
}