{
  "type": "Feature",
  "properties": {
    "iso:country":"US",
    "sg:address":"1101 Scott Ave",
    "sg:city":"Wichita Falls",
    "sg:classifiers":[
        {
            "category":"Professional",
            "type":"Services"
        }
    ],
    "sg:phone":"+1 940 322 3411",
    "sg:postcode":"76301",
    "sg:province":"TX",
    "sg:tags":[
        "establishment"
    ],
    "wof:name":"Baker-Garrett Enterprises Inc",
    "wof:placetype":"venue"
},
  "geometry": {"coordinates":[-98.48888599999999,33.908006],"type":"Point"}
}