{
  "type": "Feature",
  "properties": {
    "iso:country":"US",
    "sg:address":"805 E Hill St",
    "sg:city":"Hamilton",
    "sg:classifiers":[
        {
            "category":"Shopping",
            "subcategory":"Used Merchandise",
            "type":"Retail Goods"
        }
    ],
    "sg:phone":"+1 254 386 3499",
    "sg:postcode":"76531",
    "sg:province":"TX",
    "wof:name":"Hoppers Tires",
    "wof:placetype":"venue"
},
  "geometry": {"coordinates":[-98.116243,31.695325],"type":"Point"}
}