{
  "type": "Feature",
  "properties": {
    "iso:country":"US",
    "sg:address":"315 N Delaware St",
    "sg:city":"Irving",
    "sg:classifiers":[
        {
            "category":"Retail",
            "subcategory":"Auto Repair",
            "type":"Services"
        }
    ],
    "sg:phone":"+1 972 870 5154",
    "sg:postcode":"75061",
    "sg:province":"TX",
    "wof:name":"Chavez Auto Repair",
    "wof:placetype":"venue"
},
  "geometry": {"coordinates":[-96.943714,32.81603],"type":"Point"}
}