{
  "type": "Feature",
  "properties": {
    "iso:country":"US",
    "sg:address":"408 E Loop 254",
    "sg:city":"Ranger",
    "sg:classifiers":[
        {
            "category":"Shopping",
            "subcategory":"Gifts & Souvenirs",
            "type":"Retail Goods"
        },
        {
            "category":"Shopping",
            "subcategory":"Florist",
            "type":"Retail Goods"
        }
    ],
    "sg:phone":"+1 254 647 3303",
    "sg:postcode":"76470",
    "sg:province":"TX",
    "sg:tags":[
        "shop"
    ],
    "wof:name":"Best Friends Gifts And More",
    "wof:placetype":"venue"
},
  "geometry": {"coordinates":[-98.676213,32.472329],"type":"Point"}
}