{
  "type": "Feature",
  "properties": {
    "iso:country":"US",
    "sg:address":"2116 FM 2071",
    "sg:city":"Gainesville",
    "sg:classifiers":[
        {
            "category":"Building & Trades",
            "subcategory":"Electrical",
            "type":"Services"
        }
    ],
    "sg:phone":"+1 940 665 3046",
    "sg:postcode":"76240",
    "sg:province":"TX",
    "sg:tags":[
        "electric",
        "contractor"
    ],
    "wof:name":"Dave's Electric",
    "wof:placetype":"venue"
},
  "geometry": {"coordinates":[-97.130835,33.600615],"type":"Point"}
}