{
  "type": "Feature",
  "properties": {
    "iso:country":"US",
    "sg:address":"402 Koberlin St",
    "sg:city":"San Angelo",
    "sg:classifiers":[
        {
            "category":"Shopping",
            "subcategory":"Florist",
            "type":"Retail Goods"
        }
    ],
    "sg:phone":"+1 325 655 7367",
    "sg:postcode":"76903",
    "sg:province":"TX",
    "sg:website":"www.ridgwayflorist.com",
    "wof:name":"Tom Ridgway Florist & Grnhse",
    "wof:placetype":"venue"
},
  "geometry": {"coordinates":[-100.428622,31.468092],"type":"Point"}
}