{
  "type": "Feature",
  "properties": {
    "iso:country":"US",
    "sg:address":"2330 W Airport Fwy",
    "sg:city":"Irving",
    "sg:classifiers":[
        {
            "category":"Autos & Motor Vehicles",
            "subcategory":"Fuel & Gas Station",
            "type":"Retail Goods"
        },
        {
            "category":"Food & Beverages",
            "subcategory":"Groceries & Convenience Stores",
            "type":"Retail Goods"
        }
    ],
    "sg:phone":"+1 972 790 8323",
    "sg:postcode":"75062",
    "sg:province":"TX",
    "wof:name":"Southern United Enterprise",
    "wof:placetype":"venue"
},
  "geometry": {"coordinates":[-96.975482,32.836592],"type":"Point"}
}