{
  "type": "Feature",
  "properties": {
    "iso:country":"US",
    "sg:address":"704 E 15th St",
    "sg:city":"Plano",
    "sg:classifiers":[
        {
            "category":"Insurance",
            "subcategory":"Insurance Agent",
            "type":"Services"
        }
    ],
    "sg:phone":"+1 972 881 4606",
    "sg:postcode":"75074",
    "sg:province":"TX",
    "wof:name":"Cafeteria Plan Solutions",
    "wof:placetype":"venue"
},
  "geometry": {"coordinates":[-96.705549,33.019567],"type":"Point"}
}