{
  "type": "Feature",
  "properties": {
    "iso:country":"US",
    "sg:address":"4230 Spring Valley Rd",
    "sg:city":"Dallas",
    "sg:classifiers":[
        {
            "category":"Wholesale",
            "subcategory":"Machinery & Supplies",
            "type":"Manufacturing & Wholesale Goods"
        }
    ],
    "sg:phone":"+1 903 839 3071",
    "sg:postcode":"75244",
    "sg:province":"TX",
    "sg:tags":[
        "equipment",
        "industrial"
    ],
    "wof:name":"Wilson-Mohr Inc",
    "wof:placetype":"venue"
},
  "geometry": {"coordinates":[-96.83717799999999,32.93978],"type":"Point"}
}