{
  "type": "Feature",
  "properties": {
    "iso:country":"US",
    "sg:address":"2410 W Division St",
    "sg:city":"Arlington",
    "sg:classifiers":[
        {
            "category":"Utilities",
            "subcategory":"Refuse",
            "type":"Services"
        }
    ],
    "sg:phone":"+1 817 794 0181",
    "sg:postcode":"76012",
    "sg:province":"TX",
    "sg:tags":[
        "material",
        "system"
    ],
    "wof:name":"Master Fibers Inc",
    "wof:placetype":"venue"
},
  "geometry": {"coordinates":[-97.14739299999999,32.73585],"type":"Point"}
}