{
  "type": "Feature",
  "properties": {
    "iso:country":"US",
    "sg:address":"182 Bar L Mesa Dr",
    "sg:city":"Cedar Creek",
    "sg:classifiers":[
        {
            "category":"Building & Trades",
            "subcategory":"Plumbing",
            "type":"Services"
        }
    ],
    "sg:phone":"+1 512 581 0231",
    "sg:postcode":"78612",
    "sg:province":"TX",
    "sg:tags":[
        "conditioning",
        "air",
        "system",
        "contractor"
    ],
    "wof:name":"Cool Air Systems",
    "wof:placetype":"venue"
},
  "geometry": {"coordinates":[-97.40951699999999,30.053232],"type":"Point"}
}