{
  "type": "Feature",
  "properties": {
    "iso:country":"US",
    "sg:address":"6700 N Mesa St",
    "sg:city":"El Paso",
    "sg:classifiers":[
        {
            "category":"Insurance",
            "subcategory":"Title Insurance",
            "type":"Services"
        },
        {
            "category":"Real Estate",
            "subcategory":"Real Estate Services",
            "type":"Services"
        }
    ],
    "sg:phone":"+1 915 543 7500",
    "sg:postcode":"79912",
    "sg:province":"TX",
    "sg:tags":[
        "company",
        "carrier"
    ],
    "wof:name":"Land America Lawyers Title",
    "wof:placetype":"venue"
},
  "geometry": {"coordinates":[-106.54369,31.834513],"type":"Point"}
}