{
  "type": "Feature",
  "properties": {
    "iso:country":"US",
    "sg:address":"13711 Immanuel Rd",
    "sg:city":"Pflugerville",
    "sg:classifiers":[
        {
            "category":"Wholesale",
            "subcategory":"Machinery & Supplies",
            "type":"Manufacturing & Wholesale Goods"
        },
        {
            "category":"Retail",
            "subcategory":"Repair Shop",
            "type":"Services"
        }
    ],
    "sg:phone":"+1 512 236 1960",
    "sg:postcode":"78660",
    "sg:province":"TX",
    "sg:tags":[
        "pump",
        "pumps-service"
    ],
    "wof:name":"PHi",
    "wof:placetype":"venue"
},
  "geometry": {"coordinates":[-97.629008,30.404352],"type":"Point"}
}