{
  "type": "Feature",
  "properties": {
    "iso:country":"US",
    "sg:address":"5430 Delong St",
    "sg:city":"San Angelo",
    "sg:classifiers":[
        {
            "category":"Building & Trades",
            "subcategory":"Construction",
            "type":"Services"
        }
    ],
    "sg:phone":"+1 325 653 5477",
    "sg:postcode":"76903",
    "sg:province":"TX",
    "sg:tags":[
        "house"
    ],
    "wof:name":"West Texas Contractors",
    "wof:placetype":"venue"
},
  "geometry": {"coordinates":[-100.47407800000001,31.520975],"type":"Point"}
}