{
  "type": "Feature",
  "properties": {
    "iso:country":"US",
    "sg:address":"107 N 21st St",
    "sg:city":"Temple",
    "sg:classifiers":[
        {
            "category":"Retail",
            "subcategory":"Funeral Services",
            "type":"Services"
        }
    ],
    "sg:phone":"+1 254 771 1155",
    "sg:postcode":"76504",
    "sg:province":"TX",
    "sg:tags":[
        "director"
    ],
    "wof:name":"Temple Mortuary Svc",
    "wof:placetype":"venue"
},
  "geometry": {"coordinates":[-97.351099,31.101763],"type":"Point"}
}