{
  "type": "Feature",
  "properties": {
    "iso:country":"US",
    "sg:address":"15295 Southwest Fwy",
    "sg:city":"Sugar Land",
    "sg:classifiers":[
        {
            "category":"Restaurant",
            "type":"Food & Drink"
        }
    ],
    "sg:menulink":"http://www.allmenus.com/tx/sugar-land/15730-leonardos-italian-bistro/menu/",
    "sg:phone":"+1 281 565 2949",
    "sg:postcode":"77478",
    "sg:province":"TX",
    "sg:tags":[
        "italian"
    ],
    "wof:name":"Leonardo's Italian Bistro",
    "wof:placetype":"venue"
},
  "geometry": {"coordinates":[-95.614441,29.605493],"type":"Point"}
}