{
  "type": "Feature",
  "properties": {
    "iso:country":"US",
    "sg:address":"8518 FM 1826",
    "sg:city":"Austin",
    "sg:classifiers":[
        {
            "category":"Building & Trades",
            "subcategory":"Landscaping Services",
            "type":"Services"
        }
    ],
    "sg:phone":"+1 512 331 8733",
    "sg:postcode":"78737",
    "sg:province":"TX",
    "sg:tags":[
        "tree"
    ],
    "wof:name":"Arbor Consulting",
    "wof:placetype":"venue"
},
  "geometry": {"coordinates":[-97.891626,30.223892],"type":"Point"}
}