{
  "type": "Feature",
  "properties": {
    "iso:country":"US",
    "sg:address":"4843 Colleyville Blvd",
    "sg:city":"Colleyville",
    "sg:classifiers":[
        {
            "category":"Retail",
            "subcategory":"Auto Rental",
            "type":"Services"
        }
    ],
    "sg:phone":"+1 817 788 5903",
    "sg:postcode":"76034",
    "sg:province":"TX",
    "sg:tags":[
        "renting",
        "automobile"
    ],
    "wof:name":"Enterprise Rent-A-Car",
    "wof:placetype":"venue"
},
  "geometry": {"coordinates":[-97.157681,32.878986],"type":"Point"}
}