{
  "type": "Feature",
  "properties": {
    "iso:country":"US",
    "sg:address":"1831 Parhaven Dr",
    "sg:city":"San Antonio",
    "sg:classifiers":[
        {
            "category":"Restaurant",
            "type":"Food & Drink"
        }
    ],
    "sg:phone":"+1 210 496 9732",
    "sg:postcode":"78232",
    "sg:province":"TX",
    "sg:tags":[
        "eating"
    ],
    "wof:name":"Pasta To Go",
    "wof:placetype":"venue"
},
  "geometry": {"coordinates":[-98.46445,29.601487],"type":"Point"}
}