{
  "type": "Feature",
  "properties": {
    "iso:country":"US",
    "sg:address":"102 S Phillips Ranch Rd",
    "sg:city":"Granite Shoals",
    "sg:classifiers":[
        {
            "category":"Personal",
            "subcategory":"Beauty Salon",
            "type":"Services"
        }
    ],
    "sg:phone":"+1 830 598 2641",
    "sg:postcode":"78654",
    "sg:province":"TX",
    "wof:name":"Anne's Hair Country",
    "wof:placetype":"venue"
},
  "geometry": {"coordinates":[-98.387503,30.589351],"type":"Point"}
}