{
  "type": "Feature",
  "properties": {
    "iso:country":"US",
    "sg:address":"4009 Chestnut St",
    "sg:city":"Fort Worth",
    "sg:classifiers":[
        {
            "category":"Restaurant",
            "type":"Food & Drink"
        }
    ],
    "sg:phone":"+1 817 232 5800",
    "sg:postcode":"76137",
    "sg:province":"TX",
    "wof:name":"Rib Shack The",
    "wof:placetype":"venue"
},
  "geometry": {"coordinates":[-97.296387,32.862988],"type":"Point"}
}