{
  "type": "Feature",
  "properties": {
    "iso:country":"US",
    "sg:address":"4030 Weber Rd",
    "sg:city":"Corpus Christi",
    "sg:classifiers":[
        {
            "category":"Recreation",
            "type":"Entertainment"
        }
    ],
    "sg:phone":"+1 361 852 8776",
    "sg:postcode":"78411",
    "sg:province":"TX",
    "sg:tags":[
        "club",
        "softball"
    ],
    "wof:name":"Corpus Christi Softball Assn",
    "wof:placetype":"venue"
},
  "geometry": {"coordinates":[-97.38816300000001,27.738532],"type":"Point"}
}