{
  "type": "Feature",
  "properties": {
    "iso:country":"US",
    "sg:address":"11906 Briar Forest Dr",
    "sg:city":"Houston",
    "sg:classifiers":[
        {
            "category":"Professional",
            "type":"Services"
        }
    ],
    "sg:phone":"+1 281 759 7850",
    "sg:postcode":"77077",
    "sg:province":"TX",
    "sg:tags":[
        "establishment"
    ],
    "wof:name":"Maloy Specialties Co",
    "wof:placetype":"venue"
},
  "geometry": {"coordinates":[-95.59186099999999,29.751174],"type":"Point"}
}