{
  "type": "Feature",
  "properties": {
    "iso:country":"US",
    "sg:address":"612 Deforest Rd",
    "sg:city":"Coppell",
    "sg:classifiers":[
        {
            "category":"Professional",
            "type":"Services"
        }
    ],
    "sg:phone":"+1 972 393 2486",
    "sg:postcode":"75019",
    "sg:province":"TX",
    "wof:name":"Arcteriors",
    "wof:placetype":"venue"
},
  "geometry": {"coordinates":[-96.97617099999999,32.987277],"type":"Point"}
}