{
  "type": "Feature",
  "properties": {
    "iso:country":"US",
    "sg:address":"13606 Maham Rd",
    "sg:city":"Dallas",
    "sg:classifiers":[
        {
            "category":"Banks & Credit Unions",
            "subcategory":"Investment Brokerage",
            "type":"Services"
        }
    ],
    "sg:phone":"+1 214 691 7600",
    "sg:postcode":"75240",
    "sg:province":"TX",
    "sg:tags":[
        "management"
    ],
    "wof:name":"Fifteen Asset Mgmt Group LLC",
    "wof:placetype":"venue"
},
  "geometry": {"coordinates":[-96.761156,32.934295],"type":"Point"}
}