{
  "type": "Feature",
  "properties": {
    "iso:country":"US",
    "sg:address":"2311 W Clarendon Dr",
    "sg:city":"Dallas",
    "sg:classifiers":[
        {
            "category":"Home & Garden",
            "subcategory":"Household Appliances",
            "type":"Retail Goods"
        }
    ],
    "sg:phone":"+1 214 941 4868",
    "sg:postcode":"75208",
    "sg:province":"TX",
    "wof:name":"B & M Sales",
    "wof:placetype":"venue"
},
  "geometry": {"coordinates":[-96.85615199999999,32.734794],"type":"Point"}
}