{
  "type": "Feature",
  "properties": {
    "iso:country":"US",
    "sg:address":"418 N Grant Ave",
    "sg:city":"Odessa",
    "sg:classifiers":[
        {
            "category":"Social Services",
            "subcategory":"Child Care",
            "type":"Services"
        }
    ],
    "sg:phone":"+1 432 337 2608",
    "sg:postcode":"79761",
    "sg:province":"TX",
    "wof:name":"Head Start Maintenance",
    "wof:placetype":"venue"
},
  "geometry": {"coordinates":[-102.36939599999999,31.848237],"type":"Point"}
}