{
  "type": "Feature",
  "properties": {
    "iso:country":"US",
    "sg:address":"7726 Forest Ln",
    "sg:city":"Dallas",
    "sg:classifiers":[
        {
            "category":"Personal",
            "type":"Services"
        }
    ],
    "sg:phone":"+1 214 348 6723",
    "sg:postcode":"75230",
    "sg:province":"TX",
    "sg:tags":[
        "bankruptcy"
    ],
    "wof:name":"We The People",
    "wof:placetype":"venue"
},
  "geometry": {"coordinates":[-96.77184099999999,32.909333],"type":"Point"}
}