{
  "type": "Feature",
  "properties": {
    "iso:country":"US",
    "sg:address":"18100 Upper Bay Rd",
    "sg:city":"Houston",
    "sg:classifiers":[
        {
            "category":"Professional",
            "type":"Services"
        }
    ],
    "sg:phone":"+1 281 335 1633",
    "sg:postcode":"77058",
    "sg:province":"TX",
    "wof:name":"Cernosek Interests LLC",
    "wof:placetype":"venue"
},
  "geometry": {"coordinates":[-95.08954,29.549735],"type":"Point"}
}