{
  "type": "Feature",
  "properties": {
    "iso:country":"US",
    "sg:address":"1727 Fawn Gate St",
    "sg:city":"San Antonio",
    "sg:classifiers":[
        {
            "category":"Freight",
            "type":"Transportation"
        }
    ],
    "sg:phone":"+1 210 363 7075",
    "sg:postcode":"78248",
    "sg:province":"TX",
    "sg:tags":[
        "general"
    ],
    "wof:name":"GSM Insurors Services",
    "wof:placetype":"venue"
},
  "geometry": {"coordinates":[-98.521276,29.591364],"type":"Point"}
}