{
  "type": "Feature",
  "properties": {
    "iso:country":"US",
    "sg:address":"3100 E Park Row Dr",
    "sg:city":"Arlington",
    "sg:classifiers":[
        {
            "category":"Real Estate",
            "subcategory":"Real Estate Operator",
            "type":"Services"
        }
    ],
    "sg:phone":"+1 817 649 6000",
    "sg:postcode":"76010",
    "sg:province":"TX",
    "sg:tags":[
        "building",
        "apartment"
    ],
    "wof:name":"Park Lane Apartments",
    "wof:placetype":"venue"
},
  "geometry": {"coordinates":[-97.053297,32.720669],"type":"Point"}
}