{
  "type": "Feature",
  "properties": {
    "iso:country":"US",
    "sg:address":"14 Garceno Loop",
    "sg:city":"Roma",
    "sg:classifiers":[
        {
            "category":"Freight",
            "type":"Transportation"
        }
    ],
    "sg:phone":"+1 956 849 3364",
    "sg:postcode":"78584",
    "sg:province":"TX",
    "sg:tags":[
        "operator",
        "local",
        "trucking"
    ],
    "wof:name":"Rosa Trucking",
    "wof:placetype":"venue"
},
  "geometry": {"coordinates":[-98.94230899999999,26.40961],"type":"Point"}
}