{
  "type": "Feature",
  "properties": {
    "iso:country":"US",
    "sg:address":"400 Enterprise Blvd Ste C",
    "sg:city":"Rockport",
    "sg:classifiers":[
        {
            "category":"Shopping",
            "subcategory":"Gifts & Souvenirs",
            "type":"Retail Goods"
        }
    ],
    "sg:phone":"+1 361 729 2531",
    "sg:postcode":"78382",
    "sg:province":"TX",
    "sg:tags":[
        "shop"
    ],
    "wof:name":"Enterprises Medical Center",
    "wof:placetype":"venue"
},
  "geometry": {"coordinates":[-97.058273,28.04035],"type":"Point"}
}