{
  "type": "Feature",
  "properties": {
    "iso:country":"US",
    "sg:address":"7929 Valentine Ct",
    "sg:city":"Dallas",
    "sg:classifiers":[
        {
            "category":"Shopping",
            "subcategory":"Hobbies, Toys, & Games",
            "type":"Retail Goods"
        }
    ],
    "sg:phone":"+1 214 398 4190",
    "sg:postcode":"75217",
    "sg:province":"TX",
    "wof:name":"Georgias Ceramics",
    "wof:placetype":"venue"
},
  "geometry": {"coordinates":[-96.68622499999999,32.741009],"type":"Point"}
}