{
  "type": "Feature",
  "properties": {
    "iso:country":"US",
    "sg:address":"115 S Timberland Dr",
    "sg:city":"Lufkin",
    "sg:classifiers":[
        {
            "category":"Personal",
            "subcategory":"Barber",
            "type":"Services"
        }
    ],
    "sg:phone":"+1 936 634 7119",
    "sg:postcode":"75901",
    "sg:province":"TX",
    "wof:name":"Cut-N-Up",
    "wof:placetype":"venue"
},
  "geometry": {"coordinates":[-94.717845,31.336196],"type":"Point"}
}