{
  "type": "Feature",
  "properties": {
    "iso:country":"US",
    "sg:address":"2578 Southwell Rd",
    "sg:city":"Dallas",
    "sg:classifiers":[
        {
            "category":"Manufacturing",
            "subcategory":"Printing",
            "type":"Manufacturing & Wholesale Goods"
        }
    ],
    "sg:phone":"+1 972 620 1001",
    "sg:postcode":"75229",
    "sg:province":"TX",
    "sg:tags":[
        "screen"
    ],
    "wof:name":"Texas Screen Graphics",
    "wof:placetype":"venue"
},
  "geometry": {"coordinates":[-96.892004,32.88627],"type":"Point"}
}