{
  "type": "Feature",
  "properties": {
    "iso:country":"US",
    "sg:address":"10460 FM 2673",
    "sg:city":"Canyon Lake",
    "sg:classifiers":[
        {
            "category":"Real Estate",
            "subcategory":"Real Estate Agent",
            "type":"Services"
        }
    ],
    "sg:phone":"+1 830 899 2264",
    "sg:postcode":"78133",
    "sg:province":"TX",
    "wof:name":"Coldwell Banker D'Ann Harper",
    "wof:placetype":"venue"
},
  "geometry": {"coordinates":[-98.29549,29.86701],"type":"Point"}
}