{
  "type": "Feature",
  "properties": {
    "iso:country":"US",
    "sg:address":"108 S 1st St",
    "sg:city":"Lufkin",
    "sg:classifiers":[
        {
            "category":"Home & Garden",
            "subcategory":"Home Furnishings",
            "type":"Retail Goods"
        }
    ],
    "sg:phone":"+1 936 699 2300",
    "sg:postcode":"75901",
    "sg:province":"TX",
    "sg:tags":[
        "furniture"
    ],
    "wof:name":"Custom Lamps & Shades",
    "wof:placetype":"venue"
},
  "geometry": {"coordinates":[-94.728915,31.339062],"type":"Point"}
}