{
  "type": "Feature",
  "properties": {
    "iso:country":"US",
    "sg:address":"10203 Barwood Dr",
    "sg:city":"Houston",
    "sg:classifiers":[
        {
            "category":"Professional",
            "subcategory":"Art Services",
            "type":"Services"
        },
        {
            "category":"Professional",
            "subcategory":"Computer Services",
            "type":"Services"
        }
    ],
    "sg:phone":"+1 713 467 3579",
    "sg:postcode":"77043",
    "sg:province":"TX",
    "sg:tags":[
        "motion",
        "photography",
        "production",
        "commercial",
        "graphics"
    ],
    "sg:website":"www.buckward.com",
    "wof:name":"Buckward Digital Services Inc",
    "wof:placetype":"venue"
},
  "geometry": {"coordinates":[-95.55364299999999,29.805663],"type":"Point"}
}