{
  "type": "Feature",
  "properties": {
    "iso:country":"US",
    "sg:address":"2400 Pleasant Rose Cir",
    "sg:city":"Bryan",
    "sg:classifiers":[
        {
            "category":"Manufacturing",
            "subcategory":"Printing",
            "type":"Manufacturing & Wholesale Goods"
        }
    ],
    "sg:phone":"+1 979 774 7051",
    "sg:postcode":"77808",
    "sg:province":"TX",
    "sg:tags":[
        "commercial"
    ],
    "wof:name":"Page Prints",
    "wof:placetype":"venue"
},
  "geometry": {"coordinates":[-96.330647,30.677148],"type":"Point"}
}