{
  "type": "Feature",
  "properties": {
    "iso:country":"US",
    "sg:address":"5208 Padre Blvd",
    "sg:city":"S Padre Island",
    "sg:classifiers":[
        {
            "category":"Freight",
            "type":"Transportation"
        },
        {
            "category":"Professional",
            "subcategory":"Business Services",
            "type":"Services"
        }
    ],
    "sg:phone":"+1 956 772 9700",
    "sg:postcode":"78597",
    "sg:province":"TX",
    "sg:tags":[
        "shipping",
        "agent"
    ],
    "wof:name":"Shipping's Our Specialty",
    "wof:placetype":"venue"
},
  "geometry": {"coordinates":[-97.17051600000001,26.124086],"type":"Point"}
}