{
  "type": "Feature",
  "properties": {
    "iso:country":"US",
    "sg:address":"26 Richardson Heights Center",
    "sg:city":"Richardson",
    "sg:classifiers":[
        {
            "category":"Restaurant",
            "type":"Food & Drink"
        }
    ],
    "sg:phone":"+1 972 234 9009",
    "sg:postcode":"75080",
    "sg:province":"TX",
    "wof:name":"Hot Breads",
    "wof:placetype":"venue"
},
  "geometry": {"coordinates":[-96.735951,32.950533],"type":"Point"}
}