{
  "type": "Feature",
  "properties": {
    "iso:country":"US",
    "sg:address":"14150 Wunderlich Dr",
    "sg:city":"Houston",
    "sg:classifiers":[
        {
            "category":"Education",
            "subcategory":"Special Training",
            "type":"Public Place"
        },
        {
            "category":"Education",
            "subcategory":"Vocational School",
            "type":"Public Place"
        }
    ],
    "sg:phone":"+1 281 440 0666",
    "sg:postcode":"77069",
    "sg:province":"TX",
    "sg:tags":[
        "secretarial"
    ],
    "wof:name":"Development Training Institute",
    "wof:placetype":"venue"
},
  "geometry": {"coordinates":[-95.50606000000001,29.985369],"type":"Point"}
}