{
  "type": "Feature",
  "properties": {
    "iso:country":"US",
    "sg:address":"1009 Lakewood Dr",
    "sg:city":"Mc Kinney",
    "sg:classifiers":[
        {
            "category":"Professional",
            "subcategory":"Business Services",
            "type":"Services"
        }
    ],
    "sg:phone":"+1 972 529 9059",
    "sg:postcode":"75070",
    "sg:province":"TX",
    "sg:tags":[
        "interior",
        "consultant",
        "design",
        "decorator"
    ],
    "wof:name":"Susan Dupre Interiors",
    "wof:placetype":"venue"
},
  "geometry": {"coordinates":[-96.682435,33.186776],"type":"Point"}
}