{
  "type": "Feature",
  "properties": {
    "iso:country":"US",
    "sg:address":"150 Sundance Pkwy",
    "sg:city":"Round Rock",
    "sg:classifiers":[
        {
            "category":"Restaurant",
            "type":"Food & Drink"
        }
    ],
    "sg:menulink":"http://www.allmenus.com/tx/georgetown-round-rock/222031-chipotle/menu/",
    "sg:phone":"+1 512 828 0788",
    "sg:postcode":"78681",
    "sg:province":"TX",
    "sg:tags":[
        "mexican"
    ],
    "wof:name":"Chipotle",
    "wof:placetype":"venue"
},
  "geometry": {"coordinates":[-97.681617,30.483067],"type":"Point"}
}