{
  "type": "Feature",
  "properties": {
    "iso:country":"US",
    "sg:address":"1705 Shady Glen Ln",
    "sg:city":"Dallas",
    "sg:classifiers":[
        {
            "category":"Building & Trades",
            "subcategory":"Construction",
            "type":"Services"
        }
    ],
    "sg:phone":"+1 214 337 6310",
    "sg:postcode":"75232",
    "sg:province":"TX",
    "sg:tags":[
        "home",
        "builder"
    ],
    "wof:name":"Your Home Creation",
    "wof:placetype":"venue"
},
  "geometry": {"coordinates":[-96.85042,32.676495],"type":"Point"}
}