{
  "type": "Feature",
  "properties": {
    "iso:country":"US",
    "sg:address":"6 Par Ct",
    "sg:city":"Longview",
    "sg:classifiers":[
        {
            "category":"Shopping",
            "subcategory":"Hobbies, Toys, & Games",
            "type":"Retail Goods"
        }
    ],
    "sg:phone":"+1 903 291 0220",
    "sg:postcode":"75605",
    "sg:province":"TX",
    "wof:name":"Leah Overman",
    "wof:placetype":"venue"
},
  "geometry": {"coordinates":[-94.77788700000001,32.54818],"type":"Point"}
}