{
  "type": "Feature",
  "properties": {
    "iso:country":"US",
    "sg:address":"9902 Charter Ridge Dr",
    "sg:city":"Houston",
    "sg:classifiers":[
        {
            "category":"Building & Trades",
            "subcategory":"Electrical",
            "type":"Services"
        }
    ],
    "sg:phone":"+1 281 251 5047",
    "sg:postcode":"77070",
    "sg:province":"TX",
    "sg:tags":[
        "electrical",
        "contractor"
    ],
    "wof:name":"Harris Electrical Services",
    "wof:placetype":"venue"
},
  "geometry": {"coordinates":[-95.574547,30.006184],"type":"Point"}
}