{
  "type": "Feature",
  "properties": {
    "iso:country":"US",
    "sg:address":"10121 Windmill Lakes Blvd",
    "sg:city":"Houston",
    "sg:classifiers":[
        {
            "category":"Banks & Credit Unions",
            "subcategory":"Bank",
            "type":"Services"
        }
    ],
    "sg:phone":"+1 713 943 2419",
    "sg:postcode":"77075",
    "sg:province":"TX",
    "sg:tags":[
        "loan",
        "broker"
    ],
    "wof:name":"Infinity Funding",
    "wof:placetype":"venue"
},
  "geometry": {"coordinates":[-95.241613,29.620026],"type":"Point"}
}