{
  "type": "Feature",
  "properties": {
    "iso:country":"US",
    "sg:address":"1350 S Loop 12",
    "sg:city":"Irving",
    "sg:classifiers":[
        {
            "category":"Building & Trades",
            "subcategory":"Equipment Rental",
            "type":"Services"
        }
    ],
    "sg:phone":"+1 972 579 7506",
    "sg:postcode":"75060",
    "sg:province":"TX",
    "wof:name":"United Rentals",
    "wof:placetype":"venue"
},
  "geometry": {"coordinates":[-96.921001,32.799266],"type":"Point"}
}