{
  "type": "Feature",
  "properties": {
    "iso:country":"US",
    "sg:address":"1400 Mockingbird Ln",
    "sg:city":"Sulphur Springs",
    "sg:classifiers":[
        {
            "category":"Education",
            "subcategory":"School",
            "type":"Public Place"
        }
    ],
    "sg:phone":"+1 903 885 3772",
    "sg:postcode":"75482",
    "sg:province":"TX",
    "wof:name":"Bowie Elementary School",
    "wof:placetype":"venue"
},
  "geometry": {"coordinates":[-95.59312799999999,33.116157],"type":"Point"}
}