{
  "type": "Feature",
  "properties": {
    "iso:country":"US",
    "sg:address":"4713 Glenbrook Dr",
    "sg:city":"Grapevine",
    "sg:classifiers":[
        {
            "category":"Professional",
            "type":"Services"
        }
    ],
    "sg:phone":"+1 817 481 2403",
    "sg:postcode":"76051",
    "sg:province":"TX",
    "wof:name":"Fort Worth Processing",
    "wof:placetype":"venue"
},
  "geometry": {"coordinates":[-97.08284500000001,32.884731],"type":"Point"}
}