{
  "type": "Feature",
  "properties": {
    "iso:country":"US",
    "sg:address":"307 Shadywood Ln",
    "sg:city":"Seagoville",
    "sg:classifiers":[
        {
            "category":"Home & Garden",
            "subcategory":"Building Materials",
            "type":"Retail Goods"
        }
    ],
    "sg:phone":"+1 972 287 1424",
    "sg:postcode":"75159",
    "sg:province":"TX",
    "wof:name":"Huffmans Hardwoods",
    "wof:placetype":"venue"
},
  "geometry": {"coordinates":[-96.53742699999999,32.647206],"type":"Point"}
}