{
  "type": "Feature",
  "properties": {
    "iso:country":"US",
    "sg:address":"513 Cherokee St",
    "sg:city":"Elm Mott",
    "sg:classifiers":[
        {
            "category":"Organizations",
            "subcategory":"Religious Organization",
            "type":"Services"
        }
    ],
    "sg:phone":"+1 254 822 0742",
    "sg:postcode":"76640",
    "sg:province":"TX",
    "wof:name":"Promise Christian Fellowship",
    "wof:placetype":"venue"
},
  "geometry": {"coordinates":[-97.091622,31.673114],"type":"Point"}
}