{
  "type": "Feature",
  "properties": {
    "iso:country":"US",
    "sg:address":"11229 Alvin St",
    "sg:city":"Dallas",
    "sg:classifiers":[
        {
            "category":"Retail",
            "subcategory":"Auto Repair",
            "type":"Services"
        }
    ],
    "sg:phone":"+1 214 321 5255",
    "sg:postcode":"75218",
    "sg:province":"TX",
    "sg:tags":[
        "shop",
        "automotive",
        "general"
    ],
    "wof:name":"Auto Mart",
    "wof:placetype":"venue"
},
  "geometry": {"coordinates":[-96.687701,32.844975],"type":"Point"}
}