{
  "type": "Feature",
  "properties": {
    "iso:country":"US",
    "sg:address":"1100 E Washington St",
    "sg:city":"Stephenville",
    "sg:classifiers":[
        {
            "category":"Real Estate",
            "subcategory":"Surveying",
            "type":"Services"
        }
    ],
    "sg:phone":"+1 254 965 5489",
    "sg:postcode":"76401",
    "sg:province":"TX",
    "sg:tags":[
        "consulting",
        "management"
    ],
    "wof:name":"Wayne Graham Surveying",
    "wof:placetype":"venue"
},
  "geometry": {"coordinates":[-98.19381199999999,32.225373],"type":"Point"}
}