{
  "type": "Feature",
  "properties": {
    "iso:country":"US",
    "sg:address":"316 W Mulberry St",
    "sg:city":"Angleton",
    "sg:classifiers":[
        {
            "category":"Autos & Motor Vehicles",
            "subcategory":"Automobile Sales",
            "type":"Retail Goods"
        }
    ],
    "sg:phone":"+1 979 849 5339",
    "sg:postcode":"77515",
    "sg:province":"TX",
    "sg:tags":[
        "car",
        "used"
    ],
    "wof:name":"Thrifty Car Sales",
    "wof:placetype":"venue"
},
  "geometry": {"coordinates":[-95.435067,29.164267],"type":"Point"}
}