{
  "type": "Feature",
  "properties": {
    "iso:country":"US",
    "sg:address":"5623 Arboles Dr",
    "sg:city":"Houston",
    "sg:classifiers":[
        {
            "category":"Real Estate",
            "subcategory":"Real Estate Operator",
            "type":"Services"
        }
    ],
    "sg:phone":"+1 713 728 3859",
    "sg:postcode":"77035",
    "sg:province":"TX",
    "sg:tags":[
        "building",
        "nonresidential"
    ],
    "wof:name":"Secure Properties Inc",
    "wof:placetype":"venue"
},
  "geometry": {"coordinates":[-95.483867,29.654627],"type":"Point"}
}