{
  "type": "Feature",
  "properties": {
    "iso:country":"US",
    "sg:address":"1001 Preston St",
    "sg:city":"Houston",
    "sg:classifiers":[
        {
            "category":"Professional",
            "subcategory":"Management & Consulting",
            "type":"Services"
        }
    ],
    "sg:phone":"+1 713 755 4014",
    "sg:postcode":"77002",
    "sg:province":"TX",
    "sg:tags":[
        "public",
        "relations"
    ],
    "wof:name":"San Jacinto Community Advance",
    "wof:placetype":"venue"
},
  "geometry": {"coordinates":[-95.360457,29.76097],"type":"Point"}
}