{
  "type": "Feature",
  "properties": {
    "iso:country":"US",
    "sg:address":"300 S Ave Q",
    "sg:city":"Clifton",
    "sg:classifiers":[
        {
            "category":"Health Services",
            "subcategory":"Nursing And Care Facility",
            "type":"Services"
        }
    ],
    "sg:phone":"+1 254 675 8637",
    "sg:postcode":"76634",
    "sg:province":"TX",
    "sg:tags":[
        "home",
        "convalescent"
    ],
    "wof:name":"Clifton Lutheran Sunset Home",
    "wof:placetype":"venue"
},
  "geometry": {"coordinates":[-97.58548399999999,31.776715],"type":"Point"}
}