{
  "type": "Feature",
  "properties": {
    "iso:country":"US",
    "sg:address":"1805 Lincoln St",
    "sg:city":"Laredo",
    "sg:classifiers":[
        {
            "category":"Professional",
            "type":"Services"
        }
    ],
    "sg:phone":"+1 956 725 7062",
    "sg:postcode":"78040",
    "sg:province":"TX",
    "wof:name":"Merc International",
    "wof:placetype":"venue"
},
  "geometry": {"coordinates":[-99.514228,27.504255],"type":"Point"}
}