{
  "type": "Feature",
  "properties": {
    "iso:country":"US",
    "sg:address":"3621 Wooster Ln",
    "sg:city":"El Paso",
    "sg:phone":"+1 915 594 3340",
    "sg:postcode":"79936",
    "sg:province":"TX",
    "sg:tags":[
        "oil",
        "gasoline"
    ],
    "wof:name":"Savage Oil Co",
    "wof:placetype":"venue"
},
  "geometry": {"coordinates":[-106.309999,31.800186],"type":"Point"}
}