{
  "type": "Feature",
  "properties": {
    "iso:country":"US",
    "sg:address":"4227 Hallpark Dr",
    "sg:city":"San Antonio",
    "sg:classifiers":[
        {
            "category":"Shopping",
            "subcategory":"Catalog Store",
            "type":"Retail Goods"
        }
    ],
    "sg:phone":"+1 210 657 9256",
    "sg:postcode":"78218",
    "sg:province":"TX",
    "sg:tags":[
        "mail",
        "house"
    ],
    "wof:name":"Orlando F Frietze",
    "wof:placetype":"venue"
},
  "geometry": {"coordinates":[-98.408162,29.487754],"type":"Point"}
}