{
  "type": "Feature",
  "properties": {
    "iso:country":"US",
    "sg:address":"230 Shamrock Dr",
    "sg:city":"Floresville",
    "sg:classifiers":[
        {
            "category":"Building & Trades",
            "subcategory":"Construction",
            "type":"Services"
        }
    ],
    "sg:phone":"+1 830 216 2785",
    "sg:postcode":"78114",
    "sg:province":"TX",
    "sg:tags":[
        "residential",
        "commercial",
        "renovation",
        "repair"
    ],
    "wof:name":"Ken Benefield HM Maint & Repr",
    "wof:placetype":"venue"
},
  "geometry": {"coordinates":[-98.202034,29.198337],"type":"Point"}
}