{
  "type": "Feature",
  "properties": {
    "iso:country":"US",
    "sg:address":"5936 Bryan Pkwy",
    "sg:city":"Dallas",
    "sg:classifiers":[
        {
            "category":"Communications",
            "subcategory":"Film & Video Production",
            "type":"Services"
        },
        {
            "category":"Communications",
            "subcategory":"Television Station",
            "type":"Services"
        }
    ],
    "sg:phone":"+1 469 955 8995",
    "sg:postcode":"75206",
    "sg:province":"TX",
    "sg:tags":[
        "companies-film",
        "producer",
        "tv",
        "program",
        "radio",
        "distributor"
    ],
    "wof:name":"Psb Productions",
    "wof:placetype":"venue"
},
  "geometry": {"coordinates":[-96.76589800000001,32.807944],"type":"Point"}
}