{
  "type": "Feature",
  "properties": {
    "iso:country":"US",
    "sg:address":"99 N Post Oak Ln Apt 7205",
    "sg:city":"Houston",
    "sg:classifiers":[
        {
            "category":"Government",
            "subcategory":"Fire Station",
            "type":"Public Place"
        }
    ],
    "sg:phone":"+1 713 290 1665",
    "sg:postcode":"77024",
    "sg:province":"TX",
    "sg:tags":[
        "department"
    ],
    "sg:website":"http://www.gmtglobal.com",
    "wof:name":"Top Fire Technologies",
    "wof:placetype":"venue"
},
  "geometry": {"coordinates":[-95.457481,29.765929],"type":"Point"}
}