{
  "type": "Feature",
  "properties": {
    "iso:country":"US",
    "sg:address":"5760 Legacy Dr",
    "sg:city":"Plano",
    "sg:classifiers":[
        {
            "category":"Coffee & Tea",
            "type":"Food & Drink"
        }
    ],
    "sg:menulink":"http://www.allmenus.com/tx/plano/113085-starbucks-coffee/menu/",
    "sg:phone":"+1 972 378 3630",
    "sg:postcode":"75024",
    "sg:province":"TX",
    "sg:tags":[
        "american"
    ],
    "wof:name":"Starbucks Coffee",
    "wof:placetype":"venue"
},
  "geometry": {"coordinates":[-96.82032100000001,33.077883],"type":"Point"}
}