{
  "type": "Feature",
  "properties": {
    "iso:country":"US",
    "sg:address":"10880 Westheimer Rd",
    "sg:city":"Houston",
    "sg:classifiers":[
        {
            "category":"Retail",
            "subcategory":"Laundry & Dry Cleaning",
            "type":"Services"
        }
    ],
    "sg:phone":"+1 713 266 6466",
    "sg:postcode":"77042",
    "sg:province":"TX",
    "sg:tags":[
        "sewing",
        "alteration"
    ],
    "wof:name":"Westside Alterations",
    "wof:placetype":"venue"
},
  "geometry": {"coordinates":[-95.56819900000001,29.737],"type":"Point"}
}