{
  "type": "Feature",
  "properties": {
    "iso:country":"US",
    "sg:address":"413 Gilmer Rd",
    "sg:city":"Longview",
    "sg:classifiers":[
        {
            "category":"Insurance",
            "subcategory":"Hazard Insurance",
            "type":"Services"
        },
        {
            "category":"Insurance",
            "subcategory":"Insurance Agent",
            "type":"Services"
        },
        {
            "category":"Insurance",
            "subcategory":"Life Insurance",
            "type":"Services"
        },
        {
            "category":"Insurance",
            "subcategory":"Title Insurance",
            "type":"Services"
        }
    ],
    "sg:phone":"+1 903 758 4660",
    "sg:postcode":"75604",
    "sg:province":"TX",
    "sg:tags":[
        "auto",
        "commercial",
        "business",
        "homeowner"
    ],
    "sg:website":"http://www.farmersagent.com/mteague1/",
    "wof:name":"Michael Teague - Farmers Insurance",
    "wof:placetype":"venue"
},
  "geometry": {"coordinates":[-94.768738,32.508878],"type":"Point"}
}