{
  "type": "Feature",
  "properties": {
    "iso:country":"US",
    "sg:address":"3012 Padre Blvd",
    "sg:city":"S Padre Island",
    "sg:classifiers":[
        {
            "category":"Food & Beverages",
            "subcategory":"Groceries & Convenience Stores",
            "type":"Retail Goods"
        }
    ],
    "sg:phone":"+1 956 761 6373",
    "sg:postcode":"78597",
    "sg:province":"TX",
    "wof:name":"Speedy Pack",
    "wof:placetype":"venue"
},
  "geometry": {"coordinates":[-97.168499,26.105936],"type":"Point"}
}