{
  "type": "Feature",
  "properties": {
    "iso:country":"US",
    "sg:address":"8440 Dyer St",
    "sg:city":"El Paso",
    "sg:classifiers":[
        {
            "category":"Autos & Motor Vehicles",
            "subcategory":"Fuel & Gas Station",
            "type":"Retail Goods"
        }
    ],
    "sg:phone":"+1 915 751 4174",
    "sg:postcode":"79904",
    "sg:province":"TX",
    "sg:tags":[
        "self",
        "station"
    ],
    "wof:name":"Vickers",
    "wof:placetype":"venue"
},
  "geometry": {"coordinates":[-106.436098,31.857514],"type":"Point"}
}