{
  "type": "Feature",
  "properties": {
    "iso:country":"US",
    "sg:address":"825 Little York Rd",
    "sg:city":"Houston",
    "sg:classifiers":[
        {
            "category":"Organizations",
            "subcategory":"Religious Organization",
            "type":"Services"
        }
    ],
    "sg:phone":"+1 281 931 4663",
    "sg:postcode":"77076",
    "sg:province":"TX",
    "wof:name":"The Father's House International Fellowship",
    "wof:placetype":"venue"
},
  "geometry": {"coordinates":[-95.36900300000001,29.870399],"type":"Point"}
}