{
  "type": "Feature",
  "properties": {
    "iso:country":"US",
    "sg:address":"3709 N Main St",
    "sg:city":"Fort Worth",
    "sg:classifiers":[
        {
            "category":"Personal",
            "type":"Services"
        }
    ],
    "sg:phone":"+1 817 626 8900",
    "sg:postcode":"76106",
    "sg:province":"TX",
    "wof:name":"Tapatio Ballroom",
    "wof:placetype":"venue"
},
  "geometry": {"coordinates":[-97.35152100000001,32.811083],"type":"Point"}
}