{
  "type": "Feature",
  "properties": {
    "iso:country":"US",
    "sg:address":"1125 Broadway Ave",
    "sg:city":"Pasadena",
    "sg:classifiers":[
        {
            "category":"Wholesale",
            "subcategory":"Durable Goods & Equipment",
            "type":"Manufacturing & Wholesale Goods"
        }
    ],
    "sg:phone":"+1 713 920 1920",
    "sg:postcode":"77506",
    "sg:province":"TX",
    "sg:tags":[
        "representative",
        "manufacturer"
    ],
    "wof:name":"Bauer Industrial Supply",
    "wof:placetype":"venue"
},
  "geometry": {"coordinates":[-95.20081999999999,29.70872],"type":"Point"}
}