{
  "type": "Feature",
  "properties": {
    "iso:country":"US",
    "sg:address":"520 Birch St",
    "sg:city":"Maud",
    "sg:classifiers":[
        {
            "category":"Professional",
            "type":"Services"
        }
    ],
    "sg:phone":"+1 903 585 3326",
    "sg:postcode":"75567",
    "sg:province":"TX",
    "sg:tags":[
        "establishment"
    ],
    "wof:name":"Pursuit International",
    "wof:placetype":"venue"
},
  "geometry": {"coordinates":[-94.348984,33.323695],"type":"Point"}
}