{
  "type": "Feature",
  "properties": {
    "iso:country":"US",
    "sg:address":"110 Jefferson St",
    "sg:city":"Wichita Falls",
    "sg:classifiers":[
        {
            "category":"Travel",
            "subcategory":"Campground",
            "type":"Entertainment"
        }
    ],
    "sg:phone":"+1 940 322 7399",
    "sg:postcode":"76306",
    "sg:province":"TX",
    "sg:tags":[
        "camp"
    ],
    "wof:name":"Juvenile Boot Camp",
    "wof:placetype":"venue"
},
  "geometry": {"coordinates":[-98.495678,33.928751],"type":"Point"}
}