{
  "type": "Feature",
  "properties": {
    "iso:country":"US",
    "sg:address":"129 Cedar Ave",
    "sg:city":"Levelland",
    "sg:classifiers":[
        {
            "category":"Food & Beverages",
            "subcategory":"Bakery",
            "type":"Retail Goods"
        }
    ],
    "sg:phone":"+1 806 894 4749",
    "sg:postcode":"79336",
    "sg:province":"TX",
    "wof:name":"Little Bake Shop",
    "wof:placetype":"venue"
},
  "geometry": {"coordinates":[-102.357856,33.58405],"type":"Point"}
}