{
  "type": "Feature",
  "properties": {
    "iso:country":"US",
    "sg:address":"102 E Main St",
    "sg:city":"Balmorhea",
    "sg:classifiers":[
        {
            "category":"Travel",
            "subcategory":"Hotels & Motels",
            "type":"Entertainment"
        }
    ],
    "sg:phone":"+1 432 375 2477",
    "sg:postcode":"79780",
    "sg:province":"TX",
    "wof:name":"Country Inn",
    "wof:placetype":"venue"
},
  "geometry": {"coordinates":[-103.652599,31.022311],"type":"Point"}
}