{
  "type": "Feature",
  "properties": {
    "iso:country":"US",
    "sg:address":"5848 Colhurst St",
    "sg:city":"Dallas",
    "sg:classifiers":[
        {
            "category":"Banks & Credit Unions",
            "subcategory":"Financial Services",
            "type":"Services"
        }
    ],
    "sg:phone":"+1 214 368 0422",
    "sg:postcode":"75230",
    "sg:province":"TX",
    "sg:tags":[
        "investment"
    ],
    "wof:name":"Jkd Interest 11",
    "wof:placetype":"venue"
},
  "geometry": {"coordinates":[-96.80770800000001,32.881078],"type":"Point"}
}