{
  "type": "Feature",
  "properties": {
    "iso:country":"US",
    "sg:address":"4421 Conley Ave",
    "sg:city":"Odessa",
    "sg:classifiers":[
        {
            "category":"Building & Trades",
            "subcategory":"Electrical",
            "type":"Services"
        }
    ],
    "sg:phone":"+1 432 362 4888",
    "sg:postcode":"79762",
    "sg:province":"TX",
    "sg:tags":[
        "electrical",
        "contractor"
    ],
    "wof:name":"Atlas Electric",
    "wof:placetype":"venue"
},
  "geometry": {"coordinates":[-102.35705900000001,31.895118],"type":"Point"}
}