{
  "type": "Feature",
  "properties": {
    "iso:country":"US",
    "sg:address":"1734 N Greenville Ave",
    "sg:city":"Richardson",
    "sg:classifiers":[
        {
            "category":"Professional",
            "type":"Services"
        }
    ],
    "sg:phone":"+1 972 231 7124",
    "sg:postcode":"75081",
    "sg:province":"TX",
    "sg:tags":[
        "establishment"
    ],
    "wof:name":"Netracon",
    "wof:placetype":"venue"
},
  "geometry": {"coordinates":[-96.716283,32.971432],"type":"Point"}
}