{
  "type": "Feature",
  "properties": {
    "iso:country":"US",
    "sg:address":"7923 Irons St",
    "sg:city":"Dallas",
    "sg:classifiers":[
        {
            "category":"Manufacturing",
            "subcategory":"Electronics",
            "type":"Manufacturing & Wholesale Goods"
        }
    ],
    "sg:phone":"+1 214 391 4302",
    "sg:postcode":"75217",
    "sg:province":"TX",
    "sg:tags":[
        "equipment",
        "entertainment",
        "electronic",
        "home"
    ],
    "wof:name":"Personal Touch Audio & Video",
    "wof:placetype":"venue"
},
  "geometry": {"coordinates":[-96.68339899999999,32.700119],"type":"Point"}
}