{
  "type": "Feature",
  "properties": {
    "iso:country":"US",
    "sg:address":"714 N 7th St",
    "sg:city":"Raymondville",
    "sg:classifiers":[
        {
            "category":"Wholesale",
            "subcategory":"Auto Parts",
            "type":"Manufacturing & Wholesale Goods"
        }
    ],
    "sg:phone":"+1 956 689 3327",
    "sg:postcode":"78580",
    "sg:province":"TX",
    "sg:tags":[
        "supply"
    ],
    "wof:name":"Navarro Auto Supply",
    "wof:placetype":"venue"
},
  "geometry": {"coordinates":[-97.781762,26.488541],"type":"Point"}
}