{
  "type": "Feature",
  "properties": {
    "iso:country":"US",
    "sg:address":"2309 Hunter Place Ln",
    "sg:city":"Arlington",
    "sg:classifiers":[
        {
            "category":"Home & Garden",
            "subcategory":"Building Materials",
            "type":"Retail Goods"
        }
    ],
    "sg:phone":"+1 817 461 5606",
    "sg:postcode":"76006",
    "sg:province":"TX",
    "wof:name":"Birds In Glass Houses",
    "wof:placetype":"venue"
},
  "geometry": {"coordinates":[-97.07577499999999,32.774085],"type":"Point"}
}