{
  "type": "Feature",
  "properties": {
    "iso:country":"US",
    "sg:address":"5806 Mills St",
    "sg:city":"Hitchcock",
    "sg:classifiers":[
        {
            "category":"Building & Trades",
            "subcategory":"Cleaning & Sanitation",
            "type":"Services"
        }
    ],
    "sg:phone":"+1 409 986 1134",
    "sg:postcode":"77563",
    "sg:province":"TX",
    "sg:tags":[
        "janitor"
    ],
    "wof:name":"Shine On Cleaning Svc",
    "wof:placetype":"venue"
},
  "geometry": {"coordinates":[-94.985923,29.340527],"type":"Point"}
}