{
  "type": "Feature",
  "properties": {
    "iso:country":"US",
    "sg:address":"2401 Wild Rose Ct",
    "sg:city":"Arlington",
    "sg:classifiers":[
        {
            "category":"Shopping",
            "subcategory":"Clothing, Apparel, & Fashions",
            "type":"Retail Goods"
        }
    ],
    "sg:phone":"+1 817 640 5304",
    "sg:postcode":"76006",
    "sg:province":"TX",
    "wof:name":"Hollander H Fashons Corp",
    "wof:placetype":"venue"
},
  "geometry": {"coordinates":[-97.06822699999999,32.776623],"type":"Point"}
}