{
  "type": "Feature",
  "properties": {
    "iso:country":"US",
    "sg:address":"5800 Spring Hill Dr",
    "sg:city":"Mc Kinney",
    "sg:classifiers":[
        {
            "category":"Professional",
            "subcategory":"Business Services",
            "type":"Services"
        }
    ],
    "sg:phone":"+1 972 540 9659",
    "sg:postcode":"75070",
    "sg:province":"TX",
    "wof:name":"Gsa Enterprises Inc",
    "wof:placetype":"venue"
},
  "geometry": {"coordinates":[-96.693066,33.181483],"type":"Point"}
}