{
  "type": "Feature",
  "properties": {
    "iso:country":"US",
    "sg:address":"8508 Bellingham Dr",
    "sg:city":"Dallas",
    "sg:classifiers":[
        {
            "category":"Professional",
            "subcategory":"Management & Consulting",
            "type":"Services"
        }
    ],
    "sg:phone":"+1 972 524 8330",
    "sg:postcode":"75228",
    "sg:province":"TX",
    "sg:tags":[
        "party",
        "planning"
    ],
    "wof:name":"Triple A Bounce",
    "wof:placetype":"venue"
},
  "geometry": {"coordinates":[-96.691745,32.800917],"type":"Point"}
}