{
  "type": "Feature",
  "properties": {
    "iso:country":"US",
    "sg:address":"306 W Houston St",
    "sg:city":"Marshall",
    "sg:classifiers":[
        {
            "category":"Professional",
            "subcategory":"Business Services",
            "type":"Services"
        }
    ],
    "sg:phone":"+1 903 927 2300",
    "sg:postcode":"75670",
    "sg:province":"TX",
    "wof:name":"Discount Bail Bonds",
    "wof:placetype":"venue"
},
  "geometry": {"coordinates":[-94.37023499999999,32.54495],"type":"Point"}
}