{
  "type": "Feature",
  "properties": {
    "iso:country":"US",
    "sg:address":"100 S Dixon St",
    "sg:city":"Gainesville",
    "sg:classifiers":[
        {
            "category":"Government",
            "subcategory":"Court House",
            "type":"Public Place"
        }
    ],
    "sg:phone":"+1 940 668 5435",
    "sg:postcode":"76240",
    "sg:province":"TX",
    "sg:tags":[
        "county"
    ],
    "sg:website":"www.co.cooke.tx.us",
    "wof:name":"Cooke County Judge Ofc",
    "wof:placetype":"venue"
},
  "geometry": {"coordinates":[-97.145298,33.624286],"type":"Point"}
}