{
  "type": "Feature",
  "properties": {
    "iso:country":"US",
    "sg:address":"15834 Pipers View Dr",
    "sg:city":"Webster",
    "sg:classifiers":[
        {
            "category":"Freight",
            "type":"Transportation"
        }
    ],
    "sg:phone":"+1 281 648 7500",
    "sg:postcode":"77598",
    "sg:province":"TX",
    "sg:tags":[
        "operator",
        "local",
        "trucking"
    ],
    "wof:name":"A-1 Movers",
    "wof:placetype":"venue"
},
  "geometry": {"coordinates":[-95.14555,29.553756],"type":"Point"}
}