{
  "type": "Feature",
  "properties": {
    "iso:country":"US",
    "sg:address":"6136 Frisco Square Blvd",
    "sg:city":"Frisco",
    "sg:classifiers":[
        {
            "category":"Real Estate",
            "subcategory":"Real Estate Services",
            "type":"Services"
        },
        {
            "category":"Real Estate",
            "subcategory":"Real Estate Agent",
            "type":"Services"
        }
    ],
    "sg:phone":"+1 469 952 6622",
    "sg:postcode":"75034",
    "sg:province":"TX",
    "sg:tags":[
        "buyer",
        "broker"
    ],
    "wof:name":"Harvest Petroleum, Inc.",
    "wof:placetype":"venue"
},
  "geometry": {"coordinates":[-96.834563,33.151033],"type":"Point"}
}