{
  "type": "Feature",
  "properties": {
    "iso:country":"US",
    "sg:address":"3121 Magnolia St",
    "sg:city":"Amarillo",
    "sg:classifiers":[
        {
            "category":"Building & Trades",
            "subcategory":"Construction",
            "type":"Services"
        }
    ],
    "sg:phone":"+1 806 383 5346",
    "sg:postcode":"79107",
    "sg:province":"TX",
    "sg:tags":[
        "contractor"
    ],
    "wof:name":"Jewell Glass Repair",
    "wof:placetype":"venue"
},
  "geometry": {"coordinates":[-101.827607,35.247483],"type":"Point"}
}