{
  "type": "Feature",
  "properties": {
    "iso:country":"US",
    "sg:address":"13626 Morningbluff Dr",
    "sg:city":"San Antonio",
    "sg:classifiers":[
        {
            "category":"Retail",
            "subcategory":"Repair Shop",
            "type":"Services"
        }
    ],
    "sg:phone":"+1 210 545 1333",
    "sg:postcode":"78216",
    "sg:province":"TX",
    "wof:name":"Minute Hand",
    "wof:placetype":"venue"
},
  "geometry": {"coordinates":[-98.491917,29.565384],"type":"Point"}
}