{
  "type": "Feature",
  "properties": {
    "iso:country":"US",
    "sg:address":"9030 Royal Crest Ln",
    "sg:city":"Richmond",
    "sg:classifiers":[
        {
            "category":"Autos & Motor Vehicles",
            "subcategory":"Automobile Sales",
            "type":"Retail Goods"
        }
    ],
    "sg:phone":"+1 281 931 8300",
    "sg:postcode":"77469",
    "sg:province":"TX",
    "sg:tags":[
        "dealers-used",
        "car",
        "used",
        "cars-wholesale"
    ],
    "wof:name":"Sam's Auto Connection",
    "wof:placetype":"venue"
},
  "geometry": {"coordinates":[-95.66806200000001,29.523538],"type":"Point"}
}