{
  "type": "Feature",
  "properties": {
    "iso:country":"US",
    "sg:address":"15912 RM 620",
    "sg:city":"Austin",
    "sg:classifiers":[
        {
            "category":"Retail",
            "subcategory":"Laundry & Dry Cleaning",
            "type":"Services"
        }
    ],
    "sg:phone":"+1 512 300 3417",
    "sg:postcode":"78717",
    "sg:province":"TX",
    "wof:name":"Morgan Family Dry Cleaners",
    "wof:placetype":"venue"
},
  "geometry": {"coordinates":[-97.77647899999999,30.473664],"type":"Point"}
}