{
  "type": "Feature",
  "properties": {
    "iso:country":"US",
    "sg:address":"231 W Cypress St",
    "sg:city":"San Antonio",
    "sg:classifiers":[
        {
            "category":"Shopping",
            "subcategory":"Computers & Home Electronics",
            "type":"Retail Goods"
        }
    ],
    "sg:phone":"+1 210 271 3305",
    "sg:postcode":"78212",
    "sg:province":"TX",
    "sg:tags":[
        "television",
        "radio"
    ],
    "wof:name":"F E TV",
    "wof:placetype":"venue"
},
  "geometry": {"coordinates":[-98.496388,29.440715],"type":"Point"}
}