{
  "type": "Feature",
  "properties": {
    "iso:country":"US",
    "sg:address":"821 Vinecrest Ln",
    "sg:city":"Richardson",
    "sg:classifiers":[
        {
            "category":"Organizations",
            "subcategory":"Religious Organization",
            "type":"Services"
        }
    ],
    "sg:phone":"+1 214 642 4674",
    "sg:postcode":"75080",
    "sg:province":"TX",
    "wof:name":"Native Missionary Movement Inc",
    "wof:placetype":"venue"
},
  "geometry": {"coordinates":[-96.748312,32.976685],"type":"Point"}
}