{
  "type": "Feature",
  "properties": {
    "iso:country":"US",
    "sg:address":"8708 S Gessner Dr",
    "sg:city":"Houston",
    "sg:classifiers":[
        {
            "category":"Utilities",
            "subcategory":"Mobile Phone",
            "type":"Services"
        }
    ],
    "sg:phone":"+1 713 776 8621",
    "sg:postcode":"77074",
    "sg:province":"TX",
    "sg:tags":[
        "communication",
        "radiotelephone"
    ],
    "wof:name":"Wireless Screw",
    "wof:placetype":"venue"
},
  "geometry": {"coordinates":[-95.528571,29.68505],"type":"Point"}
}