{
  "type": "Feature",
  "properties": {
    "iso:country":"US",
    "sg:address":"1801 S Bell Blvd",
    "sg:city":"Cedar Park",
    "sg:classifiers":[
        {
            "category":"Professional",
            "subcategory":"Business Services",
            "type":"Services"
        }
    ],
    "sg:phone":"+1 512 258 0427",
    "sg:postcode":"78613",
    "sg:province":"TX",
    "wof:name":"Clay Bowman Enterprises Inc",
    "wof:placetype":"venue"
},
  "geometry": {"coordinates":[-97.80874300000001,30.489594],"type":"Point"}
}