{
  "type": "Feature",
  "properties": {
    "iso:country":"US",
    "sg:address":"10716 FM 902",
    "sg:city":"Collinsville",
    "sg:classifiers":[
        {
            "category":"Building & Trades",
            "subcategory":"Construction",
            "type":"Services"
        }
    ],
    "sg:phone":"+1 972 316 1187",
    "sg:postcode":"76233",
    "sg:province":"TX",
    "sg:tags":[
        "control",
        "erosion"
    ],
    "wof:name":"A Reg Mgmt System-Erosion Cntl",
    "wof:placetype":"venue"
},
  "geometry": {"coordinates":[-96.952609,33.553371],"type":"Point"}
}