{
  "type": "Feature",
  "properties": {
    "iso:country":"US",
    "sg:address":"1500 N Central Expy",
    "sg:city":"Mc Kinney",
    "sg:classifiers":[
        {
            "category":"Professional",
            "type":"Services"
        }
    ],
    "sg:phone":"+1 972 542 0963",
    "sg:postcode":"75070",
    "sg:province":"TX",
    "sg:tags":[
        "establishment"
    ],
    "wof:name":"I P Bandwidth",
    "wof:placetype":"venue"
},
  "geometry": {"coordinates":[-96.63690800000001,33.212545],"type":"Point"}
}