{
  "type": "Feature",
  "properties": {
    "iso:country":"US",
    "sg:address":"9700 Bissonnet St",
    "sg:city":"Houston",
    "sg:classifiers":[
        {
            "category":"Deli",
            "type":"Food & Drink"
        }
    ],
    "sg:phone":"+1 713 484 5667",
    "sg:postcode":"77036",
    "sg:province":"TX",
    "wof:name":"Pasta Pomodoro Italian Deli",
    "wof:placetype":"venue"
},
  "geometry": {"coordinates":[-95.54789700000001,29.6756],"type":"Point"}
}