{
  "type": "Feature",
  "properties": {
    "iso:country":"US",
    "sg:address":"5610 Ct of York",
    "sg:city":"Houston",
    "sg:classifiers":[
        {
            "category":"Shopping",
            "type":"Retail Goods"
        }
    ],
    "sg:phone":"+1 281 583 8784",
    "sg:postcode":"77069",
    "sg:province":"TX",
    "sg:tags":[
        "merchandise"
    ],
    "wof:name":"Puzzles Ect",
    "wof:placetype":"venue"
},
  "geometry": {"coordinates":[-95.52266400000001,29.99283],"type":"Point"}
}