{
  "type": "Feature",
  "properties": {
    "iso:country":"US",
    "sg:address":"11819 Edward St",
    "sg:city":"Elgin",
    "sg:classifiers":[
        {
            "category":"Organizations",
            "subcategory":"Religious Organization",
            "type":"Services"
        }
    ],
    "sg:phone":"+1 512 281 3356",
    "sg:postcode":"78621",
    "sg:province":"TX",
    "sg:tags":[
        "church"
    ],
    "wof:name":"Outreach Mission",
    "wof:placetype":"venue"
},
  "geometry": {"coordinates":[-97.447569,30.319853],"type":"Point"}
}