{
  "type": "Feature",
  "properties": {
    "iso:country":"US",
    "sg:address":"4616 W Howard Ln Ste 1-140",
    "sg:city":"Austin",
    "sg:classifiers":[
        {
            "category":"Shopping",
            "subcategory":"Department Store",
            "type":"Retail Goods"
        }
    ],
    "sg:phone":"+1 512 671 9090",
    "sg:postcode":"78728",
    "sg:province":"TX",
    "wof:name":"American Direct",
    "wof:placetype":"venue"
},
  "geometry": {"coordinates":[-97.69458400000001,30.438675],"type":"Point"}
}