{
  "type": "Feature",
  "properties": {
    "iso:country":"US",
    "sg:address":"604 W Main St",
    "sg:city":"League City",
    "sg:classifiers":[
        {
            "category":"Autos & Motor Vehicles",
            "subcategory":"Auto Supplies",
            "type":"Retail Goods"
        }
    ],
    "sg:phone":"+1 281 332 4571",
    "sg:postcode":"77573",
    "sg:province":"TX",
    "sg:tags":[
        "automobile",
        "parts"
    ],
    "wof:name":"O'Reilly Auto Parts",
    "wof:placetype":"venue"
},
  "geometry": {"coordinates":[-95.099458,29.506602],"type":"Point"}
}