{
  "type": "Feature",
  "properties": {
    "iso:country":"US",
    "sg:address":"9840 Twin Creek Dr",
    "sg:city":"Dallas",
    "sg:classifiers":[
        {
            "category":"Building & Trades",
            "subcategory":"Landscaping Services",
            "type":"Services"
        }
    ],
    "sg:phone":"+1 972 442 7779",
    "sg:postcode":"75228",
    "sg:province":"TX",
    "sg:tags":[
        "landscape",
        "contractor"
    ],
    "wof:name":"Texas Lawn Mowers",
    "wof:placetype":"venue"
},
  "geometry": {"coordinates":[-96.68836400000001,32.827089],"type":"Point"}
}