{
  "type": "Feature",
  "properties": {
    "iso:country":"US",
    "sg:address":"2257 Vantage St",
    "sg:city":"Dallas",
    "sg:classifiers":[
        {
            "category":"Wholesale",
            "subcategory":"Jewelry",
            "type":"Manufacturing & Wholesale Goods"
        }
    ],
    "sg:phone":"+1 214 638 0414",
    "sg:postcode":"75207",
    "sg:province":"TX",
    "sg:tags":[
        "stone",
        "metal",
        "precious",
        "mfg"
    ],
    "wof:name":"General Castings Inc",
    "wof:placetype":"venue"
},
  "geometry": {"coordinates":[-96.83486499999999,32.799275],"type":"Point"}
}