{
  "type": "Feature",
  "properties": {
    "iso:country":"US",
    "sg:address":"2731 Main Ave",
    "sg:city":"Groves",
    "sg:classifiers":[
        {
            "category":"Building & Trades",
            "subcategory":"Plumbing",
            "type":"Services"
        },
        {
            "category":"Home & Garden",
            "subcategory":"Building Materials",
            "type":"Retail Goods"
        },
        {
            "category":"Building & Trades",
            "subcategory":"Cleaning & Sanitation",
            "type":"Services"
        }
    ],
    "sg:phone":"+1 409 962 8214",
    "sg:postcode":"77619",
    "sg:province":"TX",
    "sg:tags":[
        "cleaner",
        "plumber",
        "industrial",
        "repair",
        "repairer",
        "water",
        "sewer",
        "contractors-commercial",
        "plumbing-drain",
        "heater"
    ],
    "wof:name":"Jeffco Plumbling Co",
    "wof:placetype":"venue"
},
  "geometry": {"coordinates":[-93.908078,29.936557],"type":"Point"}
}