{
  "type": "Feature",
  "properties": {
    "iso:country":"US",
    "sg:address":"901 University Dr",
    "sg:city":"Fort Worth",
    "sg:classifiers":[
        {
            "category":"Health Services",
            "subcategory":"Doctor",
            "type":"Services"
        }
    ],
    "sg:phone":"+1 817 877 5950",
    "sg:postcode":"76107",
    "sg:province":"TX",
    "sg:tags":[
        "physician",
        "medical",
        "surgeon"
    ],
    "wof:name":"Fort Worth Anesthesia Care",
    "wof:placetype":"venue"
},
  "geometry": {"coordinates":[-97.36188799999999,32.74926],"type":"Point"}
}