{
  "type": "Feature",
  "properties": {
    "iso:country":"US",
    "sg:address":"14560 Main St",
    "sg:city":"Lytle",
    "sg:classifiers":[
        {
            "category":"Retail",
            "subcategory":"Repair Shop",
            "type":"Services"
        }
    ],
    "sg:phone":"+1 830 772 4229",
    "sg:postcode":"78052",
    "sg:province":"TX",
    "sg:tags":[
        "welding"
    ],
    "wof:name":"Kirk's Welding",
    "wof:placetype":"venue"
},
  "geometry": {"coordinates":[-98.789698,29.235815],"type":"Point"}
}