{
  "type": "Feature",
  "properties": {
    "iso:country":"US",
    "sg:address":"148 Clear Water W",
    "sg:city":"Montgomery",
    "sg:classifiers":[
        {
            "category":"Professional",
            "type":"Services"
        }
    ],
    "sg:phone":"+1 936 597 7822",
    "sg:postcode":"77356",
    "sg:province":"TX",
    "wof:name":"Total Basket Kase",
    "wof:placetype":"venue"
},
  "geometry": {"coordinates":[-95.61515900000001,30.439441],"type":"Point"}
}