{
  "type": "Feature",
  "properties": {
    "iso:country":"US",
    "sg:address":"12037 Old Hwy 62",
    "sg:city":"Orange",
    "sg:classifiers":[
        {
            "category":"Organizations",
            "subcategory":"Political Organization",
            "type":"Services"
        }
    ],
    "sg:phone":"+1 409 745 9600",
    "sg:postcode":"77632",
    "sg:province":"TX",
    "wof:name":"Mike Hamilton Campaign Hq",
    "wof:placetype":"venue"
},
  "geometry": {"coordinates":[-93.862467,30.193451],"type":"Point"}
}