{
  "type": "Feature",
  "properties": {
    "iso:country":"US",
    "sg:address":"1700 N Zaragoza Rd",
    "sg:city":"El Paso",
    "sg:classifiers":[
        {
            "category":"Restaurant",
            "type":"Food & Drink"
        }
    ],
    "sg:phone":"+1 915 856 9558",
    "sg:postcode":"79936",
    "sg:province":"TX",
    "wof:name":"Siagon Restaurant",
    "wof:placetype":"venue"
},
  "geometry": {"coordinates":[-106.275626,31.754641],"type":"Point"}
}