{
  "type": "Feature",
  "properties": {
    "iso:country":"US",
    "sg:address":"11718 W Adams Ave",
    "sg:city":"Temple",
    "sg:classifiers":[
        {
            "category":"Retail",
            "subcategory":"Repair Shop",
            "type":"Services"
        }
    ],
    "sg:phone":"+1 254 780 4800",
    "sg:postcode":"76513",
    "sg:province":"TX",
    "sg:tags":[
        "welding"
    ],
    "wof:name":"GMC Welding",
    "wof:placetype":"venue"
},
  "geometry": {"coordinates":[-97.465103,31.129362],"type":"Point"}
}