{
  "type": "Feature",
  "properties": {
    "iso:country":"US",
    "sg:address":"16 Hall Dr N",
    "sg:city":"Montgomery",
    "sg:classifiers":[
        {
            "category":"Wholesale",
            "subcategory":"Non-durable Goods",
            "type":"Manufacturing & Wholesale Goods"
        }
    ],
    "sg:phone":"+1 936 597 5361",
    "sg:postcode":"77316",
    "sg:province":"TX",
    "wof:name":"TLC Imports",
    "wof:placetype":"venue"
},
  "geometry": {"coordinates":[-95.736361,30.265774],"type":"Point"}
}