{
  "type": "Feature",
  "properties": {
    "iso:country":"US",
    "sg:address":"1016 Quail Run Rd",
    "sg:city":"Southlake",
    "sg:classifiers":[
        {
            "category":"Banks & Credit Unions",
            "subcategory":"Investment Brokerage",
            "type":"Services"
        }
    ],
    "sg:phone":"+1 817 329 3198",
    "sg:postcode":"76092",
    "sg:province":"TX",
    "sg:tags":[
        "security",
        "royalty",
        "oil"
    ],
    "wof:name":"Elaine P Cox Family",
    "wof:placetype":"venue"
},
  "geometry": {"coordinates":[-97.13920899999999,32.976573],"type":"Point"}
}