{
  "type": "Feature",
  "properties": {
    "iso:country":"US",
    "sg:address":"2632 Pin Oak Ln",
    "sg:city":"Plano",
    "sg:classifiers":[
        {
            "category":"Education",
            "subcategory":"Vocational School",
            "type":"Public Place"
        }
    ],
    "sg:phone":"+1 972 867 1172",
    "sg:postcode":"75075",
    "sg:province":"TX",
    "sg:tags":[
        "training",
        "computer"
    ],
    "sg:website":"www.westfallteam.com",
    "wof:name":"Westfall Team",
    "wof:placetype":"venue"
},
  "geometry": {"coordinates":[-96.743242,33.028748],"type":"Point"}
}