{
  "type": "Feature",
  "properties": {
    "iso:country":"US",
    "sg:address":"105 S Columbia Dr",
    "sg:city":"West Columbia",
    "sg:classifiers":[
        {
            "category":"Building & Trades",
            "subcategory":"Cleaning & Sanitation",
            "type":"Services"
        }
    ],
    "sg:phone":"+1 979 345 7358",
    "sg:postcode":"77486",
    "sg:province":"TX",
    "sg:tags":[
        "maintenance"
    ],
    "wof:name":"Makin Way Inc",
    "wof:placetype":"venue"
},
  "geometry": {"coordinates":[-95.65682,29.144599],"type":"Point"}
}