{
  "type": "Feature",
  "properties": {
    "iso:country":"US",
    "sg:address":"100 Brazosport Blvd N",
    "sg:city":"Clute",
    "sg:classifiers":[
        {
            "category":"Food & Beverages",
            "subcategory":"Groceries & Convenience Stores",
            "type":"Retail Goods"
        }
    ],
    "sg:phone":"+1 979 265 3012",
    "sg:postcode":"77531",
    "sg:province":"TX",
    "wof:name":"Quick Mart",
    "wof:placetype":"venue"
},
  "geometry": {"coordinates":[-95.39595799999999,29.02511],"type":"Point"}
}