{
  "type": "Feature",
  "properties": {
    "iso:country":"US",
    "sg:address":"8600 Ranch Rd 620 N",
    "sg:city":"Austin",
    "sg:classifiers":[
        {
            "category":"Personal",
            "subcategory":"Beauty Salon",
            "type":"Services"
        }
    ],
    "sg:phone":"+1 512 791 8635",
    "sg:postcode":"78726",
    "sg:province":"TX",
    "sg:tags":[
        "shop"
    ],
    "wof:name":"Great Clips",
    "wof:placetype":"venue"
},
  "geometry": {"coordinates":[-97.845359,30.420719],"type":"Point"}
}