{
  "type": "Feature",
  "properties": {
    "iso:country":"US",
    "sg:address":"837 W Pipeline Rd",
    "sg:city":"Hurst",
    "sg:classifiers":[
        {
            "category":"Shopping",
            "subcategory":"Musical Instruments",
            "type":"Retail Goods"
        }
    ],
    "sg:phone":"+1 817 589 0100",
    "sg:postcode":"76053",
    "sg:province":"TX",
    "sg:tags":[
        "operator",
        "local",
        "trucking"
    ],
    "wof:name":"Steinway Hall Fort Worth",
    "wof:placetype":"venue"
},
  "geometry": {"coordinates":[-97.188818,32.823578],"type":"Point"}
}