{
  "type": "Feature",
  "properties": {
    "iso:country":"US",
    "sg:address":"6813 Summit Ridge Dr",
    "sg:city":"Watauga",
    "sg:classifiers":[
        {
            "category":"Personal",
            "subcategory":"Beauty Salon",
            "type":"Services"
        }
    ],
    "sg:phone":"+1 817 726 7115",
    "sg:postcode":"76148",
    "sg:province":"TX",
    "wof:name":"Studio Styles By Denise",
    "wof:placetype":"venue"
},
  "geometry": {"coordinates":[-97.24274699999999,32.869675],"type":"Point"}
}