{
  "type": "Feature",
  "properties": {
    "iso:country":"US",
    "sg:address":"676 Co Rd 3336",
    "sg:city":"Bridgeport",
    "sg:classifiers":[
        {
            "category":"Building & Trades",
            "subcategory":"Construction",
            "type":"Services"
        }
    ],
    "sg:phone":"+1 940 683 5378",
    "sg:postcode":"76073",
    "sg:province":"TX",
    "sg:tags":[
        "excavating",
        "contractor"
    ],
    "wof:name":"Strand Excavating Inc",
    "wof:placetype":"venue"
},
  "geometry": {"coordinates":[-97.72560300000001,33.172541],"type":"Point"}
}