{
  "type": "Feature",
  "properties": {
    "iso:country":"US",
    "sg:address":"3015 Renaissance Dr",
    "sg:city":"Dallas",
    "sg:classifiers":[
        {
            "category":"Shopping",
            "subcategory":"Gifts & Souvenirs",
            "type":"Retail Goods"
        }
    ],
    "sg:phone":"+1 972 306 6442",
    "sg:postcode":"75287",
    "sg:province":"TX",
    "wof:name":"Groovy Girls Gear",
    "wof:placetype":"venue"
},
  "geometry": {"coordinates":[-96.86382500000001,32.994278],"type":"Point"}
}