{
  "type": "Feature",
  "properties": {
    "iso:country":"US",
    "sg:address":"1204 Bristol St",
    "sg:city":"Bryan",
    "sg:classifiers":[
        {
            "category":"Building & Trades",
            "subcategory":"Pest Control",
            "type":"Services"
        }
    ],
    "sg:phone":"+1 979 778 3017",
    "sg:postcode":"77802",
    "sg:province":"TX",
    "sg:tags":[
        "mothproofing"
    ],
    "wof:name":"Gustavus Pest Control",
    "wof:placetype":"venue"
},
  "geometry": {"coordinates":[-96.352631,30.65535],"type":"Point"}
}