{
  "type": "Feature",
  "properties": {
    "iso:country":"US",
    "sg:address":"8801 Davis Blvd",
    "sg:city":"Fort Worth",
    "sg:classifiers":[
        {
            "category":"Retail",
            "subcategory":"Auto Repair",
            "type":"Services"
        }
    ],
    "sg:phone":"+1 817 431 1299",
    "sg:postcode":"76180",
    "sg:province":"TX",
    "sg:tags":[
        "automotive",
        "general"
    ],
    "wof:name":"C & D Automotive",
    "wof:placetype":"venue"
},
  "geometry": {"coordinates":[-97.187287,32.913465],"type":"Point"}
}