{
  "type": "Feature",
  "properties": {
    "iso:country":"US",
    "sg:address":"2018 Antonio St",
    "sg:city":"Anthony",
    "sg:classifiers":[
        {
            "category":"Food & Beverages",
            "subcategory":"Groceries & Convenience Stores",
            "type":"Retail Goods"
        }
    ],
    "sg:phone":"+1 915 886 5534",
    "sg:postcode":"79821",
    "sg:province":"TX",
    "wof:name":"7-Eleven",
    "wof:placetype":"venue"
},
  "geometry": {"coordinates":[-106.58605300000001,31.997707],"type":"Point"}
}