{
  "type": "Feature",
  "properties": {
    "iso:country":"US",
    "sg:address":"10661 Haddington Dr",
    "sg:city":"Houston",
    "sg:classifiers":[
        {
            "category":"Shopping",
            "subcategory":"Catalog Store",
            "type":"Retail Goods"
        }
    ],
    "sg:phone":"+1 832 647 5286",
    "sg:postcode":"77043",
    "sg:province":"TX",
    "sg:tags":[
        "mail",
        "house"
    ],
    "wof:name":"Momentum Electronics LLC",
    "wof:placetype":"venue"
},
  "geometry": {"coordinates":[-95.56013900000001,29.799964],"type":"Point"}
}