{
  "type": "Feature",
  "properties": {
    "iso:country":"US",
    "sg:address":"11725 W Adams Ave",
    "sg:city":"Belton",
    "sg:classifiers":[
        {
            "category":"Banks & Credit Unions",
            "subcategory":"Investment Brokerage",
            "type":"Services"
        }
    ],
    "sg:phone":"+1 254 780 2444",
    "sg:postcode":"76513",
    "sg:province":"TX",
    "wof:name":"Edward Jones Investments",
    "wof:placetype":"venue"
},
  "geometry": {"coordinates":[-97.46505399999999,31.129202],"type":"Point"}
}