{
  "type": "Feature",
  "properties": {
    "iso:country":"US",
    "sg:address":"100 N Shiloh Rd",
    "sg:city":"Garland",
    "sg:classifiers":[
        {
            "category":"Building & Trades",
            "subcategory":"Construction",
            "type":"Services"
        }
    ],
    "sg:phone":"+1 972 494 2668",
    "sg:postcode":"75042",
    "sg:province":"TX",
    "sg:tags":[
        "roofing",
        "contractor"
    ],
    "wof:name":"Assurance Restoration Contr",
    "wof:placetype":"venue"
},
  "geometry": {"coordinates":[-96.665334,32.91359],"type":"Point"}
}