{
  "type": "Feature",
  "properties": {
    "iso:country":"US",
    "sg:address":"395 W Oak St",
    "sg:city":"Stephenville",
    "sg:classifiers":[
        {
            "category":"Building & Trades",
            "subcategory":"Construction",
            "type":"Services"
        }
    ],
    "sg:phone":"+1 254 968 3515",
    "sg:postcode":"76401",
    "sg:province":"TX",
    "sg:tags":[
        "concrete",
        "contractor"
    ],
    "wof:name":"Hernandez Masonry & Concrete",
    "wof:placetype":"venue"
},
  "geometry": {"coordinates":[-98.210801,32.229279],"type":"Point"}
}