{
  "type": "Feature",
  "properties": {
    "iso:country":"US",
    "sg:address":"9513 Ranch Rd 620 N",
    "sg:city":"Austin",
    "sg:classifiers":[
        {
            "category":"Wholesale",
            "subcategory":"Sporting Goods",
            "type":"Manufacturing & Wholesale Goods"
        },
        {
            "category":"Shopping",
            "subcategory":"Bicycles & Sporting Goods",
            "type":"Retail Goods"
        }
    ],
    "sg:phone":"+1 512 257 8728",
    "sg:postcode":"78726",
    "sg:province":"TX",
    "sg:tags":[
        "paint",
        "game",
        "ball"
    ],
    "sg:website":"www.txpb.com",
    "wof:name":"Texas Paintball",
    "wof:placetype":"venue"
},
  "geometry": {"coordinates":[-97.849947,30.411728],"type":"Point"}
}