{
  "type": "Feature",
  "properties": {
    "iso:country":"US",
    "sg:address":"8880 E Evans Rd",
    "sg:city":"Selma",
    "sg:classifiers":[
        {
            "category":"Building & Trades",
            "subcategory":"Cleaning & Sanitation",
            "type":"Services"
        },
        {
            "category":"Professional",
            "subcategory":"Employment Agencies",
            "type":"Services"
        }
    ],
    "sg:phone":"+1 210 651 9204",
    "sg:postcode":"78154",
    "sg:province":"TX",
    "sg:tags":[
        "butler",
        "maid",
        "help",
        "maintenance",
        "supply"
    ],
    "wof:name":"Ginger Azzaro Cleaning Service",
    "wof:placetype":"venue"
},
  "geometry": {"coordinates":[-98.313655,29.600914],"type":"Point"}
}