{
  "type": "Feature",
  "properties": {
    "iso:country":"US",
    "sg:address":"501 Sachtleben Rd",
    "sg:city":"Wimberley",
    "sg:classifiers":[
        {
            "category":"Shopping",
            "type":"Retail Goods"
        }
    ],
    "sg:phone":"+1 512 842 1245",
    "sg:postcode":"78676",
    "sg:province":"TX",
    "sg:tags":[
        "merchandise"
    ],
    "wof:name":"4m Co",
    "wof:placetype":"venue"
},
  "geometry": {"coordinates":[-98.172738,29.985043],"type":"Point"}
}