{
  "type": "Feature",
  "properties": {
    "iso:country":"US",
    "sg:address":"122 W Amherst Dr",
    "sg:city":"Tyler",
    "sg:classifiers":[
        {
            "category":"Retail",
            "subcategory":"Laundry & Dry Cleaning",
            "type":"Services"
        },
        {
            "category":"Building & Trades",
            "subcategory":"Cleaning & Sanitation",
            "type":"Services"
        }
    ],
    "sg:phone":"+1 903 561 7011",
    "sg:postcode":"75701",
    "sg:province":"TX",
    "sg:tags":[
        "cleaner",
        "house"
    ],
    "wof:name":"Regency Cleaners",
    "wof:placetype":"venue"
},
  "geometry": {"coordinates":[-95.301086,32.311821],"type":"Point"}
}