{
  "type": "Feature",
  "properties": {
    "iso:country":"US",
    "sg:address":"505 Dallas St",
    "sg:city":"New Braunfels",
    "sg:classifiers":[
        {
            "category":"Professional",
            "subcategory":"Business Services",
            "type":"Services"
        }
    ],
    "sg:phone":"+1 830 626 0612",
    "sg:postcode":"78130",
    "sg:province":"TX",
    "sg:tags":[
        "telemarketing"
    ],
    "wof:name":"FLS",
    "wof:placetype":"venue"
},
  "geometry": {"coordinates":[-98.12849799999999,29.715346],"type":"Point"}
}