{
  "type": "Feature",
  "properties": {
    "iso:country":"US",
    "sg:address":"13918 S Village Dr",
    "sg:city":"San Antonio",
    "sg:classifiers":[
        {
            "category":"Professional",
            "subcategory":"Art Services",
            "type":"Services"
        }
    ],
    "sg:phone":"+1 210 521 0844",
    "sg:postcode":"78249",
    "sg:province":"TX",
    "sg:tags":[
        "commercial",
        "design"
    ],
    "wof:name":"Alamo Web Grapeics & Design",
    "wof:placetype":"venue"
},
  "geometry": {"coordinates":[-98.638282,29.575591],"type":"Point"}
}