{
  "type": "Feature",
  "properties": {
    "iso:country":"US",
    "sg:address":"2900 Lafferty Rd",
    "sg:city":"Pasadena",
    "sg:classifiers":[
        {
            "category":"Arena",
            "subcategory":"Sports Club",
            "type":"Entertainment"
        }
    ],
    "sg:phone":"+1 713 941 7376",
    "sg:postcode":"77502",
    "sg:province":"TX",
    "wof:name":"Pasadena Peewee League",
    "wof:placetype":"venue"
},
  "geometry": {"coordinates":[-95.197999,29.666754],"type":"Point"}
}