{
  "type": "Feature",
  "properties": {
    "iso:country":"US",
    "sg:address":"11040 Reed Rd",
    "sg:city":"San Antonio",
    "sg:classifiers":[
        {
            "category":"Social Services",
            "subcategory":"Child Care",
            "type":"Services"
        }
    ],
    "sg:phone":"+1 210 523 2613",
    "sg:postcode":"78251",
    "sg:province":"TX",
    "wof:name":"Joyland Christian Learning Ctr",
    "wof:placetype":"venue"
},
  "geometry": {"coordinates":[-98.658417,29.459617],"type":"Point"}
}