{
  "type": "Feature",
  "properties": {
    "iso:country":"US",
    "sg:address":"2902 S Central Ave",
    "sg:city":"Troy",
    "sg:classifiers":[
        {
            "category":"Wholesale",
            "subcategory":"Machinery & Supplies",
            "type":"Manufacturing & Wholesale Goods"
        }
    ],
    "sg:phone":"+1 254 938 2791",
    "sg:postcode":"76579",
    "sg:province":"TX",
    "sg:tags":[
        "truck"
    ],
    "sg:website":"www.lifttrucksupplyinc.com",
    "wof:name":"Lift Truck Supply",
    "wof:placetype":"venue"
},
  "geometry": {"coordinates":[-97.313322,31.182673],"type":"Point"}
}