{
  "type": "Feature",
  "properties": {
    "iso:country":"US",
    "sg:address":"13781 N US Hwy 183",
    "sg:city":"Austin",
    "sg:classifiers":[
        {
            "category":"Retail",
            "subcategory":"Auto Repair",
            "type":"Services"
        }
    ],
    "sg:phone":"+1 512 258 5075",
    "sg:postcode":"78750",
    "sg:province":"TX",
    "sg:tags":[
        "automobile",
        "lubrication",
        "fluid",
        "maintenance",
        "automotive"
    ],
    "wof:name":"Jiffy Lube",
    "wof:placetype":"venue"
},
  "geometry": {"coordinates":[-97.795511,30.464531],"type":"Point"}
}