{
  "type": "Feature",
  "properties": {
    "iso:country":"US",
    "sg:address":"15926 Cypress North Houston Rd",
    "sg:city":"Cypress",
    "sg:classifiers":[
        {
            "category":"Wholesale",
            "subcategory":"Machinery & Supplies",
            "type":"Manufacturing & Wholesale Goods"
        }
    ],
    "sg:phone":"+1 281 213 9285",
    "sg:postcode":"77429",
    "sg:province":"TX",
    "sg:tags":[
        "industrial"
    ],
    "wof:name":"Texas Staple Company",
    "wof:placetype":"venue"
},
  "geometry": {"coordinates":[-95.660335,29.945811],"type":"Point"}
}