{
  "type": "Feature",
  "properties": {
    "iso:country":"US",
    "sg:address":"25602 I- 45",
    "sg:city":"Spring",
    "sg:classifiers":[
        {
            "category":"Shopping",
            "subcategory":"Florist",
            "type":"Retail Goods"
        }
    ],
    "sg:phone":"+1 281 367 0436",
    "sg:postcode":"77386",
    "sg:province":"TX",
    "wof:name":"Rain Forest Florist",
    "wof:placetype":"venue"
},
  "geometry": {"coordinates":[-95.444211,30.133907],"type":"Point"}
}