{
  "type": "Feature",
  "properties": {
    "iso:country":"US",
    "sg:address":"1710 Texas Ave S",
    "sg:city":"Bryan",
    "sg:classifiers":[
        {
            "category":"Personal",
            "subcategory":"Barber",
            "type":"Services"
        }
    ],
    "sg:phone":"+1 979 775 0966",
    "sg:postcode":"77802",
    "sg:province":"TX",
    "wof:name":"Absolute Images Barber Hair",
    "wof:placetype":"venue"
},
  "geometry": {"coordinates":[-96.36408,30.653386],"type":"Point"}
}