{
  "type": "Feature",
  "properties": {
    "iso:country":"US",
    "sg:address":"5920 E University Blvd",
    "sg:city":"Dallas",
    "sg:classifiers":[
        {
            "category":"Personal",
            "type":"Services"
        }
    ],
    "sg:phone":"+1 214 739 0840",
    "sg:postcode":"75206",
    "sg:province":"TX",
    "wof:name":"Meredythe Kimbrough Wedin",
    "wof:placetype":"venue"
},
  "geometry": {"coordinates":[-96.764161,32.846162],"type":"Point"}
}