{
  "type": "Feature",
  "properties": {
    "iso:country":"US",
    "sg:address":"6406 N Interstate 35 Suite 1550",
    "sg:city":"Austin",
    "sg:classifiers":[
        {
            "category":"Restaurant",
            "type":"Food & Drink"
        }
    ],
    "sg:phone":"+1 512 452 3888",
    "sg:postcode":"78752",
    "sg:province":"TX",
    "sg:tags":[
        "thai"
    ],
    "sg:website":"www.thaivillageaustin.com",
    "wof:name":"Thai Village Restaurant",
    "wof:placetype":"venue"
},
  "geometry": {"coordinates":[-97.704736,30.331936],"type":"Point"}
}