{
  "type": "Feature",
  "properties": {
    "iso:country":"US",
    "sg:address":"3107 Fredericksburg Rd",
    "sg:city":"San Antonio",
    "sg:classifiers":[
        {
            "category":"Freight",
            "type":"Transportation"
        }
    ],
    "sg:phone":"+1 210 733 8349",
    "sg:postcode":"78201",
    "sg:province":"TX",
    "sg:tags":[
        "warehouse",
        "location"
    ],
    "wof:name":"Wittigs Office Interiors Ltd",
    "wof:placetype":"venue"
},
  "geometry": {"coordinates":[-98.53329100000001,29.471571],"type":"Point"}
}