{
  "type": "Feature",
  "properties": {
    "iso:country":"US",
    "sg:address":"5930 Birchbrook Dr Apt 209",
    "sg:city":"Dallas",
    "sg:classifiers":[
        {
            "category":"Retail",
            "subcategory":"Auto Repair",
            "type":"Services"
        }
    ],
    "sg:phone":"+1 214 613 6706",
    "sg:postcode":"75206",
    "sg:province":"TX",
    "wof:name":"Gray Mar Automotive",
    "wof:placetype":"venue"
},
  "geometry": {"coordinates":[-96.76576799999999,32.847427],"type":"Point"}
}