{
  "type": "Feature",
  "properties": {
    "iso:country":"US",
    "sg:address":"326 Nugent Dr",
    "sg:city":"Port Neches",
    "sg:classifiers":[
        {
            "category":"Wholesale",
            "subcategory":"Durable Goods & Equipment",
            "type":"Manufacturing & Wholesale Goods"
        }
    ],
    "sg:phone":"+1 409 722 3323",
    "sg:postcode":"77651",
    "sg:province":"TX",
    "wof:name":"Artifacts",
    "wof:placetype":"venue"
},
  "geometry": {"coordinates":[-93.95534000000001,29.959259],"type":"Point"}
}