{
  "type": "Feature",
  "properties": {
    "iso:country":"US",
    "sg:address":"6800 Alamo Downs Pkwy",
    "sg:city":"San Antonio",
    "sg:classifiers":[
        {
            "category":"Manufacturing",
            "subcategory":"Tools & Machinery",
            "type":"Manufacturing & Wholesale Goods"
        }
    ],
    "sg:phone":"+1 210 521 7074",
    "sg:postcode":"78238",
    "sg:province":"TX",
    "sg:tags":[
        "physician",
        "surgeon"
    ],
    "sg:website":"www.medicalz.com",
    "wof:name":"Medical Z",
    "wof:placetype":"venue"
},
  "geometry": {"coordinates":[-98.620451,29.45588],"type":"Point"}
}