{
  "type": "Feature",
  "properties": {
    "iso:country":"US",
    "sg:address":"5050 Quorum Dr",
    "sg:city":"Dallas",
    "sg:classifiers":[
        {
            "category":"Professional",
            "subcategory":"Employment Agencies",
            "type":"Services"
        }
    ],
    "sg:phone":"+1 972 458 0100",
    "sg:postcode":"75254",
    "sg:province":"TX",
    "wof:name":"M Lane & Associates Financial Recruitment",
    "wof:placetype":"venue"
},
  "geometry": {"coordinates":[-96.803596,32.944],"type":"Point"}
}