{
  "type": "Feature",
  "properties": {
    "iso:country":"US",
    "sg:address":"3910 Dyer St",
    "sg:city":"El Paso",
    "sg:classifiers":[
        {
            "category":"Restaurant",
            "type":"Food & Drink"
        }
    ],
    "sg:phone":"+1 915 566 2800",
    "sg:postcode":"79930",
    "sg:province":"TX",
    "sg:tags":[
        "eating"
    ],
    "wof:name":"Papa Johns",
    "wof:placetype":"venue"
},
  "geometry": {"coordinates":[-106.44461200000001,31.812038],"type":"Point"}
}