{
  "type": "Feature",
  "properties": {
    "iso:country":"US",
    "sg:address":"902 Bandera Rd",
    "sg:city":"San Antonio",
    "sg:classifiers":[
        {
            "category":"Health Services",
            "subcategory":"Doctor",
            "type":"Services"
        }
    ],
    "sg:phone":"+1 210 431 4503",
    "sg:postcode":"78228",
    "sg:province":"TX",
    "sg:tags":[
        "physician",
        "surgeon"
    ],
    "wof:name":"Gonzaba Medical Group",
    "wof:placetype":"venue"
},
  "geometry": {"coordinates":[-98.55613,29.458232],"type":"Point"}
}