{
  "type": "Feature",
  "properties": {
    "iso:country":"US",
    "sg:address":"652 W Parktown Dr",
    "sg:city":"Deer Park",
    "sg:classifiers":[
        {
            "category":"Wholesale",
            "subcategory":"Machinery & Supplies",
            "type":"Manufacturing & Wholesale Goods"
        }
    ],
    "sg:phone":"+1 281 542 0549",
    "sg:postcode":"77536",
    "sg:province":"TX",
    "sg:tags":[
        "field",
        "oil",
        "equipment"
    ],
    "wof:name":"International Services",
    "wof:placetype":"venue"
},
  "geometry": {"coordinates":[-95.12922,29.680167],"type":"Point"}
}