{
  "type": "Feature",
  "properties": {
    "iso:country":"US",
    "sg:address":"7444 Golf Club Dr",
    "sg:city":"Fort Worth",
    "sg:classifiers":[
        {
            "category":"Professional",
            "subcategory":"Management & Consulting",
            "type":"Services"
        }
    ],
    "sg:phone":"+1 817 236 1057",
    "sg:postcode":"76179",
    "sg:province":"TX",
    "wof:name":"Talley-OH Enterprises",
    "wof:placetype":"venue"
},
  "geometry": {"coordinates":[-97.437192,32.878329],"type":"Point"}
}