{
  "type": "Feature",
  "properties": {
    "iso:country":"US",
    "sg:address":"427 S Fannin Ave",
    "sg:city":"Tyler",
    "sg:classifiers":[
        {
            "category":"Insurance",
            "subcategory":"Insurance Agent",
            "type":"Services"
        }
    ],
    "sg:phone":"+1 903 592 2268",
    "sg:postcode":"75702",
    "sg:province":"TX",
    "wof:name":"Reassure America",
    "wof:placetype":"venue"
},
  "geometry": {"coordinates":[-95.29840799999999,32.346573],"type":"Point"}
}