{
  "type": "Feature",
  "properties": {
    "iso:country":"US",
    "sg:address":"1409 Main St",
    "sg:city":"Junction",
    "sg:classifiers":[
        {
            "category":"Shopping",
            "subcategory":"Gifts & Souvenirs",
            "type":"Retail Goods"
        }
    ],
    "sg:phone":"+1 325 446 8558",
    "sg:postcode":"76849",
    "sg:province":"TX",
    "wof:name":"Conchos & Crosses",
    "wof:placetype":"venue"
},
  "geometry": {"coordinates":[-99.77553899999999,30.48981],"type":"Point"}
}