{
  "type": "Feature",
  "properties": {
    "iso:country":"US",
    "sg:address":"7524 S Broadway Ave",
    "sg:city":"Tyler",
    "sg:classifiers":[
        {
            "category":"Professional",
            "type":"Services"
        }
    ],
    "sg:phone":"+1 903 581 2205",
    "sg:postcode":"75703",
    "sg:province":"TX",
    "sg:tags":[
        "establishment"
    ],
    "wof:name":"Gene Shelton Inc",
    "wof:placetype":"venue"
},
  "geometry": {"coordinates":[-95.307196,32.266653],"type":"Point"}
}