{
  "type": "Feature",
  "properties": {
    "iso:country":"US",
    "sg:address":"5730 College St",
    "sg:city":"Beaumont",
    "sg:classifiers":[
        {
            "category":"Building & Trades",
            "subcategory":"Plumbing",
            "type":"Services"
        }
    ],
    "sg:phone":"+1 409 981 9511",
    "sg:postcode":"77707",
    "sg:province":"TX",
    "sg:tags":[
        "conditioning",
        "air",
        "system",
        "contractor"
    ],
    "wof:name":"Richard Farris A/C Refrig",
    "wof:placetype":"venue"
},
  "geometry": {"coordinates":[-94.157886,30.06792],"type":"Point"}
}