{
  "type": "Feature",
  "properties": {
    "iso:country":"US",
    "sg:address":"5904 Texoma Pkwy",
    "sg:city":"Sherman",
    "sg:classifiers":[
        {
            "category":"Government",
            "subcategory":"Office",
            "type":"Public Place"
        }
    ],
    "sg:phone":"+1 903 893 1111",
    "sg:postcode":"75090",
    "sg:province":"TX",
    "sg:tags":[
        "regulatory",
        "agency",
        "labor"
    ],
    "wof:name":"Local Office-Sherman",
    "wof:placetype":"venue"
},
  "geometry": {"coordinates":[-96.577213,33.693562],"type":"Point"}
}