{
  "type": "Feature",
  "properties": {
    "iso:country":"US",
    "sg:address":"1800 N Main St",
    "sg:city":"Shamrock",
    "sg:classifiers":[
        {
            "category":"Autos & Motor Vehicles",
            "subcategory":"Fuel & Gas Station",
            "type":"Retail Goods"
        }
    ],
    "sg:phone":"+1 806 256 5175",
    "sg:postcode":"79079",
    "sg:province":"TX",
    "sg:tags":[
        "oil"
    ],
    "wof:name":"Lacy's Conoco",
    "wof:placetype":"venue"
},
  "geometry": {"coordinates":[-100.249138,35.231729],"type":"Point"}
}