{
  "type": "Feature",
  "properties": {
    "iso:country":"US",
    "sg:address":"1008 Wyoming Ave",
    "sg:city":"El Paso",
    "sg:classifiers":[
        {
            "category":"Wholesale",
            "subcategory":"Machinery & Supplies",
            "type":"Manufacturing & Wholesale Goods"
        }
    ],
    "sg:phone":"+1 915 533 7021",
    "sg:postcode":"79902",
    "sg:province":"TX",
    "sg:tags":[
        "equipment",
        "establishment"
    ],
    "wof:name":"Jay L Harman Fire Equipment Co",
    "wof:placetype":"venue"
},
  "geometry": {"coordinates":[-106.482399,31.767479],"type":"Point"}
}