{
  "type": "Feature",
  "properties": {
    "iso:country":"US",
    "sg:address":"2720 Chupik St",
    "sg:city":"Rosenberg",
    "sg:classifiers":[
        {
            "category":"Wholesale",
            "subcategory":"Groceries",
            "type":"Manufacturing & Wholesale Goods"
        }
    ],
    "sg:phone":"+1 281 232 2927",
    "sg:postcode":"77471",
    "sg:province":"TX",
    "sg:tags":[
        "confectionery"
    ],
    "wof:name":"Mortons Foods",
    "wof:placetype":"venue"
},
  "geometry": {"coordinates":[-95.80352999999999,29.536865],"type":"Point"}
}