{
  "type": "Feature",
  "properties": {
    "iso:country":"US",
    "sg:address":"810 Thomasson Dr",
    "sg:city":"Dallas",
    "sg:classifiers":[
        {
            "category":"Professional",
            "subcategory":"Management & Consulting",
            "type":"Services"
        }
    ],
    "sg:phone":"+1 214 941 7021",
    "sg:postcode":"75208",
    "sg:province":"TX",
    "wof:name":"Robert W Scroggins MGT Cons",
    "wof:placetype":"venue"
},
  "geometry": {"coordinates":[-96.837305,32.755994],"type":"Point"}
}