{
  "type": "Feature",
  "properties": {
    "iso:country":"US",
    "sg:address":"111 N Ave I",
    "sg:city":"Post",
    "sg:classifiers":[
        {
            "category":"Organizations",
            "subcategory":"Religious Organization",
            "type":"Services"
        }
    ],
    "sg:phone":"+1 806 495 1400",
    "sg:postcode":"79356",
    "sg:province":"TX",
    "sg:tags":[
        "church"
    ],
    "wof:name":"Family Harvest Church",
    "wof:placetype":"venue"
},
  "geometry": {"coordinates":[-101.37702299999999,33.192413],"type":"Point"}
}