{
  "type": "Feature",
  "properties": {
    "iso:country":"US",
    "sg:address":"1405 Jupiter Rd Ste 106",
    "sg:city":"Plano",
    "sg:classifiers":[
        {
            "category":"Personal",
            "subcategory":"Nail Salon",
            "type":"Services"
        }
    ],
    "sg:phone":"+1 972 398 7948",
    "sg:postcode":"75074",
    "sg:province":"TX",
    "wof:name":"Top Ten Nails",
    "wof:placetype":"venue"
},
  "geometry": {"coordinates":[-96.68254899999999,33.018175],"type":"Point"}
}