{
  "type": "Feature",
  "properties": {
    "iso:country":"US",
    "sg:address":"5825 Palm Ln",
    "sg:city":"Dallas",
    "sg:classifiers":[
        {
            "category":"Professional",
            "type":"Services"
        }
    ],
    "sg:phone":"+1 214 370 0551",
    "sg:postcode":"75206",
    "sg:province":"TX",
    "wof:name":"Prohibition",
    "wof:placetype":"venue"
},
  "geometry": {"coordinates":[-96.766527,32.837536],"type":"Point"}
}