{
  "type": "Feature",
  "properties": {
    "iso:country":"US",
    "sg:address":"824 S Crowley Rd",
    "sg:city":"Crowley",
    "sg:classifiers":[
        {
            "category":"Personal",
            "subcategory":"Beauty Salon",
            "type":"Services"
        },
        {
            "category":"Personal",
            "subcategory":"Tanning Parlor",
            "type":"Services"
        }
    ],
    "sg:phone":"+1 817 297 0606",
    "sg:postcode":"76036",
    "sg:province":"TX",
    "sg:website":"http://www.planetbeach.com",
    "wof:name":"Planet Beach",
    "wof:placetype":"venue"
},
  "geometry": {"coordinates":[-97.351049,32.586503],"type":"Point"}
}