{
  "type": "Feature",
  "properties": {
    "iso:country":"US",
    "sg:address":"2108 N Village Dr",
    "sg:city":"Bonham",
    "sg:classifiers":[
        {
            "category":"Professional",
            "type":"Services"
        }
    ],
    "sg:phone":"+1 903 640 4091",
    "sg:postcode":"75418",
    "sg:province":"TX",
    "sg:tags":[
        "establishment"
    ],
    "wof:name":"Dept Of Veteran Affairs",
    "wof:placetype":"venue"
},
  "geometry": {"coordinates":[-96.18710299999999,33.598635],"type":"Point"}
}