{
  "type": "Feature",
  "properties": {
    "iso:country":"US",
    "sg:address":"3405 Fairlane Ave",
    "sg:city":"Odessa",
    "sg:classifiers":[
        {
            "category":"Banks & Credit Unions",
            "subcategory":"Bank",
            "type":"Services"
        }
    ],
    "sg:phone":"+1 432 366 1385",
    "sg:postcode":"79762",
    "sg:province":"TX",
    "sg:tags":[
        "leasing",
        "broker"
    ],
    "wof:name":"American Leasing",
    "wof:placetype":"venue"
},
  "geometry": {"coordinates":[-102.348831,31.880072],"type":"Point"}
}