{
  "type": "Feature",
  "properties": {
    "iso:country":"US",
    "sg:address":"1002 Falling Leaf Dr",
    "sg:city":"Friendswood",
    "sg:classifiers":[
        {
            "category":"Professional",
            "type":"Services"
        }
    ],
    "sg:phone":"+1 281 648 9399",
    "sg:postcode":"77546",
    "sg:province":"TX",
    "wof:name":"Face & Body Stop",
    "wof:placetype":"venue"
},
  "geometry": {"coordinates":[-95.210914,29.515041],"type":"Point"}
}