{
  "type": "Feature",
  "properties": {
    "iso:country":"US",
    "sg:address":"9200 Lakeview Pkwy Ste A",
    "sg:city":"Rowlett",
    "sg:classifiers":[
        {
            "category":"Insurance",
            "subcategory":"Hazard Insurance",
            "type":"Services"
        }
    ],
    "sg:phone":"+1 972 463 6988",
    "sg:postcode":"75088",
    "sg:province":"TX",
    "sg:website":"http://statefarm.mqgroup.com/url.asp?usr=437271",
    "wof:name":"State Farm Insurance Agent-Sandra Trollinger",
    "wof:placetype":"venue"
},
  "geometry": {"coordinates":[-96.51246,32.91982],"type":"Point"}
}