{
  "type": "Feature",
  "properties": {
    "iso:country":"US",
    "sg:address":"2705 Kempton Dr",
    "sg:city":"Arlington",
    "sg:classifiers":[
        {
            "category":"Building & Trades",
            "subcategory":"Construction",
            "type":"Services"
        }
    ],
    "sg:phone":"+1 817 483 8213",
    "sg:postcode":"76001",
    "sg:province":"TX",
    "sg:tags":[
        "restoration",
        "cleaning",
        "patio",
        "deck"
    ],
    "wof:name":"M & R Power Washing",
    "wof:placetype":"venue"
},
  "geometry": {"coordinates":[-97.154628,32.621635],"type":"Point"}
}