{
  "type": "Feature",
  "properties": {
    "iso:country":"US",
    "sg:address":"17803 Running Brook Ln",
    "sg:city":"Spring",
    "sg:classifiers":[
        {
            "category":"Real Estate",
            "subcategory":"Real Estate Agent",
            "type":"Services"
        }
    ],
    "sg:phone":"+1 281 376 3622",
    "sg:postcode":"77379",
    "sg:province":"TX",
    "wof:name":"Virologic Inc",
    "wof:placetype":"venue"
},
  "geometry": {"coordinates":[-95.541473,30.028134],"type":"Point"}
}