{
  "type": "Feature",
  "properties": {
    "iso:country":"US",
    "sg:address":"2305 Hayes Rd",
    "sg:city":"Houston",
    "sg:classifiers":[
        {
            "category":"Arts & Performance",
            "subcategory":"Theater",
            "type":"Entertainment"
        }
    ],
    "sg:phone":"+1 713 780 1755",
    "sg:postcode":"77077",
    "sg:province":"TX",
    "sg:tags":[
        "group"
    ],
    "wof:name":"Audible Noise Entertainment",
    "wof:placetype":"venue"
},
  "geometry": {"coordinates":[-95.576131,29.739639],"type":"Point"}
}