{
  "type": "Feature",
  "properties": {
    "iso:country":"US",
    "sg:address":"1917 Melissa St",
    "sg:city":"Arlington",
    "sg:classifiers":[
        {
            "category":"Building & Trades",
            "subcategory":"Construction",
            "type":"Services"
        }
    ],
    "sg:phone":"+1 817 919 3932",
    "sg:postcode":"76010",
    "sg:province":"TX",
    "sg:tags":[
        "hanging",
        "painter",
        "contractor"
    ],
    "wof:name":"Doug Perry's Painting",
    "wof:placetype":"venue"
},
  "geometry": {"coordinates":[-97.075338,32.732212],"type":"Point"}
}