{
  "type": "Feature",
  "properties": {
    "iso:country":"US",
    "sg:address":"12631 Vance Jackson Rd",
    "sg:city":"San Antonio",
    "sg:classifiers":[
        {
            "category":"Cinema",
            "subcategory":"Movie Theater",
            "type":"Entertainment"
        }
    ],
    "sg:phone":"+1 210 641 6906",
    "sg:postcode":"78230",
    "sg:province":"TX",
    "wof:name":"Fiesta 16",
    "wof:placetype":"venue"
},
  "geometry": {"coordinates":[-98.577524,29.558541],"type":"Point"}
}