{
  "type": "Feature",
  "properties": {
    "iso:country":"US",
    "sg:address":"13115 N Stemmons Fwy",
    "sg:city":"Dallas",
    "sg:classifiers":[
        {
            "category":"Autos & Motor Vehicles",
            "subcategory":"Fuel & Gas Station",
            "type":"Retail Goods"
        }
    ],
    "sg:phone":"+1 972 406 1111",
    "sg:postcode":"75234",
    "sg:province":"TX",
    "sg:website":"www.shell.com",
    "wof:name":"Shell",
    "wof:placetype":"venue"
},
  "geometry": {"coordinates":[-96.90034799999999,32.922079],"type":"Point"}
}