{
  "type": "Feature",
  "properties": {
    "iso:country":"US",
    "sg:address":"316 Peabody St",
    "sg:city":"Edna",
    "sg:classifiers":[
        {
            "category":"Retail",
            "subcategory":"Funeral Services",
            "type":"Services"
        }
    ],
    "sg:phone":"+1 361 782 3821",
    "sg:postcode":"77957",
    "sg:province":"TX",
    "sg:tags":[
        "crematory"
    ],
    "wof:name":"Cook-Butler Funeral Home",
    "wof:placetype":"venue"
},
  "geometry": {"coordinates":[-96.64079,28.984253],"type":"Point"}
}