{
  "type": "Feature",
  "properties": {
    "iso:country":"US",
    "sg:address":"3832 Samuell Blvd",
    "sg:city":"Dallas",
    "sg:classifiers":[
        {
            "category":"Retail",
            "subcategory":"Auto Repair",
            "type":"Services"
        }
    ],
    "sg:phone":"+1 214 388 8870",
    "sg:postcode":"75228",
    "sg:province":"TX",
    "sg:tags":[
        "general"
    ],
    "wof:name":"Medrano Auto Repair",
    "wof:placetype":"venue"
},
  "geometry": {"coordinates":[-96.728638,32.792888],"type":"Point"}
}