{
  "type": "Feature",
  "properties": {
    "iso:country":"US",
    "sg:address":"299 Shadow Mountain Dr",
    "sg:city":"El Paso",
    "sg:classifiers":[
        {
            "category":"Banks & Credit Unions",
            "subcategory":"Financial Services",
            "type":"Services"
        }
    ],
    "sg:phone":"+1 915 587 4747",
    "sg:postcode":"79912",
    "sg:province":"TX",
    "sg:tags":[
        "broker",
        "mortgage"
    ],
    "wof:name":"Mortgage West",
    "wof:placetype":"venue"
},
  "geometry": {"coordinates":[-106.52600099999999,31.833099],"type":"Point"}
}