{
  "type": "Feature",
  "properties": {
    "iso:country":"US",
    "sg:address":"5329 Juliandra Ave",
    "sg:city":"El Paso",
    "sg:classifiers":[
        {
            "category":"Personal",
            "subcategory":"Beauty Salon",
            "type":"Services"
        }
    ],
    "sg:phone":"+1 915 755 4118",
    "sg:postcode":"79924",
    "sg:province":"TX",
    "sg:tags":[
        "shop"
    ],
    "wof:name":"Amelia Adams Beauty Shop",
    "wof:placetype":"venue"
},
  "geometry": {"coordinates":[-106.41857,31.89544],"type":"Point"}
}