{
  "type": "Feature",
  "properties": {
    "iso:country":"US",
    "sg:address":"8338 Southwest Fwy",
    "sg:city":"Houston",
    "sg:classifiers":[
        {
            "category":"Restaurant",
            "type":"Food & Drink"
        }
    ],
    "sg:phone":"+1 713 484 5683",
    "sg:postcode":"77074",
    "sg:province":"TX",
    "wof:name":"Altamirano Restaurante",
    "wof:placetype":"venue"
},
  "geometry": {"coordinates":[-95.529404,29.6903],"type":"Point"}
}