{
  "type": "Feature",
  "properties": {
    "iso:country":"US",
    "sg:address":"11851 Socorro Rd",
    "sg:city":"San Elizario",
    "sg:classifiers":[
        {
            "category":"Bars & Pubs",
            "type":"Food & Drink"
        }
    ],
    "sg:phone":"+1 915 851 5435",
    "sg:postcode":"79849",
    "sg:province":"TX",
    "sg:tags":[
        "drinking"
    ],
    "wof:name":"El Palanque Bar",
    "wof:placetype":"venue"
},
  "geometry": {"coordinates":[-106.276606,31.603915],"type":"Point"}
}