{
  "type": "Feature",
  "properties": {
    "iso:country":"US",
    "sg:address":"2730 N Stemmons Fwy",
    "sg:city":"Dallas",
    "sg:classifiers":[
        {
            "category":"Professional",
            "subcategory":"Lawyer & Legal Services",
            "type":"Services"
        }
    ],
    "sg:phone":"+1 214 631 4330",
    "sg:postcode":"75207",
    "sg:province":"TX",
    "sg:tags":[
        "attorney"
    ],
    "wof:name":"Umeakuana Clement",
    "wof:placetype":"venue"
},
  "geometry": {"coordinates":[-96.841767,32.807781],"type":"Point"}
}