{
  "type": "Feature",
  "properties": {
    "iso:country":"US",
    "sg:address":"800 W 5th St Apt 905",
    "sg:city":"Austin",
    "sg:classifiers":[
        {
            "category":"Food & Beverages",
            "subcategory":"Liquor & Beverages",
            "type":"Retail Goods"
        },
        {
            "category":"Wholesale",
            "subcategory":"Wine & Distilled Alcoholic Beverages",
            "type":"Manufacturing & Wholesale Goods"
        }
    ],
    "sg:phone":"+1 512 587 7542",
    "sg:postcode":"78703",
    "sg:province":"TX",
    "sg:tags":[
        "broker"
    ],
    "wof:name":"Crush Wine Marketing, Inc.",
    "wof:placetype":"venue"
},
  "geometry": {"coordinates":[-97.750923,30.26931],"type":"Point"}
}