{
  "type": "Feature",
  "properties": {
    "iso:country":"US",
    "sg:address":"2418 S 38th St",
    "sg:city":"Abilene",
    "sg:classifiers":[
        {
            "category":"Real Estate",
            "subcategory":"Real Estate Agent",
            "type":"Services"
        }
    ],
    "sg:phone":"+1 325 692 2618",
    "sg:postcode":"79605",
    "sg:province":"TX",
    "wof:name":"D Solenben Real Estate",
    "wof:placetype":"venue"
},
  "geometry": {"coordinates":[-99.75279999999999,32.405814],"type":"Point"}
}