{
  "type": "Feature",
  "properties": {
    "iso:country":"US",
    "sg:address":"2029 Emil Rd",
    "sg:city":"La Grange",
    "sg:classifiers":[
        {
            "category":"Farming",
            "subcategory":"Livestock Farm",
            "type":"Manufacturing & Wholesale Goods"
        }
    ],
    "sg:phone":"+1 979 242 3205",
    "sg:postcode":"78945",
    "sg:province":"TX",
    "sg:tags":[
        "beef",
        "feedlot",
        "cattle"
    ],
    "wof:name":"Erwin T Zoch",
    "wof:placetype":"venue"
},
  "geometry": {"coordinates":[-97.01307,30.015348],"type":"Point"}
}