{
  "type": "Feature",
  "properties": {
    "iso:country":"US",
    "sg:address":"3500 Leopard St",
    "sg:city":"Corpus Christi",
    "sg:classifiers":[
        {
            "category":"Professional",
            "subcategory":"Accounting & Tax Preparation",
            "type":"Services"
        }
    ],
    "sg:phone":"+1 361 767 9162",
    "sg:postcode":"78408",
    "sg:province":"TX",
    "sg:tags":[
        "return",
        "filing"
    ],
    "wof:name":"Tax Express",
    "wof:placetype":"venue"
},
  "geometry": {"coordinates":[-97.429092,27.796933],"type":"Point"}
}