{
  "type": "Feature",
  "properties": {
    "iso:country":"US",
    "sg:address":"4234 Spring Valley Rd",
    "sg:city":"Dallas",
    "sg:classifiers":[
        {
            "category":"Coffee & Tea",
            "type":"Food & Drink"
        }
    ],
    "sg:phone":"+1 214 821 8818",
    "sg:postcode":"75244",
    "sg:province":"TX",
    "sg:website":"www.dailyjava.com",
    "wof:name":"The Daily Java",
    "wof:placetype":"venue"
},
  "geometry": {"coordinates":[-96.838235,32.939835],"type":"Point"}
}