{
  "type": "Feature",
  "properties": {
    "iso:country":"US",
    "sg:address":"202 S Bryan Ave",
    "sg:city":"Bryan",
    "sg:classifiers":[
        {
            "category":"Shopping",
            "subcategory":"Stationery & Office Supplies",
            "type":"Retail Goods"
        },
        {
            "category":"Shopping",
            "subcategory":"Gifts & Souvenirs",
            "type":"Retail Goods"
        }
    ],
    "sg:phone":"+1 979 822 4031",
    "sg:postcode":"77803",
    "sg:province":"TX",
    "sg:tags":[
        "stationer"
    ],
    "wof:name":"Out Of The Box Cards & Designs",
    "wof:placetype":"venue"
},
  "geometry": {"coordinates":[-96.37436,30.67188],"type":"Point"}
}