{
  "type": "Feature",
  "properties": {
    "iso:country":"US",
    "sg:address":"214 S 5th St",
    "sg:city":"Brownfield",
    "sg:classifiers":[
        {
            "category":"Personal",
            "subcategory":"Barber",
            "type":"Services"
        }
    ],
    "sg:phone":"+1 806 637 4201",
    "sg:postcode":"79316",
    "sg:province":"TX",
    "sg:tags":[
        "shop",
        "salon",
        "beauty"
    ],
    "wof:name":"Wise Barber Shop",
    "wof:placetype":"venue"
},
  "geometry": {"coordinates":[-102.27995,33.177938],"type":"Point"}
}