{
  "type": "Feature",
  "properties": {
    "iso:country":"US",
    "sg:address":"8100 Precinct Line Rd",
    "sg:city":"Fort Worth",
    "sg:classifiers":[
        {
            "category":"Real Estate",
            "subcategory":"Real Estate Operator",
            "type":"Services"
        }
    ],
    "sg:phone":"+1 817 788 9742",
    "sg:postcode":"76180",
    "sg:province":"TX",
    "sg:tags":[
        "mobile",
        "home",
        "community"
    ],
    "wof:name":"Oak Leaf Mobile Home Park",
    "wof:placetype":"venue"
},
  "geometry": {"coordinates":[-97.186007,32.898273],"type":"Point"}
}