{
  "type": "Feature",
  "properties": {
    "iso:country":"US",
    "sg:address":"103 N Walcott St",
    "sg:city":"Jefferson",
    "sg:classifiers":[
        {
            "category":"Shopping",
            "subcategory":"Tobacco",
            "type":"Retail Goods"
        }
    ],
    "sg:phone":"+1 903 665 7225",
    "sg:postcode":"75657",
    "sg:province":"TX",
    "sg:tags":[
        "outlet"
    ],
    "wof:name":"Tobacco Outlet",
    "wof:placetype":"venue"
},
  "geometry": {"coordinates":[-94.355035,32.762512],"type":"Point"}
}