{
  "type": "Feature",
  "properties": {
    "iso:country":"US",
    "sg:address":"1107 Fontaine Dr",
    "sg:city":"Southlake",
    "sg:classifiers":[
        {
            "category":"Education",
            "subcategory":"Vocational School",
            "type":"Public Place"
        }
    ],
    "sg:phone":"+1 817 416 8228",
    "sg:postcode":"76092",
    "sg:province":"TX",
    "sg:tags":[
        "aviation"
    ],
    "wof:name":"Lair & Associates",
    "wof:placetype":"venue"
},
  "geometry": {"coordinates":[-97.13137,32.93198],"type":"Point"}
}