{
  "type": "Feature",
  "properties": {
    "iso:country":"US",
    "sg:address":"704 Byron Nelson Blvd",
    "sg:city":"Roanoke",
    "sg:classifiers":[
        {
            "category":"Food & Beverages",
            "subcategory":"Groceries & Convenience Stores",
            "type":"Retail Goods"
        }
    ],
    "sg:phone":"+1 817 491 7232",
    "sg:postcode":"76262",
    "sg:province":"TX",
    "wof:name":"Lovely Food Mart",
    "wof:placetype":"venue"
},
  "geometry": {"coordinates":[-97.23309,33.007729],"type":"Point"}
}