{
  "type": "Feature",
  "properties": {
    "iso:country":"US",
    "sg:address":"2112 Beaver Pelt Cv",
    "sg:city":"Austin",
    "sg:classifiers":[
        {
            "category":"Bakery",
            "type":"Food & Drink"
        }
    ],
    "sg:phone":"+1 512 367 9439",
    "sg:postcode":"78754",
    "sg:province":"TX",
    "wof:name":"Sliced Bread",
    "wof:placetype":"venue"
},
  "geometry": {"coordinates":[-97.649766,30.371693],"type":"Point"}
}