{
  "type": "Feature",
  "properties": {
    "iso:country":"US",
    "sg:address":"3105 S Woodland St",
    "sg:city":"Amarillo",
    "sg:classifiers":[
        {
            "category":"Retail",
            "subcategory":"Repair Shop",
            "type":"Services"
        }
    ],
    "sg:phone":"+1 806 373 0520",
    "sg:postcode":"79103",
    "sg:province":"TX",
    "wof:name":"Chips Repair Service",
    "wof:placetype":"venue"
},
  "geometry": {"coordinates":[-101.798557,35.178587],"type":"Point"}
}