{
  "type": "Feature",
  "properties": {
    "iso:country":"US",
    "sg:address":"2818 E Glen Dr",
    "sg:city":"El Paso",
    "sg:classifiers":[
        {
            "category":"Professional",
            "type":"Services"
        }
    ],
    "sg:phone":"+1 915 598 1929",
    "sg:postcode":"79936",
    "sg:province":"TX",
    "wof:name":"Ng & Chan Corp",
    "wof:placetype":"venue"
},
  "geometry": {"coordinates":[-106.318549,31.780937],"type":"Point"}
}