{
  "type": "Feature",
  "properties": {
    "iso:country":"US",
    "sg:address":"12170 Bissonnet St",
    "sg:city":"Houston",
    "sg:classifiers":[
        {
            "category":"Retail",
            "subcategory":"Self-service Laundry",
            "type":"Services"
        }
    ],
    "sg:phone":"+1 281 498 6269",
    "sg:postcode":"77099",
    "sg:province":"TX",
    "wof:name":"Coin Operated Washteria",
    "wof:placetype":"venue"
},
  "geometry": {"coordinates":[-95.59410699999999,29.67578],"type":"Point"}
}