{
  "type": "Feature",
  "properties": {
    "iso:country":"US",
    "sg:address":"417 Cedar Ave",
    "sg:city":"Mcallen",
    "sg:classifiers":[
        {
            "category":"Building & Trades",
            "subcategory":"Electrical",
            "type":"Services"
        }
    ],
    "sg:phone":"+1 956 631 5662",
    "sg:postcode":"78501",
    "sg:province":"TX",
    "sg:tags":[
        "electric",
        "contractor"
    ],
    "wof:name":"Eldridge Electric",
    "wof:placetype":"venue"
},
  "geometry": {"coordinates":[-98.225087,26.204998],"type":"Point"}
}