{
  "type": "Feature",
  "properties": {
    "iso:country":"US",
    "sg:address":"3925 W Braker Ln",
    "sg:city":"Austin",
    "sg:classifiers":[
        {
            "category":"Professional",
            "subcategory":"Business Services",
            "type":"Services"
        }
    ],
    "sg:phone":"+1 512 305 0690",
    "sg:postcode":"78759",
    "sg:province":"TX",
    "sg:tags":[
        "recording",
        "studio"
    ],
    "wof:name":"Keystone Studio",
    "wof:placetype":"venue"
},
  "geometry": {"coordinates":[-97.737116,30.397702],"type":"Point"}
}