{
  "type": "Feature",
  "properties": {
    "iso:country":"US",
    "sg:address":"909 E 7th St",
    "sg:city":"Dallas",
    "sg:classifiers":[
        {
            "category":"Autos & Motor Vehicles",
            "subcategory":"Automobile Sales",
            "type":"Retail Goods"
        }
    ],
    "sg:phone":"+1 214 941 1515",
    "sg:postcode":"75203",
    "sg:province":"TX",
    "sg:tags":[
        "car",
        "dealer"
    ],
    "wof:name":"Manhattan Motor Co",
    "wof:placetype":"venue"
},
  "geometry": {"coordinates":[-96.80998700000001,32.752842],"type":"Point"}
}