{
  "type": "Feature",
  "properties": {
    "iso:country":"US",
    "sg:address":"11103 S Post Oak Rd",
    "sg:city":"Houston",
    "sg:classifiers":[
        {
            "category":"Personal",
            "subcategory":"Beauty Salon",
            "type":"Services"
        }
    ],
    "sg:phone":"+1 713 728 2561",
    "sg:postcode":"77035",
    "sg:province":"TX",
    "sg:tags":[
        "shop"
    ],
    "wof:name":"Hair Evolution II",
    "wof:placetype":"venue"
},
  "geometry": {"coordinates":[-95.46392,29.659048],"type":"Point"}
}