{
  "type": "Feature",
  "properties": {
    "iso:country":"US",
    "sg:address":"401 W Main St",
    "sg:city":"Rio Grande City",
    "sg:classifiers":[
        {
            "category":"Personal",
            "subcategory":"Beauty Salon",
            "type":"Services"
        }
    ],
    "sg:phone":"+1 956 487 4295",
    "sg:postcode":"78582",
    "sg:province":"TX",
    "sg:tags":[
        "shop"
    ],
    "wof:name":"Marus Beauty Shop",
    "wof:placetype":"venue"
},
  "geometry": {"coordinates":[-98.82405199999999,26.380111],"type":"Point"}
}