{
  "type": "Feature",
  "properties": {
    "iso:country":"US",
    "sg:address":"3422 Country Club Blvd",
    "sg:city":"Montgomery",
    "sg:classifiers":[
        {
            "category":"Shopping",
            "subcategory":"Jewelry",
            "type":"Retail Goods"
        }
    ],
    "sg:phone":"+1 936 582 1779",
    "sg:postcode":"77356",
    "sg:province":"TX",
    "wof:name":"D&B Jewelers",
    "wof:placetype":"venue"
},
  "geometry": {"coordinates":[-95.62872299999999,30.395232],"type":"Point"}
}