{
  "type": "Feature",
  "properties": {
    "iso:country":"US",
    "sg:address":"307 W Poe St",
    "sg:city":"Iowa Park",
    "sg:classifiers":[
        {
            "category":"Mining & Drilling",
            "type":"Manufacturing & Wholesale Goods"
        }
    ],
    "sg:phone":"+1 940 592 5223",
    "sg:postcode":"76367",
    "sg:province":"TX",
    "sg:tags":[
        "oil",
        "well"
    ],
    "wof:name":"Spruiell Drilling Co",
    "wof:placetype":"venue"
},
  "geometry": {"coordinates":[-98.671621,33.949682],"type":"Point"}
}