{
  "type": "Feature",
  "properties": {
    "iso:country":"US",
    "sg:address":"325 S Bois D'Arc St",
    "sg:city":"Forney",
    "sg:classifiers":[
        {
            "category":"Health Services",
            "subcategory":"Doctor",
            "type":"Services"
        }
    ],
    "sg:phone":"+1 972 564 2261",
    "sg:postcode":"75126",
    "sg:province":"TX",
    "sg:tags":[
        "physician",
        "surgeon"
    ],
    "wof:name":"Forney Medical Clinic",
    "wof:placetype":"venue"
},
  "geometry": {"coordinates":[-96.47340699999999,32.746568],"type":"Point"}
}