{
  "type": "Feature",
  "properties": {
    "iso:country":"US",
    "sg:address":"4850 Pure Atlantic Rd",
    "sg:city":"Groves",
    "sg:classifiers":[
        {
            "category":"Insurance",
            "subcategory":"Insurance Agent",
            "type":"Services"
        }
    ],
    "sg:phone":"+1 409 960 6036",
    "sg:postcode":"77619",
    "sg:province":"TX",
    "wof:name":"A & B Boat & Mini Storage",
    "wof:placetype":"venue"
},
  "geometry": {"coordinates":[-93.916552,29.962074],"type":"Point"}
}