{
  "type": "Feature",
  "properties": {
    "iso:country":"US",
    "sg:address":"14028 Fm 2100 Rd",
    "sg:city":"Crosby",
    "sg:classifiers":[
        {
            "category":"Banks & Credit Unions",
            "subcategory":"Bank",
            "type":"Services"
        }
    ],
    "sg:phone":"+1 281 462 9061",
    "sg:postcode":"77532",
    "sg:province":"TX",
    "sg:website":"www.gpsccu.com",
    "wof:name":"United Community Credit Union",
    "wof:placetype":"venue"
},
  "geometry": {"coordinates":[-95.31456300000001,29.890714],"type":"Point"}
}