{
  "type": "Feature",
  "properties": {
    "iso:country":"US",
    "sg:address":"5526 Norments St",
    "sg:city":"Houston",
    "sg:classifiers":[
        {
            "category":"Professional",
            "subcategory":"Business Services",
            "type":"Services"
        }
    ],
    "sg:phone":"+1 713 353 9090",
    "sg:postcode":"77039",
    "sg:province":"TX",
    "wof:name":"First Class Enterprises",
    "wof:placetype":"venue"
},
  "geometry": {"coordinates":[-95.30787599999999,29.91281],"type":"Point"}
}