{
  "type": "Feature",
  "properties": {
    "iso:country":"US",
    "sg:address":"601 Delaware St",
    "sg:city":"San Antonio",
    "sg:classifiers":[
        {
            "category":"Building & Trades",
            "subcategory":"Plumbing",
            "type":"Services"
        }
    ],
    "sg:phone":"+1 210 532 7417",
    "sg:postcode":"78210",
    "sg:province":"TX",
    "sg:tags":[
        "plumbing"
    ],
    "wof:name":"All Rite Plumbing Co",
    "wof:placetype":"venue"
},
  "geometry": {"coordinates":[-98.47621700000001,29.408082],"type":"Point"}
}