{
  "type": "Feature",
  "properties": {
    "iso:country":"US",
    "sg:address":"6867 Thistle Hill Way",
    "sg:city":"Austin",
    "sg:classifiers":[
        {
            "category":"Professional",
            "subcategory":"Engineering",
            "type":"Services"
        }
    ],
    "sg:phone":"+1 512 832 8694",
    "sg:postcode":"78754",
    "sg:province":"TX",
    "sg:tags":[
        "consulting",
        "engineer"
    ],
    "wof:name":"Asil Cad & Services",
    "wof:placetype":"venue"
},
  "geometry": {"coordinates":[-97.612397,30.349703],"type":"Point"}
}