{
  "type": "Feature",
  "properties": {
    "iso:country":"US",
    "sg:address":"700 Ruiz St",
    "sg:city":"San Antonio",
    "sg:classifiers":[
        {
            "category":"Bars & Pubs",
            "type":"Food & Drink"
        }
    ],
    "sg:phone":"+1 210 223 0111",
    "sg:postcode":"78207",
    "sg:province":"TX",
    "sg:tags":[
        "lounge",
        "cocktail"
    ],
    "wof:name":"El Lugar",
    "wof:placetype":"venue"
},
  "geometry": {"coordinates":[-98.514574,29.435346],"type":"Point"}
}