{
  "type": "Feature",
  "properties": {
    "iso:country":"US",
    "sg:address":"705 W Harris Ave",
    "sg:city":"Raymondville",
    "sg:classifiers":[
        {
            "category":"Health Services",
            "subcategory":"Doctor",
            "type":"Services"
        }
    ],
    "sg:phone":"+1 956 689 1986",
    "sg:postcode":"78580",
    "sg:province":"TX",
    "sg:tags":[
        "physician",
        "surgeon"
    ],
    "wof:name":"Encarnacion T Silva",
    "wof:placetype":"venue"
},
  "geometry": {"coordinates":[-97.78975199999999,26.478755],"type":"Point"}
}