{
  "type": "Feature",
  "properties": {
    "iso:country":"US",
    "sg:address":"6910 S Broadway Ave",
    "sg:city":"Tyler",
    "sg:classifiers":[
        {
            "category":"Banks & Credit Unions",
            "subcategory":"Bank",
            "type":"Services"
        },
        {
            "category":"Banks & Credit Unions",
            "subcategory":"Financial Services",
            "type":"Services"
        }
    ],
    "sg:phone":"+1 903 534 8001",
    "sg:postcode":"75703",
    "sg:province":"TX",
    "sg:tags":[
        "commercial",
        "loan",
        "saving"
    ],
    "sg:website":"http://www.guarantybank.com",
    "wof:name":"BBVA Compass",
    "wof:placetype":"venue"
},
  "geometry": {"coordinates":[-95.30599599999999,32.279866],"type":"Point"}
}