{
  "type": "Feature",
  "properties": {
    "iso:country":"US",
    "sg:address":"9126 Fairhaven Ln",
    "sg:city":"Dallas",
    "sg:classifiers":[
        {
            "category":"Arts & Performance",
            "subcategory":"Theater",
            "type":"Entertainment"
        }
    ],
    "sg:phone":"+1 214 381 6760",
    "sg:postcode":"75227",
    "sg:province":"TX",
    "sg:tags":[
        "group"
    ],
    "wof:name":"Fly Trap Entertainment",
    "wof:placetype":"venue"
},
  "geometry": {"coordinates":[-96.666073,32.752195],"type":"Point"}
}