{
  "type": "Feature",
  "properties": {
    "iso:country":"US",
    "sg:address":"10112 Morning Glory Ln",
    "sg:city":"Frisco",
    "sg:classifiers":[
        {
            "category":"Building & Trades",
            "subcategory":"Construction",
            "type":"Services"
        }
    ],
    "sg:phone":"+1 972 377 7171",
    "sg:postcode":"75035",
    "sg:province":"TX",
    "sg:tags":[
        "house"
    ],
    "wof:name":"Metroplex Construction Spc Lc",
    "wof:placetype":"venue"
},
  "geometry": {"coordinates":[-96.78977500000001,33.117647],"type":"Point"}
}