{
  "type": "Feature",
  "properties": {
    "iso:country":"US",
    "sg:address":"2625 Old Denton Rd Ste 310",
    "sg:city":"Carrollton",
    "sg:classifiers":[
        {
            "category":"Restaurant",
            "type":"Food & Drink"
        }
    ],
    "sg:phone":"+1 972 242 2616",
    "sg:postcode":"75006",
    "sg:province":"TX",
    "sg:tags":[
        "korean"
    ],
    "wof:name":"To Dam Gol Tofu House",
    "wof:placetype":"venue"
},
  "geometry": {"coordinates":[-96.911638,32.986481],"type":"Point"}
}