{
  "type": "Feature",
  "properties": {
    "iso:country":"US",
    "sg:address":"7801 Woodway Dr",
    "sg:city":"Waco",
    "sg:classifiers":[
        {
            "category":"Building & Trades",
            "subcategory":"Construction",
            "type":"Services"
        }
    ],
    "sg:phone":"+1 254 772 5416",
    "sg:postcode":"76712",
    "sg:province":"TX",
    "sg:tags":[
        "contractor"
    ],
    "wof:name":"Metcalf Builders Inc",
    "wof:placetype":"venue"
},
  "geometry": {"coordinates":[-97.213447,31.500915],"type":"Point"}
}