{
  "type": "Feature",
  "properties": {
    "iso:country":"US",
    "sg:address":"13922 Van Wall St",
    "sg:city":"Houston",
    "sg:classifiers":[
        {
            "category":"Social Services",
            "subcategory":"Child Care",
            "type":"Services"
        }
    ],
    "sg:phone":"+1 713 462 3373",
    "sg:postcode":"77040",
    "sg:province":"TX",
    "sg:tags":[
        "school"
    ],
    "wof:name":"Todays Blssngs Chrstn Day Schl",
    "wof:placetype":"venue"
},
  "geometry": {"coordinates":[-95.524305,29.852852],"type":"Point"}
}