{
  "type": "Feature",
  "properties": {
    "iso:country":"US",
    "sg:address":"2862 Park Meadow Ct",
    "sg:city":"Fort Worth",
    "sg:classifiers":[
        {
            "category":"Home & Garden",
            "subcategory":"Home Furnishings",
            "type":"Retail Goods"
        },
        {
            "category":"Retail",
            "subcategory":"Auto Repair",
            "type":"Services"
        }
    ],
    "sg:phone":"+1 817 496 4520",
    "sg:postcode":"76112",
    "sg:province":"TX",
    "sg:tags":[
        "body",
        "curtain",
        "made",
        "drapery"
    ],
    "sg:website":"www.michaelsblinds.com",
    "wof:name":"Michael's Window Treatments",
    "wof:placetype":"venue"
},
  "geometry": {"coordinates":[-97.20572300000001,32.7379],"type":"Point"}
}