{
  "type": "Feature",
  "properties": {
    "iso:country":"US",
    "sg:address":"407 Duece Ct",
    "sg:city":"Harker Heights",
    "sg:classifiers":[
        {
            "category":"Shopping",
            "subcategory":"Books",
            "type":"Retail Goods"
        }
    ],
    "sg:phone":"+1 254 698 2257",
    "sg:postcode":"76548",
    "sg:province":"TX",
    "sg:tags":[
        "dealer"
    ],
    "wof:name":"Agnus Dei Books & Gifts",
    "wof:placetype":"venue"
},
  "geometry": {"coordinates":[-97.629628,31.076215],"type":"Point"}
}