{
  "type": "Feature",
  "properties": {
    "iso:country":"US",
    "sg:address":"140 Parkhouse St",
    "sg:city":"Dallas",
    "sg:classifiers":[
        {
            "category":"Communications",
            "subcategory":"Film & Video Production",
            "type":"Services"
        }
    ],
    "sg:phone":"+1 214 747 2157",
    "sg:postcode":"75207",
    "sg:province":"TX",
    "sg:tags":[
        "duplication",
        "tape"
    ],
    "sg:website":"www.showpro.com",
    "wof:name":"Showcase Duplication",
    "wof:placetype":"venue"
},
  "geometry": {"coordinates":[-96.818708,32.783421],"type":"Point"}
}