{
  "type": "Feature",
  "properties": {
    "iso:country":"US",
    "sg:address":"7555 Scott St",
    "sg:city":"Houston",
    "sg:classifiers":[
        {
            "category":"Food & Beverages",
            "subcategory":"Groceries & Convenience Stores",
            "type":"Retail Goods"
        }
    ],
    "sg:phone":"+1 713 741 8587",
    "sg:postcode":"77021",
    "sg:province":"TX",
    "wof:name":"Fuel Express",
    "wof:placetype":"venue"
},
  "geometry": {"coordinates":[-95.36601400000001,29.681637],"type":"Point"}
}