{
  "type": "Feature",
  "properties": {
    "iso:country":"US",
    "sg:address":"3918 E Jefferson St",
    "sg:city":"Grand Prairie",
    "sg:classifiers":[
        {
            "category":"Wholesale",
            "subcategory":"Auto Parts",
            "type":"Manufacturing & Wholesale Goods"
        }
    ],
    "sg:phone":"+1 972 642 4441",
    "sg:postcode":"75051",
    "sg:province":"TX",
    "sg:tags":[
        "automobile",
        "rebuilt"
    ],
    "wof:name":"Certified Auto & Truck Parts",
    "wof:placetype":"venue"
},
  "geometry": {"coordinates":[-96.940765,32.746482],"type":"Point"}
}