{
  "type": "Feature",
  "properties": {
    "iso:country":"US",
    "sg:address":"4502 Italy Ln",
    "sg:city":"Pasadena",
    "sg:classifiers":[
        {
            "category":"Structure",
            "subcategory":"Warehouse",
            "type":"Public Place"
        },
        {
            "category":"Retail",
            "subcategory":"Storage",
            "type":"Services"
        }
    ],
    "sg:phone":"+1 281 998 8869",
    "sg:postcode":"77505",
    "sg:province":"TX",
    "sg:tags":[
        "self",
        "warehouses-public-commercial"
    ],
    "wof:name":"Express Self Storage Inc",
    "wof:placetype":"venue"
},
  "geometry": {"coordinates":[-95.144785,29.64144],"type":"Point"}
}