{
  "type": "Feature",
  "properties": {
    "iso:country":"US",
    "sg:address":"1850 Bandera Rd",
    "sg:city":"San Antonio",
    "sg:classifiers":[
        {
            "category":"Retail",
            "subcategory":"Auto Repair",
            "type":"Services"
        }
    ],
    "sg:phone":"+1 210 432 1166",
    "sg:postcode":"78228",
    "sg:province":"TX",
    "sg:tags":[
        "repairing",
        "automobile",
        "exhaust"
    ],
    "wof:name":"Automotive Fitness Center",
    "wof:placetype":"venue"
},
  "geometry": {"coordinates":[-98.574128,29.471258],"type":"Point"}
}