{
  "type": "Feature",
  "properties": {
    "iso:country":"US",
    "sg:address":"8100 Southwest Fwy",
    "sg:city":"Houston",
    "sg:classifiers":[
        {
            "category":"Health Services",
            "subcategory":"Doctor",
            "type":"Services"
        }
    ],
    "sg:phone":"+1 713 772 4871",
    "sg:postcode":"77074",
    "sg:province":"TX",
    "sg:tags":[
        "medical"
    ],
    "wof:name":"Nelson Uzquiano MD",
    "wof:placetype":"venue"
},
  "geometry": {"coordinates":[-95.53022300000001,29.689331],"type":"Point"}
}