{
  "type": "Feature",
  "properties": {
    "iso:country":"US",
    "sg:address":"2021 Greenbriar Dr",
    "sg:city":"Gainesville",
    "sg:classifiers":[
        {
            "category":"Professional",
            "subcategory":"Business Services",
            "type":"Services"
        }
    ],
    "sg:phone":"+1 940 665 6910",
    "sg:postcode":"76240",
    "sg:province":"TX",
    "wof:name":"Dons Interiors",
    "wof:placetype":"venue"
},
  "geometry": {"coordinates":[-97.120786,33.632099],"type":"Point"}
}