{
  "type": "Feature",
  "properties": {
    "iso:country":"US",
    "sg:address":"441 W Mc Cart St",
    "sg:city":"Krum",
    "sg:classifiers":[
        {
            "category":"Professional",
            "subcategory":"Business Services",
            "type":"Services"
        }
    ],
    "sg:phone":"+1 940 565 1968",
    "sg:postcode":"76249",
    "sg:province":"TX",
    "wof:name":"Stewart Finley Storyteller",
    "wof:placetype":"venue"
},
  "geometry": {"coordinates":[-97.24139,33.262665],"type":"Point"}
}