{
  "type": "Feature",
  "properties": {
    "iso:country":"US",
    "sg:address":"420 Wind Wood Dr",
    "sg:city":"Lewisville",
    "sg:classifiers":[
        {
            "category":"Professional",
            "subcategory":"Management & Consulting",
            "type":"Services"
        }
    ],
    "sg:phone":"+1 972 315 3681",
    "sg:postcode":"75067",
    "sg:province":"TX",
    "sg:tags":[
        "consultant",
        "business"
    ],
    "wof:name":"Cycon Inc",
    "wof:placetype":"venue"
},
  "geometry": {"coordinates":[-97.00063900000001,33.007408],"type":"Point"}
}