{
  "type": "Feature",
  "properties": {
    "iso:country":"US",
    "sg:address":"411 Washington St",
    "sg:city":"Killeen",
    "sg:classifiers":[
        {
            "category":"Education",
            "subcategory":"Special Training",
            "type":"Public Place"
        }
    ],
    "sg:phone":"+1 254 501 3634",
    "sg:postcode":"76541",
    "sg:province":"TX",
    "sg:tags":[
        "self",
        "motivational",
        "improvement"
    ],
    "wof:name":"Let's Talk",
    "wof:placetype":"venue"
},
  "geometry": {"coordinates":[-97.738574,31.125189],"type":"Point"}
}