{
  "type": "Feature",
  "properties": {
    "iso:country":"US",
    "sg:address":"214 Lafayette St",
    "sg:city":"Pittsburg",
    "sg:classifiers":[
        {
            "category":"Professional",
            "subcategory":"Lawyer & Legal Services",
            "type":"Services"
        }
    ],
    "sg:phone":"+1 903 853 9117",
    "sg:postcode":"75686",
    "sg:province":"TX",
    "sg:tags":[
        "attorney"
    ],
    "wof:name":"Scott Ellis",
    "wof:placetype":"venue"
},
  "geometry": {"coordinates":[-94.96419899999999,32.993735],"type":"Point"}
}