{
  "type": "Feature",
  "properties": {
    "iso:country":"US",
    "sg:address":"302 Richmond Ct",
    "sg:city":"Laredo",
    "sg:classifiers":[
        {
            "category":"Professional",
            "type":"Services"
        }
    ],
    "sg:phone":"+1 956 724 3961",
    "sg:postcode":"78045",
    "sg:province":"TX",
    "wof:name":"Ig Truck Line Inc",
    "wof:placetype":"venue"
},
  "geometry": {"coordinates":[-99.488192,27.571543],"type":"Point"}
}