{
  "type": "Feature",
  "properties": {
    "iso:country":"US",
    "sg:address":"2410 Mozelle Ln",
    "sg:city":"Austin",
    "sg:classifiers":[
        {
            "category":"Professional",
            "subcategory":"Management & Consulting",
            "type":"Services"
        }
    ],
    "sg:phone":"+1 512 282 6416",
    "sg:postcode":"78744",
    "sg:province":"TX",
    "wof:name":"Miramar Enterprises",
    "wof:placetype":"venue"
},
  "geometry": {"coordinates":[-97.772486,30.166517],"type":"Point"}
}