{
  "type": "Feature",
  "properties": {
    "iso:country":"US",
    "sg:address":"Willowchase Ctr",
    "sg:city":"Houston",
    "sg:classifiers":[
        {
            "category":"Shopping",
            "subcategory":"Crafts & Fabrics",
            "type":"Retail Goods"
        }
    ],
    "sg:phone":"+1 281 469 6162",
    "sg:postcode":"77040",
    "sg:province":"TX",
    "sg:tags":[
        "store"
    ],
    "wof:name":"Jo-Ann Fabrics and Crafts",
    "wof:placetype":"venue"
},
  "geometry": {"coordinates":[-95.51460299999999,29.871799],"type":"Point"}
}