{
  "type": "Feature",
  "properties": {
    "iso:country":"US",
    "sg:address":"5903 Glenmont Dr",
    "sg:city":"Houston",
    "sg:classifiers":[
        {
            "category":"Building & Trades",
            "subcategory":"Construction",
            "type":"Services"
        }
    ],
    "sg:phone":"+1 713 432 7138",
    "sg:postcode":"77081",
    "sg:province":"TX",
    "sg:tags":[
        "hanging",
        "contractor"
    ],
    "wof:name":"Antonios General Painting Co",
    "wof:placetype":"venue"
},
  "geometry": {"coordinates":[-95.486603,29.719961],"type":"Point"}
}