{
  "type": "Feature",
  "properties": {
    "iso:country":"US",
    "sg:address":"235 Danube Pass",
    "sg:city":"Boerne",
    "sg:classifiers":[
        {
            "category":"Professional",
            "subcategory":"Lawyer & Legal Services",
            "type":"Services"
        }
    ],
    "sg:phone":"+1 830 336 4195",
    "sg:postcode":"78006",
    "sg:province":"TX",
    "sg:tags":[
        "attorney"
    ],
    "wof:name":"Judy J Jetelina Atty",
    "wof:placetype":"venue"
},
  "geometry": {"coordinates":[-98.565258,29.809005],"type":"Point"}
}