{
  "type": "Feature",
  "properties": {
    "iso:country":"US",
    "sg:address":"4356 US Hwy 59",
    "sg:city":"Lufkin",
    "sg:classifiers":[
        {
            "category":"Personal",
            "subcategory":"Barber",
            "type":"Services"
        }
    ],
    "sg:phone":"+1 936 634 7164",
    "sg:postcode":"75901",
    "sg:province":"TX",
    "wof:name":"A J's Barber Shop",
    "wof:placetype":"venue"
},
  "geometry": {"coordinates":[-94.73555399999999,31.277544],"type":"Point"}
}