{
  "type": "Feature",
  "properties": {
    "iso:country":"US",
    "sg:address":"2213 Harwood Rd",
    "sg:city":"Bedford",
    "sg:classifiers":[
        {
            "category":"Health Services",
            "subcategory":"Dentist",
            "type":"Services"
        }
    ],
    "sg:phone":"+1 817 354 9999",
    "sg:postcode":"76021",
    "sg:province":"TX",
    "sg:tags":[
        "dentists-cosmetic",
        "dental",
        "dentists-pediatric",
        "clinic",
        "dentistry",
        "implant",
        "dentists-implantology"
    ],
    "sg:website":"http://paulgdavisdds.com",
    "wof:name":"Davis Paul G D.D.S. P.A.",
    "wof:placetype":"venue"
},
  "geometry": {"coordinates":[-97.131604,32.852111],"type":"Point"}
}