{
  "type": "Feature",
  "properties": {
    "iso:country":"US",
    "sg:address":"8103 Seminary Ridge Dr",
    "sg:city":"Austin",
    "sg:classifiers":[
        {
            "category":"Professional",
            "subcategory":"Management & Consulting",
            "type":"Services"
        }
    ],
    "sg:phone":"+1 512 707 2034",
    "sg:postcode":"78745",
    "sg:province":"TX",
    "sg:tags":[
        "consultant",
        "educational",
        "business"
    ],
    "wof:name":"Evisions Of Austin",
    "wof:placetype":"venue"
},
  "geometry": {"coordinates":[-97.821257,30.195939],"type":"Point"}
}