{
  "type": "Feature",
  "properties": {
    "iso:country":"US",
    "sg:address":"1300 Patricia",
    "sg:city":"San Antonio",
    "sg:classifiers":[
        {
            "category":"Real Estate",
            "subcategory":"Real Estate Operator",
            "type":"Services"
        }
    ],
    "sg:phone":"+1 210 349 9626",
    "sg:postcode":"78213",
    "sg:province":"TX",
    "sg:tags":[
        "building",
        "apartment"
    ],
    "wof:name":"Aimco",
    "wof:placetype":"venue"
},
  "geometry": {"coordinates":[-98.51718200000001,29.547682],"type":"Point"}
}