{
  "type": "Feature",
  "properties": {
    "iso:country":"US",
    "sg:address":"615 Landa St",
    "sg:city":"New Braunfels",
    "sg:classifiers":[
        {
            "category":"Retail",
            "subcategory":"Funeral Services",
            "type":"Services"
        }
    ],
    "sg:phone":"+1 830 625 2349",
    "sg:postcode":"78130",
    "sg:province":"TX",
    "sg:tags":[
        "director"
    ],
    "wof:name":"Zoeller Funeral Home",
    "wof:placetype":"venue"
},
  "geometry": {"coordinates":[-98.13159899999999,29.705239],"type":"Point"}
}