{
  "type": "Feature",
  "properties": {
    "iso:country":"US",
    "sg:address":"2611 Eisenhauer Rd",
    "sg:city":"San Antonio",
    "sg:classifiers":[
        {
            "category":"Organizations",
            "subcategory":"Community Association",
            "type":"Services"
        }
    ],
    "sg:phone":"+1 210 828 0156",
    "sg:postcode":"78209",
    "sg:province":"TX",
    "sg:tags":[
        "home"
    ],
    "wof:name":"Farmington Cmmons Hmwners Assn",
    "wof:placetype":"venue"
},
  "geometry": {"coordinates":[-98.45170400000001,29.495817],"type":"Point"}
}