{
  "type": "Feature",
  "properties": {
    "iso:country":"US",
    "sg:address":"5418 Forest Trails Dr",
    "sg:city":"Houston",
    "sg:classifiers":[
        {
            "category":"Retail",
            "subcategory":"Repair Shop",
            "type":"Services"
        }
    ],
    "sg:phone":"+1 281 859 8810",
    "sg:postcode":"77084",
    "sg:province":"TX",
    "wof:name":"Arise & Shine Spa Cleaning",
    "wof:placetype":"venue"
},
  "geometry": {"coordinates":[-95.681337,29.852461],"type":"Point"}
}