{
  "type": "Feature",
  "properties": {
    "iso:country":"US",
    "sg:address":"1808 W Expy 83",
    "sg:city":"Penitas",
    "sg:classifiers":[
        {
            "category":"Professional",
            "subcategory":"Advertising",
            "type":"Services"
        }
    ],
    "sg:phone":"+1 956 519 8609",
    "sg:postcode":"78501",
    "sg:province":"TX",
    "sg:tags":[
        "mailing",
        "shipping"
    ],
    "wof:name":"Mailing Services & More",
    "wof:placetype":"venue"
},
  "geometry": {"coordinates":[-98.241573,26.191514],"type":"Point"}
}