{
  "type": "Feature",
  "properties": {
    "iso:country":"US",
    "sg:address":"1919 Briar Oaks at San Felipe",
    "sg:city":"Houston",
    "sg:classifiers":[
        {
            "category":"Bars & Pubs",
            "type":"Food & Drink"
        },
        {
            "category":"Bars & Pubs",
            "subcategory":"Lounge",
            "type":"Food & Drink"
        },
        {
            "category":"Bars & Pubs",
            "subcategory":"Wine Bar",
            "type":"Food & Drink"
        },
        {
            "category":"Recreation",
            "subcategory":"Dance Hall",
            "type":"Entertainment"
        }
    ],
    "sg:phone":"+1 713 403 2631",
    "sg:postcode":"77027",
    "sg:province":"TX",
    "sg:tags":[
        "club"
    ],
    "sg:website":"www.remingtonrestaurant.com",
    "wof:name":"Remington Bar",
    "wof:placetype":"venue"
},
  "geometry": {"coordinates":[-95.450937,29.747424],"type":"Point"}
}