{
  "type": "Feature",
  "properties": {
    "iso:country":"US",
    "sg:address":"409 N Guadalupe St",
    "sg:city":"Seguin",
    "sg:classifiers":[
        {
            "category":"Retail",
            "subcategory":"Auto Repair",
            "type":"Services"
        }
    ],
    "sg:phone":"+1 830 303 3180",
    "sg:postcode":"78155",
    "sg:province":"TX",
    "sg:tags":[
        "general"
    ],
    "wof:name":"Johns Auto Clinic",
    "wof:placetype":"venue"
},
  "geometry": {"coordinates":[-97.969476,29.571665],"type":"Point"}
}