{
  "type": "Feature",
  "properties": {
    "iso:country":"US",
    "sg:address":"3311 Preston Rd",
    "sg:city":"Frisco",
    "sg:classifiers":[
        {
            "category":"Shopping",
            "subcategory":"Photographic Equipment",
            "type":"Retail Goods"
        }
    ],
    "sg:phone":"+1 972 668 7990",
    "sg:postcode":"75034",
    "sg:province":"TX",
    "sg:tags":[
        "supply"
    ],
    "wof:name":"Wolf Camera & Video",
    "wof:placetype":"venue"
},
  "geometry": {"coordinates":[-96.805831,33.105567],"type":"Point"}
}