{
  "type": "Feature",
  "properties": {
    "iso:country":"US",
    "sg:address":"110 N 25 Mile Ave",
    "sg:city":"Hereford",
    "sg:classifiers":[
        {
            "category":"Social Services",
            "type":"Services"
        }
    ],
    "sg:phone":"+1 806 364 7482",
    "sg:postcode":"79045",
    "sg:province":"TX",
    "wof:name":"Carenet Pregnancy Center He",
    "wof:placetype":"venue"
},
  "geometry": {"coordinates":[-102.40553300000001,34.824688],"type":"Point"}
}