{
  "type": "Feature",
  "properties": {
    "iso:country":"US",
    "sg:address":"3333 W Alabama St",
    "sg:city":"Houston",
    "sg:classifiers":[
        {
            "category":"Professional",
            "subcategory":"Lawyer & Legal Services",
            "type":"Services"
        }
    ],
    "sg:phone":"+1 713 529 2992",
    "sg:postcode":"77098",
    "sg:province":"TX",
    "wof:name":"January William H Atty",
    "wof:placetype":"venue"
},
  "geometry": {"coordinates":[-95.427538,29.738335],"type":"Point"}
}