{
  "type": "Feature",
  "properties": {
    "iso:country":"US",
    "sg:address":"4974 Highland Ave",
    "sg:city":"Beaumont",
    "sg:classifiers":[
        {
            "category":"Retail",
            "subcategory":"Repair Shop",
            "type":"Services"
        }
    ],
    "sg:phone":"+1 409 835 1434",
    "sg:postcode":"77705",
    "sg:province":"TX",
    "sg:tags":[
        "sharpening"
    ],
    "wof:name":"Cutting Edge",
    "wof:placetype":"venue"
},
  "geometry": {"coordinates":[-94.08537699999999,30.037042],"type":"Point"}
}