{
  "type": "Feature",
  "properties": {
    "iso:country":"US",
    "sg:address":"5614 Lemmon Ave",
    "sg:city":"Dallas",
    "sg:classifiers":[
        {
            "category":"Retail",
            "subcategory":"Laundry & Dry Cleaning",
            "type":"Services"
        }
    ],
    "sg:phone":"+1 214 559 8988",
    "sg:postcode":"75209",
    "sg:province":"TX",
    "wof:name":"X-Press Cleaners & Laundry",
    "wof:placetype":"venue"
},
  "geometry": {"coordinates":[-96.824501,32.828499],"type":"Point"}
}