{
  "type": "Feature",
  "properties": {
    "iso:country":"US",
    "sg:address":"900 Main St",
    "sg:city":"Marble Falls",
    "sg:classifiers":[
        {
            "category":"Building & Trades",
            "subcategory":"Construction",
            "type":"Services"
        }
    ],
    "sg:phone":"+1 830 798 1818",
    "sg:postcode":"78654",
    "sg:province":"TX",
    "sg:tags":[
        "home",
        "builder"
    ],
    "wof:name":"Classic Constructors Inc",
    "wof:placetype":"venue"
},
  "geometry": {"coordinates":[-98.42003099999999,30.103161],"type":"Point"}
}