{
  "type": "Feature",
  "properties": {
    "iso:country":"US",
    "sg:address":"11007 Atwell Dr",
    "sg:city":"Houston",
    "sg:classifiers":[
        {
            "category":"Professional",
            "subcategory":"Lawyer & Legal Services",
            "type":"Services"
        }
    ],
    "sg:phone":"+1 713 721 8501",
    "sg:postcode":"77096",
    "sg:province":"TX",
    "wof:name":"Brink and Associates Attorney At Law",
    "wof:placetype":"venue"
},
  "geometry": {"coordinates":[-95.482101,29.6607],"type":"Point"}
}