{
  "type": "Feature",
  "properties": {
    "iso:country":"US",
    "sg:address":"809 S Midkiff Rd",
    "sg:city":"Midland",
    "sg:classifiers":[
        {
            "category":"Food & Beverages",
            "subcategory":"Groceries & Convenience Stores",
            "type":"Retail Goods"
        }
    ],
    "sg:phone":"+1 432 694 0801",
    "sg:postcode":"79701",
    "sg:province":"TX",
    "sg:tags":[
        "station",
        "gasoline"
    ],
    "wof:name":"7-Eleven",
    "wof:placetype":"venue"
},
  "geometry": {"coordinates":[-102.112712,31.982126],"type":"Point"}
}