{
  "type": "Feature",
  "properties": {
    "iso:country":"US",
    "sg:address":"7887 US Hwy 87",
    "sg:city":"San Angelo",
    "sg:classifiers":[
        {
            "category":"Education",
            "subcategory":"College",
            "type":"Public Place"
        }
    ],
    "sg:phone":"+1 325 653 4576",
    "sg:postcode":"76901",
    "sg:province":"TX",
    "wof:name":"San Angelo AG RES & EXT Ctr",
    "wof:placetype":"venue"
},
  "geometry": {"coordinates":[-100.519667,31.553243],"type":"Point"}
}