{
  "type": "Feature",
  "properties": {
    "iso:country":"US",
    "sg:address":"302 S Front St",
    "sg:city":"Cotulla",
    "sg:classifiers":[
        {
            "category":"Farming",
            "subcategory":"Livestock Farm",
            "type":"Manufacturing & Wholesale Goods"
        }
    ],
    "sg:phone":"+1 830 879 3122",
    "sg:postcode":"78014",
    "sg:province":"TX",
    "sg:tags":[
        "ranch"
    ],
    "wof:name":"Ranch Equip & Hardware Inc",
    "wof:placetype":"venue"
},
  "geometry": {"coordinates":[-99.233468,28.434098],"type":"Point"}
}