{
  "type": "Feature",
  "properties": {
    "iso:country":"US",
    "sg:address":"213 Neumann Dr",
    "sg:city":"Marlin",
    "sg:classifiers":[
        {
            "category":"Shopping",
            "subcategory":"Hobbies, Toys, & Games",
            "type":"Retail Goods"
        }
    ],
    "sg:phone":"+1 254 883 3495",
    "sg:postcode":"76661",
    "sg:province":"TX",
    "wof:name":"Marie Stowe",
    "wof:placetype":"venue"
},
  "geometry": {"coordinates":[-96.896596,31.321753],"type":"Point"}
}