{
  "type": "Feature",
  "properties": {
    "iso:country":"US",
    "sg:address":"5235 Heatherbloom Dr",
    "sg:city":"Houston",
    "sg:classifiers":[
        {
            "category":"Professional",
            "subcategory":"Accounting & Tax Preparation",
            "type":"Services"
        }
    ],
    "sg:phone":"+1 713 433 1600",
    "sg:postcode":"77045",
    "sg:province":"TX",
    "wof:name":"William B Phillips",
    "wof:placetype":"venue"
},
  "geometry": {"coordinates":[-95.46063700000001,29.622489],"type":"Point"}
}