{
  "type": "Feature",
  "properties": {
    "iso:country":"US",
    "sg:address":"2117 Tishomingo Trl",
    "sg:city":"Austin",
    "sg:classifiers":[
        {
            "category":"Building & Trades",
            "subcategory":"Electrical",
            "type":"Services"
        }
    ],
    "sg:phone":"+1 512 266 9048",
    "sg:postcode":"78734",
    "sg:province":"TX",
    "sg:tags":[
        "electric",
        "contractor"
    ],
    "wof:name":"Voltex Electric Svc",
    "wof:placetype":"venue"
},
  "geometry": {"coordinates":[-97.931905,30.379338],"type":"Point"}
}