{
  "type": "Feature",
  "properties": {
    "iso:country":"US",
    "sg:address":"1803 W 5th St",
    "sg:city":"Clifton",
    "sg:classifiers":[
        {
            "category":"Shopping",
            "subcategory":"Florist",
            "type":"Retail Goods"
        }
    ],
    "sg:phone":"+1 254 675 3112",
    "sg:postcode":"76634",
    "sg:province":"TX",
    "wof:name":"Clifton Floral Co",
    "wof:placetype":"venue"
},
  "geometry": {"coordinates":[-97.588042,31.778136],"type":"Point"}
}