{
  "type": "Feature",
  "properties": {
    "iso:country":"US",
    "sg:address":"813 S Locust St",
    "sg:city":"Denton",
    "sg:classifiers":[
        {
            "category":"Retail",
            "subcategory":"Auto Repair",
            "type":"Services"
        }
    ],
    "sg:phone":"+1 940 382 2116",
    "sg:postcode":"76201",
    "sg:province":"TX",
    "sg:tags":[
        "automobile",
        "inspection"
    ],
    "wof:name":"Sticker Station",
    "wof:placetype":"venue"
},
  "geometry": {"coordinates":[-97.132447,33.207688],"type":"Point"}
}