{
  "type": "Feature",
  "properties": {
    "iso:country":"US",
    "sg:address":"3225 Woodland Park Dr",
    "sg:city":"Houston",
    "sg:classifiers":[
        {
            "category":"Wholesale",
            "subcategory":"Petroleum",
            "type":"Manufacturing & Wholesale Goods"
        }
    ],
    "sg:phone":"+1 281 759 3190",
    "sg:postcode":"77082",
    "sg:province":"TX",
    "sg:tags":[
        "pipe",
        "line",
        "company"
    ],
    "wof:name":"EOTT Energy",
    "wof:placetype":"venue"
},
  "geometry": {"coordinates":[-95.580049,29.728777],"type":"Point"}
}