{
  "type": "Feature",
  "properties": {
    "iso:country":"US",
    "sg:address":"4776 Co Rd 473",
    "sg:city":"Hermleigh",
    "sg:classifiers":[
        {
            "category":"Building & Trades",
            "subcategory":"Construction",
            "type":"Services"
        }
    ],
    "sg:phone":"+1 325 573 8710",
    "sg:postcode":"79526",
    "sg:province":"TX",
    "sg:tags":[
        "water",
        "well",
        "drilling"
    ],
    "wof:name":"Bennie Marricle Well Service",
    "wof:placetype":"venue"
},
  "geometry": {"coordinates":[-100.803697,32.661672],"type":"Point"}
}