{
  "type": "Feature",
  "properties": {
    "iso:country":"US",
    "sg:address":"68 Lost Meadow Trl",
    "sg:city":"The Hills",
    "sg:classifiers":[
        {
            "category":"Professional",
            "subcategory":"Employment Agencies",
            "type":"Services"
        }
    ],
    "sg:phone":"+1 512 336 5406",
    "sg:postcode":"78738",
    "sg:province":"TX",
    "sg:tags":[
        "consultant",
        "search",
        "executive"
    ],
    "sg:website":"www.dougstoneassociates.com",
    "wof:name":"Doug Stone Assoc",
    "wof:placetype":"venue"
},
  "geometry": {"coordinates":[-97.98035299999999,30.353038],"type":"Point"}
}