{
  "type": "Feature",
  "properties": {
    "iso:country":"US",
    "sg:address":"1108 Albrad Ave",
    "sg:city":"Pharr",
    "sg:classifiers":[
        {
            "category":"Building & Trades",
            "subcategory":"Equipment Rental",
            "type":"Services"
        }
    ],
    "sg:phone":"+1 956 702 0435",
    "sg:postcode":"78577",
    "sg:province":"TX",
    "sg:tags":[
        "field",
        "oil"
    ],
    "wof:name":"National Oilwell",
    "wof:placetype":"venue"
},
  "geometry": {"coordinates":[-98.198167,26.207945],"type":"Point"}
}