{
  "type": "Feature",
  "properties": {
    "iso:country":"US",
    "sg:address":"10501 Goodman St",
    "sg:city":"El Paso",
    "sg:classifiers":[
        {
            "category":"Manufacturing",
            "subcategory":"Furniture",
            "type":"Manufacturing & Wholesale Goods"
        }
    ],
    "sg:phone":"+1 915 821 1769",
    "sg:postcode":"79924",
    "sg:province":"TX",
    "sg:tags":[
        "mfg"
    ],
    "wof:name":"Jimmies Merchandise & No",
    "wof:placetype":"venue"
},
  "geometry": {"coordinates":[-106.414496,31.920666],"type":"Point"}
}