{
  "type": "Feature",
  "properties": {
    "iso:country":"US",
    "sg:address":"1013 E Court House St",
    "sg:city":"Cuero",
    "sg:classifiers":[
        {
            "category":"Social Services",
            "subcategory":"Adult Care",
            "type":"Services"
        }
    ],
    "sg:phone":"+1 361 275 9182",
    "sg:postcode":"77954",
    "sg:province":"TX",
    "sg:tags":[
        "organization",
        "senior",
        "citizen"
    ],
    "wof:name":"Dewitt County Senior Citizens",
    "wof:placetype":"venue"
},
  "geometry": {"coordinates":[-97.193045,29.044146],"type":"Point"}
}