{
  "type": "Feature",
  "properties": {
    "iso:country":"US",
    "sg:address":"350 Oaks Trl",
    "sg:city":"Garland",
    "sg:classifiers":[
        {
            "category":"Building & Trades",
            "subcategory":"Plumbing",
            "type":"Services"
        }
    ],
    "sg:phone":"+1 972 289 3903",
    "sg:postcode":"75043",
    "sg:province":"TX",
    "sg:tags":[
        "conditioning",
        "air",
        "system",
        "contractor"
    ],
    "wof:name":"C & M Maintenance",
    "wof:placetype":"venue"
},
  "geometry": {"coordinates":[-96.57054100000001,32.848307],"type":"Point"}
}