{
  "type": "Feature",
  "properties": {
    "iso:country":"US",
    "sg:address":"1600 Gano St",
    "sg:city":"Dallas",
    "sg:classifiers":[
        {
            "category":"Building & Trades",
            "subcategory":"Plumbing",
            "type":"Services"
        }
    ],
    "sg:phone":"+1 214 421 7773",
    "sg:postcode":"75215",
    "sg:province":"TX",
    "sg:tags":[
        "mechanical",
        "contractor"
    ],
    "wof:name":"Farrar Mechanical Contractors",
    "wof:placetype":"venue"
},
  "geometry": {"coordinates":[-96.789214,32.771516],"type":"Point"}
}