{
  "type": "Feature",
  "properties": {
    "iso:country":"US",
    "sg:address":"7737 Skolout St",
    "sg:city":"San Antonio",
    "sg:classifiers":[
        {
            "category":"Real Estate",
            "subcategory":"Real Estate Operator",
            "type":"Services"
        }
    ],
    "sg:phone":"+1 210 673 8120",
    "sg:postcode":"78227",
    "sg:province":"TX",
    "sg:tags":[
        "building",
        "apartment"
    ],
    "wof:name":"Stepping Stone Apartments Inc",
    "wof:placetype":"venue"
},
  "geometry": {"coordinates":[-98.64226600000001,29.400555],"type":"Point"}
}