{
  "type": "Feature",
  "properties": {
    "iso:country":"US",
    "sg:address":"3550 W Camp Wisdom Rd",
    "sg:city":"Dallas",
    "sg:classifiers":[
        {
            "category":"Shopping",
            "subcategory":"Optician",
            "type":"Retail Goods"
        }
    ],
    "sg:phone":"+1 972 296 7340",
    "sg:postcode":"75237",
    "sg:province":"TX",
    "sg:tags":[
        "eyewear"
    ],
    "wof:name":"Sunglass Hut",
    "wof:placetype":"venue"
},
  "geometry": {"coordinates":[-96.877729,32.662161],"type":"Point"}
}