{
  "type": "Feature",
  "properties": {
    "iso:country":"US",
    "sg:address":"520 W Expressway 83",
    "sg:city":"Donna",
    "sg:classifiers":[
        {
            "category":"Utilities",
            "subcategory":"Recycling",
            "type":"Services"
        }
    ],
    "sg:phone":"+1 956 461 5944",
    "sg:postcode":"78537",
    "sg:province":"TX",
    "wof:name":"W. Silver Recycling, Inc.",
    "wof:placetype":"venue"
},
  "geometry": {"coordinates":[-98.051525,26.181909],"type":"Point"}
}