{
  "type": "Feature",
  "properties": {
    "iso:country":"US",
    "sg:address":"3816 Andrews Hwy",
    "sg:city":"Odessa",
    "sg:classifiers":[
        {
            "category":"Restaurant",
            "type":"Food & Drink"
        }
    ],
    "sg:phone":"+1 432 366 6606",
    "sg:postcode":"79762",
    "sg:province":"TX",
    "sg:tags":[
        "eating"
    ],
    "wof:name":"MI Abuelos Restaurant",
    "wof:placetype":"venue"
},
  "geometry": {"coordinates":[-102.384801,31.882293],"type":"Point"}
}