{
  "type": "Feature",
  "properties": {
    "iso:country":"US",
    "sg:address":"200 Co Rd 616",
    "sg:city":"Brownwood",
    "sg:classifiers":[
        {
            "category":"Health Services",
            "subcategory":"Nursing And Care Facility",
            "type":"Services"
        }
    ],
    "sg:phone":"+1 325 646 5521",
    "sg:postcode":"76802",
    "sg:province":"TX",
    "sg:tags":[
        "operator",
        "home",
        "skilled",
        "dwelling",
        "convalescent"
    ],
    "wof:name":"CARE Inc Nursing Center",
    "wof:placetype":"venue"
},
  "geometry": {"coordinates":[-98.96719,31.747563],"type":"Point"}
}