{
  "type": "Feature",
  "properties": {
    "iso:country":"US",
    "sg:address":"4802 Chrystell Ln",
    "sg:city":"Houston",
    "sg:classifiers":[
        {
            "category":"Education",
            "subcategory":"School",
            "type":"Public Place"
        }
    ],
    "sg:phone":"+1 713 613 2542",
    "sg:postcode":"77092",
    "sg:province":"TX",
    "sg:tags":[
        "high",
        "middle",
        "elementary"
    ],
    "sg:website":"www.houstonisd.org",
    "wof:name":"Houston Independent School District",
    "wof:placetype":"venue"
},
  "geometry": {"coordinates":[-95.461743,29.838587],"type":"Point"}
}