{
  "type": "Feature",
  "properties": {
    "iso:country":"US",
    "sg:address":"13637 N Central Expy",
    "sg:city":"Dallas",
    "sg:classifiers":[
        {
            "category":"Home & Garden",
            "subcategory":"Building Materials",
            "type":"Retail Goods"
        }
    ],
    "sg:phone":"+1 972 231 1133",
    "sg:postcode":"75243",
    "sg:province":"TX",
    "sg:tags":[
        "downspouts",
        "gutter"
    ],
    "sg:website":"http://www.totalgutter.com",
    "wof:name":"Total Gutter Company",
    "wof:placetype":"venue"
},
  "geometry": {"coordinates":[-96.754401,32.933729],"type":"Point"}
}