{
  "type": "Feature",
  "properties": {
    "iso:country":"US",
    "sg:address":"805 State Hwy 34",
    "sg:city":"Ennis",
    "sg:classifiers":[
        {
            "category":"Building & Trades",
            "subcategory":"Plumbing",
            "type":"Services"
        }
    ],
    "sg:phone":"+1 972 878 7370",
    "sg:postcode":"75119",
    "sg:province":"TX",
    "sg:tags":[
        "mechanical",
        "contractor"
    ],
    "wof:name":"Hamil & Harrison Mechanical",
    "wof:placetype":"venue"
},
  "geometry": {"coordinates":[-96.626957,32.307663],"type":"Point"}
}