{
  "type": "Feature",
  "properties": {
    "iso:country":"US",
    "sg:address":"403 Pinafore St",
    "sg:city":"Buda",
    "sg:classifiers":[
        {
            "category":"Shopping",
            "subcategory":"Hobbies, Toys, & Games",
            "type":"Retail Goods"
        }
    ],
    "sg:phone":"+1 512 480 4039",
    "sg:postcode":"78610",
    "sg:province":"TX",
    "wof:name":"Csa Seminars",
    "wof:placetype":"venue"
},
  "geometry": {"coordinates":[-97.84075799999999,30.072778],"type":"Point"}
}