{
  "type": "Feature",
  "properties": {
    "iso:country":"US",
    "sg:address":"6600 Hillcroft St",
    "sg:city":"Houston",
    "sg:classifiers":[
        {
            "category":"Professional",
            "type":"Services"
        }
    ],
    "sg:phone":"+1 713 269 9624",
    "sg:postcode":"77081",
    "sg:province":"TX",
    "wof:name":"Silver Line",
    "wof:placetype":"venue"
},
  "geometry": {"coordinates":[-95.49315799999999,29.707283],"type":"Point"}
}