{
  "type": "Feature",
  "properties": {
    "iso:country":"US",
    "sg:address":"3005 Bee Caves Rd",
    "sg:city":"Austin",
    "sg:classifiers":[
        {
            "category":"Building & Trades",
            "subcategory":"Plumbing",
            "type":"Services"
        }
    ],
    "sg:phone":"+1 512 251 8747",
    "sg:postcode":"78746",
    "sg:province":"TX",
    "sg:tags":[
        "conditioning",
        "air",
        "system",
        "contractor"
    ],
    "wof:name":"Craco Air Conditioning & Heat",
    "wof:placetype":"venue"
},
  "geometry": {"coordinates":[-97.795233,30.271519],"type":"Point"}
}