{
  "type": "Feature",
  "properties": {
    "iso:country":"US",
    "sg:address":"3420 Chaffin St",
    "sg:city":"Houston",
    "sg:classifiers":[
        {
            "category":"Freight",
            "type":"Transportation"
        }
    ],
    "sg:phone":"+1 713 640 1850",
    "sg:postcode":"77087",
    "sg:province":"TX",
    "sg:tags":[
        "operator",
        "local",
        "trucking"
    ],
    "wof:name":"Emilios Trucking",
    "wof:placetype":"venue"
},
  "geometry": {"coordinates":[-95.30443200000001,29.690353],"type":"Point"}
}