{
  "type": "Feature",
  "properties": {
    "iso:country":"US",
    "sg:address":"5812 S I- 35 E",
    "sg:city":"Denton",
    "sg:classifiers":[
        {
            "category":"Restaurant",
            "type":"Food & Drink"
        }
    ],
    "sg:phone":"+1 940 387 3500",
    "sg:postcode":"76210",
    "sg:province":"TX",
    "sg:tags":[
        "eating"
    ],
    "wof:name":"El Chico Restaurant",
    "wof:placetype":"venue"
},
  "geometry": {"coordinates":[-97.064142,33.154939],"type":"Point"}
}