{
  "type": "Feature",
  "properties": {
    "iso:country":"US",
    "sg:address":"2934 Pershing Dr",
    "sg:city":"El Paso",
    "sg:classifiers":[
        {
            "category":"Food & Beverages",
            "subcategory":"Groceries & Convenience Stores",
            "type":"Retail Goods"
        }
    ],
    "sg:phone":"+1 915 564 3710",
    "sg:postcode":"79903",
    "sg:province":"TX",
    "sg:tags":[
        "grocer"
    ],
    "wof:name":"WIO Market",
    "wof:placetype":"venue"
},
  "geometry": {"coordinates":[-106.461108,31.78463],"type":"Point"}
}