{
  "type": "Feature",
  "properties": {
    "iso:country":"US",
    "sg:address":"8669 Co Rd 351",
    "sg:city":"Dublin",
    "sg:classifiers":[
        {
            "category":"Professional",
            "subcategory":"Business Services",
            "type":"Services"
        }
    ],
    "sg:phone":"+1 254 445 2561",
    "sg:postcode":"76446",
    "sg:province":"TX",
    "wof:name":"Dallas Fort Worth Labrador Ret",
    "wof:placetype":"venue"
},
  "geometry": {"coordinates":[-98.309595,32.151592],"type":"Point"}
}