{
  "type": "Feature",
  "properties": {
    "iso:country":"US",
    "sg:address":"2722 Hemphill St",
    "sg:city":"Fort Worth",
    "sg:classifiers":[
        {
            "category":"Building & Trades",
            "subcategory":"Construction",
            "type":"Services"
        }
    ],
    "sg:phone":"+1 817 320 6920",
    "sg:postcode":"76110",
    "sg:province":"TX",
    "sg:tags":[
        "contractor"
    ],
    "wof:name":"Ernest E Dominguez",
    "wof:placetype":"venue"
},
  "geometry": {"coordinates":[-97.331684,32.711755],"type":"Point"}
}