{
  "type": "Feature",
  "properties": {
    "iso:country":"US",
    "sg:address":"826 Burleson St",
    "sg:city":"Jacksonville",
    "sg:classifiers":[
        {
            "category":"Retail",
            "subcategory":"Repair Shop",
            "type":"Services"
        }
    ],
    "sg:phone":"+1 903 586 2602",
    "sg:postcode":"75766",
    "sg:province":"TX",
    "sg:tags":[
        "repairing",
        "piano",
        "refinishing"
    ],
    "wof:name":"Jerry's Piano Svc",
    "wof:placetype":"venue"
},
  "geometry": {"coordinates":[-95.282314,31.957027],"type":"Point"}
}