{
  "type": "Feature",
  "properties": {
    "iso:country":"US",
    "sg:address":"20829 Sunshine Ln",
    "sg:city":"Spring",
    "sg:classifiers":[
        {
            "category":"Organizations",
            "subcategory":"Non-profit Organization",
            "type":"Services"
        }
    ],
    "sg:phone":"+1 281 288 0809",
    "sg:postcode":"77388",
    "sg:province":"TX",
    "sg:tags":[
        "information",
        "alcoholism",
        "treatment"
    ],
    "wof:name":"Alcoholics Anonymous W Spring",
    "wof:placetype":"venue"
},
  "geometry": {"coordinates":[-95.44108799999999,30.066354],"type":"Point"}
}