{
  "type": "Feature",
  "properties": {
    "iso:country":"US",
    "sg:address":"4304 Tate Springs Rd",
    "sg:city":"Arlington",
    "sg:classifiers":[
        {
            "category":"Real Estate",
            "subcategory":"Surveying",
            "type":"Services"
        }
    ],
    "sg:phone":"+1 817 478 6802",
    "sg:postcode":"76016",
    "sg:province":"TX",
    "wof:name":"Als Land Surveying Inc",
    "wof:placetype":"venue"
},
  "geometry": {"coordinates":[-97.193591,32.679634],"type":"Point"}
}