{
  "type": "Feature",
  "properties": {
    "iso:country":"US",
    "sg:address":"1101 Texas Ave S",
    "sg:city":"College Station",
    "sg:classifiers":[
        {
            "category":"Government",
            "subcategory":"Office",
            "type":"Public Place"
        }
    ],
    "sg:phone":"+1 979 764 3753",
    "sg:postcode":"77840",
    "sg:province":"TX",
    "sg:tags":[
        "city",
        "program",
        "adm"
    ],
    "wof:name":"College Station Economic Dev",
    "wof:placetype":"venue"
},
  "geometry": {"coordinates":[-96.324924,30.619725],"type":"Point"}
}