{
  "type": "Feature",
  "properties": {
    "iso:country":"US",
    "sg:address":"2827 Rimrock Dr",
    "sg:city":"Missouri City",
    "sg:classifiers":[
        {
            "category":"Professional",
            "subcategory":"Management & Consulting",
            "type":"Services"
        }
    ],
    "sg:phone":"+1 281 403 0062",
    "sg:postcode":"77459",
    "sg:province":"TX",
    "sg:tags":[
        "business"
    ],
    "wof:name":"Boundless Project Strategies",
    "wof:placetype":"venue"
},
  "geometry": {"coordinates":[-95.577303,29.575822],"type":"Point"}
}