{
  "type": "Feature",
  "properties": {
    "iso:country":"US",
    "sg:address":"2952 Boca Chica Blvd",
    "sg:city":"Brownsville",
    "sg:classifiers":[
        {
            "category":"Banks & Credit Unions",
            "subcategory":"Bank",
            "type":"Services"
        }
    ],
    "sg:phone":"+1 956 548 1436",
    "sg:postcode":"78521",
    "sg:province":"TX",
    "sg:tags":[
        "personal",
        "mortgage"
    ],
    "wof:name":"Beneficial",
    "wof:placetype":"venue"
},
  "geometry": {"coordinates":[-97.47618,25.921212],"type":"Point"}
}