{
  "type": "Feature",
  "properties": {
    "iso:country":"US",
    "sg:address":"1000 N Collins St",
    "sg:city":"Arlington",
    "sg:classifiers":[
        {
            "category":"Restaurant",
            "type":"Food & Drink"
        }
    ],
    "sg:menulink":"http://www.allmenus.com/tx/arlington/240438-panda-express/menu/",
    "sg:phone":"+1 817 274 6076",
    "sg:postcode":"76011",
    "sg:province":"TX",
    "sg:tags":[
        "asian",
        "chinese"
    ],
    "wof:name":"Panda Express",
    "wof:placetype":"venue"
},
  "geometry": {"coordinates":[-97.097673,32.750157],"type":"Point"}
}