{
  "type": "Feature",
  "properties": {
    "iso:country":"US",
    "sg:address":"901 FM 517 W",
    "sg:city":"Dickinson",
    "sg:classifiers":[
        {
            "category":"Real Estate",
            "subcategory":"Real Estate Operator",
            "type":"Services"
        }
    ],
    "sg:phone":"+1 281 534 2100",
    "sg:postcode":"77539",
    "sg:province":"TX",
    "sg:tags":[
        "building",
        "apartment"
    ],
    "wof:name":"Bay Colony Apartments",
    "wof:placetype":"venue"
},
  "geometry": {"coordinates":[-95.09021,29.442981],"type":"Point"}
}