{
  "type": "Feature",
  "properties": {
    "iso:country":"US",
    "sg:address":"2020 Solo St",
    "sg:city":"Houston",
    "sg:classifiers":[
        {
            "category":"Social Services",
            "type":"Services"
        },
        {
            "category":"Health Services",
            "subcategory":"Clinic",
            "type":"Services"
        },
        {
            "category":"Community Center",
            "type":"Public Place"
        },
        {
            "category":"Social Services",
            "subcategory":"Job Training",
            "type":"Services"
        }
    ],
    "sg:phone":"+1 713 672 2573",
    "sg:postcode":"77020",
    "sg:province":"TX",
    "sg:tags":[
        "recreation",
        "employment",
        "welfare"
    ],
    "wof:name":"Julia C Hester House Inc.",
    "wof:placetype":"venue"
},
  "geometry": {"coordinates":[-95.32109800000001,29.779237],"type":"Point"}
}