{
  "type": "Feature",
  "properties": {
    "iso:country":"US",
    "sg:address":"6811 Bill Hughes Rd",
    "sg:city":"Austin",
    "sg:classifiers":[
        {
            "category":"Professional",
            "type":"Services"
        }
    ],
    "sg:phone":"+1 512 462 1422",
    "sg:postcode":"78745",
    "sg:province":"TX",
    "wof:name":"Sowder",
    "wof:placetype":"venue"
},
  "geometry": {"coordinates":[-97.78649900000001,30.193183],"type":"Point"}
}