{
  "type": "Feature",
  "properties": {
    "iso:country":"US",
    "sg:address":"222 S Flores St",
    "sg:city":"San Antonio",
    "sg:classifiers":[
        {
            "category":"Professional",
            "subcategory":"Lawyer & Legal Services",
            "type":"Services"
        }
    ],
    "sg:phone":"+1 210 532 8888",
    "sg:postcode":"78204",
    "sg:province":"TX",
    "wof:name":"Puente Robert E Law Office",
    "wof:placetype":"venue"
},
  "geometry": {"coordinates":[-98.495097,29.422559],"type":"Point"}
}