{
  "type": "Feature",
  "properties": {
    "iso:country":"US",
    "sg:address":"1007 Main St",
    "sg:city":"Richland",
    "sg:classifiers":[
        {
            "category":"Building & Trades",
            "subcategory":"Landscaping Services",
            "type":"Services"
        }
    ],
    "sg:phone":"+1 903 362 4184",
    "sg:postcode":"76681",
    "sg:province":"TX",
    "wof:name":"William L Baldwin",
    "wof:placetype":"venue"
},
  "geometry": {"coordinates":[-96.43070899999999,31.926944],"type":"Point"}
}