{
  "type": "Feature",
  "properties": {
    "iso:country":"US",
    "sg:address":"2731 W Morton St",
    "sg:city":"Denison",
    "sg:classifiers":[
        {
            "category":"Restaurant",
            "type":"Food & Drink"
        }
    ],
    "sg:menulink":"http://www.allmenus.com/tx/east-grayson/74389-mr-jims-pizza/menu/",
    "sg:phone":"+1 903 464 0075",
    "sg:postcode":"75020",
    "sg:province":"TX",
    "sg:tags":[
        "american",
        "pizza"
    ],
    "wof:name":"Mr. Jim's Pizza",
    "wof:placetype":"venue"
},
  "geometry": {"coordinates":[-96.57818899999999,33.761875],"type":"Point"}
}