{
  "type": "Feature",
  "properties": {
    "iso:country":"US",
    "sg:address":"2001 Main St",
    "sg:city":"Bastrop",
    "sg:classifiers":[
        {
            "category":"Professional",
            "subcategory":"Art Services",
            "type":"Services"
        }
    ],
    "sg:phone":"+1 512 303 4608",
    "sg:postcode":"78602",
    "sg:province":"TX",
    "sg:tags":[
        "commercial",
        "design"
    ],
    "wof:name":"Personally Sweet",
    "wof:placetype":"venue"
},
  "geometry": {"coordinates":[-97.320324,30.125173],"type":"Point"}
}