{
  "type": "Feature",
  "properties": {
    "iso:country":"US",
    "sg:address":"5802 Brook Bend Dr",
    "sg:city":"Sugar Land",
    "sg:classifiers":[
        {
            "category":"Professional",
            "subcategory":"Management & Consulting",
            "type":"Services"
        }
    ],
    "sg:phone":"+1 281 565 3752",
    "sg:postcode":"77479",
    "sg:province":"TX",
    "sg:tags":[
        "support",
        "facility"
    ],
    "wof:name":"Energy Now Management LLC",
    "wof:placetype":"venue"
},
  "geometry": {"coordinates":[-95.631812,29.559007],"type":"Point"}
}