{
  "type": "Feature",
  "properties": {
    "iso:country":"US",
    "sg:address":"2005 Fletcher St",
    "sg:city":"Houston",
    "sg:classifiers":[
        {
            "category":"Professional",
            "type":"Services"
        }
    ],
    "sg:phone":"+1 713 236 1897",
    "sg:postcode":"77009",
    "sg:province":"TX",
    "wof:name":"Lucindo Dominguez",
    "wof:placetype":"venue"
},
  "geometry": {"coordinates":[-95.364378,29.777095],"type":"Point"}
}