{
  "type": "Feature",
  "properties": {
    "iso:country":"US",
    "sg:address":"314 E Walker St",
    "sg:city":"League City",
    "sg:classifiers":[
        {
            "category":"Manufacturing",
            "subcategory":"Tools & Machinery",
            "type":"Manufacturing & Wholesale Goods"
        }
    ],
    "sg:phone":"+1 281 332 2325",
    "sg:postcode":"77573",
    "sg:province":"TX",
    "sg:tags":[
        "equipment",
        "industrial",
        "mfg"
    ],
    "wof:name":"McClures Machine & Tool Inc",
    "wof:placetype":"venue"
},
  "geometry": {"coordinates":[-95.089303,29.506945],"type":"Point"}
}