{
  "type": "Feature",
  "properties": {
    "iso:country":"US",
    "sg:address":"633 State Hwy 123",
    "sg:city":"Stockdale",
    "sg:classifiers":[
        {
            "category":"Organizations",
            "subcategory":"Religious Organization",
            "type":"Services"
        }
    ],
    "sg:phone":"+1 830 996 3495",
    "sg:postcode":"78160",
    "sg:province":"TX",
    "sg:tags":[
        "church"
    ],
    "sg:website":"www.stockdalecofc.org",
    "wof:name":"Church Of Christ",
    "wof:placetype":"venue"
},
  "geometry": {"coordinates":[-97.95661,29.231465],"type":"Point"}
}