{
  "type": "Feature",
  "properties": {
    "iso:country":"US",
    "sg:address":"12321 Brookmeadow Ln",
    "sg:city":"Dallas",
    "sg:classifiers":[
        {
            "category":"Building & Trades",
            "subcategory":"Plumbing",
            "type":"Services"
        }
    ],
    "sg:phone":"+1 214 348 2382",
    "sg:postcode":"75218",
    "sg:province":"TX",
    "sg:tags":[
        "contractor"
    ],
    "wof:name":"Gordon Plumbing",
    "wof:placetype":"venue"
},
  "geometry": {"coordinates":[-96.688357,32.862435],"type":"Point"}
}