{
  "type": "Feature",
  "properties": {
    "iso:country":"US",
    "sg:address":"314 Greenfield Rd",
    "sg:city":"Kyle",
    "sg:classifiers":[
        {
            "category":"Shopping",
            "subcategory":"Hobbies, Toys, & Games",
            "type":"Retail Goods"
        }
    ],
    "sg:phone":"+1 512 295 5790",
    "sg:postcode":"78640",
    "sg:province":"TX",
    "sg:tags":[
        "model",
        "supply"
    ],
    "wof:name":"Leo Anderson Hobbies",
    "wof:placetype":"venue"
},
  "geometry": {"coordinates":[-97.8184,30.000349],"type":"Point"}
}