{
  "type": "Feature",
  "properties": {
    "iso:country":"US",
    "sg:address":"9014 Perrin Beitel Rd",
    "sg:city":"San Antonio",
    "sg:classifiers":[
        {
            "category":"Retail",
            "subcategory":"Auto Repair",
            "type":"Services"
        }
    ],
    "sg:phone":"+1 210 657 9696",
    "sg:postcode":"78217",
    "sg:province":"TX",
    "wof:name":"Brake Check",
    "wof:placetype":"venue"
},
  "geometry": {"coordinates":[-98.410922,29.523371],"type":"Point"}
}