{
  "type": "Feature",
  "properties": {
    "iso:country":"US",
    "sg:address":"4604 Gonzales St",
    "sg:city":"Austin",
    "sg:classifiers":[
        {
            "category":"Personal",
            "subcategory":"Beauty Salon",
            "type":"Services"
        }
    ],
    "sg:phone":"+1 512 386 7920",
    "sg:postcode":"78702",
    "sg:province":"TX",
    "sg:tags":[
        "shop"
    ],
    "wof:name":"Mane Appearance",
    "wof:placetype":"venue"
},
  "geometry": {"coordinates":[-97.699072,30.256215],"type":"Point"}
}