{
  "type": "Feature",
  "properties": {
    "iso:country":"US",
    "sg:address":"6202 Summerville Ln",
    "sg:city":"Houston",
    "sg:classifiers":[
        {
            "category":"Professional",
            "subcategory":"Business Services",
            "type":"Services"
        }
    ],
    "sg:phone":"+1 713 937 0316",
    "sg:postcode":"77041",
    "sg:province":"TX",
    "wof:name":"Vu Ventures Inc",
    "wof:placetype":"venue"
},
  "geometry": {"coordinates":[-95.621002,29.860351],"type":"Point"}
}