{
  "type": "Feature",
  "properties": {
    "iso:country":"US",
    "sg:address":"2316 Meade Ct",
    "sg:city":"League City",
    "sg:classifiers":[
        {
            "category":"Professional",
            "subcategory":"Business Services",
            "type":"Services"
        }
    ],
    "sg:phone":"+1 281 332 2935",
    "sg:postcode":"77573",
    "sg:province":"TX",
    "wof:name":"Nexx Millennium Enterprises",
    "wof:placetype":"venue"
},
  "geometry": {"coordinates":[-95.12093900000001,29.497596],"type":"Point"}
}