{
  "type": "Feature",
  "properties": {
    "iso:country":"US",
    "sg:address":"1903 Hackney St Bldg 3",
    "sg:city":"Houston",
    "sg:classifiers":[
        {
            "category":"Home & Garden",
            "subcategory":"Carpets & Floor Coverings",
            "type":"Retail Goods"
        }
    ],
    "sg:phone":"+1 281 802 1632",
    "sg:postcode":"77023",
    "sg:province":"TX",
    "sg:tags":[
        "flooring"
    ],
    "sg:website":"kandswoodflooring.com",
    "wof:name":"K&S Wood Floors",
    "wof:placetype":"venue"
},
  "geometry": {"coordinates":[-95.321314,29.721317],"type":"Point"}
}