{
  "type": "Feature",
  "properties": {
    "iso:country":"US",
    "sg:address":"107 Beaver St Ste A",
    "sg:city":"Austin",
    "sg:classifiers":[
        {
            "category":"Communications",
            "type":"Services"
        }
    ],
    "sg:phone":"+1 512 834 1941",
    "sg:postcode":"78753",
    "sg:province":"TX",
    "sg:tags":[
        "translator",
        "interpreter"
    ],
    "sg:website":"http://www.jhenryphillips.com",
    "wof:name":"Brazilian Translated",
    "wof:placetype":"venue"
},
  "geometry": {"coordinates":[-97.69994699999999,30.352138],"type":"Point"}
}