{
  "type": "Feature",
  "properties": {
    "iso:country":"US",
    "sg:address":"505 Main St",
    "sg:city":"Fort Worth",
    "sg:classifiers":[
        {
            "category":"Wholesale",
            "subcategory":"Medical Equipment & Supplies",
            "type":"Manufacturing & Wholesale Goods"
        }
    ],
    "sg:phone":"+1 817 332 1404",
    "sg:postcode":"76102",
    "sg:province":"TX",
    "sg:tags":[
        "hospital"
    ],
    "wof:name":"Welcon Inc",
    "wof:placetype":"venue"
},
  "geometry": {"coordinates":[-97.330671,32.753958],"type":"Point"}
}