{
  "type": "Feature",
  "properties": {
    "iso:country":"US",
    "sg:address":"2400 Walton Rd",
    "sg:city":"Tyler",
    "sg:classifiers":[
        {
            "category":"Organizations",
            "subcategory":"Religious Organization",
            "type":"Services"
        }
    ],
    "sg:phone":"+1 903 595 4427",
    "sg:postcode":"75701",
    "sg:province":"TX",
    "sg:tags":[
        "church"
    ],
    "wof:name":"Smith Temple Church Of God",
    "wof:placetype":"venue"
},
  "geometry": {"coordinates":[-95.32798200000001,32.319341],"type":"Point"}
}