{
  "type": "Feature",
  "properties": {
    "iso:country":"US",
    "sg:address":"16118 Chamomile Ct",
    "sg:city":"Houston",
    "sg:classifiers":[
        {
            "category":"Freight",
            "type":"Transportation"
        }
    ],
    "sg:phone":"+1 281 494 2461",
    "sg:postcode":"77083",
    "sg:province":"TX",
    "sg:tags":[
        "operator",
        "trucking"
    ],
    "wof:name":"Pro Star Trucking",
    "wof:placetype":"venue"
},
  "geometry": {"coordinates":[-95.666167,29.677785],"type":"Point"}
}