{
  "type": "Feature",
  "properties": {
    "iso:country":"US",
    "sg:address":"1209 Cerrito Grande Ln",
    "sg:city":"El Paso",
    "sg:classifiers":[
        {
            "category":"Professional",
            "subcategory":"Business Services",
            "type":"Services"
        }
    ],
    "sg:phone":"+1 915 585 2126",
    "sg:postcode":"79912",
    "sg:province":"TX",
    "sg:tags":[
        "interior",
        "consultant",
        "design",
        "decorator"
    ],
    "wof:name":"R D Interiors",
    "wof:placetype":"venue"
},
  "geometry": {"coordinates":[-106.516705,31.855165],"type":"Point"}
}