{
  "type": "Feature",
  "properties": {
    "iso:country":"US",
    "sg:address":"301 E Yandell Dr",
    "sg:city":"El Paso",
    "sg:classifiers":[
        {
            "category":"Insurance",
            "subcategory":"Title Insurance",
            "type":"Services"
        },
        {
            "category":"Real Estate",
            "subcategory":"Real Estate Services",
            "type":"Services"
        }
    ],
    "sg:phone":"+1 915 543 7600",
    "sg:postcode":"79902",
    "sg:province":"TX",
    "sg:tags":[
        "company"
    ],
    "sg:website":"www.ltep.com",
    "wof:name":"Land America Lawyers Title",
    "wof:placetype":"venue"
},
  "geometry": {"coordinates":[-106.48930799999999,31.764276],"type":"Point"}
}