{
  "type": "Feature",
  "properties": {
    "iso:country":"US",
    "sg:address":"5933 Wedgwood Dr",
    "sg:city":"Fort Worth",
    "sg:classifiers":[
        {
            "category":"Autos & Motor Vehicles",
            "subcategory":"Fuel & Gas Station",
            "type":"Retail Goods"
        }
    ],
    "sg:phone":"+1 817 292 4510",
    "sg:postcode":"76133",
    "sg:province":"TX",
    "sg:tags":[
        "station",
        "gasoline"
    ],
    "wof:name":"Crows Auto Service",
    "wof:placetype":"venue"
},
  "geometry": {"coordinates":[-97.394448,32.663466],"type":"Point"}
}