{
  "type": "Feature",
  "properties": {
    "iso:country":"US",
    "sg:address":"711 Oak Ridge Rd",
    "sg:city":"Denison",
    "sg:classifiers":[
        {
            "category":"Building & Trades",
            "subcategory":"Electrical",
            "type":"Services"
        }
    ],
    "sg:phone":"+1 903 357 3061",
    "sg:postcode":"75021",
    "sg:province":"TX",
    "sg:tags":[
        "electrician"
    ],
    "wof:name":"Triton Electric",
    "wof:placetype":"venue"
},
  "geometry": {"coordinates":[-96.456906,33.737046],"type":"Point"}
}