{
  "type": "Feature",
  "properties": {
    "iso:country":"US",
    "sg:address":"401 S Bender Ave",
    "sg:city":"Humble",
    "sg:classifiers":[
        {
            "category":"Real Estate",
            "subcategory":"Real Estate Operator",
            "type":"Services"
        }
    ],
    "sg:phone":"+1 281 446 9194",
    "sg:postcode":"77338",
    "sg:province":"TX",
    "sg:tags":[
        "building",
        "apartment"
    ],
    "wof:name":"Township Apartments",
    "wof:placetype":"venue"
},
  "geometry": {"coordinates":[-95.268182,29.996331],"type":"Point"}
}