{
  "type": "Feature",
  "properties": {
    "iso:country":"US",
    "sg:address":"3801 Olsen Blvd",
    "sg:city":"Amarillo",
    "sg:classifiers":[
        {
            "category":"Restaurant",
            "type":"Food & Drink"
        }
    ],
    "sg:phone":"+1 806 352 5050",
    "sg:postcode":"79109",
    "sg:province":"TX",
    "wof:name":"LA Bella Pizza",
    "wof:placetype":"venue"
},
  "geometry": {"coordinates":[-101.88078400000001,35.185086],"type":"Point"}
}