{
  "type": "Feature",
  "properties": {
    "iso:country":"US",
    "sg:address":"2728 Center Dr",
    "sg:city":"Vernon",
    "sg:classifiers":[
        {
            "category":"Autos & Motor Vehicles",
            "subcategory":"Automobile Sales",
            "type":"Retail Goods"
        },
        {
            "category":"Manufacturing",
            "subcategory":"Motor Vehicles & Parts",
            "type":"Manufacturing & Wholesale Goods"
        },
        {
            "category":"Autos & Motor Vehicles",
            "subcategory":"Auto Supplies",
            "type":"Retail Goods"
        },
        {
            "category":"Retail",
            "subcategory":"Auto Repair",
            "type":"Services"
        }
    ],
    "sg:phone":"+1 940 553 3422",
    "sg:postcode":"76384",
    "sg:province":"TX",
    "sg:tags":[
        "lettering",
        "cars-wholesale",
        "buses-distributors",
        "car",
        "dealers-used",
        "body",
        "buses-parts",
        "used",
        "truck",
        "painting",
        "repairing",
        "manufacturer"
    ],
    "wof:name":"Brannon's Body Shop",
    "wof:placetype":"venue"
},
  "geometry": {"coordinates":[-99.319017,34.128539],"type":"Point"}
}