{
  "type": "Feature",
  "properties": {
    "iso:country":"US",
    "sg:address":"2907 Clinton St",
    "sg:city":"Longview",
    "sg:classifiers":[
        {
            "category":"Personal",
            "type":"Services"
        }
    ],
    "sg:phone":"+1 903 759 3112",
    "sg:postcode":"75604",
    "sg:province":"TX",
    "wof:name":"Putnam Well Service & Supply",
    "wof:placetype":"venue"
},
  "geometry": {"coordinates":[-94.79919700000001,32.540272],"type":"Point"}
}