{
  "type": "Feature",
  "properties": {
    "iso:country":"US",
    "sg:address":"717 High St",
    "sg:city":"Comfort",
    "sg:classifiers":[
        {
            "category":"Shopping",
            "subcategory":"Used Merchandise",
            "type":"Retail Goods"
        }
    ],
    "sg:phone":"+1 830 816 2155",
    "sg:postcode":"78013",
    "sg:province":"TX",
    "wof:name":"B H Interiors",
    "wof:placetype":"venue"
},
  "geometry": {"coordinates":[-98.907742,29.966903],"type":"Point"}
}