{
  "type": "Feature",
  "properties": {
    "iso:country":"US",
    "sg:address":"201 E Garland St",
    "sg:city":"Grand Saline",
    "sg:classifiers":[
        {
            "category":"Retail",
            "subcategory":"Auto Repair",
            "type":"Services"
        }
    ],
    "sg:phone":"+1 903 962 6144",
    "sg:postcode":"75140",
    "sg:province":"TX",
    "sg:tags":[
        "general"
    ],
    "wof:name":"Pro Auto",
    "wof:placetype":"venue"
},
  "geometry": {"coordinates":[-95.708449,32.67454],"type":"Point"}
}