{
  "type": "Feature",
  "properties": {
    "iso:country":"US",
    "sg:address":"15533 Turner Line",
    "sg:city":"Kemp",
    "sg:classifiers":[
        {
            "category":"Building & Trades",
            "subcategory":"Construction",
            "type":"Services"
        }
    ],
    "sg:phone":"+1 903 498 4080",
    "sg:postcode":"75143",
    "sg:province":"TX",
    "sg:tags":[
        "carpentry",
        "contractor"
    ],
    "wof:name":"Pralls Custom Carpentry Inc",
    "wof:placetype":"venue"
},
  "geometry": {"coordinates":[-96.222053,32.422362],"type":"Point"}
}