{
  "type": "Feature",
  "properties": {
    "iso:country":"US",
    "sg:address":"1800 E Winding Way Dr",
    "sg:city":"Friendswood",
    "sg:classifiers":[
        {
            "category":"Building & Trades",
            "subcategory":"Construction",
            "type":"Services"
        }
    ],
    "sg:phone":"+1 281 996 9998",
    "sg:postcode":"77546",
    "sg:province":"TX",
    "sg:tags":[
        "contractor"
    ],
    "wof:name":"Cornerstone Builders",
    "wof:placetype":"venue"
},
  "geometry": {"coordinates":[-95.18159199999999,29.508074],"type":"Point"}
}