{
  "type": "Feature",
  "properties": {
    "iso:country":"US",
    "sg:address":"911 N Main St",
    "sg:city":"Cleburne",
    "sg:classifiers":[
        {
            "category":"Building & Trades",
            "subcategory":"Equipment Rental",
            "type":"Services"
        }
    ],
    "sg:phone":"+1 214 343 7312",
    "sg:postcode":"76033",
    "sg:province":"TX",
    "sg:tags":[
        "household",
        "appliance",
        "rent",
        "furniture"
    ],
    "wof:name":"Digby Ihf Inc",
    "wof:placetype":"venue"
},
  "geometry": {"coordinates":[-97.39024499999999,32.359596],"type":"Point"}
}