{
  "type": "Feature",
  "properties": {
    "iso:country":"US",
    "sg:address":"3301 Conflans Rd",
    "sg:city":"Irving",
    "sg:classifiers":[
        {
            "category":"Professional",
            "subcategory":"Management & Consulting",
            "type":"Services"
        }
    ],
    "sg:phone":"+1 972 313 7200",
    "sg:postcode":"75061",
    "sg:province":"TX",
    "sg:tags":[
        "support",
        "facility"
    ],
    "wof:name":"Custom Environmental Service",
    "wof:placetype":"venue"
},
  "geometry": {"coordinates":[-96.990161,32.821865],"type":"Point"}
}