{
  "type": "Feature",
  "properties": {
    "iso:country":"US",
    "sg:address":"4116 Bramblett Rd",
    "sg:city":"Cleburne",
    "sg:classifiers":[
        {
            "category":"Personal",
            "subcategory":"Beauty Salon",
            "type":"Services"
        }
    ],
    "sg:phone":"+1 817 558 3632",
    "sg:postcode":"76031",
    "sg:province":"TX",
    "sg:tags":[
        "shop"
    ],
    "wof:name":"Bobbies Place",
    "wof:placetype":"venue"
},
  "geometry": {"coordinates":[-97.300032,32.330184],"type":"Point"}
}