{
  "type": "Feature",
  "properties": {
    "iso:country":"US",
    "sg:address":"10712 Fm 1625",
    "sg:city":"Austin",
    "sg:classifiers":[
        {
            "category":"Retail",
            "subcategory":"Event Space",
            "type":"Services"
        }
    ],
    "sg:phone":"+1 512 243 1198",
    "sg:postcode":"78747",
    "sg:province":"TX",
    "sg:tags":[
        "venue"
    ],
    "sg:website":"www.rubioseventcenter.com",
    "wof:name":"Rubio's Event Center",
    "wof:placetype":"venue"
},
  "geometry": {"coordinates":[-97.72226999999999,30.109798],"type":"Point"}
}