{
  "type": "Feature",
  "properties": {
    "iso:country":"US",
    "sg:address":"2421 W Kiest Blvd",
    "sg:city":"Dallas",
    "sg:classifiers":[
        {
            "category":"Shopping",
            "subcategory":"Discount & Variety Stores",
            "type":"Retail Goods"
        }
    ],
    "sg:phone":"+1 214 330 9950",
    "sg:postcode":"75233",
    "sg:province":"TX",
    "sg:tags":[
        "merchandise",
        "general"
    ],
    "wof:name":"Dollar House",
    "wof:placetype":"venue"
},
  "geometry": {"coordinates":[-96.85780800000001,32.705876],"type":"Point"}
}