{
  "type": "Feature",
  "properties": {
    "iso:country":"US",
    "sg:address":"1607 Cortlandt St",
    "sg:city":"Houston",
    "sg:classifiers":[
        {
            "category":"Building & Trades",
            "subcategory":"Construction",
            "type":"Services"
        }
    ],
    "sg:phone":"+1 713 861 8613",
    "sg:postcode":"77008",
    "sg:province":"TX",
    "sg:tags":[
        "contractor"
    ],
    "sg:website":"www.gabrielhomebuilders.com",
    "wof:name":"Gabriel Home Builders Inc",
    "wof:placetype":"venue"
},
  "geometry": {"coordinates":[-95.39550699999999,29.800304],"type":"Point"}
}