{
  "type": "Feature",
  "properties": {
    "iso:country":"US",
    "sg:address":"1513 Ave F NW",
    "sg:city":"Childress",
    "sg:classifiers":[
        {
            "category":"Banks & Credit Unions",
            "subcategory":"Bank",
            "type":"Services"
        }
    ],
    "sg:phone":"+1 940 937 6341",
    "sg:postcode":"79201",
    "sg:province":"TX",
    "sg:tags":[
        "cashing",
        "depository",
        "check",
        "banking"
    ],
    "wof:name":"B & W Finance",
    "wof:placetype":"venue"
},
  "geometry": {"coordinates":[-100.22128600000001,34.432623],"type":"Point"}
}