{
  "type": "Feature",
  "properties": {
    "iso:country":"US",
    "sg:address":"709 S Moody St",
    "sg:city":"Victoria",
    "sg:classifiers":[
        {
            "category":"Restaurant",
            "type":"Food & Drink"
        }
    ],
    "sg:phone":"+1 361 575 3752",
    "sg:postcode":"77901",
    "sg:province":"TX",
    "wof:name":"Moo-Moo",
    "wof:placetype":"venue"
},
  "geometry": {"coordinates":[-97.011735,28.794198],"type":"Point"}
}