{
  "type": "Feature",
  "properties": {
    "iso:country":"US",
    "sg:address":"3407 Wells Branch Parkway",
    "sg:city":"Austin",
    "sg:classifiers":[
        {
            "category":"Retail",
            "subcategory":"Veterinary Services",
            "type":"Services"
        }
    ],
    "sg:phone":"+1 512 246 7600",
    "sg:postcode":"78728",
    "sg:province":"TX",
    "sg:tags":[
        "veterinarian"
    ],
    "wof:name":"Chase Memorial Veterinary Hospital PC",
    "wof:placetype":"venue"
},
  "geometry": {"coordinates":[-97.69641,30.439928],"type":"Point"}
}