{
  "type": "Feature",
  "properties": {
    "iso:country":"US",
    "sg:address":"205 N University Ave",
    "sg:city":"Lubbock",
    "sg:classifiers":[
        {
            "category":"Retail",
            "subcategory":"Self-service Laundry",
            "type":"Services"
        }
    ],
    "sg:phone":"+1 806 749 0889",
    "sg:postcode":"79415",
    "sg:province":"TX",
    "sg:tags":[
        "coin"
    ],
    "wof:name":"Happy Washpot",
    "wof:placetype":"venue"
},
  "geometry": {"coordinates":[-101.870469,33.600426],"type":"Point"}
}