{
  "type": "Feature",
  "properties": {
    "iso:country":"US",
    "sg:address":"7911 Copper Canyon Dr",
    "sg:city":"Arlington",
    "sg:classifiers":[
        {
            "category":"Manufacturing",
            "subcategory":"Soap",
            "type":"Manufacturing & Wholesale Goods"
        }
    ],
    "sg:phone":"+1 817 784 6744",
    "sg:postcode":"76002",
    "sg:province":"TX",
    "sg:tags":[
        "detergent",
        "mfg"
    ],
    "wof:name":"Zahara Spa Essentials",
    "wof:placetype":"venue"
},
  "geometry": {"coordinates":[-97.10876500000001,32.617008],"type":"Point"}
}