{
  "type": "Feature",
  "properties": {
    "iso:country":"US",
    "sg:address":"11078 Morrison Ln",
    "sg:city":"Dallas",
    "sg:classifiers":[
        {
            "category":"Professional",
            "subcategory":"Testing Lab",
            "type":"Services"
        }
    ],
    "sg:phone":"+1 972 481 9999",
    "sg:postcode":"75229",
    "sg:province":"TX",
    "sg:tags":[
        "laboratory"
    ],
    "wof:name":"Xenco Laboratories",
    "wof:placetype":"venue"
},
  "geometry": {"coordinates":[-96.892589,32.881777],"type":"Point"}
}