{
  "type": "Feature",
  "properties": {
    "iso:country":"US",
    "sg:address":"13915 Smitherman Rd",
    "sg:city":"Houston",
    "sg:classifiers":[
        {
            "category":"Shopping",
            "type":"Retail Goods"
        }
    ],
    "sg:phone":"+1 281 458 8459",
    "sg:postcode":"77044",
    "sg:province":"TX",
    "sg:tags":[
        "merchandise"
    ],
    "wof:name":"Hung T Nguyen",
    "wof:placetype":"venue"
},
  "geometry": {"coordinates":[-95.175743,29.859375],"type":"Point"}
}