{
  "type": "Feature",
  "properties": {
    "iso:country":"US",
    "sg:address":"16026 Pool Canyon Rd",
    "sg:city":"Austin",
    "sg:classifiers":[
        {
            "category":"Recreation",
            "subcategory":"Marina",
            "type":"Entertainment"
        }
    ],
    "sg:phone":"+1 512 266 3290",
    "sg:postcode":"78734",
    "sg:province":"TX",
    "wof:name":"Travis Marina Lake",
    "wof:placetype":"venue"
},
  "geometry": {"coordinates":[-97.92465900000001,30.422569],"type":"Point"}
}