{
  "type": "Feature",
  "properties": {
    "iso:country":"US",
    "sg:address":"1910 Villanova Dr",
    "sg:city":"Richardson",
    "sg:classifiers":[
        {
            "category":"Building & Trades",
            "subcategory":"Construction",
            "type":"Services"
        }
    ],
    "sg:phone":"+1 972 235 2359",
    "sg:postcode":"75081",
    "sg:province":"TX",
    "wof:name":"Mary Jane Snow Inc",
    "wof:placetype":"venue"
},
  "geometry": {"coordinates":[-96.687382,32.949439],"type":"Point"}
}