{
  "type": "Feature",
  "properties": {
    "iso:country":"US",
    "sg:address":"3216 Gulf Blvd",
    "sg:city":"South Padre Island",
    "sg:classifiers":[
        {
            "category":"Organizations",
            "subcategory":"Community Association",
            "type":"Services"
        }
    ],
    "sg:phone":"+1 956 761 4701",
    "sg:postcode":"78597",
    "sg:province":"TX",
    "wof:name":"Las Arenas Sun Property Assn",
    "wof:placetype":"venue"
},
  "geometry": {"coordinates":[-97.165274,26.107319],"type":"Point"}
}