{
  "type": "Feature",
  "properties": {
    "iso:country":"US",
    "sg:address":"312 Eastwood Ave",
    "sg:city":"Fort Worth",
    "sg:classifiers":[
        {
            "category":"Sports & Exercise",
            "subcategory":"Gym",
            "type":"Entertainment"
        }
    ],
    "sg:phone":"+1 817 821 1658",
    "sg:postcode":"76107",
    "sg:province":"TX",
    "sg:tags":[
        "fitness",
        "physical",
        "facility"
    ],
    "wof:name":"M Loflin Prsnl Trnr",
    "wof:placetype":"venue"
},
  "geometry": {"coordinates":[-97.372074,32.764783],"type":"Point"}
}