{
  "type": "Feature",
  "properties": {
    "iso:country":"US",
    "sg:address":"7755 Park Downs Dr",
    "sg:city":"Fort Worth",
    "sg:classifiers":[
        {
            "category":"Professional",
            "subcategory":"Management & Consulting",
            "type":"Services"
        }
    ],
    "sg:phone":"+1 817 514 8366",
    "sg:postcode":"76137",
    "sg:province":"TX",
    "sg:tags":[
        "software"
    ],
    "wof:name":"Integrity Lifestyles Inc",
    "wof:placetype":"venue"
},
  "geometry": {"coordinates":[-97.286362,32.880322],"type":"Point"}
}