{
  "type": "Feature",
  "properties": {
    "iso:country":"US",
    "sg:address":"109 S Broadway St",
    "sg:city":"Cresson",
    "sg:classifiers":[
        {
            "category":"Food & Beverages",
            "subcategory":"Groceries & Convenience Stores",
            "type":"Retail Goods"
        }
    ],
    "sg:phone":"+1 817 396 4245",
    "sg:postcode":"76035",
    "sg:province":"TX",
    "wof:name":"Kelly's",
    "wof:placetype":"venue"
},
  "geometry": {"coordinates":[-97.618312,32.531012],"type":"Point"}
}