{
  "type": "Feature",
  "properties": {
    "iso:country":"US",
    "sg:address":"7727 Streamside Dr",
    "sg:city":"Houston",
    "sg:classifiers":[
        {
            "category":"Health Services",
            "subcategory":"Doctor",
            "type":"Services"
        }
    ],
    "sg:phone":"+1 281 445 5558",
    "sg:postcode":"77088",
    "sg:province":"TX",
    "sg:tags":[
        "clinic"
    ],
    "wof:name":"Injury Rehabilitation Ctr",
    "wof:placetype":"venue"
},
  "geometry": {"coordinates":[-95.46686699999999,29.877079],"type":"Point"}
}