{
  "type": "Feature",
  "properties": {
    "iso:country":"US",
    "sg:address":"112 Creek Dr",
    "sg:city":"Georgetown",
    "sg:classifiers":[
        {
            "category":"Professional",
            "subcategory":"Management & Consulting",
            "type":"Services"
        }
    ],
    "sg:phone":"+1 512 869 3403",
    "sg:postcode":"78628",
    "sg:province":"TX",
    "sg:tags":[
        "computer",
        "related"
    ],
    "wof:name":"Derse Associates",
    "wof:placetype":"venue"
},
  "geometry": {"coordinates":[-97.68994000000001,30.67515],"type":"Point"}
}