{
  "type": "Feature",
  "properties": {
    "iso:country":"US",
    "sg:address":"2538 Montebello",
    "sg:city":"San Antonio",
    "sg:classifiers":[
        {
            "category":"Arts & Performance",
            "subcategory":"Theater",
            "type":"Entertainment"
        }
    ],
    "sg:phone":"+1 210 367 9533",
    "sg:postcode":"78259",
    "sg:province":"TX",
    "sg:tags":[
        "live",
        "music"
    ],
    "wof:name":"Mark Lozano",
    "wof:placetype":"venue"
},
  "geometry": {"coordinates":[-98.439277,29.633138],"type":"Point"}
}