{
  "type": "Feature",
  "properties": {
    "iso:country":"US",
    "sg:address":"2111 Vinita St",
    "sg:city":"Houston",
    "sg:classifiers":[
        {
            "category":"Recreation",
            "subcategory":"Arcade",
            "type":"Entertainment"
        }
    ],
    "sg:phone":"+1 713 946 0058",
    "sg:postcode":"77034",
    "sg:province":"TX",
    "sg:tags":[
        "casino"
    ],
    "wof:name":"Casino Parties Of Houston",
    "wof:placetype":"venue"
},
  "geometry": {"coordinates":[-95.228352,29.650368],"type":"Point"}
}