{
  "type": "Feature",
  "properties": {
    "iso:country":"US",
    "sg:address":"6050 Bissonet St",
    "sg:city":"Houston",
    "sg:classifiers":[
        {
            "category":"Shopping",
            "subcategory":"Used Merchandise",
            "type":"Retail Goods"
        }
    ],
    "sg:postcode":"77081",
    "sg:province":"TX",
    "sg:tags":[
        "vintage",
        "consignment"
    ],
    "wof:name":"Value Village",
    "wof:placetype":"venue"
},
  "geometry": {"coordinates":[-95.487793,29.69757],"type":"Point"}
}