{
  "type": "Feature",
  "properties": {
    "iso:country":"US",
    "sg:address":"2900 E Randol Mill Rd",
    "sg:city":"Arlington",
    "sg:classifiers":[
        {
            "category":"Building & Trades",
            "subcategory":"Electrical",
            "type":"Services"
        }
    ],
    "sg:phone":"+1 817 695 1313",
    "sg:postcode":"76011",
    "sg:province":"TX",
    "sg:tags":[
        "specializing",
        "work",
        "contractor",
        "high",
        "electrical",
        "voltage"
    ],
    "wof:name":"E-Mc Electrical Contractors",
    "wof:placetype":"venue"
},
  "geometry": {"coordinates":[-97.05602399999999,32.748908],"type":"Point"}
}