{
  "type": "Feature",
  "properties": {
    "iso:country":"US",
    "sg:address":"1005 E Kearney St",
    "sg:city":"Laredo",
    "sg:classifiers":[
        {
            "category":"Utilities",
            "subcategory":"Telephone",
            "type":"Services"
        }
    ],
    "sg:phone":"+1 956 727 6761",
    "sg:postcode":"78040",
    "sg:province":"TX",
    "sg:tags":[
        "communications"
    ],
    "wof:name":"South Western Bell",
    "wof:placetype":"venue"
},
  "geometry": {"coordinates":[-99.485558,27.521296],"type":"Point"}
}