{
  "type": "Feature",
  "properties": {
    "iso:country":"US",
    "sg:address":"9440 Harwin Dr",
    "sg:city":"Houston",
    "sg:classifiers":[
        {
            "category":"Retail",
            "subcategory":"Auto Repair",
            "type":"Services"
        }
    ],
    "sg:phone":"+1 713 782 0251",
    "sg:postcode":"77036",
    "sg:province":"TX",
    "sg:tags":[
        "repairing",
        "automobile",
        "general"
    ],
    "wof:name":"International Garage",
    "wof:placetype":"venue"
},
  "geometry": {"coordinates":[-95.529166,29.717948],"type":"Point"}
}