{
  "type": "Feature",
  "properties": {
    "iso:country":"US",
    "sg:address":"2050 Grayson Dr",
    "sg:city":"Grapevine",
    "sg:classifiers":[
        {
            "category":"Mining & Drilling",
            "type":"Manufacturing & Wholesale Goods"
        }
    ],
    "sg:phone":"+1 817 410 4909",
    "sg:postcode":"76051",
    "sg:province":"TX",
    "sg:tags":[
        "field"
    ],
    "wof:name":"Whiterock Half",
    "wof:placetype":"venue"
},
  "geometry": {"coordinates":[-97.097421,32.915411],"type":"Point"}
}