{
  "type": "Feature",
  "properties": {
    "iso:country":"US",
    "sg:address":"7519 Fernbrook Ln",
    "sg:city":"Houston",
    "sg:classifiers":[
        {
            "category":"Professional",
            "type":"Services"
        }
    ],
    "sg:phone":"+1 281 890 0612",
    "sg:postcode":"77070",
    "sg:province":"TX",
    "wof:name":"Bizret",
    "wof:placetype":"venue"
},
  "geometry": {"coordinates":[-95.548723,29.981894],"type":"Point"}
}