{
  "type": "Feature",
  "properties": {
    "iso:country":"US",
    "sg:address":"6801 S Bentsen Rd",
    "sg:city":"Mcallen",
    "sg:classifiers":[
        {
            "category":"Manufacturing",
            "subcategory":"Metals",
            "type":"Manufacturing & Wholesale Goods"
        }
    ],
    "sg:phone":"+1 956 668 0358",
    "sg:postcode":"78503",
    "sg:province":"TX",
    "sg:tags":[
        "treating",
        "heat"
    ],
    "wof:name":"Orchid Mc Allen",
    "wof:placetype":"venue"
},
  "geometry": {"coordinates":[-98.27384000000001,26.182509],"type":"Point"}
}