{
  "type": "Feature",
  "properties": {
    "iso:country":"US",
    "sg:address":"3323 Hancock Dr",
    "sg:city":"Austin",
    "sg:classifiers":[
        {
            "category":"Professional",
            "subcategory":"Accounting & Tax Preparation",
            "type":"Services"
        }
    ],
    "sg:phone":"+1 512 467 6629",
    "sg:postcode":"78731",
    "sg:province":"TX",
    "sg:tags":[
        "accountant"
    ],
    "wof:name":"Anne H Walls CPA",
    "wof:placetype":"venue"
},
  "geometry": {"coordinates":[-97.760097,30.332787],"type":"Point"}
}