{
  "type": "Feature",
  "properties": {
    "iso:country":"US",
    "sg:address":"5631 Dyer St",
    "sg:city":"El Paso",
    "sg:classifiers":[
        {
            "category":"Home & Garden",
            "subcategory":"Furniture",
            "type":"Retail Goods"
        }
    ],
    "sg:phone":"+1 915 562 8711",
    "sg:postcode":"79904",
    "sg:province":"TX",
    "wof:name":"Furniture Plus",
    "wof:placetype":"venue"
},
  "geometry": {"coordinates":[-106.44516400000001,31.829036],"type":"Point"}
}