{
  "type": "Feature",
  "properties": {
    "iso:country":"US",
    "sg:address":"822 5th St",
    "sg:city":"Bay City",
    "sg:classifiers":[
        {
            "category":"Professional",
            "subcategory":"Lawyer & Legal Services",
            "type":"Services"
        }
    ],
    "sg:phone":"+1 979 244 4244",
    "sg:postcode":"77414",
    "sg:province":"TX",
    "sg:tags":[
        "attorney"
    ],
    "wof:name":"Jill S Cornelius",
    "wof:placetype":"venue"
},
  "geometry": {"coordinates":[-95.98030799999999,28.980461],"type":"Point"}
}