{
  "type": "Feature",
  "properties": {
    "iso:country":"US",
    "sg:address":"248 SW Wilshire Blvd",
    "sg:city":"Burleson",
    "sg:classifiers":[
        {
            "category":"Shopping",
            "subcategory":"Florist",
            "type":"Retail Goods"
        }
    ],
    "sg:phone":"+1 817 295 3501",
    "sg:postcode":"76028",
    "sg:province":"TX",
    "sg:website":"www.flowersbyfran.net",
    "wof:name":"Flowers by Fran",
    "wof:placetype":"venue"
},
  "geometry": {"coordinates":[-97.33049800000001,32.542099],"type":"Point"}
}