{
  "type": "Feature",
  "properties": {
    "iso:country":"US",
    "sg:address":"6734 Northwinds Dr",
    "sg:city":"Houston",
    "sg:classifiers":[
        {
            "category":"Wholesale",
            "subcategory":"Hardware",
            "type":"Manufacturing & Wholesale Goods"
        }
    ],
    "sg:phone":"+1 713 466 7411",
    "sg:postcode":"77041",
    "sg:province":"TX",
    "sg:tags":[
        "nut",
        "bolt"
    ],
    "wof:name":"S B I",
    "wof:placetype":"venue"
},
  "geometry": {"coordinates":[-95.581491,29.876277],"type":"Point"}
}