{
  "type": "Feature",
  "properties": {
    "iso:country":"US",
    "sg:address":"2525 Country Club Dr",
    "sg:city":"Carrollton",
    "sg:classifiers":[
        {
            "category":"Sports & Exercise",
            "subcategory":"Golf",
            "type":"Entertainment"
        }
    ],
    "sg:phone":"+1 972 416 2131",
    "sg:postcode":"75006",
    "sg:province":"TX",
    "wof:name":"Columbian Country Club of Dallas",
    "wof:placetype":"venue"
},
  "geometry": {"coordinates":[-96.87069700000001,32.959801],"type":"Point"}
}