{
  "type": "Feature",
  "properties": {
    "iso:country":"US",
    "sg:address":"9001 S Normandale St",
    "sg:city":"Fort Worth",
    "sg:classifiers":[
        {
            "category":"Real Estate",
            "subcategory":"Real Estate Operator",
            "type":"Services"
        }
    ],
    "sg:phone":"+1 817 244 7933",
    "sg:postcode":"76116",
    "sg:province":"TX",
    "sg:tags":[
        "apartment"
    ],
    "wof:name":"Falls Apartments",
    "wof:placetype":"venue"
},
  "geometry": {"coordinates":[-97.474656,32.726999],"type":"Point"}
}