{
  "type": "Feature",
  "properties": {
    "iso:country":"US",
    "sg:address":"2125 Shari Ln",
    "sg:city":"Garland",
    "sg:classifiers":[
        {
            "category":"Professional",
            "subcategory":"Business Services",
            "type":"Services"
        }
    ],
    "sg:phone":"+1 972 303 0634",
    "sg:postcode":"75043",
    "sg:province":"TX",
    "sg:tags":[
        "interior",
        "consultant",
        "design",
        "decorator"
    ],
    "wof:name":"Kelly Reynolds Interiors Inc",
    "wof:placetype":"venue"
},
  "geometry": {"coordinates":[-96.598596,32.876068],"type":"Point"}
}