{
  "type": "Feature",
  "properties": {
    "iso:country":"US",
    "sg:address":"2020 Jefferson St",
    "sg:city":"Houston",
    "sg:classifiers":[
        {
            "category":"Manufacturing",
            "subcategory":"Tools & Machinery",
            "type":"Manufacturing & Wholesale Goods"
        },
        {
            "category":"Building & Trades",
            "subcategory":"Construction",
            "type":"Services"
        }
    ],
    "sg:phone":"+1 713 237 1289",
    "sg:postcode":"77003",
    "sg:province":"TX",
    "sg:tags":[
        "watch",
        "system",
        "contractor",
        "concrete",
        "time",
        "recorder"
    ],
    "wof:name":"Houston Equipment Co",
    "wof:placetype":"venue"
},
  "geometry": {"coordinates":[-95.36039700000001,29.7453],"type":"Point"}
}