{
  "type": "Feature",
  "properties": {
    "iso:country":"US",
    "sg:address":"4940 Windsor Hill",
    "sg:city":"San Antonio",
    "sg:classifiers":[
        {
            "category":"Shopping",
            "subcategory":"Clothing, Apparel, & Fashions",
            "type":"Retail Goods"
        }
    ],
    "sg:phone":"+1 210 654 8811",
    "sg:postcode":"78239",
    "sg:province":"TX",
    "wof:name":"Catherines",
    "wof:placetype":"venue"
},
  "geometry": {"coordinates":[-98.39030200000001,29.511644],"type":"Point"}
}