{
  "type": "Feature",
  "properties": {
    "iso:country":"US",
    "sg:address":"2630 FM 3034",
    "sg:city":"Abilene",
    "sg:classifiers":[
        {
            "category":"Wholesale",
            "subcategory":"Motor Vehicles",
            "type":"Manufacturing & Wholesale Goods"
        }
    ],
    "sg:phone":"+1 325 676 2996",
    "sg:postcode":"79601",
    "sg:province":"TX",
    "sg:tags":[
        "automobile",
        "used"
    ],
    "wof:name":"Copart Inc",
    "wof:placetype":"venue"
},
  "geometry": {"coordinates":[-99.74256200000001,32.524707],"type":"Point"}
}