{
  "type": "Feature",
  "properties": {
    "iso:country":"US",
    "sg:address":"4127 S Staples St",
    "sg:city":"Corpus Christi",
    "sg:classifiers":[
        {
            "category":"Shopping",
            "subcategory":"Musical Instruments",
            "type":"Retail Goods"
        }
    ],
    "sg:phone":"+1 361 808 8880",
    "sg:postcode":"78411",
    "sg:province":"TX",
    "wof:name":"Guitar Center Inc",
    "wof:placetype":"venue"
},
  "geometry": {"coordinates":[-97.37835699999999,27.725157],"type":"Point"}
}