{
  "type": "Feature",
  "properties": {
    "iso:country":"US",
    "sg:address":"4912 Haverwood Ln Ofc",
    "sg:city":"Dallas",
    "sg:classifiers":[
        {
            "category":"Real Estate",
            "subcategory":"Real Estate Operator",
            "type":"Services"
        }
    ],
    "sg:phone":"+1 972 447 0964",
    "sg:postcode":"75287",
    "sg:province":"TX",
    "sg:tags":[
        "apartment"
    ],
    "wof:name":"Champions of North Dallas",
    "wof:placetype":"venue"
},
  "geometry": {"coordinates":[-96.82620199999999,33.007301],"type":"Point"}
}