{
  "type": "Feature",
  "properties": {
    "iso:country":"US",
    "sg:address":"2706 Montopolis Dr",
    "sg:city":"Austin",
    "sg:classifiers":[
        {
            "category":"Travel",
            "subcategory":"Travel Agent",
            "type":"Entertainment"
        }
    ],
    "sg:phone":"+1 512 356 3787",
    "sg:postcode":"78741",
    "sg:province":"TX",
    "sg:tags":[
        "agency"
    ],
    "wof:name":"Maritz Travel Company Inc",
    "wof:placetype":"venue"
},
  "geometry": {"coordinates":[-97.708465,30.217821],"type":"Point"}
}