{
  "type": "Feature",
  "properties": {
    "iso:country":"US",
    "sg:address":"5565 Highway 6 N",
    "sg:city":"Houston",
    "sg:classifiers":[
        {
            "category":"Military Area",
            "type":"Public Place"
        },
        {
            "category":"Government",
            "subcategory":"Office",
            "type":"Public Place"
        }
    ],
    "sg:phone":"+1 281 859 8376",
    "sg:postcode":"77084",
    "sg:province":"TX",
    "sg:tags":[
        "force",
        "government-united",
        "armed",
        "state",
        "recruiting"
    ],
    "sg:website":"http://www.marines.com",
    "wof:name":"Marine Corps Recruiting Station",
    "wof:placetype":"venue"
},
  "geometry": {"coordinates":[-95.64503999999999,29.857499],"type":"Point"}
}