{
  "type": "Feature",
  "properties": {
    "iso:country":"US",
    "sg:address":"1226 Glencove Dr",
    "sg:city":"Richardson",
    "sg:classifiers":[
        {
            "category":"Professional",
            "subcategory":"Advertising",
            "type":"Services"
        }
    ],
    "sg:phone":"+1 972 690 6488",
    "sg:postcode":"75080",
    "sg:province":"TX",
    "sg:tags":[
        "agency",
        "full"
    ],
    "wof:name":"Past Time Sports",
    "wof:placetype":"venue"
},
  "geometry": {"coordinates":[-96.762107,32.966412],"type":"Point"}
}