{
  "type": "Feature",
  "properties": {
    "iso:country":"US",
    "sg:address":"9802 Amblewood Dr",
    "sg:city":"Houston",
    "sg:classifiers":[
        {
            "category":"Building & Trades",
            "subcategory":"Construction",
            "type":"Services"
        }
    ],
    "sg:phone":"+1 713 855 7876",
    "sg:postcode":"77099",
    "sg:province":"TX",
    "sg:tags":[
        "contractor"
    ],
    "wof:name":"Tile Prestige",
    "wof:placetype":"venue"
},
  "geometry": {"coordinates":[-95.58016600000001,29.671318],"type":"Point"}
}