{
  "type": "Feature",
  "properties": {
    "iso:country":"US",
    "sg:address":"23741 US Hwy 59",
    "sg:city":"Porter",
    "sg:classifiers":[
        {
            "category":"Shopping",
            "subcategory":"Shoes",
            "type":"Retail Goods"
        }
    ],
    "sg:phone":"+1 281 354 8622",
    "sg:postcode":"77365",
    "sg:province":"TX",
    "wof:name":"Payless Shoe Source",
    "wof:placetype":"venue"
},
  "geometry": {"coordinates":[-95.23604899999999,30.103759],"type":"Point"}
}