{
  "type": "Feature",
  "properties": {
    "iso:country":"US",
    "sg:address":"6116 Southwest Fwy",
    "sg:city":"Houston",
    "sg:classifiers":[
        {
            "category":"Shopping",
            "subcategory":"Jewelry",
            "type":"Retail Goods"
        }
    ],
    "sg:phone":"+1 713 785 8748",
    "sg:postcode":"77057",
    "sg:province":"TX",
    "wof:name":"Dang Jewelry",
    "wof:placetype":"venue"
},
  "geometry": {"coordinates":[-95.489358,29.725643],"type":"Point"}
}