{
  "type": "Feature",
  "properties": {
    "iso:country":"US",
    "sg:address":"3312 Preston Rd",
    "sg:city":"Plano",
    "sg:classifiers":[
        {
            "category":"Shopping",
            "subcategory":"Pharmacy",
            "type":"Retail Goods"
        }
    ],
    "sg:phone":"+1 972 867 0721",
    "sg:postcode":"75093",
    "sg:province":"TX",
    "sg:tags":[
        "drugstore"
    ],
    "wof:name":"Sav-on Drugs",
    "wof:placetype":"venue"
},
  "geometry": {"coordinates":[-96.794135,33.252601],"type":"Point"}
}