{
  "type": "Feature",
  "properties": {
    "iso:country":"US",
    "sg:address":"116 E Bluebonnet Dr",
    "sg:city":"Uvalde",
    "sg:classifiers":[
        {
            "category":"Professional",
            "type":"Services"
        }
    ],
    "sg:phone":"+1 830 278 5107",
    "sg:postcode":"78801",
    "sg:province":"TX",
    "wof:name":"A&L Services",
    "wof:placetype":"venue"
},
  "geometry": {"coordinates":[-99.774523,29.18694],"type":"Point"}
}