{
  "type": "Feature",
  "properties": {
    "iso:country":"US",
    "sg:address":"1504 E 6th St",
    "sg:city":"Austin",
    "sg:classifiers":[
        {
            "category":"Bars & Pubs",
            "subcategory":"Sports Bar",
            "type":"Food & Drink"
        }
    ],
    "sg:phone":"+1 512 322 5214",
    "sg:postcode":"78702",
    "sg:province":"TX",
    "wof:name":"ATX Sports Bar",
    "wof:placetype":"venue"
},
  "geometry": {"coordinates":[-97.726917,30.263511],"type":"Point"}
}