{
  "type": "Feature",
  "properties": {
    "iso:country":"US",
    "sg:address":"2004 Sun Chase Blvd",
    "sg:city":"Cedar Park",
    "sg:classifiers":[
        {
            "category":"Recreation",
            "type":"Entertainment"
        }
    ],
    "sg:phone":"+1 512 219 6459",
    "sg:postcode":"78613",
    "sg:province":"TX",
    "wof:name":"Acrotex Gymnastics",
    "wof:placetype":"venue"
},
  "geometry": {"coordinates":[-97.838202,30.477168],"type":"Point"}
}