{
  "type": "Feature",
  "properties": {
    "iso:country":"US",
    "sg:address":"12239 N Shadow Cove Dr",
    "sg:city":"Houston",
    "sg:classifiers":[
        {
            "category":"Shopping",
            "subcategory":"Hobbies, Toys, & Games",
            "type":"Retail Goods"
        }
    ],
    "sg:phone":"+1 281 531 8714",
    "sg:postcode":"77082",
    "sg:province":"TX",
    "wof:name":"Kp Group",
    "wof:placetype":"venue"
},
  "geometry": {"coordinates":[-95.59963999999999,29.720674],"type":"Point"}
}