{
  "type": "Feature",
  "properties": {
    "iso:country":"US",
    "sg:address":"3401 Shelby Ave",
    "sg:city":"Waco",
    "sg:classifiers":[
        {
            "category":"Shopping",
            "subcategory":"Clothing, Apparel, & Fashions",
            "type":"Retail Goods"
        }
    ],
    "sg:phone":"+1 254 714 0999",
    "sg:postcode":"76711",
    "sg:province":"TX",
    "sg:tags":[
        "alteration"
    ],
    "wof:name":"Mary's Alterations",
    "wof:placetype":"venue"
},
  "geometry": {"coordinates":[-97.150166,31.523194],"type":"Point"}
}