{
  "type": "Feature",
  "properties": {
    "iso:country":"US",
    "sg:address":"3253 Desert Storm Rd",
    "sg:city":"Fort Worth",
    "sg:classifiers":[
        {
            "category":"Government",
            "subcategory":"Office",
            "type":"Public Place"
        }
    ],
    "sg:phone":"+1 817 782 7462",
    "sg:postcode":"76127",
    "sg:province":"TX",
    "sg:tags":[
        "national",
        "security"
    ],
    "wof:name":"Amsel",
    "wof:placetype":"venue"
},
  "geometry": {"coordinates":[-97.423104,32.776379],"type":"Point"}
}