{
  "type": "Feature",
  "properties": {
    "iso:country":"US",
    "sg:address":"8410 Burkhart Rd",
    "sg:city":"Houston",
    "sg:classifiers":[
        {
            "category":"Professional",
            "type":"Services"
        }
    ],
    "sg:phone":"+1 713 984 8771",
    "sg:postcode":"77055",
    "sg:province":"TX",
    "wof:name":"Houston Heritage Ltd",
    "wof:placetype":"venue"
},
  "geometry": {"coordinates":[-95.49716100000001,29.789559],"type":"Point"}
}