{
  "type": "Feature",
  "properties": {
    "iso:country":"US",
    "sg:address":"247 Yellowstone St",
    "sg:city":"San Antonio",
    "sg:classifiers":[
        {
            "category":"Building & Trades",
            "subcategory":"Plumbing",
            "type":"Services"
        }
    ],
    "sg:phone":"+1 210 532 2138",
    "sg:postcode":"78210",
    "sg:province":"TX",
    "sg:tags":[
        "plumbing",
        "contractor"
    ],
    "wof:name":"Mike Campos Plumbing Repair",
    "wof:placetype":"venue"
},
  "geometry": {"coordinates":[-98.48761,29.397993],"type":"Point"}
}