{
  "type": "Feature",
  "properties": {
    "iso:country":"US",
    "sg:address":"10621 Harwin Dr",
    "sg:city":"Houston",
    "sg:classifiers":[
        {
            "category":"Home & Garden",
            "subcategory":"Building Materials",
            "type":"Retail Goods"
        },
        {
            "category":"Building & Trades",
            "subcategory":"Construction",
            "type":"Services"
        },
        {
            "category":"Home & Garden",
            "subcategory":"Furniture",
            "type":"Retail Goods"
        }
    ],
    "sg:phone":"+1 713 270 1888",
    "sg:postcode":"77036",
    "sg:province":"TX",
    "sg:tags":[
        "cabinet",
        "remodeling",
        "top",
        "counter",
        "contractor",
        "planning",
        "improvement",
        "equipment-household",
        "maker",
        "kitchen"
    ],
    "wof:name":"Sage Kitchen & Bath",
    "wof:placetype":"venue"
},
  "geometry": {"coordinates":[-95.554697,29.716781],"type":"Point"}
}