{
  "type": "Feature",
  "properties": {
    "iso:country":"US",
    "sg:address":"15810 Wilderness Pkwy",
    "sg:city":"San Antonio",
    "sg:classifiers":[
        {
            "category":"Wholesale",
            "subcategory":"Drugs",
            "type":"Manufacturing & Wholesale Goods"
        }
    ],
    "sg:phone":"+1 210 496 7386",
    "sg:postcode":"78232",
    "sg:province":"TX",
    "wof:name":"Barbara A Hajek",
    "wof:placetype":"venue"
},
  "geometry": {"coordinates":[-98.502962,29.584969],"type":"Point"}
}