{
  "type": "Feature",
  "properties": {
    "iso:country":"US",
    "sg:address":"3419 Trinity Mills Rd",
    "sg:city":"Dallas",
    "sg:classifiers":[
        {
            "category":"Sports & Exercise",
            "subcategory":"Gym",
            "type":"Entertainment"
        }
    ],
    "sg:phone":"+1 972 307 2200",
    "sg:postcode":"75287",
    "sg:province":"TX",
    "sg:tags":[
        "club",
        "health",
        "studio",
        "gymnasium"
    ],
    "wof:name":"Life Time Fitness",
    "wof:placetype":"venue"
},
  "geometry": {"coordinates":[-96.839697,32.987515],"type":"Point"}
}