{
  "type": "Feature",
  "properties": {
    "iso:country":"US",
    "sg:address":"205 Maverick Ter",
    "sg:city":"Little Elm",
    "sg:classifiers":[
        {
            "category":"Professional",
            "type":"Services"
        }
    ],
    "sg:phone":"+1 972 294 8171",
    "sg:postcode":"75068",
    "sg:province":"TX",
    "sg:tags":[
        "establishment"
    ],
    "wof:name":"Templin Choice",
    "wof:placetype":"venue"
},
  "geometry": {"coordinates":[-96.992529,33.186092],"type":"Point"}
}