{
  "type": "Feature",
  "properties": {
    "iso:country":"US",
    "sg:address":"204 Smokey Ln",
    "sg:city":"Denton",
    "sg:classifiers":[
        {
            "category":"Manufacturing",
            "subcategory":"Retail Goods",
            "type":"Manufacturing & Wholesale Goods"
        }
    ],
    "sg:phone":"+1 940 321 3750",
    "sg:postcode":"76208",
    "sg:province":"TX",
    "sg:tags":[
        "product",
        "mfg"
    ],
    "wof:name":"Lou Lous",
    "wof:placetype":"venue"
},
  "geometry": {"coordinates":[-97.039452,33.170697],"type":"Point"}
}