{
  "type": "Feature",
  "properties": {
    "iso:country":"US",
    "sg:address":"8220 San Lorenzo Dr",
    "sg:city":"Laredo",
    "sg:classifiers":[
        {
            "category":"Restaurant",
            "type":"Food & Drink"
        }
    ],
    "sg:phone":"+1 956 726 3633",
    "sg:postcode":"78045",
    "sg:province":"TX",
    "sg:website":"www.vilore.com",
    "wof:name":"Vilore Foods Co",
    "wof:placetype":"venue"
},
  "geometry": {"coordinates":[-99.510592,27.586097],"type":"Point"}
}