{
  "type": "Feature",
  "properties": {
    "iso:country":"US",
    "sg:address":"2215 N Britain Rd",
    "sg:city":"Irving",
    "sg:classifiers":[
        {
            "category":"Retail",
            "subcategory":"Auto Rental",
            "type":"Services"
        }
    ],
    "sg:phone":"+1 972 659 1424",
    "sg:postcode":"75062",
    "sg:province":"TX",
    "sg:tags":[
        "car",
        "passenger"
    ],
    "sg:website":"enterpries.com",
    "wof:name":"Enterprise Rent-A-Car",
    "wof:placetype":"venue"
},
  "geometry": {"coordinates":[-96.944553,32.837985],"type":"Point"}
}