{
  "type": "Feature",
  "properties": {
    "iso:country":"US",
    "sg:address":"5501 Lakebend East Dr",
    "sg:city":"San Antonio",
    "sg:classifiers":[
        {
            "category":"Social Services",
            "type":"Services"
        }
    ],
    "sg:phone":"+1 210 662 8083",
    "sg:postcode":"78244",
    "sg:province":"TX",
    "sg:tags":[
        "organization",
        "welfare"
    ],
    "wof:name":"YMCA",
    "wof:placetype":"venue"
},
  "geometry": {"coordinates":[-98.352593,29.477424],"type":"Point"}
}