{
  "type": "Feature",
  "properties": {
    "iso:country":"US",
    "sg:address":"6830 Moss Rose St",
    "sg:city":"Houston",
    "sg:classifiers":[
        {
            "category":"Professional",
            "subcategory":"Business Services",
            "type":"Services"
        }
    ],
    "sg:phone":"+1 713 643 7612",
    "sg:postcode":"77087",
    "sg:province":"TX",
    "wof:name":"Isabel R Barreiro",
    "wof:placetype":"venue"
},
  "geometry": {"coordinates":[-95.298282,29.707589],"type":"Point"}
}