{
  "type": "Feature",
  "properties": {
    "iso:country":"US",
    "sg:address":"1327 Drury Ln",
    "sg:city":"San Antonio",
    "sg:classifiers":[
        {
            "category":"Building & Trades",
            "subcategory":"Construction",
            "type":"Services"
        }
    ],
    "sg:phone":"+1 210 928 8227",
    "sg:postcode":"78221",
    "sg:province":"TX",
    "sg:tags":[
        "concrete",
        "contractor"
    ],
    "wof:name":"Budget House Leveling",
    "wof:placetype":"venue"
},
  "geometry": {"coordinates":[-98.52617499999999,29.347676],"type":"Point"}
}