{
  "type": "Feature",
  "properties": {
    "iso:country":"US",
    "sg:address":"10714 W Bellfort St",
    "sg:city":"Houston",
    "sg:classifiers":[
        {
            "category":"Social Services",
            "subcategory":"Child Care",
            "type":"Services"
        }
    ],
    "sg:phone":"+1 281 495 5540",
    "sg:postcode":"77099",
    "sg:province":"TX",
    "wof:name":"Arc-En-Ciel Day School",
    "wof:placetype":"venue"
},
  "geometry": {"coordinates":[-95.567669,29.654591],"type":"Point"}
}