{
  "type": "Feature",
  "properties": {
    "iso:country":"US",
    "sg:address":"2910 Commercial Center Blvd",
    "sg:city":"Katy",
    "sg:classifiers":[
        {
            "category":"Building & Trades",
            "subcategory":"Equipment Rental",
            "type":"Services"
        }
    ],
    "sg:phone":"+1 281 384 4393",
    "sg:postcode":"77494",
    "sg:province":"TX",
    "sg:tags":[
        "yard",
        "leasing",
        "store"
    ],
    "wof:name":"Red River Leasing",
    "wof:placetype":"venue"
},
  "geometry": {"coordinates":[-95.777664,29.737267],"type":"Point"}
}