{
  "type": "Feature",
  "properties": {
    "iso:country":"US",
    "sg:address":"7710 Woodway Dr",
    "sg:city":"Woodway",
    "sg:classifiers":[
        {
            "category":"Shopping",
            "subcategory":"Gifts & Souvenirs",
            "type":"Retail Goods"
        }
    ],
    "sg:phone":"+1 254 751 7699",
    "sg:postcode":"76712",
    "sg:province":"TX",
    "sg:tags":[
        "shop"
    ],
    "wof:name":"Dis N Dat Gift Shop",
    "wof:placetype":"venue"
},
  "geometry": {"coordinates":[-97.205017,31.504486],"type":"Point"}
}