{
  "type": "Feature",
  "properties": {
    "iso:country":"US",
    "sg:address":"229 Parkhill St",
    "sg:city":"Huntsville",
    "sg:classifiers":[
        {
            "category":"Real Estate",
            "subcategory":"Real Estate Agent",
            "type":"Services"
        }
    ],
    "sg:phone":"+1 936 295 9181",
    "sg:postcode":"77340",
    "sg:province":"TX",
    "wof:name":"Joe L Smith Real Estate",
    "wof:placetype":"venue"
},
  "geometry": {"coordinates":[-95.533224,30.705944],"type":"Point"}
}