{
  "type": "Feature",
  "properties": {
    "iso:country":"US",
    "sg:address":"4932 Research Dr",
    "sg:city":"San Antonio",
    "sg:classifiers":[
        {
            "category":"Professional",
            "type":"Services"
        }
    ],
    "sg:phone":"+1 210 698 3316",
    "sg:postcode":"78240",
    "sg:province":"TX",
    "sg:tags":[
        "establishment"
    ],
    "wof:name":"Bill Draving Co Inc",
    "wof:placetype":"venue"
},
  "geometry": {"coordinates":[-98.583657,29.538351],"type":"Point"}
}