{
  "type": "Feature",
  "properties": {
    "iso:country":"US",
    "sg:address":"510 Peabody Ave",
    "sg:city":"San Antonio",
    "sg:classifiers":[
        {
            "category":"Retail",
            "subcategory":"Laundry & Dry Cleaning",
            "type":"Services"
        }
    ],
    "sg:phone":"+1 210 924 1925",
    "sg:postcode":"78211",
    "sg:province":"TX",
    "wof:name":"Sierra Carpet Cleaning",
    "wof:placetype":"venue"
},
  "geometry": {"coordinates":[-98.55508,29.364953],"type":"Point"}
}