{
  "type": "Feature",
  "properties": {
    "iso:country":"US",
    "sg:address":"7726 Spyglass Dr",
    "sg:city":"Houston",
    "sg:classifiers":[
        {
            "category":"Personal",
            "type":"Services"
        }
    ],
    "sg:phone":"+1 281 861 6611",
    "sg:postcode":"77095",
    "sg:province":"TX",
    "wof:name":"Texas Apartment Connectors",
    "wof:placetype":"venue"
},
  "geometry": {"coordinates":[-95.62139000000001,29.88994],"type":"Point"}
}