{
  "type": "Feature",
  "properties": {
    "iso:country":"US",
    "sg:address":"7956 Roundrock Rd",
    "sg:city":"Dallas",
    "sg:classifiers":[
        {
            "category":"Shopping",
            "subcategory":"Beauty & Cosmetics",
            "type":"Retail Goods"
        }
    ],
    "sg:phone":"+1 972 701 9585",
    "sg:postcode":"75248",
    "sg:province":"TX",
    "sg:tags":[
        "worm"
    ],
    "wof:name":"Lady Worm",
    "wof:placetype":"venue"
},
  "geometry": {"coordinates":[-96.771007,32.956675],"type":"Point"}
}