{
  "type": "Feature",
  "properties": {
    "iso:country":"US",
    "sg:address":"2304 Berry Hill Cir",
    "sg:city":"Austin",
    "sg:classifiers":[
        {
            "category":"Building & Trades",
            "subcategory":"Landscaping Services",
            "type":"Services"
        }
    ],
    "sg:phone":"+1 512 441 2955",
    "sg:postcode":"78745",
    "sg:province":"TX",
    "wof:name":"Taylors Maintenance & Yardwork",
    "wof:placetype":"venue"
},
  "geometry": {"coordinates":[-97.803252,30.217731],"type":"Point"}
}