{
  "type": "Feature",
  "properties": {
    "iso:country":"US",
    "sg:address":"13900 N Central Expy",
    "sg:city":"Dallas",
    "sg:classifiers":[
        {
            "category":"Professional",
            "subcategory":"Management & Consulting",
            "type":"Services"
        }
    ],
    "sg:phone":"+1 972 927 1412",
    "sg:postcode":"75243",
    "sg:province":"TX",
    "wof:name":"Texas Instruments",
    "wof:placetype":"venue"
},
  "geometry": {"coordinates":[-96.74885500000001,32.936923],"type":"Point"}
}