{
  "type": "Feature",
  "properties": {
    "iso:country":"US",
    "sg:address":"1133 John Freeman Blvd",
    "sg:city":"Houston",
    "sg:classifiers":[
        {
            "category":"Education",
            "subcategory":"Library",
            "type":"Public Place"
        }
    ],
    "sg:phone":"+1 713 799 7147",
    "sg:postcode":"77030",
    "sg:province":"TX",
    "sg:website":"www.library.tmc.edu/",
    "wof:name":"HAM-TMC Library",
    "wof:placetype":"venue"
},
  "geometry": {"coordinates":[-95.397582,29.710953],"type":"Point"}
}