{
  "type": "Feature",
  "properties": {
    "iso:country":"US",
    "sg:address":"35336 US Hwy 90",
    "sg:city":"Brookshire",
    "sg:classifiers":[
        {
            "category":"Government",
            "subcategory":"Office",
            "type":"Public Place"
        }
    ],
    "sg:phone":"+1 281 934 8228",
    "sg:postcode":"77423",
    "sg:province":"TX",
    "wof:name":"Highways & Public Trans Dept",
    "wof:placetype":"venue"
},
  "geometry": {"coordinates":[-95.976125,29.785529],"type":"Point"}
}