{
  "type": "Feature",
  "properties": {
    "iso:country":"US",
    "sg:address":"3403 N Main St",
    "sg:city":"Victoria",
    "sg:classifiers":[
        {
            "category":"Social Services",
            "type":"Services"
        }
    ],
    "sg:phone":"+1 361 578 7441",
    "sg:postcode":"77901",
    "sg:province":"TX",
    "sg:tags":[
        "counselor",
        "marriage",
        "family"
    ],
    "wof:name":"Virginia Ruschhaupt",
    "wof:placetype":"venue"
},
  "geometry": {"coordinates":[-97.007582,28.825722],"type":"Point"}
}