{
  "type": "Feature",
  "properties": {
    "iso:country":"US",
    "sg:address":"8514 C E King Pkwy",
    "sg:city":"Houston",
    "sg:classifiers":[
        {
            "category":"Food & Beverages",
            "subcategory":"Meat & Fish",
            "type":"Retail Goods"
        }
    ],
    "sg:phone":"+1 281 459 2009",
    "sg:postcode":"77044",
    "sg:province":"TX",
    "sg:tags":[
        "shop",
        "seafood",
        "market"
    ],
    "wof:name":"Hay Chihuahua Meat Market",
    "wof:placetype":"venue"
},
  "geometry": {"coordinates":[-95.21403100000001,29.846643],"type":"Point"}
}