{
  "type": "Feature",
  "properties": {
    "iso:country":"US",
    "sg:address":"3354 Lasses Blvd",
    "sg:city":"San Antonio",
    "sg:classifiers":[
        {
            "category":"Bars & Pubs",
            "type":"Food & Drink"
        }
    ],
    "sg:phone":"+1 210 337 0701",
    "sg:postcode":"78223",
    "sg:province":"TX",
    "sg:tags":[
        "drinking"
    ],
    "wof:name":"Just 1 More",
    "wof:placetype":"venue"
},
  "geometry": {"coordinates":[-98.435053,29.355454],"type":"Point"}
}