{
  "type": "Feature",
  "properties": {
    "iso:country":"US",
    "sg:address":"7917 Thomas Springs Rd",
    "sg:city":"Austin",
    "sg:classifiers":[
        {
            "category":"Building & Trades",
            "subcategory":"Construction",
            "type":"Services"
        }
    ],
    "sg:phone":"+1 512 301 3339",
    "sg:postcode":"78736",
    "sg:province":"TX",
    "sg:tags":[
        "home",
        "builder"
    ],
    "wof:name":"Don Thomas Homes",
    "wof:placetype":"venue"
},
  "geometry": {"coordinates":[-97.92507999999999,30.246955],"type":"Point"}
}