{
  "type": "Feature",
  "properties": {
    "iso:country":"US",
    "sg:address":"3800 Lost Cavern Cv",
    "sg:city":"Austin",
    "sg:classifiers":[
        {
            "category":"Professional",
            "subcategory":"Employment Agencies",
            "type":"Services"
        },
        {
            "category":"Professional",
            "subcategory":"Lawyer & Legal Services",
            "type":"Services"
        }
    ],
    "sg:phone":"+1 512 282 7738",
    "sg:postcode":"78739",
    "sg:province":"TX",
    "sg:tags":[
        "convention",
        "secretarial",
        "reporters-court"
    ],
    "wof:name":"Lisa's Offsite Typographical Svcs",
    "wof:placetype":"venue"
},
  "geometry": {"coordinates":[-97.872017,30.15918],"type":"Point"}
}