{
  "type": "Feature",
  "properties": {
    "iso:country":"US",
    "sg:address":"5372 Oak Ct",
    "sg:city":"Fort Worth",
    "sg:classifiers":[
        {
            "category":"Utilities",
            "subcategory":"Mobile Phone",
            "type":"Services"
        }
    ],
    "sg:phone":"+1 817 923 2553",
    "sg:postcode":"76140",
    "sg:province":"TX",
    "sg:tags":[
        "communication",
        "electronic",
        "radiotelephone"
    ],
    "wof:name":"S & M Car Audio",
    "wof:placetype":"venue"
},
  "geometry": {"coordinates":[-97.237255,32.607492],"type":"Point"}
}