{
  "type": "Feature",
  "properties": {
    "iso:country":"US",
    "sg:address":"1301 4th St",
    "sg:city":"Seabrook",
    "sg:classifiers":[
        {
            "category":"Wholesale",
            "subcategory":"Non-durable Goods",
            "type":"Manufacturing & Wholesale Goods"
        }
    ],
    "sg:phone":"+1 281 474 1109",
    "sg:postcode":"77586",
    "sg:province":"TX",
    "sg:tags":[
        "food"
    ],
    "wof:name":"Herb Seabrook Merchant",
    "wof:placetype":"venue"
},
  "geometry": {"coordinates":[-95.023686,29.560309],"type":"Point"}
}