{
  "type": "Feature",
  "properties": {
    "iso:country":"US",
    "sg:address":"500 Morton St",
    "sg:city":"Richmond",
    "sg:classifiers":[
        {
            "category":"Social Services",
            "type":"Services"
        }
    ],
    "sg:phone":"+1 281 344 0156",
    "sg:postcode":"77469",
    "sg:province":"TX",
    "wof:name":"Alternatives In Motion",
    "wof:placetype":"venue"
},
  "geometry": {"coordinates":[-95.76259400000001,29.582542],"type":"Point"}
}