{
  "type": "Feature",
  "properties": {
    "iso:country":"US",
    "sg:address":"1430 Texas Ave S",
    "sg:city":"College Station",
    "sg:classifiers":[
        {
            "category":"Home & Garden",
            "subcategory":"Home Furnishings",
            "type":"Retail Goods"
        }
    ],
    "sg:phone":"+1 979 696 2699",
    "sg:postcode":"77840",
    "sg:province":"TX",
    "sg:tags":[
        "linen"
    ],
    "wof:name":"Bed Bath & Beyond Inc",
    "wof:placetype":"venue"
},
  "geometry": {"coordinates":[-96.32279699999999,30.618025],"type":"Point"}
}