{
  "type": "Feature",
  "properties": {
    "iso:country":"US",
    "sg:address":"5716 Palo Pinto Ave",
    "sg:city":"Dallas",
    "sg:classifiers":[
        {
            "category":"Real Estate",
            "subcategory":"Architect",
            "type":"Services"
        }
    ],
    "sg:phone":"+1 214 821 0021",
    "sg:postcode":"75206",
    "sg:province":"TX",
    "sg:tags":[
        "architectural"
    ],
    "wof:name":"Keith Traywick Assoc",
    "wof:placetype":"venue"
},
  "geometry": {"coordinates":[-96.768288,32.81976],"type":"Point"}
}