{
  "type": "Feature",
  "properties": {
    "iso:country":"US",
    "sg:address":"1302 Lane St",
    "sg:city":"Irving",
    "sg:classifiers":[
        {
            "category":"Health Services",
            "subcategory":"Medical Lab",
            "type":"Services"
        }
    ],
    "sg:phone":"+1 972 254 7185",
    "sg:postcode":"75061",
    "sg:province":"TX",
    "sg:tags":[
        "laboratory"
    ],
    "wof:name":"Laboratory Corp Of America",
    "wof:placetype":"venue"
},
  "geometry": {"coordinates":[-96.96247200000001,32.833647],"type":"Point"}
}