{
  "type": "Feature",
  "properties": {
    "iso:country":"US",
    "sg:address":"722 Paulus Ave",
    "sg:city":"Dallas",
    "sg:classifiers":[
        {
            "category":"Building & Trades",
            "subcategory":"Construction",
            "type":"Services"
        }
    ],
    "sg:phone":"+1 214 887 0005",
    "sg:postcode":"75214",
    "sg:province":"TX",
    "sg:tags":[
        "contractor"
    ],
    "wof:name":"The Burke Company",
    "wof:placetype":"venue"
},
  "geometry": {"coordinates":[-96.75359,32.811781],"type":"Point"}
}