{
  "type": "Feature",
  "properties": {
    "iso:country":"US",
    "sg:address":"325 Center St",
    "sg:city":"Center Point",
    "sg:classifiers":[
        {
            "category":"Building & Trades",
            "subcategory":"Construction",
            "type":"Services"
        }
    ],
    "sg:phone":"+1 830 634 3308",
    "sg:postcode":"78014",
    "sg:province":"TX",
    "sg:tags":[
        "house"
    ],
    "wof:name":"Whitewood Brothers Cnstr",
    "wof:placetype":"venue"
},
  "geometry": {"coordinates":[-99.23616800000001,28.435124],"type":"Point"}
}