{
  "type": "Feature",
  "properties": {
    "iso:country":"US",
    "sg:address":"1709 Westheimer",
    "sg:city":"Houston",
    "sg:classifiers":[
        {
            "category":"Shopping",
            "subcategory":"Hobbies, Toys, & Games",
            "type":"Retail Goods"
        },
        {
            "category":"Shopping",
            "subcategory":"Books",
            "type":"Retail Goods"
        }
    ],
    "sg:phone":"+1 713 523 3669",
    "sg:postcode":"77246",
    "sg:province":"TX",
    "sg:tags":[
        "bookstore",
        "toy",
        "store"
    ],
    "sg:website":"www.domybookstore.com",
    "wof:name":"Domy Books",
    "wof:placetype":"venue"
},
  "geometry": {"coordinates":[-95.402477,29.742776],"type":"Point"}
}