{
  "type": "Feature",
  "properties": {
    "iso:country":"US",
    "sg:address":"2080 Franklin St",
    "sg:city":"Beaumont",
    "sg:classifiers":[
        {
            "category":"Wholesale",
            "subcategory":"Electrical",
            "type":"Manufacturing & Wholesale Goods"
        }
    ],
    "sg:phone":"+1 409 835 6697",
    "sg:postcode":"77701",
    "sg:province":"TX",
    "sg:tags":[
        "electronic"
    ],
    "wof:name":"Wayne Copeland Cuartis",
    "wof:placetype":"venue"
},
  "geometry": {"coordinates":[-94.10781799999999,30.066779],"type":"Point"}
}