{
  "type": "Feature",
  "properties": {
    "iso:country":"US",
    "sg:address":"815 A Brazos St #552",
    "sg:city":"Austin",
    "sg:classifiers":[
        {
            "category":"Building & Trades",
            "subcategory":"Plumbing",
            "type":"Services"
        }
    ],
    "sg:phone":"+1 512 971 3164",
    "sg:postcode":"78701",
    "sg:province":"TX",
    "sg:website":"nycplumbingonline.com",
    "wof:name":"Not Your Common Plumbing",
    "wof:placetype":"venue"
},
  "geometry": {"coordinates":[-97.74043399999999,30.270245],"type":"Point"}
}