{
  "type": "Feature",
  "properties": {
    "iso:country":"US",
    "sg:address":"7928 N Glen Dr",
    "sg:city":"Irving",
    "sg:classifiers":[
        {
            "category":"Professional",
            "subcategory":"Computer Services",
            "type":"Services"
        }
    ],
    "sg:phone":"+1 972 861 9052",
    "sg:postcode":"75063",
    "sg:province":"TX",
    "sg:tags":[
        "repair"
    ],
    "wof:name":"G10 Consulting",
    "wof:placetype":"venue"
},
  "geometry": {"coordinates":[-96.95197899999999,32.91689],"type":"Point"}
}