{
  "type": "Feature",
  "properties": {
    "iso:country":"US",
    "sg:address":"6201 W Bellfort St Ofc",
    "sg:city":"Houston",
    "sg:classifiers":[
        {
            "category":"Real Estate",
            "subcategory":"Real Estate Operator",
            "type":"Services"
        }
    ],
    "sg:phone":"+1 713 729 6795",
    "sg:postcode":"77035",
    "sg:province":"TX",
    "sg:tags":[
        "apartment"
    ],
    "wof:name":"Oakwood Villa",
    "wof:placetype":"venue"
},
  "geometry": {"coordinates":[-95.49949599999999,29.6569],"type":"Point"}
}