{
  "type": "Feature",
  "properties": {
    "iso:country":"US",
    "sg:address":"9862 Daisy Dr",
    "sg:city":"Corpus Christi",
    "sg:classifiers":[
        {
            "category":"Mining & Drilling",
            "type":"Manufacturing & Wholesale Goods"
        },
        {
            "category":"Manufacturing",
            "subcategory":"Lumber",
            "type":"Manufacturing & Wholesale Goods"
        }
    ],
    "sg:phone":"+1 361 241 7884",
    "sg:postcode":"78410",
    "sg:province":"TX",
    "sg:tags":[
        "field",
        "oil",
        "logging",
        "business"
    ],
    "wof:name":"Pay Zone Mud Logging Svc",
    "wof:placetype":"venue"
},
  "geometry": {"coordinates":[-97.556588,27.836573],"type":"Point"}
}