{
  "type": "Feature",
  "properties": {
    "iso:country":"US",
    "sg:address":"10615 Meadowglen Ln",
    "sg:city":"Houston",
    "sg:classifiers":[
        {
            "category":"Sports & Exercise",
            "subcategory":"Tennis Court",
            "type":"Entertainment"
        }
    ],
    "sg:phone":"+1 713 367 6307",
    "sg:postcode":"77042",
    "sg:province":"TX",
    "wof:name":"K & Z Tennis Academy",
    "wof:placetype":"venue"
},
  "geometry": {"coordinates":[-95.561528,29.731194],"type":"Point"}
}