{
  "type": "Feature",
  "properties": {
    "iso:country":"US",
    "sg:address":"5415 Westheimer Road",
    "sg:city":"Houston",
    "sg:classifiers":[
        {
            "category":"Travel",
            "subcategory":"Hotels & Motels",
            "type":"Entertainment"
        }
    ],
    "sg:phone":"+1 713 622 7010",
    "sg:postcode":"77056",
    "sg:province":"TX",
    "sg:website":"www.starwoodhotels.com/alofthote...",
    "wof:name":"Aloft Houston by the Galleria",
    "wof:placetype":"venue"
},
  "geometry": {"coordinates":[-95.471239,29.738888],"type":"Point"}
}