{
  "type": "Feature",
  "properties": {
    "iso:country":"US",
    "sg:address":"3129 Bryn Mawr Dr",
    "sg:city":"Dallas",
    "sg:classifiers":[
        {
            "category":"Travel",
            "subcategory":"Campground",
            "type":"Entertainment"
        }
    ],
    "sg:phone":"+1 214 691 3792",
    "sg:postcode":"75225",
    "sg:province":"TX",
    "sg:tags":[
        "camp"
    ],
    "wof:name":"Anglers & Hunters Inc",
    "wof:placetype":"venue"
},
  "geometry": {"coordinates":[-96.782287,32.855924],"type":"Point"}
}