{
  "type": "Feature",
  "properties": {
    "iso:country":"US",
    "sg:address":"510 Bering Dr",
    "sg:city":"Houston",
    "sg:classifiers":[
        {
            "category":"Professional",
            "subcategory":"Management & Consulting",
            "type":"Services"
        }
    ],
    "sg:phone":"+1 832 242 3508",
    "sg:postcode":"77057",
    "sg:province":"TX",
    "sg:tags":[
        "process",
        "implementation",
        "design",
        "strategic"
    ],
    "wof:name":"Many Worlds Consulting",
    "wof:placetype":"venue"
},
  "geometry": {"coordinates":[-95.478545,29.765154],"type":"Point"}
}