{
  "type": "Feature",
  "properties": {
    "iso:country":"US",
    "sg:address":"9024 Frock Ct",
    "sg:city":"Austin",
    "sg:classifiers":[
        {
            "category":"Food & Beverages",
            "subcategory":"Groceries & Convenience Stores",
            "type":"Retail Goods"
        }
    ],
    "sg:phone":"+1 512 933 9600",
    "sg:postcode":"78748",
    "sg:province":"TX",
    "wof:name":"Maliks Food Market",
    "wof:placetype":"venue"
},
  "geometry": {"coordinates":[-97.816756,30.182841],"type":"Point"}
}