{
  "type": "Feature",
  "properties": {
    "iso:country":"US",
    "sg:address":"511 Center St",
    "sg:city":"Mc Kinney",
    "sg:classifiers":[
        {
            "category":"Building & Trades",
            "subcategory":"Equipment Rental",
            "type":"Services"
        }
    ],
    "sg:phone":"+1 972 548 2245",
    "sg:postcode":"75069",
    "sg:province":"TX",
    "wof:name":"Cellular Pager Warehouse",
    "wof:placetype":"venue"
},
  "geometry": {"coordinates":[-96.60612399999999,33.205727],"type":"Point"}
}