{
  "type": "Feature",
  "properties": {
    "iso:country":"US",
    "sg:address":"813 Bandera Rd",
    "sg:city":"San Antonio",
    "sg:classifiers":[
        {
            "category":"Social Services",
            "type":"Services"
        }
    ],
    "sg:phone":"+1 210 432 1441",
    "sg:postcode":"78228",
    "sg:province":"TX",
    "sg:tags":[
        "care",
        "center",
        "day"
    ],
    "wof:name":"Exclusive Adult Daycare",
    "wof:placetype":"venue"
},
  "geometry": {"coordinates":[-98.55428999999999,29.456716],"type":"Point"}
}