{
  "type": "Feature",
  "properties": {
    "iso:country":"US",
    "sg:address":"311 Tallowood Dr",
    "sg:city":"Seabrook",
    "sg:classifiers":[
        {
            "category":"Building & Trades",
            "subcategory":"Equipment Rental",
            "type":"Services"
        }
    ],
    "sg:phone":"+1 281 326 4225",
    "sg:postcode":"77586",
    "sg:province":"TX",
    "sg:tags":[
        "medical"
    ],
    "wof:name":"Milky Way",
    "wof:placetype":"venue"
},
  "geometry": {"coordinates":[-95.04306099999999,29.573877],"type":"Point"}
}