{
  "type": "Feature",
  "properties": {
    "iso:country":"US",
    "sg:address":"232 W US Hwy 83",
    "sg:city":"San Juan",
    "sg:classifiers":[
        {
            "category":"Wholesale",
            "subcategory":"Machinery & Supplies",
            "type":"Manufacturing & Wholesale Goods"
        }
    ],
    "sg:phone":"+1 956 702 1056",
    "sg:postcode":"78589",
    "sg:province":"TX",
    "sg:tags":[
        "industrial"
    ],
    "wof:name":"San Juan Bolt & Supply",
    "wof:placetype":"venue"
},
  "geometry": {"coordinates":[-98.15816700000001,26.189935],"type":"Point"}
}