{
  "type": "Feature",
  "properties": {
    "iso:country":"US",
    "sg:address":"1968 State Hwy 321",
    "sg:city":"Dayton",
    "sg:classifiers":[
        {
            "category":"Food & Beverages",
            "subcategory":"Groceries & Convenience Stores",
            "type":"Retail Goods"
        }
    ],
    "sg:phone":"+1 936 257 8700",
    "sg:postcode":"77535",
    "sg:province":"TX",
    "wof:name":"Calhoun's Country Store Inc",
    "wof:placetype":"venue"
},
  "geometry": {"coordinates":[-94.898911,30.057155],"type":"Point"}
}