{
  "type": "Feature",
  "properties": {
    "iso:country":"US",
    "sg:address":"4815 South St",
    "sg:city":"Nacogdoches",
    "sg:classifiers":[
        {
            "category":"Wholesale",
            "subcategory":"Machinery & Supplies",
            "type":"Manufacturing & Wholesale Goods"
        }
    ],
    "sg:phone":"+1 936 564 4674",
    "sg:postcode":"75964",
    "sg:province":"TX",
    "sg:tags":[
        "poultry",
        "equipment"
    ],
    "wof:name":"D & B Distrs/Big Dutchman",
    "wof:placetype":"venue"
},
  "geometry": {"coordinates":[-94.679529,31.562725],"type":"Point"}
}