{
  "type": "Feature",
  "properties": {
    "iso:country":"US",
    "sg:address":"8803 Fredericksburg Rd",
    "sg:city":"San Antonio",
    "sg:classifiers":[
        {
            "category":"Retail",
            "subcategory":"Auto Repair",
            "type":"Services"
        }
    ],
    "sg:phone":"+1 210 696 7060",
    "sg:postcode":"78240",
    "sg:province":"TX",
    "sg:tags":[
        "automobile",
        "lubrication",
        "automotive"
    ],
    "wof:name":"Alamo Express Oil Change",
    "wof:placetype":"venue"
},
  "geometry": {"coordinates":[-98.57509400000001,29.526103],"type":"Point"}
}