{
  "type": "Feature",
  "properties": {
    "iso:country":"US",
    "sg:address":"817 W Loop 335 S",
    "sg:city":"Amarillo",
    "sg:classifiers":[
        {
            "category":"Autos & Motor Vehicles",
            "subcategory":"Fuel & Gas Station",
            "type":"Retail Goods"
        },
        {
            "category":"Autos & Motor Vehicles",
            "subcategory":"Auto Supplies",
            "type":"Retail Goods"
        },
        {
            "category":"Freight",
            "type":"Transportation"
        }
    ],
    "sg:phone":"+1 806 359 3882",
    "sg:postcode":"79118",
    "sg:province":"TX",
    "sg:tags":[
        "dry",
        "tank",
        "trucking-liquid",
        "trucking",
        "bulk",
        "truck"
    ],
    "sg:website":"http://www.kimrad.com",
    "wof:name":"Kimrad Transport",
    "wof:placetype":"venue"
},
  "geometry": {"coordinates":[-101.829508,35.120284],"type":"Point"}
}