{
  "type": "Feature",
  "properties": {
    "iso:country":"US",
    "sg:address":"126 Midway St",
    "sg:city":"Spring",
    "sg:classifiers":[
        {
            "category":"Home & Garden",
            "subcategory":"Furniture",
            "type":"Retail Goods"
        }
    ],
    "sg:phone":"+1 281 651 0088",
    "sg:postcode":"77373",
    "sg:province":"TX",
    "wof:name":"Boswell Rustic Roundup 1",
    "wof:placetype":"venue"
},
  "geometry": {"coordinates":[-95.41776400000001,30.079339],"type":"Point"}
}