{
  "type": "Feature",
  "properties": {
    "iso:country":"US",
    "sg:address":"563 Morrison Rd",
    "sg:city":"Howe",
    "sg:classifiers":[
        {
            "category":"Professional",
            "subcategory":"Business Services",
            "type":"Services"
        }
    ],
    "sg:phone":"+1 903 532 9000",
    "sg:postcode":"75459",
    "sg:province":"TX",
    "wof:name":"Roberts Enterprises",
    "wof:placetype":"venue"
},
  "geometry": {"coordinates":[-96.56341399999999,33.510563],"type":"Point"}
}