{
  "type": "Feature",
  "properties": {
    "iso:country":"US",
    "sg:address":"11517 Memorial Dr",
    "sg:city":"Houston",
    "sg:classifiers":[
        {
            "category":"Professional",
            "subcategory":"Business Services",
            "type":"Services"
        }
    ],
    "sg:phone":"+1 713 784 4088",
    "sg:postcode":"77024",
    "sg:province":"TX",
    "wof:name":"Eubanks Reba W Interest",
    "wof:placetype":"venue"
},
  "geometry": {"coordinates":[-95.52019199999999,29.751064],"type":"Point"}
}