{
  "type": "Feature",
  "properties": {
    "iso:country":"US",
    "sg:address":"122 Roundtree Ln",
    "sg:city":"San Antonio",
    "sg:classifiers":[
        {
            "category":"Building & Trades",
            "subcategory":"Construction",
            "type":"Services"
        }
    ],
    "sg:phone":"+1 210 379 7617",
    "sg:postcode":"78233",
    "sg:province":"TX",
    "sg:tags":[
        "painter"
    ],
    "wof:name":"Ben's Painting & Remodeling",
    "wof:placetype":"venue"
},
  "geometry": {"coordinates":[-98.380393,29.533331],"type":"Point"}
}