{
  "type": "Feature",
  "properties": {
    "iso:country":"US",
    "sg:address":"5902 Old Hwy 105 W",
    "sg:city":"Conroe",
    "sg:classifiers":[
        {
            "category":"Retail",
            "subcategory":"Auto Repair",
            "type":"Services"
        }
    ],
    "sg:phone":"+1 936 760 6700",
    "sg:postcode":"77304",
    "sg:province":"TX",
    "sg:tags":[
        "body"
    ],
    "wof:name":"Conroe Collision Center",
    "wof:placetype":"venue"
},
  "geometry": {"coordinates":[-95.554588,30.328622],"type":"Point"}
}