{
  "type": "Feature",
  "properties": {
    "iso:country":"US",
    "sg:address":"1003 N Jefferson Ave",
    "sg:city":"Mount Pleasant",
    "sg:classifiers":[
        {
            "category":"Health Services",
            "subcategory":"Doctor",
            "type":"Services"
        }
    ],
    "sg:phone":"+1 903 577 1123",
    "sg:postcode":"75455",
    "sg:province":"TX",
    "wof:name":"Robert L Cooper DDS",
    "wof:placetype":"venue"
},
  "geometry": {"coordinates":[-94.969762,33.165215],"type":"Point"}
}