{
  "type": "Feature",
  "properties": {
    "iso:country":"US",
    "sg:address":"1264 N Mechanic St",
    "sg:city":"El Campo",
    "sg:classifiers":[
        {
            "category":"Shopping",
            "subcategory":"Pharmacy",
            "type":"Retail Goods"
        }
    ],
    "sg:phone":"+1 979 543 2761",
    "sg:postcode":"77437",
    "sg:province":"TX",
    "wof:name":"Professional Pharmacy",
    "wof:placetype":"venue"
},
  "geometry": {"coordinates":[-96.27631599999999,29.204794],"type":"Point"}
}