{
  "type": "Feature",
  "properties": {
    "iso:country":"US",
    "sg:address":"401 Chester Dr",
    "sg:city":"Friendswood",
    "sg:classifiers":[
        {
            "category":"Building & Trades",
            "subcategory":"Landscaping Services",
            "type":"Services"
        }
    ],
    "sg:phone":"+1 281 482 4182",
    "sg:postcode":"77546",
    "sg:province":"TX",
    "sg:tags":[
        "landscape",
        "contractor"
    ],
    "wof:name":"Mccullough Landscaping",
    "wof:placetype":"venue"
},
  "geometry": {"coordinates":[-95.216133,29.52486],"type":"Point"}
}