{
  "type": "Feature",
  "properties": {
    "iso:country":"US",
    "sg:address":"1022 Braewick Ct",
    "sg:city":"Mesquite",
    "sg:classifiers":[
        {
            "category":"Organizations",
            "subcategory":"Religious Organization",
            "type":"Services"
        }
    ],
    "sg:phone":"+1 972 289 2486",
    "sg:postcode":"75181",
    "sg:province":"TX",
    "sg:tags":[
        "church"
    ],
    "wof:name":"Grace Family Church",
    "wof:placetype":"venue"
},
  "geometry": {"coordinates":[-96.5831,32.736445],"type":"Point"}
}