{
  "type": "Feature",
  "properties": {
    "iso:country":"US",
    "sg:address":"1025 N Loop 336 E",
    "sg:city":"Conroe",
    "sg:classifiers":[
        {
            "category":"Restaurant",
            "type":"Food & Drink"
        }
    ],
    "sg:phone":"+1 936 441 3773",
    "sg:postcode":"77301",
    "sg:province":"TX",
    "sg:website":"www.sfsarbys.com",
    "wof:name":"Arby's",
    "wof:placetype":"venue"
},
  "geometry": {"coordinates":[-95.43906699999999,30.339965],"type":"Point"}
}