{
  "type": "Feature",
  "properties": {
    "iso:country":"US",
    "sg:address":"5454 Old Hwy 105 W",
    "sg:city":"Conroe",
    "sg:classifiers":[
        {
            "category":"Sports & Exercise",
            "subcategory":"Golf",
            "type":"Entertainment"
        }
    ],
    "sg:phone":"+1 936 441 4653",
    "sg:postcode":"77304",
    "sg:province":"TX",
    "sg:tags":[
        "course",
        "public"
    ],
    "wof:name":"Wedgewood Golf Course",
    "wof:placetype":"venue"
},
  "geometry": {"coordinates":[-95.55518600000001,30.329481],"type":"Point"}
}