{
  "type": "Feature",
  "properties": {
    "iso:country":"US",
    "sg:address":"502 N Cleveland Ave",
    "sg:city":"Sherman",
    "sg:classifiers":[
        {
            "category":"Manufacturing",
            "subcategory":"Glass & Minerals",
            "type":"Manufacturing & Wholesale Goods"
        }
    ],
    "sg:phone":"+1 903 813 5593",
    "sg:postcode":"75090",
    "sg:province":"TX",
    "sg:tags":[
        "ready",
        "concrete",
        "mfg"
    ],
    "wof:name":"Home Make Ready",
    "wof:placetype":"venue"
},
  "geometry": {"coordinates":[-96.59282,33.64514],"type":"Point"}
}