{
  "type": "Feature",
  "properties": {
    "iso:country":"US",
    "sg:address":"7401 Vineyard Trl",
    "sg:city":"Garland",
    "sg:classifiers":[
        {
            "category":"Professional",
            "subcategory":"Business Services",
            "type":"Services"
        }
    ],
    "sg:phone":"+1 214 616 0112",
    "sg:postcode":"75044",
    "sg:province":"TX",
    "wof:name":"Aarons Home Inspections",
    "wof:placetype":"venue"
},
  "geometry": {"coordinates":[-96.670197,32.983491],"type":"Point"}
}