{
  "type": "Feature",
  "properties": {
    "iso:country":"US",
    "sg:address":"4106 N 22nd St",
    "sg:city":"Mcallen",
    "sg:classifiers":[
        {
            "category":"Professional",
            "subcategory":"Computer Services",
            "type":"Services"
        }
    ],
    "sg:phone":"+1 956 687 7104",
    "sg:postcode":"78504",
    "sg:province":"TX",
    "sg:tags":[
        "networking"
    ],
    "wof:name":"McAllen Marketing Group",
    "wof:placetype":"venue"
},
  "geometry": {"coordinates":[-98.237048,26.243367],"type":"Point"}
}