{
  "type": "Feature",
  "properties": {
    "iso:country":"US",
    "sg:address":"6221 Bandera Rd",
    "sg:city":"San Antonio",
    "sg:classifiers":[
        {
            "category":"Autos & Motor Vehicles",
            "subcategory":"Auto Supplies",
            "type":"Retail Goods"
        }
    ],
    "sg:phone":"+1 210 523 1361",
    "sg:postcode":"78238",
    "sg:province":"TX",
    "wof:name":"Discount Tire / Americas Tire",
    "wof:placetype":"venue"
},
  "geometry": {"coordinates":[-98.607568,29.486926],"type":"Point"}
}