{
  "type": "Feature",
  "properties": {
    "iso:country":"US",
    "sg:address":"6913 Miramar Cir",
    "sg:city":"Fort Worth",
    "sg:classifiers":[
        {
            "category":"Professional",
            "subcategory":"Management & Consulting",
            "type":"Services"
        }
    ],
    "sg:phone":"+1 817 738 1450",
    "sg:postcode":"76126",
    "sg:province":"TX",
    "sg:tags":[
        "public",
        "relations"
    ],
    "wof:name":"The A/M/G Company",
    "wof:placetype":"venue"
},
  "geometry": {"coordinates":[-97.42945,32.687079],"type":"Point"}
}