{
  "type": "Feature",
  "properties": {
    "iso:country":"US",
    "sg:address":"914 Dawson Rd",
    "sg:city":"Austin",
    "sg:classifiers":[
        {
            "category":"Education",
            "subcategory":"School",
            "type":"Public Place"
        }
    ],
    "sg:phone":"+1 512 448 1840",
    "sg:postcode":"78704",
    "sg:province":"TX",
    "sg:tags":[
        "gallery"
    ],
    "wof:name":"Imagine Art",
    "wof:placetype":"venue"
},
  "geometry": {"coordinates":[-97.75733200000001,30.255859],"type":"Point"}
}