{
  "type": "Feature",
  "properties": {
    "iso:country":"US",
    "sg:address":"24 del Norte St",
    "sg:city":"Lampasas",
    "sg:classifiers":[
        {
            "category":"Personal",
            "subcategory":"Beauty Salon",
            "type":"Services"
        }
    ],
    "sg:phone":"+1 512 556 8299",
    "sg:postcode":"76550",
    "sg:province":"TX",
    "sg:tags":[
        "shop"
    ],
    "wof:name":"Chatterbox",
    "wof:placetype":"venue"
},
  "geometry": {"coordinates":[-98.174288,31.056462],"type":"Point"}
}