{
  "type": "Feature",
  "properties": {
    "iso:country":"US",
    "sg:address":"1103 Fredericksburg Rd",
    "sg:city":"San Antonio",
    "sg:classifiers":[
        {
            "category":"Retail",
            "subcategory":"Repair Shop",
            "type":"Services"
        }
    ],
    "sg:phone":"+1 210 666 5485",
    "sg:postcode":"78201",
    "sg:province":"TX",
    "sg:tags":[
        "appliance"
    ],
    "wof:name":"Affordable Appliance Svc",
    "wof:placetype":"venue"
},
  "geometry": {"coordinates":[-98.516223,29.454338],"type":"Point"}
}