{
  "type": "Feature",
  "properties": {
    "iso:country":"US",
    "sg:address":"123 Tumbleweed Trl",
    "sg:city":"Fredericksburg",
    "sg:classifiers":[
        {
            "category":"Shopping",
            "subcategory":"Crafts & Fabrics",
            "type":"Retail Goods"
        }
    ],
    "sg:phone":"+1 830 990 4629",
    "sg:postcode":"78624",
    "sg:province":"TX",
    "sg:tags":[
        "sewing"
    ],
    "wof:name":"Suzanne Roddy Handweaver",
    "wof:placetype":"venue"
},
  "geometry": {"coordinates":[-98.868201,30.235897],"type":"Point"}
}