{
  "type": "Feature",
  "properties": {
    "iso:country":"US",
    "sg:address":"18951 Cypresswood Forest Ct",
    "sg:city":"Spring",
    "sg:classifiers":[
        {
            "category":"Shopping",
            "subcategory":"Clothing, Apparel, & Fashions",
            "type":"Retail Goods"
        }
    ],
    "sg:phone":"+1 281 288 8898",
    "sg:postcode":"77388",
    "sg:province":"TX",
    "sg:tags":[
        "family"
    ],
    "wof:name":"Hosannas Outpost",
    "wof:placetype":"venue"
},
  "geometry": {"coordinates":[-95.458089,30.043318],"type":"Point"}
}