{
  "type": "Feature",
  "properties": {
    "iso:country":"US",
    "sg:address":"7004 S Gessner Dr",
    "sg:city":"Houston",
    "sg:classifiers":[
        {
            "category":"Retail",
            "subcategory":"Auto Repair",
            "type":"Services"
        }
    ],
    "sg:phone":"+1 713 988 4006",
    "sg:postcode":"77036",
    "sg:province":"TX",
    "wof:name":"Tune Up Plus No 14",
    "wof:placetype":"venue"
},
  "geometry": {"coordinates":[-95.5382,29.704901],"type":"Point"}
}