{
  "type": "Feature",
  "properties": {
    "iso:country":"US",
    "sg:address":"1737 S Cooper St",
    "sg:city":"Arlington",
    "sg:classifiers":[
        {
            "category":"Food & Beverages",
            "subcategory":"Bakery",
            "type":"Retail Goods"
        }
    ],
    "sg:phone":"+1 817 548 5730",
    "sg:postcode":"76010",
    "sg:province":"TX",
    "sg:tags":[
        "product",
        "mfg"
    ],
    "wof:name":"Q Donuts Inc",
    "wof:placetype":"venue"
},
  "geometry": {"coordinates":[-97.114672,32.718295],"type":"Point"}
}