{
  "type": "Feature",
  "properties": {
    "iso:country":"US",
    "sg:address":"2857 Central Dr",
    "sg:city":"Bedford",
    "sg:classifiers":[
        {
            "category":"Restaurant",
            "type":"Food & Drink"
        }
    ],
    "sg:menulink":"http://www.allmenus.com/tx/northeast-tarrant/86677-little-caesars-pizza/menu/",
    "sg:phone":"+1 817 288 3010",
    "sg:postcode":"76021",
    "sg:province":"TX",
    "sg:tags":[
        "american",
        "pizza"
    ],
    "wof:name":"Little Caesar's Pizza",
    "wof:placetype":"venue"
},
  "geometry": {"coordinates":[-97.13196000000001,32.850954],"type":"Point"}
}