{
  "type": "Feature",
  "properties": {
    "iso:country":"US",
    "sg:address":"11308 Cotillion Dr",
    "sg:city":"Dallas",
    "sg:classifiers":[
        {
            "category":"Manufacturing",
            "subcategory":"Tools & Machinery",
            "type":"Manufacturing & Wholesale Goods"
        }
    ],
    "sg:phone":"+1 972 270 3840",
    "sg:postcode":"75228",
    "sg:province":"TX",
    "sg:tags":[
        "equipment",
        "material",
        "handling"
    ],
    "wof:name":"Handling Equipment Corp",
    "wof:placetype":"venue"
},
  "geometry": {"coordinates":[-96.65280199999999,32.849058],"type":"Point"}
}