{
  "type": "Feature",
  "properties": {
    "iso:country":"US",
    "sg:address":"3501 Austin St",
    "sg:city":"Corpus Christi",
    "sg:classifiers":[
        {
            "category":"Building & Trades",
            "subcategory":"Plumbing",
            "type":"Services"
        }
    ],
    "sg:phone":"+1 361 853 2910",
    "sg:postcode":"78411",
    "sg:province":"TX",
    "sg:tags":[
        "plumbing"
    ],
    "wof:name":"Sunset Plumbing Inc",
    "wof:placetype":"venue"
},
  "geometry": {"coordinates":[-97.382502,27.749159],"type":"Point"}
}