{
  "type": "Feature",
  "properties": {
    "iso:country":"US",
    "sg:address":"607 W Russell Pl",
    "sg:city":"San Antonio",
    "sg:classifiers":[
        {
            "category":"Personal",
            "subcategory":"Beauty Salon",
            "type":"Services"
        }
    ],
    "sg:phone":"+1 210 736 1884",
    "sg:postcode":"78212",
    "sg:province":"TX",
    "sg:tags":[
        "shop"
    ],
    "wof:name":"Carreras Hairstyling",
    "wof:placetype":"venue"
},
  "geometry": {"coordinates":[-98.500934,29.451103],"type":"Point"}
}