{
  "type": "Feature",
  "properties": {
    "iso:country":"US",
    "sg:address":"701 S West St",
    "sg:city":"Arlington",
    "sg:classifiers":[
        {
            "category":"Education",
            "subcategory":"College",
            "type":"Public Place"
        }
    ],
    "sg:phone":"+1 817 272 3481",
    "sg:postcode":"76010",
    "sg:province":"TX",
    "sg:tags":[
        "academic",
        "school"
    ],
    "wof:name":"University Of Texas",
    "wof:placetype":"venue"
},
  "geometry": {"coordinates":[-97.11108400000001,32.72921],"type":"Point"}
}