{
  "type": "Feature",
  "properties": {
    "iso:country":"US",
    "sg:address":"7511 Beaudelaire Cir",
    "sg:city":"Galveston",
    "sg:classifiers":[
        {
            "category":"Manufacturing",
            "subcategory":"Retail Goods",
            "type":"Manufacturing & Wholesale Goods"
        }
    ],
    "sg:phone":"+1 409 765 8411",
    "sg:postcode":"77551",
    "sg:province":"TX",
    "sg:tags":[
        "product",
        "mfg"
    ],
    "wof:name":"Bastien Industries Inc",
    "wof:placetype":"venue"
},
  "geometry": {"coordinates":[-94.84306100000001,29.261017],"type":"Point"}
}