{
  "type": "Feature",
  "properties": {
    "iso:country":"US",
    "sg:address":"3298 South Loop W",
    "sg:city":"Houston",
    "sg:classifiers":[
        {
            "category":"Shopping",
            "subcategory":"Jewelry",
            "type":"Retail Goods"
        },
        {
            "category":"Shopping",
            "subcategory":"Pawn Shop",
            "type":"Retail Goods"
        }
    ],
    "sg:phone":"+1 713 662 2924",
    "sg:postcode":"77025",
    "sg:province":"TX",
    "wof:name":"Top Dollar Pawn",
    "wof:placetype":"venue"
},
  "geometry": {"coordinates":[-95.42900299999999,29.678415],"type":"Point"}
}