{
  "type": "Feature",
  "properties": {
    "iso:country":"US",
    "sg:address":"2810 Gonzales St",
    "sg:city":"Austin",
    "sg:classifiers":[
        {
            "category":"Building & Trades",
            "subcategory":"Cleaning & Sanitation",
            "type":"Services"
        }
    ],
    "sg:phone":"+1 512 385 7921",
    "sg:postcode":"78702",
    "sg:province":"TX",
    "sg:tags":[
        "janitor"
    ],
    "wof:name":"Tex-Maid Cleaning Svc",
    "wof:placetype":"venue"
},
  "geometry": {"coordinates":[-97.707576,30.259608],"type":"Point"}
}