{
  "type": "Feature",
  "properties": {
    "iso:country":"US",
    "sg:address":"2710 Ridgeview Rd",
    "sg:city":"Paris",
    "sg:classifiers":[
        {
            "category":"Professional",
            "subcategory":"Business Services",
            "type":"Services"
        }
    ],
    "sg:phone":"+1 903 783 9148",
    "sg:postcode":"75460",
    "sg:province":"TX",
    "wof:name":"Paris Design Co",
    "wof:placetype":"venue"
},
  "geometry": {"coordinates":[-95.527934,33.66882],"type":"Point"}
}