{
  "type": "Feature",
  "properties": {
    "iso:country":"US",
    "sg:address":"2427 Woodtown Dr",
    "sg:city":"Houston",
    "sg:classifiers":[
        {
            "category":"Professional",
            "type":"Services"
        }
    ],
    "sg:phone":"+1 281 591 6533",
    "sg:postcode":"77038",
    "sg:province":"TX",
    "wof:name":"John Retail",
    "wof:placetype":"venue"
},
  "geometry": {"coordinates":[-95.45585699999999,29.928863],"type":"Point"}
}