{
  "type": "Feature",
  "properties": {
    "iso:country":"US",
    "sg:address":"2000 E Randol Mill Rd",
    "sg:city":"Arlington",
    "sg:classifiers":[
        {
            "category":"Manufacturing",
            "subcategory":"Chemicals & Compounds",
            "type":"Manufacturing & Wholesale Goods"
        }
    ],
    "sg:phone":"+1 817 459 2609",
    "sg:postcode":"76011",
    "sg:province":"TX",
    "wof:name":"Lynn Laboratories",
    "wof:placetype":"venue"
},
  "geometry": {"coordinates":[-97.079232,32.749481],"type":"Point"}
}