{
  "type": "Feature",
  "properties": {
    "iso:country":"US",
    "sg:address":"2407 S Bell Blvd",
    "sg:city":"Cedar Park",
    "sg:classifiers":[
        {
            "category":"Real Estate",
            "subcategory":"Real Estate Agent",
            "type":"Services"
        }
    ],
    "sg:phone":"+1 512 335 4554",
    "sg:postcode":"78613",
    "sg:province":"TX",
    "wof:name":"KERA Realty",
    "wof:placetype":"venue"
},
  "geometry": {"coordinates":[-97.804653,30.481167],"type":"Point"}
}