{
  "type": "Feature",
  "properties": {
    "iso:country":"US",
    "sg:address":"2301 N Chandler Dr W",
    "sg:city":"Fort Worth",
    "sg:classifiers":[
        {
            "category":"Retail",
            "subcategory":"Repair Shop",
            "type":"Services"
        }
    ],
    "sg:phone":"+1 817 834 2703",
    "sg:postcode":"76111",
    "sg:province":"TX",
    "wof:name":"A Trusted Locksmith",
    "wof:placetype":"venue"
},
  "geometry": {"coordinates":[-97.304041,32.79387],"type":"Point"}
}