{
  "type": "Feature",
  "properties": {
    "iso:country":"US",
    "sg:address":"2500 E Rosedale St",
    "sg:city":"Fort Worth",
    "sg:classifiers":[
        {
            "category":"Real Estate",
            "subcategory":"Real Estate Agent",
            "type":"Services"
        }
    ],
    "sg:phone":"+1 817 531 8386",
    "sg:postcode":"76105",
    "sg:province":"TX",
    "wof:name":"Ferco Property Management",
    "wof:placetype":"venue"
},
  "geometry": {"coordinates":[-97.29065199999999,32.730767],"type":"Point"}
}