{
  "type": "Feature",
  "properties": {
    "iso:country":"US",
    "sg:address":"637 Cypress Creek Rd",
    "sg:city":"Kerrville",
    "sg:classifiers":[
        {
            "category":"Manufacturing",
            "subcategory":"Glass & Minerals",
            "type":"Manufacturing & Wholesale Goods"
        }
    ],
    "sg:phone":"+1 830 995 4035",
    "sg:postcode":"78028",
    "sg:province":"TX",
    "sg:tags":[
        "product",
        "structural",
        "clay"
    ],
    "sg:website":"www.apt2products.com",
    "wof:name":"Apt II Products Co",
    "wof:placetype":"venue"
},
  "geometry": {"coordinates":[-99.085252,30.057062],"type":"Point"}
}