{
  "type": "Feature",
  "properties": {
    "iso:country":"US",
    "sg:address":"112 N San Horacio Ave",
    "sg:city":"San Antonio",
    "sg:classifiers":[
        {
            "category":"Organizations",
            "subcategory":"Religious Organization",
            "type":"Services"
        }
    ],
    "sg:phone":"+1 210 435 5677",
    "sg:postcode":"78237",
    "sg:province":"TX",
    "sg:tags":[
        "church"
    ],
    "wof:name":"Solo Cristo Church",
    "wof:placetype":"venue"
},
  "geometry": {"coordinates":[-98.56026799999999,29.433974],"type":"Point"}
}