{
  "type": "Feature",
  "properties": {
    "iso:country":"US",
    "sg:address":"515 W Greens Rd",
    "sg:city":"Houston",
    "sg:classifiers":[
        {
            "category":"Professional",
            "subcategory":"Employment Agencies",
            "type":"Services"
        }
    ],
    "sg:phone":"+1 281 872 1000",
    "sg:postcode":"77067",
    "sg:province":"TX",
    "sg:tags":[
        "temporary",
        "help",
        "supply"
    ],
    "wof:name":"Connection Group The",
    "wof:placetype":"venue"
},
  "geometry": {"coordinates":[-95.423875,29.948964],"type":"Point"}
}