{
  "type": "Feature",
  "properties": {
    "iso:country":"US",
    "sg:address":"2747 Cypress Ave",
    "sg:city":"Dallas",
    "sg:classifiers":[
        {
            "category":"Professional",
            "subcategory":"Business Services",
            "type":"Services"
        }
    ],
    "sg:phone":"+1 214 388 1987",
    "sg:postcode":"75227",
    "sg:province":"TX",
    "wof:name":"Jester Flay",
    "wof:placetype":"venue"
},
  "geometry": {"coordinates":[-96.661783,32.759278],"type":"Point"}
}