{
  "type": "Feature",
  "properties": {
    "iso:country":"US",
    "sg:address":"8010 Woodcliff Blvd",
    "sg:city":"Selma",
    "sg:classifiers":[
        {
            "category":"Building & Trades",
            "subcategory":"Construction",
            "type":"Services"
        }
    ],
    "sg:phone":"+1 210 651 6626",
    "sg:postcode":"78154",
    "sg:province":"TX",
    "sg:tags":[
        "demolition",
        "contractor"
    ],
    "wof:name":"Troy Inc",
    "wof:placetype":"venue"
},
  "geometry": {"coordinates":[-98.32767800000001,29.578699],"type":"Point"}
}