{
  "type": "Feature",
  "properties": {
    "iso:country":"US",
    "sg:address":"601 Neri Rd",
    "sg:city":"Granbury",
    "sg:classifiers":[
        {
            "category":"Professional",
            "type":"Services"
        }
    ],
    "sg:phone":"+1 817 579 5618",
    "sg:postcode":"76048",
    "sg:province":"TX",
    "wof:name":"Jack B Morton",
    "wof:placetype":"venue"
},
  "geometry": {"coordinates":[-97.782076,32.363555],"type":"Point"}
}