{
  "type": "Feature",
  "properties": {
    "iso:country":"US",
    "sg:address":"1 Old Mill Cir",
    "sg:city":"Gainesville",
    "sg:classifiers":[
        {
            "category":"Retail",
            "subcategory":"Repair Shop",
            "type":"Services"
        }
    ],
    "sg:phone":"+1 940 665 1449",
    "sg:postcode":"76240",
    "sg:province":"TX",
    "sg:tags":[
        "help",
        "supply"
    ],
    "wof:name":"Lcc/TV Inc",
    "wof:placetype":"venue"
},
  "geometry": {"coordinates":[-97.165728,33.621641],"type":"Point"}
}