{
  "type": "Feature",
  "properties": {
    "iso:country":"US",
    "sg:address":"1006 E Pacific Ave",
    "sg:city":"Gladewater",
    "sg:classifiers":[
        {
            "category":"Government",
            "subcategory":"Office",
            "type":"Public Place"
        }
    ],
    "sg:phone":"+1 903 845 2694",
    "sg:postcode":"75647",
    "sg:province":"TX",
    "sg:tags":[
        "govt",
        "city"
    ],
    "wof:name":"Gladewater Water & Sewer Dept",
    "wof:placetype":"venue"
},
  "geometry": {"coordinates":[-94.93203699999999,32.531715],"type":"Point"}
}