{
  "type": "Feature",
  "properties": {
    "iso:country":"US",
    "sg:address":"1116 N Elm St",
    "sg:city":"Denton",
    "sg:classifiers":[
        {
            "category":"Health Services",
            "subcategory":"Doctor",
            "type":"Services"
        }
    ],
    "sg:phone":"+1 940 566 1921",
    "sg:postcode":"76201",
    "sg:province":"TX",
    "sg:tags":[
        "dentist"
    ],
    "wof:name":"John D White DDS Inc",
    "wof:placetype":"venue"
},
  "geometry": {"coordinates":[-97.133494,33.223634],"type":"Point"}
}