{
  "type": "Feature",
  "properties": {
    "iso:country":"US",
    "sg:address":"1415 Hwy 6 S Building C-400",
    "sg:city":"Stafford",
    "sg:classifiers":[
        {
            "category":"Health Services",
            "subcategory":"Doctor",
            "type":"Services"
        }
    ],
    "sg:phone":"+1 281 491 9278",
    "sg:postcode":"77477",
    "sg:province":"TX",
    "sg:tags":[
        "dermatologist"
    ],
    "sg:website":"www.drpolingerderm.com/",
    "wof:name":"Iris S Polinger MD PHD PA",
    "wof:placetype":"venue"
},
  "geometry": {"coordinates":[-95.56459,29.615257],"type":"Point"}
}