{
  "type": "Feature",
  "properties": {
    "iso:country":"US",
    "sg:address":"254 Spencer Ln",
    "sg:city":"San Antonio",
    "sg:classifiers":[
        {
            "category":"Freight",
            "type":"Transportation"
        }
    ],
    "sg:phone":"+1 210 735 9393",
    "sg:postcode":"78201",
    "sg:province":"TX",
    "sg:tags":[
        "operator",
        "mini",
        "building"
    ],
    "wof:name":"A-AAA KEY MINI STORAGE",
    "wof:placetype":"venue"
},
  "geometry": {"coordinates":[-98.539925,29.484217],"type":"Point"}
}