{
  "type": "Feature",
  "properties": {
    "iso:country":"US",
    "sg:address":"2440 Preston Rd",
    "sg:city":"Plano",
    "sg:classifiers":[
        {
            "category":"Real Estate",
            "subcategory":"Real Estate Agent",
            "type":"Services"
        }
    ],
    "sg:phone":"+1 972 931 9000",
    "sg:postcode":"75093",
    "sg:province":"TX",
    "sg:website":"www.prurealty.com",
    "wof:name":"Prudential Texas Properties",
    "wof:placetype":"venue"
},
  "geometry": {"coordinates":[-96.794735,33.028835],"type":"Point"}
}