{
  "type": "Feature",
  "properties": {
    "iso:country":"US",
    "sg:address":"1700 11th St",
    "sg:city":"Huntsville",
    "sg:classifiers":[
        {
            "category":"Personal",
            "subcategory":"Beauty Salon",
            "type":"Services"
        }
    ],
    "sg:phone":"+1 936 291 9800",
    "sg:postcode":"77320",
    "sg:province":"TX",
    "wof:name":"Just Style'n",
    "wof:placetype":"venue"
},
  "geometry": {"coordinates":[-95.556387,30.723559],"type":"Point"}
}