{
  "type": "Feature",
  "properties": {
    "iso:country":"US",
    "sg:address":"5800 Airport Blvd",
    "sg:city":"Austin",
    "sg:classifiers":[
        {
            "category":"Professional",
            "type":"Services"
        },
        {
            "category":"Professional",
            "subcategory":"Advertising",
            "type":"Services"
        },
        {
            "category":"Banks & Credit Unions",
            "subcategory":"Financial Services",
            "type":"Services"
        }
    ],
    "sg:phone":"+1 512 794 7500",
    "sg:postcode":"78752",
    "sg:province":"TX",
    "sg:tags":[
        "mail",
        "direct"
    ],
    "sg:website":"www.dnb.com",
    "wof:name":"Dun & Bradstreet",
    "wof:placetype":"venue"
},
  "geometry": {"coordinates":[-97.714685,30.322276],"type":"Point"}
}