{
  "type": "Feature",
  "properties": {
    "iso:country":"US",
    "sg:address":"350 W Pleasant Run Rd",
    "sg:city":"Lancaster",
    "sg:classifiers":[
        {
            "category":"Retail",
            "subcategory":"Laundry & Dry Cleaning",
            "type":"Services"
        }
    ],
    "sg:phone":"+1 972 227 1511",
    "sg:postcode":"75146",
    "sg:province":"TX",
    "sg:tags":[
        "plant"
    ],
    "wof:name":"Underwood Cleaners",
    "wof:placetype":"venue"
},
  "geometry": {"coordinates":[-96.761455,32.603919],"type":"Point"}
}