{
  "type": "Feature",
  "properties": {
    "iso:country":"US",
    "sg:address":"1008 Swallow Dr",
    "sg:city":"Manchaca",
    "sg:classifiers":[
        {
            "category":"Real Estate",
            "subcategory":"Real Estate Agent",
            "type":"Services"
        }
    ],
    "sg:phone":"+1 512 292 6554",
    "sg:postcode":"78652",
    "sg:province":"TX",
    "wof:name":"Central Texas Appraisals",
    "wof:placetype":"venue"
},
  "geometry": {"coordinates":[-97.88575899999999,30.137723],"type":"Point"}
}