{
  "type": "Feature",
  "properties": {
    "iso:country":"US",
    "sg:address":"4526 Glenwood Ave",
    "sg:city":"Deer Park",
    "sg:classifiers":[
        {
            "category":"Organizations",
            "subcategory":"Religious Organization",
            "type":"Services"
        }
    ],
    "sg:phone":"+1 281 479 0558",
    "sg:postcode":"77536",
    "sg:province":"TX",
    "wof:name":"Glenwood Baptist Church",
    "wof:placetype":"venue"
},
  "geometry": {"coordinates":[-95.131415,29.66509],"type":"Point"}
}