{
  "type": "Feature",
  "properties": {
    "iso:country":"US",
    "sg:address":"2620 S Lamar Blvd",
    "sg:city":"Austin",
    "sg:phone":"+1 512 442 9700",
    "sg:postcode":"78704",
    "sg:province":"TX",
    "sg:website":"http://www.cellrepairofaustin.com",
    "wof:name":"Cell Repair of Austin",
    "wof:placetype":"venue"
},
  "geometry": {"coordinates":[-97.779383,30.24572],"type":"Point"}
}