{
  "type": "Feature",
  "properties": {
    "iso:country":"US",
    "sg:address":"2555 64th St",
    "sg:city":"Port Arthur",
    "sg:classifiers":[
        {
            "category":"Manufacturing",
            "subcategory":"Wood Products",
            "type":"Manufacturing & Wholesale Goods"
        }
    ],
    "sg:phone":"+1 409 736 2283",
    "sg:postcode":"77640",
    "sg:province":"TX",
    "sg:tags":[
        "mfg"
    ],
    "wof:name":"Wood N Names Etc",
    "wof:placetype":"venue"
},
  "geometry": {"coordinates":[-94.02351299999999,29.907595],"type":"Point"}
}