{
  "type": "Feature",
  "properties": {
    "iso:country":"US",
    "sg:address":"3036 Mockingbird Ln",
    "sg:city":"Dallas",
    "sg:classifiers":[
        {
            "category":"Coffee & Tea",
            "type":"Food & Drink"
        }
    ],
    "sg:menulink":"http://www.allmenus.com/tx/northeast/112799-starbucks-coffee/menu/",
    "sg:phone":"+1 214 691 2484",
    "sg:postcode":"75205",
    "sg:province":"TX",
    "sg:tags":[
        "american"
    ],
    "wof:name":"Starbucks Coffee",
    "wof:placetype":"venue"
},
  "geometry": {"coordinates":[-96.779967,32.836662],"type":"Point"}
}