{
  "type": "Feature",
  "properties": {
    "iso:country":"US",
    "sg:address":"9030 Monroe Rd",
    "sg:city":"Houston",
    "sg:classifiers":[
        {
            "category":"Professional",
            "subcategory":"Management & Consulting",
            "type":"Services"
        }
    ],
    "sg:phone":"+1 713 947 9292",
    "sg:postcode":"77061",
    "sg:province":"TX",
    "sg:tags":[
        "consultant",
        "energy",
        "conservation"
    ],
    "sg:website":"www.heathus.com",
    "wof:name":"Heath Consultants Inc",
    "wof:placetype":"venue"
},
  "geometry": {"coordinates":[-95.264691,29.638944],"type":"Point"}
}