{
  "type": "Feature",
  "properties": {
    "iso:country":"US",
    "sg:address":"595 N Maple St",
    "sg:city":"Van",
    "sg:classifiers":[
        {
            "category":"Autos & Motor Vehicles",
            "subcategory":"Fuel & Gas Station",
            "type":"Retail Goods"
        }
    ],
    "sg:phone":"+1 903 963 5804",
    "sg:postcode":"75790",
    "sg:province":"TX",
    "sg:tags":[
        "station",
        "gasoline"
    ],
    "wof:name":"Citgo",
    "wof:placetype":"venue"
},
  "geometry": {"coordinates":[-95.637433,32.529949],"type":"Point"}
}