{
  "type": "Feature",
  "properties": {
    "iso:country":"US",
    "sg:address":"2910 S Beckley Ave",
    "sg:city":"Dallas",
    "sg:classifiers":[
        {
            "category":"Education",
            "subcategory":"School",
            "type":"Public Place"
        }
    ],
    "sg:phone":"+1 972 925 8200",
    "sg:postcode":"75224",
    "sg:province":"TX",
    "sg:website":"www.dallasisd.org",
    "wof:name":"Dallas Independent School District",
    "wof:placetype":"venue"
},
  "geometry": {"coordinates":[-96.822807,32.710965],"type":"Point"}
}