{
  "type": "Feature",
  "properties": {
    "iso:country":"US",
    "sg:address":"2314 Rock Ledge Dr",
    "sg:city":"Georgetown",
    "sg:classifiers":[
        {
            "category":"Professional",
            "subcategory":"Engineering",
            "type":"Services"
        }
    ],
    "sg:phone":"+1 512 630 8600",
    "sg:postcode":"78626",
    "sg:province":"TX",
    "wof:name":"Brandon Couch",
    "wof:placetype":"venue"
},
  "geometry": {"coordinates":[-97.652523,30.634465],"type":"Point"}
}