{
  "type": "Feature",
  "properties": {
    "iso:country":"US",
    "sg:address":"4712 Cavalcade St",
    "sg:city":"Houston",
    "sg:classifiers":[
        {
            "category":"Organizations",
            "subcategory":"Religious Organization",
            "type":"Services"
        }
    ],
    "sg:phone":"+1 713 675 0894",
    "sg:postcode":"77026",
    "sg:province":"TX",
    "wof:name":"Union Memorial Methdst Church",
    "wof:placetype":"venue"
},
  "geometry": {"coordinates":[-95.323189,29.800099],"type":"Point"}
}