{
  "type": "Feature",
  "properties": {
    "iso:country":"US",
    "sg:address":"304 Lake Ter",
    "sg:city":"Rockwall",
    "sg:classifiers":[
        {
            "category":"Professional",
            "subcategory":"Management & Consulting",
            "type":"Services"
        }
    ],
    "sg:phone":"+1 972 618 9630",
    "sg:postcode":"75087",
    "sg:province":"TX",
    "sg:tags":[
        "engineering"
    ],
    "wof:name":"Power Systems Solutions",
    "wof:placetype":"venue"
},
  "geometry": {"coordinates":[-96.46787,32.934179],"type":"Point"}
}