{
  "type": "Feature",
  "properties": {
    "iso:country":"US",
    "sg:address":"1646 Bending Oaks Trl",
    "sg:city":"Dallas",
    "sg:classifiers":[
        {
            "category":"Wholesale",
            "subcategory":"Construction Materials",
            "type":"Manufacturing & Wholesale Goods"
        }
    ],
    "sg:phone":"+1 214 398 2880",
    "sg:postcode":"75217",
    "sg:province":"TX",
    "wof:name":"Johnson Sand & Gravel",
    "wof:placetype":"venue"
},
  "geometry": {"coordinates":[-96.65966,32.740351],"type":"Point"}
}