{
  "type": "Feature",
  "properties": {
    "iso:country":"US",
    "sg:address":"3705 Pulsar Dr",
    "sg:city":"Garland",
    "sg:classifiers":[
        {
            "category":"Real Estate",
            "subcategory":"Real Estate Agent",
            "type":"Services"
        }
    ],
    "sg:phone":"+1 972 414 9833",
    "sg:postcode":"75044",
    "sg:province":"TX",
    "wof:name":"Cox Ronald H Associates",
    "wof:placetype":"venue"
},
  "geometry": {"coordinates":[-96.66860699999999,32.951046],"type":"Point"}
}