{
  "type": "Feature",
  "properties": {
    "iso:country":"US",
    "sg:address":"2901 Bristol Glen Ct",
    "sg:city":"Southlake",
    "sg:classifiers":[
        {
            "category":"Professional",
            "type":"Services"
        }
    ],
    "sg:phone":"+1 817 431 3867",
    "sg:postcode":"76092",
    "sg:province":"TX",
    "wof:name":"David M Gregor",
    "wof:placetype":"venue"
},
  "geometry": {"coordinates":[-97.19762299999999,32.94227],"type":"Point"}
}