{
  "type": "Feature",
  "properties": {
    "iso:country":"US",
    "sg:address":"2443 Forest Park Blvd",
    "sg:city":"Fort Worth",
    "sg:classifiers":[
        {
            "category":"Restaurant",
            "type":"Food & Drink"
        }
    ],
    "sg:phone":"+1 817 922 0808",
    "sg:postcode":"76110",
    "sg:province":"TX",
    "sg:tags":[
        "eating"
    ],
    "wof:name":"Pegasus Restaurant",
    "wof:placetype":"venue"
},
  "geometry": {"coordinates":[-97.351833,32.718402],"type":"Point"}
}