{
  "type": "Feature",
  "properties": {
    "iso:country":"US",
    "sg:address":"2005 Vatican Ln",
    "sg:city":"Dallas",
    "sg:classifiers":[
        {
            "category":"Building & Trades",
            "subcategory":"Construction",
            "type":"Services"
        }
    ],
    "sg:phone":"+1 214 331 2180",
    "sg:postcode":"75224",
    "sg:province":"TX",
    "sg:tags":[
        "general",
        "contractor"
    ],
    "wof:name":"S & W Construction",
    "wof:placetype":"venue"
},
  "geometry": {"coordinates":[-96.85350099999999,32.693536],"type":"Point"}
}