{
  "type": "Feature",
  "properties": {
    "iso:country":"US",
    "sg:address":"2111 Lakeview Loop",
    "sg:city":"Killeen",
    "sg:classifiers":[
        {
            "category":"Organizations",
            "subcategory":"Labor Organization",
            "type":"Services"
        }
    ],
    "sg:phone":"+1 254 699 3392",
    "sg:postcode":"76543",
    "sg:province":"TX",
    "wof:name":"Hicar Management Lc",
    "wof:placetype":"venue"
},
  "geometry": {"coordinates":[-97.679776,31.083612],"type":"Point"}
}