{
  "type": "Feature",
  "properties": {
    "iso:country":"US",
    "sg:address":"1403 Barclay Dr",
    "sg:city":"Austin",
    "sg:classifiers":[
        {
            "category":"Shopping",
            "subcategory":"Stationery & Office Supplies",
            "type":"Retail Goods"
        },
        {
            "category":"Manufacturing",
            "subcategory":"Paper Products",
            "type":"Manufacturing & Wholesale Goods"
        }
    ],
    "sg:phone":"+1 512 347 1579",
    "sg:postcode":"78746",
    "sg:province":"TX",
    "sg:tags":[
        "stationery-wholesale",
        "store",
        "manufacturer"
    ],
    "wof:name":"Lmno People",
    "wof:placetype":"venue"
},
  "geometry": {"coordinates":[-97.824162,30.277736],"type":"Point"}
}