{
  "type": "Feature",
  "properties": {
    "iso:country":"US",
    "sg:address":"4748 N Mesa St",
    "sg:city":"El Paso",
    "sg:classifiers":[
        {
            "category":"Professional",
            "type":"Services"
        }
    ],
    "sg:phone":"+1 915 544 6632",
    "sg:postcode":"79912",
    "sg:province":"TX",
    "wof:name":"Neldas On Road Again",
    "wof:placetype":"venue"
},
  "geometry": {"coordinates":[-106.509096,31.804786],"type":"Point"}
}