{
  "type": "Feature",
  "properties": {
    "iso:country":"US",
    "sg:address":"2455 Kermit Hwy",
    "sg:city":"Odessa",
    "sg:classifiers":[
        {
            "category":"Food & Beverages",
            "subcategory":"Groceries & Convenience Stores",
            "type":"Retail Goods"
        }
    ],
    "sg:phone":"+1 432 332 3152",
    "sg:postcode":"79761",
    "sg:province":"TX",
    "wof:name":"7-Eleven",
    "wof:placetype":"venue"
},
  "geometry": {"coordinates":[-102.386959,31.864033],"type":"Point"}
}