{
  "type": "Feature",
  "properties": {
    "iso:country":"US",
    "sg:address":"22682 Kent Dr",
    "sg:city":"New Caney",
    "sg:classifiers":[
        {
            "category":"Building & Trades",
            "subcategory":"Construction",
            "type":"Services"
        }
    ],
    "sg:phone":"+1 281 235 5615",
    "sg:postcode":"77357",
    "sg:province":"TX",
    "sg:tags":[
        "hanging",
        "contractor"
    ],
    "wof:name":"Dianna Guillot-Jones",
    "wof:placetype":"venue"
},
  "geometry": {"coordinates":[-95.208287,30.117253],"type":"Point"}
}