{
  "type": "Feature",
  "properties": {
    "iso:country":"US",
    "sg:address":"5450 Co Rd 281",
    "sg:city":"Kaufman",
    "sg:classifiers":[
        {
            "category":"Building & Trades",
            "subcategory":"Construction",
            "type":"Services"
        }
    ],
    "sg:phone":"+1 972 932 3146",
    "sg:postcode":"75142",
    "sg:province":"TX",
    "sg:tags":[
        "house",
        "nonresidential"
    ],
    "wof:name":"Roger Allen Construction",
    "wof:placetype":"venue"
},
  "geometry": {"coordinates":[-96.331244,32.643736],"type":"Point"}
}