{
  "type": "Feature",
  "properties": {
    "iso:country":"US",
    "sg:address":"1101 S FM 1912",
    "sg:city":"Amarillo",
    "sg:classifiers":[
        {
            "category":"Wholesale",
            "subcategory":"Machinery & Supplies",
            "type":"Manufacturing & Wholesale Goods"
        }
    ],
    "sg:phone":"+1 806 335 1511",
    "sg:postcode":"79118",
    "sg:province":"TX",
    "sg:tags":[
        "contractor"
    ],
    "sg:website":"www.wtcat.com",
    "wof:name":"Warren Cat",
    "wof:placetype":"venue"
},
  "geometry": {"coordinates":[-101.65361300000001,35.20509],"type":"Point"}
}