{
  "type": "Feature",
  "properties": {
    "iso:country":"US",
    "sg:address":"360 Silver Hills Rd",
    "sg:city":"Kerrville",
    "sg:classifiers":[
        {
            "category":"Retail",
            "subcategory":"Auto Repair",
            "type":"Services"
        }
    ],
    "sg:phone":"+1 830 634 7504",
    "sg:postcode":"78010",
    "sg:province":"TX",
    "sg:tags":[
        "antique",
        "automobile",
        "restoration",
        "classic"
    ],
    "wof:name":"James Enterprises",
    "wof:placetype":"venue"
},
  "geometry": {"coordinates":[-99.104713,29.929248],"type":"Point"}
}