{
  "type": "Feature",
  "properties": {
    "iso:country":"US",
    "sg:address":"224 Green Pasture",
    "sg:city":"Hutto",
    "sg:classifiers":[
        {
            "category":"Transit Center",
            "subcategory":"Freight",
            "type":"Transportation"
        },
        {
            "category":"Freight",
            "type":"Transportation"
        }
    ],
    "sg:phone":"+1 512 846 1333",
    "sg:postcode":"78634",
    "sg:province":"TX",
    "sg:tags":[
        "trucking-motor",
        "trucking"
    ],
    "sg:website":"http://www.bobtransportation.com",
    "wof:name":"Bob Transportation",
    "wof:placetype":"venue"
},
  "geometry": {"coordinates":[-97.587873,30.541132],"type":"Point"}
}