{
  "type": "Feature",
  "properties": {
    "iso:country":"US",
    "sg:address":"7107 Beauford Dr",
    "sg:city":"Austin",
    "sg:classifiers":[
        {
            "category":"Professional",
            "subcategory":"Business Services",
            "type":"Services"
        }
    ],
    "sg:phone":"+1 512 349 0185",
    "sg:postcode":"78750",
    "sg:province":"TX",
    "wof:name":"Interim Solutions For Business",
    "wof:placetype":"venue"
},
  "geometry": {"coordinates":[-97.796712,30.377681],"type":"Point"}
}