{
  "type": "Feature",
  "properties": {
    "iso:country":"US",
    "sg:address":"508 Washington Ave",
    "sg:city":"Amherst",
    "sg:classifiers":[
        {
            "category":"Place Of Worship",
            "subcategory":"Church",
            "type":"Public Place"
        },
        {
            "category":"Place Of Worship",
            "type":"Public Place"
        }
    ],
    "sg:phone":"+1 806 246 3411",
    "sg:postcode":"79312",
    "sg:province":"TX",
    "sg:tags":[
        "churches-methodist"
    ],
    "sg:website":"http://www.umc.org",
    "wof:name":"First United Methodist Church Of Amherst, Inc",
    "wof:placetype":"venue"
},
  "geometry": {"coordinates":[-102.41497,34.012758],"type":"Point"}
}