{
  "type": "Feature",
  "properties": {
    "iso:country":"US",
    "sg:address":"1714 Baylor Dr",
    "sg:city":"Richardson",
    "sg:classifiers":[
        {
            "category":"Social Services",
            "type":"Services"
        }
    ],
    "sg:phone":"+1 972 690 9539",
    "sg:postcode":"75081",
    "sg:province":"TX",
    "wof:name":"Kurdish Aids Center",
    "wof:placetype":"venue"
},
  "geometry": {"coordinates":[-96.692437,32.931767],"type":"Point"}
}