{
  "type": "Feature",
  "properties": {
    "iso:country":"US",
    "sg:address":"1405 S 6th St Ste C",
    "sg:city":"Austin",
    "sg:classifiers":[
        {
            "category":"Professional",
            "type":"Services"
        }
    ],
    "sg:phone":"+1 512 426 5608",
    "sg:postcode":"78704",
    "sg:province":"TX",
    "sg:tags":[
        "writer"
    ],
    "wof:name":"Great Communicate",
    "wof:placetype":"venue"
},
  "geometry": {"coordinates":[-97.760167,30.253203],"type":"Point"}
}