{
  "type": "Feature",
  "properties": {
    "iso:country":"US",
    "sg:address":"401 Hidden Creek Cir",
    "sg:city":"Sealy",
    "sg:classifiers":[
        {
            "category":"Restaurant",
            "type":"Food & Drink"
        }
    ],
    "sg:phone":"+1 979 885 6315",
    "sg:postcode":"77474",
    "sg:province":"TX",
    "sg:tags":[
        "house",
        "steak",
        "barbecue"
    ],
    "wof:name":"Red River Barbeque Co",
    "wof:placetype":"venue"
},
  "geometry": {"coordinates":[-96.045631,29.74094],"type":"Point"}
}