{
  "type": "Feature",
  "properties": {
    "iso:country":"US",
    "sg:address":"11801 Knights Brg",
    "sg:city":"Austin",
    "sg:classifiers":[
        {
            "category":"Wholesale",
            "subcategory":"Vending Machines",
            "type":"Manufacturing & Wholesale Goods"
        }
    ],
    "sg:phone":"+1 512 335 5036",
    "sg:postcode":"78759",
    "sg:province":"TX",
    "wof:name":"CIE Vending Svc",
    "wof:placetype":"venue"
},
  "geometry": {"coordinates":[-97.76888599999999,30.430146],"type":"Point"}
}