{
  "type": "Feature",
  "properties": {
    "iso:country":"US",
    "sg:address":"305 E Morrow St",
    "sg:city":"Georgetown",
    "sg:classifiers":[
        {
            "category":"Restaurant",
            "type":"Food & Drink"
        }
    ],
    "sg:phone":"+1 512 863 6219",
    "sg:postcode":"78626",
    "sg:province":"TX",
    "wof:name":"Bob's Catfish-N-More Rstrnt",
    "wof:placetype":"venue"
},
  "geometry": {"coordinates":[-97.67521000000001,30.646614],"type":"Point"}
}