{
  "type": "Feature",
  "properties": {
    "iso:country":"US",
    "sg:address":"1460 E Highway 377",
    "sg:city":"Granbury",
    "sg:classifiers":[
        {
            "category":"Fast Food",
            "type":"Food & Drink"
        },
        {
            "category":"Restaurant",
            "type":"Food & Drink"
        }
    ],
    "sg:phone":"+1 817 579 7777",
    "sg:postcode":"76048",
    "sg:province":"TX",
    "sg:tags":[
        "take",
        "pizza"
    ],
    "sg:website":"http://www.mrgattis.com",
    "wof:name":"Gatti's Pizza",
    "wof:placetype":"venue"
},
  "geometry": {"coordinates":[-97.764449,32.438481],"type":"Point"}
}