{
  "type": "Feature",
  "properties": {
    "iso:country":"US",
    "sg:address":"13030 Woodforest Blvd",
    "sg:city":"Houston",
    "sg:classifiers":[
        {
            "category":"Food & Beverages",
            "subcategory":"Groceries & Convenience Stores",
            "type":"Retail Goods"
        }
    ],
    "sg:phone":"+1 713 455 5016",
    "sg:postcode":"77015",
    "sg:province":"TX",
    "wof:name":"Save-A-Step Food Store",
    "wof:placetype":"venue"
},
  "geometry": {"coordinates":[-95.19360399999999,29.7939],"type":"Point"}
}