{
  "type": "Feature",
  "properties": {
    "iso:country":"US",
    "sg:address":"2831 W Parker Rd",
    "sg:city":"Plano",
    "sg:classifiers":[
        {
            "category":"Health Services",
            "subcategory":"Doctor",
            "type":"Services"
        }
    ],
    "sg:phone":"+1 972 867 6117",
    "sg:postcode":"75023",
    "sg:province":"TX",
    "sg:tags":[
        "dentist"
    ],
    "sg:website":"www.drrayburn.com",
    "wof:name":"Stephen Rayburn DDS Ms",
    "wof:placetype":"venue"
},
  "geometry": {"coordinates":[-96.7499,33.041195],"type":"Point"}
}