{
  "type": "Feature",
  "properties": {
    "iso:country":"US",
    "sg:address":"4251 State Highway 121",
    "sg:city":"Lewisville",
    "sg:classifiers":[
        {
            "category":"Manufacturing",
            "subcategory":"Electronics",
            "type":"Manufacturing & Wholesale Goods"
        },
        {
            "category":"Shopping",
            "subcategory":"Computers & Home Electronics",
            "type":"Retail Goods"
        }
    ],
    "sg:phone":"+1 972 539 1408",
    "sg:postcode":"75056",
    "sg:province":"TX",
    "sg:tags":[
        "supplies-wholesale",
        "manufacturer",
        "electronic",
        "consumer",
        "equipment"
    ],
    "wof:name":"Idi",
    "wof:placetype":"venue"
},
  "geometry": {"coordinates":[-96.884004,33.067468],"type":"Point"}
}