{
  "type": "Feature",
  "properties": {
    "iso:country":"US",
    "sg:address":"2379 Briarwest Blvd",
    "sg:city":"Houston",
    "sg:classifiers":[
        {
            "category":"Shopping",
            "type":"Retail Goods"
        }
    ],
    "sg:phone":"+1 281 679 0968",
    "sg:postcode":"77077",
    "sg:province":"TX",
    "sg:tags":[
        "art",
        "gallery",
        "dealer"
    ],
    "wof:name":"Art By Design",
    "wof:placetype":"venue"
},
  "geometry": {"coordinates":[-95.614108,29.740353],"type":"Point"}
}