{
  "type": "Feature",
  "properties": {
    "iso:country":"US",
    "sg:address":"319 E Los Torritos St",
    "sg:city":"Weslaco",
    "sg:classifiers":[
        {
            "category":"Organizations",
            "subcategory":"Religious Organization",
            "type":"Services"
        }
    ],
    "sg:phone":"+1 956 969 1178",
    "sg:postcode":"78596",
    "sg:province":"TX",
    "sg:tags":[
        "church"
    ],
    "wof:name":"Apostolic Church Assembly",
    "wof:placetype":"venue"
},
  "geometry": {"coordinates":[-97.987679,26.166334],"type":"Point"}
}