{
  "type": "Feature",
  "properties": {
    "iso:country":"US",
    "sg:address":"431 Lamar St",
    "sg:city":"West Columbia",
    "sg:classifiers":[
        {
            "category":"Real Estate",
            "subcategory":"Real Estate Operator",
            "type":"Services"
        }
    ],
    "sg:phone":"+1 979 345 3034",
    "sg:postcode":"77486",
    "sg:province":"TX",
    "sg:tags":[
        "apartment"
    ],
    "wof:name":"West Columbia Plaza Apartments",
    "wof:placetype":"venue"
},
  "geometry": {"coordinates":[-95.645117,29.149749],"type":"Point"}
}