{
  "type": "Feature",
  "properties": {
    "iso:country":"US",
    "sg:address":"234 Country Pl S",
    "sg:city":"Abilene",
    "sg:classifiers":[
        {
            "category":"Building & Trades",
            "subcategory":"Construction",
            "type":"Services"
        }
    ],
    "sg:phone":"+1 325 691 9200",
    "sg:postcode":"79606",
    "sg:province":"TX",
    "sg:tags":[
        "company"
    ],
    "wof:name":"Turner Construction Co",
    "wof:placetype":"venue"
},
  "geometry": {"coordinates":[-99.815878,32.325694],"type":"Point"}
}