{
  "type": "Feature",
  "properties": {
    "iso:country":"US",
    "sg:address":"4723 Kostoryz Rd",
    "sg:city":"Corpus Christi",
    "sg:classifiers":[
        {
            "category":"Shopping",
            "subcategory":"Clothing, Apparel, & Fashions",
            "type":"Retail Goods"
        }
    ],
    "sg:phone":"+1 361 855 2860",
    "sg:postcode":"78415",
    "sg:province":"TX",
    "wof:name":"Crown Tailor Shop",
    "wof:placetype":"venue"
},
  "geometry": {"coordinates":[-97.40975400000001,27.733856],"type":"Point"}
}