{
  "type": "Feature",
  "properties": {
    "iso:country":"US",
    "sg:address":"317 N Locust St",
    "sg:city":"Denton",
    "sg:classifiers":[
        {
            "category":"Autos & Motor Vehicles",
            "subcategory":"Automobile Sales",
            "type":"Retail Goods"
        }
    ],
    "sg:phone":"+1 940 243 5449",
    "sg:postcode":"76201",
    "sg:province":"TX",
    "sg:tags":[
        "used"
    ],
    "wof:name":"Wood James Denton Inc",
    "wof:placetype":"venue"
},
  "geometry": {"coordinates":[-97.13249399999999,33.216717],"type":"Point"}
}