{
  "type": "Feature",
  "properties": {
    "iso:country":"US",
    "sg:address":"128 Slaton Rd",
    "sg:city":"Lubbock",
    "sg:classifiers":[
        {
            "category":"Building & Trades",
            "subcategory":"Plumbing",
            "type":"Services"
        }
    ],
    "sg:phone":"+1 806 762 4004",
    "sg:postcode":"79404",
    "sg:province":"TX",
    "sg:tags":[
        "conditioning",
        "air",
        "system",
        "contractor"
    ],
    "wof:name":"Ideal Heating & Air Cond Inc",
    "wof:placetype":"venue"
},
  "geometry": {"coordinates":[-101.83815199999999,33.535234],"type":"Point"}
}