{
  "type": "Feature",
  "properties": {
    "iso:country":"US",
    "sg:address":"7899 Hanger Cutoff Rd",
    "sg:city":"Fort Worth",
    "sg:classifiers":[
        {
            "category":"Recreation",
            "subcategory":"Marina",
            "type":"Entertainment"
        }
    ],
    "sg:phone":"+1 817 237 2221",
    "sg:postcode":"76135",
    "sg:province":"TX",
    "sg:tags":[
        "repairing",
        "boat"
    ],
    "wof:name":"Harris Fiberglass Products",
    "wof:placetype":"venue"
},
  "geometry": {"coordinates":[-97.51082100000001,32.866884],"type":"Point"}
}