{
  "type": "Feature",
  "properties": {
    "iso:country":"US",
    "sg:address":"3620 Pershing Dr",
    "sg:city":"El Paso",
    "sg:classifiers":[
        {
            "category":"Manufacturing",
            "subcategory":"Glass & Minerals",
            "type":"Manufacturing & Wholesale Goods"
        },
        {
            "category":"Building & Trades",
            "subcategory":"Construction",
            "type":"Services"
        }
    ],
    "sg:phone":"+1 915 562 6465",
    "sg:postcode":"79903",
    "sg:province":"TX",
    "sg:tags":[
        "contractor",
        "prod",
        "made"
    ],
    "wof:name":"Sal's Glass Co",
    "wof:placetype":"venue"
},
  "geometry": {"coordinates":[-106.450307,31.787427],"type":"Point"}
}