{
  "type": "Feature",
  "properties": {
    "iso:country":"US",
    "sg:address":"6360 Lyndon B Johnson Fwy",
    "sg:city":"Dallas",
    "sg:classifiers":[
        {
            "category":"Professional",
            "type":"Services"
        }
    ],
    "sg:phone":"+1 972 448 8760",
    "sg:postcode":"75240",
    "sg:province":"TX",
    "sg:tags":[
        "establishment"
    ],
    "wof:name":"IMG",
    "wof:placetype":"venue"
},
  "geometry": {"coordinates":[-96.794411,32.924413],"type":"Point"}
}