{
  "type": "Feature",
  "properties": {
    "iso:country":"US",
    "sg:address":"1240 Blalock Rd Suite 110",
    "sg:city":"Houston",
    "sg:classifiers":[
        {
            "category":"Professional",
            "subcategory":"Business Services",
            "type":"Services"
        }
    ],
    "sg:phone":"+1 832 778 4450",
    "sg:postcode":"77055",
    "sg:province":"TX",
    "sg:tags":[
        "development",
        "economic"
    ],
    "sg:website":"http://nationalwindsolutions.com/",
    "wof:name":"National wind soultions",
    "wof:placetype":"venue"
},
  "geometry": {"coordinates":[-95.521698,29.791611],"type":"Point"}
}