{
  "type": "Feature",
  "properties": {
    "iso:country":"US",
    "sg:address":"175 NE 19th St",
    "sg:city":"Grand Prairie",
    "sg:classifiers":[
        {
            "category":"Food & Beverages",
            "subcategory":"Specialty",
            "type":"Retail Goods"
        }
    ],
    "sg:phone":"+1 972 642 1147",
    "sg:postcode":"75050",
    "sg:province":"TX",
    "wof:name":"Naturleza Ntrcion Slud Y Vigor",
    "wof:placetype":"venue"
},
  "geometry": {"coordinates":[-96.978069,32.749389],"type":"Point"}
}