{
  "type": "Feature",
  "properties": {
    "iso:country":"US",
    "sg:address":"1025 Lavon Dr",
    "sg:city":"Garland",
    "sg:classifiers":[
        {
            "category":"Autos & Motor Vehicles",
            "subcategory":"Auto Supplies",
            "type":"Retail Goods"
        }
    ],
    "sg:phone":"+1 972 276 5399",
    "sg:postcode":"75040",
    "sg:province":"TX",
    "sg:tags":[
        "tire"
    ],
    "wof:name":"C & M Tire & Wheel",
    "wof:placetype":"venue"
},
  "geometry": {"coordinates":[-96.62840300000001,32.9217],"type":"Point"}
}