{
  "type": "Feature",
  "properties": {
    "iso:country":"US",
    "sg:address":"1310 E Marvin Ave",
    "sg:city":"Waxahachie",
    "sg:classifiers":[
        {
            "category":"Building & Trades",
            "subcategory":"Construction",
            "type":"Services"
        }
    ],
    "sg:phone":"+1 972 938 7800",
    "sg:postcode":"75165",
    "sg:province":"TX",
    "sg:tags":[
        "house"
    ],
    "wof:name":"Gray Construction",
    "wof:placetype":"venue"
},
  "geometry": {"coordinates":[-96.825119,32.390082],"type":"Point"}
}