{
  "type": "Feature",
  "properties": {
    "iso:country":"US",
    "sg:address":"320 N Main St",
    "sg:city":"Winnsboro",
    "sg:classifiers":[
        {
            "category":"Insurance",
            "subcategory":"Insurance Agent",
            "type":"Services"
        }
    ],
    "sg:phone":"+1 903 342 3611",
    "sg:postcode":"75494",
    "sg:province":"TX",
    "wof:name":"State Farm Insurance",
    "wof:placetype":"venue"
},
  "geometry": {"coordinates":[-95.289704,32.959059],"type":"Point"}
}