{
  "type": "Feature",
  "properties": {
    "iso:country":"US",
    "sg:address":"504 Rockcreek Dr",
    "sg:city":"De Soto",
    "sg:classifiers":[
        {
            "category":"Shopping",
            "subcategory":"Jewelry",
            "type":"Retail Goods"
        }
    ],
    "sg:phone":"+1 972 223 5848",
    "sg:postcode":"75115",
    "sg:province":"TX",
    "wof:name":"Uniquely Yours Jewelry &",
    "wof:placetype":"venue"
},
  "geometry": {"coordinates":[-96.85037199999999,32.584514],"type":"Point"}
}