{
  "type": "Feature",
  "properties": {
    "iso:country":"US",
    "sg:address":"4528 Broadway St",
    "sg:city":"Galveston",
    "sg:classifiers":[
        {
            "category":"Retail",
            "subcategory":"Auto Repair",
            "type":"Services"
        }
    ],
    "sg:phone":"+1 409 765 6689",
    "sg:postcode":"77551",
    "sg:province":"TX",
    "sg:tags":[
        "installs",
        "muffler"
    ],
    "wof:name":"Meineke Discount Mufflers",
    "wof:placetype":"venue"
},
  "geometry": {"coordinates":[-94.818128,29.293321],"type":"Point"}
}