{
  "type": "Feature",
  "properties": {
    "iso:country":"US",
    "sg:address":"1200 Binz St",
    "sg:city":"Houston",
    "sg:classifiers":[
        {
            "category":"Health Services",
            "subcategory":"Doctor",
            "type":"Services"
        }
    ],
    "sg:phone":"+1 713 520 1230",
    "sg:postcode":"77004",
    "sg:province":"TX",
    "sg:tags":[
        "medical"
    ],
    "wof:name":"Anders R Rosendahl",
    "wof:placetype":"venue"
},
  "geometry": {"coordinates":[-95.38700300000001,29.724245],"type":"Point"}
}