{
  "type": "Feature",
  "properties": {
    "iso:country":"US",
    "sg:address":"1400 S FM 51",
    "sg:city":"Decatur",
    "sg:classifiers":[
        {
            "category":"Retail",
            "subcategory":"Laundry & Dry Cleaning",
            "type":"Services"
        }
    ],
    "sg:phone":"+1 940 627 1122",
    "sg:postcode":"76234",
    "sg:province":"TX",
    "sg:tags":[
        "cleaners"
    ],
    "wof:name":"Comet Laundry & Cleaners",
    "wof:placetype":"venue"
},
  "geometry": {"coordinates":[-97.594464,33.223721],"type":"Point"}
}