{
  "type": "Feature",
  "properties": {
    "iso:country":"US",
    "sg:address":"9623 Meadowvale Dr",
    "sg:city":"Houston",
    "sg:classifiers":[
        {
            "category":"Banks & Credit Unions",
            "subcategory":"Investment Brokerage",
            "type":"Services"
        }
    ],
    "sg:phone":"+1 832 251 2601",
    "sg:postcode":"77063",
    "sg:province":"TX",
    "sg:tags":[
        "advisory",
        "financial"
    ],
    "wof:name":"Lincoln Financial Group",
    "wof:placetype":"venue"
},
  "geometry": {"coordinates":[-95.53832,29.726789],"type":"Point"}
}