{
  "type": "Feature",
  "properties": {
    "iso:country":"US",
    "sg:address":"2850 Fannin St",
    "sg:city":"Houston",
    "sg:classifiers":[
        {
            "category":"Health Services",
            "subcategory":"Hospital",
            "type":"Services"
        }
    ],
    "sg:phone":"+1 713 970 4600",
    "sg:postcode":"77002",
    "sg:province":"TX",
    "sg:tags":[
        "mental"
    ],
    "wof:name":"Mental Health & Mental Retard",
    "wof:placetype":"venue"
},
  "geometry": {"coordinates":[-95.37453600000001,29.743336],"type":"Point"}
}