{
  "type": "Feature",
  "properties": {
    "iso:country":"US",
    "sg:address":"623 N 2nd St",
    "sg:city":"Princeton",
    "sg:classifiers":[
        {
            "category":"Real Estate",
            "subcategory":"Real Estate Services",
            "type":"Services"
        },
        {
            "category":"Building & Trades",
            "subcategory":"Cleaning & Sanitation",
            "type":"Services"
        },
        {
            "category":"Government",
            "subcategory":"Fire Station",
            "type":"Public Place"
        }
    ],
    "sg:phone":"+1 972 736 2001",
    "sg:postcode":"75407",
    "sg:province":"TX",
    "sg:tags":[
        "disaster",
        "recovery",
        "contractor",
        "cleaning-industrial",
        "relief",
        "maintenance",
        "cleaners-interior"
    ],
    "sg:website":"http://www.servpro.com",
    "wof:name":"Servpro",
    "wof:placetype":"venue"
},
  "geometry": {"coordinates":[-96.49946,33.180107],"type":"Point"}
}