{
  "type": "Feature",
  "properties": {
    "iso:country":"US",
    "sg:address":"4128 N Belt Line Rd",
    "sg:city":"Irving",
    "sg:classifiers":[
        {
            "category":"Professional",
            "subcategory":"Business Services",
            "type":"Services"
        }
    ],
    "sg:phone":"+1 972 255 0307",
    "sg:postcode":"75038",
    "sg:province":"TX",
    "wof:name":"Safia Enterprises",
    "wof:placetype":"venue"
},
  "geometry": {"coordinates":[-96.991631,32.868227],"type":"Point"}
}