{
  "type": "Feature",
  "properties": {
    "iso:country":"US",
    "sg:address":"2500 Pickwick Ln",
    "sg:city":"Plano",
    "sg:classifiers":[
        {
            "category":"Recreation",
            "type":"Entertainment"
        }
    ],
    "sg:phone":"+1 972 596 1547",
    "sg:postcode":"75093",
    "sg:province":"TX",
    "wof:name":"Summit Martial Arts",
    "wof:placetype":"venue"
},
  "geometry": {"coordinates":[-96.787369,33.032463],"type":"Point"}
}