{
  "type": "Feature",
  "properties": {
    "iso:country":"US",
    "sg:address":"2019 Valley Ln",
    "sg:city":"Arlington",
    "sg:classifiers":[
        {
            "category":"Real Estate",
            "subcategory":"Real Estate Operator",
            "type":"Services"
        }
    ],
    "sg:phone":"+1 817 275 0807",
    "sg:postcode":"76013",
    "sg:province":"TX",
    "sg:tags":[
        "building",
        "nonresidential"
    ],
    "wof:name":"Caudle Allagene",
    "wof:placetype":"venue"
},
  "geometry": {"coordinates":[-97.140867,32.724529],"type":"Point"}
}