{
  "type": "Feature",
  "properties": {
    "iso:country":"US",
    "sg:address":"9224 Lookout Way",
    "sg:city":"Fort Worth",
    "sg:classifiers":[
        {
            "category":"Building & Trades",
            "subcategory":"Construction",
            "type":"Services"
        }
    ],
    "sg:phone":"+1 817 249 5275",
    "sg:postcode":"76126",
    "sg:province":"TX",
    "sg:tags":[
        "contractor"
    ],
    "wof:name":"Monarch Roofing Co",
    "wof:placetype":"venue"
},
  "geometry": {"coordinates":[-97.47177000000001,32.674789],"type":"Point"}
}