{
  "type": "Feature",
  "properties": {
    "iso:country":"US",
    "sg:address":"3409 Evanston Ave",
    "sg:city":"Lubbock",
    "sg:classifiers":[
        {
            "category":"Building & Trades",
            "subcategory":"Landscaping Services",
            "type":"Services"
        }
    ],
    "sg:phone":"+1 806 797 4788",
    "sg:postcode":"79407",
    "sg:province":"TX",
    "wof:name":"Lawn Raiders",
    "wof:placetype":"venue"
},
  "geometry": {"coordinates":[-101.938366,33.562239],"type":"Point"}
}