{
  "type": "Feature",
  "properties": {
    "iso:country":"US",
    "sg:address":"2500 Lake Ridge Dr",
    "sg:city":"Red Oak",
    "sg:classifiers":[
        {
            "category":"Building & Trades",
            "subcategory":"Equipment Rental",
            "type":"Services"
        }
    ],
    "sg:phone":"+1 972 230 1256",
    "sg:postcode":"75154",
    "sg:province":"TX",
    "wof:name":"Payne Leasing",
    "wof:placetype":"venue"
},
  "geometry": {"coordinates":[-96.859353,32.540326],"type":"Point"}
}