{
  "type": "Feature",
  "properties": {
    "iso:country":"US",
    "sg:address":"1550 Fox Lake Dr",
    "sg:city":"Houston",
    "sg:classifiers":[
        {
            "category":"Professional",
            "type":"Services"
        },
        {
            "category":"Personal",
            "type":"Services"
        }
    ],
    "sg:phone":"+1 281 398 3111",
    "sg:postcode":"77084",
    "sg:province":"TX",
    "sg:tags":[
        "miscellaneous"
    ],
    "wof:name":"A Personal Assistant",
    "wof:placetype":"venue"
},
  "geometry": {"coordinates":[-95.71565200000001,29.791247],"type":"Point"}
}