{
  "type": "Feature",
  "properties": {
    "iso:country":"US",
    "sg:address":"2215 Post Office St",
    "sg:city":"Galveston",
    "sg:classifiers":[
        {
            "category":"Shopping",
            "subcategory":"Jewelry",
            "type":"Retail Goods"
        }
    ],
    "sg:phone":"+1 409 763 0555",
    "sg:postcode":"77550",
    "sg:province":"TX",
    "sg:tags":[
        "jeweler"
    ],
    "wof:name":"Fullen Harborside Jewelry",
    "wof:placetype":"venue"
},
  "geometry": {"coordinates":[-94.79331000000001,29.304507],"type":"Point"}
}