{
  "type": "Feature",
  "properties": {
    "iso:country":"US",
    "sg:address":"5050 FM 1960 W",
    "sg:city":"Houston",
    "sg:classifiers":[
        {
            "category":"Retail",
            "subcategory":"Laundry & Dry Cleaning",
            "type":"Services"
        }
    ],
    "sg:phone":"+1 281 444 8515",
    "sg:postcode":"77069",
    "sg:province":"TX",
    "sg:tags":[
        "cleaners"
    ],
    "wof:name":"125 Clean",
    "wof:placetype":"venue"
},
  "geometry": {"coordinates":[-95.50543,29.983877],"type":"Point"}
}