{
  "type": "Feature",
  "properties": {
    "iso:country":"US",
    "sg:address":"3600 Ryan Ct",
    "sg:city":"Burleson",
    "sg:classifiers":[
        {
            "category":"Professional",
            "type":"Services"
        }
    ],
    "sg:phone":"+1 817 561 5913",
    "sg:postcode":"76028",
    "sg:province":"TX",
    "wof:name":"Donovon E Fausnight",
    "wof:placetype":"venue"
},
  "geometry": {"coordinates":[-97.259074,32.583283],"type":"Point"}
}