{
  "type": "Feature",
  "properties": {
    "iso:country":"US",
    "sg:address":"271 Weiss Rd",
    "sg:city":"New Braunfels",
    "sg:classifiers":[
        {
            "category":"Building & Trades",
            "subcategory":"Landscaping Services",
            "type":"Services"
        }
    ],
    "sg:phone":"+1 210 274 7909",
    "sg:postcode":"78130",
    "sg:province":"TX",
    "sg:tags":[
        "landscape"
    ],
    "wof:name":"Kathie Newberry",
    "wof:placetype":"venue"
},
  "geometry": {"coordinates":[-98.032715,29.768475],"type":"Point"}
}