{
  "type": "Feature",
  "properties": {
    "iso:country":"US",
    "sg:address":"3811 Canterbury Dr",
    "sg:city":"Baytown",
    "sg:classifiers":[
        {
            "category":"Health Services",
            "subcategory":"Clinic",
            "type":"Services"
        }
    ],
    "sg:phone":"+1 281 427 3994",
    "sg:postcode":"77521",
    "sg:province":"TX",
    "wof:name":"Starling Health Claim Services",
    "wof:placetype":"venue"
},
  "geometry": {"coordinates":[-94.921301,29.769218],"type":"Point"}
}