{
  "type": "Feature",
  "properties": {
    "iso:country":"US",
    "sg:address":"5117 Creekmont Dr",
    "sg:city":"Corpus Christi",
    "sg:classifiers":[
        {
            "category":"Manufacturing",
            "subcategory":"Toys & Sporting Goods",
            "type":"Manufacturing & Wholesale Goods"
        }
    ],
    "sg:phone":"+1 361 443 2948",
    "sg:postcode":"78413",
    "sg:province":"TX",
    "sg:tags":[
        "mfg"
    ],
    "wof:name":"Corpus Christi Big Wood Drvng",
    "wof:placetype":"venue"
},
  "geometry": {"coordinates":[-97.405067,27.667902],"type":"Point"}
}