{
  "type": "Feature",
  "properties": {
    "iso:country":"US",
    "sg:address":"10906 Chimney Rock Rd",
    "sg:city":"Houston",
    "sg:classifiers":[
        {
            "category":"Building & Trades",
            "subcategory":"Plumbing",
            "type":"Services"
        }
    ],
    "sg:phone":"+1 713 723 8780",
    "sg:postcode":"77096",
    "sg:province":"TX",
    "sg:tags":[
        "contractor"
    ],
    "wof:name":"Leader Plumbing",
    "wof:placetype":"venue"
},
  "geometry": {"coordinates":[-95.476831,29.661355],"type":"Point"}
}