{
  "type": "Feature",
  "properties": {
    "iso:country":"US",
    "sg:address":"5712 Lazy River Dr",
    "sg:city":"Dallas",
    "sg:classifiers":[
        {
            "category":"Retail",
            "subcategory":"Laundry & Dry Cleaning",
            "type":"Services"
        }
    ],
    "sg:phone":"+1 214 371 2679",
    "sg:postcode":"75241",
    "sg:province":"TX",
    "wof:name":"Babys Bottom Neighborhood",
    "wof:placetype":"venue"
},
  "geometry": {"coordinates":[-96.793429,32.677002],"type":"Point"}
}