{
  "type": "Feature",
  "properties": {
    "iso:country":"US",
    "sg:address":"8500 Senate St",
    "sg:city":"Houston",
    "sg:classifiers":[
        {
            "category":"Recreation",
            "subcategory":"Marina",
            "type":"Entertainment"
        }
    ],
    "sg:phone":"+1 713 644 4764",
    "sg:postcode":"77040",
    "sg:province":"TX",
    "sg:tags":[
        "repair",
        "operation"
    ],
    "wof:name":"Boat Shed",
    "wof:placetype":"venue"
},
  "geometry": {"coordinates":[-95.563406,29.891266],"type":"Point"}
}