{
  "type": "Feature",
  "properties": {
    "iso:country":"US",
    "sg:address":"1212 Guadalupe St Ste 103",
    "sg:city":"Austin",
    "sg:classifiers":[
        {
            "category":"Professional",
            "subcategory":"Lawyer & Legal Services",
            "type":"Services"
        }
    ],
    "sg:phone":"+1 512 371 6851",
    "sg:postcode":"78701",
    "sg:province":"TX",
    "sg:tags":[
        "litigation"
    ],
    "sg:website":"davidfranklaw.net?n=t&ubl=true",
    "wof:name":"Austin Criminal Defense Trial Lawyer",
    "wof:placetype":"venue"
},
  "geometry": {"coordinates":[-97.744186,30.275109],"type":"Point"}
}