{
  "type": "Feature",
  "properties": {
    "iso:country":"US",
    "sg:address":"7218 Halfpenny Rd",
    "sg:city":"Houston",
    "sg:phone":"+1 281 855 0657",
    "sg:postcode":"77095",
    "sg:province":"TX",
    "sg:tags":[
        "fabric",
        "mfg",
        "leather",
        "travel",
        "hand",
        "bag",
        "tapestry"
    ],
    "wof:name":"Bogey Inc",
    "wof:placetype":"venue"
},
  "geometry": {"coordinates":[-95.634659,29.880956],"type":"Point"}
}