{
  "type": "Feature",
  "properties": {
    "iso:country":"US",
    "sg:address":"5726 Van Winkle Blvd",
    "sg:city":"Dallas",
    "sg:classifiers":[
        {
            "category":"Organizations",
            "subcategory":"Religious Organization",
            "type":"Services"
        }
    ],
    "sg:phone":"+1 214 631 9633",
    "sg:postcode":"75235",
    "sg:province":"TX",
    "wof:name":"Arlington Pk Frst Bptst Church",
    "wof:placetype":"venue"
},
  "geometry": {"coordinates":[-96.857409,32.815604],"type":"Point"}
}