{
  "type": "Feature",
  "properties": {
    "iso:country":"US",
    "sg:address":"1104 Timber Ridge Dr",
    "sg:city":"Euless",
    "sg:classifiers":[
        {
            "category":"Organizations",
            "subcategory":"Religious Organization",
            "type":"Services"
        }
    ],
    "sg:phone":"+1 817 483 6651",
    "sg:postcode":"76039",
    "sg:province":"TX",
    "wof:name":"Embroiderers Guild of AME",
    "wof:placetype":"venue"
},
  "geometry": {"coordinates":[-97.097138,32.851929],"type":"Point"}
}