{
  "type": "Feature",
  "properties": {
    "iso:country":"US",
    "sg:address":"103 Tiffany Dr",
    "sg:city":"Boerne",
    "sg:classifiers":[
        {
            "category":"Building & Trades",
            "subcategory":"Landscaping Services",
            "type":"Services"
        }
    ],
    "sg:phone":"+1 830 229 5696",
    "sg:postcode":"78006",
    "sg:province":"TX",
    "sg:tags":[
        "landscape"
    ],
    "wof:name":"Chapparal Services Inc",
    "wof:placetype":"venue"
},
  "geometry": {"coordinates":[-98.614661,29.83891],"type":"Point"}
}