{
  "type": "Feature",
  "properties": {
    "iso:country":"US",
    "sg:address":"1222 Sadler St",
    "sg:city":"Houston",
    "sg:classifiers":[
        {
            "category":"Building & Trades",
            "subcategory":"Construction",
            "type":"Services"
        }
    ],
    "sg:phone":"+1 713 699 4210",
    "sg:postcode":"77022",
    "sg:province":"TX",
    "sg:tags":[
        "contractor"
    ],
    "wof:name":"Bernys Roofer",
    "wof:placetype":"venue"
},
  "geometry": {"coordinates":[-95.356545,29.834757],"type":"Point"}
}