{
  "type": "Feature",
  "properties": {
    "iso:country":"US",
    "sg:address":"2200 Willowick Rd",
    "sg:city":"Houston",
    "sg:classifiers":[
        {
            "category":"Shopping",
            "type":"Retail Goods"
        }
    ],
    "sg:phone":"+1 713 526 9995",
    "sg:postcode":"77027",
    "sg:province":"TX",
    "sg:tags":[
        "art",
        "gallery",
        "dealer"
    ],
    "sg:website":"www.somozagallery.com",
    "wof:name":"Amin Karim",
    "wof:placetype":"venue"
},
  "geometry": {"coordinates":[-95.44164600000001,29.744839],"type":"Point"}
}