{
  "type": "Feature",
  "properties": {
    "iso:country":"US",
    "sg:address":"5044 Callaghan Rd",
    "sg:city":"San Antonio",
    "sg:classifiers":[
        {
            "category":"Retail",
            "subcategory":"Repair Shop",
            "type":"Services"
        }
    ],
    "sg:phone":"+1 210 434 7949",
    "sg:postcode":"78228",
    "sg:province":"TX",
    "wof:name":"Pallet Place",
    "wof:placetype":"venue"
},
  "geometry": {"coordinates":[-98.59254799999999,29.476801],"type":"Point"}
}