{
  "type": "Feature",
  "properties": {
    "iso:country":"US",
    "sg:address":"10930 N Central Expy",
    "sg:city":"Dallas",
    "sg:classifiers":[
        {
            "category":"Fast Food",
            "type":"Food & Drink"
        }
    ],
    "sg:phone":"+1 214 361 8544",
    "sg:postcode":"75231",
    "sg:province":"TX",
    "sg:tags":[
        "burger"
    ],
    "sg:website":"www.backyardburgers.com",
    "wof:name":"Back Yard Burgers",
    "wof:placetype":"venue"
},
  "geometry": {"coordinates":[-96.76870099999999,32.897612],"type":"Point"}
}