{
  "type": "Feature",
  "properties": {
    "iso:country":"US",
    "sg:address":"16909 Colegrove Dr",
    "sg:city":"Dallas",
    "sg:classifiers":[
        {
            "category":"Banks & Credit Unions",
            "subcategory":"Financial Services",
            "type":"Services"
        }
    ],
    "sg:phone":"+1 972 392 2346",
    "sg:postcode":"75248",
    "sg:province":"TX",
    "sg:tags":[
        "investor"
    ],
    "wof:name":"DMS Investments",
    "wof:placetype":"venue"
},
  "geometry": {"coordinates":[-96.78656100000001,32.980857],"type":"Point"}
}