{
  "type": "Feature",
  "properties": {
    "iso:country":"US",
    "sg:address":"315 Andre Dr",
    "sg:city":"Irving",
    "sg:classifiers":[
        {
            "category":"Professional",
            "subcategory":"Computer Services",
            "type":"Services"
        }
    ],
    "sg:phone":"+1 972 506 9815",
    "sg:postcode":"75063",
    "sg:province":"TX",
    "wof:name":"Smithen Consulting Svc",
    "wof:placetype":"venue"
},
  "geometry": {"coordinates":[-96.946652,32.945513],"type":"Point"}
}