{
  "type": "Feature",
  "properties": {
    "iso:country":"US",
    "sg:address":"5303 Wurzbach Rd",
    "sg:city":"San Antonio",
    "sg:classifiers":[
        {
            "category":"Manufacturing",
            "subcategory":"Apparel",
            "type":"Manufacturing & Wholesale Goods"
        },
        {
            "category":"Shopping",
            "subcategory":"Clothing, Apparel, & Fashions",
            "type":"Retail Goods"
        }
    ],
    "sg:phone":"+1 210 684 7950",
    "sg:postcode":"78229",
    "sg:province":"TX",
    "wof:name":"Barry Manufacturing 40",
    "wof:placetype":"venue"
},
  "geometry": {"coordinates":[-98.609292,29.481262],"type":"Point"}
}