{
  "type": "Feature",
  "properties": {
    "iso:country":"US",
    "sg:address":"2108 New Boston Rd",
    "sg:city":"Texarkana",
    "sg:classifiers":[
        {
            "category":"Home & Garden",
            "subcategory":"Carpets & Floor Coverings",
            "type":"Retail Goods"
        }
    ],
    "sg:phone":"+1 903 793 8399",
    "sg:postcode":"75501",
    "sg:province":"TX",
    "sg:tags":[
        "dealer",
        "rug"
    ],
    "wof:name":"Contract Flooring",
    "wof:placetype":"venue"
},
  "geometry": {"coordinates":[-94.06776000000001,33.43494],"type":"Point"}
}