{
  "type": "Feature",
  "properties": {
    "iso:country":"US",
    "sg:address":"400 Medical Center Blvd # 201",
    "sg:city":"Webster",
    "sg:classifiers":[
        {
            "category":"Health Services",
            "subcategory":"Nursing And Care Facility",
            "type":"Services"
        },
        {
            "category":"Health Services",
            "subcategory":"Health Practitioner",
            "type":"Services"
        }
    ],
    "sg:phone":"+1 281 332 2498",
    "sg:postcode":"77598",
    "sg:province":"TX",
    "sg:tags":[
        "home",
        "eldercare-home"
    ],
    "wof:name":"Home Care Prof Serv",
    "wof:placetype":"venue"
},
  "geometry": {"coordinates":[-95.126881,29.540623],"type":"Point"}
}