{
  "type": "Feature",
  "properties": {
    "iso:country":"US",
    "sg:address":"823 Hidden Canyon Rd",
    "sg:city":"Katy",
    "sg:classifiers":[
        {
            "category":"Community Center",
            "subcategory":"Senior",
            "type":"Public Place"
        },
        {
            "category":"Health Services",
            "subcategory":"Nursing And Care Facility",
            "type":"Services"
        },
        {
            "category":"Social Services",
            "subcategory":"Retirement Home",
            "type":"Services"
        },
        {
            "category":"Social Services",
            "subcategory":"Adult Care",
            "type":"Services"
        }
    ],
    "sg:phone":"+1 866 333 4173",
    "sg:postcode":"77450",
    "sg:province":"TX",
    "sg:tags":[
        "living",
        "nurses-home",
        "people",
        "alzheimer's",
        "assisted",
        "homes-elderly",
        "citizen"
    ],
    "wof:name":"Serenity Assisted Living",
    "wof:placetype":"venue"
},
  "geometry": {"coordinates":[-95.75619399999999,29.768715],"type":"Point"}
}