{
  "type": "Feature",
  "properties": {
    "iso:country":"US",
    "sg:address":"1400 N Cowan Ave",
    "sg:city":"Lewisville",
    "sg:classifiers":[
        {
            "category":"Government",
            "subcategory":"Office",
            "type":"Public Place"
        }
    ],
    "sg:phone":"+1 972 219 3540",
    "sg:postcode":"75057",
    "sg:province":"TX",
    "sg:tags":[
        "village"
    ],
    "sg:website":"www.cityoflewisville.com",
    "wof:name":"Lewisville Water Trtmnt Plant",
    "wof:placetype":"venue"
},
  "geometry": {"coordinates":[-97.00117,33.06216],"type":"Point"}
}