{
  "type": "Feature",
  "properties": {
    "iso:country":"US",
    "sg:address":"624 N General Bruce Dr",
    "sg:city":"Temple",
    "sg:classifiers":[
        {
            "category":"Restaurant",
            "type":"Food & Drink"
        }
    ],
    "sg:menulink":"http://www.allmenus.com/tx/temple/10685-texas-roadhouse/menu/",
    "sg:phone":"+1 254 773 0033",
    "sg:postcode":"76504",
    "sg:province":"TX",
    "sg:tags":[
        "american",
        "steakhouse"
    ],
    "wof:name":"Texas Roadhouse",
    "wof:placetype":"venue"
},
  "geometry": {"coordinates":[-97.357677,31.108248],"type":"Point"}
}