{
  "type": "Feature",
  "properties": {
    "iso:country":"US",
    "sg:address":"1358 Backus St",
    "sg:city":"El Paso",
    "sg:classifiers":[
        {
            "category":"Professional",
            "subcategory":"Business Services",
            "type":"Services"
        }
    ],
    "sg:phone":"+1 915 747 5016",
    "sg:postcode":"79925",
    "sg:province":"TX",
    "wof:name":"Echeverria Design Group",
    "wof:placetype":"venue"
},
  "geometry": {"coordinates":[-106.361779,31.777696],"type":"Point"}
}