{
  "type": "Feature",
  "properties": {
    "iso:country":"US",
    "sg:address":"813 8th St",
    "sg:city":"Wichita Falls",
    "sg:classifiers":[
        {
            "category":"Insurance",
            "subcategory":"Insurance Agent",
            "type":"Services"
        }
    ],
    "sg:phone":"+1 940 767 7716",
    "sg:postcode":"76301",
    "sg:province":"TX",
    "wof:name":"Fenoglio Insurance",
    "wof:placetype":"venue"
},
  "geometry": {"coordinates":[-98.493039,33.911294],"type":"Point"}
}