{
  "type": "Feature",
  "properties": {
    "iso:country":"US",
    "sg:address":"15120 Paradise View Dr",
    "sg:city":"Willis",
    "sg:classifiers":[
        {
            "category":"Shopping",
            "subcategory":"Computers & Home Electronics",
            "type":"Retail Goods"
        }
    ],
    "sg:phone":"+1 936 890 2838",
    "sg:postcode":"77318",
    "sg:province":"TX",
    "wof:name":"Jehar & Assoc",
    "wof:placetype":"venue"
},
  "geometry": {"coordinates":[-95.56372500000001,30.460297],"type":"Point"}
}