{
  "type": "Feature",
  "properties": {
    "iso:country":"US",
    "sg:address":"4311 Pan American Blvd",
    "sg:city":"Laredo",
    "sg:classifiers":[
        {
            "category":"Shopping",
            "subcategory":"Bicycles & Sporting Goods",
            "type":"Retail Goods"
        }
    ],
    "sg:phone":"+1 956 727 8805",
    "sg:postcode":"78045",
    "sg:province":"TX",
    "wof:name":"Laredo Sport City",
    "wof:placetype":"venue"
},
  "geometry": {"coordinates":[-99.53928999999999,27.634004],"type":"Point"}
}