{
  "type": "Feature",
  "properties": {
    "iso:country":"US",
    "sg:address":"2 Allen Civic Plz",
    "sg:city":"Allen",
    "sg:classifiers":[
        {
            "category":"Education",
            "subcategory":"Library",
            "type":"Public Place"
        }
    ],
    "sg:phone":"+1 972 727 0190",
    "sg:postcode":"75013",
    "sg:province":"TX",
    "sg:tags":[
        "gallery"
    ],
    "wof:name":"Allen Public Library",
    "wof:placetype":"venue"
},
  "geometry": {"coordinates":[-96.67448,33.100477],"type":"Point"}
}