{
  "type": "Feature",
  "properties": {
    "iso:country":"US",
    "sg:address":"2619 Hidden Valley Dr",
    "sg:city":"Killeen",
    "sg:classifiers":[
        {
            "category":"Shopping",
            "subcategory":"Computers & Home Electronics",
            "type":"Retail Goods"
        }
    ],
    "sg:phone":"+1 254 526 2477",
    "sg:postcode":"76543",
    "sg:province":"TX",
    "sg:tags":[
        "equipment",
        "dealer"
    ],
    "wof:name":"Hudson Enterprises",
    "wof:placetype":"venue"
},
  "geometry": {"coordinates":[-97.693879,31.13225],"type":"Point"}
}