{
  "type": "Feature",
  "properties": {
    "iso:country":"US",
    "sg:address":"1562 FM 2294",
    "sg:city":"Delmita",
    "sg:classifiers":[
        {
            "category":"Food & Beverages",
            "subcategory":"Groceries & Convenience Stores",
            "type":"Retail Goods"
        }
    ],
    "sg:phone":"+1 956 481 3922",
    "sg:postcode":"78582",
    "sg:province":"TX",
    "sg:tags":[
        "grocer"
    ],
    "wof:name":"El Ranchito Grocery & Meat Mkt",
    "wof:placetype":"venue"
},
  "geometry": {"coordinates":[-98.433492,26.696739],"type":"Point"}
}