{
  "type": "Feature",
  "properties": {
    "iso:country":"US",
    "sg:address":"401 S Brackenridge",
    "sg:city":"Boerne",
    "sg:classifiers":[
        {
            "category":"Farming",
            "subcategory":"Livestock Farm",
            "type":"Manufacturing & Wholesale Goods"
        }
    ],
    "sg:phone":"+1 830 249 8519",
    "sg:postcode":"78006",
    "sg:province":"TX",
    "sg:tags":[
        "horse"
    ],
    "wof:name":"White Horse Services",
    "wof:placetype":"venue"
},
  "geometry": {"coordinates":[-98.73307,29.79085],"type":"Point"}
}