{
  "type": "Feature",
  "properties": {
    "iso:country":"US",
    "sg:address":"1900 N Grand Ave Ste 1930",
    "sg:city":"Sherman",
    "sg:classifiers":[
        {
            "category":"Shopping",
            "subcategory":"Gifts & Souvenirs",
            "type":"Retail Goods"
        },
        {
            "category":"Home & Garden",
            "subcategory":"Home Furnishings",
            "type":"Retail Goods"
        },
        {
            "category":"Shopping",
            "subcategory":"Discount & Variety Stores",
            "type":"Retail Goods"
        }
    ],
    "sg:phone":"+1 903 892 3359",
    "sg:postcode":"75090",
    "sg:province":"TX",
    "sg:tags":[
        "housewares",
        "shop"
    ],
    "sg:website":"http://www.tuesdaymorning.com",
    "wof:name":"Tuesday Morning",
    "wof:placetype":"venue"
},
  "geometry": {"coordinates":[-96.601158,33.656231],"type":"Point"}
}