{
  "type": "Feature",
  "properties": {
    "iso:country":"US",
    "sg:address":"1806 Campbell Trl",
    "sg:city":"Richardson",
    "sg:classifiers":[
        {
            "category":"Professional",
            "subcategory":"Management & Consulting",
            "type":"Services"
        }
    ],
    "sg:phone":"+1 972 690 1109",
    "sg:postcode":"75082",
    "sg:province":"TX",
    "wof:name":"Brocker Management LLC",
    "wof:placetype":"venue"
},
  "geometry": {"coordinates":[-96.69064899999999,32.975906],"type":"Point"}
}