{
  "type": "Feature",
  "properties": {
    "iso:country":"US",
    "sg:address":"1509 19th St",
    "sg:city":"Hondo",
    "sg:classifiers":[
        {
            "category":"Autos & Motor Vehicles",
            "subcategory":"Fuel & Gas Station",
            "type":"Retail Goods"
        }
    ],
    "sg:phone":"+1 830 426 3393",
    "sg:postcode":"78861",
    "sg:province":"TX",
    "sg:tags":[
        "oil"
    ],
    "wof:name":"Midtown Exxon",
    "wof:placetype":"venue"
},
  "geometry": {"coordinates":[-99.14514,29.347251],"type":"Point"}
}