{
  "type": "Feature",
  "properties": {
    "iso:country":"US",
    "sg:address":"100 E Tyler St",
    "sg:city":"Athens",
    "sg:classifiers":[
        {
            "category":"Government",
            "subcategory":"Office",
            "type":"Public Place"
        }
    ],
    "sg:phone":"+1 903 675 6145",
    "sg:postcode":"75751",
    "sg:province":"TX",
    "sg:tags":[
        "executive"
    ],
    "wof:name":"County Auditors Office",
    "wof:placetype":"venue"
},
  "geometry": {"coordinates":[-95.853754,32.205383],"type":"Point"}
}