{
  "type": "Feature",
  "properties": {
    "iso:country":"US",
    "sg:address":"845 S Indiana Ave",
    "sg:city":"Mercedes",
    "sg:classifiers":[
        {
            "category":"Social Services",
            "subcategory":"Child Care",
            "type":"Services"
        }
    ],
    "sg:phone":"+1 956 565 0300",
    "sg:postcode":"78570",
    "sg:province":"TX",
    "sg:tags":[
        "nursery",
        "day"
    ],
    "wof:name":"Noah's Ark Daycare",
    "wof:placetype":"venue"
},
  "geometry": {"coordinates":[-97.919274,26.143438],"type":"Point"}
}