{
  "type": "Feature",
  "properties": {
    "iso:country":"US",
    "sg:address":"1004 Junction Hwy",
    "sg:city":"Kerrville",
    "sg:classifiers":[
        {
            "category":"Government",
            "subcategory":"Office",
            "type":"Public Place"
        }
    ],
    "sg:phone":"+1 830 895 1422",
    "sg:postcode":"78028",
    "sg:province":"TX",
    "sg:tags":[
        "federal",
        "human"
    ],
    "wof:name":"US Social Security Adm",
    "wof:placetype":"venue"
},
  "geometry": {"coordinates":[-99.16455000000001,30.059134],"type":"Point"}
}