{
  "type": "Feature",
  "properties": {
    "iso:country":"US",
    "sg:address":"812 E Park Row Dr",
    "sg:city":"Arlington",
    "sg:classifiers":[
        {
            "category":"Retail",
            "subcategory":"Repair Shop",
            "type":"Services"
        }
    ],
    "sg:phone":"+1 817 303 3330",
    "sg:postcode":"76010",
    "sg:province":"TX",
    "sg:tags":[
        "refinishing",
        "furniture"
    ],
    "wof:name":"AOK Repair Group",
    "wof:placetype":"venue"
},
  "geometry": {"coordinates":[-97.097694,32.720938],"type":"Point"}
}