{
  "type": "Feature",
  "properties": {
    "iso:country":"US",
    "sg:address":"411 Shiloh Dr",
    "sg:city":"Laredo",
    "sg:classifiers":[
        {
            "category":"Professional",
            "type":"Services"
        }
    ],
    "sg:phone":"+1 956 717 9966",
    "sg:postcode":"78045",
    "sg:province":"TX",
    "wof:name":"Rodcan LLC",
    "wof:placetype":"venue"
},
  "geometry": {"coordinates":[-99.48521599999999,27.590892],"type":"Point"}
}