{
  "type": "Feature",
  "properties": {
    "iso:country":"US",
    "sg:address":"670 Louis Henna Blvd",
    "sg:city":"Round Rock",
    "sg:classifiers":[
        {
            "category":"Real Estate",
            "subcategory":"Real Estate Operator",
            "type":"Services"
        }
    ],
    "sg:phone":"+1 512 733 6411",
    "sg:postcode":"78664",
    "sg:province":"TX",
    "sg:tags":[
        "building",
        "apartment"
    ],
    "wof:name":"Mansion The Apartments",
    "wof:placetype":"venue"
},
  "geometry": {"coordinates":[-97.672477,30.481041],"type":"Point"}
}