{
  "type": "Feature",
  "properties": {
    "iso:country":"US",
    "sg:address":"1111 McKinley St",
    "sg:city":"Benbrook",
    "sg:classifiers":[
        {
            "category":"Professional",
            "subcategory":"Management & Consulting",
            "type":"Services"
        }
    ],
    "sg:phone":"+1 817 249 6266",
    "sg:postcode":"76126",
    "sg:province":"TX",
    "sg:tags":[
        "consultant",
        "business"
    ],
    "sg:website":"www.insightsuccess.com",
    "wof:name":"Directional Insight Intl Inc",
    "wof:placetype":"venue"
},
  "geometry": {"coordinates":[-97.46844400000001,32.672966],"type":"Point"}
}