{
  "type": "Feature",
  "properties": {
    "iso:country":"US",
    "sg:address":"2302 N Travis St",
    "sg:city":"Sherman",
    "sg:classifiers":[
        {
            "category":"Health Services",
            "subcategory":"Doctor",
            "type":"Services"
        }
    ],
    "sg:phone":"+1 903 892 4531",
    "sg:postcode":"75092",
    "sg:province":"TX",
    "wof:name":"Marze T Brawley DDS",
    "wof:placetype":"venue"
},
  "geometry": {"coordinates":[-96.616828,33.661738],"type":"Point"}
}