{
  "type": "Feature",
  "properties": {
    "iso:country":"US",
    "sg:address":"2829 Babcock Rd",
    "sg:city":"San Antonio",
    "sg:classifiers":[
        {
            "category":"Personal",
            "type":"Services"
        }
    ],
    "sg:phone":"+1 210 692 9153",
    "sg:postcode":"78229",
    "sg:province":"TX",
    "sg:tags":[
        "therapist",
        "massage"
    ],
    "wof:name":"Therapeutic Massage Ctr",
    "wof:placetype":"venue"
},
  "geometry": {"coordinates":[-98.590671,29.509915],"type":"Point"}
}