{
  "type": "Feature",
  "properties": {
    "iso:country":"US",
    "sg:address":"1112 Hays St",
    "sg:city":"San Antonio",
    "sg:classifiers":[
        {
            "category":"Wholesale",
            "subcategory":"Vending Machines",
            "type":"Manufacturing & Wholesale Goods"
        }
    ],
    "sg:phone":"+1 210 224 1026",
    "sg:postcode":"78202",
    "sg:province":"TX",
    "sg:tags":[
        "operator"
    ],
    "wof:name":"Suarez Vending",
    "wof:placetype":"venue"
},
  "geometry": {"coordinates":[-98.464213,29.430142],"type":"Point"}
}