{
  "type": "Feature",
  "properties": {
    "iso:country":"US",
    "sg:address":"3868 Mockingbird Ln",
    "sg:city":"Dallas",
    "sg:classifiers":[
        {
            "category":"Wholesale",
            "subcategory":"Music Publishers",
            "type":"Manufacturing & Wholesale Goods"
        },
        {
            "category":"Wholesale",
            "subcategory":"Books, Periodicals, & Newspapers",
            "type":"Manufacturing & Wholesale Goods"
        }
    ],
    "sg:phone":"+1 214 520 8560",
    "sg:postcode":"75205",
    "sg:province":"TX",
    "sg:tags":[
        "distribution"
    ],
    "sg:website":"http://www.sales-office.net",
    "wof:name":"Find My Bliss Management",
    "wof:placetype":"venue"
},
  "geometry": {"coordinates":[-96.79795,32.836578],"type":"Point"}
}