{
  "type": "Feature",
  "properties": {
    "iso:country":"US",
    "sg:address":"126 S Village St",
    "sg:city":"Zavalla",
    "sg:classifiers":[
        {
            "category":"Social Services",
            "type":"Services"
        }
    ],
    "sg:phone":"+1 936 897 2419",
    "sg:postcode":"75979",
    "sg:province":"TX",
    "sg:tags":[
        "organization",
        "welfare"
    ],
    "wof:name":"Lufkin Alliance-Mentally Ill",
    "wof:placetype":"venue"
},
  "geometry": {"coordinates":[-94.417298,30.775092],"type":"Point"}
}