{
  "type": "Feature",
  "properties": {
    "iso:country":"US",
    "sg:address":"12007 Bobcat Trl",
    "sg:city":"Austin",
    "sg:classifiers":[
        {
            "category":"Building & Trades",
            "subcategory":"Plumbing",
            "type":"Services"
        }
    ],
    "sg:phone":"+1 512 335 7733",
    "sg:postcode":"78750",
    "sg:province":"TX",
    "sg:tags":[
        "repair",
        "refrigeration",
        "contractor"
    ],
    "wof:name":"BT Services",
    "wof:placetype":"venue"
},
  "geometry": {"coordinates":[-97.81938100000001,30.460451],"type":"Point"}
}