{
  "type": "Feature",
  "properties": {
    "iso:country":"US",
    "sg:address":"4814 Kelsey Rd",
    "sg:city":"Dallas",
    "sg:classifiers":[
        {
            "category":"Banks & Credit Unions",
            "subcategory":"Financial Services",
            "type":"Services"
        }
    ],
    "sg:phone":"+1 214 361 7573",
    "sg:postcode":"75229",
    "sg:province":"TX",
    "sg:tags":[
        "investor"
    ],
    "wof:name":"Tpw 1 Investments Corp",
    "wof:placetype":"venue"
},
  "geometry": {"coordinates":[-96.82631000000001,32.886683],"type":"Point"}
}