{
  "type": "Feature",
  "properties": {
    "iso:country":"US",
    "sg:address":"1220 S 1st St",
    "sg:city":"Temple",
    "sg:classifiers":[
        {
            "category":"Insurance",
            "subcategory":"Insurance Agent",
            "type":"Services"
        }
    ],
    "sg:phone":"+1 254 774 7788",
    "sg:postcode":"76504",
    "sg:province":"TX",
    "wof:name":"Texas State Low Cost Insurance",
    "wof:placetype":"venue"
},
  "geometry": {"coordinates":[-97.346886,31.084516],"type":"Point"}
}