{
  "type": "Feature",
  "properties": {
    "iso:country":"US",
    "sg:address":"1001 State Hwy 160",
    "sg:city":"Whitewright",
    "sg:classifiers":[
        {
            "category":"Real Estate",
            "subcategory":"Real Estate Operator",
            "type":"Services"
        }
    ],
    "sg:phone":"+1 903 364 5630",
    "sg:postcode":"75491",
    "sg:province":"TX",
    "sg:tags":[
        "apartment"
    ],
    "wof:name":"Waterford Apartments",
    "wof:placetype":"venue"
},
  "geometry": {"coordinates":[-96.400852,33.504157],"type":"Point"}
}