{
  "type": "Feature",
  "properties": {
    "iso:country":"US",
    "sg:address":"1407 Spencer Hwy",
    "sg:city":"South Houston",
    "sg:classifiers":[
        {
            "category":"Professional",
            "type":"Services"
        }
    ],
    "sg:phone":"+1 713 943 7867",
    "sg:postcode":"77587",
    "sg:province":"TX",
    "wof:name":"Ink Stop",
    "wof:placetype":"venue"
},
  "geometry": {"coordinates":[-95.213689,29.664763],"type":"Point"}
}