{
  "type": "Feature",
  "properties": {
    "iso:country":"US",
    "sg:address":"33200 US Hwy 281",
    "sg:city":"Bulverde",
    "sg:classifiers":[
        {
            "category":"Building & Trades",
            "subcategory":"Construction",
            "type":"Services"
        }
    ],
    "sg:phone":"+1 210 477 1260",
    "sg:postcode":"78163",
    "sg:province":"TX",
    "sg:tags":[
        "metal"
    ],
    "wof:name":"Cross Metal Buildings Inc",
    "wof:placetype":"venue"
},
  "geometry": {"coordinates":[-98.42409499999999,29.780897],"type":"Point"}
}