{
  "type": "Feature",
  "properties": {
    "iso:country":"US",
    "sg:address":"12009 Coit Rd",
    "sg:city":"Dallas",
    "sg:classifiers":[
        {
            "category":"Professional",
            "type":"Services"
        }
    ],
    "sg:phone":"+1 972 385 3539",
    "sg:postcode":"75251",
    "sg:province":"TX",
    "wof:name":"For Fun LLC",
    "wof:placetype":"venue"
},
  "geometry": {"coordinates":[-96.769447,32.911711],"type":"Point"}
}