{
  "type": "Feature",
  "properties": {
    "iso:country":"US",
    "sg:address":"62 Hilltop Dr",
    "sg:city":"Kerrville",
    "sg:classifiers":[
        {
            "category":"Professional",
            "type":"Services"
        }
    ],
    "sg:phone":"+1 830 257 5834",
    "sg:postcode":"78028",
    "sg:province":"TX",
    "sg:tags":[
        "establishment"
    ],
    "wof:name":"Montebello Estates Water Works",
    "wof:placetype":"venue"
},
  "geometry": {"coordinates":[-99.10418799999999,29.995808],"type":"Point"}
}