{
  "type": "Feature",
  "properties": {
    "iso:country":"US",
    "sg:address":"2014 E Business Highway 83",
    "sg:city":"Mission",
    "sg:classifiers":[
        {
            "category":"Social Services",
            "type":"Services"
        }
    ],
    "sg:phone":"+1 956 583 4004",
    "sg:postcode":"78572",
    "sg:province":"TX",
    "sg:tags":[
        "day",
        "center",
        "adult",
        "care"
    ],
    "wof:name":"Heavenly Day Adult Day Care",
    "wof:placetype":"venue"
},
  "geometry": {"coordinates":[-98.358311,26.227088],"type":"Point"}
}