{
  "type": "Feature",
  "properties": {
    "iso:country":"US",
    "sg:address":"3489 Catclaw Dr",
    "sg:city":"Abilene",
    "sg:classifiers":[
        {
            "category":"Personal",
            "subcategory":"Beauty Salon",
            "type":"Services"
        },
        {
            "category":"Personal",
            "subcategory":"Barber",
            "type":"Services"
        }
    ],
    "sg:phone":"+1 325 691 1960",
    "sg:postcode":"79606",
    "sg:province":"TX",
    "wof:name":"Cool Cuts 4 Kids Inc",
    "wof:placetype":"venue"
},
  "geometry": {"coordinates":[-99.777038,32.408293],"type":"Point"}
}