{
  "type": "Feature",
  "properties": {
    "iso:country":"US",
    "sg:address":"2509 Tolosa Dr",
    "sg:city":"Dallas",
    "sg:classifiers":[
        {
            "category":"Professional",
            "subcategory":"Business Services",
            "type":"Services"
        }
    ],
    "sg:phone":"+1 214 320 9061",
    "sg:postcode":"75228",
    "sg:province":"TX",
    "sg:tags":[
        "process",
        "server"
    ],
    "wof:name":"Paul Freeman's Process",
    "wof:placetype":"venue"
},
  "geometry": {"coordinates":[-96.668143,32.851614],"type":"Point"}
}