{
  "type": "Feature",
  "properties": {
    "iso:country":"US",
    "sg:address":"3812 W 7th St",
    "sg:city":"Fort Worth",
    "sg:classifiers":[
        {
            "category":"Professional",
            "subcategory":"Business Services",
            "type":"Services"
        }
    ],
    "sg:phone":"+1 817 731 2991",
    "sg:postcode":"76107",
    "sg:province":"TX",
    "wof:name":"Lucy Steele",
    "wof:placetype":"venue"
},
  "geometry": {"coordinates":[-97.37513199999999,32.75154],"type":"Point"}
}