{
  "type": "Feature",
  "properties": {
    "iso:country":"US",
    "sg:address":"3315 State Hwy 103",
    "sg:city":"Lufkin",
    "sg:classifiers":[
        {
            "category":"Building & Trades",
            "subcategory":"Plumbing",
            "type":"Services"
        }
    ],
    "sg:phone":"+1 936 632 2411",
    "sg:postcode":"75904",
    "sg:province":"TX",
    "sg:tags":[
        "sheet",
        "work",
        "metal",
        "contractor"
    ],
    "wof:name":"Evans Sheet Metal",
    "wof:placetype":"venue"
},
  "geometry": {"coordinates":[-94.77121,31.362948],"type":"Point"}
}