{
  "type": "Feature",
  "properties": {
    "iso:country":"US",
    "sg:address":"6894 Bandera Rd",
    "sg:city":"San Antonio",
    "sg:classifiers":[
        {
            "category":"Home & Garden",
            "subcategory":"Furniture",
            "type":"Retail Goods"
        }
    ],
    "sg:phone":"+1 210 256 2000",
    "sg:postcode":"78238",
    "sg:province":"TX",
    "sg:tags":[
        "appliance"
    ],
    "wof:name":"Warehouse Furniture",
    "wof:placetype":"venue"
},
  "geometry": {"coordinates":[-98.62185599999999,29.497632],"type":"Point"}
}