{
  "type": "Feature",
  "properties": {
    "iso:country":"US",
    "sg:address":"155 Fredericksburg St",
    "sg:city":"Comfort",
    "sg:classifiers":[
        {
            "category":"Banks & Credit Unions",
            "subcategory":"Bank",
            "type":"Services"
        }
    ],
    "sg:phone":"+1 830 995 9865",
    "sg:postcode":"78013",
    "sg:province":"TX",
    "wof:name":"Texas American Bank",
    "wof:placetype":"venue"
},
  "geometry": {"coordinates":[-98.80515,29.951971],"type":"Point"}
}