{
  "type": "Feature",
  "properties": {
    "iso:country":"US",
    "sg:address":"516 S San Patricio Ave",
    "sg:city":"Sinton",
    "sg:classifiers":[
        {
            "category":"Professional",
            "type":"Services"
        }
    ],
    "sg:phone":"+1 361 364 0500",
    "sg:postcode":"78387",
    "sg:province":"TX",
    "wof:name":"South Texas Gas Svc",
    "wof:placetype":"venue"
},
  "geometry": {"coordinates":[-97.516806,28.032249],"type":"Point"}
}