{
  "type": "Feature",
  "properties": {
    "iso:country":"US",
    "sg:address":"302 W 14th St",
    "sg:city":"Post",
    "sg:classifiers":[
        {
            "category":"Personal",
            "subcategory":"Beauty Salon",
            "type":"Services"
        }
    ],
    "sg:phone":"+1 806 495 2617",
    "sg:postcode":"79356",
    "sg:province":"TX",
    "wof:name":"Donald Hair",
    "wof:placetype":"venue"
},
  "geometry": {"coordinates":[-101.380939,33.196949],"type":"Point"}
}