{
  "type": "Feature",
  "properties": {
    "iso:country":"US",
    "sg:address":"6930 W Military Dr",
    "sg:city":"San Antonio",
    "sg:classifiers":[
        {
            "category":"Shopping",
            "subcategory":"Clothing, Apparel, & Fashions",
            "type":"Retail Goods"
        }
    ],
    "sg:phone":"+1 210 645 9900",
    "sg:postcode":"78227",
    "sg:province":"TX",
    "sg:tags":[
        "alteration"
    ],
    "wof:name":"Lee Alterations & Cleaners",
    "wof:placetype":"venue"
},
  "geometry": {"coordinates":[-98.629093,29.405941],"type":"Point"}
}