{
  "type": "Feature",
  "properties": {
    "iso:country":"US",
    "sg:address":"911 Sam Houston Dr",
    "sg:city":"Victoria",
    "sg:classifiers":[
        {
            "category":"Autos & Motor Vehicles",
            "subcategory":"Automobile Sales",
            "type":"Retail Goods"
        }
    ],
    "sg:phone":"+1 361 576 1064",
    "sg:postcode":"77901",
    "sg:province":"TX",
    "sg:tags":[
        "used"
    ],
    "wof:name":"Obenhaus Enterprises Inc",
    "wof:placetype":"venue"
},
  "geometry": {"coordinates":[-96.97377,28.822031],"type":"Point"}
}