{
  "type": "Feature",
  "properties": {
    "iso:country":"US",
    "sg:address":"2261 Singleton Blvd",
    "sg:city":"Dallas",
    "sg:classifiers":[
        {
            "category":"Shopping",
            "subcategory":"Music",
            "type":"Retail Goods"
        }
    ],
    "sg:phone":"+1 214 631 1556",
    "sg:postcode":"75212",
    "sg:province":"TX",
    "wof:name":"Latin One Stop Mus Rcrding LLC",
    "wof:placetype":"venue"
},
  "geometry": {"coordinates":[-96.859917,32.778771],"type":"Point"}
}