{
  "type": "Feature",
  "properties": {
    "iso:country":"US",
    "sg:address":"4601 West Fwy",
    "sg:city":"Fort Worth",
    "sg:classifiers":[
        {
            "category":"Utilities",
            "subcategory":"Mobile Phone",
            "type":"Services"
        }
    ],
    "sg:phone":"+1 817 738 4302",
    "sg:postcode":"76107",
    "sg:province":"TX",
    "sg:tags":[
        "telephone",
        "cellular"
    ],
    "wof:name":"Cingular Wireless",
    "wof:placetype":"venue"
},
  "geometry": {"coordinates":[-97.387773,32.733311],"type":"Point"}
}