{
  "type": "Feature",
  "properties": {
    "iso:country":"US",
    "sg:address":"711 S el Paso St",
    "sg:city":"El Paso",
    "sg:classifiers":[
        {
            "category":"Shopping",
            "subcategory":"Clothing, Apparel, & Fashions",
            "type":"Retail Goods"
        }
    ],
    "sg:phone":"+1 915 532 0221",
    "sg:postcode":"79901",
    "sg:province":"TX",
    "wof:name":"Popcorn",
    "wof:placetype":"venue"
},
  "geometry": {"coordinates":[-106.487182,31.751734],"type":"Point"}
}