{
  "type": "Feature",
  "properties": {
    "iso:country":"US",
    "sg:address":"4018 FM 1781",
    "sg:city":"Rockport",
    "sg:classifiers":[
        {
            "category":"Professional",
            "type":"Services"
        }
    ],
    "sg:phone":"+1 361 729 9578",
    "sg:postcode":"78382",
    "sg:province":"TX",
    "sg:tags":[
        "establishment"
    ],
    "wof:name":"WITT Carrie Kitchens",
    "wof:placetype":"venue"
},
  "geometry": {"coordinates":[-97.06106,28.086693],"type":"Point"}
}