{
  "type": "Feature",
  "properties": {
    "iso:country":"US",
    "sg:address":"815 E Abram St",
    "sg:city":"Arlington",
    "sg:classifiers":[
        {
            "category":"Shopping",
            "subcategory":"Pharmacy",
            "type":"Retail Goods"
        }
    ],
    "sg:phone":"+1 817 804 0109",
    "sg:postcode":"76010",
    "sg:province":"TX",
    "wof:name":"CVS",
    "wof:placetype":"venue"
},
  "geometry": {"coordinates":[-97.09754100000001,32.73563],"type":"Point"}
}