{
  "type": "Feature",
  "properties": {
    "iso:country":"US",
    "sg:address":"321 New Dallas Hwy",
    "sg:city":"Waco",
    "sg:classifiers":[
        {
            "category":"Wholesale",
            "subcategory":"Machinery & Supplies",
            "type":"Manufacturing & Wholesale Goods"
        }
    ],
    "sg:phone":"+1 254 799 6201",
    "sg:postcode":"76705",
    "sg:province":"TX",
    "sg:tags":[
        "equipment",
        "welding"
    ],
    "wof:name":"Praxair Inc",
    "wof:placetype":"venue"
},
  "geometry": {"coordinates":[-97.109258,31.613387],"type":"Point"}
}