{
  "type": "Feature",
  "properties": {
    "iso:country":"US",
    "sg:address":"918 Main St",
    "sg:city":"Bastrop",
    "sg:classifiers":[
        {
            "category":"Shopping",
            "subcategory":"Used Merchandise",
            "type":"Retail Goods"
        }
    ],
    "sg:phone":"+1 512 321 3635",
    "sg:postcode":"78602",
    "sg:province":"TX",
    "wof:name":"Old Town Emporium",
    "wof:placetype":"venue"
},
  "geometry": {"coordinates":[-97.320049,30.10926],"type":"Point"}
}