{
  "type": "Feature",
  "properties": {
    "iso:country":"US",
    "sg:address":"1006 Lawndale Ave",
    "sg:city":"Victoria",
    "sg:classifiers":[
        {
            "category":"Professional",
            "type":"Services"
        }
    ],
    "sg:phone":"+1 361 572 4261",
    "sg:postcode":"77901",
    "sg:province":"TX",
    "sg:tags":[
        "establishment"
    ],
    "wof:name":"S Vela",
    "wof:placetype":"venue"
},
  "geometry": {"coordinates":[-96.995803,28.830659],"type":"Point"}
}