{
  "type": "Feature",
  "properties": {
    "iso:country":"US",
    "sg:address":"2313 Thornton Rd",
    "sg:city":"Austin",
    "sg:classifiers":[
        {
            "category":"Autos & Motor Vehicles",
            "subcategory":"Auto Supplies",
            "type":"Retail Goods"
        },
        {
            "category":"Retail",
            "subcategory":"Auto Repair",
            "type":"Services"
        }
    ],
    "sg:phone":"+1 512 445 6731",
    "sg:postcode":"78704",
    "sg:province":"TX",
    "sg:tags":[
        "engine",
        "installation",
        "exchange",
        "transmission",
        "brake",
        "rebuilding"
    ],
    "sg:website":"http://www.zimmerautorepair.com",
    "wof:name":"Zimmer's Auto Repair",
    "wof:placetype":"venue"
},
  "geometry": {"coordinates":[-97.772233,30.244795],"type":"Point"}
}