{
  "type": "Feature",
  "properties": {
    "iso:country":"US",
    "sg:address":"1000 Magnolia St",
    "sg:city":"Lockhart",
    "sg:classifiers":[
        {
            "category":"Wholesale",
            "subcategory":"Durable Goods & Equipment",
            "type":"Manufacturing & Wholesale Goods"
        }
    ],
    "sg:phone":"+1 512 376 4415",
    "sg:postcode":"78644",
    "sg:province":"TX",
    "sg:tags":[
        "laboratory"
    ],
    "wof:name":"Accredited Equipment & Service",
    "wof:placetype":"venue"
},
  "geometry": {"coordinates":[-97.684167,29.882889],"type":"Point"}
}