{
  "type": "Feature",
  "properties": {
    "iso:country":"US",
    "sg:address":"2842 5th Ave",
    "sg:city":"Fort Worth",
    "sg:classifiers":[
        {
            "category":"Professional",
            "subcategory":"Management & Consulting",
            "type":"Services"
        }
    ],
    "sg:phone":"+1 817 923 9233",
    "sg:postcode":"76110",
    "sg:province":"TX",
    "sg:tags":[
        "marketing",
        "program"
    ],
    "wof:name":"Register To Win",
    "wof:placetype":"venue"
},
  "geometry": {"coordinates":[-97.33919400000001,32.710332],"type":"Point"}
}