{
  "type": "Feature",
  "properties": {
    "iso:country":"US",
    "sg:address":"3211 Timberview Dr",
    "sg:city":"Sugar Land",
    "sg:classifiers":[
        {
            "category":"Professional",
            "type":"Services"
        }
    ],
    "sg:phone":"+1 281 980 6562",
    "sg:postcode":"77479",
    "sg:province":"TX",
    "wof:name":"Outside Box",
    "wof:placetype":"venue"
},
  "geometry": {"coordinates":[-95.598668,29.575231],"type":"Point"}
}