{
  "type": "Feature",
  "properties": {
    "iso:country":"US",
    "sg:address":"3004 50th St",
    "sg:city":"Lubbock",
    "sg:classifiers":[
        {
            "category":"Building & Trades",
            "subcategory":"Construction",
            "type":"Services"
        }
    ],
    "sg:phone":"+1 806 797 8898",
    "sg:postcode":"79413",
    "sg:province":"TX",
    "sg:tags":[
        "general",
        "contractor"
    ],
    "wof:name":"Associated General Contractors",
    "wof:placetype":"venue"
},
  "geometry": {"coordinates":[-101.881182,33.548799],"type":"Point"}
}