{
  "type": "Feature",
  "properties": {
    "iso:country":"US",
    "sg:address":"12 Wicklow Dr",
    "sg:city":"Orange",
    "sg:classifiers":[
        {
            "category":"Shopping",
            "subcategory":"Catalog Store",
            "type":"Retail Goods"
        }
    ],
    "sg:phone":"+1 409 883 0008",
    "sg:postcode":"77632",
    "sg:province":"TX",
    "sg:tags":[
        "mail",
        "house"
    ],
    "wof:name":"Tracies Candle Creations",
    "wof:placetype":"venue"
},
  "geometry": {"coordinates":[-93.753568,30.165134],"type":"Point"}
}