{
  "type": "Feature",
  "properties": {
    "iso:country":"US",
    "sg:address":"2522 Berkeley Ave",
    "sg:city":"Austin",
    "sg:classifiers":[
        {
            "category":"Local Transit",
            "type":"Transportation"
        }
    ],
    "sg:phone":"+1 512 444 7337",
    "sg:postcode":"78745",
    "sg:province":"TX",
    "sg:tags":[
        "passenger"
    ],
    "wof:name":"Liberty Transportation",
    "wof:placetype":"venue"
},
  "geometry": {"coordinates":[-97.812439,30.208253],"type":"Point"}
}