{
  "type": "Feature",
  "properties": {
    "iso:country":"US",
    "sg:address":"15806 Blue Ridge Rd",
    "sg:city":"Missouri City",
    "sg:classifiers":[
        {
            "category":"Professional",
            "type":"Services"
        }
    ],
    "sg:phone":"+1 281 835 0787",
    "sg:postcode":"77489",
    "sg:province":"TX",
    "wof:name":"New Light Work Inc",
    "wof:placetype":"venue"
},
  "geometry": {"coordinates":[-95.492485,29.598309],"type":"Point"}
}