{
  "type": "Feature",
  "properties": {
    "iso:country":"US",
    "sg:address":"9050 N Capital of Texas Hwy",
    "sg:city":"Austin",
    "sg:classifiers":[
        {
            "category":"Professional",
            "subcategory":"Computer Services",
            "type":"Services"
        }
    ],
    "sg:phone":"+1 512 436 8000",
    "sg:postcode":"78759",
    "sg:province":"TX",
    "sg:tags":[
        "program",
        "software"
    ],
    "wof:name":"Tivoli Systems Inc (de)",
    "wof:placetype":"venue"
},
  "geometry": {"coordinates":[-97.75533799999999,30.38824],"type":"Point"}
}