{
  "type": "Feature",
  "properties": {
    "iso:country":"US",
    "sg:address":"1713 N 25th St",
    "sg:city":"Harlingen",
    "sg:classifiers":[
        {
            "category":"Home & Garden",
            "subcategory":"Furniture",
            "type":"Retail Goods"
        }
    ],
    "sg:phone":"+1 956 425 0539",
    "sg:postcode":"78550",
    "sg:province":"TX",
    "sg:tags":[
        "builder",
        "custom"
    ],
    "wof:name":"Sosa Furniture Cabinets",
    "wof:placetype":"venue"
},
  "geometry": {"coordinates":[-97.67027299999999,26.21151],"type":"Point"}
}