{
  "type": "Feature",
  "properties": {
    "iso:country":"US",
    "sg:address":"5930 Sam Houston Pkwy",
    "sg:city":"Humble",
    "sg:classifiers":[
        {
            "category":"Freight",
            "type":"Transportation"
        }
    ],
    "sg:phone":"+1 281 441 1902",
    "sg:postcode":"77396",
    "sg:province":"TX",
    "sg:tags":[
        "hauling",
        "trucking"
    ],
    "wof:name":"Debrick Truck Line",
    "wof:placetype":"venue"
},
  "geometry": {"coordinates":[-95.302829,29.939563],"type":"Point"}
}