{
  "type": "Feature",
  "properties": {
    "iso:country":"US",
    "sg:address":"126 Old US Hwy 90 W",
    "sg:city":"San Antonio",
    "sg:classifiers":[
        {
            "category":"Restaurant",
            "type":"Food & Drink"
        }
    ],
    "sg:phone":"+1 210 435 2211",
    "sg:postcode":"78237",
    "sg:province":"TX",
    "sg:tags":[
        "eating"
    ],
    "wof:name":"Golden Nuggett Fried Chicken &",
    "wof:placetype":"venue"
},
  "geometry": {"coordinates":[-98.560731,29.431244],"type":"Point"}
}