{
  "type": "Feature",
  "properties": {
    "iso:country":"US",
    "sg:address":"102 S Friou St",
    "sg:city":"Alvarado",
    "sg:classifiers":[
        {
            "category":"Real Estate",
            "subcategory":"Real Estate Agent",
            "type":"Services"
        }
    ],
    "sg:phone":"+1 817 645 5559",
    "sg:postcode":"76009",
    "sg:province":"TX",
    "wof:name":"Long Gina Country Living Rlty",
    "wof:placetype":"venue"
},
  "geometry": {"coordinates":[-97.211287,32.406262],"type":"Point"}
}