{
  "type": "Feature",
  "properties": {
    "iso:country":"US",
    "sg:address":"9123 Southbluff Blvd",
    "sg:city":"Houston",
    "sg:classifiers":[
        {
            "category":"Wholesale",
            "subcategory":"Machinery & Supplies",
            "type":"Manufacturing & Wholesale Goods"
        }
    ],
    "sg:phone":"+1 281 484 2905",
    "sg:postcode":"77089",
    "sg:province":"TX",
    "sg:tags":[
        "equipment",
        "industrial"
    ],
    "wof:name":"Diamond Machinery",
    "wof:placetype":"venue"
},
  "geometry": {"coordinates":[-95.24030999999999,29.598301],"type":"Point"}
}