{
  "type": "Feature",
  "properties": {
    "iso:country":"US",
    "sg:address":"4115 Cleveland Ave",
    "sg:city":"Beaumont",
    "sg:classifiers":[
        {
            "category":"Building & Trades",
            "subcategory":"Construction",
            "type":"Services"
        }
    ],
    "sg:phone":"+1 409 832 2429",
    "sg:postcode":"77703",
    "sg:province":"TX",
    "sg:tags":[
        "floor",
        "laying",
        "contractor"
    ],
    "wof:name":"Dewaynes Carpet Installation",
    "wof:placetype":"venue"
},
  "geometry": {"coordinates":[-94.12206399999999,30.118556],"type":"Point"}
}