{
  "type": "Feature",
  "properties": {
    "iso:country":"US",
    "sg:address":"5901 Hillcroft St Suite D-4",
    "sg:city":"Houston",
    "sg:classifiers":[
        {
            "category":"Insurance",
            "subcategory":"Insurance Agent",
            "type":"Services"
        },
        {
            "category":"Insurance",
            "subcategory":"Hazard Insurance",
            "type":"Services"
        }
    ],
    "sg:phone":"+1 281 619 8403",
    "sg:postcode":"77036",
    "sg:province":"TX",
    "sg:tags":[
        "auto",
        "property",
        "motorcycle",
        "casualty"
    ],
    "sg:website":"http://ad.doubleclick.net/clk;227136937;50888565;y?http://www.ronniepatelinsurance.com",
    "wof:name":"Save on Auto Insurance with Ronnie Patel",
    "wof:placetype":"venue"
},
  "geometry": {"coordinates":[-95.50032299999999,29.717969],"type":"Point"}
}