{
  "type": "Feature",
  "properties": {
    "iso:country":"US",
    "sg:address":"1928 W Belt",
    "sg:city":"Houston",
    "sg:classifiers":[
        {
            "category":"Health Services",
            "subcategory":"Dentist",
            "type":"Services"
        }
    ],
    "sg:phone":"+1 713 590 9777",
    "sg:postcode":"77002",
    "sg:province":"TX",
    "wof:name":"Dental Wellness Group",
    "wof:placetype":"venue"
},
  "geometry": {"coordinates":[-95.563091,29.806201],"type":"Point"}
}