{
  "type": "Feature",
  "properties": {
    "iso:country":"US",
    "sg:address":"200 Northstar Rd",
    "sg:city":"Royse City",
    "sg:classifiers":[
        {
            "category":"Health Services",
            "subcategory":"Doctor",
            "type":"Services"
        }
    ],
    "sg:phone":"+1 972 635 9577",
    "sg:postcode":"75189",
    "sg:province":"TX",
    "sg:tags":[
        "physician",
        "surgeon"
    ],
    "wof:name":"Royse City Medical & Surgical",
    "wof:placetype":"venue"
},
  "geometry": {"coordinates":[-96.37549799999999,32.980526],"type":"Point"}
}