{
  "type": "Feature",
  "properties": {
    "iso:country":"US",
    "sg:address":"601 Samuel St",
    "sg:city":"Marshall",
    "sg:classifiers":[
        {
            "category":"Organizations",
            "subcategory":"Religious Organization",
            "type":"Services"
        }
    ],
    "sg:phone":"+1 903 923 9522",
    "sg:postcode":"75672",
    "sg:province":"TX",
    "sg:tags":[
        "church"
    ],
    "wof:name":"St Mark's United Meth Prsng",
    "wof:placetype":"venue"
},
  "geometry": {"coordinates":[-94.320331,32.546917],"type":"Point"}
}