{
  "type": "Feature",
  "properties": {
    "iso:country":"US",
    "sg:address":"6121 Greenville Ave",
    "sg:city":"Dallas",
    "sg:classifiers":[
        {
            "category":"Personal",
            "subcategory":"Beauty Salon",
            "type":"Services"
        }
    ],
    "sg:phone":"+1 214 696 5007",
    "sg:postcode":"75206",
    "sg:province":"TX",
    "sg:tags":[
        "shop"
    ],
    "wof:name":"Hair Colour Excellence",
    "wof:placetype":"venue"
},
  "geometry": {"coordinates":[-96.768039,32.860203],"type":"Point"}
}