{
  "type": "Feature",
  "properties": {
    "iso:country":"US",
    "sg:address":"2381 N Chestnut Dr",
    "sg:city":"Pampa",
    "sg:classifiers":[
        {
            "category":"Health Services",
            "subcategory":"Doctor",
            "type":"Services"
        }
    ],
    "sg:phone":"+1 806 669 3235",
    "sg:postcode":"79065",
    "sg:province":"TX",
    "sg:tags":[
        "medical"
    ],
    "wof:name":"Jack & Phyllis Curtis",
    "wof:placetype":"venue"
},
  "geometry": {"coordinates":[-100.95934699999999,35.563073],"type":"Point"}
}