{
  "type": "Feature",
  "properties": {
    "iso:country":"US",
    "sg:address":"18539 Skytrain Rd",
    "sg:city":"Houston",
    "sg:classifiers":[
        {
            "category":"Airline",
            "type":"Transportation"
        }
    ],
    "sg:phone":"+1 281 821 9434",
    "sg:postcode":"77032",
    "sg:province":"TX",
    "sg:tags":[
        "company"
    ],
    "wof:name":"America West Airlines Inc",
    "wof:placetype":"venue"
},
  "geometry": {"coordinates":[-95.350561,29.98237],"type":"Point"}
}