{
  "type": "Feature",
  "properties": {
    "iso:country":"US",
    "sg:address":"304 E Overland Ave",
    "sg:city":"El Paso",
    "sg:classifiers":[
        {
            "category":"Shopping",
            "subcategory":"Clothing, Apparel, & Fashions",
            "type":"Retail Goods"
        }
    ],
    "sg:phone":"+1 915 544 7340",
    "sg:postcode":"79901",
    "sg:province":"TX",
    "sg:tags":[
        "ready",
        "to",
        "wear",
        "uniform"
    ],
    "wof:name":"Bazaar Uniforms & Men's Store",
    "wof:placetype":"venue"
},
  "geometry": {"coordinates":[-106.48630900000001,31.757374],"type":"Point"}
}