{
  "type": "Feature",
  "properties": {
    "iso:country":"US",
    "sg:address":"100 S Rangerville Rd",
    "sg:city":"Harlingen",
    "sg:classifiers":[
        {
            "category":"Education",
            "subcategory":"Special Training",
            "type":"Public Place"
        }
    ],
    "sg:phone":"+1 956 423 7146",
    "sg:postcode":"78552",
    "sg:province":"TX",
    "sg:tags":[
        "center"
    ],
    "wof:name":"Bonita Park Family Learning",
    "wof:placetype":"venue"
},
  "geometry": {"coordinates":[-97.70123700000001,26.172217],"type":"Point"}
}