{
  "type": "Feature",
  "properties": {
    "iso:country":"US",
    "sg:address":"505 N Sam Houston Pkwy E Ste 142",
    "sg:city":"Houston",
    "sg:classifiers":[
        {
            "category":"Insurance",
            "subcategory":"Health Insurance",
            "type":"Services"
        }
    ],
    "sg:phone":"+1 281 820 4322",
    "sg:postcode":"77060",
    "sg:province":"TX",
    "sg:tags":[
        "market"
    ],
    "sg:website":"www.healthyfaceandbody.com",
    "wof:name":"Healthy Face & Body",
    "wof:placetype":"venue"
},
  "geometry": {"coordinates":[-95.393075,29.939113],"type":"Point"}
}