{
  "type": "Feature",
  "properties": {
    "iso:country":"US",
    "sg:address":"13375 Noel Rd",
    "sg:city":"Dallas",
    "sg:classifiers":[
        {
            "category":"Shopping",
            "subcategory":"Department Store",
            "type":"Retail Goods"
        }
    ],
    "sg:phone":"+1 972 851 5185",
    "sg:postcode":"75240",
    "sg:province":"TX",
    "wof:name":"Macys",
    "wof:placetype":"venue"
},
  "geometry": {"coordinates":[-96.818122,32.929405],"type":"Point"}
}