{
  "type": "Feature",
  "properties": {
    "iso:country":"US",
    "sg:address":"2155 Stillwater Dr",
    "sg:city":"Beaumont",
    "sg:classifiers":[
        {
            "category":"Organizations",
            "subcategory":"Professional Association",
            "type":"Services"
        }
    ],
    "sg:phone":"+1 409 722 5402",
    "sg:postcode":"77705",
    "sg:province":"TX",
    "sg:tags":[
        "business",
        "trade"
    ],
    "wof:name":"Golden Triangle Minority Business Council",
    "wof:placetype":"venue"
},
  "geometry": {"coordinates":[-94.029949,29.985481],"type":"Point"}
}