{
  "type": "Feature",
  "properties": {
    "iso:country":"US",
    "sg:address":"410 W Red Bird Ln",
    "sg:city":"Duncanville",
    "sg:classifiers":[
        {
            "category":"Industrial Area",
            "type":"Public Place"
        }
    ],
    "sg:phone":"+1 972 296 7272",
    "sg:postcode":"75116",
    "sg:province":"TX",
    "sg:tags":[
        "consultant"
    ],
    "wof:name":"Lonzo H Stillwell",
    "wof:placetype":"venue"
},
  "geometry": {"coordinates":[-96.91400299999999,32.674606],"type":"Point"}
}