{
  "type": "Feature",
  "properties": {
    "iso:country":"US",
    "sg:address":"619 E Harrison Ave",
    "sg:city":"Harlingen",
    "sg:classifiers":[
        {
            "category":"Restaurant",
            "type":"Food & Drink"
        }
    ],
    "sg:phone":"+1 956 364 1870",
    "sg:postcode":"78550",
    "sg:province":"TX",
    "sg:tags":[
        "eating"
    ],
    "wof:name":"Melas Cafe Express",
    "wof:placetype":"venue"
},
  "geometry": {"coordinates":[-97.689329,26.190754],"type":"Point"}
}