{
  "type": "Feature",
  "properties": {
    "iso:country":"US",
    "sg:address":"8002 Boone Rd",
    "sg:city":"Houston",
    "sg:classifiers":[
        {
            "category":"Food & Beverages",
            "subcategory":"Groceries & Convenience Stores",
            "type":"Retail Goods"
        }
    ],
    "sg:phone":"+1 281 495 7947",
    "sg:postcode":"77072",
    "sg:province":"TX",
    "wof:name":"Boone Food Store",
    "wof:placetype":"venue"
},
  "geometry": {"coordinates":[-95.574724,29.690243],"type":"Point"}
}