{
  "type": "Feature",
  "properties": {
    "iso:country":"US",
    "sg:address":"1408 S 31st St",
    "sg:city":"Temple",
    "sg:classifiers":[
        {
            "category":"Utilities",
            "subcategory":"Mobile Phone",
            "type":"Services"
        }
    ],
    "sg:phone":"+1 254 899 0530",
    "sg:postcode":"76504",
    "sg:province":"TX",
    "sg:tags":[
        "communication",
        "radiotelephone"
    ],
    "wof:name":"Aladdin Wireless Communciation",
    "wof:placetype":"venue"
},
  "geometry": {"coordinates":[-97.36302999999999,31.086785],"type":"Point"}
}