{
  "type": "Feature",
  "properties": {
    "iso:country":"US",
    "sg:address":"1200 S Sugar Rd",
    "sg:city":"Edinburg",
    "sg:classifiers":[
        {
            "category":"Banks & Credit Unions",
            "subcategory":"Financial Services",
            "type":"Services"
        }
    ],
    "sg:phone":"+1 956 381 5926",
    "sg:postcode":"78539",
    "sg:province":"TX",
    "sg:tags":[
        "investor"
    ],
    "wof:name":"Nevrez Investments Inc",
    "wof:placetype":"venue"
},
  "geometry": {"coordinates":[-98.18004000000001,26.293184],"type":"Point"}
}