{
  "type": "Feature",
  "properties": {
    "iso:country":"US",
    "sg:address":"18363 Kuykendahl Rd",
    "sg:city":"Spring",
    "sg:classifiers":[
        {
            "category":"Restaurant",
            "type":"Food & Drink"
        }
    ],
    "sg:phone":"+1 281 251 9190",
    "sg:postcode":"77379",
    "sg:province":"TX",
    "sg:tags":[
        "chinese"
    ],
    "wof:name":"Tommy Wok",
    "wof:placetype":"venue"
},
  "geometry": {"coordinates":[-95.48700100000001,30.038251],"type":"Point"}
}