{
  "type": "Feature",
  "properties": {
    "iso:country":"US",
    "sg:address":"5730 US Hwy 87",
    "sg:city":"San Angelo",
    "sg:classifiers":[
        {
            "category":"Arts & Performance",
            "subcategory":"Theater",
            "type":"Entertainment"
        }
    ],
    "sg:phone":"+1 325 486 0767",
    "sg:postcode":"76901",
    "sg:province":"TX",
    "sg:tags":[
        "entertainer"
    ],
    "wof:name":"Love Shack",
    "wof:placetype":"venue"
},
  "geometry": {"coordinates":[-100.48340399999999,31.521983],"type":"Point"}
}