{
  "type": "Feature",
  "properties": {
    "iso:country":"US",
    "sg:address":"100 N Expressway",
    "sg:city":"Brownsville",
    "sg:classifiers":[
        {
            "category":"Utilities",
            "subcategory":"Mobile Phone",
            "type":"Services"
        },
        {
            "category":"Coffee & Tea",
            "type":"Food & Drink"
        }
    ],
    "sg:phone":"+1 956 541 4178",
    "sg:postcode":"78521",
    "sg:province":"TX",
    "sg:tags":[
        "shop",
        "wi-fi",
        "espresso",
        "hotspot",
        "restaurant"
    ],
    "sg:website":"http://www.starbuckscoffee.com",
    "wof:name":"Starbucks Coffee",
    "wof:placetype":"venue"
},
  "geometry": {"coordinates":[-97.49030500000001,25.923244],"type":"Point"}
}