{
  "type": "Feature",
  "properties": {
    "iso:country":"US",
    "sg:address":"1221 W Bond St",
    "sg:city":"Denison",
    "sg:classifiers":[
        {
            "category":"Freight",
            "type":"Transportation"
        }
    ],
    "sg:phone":"+1 903 463 4406",
    "sg:postcode":"75020",
    "sg:province":"TX",
    "sg:tags":[
        "arrangement"
    ],
    "wof:name":"Texoma Logistics Inc",
    "wof:placetype":"venue"
},
  "geometry": {"coordinates":[-96.553326,33.761243],"type":"Point"}
}