{
  "type": "Feature",
  "properties": {
    "iso:country":"US",
    "sg:address":"9008 Brigadoon St",
    "sg:city":"San Antonio",
    "sg:classifiers":[
        {
            "category":"Professional",
            "type":"Services"
        }
    ],
    "sg:phone":"+1 210 680 6906",
    "sg:postcode":"78254",
    "sg:province":"TX",
    "wof:name":"Kybrooke Inc",
    "wof:placetype":"venue"
},
  "geometry": {"coordinates":[-98.665091,29.526308],"type":"Point"}
}