{
  "type": "Feature",
  "properties": {
    "iso:country":"US",
    "sg:address":"301 US Hwy 380",
    "sg:city":"Farmersville",
    "sg:classifiers":[
        {
            "category":"Insurance",
            "subcategory":"Insurance Agent",
            "type":"Services"
        }
    ],
    "sg:phone":"+1 972 784 8999",
    "sg:postcode":"75442",
    "sg:province":"TX",
    "wof:name":"Donna Rice Insurance Agency",
    "wof:placetype":"venue"
},
  "geometry": {"coordinates":[-96.35571899999999,33.156487],"type":"Point"}
}