{
  "type": "Feature",
  "properties": {
    "iso:country":"US",
    "sg:address":"9 Bramblewood Ln",
    "sg:city":"Canyon",
    "sg:phone":"+1 806 655 4674",
    "sg:postcode":"79015",
    "sg:province":"TX",
    "sg:tags":[
        "farm",
        "wheat"
    ],
    "wof:name":"Bob Henry",
    "wof:placetype":"venue"
},
  "geometry": {"coordinates":[-101.925,34.987897],"type":"Point"}
}