{
  "type": "Feature",
  "properties": {
    "iso:country":"US",
    "sg:address":"8754 E Rylander Cir",
    "sg:city":"Houston",
    "sg:classifiers":[
        {
            "category":"Retail",
            "subcategory":"Repair Shop",
            "type":"Services"
        }
    ],
    "sg:phone":"+1 713 774 6035",
    "sg:postcode":"77071",
    "sg:province":"TX",
    "wof:name":"Custom Electronic Design",
    "wof:placetype":"venue"
},
  "geometry": {"coordinates":[-95.532259,29.642676],"type":"Point"}
}