{
  "type": "Feature",
  "properties": {
    "iso:country":"US",
    "sg:address":"3313 FM 3136",
    "sg:city":"Cleburne",
    "sg:classifiers":[
        {
            "category":"Building & Trades",
            "subcategory":"Cleaning & Sanitation",
            "type":"Services"
        }
    ],
    "sg:phone":"+1 817 558 6698",
    "sg:postcode":"76031",
    "sg:province":"TX",
    "sg:tags":[
        "maintenance"
    ],
    "wof:name":"Donnie's Maintenance Co",
    "wof:placetype":"venue"
},
  "geometry": {"coordinates":[-97.324291,32.354473],"type":"Point"}
}