{
  "type": "Feature",
  "properties": {
    "iso:country":"US",
    "sg:address":"1161 Angelina",
    "sg:city":"Austin",
    "sg:classifiers":[
        {
            "category":"Education",
            "subcategory":"Library",
            "type":"Public Place"
        }
    ],
    "sg:phone":"+1 512 974 1010",
    "sg:postcode":"78702",
    "sg:province":"TX",
    "sg:website":"www.austinlibrary.com/branches/i...",
    "wof:name":"Austin Public Library - Carver Branch",
    "wof:placetype":"venue"
},
  "geometry": {"coordinates":[-97.72444,30.269707],"type":"Point"}
}