{
  "type": "Feature",
  "properties": {
    "iso:country":"US",
    "sg:address":"9105 S McColl Rd",
    "sg:city":"Hidalgo",
    "sg:classifiers":[
        {
            "category":"Wholesale",
            "subcategory":"Auto Parts",
            "type":"Manufacturing & Wholesale Goods"
        }
    ],
    "sg:phone":"+1 956 843 6772",
    "sg:postcode":"78503",
    "sg:province":"TX",
    "sg:tags":[
        "automobile",
        "rebuilt"
    ],
    "wof:name":"South Mc Coll Parts & Sales",
    "wof:placetype":"venue"
},
  "geometry": {"coordinates":[-98.225827,26.124892],"type":"Point"}
}