{
  "type": "Feature",
  "properties": {
    "iso:country":"US",
    "sg:address":"515 Texas Ave",
    "sg:city":"Texas City",
    "sg:classifiers":[
        {
            "category":"Retail",
            "subcategory":"Auto Repair",
            "type":"Services"
        }
    ],
    "sg:phone":"+1 409 935 9679",
    "sg:postcode":"77590",
    "sg:province":"TX",
    "sg:tags":[
        "muffler",
        "exhaust",
        "system"
    ],
    "wof:name":"Mighty Muffler Svc Ctr",
    "wof:placetype":"venue"
},
  "geometry": {"coordinates":[-94.902362,29.383971],"type":"Point"}
}