{
  "type": "Feature",
  "properties": {
    "iso:country":"US",
    "sg:address":"6910 Meadow Lake Ave",
    "sg:city":"Dallas",
    "sg:classifiers":[
        {
            "category":"Professional",
            "subcategory":"Business Services",
            "type":"Services"
        }
    ],
    "sg:phone":"+1 214 321 5427",
    "sg:postcode":"75214",
    "sg:province":"TX",
    "wof:name":"Schumacher Interiors",
    "wof:placetype":"venue"
},
  "geometry": {"coordinates":[-96.738822,32.823583],"type":"Point"}
}