{
  "type": "Feature",
  "properties": {
    "iso:country":"US",
    "sg:address":"125 Moore St",
    "sg:city":"San Marcos",
    "sg:classifiers":[
        {
            "category":"Professional",
            "type":"Services"
        }
    ],
    "sg:phone":"+1 512 396 1040",
    "sg:postcode":"78666",
    "sg:province":"TX",
    "sg:tags":[
        "establishment"
    ],
    "wof:name":"Professional Medical Ofc Sltn",
    "wof:placetype":"venue"
},
  "geometry": {"coordinates":[-97.945904,29.882027],"type":"Point"}
}