{
  "type": "Feature",
  "properties": {
    "iso:country":"US",
    "sg:address":"16803 Hedgecroft Dr",
    "sg:city":"Houston",
    "sg:classifiers":[
        {
            "category":"Wholesale",
            "subcategory":"Medical Equipment & Supplies",
            "type":"Manufacturing & Wholesale Goods"
        }
    ],
    "sg:phone":"+1 281 847 2212",
    "sg:postcode":"77060",
    "sg:province":"TX",
    "sg:tags":[
        "sling"
    ],
    "sg:website":"http://www.lift-all.com",
    "wof:name":"Lift-All Company, Inc.",
    "wof:placetype":"venue"
},
  "geometry": {"coordinates":[-95.389122,29.94348],"type":"Point"}
}