{
  "type": "Feature",
  "properties": {
    "iso:country":"US",
    "sg:address":"2614 Ridgemeade Dr",
    "sg:city":"Garland",
    "sg:classifiers":[
        {
            "category":"Banks & Credit Unions",
            "subcategory":"Financial Services",
            "type":"Services"
        }
    ],
    "sg:phone":"+1 972 414 5760",
    "sg:postcode":"75040",
    "sg:province":"TX",
    "sg:tags":[
        "investor"
    ],
    "wof:name":"Ramsun Investments Inc",
    "wof:placetype":"venue"
},
  "geometry": {"coordinates":[-96.647386,32.940461],"type":"Point"}
}