{
  "type": "Feature",
  "properties": {
    "iso:country":"US",
    "sg:address":"114 S Houston St",
    "sg:city":"Wharton",
    "sg:classifiers":[
        {
            "category":"Home & Garden",
            "subcategory":"Carpets & Floor Coverings",
            "type":"Retail Goods"
        }
    ],
    "sg:phone":"+1 979 532 1040",
    "sg:postcode":"77488",
    "sg:province":"TX",
    "sg:tags":[
        "dealer",
        "rug"
    ],
    "wof:name":"Tripulas Carpet Co",
    "wof:placetype":"venue"
},
  "geometry": {"coordinates":[-96.10158800000001,29.309885],"type":"Point"}
}