{
  "type": "Feature",
  "properties": {
    "iso:country":"US",
    "sg:address":"6959 Arapaho Rd",
    "sg:city":"Dallas",
    "sg:classifiers":[
        {
            "category":"Shopping",
            "subcategory":"Clothing, Apparel, & Fashions",
            "type":"Retail Goods"
        }
    ],
    "sg:phone":"+1 214 361 9994",
    "sg:postcode":"75248",
    "sg:province":"TX",
    "sg:tags":[
        "accessory",
        "clothing",
        "women's"
    ],
    "sg:website":"www.linvest.com",
    "wof:name":"Linvest the Co",
    "wof:placetype":"venue"
},
  "geometry": {"coordinates":[-96.78929599999999,32.962215],"type":"Point"}
}