{
  "type": "Feature",
  "properties": {
    "iso:country":"US",
    "sg:address":"4113 Esters Rd",
    "sg:city":"Irving",
    "sg:classifiers":[
        {
            "category":"Restaurant",
            "type":"Food & Drink"
        }
    ],
    "sg:phone":"+1 972 659 1904",
    "sg:postcode":"75038",
    "sg:province":"TX",
    "sg:tags":[
        "eating"
    ],
    "wof:name":"Taylor Divine Taste",
    "wof:placetype":"venue"
},
  "geometry": {"coordinates":[-97.00351499999999,32.862564],"type":"Point"}
}