{
  "type": "Feature",
  "properties": {
    "iso:country":"US",
    "sg:address":"5813 E Roselane St",
    "sg:city":"Fort Worth",
    "sg:classifiers":[
        {
            "category":"Autos & Motor Vehicles",
            "subcategory":"Automobile Sales",
            "type":"Retail Goods"
        }
    ],
    "sg:phone":"+1 817 429 1681",
    "sg:postcode":"76112",
    "sg:province":"TX",
    "sg:tags":[
        "used"
    ],
    "wof:name":"Rippetoe Motor Co",
    "wof:placetype":"venue"
},
  "geometry": {"coordinates":[-97.23079799999999,32.732783],"type":"Point"}
}