{
  "type": "Feature",
  "properties": {
    "iso:country":"US",
    "sg:address":"1105 Coolidge St",
    "sg:city":"Plano",
    "sg:classifiers":[
        {
            "category":"Personal",
            "subcategory":"Beauty Salon",
            "type":"Services"
        }
    ],
    "sg:phone":"+1 972 423 7145",
    "sg:postcode":"75094",
    "sg:province":"TX",
    "wof:name":"Purvi Beauty",
    "wof:placetype":"venue"
},
  "geometry": {"coordinates":[-96.61715700000001,33.007481],"type":"Point"}
}