{
  "type": "Feature",
  "properties": {
    "iso:country":"US",
    "sg:address":"3412 Caleo Ct",
    "sg:city":"Plano",
    "sg:classifiers":[
        {
            "category":"Building & Trades",
            "subcategory":"Construction",
            "type":"Services"
        }
    ],
    "sg:phone":"+1 972 618 4176",
    "sg:postcode":"75025",
    "sg:province":"TX",
    "sg:tags":[
        "home",
        "builder",
        "custom"
    ],
    "wof:name":"Sullivan M Homes",
    "wof:placetype":"venue"
},
  "geometry": {"coordinates":[-96.759101,33.075491],"type":"Point"}
}