{
  "type": "Feature",
  "properties": {
    "iso:country":"US",
    "sg:address":"1300 Milmo Dr",
    "sg:city":"Fort Worth",
    "sg:classifiers":[
        {
            "category":"Social Services",
            "subcategory":"Child Care",
            "type":"Services"
        }
    ],
    "sg:phone":"+1 817 551 5033",
    "sg:postcode":"76134",
    "sg:province":"TX",
    "sg:tags":[
        "day"
    ],
    "wof:name":"Safe Place Christian Daycare",
    "wof:placetype":"venue"
},
  "geometry": {"coordinates":[-97.305584,32.668484],"type":"Point"}
}