{
  "type": "Feature",
  "properties": {
    "iso:country":"US",
    "sg:address":"218 S 8th St",
    "sg:city":"Wallis",
    "sg:classifiers":[
        {
            "category":"Organizations",
            "subcategory":"Religious Organization",
            "type":"Services"
        }
    ],
    "sg:phone":"+1 979 478 6662",
    "sg:postcode":"77485",
    "sg:province":"TX",
    "sg:tags":[
        "church"
    ],
    "wof:name":"Evergreen Missionary Baptist",
    "wof:placetype":"venue"
},
  "geometry": {"coordinates":[-96.056544,29.626293],"type":"Point"}
}