{
  "type": "Feature",
  "properties": {
    "iso:country":"US",
    "sg:address":"8501 S Sam Houston Pkwy E",
    "sg:city":"Houston",
    "sg:classifiers":[
        {
            "category":"Shopping",
            "subcategory":"Mobile Phones",
            "type":"Retail Goods"
        }
    ],
    "sg:phone":"+1 713 987 5129",
    "sg:postcode":"77075",
    "sg:province":"TX",
    "wof:name":"RadioShack",
    "wof:placetype":"venue"
},
  "geometry": {"coordinates":[-95.26617,29.600957],"type":"Point"}
}