{
  "type": "Feature",
  "properties": {
    "iso:country":"US",
    "sg:address":"1408 Eldora Rd",
    "sg:city":"Alamo",
    "sg:classifiers":[
        {
            "category":"Building & Trades",
            "subcategory":"Construction",
            "type":"Services"
        }
    ],
    "sg:phone":"+1 956 782 5966",
    "sg:postcode":"78516",
    "sg:province":"TX",
    "sg:tags":[
        "residential",
        "nonresidential"
    ],
    "wof:name":"Lynns Homes",
    "wof:placetype":"venue"
},
  "geometry": {"coordinates":[-98.128848,26.219248],"type":"Point"}
}