{
  "type": "Feature",
  "properties": {
    "iso:country":"US",
    "sg:address":"2435 Oak Crest Ave",
    "sg:city":"Austin",
    "sg:classifiers":[
        {
            "category":"Organizations",
            "subcategory":"Religious Organization",
            "type":"Services"
        }
    ],
    "sg:phone":"+1 512 444 7587",
    "sg:postcode":"78704",
    "sg:province":"TX",
    "wof:name":"San Jose Church",
    "wof:placetype":"venue"
},
  "geometry": {"coordinates":[-97.76246500000001,30.242421],"type":"Point"}
}