{
  "type": "Feature",
  "properties": {
    "iso:country":"US",
    "sg:address":"4806 N I- 35",
    "sg:city":"Austin",
    "sg:classifiers":[
        {
            "category":"Wholesale",
            "subcategory":"Machinery & Supplies",
            "type":"Manufacturing & Wholesale Goods"
        }
    ],
    "sg:phone":"+1 512 371 7773",
    "sg:postcode":"78751",
    "sg:province":"TX",
    "sg:tags":[
        "equipment",
        "computer",
        "parking",
        "programing",
        "custom"
    ],
    "sg:website":"www.mitchell-time-parking.com",
    "wof:name":"Mitchell Time & Parking",
    "wof:placetype":"venue"
},
  "geometry": {"coordinates":[-97.71405900000001,30.304097],"type":"Point"}
}