{
  "type": "Feature",
  "properties": {
    "iso:country":"US",
    "sg:address":"503 FM 147",
    "sg:city":"Marlin",
    "sg:classifiers":[
        {
            "category":"Wholesale",
            "subcategory":"Machinery & Supplies",
            "type":"Manufacturing & Wholesale Goods"
        }
    ],
    "sg:phone":"+1 254 838 2200",
    "sg:postcode":"76661",
    "sg:province":"TX",
    "sg:tags":[
        "equipment",
        "railroad"
    ],
    "wof:name":"Global Rail Systems",
    "wof:placetype":"venue"
},
  "geometry": {"coordinates":[-96.89000900000001,31.311512],"type":"Point"}
}