{
  "type": "Feature",
  "properties": {
    "iso:country":"US",
    "sg:address":"17227 Mercury Dr",
    "sg:city":"Houston",
    "sg:classifiers":[
        {
            "category":"Professional",
            "subcategory":"Accounting & Tax Preparation",
            "type":"Services"
        }
    ],
    "sg:phone":"+1 281 486 8800",
    "sg:postcode":"77058",
    "sg:province":"TX",
    "sg:tags":[
        "return",
        "filing"
    ],
    "sg:website":"www.jemtpa.com",
    "wof:name":"JEM Resource Partners",
    "wof:placetype":"venue"
},
  "geometry": {"coordinates":[-95.11546800000001,29.550911],"type":"Point"}
}