{
  "type": "Feature",
  "properties": {
    "iso:country":"US",
    "sg:address":"1412 W California St",
    "sg:city":"Gainesville",
    "sg:classifiers":[
        {
            "category":"Real Estate",
            "subcategory":"Developer",
            "type":"Services"
        }
    ],
    "sg:phone":"+1 940 665 9345",
    "sg:postcode":"76240",
    "sg:province":"TX",
    "sg:tags":[
        "cemetery"
    ],
    "wof:name":"Marysville Cemetery Assoc",
    "wof:placetype":"venue"
},
  "geometry": {"coordinates":[-97.15373,33.62431],"type":"Point"}
}