{
  "type": "Feature",
  "properties": {
    "iso:country":"US",
    "sg:address":"2653 E Davis St",
    "sg:city":"Conroe",
    "sg:classifiers":[
        {
            "category":"Retail",
            "subcategory":"Auto Rental",
            "type":"Services"
        }
    ],
    "sg:phone":"+1 936 756 4997",
    "sg:postcode":"77301",
    "sg:province":"TX",
    "sg:tags":[
        "renting",
        "truck",
        "leasing"
    ],
    "wof:name":"U-Haul Co",
    "wof:placetype":"venue"
},
  "geometry": {"coordinates":[-95.415384,30.320717],"type":"Point"}
}