{
  "type": "Feature",
  "properties": {
    "iso:country":"US",
    "sg:address":"7570 FM 1123",
    "sg:city":"Belton",
    "sg:classifiers":[
        {
            "category":"Farming",
            "subcategory":"Livestock Farm",
            "type":"Manufacturing & Wholesale Goods"
        }
    ],
    "sg:phone":"+1 254 939 7800",
    "sg:postcode":"76513",
    "sg:province":"TX",
    "sg:tags":[
        "equine"
    ],
    "wof:name":"Kenneth Quirk Dvm",
    "wof:placetype":"venue"
},
  "geometry": {"coordinates":[-97.43193100000001,30.970309],"type":"Point"}
}