{
  "type": "Feature",
  "properties": {
    "iso:country":"US",
    "sg:address":"505 E Blackjack St",
    "sg:city":"Dublin",
    "sg:classifiers":[
        {
            "category":"Food & Beverages",
            "subcategory":"Groceries & Convenience Stores",
            "type":"Retail Goods"
        }
    ],
    "sg:phone":"+1 254 445 2016",
    "sg:postcode":"76446",
    "sg:province":"TX",
    "wof:name":"Smokeys Market",
    "wof:placetype":"venue"
},
  "geometry": {"coordinates":[-98.33653099999999,32.083664],"type":"Point"}
}