{
  "type": "Feature",
  "properties": {
    "iso:country":"US",
    "sg:address":"1305 E 8th St",
    "sg:city":"Odessa",
    "sg:classifiers":[
        {
            "category":"Banks & Credit Unions",
            "subcategory":"Bank",
            "type":"Services"
        }
    ],
    "sg:phone":"+1 432 617 0044",
    "sg:postcode":"79761",
    "sg:province":"TX",
    "sg:tags":[
        "cashing",
        "check"
    ],
    "wof:name":"Ace Cash Express",
    "wof:placetype":"venue"
},
  "geometry": {"coordinates":[-102.35691799999999,31.858564],"type":"Point"}
}