{
  "type": "Feature",
  "properties": {
    "iso:country":"US",
    "sg:address":"14590 State Hwy 53",
    "sg:city":"Temple",
    "sg:classifiers":[
        {
            "category":"Professional",
            "type":"Services"
        }
    ],
    "sg:phone":"+1 254 985 2075",
    "sg:postcode":"76501",
    "sg:province":"TX",
    "wof:name":"Vintage House",
    "wof:placetype":"venue"
},
  "geometry": {"coordinates":[-97.187017,31.051018],"type":"Point"}
}