{
  "type": "Feature",
  "properties": {
    "iso:country":"US",
    "sg:address":"919 N Ave A",
    "sg:city":"Freeport",
    "sg:classifiers":[
        {
            "category":"Wholesale",
            "subcategory":"Electrical",
            "type":"Manufacturing & Wholesale Goods"
        }
    ],
    "sg:phone":"+1 979 233 2203",
    "sg:postcode":"77541",
    "sg:province":"TX",
    "sg:tags":[
        "equipment",
        "testing",
        "electronic"
    ],
    "wof:name":"Testech Inc",
    "wof:placetype":"venue"
},
  "geometry": {"coordinates":[-95.368707,28.963474],"type":"Point"}
}