{
  "type": "Feature",
  "properties": {
    "iso:country":"US",
    "sg:address":"2300 Central Pkwy",
    "sg:city":"Houston",
    "sg:classifiers":[
        {
            "category":"Utilities",
            "subcategory":"Water",
            "type":"Services"
        },
        {
            "category":"Coffee & Tea",
            "type":"Food & Drink"
        },
        {
            "category":"Food & Beverages",
            "subcategory":"Liquor & Beverages",
            "type":"Retail Goods"
        },
        {
            "category":"Wholesale",
            "subcategory":"Vending Machines",
            "type":"Manufacturing & Wholesale Goods"
        }
    ],
    "sg:phone":"+1 713 682 4300",
    "sg:postcode":"77092",
    "sg:province":"TX",
    "sg:tags":[
        "supply",
        "break",
        "brewing",
        "devices-wholesale",
        "companies-bottled",
        "bulk",
        "device",
        "merchandise",
        "manufacturer"
    ],
    "wof:name":"Prostar Services Inc",
    "wof:placetype":"venue"
},
  "geometry": {"coordinates":[-95.46521,29.808813],"type":"Point"}
}