{
  "type": "Feature",
  "properties": {
    "iso:country":"US",
    "sg:address":"2000 I- 45 N",
    "sg:city":"Conroe",
    "sg:classifiers":[
        {
            "category":"Communications",
            "type":"Services"
        }
    ],
    "sg:phone":"+1 936 539 9035",
    "sg:postcode":"77301",
    "sg:province":"TX",
    "wof:name":"VVC Communications",
    "wof:placetype":"venue"
},
  "geometry": {"coordinates":[-95.479906,30.339076],"type":"Point"}
}