{
  "type": "Feature",
  "properties": {
    "iso:country":"US",
    "sg:address":"1200 N Main St",
    "sg:city":"Euless",
    "sg:classifiers":[
        {
            "category":"Food & Beverages",
            "subcategory":"Groceries & Convenience Stores",
            "type":"Retail Goods"
        }
    ],
    "sg:phone":"+1 817 545 6896",
    "sg:postcode":"76039",
    "sg:province":"TX",
    "sg:tags":[
        "supermarket",
        "chain"
    ],
    "wof:name":"Food Lion Store 1036",
    "wof:placetype":"venue"
},
  "geometry": {"coordinates":[-97.082448,32.853225],"type":"Point"}
}