{
  "type": "Feature",
  "properties": {
    "iso:country":"US",
    "sg:address":"107 W Sabine St",
    "sg:city":"Carthage",
    "sg:classifiers":[
        {
            "category":"Shopping",
            "subcategory":"Shoes",
            "type":"Retail Goods"
        }
    ],
    "sg:phone":"+1 903 693 2939",
    "sg:postcode":"75633",
    "sg:province":"TX",
    "sg:tags":[
        "boot",
        "gift"
    ],
    "wof:name":"Unique Gifts",
    "wof:placetype":"venue"
},
  "geometry": {"coordinates":[-94.33854599999999,32.156506],"type":"Point"}
}