{
  "type": "Feature",
  "properties": {
    "iso:country":"US",
    "sg:address":"4230 Fairway Dr",
    "sg:city":"Carrollton",
    "sg:classifiers":[
        {
            "category":"Shopping",
            "subcategory":"Gifts & Souvenirs",
            "type":"Retail Goods"
        }
    ],
    "sg:phone":"+1 972 245 2025",
    "sg:postcode":"75010",
    "sg:province":"TX",
    "sg:tags":[
        "shop"
    ],
    "wof:name":"Retro Radar",
    "wof:placetype":"venue"
},
  "geometry": {"coordinates":[-96.933913,33.027941],"type":"Point"}
}