{
  "type": "Feature",
  "properties": {
    "iso:country":"US",
    "sg:address":"820 Coit St",
    "sg:city":"Denton",
    "sg:classifiers":[
        {
            "category":"Building & Trades",
            "subcategory":"Cleaning & Sanitation",
            "type":"Services"
        }
    ],
    "sg:phone":"+1 940 382 4960",
    "sg:postcode":"76201",
    "sg:province":"TX",
    "sg:tags":[
        "janitor"
    ],
    "wof:name":"Associated Janitorial Svc",
    "wof:placetype":"venue"
},
  "geometry": {"coordinates":[-97.137856,33.225152],"type":"Point"}
}