{
  "type": "Feature",
  "properties": {
    "iso:country":"US",
    "sg:address":"5415 Kelley St",
    "sg:city":"Houston",
    "sg:classifiers":[
        {
            "category":"Shopping",
            "subcategory":"Pharmacy",
            "type":"Retail Goods"
        }
    ],
    "sg:phone":"+1 713 330 8011",
    "sg:postcode":"77026",
    "sg:province":"TX",
    "sg:tags":[
        "drugstore"
    ],
    "wof:name":"Qualicare Pharmacy",
    "wof:placetype":"venue"
},
  "geometry": {"coordinates":[-95.315037,29.813804],"type":"Point"}
}