{
  "type": "Feature",
  "properties": {
    "iso:country":"US",
    "sg:address":"15147 Diana Ln",
    "sg:city":"Houston",
    "sg:classifiers":[
        {
            "category":"Banks & Credit Unions",
            "subcategory":"Investment Brokerage",
            "type":"Services"
        }
    ],
    "sg:phone":"+1 281 488 2866",
    "sg:postcode":"77062",
    "sg:province":"TX",
    "sg:tags":[
        "advisory"
    ],
    "wof:name":"Juno Investment Advisors",
    "wof:placetype":"venue"
},
  "geometry": {"coordinates":[-95.13269099999999,29.577682],"type":"Point"}
}