{
  "type": "Feature",
  "properties": {
    "iso:country":"US",
    "sg:address":"701 Ross Ave",
    "sg:city":"Hillsboro",
    "sg:classifiers":[
        {
            "category":"Bars & Pubs",
            "type":"Food & Drink"
        }
    ],
    "sg:phone":"+1 254 582 7282",
    "sg:postcode":"76645",
    "sg:province":"TX",
    "wof:name":"LA Bar",
    "wof:placetype":"venue"
},
  "geometry": {"coordinates":[-97.13299499999999,31.99759],"type":"Point"}
}