{
  "type": "Feature",
  "properties": {
    "iso:country":"US",
    "sg:address":"1749 13th St",
    "sg:city":"Port Arthur",
    "sg:classifiers":[
        {
            "category":"Organizations",
            "subcategory":"Religious Organization",
            "type":"Services"
        }
    ],
    "sg:phone":"+1 409 982 9427",
    "sg:postcode":"77640",
    "sg:province":"TX",
    "sg:tags":[
        "church"
    ],
    "wof:name":"Progressive Missionary Bapt",
    "wof:placetype":"venue"
},
  "geometry": {"coordinates":[-93.93464299999999,29.887927],"type":"Point"}
}