{
  "type": "Feature",
  "properties": {
    "iso:country":"US",
    "sg:address":"28617 Sierra Dr",
    "sg:city":"New Braunfels",
    "sg:classifiers":[
        {
            "category":"Professional",
            "type":"Services"
        }
    ],
    "sg:phone":"+1 830 438 7010",
    "sg:postcode":"78132",
    "sg:province":"TX",
    "wof:name":"Peace Within Works",
    "wof:placetype":"venue"
},
  "geometry": {"coordinates":[-98.28626300000001,29.725517],"type":"Point"}
}