{
  "type": "Feature",
  "properties": {
    "iso:country":"US",
    "sg:address":"4606 Federal Cir",
    "sg:city":"Austin",
    "sg:classifiers":[
        {
            "category":"Professional",
            "subcategory":"Business Services",
            "type":"Services"
        }
    ],
    "sg:phone":"+1 512 441 1628",
    "sg:postcode":"78744",
    "sg:province":"TX",
    "wof:name":"El Rudd Products",
    "wof:placetype":"venue"
},
  "geometry": {"coordinates":[-97.741512,30.199497],"type":"Point"}
}