{
  "type": "Feature",
  "properties": {
    "iso:country":"US",
    "sg:address":"107 Kelly Rd",
    "sg:city":"Aledo",
    "sg:classifiers":[
        {
            "category":"Building & Trades",
            "subcategory":"Landscaping Services",
            "type":"Services"
        }
    ],
    "sg:phone":"+1 817 441 6876",
    "sg:postcode":"76008",
    "sg:province":"TX",
    "wof:name":"Buyers Landscape Services",
    "wof:placetype":"venue"
},
  "geometry": {"coordinates":[-97.585793,32.672207],"type":"Point"}
}