{
  "type": "Feature",
  "properties": {
    "iso:country":"US",
    "sg:address":"3701 Castle Dr",
    "sg:city":"Rowlett",
    "sg:classifiers":[
        {
            "category":"Building & Trades",
            "subcategory":"Landscaping Services",
            "type":"Services"
        }
    ],
    "sg:phone":"+1 972 412 8376",
    "sg:postcode":"75089",
    "sg:province":"TX",
    "wof:name":"Master Care Lawn Service",
    "wof:placetype":"venue"
},
  "geometry": {"coordinates":[-96.567387,32.942344],"type":"Point"}
}