{
  "type": "Feature",
  "properties": {
    "iso:country":"US",
    "sg:address":"301 N Broadway St",
    "sg:city":"Mcallen",
    "sg:classifiers":[
        {
            "category":"Social Services",
            "type":"Services"
        }
    ],
    "sg:phone":"+1 956 262 6229",
    "sg:postcode":"78501",
    "sg:province":"TX",
    "sg:tags":[
        "care",
        "center",
        "day"
    ],
    "wof:name":"Santa Cruz Day Care For Adults",
    "wof:placetype":"venue"
},
  "geometry": {"coordinates":[-98.232761,26.207293],"type":"Point"}
}