{
  "type": "Feature",
  "properties": {
    "iso:country":"US",
    "sg:address":"2617 Co Rd 288",
    "sg:city":"Angleton",
    "sg:classifiers":[
        {
            "category":"Building & Trades",
            "subcategory":"Construction",
            "type":"Services"
        }
    ],
    "sg:phone":"+1 979 848 2126",
    "sg:postcode":"77515",
    "sg:province":"TX",
    "sg:tags":[
        "general",
        "contractor"
    ],
    "wof:name":"Brazos Port Small Business Pk",
    "wof:placetype":"venue"
},
  "geometry": {"coordinates":[-95.430615,29.128508],"type":"Point"}
}