{
  "type": "Feature",
  "properties": {
    "iso:country":"US",
    "sg:address":"4522 Enchanted Gate Dr",
    "sg:city":"Spring",
    "sg:classifiers":[
        {
            "category":"Shopping",
            "subcategory":"Gifts & Souvenirs",
            "type":"Retail Goods"
        }
    ],
    "sg:phone":"+1 281 350 5218",
    "sg:postcode":"77373",
    "sg:province":"TX",
    "wof:name":"A Little Something Different",
    "wof:placetype":"venue"
},
  "geometry": {"coordinates":[-95.367362,30.049412],"type":"Point"}
}