{
  "type": "Feature",
  "properties": {
    "iso:country":"US",
    "sg:address":"120 E Abram St",
    "sg:city":"Arlington",
    "sg:classifiers":[
        {
            "category":"Professional",
            "type":"Services"
        },
        {
            "category":"Education",
            "subcategory":"College",
            "type":"Public Place"
        }
    ],
    "sg:phone":"+1 817 274 4284",
    "sg:postcode":"76010",
    "sg:province":"TX",
    "sg:tags":[
        "academic",
        "school"
    ],
    "wof:name":"B H Carroll Theological Instit",
    "wof:placetype":"venue"
},
  "geometry": {"coordinates":[-97.106106,32.735483],"type":"Point"}
}