{
  "type": "Feature",
  "properties": {
    "iso:country":"US",
    "sg:address":"425 N Britain Rd",
    "sg:city":"Irving",
    "sg:classifiers":[
        {
            "category":"Wholesale",
            "subcategory":"Auto Parts",
            "type":"Manufacturing & Wholesale Goods"
        }
    ],
    "sg:phone":"+1 972 785 2828",
    "sg:postcode":"75061",
    "sg:province":"TX",
    "sg:tags":[
        "tire"
    ],
    "wof:name":"Cheap Tires Inc",
    "wof:placetype":"venue"
},
  "geometry": {"coordinates":[-96.942429,32.817763],"type":"Point"}
}