{
  "type": "Feature",
  "properties": {
    "iso:country":"US",
    "sg:address":"7502 Scott St",
    "sg:city":"Houston",
    "sg:classifiers":[
        {
            "category":"Travel",
            "subcategory":"Hotels & Motels",
            "type":"Entertainment"
        }
    ],
    "sg:phone":"+1 713 747 9530",
    "sg:postcode":"77021",
    "sg:province":"TX",
    "wof:name":"Motel 610",
    "wof:placetype":"venue"
},
  "geometry": {"coordinates":[-95.367203,29.680401],"type":"Point"}
}