{
  "type": "Feature",
  "properties": {
    "iso:country":"US",
    "sg:address":"1424 45th St",
    "sg:city":"Galveston",
    "sg:classifiers":[
        {
            "category":"Social Services",
            "subcategory":"Adult Care",
            "type":"Services"
        }
    ],
    "sg:phone":"+1 409 762 0011",
    "sg:postcode":"77550",
    "sg:province":"TX",
    "sg:tags":[
        "foster"
    ],
    "wof:name":"Childrens Center",
    "wof:placetype":"venue"
},
  "geometry": {"coordinates":[-94.81586799999999,29.289813],"type":"Point"}
}