{
  "type": "Feature",
  "properties": {
    "iso:country":"US",
    "sg:address":"7601 S Will Rogers Blvd",
    "sg:city":"Fort Worth",
    "sg:classifiers":[
        {
            "category":"Manufacturing",
            "subcategory":"Aerospace",
            "type":"Manufacturing & Wholesale Goods"
        }
    ],
    "sg:phone":"+1 817 590 9290",
    "sg:postcode":"76140",
    "sg:province":"TX",
    "sg:tags":[
        "equipment",
        "aircraft",
        "mfg"
    ],
    "wof:name":"Modern Instrument Technology",
    "wof:placetype":"venue"
},
  "geometry": {"coordinates":[-97.313103,32.639213],"type":"Point"}
}