{
  "type": "Feature",
  "properties": {
    "iso:country":"US",
    "sg:address":"2201 Mills Way",
    "sg:city":"Seguin",
    "sg:classifiers":[
        {
            "category":"Professional",
            "subcategory":"Business Services",
            "type":"Services"
        }
    ],
    "sg:phone":"+1 830 401 0753",
    "sg:postcode":"78155",
    "sg:province":"TX",
    "wof:name":"Dick Richter Auctioneer",
    "wof:placetype":"venue"
},
  "geometry": {"coordinates":[-97.889897,29.595341],"type":"Point"}
}