{
  "type": "Feature",
  "properties": {
    "iso:country":"US",
    "sg:address":"813 E Ferguson St",
    "sg:city":"Pharr",
    "sg:classifiers":[
        {
            "category":"Health Services",
            "subcategory":"Hospital",
            "type":"Services"
        }
    ],
    "sg:phone":"+1 956 781 3344",
    "sg:postcode":"78577",
    "sg:province":"TX",
    "sg:tags":[
        "ambulance"
    ],
    "wof:name":"Vida Medical Transport",
    "wof:placetype":"venue"
},
  "geometry": {"coordinates":[-98.17204,26.210444],"type":"Point"}
}