{
  "type": "Feature",
  "properties": {
    "iso:country":"US",
    "sg:address":"4125 Todd Ln",
    "sg:city":"Austin",
    "sg:classifiers":[
        {
            "category":"Retail",
            "subcategory":"Auto Repair",
            "type":"Services"
        }
    ],
    "sg:phone":"+1 512 326 3555",
    "sg:postcode":"78744",
    "sg:province":"TX",
    "sg:tags":[
        "repairing",
        "automobile",
        "general"
    ],
    "wof:name":"Jeep Masters",
    "wof:placetype":"venue"
},
  "geometry": {"coordinates":[-97.739276,30.208801],"type":"Point"}
}