{
  "type": "Feature",
  "properties": {
    "iso:country":"US",
    "sg:address":"209 Crooked Creek Dr",
    "sg:city":"Richardson",
    "sg:classifiers":[
        {
            "category":"Professional",
            "subcategory":"Business Services",
            "type":"Services"
        }
    ],
    "sg:phone":"+1 972 231 7944",
    "sg:postcode":"75080",
    "sg:province":"TX",
    "wof:name":"Linda Veteto Interiors",
    "wof:placetype":"venue"
},
  "geometry": {"coordinates":[-96.714299,32.993209],"type":"Point"}
}