{
  "type": "Feature",
  "properties": {
    "iso:country":"US",
    "sg:address":"5302 Galveston Rd",
    "sg:city":"Houston",
    "sg:classifiers":[
        {
            "category":"Government",
            "subcategory":"Post Office",
            "type":"Public Place"
        }
    ],
    "sg:phone":"+1 713 910 1805",
    "sg:postcode":"77017",
    "sg:province":"TX",
    "sg:tags":[
        "postal",
        "us"
    ],
    "wof:name":"US Post Office",
    "wof:placetype":"venue"
},
  "geometry": {"coordinates":[-95.246765,29.675178],"type":"Point"}
}