{
  "type": "Feature",
  "properties": {
    "iso:country":"US",
    "sg:address":"4281 John Ben Shepperd Pkwy",
    "sg:city":"Odessa",
    "sg:classifiers":[
        {
            "category":"Banks & Credit Unions",
            "subcategory":"Bank",
            "type":"Services"
        }
    ],
    "sg:phone":"+1 432 580 2380",
    "sg:postcode":"79762",
    "sg:province":"TX",
    "wof:name":"American State Bank",
    "wof:placetype":"venue"
},
  "geometry": {"coordinates":[-102.33504000000001,31.896052],"type":"Point"}
}