{
  "type": "Feature",
  "properties": {
    "iso:country":"US",
    "sg:address":"4110 Guadalupe St # 635",
    "sg:city":"Austin",
    "sg:classifiers":[
        {
            "category":"Social Services",
            "type":"Services"
        }
    ],
    "sg:phone":"+1 512 922 1648",
    "sg:postcode":"78751",
    "sg:province":"TX",
    "sg:tags":[
        "human"
    ],
    "wof:name":"Communities For Recovery",
    "wof:placetype":"venue"
},
  "geometry": {"coordinates":[-97.73574000000001,30.306592],"type":"Point"}
}