{
  "type": "Feature",
  "properties": {
    "iso:country":"US",
    "sg:address":"1106 3rd St",
    "sg:city":"Corpus Christi",
    "sg:classifiers":[
        {
            "category":"Shopping",
            "subcategory":"Florist",
            "type":"Retail Goods"
        }
    ],
    "sg:phone":"+1 361 888 6950",
    "sg:postcode":"78404",
    "sg:province":"TX",
    "wof:name":"Artistic Floral Creations-Jim",
    "wof:placetype":"venue"
},
  "geometry": {"coordinates":[-97.39718000000001,27.780685],"type":"Point"}
}