{
  "type": "Feature",
  "properties": {
    "iso:country":"US",
    "sg:address":"2102 S W S Young Dr",
    "sg:city":"Killeen",
    "sg:classifiers":[
        {
            "category":"Shopping",
            "subcategory":"Used Merchandise",
            "type":"Retail Goods"
        }
    ],
    "sg:phone":"+1 254 699 1555",
    "sg:postcode":"76543",
    "sg:province":"TX",
    "sg:tags":[
        "shop",
        "thrift"
    ],
    "wof:name":"Goodwill Industries",
    "wof:placetype":"venue"
},
  "geometry": {"coordinates":[-97.72104299999999,31.095585],"type":"Point"}
}