{
  "type": "Feature",
  "properties": {
    "iso:country":"US",
    "sg:address":"6814 Alamo Downs Pkwy",
    "sg:city":"San Antonio",
    "sg:classifiers":[
        {
            "category":"Manufacturing",
            "subcategory":"Food",
            "type":"Manufacturing & Wholesale Goods"
        }
    ],
    "sg:phone":"+1 210 684 6363",
    "sg:postcode":"78238",
    "sg:province":"TX",
    "sg:tags":[
        "coffee",
        "mfg",
        "roasted"
    ],
    "wof:name":"Granito Coffee Works Inc",
    "wof:placetype":"venue"
},
  "geometry": {"coordinates":[-98.620548,29.455935],"type":"Point"}
}