{
  "type": "Feature",
  "properties": {
    "iso:country":"US",
    "sg:address":"146 Westwood Dr",
    "sg:city":"Rockwall",
    "sg:classifiers":[
        {
            "category":"Professional",
            "subcategory":"Business Services",
            "type":"Services"
        }
    ],
    "sg:phone":"+1 972 771 2294",
    "sg:postcode":"75032",
    "sg:province":"TX",
    "wof:name":"Upstage Designs",
    "wof:placetype":"venue"
},
  "geometry": {"coordinates":[-96.46260599999999,32.888943],"type":"Point"}
}