{
  "type": "Feature",
  "properties": {
    "iso:country":"US",
    "sg:address":"4120 McKinney St",
    "sg:city":"Houston",
    "sg:classifiers":[
        {
            "category":"Food & Beverages",
            "subcategory":"Bakery",
            "type":"Retail Goods"
        }
    ],
    "sg:phone":"+1 713 224 1575",
    "sg:postcode":"77023",
    "sg:province":"TX",
    "sg:tags":[
        "baker"
    ],
    "sg:website":"www.htowncoupons.com/lareynera",
    "wof:name":"La Reynera Panaderia-Bakery",
    "wof:placetype":"venue"
},
  "geometry": {"coordinates":[-95.33704,29.741991],"type":"Point"}
}