{
  "type": "Feature",
  "properties": {
    "iso:country":"US",
    "sg:address":"9120 Gosling Rd",
    "sg:city":"Spring",
    "sg:classifiers":[
        {
            "category":"Restaurant",
            "type":"Food & Drink"
        }
    ],
    "sg:menulink":"http://www.allmenus.com/tx/southeast-montgomery/218129-burger-king/menu/",
    "sg:phone":"+1 281 298 6453",
    "sg:postcode":"77381",
    "sg:province":"TX",
    "sg:tags":[
        "american"
    ],
    "wof:name":"Burger King",
    "wof:placetype":"venue"
},
  "geometry": {"coordinates":[-95.48865600000001,30.183142],"type":"Point"}
}