{
  "type": "Feature",
  "properties": {
    "iso:country":"US",
    "sg:address":"306 Ave C",
    "sg:city":"Van Vleck",
    "sg:classifiers":[
        {
            "category":"Food & Beverages",
            "subcategory":"Groceries & Convenience Stores",
            "type":"Retail Goods"
        }
    ],
    "sg:phone":"+1 979 245 9141",
    "sg:postcode":"77482",
    "sg:province":"TX",
    "wof:name":"E Z Mart Stores",
    "wof:placetype":"venue"
},
  "geometry": {"coordinates":[-95.894412,29.019244],"type":"Point"}
}