{
  "type": "Feature",
  "properties": {
    "iso:country":"US",
    "sg:address":"100 Pawnee Way",
    "sg:city":"Lyons",
    "sg:classifiers":[
        {
            "category":"Building & Trades",
            "subcategory":"Equipment Rental",
            "type":"Services"
        }
    ],
    "sg:phone":"+1 979 596 2873",
    "sg:postcode":"77879",
    "sg:province":"TX",
    "sg:tags":[
        "heavy",
        "construction"
    ],
    "wof:name":"Gate Security Service",
    "wof:placetype":"venue"
},
  "geometry": {"coordinates":[-96.568556,30.355594],"type":"Point"}
}