{
  "type": "Feature",
  "properties": {
    "iso:country":"US",
    "sg:address":"11755 Beechnut St",
    "sg:city":"Houston",
    "sg:classifiers":[
        {
            "category":"Food & Beverages",
            "subcategory":"Groceries & Convenience Stores",
            "type":"Retail Goods"
        }
    ],
    "sg:phone":"+1 281 328 1638",
    "sg:postcode":"77072",
    "sg:province":"TX",
    "wof:name":"Wal-Mart",
    "wof:placetype":"venue"
},
  "geometry": {"coordinates":[-95.58756200000001,29.688851],"type":"Point"}
}