{
  "type": "Feature",
  "properties": {
    "iso:country":"US",
    "sg:address":"3107 Windmill St",
    "sg:city":"Sugar Land",
    "sg:classifiers":[
        {
            "category":"Professional",
            "subcategory":"Computer Services",
            "type":"Services"
        }
    ],
    "sg:phone":"+1 281 980 1119",
    "sg:postcode":"77479",
    "sg:province":"TX",
    "sg:tags":[
        "related"
    ],
    "wof:name":"Lesley Ann Studios",
    "wof:placetype":"venue"
},
  "geometry": {"coordinates":[-95.597213,29.583696],"type":"Point"}
}