{
  "type": "Feature",
  "properties": {
    "iso:country":"US",
    "sg:address":"1605 W Harrison Ave",
    "sg:city":"Harlingen",
    "sg:classifiers":[
        {
            "category":"Restaurant",
            "type":"Food & Drink"
        }
    ],
    "sg:menulink":"http://www.allmenus.com/tx/harlingen-san-benito/157196-whataburger/menu/",
    "sg:phone":"+1 956 423 8800",
    "sg:postcode":"78550",
    "sg:province":"TX",
    "sg:tags":[
        "burger",
        "american"
    ],
    "wof:name":"Whataburger",
    "wof:placetype":"venue"
},
  "geometry": {"coordinates":[-97.71265200000001,26.190601],"type":"Point"}
}