{
  "type": "Feature",
  "properties": {
    "iso:country":"US",
    "sg:address":"5439 Harwood Rd",
    "sg:city":"Luling",
    "sg:classifiers":[
        {
            "category":"Farming",
            "subcategory":"Livestock Farm",
            "type":"Manufacturing & Wholesale Goods"
        }
    ],
    "sg:phone":"+1 830 540 4721",
    "sg:postcode":"78648",
    "sg:province":"TX",
    "sg:tags":[
        "ranch"
    ],
    "wof:name":"Pitner Land And Cattle Co",
    "wof:placetype":"venue"
},
  "geometry": {"coordinates":[-97.524249,29.71206],"type":"Point"}
}