{
  "type": "Feature",
  "properties": {
    "iso:country":"US",
    "sg:address":"1326 Pennsylvania Ave",
    "sg:city":"Fort Worth",
    "sg:classifiers":[
        {
            "category":"Organizations",
            "subcategory":"Community Association",
            "type":"Services"
        }
    ],
    "sg:phone":"+1 817 335 4671",
    "sg:postcode":"76104",
    "sg:province":"TX",
    "sg:tags":[
        "club"
    ],
    "wof:name":"Junior Woman's Club",
    "wof:placetype":"venue"
},
  "geometry": {"coordinates":[-97.33982399999999,32.738562],"type":"Point"}
}