{
  "type": "Feature",
  "properties": {
    "iso:country":"US",
    "sg:address":"3627 Harrison Ave",
    "sg:city":"El Paso",
    "sg:classifiers":[
        {
            "category":"Banks & Credit Unions",
            "subcategory":"Bank",
            "type":"Services"
        }
    ],
    "sg:phone":"+1 915 566 8559",
    "sg:postcode":"79930",
    "sg:province":"TX",
    "sg:tags":[
        "federal",
        "agency"
    ],
    "wof:name":"Red Com",
    "wof:placetype":"venue"
},
  "geometry": {"coordinates":[-106.449597,31.813998],"type":"Point"}
}