{
  "type": "Feature",
  "properties": {
    "iso:country":"US",
    "sg:address":"4002 E Crosstimbers St",
    "sg:city":"Houston",
    "sg:classifiers":[
        {
            "category":"Organizations",
            "subcategory":"Religious Organization",
            "type":"Services"
        }
    ],
    "sg:phone":"+1 713 633 2474",
    "sg:postcode":"77016",
    "sg:province":"TX",
    "wof:name":"Strait Life Baptist Church",
    "wof:placetype":"venue"
},
  "geometry": {"coordinates":[-95.33068400000001,29.829159],"type":"Point"}
}