{
  "type": "Feature",
  "properties": {
    "iso:country":"US",
    "sg:address":"408 E Irving Blvd",
    "sg:city":"Irving",
    "sg:classifiers":[
        {
            "category":"Insurance",
            "subcategory":"Insurance Agent",
            "type":"Services"
        }
    ],
    "sg:phone":"+1 972 871 1363",
    "sg:postcode":"75060",
    "sg:province":"TX",
    "wof:name":"K & V Auto Insurance",
    "wof:placetype":"venue"
},
  "geometry": {"coordinates":[-96.94036,32.81375],"type":"Point"}
}