{
  "type": "Feature",
  "properties": {
    "iso:country":"US",
    "sg:address":"113 W San Pedro St",
    "sg:city":"Laredo",
    "sg:classifiers":[
        {
            "category":"Travel",
            "subcategory":"Hotels & Motels",
            "type":"Entertainment"
        }
    ],
    "sg:phone":"+1 956 791 1068",
    "sg:postcode":"78041",
    "sg:province":"TX",
    "wof:name":"Courtesy Motor Inn",
    "wof:placetype":"venue"
},
  "geometry": {"coordinates":[-99.49590000000001,27.532419],"type":"Point"}
}