{
  "type": "Feature",
  "properties": {
    "iso:country":"US",
    "sg:address":"23302 Enchanted Landing Ln",
    "sg:city":"Katy",
    "sg:classifiers":[
        {
            "category":"Professional",
            "subcategory":"Business Services",
            "type":"Services"
        }
    ],
    "sg:phone":"+1 281 693 7356",
    "sg:postcode":"77494",
    "sg:province":"TX",
    "wof:name":"National Assoc of Profess",
    "wof:placetype":"venue"
},
  "geometry": {"coordinates":[-95.768923,29.741443],"type":"Point"}
}