{
  "type": "Feature",
  "properties": {
    "iso:country":"US",
    "sg:address":"11331 Veterans Memorial Dr",
    "sg:city":"Houston",
    "sg:classifiers":[
        {
            "category":"Social Services",
            "subcategory":"Child Care",
            "type":"Services"
        }
    ],
    "sg:phone":"+1 281 537 5333",
    "sg:postcode":"77067",
    "sg:province":"TX",
    "sg:tags":[
        "day"
    ],
    "wof:name":"Lil Folks Daycare Center",
    "wof:placetype":"venue"
},
  "geometry": {"coordinates":[-95.46655800000001,29.945858],"type":"Point"}
}