{
  "type": "Feature",
  "properties": {
    "iso:country":"US",
    "sg:address":"3626 85th Street",
    "sg:city":"Galveston",
    "sg:classifiers":[
        {
            "category":"Home & Garden",
            "subcategory":"Building Materials",
            "type":"Retail Goods"
        },
        {
            "category":"Utilities",
            "subcategory":"Cable",
            "type":"Services"
        }
    ],
    "sg:phone":"+1 409 762 0800",
    "sg:postcode":"77554",
    "sg:province":"TX",
    "sg:tags":[
        "light",
        "tube",
        "bulb"
    ],
    "wof:name":"Light Bulb Connexion LLC",
    "wof:placetype":"venue"
},
  "geometry": {"coordinates":[-94.849693,29.255305],"type":"Point"}
}