{
  "type": "Feature",
  "properties": {
    "iso:country":"US",
    "sg:address":"8102 Pilgrims Pl",
    "sg:city":"Austin",
    "sg:classifiers":[
        {
            "category":"Restaurant",
            "type":"Food & Drink"
        }
    ],
    "sg:phone":"+1 512 918 1083",
    "sg:postcode":"78759",
    "sg:province":"TX",
    "sg:tags":[
        "eating"
    ],
    "wof:name":"Lucky Heart Inc",
    "wof:placetype":"venue"
},
  "geometry": {"coordinates":[-97.77707599999999,30.428146],"type":"Point"}
}