{
  "type": "Feature",
  "properties": {
    "iso:country":"US",
    "sg:address":"2442 S 14th St",
    "sg:city":"Abilene",
    "sg:classifiers":[
        {
            "category":"Professional",
            "subcategory":"Business Services",
            "type":"Services"
        }
    ],
    "sg:phone":"+1 866 254 2657",
    "sg:postcode":"79605",
    "sg:province":"TX",
    "sg:tags":[
        "shop",
        "lettering",
        "product",
        "sign",
        "advertising-promotional",
        "painting"
    ],
    "sg:website":"http://ad.doubleclick.net/clk;226205666;50079909;n?http://fastsigns.com/145",
    "wof:name":"FASTSIGNS",
    "wof:placetype":"venue"
},
  "geometry": {"coordinates":[-99.75174800000001,32.43219],"type":"Point"}
}