{
  "type": "Feature",
  "properties": {
    "iso:country":"US",
    "sg:address":"10432 Brian Mooney Ave",
    "sg:city":"El Paso",
    "sg:classifiers":[
        {
            "category":"Professional",
            "type":"Services"
        }
    ],
    "sg:phone":"+1 915 590 4310",
    "sg:postcode":"79935",
    "sg:province":"TX",
    "wof:name":"John P Rodriguez",
    "wof:placetype":"venue"
},
  "geometry": {"coordinates":[-106.338419,31.771175],"type":"Point"}
}