{
  "type": "Feature",
  "properties": {
    "iso:country":"US",
    "sg:address":"2601 Oak Meadow Dr",
    "sg:city":"Round Rock",
    "sg:classifiers":[
        {
            "category":"Retail",
            "subcategory":"Laundry & Dry Cleaning",
            "type":"Services"
        }
    ],
    "sg:phone":"+1 512 244 9773",
    "sg:postcode":"78681",
    "sg:province":"TX",
    "wof:name":"Suns Alteration",
    "wof:placetype":"venue"
},
  "geometry": {"coordinates":[-97.699743,30.48722],"type":"Point"}
}