{
  "type": "Feature",
  "properties": {
    "iso:country":"US",
    "sg:address":"4352 Hwy 365",
    "sg:city":"Port Arthur",
    "sg:classifiers":[
        {
            "category":"Organizations",
            "subcategory":"Religious Organization",
            "type":"Services"
        }
    ],
    "sg:phone":"+1 409 722 5083",
    "sg:postcode":"77642",
    "sg:province":"TX",
    "sg:tags":[
        "church"
    ],
    "wof:name":"Stonegate Missionary Baptist",
    "wof:placetype":"venue"
},
  "geometry": {"coordinates":[-93.98326299999999,29.957779],"type":"Point"}
}