{
  "type": "Feature",
  "properties": {
    "iso:country":"US",
    "sg:address":"213 N Fredonia St",
    "sg:city":"Longview",
    "sg:classifiers":[
        {
            "category":"Banks & Credit Unions",
            "subcategory":"Bank",
            "type":"Services"
        },
        {
            "category":"Banks & Credit Unions",
            "subcategory":"Financial Services",
            "type":"Services"
        }
    ],
    "sg:phone":"+1 903 757 7283",
    "sg:postcode":"75601",
    "sg:province":"TX",
    "sg:tags":[
        "saving",
        "loan",
        "commercial"
    ],
    "sg:website":"http://www.commerceonline.com/",
    "wof:name":"Commerce Bank",
    "wof:placetype":"venue"
},
  "geometry": {"coordinates":[-94.738472,32.4953],"type":"Point"}
}