{
  "type": "Feature",
  "properties": {
    "iso:country":"US",
    "sg:address":"4002 US Hwy 59",
    "sg:city":"Victoria",
    "sg:classifiers":[
        {
            "category":"Mining & Drilling",
            "type":"Manufacturing & Wholesale Goods"
        }
    ],
    "sg:phone":"+1 361 570 3100",
    "sg:postcode":"77905",
    "sg:province":"TX",
    "sg:tags":[
        "field",
        "oil"
    ],
    "wof:name":"M W Rentals & Svc",
    "wof:placetype":"venue"
},
  "geometry": {"coordinates":[-97.04187899999999,28.730418],"type":"Point"}
}