{
  "type": "Feature",
  "properties": {
    "iso:country":"US",
    "sg:address":"101 N 4th St",
    "sg:city":"Wills Point",
    "sg:classifiers":[
        {
            "category":"Personal",
            "subcategory":"Beauty Salon",
            "type":"Services"
        }
    ],
    "sg:phone":"+1 903 873 2766",
    "sg:postcode":"75169",
    "sg:province":"TX",
    "sg:tags":[
        "shop"
    ],
    "wof:name":"Get Nailed",
    "wof:placetype":"venue"
},
  "geometry": {"coordinates":[-96.00814699999999,32.708171],"type":"Point"}
}