{
  "type": "Feature",
  "properties": {
    "iso:country":"US",
    "sg:address":"1846 Richmond Ave",
    "sg:city":"Houston",
    "sg:classifiers":[
        {
            "category":"Shopping",
            "subcategory":"Music",
            "type":"Retail Goods"
        }
    ],
    "sg:phone":"+1 713 666 5555",
    "sg:postcode":"77098",
    "sg:province":"TX",
    "sg:tags":[
        "used",
        "amplifier",
        "musical",
        "guitar",
        "dvd's",
        "merchandise"
    ],
    "sg:website":"www.soundexchangehouston.com",
    "wof:name":"Sound Exchange",
    "wof:placetype":"venue"
},
  "geometry": {"coordinates":[-95.40660099999999,29.7344],"type":"Point"}
}