{
  "type": "Feature",
  "properties": {
    "iso:country":"US",
    "sg:address":"2855 Mangum Ste 570",
    "sg:city":"Houston",
    "sg:classifiers":[
        {
            "category":"Professional",
            "subcategory":"Advertising",
            "type":"Services"
        }
    ],
    "sg:phone":"+1 713 862 0001",
    "sg:postcode":"77092",
    "sg:province":"TX",
    "sg:tags":[
        "marketing"
    ],
    "sg:website":"www.salesnexus.com",
    "wof:name":"SalesNexus",
    "wof:placetype":"venue"
},
  "geometry": {"coordinates":[-95.459884,29.813468],"type":"Point"}
}