{
  "type": "Feature",
  "properties": {
    "iso:country":"US",
    "sg:address":"408 2nd St",
    "sg:city":"Louise",
    "sg:classifiers":[
        {
            "category":"Education",
            "subcategory":"School",
            "type":"Public Place"
        }
    ],
    "sg:phone":"+1 979 648 2262",
    "sg:postcode":"77455",
    "sg:province":"TX",
    "sg:website":"www.louiseisd.org",
    "wof:name":"Louise Elementary School",
    "wof:placetype":"venue"
},
  "geometry": {"coordinates":[-96.40701,29.111686],"type":"Point"}
}