{
  "type": "Feature",
  "properties": {
    "iso:country":"US",
    "sg:address":"1902 Austin Ave",
    "sg:city":"Waco",
    "sg:classifiers":[
        {
            "category":"Travel",
            "subcategory":"Hotels & Motels",
            "type":"Entertainment"
        }
    ],
    "sg:phone":"+1 254 666 4730",
    "sg:postcode":"76701",
    "sg:province":"TX",
    "sg:tags":[
        "breakfast",
        "accommodation",
        "bed"
    ],
    "wof:name":"Magnolia Blossom B & B",
    "wof:placetype":"venue"
},
  "geometry": {"coordinates":[-97.145543,31.544628],"type":"Point"}
}