{
  "type": "Feature",
  "properties": {
    "iso:country":"US",
    "sg:address":"1959 W Hwy 97",
    "sg:city":"Pleasanton",
    "sg:classifiers":[
        {
            "category":"Shopping",
            "subcategory":"Gifts & Souvenirs",
            "type":"Retail Goods"
        }
    ],
    "sg:phone":"+1 830 569 6313",
    "sg:postcode":"78064",
    "sg:province":"TX",
    "sg:tags":[
        "shop",
        "novelty"
    ],
    "wof:name":"Longhorn Museum",
    "wof:placetype":"venue"
},
  "geometry": {"coordinates":[-98.51152999999999,28.940918],"type":"Point"}
}