{
  "type": "Feature",
  "properties": {
    "iso:country":"US",
    "sg:address":"8624 W Montgomery Rd",
    "sg:city":"Houston",
    "sg:classifiers":[
        {
            "category":"Shopping",
            "subcategory":"Discount & Variety Stores",
            "type":"Retail Goods"
        }
    ],
    "sg:phone":"+1 281 591 1112",
    "sg:postcode":"77088",
    "sg:province":"TX",
    "sg:website":"www.familydollar.com",
    "wof:name":"Family Dollar",
    "wof:placetype":"venue"
},
  "geometry": {"coordinates":[-95.43811100000001,29.872439],"type":"Point"}
}