{
  "type": "Feature",
  "properties": {
    "iso:country":"US",
    "sg:address":"303 W Loop 281",
    "sg:city":"Longview",
    "sg:classifiers":[
        {
            "category":"Travel",
            "subcategory":"Travel Agent",
            "type":"Entertainment"
        }
    ],
    "sg:phone":"+1 903 663 3037",
    "sg:postcode":"75605",
    "sg:province":"TX",
    "sg:tags":[
        "agency",
        "bureau"
    ],
    "sg:website":"www.flyoasis.com",
    "wof:name":"OASIS Travel",
    "wof:placetype":"venue"
},
  "geometry": {"coordinates":[-94.751991,32.541949],"type":"Point"}
}