{
  "type": "Feature",
  "properties": {
    "iso:country":"US",
    "sg:address":"1313 Valwood Pkwy",
    "sg:city":"Carrollton",
    "sg:classifiers":[
        {
            "category":"Manufacturing",
            "subcategory":"Chemicals & Compounds",
            "type":"Manufacturing & Wholesale Goods"
        }
    ],
    "sg:phone":"+1 972 889 8921",
    "sg:postcode":"75006",
    "sg:province":"TX",
    "sg:tags":[
        "water",
        "treatment",
        "system"
    ],
    "wof:name":"Kuritaamericacom",
    "wof:placetype":"venue"
},
  "geometry": {"coordinates":[-96.91345,32.939257],"type":"Point"}
}