{
  "type": "Feature",
  "properties": {
    "iso:country":"US",
    "sg:address":"15925 Lexington Blvd",
    "sg:city":"Sugar Land",
    "sg:classifiers":[
        {
            "category":"Banks & Credit Unions",
            "subcategory":"Bank",
            "type":"Services"
        }
    ],
    "sg:phone":"+1 713 216 7000",
    "sg:postcode":"77479",
    "sg:province":"TX",
    "wof:name":"J P Morgan Chase",
    "wof:placetype":"venue"
},
  "geometry": {"coordinates":[-95.616687,29.595041],"type":"Point"}
}