{
  "type": "Feature",
  "properties": {
    "iso:country":"US",
    "sg:address":"3957 Belt Line Rd",
    "sg:city":"Addison",
    "sg:classifiers":[
        {
            "category":"Restaurant",
            "type":"Food & Drink"
        }
    ],
    "sg:phone":"+1 972 386 7786",
    "sg:postcode":"75001",
    "sg:province":"TX",
    "sg:tags":[
        "tex-mex"
    ],
    "wof:name":"Mi Taquito Mexican Restaurant",
    "wof:placetype":"venue"
},
  "geometry": {"coordinates":[-96.847488,32.953744],"type":"Point"}
}