{
  "type": "Feature",
  "properties": {
    "iso:country":"US",
    "sg:address":"1202 Simmons Ave",
    "sg:city":"Jourdanton",
    "sg:classifiers":[
        {
            "category":"Utilities",
            "subcategory":"Fuel Oil & Lpg",
            "type":"Services"
        }
    ],
    "sg:phone":"+1 830 767 3155",
    "sg:postcode":"78026",
    "sg:province":"TX",
    "sg:tags":[
        "propane",
        "gas"
    ],
    "sg:website":"www.wardandsonspropane.com",
    "wof:name":"Texas Propane Energy",
    "wof:placetype":"venue"
},
  "geometry": {"coordinates":[-98.54308399999999,28.920191],"type":"Point"}
}