{
  "type": "Feature",
  "properties": {
    "iso:country":"US",
    "sg:address":"1501 Mc Gee Dr",
    "sg:city":"Abilene",
    "sg:classifiers":[
        {
            "category":"Manufacturing",
            "subcategory":"Tools & Machinery",
            "type":"Manufacturing & Wholesale Goods"
        }
    ],
    "sg:phone":"+1 325 692 9801",
    "sg:postcode":"79602",
    "sg:province":"TX",
    "sg:tags":[
        "machine",
        "shop"
    ],
    "wof:name":"Atlas Machine & Welding Inc",
    "wof:placetype":"venue"
},
  "geometry": {"coordinates":[-99.739963,32.393294],"type":"Point"}
}