{
  "type": "Feature",
  "properties": {
    "iso:country":"US",
    "sg:address":"10612 Co Rd 497",
    "sg:city":"Lindale",
    "sg:classifiers":[
        {
            "category":"Building & Trades",
            "subcategory":"Cleaning & Sanitation",
            "type":"Services"
        }
    ],
    "sg:phone":"+1 903 882 6034",
    "sg:postcode":"75771",
    "sg:province":"TX",
    "sg:tags":[
        "ventilating",
        "system"
    ],
    "wof:name":"Domino Vent Co",
    "wof:placetype":"venue"
},
  "geometry": {"coordinates":[-95.339122,32.494905],"type":"Point"}
}