{
  "type": "Feature",
  "properties": {
    "iso:country":"US",
    "sg:address":"1089 Rogers Hill Spr",
    "sg:city":"Waco",
    "sg:classifiers":[
        {
            "category":"Shopping",
            "type":"Retail Goods"
        }
    ],
    "sg:phone":"+1 254 829 0195",
    "sg:postcode":"76705",
    "sg:province":"TX",
    "sg:tags":[
        "pet",
        "shop"
    ],
    "wof:name":"Feather Haven",
    "wof:placetype":"venue"
},
  "geometry": {"coordinates":[-97.14774800000001,31.693583],"type":"Point"}
}