{
  "type": "Feature",
  "properties": {
    "iso:country":"US",
    "sg:address":"3400 Hwy 365",
    "sg:city":"Nederland",
    "sg:classifiers":[
        {
            "category":"Insurance",
            "subcategory":"Title Insurance",
            "type":"Services"
        },
        {
            "category":"Real Estate",
            "subcategory":"Real Estate Services",
            "type":"Services"
        }
    ],
    "sg:phone":"+1 409 727 1070",
    "sg:postcode":"77642",
    "sg:province":"TX",
    "sg:tags":[
        "company"
    ],
    "wof:name":"Stewart Title Co",
    "wof:placetype":"venue"
},
  "geometry": {"coordinates":[-93.99118,29.949164],"type":"Point"}
}