{
  "type": "Feature",
  "properties": {
    "iso:country":"US",
    "sg:address":"1001 N Main St",
    "sg:city":"Taylor",
    "sg:classifiers":[
        {
            "category":"Real Estate",
            "subcategory":"Real Estate Agent",
            "type":"Services"
        }
    ],
    "sg:phone":"+1 512 365 1959",
    "sg:postcode":"76574",
    "sg:province":"TX",
    "wof:name":"Realty World",
    "wof:placetype":"venue"
},
  "geometry": {"coordinates":[-97.41036200000001,30.577088],"type":"Point"}
}