{
  "type": "Feature",
  "properties": {
    "iso:country":"US",
    "sg:address":"2506 Long Reach Dr",
    "sg:city":"Sugar Land",
    "sg:classifiers":[
        {
            "category":"Professional",
            "subcategory":"Advertising",
            "type":"Services"
        }
    ],
    "sg:phone":"+1 281 980 5093",
    "sg:postcode":"77478",
    "sg:province":"TX",
    "sg:tags":[
        "mail",
        "direct"
    ],
    "wof:name":"U O Tech",
    "wof:placetype":"venue"
},
  "geometry": {"coordinates":[-95.610652,29.597365],"type":"Point"}
}