{
  "type": "Feature",
  "properties": {
    "iso:country":"US",
    "sg:address":"922 W Loop 281",
    "sg:city":"Longview",
    "sg:classifiers":[
        {
            "category":"Real Estate",
            "subcategory":"Real Estate Agent",
            "type":"Services"
        }
    ],
    "sg:phone":"+1 903 295 9394",
    "sg:postcode":"75604",
    "sg:province":"TX",
    "sg:tags":[
        "agency",
        "rental"
    ],
    "wof:name":"D R Rentals",
    "wof:placetype":"venue"
},
  "geometry": {"coordinates":[-94.764155,32.538054],"type":"Point"}
}