{
  "type": "Feature",
  "properties": {
    "iso:country":"US",
    "sg:address":"7000 Lake Mead Blvd",
    "sg:city":"Arlington",
    "sg:classifiers":[
        {
            "category":"Professional",
            "subcategory":"Management & Consulting",
            "type":"Services"
        }
    ],
    "sg:phone":"+1 817 572 1556",
    "sg:postcode":"76016",
    "sg:province":"TX",
    "sg:tags":[
        "counselor",
        "relation",
        "public"
    ],
    "wof:name":"Brodnicki Public Relations",
    "wof:placetype":"venue"
},
  "geometry": {"coordinates":[-97.218887,32.682041],"type":"Point"}
}