{
  "type": "Feature",
  "properties": {
    "iso:country":"US",
    "sg:address":"2703 Lauder Rd",
    "sg:city":"Houston",
    "sg:classifiers":[
        {
            "category":"Retail",
            "subcategory":"Auto Repair",
            "type":"Services"
        }
    ],
    "sg:phone":"+1 281 590 3050",
    "sg:postcode":"77039",
    "sg:province":"TX",
    "wof:name":"Martinez Auto Repair",
    "wof:placetype":"venue"
},
  "geometry": {"coordinates":[-95.3442,29.913099],"type":"Point"}
}