{
  "type": "Feature",
  "properties": {
    "iso:country":"US",
    "sg:address":"6519 Deloache Ave",
    "sg:city":"Dallas",
    "sg:classifiers":[
        {
            "category":"Real Estate",
            "subcategory":"Developer",
            "type":"Services"
        }
    ],
    "sg:phone":"+1 214 265 7635",
    "sg:postcode":"75225",
    "sg:province":"TX",
    "wof:name":"Vr Partners Inc",
    "wof:placetype":"venue"
},
  "geometry": {"coordinates":[-96.79380500000001,32.870657],"type":"Point"}
}