{
  "type": "Feature",
  "properties": {
    "iso:country":"US",
    "sg:address":"2219 Forest Park Cir",
    "sg:city":"Mansfield",
    "sg:classifiers":[
        {
            "category":"Insurance",
            "subcategory":"Insurance Agent",
            "type":"Services"
        }
    ],
    "sg:phone":"+1 817 473 8464",
    "sg:postcode":"76063",
    "sg:province":"TX",
    "sg:tags":[
        "allied",
        "health"
    ],
    "wof:name":"Fastfingers Med Transcription",
    "wof:placetype":"venue"
},
  "geometry": {"coordinates":[-97.144115,32.597294],"type":"Point"}
}