{
  "type": "Feature",
  "properties": {
    "iso:country":"US",
    "sg:address":"5911 Co Rd 200",
    "sg:city":"Liberty Hill",
    "sg:classifiers":[
        {
            "category":"Professional",
            "subcategory":"Business Services",
            "type":"Services"
        }
    ],
    "sg:phone":"+1 512 515 0750",
    "sg:postcode":"78642",
    "sg:province":"TX",
    "wof:name":"Chexmate",
    "wof:placetype":"venue"
},
  "geometry": {"coordinates":[-97.93718,30.751682],"type":"Point"}
}