{
  "type": "Feature",
  "properties": {
    "iso:country":"US",
    "sg:address":"200 E Kleberg Ave",
    "sg:city":"Kingsville",
    "sg:classifiers":[
        {
            "category":"Government",
            "subcategory":"Office",
            "type":"Public Place"
        }
    ],
    "sg:phone":"+1 361 595 8017",
    "sg:postcode":"78363",
    "sg:province":"TX",
    "sg:tags":[
        "village"
    ],
    "wof:name":"Kingsville Personnel Dept",
    "wof:placetype":"venue"
},
  "geometry": {"coordinates":[-97.86618799999999,27.516645],"type":"Point"}
}