{
  "type": "Feature",
  "properties": {
    "iso:country":"US",
    "sg:address":"409 N Main St",
    "sg:city":"Highlands",
    "sg:classifiers":[
        {
            "category":"Food & Beverages",
            "subcategory":"Specialty",
            "type":"Retail Goods"
        },
        {
            "category":"Food & Beverages",
            "subcategory":"Groceries & Convenience Stores",
            "type":"Retail Goods"
        }
    ],
    "sg:phone":"+1 281 426 8600",
    "sg:postcode":"77562",
    "sg:province":"TX",
    "sg:tags":[
        "grocers-specialty"
    ],
    "wof:name":"Aby Food Mart",
    "wof:placetype":"venue"
},
  "geometry": {"coordinates":[-95.05736899999999,29.819962],"type":"Point"}
}