{
  "type": "Feature",
  "properties": {
    "iso:country":"US",
    "sg:address":"300 Sharla Smelley Rd",
    "sg:city":"Weatherford",
    "sg:classifiers":[
        {
            "category":"Place Of Worship",
            "type":"Public Place"
        }
    ],
    "sg:phone":"+1 817 599 7377",
    "sg:postcode":"76088",
    "sg:province":"TX",
    "sg:tags":[
        "church"
    ],
    "wof:name":"Brazos Trails Cowboy Church",
    "wof:placetype":"venue"
},
  "geometry": {"coordinates":[-97.855407,32.8176],"type":"Point"}
}