{
  "type": "Feature",
  "properties": {
    "iso:country":"US",
    "sg:address":"10240 Strait Ln",
    "sg:city":"Dallas",
    "sg:classifiers":[
        {
            "category":"Social Services",
            "subcategory":"Child Care",
            "type":"Services"
        }
    ],
    "sg:phone":"+1 214 369 5817",
    "sg:postcode":"75229",
    "sg:province":"TX",
    "sg:tags":[
        "day"
    ],
    "wof:name":"Eddie Wynelle Parker Fmly Ltd",
    "wof:placetype":"venue"
},
  "geometry": {"coordinates":[-96.82471,32.883566],"type":"Point"}
}