{
  "type": "Feature",
  "properties": {
    "iso:country":"US",
    "sg:address":"3067 S Westmoreland Rd",
    "sg:city":"Dallas",
    "sg:classifiers":[
        {
            "category":"Professional",
            "subcategory":"Employment Agencies",
            "type":"Services"
        }
    ],
    "sg:phone":"+1 214 333 4495",
    "sg:postcode":"75233",
    "sg:province":"TX",
    "wof:name":"A Plus Apartment People",
    "wof:placetype":"venue"
},
  "geometry": {"coordinates":[-96.874422,32.707976],"type":"Point"}
}