{
  "type": "Feature",
  "properties": {
    "iso:country":"US",
    "sg:address":"942 W Kearney St",
    "sg:city":"Mesquite",
    "sg:classifiers":[
        {
            "category":"Wholesale",
            "subcategory":"Jewelry",
            "type":"Manufacturing & Wholesale Goods"
        }
    ],
    "sg:phone":"+1 972 288 0298",
    "sg:postcode":"75149",
    "sg:province":"TX",
    "sg:tags":[
        "jeweler"
    ],
    "wof:name":"Sweetwater Imports Dallas",
    "wof:placetype":"venue"
},
  "geometry": {"coordinates":[-96.60923,32.770682],"type":"Point"}
}