{
  "type": "Feature",
  "properties": {
    "iso:country":"US",
    "sg:address":"950 W Crosby Rd",
    "sg:city":"Carrollton",
    "sg:classifiers":[
        {
            "category":"Home & Garden",
            "subcategory":"Building Materials",
            "type":"Retail Goods"
        },
        {
            "category":"Building & Trades",
            "subcategory":"Construction",
            "type":"Services"
        }
    ],
    "sg:phone":"+1 214 718 6204",
    "sg:postcode":"75006",
    "sg:province":"TX",
    "sg:tags":[
        "contractor",
        "supply"
    ],
    "wof:name":"JSK Glass, Inc",
    "wof:placetype":"venue"
},
  "geometry": {"coordinates":[-96.90825599999999,32.947369],"type":"Point"}
}