{
  "type": "Feature",
  "properties": {
    "iso:country":"US",
    "sg:address":"7500 N Mesa St",
    "sg:city":"El Paso",
    "sg:classifiers":[
        {
            "category":"Restaurant",
            "type":"Food & Drink"
        }
    ],
    "sg:menulink":"http://www.allmenus.com/tx/el-paso/139429-quiznos-sub/menu/",
    "sg:phone":"+1 915 584 5900",
    "sg:postcode":"79912",
    "sg:province":"TX",
    "sg:tags":[
        "wrap",
        "american",
        "sandwich"
    ],
    "wof:name":"Quiznos Sub",
    "wof:placetype":"venue"
},
  "geometry": {"coordinates":[-106.563712,31.838706],"type":"Point"}
}