{
  "type": "Feature",
  "properties": {
    "iso:country":"US",
    "sg:address":"3418 Olsen Blvd",
    "sg:city":"Amarillo",
    "sg:classifiers":[
        {
            "category":"Building & Trades",
            "subcategory":"Construction",
            "type":"Services"
        }
    ],
    "sg:phone":"+1 806 351 0706",
    "sg:postcode":"79109",
    "sg:province":"TX",
    "sg:tags":[
        "repairing",
        "remodeling",
        "contractor"
    ],
    "wof:name":"S Ammons",
    "wof:placetype":"venue"
},
  "geometry": {"coordinates":[-101.879098,35.184984],"type":"Point"}
}