{
  "type": "Feature",
  "properties": {
    "iso:country":"US",
    "sg:address":"3217 Clydesdale Dr",
    "sg:city":"Denton",
    "sg:classifiers":[
        {
            "category":"Banks & Credit Unions",
            "subcategory":"Investment Brokerage",
            "type":"Services"
        },
        {
            "category":"Banks & Credit Unions",
            "subcategory":"Financial Services",
            "type":"Services"
        }
    ],
    "sg:phone":"+1 940 231 6361",
    "sg:postcode":"76210",
    "sg:province":"TX",
    "sg:tags":[
        "advisory",
        "planner"
    ],
    "wof:name":"Rich Port Financial",
    "wof:placetype":"venue"
},
  "geometry": {"coordinates":[-97.101507,33.156844],"type":"Point"}
}