{
  "type": "Feature",
  "properties": {
    "iso:country":"US",
    "sg:address":"2005 Griswold Ln",
    "sg:city":"Austin",
    "sg:classifiers":[
        {
            "category":"Manufacturing",
            "subcategory":"Signs",
            "type":"Manufacturing & Wholesale Goods"
        }
    ],
    "sg:phone":"+1 512 479 6063",
    "sg:postcode":"78703",
    "sg:province":"TX",
    "sg:tags":[
        "specialty",
        "mfg"
    ],
    "wof:name":"Able Signs",
    "wof:placetype":"venue"
},
  "geometry": {"coordinates":[-97.762601,30.289898],"type":"Point"}
}