{
  "type": "Feature",
  "properties": {
    "iso:country":"US",
    "sg:address":"308 E Renfro St",
    "sg:city":"Burleson",
    "sg:classifiers":[
        {
            "category":"Autos & Motor Vehicles",
            "subcategory":"Automobile Sales",
            "type":"Retail Goods"
        }
    ],
    "sg:phone":"+1 817 426 6688",
    "sg:postcode":"76028",
    "sg:province":"TX",
    "sg:tags":[
        "car",
        "dealer"
    ],
    "wof:name":"Elite Auto Brokers",
    "wof:placetype":"venue"
},
  "geometry": {"coordinates":[-97.315286,32.543521],"type":"Point"}
}