{
  "type": "Feature",
  "properties": {
    "iso:country":"US",
    "sg:address":"2304 Madera St",
    "sg:city":"Dallas",
    "sg:classifiers":[
        {
            "category":"Shopping",
            "subcategory":"Used Merchandise",
            "type":"Retail Goods"
        }
    ],
    "sg:phone":"+1 214 824 6238",
    "sg:postcode":"75206",
    "sg:province":"TX",
    "wof:name":"Fortney Antiques & Vintage Fur",
    "wof:placetype":"venue"
},
  "geometry": {"coordinates":[-96.778622,32.816441],"type":"Point"}
}