{
  "type": "Feature",
  "properties": {
    "iso:country":"US",
    "sg:address":"10501 River Rd",
    "sg:city":"New Braunfels",
    "sg:classifiers":[
        {
            "category":"Recreation",
            "type":"Entertainment"
        }
    ],
    "sg:phone":"+1 830 964 2640",
    "sg:postcode":"78132",
    "sg:province":"TX",
    "wof:name":"Rocky Beach Inc",
    "wof:placetype":"venue"
},
  "geometry": {"coordinates":[-98.173597,29.809552],"type":"Point"}
}