{
  "type": "Feature",
  "properties": {
    "iso:country":"US",
    "sg:address":"214 Fryer St",
    "sg:city":"Conroe",
    "sg:classifiers":[
        {
            "category":"Building & Trades",
            "subcategory":"Landscaping Services",
            "type":"Services"
        }
    ],
    "sg:phone":"+1 936 539 2640",
    "sg:postcode":"77301",
    "sg:province":"TX",
    "sg:tags":[
        "caretaker"
    ],
    "wof:name":"Dale Keith",
    "wof:placetype":"venue"
},
  "geometry": {"coordinates":[-95.455254,30.329383],"type":"Point"}
}