{
  "type": "Feature",
  "properties": {
    "iso:country":"US",
    "sg:address":"2605 Brenner Dr",
    "sg:city":"Dallas",
    "sg:classifiers":[
        {
            "category":"Manufacturing",
            "subcategory":"Tools & Machinery",
            "type":"Manufacturing & Wholesale Goods"
        }
    ],
    "sg:phone":"+1 214 357 5648",
    "sg:postcode":"75220",
    "sg:province":"TX",
    "sg:tags":[
        "industrial",
        "mfg"
    ],
    "wof:name":"Connolly Tool & Machine Co",
    "wof:placetype":"venue"
},
  "geometry": {"coordinates":[-96.88950699999999,32.872143],"type":"Point"}
}