{
  "type": "Feature",
  "properties": {
    "iso:country":"US",
    "sg:address":"5866 Eastex Fwy",
    "sg:city":"Beaumont",
    "sg:classifiers":[
        {
            "category":"Wholesale",
            "subcategory":"Machinery & Supplies",
            "type":"Manufacturing & Wholesale Goods"
        }
    ],
    "sg:phone":"+1 409 924 9343",
    "sg:postcode":"77708",
    "sg:province":"TX",
    "sg:tags":[
        "equipment",
        "transportation"
    ],
    "wof:name":"West Marine",
    "wof:placetype":"venue"
},
  "geometry": {"coordinates":[-94.155812,30.126572],"type":"Point"}
}