{
  "type": "Feature",
  "properties": {
    "iso:country":"US",
    "sg:address":"3535 W 7th St",
    "sg:city":"Fort Worth",
    "sg:classifiers":[
        {
            "category":"Real Estate",
            "subcategory":"Real Estate Services",
            "type":"Services"
        }
    ],
    "sg:phone":"+1 817 737 7003",
    "sg:postcode":"76107",
    "sg:province":"TX",
    "sg:tags":[
        "abstract",
        "title"
    ],
    "wof:name":"Alamo Title Company",
    "wof:placetype":"venue"
},
  "geometry": {"coordinates":[-97.36982500000001,32.751308],"type":"Point"}
}