{
  "type": "Feature",
  "properties": {
    "iso:country":"US",
    "sg:address":"801 SW 13th St",
    "sg:city":"Mineral Wells",
    "sg:classifiers":[
        {
            "category":"Manufacturing",
            "subcategory":"Printing",
            "type":"Manufacturing & Wholesale Goods"
        }
    ],
    "sg:phone":"+1 940 325 0567",
    "sg:postcode":"76067",
    "sg:province":"TX",
    "sg:tags":[
        "commercial"
    ],
    "wof:name":"Ford Sign & Silk Screening",
    "wof:placetype":"venue"
},
  "geometry": {"coordinates":[-98.120913,32.798882],"type":"Point"}
}