{
  "type": "Feature",
  "properties": {
    "iso:country":"US",
    "sg:address":"410 N Shiloh Rd",
    "sg:city":"Garland",
    "sg:classifiers":[
        {
            "category":"Health Services",
            "subcategory":"Doctor",
            "type":"Services"
        }
    ],
    "sg:phone":"+1 972 487 8701",
    "sg:postcode":"75042",
    "sg:province":"TX",
    "sg:tags":[
        "medical"
    ],
    "wof:name":"Asthma & Lung Specialists PA",
    "wof:placetype":"venue"
},
  "geometry": {"coordinates":[-96.665256,32.918062],"type":"Point"}
}