{
  "type": "Feature",
  "properties": {
    "iso:country":"US",
    "sg:address":"4301 Texas Ave S",
    "sg:city":"Bryan",
    "sg:classifiers":[
        {
            "category":"Shopping",
            "subcategory":"Books",
            "type":"Retail Goods"
        }
    ],
    "sg:phone":"+1 979 846 3433",
    "sg:postcode":"77802",
    "sg:province":"TX",
    "sg:tags":[
        "record",
        "tape",
        "gift"
    ],
    "wof:name":"Brazos Vly Christn Bks & Gifts",
    "wof:placetype":"venue"
},
  "geometry": {"coordinates":[-96.339787,30.631959],"type":"Point"}
}