{
  "type": "Feature",
  "properties": {
    "iso:country":"US",
    "sg:address":"8112 Park Ter",
    "sg:city":"Houston",
    "sg:classifiers":[
        {
            "category":"Shopping",
            "subcategory":"Clothing, Apparel, & Fashions",
            "type":"Retail Goods"
        }
    ],
    "sg:phone":"+1 713 645 5387",
    "sg:postcode":"77017",
    "sg:province":"TX",
    "wof:name":"Chandler Custom Creations",
    "wof:placetype":"venue"
},
  "geometry": {"coordinates":[-95.277151,29.700772],"type":"Point"}
}