{
  "type": "Feature",
  "properties": {
    "iso:country":"US",
    "sg:address":"200 W Walnut Rd",
    "sg:city":"Hereford",
    "sg:classifiers":[
        {
            "category":"Transit Center",
            "subcategory":"Freight",
            "type":"Transportation"
        },
        {
            "category":"Freight",
            "type":"Transportation"
        }
    ],
    "sg:phone":"+1 806 364 6822",
    "sg:postcode":"79045",
    "sg:province":"TX",
    "sg:tags":[
        "local",
        "trucking-motor",
        "trucking"
    ],
    "wof:name":"Newton Trucking Inc",
    "wof:placetype":"venue"
},
  "geometry": {"coordinates":[-102.38829,34.792858],"type":"Point"}
}