{
  "type": "Feature",
  "properties": {
    "iso:country":"US",
    "sg:address":"8605 Soho Dr",
    "sg:city":"Austin",
    "sg:classifiers":[
        {
            "category":"Real Estate",
            "subcategory":"Real Estate Agent",
            "type":"Services"
        }
    ],
    "sg:phone":"+1 512 280 0521",
    "sg:postcode":"78748",
    "sg:province":"TX",
    "wof:name":"Austin Gateway Realators",
    "wof:placetype":"venue"
},
  "geometry": {"coordinates":[-97.800729,30.177517],"type":"Point"}
}