{
  "type": "Feature",
  "properties": {
    "iso:country":"US",
    "sg:address":"515 W 14th St",
    "sg:city":"Texarkana",
    "sg:classifiers":[
        {
            "category":"Health Services",
            "subcategory":"Medical Lab",
            "type":"Services"
        }
    ],
    "sg:phone":"+1 903 793 1411",
    "sg:postcode":"75501",
    "sg:province":"TX",
    "sg:tags":[
        "laboratory"
    ],
    "wof:name":"B & W Dental Lab",
    "wof:placetype":"venue"
},
  "geometry": {"coordinates":[-94.04817199999999,33.432865],"type":"Point"}
}