{
  "type": "Feature",
  "properties": {
    "iso:country":"US",
    "sg:address":"1110 W San Antonio St",
    "sg:city":"New Braunfels",
    "sg:classifiers":[
        {
            "category":"Banks & Credit Unions",
            "subcategory":"Bank",
            "type":"Services"
        }
    ],
    "sg:phone":"+1 830 620 9490",
    "sg:postcode":"78130",
    "sg:province":"TX",
    "sg:tags":[
        "loan",
        "mortgage",
        "real estate"
    ],
    "wof:name":"Network Funding Corporation",
    "wof:placetype":"venue"
},
  "geometry": {"coordinates":[-98.13343,29.693711],"type":"Point"}
}