{
  "type": "Feature",
  "properties": {
    "iso:country":"US",
    "sg:address":"2909 Winterberry Dr",
    "sg:city":"Carrollton",
    "sg:classifiers":[
        {
            "category":"Professional",
            "subcategory":"Business Services",
            "type":"Services"
        },
        {
            "category":"Restaurant",
            "type":"Food & Drink"
        }
    ],
    "sg:phone":"+1 972 395 0657",
    "sg:postcode":"75007",
    "sg:province":"TX",
    "sg:tags":[
        "eating",
        "caterer"
    ],
    "wof:name":"Lukens Enterprises Ltd",
    "wof:placetype":"venue"
},
  "geometry": {"coordinates":[-96.88363699999999,32.997801],"type":"Point"}
}