{
  "type": "Feature",
  "properties": {
    "iso:country":"US",
    "sg:address":"2212 E 84th St",
    "sg:city":"Lubbock",
    "sg:classifiers":[
        {
            "category":"Wholesale",
            "subcategory":"Machinery & Supplies",
            "type":"Manufacturing & Wholesale Goods"
        },
        {
            "category":"Shopping",
            "type":"Retail Goods"
        }
    ],
    "sg:phone":"+1 806 745 1834",
    "sg:postcode":"79404",
    "sg:province":"TX",
    "sg:tags":[
        "merchandise",
        "tractor"
    ],
    "wof:name":"Triple S Tractor",
    "wof:placetype":"venue"
},
  "geometry": {"coordinates":[-101.813919,33.517784],"type":"Point"}
}