{
  "type": "Feature",
  "properties": {
    "iso:country":"US",
    "sg:address":"409 Eric Dr",
    "sg:city":"Killeen",
    "sg:classifiers":[
        {
            "category":"Communications",
            "subcategory":"Film & Video Production",
            "type":"Services"
        }
    ],
    "sg:phone":"+1 254 554 2814",
    "sg:postcode":"76542",
    "sg:province":"TX",
    "sg:tags":[
        "motion"
    ],
    "wof:name":"Cloud 9 Video Productions",
    "wof:placetype":"venue"
},
  "geometry": {"coordinates":[-97.75308,31.079011],"type":"Point"}
}