{
  "type": "Feature",
  "properties": {
    "iso:country":"US",
    "sg:address":"6201 Southwest Fwy",
    "sg:city":"Houston",
    "sg:classifiers":[
        {
            "category":"Home & Garden",
            "subcategory":"Furniture",
            "type":"Retail Goods"
        }
    ],
    "sg:phone":"+1 713 785 2321",
    "sg:postcode":"77074",
    "sg:province":"TX",
    "sg:tags":[
        "store"
    ],
    "wof:name":"Furniture Land",
    "wof:placetype":"venue"
},
  "geometry": {"coordinates":[-95.490449,29.723776],"type":"Point"}
}