{
  "type": "Feature",
  "properties": {
    "iso:country":"US",
    "sg:address":"5560 E Grand Ave",
    "sg:city":"Dallas",
    "sg:classifiers":[
        {
            "category":"Restaurant",
            "type":"Food & Drink"
        }
    ],
    "sg:phone":"+1 214 370 5633",
    "sg:postcode":"75223",
    "sg:province":"TX",
    "sg:tags":[
        "eating",
        "fast"
    ],
    "wof:name":"Fast Food Station",
    "wof:placetype":"venue"
},
  "geometry": {"coordinates":[-96.74749799999999,32.7934],"type":"Point"}
}