{
  "type": "Feature",
  "properties": {
    "iso:country":"US",
    "sg:address":"20275 Tilden Rd",
    "sg:city":"San Benito",
    "sg:classifiers":[
        {
            "category":"Autos & Motor Vehicles",
            "subcategory":"Automobile Sales",
            "type":"Retail Goods"
        }
    ],
    "sg:phone":"+1 956 361 2731",
    "sg:postcode":"78586",
    "sg:province":"TX",
    "sg:tags":[
        "car",
        "dealer"
    ],
    "wof:name":"A Waldrep Autos",
    "wof:placetype":"venue"
},
  "geometry": {"coordinates":[-97.69812899999999,26.092633],"type":"Point"}
}