{
  "type": "Feature",
  "properties": {
    "iso:country":"US",
    "sg:address":"2700 Post Oak Blvd",
    "sg:city":"Houston",
    "sg:classifiers":[
        {
            "category":"Building & Trades",
            "subcategory":"Construction",
            "type":"Services"
        }
    ],
    "sg:phone":"+1 713 623 4646",
    "sg:postcode":"77056",
    "sg:province":"TX",
    "sg:tags":[
        "builder",
        "operative"
    ],
    "wof:name":"Jim Frankel Custom Homes",
    "wof:placetype":"venue"
},
  "geometry": {"coordinates":[-95.460759,29.739373],"type":"Point"}
}