{
  "type": "Feature",
  "properties": {
    "iso:country":"US",
    "sg:address":"14261 Montana Ave",
    "sg:city":"El Paso",
    "sg:classifiers":[
        {
            "category":"Real Estate",
            "subcategory":"Real Estate Agent",
            "type":"Services"
        }
    ],
    "sg:phone":"+1 915 855 3355",
    "sg:postcode":"79938",
    "sg:province":"TX",
    "sg:website":"www.elptx.com",
    "wof:name":"Tres Amigos Realty",
    "wof:placetype":"venue"
},
  "geometry": {"coordinates":[-106.182495,31.817835],"type":"Point"}
}