{
  "type": "Feature",
  "properties": {
    "iso:country":"US",
    "sg:address":"9412 Gaylord Dr",
    "sg:city":"Houston",
    "sg:classifiers":[
        {
            "category":"Building & Trades",
            "subcategory":"Construction",
            "type":"Services"
        }
    ],
    "sg:phone":"+1 713 665 5600",
    "sg:postcode":"77024",
    "sg:province":"TX",
    "sg:tags":[
        "contractor"
    ],
    "wof:name":"Courtney & Company",
    "wof:placetype":"venue"
},
  "geometry": {"coordinates":[-95.50994,29.782767],"type":"Point"}
}