{
  "type": "Feature",
  "properties": {
    "iso:country":"US",
    "sg:address":"328 W Main St",
    "sg:city":"Kenedy",
    "sg:classifiers":[
        {
            "category":"Utilities",
            "subcategory":"Natural Gas",
            "type":"Services"
        }
    ],
    "sg:phone":"+1 830 583 2018",
    "sg:postcode":"78119",
    "sg:province":"TX",
    "sg:tags":[
        "company"
    ],
    "wof:name":"Center Point Energy Entex",
    "wof:placetype":"venue"
},
  "geometry": {"coordinates":[-97.850475,28.818606],"type":"Point"}
}