{
  "type": "Feature",
  "properties": {
    "iso:country":"US",
    "sg:address":"5528 Forney Rd",
    "sg:city":"Dallas",
    "sg:classifiers":[
        {
            "category":"Organizations",
            "subcategory":"Religious Organization",
            "type":"Services"
        }
    ],
    "sg:phone":"+1 214 388 6733",
    "sg:postcode":"75227",
    "sg:province":"TX",
    "wof:name":"Message For Today Deliverance",
    "wof:placetype":"venue"
},
  "geometry": {"coordinates":[-96.720664,32.784743],"type":"Point"}
}