{
  "type": "Feature",
  "properties": {
    "iso:country":"US",
    "sg:address":"12015 Plumbrook Dr",
    "sg:city":"Houston",
    "sg:classifiers":[
        {
            "category":"Building & Trades",
            "subcategory":"Plumbing",
            "type":"Services"
        }
    ],
    "sg:phone":"+1 281 933 9500",
    "sg:postcode":"77099",
    "sg:province":"TX",
    "sg:tags":[
        "contractor"
    ],
    "wof:name":"Aaac Htg Refrig",
    "wof:placetype":"venue"
},
  "geometry": {"coordinates":[-95.59291899999999,29.669244],"type":"Point"}
}