{
  "type": "Feature",
  "properties": {
    "iso:country":"US",
    "sg:address":"3684 FM 306",
    "sg:city":"New Braunfels",
    "sg:classifiers":[
        {
            "category":"Home & Garden",
            "subcategory":"Building Materials",
            "type":"Retail Goods"
        }
    ],
    "sg:phone":"+1 830 606 4090",
    "sg:postcode":"78132",
    "sg:province":"TX",
    "wof:name":"Independent Stone Guys Co",
    "wof:placetype":"venue"
},
  "geometry": {"coordinates":[-98.10529099999999,29.783882],"type":"Point"}
}