{
  "type": "Feature",
  "properties": {
    "iso:country":"US",
    "sg:address":"2154 Forest Ln",
    "sg:city":"Garland",
    "sg:classifiers":[
        {
            "category":"Banks & Credit Unions",
            "subcategory":"Bank",
            "type":"Services"
        }
    ],
    "sg:phone":"+1 972 494 5328",
    "sg:postcode":"75042",
    "sg:province":"TX",
    "wof:name":"Kraft America Credit Union",
    "wof:placetype":"venue"
},
  "geometry": {"coordinates":[-96.660202,32.909],"type":"Point"}
}