{
  "type": "Feature",
  "properties": {
    "iso:country":"US",
    "sg:address":"316 Anderson Dr",
    "sg:city":"Hurst",
    "sg:classifiers":[
        {
            "category":"Freight",
            "type":"Transportation"
        }
    ],
    "sg:phone":"+1 817 285 8802",
    "sg:postcode":"76053",
    "sg:province":"TX",
    "sg:tags":[
        "trucking"
    ],
    "wof:name":"Autonet America",
    "wof:placetype":"venue"
},
  "geometry": {"coordinates":[-97.183267,32.814259],"type":"Point"}
}