{
  "type": "Feature",
  "properties": {
    "iso:country":"US",
    "sg:address":"6565 N Macarthur Blvd",
    "sg:city":"Irving",
    "sg:classifiers":[
        {
            "category":"Shopping",
            "subcategory":"Used Merchandise",
            "type":"Retail Goods"
        }
    ],
    "sg:phone":"+1 972 501 1500",
    "sg:postcode":"75039",
    "sg:province":"TX",
    "sg:tags":[
        "shop",
        "consignment"
    ],
    "wof:name":"North American Resale Inc",
    "wof:placetype":"venue"
},
  "geometry": {"coordinates":[-96.9589,32.90012],"type":"Point"}
}