{
  "type": "Feature",
  "properties": {
    "iso:country":"US",
    "sg:address":"2432 Kelly Ln",
    "sg:city":"Houston",
    "sg:classifiers":[
        {
            "category":"Wholesale",
            "subcategory":"Auto Parts",
            "type":"Manufacturing & Wholesale Goods"
        }
    ],
    "sg:phone":"+1 281 537 2024",
    "sg:postcode":"77066",
    "sg:province":"TX",
    "sg:tags":[
        "repair",
        "automotive"
    ],
    "wof:name":"Jorge Auto Service",
    "wof:placetype":"venue"
},
  "geometry": {"coordinates":[-95.47423000000001,29.955841],"type":"Point"}
}