{
  "type": "Feature",
  "properties": {
    "iso:country":"US",
    "sg:address":"215 S Standard St",
    "sg:city":"Longview",
    "sg:classifiers":[
        {
            "category":"Restaurant",
            "type":"Food & Drink"
        }
    ],
    "sg:phone":"+1 903 297 8895",
    "sg:postcode":"75604",
    "sg:province":"TX",
    "wof:name":"Elpuente Mexican Food Rstrnt",
    "wof:placetype":"venue"
},
  "geometry": {"coordinates":[-94.797078,32.505249],"type":"Point"}
}