{
  "type": "Feature",
  "properties": {
    "iso:country":"US",
    "sg:address":"909 Radecke Rd",
    "sg:city":"Krum",
    "sg:classifiers":[
        {
            "category":"Wholesale",
            "subcategory":"Sporting Goods",
            "type":"Manufacturing & Wholesale Goods"
        }
    ],
    "sg:phone":"+1 940 482 6658",
    "sg:postcode":"76249",
    "sg:province":"TX",
    "wof:name":"Point Man Products",
    "wof:placetype":"venue"
},
  "geometry": {"coordinates":[-97.228308,33.251955],"type":"Point"}
}