{
  "type": "Feature",
  "properties": {
    "iso:country":"US",
    "sg:address":"220 N Merill St",
    "sg:city":"Buffalo",
    "sg:classifiers":[
        {
            "category":"Organizations",
            "subcategory":"Religious Organization",
            "type":"Services"
        }
    ],
    "sg:phone":"+1 903 322 3705",
    "sg:postcode":"75831",
    "sg:province":"TX",
    "sg:tags":[
        "church"
    ],
    "wof:name":"Blessed Kateri Roman Catholic",
    "wof:placetype":"venue"
},
  "geometry": {"coordinates":[-96.07168299999999,31.461005],"type":"Point"}
}