{
  "type": "Feature",
  "properties": {
    "iso:country":"US",
    "sg:address":"2513 Magnolia Leaf Ln",
    "sg:city":"Flower Mound",
    "sg:classifiers":[
        {
            "category":"Professional",
            "type":"Services"
        }
    ],
    "sg:phone":"+1 972 874 9900",
    "sg:postcode":"75022",
    "sg:province":"TX",
    "wof:name":"Erosion Specialists Inc",
    "wof:placetype":"venue"
},
  "geometry": {"coordinates":[-97.07113200000001,33.01995],"type":"Point"}
}