{
  "type": "Feature",
  "properties": {
    "iso:country":"US",
    "sg:address":"511 N Warren St",
    "sg:city":"Lufkin",
    "sg:classifiers":[
        {
            "category":"Personal",
            "subcategory":"Beauty Salon",
            "type":"Services"
        }
    ],
    "sg:phone":"+1 936 632 9903",
    "sg:postcode":"75901",
    "sg:province":"TX",
    "wof:name":"Divas Closet Exclusive",
    "wof:placetype":"venue"
},
  "geometry": {"coordinates":[-94.71502700000001,31.346981],"type":"Point"}
}