{
  "type": "Feature",
  "properties": {
    "iso:country":"US",
    "sg:address":"3604 Gulf Ave",
    "sg:city":"Midland",
    "sg:classifiers":[
        {
            "category":"Building & Trades",
            "subcategory":"Equipment Rental",
            "type":"Services"
        }
    ],
    "sg:phone":"+1 432 520 4565",
    "sg:postcode":"79707",
    "sg:province":"TX",
    "sg:tags":[
        "party",
        "supply"
    ],
    "wof:name":"ABC Party Jumpers",
    "wof:placetype":"venue"
},
  "geometry": {"coordinates":[-102.13085100000001,32.008033],"type":"Point"}
}