{
  "type": "Feature",
  "properties": {
    "iso:country":"US",
    "sg:address":"10840 Beaumont Hwy",
    "sg:city":"Houston",
    "sg:classifiers":[
        {
            "category":"Restaurant",
            "type":"Food & Drink"
        }
    ],
    "sg:phone":"+1 713 670 8660",
    "sg:postcode":"77078",
    "sg:province":"TX",
    "wof:name":"C and A Cb Sales & Service",
    "wof:placetype":"venue"
},
  "geometry": {"coordinates":[-95.24189800000001,29.818899],"type":"Point"}
}