{
  "type": "Feature",
  "properties": {
    "iso:country":"US",
    "sg:address":"6790 Southwest Fwy",
    "sg:city":"Houston",
    "sg:classifiers":[
        {
            "category":"Travel",
            "subcategory":"Hotels & Motels",
            "type":"Entertainment"
        }
    ],
    "sg:phone":"+1 713 784 3838",
    "sg:postcode":"77074",
    "sg:province":"TX",
    "wof:name":"Baymont Inns",
    "wof:placetype":"venue"
},
  "geometry": {"coordinates":[-95.502701,29.714199],"type":"Point"}
}