{
  "type": "Feature",
  "properties": {
    "iso:country":"US",
    "sg:address":"7030 Hazen St",
    "sg:city":"Houston",
    "sg:classifiers":[
        {
            "category":"Professional",
            "subcategory":"Lawyer & Legal Services",
            "type":"Services"
        }
    ],
    "sg:phone":"+1 713 772 9788",
    "sg:postcode":"77074",
    "sg:province":"TX",
    "wof:name":"Cr Legal Clinic",
    "wof:placetype":"venue"
},
  "geometry": {"coordinates":[-95.507581,29.693186],"type":"Point"}
}