{
  "type": "Feature",
  "properties": {
    "iso:country":"US",
    "sg:address":"901 Adams Ave",
    "sg:city":"Odessa",
    "sg:classifiers":[
        {
            "category":"Wholesale",
            "subcategory":"Auto Parts",
            "type":"Manufacturing & Wholesale Goods"
        }
    ],
    "sg:phone":"+1 432 332 7141",
    "sg:postcode":"79761",
    "sg:province":"TX",
    "sg:tags":[
        "machine",
        "shop",
        "automotive"
    ],
    "wof:name":"Automotive Machine & Supply",
    "wof:placetype":"venue"
},
  "geometry": {"coordinates":[-102.366428,31.856191],"type":"Point"}
}