{
  "type": "Feature",
  "properties": {
    "iso:country":"US",
    "sg:address":"319 Bon Aire Dr",
    "sg:city":"Dallas",
    "sg:classifiers":[
        {
            "category":"Social Services",
            "subcategory":"Child Care",
            "type":"Services"
        }
    ],
    "sg:phone":"+1 214 348 6862",
    "sg:postcode":"75218",
    "sg:province":"TX",
    "sg:tags":[
        "day"
    ],
    "wof:name":"Musikgarten of Dallas",
    "wof:placetype":"venue"
},
  "geometry": {"coordinates":[-96.705752,32.859519],"type":"Point"}
}