{
  "type": "Feature",
  "properties": {
    "iso:country":"US",
    "sg:address":"2221 Southern Cir",
    "sg:city":"Carrollton",
    "sg:classifiers":[
        {
            "category":"Sports & Exercise",
            "subcategory":"Gym",
            "type":"Entertainment"
        }
    ],
    "sg:phone":"+1 972 323 9449",
    "sg:postcode":"75006",
    "sg:province":"TX",
    "sg:tags":[
        "spa",
        "health"
    ],
    "wof:name":"Dial One Wood & Spa Designs",
    "wof:placetype":"venue"
},
  "geometry": {"coordinates":[-96.875603,32.978256],"type":"Point"}
}