{
  "type": "Feature",
  "properties": {
    "iso:country":"US",
    "sg:address":"9528 Webb Chapel Rd",
    "sg:city":"Dallas",
    "sg:classifiers":[
        {
            "category":"Health Services",
            "subcategory":"Doctor",
            "type":"Services"
        }
    ],
    "sg:phone":"+1 214 357 7311",
    "sg:postcode":"75220",
    "sg:province":"TX",
    "sg:tags":[
        "clinic"
    ],
    "wof:name":"Launey Medical & Surgical Clnc",
    "wof:placetype":"venue"
},
  "geometry": {"coordinates":[-96.86047600000001,32.863191],"type":"Point"}
}