{
  "type": "Feature",
  "properties": {
    "iso:country":"US",
    "sg:address":"7405 S Westmoreland Rd",
    "sg:city":"Dallas",
    "sg:classifiers":[
        {
            "category":"Wholesale",
            "subcategory":"Machinery & Supplies",
            "type":"Manufacturing & Wholesale Goods"
        }
    ],
    "sg:phone":"+1 972 780 9096",
    "sg:postcode":"75237",
    "sg:province":"TX",
    "sg:tags":[
        "industrial"
    ],
    "wof:name":"U-Fix-It",
    "wof:placetype":"venue"
},
  "geometry": {"coordinates":[-96.88557900000001,32.654824],"type":"Point"}
}