{
  "type": "Feature",
  "properties": {
    "iso:country":"US",
    "sg:address":"325 Carolyn Dr",
    "sg:city":"Bedford",
    "sg:classifiers":[
        {
            "category":"Education",
            "subcategory":"School",
            "type":"Public Place"
        }
    ],
    "sg:phone":"+1 817 788 3101",
    "sg:postcode":"76021",
    "sg:province":"TX",
    "sg:tags":[
        "high",
        "junior"
    ],
    "wof:name":"Bedford Junior High School",
    "wof:placetype":"venue"
},
  "geometry": {"coordinates":[-97.16324899999999,32.854481],"type":"Point"}
}