{
  "type": "Feature",
  "properties": {
    "iso:country":"US",
    "sg:address":"9580 Crestshire Dr",
    "sg:city":"Dallas",
    "sg:classifiers":[
        {
            "category":"Retail",
            "subcategory":"Repair Shop",
            "type":"Services"
        }
    ],
    "sg:phone":"+1 214 381 1055",
    "sg:postcode":"75227",
    "sg:province":"TX",
    "wof:name":"Two Sister Cleaning & Janitora",
    "wof:placetype":"venue"
},
  "geometry": {"coordinates":[-96.659144,32.753066],"type":"Point"}
}