{
  "type": "Feature",
  "properties": {
    "iso:country":"US",
    "sg:address":"2120 Little York Rd",
    "sg:city":"Houston",
    "sg:classifiers":[
        {
            "category":"Shopping",
            "subcategory":"Used Merchandise",
            "type":"Retail Goods"
        }
    ],
    "sg:phone":"+1 713 691 0658",
    "sg:postcode":"77093",
    "sg:province":"TX",
    "sg:tags":[
        "pawnbroker"
    ],
    "wof:name":"Cash America Pawn",
    "wof:placetype":"venue"
},
  "geometry": {"coordinates":[-95.357196,29.87081],"type":"Point"}
}