{
  "type": "Feature",
  "properties": {
    "iso:country":"US",
    "sg:address":"5525 Meadowcrest Dr",
    "sg:city":"Dallas",
    "sg:classifiers":[
        {
            "category":"Shopping",
            "type":"Retail Goods"
        }
    ],
    "sg:phone":"+1 214 739 1333",
    "sg:postcode":"75229",
    "sg:province":"TX",
    "sg:tags":[
        "merchandise"
    ],
    "wof:name":"Brandy Walker Glass Art",
    "wof:placetype":"venue"
},
  "geometry": {"coordinates":[-96.817043,32.903725],"type":"Point"}
}