{
  "type": "Feature",
  "properties": {
    "iso:country":"US",
    "sg:address":"4611 E Mlk J",
    "sg:city":"Austin",
    "sg:classifiers":[
        {
            "category":"Food & Beverages",
            "subcategory":"Groceries & Convenience Stores",
            "type":"Retail Goods"
        }
    ],
    "sg:phone":"+1 512 926 1210",
    "sg:postcode":"78721",
    "sg:province":"TX",
    "wof:name":"Fast Stop 4",
    "wof:placetype":"venue"
},
  "geometry": {"coordinates":[-97.688698,30.2757],"type":"Point"}
}