{
  "type": "Feature",
  "properties": {
    "iso:country":"US",
    "sg:address":"27 Circle Rd",
    "sg:city":"Longview",
    "sg:classifiers":[
        {
            "category":"Real Estate",
            "subcategory":"Real Estate Agent",
            "type":"Services"
        }
    ],
    "sg:phone":"+1 903 757 5768",
    "sg:postcode":"75602",
    "sg:province":"TX",
    "wof:name":"Evans Real Estate",
    "wof:placetype":"venue"
},
  "geometry": {"coordinates":[-94.67906600000001,32.463455],"type":"Point"}
}