{
  "type": "Feature",
  "properties": {
    "iso:country":"US",
    "sg:address":"5502 Memorial Dr",
    "sg:city":"Houston",
    "sg:classifiers":[
        {
            "category":"Restaurant",
            "type":"Food & Drink"
        }
    ],
    "sg:phone":"+1 713 864 8526",
    "sg:postcode":"77007",
    "sg:province":"TX",
    "sg:tags":[
        "eating"
    ],
    "wof:name":"Ottos Hamburgers",
    "wof:placetype":"venue"
},
  "geometry": {"coordinates":[-95.41836499999999,29.761445],"type":"Point"}
}