{
  "type": "Feature",
  "properties": {
    "iso:country":"US",
    "sg:address":"400 Medical Center Blvd",
    "sg:city":"Webster",
    "sg:classifiers":[
        {
            "category":"Shopping",
            "subcategory":"Pharmacy",
            "type":"Retail Goods"
        }
    ],
    "sg:phone":"+1 281 332 2496",
    "sg:postcode":"77598",
    "sg:province":"TX",
    "wof:name":"Professional Bldg Pharmacy",
    "wof:placetype":"venue"
},
  "geometry": {"coordinates":[-95.127786,29.540045],"type":"Point"}
}