{
  "type": "Feature",
  "properties": {
    "iso:country":"US",
    "sg:address":"950 S Mill St",
    "sg:city":"Lewisville",
    "sg:classifiers":[
        {
            "category":"Autos & Motor Vehicles",
            "subcategory":"Automobile Sales",
            "type":"Retail Goods"
        }
    ],
    "sg:phone":"+1 972 221 9033",
    "sg:postcode":"75057",
    "sg:province":"TX",
    "wof:name":"JD Motors Inc",
    "wof:placetype":"venue"
},
  "geometry": {"coordinates":[-96.992796,33.034773],"type":"Point"}
}