{
  "type": "Feature",
  "properties": {
    "iso:country":"US",
    "sg:address":"434 North Dr",
    "sg:city":"San Antonio",
    "sg:classifiers":[
        {
            "category":"Professional",
            "subcategory":"Advertising",
            "type":"Services"
        }
    ],
    "sg:phone":"+1 210 734 2636",
    "sg:postcode":"78201",
    "sg:province":"TX",
    "wof:name":"Debbie Little Dist",
    "wof:placetype":"venue"
},
  "geometry": {"coordinates":[-98.53812000000001,29.467812],"type":"Point"}
}