{
  "type": "Feature",
  "properties": {
    "iso:country":"US",
    "sg:address":"11341 Hughes Rd",
    "sg:city":"Houston",
    "sg:classifiers":[
        {
            "category":"Retail",
            "subcategory":"Auto Repair",
            "type":"Services"
        }
    ],
    "sg:phone":"+1 281 481 1445",
    "sg:postcode":"77089",
    "sg:province":"TX",
    "sg:tags":[
        "repairing",
        "automobile"
    ],
    "wof:name":"Lam Auto Repair",
    "wof:placetype":"venue"
},
  "geometry": {"coordinates":[-95.216797,29.5977],"type":"Point"}
}