{
  "type": "Feature",
  "properties": {
    "iso:country":"US",
    "sg:address":"6244 Glenview Dr",
    "sg:city":"Fort Worth",
    "sg:classifiers":[
        {
            "category":"Shopping",
            "subcategory":"Gifts & Souvenirs",
            "type":"Retail Goods"
        }
    ],
    "sg:phone":"+1 817 605 6037",
    "sg:postcode":"76180",
    "sg:province":"TX",
    "sg:tags":[
        "various",
        "novelty",
        "type"
    ],
    "wof:name":"Marvins Wholesale",
    "wof:placetype":"venue"
},
  "geometry": {"coordinates":[-97.24834199999999,32.82518],"type":"Point"}
}