{
  "type": "Feature",
  "properties": {
    "iso:country":"US",
    "sg:address":"6207 Liberty Hill St",
    "sg:city":"Dallas",
    "sg:classifiers":[
        {
            "category":"Professional",
            "subcategory":"Business Services",
            "type":"Services"
        }
    ],
    "sg:phone":"+1 972 385 8306",
    "sg:postcode":"75248",
    "sg:province":"TX",
    "wof:name":"Carolyn Foust Intr Design",
    "wof:placetype":"venue"
},
  "geometry": {"coordinates":[-96.798343,32.954834],"type":"Point"}
}