{
  "type": "Feature",
  "properties": {
    "iso:country":"US",
    "sg:address":"8100 Dallas Pkwy",
    "sg:city":"Plano",
    "sg:classifiers":[
        {
            "category":"Restaurant",
            "type":"Food & Drink"
        }
    ],
    "sg:menulink":"http://www.allmenus.com/tx/plano/130965-subway/menu/",
    "sg:phone":"+1 214 387 0222",
    "sg:postcode":"75024",
    "sg:province":"TX",
    "sg:tags":[
        "american",
        "sandwich"
    ],
    "wof:name":"Subway",
    "wof:placetype":"venue"
},
  "geometry": {"coordinates":[-96.822529,33.087983],"type":"Point"}
}