{
  "type": "Feature",
  "properties": {
    "iso:country":"US",
    "sg:address":"805 Stark St",
    "sg:city":"Austin",
    "sg:classifiers":[
        {
            "category":"Retail",
            "subcategory":"Laundry & Dry Cleaning",
            "type":"Services"
        }
    ],
    "sg:phone":"+1 512 322 9284",
    "sg:postcode":"78756",
    "sg:province":"TX",
    "wof:name":"Continental Tailor Shop",
    "wof:placetype":"venue"
},
  "geometry": {"coordinates":[-97.72888399999999,30.326493],"type":"Point"}
}