{
  "type": "Feature",
  "properties": {
    "iso:country":"US",
    "sg:address":"3528 S Broadway Ave",
    "sg:city":"Tyler",
    "sg:classifiers":[
        {
            "category":"Personal",
            "type":"Services"
        }
    ],
    "sg:phone":"+1 903 561 8471",
    "sg:postcode":"75701",
    "sg:province":"TX",
    "sg:tags":[
        "wear",
        "formal"
    ],
    "wof:name":"Al's Formal Wear",
    "wof:placetype":"venue"
},
  "geometry": {"coordinates":[-95.300583,32.3109],"type":"Point"}
}