{
  "type": "Feature",
  "properties": {
    "iso:country":"US",
    "sg:address":"2525 Players Ct",
    "sg:city":"Dallas",
    "sg:classifiers":[
        {
            "category":"Professional",
            "subcategory":"Business Services",
            "type":"Services"
        }
    ],
    "sg:phone":"+1 972 307 0167",
    "sg:postcode":"75287",
    "sg:province":"TX",
    "sg:tags":[
        "graphic",
        "design",
        "imaging"
    ],
    "wof:name":"Eleventh Hour Imaging",
    "wof:placetype":"venue"
},
  "geometry": {"coordinates":[-96.86672900000001,32.991637],"type":"Point"}
}