{
  "type": "Feature",
  "properties": {
    "iso:country":"US",
    "sg:address":"7272 Wurzbach Rd",
    "sg:city":"San Antonio",
    "sg:classifiers":[
        {
            "category":"Health Services",
            "subcategory":"Doctor",
            "type":"Services"
        }
    ],
    "sg:phone":"+1 210 615 1545",
    "sg:postcode":"78240",
    "sg:province":"TX",
    "sg:tags":[
        "dentist"
    ],
    "wof:name":"Miller-Lunt Dental Ctr",
    "wof:placetype":"venue"
},
  "geometry": {"coordinates":[-98.58819800000001,29.49989],"type":"Point"}
}