{
  "type": "Feature",
  "properties": {
    "iso:country":"US",
    "sg:address":"500 N Interstate 45 Svc Rd",
    "sg:city":"Palmer",
    "sg:classifiers":[
        {
            "category":"Freight",
            "type":"Transportation"
        }
    ],
    "sg:phone":"+1 972 845 2472",
    "sg:postcode":"75141",
    "sg:province":"TX",
    "sg:tags":[
        "delivery"
    ],
    "wof:name":"Mike's Delivery Inc",
    "wof:placetype":"venue"
},
  "geometry": {"coordinates":[-96.715093,32.655011],"type":"Point"}
}