{
  "type": "Feature",
  "properties": {
    "iso:country":"US",
    "sg:address":"4309 Yoakum Blvd",
    "sg:city":"Houston",
    "sg:classifiers":[
        {
            "category":"Professional",
            "subcategory":"Lawyer & Legal Services",
            "type":"Services"
        }
    ],
    "sg:phone":"+1 713 522 9444",
    "sg:postcode":"77006",
    "sg:province":"TX",
    "wof:name":"Hanszen Laporte",
    "wof:placetype":"venue"
},
  "geometry": {"coordinates":[-95.392403,29.7339],"type":"Point"}
}