{
  "type": "Feature",
  "properties": {
    "iso:country":"US",
    "sg:address":"5001 Rowlett Rd",
    "sg:city":"Rowlett",
    "sg:classifiers":[
        {
            "category":"Health Services",
            "subcategory":"Doctor",
            "type":"Services"
        }
    ],
    "sg:phone":"+1 972 463 8623",
    "sg:postcode":"75088",
    "sg:province":"TX",
    "sg:tags":[
        "physician",
        "surgeon"
    ],
    "wof:name":"Les T Sandknop Do Pa",
    "wof:placetype":"venue"
},
  "geometry": {"coordinates":[-96.569519,32.905105],"type":"Point"}
}