{
  "type": "Feature",
  "properties": {
    "iso:country":"US",
    "sg:address":"701 W Division Ave",
    "sg:city":"Orange",
    "sg:classifiers":[
        {
            "category":"Manufacturing",
            "subcategory":"Rubber & Plastics",
            "type":"Manufacturing & Wholesale Goods"
        },
        {
            "category":"Shopping",
            "subcategory":"Computers & Home Electronics",
            "type":"Retail Goods"
        },
        {
            "category":"Shopping",
            "subcategory":"Used Merchandise",
            "type":"Retail Goods"
        },
        {
            "category":"Wholesale",
            "subcategory":"Office Equipment",
            "type":"Manufacturing & Wholesale Goods"
        },
        {
            "category":"Professional",
            "subcategory":"Printing & Photocopies",
            "type":"Services"
        },
        {
            "category":"Shopping",
            "subcategory":"Stationery & Office Supplies",
            "type":"Retail Goods"
        }
    ],
    "sg:phone":"+1 800 244 6208",
    "sg:postcode":"77630",
    "sg:province":"TX",
    "sg:tags":[
        "stamp",
        "register",
        "autographic",
        "duplicating",
        "copying",
        "typewriter",
        "furniture"
    ],
    "sg:website":"http://www.orangestationer.com",
    "wof:name":"Orange Stationer Inc The",
    "wof:placetype":"venue"
},
  "geometry": {"coordinates":[-93.73526,30.090139],"type":"Point"}
}