{
  "type": "Feature",
  "properties": {
    "iso:country":"US",
    "sg:address":"954 Wakefield Dr",
    "sg:city":"Houston",
    "sg:classifiers":[
        {
            "category":"Building & Trades",
            "subcategory":"Construction",
            "type":"Services"
        }
    ],
    "sg:phone":"+1 713 682 2494",
    "sg:postcode":"77018",
    "sg:province":"TX",
    "sg:tags":[
        "contractor"
    ],
    "wof:name":"West Mark J",
    "wof:placetype":"venue"
},
  "geometry": {"coordinates":[-95.423103,29.8216],"type":"Point"}
}