{
  "type": "Feature",
  "properties": {
    "iso:country":"US",
    "sg:address":"5915 Windhaven Dr",
    "sg:city":"San Antonio",
    "sg:classifiers":[
        {
            "category":"Arts & Performance",
            "subcategory":"Theater",
            "type":"Entertainment"
        }
    ],
    "sg:phone":"+1 210 394 2807",
    "sg:postcode":"78239",
    "sg:province":"TX",
    "sg:tags":[
        "live",
        "music"
    ],
    "wof:name":"Norris Entertainment",
    "wof:placetype":"venue"
},
  "geometry": {"coordinates":[-98.372238,29.525411],"type":"Point"}
}