{
  "type": "Feature",
  "properties": {
    "iso:country":"US",
    "sg:address":"815 W Wall St",
    "sg:city":"Grapevine",
    "sg:classifiers":[
        {
            "category":"Building & Trades",
            "subcategory":"Construction",
            "type":"Services"
        }
    ],
    "sg:phone":"+1 817 424 3261",
    "sg:postcode":"76051",
    "sg:province":"TX",
    "sg:tags":[
        "acoustical",
        "contractor"
    ],
    "wof:name":"J W Fox Sales",
    "wof:placetype":"venue"
},
  "geometry": {"coordinates":[-97.08577,32.940057],"type":"Point"}
}