{
  "type": "Feature",
  "properties": {
    "iso:country":"US",
    "sg:address":"6404 State Hwy 78",
    "sg:city":"Sachse",
    "sg:classifiers":[
        {
            "category":"Real Estate",
            "subcategory":"Real Estate Agent",
            "type":"Services"
        }
    ],
    "sg:phone":"+1 972 675 8884",
    "sg:postcode":"75048",
    "sg:province":"TX",
    "wof:name":"Prescourt Properties",
    "wof:placetype":"venue"
},
  "geometry": {"coordinates":[-96.592409,32.978223],"type":"Point"}
}