{
  "type": "Feature",
  "properties": {
    "iso:country":"US",
    "sg:address":"1301 E 4th St",
    "sg:city":"Austin",
    "sg:classifiers":[
        {
            "category":"Freight",
            "type":"Transportation"
        },
        {
            "category":"Manufacturing",
            "subcategory":"Motor Vehicles & Parts",
            "type":"Manufacturing & Wholesale Goods"
        }
    ],
    "sg:phone":"+1 512 477 8824",
    "sg:postcode":"78702",
    "sg:province":"TX",
    "sg:tags":[
        "equipment",
        "carriage",
        "mfg"
    ],
    "wof:name":"Rose Die Gelbe Carriage",
    "wof:placetype":"venue"
},
  "geometry": {"coordinates":[-97.729373,30.261891],"type":"Point"}
}