{
  "type": "Feature",
  "properties": {
    "iso:country":"US",
    "sg:address":"1106 E Expy 83",
    "sg:city":"Pharr",
    "sg:classifiers":[
        {
            "category":"Building & Trades",
            "subcategory":"Equipment Rental",
            "type":"Services"
        }
    ],
    "sg:phone":"+1 956 781 6011",
    "sg:postcode":"78577",
    "sg:province":"TX",
    "sg:tags":[
        "oil",
        "well",
        "supply"
    ],
    "wof:name":"Baker Service Tools Inc",
    "wof:placetype":"venue"
},
  "geometry": {"coordinates":[-98.169297,26.204639],"type":"Point"}
}