{
  "type": "Feature",
  "properties": {
    "iso:country":"US",
    "sg:address":"925 Coronado Blvd",
    "sg:city":"Universal City",
    "sg:classifiers":[
        {
            "category":"Professional",
            "subcategory":"Management & Consulting",
            "type":"Services"
        }
    ],
    "sg:phone":"+1 210 658 2727",
    "sg:postcode":"78148",
    "sg:province":"TX",
    "sg:tags":[
        "consultant",
        "educational"
    ],
    "sg:website":"www.baotraining.com",
    "wof:name":"Boeing Co",
    "wof:placetype":"venue"
},
  "geometry": {"coordinates":[-98.31598099999999,29.556094],"type":"Point"}
}