{
  "type": "Feature",
  "properties": {
    "iso:country":"US",
    "sg:address":"670 W Campbell Rd",
    "sg:city":"Richardson",
    "sg:classifiers":[
        {
            "category":"Health Services",
            "subcategory":"Doctor",
            "type":"Services"
        }
    ],
    "sg:phone":"+1 972 898 2683",
    "sg:postcode":"75080",
    "sg:province":"TX",
    "sg:tags":[
        "dentist"
    ],
    "wof:name":"Rupande Patel DDS",
    "wof:placetype":"venue"
},
  "geometry": {"coordinates":[-96.740707,32.978136],"type":"Point"}
}