{
  "type": "Feature",
  "properties": {
    "iso:country":"US",
    "sg:address":"7457 McCart Ave",
    "sg:city":"Fort Worth",
    "sg:classifiers":[
        {
            "category":"Health Services",
            "subcategory":"Optometrist",
            "type":"Services"
        }
    ],
    "sg:phone":"+1 817 346 3700",
    "sg:postcode":"76133",
    "sg:province":"TX",
    "wof:name":"Bz Buie OD",
    "wof:placetype":"venue"
},
  "geometry": {"coordinates":[-97.369856,32.636812],"type":"Point"}
}