{
  "type": "Feature",
  "properties": {
    "iso:country":"US",
    "sg:address":"273 W Broadview Dr",
    "sg:city":"San Antonio",
    "sg:classifiers":[
        {
            "category":"Manufacturing",
            "subcategory":"Printing",
            "type":"Manufacturing & Wholesale Goods"
        }
    ],
    "sg:phone":"+1 210 433 1377",
    "sg:postcode":"78228",
    "sg:province":"TX",
    "sg:tags":[
        "commercial"
    ],
    "wof:name":"DRS Graphics & Printing",
    "wof:placetype":"venue"
},
  "geometry": {"coordinates":[-98.57826,29.468103],"type":"Point"}
}