{
  "type": "Feature",
  "properties": {
    "iso:country":"US",
    "sg:address":"107 N Dixon St",
    "sg:city":"Gainesville",
    "sg:classifiers":[
        {
            "category":"Real Estate",
            "subcategory":"Surveying",
            "type":"Services"
        }
    ],
    "sg:phone":"+1 940 665 1914",
    "sg:postcode":"76240",
    "sg:province":"TX",
    "sg:tags":[
        "surveyor"
    ],
    "wof:name":"Delbert W West Land Surveyor",
    "wof:placetype":"venue"
},
  "geometry": {"coordinates":[-97.145387,33.624969],"type":"Point"}
}