{
  "type": "Feature",
  "properties": {
    "iso:country":"US",
    "sg:address":"185 Honey Bee Ln",
    "sg:city":"Brownsville",
    "sg:classifiers":[
        {
            "category":"Shopping",
            "subcategory":"Gifts & Souvenirs",
            "type":"Retail Goods"
        }
    ],
    "sg:phone":"+1 956 592 6455",
    "sg:postcode":"78520",
    "sg:province":"TX",
    "sg:tags":[
        "shop"
    ],
    "wof:name":"Mario's World's Gift Shop",
    "wof:placetype":"venue"
},
  "geometry": {"coordinates":[-97.515698,25.952342],"type":"Point"}
}