{
  "type": "Feature",
  "properties": {
    "iso:country":"US",
    "sg:address":"4313 Ken Michael Ct",
    "sg:city":"Fort Worth",
    "sg:classifiers":[
        {
            "category":"Professional",
            "subcategory":"Business Services",
            "type":"Services"
        }
    ],
    "sg:phone":"+1 817 428 0856",
    "sg:postcode":"76180",
    "sg:province":"TX",
    "wof:name":"JM Southwest Enterprise",
    "wof:placetype":"venue"
},
  "geometry": {"coordinates":[-97.222899,32.833262],"type":"Point"}
}