{
  "type": "Feature",
  "properties": {
    "iso:country":"US",
    "sg:address":"8807 Grand Lake Estates Dr",
    "sg:city":"Montgomery",
    "sg:classifiers":[
        {
            "category":"Home & Garden",
            "subcategory":"Building Materials",
            "type":"Retail Goods"
        }
    ],
    "sg:phone":"+1 936 447 6000",
    "sg:postcode":"77316",
    "sg:province":"TX",
    "sg:tags":[
        "glass",
        "window",
        "plate"
    ],
    "wof:name":"Kent Glass Art",
    "wof:placetype":"venue"
},
  "geometry": {"coordinates":[-95.64038499999999,30.280275],"type":"Point"}
}