{
  "type": "Feature",
  "properties": {
    "iso:country":"US",
    "sg:address":"5221 N O Connor Blvd",
    "sg:city":"Irving",
    "sg:classifiers":[
        {
            "category":"Professional",
            "subcategory":"Accounting & Tax Preparation",
            "type":"Services"
        }
    ],
    "sg:phone":"+1 972 791 5900",
    "sg:postcode":"75039",
    "sg:province":"TX",
    "sg:tags":[
        "company",
        "holding"
    ],
    "wof:name":"GTE International Incorporated",
    "wof:placetype":"venue"
},
  "geometry": {"coordinates":[-96.940048,32.869826],"type":"Point"}
}