{
  "type": "Feature",
  "properties": {
    "iso:country":"US",
    "sg:address":"7636 Pebble Dr",
    "sg:city":"Fort Worth",
    "sg:classifiers":[
        {
            "category":"Professional",
            "subcategory":"Engineering",
            "type":"Services"
        }
    ],
    "sg:phone":"+1 817 284 9400",
    "sg:postcode":"76118",
    "sg:province":"TX",
    "wof:name":"CMJ Engineering Inc",
    "wof:placetype":"venue"
},
  "geometry": {"coordinates":[-97.216224,32.792854],"type":"Point"}
}