{
  "type": "Feature",
  "properties": {
    "iso:country":"US",
    "sg:address":"5525 Burnet Rd",
    "sg:city":"Austin",
    "sg:classifiers":[
        {
            "category":"Arts & Performance",
            "subcategory":"Arts Center",
            "type":"Entertainment"
        },
        {
            "category":"Sports & Exercise",
            "subcategory":"Playing Field",
            "type":"Entertainment"
        }
    ],
    "sg:phone":"+1 512 371 1213",
    "sg:postcode":"78756",
    "sg:province":"TX",
    "sg:tags":[
        "performing",
        "instruction",
        "fitness"
    ],
    "sg:website":"www.slavinnadalballet.com/",
    "wof:name":"Slavin Nadal School of Ballet",
    "wof:placetype":"venue"
},
  "geometry": {"coordinates":[-97.74009700000001,30.3307],"type":"Point"}
}