{
  "type": "Feature",
  "properties": {
    "iso:country":"US",
    "sg:address":"10218 Red Maple Dr",
    "sg:city":"Dallas",
    "sg:classifiers":[
        {
            "category":"Home & Garden",
            "subcategory":"Home Furnishings",
            "type":"Retail Goods"
        }
    ],
    "sg:phone":"+1 972 296 3776",
    "sg:postcode":"75249",
    "sg:province":"TX",
    "sg:tags":[
        "candle"
    ],
    "wof:name":"Touch Of Tenderness",
    "wof:placetype":"venue"
},
  "geometry": {"coordinates":[-96.946806,32.623484],"type":"Point"}
}