{
  "type": "Feature",
  "properties": {
    "iso:country":"US",
    "sg:address":"198 E Robertson St",
    "sg:city":"San Benito",
    "sg:classifiers":[
        {
            "category":"Bars & Pubs",
            "type":"Food & Drink"
        }
    ],
    "sg:phone":"+1 956 361 3696",
    "sg:postcode":"78586",
    "sg:province":"TX",
    "sg:tags":[
        "drinking"
    ],
    "wof:name":"Somewhere In Time",
    "wof:placetype":"venue"
},
  "geometry": {"coordinates":[-97.63277100000001,26.130733],"type":"Point"}
}