{
  "type": "Feature",
  "properties": {
    "iso:country":"US",
    "sg:address":"480 S Dickinson Dr",
    "sg:city":"Rusk",
    "sg:classifiers":[
        {
            "category":"Home & Garden",
            "subcategory":"Building Materials",
            "type":"Retail Goods"
        }
    ],
    "sg:phone":"+1 903 683 2637",
    "sg:postcode":"75785",
    "sg:province":"TX",
    "wof:name":"Ameri-Tech Portable Buildings",
    "wof:placetype":"venue"
},
  "geometry": {"coordinates":[-95.128512,31.786878],"type":"Point"}
}