{
  "type": "Feature",
  "properties": {
    "iso:country":"US",
    "sg:address":"1126 Perry St",
    "sg:city":"Irving",
    "sg:classifiers":[
        {
            "category":"Real Estate",
            "subcategory":"Real Estate Operator",
            "type":"Services"
        }
    ],
    "sg:phone":"+1 214 596 0033",
    "sg:postcode":"75060",
    "sg:province":"TX",
    "sg:tags":[
        "apartment"
    ],
    "wof:name":"Sun Valley Apartments",
    "wof:placetype":"venue"
},
  "geometry": {"coordinates":[-96.93246600000001,32.813001],"type":"Point"}
}