{
  "type": "Feature",
  "properties": {
    "iso:country":"US",
    "sg:address":"11471 Co Rd 213",
    "sg:city":"Forney",
    "sg:classifiers":[
        {
            "category":"Building & Trades",
            "subcategory":"Pest Control",
            "type":"Services"
        }
    ],
    "sg:phone":"+1 972 564 1657",
    "sg:postcode":"75126",
    "sg:province":"TX",
    "wof:name":"All Time Pest Control",
    "wof:placetype":"venue"
},
  "geometry": {"coordinates":[-96.403413,32.720928],"type":"Point"}
}