{
  "type": "Feature",
  "properties": {
    "iso:country":"US",
    "sg:address":"506 Grant St",
    "sg:city":"Roma",
    "sg:classifiers":[
        {
            "category":"Shopping",
            "subcategory":"Clothing, Apparel, & Fashions",
            "type":"Retail Goods"
        }
    ],
    "sg:phone":"+1 956 849 2706",
    "sg:postcode":"78584",
    "sg:province":"TX",
    "wof:name":"Acapulco Stores",
    "wof:placetype":"venue"
},
  "geometry": {"coordinates":[-99.00392600000001,26.401685],"type":"Point"}
}