{
  "type": "Feature",
  "properties": {
    "iso:country":"US",
    "sg:address":"3216 Press Rd",
    "sg:city":"Nacogdoches",
    "sg:classifiers":[
        {
            "category":"Building & Trades",
            "subcategory":"Construction",
            "type":"Services"
        }
    ],
    "sg:phone":"+1 409 560 9859",
    "sg:postcode":"75964",
    "sg:province":"TX",
    "sg:tags":[
        "concrete",
        "contractor"
    ],
    "wof:name":"Sparks Concrete Construction",
    "wof:placetype":"venue"
},
  "geometry": {"coordinates":[-94.65797499999999,31.5776],"type":"Point"}
}