{
  "type": "Feature",
  "properties": {
    "iso:country":"US",
    "sg:address":"5415 Cameron Road",
    "sg:city":"Austin",
    "sg:classifiers":[
        {
            "category":"Restaurant",
            "type":"Food & Drink"
        }
    ],
    "sg:postcode":"78723",
    "sg:province":"TX",
    "sg:tags":[
        "mexican"
    ],
    "wof:name":"Tortas El Guero",
    "wof:placetype":"venue"
},
  "geometry": {"coordinates":[-97.70518800000001,30.31228],"type":"Point"}
}