{
  "type": "Feature",
  "properties": {
    "iso:country":"US",
    "sg:address":"2201 Tin Top Rd",
    "sg:city":"Weatherford",
    "sg:classifiers":[
        {
            "category":"Home & Garden",
            "subcategory":"Furniture",
            "type":"Retail Goods"
        },
        {
            "category":"Shopping",
            "subcategory":"Gifts & Souvenirs",
            "type":"Retail Goods"
        }
    ],
    "sg:phone":"+1 817 594 6873",
    "sg:postcode":"76086",
    "sg:province":"TX",
    "wof:name":"Lighthouse Furniture & ACC",
    "wof:placetype":"venue"
},
  "geometry": {"coordinates":[-97.79792500000001,32.727975],"type":"Point"}
}