{
  "type": "Feature",
  "properties": {
    "iso:country":"US",
    "sg:address":"222 S Montclair Ave",
    "sg:city":"Dallas",
    "sg:classifiers":[
        {
            "category":"Professional",
            "type":"Services"
        }
    ],
    "sg:phone":"+1 214 948 6108",
    "sg:postcode":"75208",
    "sg:province":"TX",
    "wof:name":"Itzcuintli Films Inc",
    "wof:placetype":"venue"
},
  "geometry": {"coordinates":[-96.846512,32.744228],"type":"Point"}
}