{
  "type": "Feature",
  "properties": {
    "iso:country":"US",
    "sg:address":"300 Water St",
    "sg:city":"Waxahachie",
    "sg:classifiers":[
        {
            "category":"Autos & Motor Vehicles",
            "subcategory":"Fuel & Gas Station",
            "type":"Retail Goods"
        }
    ],
    "sg:phone":"+1 972 937 1100",
    "sg:postcode":"75165",
    "sg:province":"TX",
    "sg:tags":[
        "station",
        "gasoline",
        "supply"
    ],
    "wof:name":"Tire Town",
    "wof:placetype":"venue"
},
  "geometry": {"coordinates":[-96.848438,32.38695],"type":"Point"}
}