{
  "type": "Feature",
  "properties": {
    "iso:country":"US",
    "sg:address":"2192 McPherson Dr",
    "sg:city":"Grapevine",
    "sg:classifiers":[
        {
            "category":"Building & Trades",
            "subcategory":"Construction",
            "type":"Services"
        }
    ],
    "sg:phone":"+1 512 238 0142",
    "sg:postcode":"76051",
    "sg:province":"TX",
    "sg:tags":[
        "hanging",
        "contractor"
    ],
    "wof:name":"Extraordinary Walls",
    "wof:placetype":"venue"
},
  "geometry": {"coordinates":[-97.103858,32.945647],"type":"Point"}
}