{
  "type": "Feature",
  "properties": {
    "iso:country":"US",
    "sg:address":"723 Main St",
    "sg:city":"Houston",
    "sg:classifiers":[
        {
            "category":"Personal",
            "type":"Services"
        }
    ],
    "sg:phone":"+1 713 223 2069",
    "sg:postcode":"77002",
    "sg:province":"TX",
    "sg:tags":[
        "document",
        "duplicating"
    ],
    "wof:name":"Docucenter",
    "wof:placetype":"venue"
},
  "geometry": {"coordinates":[-95.363564,29.758572],"type":"Point"}
}