{
  "type": "Feature",
  "properties": {
    "iso:country":"US",
    "sg:address":"201 W Heritage Dr",
    "sg:city":"Friendswood",
    "sg:classifiers":[
        {
            "category":"Professional",
            "subcategory":"Business Services",
            "type":"Services"
        }
    ],
    "sg:phone":"+1 281 992 9919",
    "sg:postcode":"77546",
    "sg:province":"TX",
    "wof:name":"Beacon Inspection Co",
    "wof:placetype":"venue"
},
  "geometry": {"coordinates":[-95.207346,29.529671],"type":"Point"}
}