{
  "type": "Feature",
  "properties": {
    "iso:country":"US",
    "sg:address":"1255 Corporate Dr",
    "sg:city":"Irving",
    "sg:classifiers":[
        {
            "category":"Professional",
            "subcategory":"Computer Services",
            "type":"Services"
        }
    ],
    "sg:phone":"+1 972 677 6000",
    "sg:postcode":"75038",
    "sg:province":"TX",
    "wof:name":"Genpass Service Solutions  LLC",
    "wof:placetype":"venue"
},
  "geometry": {"coordinates":[-96.96975,32.887488],"type":"Point"}
}