{
  "type": "Feature",
  "properties": {
    "iso:country":"US",
    "sg:address":"13101 Preston Rd",
    "sg:city":"Dallas",
    "sg:classifiers":[
        {
            "category":"Professional",
            "subcategory":"Advertising",
            "type":"Services"
        }
    ],
    "sg:phone":"+1 972 490 4949",
    "sg:postcode":"75240",
    "sg:province":"TX",
    "wof:name":"Radio Marketing Group Inc",
    "wof:placetype":"venue"
},
  "geometry": {"coordinates":[-96.803556,32.927363],"type":"Point"}
}