{
  "type": "Feature",
  "properties": {
    "iso:country":"US",
    "sg:address":"1201 Main St",
    "sg:city":"Dallas",
    "sg:classifiers":[
        {
            "category":"Deli",
            "type":"Food & Drink"
        }
    ],
    "sg:menulink":"http://www.allmenus.com/tx/northeast/126745-blimpie-subs--sandwiches/menu/",
    "sg:phone":"+1 214 698 0300",
    "sg:postcode":"75202",
    "sg:province":"TX",
    "sg:tags":[
        "wrap",
        "american",
        "sandwich"
    ],
    "wof:name":"Blimpie Subs & Sandwiches",
    "wof:placetype":"venue"
},
  "geometry": {"coordinates":[-96.80206200000001,32.780449],"type":"Point"}
}