{
  "type": "Feature",
  "properties": {
    "iso:country":"US",
    "sg:address":"3400 Cabriolet Ct",
    "sg:city":"Plano",
    "sg:classifiers":[
        {
            "category":"Professional",
            "subcategory":"Management & Consulting",
            "type":"Services"
        }
    ],
    "sg:phone":"+1 972 599 2833",
    "sg:postcode":"75023",
    "sg:province":"TX",
    "wof:name":"Management Alternatives",
    "wof:placetype":"venue"
},
  "geometry": {"coordinates":[-96.758831,33.054738],"type":"Point"}
}