{
  "type": "Feature",
  "properties": {
    "iso:country":"US",
    "sg:address":"111 S Wilson St",
    "sg:city":"Burleson",
    "sg:classifiers":[
        {
            "category":"Recreation",
            "subcategory":"Amusement Park",
            "type":"Entertainment"
        },
        {
            "category":"Shopping",
            "subcategory":"Bicycles & Sporting Goods",
            "type":"Retail Goods"
        }
    ],
    "sg:phone":"+1 817 295 3700",
    "sg:postcode":"76028",
    "sg:province":"TX",
    "wof:name":"Jamz Sports For Girls",
    "wof:placetype":"venue"
},
  "geometry": {"coordinates":[-97.321888,32.542684],"type":"Point"}
}