{
  "type": "Feature",
  "properties": {
    "iso:country":"US",
    "sg:address":"6316 Telephone Rd",
    "sg:city":"Houston",
    "sg:classifiers":[
        {
            "category":"Shopping",
            "subcategory":"Shoes",
            "type":"Retail Goods"
        }
    ],
    "sg:phone":"+1 713 242 0424",
    "sg:postcode":"77087",
    "sg:province":"TX",
    "sg:tags":[
        "store"
    ],
    "sg:website":"www.activeathletesports.com",
    "wof:name":"Active Athlete",
    "wof:placetype":"venue"
},
  "geometry": {"coordinates":[-95.28980300000001,29.675301],"type":"Point"}
}