{
  "type": "Feature",
  "properties": {
    "iso:country":"US",
    "sg:address":"521 E Baker St",
    "sg:city":"Brownwood",
    "sg:classifiers":[
        {
            "category":"Education",
            "subcategory":"School",
            "type":"Public Place"
        }
    ],
    "sg:phone":"+1 325 646 7447",
    "sg:postcode":"76801",
    "sg:province":"TX",
    "wof:name":"Brown County Schools",
    "wof:placetype":"venue"
},
  "geometry": {"coordinates":[-98.97884500000001,31.719481],"type":"Point"}
}