{
  "type": "Feature",
  "properties": {
    "iso:country":"US",
    "sg:address":"2908 West Ave",
    "sg:city":"San Antonio",
    "sg:classifiers":[
        {
            "category":"Personal",
            "subcategory":"Beauty Salon",
            "type":"Services"
        }
    ],
    "sg:phone":"+1 210 375 8450",
    "sg:postcode":"78201",
    "sg:province":"TX",
    "wof:name":"Rios Golden Cut",
    "wof:placetype":"venue"
},
  "geometry": {"coordinates":[-98.525902,29.487347],"type":"Point"}
}