{
  "type": "Feature",
  "properties": {
    "iso:country":"US",
    "sg:address":"1701 W Main St",
    "sg:city":"Gatesville",
    "sg:classifiers":[
        {
            "category":"Building & Trades",
            "subcategory":"Construction",
            "type":"Services"
        }
    ],
    "sg:phone":"+1 254 865 8686",
    "sg:postcode":"76528",
    "sg:province":"TX",
    "sg:tags":[
        "garage",
        "door",
        "installation"
    ],
    "wof:name":"J & S Garage Door Co",
    "wof:placetype":"venue"
},
  "geometry": {"coordinates":[-97.785709,31.433532],"type":"Point"}
}