{
  "type": "Feature",
  "properties": {
    "iso:country":"US",
    "sg:address":"1100 Nashua St",
    "sg:city":"Houston",
    "sg:classifiers":[
        {
            "category":"Professional",
            "type":"Services"
        }
    ],
    "sg:phone":"+1 281 333 4311",
    "sg:postcode":"77008",
    "sg:province":"TX",
    "wof:name":"North Star Information SE",
    "wof:placetype":"venue"
},
  "geometry": {"coordinates":[-95.41251099999999,29.792333],"type":"Point"}
}