{
  "type": "Feature",
  "properties": {
    "iso:country":"US",
    "sg:address":"9613 Co Rd 528",
    "sg:city":"Burleson",
    "sg:classifiers":[
        {
            "category":"Freight",
            "type":"Transportation"
        }
    ],
    "sg:phone":"+1 817 295 7343",
    "sg:postcode":"76028",
    "sg:province":"TX",
    "sg:tags":[
        "mover"
    ],
    "wof:name":"Addison Bailey's Rapid Movers",
    "wof:placetype":"venue"
},
  "geometry": {"coordinates":[-97.231143,32.523202],"type":"Point"}
}