{
  "type": "Feature",
  "properties": {
    "iso:country":"US",
    "sg:address":"1111 Executive Dr",
    "sg:city":"Coppell",
    "sg:classifiers":[
        {
            "category":"Freight",
            "type":"Transportation"
        }
    ],
    "sg:phone":"+1 972 471 3736",
    "sg:postcode":"75019",
    "sg:province":"TX",
    "sg:tags":[
        "warehouse",
        "general"
    ],
    "wof:name":"Meiko America Inc",
    "wof:placetype":"venue"
},
  "geometry": {"coordinates":[-96.99862299999999,32.940318],"type":"Point"}
}