{
  "type": "Feature",
  "properties": {
    "iso:country":"US",
    "sg:address":"4141 Valley Vw",
    "sg:city":"Lone Oak",
    "sg:classifiers":[
        {
            "category":"Autos & Motor Vehicles",
            "subcategory":"Auto Supplies",
            "type":"Retail Goods"
        }
    ],
    "sg:phone":"+1 903 447 5871",
    "sg:postcode":"75453",
    "sg:province":"TX",
    "sg:tags":[
        "product",
        "mfg"
    ],
    "wof:name":"Fetty Racing Products",
    "wof:placetype":"venue"
},
  "geometry": {"coordinates":[-95.974464,32.942529],"type":"Point"}
}