{
  "type": "Feature",
  "properties": {
    "iso:country":"US",
    "sg:address":"14643 Dallas Pkwy Ste 880",
    "sg:city":"Dallas",
    "sg:classifiers":[
        {
            "category":"Professional",
            "subcategory":"Employment Agencies",
            "type":"Services"
        }
    ],
    "sg:phone":"+1 972 392 3163",
    "sg:postcode":"75254",
    "sg:province":"TX",
    "wof:name":"Talent Tree",
    "wof:placetype":"venue"
},
  "geometry": {"coordinates":[-96.823744,32.947261],"type":"Point"}
}