{
  "type": "Feature",
  "properties": {
    "iso:country":"US",
    "sg:address":"555 Funston Pl",
    "sg:city":"San Antonio",
    "sg:classifiers":[
        {
            "category":"Restaurant",
            "type":"Food & Drink"
        }
    ],
    "sg:phone":"+1 210 821 6447",
    "sg:postcode":"78209",
    "sg:province":"TX",
    "sg:tags":[
        "party",
        "private",
        "caterer"
    ],
    "wof:name":"Carriage House Kitchen",
    "wof:placetype":"venue"
},
  "geometry": {"coordinates":[-98.457272,29.457696],"type":"Point"}
}