{
  "type": "Feature",
  "properties": {
    "iso:country":"US",
    "sg:address":"5015 Westheimer Rd",
    "sg:city":"Houston",
    "sg:classifiers":[
        {
            "category":"Wholesale",
            "subcategory":"Jewelry",
            "type":"Manufacturing & Wholesale Goods"
        }
    ],
    "sg:phone":"+1 713 572 2557",
    "sg:postcode":"77056",
    "sg:province":"TX",
    "sg:tags":[
        "stone"
    ],
    "wof:name":"Christofle",
    "wof:placetype":"venue"
},
  "geometry": {"coordinates":[-95.461484,29.740679],"type":"Point"}
}