{
  "type": "Feature",
  "properties": {
    "iso:country":"US",
    "sg:address":"1829 Anna Dr",
    "sg:city":"Irving",
    "sg:classifiers":[
        {
            "category":"Health Services",
            "subcategory":"Nursing And Care Facility",
            "type":"Services"
        }
    ],
    "sg:phone":"+1 972 445 2250",
    "sg:postcode":"75061",
    "sg:province":"TX",
    "wof:name":"Volunteers of America",
    "wof:placetype":"venue"
},
  "geometry": {"coordinates":[-96.919528,32.828938],"type":"Point"}
}