{
  "type": "Feature",
  "properties": {
    "iso:country":"US",
    "sg:address":"3107 Manor Rd",
    "sg:city":"Austin",
    "sg:classifiers":[
        {
            "category":"Retail",
            "subcategory":"Auto Repair",
            "type":"Services"
        }
    ],
    "sg:phone":"+1 512 385 2638",
    "sg:postcode":"78723",
    "sg:province":"TX",
    "sg:tags":[
        "body",
        "automotive",
        "general"
    ],
    "wof:name":"Superior Automotive",
    "wof:placetype":"venue"
},
  "geometry": {"coordinates":[-97.70535,30.286346],"type":"Point"}
}