{
  "type": "Feature",
  "properties": {
    "iso:country":"US",
    "sg:address":"6918 Canyon Way Dr",
    "sg:city":"Houston",
    "sg:classifiers":[
        {
            "category":"Building & Trades",
            "subcategory":"Landscaping Services",
            "type":"Services"
        }
    ],
    "sg:phone":"+1 281 999 4272",
    "sg:postcode":"77086",
    "sg:province":"TX",
    "wof:name":"Abloom Creative Landscaping",
    "wof:placetype":"venue"
},
  "geometry": {"coordinates":[-95.487955,29.933599],"type":"Point"}
}