{
  "type": "Feature",
  "properties": {
    "iso:country":"US",
    "sg:address":"814 N Polk St",
    "sg:city":"Beeville",
    "sg:classifiers":[
        {
            "category":"Organizations",
            "subcategory":"Religious Organization",
            "type":"Services"
        }
    ],
    "sg:phone":"+1 361 358 3091",
    "sg:postcode":"78102",
    "sg:province":"TX",
    "sg:tags":[
        "church"
    ],
    "wof:name":"Seventh Day Adventist",
    "wof:placetype":"venue"
},
  "geometry": {"coordinates":[-97.745566,28.412913],"type":"Point"}
}