{
  "type": "Feature",
  "properties": {
    "iso:country":"US",
    "sg:address":"1800 S I- 27",
    "sg:city":"Plainview",
    "sg:classifiers":[
        {
            "category":"Organizations",
            "subcategory":"Religious Organization",
            "type":"Services"
        }
    ],
    "sg:phone":"+1 806 293 2521",
    "sg:postcode":"79072",
    "sg:province":"TX",
    "wof:name":"First Christian Church",
    "wof:placetype":"venue"
},
  "geometry": {"coordinates":[-101.75018300000001,34.193414],"type":"Point"}
}