{
  "type": "Feature",
  "properties": {
    "iso:country":"US",
    "sg:address":"214 N Main St",
    "sg:city":"Henrietta",
    "sg:classifiers":[
        {
            "category":"Food & Beverages",
            "subcategory":"Groceries & Convenience Stores",
            "type":"Retail Goods"
        }
    ],
    "sg:phone":"+1 940 538 4941",
    "sg:postcode":"76365",
    "sg:province":"TX",
    "sg:tags":[
        "grocer"
    ],
    "wof:name":"Clayton Grocery",
    "wof:placetype":"venue"
},
  "geometry": {"coordinates":[-98.196243,33.81717],"type":"Point"}
}