{
  "type": "Feature",
  "properties": {
    "iso:country":"US",
    "sg:address":"3801 Adam Grubb St",
    "sg:city":"Fort Worth",
    "sg:classifiers":[
        {
            "category":"Education",
            "subcategory":"Library",
            "type":"Public Place"
        }
    ],
    "sg:phone":"+1 817 237 9681",
    "sg:postcode":"76135",
    "sg:province":"TX",
    "sg:tags":[
        "executive"
    ],
    "wof:name":"Lake Worth Public Library",
    "wof:placetype":"venue"
},
  "geometry": {"coordinates":[-97.436064,32.810404],"type":"Point"}
}