{
  "type": "Feature",
  "properties": {
    "iso:country":"US",
    "sg:address":"466 FM 196",
    "sg:city":"Pattonville",
    "sg:classifiers":[
        {
            "category":"Education",
            "subcategory":"School",
            "type":"Public Place"
        }
    ],
    "sg:phone":"+1 903 652 6476",
    "sg:postcode":"75416",
    "sg:province":"TX",
    "wof:name":"Prairieland Ind Schl Dst ADM",
    "wof:placetype":"venue"
},
  "geometry": {"coordinates":[-95.382276,33.658644],"type":"Point"}
}