{
  "type": "Feature",
  "properties": {
    "iso:country":"US",
    "sg:address":"5925 Kirby Dr",
    "sg:city":"Houston",
    "sg:classifiers":[
        {
            "category":"Real Estate",
            "subcategory":"Architect",
            "type":"Services"
        }
    ],
    "sg:phone":"+1 713 522 8825",
    "sg:postcode":"77005",
    "sg:province":"TX",
    "wof:name":"Bill May",
    "wof:placetype":"venue"
},
  "geometry": {"coordinates":[-95.41839,29.718442],"type":"Point"}
}