{
  "type": "Feature",
  "properties": {
    "iso:country":"US",
    "sg:address":"1401 Preston Rd NW Corner of Preston at Plano Pkwy",
    "sg:city":"Plano",
    "sg:classifiers":[
        {
            "category":"Restaurant",
            "type":"Food & Drink"
        }
    ],
    "sg:phone":"+1 972 818 2727",
    "sg:postcode":"75086",
    "sg:province":"TX",
    "sg:tags":[
        "tex-mex"
    ],
    "sg:website":"www.lunadenochetexmex.com",
    "wof:name":"Luna de Noche",
    "wof:placetype":"venue"
},
  "geometry": {"coordinates":[-96.795349,33.01827],"type":"Point"}
}