{
  "type": "Feature",
  "properties": {
    "iso:country":"US",
    "sg:address":"5556 US Hwy 87",
    "sg:city":"San Angelo",
    "sg:classifiers":[
        {
            "category":"Personal",
            "type":"Services"
        }
    ],
    "sg:phone":"+1 325 659 4531",
    "sg:postcode":"76901",
    "sg:province":"TX",
    "wof:name":"Concho Valley Quilters Guild",
    "wof:placetype":"venue"
},
  "geometry": {"coordinates":[-100.486463,31.527149],"type":"Point"}
}