{
  "type": "Feature",
  "properties": {
    "iso:country":"US",
    "sg:address":"6828 College St",
    "sg:city":"Beaumont",
    "sg:classifiers":[
        {
            "category":"Retail",
            "subcategory":"Auto Repair",
            "type":"Services"
        }
    ],
    "sg:phone":"+1 409 866 5433",
    "sg:postcode":"77707",
    "sg:province":"TX",
    "sg:tags":[
        "general"
    ],
    "wof:name":"Progressive Automotive",
    "wof:placetype":"venue"
},
  "geometry": {"coordinates":[-94.17083599999999,30.067739],"type":"Point"}
}