{
  "type": "Feature",
  "properties": {
    "iso:country":"US",
    "sg:address":"1740 San Jacinto Mall",
    "sg:city":"Baytown",
    "sg:classifiers":[
        {
            "category":"Shopping",
            "subcategory":"Gifts & Souvenirs",
            "type":"Retail Goods"
        }
    ],
    "sg:phone":"+1 281 421 8747",
    "sg:postcode":"77521",
    "sg:province":"TX",
    "sg:tags":[
        "shop"
    ],
    "wof:name":"Googleheim",
    "wof:placetype":"venue"
},
  "geometry": {"coordinates":[-94.985859,29.803263],"type":"Point"}
}