{
  "type": "Feature",
  "properties": {
    "iso:country":"US",
    "sg:address":"8028 Fredericksburg Rd",
    "sg:city":"San Antonio",
    "sg:classifiers":[
        {
            "category":"Restaurant",
            "type":"Food & Drink"
        }
    ],
    "sg:phone":"+1 210 692 7333",
    "sg:postcode":"78229",
    "sg:province":"TX",
    "wof:name":"Mexican Taco Restaurant",
    "wof:placetype":"venue"
},
  "geometry": {"coordinates":[-98.56956599999999,29.513384],"type":"Point"}
}