{
  "type": "Feature",
  "properties": {
    "iso:country":"US",
    "sg:address":"3400 Silverstone Dr",
    "sg:city":"Plano",
    "sg:classifiers":[
        {
            "category":"Professional",
            "subcategory":"Management & Consulting",
            "type":"Services"
        },
        {
            "category":"Insurance",
            "subcategory":"Insurance Agent",
            "type":"Services"
        }
    ],
    "sg:phone":"+1 972 964 7028",
    "sg:postcode":"75023",
    "sg:province":"TX",
    "wof:name":"Graves Financial Resources",
    "wof:placetype":"venue"
},
  "geometry": {"coordinates":[-96.735913,33.041078],"type":"Point"}
}