{
  "type": "Feature",
  "properties": {
    "iso:country":"US",
    "sg:address":"390 Cottle Town Rd",
    "sg:city":"Smithville",
    "sg:classifiers":[
        {
            "category":"Mining & Drilling",
            "type":"Manufacturing & Wholesale Goods"
        }
    ],
    "sg:phone":"+1 512 237 2655",
    "sg:postcode":"78957",
    "sg:province":"TX",
    "sg:tags":[
        "field",
        "oil"
    ],
    "wof:name":"Texwis Inc",
    "wof:placetype":"venue"
},
  "geometry": {"coordinates":[-97.19750999999999,30.081234],"type":"Point"}
}