{
  "type": "Feature",
  "properties": {
    "iso:country":"US",
    "sg:address":"2613 Kimberly Dr",
    "sg:city":"Grapevine",
    "sg:classifiers":[
        {
            "category":"Communications",
            "subcategory":"Film & Video Production",
            "type":"Services"
        }
    ],
    "sg:phone":"+1 817 481 6882",
    "sg:postcode":"76051",
    "sg:province":"TX",
    "sg:tags":[
        "motion"
    ],
    "wof:name":"Rawhide Productions",
    "wof:placetype":"venue"
},
  "geometry": {"coordinates":[-97.102508,32.967329],"type":"Point"}
}