{
  "type": "Feature",
  "properties": {
    "iso:country":"US",
    "sg:address":"465 Uvalde Rd",
    "sg:city":"Houston",
    "sg:classifiers":[
        {
            "category":"Shopping",
            "type":"Retail Goods"
        },
        {
            "category":"Shopping",
            "subcategory":"Beauty & Cosmetics",
            "type":"Retail Goods"
        }
    ],
    "sg:phone":"+1 713 455 6995",
    "sg:postcode":"77015",
    "sg:province":"TX",
    "sg:tags":[
        "perfume"
    ],
    "wof:name":"Merle Norman Cosmetic & Nail",
    "wof:placetype":"venue"
},
  "geometry": {"coordinates":[-95.18685499999999,29.790934],"type":"Point"}
}