{
  "type": "Feature",
  "properties": {
    "iso:country":"US",
    "sg:address":"317 Redbud Ave",
    "sg:city":"Mcallen",
    "sg:classifiers":[
        {
            "category":"Wholesale",
            "subcategory":"Machinery & Supplies",
            "type":"Manufacturing & Wholesale Goods"
        }
    ],
    "sg:phone":"+1 956 630 1027",
    "sg:postcode":"78504",
    "sg:province":"TX",
    "sg:tags":[
        "industrial"
    ],
    "wof:name":"Mgr Sales",
    "wof:placetype":"venue"
},
  "geometry": {"coordinates":[-98.21652,26.241547],"type":"Point"}
}