{
  "type": "Feature",
  "properties": {
    "iso:country":"US",
    "sg:address":"7500 San Felipe St Ste 335",
    "sg:city":"Houston",
    "sg:classifiers":[
        {
            "category":"Professional",
            "subcategory":"Lawyer & Legal Services",
            "type":"Services"
        }
    ],
    "sg:phone":"+1 713 621 8185",
    "sg:postcode":"77063",
    "sg:province":"TX",
    "wof:name":"Moore R Michael Atty",
    "wof:placetype":"venue"
},
  "geometry": {"coordinates":[-95.50242799999999,29.751257],"type":"Point"}
}