{
  "type": "Feature",
  "properties": {
    "iso:country":"US",
    "sg:address":"300 US Hwy 96",
    "sg:city":"Buna",
    "sg:classifiers":[
        {
            "category":"Shopping",
            "subcategory":"Used Merchandise",
            "type":"Retail Goods"
        }
    ],
    "sg:phone":"+1 409 994 3524",
    "sg:postcode":"77657",
    "sg:province":"TX",
    "sg:tags":[
        "pawnbroker"
    ],
    "wof:name":"Buna Pawn & Loan",
    "wof:placetype":"venue"
},
  "geometry": {"coordinates":[-94.19830399999999,30.257019],"type":"Point"}
}