{
  "type": "Feature",
  "properties": {
    "iso:country":"US",
    "sg:address":"12702 Old Oaks Dr",
    "sg:city":"Houston",
    "sg:classifiers":[
        {
            "category":"Professional",
            "type":"Services"
        }
    ],
    "sg:phone":"+1 713 647 9923",
    "sg:postcode":"77024",
    "sg:province":"TX",
    "wof:name":"Agroenlineacom Inc",
    "wof:placetype":"venue"
},
  "geometry": {"coordinates":[-95.557856,29.769906],"type":"Point"}
}