{
  "type": "Feature",
  "properties": {
    "iso:country":"US",
    "sg:address":"1711 Skinner Rd",
    "sg:city":"Houston",
    "sg:classifiers":[
        {
            "category":"Banks & Credit Unions",
            "subcategory":"Financial Services",
            "type":"Services"
        }
    ],
    "sg:phone":"+1 713 697 3980",
    "sg:postcode":"77093",
    "sg:province":"TX",
    "sg:tags":[
        "investor"
    ],
    "wof:name":"IPC Venture Co",
    "wof:placetype":"venue"
},
  "geometry": {"coordinates":[-95.35813,29.867358],"type":"Point"}
}