{
  "type": "Feature",
  "properties": {
    "iso:country":"US",
    "sg:address":"6330 Lakeshore Dr",
    "sg:city":"Dallas",
    "sg:classifiers":[
        {
            "category":"Banks & Credit Unions",
            "subcategory":"Investment Brokerage",
            "type":"Services"
        }
    ],
    "sg:phone":"+1 214 827 6803",
    "sg:postcode":"75214",
    "sg:province":"TX",
    "sg:tags":[
        "advisory",
        "financial"
    ],
    "wof:name":"Ethic Financial Group",
    "wof:placetype":"venue"
},
  "geometry": {"coordinates":[-96.75375,32.819006],"type":"Point"}
}