{
  "type": "Feature",
  "properties": {
    "iso:country":"US",
    "sg:address":"10655 Richmond Ave",
    "sg:city":"Houston",
    "sg:classifiers":[
        {
            "category":"Building & Trades",
            "subcategory":"Plumbing",
            "type":"Services"
        }
    ],
    "sg:phone":"+1 713 339 4007",
    "sg:postcode":"77042",
    "sg:province":"TX",
    "wof:name":"Tac Americas Inc",
    "wof:placetype":"venue"
},
  "geometry": {"coordinates":[-95.56262,29.727533],"type":"Point"}
}