{
  "type": "Feature",
  "properties": {
    "iso:country":"US",
    "sg:address":"11010 Wallisville Rd",
    "sg:city":"Houston",
    "sg:classifiers":[
        {
            "category":"Manufacturing",
            "subcategory":"Metals",
            "type":"Manufacturing & Wholesale Goods"
        }
    ],
    "sg:phone":"+1 713 676 0085",
    "sg:postcode":"77013",
    "sg:province":"TX",
    "sg:tags":[
        "product",
        "metalwork",
        "sheet",
        "mfg"
    ],
    "wof:name":"Power Lone Star Inc",
    "wof:placetype":"venue"
},
  "geometry": {"coordinates":[-95.244163,29.794964],"type":"Point"}
}