{
  "type": "Feature",
  "properties": {
    "iso:country":"US",
    "sg:address":"1126 S Padre Island Dr",
    "sg:city":"Corpus Christi",
    "sg:classifiers":[
        {
            "category":"Recreation",
            "type":"Entertainment"
        }
    ],
    "sg:phone":"+1 361 854 8866",
    "sg:postcode":"78416",
    "sg:province":"TX",
    "sg:tags":[
        "guide"
    ],
    "wof:name":"Offshore Willie's Charters",
    "wof:placetype":"venue"
},
  "geometry": {"coordinates":[-97.44780900000001,27.746153],"type":"Point"}
}