{
  "type": "Feature",
  "properties": {
    "iso:country":"US",
    "sg:address":"433 W I- 30",
    "sg:city":"Garland",
    "sg:classifiers":[
        {
            "category":"Food & Beverages",
            "subcategory":"Groceries & Convenience Stores",
            "type":"Retail Goods"
        }
    ],
    "sg:phone":"+1 972 240 4403",
    "sg:postcode":"75043",
    "sg:province":"TX",
    "wof:name":"Unique Indian Stores",
    "wof:placetype":"venue"
},
  "geometry": {"coordinates":[-96.59123099999999,32.842381],"type":"Point"}
}