{
  "type": "Feature",
  "properties": {
    "iso:country":"US",
    "sg:address":"211 Winnsboro St",
    "sg:city":"Quitman",
    "sg:classifiers":[
        {
            "category":"Building & Trades",
            "subcategory":"Electrical",
            "type":"Services"
        }
    ],
    "sg:phone":"+1 903 763 4644",
    "sg:postcode":"75783",
    "sg:province":"TX",
    "sg:tags":[
        "electric",
        "contractor"
    ],
    "wof:name":"Medlin Electric Inc",
    "wof:placetype":"venue"
},
  "geometry": {"coordinates":[-95.44301900000001,32.798554],"type":"Point"}
}