{
  "type": "Feature",
  "properties": {
    "iso:country":"US",
    "sg:address":"210 W 4th St",
    "sg:city":"Denver City",
    "sg:classifiers":[
        {
            "category":"Organizations",
            "subcategory":"Religious Organization",
            "type":"Services"
        }
    ],
    "sg:phone":"+1 806 592 2516",
    "sg:postcode":"79323",
    "sg:province":"TX",
    "wof:name":"First United Methodist Church",
    "wof:placetype":"venue"
},
  "geometry": {"coordinates":[-102.83069500000001,32.967973],"type":"Point"}
}