{
  "type": "Feature",
  "properties": {
    "iso:country":"US",
    "sg:address":"330 Bartlett Dr",
    "sg:city":"El Paso",
    "sg:classifiers":[
        {
            "category":"Professional",
            "subcategory":"Management & Consulting",
            "type":"Services"
        }
    ],
    "sg:phone":"+1 915 533 6900",
    "sg:postcode":"79912",
    "sg:province":"TX",
    "wof:name":"Tower Square Securities Inc",
    "wof:placetype":"venue"
},
  "geometry": {"coordinates":[-106.56732100000001,31.844786],"type":"Point"}
}