{
  "type": "Feature",
  "properties": {
    "iso:country":"US",
    "sg:address":"842 E Jefferson Blvd",
    "sg:city":"Dallas",
    "sg:classifiers":[
        {
            "category":"Food & Beverages",
            "subcategory":"Groceries & Convenience Stores",
            "type":"Retail Goods"
        }
    ],
    "sg:phone":"+1 214 948 7970",
    "sg:postcode":"75203",
    "sg:province":"TX",
    "wof:name":"Bair's In & Out Convenience Store",
    "wof:placetype":"venue"
},
  "geometry": {"coordinates":[-96.811886,32.750224],"type":"Point"}
}