{
  "type": "Feature",
  "properties": {
    "iso:country":"US",
    "sg:address":"10611 Huntington Dale Dr",
    "sg:city":"Houston",
    "sg:classifiers":[
        {
            "category":"Professional",
            "subcategory":"Detective & Security Services",
            "type":"Services"
        }
    ],
    "sg:phone":"+1 281 530 9035",
    "sg:postcode":"77099",
    "sg:province":"TX",
    "sg:tags":[
        "car"
    ],
    "wof:name":"David W Brown Investigation",
    "wof:placetype":"venue"
},
  "geometry": {"coordinates":[-95.60565800000001,29.663558],"type":"Point"}
}