{
  "type": "Feature",
  "properties": {
    "iso:country":"US",
    "sg:address":"10901 Oak Hill Dr",
    "sg:city":"Tyler",
    "sg:classifiers":[
        {
            "category":"Shopping",
            "subcategory":"Gifts & Souvenirs",
            "type":"Retail Goods"
        }
    ],
    "sg:phone":"+1 903 534 8980",
    "sg:postcode":"75707",
    "sg:province":"TX",
    "wof:name":"Wood N Things",
    "wof:placetype":"venue"
},
  "geometry": {"coordinates":[-95.232975,32.280834],"type":"Point"}
}