{
  "type": "Feature",
  "properties": {
    "iso:country":"US",
    "sg:address":"4807 Wycliff Dr",
    "sg:city":"San Antonio",
    "sg:classifiers":[
        {
            "category":"Organizations",
            "subcategory":"Religious Organization",
            "type":"Services"
        }
    ],
    "sg:phone":"+1 210 648 4843",
    "sg:postcode":"78220",
    "sg:province":"TX",
    "sg:tags":[
        "church"
    ],
    "wof:name":"Philadelphia Seventh-Day Adv",
    "wof:placetype":"venue"
},
  "geometry": {"coordinates":[-98.398118,29.400253],"type":"Point"}
}