{
  "type": "Feature",
  "properties": {
    "iso:country":"US",
    "sg:address":"2422 Arbuckle Ct",
    "sg:city":"Dallas",
    "sg:classifiers":[
        {
            "category":"Shopping",
            "type":"Retail Goods"
        }
    ],
    "sg:phone":"+1 214 239 2900",
    "sg:postcode":"75229",
    "sg:province":"TX",
    "sg:tags":[
        "equipment",
        "care",
        "health",
        "home"
    ],
    "wof:name":"Medical Mobility Of Texas",
    "wof:placetype":"venue"
},
  "geometry": {"coordinates":[-96.89469800000001,32.884985],"type":"Point"}
}