{
  "type": "Feature",
  "properties": {
    "iso:country":"US",
    "sg:address":"210 SE 24th Ave",
    "sg:city":"Perryton",
    "sg:classifiers":[
        {
            "category":"Travel",
            "subcategory":"Hotels & Motels",
            "type":"Entertainment"
        }
    ],
    "sg:phone":"+1 806 435 9611",
    "sg:postcode":"79070",
    "sg:province":"TX",
    "wof:name":"Ambassador Inn Inc",
    "wof:placetype":"venue"
},
  "geometry": {"coordinates":[-100.800319,36.376876],"type":"Point"}
}