{
  "type": "Feature",
  "properties": {
    "iso:country":"US",
    "sg:address":"320 Wolfe St",
    "sg:city":"Cedar Hill",
    "sg:classifiers":[
        {
            "category":"Professional",
            "subcategory":"Business Services",
            "type":"Services"
        }
    ],
    "sg:phone":"+1 972 291 9305",
    "sg:postcode":"75104",
    "sg:province":"TX",
    "wof:name":"Kendall Interiors",
    "wof:placetype":"venue"
},
  "geometry": {"coordinates":[-96.94824199999999,32.611768],"type":"Point"}
}