{
  "type": "Feature",
  "properties": {
    "iso:country":"US",
    "sg:address":"201 State Hwy 27",
    "sg:city":"Comfort",
    "sg:classifiers":[
        {
            "category":"Personal",
            "type":"Services"
        }
    ],
    "sg:phone":"+1 830 995 5170",
    "sg:postcode":"78013",
    "sg:province":"TX",
    "sg:tags":[
        "therapist",
        "massage"
    ],
    "wof:name":"Comfort Massage",
    "wof:placetype":"venue"
},
  "geometry": {"coordinates":[-98.914525,29.966817],"type":"Point"}
}