{
  "type": "Feature",
  "properties": {
    "iso:country":"US",
    "sg:address":"11406 Potter Valley Rd",
    "sg:city":"San Antonio",
    "sg:classifiers":[
        {
            "category":"Social Services",
            "subcategory":"Child Care",
            "type":"Services"
        }
    ],
    "sg:phone":"+1 210 674 2445",
    "sg:postcode":"78245",
    "sg:province":"TX",
    "wof:name":"Vbee's Daycare",
    "wof:placetype":"venue"
},
  "geometry": {"coordinates":[-98.698106,29.403528],"type":"Point"}
}