{
  "type": "Feature",
  "properties": {
    "iso:country":"US",
    "sg:address":"12150 Garland Rd",
    "sg:city":"Dallas",
    "sg:classifiers":[
        {
            "category":"Autos & Motor Vehicles",
            "subcategory":"Auto Supplies",
            "type":"Retail Goods"
        }
    ],
    "sg:phone":"+1 214 660 1081",
    "sg:postcode":"75218",
    "sg:province":"TX",
    "sg:tags":[
        "pickup",
        "truck",
        "for",
        "accessory"
    ],
    "wof:name":"Star Off- Road Truck Center",
    "wof:placetype":"venue"
},
  "geometry": {"coordinates":[-96.669262,32.866243],"type":"Point"}
}