{
  "type": "Feature",
  "properties": {
    "iso:country":"US",
    "sg:address":"300 E Holland Ave",
    "sg:city":"Alpine",
    "sg:classifiers":[
        {
            "category":"Shopping",
            "subcategory":"Beauty & Cosmetics",
            "type":"Retail Goods"
        }
    ],
    "sg:phone":"+1 432 837 3567",
    "sg:postcode":"79830",
    "sg:province":"TX",
    "sg:tags":[
        "perfume",
        "salons-equipment",
        "supply"
    ],
    "wof:name":"Patti Hildreth Studio",
    "wof:placetype":"venue"
},
  "geometry": {"coordinates":[-103.65937,30.358231],"type":"Point"}
}