{
  "type": "Feature",
  "properties": {
    "iso:country":"US",
    "sg:address":"5359 Fredericksburg Rd",
    "sg:city":"San Antonio",
    "sg:classifiers":[
        {
            "category":"Insurance",
            "subcategory":"Insurance Agent",
            "type":"Services"
        }
    ],
    "sg:phone":"+1 210 657 8500",
    "sg:postcode":"78229",
    "sg:province":"TX",
    "wof:name":"G Mac Insurance",
    "wof:placetype":"venue"
},
  "geometry": {"coordinates":[-98.56219900000001,29.504786],"type":"Point"}
}