{
  "type": "Feature",
  "properties": {
    "iso:country":"US",
    "sg:address":"10711 Glenda Kay Dr",
    "sg:city":"Houston",
    "sg:classifiers":[
        {
            "category":"Recreation",
            "type":"Entertainment"
        }
    ],
    "sg:phone":"+1 281 890 9292",
    "sg:postcode":"77065",
    "sg:province":"TX",
    "sg:tags":[
        "club",
        "membership"
    ],
    "wof:name":"Family Golf Club",
    "wof:placetype":"venue"
},
  "geometry": {"coordinates":[-95.624813,29.930955],"type":"Point"}
}