{
  "type": "Feature",
  "properties": {
    "iso:country":"US",
    "sg:address":"7007 Fred Morse Dr",
    "sg:city":"Austin",
    "sg:classifiers":[
        {
            "category":"Building & Trades",
            "subcategory":"Construction",
            "type":"Services"
        }
    ],
    "sg:phone":"+1 512 929 7207",
    "sg:postcode":"78723",
    "sg:province":"TX",
    "sg:tags":[
        "hanging",
        "contractor"
    ],
    "wof:name":"Emilysmithcom",
    "wof:placetype":"venue"
},
  "geometry": {"coordinates":[-97.671768,30.318495],"type":"Point"}
}