{
  "type": "Feature",
  "properties": {
    "iso:country":"US",
    "sg:address":"1401 Sierra Dr",
    "sg:city":"Mesquite",
    "sg:classifiers":[
        {
            "category":"Shopping",
            "subcategory":"Hobbies, Toys, & Games",
            "type":"Retail Goods"
        }
    ],
    "sg:phone":"+1 972 288 8422",
    "sg:postcode":"75149",
    "sg:province":"TX",
    "wof:name":"Troy & Estelles Hobbies",
    "wof:placetype":"venue"
},
  "geometry": {"coordinates":[-96.578884,32.752656],"type":"Point"}
}