{
  "type": "Feature",
  "properties": {
    "iso:country":"US",
    "sg:address":"508 E Van Week St",
    "sg:city":"Edinburg",
    "sg:classifiers":[
        {
            "category":"Organizations",
            "subcategory":"Religious Organization",
            "type":"Services"
        }
    ],
    "sg:phone":"+1 956 318 1330",
    "sg:postcode":"78541",
    "sg:province":"TX",
    "sg:tags":[
        "school",
        "bible",
        "study"
    ],
    "wof:name":"Regional Bible Institute",
    "wof:placetype":"venue"
},
  "geometry": {"coordinates":[-98.15589900000001,26.306516],"type":"Point"}
}