{
  "type": "Feature",
  "properties": {
    "iso:country":"US",
    "sg:address":"2521 Delaney Ter",
    "sg:city":"Flower Mound",
    "sg:classifiers":[
        {
            "category":"Freight",
            "type":"Transportation"
        }
    ],
    "sg:phone":"+1 972 539 8925",
    "sg:postcode":"75028",
    "sg:province":"TX",
    "sg:tags":[
        "delivery",
        "disposable",
        "diaper"
    ],
    "wof:name":"Neighborhood Diaper Delivery",
    "wof:placetype":"venue"
},
  "geometry": {"coordinates":[-97.066334,33.02892],"type":"Point"}
}