{
  "type": "Feature",
  "properties": {
    "iso:country":"US",
    "sg:address":"8103 Southwest Fwy",
    "sg:city":"Houston",
    "sg:classifiers":[
        {
            "category":"Food & Beverages",
            "subcategory":"Groceries & Convenience Stores",
            "type":"Retail Goods"
        }
    ],
    "sg:phone":"+1 713 771 3777",
    "sg:postcode":"77074",
    "sg:province":"TX",
    "wof:name":"Handi Plus 39",
    "wof:placetype":"venue"
},
  "geometry": {"coordinates":[-95.52739699999999,29.691099],"type":"Point"}
}