{
  "type": "Feature",
  "properties": {
    "iso:country":"US",
    "sg:address":"9570 Sam Houston Pkwy",
    "sg:city":"Houston",
    "sg:classifiers":[
        {
            "category":"Professional",
            "subcategory":"Employment Agencies",
            "type":"Services"
        }
    ],
    "sg:phone":"+1 713 774 6631",
    "sg:postcode":"77044",
    "sg:province":"TX",
    "wof:name":"Texas Services",
    "wof:placetype":"venue"
},
  "geometry": {"coordinates":[-95.217484,29.934668],"type":"Point"}
}