{
  "type": "Feature",
  "properties": {
    "iso:country":"US",
    "sg:address":"5741 Belding Dr",
    "sg:city":"El Paso",
    "sg:classifiers":[
        {
            "category":"Health Services",
            "subcategory":"Doctor",
            "type":"Services"
        }
    ],
    "sg:phone":"+1 915 872 9050",
    "sg:postcode":"79925",
    "sg:province":"TX",
    "wof:name":"Quiroga Dentistry Inc",
    "wof:placetype":"venue"
},
  "geometry": {"coordinates":[-106.41846099999999,31.781751],"type":"Point"}
}