{
  "type": "Feature",
  "properties": {
    "iso:country":"US",
    "sg:address":"1705 19th St",
    "sg:city":"Hondo",
    "sg:classifiers":[
        {
            "category":"Coffee & Tea",
            "type":"Food & Drink"
        },
        {
            "category":"Restaurant",
            "type":"Food & Drink"
        }
    ],
    "sg:phone":"+1 830 426 3580",
    "sg:postcode":"78861",
    "sg:province":"TX",
    "sg:tags":[
        "espresso"
    ],
    "wof:name":"Alberto's Cafe",
    "wof:placetype":"venue"
},
  "geometry": {"coordinates":[-99.14739400000001,29.347074],"type":"Point"}
}