{
  "type": "Feature",
  "properties": {
    "iso:country":"US",
    "sg:address":"4410 19th St",
    "sg:city":"Lubbock",
    "sg:classifiers":[
        {
            "category":"Restaurant",
            "type":"Food & Drink"
        }
    ],
    "sg:menulink":"http://www.allmenus.com/tx/lubbock/121844-keva-juice/menu/",
    "sg:phone":"+1 806 771 5382",
    "sg:postcode":"79407",
    "sg:province":"TX",
    "sg:tags":[
        "smoothy",
        "juice",
        "american"
    ],
    "wof:name":"Keva Juice",
    "wof:placetype":"venue"
},
  "geometry": {"coordinates":[-101.90648299999999,33.578336],"type":"Point"}
}