{
  "type": "Feature",
  "properties": {
    "iso:country":"US",
    "sg:address":"340 Freeman St",
    "sg:city":"Mathis",
    "sg:classifiers":[
        {
            "category":"Retail",
            "subcategory":"Auto Repair",
            "type":"Services"
        }
    ],
    "sg:phone":"+1 361 980 1301",
    "sg:postcode":"78368",
    "sg:province":"TX",
    "sg:tags":[
        "automotive"
    ],
    "wof:name":"All Terrain Towing",
    "wof:placetype":"venue"
},
  "geometry": {"coordinates":[-97.82464299999999,28.10303],"type":"Point"}
}