{
  "type": "Feature",
  "properties": {
    "iso:country":"US",
    "sg:address":"110 W Hopkins St",
    "sg:city":"San Marcos",
    "sg:classifiers":[
        {
            "category":"Shopping",
            "subcategory":"Jewelry",
            "type":"Retail Goods"
        }
    ],
    "sg:phone":"+1 512 396 9188",
    "sg:postcode":"78666",
    "sg:province":"TX",
    "sg:tags":[
        "repair",
        "jeweler"
    ],
    "wof:name":"Alfredo's Jewelry",
    "wof:placetype":"venue"
},
  "geometry": {"coordinates":[-97.941514,29.883088],"type":"Point"}
}