{
  "type": "Feature",
  "properties": {
    "iso:country":"US",
    "sg:address":"6560 Fannin St Ste 1980",
    "sg:city":"Houston",
    "sg:classifiers":[
        {
            "category":"Health Services",
            "subcategory":"Doctor",
            "type":"Services"
        }
    ],
    "sg:phone":"+1 713 335 0335",
    "sg:postcode":"77030",
    "sg:province":"TX",
    "wof:name":"Putterman Bart D MD",
    "wof:placetype":"venue"
},
  "geometry": {"coordinates":[-95.400141,29.711527],"type":"Point"}
}