{
  "type": "Feature",
  "properties": {
    "iso:country":"US",
    "sg:address":"11432 Hillcrest Rd",
    "sg:city":"Dallas",
    "sg:classifiers":[
        {
            "category":"Professional",
            "subcategory":"Business Services",
            "type":"Services"
        }
    ],
    "sg:phone":"+1 214 369 7486",
    "sg:postcode":"75230",
    "sg:province":"TX",
    "sg:tags":[
        "interior",
        "consultant",
        "design",
        "decorator"
    ],
    "wof:name":"Cheri Etchelecu Interior",
    "wof:placetype":"venue"
},
  "geometry": {"coordinates":[-96.788133,32.902613],"type":"Point"}
}