{
  "type": "Feature",
  "properties": {
    "iso:country":"US",
    "sg:address":"122 E Main St",
    "sg:city":"Van",
    "sg:classifiers":[
        {
            "category":"Insurance",
            "subcategory":"Insurance Agent",
            "type":"Services"
        }
    ],
    "sg:phone":"+1 903 963 8668",
    "sg:postcode":"75790",
    "sg:province":"TX",
    "wof:name":"National Gold Seal Corp",
    "wof:placetype":"venue"
},
  "geometry": {"coordinates":[-95.633966,32.524487],"type":"Point"}
}