{
  "type": "Feature",
  "properties": {
    "iso:country":"US",
    "sg:address":"2408 Glen Forest Ln",
    "sg:city":"Plano",
    "sg:classifiers":[
        {
            "category":"Insurance",
            "subcategory":"Insurance Agent",
            "type":"Services"
        }
    ],
    "sg:phone":"+1 972 964 9064",
    "sg:postcode":"75023",
    "sg:province":"TX",
    "wof:name":"Mickey McKnight",
    "wof:placetype":"venue"
},
  "geometry": {"coordinates":[-96.74093000000001,33.044899],"type":"Point"}
}