{
  "type": "Feature",
  "properties": {
    "iso:country":"US",
    "sg:address":"209 E Mansfield Hwy",
    "sg:city":"Kennedale",
    "sg:classifiers":[
        {
            "category":"Building & Trades",
            "subcategory":"Construction",
            "type":"Services"
        }
    ],
    "sg:phone":"+1 817 572 6635",
    "sg:postcode":"76060",
    "sg:province":"TX",
    "sg:tags":[
        "dry wall",
        "contractor"
    ],
    "wof:name":"Robby Fox Drywall Finishing",
    "wof:placetype":"venue"
},
  "geometry": {"coordinates":[-97.21965299999999,32.645098],"type":"Point"}
}