{
  "type": "Feature",
  "properties": {
    "iso:country":"US",
    "sg:address":"3214 Mercer St",
    "sg:city":"Houston",
    "sg:classifiers":[
        {
            "category":"Professional",
            "subcategory":"Management & Consulting",
            "type":"Services"
        }
    ],
    "sg:phone":"+1 713 961 4910",
    "sg:postcode":"77027",
    "sg:province":"TX",
    "sg:tags":[
        "fuel"
    ],
    "wof:name":"Evalution Capitol Management",
    "wof:placetype":"venue"
},
  "geometry": {"coordinates":[-95.43221800000001,29.737527],"type":"Point"}
}