{
  "type": "Feature",
  "properties": {
    "iso:country":"US",
    "sg:address":"1601 Clover Ln",
    "sg:city":"Fort Worth",
    "sg:classifiers":[
        {
            "category":"Shopping",
            "type":"Retail Goods"
        }
    ],
    "sg:phone":"+1 817 763 5227",
    "sg:postcode":"76107",
    "sg:province":"TX",
    "sg:tags":[
        "gallery",
        "merchandise"
    ],
    "wof:name":"Galerie Kornye West",
    "wof:placetype":"venue"
},
  "geometry": {"coordinates":[-97.37847600000001,32.741527],"type":"Point"}
}