{
  "type": "Feature",
  "properties": {
    "iso:country":"US",
    "sg:address":"2605 W Airport Fwy",
    "sg:city":"Irving",
    "sg:classifiers":[
        {
            "category":"Home & Garden",
            "subcategory":"Furniture",
            "type":"Retail Goods"
        }
    ],
    "sg:phone":"+1 972 252 7471",
    "sg:postcode":"75062",
    "sg:province":"TX",
    "sg:tags":[
        "mattress"
    ],
    "wof:name":"Mattress Firm Inc",
    "wof:placetype":"venue"
},
  "geometry": {"coordinates":[-96.98146800000001,32.837403],"type":"Point"}
}