{
  "type": "Feature",
  "properties": {
    "iso:country":"US",
    "sg:address":"4231 Gibson St",
    "sg:city":"Houston",
    "sg:classifiers":[
        {
            "category":"Food & Beverages",
            "subcategory":"Dairy",
            "type":"Retail Goods"
        }
    ],
    "sg:phone":"+1 713 869 8531",
    "sg:postcode":"77007",
    "sg:province":"TX",
    "sg:tags":[
        "product"
    ],
    "wof:name":"Valle Ice Cream",
    "wof:placetype":"venue"
},
  "geometry": {"coordinates":[-95.403671,29.766812],"type":"Point"}
}