{
  "type": "Feature",
  "properties": {
    "iso:country":"US",
    "sg:address":"213 E Cameron Ave",
    "sg:city":"Rockdale",
    "sg:classifiers":[
        {
            "category":"Restaurant",
            "type":"Food & Drink"
        }
    ],
    "sg:phone":"+1 512 446 7201",
    "sg:postcode":"76567",
    "sg:province":"TX",
    "sg:tags":[
        "shop",
        "coffee"
    ],
    "wof:name":"Serendipity",
    "wof:placetype":"venue"
},
  "geometry": {"coordinates":[-97.000488,30.656125],"type":"Point"}
}