{
  "type": "Feature",
  "properties": {
    "iso:country":"US",
    "sg:address":"7805 Adobe Trl",
    "sg:city":"Austin",
    "sg:classifiers":[
        {
            "category":"Manufacturing",
            "subcategory":"Signs",
            "type":"Manufacturing & Wholesale Goods"
        }
    ],
    "sg:phone":"+1 512 301 4321",
    "sg:postcode":"78737",
    "sg:province":"TX",
    "sg:tags":[
        "signs-erectors",
        "hanger"
    ],
    "wof:name":"January's",
    "wof:placetype":"venue"
},
  "geometry": {"coordinates":[-97.89815900000001,30.219112],"type":"Point"}
}