{
  "type": "Feature",
  "properties": {
    "iso:country":"US",
    "sg:address":"1703 State Highway 135 E",
    "sg:city":"Overton",
    "sg:classifiers":[
        {
            "category":"Real Estate",
            "subcategory":"Real Estate Services",
            "type":"Services"
        },
        {
            "category":"Real Estate",
            "subcategory":"Real Estate Agent",
            "type":"Services"
        }
    ],
    "sg:phone":"+1 903 834 3481",
    "sg:postcode":"75684",
    "sg:province":"TX",
    "sg:tags":[
        "buyer",
        "broker"
    ],
    "wof:name":"Mary Rhodes Real Estate",
    "wof:placetype":"venue"
},
  "geometry": {"coordinates":[-94.948128,32.289143],"type":"Point"}
}