{
  "type": "Feature",
  "properties": {
    "iso:country":"US",
    "sg:address":"4300 N Cage Blvd",
    "sg:city":"Pharr",
    "sg:classifiers":[
        {
            "category":"Autos & Motor Vehicles",
            "subcategory":"Automobile Sales",
            "type":"Retail Goods"
        },
        {
            "category":"Wholesale",
            "subcategory":"Auto Parts",
            "type":"Manufacturing & Wholesale Goods"
        },
        {
            "category":"Retail",
            "subcategory":"Auto Repair",
            "type":"Services"
        }
    ],
    "sg:phone":"+1 888 526 6333",
    "sg:postcode":"78577",
    "sg:province":"TX",
    "sg:tags":[
        "used",
        "trucks-industrial",
        "equipment",
        "truck",
        "new"
    ],
    "wof:name":"French Ellison Truck Center",
    "wof:placetype":"venue"
},
  "geometry": {"coordinates":[-98.17797899999999,26.22966],"type":"Point"}
}