{
  "type": "Feature",
  "properties": {
    "iso:country":"US",
    "sg:address":"2072 Sailmaker Dr",
    "sg:city":"Lewisville",
    "sg:classifiers":[
        {
            "category":"Professional",
            "type":"Services"
        }
    ],
    "sg:phone":"+1 214 488 8686",
    "sg:postcode":"75067",
    "sg:province":"TX",
    "sg:tags":[
        "establishment"
    ],
    "wof:name":"First Impressions",
    "wof:placetype":"venue"
},
  "geometry": {"coordinates":[-97.00555300000001,33.011837],"type":"Point"}
}