{
  "type": "Feature",
  "properties": {
    "iso:country":"US",
    "sg:address":"2754 Letchester Dr",
    "sg:city":"Spring",
    "sg:classifiers":[
        {
            "category":"Communications",
            "subcategory":"Film & Video Production",
            "type":"Services"
        }
    ],
    "sg:phone":"+1 281 355 7031",
    "sg:postcode":"77386",
    "sg:province":"TX",
    "sg:tags":[
        "motion"
    ],
    "wof:name":"Frontline Productions",
    "wof:placetype":"venue"
},
  "geometry": {"coordinates":[-95.40255399999999,30.112614],"type":"Point"}
}