{
  "type": "Feature",
  "properties": {
    "iso:country":"US",
    "sg:address":"318 Terrace Dr",
    "sg:city":"Houston",
    "sg:classifiers":[
        {
            "category":"Professional",
            "subcategory":"Business Services",
            "type":"Services"
        }
    ],
    "sg:phone":"+1 713 864 1446",
    "sg:postcode":"77007",
    "sg:province":"TX",
    "wof:name":"Al Wolf Enterprises LLC",
    "wof:placetype":"venue"
},
  "geometry": {"coordinates":[-95.424149,29.763225],"type":"Point"}
}