{
  "type": "Feature",
  "properties": {
    "iso:country":"US",
    "sg:address":"1115 Apache St",
    "sg:city":"El Paso",
    "sg:classifiers":[
        {
            "category":"Professional",
            "subcategory":"Management & Consulting",
            "type":"Services"
        }
    ],
    "sg:phone":"+1 915 772 4669",
    "sg:postcode":"79925",
    "sg:province":"TX",
    "sg:tags":[
        "business"
    ],
    "wof:name":"MRM Consulting Service",
    "wof:placetype":"venue"
},
  "geometry": {"coordinates":[-106.404417,31.784817],"type":"Point"}
}