{
  "type": "Feature",
  "properties": {
    "iso:country":"US",
    "sg:address":"4916 Remington Park Dr",
    "sg:city":"Flower Mound",
    "sg:classifiers":[
        {
            "category":"Professional",
            "subcategory":"Engineering",
            "type":"Services"
        }
    ],
    "sg:phone":"+1 972 539 5564",
    "sg:postcode":"75028",
    "sg:province":"TX",
    "wof:name":"Dillion & Dillion",
    "wof:placetype":"venue"
},
  "geometry": {"coordinates":[-97.09932000000001,33.05339],"type":"Point"}
}