{
  "type": "Feature",
  "properties": {
    "iso:country":"US",
    "sg:address":"1418 S Main St",
    "sg:city":"Henderson",
    "sg:classifiers":[
        {
            "category":"Utilities",
            "subcategory":"Mobile Phone",
            "type":"Services"
        }
    ],
    "sg:phone":"+1 903 657 0781",
    "sg:postcode":"75654",
    "sg:province":"TX",
    "sg:tags":[
        "telephone",
        "cellular"
    ],
    "wof:name":"Alltel",
    "wof:placetype":"venue"
},
  "geometry": {"coordinates":[-94.798441,32.138879],"type":"Point"}
}