{
  "type": "Feature",
  "properties": {
    "iso:country":"US",
    "sg:address":"1515 S Commerce St",
    "sg:city":"Lockhart",
    "sg:classifiers":[
        {
            "category":"Manufacturing",
            "subcategory":"Rubber & Plastics",
            "type":"Manufacturing & Wholesale Goods"
        },
        {
            "category":"Manufacturing",
            "subcategory":"Tools & Machinery",
            "type":"Manufacturing & Wholesale Goods"
        }
    ],
    "sg:phone":"+1 512 398 6044",
    "sg:postcode":"78644",
    "sg:province":"TX",
    "sg:tags":[
        "product",
        "mold",
        "molded",
        "mfg"
    ],
    "wof:name":"R & D Molders Inc",
    "wof:placetype":"venue"
},
  "geometry": {"coordinates":[-97.66336200000001,29.865849],"type":"Point"}
}