{
  "type": "Feature",
  "properties": {
    "iso:country":"US",
    "sg:address":"1208 W Panola St",
    "sg:city":"Carthage",
    "sg:classifiers":[
        {
            "category":"Restaurant",
            "type":"Food & Drink"
        }
    ],
    "sg:menulink":"http://www.allmenus.com/tx/carthage/176980-kfc---kentucky-fried-chicken/menu/",
    "sg:phone":"+1 903 693 4281",
    "sg:postcode":"75633",
    "sg:province":"TX",
    "sg:tags":[
        "american",
        "chicken"
    ],
    "wof:name":"KFC - Kentucky Fried Chicken",
    "wof:placetype":"venue"
},
  "geometry": {"coordinates":[-94.356634,32.158463],"type":"Point"}
}