{
  "type": "Feature",
  "properties": {
    "iso:country":"US",
    "sg:address":"5653 Overland Dr",
    "sg:city":"The Colony",
    "sg:classifiers":[
        {
            "category":"Wholesale",
            "subcategory":"Chemicals & Plastics",
            "type":"Manufacturing & Wholesale Goods"
        }
    ],
    "sg:phone":"+1 469 384 0089",
    "sg:postcode":"75056",
    "sg:province":"TX",
    "sg:tags":[
        "floor",
        "treatment",
        "compound"
    ],
    "wof:name":"Slick Guard",
    "wof:placetype":"venue"
},
  "geometry": {"coordinates":[-96.869601,33.091255],"type":"Point"}
}