{
  "type": "Feature",
  "properties": {
    "iso:country":"US",
    "sg:address":"804 Tealwood Cir",
    "sg:city":"Flower Mound",
    "sg:classifiers":[
        {
            "category":"Personal",
            "subcategory":"Barber",
            "type":"Services"
        }
    ],
    "sg:phone":"+1 972 355 6657",
    "sg:postcode":"75028",
    "sg:province":"TX",
    "sg:tags":[
        "shop"
    ],
    "wof:name":"SJS Technique 2000",
    "wof:placetype":"venue"
},
  "geometry": {"coordinates":[-97.041973,33.010821],"type":"Point"}
}