{
  "type": "Feature",
  "properties": {
    "iso:country":"US",
    "sg:address":"3711 66th St",
    "sg:city":"Lubbock",
    "sg:classifiers":[
        {
            "category":"Professional",
            "subcategory":"Lawyer & Legal Services",
            "type":"Services"
        }
    ],
    "sg:phone":"+1 806 793 1259",
    "sg:postcode":"79413",
    "sg:province":"TX",
    "wof:name":"Energy Disputes Solutions",
    "wof:placetype":"venue"
},
  "geometry": {"coordinates":[-101.89622799999999,33.53417],"type":"Point"}
}