{
  "type": "Feature",
  "properties": {
    "iso:country":"US",
    "sg:address":"9301 Broadway St",
    "sg:city":"Galveston",
    "sg:classifiers":[
        {
            "category":"Shopping",
            "subcategory":"Bicycles & Sporting Goods",
            "type":"Retail Goods"
        }
    ],
    "sg:phone":"+1 409 740 1185",
    "sg:postcode":"77554",
    "sg:province":"TX",
    "sg:tags":[
        "bait",
        "fishing"
    ],
    "wof:name":"Galveston Bait & Tackle",
    "wof:placetype":"venue"
},
  "geometry": {"coordinates":[-94.869747,29.28782],"type":"Point"}
}