{
  "type": "Feature",
  "properties": {
    "iso:country":"US",
    "sg:address":"7103 Santa Fe Dr",
    "sg:city":"Lubbock",
    "sg:classifiers":[
        {
            "category":"Building & Trades",
            "subcategory":"Plumbing",
            "type":"Services"
        }
    ],
    "sg:phone":"+1 806 795 5528",
    "sg:postcode":"79407",
    "sg:province":"TX",
    "sg:tags":[
        "conditioning",
        "air",
        "system",
        "contractor"
    ],
    "wof:name":"Dale Bolles Plumbing Heating",
    "wof:placetype":"venue"
},
  "geometry": {"coordinates":[-101.972836,33.534295],"type":"Point"}
}