{
  "type": "Feature",
  "properties": {
    "iso:country":"US",
    "sg:address":"31338 Sunlight Dr",
    "sg:city":"Bulverde",
    "sg:classifiers":[
        {
            "category":"Wholesale",
            "subcategory":"Non-durable Goods",
            "type":"Manufacturing & Wholesale Goods"
        }
    ],
    "sg:phone":"+1 830 980 5996",
    "sg:postcode":"78163",
    "sg:province":"TX",
    "wof:name":"Guethle Distributing Co",
    "wof:placetype":"venue"
},
  "geometry": {"coordinates":[-98.399354,29.75861],"type":"Point"}
}