{
  "type": "Feature",
  "properties": {
    "iso:country":"US",
    "sg:address":"415 W Pecan St",
    "sg:city":"Coleman",
    "sg:classifiers":[
        {
            "category":"Personal",
            "subcategory":"Beauty Salon",
            "type":"Services"
        }
    ],
    "sg:phone":"+1 325 625 5119",
    "sg:postcode":"76834",
    "sg:province":"TX",
    "sg:tags":[
        "shop"
    ],
    "wof:name":"Margie's Beauty Salon",
    "wof:placetype":"venue"
},
  "geometry": {"coordinates":[-99.426349,31.829999],"type":"Point"}
}