{
  "type": "Feature",
  "properties": {
    "iso:country":"US",
    "sg:address":"4007 30th St",
    "sg:city":"Lubbock",
    "sg:classifiers":[
        {
            "category":"Recreation",
            "type":"Entertainment"
        }
    ],
    "sg:phone":"+1 806 767 3739",
    "sg:postcode":"79410",
    "sg:province":"TX",
    "wof:name":"Maxey Swimming Pool",
    "wof:placetype":"venue"
},
  "geometry": {"coordinates":[-101.900639,33.56683],"type":"Point"}
}