{
  "type": "Feature",
  "properties": {
    "iso:country":"US",
    "sg:address":"16503 Innisbrook Dr",
    "sg:city":"Houston",
    "sg:classifiers":[
        {
            "category":"Wholesale",
            "subcategory":"Machinery & Supplies",
            "type":"Manufacturing & Wholesale Goods"
        }
    ],
    "sg:phone":"+1 832 593 0173",
    "sg:postcode":"77095",
    "sg:province":"TX",
    "sg:tags":[
        "equipment"
    ],
    "wof:name":"Orellana Export & Supply",
    "wof:placetype":"venue"
},
  "geometry": {"coordinates":[-95.664745,29.901945],"type":"Point"}
}