{
  "type": "Feature",
  "properties": {
    "iso:country":"US",
    "sg:address":"600 N Pearl St Ste 900",
    "sg:city":"Dallas",
    "sg:classifiers":[
        {
            "category":"Professional",
            "subcategory":"Lawyer & Legal Services",
            "type":"Services"
        }
    ],
    "sg:phone":"+1 214 954 6386",
    "sg:postcode":"75201",
    "sg:province":"TX",
    "wof:name":"Leonard Hurt Frost & Lilly",
    "wof:placetype":"venue"
},
  "geometry": {"coordinates":[-96.795097,32.785999],"type":"Point"}
}