{
  "type": "Feature",
  "properties": {
    "iso:country":"US",
    "sg:address":"1505 Hillview Dr",
    "sg:city":"Hillsboro",
    "sg:classifiers":[
        {
            "category":"Travel",
            "subcategory":"Hotels & Motels",
            "type":"Entertainment"
        },
        {
            "category":"Retail",
            "subcategory":"Event Space",
            "type":"Services"
        }
    ],
    "sg:phone":"+1 800 345 8082",
    "sg:postcode":"76645",
    "sg:province":"TX",
    "sg:tags":[
        "facility",
        "banquet",
        "reception",
        "lodging",
        "corporate",
        "hall"
    ],
    "sg:website":"http://ad.doubleclick.net/clk;222816988;46581822;v?http://www.hiexpress.com/redirect?path=hd&brandCode=ex&hotelCode=hlbtx&_PMID=99601036&cm_mmc=mdpr-_-yellowpages-_-ex-_-hlbtx",
    "wof:name":"Holiday Inn Express Hillsboro (I-35)",
    "wof:placetype":"venue"
},
  "geometry": {"coordinates":[-97.094526,32.010877],"type":"Point"}
}