{
  "type": "Feature",
  "properties": {
    "iso:country":"US",
    "sg:address":"2889 S Eastman Rd",
    "sg:city":"Longview",
    "sg:classifiers":[
        {
            "category":"Shopping",
            "subcategory":"Computers & Home Electronics",
            "type":"Retail Goods"
        }
    ],
    "sg:phone":"+1 903 757 7481",
    "sg:postcode":"75602",
    "sg:province":"TX",
    "sg:tags":[
        "equipment",
        "satellite",
        "system"
    ],
    "wof:name":"Southern Star Satellites",
    "wof:placetype":"venue"
},
  "geometry": {"coordinates":[-94.70757999999999,32.454667],"type":"Point"}
}