{
  "type": "Feature",
  "properties": {
    "iso:country":"US",
    "sg:address":"2685 N Main St",
    "sg:city":"Paris",
    "sg:classifiers":[
        {
            "category":"Professional",
            "type":"Services"
        }
    ],
    "sg:phone":"+1 903 784 6888",
    "sg:postcode":"75460",
    "sg:province":"TX",
    "sg:tags":[
        "establishment"
    ],
    "wof:name":"AAA Safe Guard Storage",
    "wof:placetype":"venue"
},
  "geometry": {"coordinates":[-95.554376,33.691454],"type":"Point"}
}