{
  "type": "Feature",
  "properties": {
    "iso:country":"US",
    "sg:address":"510 Waugh Dr",
    "sg:city":"Houston",
    "sg:classifiers":[
        {
            "category":"Health Services",
            "subcategory":"Doctor",
            "type":"Services"
        }
    ],
    "sg:phone":"+1 713 524 0400",
    "sg:postcode":"77019",
    "sg:province":"TX",
    "sg:tags":[
        "medical"
    ],
    "wof:name":"Midtown Orthopaedics & Sports",
    "wof:placetype":"venue"
},
  "geometry": {"coordinates":[-95.39818200000001,29.761115],"type":"Point"}
}