{
  "type": "Feature",
  "properties": {
    "iso:country":"US",
    "sg:address":"2524 Nottingham St",
    "sg:city":"Houston",
    "sg:classifiers":[
        {
            "category":"Professional",
            "subcategory":"Employment Agencies",
            "type":"Services"
        }
    ],
    "sg:phone":"+1 713 981 9422",
    "sg:postcode":"77005",
    "sg:province":"TX",
    "wof:name":"Quintessence Corp Staffing",
    "wof:placetype":"venue"
},
  "geometry": {"coordinates":[-95.418149,29.72236],"type":"Point"}
}