{
  "type": "Feature",
  "properties": {
    "iso:country":"US",
    "sg:address":"1221 Flower Mound Rd",
    "sg:city":"Flower Mound",
    "sg:classifiers":[
        {
            "category":"Restaurant",
            "type":"Food & Drink"
        }
    ],
    "sg:menulink":"http://www.allmenus.com/tx/lewisville/250229-mikado-sushi-and-hibachi/menu/",
    "sg:phone":"+1 972 539 0831",
    "sg:postcode":"75028",
    "sg:province":"TX",
    "sg:tags":[
        "japanese",
        "asian"
    ],
    "wof:name":"Mikado Sushi And Hibachi",
    "wof:placetype":"venue"
},
  "geometry": {"coordinates":[-97.041726,33.01002],"type":"Point"}
}