{
  "type": "Feature",
  "properties": {
    "iso:country":"US",
    "sg:address":"9519 Riverland Ln",
    "sg:city":"Houston",
    "sg:classifiers":[
        {
            "category":"Manufacturing",
            "subcategory":"Printing",
            "type":"Manufacturing & Wholesale Goods"
        }
    ],
    "sg:phone":"+1 713 849 2831",
    "sg:postcode":"77040",
    "sg:province":"TX",
    "sg:tags":[
        "periodical"
    ],
    "wof:name":"Mags Galore Magazine Superstor",
    "wof:placetype":"venue"
},
  "geometry": {"coordinates":[-95.54465399999999,29.900098],"type":"Point"}
}