{
  "type": "Feature",
  "properties": {
    "iso:country":"US",
    "sg:address":"200 W Bowie St",
    "sg:city":"Marshall",
    "sg:classifiers":[
        {
            "category":"Professional",
            "subcategory":"Lawyer & Legal Services",
            "type":"Services"
        }
    ],
    "sg:phone":"+1 903 938 3070",
    "sg:postcode":"75670",
    "sg:province":"TX",
    "wof:name":"Dean Charlie Jack Atty",
    "wof:placetype":"venue"
},
  "geometry": {"coordinates":[-94.369311,32.544174],"type":"Point"}
}