{
  "type": "Feature",
  "properties": {
    "iso:country":"US",
    "sg:address":"204 Reinerman St",
    "sg:city":"Houston",
    "sg:classifiers":[
        {
            "category":"Wholesale",
            "subcategory":"Hardware",
            "type":"Manufacturing & Wholesale Goods"
        }
    ],
    "sg:phone":"+1 713 869 9444",
    "sg:postcode":"77007",
    "sg:province":"TX",
    "sg:tags":[
        "installation",
        "commercial",
        "sale",
        "ice",
        "machine",
        "equipment",
        "making",
        "refrigerator"
    ],
    "sg:website":"www.coolersinc.com",
    "wof:name":"Cooler's Inc",
    "wof:placetype":"venue"
},
  "geometry": {"coordinates":[-95.413338,29.765257],"type":"Point"}
}