{
  "type": "Feature",
  "properties": {
    "iso:country":"US",
    "sg:address":"13019 Horseshoe Trl",
    "sg:city":"Mesquite",
    "sg:classifiers":[
        {
            "category":"Wholesale",
            "subcategory":"Electrical",
            "type":"Manufacturing & Wholesale Goods"
        },
        {
            "category":"Shopping",
            "subcategory":"Computers & Home Electronics",
            "type":"Retail Goods"
        }
    ],
    "sg:phone":"+1 972 557 5252",
    "sg:postcode":"75180",
    "sg:province":"TX",
    "sg:tags":[
        "equipment",
        "consumer",
        "electric",
        "supply"
    ],
    "wof:name":"Tecs Electronics",
    "wof:placetype":"venue"
},
  "geometry": {"coordinates":[-96.604834,32.709301],"type":"Point"}
}