{
  "type": "Feature",
  "properties": {
    "iso:country":"US",
    "sg:address":"521 S F St",
    "sg:city":"Harlingen",
    "sg:classifiers":[
        {
            "category":"Banks & Credit Unions",
            "subcategory":"Bank",
            "type":"Services"
        }
    ],
    "sg:phone":"+1 956 440 1515",
    "sg:postcode":"78550",
    "sg:province":"TX",
    "sg:tags":[
        "personal",
        "institution",
        "business"
    ],
    "wof:name":"Prestamas",
    "wof:placetype":"venue"
},
  "geometry": {"coordinates":[-97.702061,26.187544],"type":"Point"}
}