{
  "type": "Feature",
  "properties": {
    "iso:country":"US",
    "sg:address":"3610 McKinney Ave",
    "sg:city":"Dallas",
    "sg:classifiers":[
        {
            "category":"Banks & Credit Unions",
            "subcategory":"Bank",
            "type":"Services"
        }
    ],
    "sg:phone":"+1 214 443 1550",
    "sg:postcode":"75204",
    "sg:province":"TX",
    "sg:website":"www.chase.com",
    "wof:name":"Chase",
    "wof:placetype":"venue"
},
  "geometry": {"coordinates":[-96.79733299999999,32.807152],"type":"Point"}
}