{
  "type": "Feature",
  "properties": {
    "iso:country":"US",
    "sg:address":"4313 Roseland St",
    "sg:city":"Houston",
    "sg:classifiers":[
        {
            "category":"Communications",
            "subcategory":"Film & Video Production",
            "type":"Services"
        }
    ],
    "sg:phone":"+1 713 522 8393",
    "sg:postcode":"77006",
    "sg:province":"TX",
    "sg:tags":[
        "motion"
    ],
    "wof:name":"Amazon Films",
    "wof:placetype":"venue"
},
  "geometry": {"coordinates":[-95.38972699999999,29.733459],"type":"Point"}
}