{
  "type": "Feature",
  "properties": {
    "iso:country":"US",
    "sg:address":"704 Moore Ave",
    "sg:city":"Portland",
    "sg:classifiers":[
        {
            "category":"Manufacturing",
            "subcategory":"Printing",
            "type":"Manufacturing & Wholesale Goods"
        }
    ],
    "sg:phone":"+1 361 643 5679",
    "sg:postcode":"78374",
    "sg:province":"TX",
    "sg:tags":[
        "lithographic",
        "commercial",
        "photocopying"
    ],
    "wof:name":"Nikos Printing",
    "wof:placetype":"venue"
},
  "geometry": {"coordinates":[-97.32657,27.876039],"type":"Point"}
}