{
  "type": "Feature",
  "properties": {
    "iso:country":"US",
    "sg:address":"505 Tate Dr",
    "sg:city":"De Soto",
    "sg:classifiers":[
        {
            "category":"Freight",
            "type":"Transportation"
        }
    ],
    "sg:phone":"+1 972 223 5380",
    "sg:postcode":"75115",
    "sg:province":"TX",
    "sg:tags":[
        "operator",
        "local",
        "trucking"
    ],
    "wof:name":"Frazier Trucking",
    "wof:placetype":"venue"
},
  "geometry": {"coordinates":[-96.865334,32.5786],"type":"Point"}
}