{
  "type": "Feature",
  "properties": {
    "iso:country":"US",
    "sg:address":"440 Beard Dr",
    "sg:city":"Cedar Hill",
    "sg:classifiers":[
        {
            "category":"Professional",
            "subcategory":"Accounting & Tax Preparation",
            "type":"Services"
        }
    ],
    "sg:phone":"+1 972 293 2641",
    "sg:postcode":"75104",
    "sg:province":"TX",
    "sg:tags":[
        "return"
    ],
    "wof:name":"Salar Tax",
    "wof:placetype":"venue"
},
  "geometry": {"coordinates":[-96.958214,32.615061],"type":"Point"}
}