{
  "type": "Feature",
  "properties": {
    "iso:country":"US",
    "sg:address":"910 S Friendswood Dr",
    "sg:city":"Friendswood",
    "sg:classifiers":[
        {
            "category":"Recreation",
            "type":"Entertainment"
        }
    ],
    "sg:phone":"+1 281 996 3220",
    "sg:postcode":"77565",
    "sg:province":"TX",
    "sg:tags":[
        "parks"
    ],
    "wof:name":"Friendswood Parks & Recreation",
    "wof:placetype":"venue"
},
  "geometry": {"coordinates":[-95.193918,29.523395],"type":"Point"}
}