{
  "type": "Feature",
  "properties": {
    "iso:country":"US",
    "sg:address":"1216 Houston Ave",
    "sg:city":"Houston",
    "sg:classifiers":[
        {
            "category":"Retail",
            "subcategory":"Laundry & Dry Cleaning",
            "type":"Services"
        }
    ],
    "sg:phone":"+1 713 224 1216",
    "sg:postcode":"77007",
    "sg:province":"TX",
    "sg:tags":[
        "rental",
        "uniform"
    ],
    "wof:name":"Triple D Uniform Rental Inc",
    "wof:placetype":"venue"
},
  "geometry": {"coordinates":[-95.372266,29.769846],"type":"Point"}
}