{
  "type": "Feature",
  "properties": {
    "iso:country":"US",
    "sg:address":"350 Equestrian Way",
    "sg:city":"Prosper",
    "sg:classifiers":[
        {
            "category":"Shopping",
            "subcategory":"Crafts & Fabrics",
            "type":"Retail Goods"
        }
    ],
    "sg:phone":"+1 972 347 2301",
    "sg:postcode":"75078",
    "sg:province":"TX",
    "sg:tags":[
        "sewing"
    ],
    "wof:name":"Sew Biz",
    "wof:placetype":"venue"
},
  "geometry": {"coordinates":[-96.77245000000001,33.238188],"type":"Point"}
}