{
  "type": "Feature",
  "properties": {
    "iso:country":"US",
    "sg:address":"5441 Gibson Dr",
    "sg:city":"Lewisville",
    "sg:classifiers":[
        {
            "category":"Social Services",
            "subcategory":"Child Care",
            "type":"Services"
        }
    ],
    "sg:phone":"+1 972 625 3904",
    "sg:postcode":"75056",
    "sg:province":"TX",
    "wof:name":"Donna Wright",
    "wof:placetype":"venue"
},
  "geometry": {"coordinates":[-96.87309,33.09608],"type":"Point"}
}