{
  "type": "Feature",
  "properties": {
    "iso:country":"US",
    "sg:address":"1101 W Park St",
    "sg:city":"Cedar Park",
    "sg:classifiers":[
        {
            "category":"Building & Trades",
            "subcategory":"Construction",
            "type":"Services"
        }
    ],
    "sg:phone":"+1 512 763 1313",
    "sg:postcode":"78613",
    "sg:province":"TX",
    "sg:tags":[
        "contractor",
        "nonresidential"
    ],
    "wof:name":"Elite Dry Wall Inc",
    "wof:placetype":"venue"
},
  "geometry": {"coordinates":[-97.837656,30.505149],"type":"Point"}
}