{
  "type": "Feature",
  "properties": {
    "iso:country":"US",
    "sg:address":"2004 Bedford Rd Ste 200",
    "sg:city":"Bedford",
    "sg:classifiers":[
        {
            "category":"Local Transit",
            "type":"Transportation"
        }
    ],
    "sg:phone":"+1 214 351 6306",
    "sg:postcode":"76021",
    "sg:province":"TX",
    "sg:tags":[
        "shuttle"
    ],
    "wof:name":"Aircar Inc",
    "wof:placetype":"venue"
},
  "geometry": {"coordinates":[-97.136357,32.844817],"type":"Point"}
}