{
  "type": "Feature",
  "properties": {
    "iso:country":"US",
    "sg:address":"5339 Easthampton Dr",
    "sg:city":"Houston",
    "sg:classifiers":[
        {
            "category":"Organizations",
            "subcategory":"Religious Organization",
            "type":"Services"
        }
    ],
    "sg:phone":"+1 281 449 7797",
    "sg:postcode":"77039",
    "sg:province":"TX",
    "sg:tags":[
        "church"
    ],
    "wof:name":"Iglesia Bautista Principe De",
    "wof:placetype":"venue"
},
  "geometry": {"coordinates":[-95.309091,29.901191],"type":"Point"}
}