{
  "type": "Feature",
  "properties": {
    "iso:country":"US",
    "sg:address":"2711 Inwood Rd",
    "sg:city":"Dallas",
    "sg:classifiers":[
        {
            "category":"Autos & Motor Vehicles",
            "subcategory":"Automobile Sales",
            "type":"Retail Goods"
        },
        {
            "category":"Wholesale",
            "subcategory":"Motor Vehicles",
            "type":"Manufacturing & Wholesale Goods"
        }
    ],
    "sg:phone":"+1 214 521 8710",
    "sg:postcode":"75235",
    "sg:province":"TX",
    "sg:tags":[
        "car",
        "used",
        "dealer"
    ],
    "wof:name":"Diamond Motor Co Inc",
    "wof:placetype":"venue"
},
  "geometry": {"coordinates":[-96.83396399999999,32.823608],"type":"Point"}
}