{
  "type": "Feature",
  "properties": {
    "iso:country":"US",
    "sg:address":"601 Co Rd 805A",
    "sg:city":"Cleburne",
    "sg:classifiers":[
        {
            "category":"Professional",
            "type":"Services"
        }
    ],
    "sg:phone":"+1 817 517 5596",
    "sg:postcode":"76031",
    "sg:province":"TX",
    "wof:name":"Suzis Unigues",
    "wof:placetype":"venue"
},
  "geometry": {"coordinates":[-97.348328,32.382394],"type":"Point"}
}