{
  "type": "Feature",
  "properties": {
    "iso:country":"US",
    "sg:address":"4700 E Main St",
    "sg:city":"Grand Prairie",
    "sg:classifiers":[
        {
            "category":"Sports & Exercise",
            "subcategory":"Race Track",
            "type":"Entertainment"
        }
    ],
    "sg:phone":"+1 972 264 5800",
    "sg:postcode":"75050",
    "sg:province":"TX",
    "wof:name":"Grand Prairie Speedway",
    "wof:placetype":"venue"
},
  "geometry": {"coordinates":[-96.94320399999999,32.749371],"type":"Point"}
}