{
  "type": "Feature",
  "properties": {
    "iso:country":"US",
    "sg:address":"911 25th St",
    "sg:city":"Canyon",
    "sg:classifiers":[
        {
            "category":"Retail",
            "subcategory":"Repair Shop",
            "type":"Services"
        }
    ],
    "sg:phone":"+1 806 655 3982",
    "sg:postcode":"79015",
    "sg:province":"TX",
    "sg:tags":[
        "welding"
    ],
    "wof:name":"Alans Welding",
    "wof:placetype":"venue"
},
  "geometry": {"coordinates":[-101.915863,34.974486],"type":"Point"}
}