{
  "type": "Feature",
  "properties": {
    "iso:country":"US",
    "sg:address":"250 S 10th St",
    "sg:city":"Slaton",
    "sg:classifiers":[
        {
            "category":"Banks & Credit Unions",
            "subcategory":"Investment Brokerage",
            "type":"Services"
        },
        {
            "category":"Insurance",
            "subcategory":"Hazard Insurance",
            "type":"Services"
        },
        {
            "category":"Banks & Credit Unions",
            "subcategory":"Financial Services",
            "type":"Services"
        }
    ],
    "sg:phone":"+1 806 828 3188",
    "sg:postcode":"79364",
    "sg:province":"TX",
    "sg:tags":[
        "advisory",
        "planner",
        "commercial",
        "business"
    ],
    "wof:name":"Meurer Agency",
    "wof:placetype":"venue"
},
  "geometry": {"coordinates":[-101.64510799999999,33.435946],"type":"Point"}
}