{
  "type": "Feature",
  "properties": {
    "iso:country":"US",
    "sg:address":"503 N Industrial Blvd",
    "sg:city":"Dallas",
    "sg:classifiers":[
        {
            "category":"Professional",
            "subcategory":"Lawyer & Legal Services",
            "type":"Services"
        }
    ],
    "sg:phone":"+1 214 760 3051",
    "sg:postcode":"75207",
    "sg:province":"TX",
    "sg:tags":[
        "attorney"
    ],
    "wof:name":"William C Dowdy",
    "wof:placetype":"venue"
},
  "geometry": {"coordinates":[-96.81372,32.779768],"type":"Point"}
}