{
  "type": "Feature",
  "properties": {
    "iso:country":"US",
    "sg:address":"2560 Electronic Ln",
    "sg:city":"Dallas",
    "sg:classifiers":[
        {
            "category":"Retail",
            "subcategory":"Repair Shop",
            "type":"Services"
        }
    ],
    "sg:phone":"+1 972 484 2800",
    "sg:postcode":"75220",
    "sg:province":"TX",
    "sg:tags":[
        "electronic",
        "electrical"
    ],
    "wof:name":"Advent Telecom",
    "wof:placetype":"venue"
},
  "geometry": {"coordinates":[-96.893109,32.877739],"type":"Point"}
}