{
  "type": "Feature",
  "properties": {
    "iso:country":"US",
    "sg:address":"3988 Highgrove Dr",
    "sg:city":"Dallas",
    "sg:classifiers":[
        {
            "category":"Banks & Credit Unions",
            "subcategory":"Bank",
            "type":"Services"
        }
    ],
    "sg:phone":"+1 214 352 5334",
    "sg:postcode":"75220",
    "sg:province":"TX",
    "sg:tags":[
        "mortgage"
    ],
    "wof:name":"Craig Mortgage Services Inc",
    "wof:placetype":"venue"
},
  "geometry": {"coordinates":[-96.84804699999999,32.86885],"type":"Point"}
}