{
  "type": "Feature",
  "properties": {
    "iso:country":"US",
    "sg:address":"1602 Island St",
    "sg:city":"Laredo",
    "sg:classifiers":[
        {
            "category":"Freight",
            "type":"Transportation"
        }
    ],
    "sg:phone":"+1 956 722 3951",
    "sg:postcode":"78041",
    "sg:province":"TX",
    "sg:tags":[
        "warehouse",
        "storage"
    ],
    "wof:name":"United States Cold Storage",
    "wof:placetype":"venue"
},
  "geometry": {"coordinates":[-99.512107,27.551698],"type":"Point"}
}