{
  "type": "Feature",
  "properties": {
    "iso:country":"US",
    "sg:address":"6302 Lewis Ln",
    "sg:city":"Rosharon",
    "sg:classifiers":[
        {
            "category":"Professional",
            "subcategory":"Management & Consulting",
            "type":"Services"
        }
    ],
    "sg:phone":"+1 281 369 2018",
    "sg:postcode":"77583",
    "sg:province":"TX",
    "wof:name":"Cosmic Computer Co",
    "wof:placetype":"venue"
},
  "geometry": {"coordinates":[-95.37398399999999,29.388363],"type":"Point"}
}