{
  "type": "Feature",
  "properties": {
    "iso:country":"US",
    "sg:address":"1508 Woodhaven Dr",
    "sg:city":"Mc Kinney",
    "sg:classifiers":[
        {
            "category":"Building & Trades",
            "subcategory":"Construction",
            "type":"Services"
        }
    ],
    "sg:phone":"+1 972 529 1394",
    "sg:postcode":"75070",
    "sg:province":"TX",
    "sg:tags":[
        "house"
    ],
    "wof:name":"Drees Custom Homes",
    "wof:placetype":"venue"
},
  "geometry": {"coordinates":[-96.723472,33.189662],"type":"Point"}
}