{
  "type": "Feature",
  "properties": {
    "iso:country":"US",
    "sg:address":"17610 Midway Rd",
    "sg:city":"Dallas",
    "sg:classifiers":[
        {
            "category":"Restaurant",
            "type":"Food & Drink"
        }
    ],
    "sg:phone":"+1 972 267 2797",
    "sg:postcode":"75287",
    "sg:province":"TX",
    "sg:tags":[
        "eating"
    ],
    "wof:name":"Cozys Restaurant & Bar",
    "wof:placetype":"venue"
},
  "geometry": {"coordinates":[-96.841998,32.98777],"type":"Point"}
}