{
  "type": "Feature",
  "properties": {
    "iso:country":"US",
    "sg:address":"11601 FM 2759",
    "sg:city":"Richmond",
    "sg:classifiers":[
        {
            "category":"Bars & Pubs",
            "type":"Food & Drink"
        }
    ],
    "sg:phone":"+1 281 545 9449",
    "sg:postcode":"77469",
    "sg:province":"TX",
    "sg:tags":[
        "club",
        "drinking",
        "night"
    ],
    "wof:name":"Jay's Place",
    "wof:placetype":"venue"
},
  "geometry": {"coordinates":[-95.62508699999999,29.518193],"type":"Point"}
}