{
  "type": "Feature",
  "properties": {
    "iso:country":"US",
    "sg:address":"2200 Ivanhoe Ln",
    "sg:city":"Abilene",
    "sg:classifiers":[
        {
            "category":"Retail",
            "subcategory":"Portrait Studio",
            "type":"Services"
        }
    ],
    "sg:phone":"+1 325 698 1144",
    "sg:postcode":"79605",
    "sg:province":"TX",
    "sg:tags":[
        "photo"
    ],
    "wof:name":"Mike Flippo Photography",
    "wof:placetype":"venue"
},
  "geometry": {"coordinates":[-99.764561,32.422852],"type":"Point"}
}