{
  "type": "Feature",
  "properties": {
    "iso:country":"US",
    "sg:address":"2111 Eldorado Pkwy",
    "sg:city":"Mc Kinney",
    "sg:classifiers":[
        {
            "category":"Professional",
            "subcategory":"Engineering",
            "type":"Services"
        }
    ],
    "sg:phone":"+1 214 544 8880",
    "sg:postcode":"75070",
    "sg:province":"TX",
    "sg:tags":[
        "civil",
        "engineer"
    ],
    "wof:name":"Pogue Engineering & Dev",
    "wof:placetype":"venue"
},
  "geometry": {"coordinates":[-96.643923,33.172077],"type":"Point"}
}