{
  "type": "Feature",
  "properties": {
    "iso:country":"US",
    "sg:address":"1113 W Baker Rd",
    "sg:city":"Baytown",
    "sg:classifiers":[
        {
            "category":"Banks & Credit Unions",
            "subcategory":"Bank",
            "type":"Services"
        }
    ],
    "sg:phone":"+1 281 422 4500",
    "sg:postcode":"77521",
    "sg:province":"TX",
    "sg:tags":[
        "loan"
    ],
    "wof:name":"Allied Home Mortgage Capital",
    "wof:placetype":"venue"
},
  "geometry": {"coordinates":[-94.980666,29.769723],"type":"Point"}
}