{
  "type": "Feature",
  "properties": {
    "iso:country":"US",
    "sg:address":"695 Dixie Dr",
    "sg:city":"Beaumont",
    "sg:classifiers":[
        {
            "category":"Shopping",
            "subcategory":"Hobbies, Toys, & Games",
            "type":"Retail Goods"
        }
    ],
    "sg:phone":"+1 409 842 1576",
    "sg:postcode":"77707",
    "sg:province":"TX",
    "wof:name":"Beatrice Smith",
    "wof:placetype":"venue"
},
  "geometry": {"coordinates":[-94.146157,30.071014],"type":"Point"}
}