{
  "type": "Feature",
  "properties": {
    "iso:country":"US",
    "sg:address":"4211 Todd Ln",
    "sg:city":"Austin",
    "sg:classifiers":[
        {
            "category":"Wholesale",
            "subcategory":"Hardware",
            "type":"Manufacturing & Wholesale Goods"
        }
    ],
    "sg:phone":"+1 512 416 9200",
    "sg:postcode":"78744",
    "sg:province":"TX",
    "sg:tags":[
        "plumbing",
        "fixture",
        "supply"
    ],
    "sg:website":"www.centralcomponents.com",
    "wof:name":"Central Components Co",
    "wof:placetype":"venue"
},
  "geometry": {"coordinates":[-97.738984,30.20933],"type":"Point"}
}