{
  "type": "Feature",
  "properties": {
    "iso:country":"US",
    "sg:address":"833 Pine St",
    "sg:city":"Gilmer",
    "sg:classifiers":[
        {
            "category":"Shopping",
            "subcategory":"Jewelry",
            "type":"Retail Goods"
        }
    ],
    "sg:phone":"+1 903 843 6201",
    "sg:postcode":"75644",
    "sg:province":"TX",
    "wof:name":"Cool Jewels",
    "wof:placetype":"venue"
},
  "geometry": {"coordinates":[-94.954083,32.737508],"type":"Point"}
}