{
  "type": "Feature",
  "properties": {
    "iso:country":"US",
    "sg:address":"7710 Bryonwood Dr",
    "sg:city":"Houston",
    "sg:classifiers":[
        {
            "category":"Professional",
            "subcategory":"Business Services",
            "type":"Services"
        }
    ],
    "sg:phone":"+1 713 957 8871",
    "sg:postcode":"77055",
    "sg:province":"TX",
    "wof:name":"Huntley Ventures Inc TCH",
    "wof:placetype":"venue"
},
  "geometry": {"coordinates":[-95.483262,29.787349],"type":"Point"}
}