{
  "type": "Feature",
  "properties": {
    "iso:country":"US",
    "sg:address":"917 Hackberry St",
    "sg:city":"Nacogdoches",
    "sg:classifiers":[
        {
            "category":"Professional",
            "subcategory":"Management & Consulting",
            "type":"Services"
        }
    ],
    "sg:phone":"+1 936 560 6455",
    "sg:postcode":"75964",
    "sg:province":"TX",
    "sg:tags":[
        "business"
    ],
    "wof:name":"Sevagram Enterprises",
    "wof:placetype":"venue"
},
  "geometry": {"coordinates":[-94.66243799999999,31.593123],"type":"Point"}
}