{
  "type": "Feature",
  "properties": {
    "iso:country":"US",
    "sg:address":"4101 Belt Line Rd",
    "sg:city":"Addison",
    "sg:classifiers":[
        {
            "category":"Restaurant",
            "type":"Food & Drink"
        }
    ],
    "sg:phone":"+1 214 352 5480",
    "sg:postcode":"75001",
    "sg:province":"TX",
    "sg:tags":[
        "eating"
    ],
    "wof:name":"Cafe Express",
    "wof:placetype":"venue"
},
  "geometry": {"coordinates":[-96.845703,32.954399],"type":"Point"}
}