{
  "type": "Feature",
  "properties": {
    "iso:country":"US",
    "sg:address":"209 E Market St",
    "sg:city":"Sinton",
    "sg:classifiers":[
        {
            "category":"Health Services",
            "subcategory":"Doctor",
            "type":"Services"
        }
    ],
    "sg:phone":"+1 361 364 0650",
    "sg:postcode":"78387",
    "sg:province":"TX",
    "sg:tags":[
        "physician",
        "family",
        "practice",
        "surgeons",
        "medicine"
    ],
    "wof:name":"Joseph Paul Puente Md",
    "wof:placetype":"venue"
},
  "geometry": {"coordinates":[-97.50912099999999,28.037769],"type":"Point"}
}