{
  "type": "Feature",
  "properties": {
    "iso:country":"US",
    "sg:address":"221 Spruce Ave",
    "sg:city":"Dumas",
    "sg:classifiers":[
        {
            "category":"Building & Trades",
            "subcategory":"Cleaning & Sanitation",
            "type":"Services"
        }
    ],
    "sg:phone":"+1 806 935 4068",
    "sg:postcode":"79029",
    "sg:province":"TX",
    "sg:tags":[
        "janitor"
    ],
    "wof:name":"AAA Cleaning",
    "wof:placetype":"venue"
},
  "geometry": {"coordinates":[-101.964844,35.870435],"type":"Point"}
}