{
  "type": "Feature",
  "properties": {
    "iso:country":"US",
    "sg:address":"719 Scott Ave",
    "sg:city":"Wichita Falls",
    "sg:classifiers":[
        {
            "category":"Professional",
            "type":"Services"
        }
    ],
    "sg:phone":"+1 940 766 6048",
    "sg:postcode":"76301",
    "sg:province":"TX",
    "sg:tags":[
        "consultant",
        "geological"
    ],
    "wof:name":"Robert L Mc Broom",
    "wof:placetype":"venue"
},
  "geometry": {"coordinates":[-98.492143,33.912128],"type":"Point"}
}