{
  "type": "Feature",
  "properties": {
    "iso:country":"US",
    "sg:address":"3740 Gattis School Rd",
    "sg:city":"Round Rock",
    "sg:classifiers":[
        {
            "category":"Banks & Credit Unions",
            "subcategory":"Bank",
            "type":"Services"
        }
    ],
    "sg:phone":"+1 512 421 5911",
    "sg:postcode":"78664",
    "sg:province":"TX",
    "wof:name":"Compass Bank",
    "wof:placetype":"venue"
},
  "geometry": {"coordinates":[-97.613315,30.497106],"type":"Point"}
}