{
  "type": "Feature",
  "properties": {
    "iso:country":"US",
    "sg:address":"1600 Airport Fwy",
    "sg:city":"Bedford",
    "sg:classifiers":[
        {
            "category":"Professional",
            "subcategory":"Management & Consulting",
            "type":"Services"
        }
    ],
    "sg:phone":"+1 817 358 0551",
    "sg:postcode":"76022",
    "sg:province":"TX",
    "sg:tags":[
        "aviation",
        "consultant"
    ],
    "wof:name":"Gate One",
    "wof:placetype":"venue"
},
  "geometry": {"coordinates":[-97.141379,32.836554],"type":"Point"}
}