{
  "type": "Feature",
  "properties": {
    "iso:country":"US",
    "sg:address":"4690 Southmost Rd",
    "sg:city":"Brownsville",
    "sg:classifiers":[
        {
            "category":"Restaurant",
            "type":"Food & Drink"
        }
    ],
    "sg:phone":"+1 956 542 4603",
    "sg:postcode":"78521",
    "sg:province":"TX",
    "wof:name":"Mc Donald's",
    "wof:placetype":"venue"
},
  "geometry": {"coordinates":[-97.4487,25.895361],"type":"Point"}
}