{
  "type": "Feature",
  "properties": {
    "iso:country":"US",
    "sg:address":"6106 Cary Dr",
    "sg:city":"Austin",
    "sg:classifiers":[
        {
            "category":"Professional",
            "subcategory":"Business Services",
            "type":"Services"
        }
    ],
    "sg:phone":"+1 512 452 3047",
    "sg:postcode":"78757",
    "sg:province":"TX",
    "wof:name":"Little Bear Association Inc",
    "wof:placetype":"venue"
},
  "geometry": {"coordinates":[-97.744884,30.340496],"type":"Point"}
}