{
  "type": "Feature",
  "properties": {
    "iso:country":"US",
    "sg:address":"2000 Coulter St",
    "sg:city":"Amarillo",
    "sg:classifiers":[
        {
            "category":"Restaurant",
            "type":"Food & Drink"
        }
    ],
    "sg:phone":"+1 806 355 9529",
    "sg:postcode":"79106",
    "sg:province":"TX",
    "sg:tags":[
        "eating"
    ],
    "wof:name":"Taco Bell",
    "wof:placetype":"venue"
},
  "geometry": {"coordinates":[-101.920429,35.190038],"type":"Point"}
}