{
  "type": "Feature",
  "properties": {
    "iso:country":"US",
    "sg:address":"923 Bent Creek Ct",
    "sg:city":"Richmond",
    "sg:classifiers":[
        {
            "category":"Shopping",
            "subcategory":"Gifts & Souvenirs",
            "type":"Retail Goods"
        }
    ],
    "sg:phone":"+1 281 232 3053",
    "sg:postcode":"77469",
    "sg:province":"TX",
    "wof:name":"Woodcraft",
    "wof:placetype":"venue"
},
  "geometry": {"coordinates":[-95.734844,29.617711],"type":"Point"}
}