{
  "type": "Feature",
  "properties": {
    "iso:country":"US",
    "sg:address":"310 Padre Blvd",
    "sg:city":"South Padre Island",
    "sg:classifiers":[
        {
            "category":"Banks & Credit Unions",
            "subcategory":"Bank",
            "type":"Services"
        }
    ],
    "sg:phone":"+1 956 761 5059",
    "sg:postcode":"78597",
    "sg:province":"TX",
    "sg:tags":[
        "depository",
        "banking"
    ],
    "wof:name":"Moneytree A T M",
    "wof:placetype":"venue"
},
  "geometry": {"coordinates":[-97.165663,26.079499],"type":"Point"}
}