{
  "type": "Feature",
  "properties": {
    "iso:country":"US",
    "sg:address":"107 W Damon St",
    "sg:city":"Terrell",
    "sg:classifiers":[
        {
            "category":"Building & Trades",
            "subcategory":"Plumbing",
            "type":"Services"
        }
    ],
    "sg:phone":"+1 972 524 1107",
    "sg:postcode":"75160",
    "sg:province":"TX",
    "sg:tags":[
        "contractor"
    ],
    "wof:name":"Moss Plumbing",
    "wof:placetype":"venue"
},
  "geometry": {"coordinates":[-96.27937300000001,32.747604],"type":"Point"}
}