{
  "type": "Feature",
  "properties": {
    "iso:country":"US",
    "sg:address":"2724 Edinboro Dr",
    "sg:city":"Arlington",
    "sg:classifiers":[
        {
            "category":"Wholesale",
            "subcategory":"Stationery",
            "type":"Manufacturing & Wholesale Goods"
        }
    ],
    "sg:phone":"+1 817 261 0257",
    "sg:postcode":"76012",
    "sg:province":"TX",
    "sg:tags":[
        "packaging",
        "material"
    ],
    "wof:name":"Liberty Supply Co",
    "wof:placetype":"venue"
},
  "geometry": {"coordinates":[-97.117991,32.780057],"type":"Point"}
}