{
  "type": "Feature",
  "properties": {
    "iso:country":"US",
    "sg:address":"6300 McCart Ave",
    "sg:city":"Fort Worth",
    "sg:classifiers":[
        {
            "category":"Retail",
            "subcategory":"Auto Repair",
            "type":"Services"
        }
    ],
    "sg:phone":"+1 817 361 0207",
    "sg:postcode":"76133",
    "sg:province":"TX",
    "sg:tags":[
        "repairing",
        "automobile",
        "general"
    ],
    "wof:name":"Neighbor's Garage",
    "wof:placetype":"venue"
},
  "geometry": {"coordinates":[-97.36454999999999,32.652788],"type":"Point"}
}