{
  "type": "Feature",
  "properties": {
    "iso:country":"US",
    "sg:address":"201 N Front St",
    "sg:city":"Freeport",
    "sg:classifiers":[
        {
            "category":"Recreation",
            "subcategory":"Marina",
            "type":"Entertainment"
        }
    ],
    "sg:phone":"+1 979 233 7552",
    "sg:postcode":"77541",
    "sg:province":"TX",
    "sg:tags":[
        "operation"
    ],
    "wof:name":"Marina 70",
    "wof:placetype":"venue"
},
  "geometry": {"coordinates":[-95.36514699999999,28.960891],"type":"Point"}
}