{
  "type": "Feature",
  "properties": {
    "iso:country":"US",
    "sg:address":"13 Glenway Dr",
    "sg:city":"Austin",
    "sg:classifiers":[
        {
            "category":"Professional",
            "subcategory":"Business Services",
            "type":"Services"
        }
    ],
    "sg:phone":"+1 512 608 0566",
    "sg:postcode":"78738",
    "sg:province":"TX",
    "wof:name":"Felice Woods Comapny",
    "wof:placetype":"venue"
},
  "geometry": {"coordinates":[-97.98408999999999,30.344342],"type":"Point"}
}