{
  "type": "Feature",
  "properties": {
    "iso:country":"US",
    "sg:address":"17001 Northchase Dr",
    "sg:city":"Houston",
    "sg:classifiers":[
        {
            "category":"Mining & Drilling",
            "type":"Manufacturing & Wholesale Goods"
        }
    ],
    "sg:phone":"+1 713 656 3636",
    "sg:postcode":"77060",
    "sg:province":"TX",
    "sg:tags":[
        "oil"
    ],
    "wof:name":"Exxon",
    "wof:placetype":"venue"
},
  "geometry": {"coordinates":[-95.406358,29.947837],"type":"Point"}
}