{
  "type": "Feature",
  "properties": {
    "iso:country":"US",
    "sg:address":"302 N Ave D",
    "sg:city":"Humble",
    "sg:classifiers":[
        {
            "category":"Building & Trades",
            "subcategory":"Pest Control",
            "type":"Services"
        }
    ],
    "sg:phone":"+1 281 852 5495",
    "sg:postcode":"77338",
    "sg:province":"TX",
    "wof:name":"IDF Pest Control",
    "wof:placetype":"venue"
},
  "geometry": {"coordinates":[-95.261252,29.998979],"type":"Point"}
}