{
  "type": "Feature",
  "properties": {
    "iso:country":"US",
    "sg:address":"410 Grosvenor Blvd",
    "sg:city":"San Antonio",
    "sg:classifiers":[
        {
            "category":"Shopping",
            "subcategory":"Discount & Variety Stores",
            "type":"Retail Goods"
        }
    ],
    "sg:phone":"+1 210 923 7760",
    "sg:postcode":"78221",
    "sg:province":"TX",
    "sg:tags":[
        "merchandise",
        "general"
    ],
    "wof:name":"Pedros",
    "wof:placetype":"venue"
},
  "geometry": {"coordinates":[-98.510679,29.354531],"type":"Point"}
}