{
  "type": "Feature",
  "properties": {
    "iso:country":"US",
    "sg:address":"3031 Van Buren Ave",
    "sg:city":"El Paso",
    "sg:classifiers":[
        {
            "category":"Building & Trades",
            "subcategory":"Construction",
            "type":"Services"
        }
    ],
    "sg:phone":"+1 915 566 1889",
    "sg:postcode":"79930",
    "sg:province":"TX",
    "sg:tags":[
        "nonresidential"
    ],
    "wof:name":"G M Construction",
    "wof:placetype":"venue"
},
  "geometry": {"coordinates":[-106.45832299999999,31.813152],"type":"Point"}
}