{
  "type": "Feature",
  "properties": {
    "iso:country":"US",
    "sg:address":"1120 Reitz Dr",
    "sg:city":"Cedar Hill",
    "sg:classifiers":[
        {
            "category":"Social Services",
            "type":"Services"
        }
    ],
    "sg:phone":"+1 972 299 0811",
    "sg:postcode":"75104",
    "sg:province":"TX",
    "wof:name":"NGoyala Community Development",
    "wof:placetype":"venue"
},
  "geometry": {"coordinates":[-96.920497,32.592806],"type":"Point"}
}