{
  "type": "Feature",
  "properties": {
    "iso:country":"US",
    "sg:address":"1104 N 4th St",
    "sg:city":"Killeen",
    "sg:classifiers":[
        {
            "category":"Organizations",
            "subcategory":"Religious Organization",
            "type":"Services"
        }
    ],
    "sg:phone":"+1 254 634 2772",
    "sg:postcode":"76541",
    "sg:province":"TX",
    "wof:name":"Immanuel Lutheran Church",
    "wof:placetype":"venue"
},
  "geometry": {"coordinates":[-97.726606,31.12771],"type":"Point"}
}