{
  "type": "Feature",
  "properties": {
    "iso:country":"US",
    "sg:address":"1216 Reedsport Pl",
    "sg:city":"Desoto",
    "sg:classifiers":[
        {
            "category":"Building & Trades",
            "subcategory":"Electrical",
            "type":"Services"
        }
    ],
    "sg:phone":"+1 972 223 8168",
    "sg:postcode":"75115",
    "sg:province":"TX",
    "sg:tags":[
        "electrician"
    ],
    "wof:name":"Packer Electric",
    "wof:placetype":"venue"
},
  "geometry": {"coordinates":[-96.889099,32.5993],"type":"Point"}
}