{
  "type": "Feature",
  "properties": {
    "iso:country":"US",
    "sg:address":"3835 Louetta Rd",
    "sg:city":"Spring",
    "sg:classifiers":[
        {
            "category":"Autos & Motor Vehicles",
            "subcategory":"Fuel & Gas Station",
            "type":"Retail Goods"
        }
    ],
    "sg:phone":"+1 281 350 3013",
    "sg:postcode":"77388",
    "sg:province":"TX",
    "sg:tags":[
        "station",
        "gasoline"
    ],
    "wof:name":"Shell",
    "wof:placetype":"venue"
},
  "geometry": {"coordinates":[-95.471632,30.049571],"type":"Point"}
}