{
  "type": "Feature",
  "properties": {
    "iso:country":"US",
    "sg:address":"3139 Fall St",
    "sg:city":"Houston",
    "sg:classifiers":[
        {
            "category":"Arena",
            "subcategory":"Sports Club",
            "type":"Entertainment"
        }
    ],
    "sg:phone":"+1 713 748 1316",
    "sg:postcode":"77054",
    "sg:province":"TX",
    "sg:tags":[
        "martial art"
    ],
    "sg:website":"www.jujutsuacademy.com",
    "wof:name":"Houston Jujutsu Academy",
    "wof:placetype":"venue"
},
  "geometry": {"coordinates":[-95.381618,29.698236],"type":"Point"}
}