{
  "type": "Feature",
  "properties": {
    "iso:country":"US",
    "sg:address":"300 S Trinity St",
    "sg:city":"Decatur",
    "sg:classifiers":[
        {
            "category":"Farming",
            "subcategory":"Livestock Farm",
            "type":"Manufacturing & Wholesale Goods"
        }
    ],
    "sg:phone":"+1 940 627 5325",
    "sg:postcode":"76234",
    "sg:province":"TX",
    "sg:tags":[
        "ranch"
    ],
    "wof:name":"Williams/Ferguson Ranch",
    "wof:placetype":"venue"
},
  "geometry": {"coordinates":[-97.586512,33.232724],"type":"Point"}
}