{
  "type": "Feature",
  "properties": {
    "iso:country":"US",
    "sg:address":"9114 US Hwy 80",
    "sg:city":"Fort Worth",
    "sg:classifiers":[
        {
            "category":"Food & Beverages",
            "subcategory":"Groceries & Convenience Stores",
            "type":"Retail Goods"
        }
    ],
    "sg:phone":"+1 817 244 2576",
    "sg:postcode":"76116",
    "sg:province":"TX",
    "wof:name":"Kroger",
    "wof:placetype":"venue"
},
  "geometry": {"coordinates":[-97.477141,32.724535],"type":"Point"}
}