{
  "type": "Feature",
  "properties": {
    "iso:country":"US",
    "sg:address":"5526 Dumfries Dr",
    "sg:city":"Houston",
    "sg:classifiers":[
        {
            "category":"Real Estate",
            "subcategory":"Real Estate Agent",
            "type":"Services"
        }
    ],
    "sg:phone":"+1 713 729 8338",
    "sg:postcode":"77096",
    "sg:province":"TX",
    "sg:tags":[
        "property",
        "management"
    ],
    "wof:name":"Calato Properties",
    "wof:placetype":"venue"
},
  "geometry": {"coordinates":[-95.48200199999999,29.671259],"type":"Point"}
}