{
  "type": "Feature",
  "properties": {
    "iso:country":"US",
    "sg:address":"5408 Austin Rd",
    "sg:city":"Brownsville",
    "sg:classifiers":[
        {
            "category":"Social Services",
            "subcategory":"Child Care",
            "type":"Services"
        }
    ],
    "sg:phone":"+1 956 831 3267",
    "sg:postcode":"78521",
    "sg:province":"TX",
    "wof:name":"D J Lerma Head Start Ctr",
    "wof:placetype":"venue"
},
  "geometry": {"coordinates":[-97.433553,25.929657],"type":"Point"}
}