{
  "type": "Feature",
  "properties": {
    "iso:country":"US",
    "sg:address":"2918 N Henderson Ave",
    "sg:city":"Dallas",
    "sg:classifiers":[
        {
            "category":"Home & Garden",
            "subcategory":"Home Furnishings",
            "type":"Retail Goods"
        },
        {
            "category":"Home & Garden",
            "subcategory":"Furniture",
            "type":"Retail Goods"
        }
    ],
    "sg:phone":"+1 214 823 0002",
    "sg:postcode":"75206",
    "sg:province":"TX",
    "sg:tags":[
        "decor",
        "store"
    ],
    "sg:website":"thewoodenhouse.org",
    "wof:name":"The Wooden House",
    "wof:placetype":"venue"
},
  "geometry": {"coordinates":[-96.785022,32.820803],"type":"Point"}
}