{
  "type": "Feature",
  "properties": {
    "iso:country":"US",
    "sg:address":"3333 Telephone Rd",
    "sg:city":"Houston",
    "sg:classifiers":[
        {
            "category":"Restaurant",
            "type":"Food & Drink"
        }
    ],
    "sg:phone":"+1 713 928 6588",
    "sg:postcode":"77023",
    "sg:province":"TX",
    "sg:tags":[
        "chinese"
    ],
    "wof:name":"Great Wall Chinese Restaurant",
    "wof:placetype":"venue"
},
  "geometry": {"coordinates":[-95.315276,29.711904],"type":"Point"}
}