{
  "type": "Feature",
  "properties": {
    "iso:country":"US",
    "sg:address":"3420 W Risinger Rd",
    "sg:city":"Fort Worth",
    "sg:classifiers":[
        {
            "category":"Social Services",
            "subcategory":"Child Care",
            "type":"Services"
        },
        {
            "category":"Education",
            "subcategory":"Preschool",
            "type":"Public Place"
        },
        {
            "category":"Education",
            "subcategory":"School",
            "type":"Public Place"
        }
    ],
    "sg:phone":"+1 817 292 5599",
    "sg:postcode":"76123",
    "sg:province":"TX",
    "sg:tags":[
        "elementary",
        "day"
    ],
    "sg:website":"www.childrenslighthouse.com",
    "wof:name":"Childrens Lighthouse",
    "wof:placetype":"venue"
},
  "geometry": {"coordinates":[-97.370603,32.615046],"type":"Point"}
}