{
  "type": "Feature",
  "properties": {
    "iso:country":"US",
    "sg:address":"727 W Ware Blvd",
    "sg:city":"San Antonio",
    "sg:classifiers":[
        {
            "category":"Building & Trades",
            "subcategory":"Landscaping Services",
            "type":"Services"
        }
    ],
    "sg:phone":"+1 210 922 4190",
    "sg:postcode":"78221",
    "sg:province":"TX",
    "sg:tags":[
        "lawn",
        "maintenance",
        "grounds"
    ],
    "wof:name":"Gil's Cut Rite Lawn Care",
    "wof:placetype":"venue"
},
  "geometry": {"coordinates":[-98.488365,29.349017],"type":"Point"}
}