{
  "type": "Feature",
  "properties": {
    "iso:country":"US",
    "sg:address":"2406 Dublin Dr",
    "sg:city":"Carrollton",
    "sg:classifiers":[
        {
            "category":"Autos & Motor Vehicles",
            "subcategory":"Auto Supplies",
            "type":"Retail Goods"
        }
    ],
    "sg:phone":"+1 972 380 8200",
    "sg:postcode":"75006",
    "sg:province":"TX",
    "sg:tags":[
        "glass"
    ],
    "wof:name":"Glass Max",
    "wof:placetype":"venue"
},
  "geometry": {"coordinates":[-96.861986,32.975909],"type":"Point"}
}