{
  "type": "Feature",
  "properties": {
    "iso:country":"US",
    "sg:address":"2050 Ray Ave",
    "sg:city":"Groves",
    "sg:classifiers":[
        {
            "category":"Food & Beverages",
            "subcategory":"Candy",
            "type":"Retail Goods"
        }
    ],
    "sg:phone":"+1 409 963 1318",
    "sg:postcode":"77619",
    "sg:province":"TX",
    "sg:tags":[
        "confectionery"
    ],
    "wof:name":"Pj Enterprises",
    "wof:placetype":"venue"
},
  "geometry": {"coordinates":[-93.902913,29.931872],"type":"Point"}
}