{
  "type": "Feature",
  "properties": {
    "iso:country":"US",
    "sg:address":"137 S Main St",
    "sg:city":"Irving",
    "sg:classifiers":[
        {
            "category":"Restaurant",
            "type":"Food & Drink"
        }
    ],
    "sg:phone":"+1 972 259 2939",
    "sg:postcode":"75060",
    "sg:province":"TX",
    "sg:tags":[
        "brazilian"
    ],
    "sg:website":"www.villasgrill.com",
    "wof:name":"Villas Grill",
    "wof:placetype":"venue"
},
  "geometry": {"coordinates":[-96.94658099999999,32.813035],"type":"Point"}
}