{
  "type": "Feature",
  "properties": {
    "iso:country":"US",
    "sg:address":"114 N Hill Ave",
    "sg:city":"Tyler",
    "sg:classifiers":[
        {
            "category":"Shopping",
            "type":"Retail Goods"
        }
    ],
    "sg:phone":"+1 903 595 1036",
    "sg:postcode":"75702",
    "sg:province":"TX",
    "sg:tags":[
        "candle"
    ],
    "wof:name":"Light Of The World Candle Co",
    "wof:placetype":"venue"
},
  "geometry": {"coordinates":[-95.31805900000001,32.35156],"type":"Point"}
}