{
  "type": "Feature",
  "properties": {
    "iso:country":"US",
    "sg:address":"417 E Texas Ave",
    "sg:city":"Mart",
    "sg:classifiers":[
        {
            "category":"Autos & Motor Vehicles",
            "subcategory":"Auto Supplies",
            "type":"Retail Goods"
        }
    ],
    "sg:phone":"+1 254 876 2290",
    "sg:postcode":"76664",
    "sg:province":"TX",
    "wof:name":"Lynd Auto Parts",
    "wof:placetype":"venue"
},
  "geometry": {"coordinates":[-96.833713,31.542431],"type":"Point"}
}