{
  "type": "Feature",
  "properties": {
    "iso:country":"US",
    "sg:address":"145 Caddo Dr",
    "sg:city":"Abilene",
    "sg:classifiers":[
        {
            "category":"Building & Trades",
            "subcategory":"Construction",
            "type":"Services"
        }
    ],
    "sg:phone":"+1 325 692 5389",
    "sg:postcode":"79602",
    "sg:province":"TX",
    "sg:tags":[
        "carpentry",
        "contractor"
    ],
    "wof:name":"Moore Construction Inc",
    "wof:placetype":"venue"
},
  "geometry": {"coordinates":[-99.721416,32.396974],"type":"Point"}
}