{
  "type": "Feature",
  "properties": {
    "iso:country":"US",
    "sg:address":"10753 Co Rd 4038",
    "sg:city":"Scurry",
    "sg:classifiers":[
        {
            "category":"Retail",
            "subcategory":"Self-service Laundry",
            "type":"Services"
        }
    ],
    "sg:phone":"+1 972 452 8965",
    "sg:postcode":"75158",
    "sg:province":"TX",
    "sg:tags":[
        "coin"
    ],
    "wof:name":"Susans Soaps & More",
    "wof:placetype":"venue"
},
  "geometry": {"coordinates":[-96.355825,32.48999],"type":"Point"}
}