{
  "type": "Feature",
  "properties": {
    "iso:country":"US",
    "sg:address":"7945 Parral Dr",
    "sg:city":"El Paso",
    "sg:classifiers":[
        {
            "category":"Building & Trades",
            "subcategory":"Equipment Rental",
            "type":"Services"
        }
    ],
    "sg:phone":"+1 915 595 4567",
    "sg:postcode":"79915",
    "sg:province":"TX",
    "sg:tags":[
        "medical"
    ],
    "wof:name":"Associated Physicians",
    "wof:placetype":"venue"
},
  "geometry": {"coordinates":[-106.34669,31.75065],"type":"Point"}
}