{
  "type": "Feature",
  "properties": {
    "iso:country":"US",
    "sg:address":"516 S 1st St",
    "sg:city":"Muleshoe",
    "sg:classifiers":[
        {
            "category":"Shopping",
            "subcategory":"Florist",
            "type":"Retail Goods"
        }
    ],
    "sg:phone":"+1 806 272 4287",
    "sg:postcode":"79347",
    "sg:province":"TX",
    "wof:name":"Lastings Impressions",
    "wof:placetype":"venue"
},
  "geometry": {"coordinates":[-102.72699299999999,34.222804],"type":"Point"}
}