{
  "type": "Feature",
  "properties": {
    "iso:country":"US",
    "sg:address":"4516 Avebury Dr",
    "sg:city":"Plano",
    "sg:classifiers":[
        {
            "category":"Professional",
            "subcategory":"Business Services",
            "type":"Services"
        }
    ],
    "sg:phone":"+1 972 377 2664",
    "sg:postcode":"75024",
    "sg:province":"TX",
    "wof:name":"Eminent Technologies Inc",
    "wof:placetype":"venue"
},
  "geometry": {"coordinates":[-96.783444,33.095292],"type":"Point"}
}