{
  "type": "Feature",
  "properties": {
    "iso:country":"US",
    "sg:address":"11515 Camphorwood Dr",
    "sg:city":"Houston",
    "sg:classifiers":[
        {
            "category":"Shopping",
            "subcategory":"Gifts & Souvenirs",
            "type":"Retail Goods"
        }
    ],
    "sg:phone":"+1 281 484 8344",
    "sg:postcode":"77089",
    "sg:province":"TX",
    "wof:name":"Balloon Menagerie",
    "wof:placetype":"venue"
},
  "geometry": {"coordinates":[-95.210796,29.59663],"type":"Point"}
}