{
  "type": "Feature",
  "properties": {
    "iso:country":"US",
    "sg:address":"718 E Main St",
    "sg:city":"Hamilton",
    "sg:classifiers":[
        {
            "category":"Museum",
            "type":"Entertainment"
        }
    ],
    "sg:phone":"+1 254 386 5607",
    "sg:postcode":"76531",
    "sg:province":"TX",
    "sg:tags":[
        "gallery"
    ],
    "wof:name":"Hamilton Cnty Hstorical Museum",
    "wof:placetype":"venue"
},
  "geometry": {"coordinates":[-98.11551900000001,31.701231],"type":"Point"}
}