{
  "type": "Feature",
  "properties": {
    "iso:country":"US",
    "sg:address":"8401 Boat Club Rd",
    "sg:city":"Fort Worth",
    "sg:classifiers":[
        {
            "category":"Retail",
            "subcategory":"Laundry & Dry Cleaning",
            "type":"Services"
        }
    ],
    "sg:phone":"+1 817 236 5187",
    "sg:postcode":"76179",
    "sg:province":"TX",
    "sg:tags":[
        "cleaners"
    ],
    "wof:name":"Comet Cleaners",
    "wof:placetype":"venue"
},
  "geometry": {"coordinates":[-97.42585099999999,32.878468],"type":"Point"}
}