{
  "type": "Feature",
  "properties": {
    "iso:country":"US",
    "sg:address":"1206 W 12th St",
    "sg:city":"Caldwell",
    "sg:classifiers":[
        {
            "category":"Organizations",
            "subcategory":"Religious Organization",
            "type":"Services"
        }
    ],
    "sg:phone":"+1 979 567 3712",
    "sg:postcode":"77836",
    "sg:province":"TX",
    "sg:tags":[
        "church"
    ],
    "wof:name":"First Assembly Of God Church",
    "wof:placetype":"venue"
},
  "geometry": {"coordinates":[-96.699625,30.524466],"type":"Point"}
}