{
  "type": "Feature",
  "properties": {
    "iso:country":"US",
    "sg:address":"120 Hardwicke Ln",
    "sg:city":"Little Elm",
    "sg:classifiers":[
        {
            "category":"Banks & Credit Unions",
            "subcategory":"Financial Services",
            "type":"Services"
        }
    ],
    "sg:phone":"+1 972 294 8330",
    "sg:postcode":"75068",
    "sg:province":"TX",
    "sg:tags":[
        "trust",
        "investment",
        "real estate"
    ],
    "wof:name":"Rhea & Marsh Investment",
    "wof:placetype":"venue"
},
  "geometry": {"coordinates":[-96.93835,33.158809],"type":"Point"}
}