{
  "type": "Feature",
  "properties": {
    "iso:country":"US",
    "sg:address":"1160 Thorpe Ln",
    "sg:city":"San Marcos",
    "sg:classifiers":[
        {
            "category":"Personal",
            "subcategory":"Beauty Salon",
            "type":"Services"
        }
    ],
    "sg:phone":"+1 512 805 8384",
    "sg:postcode":"78666",
    "sg:province":"TX",
    "sg:website":"www.tgf.com",
    "wof:name":"TGF Haircutters",
    "wof:placetype":"venue"
},
  "geometry": {"coordinates":[-97.91889399999999,29.891605],"type":"Point"}
}