{
  "type": "Feature",
  "properties": {
    "iso:country":"US",
    "sg:address":"1605 E Abram St",
    "sg:city":"Arlington",
    "sg:classifiers":[
        {
            "category":"Manufacturing",
            "subcategory":"Rubber & Plastics",
            "type":"Manufacturing & Wholesale Goods"
        }
    ],
    "sg:phone":"+1 817 860 5645",
    "sg:postcode":"76010",
    "sg:province":"TX",
    "sg:tags":[
        "tires-wholesale",
        "manufacturer"
    ],
    "wof:name":"A Guaranteed Tire &Wheels",
    "wof:placetype":"venue"
},
  "geometry": {"coordinates":[-97.086624,32.73547],"type":"Point"}
}