{
  "type": "Feature",
  "properties": {
    "iso:country":"US",
    "sg:address":"4333 Woodbluff Dr",
    "sg:city":"Mesquite",
    "sg:classifiers":[
        {
            "category":"Real Estate",
            "subcategory":"Developer",
            "type":"Services"
        }
    ],
    "sg:phone":"+1 972 226 1360",
    "sg:postcode":"75150",
    "sg:province":"TX",
    "wof:name":"Mw Properties",
    "wof:placetype":"venue"
},
  "geometry": {"coordinates":[-96.599465,32.82422],"type":"Point"}
}