{
  "type": "Feature",
  "properties": {
    "iso:country":"US",
    "sg:address":"1503 W 35th St",
    "sg:city":"Austin",
    "sg:classifiers":[
        {
            "category":"Fast Food",
            "type":"Food & Drink"
        }
    ],
    "sg:phone":"+1 512 452 3287",
    "sg:postcode":"78703",
    "sg:province":"TX",
    "sg:tags":[
        "burger"
    ],
    "sg:website":"www.hill-bertsburgers.com",
    "wof:name":"Hill-Bert's Burgers",
    "wof:placetype":"venue"
},
  "geometry": {"coordinates":[-97.74975499999999,30.306067],"type":"Point"}
}