{
  "type": "Feature",
  "properties": {
    "iso:country":"US",
    "sg:address":"11401 State Hwy 36",
    "sg:city":"Jonesboro",
    "sg:classifiers":[
        {
            "category":"Professional",
            "type":"Services"
        }
    ],
    "sg:phone":"+1 254 463 4831",
    "sg:postcode":"76538",
    "sg:province":"TX",
    "sg:tags":[
        "establishment"
    ],
    "wof:name":"Outlaws & Inlaws Red Barn",
    "wof:placetype":"venue"
},
  "geometry": {"coordinates":[-97.869411,31.611969],"type":"Point"}
}