{
  "type": "Feature",
  "properties": {
    "iso:country":"US",
    "sg:address":"1407 E Houston St",
    "sg:city":"Cleveland",
    "sg:classifiers":[
        {
            "category":"Freight",
            "type":"Transportation"
        }
    ],
    "sg:phone":"+1 281 593 2323",
    "sg:postcode":"77327",
    "sg:province":"TX",
    "sg:tags":[
        "special"
    ],
    "wof:name":"321 Mini Storage",
    "wof:placetype":"venue"
},
  "geometry": {"coordinates":[-95.071387,30.340943],"type":"Point"}
}