{
  "type": "Feature",
  "properties": {
    "iso:country":"US",
    "sg:address":"942 Bridget Dr",
    "sg:city":"Dallas",
    "sg:classifiers":[
        {
            "category":"Education",
            "subcategory":"Special Training",
            "type":"Public Place"
        }
    ],
    "sg:phone":"+1 214 324 2224",
    "sg:postcode":"75218",
    "sg:province":"TX",
    "sg:tags":[
        "instruction",
        "music"
    ],
    "wof:name":"East Dallas Children's Music",
    "wof:placetype":"venue"
},
  "geometry": {"coordinates":[-96.70200800000001,32.842287],"type":"Point"}
}