{
  "type": "Feature",
  "properties": {
    "iso:country":"US",
    "sg:address":"1167 Arrowhead Trl",
    "sg:city":"San Antonio",
    "sg:classifiers":[
        {
            "category":"Retail",
            "subcategory":"Repair Shop",
            "type":"Services"
        }
    ],
    "sg:phone":"+1 210 523 8773",
    "sg:postcode":"78245",
    "sg:province":"TX",
    "sg:tags":[
        "equipment",
        "conditioning",
        "air"
    ],
    "wof:name":"Master-Tech Air Conditioning",
    "wof:placetype":"venue"
},
  "geometry": {"coordinates":[-98.693471,29.428791],"type":"Point"}
}