{
  "type": "Feature",
  "properties": {
    "iso:country":"US",
    "sg:address":"122 Mimms Ave",
    "sg:city":"Nacogdoches",
    "sg:classifiers":[
        {
            "category":"Organizations",
            "subcategory":"Professional Association",
            "type":"Services"
        }
    ],
    "sg:phone":"+1 936 560 2965",
    "sg:postcode":"75961",
    "sg:province":"TX",
    "sg:tags":[
        "employer"
    ],
    "sg:website":"www.napatdc.org",
    "wof:name":"Nacogdoches Area Physicians Association",
    "wof:placetype":"venue"
},
  "geometry": {"coordinates":[-94.65434,31.607847],"type":"Point"}
}