{
  "type": "Feature",
  "properties": {
    "iso:country":"US",
    "sg:address":"1305 Oakhurst Dr",
    "sg:city":"Wichita Falls",
    "sg:classifiers":[
        {
            "category":"Retail",
            "subcategory":"Auto Repair",
            "type":"Services"
        }
    ],
    "sg:phone":"+1 940 322 6416",
    "sg:postcode":"76302",
    "sg:province":"TX",
    "sg:tags":[
        "contracting",
        "electrical"
    ],
    "wof:name":"Dt Electric",
    "wof:placetype":"venue"
},
  "geometry": {"coordinates":[-98.48844699999999,33.870777],"type":"Point"}
}