{
  "type": "Feature",
  "properties": {
    "iso:country":"US",
    "sg:address":"404 Houston St",
    "sg:city":"Kilgore",
    "sg:classifiers":[
        {
            "category":"Mining & Drilling",
            "type":"Manufacturing & Wholesale Goods"
        }
    ],
    "sg:phone":"+1 903 983 1432",
    "sg:postcode":"75662",
    "sg:province":"TX",
    "sg:tags":[
        "field"
    ],
    "wof:name":"Donnell Pump & Supply",
    "wof:placetype":"venue"
},
  "geometry": {"coordinates":[-94.877014,32.379587],"type":"Point"}
}