{
  "type": "Feature",
  "properties": {
    "iso:country":"US",
    "sg:address":"1803 S Presa St",
    "sg:city":"San Antonio",
    "sg:classifiers":[
        {
            "category":"Organizations",
            "subcategory":"Labor Organization",
            "type":"Services"
        }
    ],
    "sg:phone":"+1 210 532 3572",
    "sg:postcode":"78210",
    "sg:province":"TX",
    "wof:name":"Teamsters Local Union 1110",
    "wof:placetype":"venue"
},
  "geometry": {"coordinates":[-98.483205,29.402629],"type":"Point"}
}