{
  "type": "Feature",
  "properties": {
    "iso:country":"US",
    "sg:address":"902 Ross Ave",
    "sg:city":"Dallas",
    "sg:classifiers":[
        {
            "category":"Food & Beverages",
            "subcategory":"Bakery",
            "type":"Retail Goods"
        }
    ],
    "sg:phone":"+1 214 999 0530",
    "sg:postcode":"75202",
    "sg:province":"TX",
    "sg:tags":[
        "sandwich"
    ],
    "wof:name":"Go Philly",
    "wof:placetype":"venue"
},
  "geometry": {"coordinates":[-96.80510099999999,32.782019],"type":"Point"}
}