{
  "type": "Feature",
  "properties": {
    "iso:country":"US",
    "sg:address":"1771 Terre Colony Ct",
    "sg:city":"Dallas",
    "sg:classifiers":[
        {
            "category":"Personal",
            "subcategory":"Adult",
            "type":"Services"
        }
    ],
    "sg:phone":"+1 214 748 6116",
    "sg:postcode":"75212",
    "sg:province":"TX",
    "sg:tags":[
        "escort"
    ],
    "wof:name":"America's Most Wanted Blond",
    "wof:placetype":"venue"
},
  "geometry": {"coordinates":[-96.869451,32.768999],"type":"Point"}
}