{
  "type": "Feature",
  "properties": {
    "iso:country":"US",
    "sg:address":"9508 Co Rd 415",
    "sg:city":"Tyler",
    "sg:classifiers":[
        {
            "category":"Farming",
            "subcategory":"Livestock Farm",
            "type":"Manufacturing & Wholesale Goods"
        }
    ],
    "sg:phone":"+1 903 593 2095",
    "sg:postcode":"75704",
    "sg:province":"TX",
    "sg:tags":[
        "hay",
        "cattle"
    ],
    "wof:name":"Judd Long",
    "wof:placetype":"venue"
},
  "geometry": {"coordinates":[-95.484632,32.411059],"type":"Point"}
}