{
  "type": "Feature",
  "properties": {
    "iso:country":"US",
    "sg:address":"179 S Watson Rd",
    "sg:city":"Arlington",
    "sg:classifiers":[
        {
            "category":"Home & Garden",
            "subcategory":"Home Furnishings",
            "type":"Retail Goods"
        }
    ],
    "sg:phone":"+1 817 385 0300",
    "sg:postcode":"76010",
    "sg:province":"TX",
    "sg:tags":[
        "linen"
    ],
    "wof:name":"Vianney",
    "wof:placetype":"venue"
},
  "geometry": {"coordinates":[-97.06179899999999,32.737376],"type":"Point"}
}