{
  "type": "Feature",
  "properties": {
    "iso:country":"US",
    "sg:address":"1904 Hill St",
    "sg:city":"Killeen",
    "sg:classifiers":[
        {
            "category":"Social Services",
            "subcategory":"Child Care",
            "type":"Services"
        }
    ],
    "sg:phone":"+1 254 680 3180",
    "sg:postcode":"76543",
    "sg:province":"TX",
    "sg:tags":[
        "childcare"
    ],
    "wof:name":"LEARNING TOGETHER FAMILY",
    "wof:placetype":"venue"
},
  "geometry": {"coordinates":[-97.682599,31.124082],"type":"Point"}
}