{
  "type": "Feature",
  "properties": {
    "iso:country":"US",
    "sg:address":"500 W Texas Ave",
    "sg:city":"Mart",
    "sg:classifiers":[
        {
            "category":"Organizations",
            "subcategory":"Religious Organization",
            "type":"Services"
        }
    ],
    "sg:phone":"+1 254 876 2724",
    "sg:postcode":"76664",
    "sg:province":"TX",
    "sg:tags":[
        "church"
    ],
    "wof:name":"Mt Zion Baptist Church",
    "wof:placetype":"venue"
},
  "geometry": {"coordinates":[-96.841326,31.53852],"type":"Point"}
}