{
  "type": "Feature",
  "properties": {
    "iso:country":"US",
    "sg:address":"1701 Reserve St",
    "sg:city":"Garland",
    "sg:classifiers":[
        {
            "category":"Manufacturing",
            "subcategory":"Tools & Machinery",
            "type":"Manufacturing & Wholesale Goods"
        },
        {
            "category":"Retail",
            "subcategory":"Auto Repair",
            "type":"Services"
        }
    ],
    "sg:phone":"+1 214 503 1705",
    "sg:postcode":"75042",
    "sg:province":"TX",
    "sg:tags":[
        "engine",
        "automotive",
        "supply"
    ],
    "wof:name":"E T Automotive Inc",
    "wof:placetype":"venue"
},
  "geometry": {"coordinates":[-96.686008,32.895958],"type":"Point"}
}