{
  "type": "Feature",
  "properties": {
    "iso:country":"US",
    "sg:address":"917 Hwy 81 N",
    "sg:city":"Bowie",
    "sg:classifiers":[
        {
            "category":"Freight",
            "type":"Transportation"
        }
    ],
    "sg:phone":"+1 940 872 5493",
    "sg:postcode":"76230",
    "sg:province":"TX",
    "sg:tags":[
        "commercial",
        "storage"
    ],
    "wof:name":"Bowie Storage",
    "wof:placetype":"venue"
},
  "geometry": {"coordinates":[-97.856711,33.568635],"type":"Point"}
}