{
  "type": "Feature",
  "properties": {
    "iso:country":"US",
    "sg:address":"211 E Caesar Ave",
    "sg:city":"Kingsville",
    "sg:classifiers":[
        {
            "category":"Professional",
            "type":"Services"
        }
    ],
    "sg:phone":"+1 361 592 4780",
    "sg:postcode":"78363",
    "sg:province":"TX",
    "sg:tags":[
        "establishment"
    ],
    "wof:name":"Skylink",
    "wof:placetype":"venue"
},
  "geometry": {"coordinates":[-97.866175,27.506599],"type":"Point"}
}