{
  "type": "Feature",
  "properties": {
    "iso:country":"US",
    "sg:address":"3417 Bryn Mawr Dr",
    "sg:city":"Dallas",
    "sg:classifiers":[
        {
            "category":"Professional",
            "subcategory":"Business Services",
            "type":"Services"
        }
    ],
    "sg:phone":"+1 214 373 1370",
    "sg:postcode":"75225",
    "sg:province":"TX",
    "wof:name":"Mary Elizabeth Canon Interiors",
    "wof:placetype":"venue"
},
  "geometry": {"coordinates":[-96.78888499999999,32.855917],"type":"Point"}
}