{
  "type": "Feature",
  "properties": {
    "iso:country":"US",
    "sg:address":"3128 Saba Ln",
    "sg:city":"Port Neches",
    "sg:classifiers":[
        {
            "category":"Building & Trades",
            "subcategory":"Construction",
            "type":"Services"
        }
    ],
    "sg:phone":"+1 409 724 2719",
    "sg:postcode":"77651",
    "sg:province":"TX",
    "sg:tags":[
        "repairing",
        "remodeling",
        "contractor"
    ],
    "wof:name":"Bru-Co Aluminum",
    "wof:placetype":"venue"
},
  "geometry": {"coordinates":[-93.95533500000001,29.953352],"type":"Point"}
}