{
  "type": "Feature",
  "properties": {
    "iso:country":"US",
    "sg:address":"5623 Morningside Ave",
    "sg:city":"Dallas",
    "sg:classifiers":[
        {
            "category":"Building & Trades",
            "subcategory":"Construction",
            "type":"Services"
        }
    ],
    "sg:phone":"+1 972 709 3636",
    "sg:postcode":"75206",
    "sg:province":"TX",
    "sg:tags":[
        "painter"
    ],
    "wof:name":"Jade Painting",
    "wof:placetype":"venue"
},
  "geometry": {"coordinates":[-96.771202,32.829201],"type":"Point"}
}