{
  "type": "Feature",
  "properties": {
    "iso:country":"US",
    "sg:address":"4700 Andrews Hwy",
    "sg:city":"Odessa",
    "sg:classifiers":[
        {
            "category":"Retail",
            "subcategory":"Animal Services",
            "type":"Services"
        }
    ],
    "sg:phone":"+1 432 550 9200",
    "sg:postcode":"79762",
    "sg:province":"TX",
    "sg:tags":[
        "pet",
        "boarding",
        "sitting"
    ],
    "wof:name":"Pampered Pet Haven",
    "wof:placetype":"venue"
},
  "geometry": {"coordinates":[-102.386982,31.888827],"type":"Point"}
}