{
  "type": "Feature",
  "properties": {
    "iso:country":"US",
    "sg:address":"11508 Chancellroy Dr",
    "sg:city":"Austin",
    "sg:classifiers":[
        {
            "category":"Professional",
            "subcategory":"Business Services",
            "type":"Services"
        }
    ],
    "sg:phone":"+1 512 219 9117",
    "sg:postcode":"78759",
    "sg:province":"TX",
    "wof:name":"Greenwich Meridian Enterprises",
    "wof:placetype":"venue"
},
  "geometry": {"coordinates":[-97.779163,30.431133],"type":"Point"}
}