{
  "type": "Feature",
  "properties": {
    "iso:country":"US",
    "sg:address":"10731 Goodnight Ln Ste D",
    "sg:city":"Dallas",
    "sg:classifiers":[
        {
            "category":"Home & Garden",
            "subcategory":"Garden Supply",
            "type":"Retail Goods"
        }
    ],
    "sg:phone":"+1 972 910 9996",
    "sg:postcode":"75220",
    "sg:province":"TX",
    "sg:tags":[
        "nursery",
        "gardening"
    ],
    "wof:name":"Jorge's Lawn Equipment",
    "wof:placetype":"venue"
},
  "geometry": {"coordinates":[-96.902513,32.872203],"type":"Point"}
}