{
  "type": "Feature",
  "properties": {
    "iso:country":"US",
    "sg:address":"13 Via Placita",
    "sg:city":"El Paso",
    "sg:classifiers":[
        {
            "category":"Manufacturing",
            "subcategory":"Glass & Minerals",
            "type":"Manufacturing & Wholesale Goods"
        }
    ],
    "sg:phone":"+1 915 859 5166",
    "sg:postcode":"79927",
    "sg:province":"TX",
    "sg:tags":[
        "ready",
        "concrete",
        "mfg"
    ],
    "wof:name":"Mix Tape Connect",
    "wof:placetype":"venue"
},
  "geometry": {"coordinates":[-106.29225,31.682593],"type":"Point"}
}