{
  "type": "Feature",
  "properties": {
    "iso:country":"US",
    "sg:address":"3443 el Dorado Blvd",
    "sg:city":"Missouri City",
    "sg:classifiers":[
        {
            "category":"Shopping",
            "subcategory":"Catalog Store",
            "type":"Retail Goods"
        }
    ],
    "sg:phone":"+1 281 499 4625",
    "sg:postcode":"77459",
    "sg:province":"TX",
    "sg:tags":[
        "mail",
        "house"
    ],
    "wof:name":"C C G Creations",
    "wof:placetype":"venue"
},
  "geometry": {"coordinates":[-95.5595,29.576897],"type":"Point"}
}