{
  "type": "Feature",
  "properties": {
    "iso:country":"US",
    "sg:address":"1399 US Hwy 79",
    "sg:city":"Carthage",
    "sg:classifiers":[
        {
            "category":"Retail",
            "subcategory":"Auto Repair",
            "type":"Services"
        }
    ],
    "sg:phone":"+1 903 693 5330",
    "sg:postcode":"75633",
    "sg:province":"TX",
    "sg:tags":[
        "general"
    ],
    "wof:name":"Mom & Pops Auto/Tire/Lawnmow",
    "wof:placetype":"venue"
},
  "geometry": {"coordinates":[-94.3942,32.163337],"type":"Point"}
}