{
  "type": "Feature",
  "properties": {
    "iso:country":"US",
    "sg:address":"11222 FM 2021",
    "sg:city":"Lufkin",
    "sg:classifiers":[
        {
            "category":"Retail",
            "subcategory":"Auto Repair",
            "type":"Services"
        }
    ],
    "sg:phone":"+1 936 632 9313",
    "sg:postcode":"75904",
    "sg:province":"TX",
    "sg:tags":[
        "body"
    ],
    "wof:name":"C C Enterprises",
    "wof:placetype":"venue"
},
  "geometry": {"coordinates":[-94.84156900000001,31.3895],"type":"Point"}
}