{
  "type": "Feature",
  "properties": {
    "iso:country":"US",
    "sg:address":"11602 Habersham Ln",
    "sg:city":"Houston",
    "sg:classifiers":[
        {
            "category":"Professional",
            "subcategory":"Art Services",
            "type":"Services"
        }
    ],
    "sg:phone":"+1 713 780 9064",
    "sg:postcode":"77024",
    "sg:province":"TX",
    "sg:tags":[
        "commercial",
        "design",
        "datum"
    ],
    "wof:name":"Webart Studio",
    "wof:placetype":"venue"
},
  "geometry": {"coordinates":[-95.52378899999999,29.758816],"type":"Point"}
}