{
  "type": "Feature",
  "properties": {
    "iso:country":"US",
    "sg:address":"3201 Paluxy Dr",
    "sg:city":"Tyler",
    "sg:classifiers":[
        {
            "category":"Health Services",
            "subcategory":"Doctor",
            "type":"Services"
        }
    ],
    "sg:phone":"+1 903 593 5161",
    "sg:postcode":"75701",
    "sg:province":"TX",
    "sg:tags":[
        "dentist"
    ],
    "wof:name":"Paluxy Dental Group Ppc",
    "wof:placetype":"venue"
},
  "geometry": {"coordinates":[-95.27904100000001,32.314545],"type":"Point"}
}