{
  "type": "Feature",
  "properties": {
    "iso:country":"US",
    "sg:address":"4011 Hollister St",
    "sg:city":"Houston",
    "sg:classifiers":[
        {
            "category":"Personal",
            "subcategory":"Beauty Salon",
            "type":"Services"
        }
    ],
    "sg:phone":"+1 713 462 3988",
    "sg:postcode":"77080",
    "sg:province":"TX",
    "sg:tags":[
        "hair"
    ],
    "wof:name":"Febe Beauty Salon",
    "wof:placetype":"venue"
},
  "geometry": {"coordinates":[-95.509423,29.82953],"type":"Point"}
}