{
  "type": "Feature",
  "properties": {
    "iso:country":"US",
    "sg:address":"815 N Elm St",
    "sg:city":"Denton",
    "sg:classifiers":[
        {
            "category":"Building & Trades",
            "subcategory":"Plumbing",
            "type":"Services"
        }
    ],
    "sg:phone":"+1 940 382 7464",
    "sg:postcode":"76201",
    "sg:province":"TX",
    "sg:tags":[
        "plumbing",
        "contractor"
    ],
    "wof:name":"Sawyer Plumbing Svc",
    "wof:placetype":"venue"
},
  "geometry": {"coordinates":[-97.13366499999999,33.221975],"type":"Point"}
}