{
  "type": "Feature",
  "properties": {
    "iso:country":"US",
    "sg:address":"22 Co Rd 305",
    "sg:city":"Edna",
    "sg:classifiers":[
        {
            "category":"Building & Trades",
            "subcategory":"Construction",
            "type":"Services"
        }
    ],
    "sg:phone":"+1 361 782 8833",
    "sg:postcode":"77957",
    "sg:province":"TX",
    "sg:tags":[
        "contractor"
    ],
    "wof:name":"Westerman Contracting",
    "wof:placetype":"venue"
},
  "geometry": {"coordinates":[-96.617071,28.950482],"type":"Point"}
}