{
  "type": "Feature",
  "properties": {
    "iso:country":"US",
    "sg:address":"4949 Main Ave",
    "sg:city":"Groves",
    "sg:classifiers":[
        {
            "category":"Social Services",
            "type":"Services"
        }
    ],
    "sg:phone":"+1 409 962 6296",
    "sg:postcode":"77619",
    "sg:province":"TX",
    "wof:name":"Enlighteneds",
    "wof:placetype":"venue"
},
  "geometry": {"coordinates":[-93.928093,29.95064],"type":"Point"}
}