{
  "type": "Feature",
  "properties": {
    "iso:country":"US",
    "sg:address":"6500 Onyx Dr S",
    "sg:city":"Fort Worth",
    "sg:classifiers":[
        {
            "category":"Government",
            "subcategory":"Office",
            "type":"Public Place"
        }
    ],
    "sg:phone":"+1 817 595 1539",
    "sg:postcode":"76180",
    "sg:province":"TX",
    "sg:tags":[
        "general"
    ],
    "wof:name":"Dfw Fleet Management",
    "wof:placetype":"venue"
},
  "geometry": {"coordinates":[-97.241259,32.814204],"type":"Point"}
}