{
  "type": "Feature",
  "properties": {
    "iso:country":"US",
    "sg:address":"2818 Ruder St",
    "sg:city":"Dallas",
    "sg:classifiers":[
        {
            "category":"Building & Trades",
            "subcategory":"Construction",
            "type":"Services"
        }
    ],
    "sg:phone":"+1 214 239 8310",
    "sg:postcode":"75212",
    "sg:province":"TX",
    "sg:tags":[
        "general",
        "contractor"
    ],
    "wof:name":"Azteca Enterprises",
    "wof:placetype":"venue"
},
  "geometry": {"coordinates":[-96.918778,32.777031],"type":"Point"}
}