{
  "type": "Feature",
  "properties": {
    "iso:country":"US",
    "sg:address":"840 N Watson Rd",
    "sg:city":"Arlington",
    "sg:classifiers":[
        {
            "category":"Autos & Motor Vehicles",
            "subcategory":"Fuel & Gas Station",
            "type":"Retail Goods"
        }
    ],
    "sg:phone":"+1 817 649 8021",
    "sg:postcode":"76011",
    "sg:province":"TX",
    "sg:tags":[
        "oil"
    ],
    "wof:name":"Six Flags Conoco",
    "wof:placetype":"venue"
},
  "geometry": {"coordinates":[-97.06282,32.755285],"type":"Point"}
}