{
  "type": "Feature",
  "properties": {
    "iso:country":"US",
    "sg:address":"291 Scarborough Dr",
    "sg:city":"Conroe",
    "sg:classifiers":[
        {
            "category":"Shopping",
            "subcategory":"Jewelry",
            "type":"Retail Goods"
        }
    ],
    "sg:phone":"+1 936 494 3479",
    "sg:postcode":"77304",
    "sg:province":"TX",
    "wof:name":"Rhinestone Cowgirl",
    "wof:placetype":"venue"
},
  "geometry": {"coordinates":[-95.46810499999999,30.28881],"type":"Point"}
}