{
  "type": "Feature",
  "properties": {
    "iso:country":"US",
    "sg:address":"8508 Hwy 377 S",
    "sg:city":"Benbrook",
    "sg:classifiers":[
        {
            "category":"Building & Trades",
            "subcategory":"Cleaning & Sanitation",
            "type":"Services"
        }
    ],
    "sg:phone":"+1 817 249 0324",
    "sg:postcode":"76126",
    "sg:province":"TX",
    "sg:tags":[
        "ventilating",
        "system"
    ],
    "wof:name":"A-Best Cleaners",
    "wof:placetype":"venue"
},
  "geometry": {"coordinates":[-97.464157,32.679269],"type":"Point"}
}