{
  "type": "Feature",
  "properties": {
    "iso:country":"US",
    "sg:address":"6925 Airport Blvd",
    "sg:city":"Austin",
    "sg:classifiers":[
        {
            "category":"Shopping",
            "subcategory":"Clothing, Apparel, & Fashions",
            "type":"Retail Goods"
        }
    ],
    "sg:postcode":"78752",
    "sg:province":"TX",
    "sg:website":"www.fallasparedes.com/index.html",
    "wof:name":"Fallas Paredes",
    "wof:placetype":"venue"
},
  "geometry": {"coordinates":[-97.717879,30.335722],"type":"Point"}
}