{
  "type": "Feature",
  "properties": {
    "iso:country":"US",
    "sg:address":"1040 Shoreline Dr",
    "sg:city":"Quinlan",
    "sg:classifiers":[
        {
            "category":"Education",
            "subcategory":"Special Training",
            "type":"Public Place"
        }
    ],
    "sg:phone":"+1 903 447 0693",
    "sg:postcode":"75474",
    "sg:province":"TX",
    "wof:name":"Diane Leggett-Independent Dist",
    "wof:placetype":"venue"
},
  "geometry": {"coordinates":[-96.02372,32.906601],"type":"Point"}
}