{
  "type": "Feature",
  "properties": {
    "iso:country":"US",
    "sg:address":"320 Southmore Ave Ste 327",
    "sg:city":"Pasadena",
    "sg:classifiers":[
        {
            "category":"Professional",
            "subcategory":"Employment Agencies",
            "type":"Services"
        }
    ],
    "sg:phone":"+1 713 740 9921",
    "sg:postcode":"77502",
    "sg:province":"TX",
    "sg:tags":[
        "contractor"
    ],
    "sg:website":"http://www.laborready.com",
    "wof:name":"Labor Ready",
    "wof:placetype":"venue"
},
  "geometry": {"coordinates":[-95.208298,29.6908],"type":"Point"}
}