{
  "type": "Feature",
  "properties": {
    "iso:country":"US",
    "sg:address":"1400 E Ridge Rd",
    "sg:city":"Mcallen",
    "sg:classifiers":[
        {
            "category":"Health Services",
            "subcategory":"Doctor",
            "type":"Services"
        }
    ],
    "sg:phone":"+1 956 618 0404",
    "sg:postcode":"78503",
    "sg:province":"TX",
    "sg:tags":[
        "physician",
        "family",
        "practice",
        "surgeons",
        "medicine",
        "surgeon"
    ],
    "wof:name":"Rodriguez Luis A",
    "wof:placetype":"venue"
},
  "geometry": {"coordinates":[-98.208119,26.18369],"type":"Point"}
}