{
  "type": "Feature",
  "properties": {
    "iso:country":"US",
    "sg:address":"3303 Thornbird Ln",
    "sg:city":"Arlington",
    "sg:classifiers":[
        {
            "category":"Restaurant",
            "type":"Food & Drink"
        }
    ],
    "sg:phone":"+1 817 561 4644",
    "sg:postcode":"76001",
    "sg:province":"TX",
    "sg:tags":[
        "eating"
    ],
    "wof:name":"T & V Cuisine",
    "wof:placetype":"venue"
},
  "geometry": {"coordinates":[-97.160544,32.63378],"type":"Point"}
}