{
  "type": "Feature",
  "properties": {
    "iso:country":"US",
    "sg:address":"3707 Shelley Blvd",
    "sg:city":"Dallas",
    "sg:classifiers":[
        {
            "category":"Autos & Motor Vehicles",
            "subcategory":"Auto Supplies",
            "type":"Retail Goods"
        }
    ],
    "sg:phone":"+1 214 339 6468",
    "sg:postcode":"75211",
    "sg:province":"TX",
    "wof:name":"As Wholesale Auto Parts",
    "wof:placetype":"venue"
},
  "geometry": {"coordinates":[-96.880826,32.728395],"type":"Point"}
}