{
  "type": "Feature",
  "properties": {
    "iso:country":"US",
    "sg:address":"3604 N McColl Rd",
    "sg:city":"Mcallen",
    "sg:classifiers":[
        {
            "category":"Insurance",
            "subcategory":"Health Insurance",
            "type":"Services"
        }
    ],
    "sg:phone":"+1 956 682 6661",
    "sg:postcode":"78501",
    "sg:province":"TX",
    "sg:tags":[
        "carrier"
    ],
    "wof:name":"Luis De La Garza",
    "wof:placetype":"venue"
},
  "geometry": {"coordinates":[-98.206844,26.235558],"type":"Point"}
}