{
  "type": "Feature",
  "properties": {
    "iso:country":"US",
    "sg:address":"10907 Whisper Valley St",
    "sg:city":"San Antonio",
    "sg:classifiers":[
        {
            "category":"Real Estate",
            "subcategory":"Architect",
            "type":"Services"
        }
    ],
    "sg:phone":"+1 210 492 4327",
    "sg:postcode":"78230",
    "sg:province":"TX",
    "sg:tags":[
        "architectural"
    ],
    "wof:name":"Winakur & Associates",
    "wof:placetype":"venue"
},
  "geometry": {"coordinates":[-98.54067499999999,29.541622],"type":"Point"}
}