{
  "type": "Feature",
  "properties": {
    "iso:country":"US",
    "sg:address":"410 North St",
    "sg:city":"San Marcos",
    "sg:classifiers":[
        {
            "category":"Professional",
            "subcategory":"Business Services",
            "type":"Services"
        }
    ],
    "sg:phone":"+1 512 878 0787",
    "sg:postcode":"78666",
    "sg:province":"TX",
    "wof:name":"Lone Star Medical Staffing",
    "wof:placetype":"venue"
},
  "geometry": {"coordinates":[-97.946026,29.885887],"type":"Point"}
}