{
  "type": "Feature",
  "properties": {
    "iso:country":"US",
    "sg:address":"2000 Castroville Rd",
    "sg:city":"San Antonio",
    "sg:classifiers":[
        {
            "category":"Professional",
            "type":"Services"
        }
    ],
    "sg:phone":"+1 210 645 4152",
    "sg:postcode":"78237",
    "sg:province":"TX",
    "wof:name":"M O Backfill Contrs Inc A Corp",
    "wof:placetype":"venue"
},
  "geometry": {"coordinates":[-98.56789999999999,29.413387],"type":"Point"}
}