{
  "type": "Feature",
  "properties": {
    "iso:country":"US",
    "sg:address":"7517 Grapevine Hwy",
    "sg:city":"Fort Worth",
    "sg:classifiers":[
        {
            "category":"Professional",
            "subcategory":"Business Services",
            "type":"Services"
        },
        {
            "category":"Retail",
            "subcategory":"Animal Services",
            "type":"Services"
        }
    ],
    "sg:phone":"+1 817 281 0144",
    "sg:postcode":"76180",
    "sg:province":"TX",
    "sg:tags":[
        "pet",
        "boarding",
        "sitting"
    ],
    "wof:name":"Wag The Dog Daycare",
    "wof:placetype":"venue"
},
  "geometry": {"coordinates":[-97.220511,32.829333],"type":"Point"}
}