{
  "type": "Feature",
  "properties": {
    "iso:country":"US",
    "sg:address":"503 Maximo St",
    "sg:city":"Del Rio",
    "sg:classifiers":[
        {
            "category":"Organizations",
            "subcategory":"Religious Organization",
            "type":"Services"
        }
    ],
    "sg:phone":"+1 830 774 5753",
    "sg:postcode":"78840",
    "sg:province":"TX",
    "sg:tags":[
        "church"
    ],
    "wof:name":"Iglesia Bautista Horeb",
    "wof:placetype":"venue"
},
  "geometry": {"coordinates":[-100.881388,29.356685],"type":"Point"}
}