{
  "type": "Feature",
  "properties": {
    "iso:country":"US",
    "sg:address":"3149 Hwy 67",
    "sg:city":"Mesquite",
    "sg:classifiers":[
        {
            "category":"Health Services",
            "subcategory":"Clinic",
            "type":"Services"
        }
    ],
    "sg:phone":"+1 972 698 7451",
    "sg:postcode":"75150",
    "sg:province":"TX",
    "sg:tags":[
        "home"
    ],
    "wof:name":"Blessing's Home Health Agency",
    "wof:placetype":"venue"
},
  "geometry": {"coordinates":[-96.647119,32.814259],"type":"Point"}
}