{
  "type": "Feature",
  "properties": {
    "iso:country":"US",
    "sg:address":"308 S Winecup Trl",
    "sg:city":"Cedar Park",
    "sg:classifiers":[
        {
            "category":"Manufacturing",
            "subcategory":"Tools & Machinery",
            "type":"Manufacturing & Wholesale Goods"
        }
    ],
    "sg:phone":"+1 512 249 1466",
    "sg:postcode":"78613",
    "sg:province":"TX",
    "sg:tags":[
        "mfg"
    ],
    "wof:name":"Wright Mold Specialty",
    "wof:placetype":"venue"
},
  "geometry": {"coordinates":[-97.83148799999999,30.50352],"type":"Point"}
}