{
  "type": "Feature",
  "properties": {
    "iso:country":"US",
    "sg:address":"7301 Burnet Rd",
    "sg:city":"Austin",
    "sg:classifiers":[
        {
            "category":"Shopping",
            "subcategory":"Discount & Variety Stores",
            "type":"Retail Goods"
        }
    ],
    "sg:phone":"+1 512 458 4716",
    "sg:postcode":"78757",
    "sg:province":"TX",
    "sg:tags":[
        "merchandise",
        "general"
    ],
    "sg:website":"www.harryhinesonline.com",
    "wof:name":"Harry Hines Trading Company",
    "wof:placetype":"venue"
},
  "geometry": {"coordinates":[-97.735218,30.348869],"type":"Point"}
}