{
  "type": "Feature",
  "properties": {
    "iso:country":"US",
    "sg:address":"902 S Oak Ave",
    "sg:city":"Mineral Wells",
    "sg:classifiers":[
        {
            "category":"Retail",
            "subcategory":"Auto Repair",
            "type":"Services"
        }
    ],
    "sg:phone":"+1 940 325 1732",
    "sg:postcode":"76067",
    "sg:province":"TX",
    "sg:tags":[
        "automotive",
        "exhaust"
    ],
    "wof:name":"Nickels Exhaustcenter",
    "wof:placetype":"venue"
},
  "geometry": {"coordinates":[-98.113029,32.80286],"type":"Point"}
}