{
  "type": "Feature",
  "properties": {
    "iso:country":"US",
    "sg:address":"610 E 32nd St",
    "sg:city":"Houston",
    "sg:classifiers":[
        {
            "category":"Social Services",
            "type":"Services"
        }
    ],
    "sg:phone":"+1 713 880 0865",
    "sg:postcode":"77022",
    "sg:province":"TX",
    "sg:tags":[
        "child",
        "welfare"
    ],
    "wof:name":"National One Church One Child",
    "wof:placetype":"venue"
},
  "geometry": {"coordinates":[-95.391088,29.815522],"type":"Point"}
}