{
  "type": "Feature",
  "properties": {
    "iso:country":"US",
    "sg:address":"507 Sandpiper Dr",
    "sg:city":"Arlington",
    "sg:classifiers":[
        {
            "category":"Real Estate",
            "subcategory":"Real Estate Operator",
            "type":"Services"
        }
    ],
    "sg:phone":"+1 817 275 3565",
    "sg:postcode":"76013",
    "sg:province":"TX",
    "sg:tags":[
        "building",
        "apartment"
    ],
    "wof:name":"Bowen Square/Bowen II",
    "wof:placetype":"venue"
},
  "geometry": {"coordinates":[-97.145213,32.730098],"type":"Point"}
}