{
  "type": "Feature",
  "properties": {
    "iso:country":"US",
    "sg:address":"4057 Hanover St",
    "sg:city":"Dallas",
    "sg:classifiers":[
        {
            "category":"Wholesale",
            "subcategory":"Durable Goods & Equipment",
            "type":"Manufacturing & Wholesale Goods"
        }
    ],
    "sg:phone":"+1 214 696 6282",
    "sg:postcode":"75225",
    "sg:province":"TX",
    "wof:name":"About House",
    "wof:placetype":"venue"
},
  "geometry": {"coordinates":[-96.802105,32.854806],"type":"Point"}
}