{
  "type": "Feature",
  "properties": {
    "iso:country":"US",
    "sg:address":"1041 Airline Rd",
    "sg:city":"Corpus Christi",
    "sg:classifiers":[
        {
            "category":"Real Estate",
            "subcategory":"Real Estate Agent",
            "type":"Services"
        }
    ],
    "sg:phone":"+1 361 992 6446",
    "sg:postcode":"78412",
    "sg:province":"TX",
    "sg:website":"www.rent2ownhomes.com",
    "wof:name":"Rent 2 Own Homes",
    "wof:placetype":"venue"
},
  "geometry": {"coordinates":[-97.362512,27.711987],"type":"Point"}
}