{
  "type": "Feature",
  "properties": {
    "iso:country":"US",
    "sg:address":"7920 Belt Line Rd Ste 170",
    "sg:city":"Dallas",
    "sg:classifiers":[
        {
            "category":"Professional",
            "subcategory":"Printing & Photocopies",
            "type":"Services"
        }
    ],
    "sg:phone":"+1 972 233 5992",
    "sg:postcode":"75254",
    "sg:province":"TX",
    "sg:tags":[
        "duplicating",
        "copying"
    ],
    "sg:website":"http://www.ahlwrightprinting.com",
    "wof:name":"Ahlwright Printing & Copy Center",
    "wof:placetype":"venue"
},
  "geometry": {"coordinates":[-96.770391,32.949797],"type":"Point"}
}