{
  "type": "Feature",
  "properties": {
    "iso:country":"US",
    "sg:address":"5545 Charlestown Dr",
    "sg:city":"Dallas",
    "sg:classifiers":[
        {
            "category":"Professional",
            "type":"Services"
        }
    ],
    "sg:phone":"+1 972 960 9053",
    "sg:postcode":"75230",
    "sg:province":"TX",
    "wof:name":"Music Together of Dallas",
    "wof:placetype":"venue"
},
  "geometry": {"coordinates":[-96.812528,32.91763],"type":"Point"}
}