{
  "type": "Feature",
  "properties": {
    "iso:country":"US",
    "sg:address":"14597 Evergreen Ct",
    "sg:city":"Addison",
    "sg:classifiers":[
        {
            "category":"Shopping",
            "type":"Retail Goods"
        }
    ],
    "sg:phone":"+1 972 243 8324",
    "sg:postcode":"75001",
    "sg:province":"TX",
    "sg:tags":[
        "merchandise"
    ],
    "wof:name":"Ybs General Shop",
    "wof:placetype":"venue"
},
  "geometry": {"coordinates":[-96.85089600000001,32.944217],"type":"Point"}
}