{
  "type": "Feature",
  "properties": {
    "iso:country":"US",
    "sg:address":"109 E Nopal St",
    "sg:city":"Uvalde",
    "sg:classifiers":[
        {
            "category":"Shopping",
            "subcategory":"Clothing, Apparel, & Fashions",
            "type":"Retail Goods"
        }
    ],
    "sg:phone":"+1 830 278 4244",
    "sg:postcode":"78801",
    "sg:province":"TX",
    "sg:tags":[
        "alteration"
    ],
    "wof:name":"Nina's Creative Sewing",
    "wof:placetype":"venue"
},
  "geometry": {"coordinates":[-99.786283,29.211127],"type":"Point"}
}