{
  "type": "Feature",
  "properties": {
    "iso:country":"US",
    "sg:address":"15510 Ripplestream St",
    "sg:city":"Houston",
    "sg:classifiers":[
        {
            "category":"Professional",
            "subcategory":"Engineering",
            "type":"Services"
        }
    ],
    "sg:phone":"+1 281 440 5924",
    "sg:postcode":"77068",
    "sg:province":"TX",
    "wof:name":"T Dowse & Assoc LLC",
    "wof:placetype":"venue"
},
  "geometry": {"coordinates":[-95.49699099999999,30.004071],"type":"Point"}
}