{
  "type": "Feature",
  "properties": {
    "iso:country":"US",
    "sg:address":"1001 Fannin St",
    "sg:city":"Houston",
    "sg:classifiers":[
        {
            "category":"Professional",
            "subcategory":"Management & Consulting",
            "type":"Services"
        }
    ],
    "sg:phone":"+1 713 654 5001",
    "sg:postcode":"77002",
    "sg:province":"TX",
    "sg:tags":[
        "litigation",
        "consultant"
    ],
    "wof:name":"Forensic Technologies Intl",
    "wof:placetype":"venue"
},
  "geometry": {"coordinates":[-95.364639,29.755689],"type":"Point"}
}