{
  "type": "Feature",
  "properties": {
    "iso:country":"US",
    "sg:address":"315 N San Saba St",
    "sg:city":"San Antonio",
    "sg:classifiers":[
        {
            "category":"Health Services",
            "subcategory":"Optometrist",
            "type":"Services"
        },
        {
            "category":"Health Services",
            "subcategory":"Doctor",
            "type":"Services"
        }
    ],
    "sg:phone":"+1 210 225 3937",
    "sg:postcode":"78207",
    "sg:province":"TX",
    "sg:tags":[
        "physician",
        "surgeon"
    ],
    "wof:name":"San Martin Eye Clinic",
    "wof:placetype":"venue"
},
  "geometry": {"coordinates":[-98.499898,29.428506],"type":"Point"}
}