{
  "type": "Feature",
  "properties": {
    "iso:country":"US",
    "sg:address":"3707 Farmer St",
    "sg:city":"Houston",
    "sg:classifiers":[
        {
            "category":"Manufacturing",
            "subcategory":"Electronics",
            "type":"Manufacturing & Wholesale Goods"
        }
    ],
    "sg:phone":"+1 281 386 0002",
    "sg:postcode":"77020",
    "sg:province":"TX",
    "sg:tags":[
        "equipment",
        "mfg",
        "communication"
    ],
    "wof:name":"By Disign LLC",
    "wof:placetype":"venue"
},
  "geometry": {"coordinates":[-95.332325,29.775171],"type":"Point"}
}