{
  "type": "Feature",
  "properties": {
    "iso:country":"US",
    "sg:address":"822 Cedar Crest Ln",
    "sg:city":"Allen",
    "sg:classifiers":[
        {
            "category":"Shopping",
            "type":"Retail Goods"
        }
    ],
    "sg:phone":"+1 469 675 0666",
    "sg:postcode":"75002",
    "sg:province":"TX",
    "sg:tags":[
        "merchandise"
    ],
    "wof:name":"Uber Shop",
    "wof:placetype":"venue"
},
  "geometry": {"coordinates":[-96.658795,33.081207],"type":"Point"}
}