{
  "type": "Feature",
  "properties": {
    "iso:country":"US",
    "sg:address":"11117 Mahaffey Rd",
    "sg:city":"Tomball",
    "sg:classifiers":[
        {
            "category":"Manufacturing",
            "subcategory":"Tools & Machinery",
            "type":"Manufacturing & Wholesale Goods"
        }
    ],
    "sg:phone":"+1 281 516 7943",
    "sg:postcode":"77375",
    "sg:province":"TX",
    "sg:tags":[
        "transmission",
        "equipment",
        "power",
        "mfg"
    ],
    "wof:name":"Tomahawk Manufacturing LLC",
    "wof:placetype":"venue"
},
  "geometry": {"coordinates":[-95.583434,30.09026],"type":"Point"}
}