{
  "type": "Feature",
  "properties": {
    "iso:country":"US",
    "sg:address":"131 Mill Valley Dr",
    "sg:city":"Colleyville",
    "sg:classifiers":[
        {
            "category":"Manufacturing",
            "subcategory":"Apparel",
            "type":"Manufacturing & Wholesale Goods"
        }
    ],
    "sg:phone":"+1 817 788 9183",
    "sg:postcode":"76034",
    "sg:province":"TX",
    "sg:tags":[
        "embroidery",
        "mfg"
    ],
    "wof:name":"Sew It Is Written",
    "wof:placetype":"venue"
},
  "geometry": {"coordinates":[-97.166573,32.875193],"type":"Point"}
}