{
  "type": "Feature",
  "properties": {
    "iso:country":"US",
    "sg:address":"2203 College Dr",
    "sg:city":"Victoria",
    "sg:classifiers":[
        {
            "category":"Shopping",
            "subcategory":"Jewelry",
            "type":"Retail Goods"
        }
    ],
    "sg:phone":"+1 361 576 5674",
    "sg:postcode":"77901",
    "sg:province":"TX",
    "wof:name":"T&G Jewelry & Gifts",
    "wof:placetype":"venue"
},
  "geometry": {"coordinates":[-96.980107,28.819277],"type":"Point"}
}