{
  "type": "Feature",
  "properties": {
    "iso:country":"US",
    "sg:address":"1305 Taylor St",
    "sg:city":"Lampasas",
    "sg:classifiers":[
        {
            "category":"Building & Trades",
            "subcategory":"Construction",
            "type":"Services"
        }
    ],
    "sg:phone":"+1 512 556 3426",
    "sg:postcode":"76550",
    "sg:province":"TX",
    "sg:tags":[
        "hanging",
        "contractor"
    ],
    "wof:name":"Rocha Painting Service Inc",
    "wof:placetype":"venue"
},
  "geometry": {"coordinates":[-98.167688,31.064766],"type":"Point"}
}