{
  "type": "Feature",
  "properties": {
    "iso:country":"US",
    "sg:address":"2301 43rd St",
    "sg:city":"Galveston",
    "sg:classifiers":[
        {
            "category":"Retail",
            "subcategory":"Repair Shop",
            "type":"Services"
        }
    ],
    "sg:phone":"+1 409 762 7632",
    "sg:postcode":"77550",
    "sg:province":"TX",
    "wof:name":"Wetworks",
    "wof:placetype":"venue"
},
  "geometry": {"coordinates":[-94.81090399999999,29.282221],"type":"Point"}
}