{
  "type": "Feature",
  "properties": {
    "iso:country":"US",
    "sg:address":"10410 Aves St",
    "sg:city":"Houston",
    "sg:classifiers":[
        {
            "category":"Insurance",
            "subcategory":"Insurance Agent",
            "type":"Services"
        }
    ],
    "sg:phone":"+1 713 941 9500",
    "sg:postcode":"77034",
    "sg:province":"TX",
    "wof:name":"Accurate Claims Inc",
    "wof:placetype":"venue"
},
  "geometry": {"coordinates":[-95.227006,29.638606],"type":"Point"}
}