{
  "type": "Feature",
  "properties": {
    "iso:country":"US",
    "sg:address":"811 Studewood St",
    "sg:city":"Houston",
    "sg:classifiers":[
        {
            "category":"Personal",
            "type":"Services"
        },
        {
            "category":"Retail",
            "subcategory":"Laundry & Dry Cleaning",
            "type":"Services"
        }
    ],
    "sg:phone":"+1 713 862 9382",
    "sg:postcode":"77007",
    "sg:province":"TX",
    "sg:tags":[
        "sewing",
        "alteration"
    ],
    "sg:website":"www.wolfecleaners.com",
    "wof:name":"Wolfe Cleaners",
    "wof:placetype":"venue"
},
  "geometry": {"coordinates":[-95.387901,29.7859],"type":"Point"}
}