{
  "type": "Feature",
  "properties": {
    "iso:country":"US",
    "sg:address":"7042 Cole Creek Dr",
    "sg:city":"Houston",
    "sg:classifiers":[
        {
            "category":"Wholesale",
            "subcategory":"Apparel",
            "type":"Manufacturing & Wholesale Goods"
        }
    ],
    "sg:phone":"+1 713 462 4313",
    "sg:postcode":"77092",
    "sg:province":"TX",
    "sg:tags":[
        "piece"
    ],
    "wof:name":"Nora Lee Rightmer",
    "wof:placetype":"venue"
},
  "geometry": {"coordinates":[-95.495149,29.853129],"type":"Point"}
}