{
  "type": "Feature",
  "properties": {
    "iso:country":"US",
    "sg:address":"104 N 25 Mile Ave",
    "sg:city":"Hereford",
    "sg:classifiers":[
        {
            "category":"Restaurant",
            "type":"Food & Drink"
        }
    ],
    "sg:menulink":"http://www.allmenus.com/tx/hereford-east/130108-subway/menu/",
    "sg:phone":"+1 806 364 5140",
    "sg:postcode":"79045",
    "sg:province":"TX",
    "sg:tags":[
        "american",
        "sandwich"
    ],
    "wof:name":"Subway",
    "wof:placetype":"venue"
},
  "geometry": {"coordinates":[-102.405649,34.822429],"type":"Point"}
}