{
  "type": "Feature",
  "properties": {
    "iso:country":"US",
    "sg:address":"4822 Baldwin Blvd",
    "sg:city":"Corpus Christi",
    "sg:classifiers":[
        {
            "category":"Wholesale",
            "subcategory":"Machinery & Supplies",
            "type":"Manufacturing & Wholesale Goods"
        }
    ],
    "sg:phone":"+1 361 888 4228",
    "sg:postcode":"78408",
    "sg:province":"TX",
    "sg:tags":[
        "hardware",
        "industrial"
    ],
    "wof:name":"C C Bolt and Screw Company",
    "wof:placetype":"venue"
},
  "geometry": {"coordinates":[-97.451533,27.796496],"type":"Point"}
}