{
  "type": "Feature",
  "properties": {
    "iso:country":"US",
    "sg:address":"1758 Old Annetta Rd",
    "sg:city":"Aledo",
    "sg:classifiers":[
        {
            "category":"Professional",
            "type":"Services"
        }
    ],
    "sg:phone":"+1 817 441 7623",
    "sg:postcode":"76008",
    "sg:province":"TX",
    "wof:name":"Jarrod Daniels",
    "wof:placetype":"venue"
},
  "geometry": {"coordinates":[-97.65501,32.699146],"type":"Point"}
}