{
  "type": "Feature",
  "properties": {
    "iso:country":"US",
    "sg:address":"300 E Little York Rd",
    "sg:city":"Houston",
    "sg:classifiers":[
        {
            "category":"Freight",
            "type":"Transportation"
        }
    ],
    "sg:phone":"+1 713 692 0336",
    "sg:postcode":"77076",
    "sg:province":"TX",
    "sg:tags":[
        "warehouse",
        "individual",
        "commercial"
    ],
    "wof:name":"Watson & Taylor Mini Storage",
    "wof:placetype":"venue"
},
  "geometry": {"coordinates":[-95.394554,29.869936],"type":"Point"}
}