{
  "type": "Feature",
  "properties": {
    "iso:country":"US",
    "sg:address":"2897 State Hwy 66",
    "sg:city":"Rockwall",
    "sg:classifiers":[
        {
            "category":"Retail",
            "subcategory":"Veterinary Services",
            "type":"Services"
        }
    ],
    "sg:phone":"+1 972 722 9222",
    "sg:postcode":"75087",
    "sg:province":"TX",
    "wof:name":"Keith Taylor",
    "wof:placetype":"venue"
},
  "geometry": {"coordinates":[-96.420767,32.936311],"type":"Point"}
}