{
  "type": "Feature",
  "properties": {
    "iso:country":"US",
    "sg:address":"1006 S Shepherd Dr",
    "sg:city":"Baytown",
    "sg:classifiers":[
        {
            "category":"Professional",
            "type":"Services"
        }
    ],
    "sg:phone":"+1 281 837 1040",
    "sg:postcode":"77520",
    "sg:province":"TX",
    "wof:name":"Merry Maintenance",
    "wof:placetype":"venue"
},
  "geometry": {"coordinates":[-94.95478300000001,29.729741],"type":"Point"}
}