{
  "type": "Feature",
  "properties": {
    "iso:country":"US",
    "sg:address":"212 Woodridge Dr",
    "sg:city":"Victoria",
    "sg:classifiers":[
        {
            "category":"Professional",
            "subcategory":"Business Services",
            "type":"Services"
        }
    ],
    "sg:phone":"+1 361 578 3782",
    "sg:postcode":"77904",
    "sg:province":"TX",
    "sg:tags":[
        "consulting",
        "management"
    ],
    "wof:name":"Verde Financial Services",
    "wof:placetype":"venue"
},
  "geometry": {"coordinates":[-97.027446,28.862774],"type":"Point"}
}