{
  "type": "Feature",
  "properties": {
    "iso:country":"US",
    "sg:address":"13960 Trinity Blvd",
    "sg:city":"Euless",
    "sg:classifiers":[
        {
            "category":"Wholesale",
            "subcategory":"Office Equipment",
            "type":"Manufacturing & Wholesale Goods"
        }
    ],
    "sg:phone":"+1 817 730 8000",
    "sg:postcode":"76040",
    "sg:province":"TX",
    "sg:tags":[
        "machine",
        "duplicating",
        "copying"
    ],
    "wof:name":"Southwest Office Systems Inc",
    "wof:placetype":"venue"
},
  "geometry": {"coordinates":[-97.06685,32.823011],"type":"Point"}
}