{
  "type": "Feature",
  "properties": {
    "iso:country":"US",
    "sg:address":"2 Meta Dr",
    "sg:city":"Midland",
    "sg:classifiers":[
        {
            "category":"Food & Beverages",
            "subcategory":"Specialty",
            "type":"Retail Goods"
        }
    ],
    "sg:phone":"+1 432 620 9007",
    "sg:postcode":"79701",
    "sg:province":"TX",
    "sg:tags":[
        "herb"
    ],
    "wof:name":"Herbalife Distributor",
    "wof:placetype":"venue"
},
  "geometry": {"coordinates":[-102.100784,31.994245],"type":"Point"}
}