{
  "type": "Feature",
  "properties": {
    "iso:country":"US",
    "sg:address":"4335 Berwick Dr",
    "sg:city":"Wichita Falls",
    "sg:classifiers":[
        {
            "category":"Wholesale",
            "subcategory":"Stationery",
            "type":"Manufacturing & Wholesale Goods"
        }
    ],
    "sg:phone":"+1 940 691 0043",
    "sg:postcode":"76309",
    "sg:province":"TX",
    "sg:tags":[
        "supply"
    ],
    "wof:name":"Bear Graphics",
    "wof:placetype":"venue"
},
  "geometry": {"coordinates":[-98.55409899999999,33.882095],"type":"Point"}
}