{
  "type": "Feature",
  "properties": {
    "iso:country":"US",
    "sg:address":"1917 West St",
    "sg:city":"Rosenberg",
    "sg:classifiers":[
        {
            "category":"Manufacturing",
            "subcategory":"Textiles",
            "type":"Manufacturing & Wholesale Goods"
        }
    ],
    "sg:phone":"+1 281 342 2023",
    "sg:postcode":"77471",
    "sg:province":"TX",
    "sg:tags":[
        "gin",
        "cotton"
    ],
    "wof:name":"Gin Gin's Holding Co",
    "wof:placetype":"venue"
},
  "geometry": {"coordinates":[-95.814086,29.548762],"type":"Point"}
}