{
  "type": "Feature",
  "properties": {
    "iso:country":"US",
    "sg:address":"1802 Woodcrest Dr",
    "sg:city":"Houston",
    "sg:classifiers":[
        {
            "category":"Professional",
            "type":"Services"
        }
    ],
    "sg:phone":"+1 713 688 3158",
    "sg:postcode":"77018",
    "sg:province":"TX",
    "wof:name":"Laura Gass Bussiness Services",
    "wof:placetype":"venue"
},
  "geometry": {"coordinates":[-95.44741,29.822626],"type":"Point"}
}