{
  "type": "Feature",
  "properties": {
    "iso:country":"US",
    "sg:address":"8200 Northeast Pkwy",
    "sg:city":"Fort Worth",
    "sg:classifiers":[
        {
            "category":"Shopping",
            "subcategory":"Tobacco",
            "type":"Retail Goods"
        }
    ],
    "sg:phone":"+1 817 427 1777",
    "sg:postcode":"76180",
    "sg:province":"TX",
    "sg:tags":[
        "product"
    ],
    "wof:name":"Town & Country Cigars of Nrh",
    "wof:placetype":"venue"
},
  "geometry": {"coordinates":[-97.20177099999999,32.871212],"type":"Point"}
}