{
  "type": "Feature",
  "properties": {
    "iso:country":"US",
    "sg:address":"818 Placid Dr",
    "sg:city":"Mesquite",
    "sg:classifiers":[
        {
            "category":"Real Estate",
            "subcategory":"Real Estate Agent",
            "type":"Services"
        }
    ],
    "sg:phone":"+1 972 270 3437",
    "sg:postcode":"75150",
    "sg:province":"TX",
    "wof:name":"West Appraisals",
    "wof:placetype":"venue"
},
  "geometry": {"coordinates":[-96.606995,32.829182],"type":"Point"}
}