{
  "type": "Feature",
  "properties": {
    "iso:country":"US",
    "sg:address":"55 Honey Dr",
    "sg:city":"Brownsville",
    "sg:classifiers":[
        {
            "category":"Utilities",
            "subcategory":"Telephone",
            "type":"Services"
        }
    ],
    "sg:phone":"+1 956 541 4485",
    "sg:postcode":"78520",
    "sg:province":"TX",
    "sg:tags":[
        "communications"
    ],
    "wof:name":"Aa Telephone",
    "wof:placetype":"venue"
},
  "geometry": {"coordinates":[-97.518997,25.936925],"type":"Point"}
}