{
  "type": "Feature",
  "properties": {
    "iso:country":"US",
    "sg:address":"517 Belmont Dr",
    "sg:city":"Dumas",
    "sg:classifiers":[
        {
            "category":"Social Services",
            "type":"Services"
        }
    ],
    "sg:phone":"+1 806 935 6531",
    "sg:postcode":"79029",
    "sg:province":"TX",
    "wof:name":"Sunrise Counseling",
    "wof:placetype":"venue"
},
  "geometry": {"coordinates":[-101.957508,35.875849],"type":"Point"}
}