{
  "type": "Feature",
  "properties": {
    "iso:country":"US",
    "sg:address":"3108 Barkley Ave",
    "sg:city":"Midland",
    "sg:classifiers":[
        {
            "category":"Shopping",
            "subcategory":"Computers & Home Electronics",
            "type":"Retail Goods"
        }
    ],
    "sg:phone":"+1 432 689 5440",
    "sg:postcode":"79701",
    "sg:province":"TX",
    "sg:tags":[
        "parts",
        "supply"
    ],
    "wof:name":"Pro Tronics USA",
    "wof:placetype":"venue"
},
  "geometry": {"coordinates":[-102.11261,31.991407],"type":"Point"}
}