{
  "type": "Feature",
  "properties": {
    "iso:country":"US",
    "sg:address":"245 E Nasa Rd 1",
    "sg:city":"Webster",
    "sg:classifiers":[
        {
            "category":"Personal",
            "subcategory":"Beauty Salon",
            "type":"Services"
        }
    ],
    "sg:phone":"+1 281 557 0051",
    "sg:postcode":"77598",
    "sg:province":"TX",
    "wof:name":"Shehla's Beauty Salon",
    "wof:placetype":"venue"
},
  "geometry": {"coordinates":[-95.116876,29.538519],"type":"Point"}
}