{
  "type": "Feature",
  "properties": {
    "iso:country":"US",
    "sg:address":"419 Cactus St",
    "sg:city":"San Antonio",
    "sg:classifiers":[
        {
            "category":"Real Estate",
            "subcategory":"Real Estate Operator",
            "type":"Services"
        }
    ],
    "sg:phone":"+1 979 540 2162",
    "sg:postcode":"78203",
    "sg:province":"TX",
    "sg:tags":[
        "apartment"
    ],
    "wof:name":"Shade Tree Apartments",
    "wof:placetype":"venue"
},
  "geometry": {"coordinates":[-98.472584,29.410931],"type":"Point"}
}