{
  "type": "Feature",
  "properties": {
    "iso:country":"US",
    "sg:address":"344 W Campbell Rd",
    "sg:city":"Richardson",
    "sg:classifiers":[
        {
            "category":"Freight",
            "type":"Transportation"
        }
    ],
    "sg:phone":"+1 972 234 0957",
    "sg:postcode":"75080",
    "sg:province":"TX",
    "sg:tags":[
        "shipping",
        "agent"
    ],
    "wof:name":"Qwikpack & Ship",
    "wof:placetype":"venue"
},
  "geometry": {"coordinates":[-96.726859,32.975446],"type":"Point"}
}