{
  "type": "Feature",
  "properties": {
    "iso:country":"US",
    "sg:address":"1804 S Beckley Ave",
    "sg:city":"Dallas",
    "sg:classifiers":[
        {
            "category":"Professional",
            "type":"Services"
        }
    ],
    "sg:phone":"+1 214 943 2116",
    "sg:postcode":"75224",
    "sg:province":"TX",
    "sg:tags":[
        "establishment"
    ],
    "wof:name":"Texas Classics",
    "wof:placetype":"venue"
},
  "geometry": {"coordinates":[-96.822738,32.725173],"type":"Point"}
}