{
  "type": "Feature",
  "properties": {
    "iso:country":"US",
    "sg:address":"5109 Brentwood Stair Rd",
    "sg:city":"Fort Worth",
    "sg:classifiers":[
        {
            "category":"Professional",
            "subcategory":"Detective & Security Services",
            "type":"Services"
        }
    ],
    "sg:phone":"+1 817 451 1122",
    "sg:postcode":"76112",
    "sg:province":"TX",
    "sg:tags":[
        "car",
        "polygraph"
    ],
    "wof:name":"Southwest Polygraph Service",
    "wof:placetype":"venue"
},
  "geometry": {"coordinates":[-97.24935000000001,32.758372],"type":"Point"}
}