{
  "type": "Feature",
  "properties": {
    "iso:country":"US",
    "sg:address":"1880 Co Rd 3615",
    "sg:city":"Bigfoot",
    "sg:phone":"+1 830 466 5216",
    "sg:postcode":"78061",
    "sg:province":"TX",
    "sg:tags":[
        "beef",
        "farm",
        "crop",
        "field",
        "cattle",
        "feedlot"
    ],
    "wof:name":"Mann Otto Jr Sons Inc",
    "wof:placetype":"venue"
},
  "geometry": {"coordinates":[-98.901554,28.864207],"type":"Point"}
}