{
  "type": "Feature",
  "properties": {
    "iso:country":"US",
    "sg:address":"1102 N Florence St",
    "sg:city":"El Paso",
    "sg:classifiers":[
        {
            "category":"Wholesale",
            "subcategory":"Machinery & Supplies",
            "type":"Manufacturing & Wholesale Goods"
        }
    ],
    "sg:phone":"+1 915 577 9790",
    "sg:postcode":"79902",
    "sg:province":"TX",
    "sg:tags":[
        "industrial"
    ],
    "wof:name":"Sg Industrial Supply",
    "wof:placetype":"venue"
},
  "geometry": {"coordinates":[-106.490089,31.768295],"type":"Point"}
}