{
  "type": "Feature",
  "properties": {
    "iso:country":"US",
    "sg:address":"1405 E Sabine St",
    "sg:city":"Carthage",
    "sg:classifiers":[
        {
            "category":"Mining & Drilling",
            "type":"Manufacturing & Wholesale Goods"
        }
    ],
    "sg:phone":"+1 903 694 2041",
    "sg:postcode":"75633",
    "sg:province":"TX",
    "sg:tags":[
        "crude",
        "oil",
        "production",
        "gas",
        "producer"
    ],
    "wof:name":"Glassell Producing Co",
    "wof:placetype":"venue"
},
  "geometry": {"coordinates":[-94.30832599999999,32.164021],"type":"Point"}
}