{
  "type": "Feature",
  "properties": {
    "iso:country":"US",
    "sg:address":"503 N 16th St",
    "sg:city":"Lamesa",
    "sg:classifiers":[
        {
            "category":"Farming",
            "subcategory":"Farm & Veterinary Services",
            "type":"Manufacturing & Wholesale Goods"
        }
    ],
    "sg:phone":"+1 806 872 3173",
    "sg:postcode":"79331",
    "sg:province":"TX",
    "sg:tags":[
        "cotton",
        "ginning"
    ],
    "wof:name":"J Schrader Inc",
    "wof:placetype":"venue"
},
  "geometry": {"coordinates":[-101.958044,32.746993],"type":"Point"}
}