{
  "type": "Feature",
  "properties": {
    "iso:country":"US",
    "sg:address":"996 US Hwy 385",
    "sg:city":"Crane",
    "sg:classifiers":[
        {
            "category":"Government",
            "subcategory":"Office",
            "type":"Public Place"
        }
    ],
    "sg:phone":"+1 432 558 2711",
    "sg:postcode":"79731",
    "sg:province":"TX",
    "sg:tags":[
        "state",
        "program"
    ],
    "wof:name":"Transportation Dept Mntnc",
    "wof:placetype":"venue"
},
  "geometry": {"coordinates":[-102.349199,31.39378],"type":"Point"}
}