{
  "type": "Feature",
  "properties": {
    "iso:country":"US",
    "sg:address":"11842 Pamela Raye Rd",
    "sg:city":"El Paso",
    "sg:classifiers":[
        {
            "category":"Building & Trades",
            "subcategory":"Construction",
            "type":"Services"
        }
    ],
    "sg:phone":"+1 915 851 4177",
    "sg:postcode":"79927",
    "sg:province":"TX",
    "sg:tags":[
        "residential"
    ],
    "wof:name":"A G Construction",
    "wof:placetype":"venue"
},
  "geometry": {"coordinates":[-106.23930799999999,31.621547],"type":"Point"}
}