{
  "type": "Feature",
  "properties": {
    "iso:country":"US",
    "sg:address":"15710 FM 849",
    "sg:city":"Lindale",
    "sg:classifiers":[
        {
            "category":"Wholesale",
            "subcategory":"Toys & Hobbies",
            "type":"Manufacturing & Wholesale Goods"
        }
    ],
    "sg:phone":"+1 903 882 0281",
    "sg:postcode":"75706",
    "sg:province":"TX",
    "sg:tags":[
        "firework"
    ],
    "wof:name":"M & R Fireworks",
    "wof:placetype":"venue"
},
  "geometry": {"coordinates":[-95.42966699999999,32.48943],"type":"Point"}
}