{
  "type": "Feature",
  "properties": {
    "iso:country":"US",
    "sg:address":"2500 Whitis Ave",
    "sg:city":"Austin",
    "sg:classifiers":[
        {
            "category":"Manufacturing",
            "subcategory":"Printing",
            "type":"Manufacturing & Wholesale Goods"
        }
    ],
    "sg:phone":"+1 512 471 1084",
    "sg:postcode":"78712",
    "sg:province":"TX",
    "sg:tags":[
        "newspaper",
        "publishing"
    ],
    "sg:website":"www.dailytexanonline.com",
    "wof:name":"Texas Student Publications",
    "wof:placetype":"venue"
},
  "geometry": {"coordinates":[-97.74024900000001,30.289755],"type":"Point"}
}