{
  "type": "Feature",
  "properties": {
    "iso:country":"US",
    "sg:address":"305 W Woodard St",
    "sg:city":"Denison",
    "sg:classifiers":[
        {
            "category":"Insurance",
            "subcategory":"Life Insurance",
            "type":"Services"
        },
        {
            "category":"Banks & Credit Unions",
            "subcategory":"Financial Services",
            "type":"Services"
        }
    ],
    "sg:phone":"+1 903 463 1151",
    "sg:postcode":"75020",
    "sg:province":"TX",
    "sg:tags":[
        "planning",
        "consultant",
        "retirement",
        "plan",
        "annuity"
    ],
    "wof:name":"Independent Financial Service Center",
    "wof:placetype":"venue"
},
  "geometry": {"coordinates":[-96.53842400000001,33.756392],"type":"Point"}
}