{
  "type": "Feature",
  "properties": {
    "iso:country":"US",
    "sg:address":"2216 Gulf Blvd",
    "sg:city":"S Padre Island",
    "sg:classifiers":[
        {
            "category":"Professional",
            "subcategory":"Lawyer & Legal Services",
            "type":"Services"
        }
    ],
    "sg:phone":"+1 956 761 6225",
    "sg:postcode":"78597",
    "sg:province":"TX",
    "sg:tags":[
        "attorney"
    ],
    "wof:name":"Tidwell Swaim & Assoc",
    "wof:placetype":"venue"
},
  "geometry": {"coordinates":[-97.16454,26.101328],"type":"Point"}
}