{
  "type": "Feature",
  "properties": {
    "iso:country":"US",
    "sg:address":"3793 FM 446",
    "sg:city":"Victoria",
    "sg:classifiers":[
        {
            "category":"Retail",
            "subcategory":"Repair Shop",
            "type":"Services"
        }
    ],
    "sg:phone":"+1 361 578 6855",
    "sg:postcode":"77905",
    "sg:province":"TX",
    "sg:tags":[
        "welding"
    ],
    "wof:name":"Rps Custom Fab Welding",
    "wof:placetype":"venue"
},
  "geometry": {"coordinates":[-97.077026,28.735538],"type":"Point"}
}