{
  "type": "Feature",
  "properties": {
    "iso:country":"US",
    "sg:address":"778 Timber Dr",
    "sg:city":"New Braunfels",
    "sg:classifiers":[
        {
            "category":"Building & Trades",
            "subcategory":"Plumbing",
            "type":"Services"
        }
    ],
    "sg:phone":"+1 830 620 8432",
    "sg:postcode":"78130",
    "sg:province":"TX",
    "sg:tags":[
        "conditioning",
        "air",
        "system",
        "contractor"
    ],
    "wof:name":"Foerster Heating & Air Cond",
    "wof:placetype":"venue"
},
  "geometry": {"coordinates":[-98.155952,29.702844],"type":"Point"}
}