{
  "type": "Feature",
  "properties": {
    "iso:country":"US",
    "sg:address":"2205 Southgate St",
    "sg:city":"Arlington",
    "sg:classifiers":[
        {
            "category":"Health Services",
            "subcategory":"Chiropractor",
            "type":"Services"
        }
    ],
    "sg:phone":"+1 817 461 7246",
    "sg:postcode":"76013",
    "sg:province":"TX",
    "wof:name":"Accident & Injury Chiropractic",
    "wof:placetype":"venue"
},
  "geometry": {"coordinates":[-97.11834899999999,32.706626],"type":"Point"}
}