{
  "type": "Feature",
  "properties": {
    "iso:country":"US",
    "sg:address":"1213 W Van Buren Ave",
    "sg:city":"Harlingen",
    "sg:classifiers":[
        {
            "category":"Personal",
            "subcategory":"Beauty Salon",
            "type":"Services"
        }
    ],
    "sg:phone":"+1 956 440 9322",
    "sg:postcode":"78550",
    "sg:province":"TX",
    "wof:name":"Chabel's Hair & Nails",
    "wof:placetype":"venue"
},
  "geometry": {"coordinates":[-97.709405,26.191609],"type":"Point"}
}