{
  "type": "Feature",
  "properties": {
    "iso:country":"US",
    "sg:address":"1115 Congress St",
    "sg:city":"Houston",
    "sg:classifiers":[
        {
            "category":"Professional",
            "subcategory":"Lawyer & Legal Services",
            "type":"Services"
        }
    ],
    "sg:phone":"+1 713 228 5101",
    "sg:postcode":"77002",
    "sg:province":"TX",
    "sg:tags":[
        "attorney"
    ],
    "wof:name":"Honorable Mike Wood",
    "wof:placetype":"venue"
},
  "geometry": {"coordinates":[-95.35905700000001,29.761352],"type":"Point"}
}