{
  "type": "Feature",
  "properties": {
    "iso:country":"US",
    "sg:address":"115 4th St",
    "sg:city":"Sugar Land",
    "sg:classifiers":[
        {
            "category":"Professional",
            "subcategory":"Management & Consulting",
            "type":"Services"
        }
    ],
    "sg:phone":"+1 281 494 7704",
    "sg:postcode":"77478",
    "sg:province":"TX",
    "wof:name":"Loper Management LLC",
    "wof:placetype":"venue"
},
  "geometry": {"coordinates":[-95.631748,29.625661],"type":"Point"}
}