{
  "type": "Feature",
  "properties": {
    "iso:country":"US",
    "sg:address":"3608 Chapman Ln",
    "sg:city":"Austin",
    "sg:classifiers":[
        {
            "category":"Manufacturing",
            "subcategory":"Printing",
            "type":"Manufacturing & Wholesale Goods"
        }
    ],
    "sg:phone":"+1 512 447 4797",
    "sg:postcode":"78744",
    "sg:province":"TX",
    "sg:tags":[
        "commercial"
    ],
    "wof:name":"Travis Printing",
    "wof:placetype":"venue"
},
  "geometry": {"coordinates":[-97.728877,30.213186],"type":"Point"}
}