{
  "type": "Feature",
  "properties": {
    "iso:country":"US",
    "sg:address":"4030 Sulphur Springs Rd",
    "sg:city":"Navasota",
    "sg:classifiers":[
        {
            "category":"Health Services",
            "subcategory":"Doctor",
            "type":"Services"
        }
    ],
    "sg:phone":"+1 936 825 2683",
    "sg:postcode":"77845",
    "sg:province":"TX",
    "sg:tags":[
        "medical"
    ],
    "wof:name":"Wayne Reser Dr",
    "wof:placetype":"venue"
},
  "geometry": {"coordinates":[-96.18040999999999,30.555805],"type":"Point"}
}