{
  "type": "Feature",
  "properties": {
    "iso:country":"US",
    "sg:address":"2020 Centimeter Cir",
    "sg:city":"Austin",
    "sg:classifiers":[
        {
            "category":"Wholesale",
            "subcategory":"Medical Equipment & Supplies",
            "type":"Manufacturing & Wholesale Goods"
        }
    ],
    "sg:phone":"+1 512 997 7780",
    "sg:postcode":"78758",
    "sg:province":"TX",
    "sg:tags":[
        "apparatus",
        "x-ray"
    ],
    "sg:website":"http://www.stellardisplay.com",
    "wof:name":"Stellar Micro Devices, Inc.",
    "wof:placetype":"venue"
},
  "geometry": {"coordinates":[-97.71365,30.381311],"type":"Point"}
}