{
  "type": "Feature",
  "properties": {
    "iso:country":"US",
    "sg:address":"2007 Briarchester Dr",
    "sg:city":"Katy",
    "sg:classifiers":[
        {
            "category":"Travel",
            "subcategory":"Travel Agent",
            "type":"Entertainment"
        }
    ],
    "sg:phone":"+1 281 392 1828",
    "sg:postcode":"77450",
    "sg:province":"TX",
    "sg:tags":[
        "agency"
    ],
    "wof:name":"All World Travel",
    "wof:placetype":"venue"
},
  "geometry": {"coordinates":[-95.753705,29.751875],"type":"Point"}
}