{
  "type": "Feature",
  "properties": {
    "iso:country":"US",
    "sg:address":"5425 S Padre Island Dr",
    "sg:city":"Corpus Christi",
    "sg:classifiers":[
        {
            "category":"Restaurant",
            "type":"Food & Drink"
        }
    ],
    "sg:menulink":"http://www.allmenus.com/tx/corpus-christi/96025-souper-salad/menu/",
    "sg:phone":"+1 361 985 6170",
    "sg:postcode":"78411",
    "sg:province":"TX",
    "sg:tags":[
        "smoothy",
        "soup",
        "american",
        "salad",
        "juice"
    ],
    "wof:name":"Souper Salad",
    "wof:placetype":"venue"
},
  "geometry": {"coordinates":[-97.379486,27.711995],"type":"Point"}
}