{
  "type": "Feature",
  "properties": {
    "iso:country":"US",
    "sg:address":"7023 Quig Dr",
    "sg:city":"San Antonio",
    "sg:classifiers":[
        {
            "category":"Shopping",
            "subcategory":"Catalog Store",
            "type":"Retail Goods"
        }
    ],
    "sg:phone":"+1 210 333 1371",
    "sg:postcode":"78223",
    "sg:province":"TX",
    "sg:tags":[
        "mail",
        "order"
    ],
    "wof:name":"Cabrera's Enterprises",
    "wof:placetype":"venue"
},
  "geometry": {"coordinates":[-98.445863,29.356729],"type":"Point"}
}