{
  "type": "Feature",
  "properties": {
    "iso:country":"US",
    "sg:address":"238 1st St W",
    "sg:city":"Humble",
    "sg:classifiers":[
        {
            "category":"Personal",
            "type":"Services"
        }
    ],
    "sg:phone":"+1 281 446 0213",
    "sg:postcode":"77338",
    "sg:province":"TX",
    "wof:name":"Weighco of Florida Inc",
    "wof:placetype":"venue"
},
  "geometry": {"coordinates":[-95.266458,30.000304],"type":"Point"}
}