{
  "type": "Feature",
  "properties": {
    "iso:country":"US",
    "sg:address":"1320 N Zaragoza Rd",
    "sg:city":"El Paso",
    "sg:classifiers":[
        {
            "category":"Restaurant",
            "type":"Food & Drink"
        },
        {
            "category":"Ice Cream",
            "type":"Food & Drink"
        }
    ],
    "sg:menulink":"http://www.allmenus.com/tx/el-paso-east/242696-baskin-robbins/menu/",
    "sg:phone":"+1 915 790 2210",
    "sg:postcode":"79936",
    "sg:province":"TX",
    "sg:tags":[
        "american",
        "ice",
        "cream"
    ],
    "wof:name":"Baskin-Robbins",
    "wof:placetype":"venue"
},
  "geometry": {"coordinates":[-106.299723,31.726267],"type":"Point"}
}