{
  "type": "Feature",
  "properties": {
    "iso:country":"US",
    "sg:address":"11966 FM 346 W",
    "sg:city":"Bullard",
    "sg:classifiers":[
        {
            "category":"Professional",
            "type":"Services"
        }
    ],
    "sg:phone":"+1 903 894 8662",
    "sg:postcode":"75757",
    "sg:province":"TX",
    "wof:name":"Marilyn Holmes",
    "wof:placetype":"venue"
},
  "geometry": {"coordinates":[-95.36912100000001,32.18455],"type":"Point"}
}