{
  "type": "Feature",
  "properties": {
    "iso:country":"US",
    "sg:address":"5819 Weber Rd",
    "sg:city":"Corpus Christi",
    "sg:classifiers":[
        {
            "category":"Banks & Credit Unions",
            "subcategory":"Bank",
            "type":"Services"
        }
    ],
    "sg:phone":"+1 361 814 5819",
    "sg:postcode":"78413",
    "sg:province":"TX",
    "sg:tags":[
        "personal",
        "institution",
        "jewelry"
    ],
    "wof:name":"Best Finance Company Inc",
    "wof:placetype":"venue"
},
  "geometry": {"coordinates":[-97.40539,27.711012],"type":"Point"}
}