{
  "type": "Feature",
  "properties": {
    "iso:country":"US",
    "sg:address":"125 College Ave",
    "sg:city":"Oglesby",
    "sg:classifiers":[
        {
            "category":"Education",
            "subcategory":"School",
            "type":"Public Place"
        }
    ],
    "sg:phone":"+1 254 456 2242",
    "sg:postcode":"76561",
    "sg:province":"TX",
    "wof:name":"Oglesby ISD School",
    "wof:placetype":"venue"
},
  "geometry": {"coordinates":[-97.50859699999999,31.419777],"type":"Point"}
}