{
  "type": "Feature",
  "properties": {
    "iso:country":"US",
    "sg:address":"2724 Hanover St",
    "sg:city":"Dallas",
    "sg:classifiers":[
        {
            "category":"Communications",
            "subcategory":"Film & Video Production",
            "type":"Services"
        }
    ],
    "sg:phone":"+1 214 373 7031",
    "sg:postcode":"75225",
    "sg:province":"TX",
    "sg:tags":[
        "taping"
    ],
    "wof:name":"Avideo Groove",
    "wof:placetype":"venue"
},
  "geometry": {"coordinates":[-96.776597,32.855038],"type":"Point"}
}