{
  "type": "Feature",
  "properties": {
    "iso:country":"US",
    "sg:address":"1717 W 6th St #365",
    "sg:city":"Austin",
    "sg:classifiers":[
        {
            "category":"Health Services",
            "subcategory":"Dentist",
            "type":"Services"
        }
    ],
    "sg:phone":"+1 512 482 9383",
    "sg:postcode":"78701",
    "sg:province":"TX",
    "sg:website":"www.downtowndentaldesign.com",
    "wof:name":"Downtown Dental Design",
    "wof:placetype":"venue"
},
  "geometry": {"coordinates":[-97.765338,30.276376],"type":"Point"}
}