{
  "type": "Feature",
  "properties": {
    "iso:country":"US",
    "sg:address":"1302 N Robinson Dr",
    "sg:city":"Robinson",
    "sg:classifiers":[
        {
            "category":"Home & Garden",
            "subcategory":"Household Appliances",
            "type":"Retail Goods"
        },
        {
            "category":"Building & Trades",
            "subcategory":"Plumbing",
            "type":"Services"
        },
        {
            "category":"Home & Garden",
            "subcategory":"Building Materials",
            "type":"Retail Goods"
        },
        {
            "category":"Building & Trades",
            "subcategory":"Construction",
            "type":"Services"
        }
    ],
    "sg:phone":"+1 254 662 4404",
    "sg:postcode":"76706",
    "sg:province":"TX",
    "sg:tags":[
        "heater",
        "systems-repairing",
        "system",
        "specialty",
        "water",
        "equipment",
        "heat",
        "heating",
        "pump",
        "contractor",
        "repair",
        "air conditioning"
    ],
    "sg:website":"http://www.castillejahvac.com",
    "wof:name":"Castilleja's Central Heating and Air",
    "wof:placetype":"venue"
},
  "geometry": {"coordinates":[-97.126154,31.50308],"type":"Point"}
}