{
  "type": "Feature",
  "properties": {
    "iso:country":"US",
    "sg:address":"469 W Clark St",
    "sg:city":"New Braunfels",
    "sg:classifiers":[
        {
            "category":"Travel",
            "subcategory":"Hotels & Motels",
            "type":"Entertainment"
        }
    ],
    "sg:phone":"+1 830 899 2544",
    "sg:postcode":"78133",
    "sg:province":"TX",
    "sg:tags":[
        "operation"
    ],
    "wof:name":"Canyon Lake Campground & Rv Pk",
    "wof:placetype":"venue"
},
  "geometry": {"coordinates":[-98.302615,29.873454],"type":"Point"}
}