{
  "type": "Feature",
  "properties": {
    "iso:country":"US",
    "sg:address":"5202 Ripplebrook Dr",
    "sg:city":"Houston",
    "sg:classifiers":[
        {
            "category":"Real Estate",
            "subcategory":"Real Estate Agent",
            "type":"Services"
        }
    ],
    "sg:phone":"+1 713 433 2928",
    "sg:postcode":"77045",
    "sg:province":"TX",
    "wof:name":"C Teachout Real Estate Afent",
    "wof:placetype":"venue"
},
  "geometry": {"coordinates":[-95.46052,29.625662],"type":"Point"}
}