{
  "type": "Feature",
  "properties": {
    "iso:country":"US",
    "sg:address":"3033 Cockrell Ave",
    "sg:city":"Fort Worth",
    "sg:classifiers":[
        {
            "category":"Restaurant",
            "type":"Food & Drink"
        }
    ],
    "sg:phone":"+1 817 926 4117",
    "sg:postcode":"76109",
    "sg:province":"TX",
    "sg:tags":[
        "eating"
    ],
    "wof:name":"Pizza Hut",
    "wof:placetype":"venue"
},
  "geometry": {"coordinates":[-97.35920900000001,32.706679],"type":"Point"}
}