{
  "type": "Feature",
  "properties": {
    "iso:country":"US",
    "sg:address":"226 Scarlet Maple Dr",
    "sg:city":"Sugar Land",
    "sg:classifiers":[
        {
            "category":"Professional",
            "type":"Services"
        }
    ],
    "sg:phone":"+1 281 565 0140",
    "sg:postcode":"77479",
    "sg:province":"TX",
    "wof:name":"Creative Stripes of Houst",
    "wof:placetype":"venue"
},
  "geometry": {"coordinates":[-95.66104300000001,29.604639],"type":"Point"}
}