{
  "type": "Feature",
  "properties": {
    "iso:country":"US",
    "sg:address":"722 Duchess Dr",
    "sg:city":"Allen",
    "sg:classifiers":[
        {
            "category":"Professional",
            "subcategory":"Computer Services",
            "type":"Services"
        }
    ],
    "sg:phone":"+1 972 396 7362",
    "sg:postcode":"75013",
    "sg:province":"TX",
    "sg:tags":[
        "related"
    ],
    "wof:name":"Quadmatrix",
    "wof:placetype":"venue"
},
  "geometry": {"coordinates":[-96.72974000000001,33.086834],"type":"Point"}
}