{
  "type": "Feature",
  "properties": {
    "iso:country":"US",
    "sg:address":"1111 Seminole Rd",
    "sg:city":"Lamesa",
    "sg:classifiers":[
        {
            "category":"Autos & Motor Vehicles",
            "subcategory":"Fuel & Gas Station",
            "type":"Retail Goods"
        }
    ],
    "sg:phone":"+1 806 872 7636",
    "sg:postcode":"79331",
    "sg:province":"TX",
    "sg:tags":[
        "station",
        "gasoline"
    ],
    "wof:name":"Trent Investments Inc",
    "wof:placetype":"venue"
},
  "geometry": {"coordinates":[-101.961726,32.734381],"type":"Point"}
}