{
  "type": "Feature",
  "properties": {
    "iso:country":"US",
    "sg:address":"6051 Mendocino Dr",
    "sg:city":"Dallas",
    "sg:classifiers":[
        {
            "category":"Building & Trades",
            "subcategory":"Construction",
            "type":"Services"
        }
    ],
    "sg:phone":"+1 972 392 4409",
    "sg:postcode":"75248",
    "sg:province":"TX",
    "sg:tags":[
        "house"
    ],
    "wof:name":"Premium Painting & Home Repair",
    "wof:placetype":"venue"
},
  "geometry": {"coordinates":[-96.805975,32.956764],"type":"Point"}
}