{
  "type": "Feature",
  "properties": {
    "iso:country":"US",
    "sg:address":"1701 Columbia Dr",
    "sg:city":"Richardson",
    "sg:classifiers":[
        {
            "category":"Retail",
            "subcategory":"Repair Shop",
            "type":"Services"
        }
    ],
    "sg:phone":"+1 972 437 0990",
    "sg:postcode":"75081",
    "sg:province":"TX",
    "sg:tags":[
        "spa",
        "hot",
        "tub"
    ],
    "wof:name":"Daily Pool Svc",
    "wof:placetype":"venue"
},
  "geometry": {"coordinates":[-96.691203,32.95572],"type":"Point"}
}