{
  "type": "Feature",
  "properties": {
    "iso:country":"US",
    "sg:address":"3740 Little Rd Ofc",
    "sg:city":"Arlington",
    "sg:classifiers":[
        {
            "category":"Real Estate",
            "subcategory":"Real Estate Operator",
            "type":"Services"
        }
    ],
    "sg:phone":"+1 817 429 4095",
    "sg:postcode":"76016",
    "sg:province":"TX",
    "sg:tags":[
        "apartment"
    ],
    "sg:website":"http://www.aimco.com",
    "wof:name":"Aimco",
    "wof:placetype":"venue"
},
  "geometry": {"coordinates":[-97.189679,32.686056],"type":"Point"}
}