{
  "type": "Feature",
  "properties": {
    "iso:country":"US",
    "sg:address":"4416 Windsor Pkwy",
    "sg:city":"Dallas",
    "sg:classifiers":[
        {
            "category":"Professional",
            "subcategory":"Business Services",
            "type":"Services"
        }
    ],
    "sg:phone":"+1 214 520 7822",
    "sg:postcode":"75205",
    "sg:province":"TX",
    "sg:tags":[
        "bus"
    ],
    "wof:name":"Greystone Capital Corp",
    "wof:placetype":"venue"
},
  "geometry": {"coordinates":[-96.812789,32.842552],"type":"Point"}
}