{
  "type": "Feature",
  "properties": {
    "iso:country":"US",
    "sg:address":"9417 Great Hills Trl # 1043",
    "sg:city":"Austin",
    "sg:classifiers":[
        {
            "category":"Professional",
            "subcategory":"Art Services",
            "type":"Services"
        }
    ],
    "sg:phone":"+1 512 345 7896",
    "sg:postcode":"78759",
    "sg:province":"TX",
    "sg:tags":[
        "picture",
        "frame"
    ],
    "wof:name":"System Frame",
    "wof:placetype":"venue"
},
  "geometry": {"coordinates":[-97.755506,30.394071],"type":"Point"}
}