{
  "type": "Feature",
  "properties": {
    "iso:country":"US",
    "sg:address":"428 Stark Rd",
    "sg:city":"Dallas",
    "sg:classifiers":[
        {
            "category":"Manufacturing",
            "subcategory":"Printing",
            "type":"Manufacturing & Wholesale Goods"
        }
    ],
    "sg:phone":"+1 972 286 8082",
    "sg:postcode":"75253",
    "sg:province":"TX",
    "sg:tags":[
        "commercial"
    ],
    "wof:name":"Dangerous Designs",
    "wof:placetype":"venue"
},
  "geometry": {"coordinates":[-96.568851,32.680633],"type":"Point"}
}