{
  "type": "Feature",
  "properties": {
    "iso:country":"US",
    "sg:address":"209 Eden Rd",
    "sg:city":"Weatherford",
    "sg:classifiers":[
        {
            "category":"Building & Trades",
            "subcategory":"Construction",
            "type":"Services"
        }
    ],
    "sg:phone":"+1 817 341 0684",
    "sg:postcode":"76085",
    "sg:province":"TX",
    "sg:tags":[
        "contractor"
    ],
    "wof:name":"Cleve Smethers Cement Constr",
    "wof:placetype":"venue"
},
  "geometry": {"coordinates":[-97.793122,32.78739],"type":"Point"}
}