{
  "type": "Feature",
  "properties": {
    "iso:country":"US",
    "sg:address":"900 W Plummer St",
    "sg:city":"Eastland",
    "sg:classifiers":[
        {
            "category":"Education",
            "subcategory":"School",
            "type":"Public Place"
        }
    ],
    "sg:phone":"+1 254 631 5016",
    "sg:postcode":"76448",
    "sg:province":"TX",
    "wof:name":"Eastland Vocational Agri Bldg",
    "wof:placetype":"venue"
},
  "geometry": {"coordinates":[-98.828092,32.399498],"type":"Point"}
}