{
  "type": "Feature",
  "properties": {
    "iso:country":"US",
    "sg:address":"1921 62nd St",
    "sg:city":"Lubbock",
    "sg:classifiers":[
        {
            "category":"Health Services",
            "subcategory":"Clinic",
            "type":"Services"
        }
    ],
    "sg:phone":"+1 806 747 9042",
    "sg:postcode":"79412",
    "sg:province":"TX",
    "sg:tags":[
        "home"
    ],
    "wof:name":"Perrylee Home Health Care Svc",
    "wof:placetype":"venue"
},
  "geometry": {"coordinates":[-101.85620299999999,33.537982],"type":"Point"}
}