{
  "type": "Feature",
  "properties": {
    "iso:country":"US",
    "sg:address":"5110 Almeda Rd",
    "sg:city":"Houston",
    "sg:classifiers":[
        {
            "category":"Shopping",
            "subcategory":"Department Store",
            "type":"Retail Goods"
        },
        {
            "category":"Shopping",
            "subcategory":"Discount & Variety Stores",
            "type":"Retail Goods"
        }
    ],
    "sg:phone":"+1 713 521 4627",
    "sg:postcode":"77004",
    "sg:province":"TX",
    "sg:tags":[
        "shop"
    ],
    "wof:name":"Family Dollar Stores Inc",
    "wof:placetype":"venue"
},
  "geometry": {"coordinates":[-95.378601,29.723499],"type":"Point"}
}