{
  "type": "Feature",
  "properties": {
    "iso:country":"US",
    "sg:address":"3008 Swallow Ave",
    "sg:city":"Mcallen",
    "sg:classifiers":[
        {
            "category":"Professional",
            "subcategory":"Advertising",
            "type":"Services"
        }
    ],
    "sg:phone":"+1 956 682 6991",
    "sg:postcode":"78504",
    "sg:province":"TX",
    "sg:tags":[
        "book",
        "representative"
    ],
    "wof:name":"Holt Reinhart & Winston",
    "wof:placetype":"venue"
},
  "geometry": {"coordinates":[-98.24382300000001,26.26904],"type":"Point"}
}