{
  "type": "Feature",
  "properties": {
    "iso:country":"US",
    "sg:address":"1319 S Belt Line Rd",
    "sg:city":"Irving",
    "sg:classifiers":[
        {
            "category":"Freight",
            "type":"Transportation"
        }
    ],
    "sg:phone":"+1 972 399 6401",
    "sg:postcode":"75060",
    "sg:province":"TX",
    "sg:tags":[
        "operator",
        "trucking"
    ],
    "wof:name":"Lynden Transport Inc",
    "wof:placetype":"venue"
},
  "geometry": {"coordinates":[-96.994591,32.803762],"type":"Point"}
}