{
  "type": "Feature",
  "properties": {
    "iso:country":"US",
    "sg:address":"1605 Lillius St",
    "sg:city":"Abilene",
    "sg:classifiers":[
        {
            "category":"Personal",
            "subcategory":"Barber",
            "type":"Services"
        }
    ],
    "sg:phone":"+1 325 673 8229",
    "sg:postcode":"79603",
    "sg:province":"TX",
    "sg:tags":[
        "hair",
        "shop",
        "stylist",
        "beauty"
    ],
    "wof:name":"Maria's Beauty Salon",
    "wof:placetype":"venue"
},
  "geometry": {"coordinates":[-99.746849,32.4685],"type":"Point"}
}