{
  "type": "Feature",
  "properties": {
    "iso:country":"US",
    "sg:address":"2309 Canyonwood Dr",
    "sg:city":"Arlington",
    "sg:classifiers":[
        {
            "category":"Professional",
            "type":"Services"
        }
    ],
    "sg:phone":"+1 817 261 1484",
    "sg:postcode":"76012",
    "sg:province":"TX",
    "wof:name":"Kp Wood Works",
    "wof:placetype":"venue"
},
  "geometry": {"coordinates":[-97.12703500000001,32.774073],"type":"Point"}
}