{
  "type": "Feature",
  "properties": {
    "iso:country":"US",
    "sg:address":"2407 W Azalea Dr",
    "sg:city":"Tyler",
    "sg:classifiers":[
        {
            "category":"Professional",
            "subcategory":"Management & Consulting",
            "type":"Services"
        }
    ],
    "sg:phone":"+1 903 593 7056",
    "sg:postcode":"75701",
    "sg:province":"TX",
    "wof:name":"Russell Management LLC",
    "wof:placetype":"venue"
},
  "geometry": {"coordinates":[-95.314761,32.324465],"type":"Point"}
}