{
  "type": "Feature",
  "properties": {
    "iso:country":"US",
    "sg:address":"425 Lantana St",
    "sg:city":"Corpus Christi",
    "sg:classifiers":[
        {
            "category":"Wholesale",
            "subcategory":"Machinery & Supplies",
            "type":"Manufacturing & Wholesale Goods"
        }
    ],
    "sg:phone":"+1 361 289 2168",
    "sg:postcode":"78408",
    "sg:province":"TX",
    "sg:tags":[
        "equipment",
        "industrial"
    ],
    "wof:name":"BEC Bell Equipment Company",
    "wof:placetype":"venue"
},
  "geometry": {"coordinates":[-97.470327,27.793759],"type":"Point"}
}