{
  "type": "Feature",
  "properties": {
    "iso:country":"US",
    "sg:address":"108 E 6th St",
    "sg:city":"Borger",
    "sg:classifiers":[
        {
            "category":"Professional",
            "subcategory":"Lawyer & Legal Services",
            "type":"Services"
        }
    ],
    "sg:phone":"+1 806 274 5215",
    "sg:postcode":"79007",
    "sg:province":"TX",
    "wof:name":"Hinshaw Law Firm",
    "wof:placetype":"venue"
},
  "geometry": {"coordinates":[-101.38878800000001,35.671629],"type":"Point"}
}