{
  "type": "Feature",
  "properties": {
    "iso:country":"US",
    "sg:address":"8871 Co Rd 678",
    "sg:city":"Royse City",
    "sg:classifiers":[
        {
            "category":"Shopping",
            "subcategory":"Gifts & Souvenirs",
            "type":"Retail Goods"
        }
    ],
    "sg:phone":"+1 972 636 2709",
    "sg:postcode":"75189",
    "sg:province":"TX",
    "sg:tags":[
        "shop",
        "novelty"
    ],
    "wof:name":"Piggybanks Etc",
    "wof:placetype":"venue"
},
  "geometry": {"coordinates":[-96.300916,33.040551],"type":"Point"}
}