{
  "type": "Feature",
  "properties": {
    "iso:country":"US",
    "sg:address":"605 Martin Luther King Jr Dr",
    "sg:city":"Temple",
    "sg:classifiers":[
        {
            "category":"Manufacturing",
            "subcategory":"Signs",
            "type":"Manufacturing & Wholesale Goods"
        }
    ],
    "sg:phone":"+1 254 774 9400",
    "sg:postcode":"76504",
    "sg:province":"TX",
    "wof:name":"Glass Mirror & Blind Shop",
    "wof:placetype":"venue"
},
  "geometry": {"coordinates":[-97.3398,31.088621],"type":"Point"}
}