{
  "type": "Feature",
  "properties": {
    "iso:country":"US",
    "sg:address":"2300 Franklin Dr",
    "sg:city":"Fort Worth",
    "sg:classifiers":[
        {
            "category":"Professional",
            "subcategory":"Advertising",
            "type":"Services"
        }
    ],
    "sg:phone":"+1 817 625 1562",
    "sg:postcode":"76106",
    "sg:province":"TX",
    "sg:tags":[
        "distribution"
    ],
    "wof:name":"Baker Distributing Co",
    "wof:placetype":"venue"
},
  "geometry": {"coordinates":[-97.327855,32.825901],"type":"Point"}
}