{
  "type": "Feature",
  "properties": {
    "iso:country":"US",
    "sg:address":"1002 Barcus St",
    "sg:city":"Clarendon",
    "sg:classifiers":[
        {
            "category":"Shopping",
            "subcategory":"Hobbies, Toys, & Games",
            "type":"Retail Goods"
        }
    ],
    "sg:phone":"+1 806 874 2324",
    "sg:postcode":"79226",
    "sg:province":"TX",
    "sg:tags":[
        "craft"
    ],
    "wof:name":"From The Heart",
    "wof:placetype":"venue"
},
  "geometry": {"coordinates":[-100.881421,34.930142],"type":"Point"}
}