{
  "type": "Feature",
  "properties": {
    "iso:country":"US",
    "sg:address":"1718 Altacrest Dr",
    "sg:city":"Grapevine",
    "sg:classifiers":[
        {
            "category":"Sports & Exercise",
            "subcategory":"Gym",
            "type":"Entertainment"
        }
    ],
    "sg:phone":"+1 817 329 0663",
    "sg:postcode":"76051",
    "sg:province":"TX",
    "sg:tags":[
        "fitness",
        "physical",
        "facility"
    ],
    "wof:name":"Joy & Fitness Partners",
    "wof:placetype":"venue"
},
  "geometry": {"coordinates":[-97.09025200000001,32.88323],"type":"Point"}
}