{
  "type": "Feature",
  "properties": {
    "iso:country":"US",
    "sg:address":"3426 Milton Ave",
    "sg:city":"Dallas",
    "sg:classifiers":[
        {
            "category":"Health Services",
            "subcategory":"Doctor",
            "type":"Services"
        }
    ],
    "sg:phone":"+1 972 739 7500",
    "sg:postcode":"75205",
    "sg:province":"TX",
    "sg:tags":[
        "physician",
        "surgeon"
    ],
    "wof:name":"Neurosurgeons For Tx",
    "wof:placetype":"venue"
},
  "geometry": {"coordinates":[-96.78849700000001,32.848562],"type":"Point"}
}