{
  "type": "Feature",
  "properties": {
    "iso:country":"US",
    "sg:address":"12602 Taylor Dr",
    "sg:city":"Buda",
    "sg:classifiers":[
        {
            "category":"Professional",
            "subcategory":"Business Services",
            "type":"Services"
        }
    ],
    "sg:phone":"+1 512 312 2671",
    "sg:postcode":"78610",
    "sg:province":"TX",
    "wof:name":"Crouch and Associates Ltd",
    "wof:placetype":"venue"
},
  "geometry": {"coordinates":[-97.861649,30.117336],"type":"Point"}
}