{
  "type": "Feature",
  "properties": {
    "iso:country":"US",
    "sg:address":"111 N Hampton Rd",
    "sg:city":"Desoto",
    "sg:classifiers":[
        {
            "category":"Shopping",
            "type":"Retail Goods"
        },
        {
            "category":"Building & Trades",
            "subcategory":"Construction",
            "type":"Services"
        }
    ],
    "sg:phone":"+1 972 230 2565",
    "sg:postcode":"75115",
    "sg:province":"TX",
    "sg:tags":[
        "designer",
        "supply",
        "accessory",
        "dealer",
        "pool",
        "swimming"
    ],
    "wof:name":"Crown Pools",
    "wof:placetype":"venue"
},
  "geometry": {"coordinates":[-96.857026,32.591144],"type":"Point"}
}