{
  "type": "Feature",
  "properties": {
    "iso:country":"US",
    "sg:address":"1512 Brimwood Dr",
    "sg:city":"Mckinney",
    "sg:classifiers":[
        {
            "category":"Professional",
            "subcategory":"Art Services",
            "type":"Services"
        }
    ],
    "sg:phone":"+1 214 544 0220",
    "sg:postcode":"75070",
    "sg:province":"TX",
    "sg:tags":[
        "designer",
        "display",
        "producer"
    ],
    "wof:name":"Duke & Duchess Design Group",
    "wof:placetype":"venue"
},
  "geometry": {"coordinates":[-96.658838,33.183374],"type":"Point"}
}