{
  "type": "Feature",
  "properties": {
    "iso:country":"US",
    "sg:address":"1530 State Hwy 46",
    "sg:city":"Seguin",
    "sg:classifiers":[
        {
            "category":"Shopping",
            "subcategory":"Used Merchandise",
            "type":"Retail Goods"
        }
    ],
    "sg:phone":"+1 830 303 2037",
    "sg:postcode":"78155",
    "sg:province":"TX",
    "sg:tags":[
        "antique"
    ],
    "wof:name":"Antique Trading Post",
    "wof:placetype":"venue"
},
  "geometry": {"coordinates":[-97.994455,29.587526],"type":"Point"}
}