{
  "type": "Feature",
  "properties": {
    "iso:country":"US",
    "sg:address":"3308 Ethel Ave",
    "sg:city":"Waco",
    "sg:classifiers":[
        {
            "category":"Shopping",
            "subcategory":"Used Merchandise",
            "type":"Retail Goods"
        }
    ],
    "sg:phone":"+1 254 753 5840",
    "sg:postcode":"76707",
    "sg:province":"TX",
    "wof:name":"Jessies Place",
    "wof:placetype":"venue"
},
  "geometry": {"coordinates":[-97.171705,31.546491],"type":"Point"}
}