{
  "type": "Feature",
  "properties": {
    "iso:country":"US",
    "sg:address":"149 Tillison St",
    "sg:city":"Athens",
    "sg:classifiers":[
        {
            "category":"Professional",
            "subcategory":"Detective & Security Services",
            "type":"Services"
        }
    ],
    "sg:phone":"+1 903 288 3399",
    "sg:postcode":"75751",
    "sg:province":"TX",
    "sg:tags":[
        "information",
        "bureau"
    ],
    "wof:name":"Rc Services",
    "wof:placetype":"venue"
},
  "geometry": {"coordinates":[-95.85858,32.208011],"type":"Point"}
}