{
  "type": "Feature",
  "properties": {
    "iso:country":"US",
    "sg:address":"1313 US Hwy 281 Bus",
    "sg:city":"Edinburg",
    "sg:classifiers":[
        {
            "category":"Wholesale",
            "subcategory":"Electrical",
            "type":"Manufacturing & Wholesale Goods"
        }
    ],
    "sg:phone":"+1 956 393 2233",
    "sg:postcode":"78539",
    "sg:province":"TX",
    "sg:tags":[
        "electric",
        "motor"
    ],
    "wof:name":"Valley Armature & Electric Co",
    "wof:placetype":"venue"
},
  "geometry": {"coordinates":[-98.16006,26.315391],"type":"Point"}
}