{
  "type": "Feature",
  "properties": {
    "iso:country":"US",
    "sg:address":"1515 Knox Rd",
    "sg:city":"Roanoke",
    "sg:classifiers":[
        {
            "category":"Building & Trades",
            "subcategory":"Construction",
            "type":"Services"
        }
    ],
    "sg:phone":"+1 817 430 2158",
    "sg:postcode":"76262",
    "sg:province":"TX",
    "sg:tags":[
        "general",
        "contractor"
    ],
    "wof:name":"J J Culp & Associates",
    "wof:placetype":"venue"
},
  "geometry": {"coordinates":[-97.216874,32.969393],"type":"Point"}
}