{
  "type": "Feature",
  "properties": {
    "iso:country":"US",
    "sg:address":"3648 Matlock Rd",
    "sg:city":"Arlington",
    "sg:classifiers":[
        {
            "category":"Food & Beverages",
            "subcategory":"Groceries & Convenience Stores",
            "type":"Retail Goods"
        }
    ],
    "sg:phone":"+1 817 468 0018",
    "sg:postcode":"76015",
    "sg:province":"TX",
    "wof:name":"7-Eleven",
    "wof:placetype":"venue"
},
  "geometry": {"coordinates":[-97.115111,32.687691],"type":"Point"}
}