{
  "type": "Feature",
  "properties": {
    "iso:country":"US",
    "sg:address":"40910 Roundup Rd",
    "sg:city":"Magnolia",
    "sg:classifiers":[
        {
            "category":"Personal",
            "subcategory":"Beauty Salon",
            "type":"Services"
        }
    ],
    "sg:phone":"+1 832 934 2755",
    "sg:postcode":"77354",
    "sg:province":"TX",
    "wof:name":"Shirls Skin Care",
    "wof:placetype":"venue"
},
  "geometry": {"coordinates":[-95.593129,30.239388],"type":"Point"}
}