{
  "type": "Feature",
  "properties": {
    "iso:country":"US",
    "sg:address":"1604 Allen Dr",
    "sg:city":"Cedar Hill",
    "sg:classifiers":[
        {
            "category":"Shopping",
            "subcategory":"Books",
            "type":"Retail Goods"
        }
    ],
    "sg:phone":"+1 972 293 9779",
    "sg:postcode":"75104",
    "sg:province":"TX",
    "wof:name":"Wilson Productions",
    "wof:placetype":"venue"
},
  "geometry": {"coordinates":[-96.93969300000001,32.62408],"type":"Point"}
}