{
  "type": "Feature",
  "properties": {
    "iso:country":"US",
    "sg:address":"8101 S 23rd St",
    "sg:city":"Hidalgo",
    "sg:classifiers":[
        {
            "category":"Freight",
            "type":"Transportation"
        }
    ],
    "sg:phone":"+1 956 843 7740",
    "sg:postcode":"78503",
    "sg:province":"TX",
    "wof:name":"St Judes Transportation",
    "wof:placetype":"venue"
},
  "geometry": {"coordinates":[-98.255184,26.140839],"type":"Point"}
}