{
  "type": "Feature",
  "properties": {
    "iso:country":"US",
    "sg:address":"1408 E Tyler St",
    "sg:city":"Athens",
    "sg:classifiers":[
        {
            "category":"Restaurant",
            "type":"Food & Drink"
        }
    ],
    "sg:phone":"+1 903 677 1450",
    "sg:postcode":"75751",
    "sg:province":"TX",
    "sg:tags":[
        "eating"
    ],
    "wof:name":"Felipes Mexican Food",
    "wof:placetype":"venue"
},
  "geometry": {"coordinates":[-95.830297,32.20997],"type":"Point"}
}