{
  "type": "Feature",
  "properties": {
    "iso:country":"US",
    "sg:address":"12414 Stafford Springs Dr",
    "sg:city":"Houston",
    "sg:classifiers":[
        {
            "category":"Real Estate",
            "subcategory":"Real Estate Agent",
            "type":"Services"
        }
    ],
    "sg:phone":"+1 281 493 0155",
    "sg:postcode":"77077",
    "sg:province":"TX",
    "wof:name":"Marilyn Arendt Properties",
    "wof:placetype":"venue"
},
  "geometry": {"coordinates":[-95.601949,29.75305],"type":"Point"}
}