{
  "type": "Feature",
  "properties": {
    "iso:country":"US",
    "sg:address":"846 N Glenville Dr",
    "sg:city":"Richardson",
    "sg:classifiers":[
        {
            "category":"Wholesale",
            "subcategory":"Metals & Minerals",
            "type":"Manufacturing & Wholesale Goods"
        }
    ],
    "sg:phone":"+1 972 437 4984",
    "sg:postcode":"75081",
    "sg:province":"TX",
    "sg:tags":[
        "high",
        "resistant",
        "chemically",
        "purity",
        "tubing"
    ],
    "wof:name":"Ultra Pure Products",
    "wof:placetype":"venue"
},
  "geometry": {"coordinates":[-96.70528400000001,32.958729],"type":"Point"}
}