{
  "type": "Feature",
  "properties": {
    "iso:country":"US",
    "sg:address":"5900 E Lancaster Ave",
    "sg:city":"Fort Worth",
    "sg:classifiers":[
        {
            "category":"Real Estate",
            "subcategory":"Real Estate Agent",
            "type":"Services"
        }
    ],
    "sg:phone":"+1 817 446 8707",
    "sg:postcode":"76112",
    "sg:province":"TX",
    "wof:name":"Dreiling Realty",
    "wof:placetype":"venue"
},
  "geometry": {"coordinates":[-97.22838,32.736022],"type":"Point"}
}