{
  "type": "Feature",
  "properties": {
    "iso:country":"US",
    "sg:address":"2215 Washington Ave",
    "sg:city":"Houston",
    "sg:classifiers":[
        {
            "category":"Food & Beverages",
            "subcategory":"Groceries & Convenience Stores",
            "type":"Retail Goods"
        }
    ],
    "sg:phone":"+1 713 863 1986",
    "sg:postcode":"77007",
    "sg:province":"TX",
    "sg:tags":[
        "market"
    ],
    "wof:name":"Mid-Century Pavilion",
    "wof:placetype":"venue"
},
  "geometry": {"coordinates":[-95.38130200000001,29.768101],"type":"Point"}
}