{
  "type": "Feature",
  "properties": {
    "iso:country":"US",
    "sg:address":"355 Guenther Ranch",
    "sg:city":"New Braunfels",
    "sg:classifiers":[
        {
            "category":"Professional",
            "type":"Services"
        }
    ],
    "sg:phone":"+1 830 935 4109",
    "sg:postcode":"78133",
    "sg:province":"TX",
    "wof:name":"Paul A Toudouze",
    "wof:placetype":"venue"
},
  "geometry": {"coordinates":[-98.228615,29.929024],"type":"Point"}
}