{
  "type": "Feature",
  "properties": {
    "iso:country":"US",
    "sg:address":"12220 Jones Rd",
    "sg:city":"Houston",
    "sg:classifiers":[
        {
            "category":"Personal",
            "subcategory":"Beauty Salon",
            "type":"Services"
        }
    ],
    "sg:phone":"+1 281 970 9990",
    "sg:postcode":"77070",
    "sg:province":"TX",
    "sg:tags":[
        "shop"
    ],
    "wof:name":"Serene Nails Spa",
    "wof:placetype":"venue"
},
  "geometry": {"coordinates":[-95.584788,29.952266],"type":"Point"}
}