{
  "type": "Feature",
  "properties": {
    "iso:country":"US",
    "sg:address":"17606 Majestic Forest Dr",
    "sg:city":"Spring",
    "sg:classifiers":[
        {
            "category":"Wholesale",
            "subcategory":"Durable Goods & Equipment",
            "type":"Manufacturing & Wholesale Goods"
        }
    ],
    "sg:phone":"+1 281 370 6844",
    "sg:postcode":"77379",
    "sg:province":"TX",
    "wof:name":"Bill Weatherly Assoc",
    "wof:placetype":"venue"
},
  "geometry": {"coordinates":[-95.51854,30.036813],"type":"Point"}
}