{
  "type": "Feature",
  "properties": {
    "iso:country":"US",
    "sg:address":"1101 Richland Dr",
    "sg:city":"Waco",
    "sg:classifiers":[
        {
            "category":"Travel",
            "subcategory":"Travel Agent",
            "type":"Entertainment"
        }
    ],
    "sg:phone":"+1 254 776 4401",
    "sg:postcode":"76710",
    "sg:province":"TX",
    "sg:tags":[
        "agency"
    ],
    "wof:name":"Waco Travel Time Inc",
    "wof:placetype":"venue"
},
  "geometry": {"coordinates":[-97.194154,31.531373],"type":"Point"}
}