{
  "type": "Feature",
  "properties": {
    "iso:country":"US",
    "sg:address":"10902 Cora St",
    "sg:city":"Houston",
    "sg:classifiers":[
        {
            "category":"Manufacturing",
            "subcategory":"Tools & Machinery",
            "type":"Manufacturing & Wholesale Goods"
        }
    ],
    "sg:phone":"+1 281 447 2201",
    "sg:postcode":"77088",
    "sg:province":"TX",
    "sg:tags":[
        "compressor",
        "mfg"
    ],
    "wof:name":"Reed Mfg",
    "wof:placetype":"venue"
},
  "geometry": {"coordinates":[-95.441366,29.896392],"type":"Point"}
}