{
  "type": "Feature",
  "properties": {
    "iso:country":"US",
    "sg:address":"1701 River Run",
    "sg:city":"Fort Worth",
    "sg:classifiers":[
        {
            "category":"Professional",
            "subcategory":"Accounting & Tax Preparation",
            "type":"Services"
        }
    ],
    "sg:phone":"+1 817 348 8969",
    "sg:postcode":"76107",
    "sg:province":"TX",
    "sg:tags":[
        "billing"
    ],
    "wof:name":"Collection Concepts Inc",
    "wof:placetype":"venue"
},
  "geometry": {"coordinates":[-97.36111699999999,32.726745],"type":"Point"}
}