{
  "type": "Feature",
  "properties": {
    "iso:country":"US",
    "sg:address":"11916 Green Pines Cir",
    "sg:city":"Houston",
    "sg:classifiers":[
        {
            "category":"Building & Trades",
            "subcategory":"Construction",
            "type":"Services"
        }
    ],
    "sg:phone":"+1 281 444 0884",
    "sg:postcode":"77066",
    "sg:province":"TX",
    "wof:name":"H & U Construction Co",
    "wof:placetype":"venue"
},
  "geometry": {"coordinates":[-95.50080199999999,29.94973],"type":"Point"}
}