{
  "type": "Feature",
  "properties": {
    "iso:country":"US",
    "sg:address":"2901 W Bolt St",
    "sg:city":"Fort Worth",
    "sg:classifiers":[
        {
            "category":"Wholesale",
            "subcategory":"Apparel",
            "type":"Manufacturing & Wholesale Goods"
        }
    ],
    "sg:phone":"+1 817 921 6898",
    "sg:postcode":"76110",
    "sg:province":"TX",
    "sg:tags":[
        "piece"
    ],
    "wof:name":"Owens & Perry",
    "wof:placetype":"venue"
},
  "geometry": {"coordinates":[-97.363309,32.689324],"type":"Point"}
}