{
  "type": "Feature",
  "properties": {
    "iso:country":"US",
    "sg:address":"89 S Lake Shore Dr",
    "sg:city":"Ransom Canyon",
    "sg:classifiers":[
        {
            "category":"Professional",
            "subcategory":"Management & Consulting",
            "type":"Services"
        }
    ],
    "sg:phone":"+1 806 745 7437",
    "sg:postcode":"79366",
    "sg:province":"TX",
    "sg:tags":[
        "business"
    ],
    "wof:name":"Big Muscles Inc",
    "wof:placetype":"venue"
},
  "geometry": {"coordinates":[-101.68272399999999,33.526877],"type":"Point"}
}