{
  "type": "Feature",
  "properties": {
    "iso:country":"US",
    "sg:address":"1818 Swan Dr",
    "sg:city":"Dallas",
    "sg:classifiers":[
        {
            "category":"Professional",
            "subcategory":"Business Services",
            "type":"Services"
        }
    ],
    "sg:phone":"+1 214 319 9434",
    "sg:postcode":"75228",
    "sg:province":"TX",
    "wof:name":"Strong Designs",
    "wof:placetype":"venue"
},
  "geometry": {"coordinates":[-96.68289300000001,32.819457],"type":"Point"}
}