{
  "type": "Feature",
  "properties": {
    "iso:country":"US",
    "sg:address":"10990 Switzer Ave",
    "sg:city":"Dallas",
    "sg:classifiers":[
        {
            "category":"Professional",
            "subcategory":"Lawyer & Legal Services",
            "type":"Services"
        }
    ],
    "sg:phone":"+1 214 221 6053",
    "sg:postcode":"75238",
    "sg:province":"TX",
    "wof:name":"P & P Office Service",
    "wof:placetype":"venue"
},
  "geometry": {"coordinates":[-96.704392,32.896901],"type":"Point"}
}