{
  "type": "Feature",
  "properties": {
    "iso:country":"US",
    "sg:address":"1611 S I- 35 E",
    "sg:city":"Carrollton",
    "sg:classifiers":[
        {
            "category":"Wholesale",
            "subcategory":"Apparel",
            "type":"Manufacturing & Wholesale Goods"
        }
    ],
    "sg:phone":"+1 972 446 8809",
    "sg:postcode":"75006",
    "sg:province":"TX",
    "sg:tags":[
        "clothing"
    ],
    "wof:name":"Strings",
    "wof:placetype":"venue"
},
  "geometry": {"coordinates":[-96.904866,32.946065],"type":"Point"}
}