{
  "type": "Feature",
  "properties": {
    "iso:country":"US",
    "sg:address":"1416 N Hwy 360",
    "sg:city":"Arlington",
    "sg:classifiers":[
        {
            "category":"Health Services",
            "subcategory":"Optometrist",
            "type":"Services"
        }
    ],
    "sg:phone":"+1 817 633 2020",
    "sg:postcode":"76006",
    "sg:province":"TX",
    "wof:name":"Contact Lens Clinic",
    "wof:placetype":"venue"
},
  "geometry": {"coordinates":[-97.063064,32.771073],"type":"Point"}
}