{
  "type": "Feature",
  "properties": {
    "iso:country":"US",
    "sg:address":"3914 Kashmere St",
    "sg:city":"Houston",
    "sg:classifiers":[
        {
            "category":"Social Services",
            "subcategory":"Child Care",
            "type":"Services"
        }
    ],
    "sg:phone":"+1 713 672 0478",
    "sg:postcode":"77026",
    "sg:province":"TX",
    "sg:tags":[
        "day"
    ],
    "wof:name":"Little Audreys Day Care/Kindr",
    "wof:placetype":"venue"
},
  "geometry": {"coordinates":[-95.323942,29.795215],"type":"Point"}
}