{
  "type": "Feature",
  "properties": {
    "iso:country":"US",
    "sg:address":"837 N University Dr",
    "sg:city":"Nacogdoches",
    "sg:classifiers":[
        {
            "category":"Shopping",
            "type":"Retail Goods"
        },
        {
            "category":"Wholesale",
            "subcategory":"Jewelry",
            "type":"Manufacturing & Wholesale Goods"
        }
    ],
    "sg:phone":"+1 936 560 6888",
    "sg:postcode":"75962",
    "sg:province":"TX",
    "sg:tags":[
        "stone",
        "des",
        "commercial",
        "plaque"
    ],
    "wof:name":"AAA Trophy T-Shirt & Sport Sp",
    "wof:placetype":"venue"
},
  "geometry": {"coordinates":[-94.64060000000001,31.610232],"type":"Point"}
}