{
  "type": "Feature",
  "properties": {
    "iso:country":"US",
    "sg:address":"155 Lemens Cir",
    "sg:city":"Hutto",
    "sg:classifiers":[
        {
            "category":"Retail",
            "subcategory":"Animal Services",
            "type":"Services"
        }
    ],
    "sg:phone":"+1 512 759 5119",
    "sg:postcode":"78634",
    "sg:province":"TX",
    "sg:tags":[
        "cat",
        "dog",
        "kennel"
    ],
    "wof:name":"Covered Wagon Kennel",
    "wof:placetype":"venue"
},
  "geometry": {"coordinates":[-97.590138,30.571918],"type":"Point"}
}