{
  "type": "Feature",
  "properties": {
    "iso:country":"US",
    "sg:address":"6010 Autumn Hills Dr",
    "sg:city":"Fort Worth",
    "sg:classifiers":[
        {
            "category":"Professional",
            "subcategory":"Management & Consulting",
            "type":"Services"
        }
    ],
    "sg:phone":"+1 817 516 9668",
    "sg:postcode":"76140",
    "sg:province":"TX",
    "sg:tags":[
        "business"
    ],
    "wof:name":"HB Belcher & Assoc",
    "wof:placetype":"venue"
},
  "geometry": {"coordinates":[-97.25626099999999,32.592614],"type":"Point"}
}