{
  "type": "Feature",
  "properties": {
    "iso:country":"US",
    "sg:address":"1807 Thompson Crossing Dr",
    "sg:city":"Richmond",
    "sg:classifiers":[
        {
            "category":"Freight",
            "type":"Transportation"
        }
    ],
    "sg:phone":"+1 281 520 6563",
    "sg:postcode":"77469",
    "sg:province":"TX",
    "sg:tags":[
        "trucking"
    ],
    "wof:name":"Roosevelt Miller",
    "wof:placetype":"venue"
},
  "geometry": {"coordinates":[-95.735473,29.630357],"type":"Point"}
}