{
  "type": "Feature",
  "properties": {
    "iso:country":"US",
    "sg:address":"1105 E Plano Pkwy",
    "sg:city":"Plano",
    "sg:classifiers":[
        {
            "category":"Home & Garden",
            "subcategory":"Household Appliances",
            "type":"Retail Goods"
        },
        {
            "category":"Retail",
            "subcategory":"Repair Shop",
            "type":"Services"
        }
    ],
    "sg:phone":"+1 972 496 1000",
    "sg:postcode":"75074",
    "sg:province":"TX",
    "sg:tags":[
        "small",
        "major"
    ],
    "wof:name":"A-Appliance",
    "wof:placetype":"venue"
},
  "geometry": {"coordinates":[-96.699268,33.007369],"type":"Point"}
}