{
  "type": "Feature",
  "properties": {
    "iso:country":"US",
    "sg:address":"18351 Kuykendahl Rd",
    "sg:city":"Spring",
    "sg:classifiers":[
        {
            "category":"Personal",
            "type":"Services"
        }
    ],
    "sg:phone":"+1 281 821 1160",
    "sg:postcode":"77379",
    "sg:province":"TX",
    "sg:tags":[
        "control",
        "weight"
    ],
    "wof:name":"Jeanne Singer & Assoc",
    "wof:placetype":"venue"
},
  "geometry": {"coordinates":[-95.486923,30.037929],"type":"Point"}
}