{
  "type": "Feature",
  "properties": {
    "iso:country":"US",
    "sg:address":"6116 Windswept Ln",
    "sg:city":"Houston",
    "sg:classifiers":[
        {
            "category":"Utilities",
            "subcategory":"Telephone",
            "type":"Services"
        }
    ],
    "sg:phone":"+1 713 954 5712",
    "sg:postcode":"77057",
    "sg:province":"TX",
    "sg:tags":[
        "distance",
        "ca",
        "lottery",
        "ticket",
        "long"
    ],
    "wof:name":"Lotto-Tel",
    "wof:placetype":"venue"
},
  "geometry": {"coordinates":[-95.48952300000001,29.726515],"type":"Point"}
}