{
  "type": "Feature",
  "properties": {
    "iso:country":"US",
    "sg:address":"1214 Canterbury Ct",
    "sg:city":"Arlington",
    "sg:classifiers":[
        {
            "category":"Banks & Credit Unions",
            "subcategory":"Investment Brokerage",
            "type":"Services"
        }
    ],
    "sg:phone":"+1 817 459 1024",
    "sg:postcode":"76013",
    "sg:province":"TX",
    "sg:tags":[
        "security",
        "real estate"
    ],
    "wof:name":"In-Store Promotions",
    "wof:placetype":"venue"
},
  "geometry": {"coordinates":[-97.168359,32.724959],"type":"Point"}
}