{
  "type": "Feature",
  "properties": {
    "iso:country":"US",
    "sg:address":"1605 Ranch House Rd",
    "sg:city":"Willow Park",
    "sg:classifiers":[
        {
            "category":"Recreation",
            "type":"Entertainment"
        }
    ],
    "sg:phone":"+1 817 441 8185",
    "sg:postcode":"76087",
    "sg:province":"TX",
    "sg:tags":[
        "club",
        "course",
        "golf"
    ],
    "sg:website":"www.flash.net",
    "wof:name":"Squaw Creek Golf Club",
    "wof:placetype":"venue"
},
  "geometry": {"coordinates":[-97.63856,32.755683],"type":"Point"}
}