{
  "type": "Feature",
  "properties": {
    "iso:country":"US",
    "sg:address":"2401 S Ervay St",
    "sg:city":"Dallas",
    "sg:classifiers":[
        {
            "category":"Professional",
            "subcategory":"Art Services",
            "type":"Services"
        },
        {
            "category":"Professional",
            "subcategory":"Advertising",
            "type":"Services"
        }
    ],
    "sg:phone":"+1 214 428 8251",
    "sg:postcode":"75215",
    "sg:province":"TX",
    "sg:tags":[
        "design",
        "graphic",
        "commercial",
        "agency",
        "designer"
    ],
    "wof:name":"Henvey & Assoc",
    "wof:placetype":"venue"
},
  "geometry": {"coordinates":[-96.78261500000001,32.766577],"type":"Point"}
}