{
  "type": "Feature",
  "properties": {
    "iso:country":"US",
    "sg:address":"2804 Clark Blvd",
    "sg:city":"Laredo",
    "sg:classifiers":[
        {
            "category":"Retail",
            "subcategory":"Auto Repair",
            "type":"Services"
        }
    ],
    "sg:phone":"+1 956 723 7433",
    "sg:postcode":"78043",
    "sg:province":"TX",
    "sg:tags":[
        "general"
    ],
    "wof:name":"Ace Auto Service",
    "wof:placetype":"venue"
},
  "geometry": {"coordinates":[-99.46701299999999,27.516706],"type":"Point"}
}