{
  "type": "Feature",
  "properties": {
    "iso:country":"US",
    "sg:address":"12225 League Line Rd",
    "sg:city":"Conroe",
    "sg:classifiers":[
        {
            "category":"Building & Trades",
            "subcategory":"Construction",
            "type":"Services"
        }
    ],
    "sg:phone":"+1 936 756 6465",
    "sg:postcode":"77304",
    "sg:province":"TX",
    "sg:tags":[
        "home",
        "repair"
    ],
    "wof:name":"Honey Dos",
    "wof:placetype":"venue"
},
  "geometry": {"coordinates":[-95.542652,30.38017],"type":"Point"}
}