{
  "type": "Feature",
  "properties": {
    "iso:country":"US",
    "sg:address":"13777 Bee St",
    "sg:city":"Dallas",
    "sg:classifiers":[
        {
            "category":"Home & Garden",
            "subcategory":"Carpets & Floor Coverings",
            "type":"Retail Goods"
        }
    ],
    "sg:phone":"+1 214 389 4737",
    "sg:postcode":"75234",
    "sg:province":"TX",
    "sg:tags":[
        "material"
    ],
    "wof:name":"Professional Flooring Supply C",
    "wof:placetype":"venue"
},
  "geometry": {"coordinates":[-96.896477,32.931988],"type":"Point"}
}