{
  "type": "Feature",
  "properties": {
    "iso:country":"US",
    "sg:address":"14631 River Forest Dr",
    "sg:city":"Houston",
    "sg:classifiers":[
        {
            "category":"Professional",
            "type":"Services"
        }
    ],
    "sg:phone":"+1 281 497 7139",
    "sg:postcode":"77079",
    "sg:province":"TX",
    "wof:name":"Kr Petroleum Inc",
    "wof:placetype":"venue"
},
  "geometry": {"coordinates":[-95.607972,29.76457],"type":"Point"}
}