{
  "type": "Feature",
  "properties": {
    "iso:country":"US",
    "sg:address":"1214 Chandler Cir",
    "sg:city":"Prosper",
    "sg:classifiers":[
        {
            "category":"Health Services",
            "subcategory":"Doctor",
            "type":"Services"
        }
    ],
    "sg:phone":"+1 972 347 2849",
    "sg:postcode":"75078",
    "sg:province":"TX",
    "wof:name":"Odom Charles B MD",
    "wof:placetype":"venue"
},
  "geometry": {"coordinates":[-96.782796,33.247053],"type":"Point"}
}