{
  "type": "Feature",
  "properties": {
    "iso:country":"US",
    "sg:address":"8507 Hwy 377 S",
    "sg:city":"Benbrook",
    "sg:classifiers":[
        {
            "category":"Wholesale",
            "subcategory":"Durable Goods & Equipment",
            "type":"Manufacturing & Wholesale Goods"
        }
    ],
    "sg:phone":"+1 817 249 0099",
    "sg:postcode":"76126",
    "sg:province":"TX",
    "sg:tags":[
        "representative",
        "manufacturer"
    ],
    "wof:name":"Five Star Marketing",
    "wof:placetype":"venue"
},
  "geometry": {"coordinates":[-97.46412100000001,32.679194],"type":"Point"}
}