{
  "type": "Feature",
  "properties": {
    "iso:country":"US",
    "sg:address":"6602 Ampton Dr",
    "sg:city":"Spring",
    "sg:classifiers":[
        {
            "category":"Organizations",
            "subcategory":"Non-profit Organization",
            "type":"Services"
        }
    ],
    "sg:phone":"+1 281 320 9973",
    "sg:postcode":"77379",
    "sg:province":"TX",
    "sg:tags":[
        "social"
    ],
    "wof:name":"Compassionate Friends",
    "wof:placetype":"venue"
},
  "geometry": {"coordinates":[-95.509826,30.016718],"type":"Point"}
}