{
  "type": "Feature",
  "properties": {
    "iso:country":"US",
    "sg:address":"2701 Melba Ave",
    "sg:city":"Mcallen",
    "sg:classifiers":[
        {
            "category":"Shopping",
            "subcategory":"Gifts & Souvenirs",
            "type":"Retail Goods"
        }
    ],
    "sg:phone":"+1 956 682 3682",
    "sg:postcode":"78503",
    "sg:province":"TX",
    "sg:tags":[
        "shop"
    ],
    "wof:name":"Romance Flower & Gift Shop",
    "wof:placetype":"venue"
},
  "geometry": {"coordinates":[-98.258082,26.163117],"type":"Point"}
}