{
  "type": "Feature",
  "properties": {
    "iso:country":"US",
    "sg:address":"1465 Coolidge St",
    "sg:city":"Brownsville",
    "sg:classifiers":[
        {
            "category":"Professional",
            "type":"Services"
        }
    ],
    "sg:phone":"+1 956 542 6177",
    "sg:postcode":"78521",
    "sg:province":"TX",
    "sg:tags":[
        "place",
        "worship",
        "church"
    ],
    "wof:name":"Iglesia De Dios De La Profecia",
    "wof:placetype":"venue"
},
  "geometry": {"coordinates":[-97.477504,25.912839],"type":"Point"}
}