{
  "type": "Feature",
  "properties": {
    "iso:country":"US",
    "sg:address":"10133 Dyer Rd",
    "sg:city":"Sanger",
    "sg:classifiers":[
        {
            "category":"Professional",
            "type":"Services"
        }
    ],
    "sg:phone":"+1 940 458 7551",
    "sg:postcode":"76266",
    "sg:province":"TX",
    "wof:name":"Browns Farrier Service",
    "wof:placetype":"venue"
},
  "geometry": {"coordinates":[-97.28894699999999,33.347642],"type":"Point"}
}