{
  "type": "Feature",
  "properties": {
    "iso:country":"US",
    "sg:address":"10701 Sam Snead Dr",
    "sg:city":"El Paso",
    "sg:classifiers":[
        {
            "category":"Professional",
            "subcategory":"Management & Consulting",
            "type":"Services"
        }
    ],
    "sg:phone":"+1 915 591 9215",
    "sg:postcode":"79935",
    "sg:province":"TX",
    "sg:tags":[
        "business"
    ],
    "wof:name":"Practice Enhancement Co",
    "wof:placetype":"venue"
},
  "geometry": {"coordinates":[-106.326776,31.776353],"type":"Point"}
}