{
  "type": "Feature",
  "properties": {
    "iso:country":"US",
    "sg:address":"32521 Co Rd 2520",
    "sg:city":"San Benito",
    "sg:classifiers":[
        {
            "category":"Shopping",
            "subcategory":"Hobbies, Toys, & Games",
            "type":"Retail Goods"
        }
    ],
    "sg:phone":"+1 956 361 9297",
    "sg:postcode":"78586",
    "sg:province":"TX",
    "sg:tags":[
        "supply"
    ],
    "wof:name":"Magic Seven's Game Room",
    "wof:placetype":"venue"
},
  "geometry": {"coordinates":[-97.671199,26.087787],"type":"Point"}
}