{
  "type": "Feature",
  "properties": {
    "iso:country":"US",
    "sg:address":"311 E Sabinal St",
    "sg:city":"Uvalde",
    "sg:classifiers":[
        {
            "category":"Organizations",
            "subcategory":"Religious Organization",
            "type":"Services"
        }
    ],
    "sg:phone":"+1 830 278 6193",
    "sg:postcode":"78801",
    "sg:province":"TX",
    "wof:name":"Church Of The Nazarene",
    "wof:placetype":"venue"
},
  "geometry": {"coordinates":[-99.795135,29.228158],"type":"Point"}
}