{
  "type": "Feature",
  "properties": {
    "iso:country":"US",
    "sg:address":"1700 N Redbud Blvd",
    "sg:city":"Mc Kinney",
    "sg:classifiers":[
        {
            "category":"Manufacturing",
            "subcategory":"Tools & Machinery",
            "type":"Manufacturing & Wholesale Goods"
        }
    ],
    "sg:phone":"+1 972 529 7027",
    "sg:postcode":"75069",
    "sg:province":"TX",
    "sg:tags":[
        "pharmaceutical",
        "mfg",
        "prep",
        "ophthalmic"
    ],
    "wof:name":"Allergan",
    "wof:placetype":"venue"
},
  "geometry": {"coordinates":[-96.63170599999999,33.216502],"type":"Point"}
}