{
  "type": "Feature",
  "properties": {
    "iso:country":"US",
    "sg:address":"206 Southlawn Ave",
    "sg:city":"San Antonio",
    "sg:classifiers":[
        {
            "category":"Building & Trades",
            "subcategory":"Plumbing",
            "type":"Services"
        }
    ],
    "sg:phone":"+1 210 435 0843",
    "sg:postcode":"78237",
    "sg:province":"TX",
    "sg:tags":[
        "plumbing",
        "repair",
        "contractor"
    ],
    "wof:name":"Nicer Plumbing Co",
    "wof:placetype":"venue"
},
  "geometry": {"coordinates":[-98.560914,29.412887],"type":"Point"}
}