{
  "type": "Feature",
  "properties": {
    "iso:country":"US",
    "sg:address":"682 N FM 120",
    "sg:city":"Pottsboro",
    "sg:classifiers":[
        {
            "category":"Professional",
            "subcategory":"Management & Consulting",
            "type":"Services"
        },
        {
            "category":"Education",
            "subcategory":"Special Training",
            "type":"Public Place"
        }
    ],
    "sg:phone":"+1 903 786 5353",
    "sg:postcode":"75076",
    "sg:province":"TX",
    "sg:tags":[
        "educational"
    ],
    "wof:name":"Northwest Evaluation Assn",
    "wof:placetype":"venue"
},
  "geometry": {"coordinates":[-96.67482699999999,33.766496],"type":"Point"}
}