{
  "type": "Feature",
  "properties": {
    "iso:country":"US",
    "sg:address":"3018 N Stone Ave",
    "sg:city":"Laredo",
    "sg:classifiers":[
        {
            "category":"Place Of Worship",
            "subcategory":"Church",
            "type":"Public Place"
        },
        {
            "category":"Place Of Worship",
            "type":"Public Place"
        }
    ],
    "sg:phone":"+1 956 251 2220",
    "sg:postcode":"78040",
    "sg:province":"TX",
    "sg:tags":[
        "churches-interdenominational",
        "churches-various",
        "denomination"
    ],
    "wof:name":"The Good Shepherd Church Of The Nazarene",
    "wof:placetype":"venue"
},
  "geometry": {"coordinates":[-99.483437,27.523368],"type":"Point"}
}