{
  "type": "Feature",
  "properties": {
    "iso:country":"US",
    "sg:address":"4949 Westgrove Dr Ste 200",
    "sg:city":"Dallas",
    "sg:classifiers":[
        {
            "category":"Professional",
            "subcategory":"Lawyer & Legal Services",
            "type":"Services"
        }
    ],
    "sg:phone":"+1 972 960 6300",
    "sg:postcode":"75248",
    "sg:province":"TX",
    "wof:name":"Littleton Larry O Atty",
    "wof:placetype":"venue"
},
  "geometry": {"coordinates":[-96.8228,32.975899],"type":"Point"}
}