{
  "type": "Feature",
  "properties": {
    "iso:country":"US",
    "sg:address":"4835 Norma St",
    "sg:city":"Dallas",
    "sg:classifiers":[
        {
            "category":"Government",
            "subcategory":"Fire Station",
            "type":"Public Place"
        },
        {
            "category":"Retail",
            "subcategory":"Laundry & Dry Cleaning",
            "type":"Services"
        },
        {
            "category":"Building & Trades",
            "subcategory":"Cleaning & Sanitation",
            "type":"Services"
        }
    ],
    "sg:phone":"+1 214 678 0588",
    "sg:postcode":"75247",
    "sg:province":"TX",
    "sg:tags":[
        "cleaner",
        "disaster",
        "recovery",
        "damage",
        "rug",
        "water",
        "restoration",
        "relief",
        "carpet"
    ],
    "wof:name":"Griffin Restoration Inc",
    "wof:placetype":"venue"
},
  "geometry": {"coordinates":[-96.878378,32.803971],"type":"Point"}
}