{
  "type": "Feature",
  "properties": {
    "iso:country":"US",
    "sg:address":"3429 Hidalgo Dr",
    "sg:city":"Dallas",
    "sg:classifiers":[
        {
            "category":"Organizations",
            "subcategory":"Religious Organization",
            "type":"Services"
        }
    ],
    "sg:phone":"+1 214 350 8701",
    "sg:postcode":"75220",
    "sg:province":"TX",
    "sg:tags":[
        "church"
    ],
    "wof:name":"Jehovah Witnesses Nw Dallas",
    "wof:placetype":"venue"
},
  "geometry": {"coordinates":[-96.862588,32.870831],"type":"Point"}
}