{
  "type": "Feature",
  "properties": {
    "iso:country":"US",
    "sg:address":"514 W Veterans Memorial Blvd",
    "sg:city":"Harker Heights",
    "sg:classifiers":[
        {
            "category":"Autos & Motor Vehicles",
            "subcategory":"Automobile Sales",
            "type":"Retail Goods"
        }
    ],
    "sg:phone":"+1 254 699 9114",
    "sg:postcode":"76548",
    "sg:province":"TX",
    "sg:tags":[
        "car",
        "dealer"
    ],
    "wof:name":"Ideal Auto Repair & Machine",
    "wof:placetype":"venue"
},
  "geometry": {"coordinates":[-97.67064499999999,31.091498],"type":"Point"}
}