{
  "type": "Feature",
  "properties": {
    "iso:country":"US",
    "sg:address":"505 E Abram St",
    "sg:city":"Arlington",
    "sg:classifiers":[
        {
            "category":"Personal",
            "subcategory":"Beauty Salon",
            "type":"Services"
        }
    ],
    "sg:phone":"+1 817 261 7999",
    "sg:postcode":"76010",
    "sg:province":"TX",
    "sg:tags":[
        "shop"
    ],
    "wof:name":"Eden & Co",
    "wof:placetype":"venue"
},
  "geometry": {"coordinates":[-97.101702,32.735637],"type":"Point"}
}