{
  "type": "Feature",
  "properties": {
    "iso:country":"US",
    "sg:address":"10002 Zac Lentz Pkwy",
    "sg:city":"Victoria",
    "sg:classifiers":[
        {
            "category":"Retail",
            "subcategory":"Laundry & Dry Cleaning",
            "type":"Services"
        }
    ],
    "sg:phone":"+1 361 574 9880",
    "sg:postcode":"77904",
    "sg:province":"TX",
    "sg:tags":[
        "cleaners"
    ],
    "wof:name":"Klayville Cleaners and Laundry",
    "wof:placetype":"venue"
},
  "geometry": {"coordinates":[-97.02221299999999,28.859574],"type":"Point"}
}