{
  "type": "Feature",
  "properties": {
    "iso:country":"US",
    "sg:address":"3713 Westheimer Rd",
    "sg:city":"Houston",
    "sg:classifiers":[
        {
            "category":"Professional",
            "subcategory":"Detective & Security Services",
            "type":"Services"
        }
    ],
    "sg:phone":"+1 713 629 5854",
    "sg:postcode":"77027",
    "sg:province":"TX",
    "sg:tags":[
        "car"
    ],
    "wof:name":"Sutton Court Guardhouse",
    "wof:placetype":"venue"
},
  "geometry": {"coordinates":[-95.43818400000001,29.741619],"type":"Point"}
}