{
  "type": "Feature",
  "properties": {
    "iso:country":"US",
    "sg:address":"7696 FM 1101",
    "sg:city":"Seguin",
    "sg:classifiers":[
        {
            "category":"Wholesale",
            "subcategory":"Chemicals & Plastics",
            "type":"Manufacturing & Wholesale Goods"
        },
        {
            "category":"Manufacturing",
            "subcategory":"Chemicals & Compounds",
            "type":"Manufacturing & Wholesale Goods"
        }
    ],
    "sg:phone":"+1 830 606 7774",
    "sg:postcode":"78155",
    "sg:province":"TX",
    "sg:tags":[
        "explosive",
        "mfg"
    ],
    "wof:name":"Austin Powder Company",
    "wof:placetype":"venue"
},
  "geometry": {"coordinates":[-97.994811,29.746111],"type":"Point"}
}