{
  "type": "Feature",
  "properties": {
    "iso:country":"US",
    "sg:address":"500 Navasota St",
    "sg:city":"Austin",
    "sg:classifiers":[
        {
            "category":"Freight",
            "type":"Transportation"
        }
    ],
    "sg:phone":"+1 512 563 7004",
    "sg:postcode":"78702",
    "sg:province":"TX",
    "sg:tags":[
        "mover"
    ],
    "sg:website":"www.topstexas.com",
    "wof:name":"A-Austin Move & Modular Svc",
    "wof:placetype":"venue"
},
  "geometry": {"coordinates":[-97.72851799999999,30.263719],"type":"Point"}
}