{
  "type": "Feature",
  "properties": {
    "iso:country":"US",
    "sg:address":"127 N 7th St",
    "sg:city":"Waco",
    "sg:classifiers":[
        {
            "category":"Banks & Credit Unions",
            "subcategory":"Bank",
            "type":"Services"
        }
    ],
    "sg:phone":"+1 254 753 6441",
    "sg:postcode":"76701",
    "sg:province":"TX",
    "sg:tags":[
        "loan"
    ],
    "wof:name":"Capitol Finance Co",
    "wof:placetype":"venue"
},
  "geometry": {"coordinates":[-97.13424999999999,31.555905],"type":"Point"}
}