{
  "type": "Feature",
  "properties": {
    "iso:country":"US",
    "sg:address":"103 Sage Dr",
    "sg:city":"Justin",
    "sg:classifiers":[
        {
            "category":"Building & Trades",
            "subcategory":"Construction",
            "type":"Services"
        }
    ],
    "sg:phone":"+1 940 648 2288",
    "sg:postcode":"76247",
    "sg:province":"TX",
    "sg:tags":[
        "roofing",
        "industrial",
        "contractors-commercial",
        "contractor"
    ],
    "wof:name":"Frontier Roofing Inc",
    "wof:placetype":"venue"
},
  "geometry": {"coordinates":[-97.282748,33.086994],"type":"Point"}
}