{
  "type": "Feature",
  "properties": {
    "iso:country":"US",
    "sg:address":"905 Tulane St",
    "sg:city":"Lubbock",
    "sg:classifiers":[
        {
            "category":"Freight",
            "type":"Transportation"
        }
    ],
    "sg:phone":"+1 806 747 6161",
    "sg:postcode":"79403",
    "sg:province":"TX",
    "sg:tags":[
        "mover"
    ],
    "wof:name":"A-24 Hour Moving Svc",
    "wof:placetype":"venue"
},
  "geometry": {"coordinates":[-101.845715,33.620055],"type":"Point"}
}