{
  "type": "Feature",
  "properties": {
    "iso:country":"US",
    "sg:address":"19877 Old Hwy 105 W",
    "sg:city":"Montgomery",
    "sg:classifiers":[
        {
            "category":"Building & Trades",
            "subcategory":"Landscaping Services",
            "type":"Services"
        }
    ],
    "sg:phone":"+1 936 588 6702",
    "sg:postcode":"77356",
    "sg:province":"TX",
    "sg:tags":[
        "grass"
    ],
    "wof:name":"Jamies All American Grass",
    "wof:placetype":"venue"
},
  "geometry": {"coordinates":[-95.793469,30.345219],"type":"Point"}
}