{
  "type": "Feature",
  "properties": {
    "iso:country":"US",
    "sg:address":"6133 Walnut Dr",
    "sg:city":"Fort Worth",
    "sg:classifiers":[
        {
            "category":"Professional",
            "type":"Services"
        }
    ],
    "sg:phone":"+1 817 738 4383",
    "sg:postcode":"76114",
    "sg:province":"TX",
    "wof:name":"D Tech Service",
    "wof:placetype":"venue"
},
  "geometry": {"coordinates":[-97.414536,32.77018],"type":"Point"}
}