{
  "type": "Feature",
  "properties": {
    "iso:country":"US",
    "sg:address":"5310 S Lamar St",
    "sg:city":"Dallas",
    "sg:classifiers":[
        {
            "category":"Professional",
            "type":"Services"
        }
    ],
    "sg:phone":"+1 972 613 1604",
    "sg:postcode":"75215",
    "sg:province":"TX",
    "wof:name":"Little Dog Inc",
    "wof:placetype":"venue"
},
  "geometry": {"coordinates":[-96.75955399999999,32.743816],"type":"Point"}
}