{
  "type": "Feature",
  "properties": {
    "iso:country":"US",
    "sg:address":"1015 Hemphill St",
    "sg:city":"Houston",
    "sg:classifiers":[
        {
            "category":"Organizations",
            "subcategory":"Non-profit Organization",
            "type":"Services"
        }
    ],
    "sg:phone":"+1 713 869 3551",
    "sg:postcode":"77007",
    "sg:province":"TX",
    "sg:tags":[
        "service/non-profit",
        "community"
    ],
    "wof:name":"Salvation Army Truck Pick-Up Service",
    "wof:placetype":"venue"
},
  "geometry": {"coordinates":[-95.38069900000001,29.7684],"type":"Point"}
}