{
  "type": "Feature",
  "properties": {
    "iso:country":"US",
    "sg:address":"1212 S Main St",
    "sg:city":"Linden",
    "sg:classifiers":[
        {
            "category":"Social Services",
            "subcategory":"Job Training",
            "type":"Services"
        }
    ],
    "sg:phone":"+1 903 756 8489",
    "sg:postcode":"75563",
    "sg:province":"TX",
    "sg:tags":[
        "rehabilitation"
    ],
    "wof:name":"Texas Rehab Comm",
    "wof:placetype":"venue"
},
  "geometry": {"coordinates":[-94.363141,33.002131],"type":"Point"}
}