{
  "type": "Feature",
  "properties": {
    "iso:country":"US",
    "sg:address":"3501 Dime Cir",
    "sg:city":"Austin",
    "sg:classifiers":[
        {
            "category":"Insurance",
            "subcategory":"Insurance Agent",
            "type":"Services"
        }
    ],
    "sg:phone":"+1 512 386 9761",
    "sg:postcode":"78744",
    "sg:province":"TX",
    "wof:name":"Protection Casteel Auto Fire",
    "wof:placetype":"venue"
},
  "geometry": {"coordinates":[-97.71215599999999,30.20354],"type":"Point"}
}