{
  "type": "Feature",
  "properties": {
    "iso:country":"US",
    "sg:address":"50 Eton Green Cir",
    "sg:city":"San Antonio",
    "sg:classifiers":[
        {
            "category":"Professional",
            "type":"Services"
        }
    ],
    "sg:phone":"+1 210 698 5412",
    "sg:postcode":"78257",
    "sg:province":"TX",
    "sg:tags":[
        "establishment"
    ],
    "wof:name":"M & N Of Monterrey LTD",
    "wof:placetype":"venue"
},
  "geometry": {"coordinates":[-98.61214200000001,29.640571],"type":"Point"}
}