{
  "type": "Feature",
  "properties": {
    "iso:country":"US",
    "sg:address":"5622 Darnell St",
    "sg:city":"Houston",
    "sg:classifiers":[
        {
            "category":"Professional",
            "type":"Services"
        }
    ],
    "sg:phone":"+1 713 782 9300",
    "sg:postcode":"77096",
    "sg:province":"TX",
    "sg:tags":[
        "establishment"
    ],
    "sg:website":"www.mwginc.com",
    "wof:name":"Michael Wendy Group",
    "wof:placetype":"venue"
},
  "geometry": {"coordinates":[-95.48846399999999,29.687362],"type":"Point"}
}