{
  "type": "Feature",
  "properties": {
    "iso:country":"US",
    "sg:address":"200 Harris Ranch Rd",
    "sg:city":"Canyon Lake",
    "sg:classifiers":[
        {
            "category":"Retail",
            "subcategory":"Portrait Studio",
            "type":"Services"
        }
    ],
    "sg:phone":"+1 830 228 4846",
    "sg:postcode":"78133",
    "sg:province":"TX",
    "sg:tags":[
        "photographer"
    ],
    "wof:name":"Rebecca Creek Photography",
    "wof:placetype":"venue"
},
  "geometry": {"coordinates":[-98.36433,29.88527],"type":"Point"}
}