{
  "type": "Feature",
  "properties": {
    "iso:country":"US",
    "sg:address":"108 Althea Rd",
    "sg:city":"Rockwall",
    "sg:classifiers":[
        {
            "category":"Social Services",
            "subcategory":"Child Care",
            "type":"Services"
        }
    ],
    "sg:phone":"+1 972 771 5514",
    "sg:postcode":"75032",
    "sg:province":"TX",
    "wof:name":"Christy's Daycare Inc",
    "wof:placetype":"venue"
},
  "geometry": {"coordinates":[-96.459639,32.882744],"type":"Point"}
}