{
  "type": "Feature",
  "properties": {
    "iso:country":"US",
    "sg:address":"30435 Dobbin Hufsmith Rd",
    "sg:city":"Magnolia",
    "sg:classifiers":[
        {
            "category":"Retail",
            "subcategory":"Repair Shop",
            "type":"Services"
        }
    ],
    "sg:phone":"+1 281 252 9868",
    "sg:postcode":"77354",
    "sg:province":"TX",
    "wof:name":"Most Repair",
    "wof:placetype":"venue"
},
  "geometry": {"coordinates":[-95.636364,30.189237],"type":"Point"}
}