{
  "type": "Feature",
  "properties": {
    "iso:country":"US",
    "sg:address":"211 N Commerce St",
    "sg:city":"Mart",
    "sg:classifiers":[
        {
            "category":"Building & Trades",
            "subcategory":"Equipment Rental",
            "type":"Services"
        }
    ],
    "sg:phone":"+1 254 876 3394",
    "sg:postcode":"76664",
    "sg:province":"TX",
    "sg:tags":[
        "yard",
        "leasing",
        "store"
    ],
    "wof:name":"Dove Rental",
    "wof:placetype":"venue"
},
  "geometry": {"coordinates":[-96.835177,31.543073],"type":"Point"}
}