{
  "type": "Feature",
  "properties": {
    "iso:country":"US",
    "sg:address":"4128 Montana Ave",
    "sg:city":"El Paso",
    "sg:classifiers":[
        {
            "category":"Wholesale",
            "subcategory":"Plants",
            "type":"Manufacturing & Wholesale Goods"
        }
    ],
    "sg:phone":"+1 915 565 6227",
    "sg:postcode":"79903",
    "sg:province":"TX",
    "sg:tags":[
        "florist",
        "flower"
    ],
    "wof:name":"Flowerland Wholesale Flowers",
    "wof:placetype":"venue"
},
  "geometry": {"coordinates":[-106.44242300000001,31.78356],"type":"Point"}
}