{
  "type": "Feature",
  "properties": {
    "iso:country":"US",
    "sg:address":"414 Rorary Dr",
    "sg:city":"Richardson",
    "sg:classifiers":[
        {
            "category":"Banks & Credit Unions",
            "subcategory":"Investment Brokerage",
            "type":"Services"
        }
    ],
    "sg:phone":"+1 972 644 6679",
    "sg:postcode":"75081",
    "sg:province":"TX",
    "sg:tags":[
        "advisory",
        "financial"
    ],
    "wof:name":"Deutsche Financial Svc",
    "wof:placetype":"venue"
},
  "geometry": {"coordinates":[-96.72358699999999,32.952846],"type":"Point"}
}