{
  "type": "Feature",
  "properties": {
    "iso:country":"US",
    "sg:address":"3811 Polk Ave",
    "sg:city":"El Paso",
    "sg:classifiers":[
        {
            "category":"Shopping",
            "type":"Retail Goods"
        }
    ],
    "sg:phone":"+1 915 562 1679",
    "sg:postcode":"79930",
    "sg:province":"TX",
    "sg:tags":[
        "merchandise"
    ],
    "wof:name":"Norman R Wood",
    "wof:placetype":"venue"
},
  "geometry": {"coordinates":[-106.446316,31.815721],"type":"Point"}
}