{
  "type": "Feature",
  "properties": {
    "iso:country":"US",
    "sg:address":"122 Cyril Dr",
    "sg:city":"San Antonio",
    "sg:classifiers":[
        {
            "category":"Building & Trades",
            "subcategory":"Electrical",
            "type":"Services"
        }
    ],
    "sg:phone":"+1 210 599 7737",
    "sg:postcode":"78218",
    "sg:province":"TX",
    "sg:tags":[
        "electrical",
        "refrigeration",
        "contractor"
    ],
    "wof:name":"G H Seale Co",
    "wof:placetype":"venue"
},
  "geometry": {"coordinates":[-98.402895,29.504319],"type":"Point"}
}