{
  "type": "Feature",
  "properties": {
    "iso:country":"US",
    "sg:address":"2236 Mail Ave",
    "sg:city":"Dallas",
    "sg:classifiers":[
        {
            "category":"Manufacturing",
            "subcategory":"Signs",
            "type":"Manufacturing & Wholesale Goods"
        }
    ],
    "sg:phone":"+1 214 352 7789",
    "sg:postcode":"75235",
    "sg:province":"TX",
    "sg:tags":[
        "specialty",
        "mfg"
    ],
    "wof:name":"Dallas Signs & Neon",
    "wof:placetype":"venue"
},
  "geometry": {"coordinates":[-96.85373800000001,32.831836],"type":"Point"}
}