{
  "type": "Feature",
  "properties": {
    "iso:country":"US",
    "sg:address":"1101 W Pipeline Rd",
    "sg:city":"Hurst",
    "sg:classifiers":[
        {
            "category":"Health Services",
            "subcategory":"Clinic",
            "type":"Services"
        }
    ],
    "sg:phone":"+1 817 595 9198",
    "sg:postcode":"76053",
    "sg:province":"TX",
    "sg:tags":[
        "hospital",
        "specialty",
        "outpatient"
    ],
    "wof:name":"Control Diabetes Services Inc",
    "wof:placetype":"venue"
},
  "geometry": {"coordinates":[-97.19814700000001,32.823678],"type":"Point"}
}