{
  "type": "Feature",
  "properties": {
    "iso:country":"US",
    "sg:address":"7880 San Felipe St",
    "sg:city":"Houston",
    "sg:classifiers":[
        {
            "category":"Social Services",
            "type":"Services"
        }
    ],
    "sg:phone":"+1 713 780 2286",
    "sg:postcode":"77063",
    "sg:province":"TX",
    "wof:name":"Turboff Denise",
    "wof:placetype":"venue"
},
  "geometry": {"coordinates":[-95.50462899999999,29.750894],"type":"Point"}
}