{
  "type": "Feature",
  "properties": {
    "iso:country":"US",
    "sg:address":"1849 Lamar Ave",
    "sg:city":"Paris",
    "sg:classifiers":[
        {
            "category":"Professional",
            "subcategory":"Detective & Security Services",
            "type":"Services"
        }
    ],
    "sg:phone":"+1 903 785 4600",
    "sg:postcode":"75460",
    "sg:province":"TX",
    "sg:tags":[
        "car"
    ],
    "wof:name":"Lamar Security Service",
    "wof:placetype":"venue"
},
  "geometry": {"coordinates":[-95.53756799999999,33.661327],"type":"Point"}
}