{
  "type": "Feature",
  "properties": {
    "iso:country":"US",
    "sg:address":"10405 Orourke Ln",
    "sg:city":"Austin",
    "sg:classifiers":[
        {
            "category":"Professional",
            "subcategory":"Computer Services",
            "type":"Services"
        }
    ],
    "sg:phone":"+1 512 288 3985",
    "sg:postcode":"78739",
    "sg:province":"TX",
    "sg:tags":[
        "consultant",
        "designer"
    ],
    "wof:name":"Computer Consultants",
    "wof:placetype":"venue"
},
  "geometry": {"coordinates":[-97.88916,30.194578],"type":"Point"}
}