{
  "type": "Feature",
  "properties": {
    "iso:country":"US",
    "sg:address":"1642 Kelliwood Oaks Dr",
    "sg:city":"Katy",
    "sg:classifiers":[
        {
            "category":"Manufacturing",
            "subcategory":"Printing",
            "type":"Manufacturing & Wholesale Goods"
        }
    ],
    "sg:phone":"+1 281 398 5398",
    "sg:postcode":"77450",
    "sg:province":"TX",
    "sg:tags":[
        "newspaper"
    ],
    "wof:name":"Corporate News",
    "wof:placetype":"venue"
},
  "geometry": {"coordinates":[-95.717393,29.761712],"type":"Point"}
}