{
  "type": "Feature",
  "properties": {
    "iso:country":"US",
    "sg:address":"160 W Garza St",
    "sg:city":"Slaton",
    "sg:classifiers":[
        {
            "category":"Utilities",
            "subcategory":"Mobile Phone",
            "type":"Services"
        }
    ],
    "sg:phone":"+1 806 828 1990",
    "sg:postcode":"79364",
    "sg:province":"TX",
    "sg:tags":[
        "telephone",
        "cellular"
    ],
    "wof:name":"Cingular Wireless",
    "wof:placetype":"venue"
},
  "geometry": {"coordinates":[-101.643508,33.437942],"type":"Point"}
}