{
  "type": "Feature",
  "properties": {
    "iso:country":"US",
    "sg:address":"903 Garner Rd",
    "sg:city":"Houston",
    "sg:classifiers":[
        {
            "category":"Shopping",
            "subcategory":"Party Supplies",
            "type":"Retail Goods"
        }
    ],
    "sg:phone":"+1 713 740 9958",
    "sg:postcode":"77502",
    "sg:province":"TX",
    "wof:name":"Sanchez Mexico Store",
    "wof:placetype":"venue"
},
  "geometry": {"coordinates":[-95.201448,29.683669],"type":"Point"}
}