{
  "type": "Feature",
  "properties": {
    "iso:country":"US",
    "sg:address":"2860 Walnut Hill Ln",
    "sg:city":"Dallas",
    "sg:classifiers":[
        {
            "category":"Organizations",
            "subcategory":"Membership Organization",
            "type":"Services"
        }
    ],
    "sg:phone":"+1 214 357 6648",
    "sg:postcode":"75229",
    "sg:province":"TX",
    "sg:tags":[
        "support",
        "group"
    ],
    "sg:website":"http://www.alcoholics-anonymous.org",
    "wof:name":"Alcoholics Anonymous",
    "wof:placetype":"venue"
},
  "geometry": {"coordinates":[-96.882469,32.880945],"type":"Point"}
}