{
  "type": "Feature",
  "properties": {
    "iso:country":"US",
    "sg:address":"3602 Burke Rd",
    "sg:city":"Pasadena",
    "sg:classifiers":[
        {
            "category":"Building & Trades",
            "subcategory":"Cleaning & Sanitation",
            "type":"Services"
        },
        {
            "category":"Utilities",
            "subcategory":"Telephone",
            "type":"Services"
        }
    ],
    "sg:phone":"+1 713 944 7648",
    "sg:postcode":"77504",
    "sg:province":"TX",
    "sg:tags":[
        "phones-equipment",
        "pay",
        "carpet"
    ],
    "wof:name":"Extra Effort",
    "wof:placetype":"venue"
},
  "geometry": {"coordinates":[-95.18623599999999,29.655493],"type":"Point"}
}