{
  "type": "Feature",
  "properties": {
    "iso:country":"US",
    "sg:address":"2634 Gravel Dr",
    "sg:city":"Fort Worth",
    "sg:classifiers":[
        {
            "category":"Wholesale",
            "subcategory":"Auto Parts",
            "type":"Manufacturing & Wholesale Goods"
        }
    ],
    "sg:phone":"+1 817 589 2645",
    "sg:postcode":"76118",
    "sg:province":"TX",
    "sg:tags":[
        "automobile",
        "supply"
    ],
    "wof:name":"Friendly Car Wash Supply",
    "wof:placetype":"venue"
},
  "geometry": {"coordinates":[-97.21718,32.796978],"type":"Point"}
}