{
  "type": "Feature",
  "properties": {
    "iso:country":"US",
    "sg:address":"100 N Central Expy",
    "sg:city":"Richardson",
    "sg:classifiers":[
        {
            "category":"Real Estate",
            "subcategory":"Real Estate Agent",
            "type":"Services"
        }
    ],
    "sg:phone":"+1 972 231 6040",
    "sg:postcode":"75080",
    "sg:province":"TX",
    "wof:name":"Jack Walton Real Estate",
    "wof:placetype":"venue"
},
  "geometry": {"coordinates":[-96.734331,32.950429],"type":"Point"}
}