{
  "type": "Feature",
  "properties": {
    "iso:country":"US",
    "sg:address":"701 N Carroll Blvd",
    "sg:city":"Denton",
    "sg:classifiers":[
        {
            "category":"Banks & Credit Unions",
            "subcategory":"Investment Brokerage",
            "type":"Services"
        }
    ],
    "sg:phone":"+1 940 565 1819",
    "sg:postcode":"76201",
    "sg:province":"TX",
    "sg:tags":[
        "security"
    ],
    "sg:website":"www.agedwards.com",
    "wof:name":"A G Edwards & Sons Inc",
    "wof:placetype":"venue"
},
  "geometry": {"coordinates":[-97.13720000000001,33.22137],"type":"Point"}
}