{
  "type": "Feature",
  "properties": {
    "iso:country":"US",
    "sg:address":"2286 W Pleasant Run Rd",
    "sg:city":"Lancaster",
    "sg:classifiers":[
        {
            "category":"Organizations",
            "subcategory":"Religious Organization",
            "type":"Services"
        }
    ],
    "sg:phone":"+1 972 218 2224",
    "sg:postcode":"75146",
    "sg:province":"TX",
    "sg:tags":[
        "church"
    ],
    "wof:name":"Word Of Life",
    "wof:placetype":"venue"
},
  "geometry": {"coordinates":[-96.80416099999999,32.6042],"type":"Point"}
}