{
  "type": "Feature",
  "properties": {
    "iso:country":"US",
    "sg:address":"2211 N Beckley Ave",
    "sg:city":"Dallas",
    "sg:classifiers":[
        {
            "category":"Home & Garden",
            "subcategory":"Garden Supply",
            "type":"Retail Goods"
        }
    ],
    "sg:phone":"+1 214 752 5750",
    "sg:postcode":"75208",
    "sg:province":"TX",
    "sg:tags":[
        "nursery",
        "gardening"
    ],
    "wof:name":"Plantkeeper Inc",
    "wof:placetype":"venue"
},
  "geometry": {"coordinates":[-96.82289900000001,32.7705],"type":"Point"}
}