{
  "type": "Feature",
  "properties": {
    "iso:country":"US",
    "sg:address":"505 Old Hwy 87",
    "sg:city":"Orange",
    "sg:classifiers":[
        {
            "category":"Wholesale",
            "subcategory":"Metals & Minerals",
            "type":"Manufacturing & Wholesale Goods"
        }
    ],
    "sg:phone":"+1 409 883 7373",
    "sg:postcode":"77632",
    "sg:province":"TX",
    "sg:tags":[
        "center"
    ],
    "wof:name":"Steel Rack",
    "wof:placetype":"venue"
},
  "geometry": {"coordinates":[-93.75508000000001,30.242535],"type":"Point"}
}