{
  "type": "Feature",
  "properties": {
    "iso:country":"US",
    "sg:address":"8152 C F Hawn Fwy",
    "sg:city":"Dallas",
    "sg:classifiers":[
        {
            "category":"Autos & Motor Vehicles",
            "subcategory":"Motorcycle Sales",
            "type":"Retail Goods"
        }
    ],
    "sg:phone":"+1 214 398 6500",
    "sg:postcode":"75217",
    "sg:province":"TX",
    "wof:name":"Stovall's Cycle",
    "wof:placetype":"venue"
},
  "geometry": {"coordinates":[-96.679703,32.710201],"type":"Point"}
}