{
  "type": "Feature",
  "properties": {
    "iso:country":"US",
    "sg:address":"2619 Red Bluff Rd Ofc",
    "sg:city":"Pasadena",
    "sg:classifiers":[
        {
            "category":"Food & Beverages",
            "subcategory":"Groceries & Convenience Stores",
            "type":"Retail Goods"
        }
    ],
    "sg:phone":"+1 713 475 0925",
    "sg:postcode":"77506",
    "sg:province":"TX",
    "wof:name":"Kroger Food Stores",
    "wof:placetype":"venue"
},
  "geometry": {"coordinates":[-95.17559799999999,29.696199],"type":"Point"}
}