{
  "type": "Feature",
  "properties": {
    "iso:country":"US",
    "sg:address":"59 Ken Dr",
    "sg:city":"Sherman",
    "sg:classifiers":[
        {
            "category":"Wholesale",
            "subcategory":"Electrical",
            "type":"Manufacturing & Wholesale Goods"
        }
    ],
    "sg:phone":"+1 903 893 6178",
    "sg:postcode":"75092",
    "sg:province":"TX",
    "sg:tags":[
        "equipment",
        "industrial"
    ],
    "wof:name":"Kaman Industrial Tech Corp",
    "wof:placetype":"venue"
},
  "geometry": {"coordinates":[-96.660071,33.622142],"type":"Point"}
}