{
  "type": "Feature",
  "properties": {
    "iso:country":"US",
    "sg:address":"4321 Profit Dr",
    "sg:city":"San Antonio",
    "sg:classifiers":[
        {
            "category":"Manufacturing",
            "subcategory":"Petroleum Products",
            "type":"Manufacturing & Wholesale Goods"
        }
    ],
    "sg:phone":"+1 210 337 2720",
    "sg:postcode":"78219",
    "sg:province":"TX",
    "sg:tags":[
        "lubricating",
        "oil",
        "grease"
    ],
    "sg:website":"www.royalmfg.com",
    "wof:name":"Wright Oil Co",
    "wof:placetype":"venue"
},
  "geometry": {"coordinates":[-98.40976499999999,29.442844],"type":"Point"}
}