{
  "type": "Feature",
  "properties": {
    "iso:country":"US",
    "sg:address":"2921 Boca Chica Blvd",
    "sg:city":"Brownsville",
    "sg:classifiers":[
        {
            "category":"Shopping",
            "subcategory":"Clothing, Apparel, & Fashions",
            "type":"Retail Goods"
        }
    ],
    "sg:phone":"+1 956 544 7637",
    "sg:postcode":"78521",
    "sg:province":"TX",
    "wof:name":"Melrose",
    "wof:placetype":"venue"
},
  "geometry": {"coordinates":[-97.475199,25.921292],"type":"Point"}
}