{
  "type": "Feature",
  "properties": {
    "iso:country":"US",
    "sg:address":"4919 N Sam Houston Pkwy W Ste B",
    "sg:city":"Houston",
    "sg:classifiers":[
        {
            "category":"Food & Beverages",
            "subcategory":"Groceries & Convenience Stores",
            "type":"Retail Goods"
        }
    ],
    "sg:phone":"+1 281 580 5199",
    "sg:postcode":"77086",
    "sg:province":"TX",
    "wof:name":"Bmmel Express",
    "wof:placetype":"venue"
},
  "geometry": {"coordinates":[-95.504228,29.936693],"type":"Point"}
}