{
  "type": "Feature",
  "properties": {
    "iso:country":"US",
    "sg:address":"15000 Ashford St",
    "sg:city":"El Paso",
    "sg:classifiers":[
        {
            "category":"Building & Trades",
            "subcategory":"Landscaping Services",
            "type":"Services"
        }
    ],
    "sg:phone":"+1 915 852 6190",
    "sg:postcode":"79928",
    "sg:province":"TX",
    "wof:name":"Georgegood Lawn Maintenance",
    "wof:placetype":"venue"
},
  "geometry": {"coordinates":[-106.215523,31.686586],"type":"Point"}
}