{
  "type": "Feature",
  "properties": {
    "iso:country":"US",
    "sg:address":"2700 Turnersville Rd",
    "sg:city":"Buda",
    "sg:classifiers":[
        {
            "category":"Building & Trades",
            "subcategory":"Plumbing",
            "type":"Services"
        }
    ],
    "sg:phone":"+1 512 243 2889",
    "sg:postcode":"78610",
    "sg:province":"TX",
    "sg:tags":[
        "contractor"
    ],
    "wof:name":"Blazek Mechanical",
    "wof:placetype":"venue"
},
  "geometry": {"coordinates":[-97.7589,30.081763],"type":"Point"}
}