{
  "type": "Feature",
  "properties": {
    "iso:country":"US",
    "sg:address":"1522 Highland Rd",
    "sg:city":"Dallas",
    "sg:classifiers":[
        {
            "category":"Organizations",
            "subcategory":"Religious Organization",
            "type":"Services"
        }
    ],
    "sg:phone":"+1 214 328 3883",
    "sg:postcode":"75218",
    "sg:province":"TX",
    "wof:name":"Church of Good Smrtan Episcpal",
    "wof:placetype":"venue"
},
  "geometry": {"coordinates":[-96.722162,32.808737],"type":"Point"}
}