{
  "type": "Feature",
  "properties": {
    "iso:country":"US",
    "sg:address":"211 N Gulf Blvd",
    "sg:city":"Freeport",
    "sg:classifiers":[
        {
            "category":"Organizations",
            "subcategory":"Religious Organization",
            "type":"Services"
        }
    ],
    "sg:phone":"+1 979 230 9646",
    "sg:postcode":"77541",
    "sg:province":"TX",
    "wof:name":"Spanish Untd Pntecostal Church",
    "wof:placetype":"venue"
},
  "geometry": {"coordinates":[-95.36160599999999,28.963955],"type":"Point"}
}