{
  "type": "Feature",
  "properties": {
    "iso:country":"US",
    "sg:address":"7658 Blue Carriage Ct",
    "sg:city":"Fort Worth",
    "sg:classifiers":[
        {
            "category":"Shopping",
            "subcategory":"Gifts & Souvenirs",
            "type":"Retail Goods"
        }
    ],
    "sg:phone":"+1 817 496 0102",
    "sg:postcode":"76120",
    "sg:province":"TX",
    "wof:name":"Visions of One Crafts & Gifts",
    "wof:placetype":"venue"
},
  "geometry": {"coordinates":[-97.187872,32.763209],"type":"Point"}
}