{
  "type": "Feature",
  "properties": {
    "iso:country":"US",
    "sg:address":"800 E Expy 83",
    "sg:city":"Mcallen",
    "sg:classifiers":[
        {
            "category":"Shopping",
            "subcategory":"Computers & Home Electronics",
            "type":"Retail Goods"
        }
    ],
    "sg:phone":"+1 956 618 2241",
    "sg:postcode":"78503",
    "sg:province":"TX",
    "sg:tags":[
        "consumer",
        "household",
        "appliance"
    ],
    "wof:name":"Best Buy",
    "wof:placetype":"venue"
},
  "geometry": {"coordinates":[-98.21111399999999,26.190102],"type":"Point"}
}