{
  "type": "Feature",
  "properties": {
    "iso:country":"US",
    "sg:address":"4404 Richmond Ave",
    "sg:city":"Houston",
    "sg:classifiers":[
        {
            "category":"Shopping",
            "subcategory":"Clothing, Apparel, & Fashions",
            "type":"Retail Goods"
        }
    ],
    "sg:phone":"+1 713 621 1619",
    "sg:postcode":"77027",
    "sg:province":"TX",
    "sg:tags":[
        "tailor",
        "alterations-clothing"
    ],
    "wof:name":"Jarinee's Dressmaking & Alterations",
    "wof:placetype":"venue"
},
  "geometry": {"coordinates":[-95.44938500000001,29.732532],"type":"Point"}
}