{
  "type": "Feature",
  "properties": {
    "iso:country":"US",
    "sg:address":"850 N Bell Blvd",
    "sg:city":"Cedar Park",
    "sg:classifiers":[
        {
            "category":"Restaurant",
            "type":"Food & Drink"
        }
    ],
    "sg:phone":"+1 512 250 2253",
    "sg:postcode":"78613",
    "sg:province":"TX",
    "wof:name":"Quizno's Subs",
    "wof:placetype":"venue"
},
  "geometry": {"coordinates":[-97.82900600000001,30.519178],"type":"Point"}
}