{
  "type": "Feature",
  "properties": {
    "iso:country":"US",
    "sg:address":"801 W Corsicana St",
    "sg:city":"Athens",
    "sg:classifiers":[
        {
            "category":"Shopping",
            "subcategory":"Tobacco",
            "type":"Retail Goods"
        }
    ],
    "sg:phone":"+1 903 675 6710",
    "sg:postcode":"75751",
    "sg:province":"TX",
    "sg:tags":[
        "product"
    ],
    "wof:name":"Trinity Tobacco Co",
    "wof:placetype":"venue"
},
  "geometry": {"coordinates":[-95.873198,32.20293],"type":"Point"}
}