{
  "type": "Feature",
  "properties": {
    "iso:country":"US",
    "sg:address":"624 Seminole Trl",
    "sg:city":"Allen",
    "sg:classifiers":[
        {
            "category":"Professional",
            "subcategory":"Management & Consulting",
            "type":"Services"
        }
    ],
    "sg:phone":"+1 972 727 6401",
    "sg:postcode":"75002",
    "sg:province":"TX",
    "sg:tags":[
        "business"
    ],
    "wof:name":"M Thomas Consulting",
    "wof:placetype":"venue"
},
  "geometry": {"coordinates":[-96.63551,33.088552],"type":"Point"}
}