{
  "type": "Feature",
  "properties": {
    "iso:country":"US",
    "sg:address":"422 Sawdust Rd",
    "sg:city":"Spring",
    "sg:classifiers":[
        {
            "category":"Personal",
            "subcategory":"Beauty Salon",
            "type":"Services"
        }
    ],
    "sg:phone":"+1 281 298 6242",
    "sg:postcode":"77380",
    "sg:province":"TX",
    "sg:tags":[
        "nail",
        "manicuring",
        "finger"
    ],
    "wof:name":"N C Nails",
    "wof:placetype":"venue"
},
  "geometry": {"coordinates":[-95.44621600000001,30.126716],"type":"Point"}
}