{
  "type": "Feature",
  "properties": {
    "iso:country":"US",
    "sg:address":"3811 Cemetery Hill Rd",
    "sg:city":"Carrollton",
    "sg:classifiers":[
        {
            "category":"Shopping",
            "subcategory":"Music",
            "type":"Retail Goods"
        }
    ],
    "sg:phone":"+1 214 850 1237",
    "sg:postcode":"75007",
    "sg:province":"TX",
    "wof:name":"Orbit Records Management Inc",
    "wof:placetype":"venue"
},
  "geometry": {"coordinates":[-96.892392,33.014797],"type":"Point"}
}