{
  "type": "Feature",
  "properties": {
    "iso:country":"US",
    "sg:address":"719 N Main St",
    "sg:city":"Borger",
    "sg:classifiers":[
        {
            "category":"Coffee & Tea",
            "type":"Food & Drink"
        },
        {
            "category":"Restaurant",
            "type":"Food & Drink"
        }
    ],
    "sg:phone":"+1 806 274 5055",
    "sg:postcode":"79007",
    "sg:province":"TX",
    "sg:tags":[
        "shop",
        "espresso"
    ],
    "wof:name":"The Coffee Ranch",
    "wof:placetype":"venue"
},
  "geometry": {"coordinates":[-101.389893,35.672963],"type":"Point"}
}