{
  "type": "Feature",
  "properties": {
    "iso:country":"US",
    "sg:address":"2903 FM 1294",
    "sg:city":"Lubbock",
    "sg:classifiers":[
        {
            "category":"Autos & Motor Vehicles",
            "subcategory":"Automobile Sales",
            "type":"Retail Goods"
        }
    ],
    "sg:phone":"+1 806 746 9878",
    "sg:postcode":"79415",
    "sg:province":"TX",
    "sg:tags":[
        "car",
        "dealer"
    ],
    "wof:name":"T & T Used Auto Sales",
    "wof:placetype":"venue"
},
  "geometry": {"coordinates":[-101.877475,33.693594],"type":"Point"}
}