{
  "type": "Feature",
  "properties": {
    "iso:country":"US",
    "sg:address":"2201 Tucker St",
    "sg:city":"Dallas",
    "sg:classifiers":[
        {
            "category":"Home & Garden",
            "subcategory":"Building Materials",
            "type":"Retail Goods"
        }
    ],
    "sg:phone":"+1 214 321 8414",
    "sg:postcode":"75214",
    "sg:province":"TX",
    "sg:tags":[
        "glass",
        "window",
        "plate"
    ],
    "wof:name":"Gemini Glass Co",
    "wof:placetype":"venue"
},
  "geometry": {"coordinates":[-96.73187900000001,32.811464],"type":"Point"}
}