{
  "type": "Feature",
  "properties": {
    "iso:country":"US",
    "sg:address":"68 Maverick Dr",
    "sg:city":"Dale",
    "sg:classifiers":[
        {
            "category":"Building & Trades",
            "subcategory":"Construction",
            "type":"Services"
        }
    ],
    "sg:phone":"+1 512 373 0622",
    "sg:postcode":"78616",
    "sg:province":"TX",
    "sg:tags":[
        "wallcoverings-installation",
        "wallpaper",
        "painting",
        "contractor"
    ],
    "wof:name":"R S Painting",
    "wof:placetype":"venue"
},
  "geometry": {"coordinates":[-97.631074,29.995952],"type":"Point"}
}