{
  "type": "Feature",
  "properties": {
    "iso:country":"US",
    "sg:address":"815 E Main St",
    "sg:city":"Kilgore",
    "sg:classifiers":[
        {
            "category":"Place Of Worship",
            "subcategory":"Church",
            "type":"Public Place"
        },
        {
            "category":"Place Of Worship",
            "type":"Public Place"
        }
    ],
    "sg:phone":"+1 903 984 1502",
    "sg:postcode":"75662",
    "sg:province":"TX",
    "sg:tags":[
        "churches-presbyterian-arp",
        "churches-presbyterian"
    ],
    "sg:website":"http://www.fpcjackson.org",
    "wof:name":"First Presbyterian Church Of Kilgore Tx",
    "wof:placetype":"venue"
},
  "geometry": {"coordinates":[-94.871362,32.380932],"type":"Point"}
}