{
  "type": "Feature",
  "properties": {
    "iso:country":"US",
    "sg:address":"10603 Casnett Dr",
    "sg:city":"Dallas",
    "sg:classifiers":[
        {
            "category":"Home & Garden",
            "subcategory":"Furniture",
            "type":"Retail Goods"
        }
    ],
    "sg:phone":"+1 972 557 2073",
    "sg:postcode":"75217",
    "sg:province":"TX",
    "wof:name":"Cabinets & More",
    "wof:placetype":"venue"
},
  "geometry": {"coordinates":[-96.641378,32.715202],"type":"Point"}
}