{
  "type": "Feature",
  "properties": {
    "iso:country":"US",
    "sg:address":"837 Exposition Ave",
    "sg:city":"Dallas",
    "sg:classifiers":[
        {
            "category":"Cinema",
            "subcategory":"Movie Rental",
            "type":"Entertainment"
        }
    ],
    "sg:phone":"+1 214 823 6030",
    "sg:postcode":"75226",
    "sg:province":"TX",
    "sg:tags":[
        "leasing",
        "video",
        "disc",
        "tape"
    ],
    "wof:name":"Alternative Videos",
    "wof:placetype":"venue"
},
  "geometry": {"coordinates":[-96.76663499999999,32.782172],"type":"Point"}
}