{
  "type": "Feature",
  "properties": {
    "iso:country":"US",
    "sg:address":"382 Tailwind Dr",
    "sg:city":"Seguin",
    "sg:classifiers":[
        {
            "category":"Organizations",
            "subcategory":"Religious Organization",
            "type":"Services"
        }
    ],
    "sg:phone":"+1 830 379 1313",
    "sg:postcode":"78155",
    "sg:province":"TX",
    "wof:name":"Trinity Automotive LLC",
    "wof:placetype":"venue"
},
  "geometry": {"coordinates":[-97.99755,29.508117],"type":"Point"}
}