{
  "type": "Feature",
  "properties": {
    "iso:country":"US",
    "sg:address":"14222 Edinburgh Ct",
    "sg:city":"Houston",
    "sg:classifiers":[
        {
            "category":"Professional",
            "subcategory":"Management & Consulting",
            "type":"Services"
        }
    ],
    "sg:phone":"+1 281 870 9690",
    "sg:postcode":"77077",
    "sg:province":"TX",
    "sg:tags":[
        "business"
    ],
    "wof:name":"Mistral Consultants Inc",
    "wof:placetype":"venue"
},
  "geometry": {"coordinates":[-95.636644,29.757346],"type":"Point"}
}