{
  "type": "Feature",
  "properties": {
    "iso:country":"US",
    "sg:address":"22211 Buescher Rd",
    "sg:city":"Tomball",
    "sg:classifiers":[
        {
            "category":"Organizations",
            "subcategory":"Religious Organization",
            "type":"Services"
        }
    ],
    "sg:phone":"+1 281 351 7856",
    "sg:postcode":"77377",
    "sg:province":"TX",
    "wof:name":"Leap of Faith Enterprises",
    "wof:placetype":"venue"
},
  "geometry": {"coordinates":[-95.676602,30.083992],"type":"Point"}
}