{
  "type": "Feature",
  "properties": {
    "iso:country":"US",
    "sg:address":"3056 Mansfield Hwy",
    "sg:city":"Fort Worth",
    "sg:classifiers":[
        {
            "category":"Food & Beverages",
            "subcategory":"Groceries & Convenience Stores",
            "type":"Retail Goods"
        }
    ],
    "sg:phone":"+1 817 534 9000",
    "sg:postcode":"76119",
    "sg:province":"TX",
    "wof:name":"Noor Shans Texaco Food Mart",
    "wof:placetype":"venue"
},
  "geometry": {"coordinates":[-97.290121,32.68787],"type":"Point"}
}