{
  "type": "Feature",
  "properties": {
    "iso:country":"US",
    "sg:address":"3602 N Elm Rd",
    "sg:city":"Santa Fe",
    "sg:classifiers":[
        {
            "category":"Building & Trades",
            "subcategory":"Construction",
            "type":"Services"
        }
    ],
    "sg:phone":"+1 409 925 7278",
    "sg:postcode":"77517",
    "sg:province":"TX",
    "sg:tags":[
        "house"
    ],
    "wof:name":"Cochran Construction",
    "wof:placetype":"venue"
},
  "geometry": {"coordinates":[-95.12761399999999,29.390362],"type":"Point"}
}