{
  "type": "Feature",
  "properties": {
    "iso:country":"US",
    "sg:address":"1024 Delesandri Ln",
    "sg:city":"Kemah",
    "sg:classifiers":[
        {
            "category":"Wholesale",
            "subcategory":"Machinery & Supplies",
            "type":"Manufacturing & Wholesale Goods"
        }
    ],
    "sg:phone":"+1 281 535 0866",
    "sg:postcode":"77565",
    "sg:province":"TX",
    "sg:tags":[
        "industrial",
        "for",
        "material",
        "equipment",
        "handling",
        "representative",
        "manufacturer"
    ],
    "wof:name":"Tech Equipment Corporation",
    "wof:placetype":"venue"
},
  "geometry": {"coordinates":[-95.02758799999999,29.526343],"type":"Point"}
}