{
  "type": "Feature",
  "properties": {
    "iso:country":"US",
    "sg:address":"3711 Everton Dr",
    "sg:city":"Flower Mound",
    "sg:classifiers":[
        {
            "category":"Building & Trades",
            "subcategory":"Construction",
            "type":"Services"
        }
    ],
    "sg:phone":"+1 972 874 1596",
    "sg:postcode":"75022",
    "sg:province":"TX",
    "sg:tags":[
        "general",
        "contractor"
    ],
    "wof:name":"Lees Construction",
    "wof:placetype":"venue"
},
  "geometry": {"coordinates":[-97.086574,33.010592],"type":"Point"}
}