{
  "type": "Feature",
  "properties": {
    "iso:country":"US",
    "sg:address":"3509 E Park Blvd",
    "sg:city":"Plano",
    "sg:classifiers":[
        {
            "category":"Utilities",
            "subcategory":"Mobile Phone",
            "type":"Services"
        }
    ],
    "sg:phone":"+1 972 385 2401",
    "sg:postcode":"75074",
    "sg:province":"TX",
    "sg:tags":[
        "telecommunication"
    ],
    "wof:name":"Cyneta Networks Inc",
    "wof:placetype":"venue"
},
  "geometry": {"coordinates":[-96.665092,33.031091],"type":"Point"}
}