{
  "type": "Feature",
  "properties": {
    "iso:country":"US",
    "sg:address":"3908 Bellaire Blvd",
    "sg:city":"Houston",
    "sg:classifiers":[
        {
            "category":"Fast Food",
            "type":"Food & Drink"
        }
    ],
    "sg:phone":"+1 713 664 6919",
    "sg:postcode":"77025",
    "sg:province":"TX",
    "sg:website":"www.jackinthebox.com",
    "wof:name":"Jack In the Box",
    "wof:placetype":"venue"
},
  "geometry": {"coordinates":[-95.439548,29.706349],"type":"Point"}
}