{
  "type": "Feature",
  "properties": {
    "iso:country":"US",
    "sg:address":"307 Hazeltine Dr",
    "sg:city":"Lakeway",
    "sg:classifiers":[
        {
            "category":"Building & Trades",
            "subcategory":"Construction",
            "type":"Services"
        }
    ],
    "sg:phone":"+1 512 261 4726",
    "sg:postcode":"78734",
    "sg:province":"TX",
    "sg:tags":[
        "contractor"
    ],
    "wof:name":"Bryan Earl Bailey",
    "wof:placetype":"venue"
},
  "geometry": {"coordinates":[-97.964986,30.361074],"type":"Point"}
}