{
  "type": "Feature",
  "properties": {
    "iso:country":"US",
    "sg:address":"1 Rip Van Winkle Ln",
    "sg:city":"Houston",
    "sg:classifiers":[
        {
            "category":"Health Services",
            "subcategory":"Doctor",
            "type":"Services"
        }
    ],
    "sg:phone":"+1 713 464 2464",
    "sg:postcode":"77024",
    "sg:province":"TX",
    "wof:name":"Rosenthal Paul G MD",
    "wof:placetype":"venue"
},
  "geometry": {"coordinates":[-95.537989,29.767547],"type":"Point"}
}