{
  "type": "Feature",
  "properties": {
    "iso:country":"US",
    "sg:address":"1309 US Hwy 83",
    "sg:city":"Zapata",
    "sg:classifiers":[
        {
            "category":"Organizations",
            "subcategory":"Religious Organization",
            "type":"Services"
        }
    ],
    "sg:phone":"+1 956 765 9709",
    "sg:postcode":"78076",
    "sg:province":"TX",
    "sg:tags":[
        "church"
    ],
    "sg:website":"www.lds.org",
    "wof:name":"Church Of Jesus Christ Of Lds",
    "wof:placetype":"venue"
},
  "geometry": {"coordinates":[-99.272464,26.908251],"type":"Point"}
}