{
  "type": "Feature",
  "properties": {
    "iso:country":"US",
    "sg:address":"106 Siesta Cir",
    "sg:city":"Del Rio",
    "sg:classifiers":[
        {
            "category":"Restaurant",
            "type":"Food & Drink"
        }
    ],
    "sg:phone":"+1 830 775 9362",
    "sg:postcode":"78840",
    "sg:province":"TX",
    "sg:tags":[
        "eating"
    ],
    "wof:name":"Bangkok Cuisine",
    "wof:placetype":"venue"
},
  "geometry": {"coordinates":[-100.920908,29.392813],"type":"Point"}
}