{
  "type": "Feature",
  "properties": {
    "iso:country":"US",
    "sg:address":"3207 Storey Ln",
    "sg:city":"Dallas",
    "sg:classifiers":[
        {
            "category":"Building & Trades",
            "subcategory":"Cleaning & Sanitation",
            "type":"Services"
        }
    ],
    "sg:phone":"+1 214 956 9244",
    "sg:postcode":"75220",
    "sg:province":"TX",
    "sg:tags":[
        "maintenance"
    ],
    "wof:name":"Maintenance G Torres",
    "wof:placetype":"venue"
},
  "geometry": {"coordinates":[-96.87137800000001,32.864714],"type":"Point"}
}