{
  "type": "Feature",
  "properties": {
    "iso:country":"US",
    "sg:address":"411 E Walnut St",
    "sg:city":"Garland",
    "sg:classifiers":[
        {
            "category":"Retail",
            "subcategory":"Auto Repair",
            "type":"Services"
        }
    ],
    "sg:phone":"+1 972 276 3404",
    "sg:postcode":"75040",
    "sg:province":"TX",
    "wof:name":"Tops Auto Trim",
    "wof:placetype":"venue"
},
  "geometry": {"coordinates":[-96.626516,32.916049],"type":"Point"}
}