{
  "type": "Feature",
  "properties": {
    "iso:country":"US",
    "sg:address":"7124 Tanaqua Ln",
    "sg:city":"Austin",
    "sg:classifiers":[
        {
            "category":"Shopping",
            "subcategory":"Clothing, Apparel, & Fashions",
            "type":"Retail Goods"
        }
    ],
    "sg:phone":"+1 512 288 7107",
    "sg:postcode":"78739",
    "sg:province":"TX",
    "sg:tags":[
        "t-shirt"
    ],
    "wof:name":"Godfellas Inc",
    "wof:placetype":"venue"
},
  "geometry": {"coordinates":[-97.90110799999999,30.189422],"type":"Point"}
}