{
  "type": "Feature",
  "properties": {
    "iso:country":"US",
    "sg:address":"5110 W Broadway Ave",
    "sg:city":"Fort Worth",
    "sg:classifiers":[
        {
            "category":"Government",
            "subcategory":"Police Station",
            "type":"Public Place"
        }
    ],
    "sg:phone":"+1 817 222 7100",
    "sg:postcode":"76117",
    "sg:province":"TX",
    "sg:tags":[
        "department",
        "protection"
    ],
    "wof:name":"Haltom City Police Department",
    "wof:placetype":"venue"
},
  "geometry": {"coordinates":[-97.27212,32.809562],"type":"Point"}
}