{
  "type": "Feature",
  "properties": {
    "iso:country":"US",
    "sg:address":"908 Town and Country Blvd",
    "sg:city":"Houston",
    "sg:classifiers":[
        {
            "category":"Professional",
            "subcategory":"Employment Agencies",
            "type":"Services"
        }
    ],
    "sg:phone":"+1 713 984 7598",
    "sg:postcode":"77024",
    "sg:province":"TX",
    "sg:tags":[
        "opportunity",
        "help",
        "supply"
    ],
    "wof:name":"Majesty Hospitality Staffing",
    "wof:placetype":"venue"
},
  "geometry": {"coordinates":[-95.56076,29.78288],"type":"Point"}
}