{
  "type": "Feature",
  "properties": {
    "iso:country":"US",
    "sg:address":"1619 Chapman St",
    "sg:city":"Houston",
    "sg:classifiers":[
        {
            "category":"Food & Beverages",
            "subcategory":"Groceries & Convenience Stores",
            "type":"Retail Goods"
        }
    ],
    "sg:phone":"+1 713 224 6551",
    "sg:postcode":"77009",
    "sg:province":"TX",
    "wof:name":"Lam Food Market",
    "wof:placetype":"venue"
},
  "geometry": {"coordinates":[-95.353877,29.776332],"type":"Point"}
}