{
  "type": "Feature",
  "properties": {
    "iso:country":"US",
    "sg:address":"2106 Briarview Dr",
    "sg:city":"Houston",
    "sg:classifiers":[
        {
            "category":"Professional",
            "type":"Services"
        }
    ],
    "sg:phone":"+1 832 274 7831",
    "sg:postcode":"77077",
    "sg:province":"TX",
    "wof:name":"DESA Network Services LLC",
    "wof:placetype":"venue"
},
  "geometry": {"coordinates":[-95.642842,29.741704],"type":"Point"}
}