{
  "type": "Feature",
  "properties": {
    "iso:country":"US",
    "sg:address":"11021 Tumbleweed Dr",
    "sg:city":"Dallas",
    "sg:classifiers":[
        {
            "category":"Building & Trades",
            "subcategory":"Construction",
            "type":"Services"
        }
    ],
    "sg:phone":"+1 972 286 4188",
    "sg:postcode":"75217",
    "sg:province":"TX",
    "sg:tags":[
        "house"
    ],
    "wof:name":"Jims Remodeling",
    "wof:placetype":"venue"
},
  "geometry": {"coordinates":[-96.638087,32.69107],"type":"Point"}
}