{
  "type": "Feature",
  "properties": {
    "iso:country":"US",
    "sg:address":"712 Schilling St",
    "sg:city":"Baytown",
    "sg:classifiers":[
        {
            "category":"Organizations",
            "subcategory":"Religious Organization",
            "type":"Services"
        }
    ],
    "sg:phone":"+1 281 422 9333",
    "sg:postcode":"77520",
    "sg:province":"TX",
    "wof:name":"Lutheran Churches",
    "wof:placetype":"venue"
},
  "geometry": {"coordinates":[-94.975173,29.748988],"type":"Point"}
}