{
  "type": "Feature",
  "properties": {
    "iso:country":"US",
    "sg:address":"1209 E 7th St",
    "sg:city":"Sweeny",
    "sg:classifiers":[
        {
            "category":"Manufacturing",
            "subcategory":"Apparel",
            "type":"Manufacturing & Wholesale Goods"
        }
    ],
    "sg:phone":"+1 979 548 5570",
    "sg:postcode":"77480",
    "sg:province":"TX",
    "sg:tags":[
        "sewing",
        "contractor"
    ],
    "wof:name":"Hot Caps",
    "wof:placetype":"venue"
},
  "geometry": {"coordinates":[-95.693332,29.050937],"type":"Point"}
}