{
  "type": "Feature",
  "properties": {
    "iso:country":"US",
    "sg:address":"24740 Shady Oaks Blvd",
    "sg:city":"Montgomery",
    "sg:classifiers":[
        {
            "category":"Building & Trades",
            "subcategory":"Cleaning & Sanitation",
            "type":"Services"
        }
    ],
    "sg:phone":"+1 281 615 4969",
    "sg:postcode":"77316",
    "sg:province":"TX",
    "sg:tags":[
        "maintenance"
    ],
    "wof:name":"Elizas Cleaning Service",
    "wof:placetype":"venue"
},
  "geometry": {"coordinates":[-95.737587,30.275575],"type":"Point"}
}