{
  "type": "Feature",
  "properties": {
    "iso:country":"US",
    "sg:address":"1421 Sierra Dr",
    "sg:city":"Mesquite",
    "sg:classifiers":[
        {
            "category":"Home & Garden",
            "subcategory":"Building Materials",
            "type":"Retail Goods"
        }
    ],
    "sg:phone":"+1 972 289 1618",
    "sg:postcode":"75149",
    "sg:province":"TX",
    "wof:name":"All Star Stain",
    "wof:placetype":"venue"
},
  "geometry": {"coordinates":[-96.577877,32.752723],"type":"Point"}
}