{
  "type": "Feature",
  "properties": {
    "iso:country":"US",
    "sg:address":"2456 S Dairy Ashford St",
    "sg:city":"Houston",
    "sg:classifiers":[
        {
            "category":"Building & Trades",
            "subcategory":"Construction",
            "type":"Services"
        }
    ],
    "sg:phone":"+1 281 579 3800",
    "sg:postcode":"77077",
    "sg:province":"TX",
    "sg:tags":[
        "home",
        "builder"
    ],
    "wof:name":"Home Co",
    "wof:placetype":"venue"
},
  "geometry": {"coordinates":[-95.60596099999999,29.73793],"type":"Point"}
}