{
  "type": "Feature",
  "properties": {
    "iso:country":"US",
    "sg:address":"3302 Morris Ave",
    "sg:city":"Irving",
    "sg:classifiers":[
        {
            "category":"Building & Trades",
            "subcategory":"Construction",
            "type":"Services"
        }
    ],
    "sg:phone":"+1 972 790 1454",
    "sg:postcode":"75061",
    "sg:province":"TX",
    "sg:tags":[
        "contractor"
    ],
    "wof:name":"Perlas Tile Contractors",
    "wof:placetype":"venue"
},
  "geometry": {"coordinates":[-96.989037,32.826289],"type":"Point"}
}