{
  "type": "Feature",
  "properties": {
    "iso:country":"US",
    "sg:address":"3426 Westminister Ave",
    "sg:city":"Dallas",
    "sg:classifiers":[
        {
            "category":"Home & Garden",
            "subcategory":"Furniture",
            "type":"Retail Goods"
        }
    ],
    "sg:phone":"+1 214 692 6328",
    "sg:postcode":"75205",
    "sg:province":"TX",
    "wof:name":"Rosemary Nisis Designs",
    "wof:placetype":"venue"
},
  "geometry": {"coordinates":[-96.786901,32.850243],"type":"Point"}
}