{
  "type": "Feature",
  "properties": {
    "iso:country":"US",
    "sg:address":"3301 FM 1978",
    "sg:city":"San Marcos",
    "sg:classifiers":[
        {
            "category":"Shopping",
            "subcategory":"Used Merchandise",
            "type":"Retail Goods"
        }
    ],
    "sg:phone":"+1 512 353 3163",
    "sg:postcode":"78666",
    "sg:province":"TX",
    "wof:name":"Blue Swan Antq & Collectibles",
    "wof:placetype":"venue"
},
  "geometry": {"coordinates":[-97.92032500000001,29.804609],"type":"Point"}
}