{
  "type": "Feature",
  "properties": {
    "iso:country":"US",
    "sg:address":"1602 Shady Point Circle Dr",
    "sg:city":"San Angelo",
    "sg:classifiers":[
        {
            "category":"Retail",
            "subcategory":"Car Wash",
            "type":"Services"
        }
    ],
    "sg:phone":"+1 325 942 8112",
    "sg:postcode":"76904",
    "sg:province":"TX",
    "sg:tags":[
        "carwash"
    ],
    "wof:name":"Bobs Wash Service",
    "wof:placetype":"venue"
},
  "geometry": {"coordinates":[-100.48919600000001,31.386607],"type":"Point"}
}