{
  "type": "Feature",
  "properties": {
    "iso:country":"US",
    "sg:address":"2519 Winnequah St",
    "sg:city":"Dallas",
    "sg:classifiers":[
        {
            "category":"Wholesale",
            "subcategory":"Metals & Minerals",
            "type":"Manufacturing & Wholesale Goods"
        }
    ],
    "sg:phone":"+1 214 637 0843",
    "sg:postcode":"75212",
    "sg:province":"TX",
    "sg:tags":[
        "center",
        "nonferrous"
    ],
    "wof:name":"Douglas Lead Supply",
    "wof:placetype":"venue"
},
  "geometry": {"coordinates":[-96.919648,32.777616],"type":"Point"}
}