{
  "type": "Feature",
  "properties": {
    "iso:country":"US",
    "sg:address":"6929 Airport Blvd Ste 134",
    "sg:city":"Austin",
    "sg:classifiers":[
        {
            "category":"Shopping",
            "subcategory":"Clothing, Apparel, & Fashions",
            "type":"Retail Goods"
        },
        {
            "category":"Shopping",
            "subcategory":"Party Supplies",
            "type":"Retail Goods"
        },
        {
            "category":"Personal",
            "type":"Services"
        },
        {
            "category":"Shopping",
            "subcategory":"Bridal",
            "type":"Retail Goods"
        }
    ],
    "sg:phone":"+1 512 451 0179",
    "sg:postcode":"78752",
    "sg:province":"TX",
    "sg:tags":[
        "shop",
        "tailor",
        "tailoring",
        "sewing",
        "alteration",
        "alterations-clothing",
        "wedding"
    ],
    "sg:website":"www.neldastailors.com",
    "wof:name":"Nelda's Tailors",
    "wof:placetype":"venue"
},
  "geometry": {"coordinates":[-97.717915,30.335796],"type":"Point"}
}