{
  "type": "Feature",
  "properties": {
    "iso:country":"US",
    "sg:address":"412 S 1st St",
    "sg:city":"Lufkin",
    "sg:classifiers":[
        {
            "category":"Professional",
            "subcategory":"Lawyer & Legal Services",
            "type":"Services"
        }
    ],
    "sg:phone":"+1 936 637 6705",
    "sg:postcode":"75901",
    "sg:province":"TX",
    "sg:tags":[
        "attorney"
    ],
    "sg:website":"www.bsatroop121.com",
    "wof:name":"Weismuller Law Firm",
    "wof:placetype":"venue"
},
  "geometry": {"coordinates":[-94.73012900000001,31.336175],"type":"Point"}
}