{
  "type": "Feature",
  "properties": {
    "iso:country":"US",
    "sg:address":"12250 Gulf Fwy",
    "sg:city":"Houston",
    "sg:classifiers":[
        {
            "category":"Fast Food",
            "type":"Food & Drink"
        }
    ],
    "sg:phone":"+1 713 910 9464",
    "sg:postcode":"77034",
    "sg:province":"TX",
    "sg:tags":[
        "chicken",
        "wing"
    ],
    "wof:name":"Wings 'N More",
    "wof:placetype":"venue"
},
  "geometry": {"coordinates":[-95.223066,29.621798],"type":"Point"}
}