{
  "type": "Feature",
  "properties": {
    "iso:country":"US",
    "sg:address":"3611 Mineola Hwy",
    "sg:city":"Tyler",
    "sg:classifiers":[
        {
            "category":"Freight",
            "type":"Transportation"
        }
    ],
    "sg:phone":"+1 903 729 3101",
    "sg:postcode":"75702",
    "sg:province":"TX",
    "sg:tags":[
        "operator",
        "trucking"
    ],
    "wof:name":"Central Freight Lines Inc",
    "wof:placetype":"venue"
},
  "geometry": {"coordinates":[-95.332413,32.384938],"type":"Point"}
}