{
  "type": "Feature",
  "properties": {
    "iso:country":"US",
    "sg:address":"210 Hulett St",
    "sg:city":"Vidor",
    "sg:classifiers":[
        {
            "category":"Professional",
            "subcategory":"Accounting & Tax Preparation",
            "type":"Services"
        },
        {
            "category":"Insurance",
            "subcategory":"Insurance Agent",
            "type":"Services"
        }
    ],
    "sg:phone":"+1 409 786 4526",
    "sg:postcode":"77662",
    "sg:province":"TX",
    "sg:tags":[
        "processing"
    ],
    "wof:name":"Texas Star Medical Billing Inc",
    "wof:placetype":"venue"
},
  "geometry": {"coordinates":[-94.03496699999999,30.176131],"type":"Point"}
}