{
  "type": "Feature",
  "properties": {
    "iso:country":"US",
    "sg:address":"11516 11th St",
    "sg:city":"Santa Fe",
    "sg:classifiers":[
        {
            "category":"Building & Trades",
            "subcategory":"Construction",
            "type":"Services"
        }
    ],
    "sg:phone":"+1 409 925 2756",
    "sg:postcode":"77510",
    "sg:province":"TX",
    "sg:tags":[
        "house"
    ],
    "wof:name":"Bobs Handyman Repairs",
    "wof:placetype":"venue"
},
  "geometry": {"coordinates":[-95.07606199999999,29.375224],"type":"Point"}
}