{
  "type": "Feature",
  "properties": {
    "iso:country":"US",
    "sg:address":"11911 Barker Cypress Rd",
    "sg:city":"Cypress",
    "sg:classifiers":[
        {
            "category":"Food & Beverages",
            "subcategory":"Groceries & Convenience Stores",
            "type":"Retail Goods"
        }
    ],
    "sg:phone":"+1 281 304 0494",
    "sg:postcode":"77433",
    "sg:province":"TX",
    "wof:name":"C N S Enterprises",
    "wof:placetype":"venue"
},
  "geometry": {"coordinates":[-95.68068,29.938115],"type":"Point"}
}