{
  "type": "Feature",
  "properties": {
    "iso:country":"US",
    "sg:address":"307 Morgan Rd",
    "sg:city":"Mansfield",
    "sg:classifiers":[
        {
            "category":"Organizations",
            "subcategory":"Religious Organization",
            "type":"Services"
        }
    ],
    "sg:phone":"+1 817 453 9541",
    "sg:postcode":"76063",
    "sg:province":"TX",
    "sg:tags":[
        "church"
    ],
    "wof:name":"New Zion Missionary Bptst Chr",
    "wof:placetype":"venue"
},
  "geometry": {"coordinates":[-97.163157,32.560222],"type":"Point"}
}