{
  "type": "Feature",
  "properties": {
    "iso:country":"US",
    "sg:address":"9916 Bradford Grove Dr",
    "sg:city":"Frisco",
    "sg:classifiers":[
        {
            "category":"Government",
            "subcategory":"Office",
            "type":"Public Place"
        }
    ],
    "sg:phone":"+1 469 362 5556",
    "sg:postcode":"75035",
    "sg:province":"TX",
    "sg:tags":[
        "government-united",
        "state"
    ],
    "wof:name":"Global Housing Initiatives",
    "wof:placetype":"venue"
},
  "geometry": {"coordinates":[-96.792823,33.14837],"type":"Point"}
}