{
  "type": "Feature",
  "properties": {
    "iso:country":"US",
    "sg:address":"15445 Buckwheat St",
    "sg:city":"El Paso",
    "sg:classifiers":[
        {
            "category":"Freight",
            "type":"Transportation"
        }
    ],
    "sg:phone":"+1 915 921 1191",
    "sg:postcode":"79938",
    "sg:province":"TX",
    "wof:name":"Tiger Boy Moving Company",
    "wof:placetype":"venue"
},
  "geometry": {"coordinates":[-106.135166,31.873188],"type":"Point"}
}