{
  "type": "Feature",
  "properties": {
    "iso:country":"US",
    "sg:address":"300 State Highway 110 N",
    "sg:city":"Whitehouse",
    "sg:classifiers":[
        {
            "category":"Wholesale",
            "subcategory":"Hardware",
            "type":"Manufacturing & Wholesale Goods"
        },
        {
            "category":"Home & Garden",
            "subcategory":"Garden Supply",
            "type":"Retail Goods"
        },
        {
            "category":"Retail",
            "subcategory":"Repair Shop",
            "type":"Services"
        }
    ],
    "sg:phone":"+1 903 839 6606",
    "sg:postcode":"75791",
    "sg:province":"TX",
    "sg:tags":[
        "renting",
        "lawn",
        "outdoor",
        "power",
        "landscaping",
        "equipment-sales",
        "equipment",
        "saw"
    ],
    "sg:website":"http://www.stihldealer.net/default-dealer-040015.aspx",
    "wof:name":"Roquemore's Hardware, Inc.",
    "wof:placetype":"venue"
},
  "geometry": {"coordinates":[-95.22757,32.233135],"type":"Point"}
}