{
  "type": "Feature",
  "properties": {
    "iso:country":"US",
    "sg:address":"14954 Cadillac Dr",
    "sg:city":"San Antonio",
    "sg:classifiers":[
        {
            "category":"Professional",
            "subcategory":"Art Services",
            "type":"Services"
        }
    ],
    "sg:phone":"+1 210 764 1819",
    "sg:postcode":"78248",
    "sg:province":"TX",
    "sg:tags":[
        "photographer"
    ],
    "wof:name":"Photography By Simon",
    "wof:placetype":"venue"
},
  "geometry": {"coordinates":[-98.51751400000001,29.575233],"type":"Point"}
}