{
  "type": "Feature",
  "properties": {
    "iso:country":"US",
    "sg:address":"19 Elm Ln",
    "sg:city":"Bay City",
    "sg:classifiers":[
        {
            "category":"Retail",
            "subcategory":"Portrait Studio",
            "type":"Services"
        }
    ],
    "sg:phone":"+1 979 244 8803",
    "sg:postcode":"77414",
    "sg:province":"TX",
    "sg:tags":[
        "photo"
    ],
    "wof:name":"Curt Bean",
    "wof:placetype":"venue"
},
  "geometry": {"coordinates":[-95.65344,28.806948],"type":"Point"}
}