{
  "type": "Feature",
  "properties": {
    "iso:country":"US",
    "sg:address":"560 Copperhead Rd",
    "sg:city":"Mineral Wells",
    "sg:classifiers":[
        {
            "category":"Retail",
            "subcategory":"Repair Shop",
            "type":"Services"
        }
    ],
    "sg:phone":"+1 940 328 0410",
    "sg:postcode":"76067",
    "sg:province":"TX",
    "sg:tags":[
        "welding"
    ],
    "wof:name":"Rays Portable Welding",
    "wof:placetype":"venue"
},
  "geometry": {"coordinates":[-98.112674,32.906765],"type":"Point"}
}