{
  "type": "Feature",
  "properties": {
    "iso:country":"US",
    "sg:address":"5956 Sherry Ln",
    "sg:city":"Dallas",
    "sg:classifiers":[
        {
            "category":"Professional",
            "type":"Services"
        }
    ],
    "sg:phone":"+1 214 360 4700",
    "sg:postcode":"75225",
    "sg:province":"TX",
    "sg:tags":[
        "establishment"
    ],
    "wof:name":"Second Nature",
    "wof:placetype":"venue"
},
  "geometry": {"coordinates":[-96.810238,32.862216],"type":"Point"}
}