{
  "type": "Feature",
  "properties": {
    "iso:country":"US",
    "sg:address":"4214 Bluebonnet Dr",
    "sg:city":"Stafford",
    "sg:classifiers":[
        {
            "category":"Wholesale",
            "subcategory":"Machinery & Supplies",
            "type":"Manufacturing & Wholesale Goods"
        }
    ],
    "sg:phone":"+1 281 240 4120",
    "sg:postcode":"77477",
    "sg:province":"TX",
    "sg:tags":[
        "hardware",
        "industrial",
        "e"
    ],
    "wof:name":"Flowserve Corporation",
    "wof:placetype":"venue"
},
  "geometry": {"coordinates":[-95.575126,29.635884],"type":"Point"}
}