{
  "type": "Feature",
  "properties": {
    "iso:country":"US",
    "sg:address":"103 N Linda St",
    "sg:city":"Alton",
    "sg:classifiers":[
        {
            "category":"Restaurant",
            "type":"Food & Drink"
        }
    ],
    "sg:phone":"+1 956 584 0005",
    "sg:postcode":"78573",
    "sg:province":"TX",
    "wof:name":"El Farolito",
    "wof:placetype":"venue"
},
  "geometry": {"coordinates":[-98.286298,26.283346],"type":"Point"}
}