{
  "type": "Feature",
  "properties": {
    "iso:country":"US",
    "sg:address":"2730 Antero Dr",
    "sg:city":"Arlington",
    "sg:classifiers":[
        {
            "category":"Shopping",
            "subcategory":"Clothing, Apparel, & Fashions",
            "type":"Retail Goods"
        }
    ],
    "sg:phone":"+1 817 461 8718",
    "sg:postcode":"76006",
    "sg:province":"TX",
    "wof:name":"Granbury Square Clothing",
    "wof:placetype":"venue"
},
  "geometry": {"coordinates":[-97.103993,32.784747],"type":"Point"}
}