{
  "type": "Feature",
  "properties": {
    "iso:country":"US",
    "sg:address":"612 W Moore Ave",
    "sg:city":"Devine",
    "sg:classifiers":[
        {
            "category":"Organizations",
            "subcategory":"Community Association",
            "type":"Services"
        }
    ],
    "sg:phone":"+1 830 663 2113",
    "sg:postcode":"78016",
    "sg:province":"TX",
    "sg:tags":[
        "club"
    ],
    "wof:name":"Masonic Lodge",
    "wof:placetype":"venue"
},
  "geometry": {"coordinates":[-98.90933,29.14632],"type":"Point"}
}