{
  "type": "Feature",
  "properties": {
    "iso:country":"US",
    "sg:address":"111 5th Ave",
    "sg:city":"Nederland",
    "sg:classifiers":[
        {
            "category":"Home & Garden",
            "subcategory":"Household Appliances",
            "type":"Retail Goods"
        }
    ],
    "sg:phone":"+1 409 796 2878",
    "sg:postcode":"77627",
    "sg:province":"TX",
    "wof:name":"Golden A/C Appliance",
    "wof:placetype":"venue"
},
  "geometry": {"coordinates":[-94.02093000000001,29.995456],"type":"Point"}
}