{
  "type": "Feature",
  "properties": {
    "iso:country":"US",
    "sg:address":"6317 Bee Cave Rd",
    "sg:city":"Austin",
    "sg:classifiers":[
        {
            "category":"Winery",
            "type":"Food & Drink"
        },
        {
            "category":"Coffee & Tea",
            "type":"Food & Drink"
        }
    ],
    "sg:phone":"+1 512 732 0093",
    "sg:postcode":"78746",
    "sg:province":"TX",
    "sg:website":"www.lolasavannah.com",
    "wof:name":"Lola Savannah",
    "wof:placetype":"venue"
},
  "geometry": {"coordinates":[-97.832162,30.296033],"type":"Point"}
}