{
  "type": "Feature",
  "properties": {
    "iso:country":"US",
    "sg:address":"20770 S Hillcrest Dr",
    "sg:city":"Porter",
    "sg:classifiers":[
        {
            "category":"Autos & Motor Vehicles",
            "subcategory":"Automobile Sales",
            "type":"Retail Goods"
        }
    ],
    "sg:phone":"+1 281 354 0620",
    "sg:postcode":"77365",
    "sg:province":"TX",
    "sg:tags":[
        "trailer",
        "utility"
    ],
    "wof:name":"L & R Trailer",
    "wof:placetype":"venue"
},
  "geometry": {"coordinates":[-95.25671800000001,30.117667],"type":"Point"}
}