{
  "type": "Feature",
  "properties": {
    "iso:country":"US",
    "sg:address":"2716 Barton Creek Blvd",
    "sg:city":"Austin",
    "sg:classifiers":[
        {
            "category":"Building & Trades",
            "subcategory":"Construction",
            "type":"Services"
        }
    ],
    "sg:phone":"+1 512 330 0531",
    "sg:postcode":"78735",
    "sg:province":"TX",
    "sg:tags":[
        "nonresidential"
    ],
    "wof:name":"Thuringer Construction",
    "wof:placetype":"venue"
},
  "geometry": {"coordinates":[-97.873616,30.288191],"type":"Point"}
}