{
  "type": "Feature",
  "properties": {
    "iso:country":"US",
    "sg:address":"809 S Commerce St",
    "sg:city":"Harlingen",
    "sg:classifiers":[
        {
            "category":"Food & Beverages",
            "subcategory":"Groceries & Convenience Stores",
            "type":"Retail Goods"
        },
        {
            "category":"Food & Beverages",
            "subcategory":"Liquor & Beverages",
            "type":"Retail Goods"
        },
        {
            "category":"Wholesale",
            "subcategory":"Wine & Distilled Alcoholic Beverages",
            "type":"Manufacturing & Wholesale Goods"
        }
    ],
    "sg:phone":"+1 956 423 8019",
    "sg:postcode":"78550",
    "sg:province":"TX",
    "sg:tags":[
        "beer",
        "ale",
        "broker"
    ],
    "wof:name":"Holiday Wine & Liquor",
    "wof:placetype":"venue"
},
  "geometry": {"coordinates":[-97.69123500000001,26.185289],"type":"Point"}
}