{
  "type": "Feature",
  "properties": {
    "iso:country":"US",
    "sg:address":"400 Ranger St",
    "sg:city":"Hereford",
    "sg:classifiers":[
        {
            "category":"Social Services",
            "subcategory":"Child Care",
            "type":"Services"
        }
    ],
    "sg:phone":"+1 806 364 3972",
    "sg:postcode":"79045",
    "sg:province":"TX",
    "wof:name":"King's Manor Child Care",
    "wof:placetype":"venue"
},
  "geometry": {"coordinates":[-102.410117,34.833123],"type":"Point"}
}