{
  "type": "Feature",
  "properties": {
    "iso:country":"US",
    "sg:address":"302 N 2nd St",
    "sg:city":"Killeen",
    "sg:classifiers":[
        {
            "category":"Government",
            "subcategory":"Office",
            "type":"Public Place"
        }
    ],
    "sg:phone":"+1 254 526 8371",
    "sg:postcode":"76541",
    "sg:province":"TX",
    "sg:tags":[
        "county",
        "program",
        "health"
    ],
    "wof:name":"Bell County Health Dept",
    "wof:placetype":"venue"
},
  "geometry": {"coordinates":[-97.730152,31.120616],"type":"Point"}
}