{
  "type": "Feature",
  "properties": {
    "iso:country":"US",
    "sg:address":"2727 Montana Ave",
    "sg:city":"El Paso",
    "sg:classifiers":[
        {
            "category":"Professional",
            "subcategory":"Accounting & Tax Preparation",
            "type":"Services"
        }
    ],
    "sg:phone":"+1 915 562 2200",
    "sg:postcode":"79903",
    "sg:province":"TX",
    "sg:tags":[
        "accountant"
    ],
    "wof:name":"Jensen Cottrell & Co",
    "wof:placetype":"venue"
},
  "geometry": {"coordinates":[-106.46343899999999,31.782116],"type":"Point"}
}