{
  "type": "Feature",
  "properties": {
    "iso:country":"US",
    "sg:address":"1102 Rustic Knoll Dr",
    "sg:city":"Katy",
    "sg:classifiers":[
        {
            "category":"Banks & Credit Unions",
            "subcategory":"Financial Services",
            "type":"Services"
        }
    ],
    "sg:phone":"+1 281 579 7152",
    "sg:postcode":"77450",
    "sg:province":"TX",
    "sg:tags":[
        "investment",
        "closed"
    ],
    "wof:name":"Jarnaco Inc",
    "wof:placetype":"venue"
},
  "geometry": {"coordinates":[-95.730681,29.768157],"type":"Point"}
}