{
  "type": "Feature",
  "properties": {
    "iso:country":"US",
    "sg:address":"14917 Calaveras Dr",
    "sg:city":"Austin",
    "sg:classifiers":[
        {
            "category":"Wholesale",
            "subcategory":"Vending Machines",
            "type":"Manufacturing & Wholesale Goods"
        }
    ],
    "sg:phone":"+1 512 470 1248",
    "sg:postcode":"78717",
    "sg:province":"TX",
    "sg:tags":[
        "operator"
    ],
    "wof:name":"T & B Ventures Inc",
    "wof:placetype":"venue"
},
  "geometry": {"coordinates":[-97.76944399999999,30.491634],"type":"Point"}
}