{
  "type": "Feature",
  "properties": {
    "iso:country":"US",
    "sg:address":"304 Dancer Dr",
    "sg:city":"Longview",
    "sg:classifiers":[
        {
            "category":"Building & Trades",
            "subcategory":"Plumbing",
            "type":"Services"
        }
    ],
    "sg:phone":"+1 903 759 6759",
    "sg:postcode":"75604",
    "sg:province":"TX",
    "sg:tags":[
        "plumbing",
        "repair",
        "contractor"
    ],
    "wof:name":"Jan Clark Plumbing Co",
    "wof:placetype":"venue"
},
  "geometry": {"coordinates":[-94.794571,32.516846],"type":"Point"}
}