{
  "type": "Feature",
  "properties": {
    "iso:country":"US",
    "sg:address":"6020 Autumn Hills Dr",
    "sg:city":"Fort Worth",
    "sg:classifiers":[
        {
            "category":"Restaurant",
            "type":"Food & Drink"
        }
    ],
    "sg:phone":"+1 817 516 7328",
    "sg:postcode":"76140",
    "sg:province":"TX",
    "sg:tags":[
        "eating"
    ],
    "wof:name":"Ice Charles Etux Paula",
    "wof:placetype":"venue"
},
  "geometry": {"coordinates":[-97.25669000000001,32.591411],"type":"Point"}
}