{
  "type": "Feature",
  "properties": {
    "iso:country":"US",
    "sg:address":"2334 Stillwater Dr",
    "sg:city":"Mesquite",
    "sg:classifiers":[
        {
            "category":"Building & Trades",
            "subcategory":"Landscaping Services",
            "type":"Services"
        }
    ],
    "sg:phone":"+1 972 222 6666",
    "sg:postcode":"75181",
    "sg:province":"TX",
    "sg:tags":[
        "landscape"
    ],
    "wof:name":"Leath Hydromulch",
    "wof:placetype":"venue"
},
  "geometry": {"coordinates":[-96.546499,32.741541],"type":"Point"}
}