{
  "type": "Feature",
  "properties": {
    "iso:country":"US",
    "sg:address":"3820 Rotary St",
    "sg:city":"Laredo",
    "sg:phone":"+1 956 725 9940",
    "sg:postcode":"78043",
    "sg:province":"TX",
    "sg:tags":[
        "product",
        "oil",
        "petroleum"
    ],
    "wof:name":"Oil Patch Petroleum Inc",
    "wof:placetype":"venue"
},
  "geometry": {"coordinates":[-99.455185,27.497448],"type":"Point"}
}