{
  "type": "Feature",
  "properties": {
    "iso:country":"US",
    "sg:address":"1504 Paintbrush St",
    "sg:city":"Mesquite",
    "sg:classifiers":[
        {
            "category":"Personal",
            "subcategory":"Beauty Salon",
            "type":"Services"
        }
    ],
    "sg:phone":"+1 972 289 0550",
    "sg:postcode":"75149",
    "sg:province":"TX",
    "wof:name":"Braid By Nee Nee",
    "wof:placetype":"venue"
},
  "geometry": {"coordinates":[-96.578791,32.771353],"type":"Point"}
}