{
  "type": "Feature",
  "properties": {
    "iso:country":"US",
    "sg:address":"405 el Chico Trl",
    "sg:city":"Weatherford",
    "sg:classifiers":[
        {
            "category":"Shopping",
            "subcategory":"Gifts & Souvenirs",
            "type":"Retail Goods"
        }
    ],
    "sg:phone":"+1 817 441 6126",
    "sg:postcode":"76087",
    "sg:province":"TX",
    "wof:name":"A&A Enterprises",
    "wof:placetype":"venue"
},
  "geometry": {"coordinates":[-97.629903,32.744315],"type":"Point"}
}