{
  "type": "Feature",
  "properties": {
    "iso:country":"US",
    "sg:address":"2615 Tidewater Dr",
    "sg:city":"Houston",
    "sg:classifiers":[
        {
            "category":"Government",
            "subcategory":"Fire Station",
            "type":"Public Place"
        }
    ],
    "sg:phone":"+1 713 222 7643",
    "sg:postcode":"77045",
    "sg:province":"TX",
    "sg:tags":[
        "protection"
    ],
    "wof:name":"Fire Dept-Station 47",
    "wof:placetype":"venue"
},
  "geometry": {"coordinates":[-95.412623,29.631652],"type":"Point"}
}