{
  "type": "Feature",
  "properties": {
    "iso:country":"US",
    "sg:address":"753 Westwood Dr",
    "sg:city":"Marlin",
    "sg:classifiers":[
        {
            "category":"Home & Garden",
            "subcategory":"Furniture",
            "type":"Retail Goods"
        }
    ],
    "sg:phone":"+1 254 803 2100",
    "sg:postcode":"76661",
    "sg:province":"TX",
    "wof:name":"D Rockin Enterprises Inc",
    "wof:placetype":"venue"
},
  "geometry": {"coordinates":[-96.909065,31.310055],"type":"Point"}
}