{
  "type": "Feature",
  "properties": {
    "iso:country":"US",
    "sg:address":"12847 Burninglog Ln",
    "sg:city":"Dallas",
    "sg:classifiers":[
        {
            "category":"Communications",
            "type":"Services"
        }
    ],
    "sg:phone":"+1 972 690 1736",
    "sg:postcode":"75243",
    "sg:province":"TX",
    "sg:tags":[
        "pathologist",
        "speech-language"
    ],
    "wof:name":"Auditory Oral Action Committee Aoac",
    "wof:placetype":"venue"
},
  "geometry": {"coordinates":[-96.734622,32.918469],"type":"Point"}
}