{
  "type": "Feature",
  "properties": {
    "iso:country":"US",
    "sg:address":"1809 N Westmoreland Rd",
    "sg:city":"Desoto",
    "sg:classifiers":[
        {
            "category":"Organizations",
            "subcategory":"Religious Organization",
            "type":"Services"
        }
    ],
    "sg:phone":"+1 972 283 8900",
    "sg:postcode":"75115",
    "sg:province":"TX",
    "wof:name":"Missionary Revival Crusade",
    "wof:placetype":"venue"
},
  "geometry": {"coordinates":[-96.874422,32.623529],"type":"Point"}
}