{
  "type": "Feature",
  "properties": {
    "iso:country":"US",
    "sg:address":"1112 E Washington St",
    "sg:city":"Brownsville",
    "sg:classifiers":[
        {
            "category":"Shopping",
            "subcategory":"Jewelry",
            "type":"Retail Goods"
        }
    ],
    "sg:phone":"+1 956 544 5710",
    "sg:postcode":"78520",
    "sg:province":"TX",
    "sg:tags":[
        "merchandise"
    ],
    "wof:name":"Indian Palace",
    "wof:placetype":"venue"
},
  "geometry": {"coordinates":[-97.497552,25.901742],"type":"Point"}
}