{
  "type": "Feature",
  "properties": {
    "iso:country":"US",
    "sg:address":"900 N 8th St",
    "sg:city":"Temple",
    "sg:classifiers":[
        {
            "category":"Real Estate",
            "subcategory":"Real Estate Services",
            "type":"Services"
        },
        {
            "category":"Real Estate",
            "subcategory":"Real Estate Agent",
            "type":"Services"
        }
    ],
    "sg:phone":"+1 254 771 9997",
    "sg:postcode":"76501",
    "sg:province":"TX",
    "sg:tags":[
        "buyer",
        "broker"
    ],
    "wof:name":"La Raza Realty",
    "wof:placetype":"venue"
},
  "geometry": {"coordinates":[-97.334367,31.103447],"type":"Point"}
}