{
  "type": "Feature",
  "properties": {
    "iso:country":"US",
    "sg:address":"9951 Anderson Mill Rd",
    "sg:city":"Austin",
    "sg:classifiers":[
        {
            "category":"Professional",
            "subcategory":"Accounting & Tax Preparation",
            "type":"Services"
        }
    ],
    "sg:phone":"+1 512 250 0027",
    "sg:postcode":"78750",
    "sg:province":"TX",
    "sg:tags":[
        "accountant"
    ],
    "sg:website":"www.bargsley.com/",
    "wof:name":"Bargsley Andrews & Steinbach Cpa's Llp",
    "wof:placetype":"venue"
},
  "geometry": {"coordinates":[-97.798914,30.446554],"type":"Point"}
}