{
  "type": "Feature",
  "properties": {
    "iso:country":"US",
    "sg:address":"3801 S Congress Ave",
    "sg:city":"Austin",
    "sg:classifiers":[
        {
            "category":"Real Estate",
            "subcategory":"Real Estate Operator",
            "type":"Services"
        }
    ],
    "sg:phone":"+1 512 240 9110",
    "sg:postcode":"78704",
    "sg:province":"TX",
    "sg:tags":[
        "apartment"
    ],
    "wof:name":"SoCo Lofts",
    "wof:placetype":"venue"
},
  "geometry": {"coordinates":[-97.761904,30.226028],"type":"Point"}
}