{
  "type": "Feature",
  "properties": {
    "iso:country":"US",
    "sg:address":"7402 Shiner Ln",
    "sg:city":"Houston",
    "sg:classifiers":[
        {
            "category":"Food & Beverages",
            "subcategory":"Groceries & Convenience Stores",
            "type":"Retail Goods"
        }
    ],
    "sg:phone":"+1 281 561 9943",
    "sg:postcode":"77072",
    "sg:province":"TX",
    "wof:name":"Cantus Taqueria",
    "wof:placetype":"venue"
},
  "geometry": {"coordinates":[-95.58892299999999,29.698283],"type":"Point"}
}