{
  "type": "Feature",
  "properties": {
    "iso:country":"US",
    "sg:address":"1900 Timber Ridge Dr",
    "sg:city":"Frisco",
    "sg:classifiers":[
        {
            "category":"Education",
            "subcategory":"School",
            "type":"Public Place"
        }
    ],
    "sg:phone":"+1 469 633 3600",
    "sg:postcode":"75034",
    "sg:province":"TX",
    "wof:name":"Bledsoe Elementary School",
    "wof:placetype":"venue"
},
  "geometry": {"coordinates":[-96.8751,33.129321],"type":"Point"}
}