{
  "type": "Feature",
  "properties": {
    "iso:country":"US",
    "sg:address":"1811 Oak Tree Cir",
    "sg:city":"Pearland",
    "sg:classifiers":[
        {
            "category":"Health Services",
            "subcategory":"Nursing And Care Facility",
            "type":"Services"
        }
    ],
    "sg:phone":"+1 281 992 8176",
    "sg:postcode":"77581",
    "sg:province":"TX",
    "wof:name":"Oak Tree",
    "wof:placetype":"venue"
},
  "geometry": {"coordinates":[-95.248758,29.539237],"type":"Point"}
}