{
  "type": "Feature",
  "properties": {
    "iso:country":"US",
    "sg:address":"15700 John F Kennedy Blvd",
    "sg:city":"Houston",
    "sg:classifiers":[
        {
            "category":"Travel",
            "subcategory":"Hotels & Motels",
            "type":"Entertainment"
        },
        {
            "category":"Travel",
            "subcategory":"Resort",
            "type":"Entertainment"
        },
        {
            "category":"Sports & Exercise",
            "subcategory":"Ski Resort",
            "type":"Entertainment"
        }
    ],
    "sg:phone":"+1 281 442 5100",
    "sg:postcode":"77032",
    "sg:province":"TX",
    "sg:tags":[
        "corporate",
        "lodging"
    ],
    "sg:website":"http://clk.atdmt.com/NYC/go/156827385/direct/01/",
    "wof:name":"Sheraton North Houston at George Bush Intercontinental",
    "wof:placetype":"venue"
},
  "geometry": {"coordinates":[-95.331352,29.946299],"type":"Point"}
}