{
  "type": "Feature",
  "properties": {
    "iso:country":"US",
    "sg:address":"11022 Somerford Dr",
    "sg:city":"Houston",
    "sg:classifiers":[
        {
            "category":"Social Services",
            "subcategory":"Child Care",
            "type":"Services"
        }
    ],
    "sg:phone":"+1 281 561 8937",
    "sg:postcode":"77072",
    "sg:province":"TX",
    "wof:name":"Le Kip Thi Pham",
    "wof:placetype":"venue"
},
  "geometry": {"coordinates":[-95.575281,29.711014],"type":"Point"}
}