{
  "type": "Feature",
  "properties": {
    "iso:country":"US",
    "sg:address":"300 W Palestine Ave",
    "sg:city":"Palestine",
    "sg:classifiers":[
        {
            "category":"Autos & Motor Vehicles",
            "subcategory":"Automobile Sales",
            "type":"Retail Goods"
        }
    ],
    "sg:phone":"+1 903 731 9191",
    "sg:postcode":"75801",
    "sg:province":"TX",
    "sg:tags":[
        "car",
        "dealer"
    ],
    "wof:name":"A-1 Auto Sales",
    "wof:placetype":"venue"
},
  "geometry": {"coordinates":[-95.63534300000001,31.770611],"type":"Point"}
}