{
  "type": "Feature",
  "properties": {
    "iso:country":"US",
    "sg:address":"1948 9th Ave",
    "sg:city":"Port Arthur",
    "sg:classifiers":[
        {
            "category":"Shopping",
            "subcategory":"Pharmacy",
            "type":"Retail Goods"
        }
    ],
    "sg:phone":"+1 409 983 2481",
    "sg:postcode":"77642",
    "sg:province":"TX",
    "sg:tags":[
        "drug",
        "store"
    ],
    "wof:name":"Kings Pharmacy 4",
    "wof:placetype":"venue"
},
  "geometry": {"coordinates":[-93.92198399999999,29.909049],"type":"Point"}
}