{
  "type": "Feature",
  "properties": {
    "iso:country":"US",
    "sg:address":"3004 Pecan Cir",
    "sg:city":"Bedford",
    "sg:classifiers":[
        {
            "category":"Shopping",
            "subcategory":"Books",
            "type":"Retail Goods"
        },
        {
            "category":"Wholesale",
            "subcategory":"Books, Periodicals, & Newspapers",
            "type":"Manufacturing & Wholesale Goods"
        }
    ],
    "sg:phone":"+1 817 267 5554",
    "sg:postcode":"76021",
    "sg:province":"TX",
    "sg:tags":[
        "books-wholesale",
        "store",
        "manufacturer"
    ],
    "wof:name":"Gray Educational Marketing Inc",
    "wof:placetype":"venue"
},
  "geometry": {"coordinates":[-97.119848,32.861133],"type":"Point"}
}