{
  "type": "Feature",
  "properties": {
    "iso:country":"US",
    "sg:address":"3291 Independence Pkwy",
    "sg:city":"Plano",
    "sg:classifiers":[
        {
            "category":"Professional",
            "subcategory":"Business Services",
            "type":"Services"
        }
    ],
    "sg:phone":"+1 214 679 2836",
    "sg:postcode":"75075",
    "sg:province":"TX",
    "wof:name":"Chuan LI Enterprises Inc",
    "wof:placetype":"venue"
},
  "geometry": {"coordinates":[-96.753468,33.040115],"type":"Point"}
}