{
  "type": "Feature",
  "properties": {
    "iso:country":"US",
    "sg:address":"4433 Purdue Ave",
    "sg:city":"Dallas",
    "sg:classifiers":[
        {
            "category":"Organizations",
            "subcategory":"Community Association",
            "type":"Services"
        }
    ],
    "sg:phone":"+1 214 739 1855",
    "sg:postcode":"75225",
    "sg:province":"TX",
    "wof:name":"Texas Omicron Alumni Corp",
    "wof:placetype":"venue"
},
  "geometry": {"coordinates":[-96.810389,32.853952],"type":"Point"}
}