{
  "type": "Feature",
  "properties": {
    "iso:country":"US",
    "sg:address":"2956 Portales Dr",
    "sg:city":"Fort Worth",
    "sg:classifiers":[
        {
            "category":"Wholesale",
            "subcategory":"Computers",
            "type":"Manufacturing & Wholesale Goods"
        }
    ],
    "sg:phone":"+1 817 560 1281",
    "sg:postcode":"76116",
    "sg:province":"TX",
    "wof:name":"Tace Inc",
    "wof:placetype":"venue"
},
  "geometry": {"coordinates":[-97.470212,32.729601],"type":"Point"}
}