{
  "type": "Feature",
  "properties": {
    "iso:country":"US",
    "sg:address":"8115 Broussard Rd",
    "sg:city":"Beaumont",
    "sg:classifiers":[
        {
            "category":"Home & Garden",
            "subcategory":"Building Materials",
            "type":"Retail Goods"
        }
    ],
    "sg:phone":"+1 409 924 7214",
    "sg:postcode":"77713",
    "sg:province":"TX",
    "wof:name":"Gulf Coast Wallpaper Serv",
    "wof:placetype":"venue"
},
  "geometry": {"coordinates":[-94.205905,30.1749],"type":"Point"}
}