{
  "type": "Feature",
  "properties": {
    "iso:country":"US",
    "sg:address":"319 N Hwy 69",
    "sg:city":"Whitewright",
    "sg:classifiers":[
        {
            "category":"Health Services",
            "subcategory":"Doctor",
            "type":"Services"
        }
    ],
    "sg:phone":"+1 903 364 2022",
    "sg:postcode":"75491",
    "sg:province":"TX",
    "sg:tags":[
        "physician",
        "surgeon"
    ],
    "wof:name":"Whitewright Family Practice",
    "wof:placetype":"venue"
},
  "geometry": {"coordinates":[-96.40243100000001,33.5172],"type":"Point"}
}