{
  "type": "Feature",
  "properties": {
    "iso:country":"US",
    "sg:address":"4415 71st St",
    "sg:city":"Lubbock",
    "sg:classifiers":[
        {
            "category":"Insurance",
            "subcategory":"Hazard Insurance",
            "type":"Services"
        }
    ],
    "sg:phone":"+1 806 792 6015",
    "sg:postcode":"79424",
    "sg:province":"TX",
    "sg:tags":[
        "carrier"
    ],
    "wof:name":"Sentry Insurance",
    "wof:placetype":"venue"
},
  "geometry": {"coordinates":[-101.90698500000001,33.528804],"type":"Point"}
}