{
  "type": "Feature",
  "properties": {
    "iso:country":"US",
    "sg:address":"510 E Oak St",
    "sg:city":"Weatherford",
    "sg:classifiers":[
        {
            "category":"Building & Trades",
            "subcategory":"Plumbing",
            "type":"Services"
        }
    ],
    "sg:phone":"+1 817 596 4810",
    "sg:postcode":"76086",
    "sg:province":"TX",
    "sg:tags":[
        "contractor"
    ],
    "wof:name":"Comfort Experts Inc",
    "wof:placetype":"venue"
},
  "geometry": {"coordinates":[-97.789101,32.757317],"type":"Point"}
}