{
  "type": "Feature",
  "properties": {
    "iso:country":"US",
    "sg:address":"3525 Deep Valley Trl",
    "sg:city":"Plano",
    "sg:classifiers":[
        {
            "category":"Health Services",
            "subcategory":"Clinic",
            "type":"Services"
        }
    ],
    "sg:phone":"+1 972 964 9563",
    "sg:postcode":"75023",
    "sg:province":"TX",
    "wof:name":"North Texas Dynamic Health Svc",
    "wof:placetype":"venue"
},
  "geometry": {"coordinates":[-96.749162,33.045759],"type":"Point"}
}