{
  "type": "Feature",
  "properties": {
    "iso:country":"US",
    "sg:address":"809 Applewood Rd",
    "sg:city":"Canutillo",
    "sg:classifiers":[
        {
            "category":"Professional",
            "subcategory":"Management & Consulting",
            "type":"Services"
        }
    ],
    "sg:phone":"+1 915 886 4604",
    "sg:postcode":"79835",
    "sg:province":"TX",
    "sg:tags":[
        "retail",
        "direct",
        "sales"
    ],
    "wof:name":"Gerardo Gonzalez",
    "wof:placetype":"venue"
},
  "geometry": {"coordinates":[-106.577084,31.963645],"type":"Point"}
}