{
  "type": "Feature",
  "properties": {
    "iso:country":"US",
    "sg:address":"123 Lecompte Pl",
    "sg:city":"San Antonio",
    "sg:classifiers":[
        {
            "category":"Autos & Motor Vehicles",
            "subcategory":"Recreational Vehicle Sales",
            "type":"Retail Goods"
        }
    ],
    "sg:phone":"+1 210 534 6006",
    "sg:postcode":"78214",
    "sg:province":"TX",
    "wof:name":"Discount Campers",
    "wof:placetype":"venue"
},
  "geometry": {"coordinates":[-98.499982,29.380381],"type":"Point"}
}