{
  "type": "Feature",
  "properties": {
    "iso:country":"US",
    "sg:address":"37125 FM 1774",
    "sg:city":"Magnolia",
    "sg:classifiers":[
        {
            "category":"Bars & Pubs",
            "type":"Food & Drink"
        }
    ],
    "sg:phone":"+1 281 259 1055",
    "sg:postcode":"77355",
    "sg:province":"TX",
    "wof:name":"El Gran Tago",
    "wof:placetype":"venue"
},
  "geometry": {"coordinates":[-95.707066,30.184759],"type":"Point"}
}