{
  "type": "Feature",
  "properties": {
    "iso:country":"US",
    "sg:address":"5105 Bennett Lawson Rd",
    "sg:city":"Mansfield",
    "sg:classifiers":[
        {
            "category":"Shopping",
            "subcategory":"Stationery & Office Supplies",
            "type":"Retail Goods"
        }
    ],
    "sg:phone":"+1 817 478 5582",
    "sg:postcode":"76063",
    "sg:province":"TX",
    "sg:tags":[
        "store"
    ],
    "wof:name":"Pervenche Paperie",
    "wof:placetype":"venue"
},
  "geometry": {"coordinates":[-97.21536399999999,32.603059],"type":"Point"}
}