{
  "type": "Feature",
  "properties": {
    "iso:country":"US",
    "sg:address":"6601 FM 2738",
    "sg:city":"Burleson",
    "sg:classifiers":[
        {
            "category":"Professional",
            "subcategory":"Management & Consulting",
            "type":"Services"
        }
    ],
    "sg:phone":"+1 817 477 1437",
    "sg:postcode":"76028",
    "sg:province":"TX",
    "sg:tags":[
        "party",
        "planning"
    ],
    "wof:name":"All Star Equestrian Foundation",
    "wof:placetype":"venue"
},
  "geometry": {"coordinates":[-97.199665,32.525945],"type":"Point"}
}