{
  "type": "Feature",
  "properties": {
    "iso:country":"US",
    "sg:address":"2968 Park Hill Dr",
    "sg:city":"Fort Worth",
    "sg:classifiers":[
        {
            "category":"Personal",
            "subcategory":"Beauty Salon",
            "type":"Services"
        }
    ],
    "sg:phone":"+1 817 921 0996",
    "sg:postcode":"76109",
    "sg:province":"TX",
    "sg:tags":[
        "shop"
    ],
    "wof:name":"Park Hill Hair Designs",
    "wof:placetype":"venue"
},
  "geometry": {"coordinates":[-97.35914699999999,32.71611],"type":"Point"}
}