{
  "type": "Feature",
  "properties": {
    "iso:country":"US",
    "sg:address":"14715 Lepus Dr",
    "sg:city":"Willis",
    "sg:classifiers":[
        {
            "category":"Building & Trades",
            "subcategory":"Construction",
            "type":"Services"
        }
    ],
    "sg:phone":"+1 936 228 5100",
    "sg:postcode":"77318",
    "sg:province":"TX",
    "sg:tags":[
        "concrete",
        "contractor"
    ],
    "wof:name":"B & B Concrete Construction",
    "wof:placetype":"venue"
},
  "geometry": {"coordinates":[-95.58057700000001,30.424627],"type":"Point"}
}