{
  "type": "Feature",
  "properties": {
    "iso:country":"US",
    "sg:address":"6300 Ridglea Pl",
    "sg:city":"Fort Worth",
    "sg:classifiers":[
        {
            "category":"Professional",
            "subcategory":"Management & Consulting",
            "type":"Services"
        }
    ],
    "sg:phone":"+1 817 731 8730",
    "sg:postcode":"76116",
    "sg:province":"TX",
    "sg:tags":[
        "consultant",
        "business"
    ],
    "wof:name":"Entrepreneur's Source",
    "wof:placetype":"venue"
},
  "geometry": {"coordinates":[-97.41809499999999,32.724086],"type":"Point"}
}