{
  "type": "Feature",
  "properties": {
    "iso:country":"US",
    "sg:address":"5728 89th St",
    "sg:city":"Lubbock",
    "sg:classifiers":[
        {
            "category":"Wholesale",
            "subcategory":"Durable Goods & Equipment",
            "type":"Manufacturing & Wholesale Goods"
        }
    ],
    "sg:phone":"+1 806 698 8162",
    "sg:postcode":"79424",
    "sg:province":"TX",
    "wof:name":"Altex Supply Co",
    "wof:placetype":"venue"
},
  "geometry": {"coordinates":[-101.93840400000001,33.51242],"type":"Point"}
}