{
  "type": "Feature",
  "properties": {
    "iso:country":"US",
    "sg:address":"1301 W Grand Ave",
    "sg:city":"Marshall",
    "sg:classifiers":[
        {
            "category":"Retail",
            "subcategory":"Funeral Services",
            "type":"Services"
        }
    ],
    "sg:phone":"+1 903 935 3513",
    "sg:postcode":"75670",
    "sg:province":"TX",
    "sg:tags":[
        "director"
    ],
    "wof:name":"Peoples Funeral Home Inc",
    "wof:placetype":"venue"
},
  "geometry": {"coordinates":[-94.37997300000001,32.548384],"type":"Point"}
}