{
  "type": "Feature",
  "properties": {
    "iso:country":"US",
    "sg:address":"1115 Caplin St",
    "sg:city":"Houston",
    "sg:classifiers":[
        {
            "category":"Banks & Credit Unions",
            "subcategory":"Investment Brokerage",
            "type":"Services"
        },
        {
            "category":"Real Estate",
            "subcategory":"Developer",
            "type":"Services"
        }
    ],
    "sg:phone":"+1 281 416 6401",
    "sg:postcode":"77022",
    "sg:province":"TX",
    "sg:tags":[
        "investing"
    ],
    "wof:name":"Digital Media Group",
    "wof:placetype":"venue"
},
  "geometry": {"coordinates":[-95.357304,29.81567],"type":"Point"}
}