{
  "type": "Feature",
  "properties": {
    "iso:country":"US",
    "sg:address":"2906 Peppertree Pl",
    "sg:city":"Plano",
    "sg:classifiers":[
        {
            "category":"Building & Trades",
            "subcategory":"Cleaning & Sanitation",
            "type":"Services"
        }
    ],
    "sg:phone":"+1 972 578 7943",
    "sg:postcode":"75074",
    "sg:province":"TX",
    "sg:tags":[
        "ventilating",
        "system"
    ],
    "wof:name":"APC Svc",
    "wof:placetype":"venue"
},
  "geometry": {"coordinates":[-96.67091000000001,33.03358],"type":"Point"}
}