{
  "type": "Feature",
  "properties": {
    "iso:country":"US",
    "sg:address":"9 Meta Dr",
    "sg:city":"Midland",
    "sg:classifiers":[
        {
            "category":"Shopping",
            "subcategory":"Crafts & Fabrics",
            "type":"Retail Goods"
        }
    ],
    "sg:phone":"+1 432 682 3154",
    "sg:postcode":"79701",
    "sg:province":"TX",
    "sg:tags":[
        "shop"
    ],
    "wof:name":"Lundy Look",
    "wof:placetype":"venue"
},
  "geometry": {"coordinates":[-102.10081599999999,31.994016],"type":"Point"}
}