{
  "type": "Feature",
  "properties": {
    "iso:country":"US",
    "sg:address":"1213 W 5th St",
    "sg:city":"Austin",
    "sg:classifiers":[
        {
            "category":"Home & Garden",
            "subcategory":"Building Materials",
            "type":"Retail Goods"
        }
    ],
    "sg:phone":"+1 512 477 1377",
    "sg:postcode":"78703",
    "sg:province":"TX",
    "wof:name":"Zollo Studio",
    "wof:placetype":"venue"
},
  "geometry": {"coordinates":[-97.759162,30.271937],"type":"Point"}
}