{
  "type": "Feature",
  "properties": {
    "iso:country":"US",
    "sg:address":"16703 Worgan Ct",
    "sg:city":"Spring",
    "sg:classifiers":[
        {
            "category":"Professional",
            "subcategory":"Computer Services",
            "type":"Services"
        }
    ],
    "sg:phone":"+1 713 226 2333",
    "sg:postcode":"77379",
    "sg:province":"TX",
    "sg:tags":[
        "home",
        "consulting",
        "page",
        "dev",
        "internet"
    ],
    "wof:name":"Musical Candles",
    "wof:placetype":"venue"
},
  "geometry": {"coordinates":[-95.509564,30.02667],"type":"Point"}
}