{
  "type": "Feature",
  "properties": {
    "iso:country":"US",
    "sg:address":"122 Gillette Blvd",
    "sg:city":"San Antonio",
    "sg:classifiers":[
        {
            "category":"Retail",
            "subcategory":"Repair Shop",
            "type":"Services"
        }
    ],
    "sg:phone":"+1 210 932 2065",
    "sg:postcode":"78221",
    "sg:province":"TX",
    "wof:name":"McM TV Repair",
    "wof:placetype":"venue"
},
  "geometry": {"coordinates":[-98.507009,29.330182],"type":"Point"}
}