{
  "type": "Feature",
  "properties": {
    "iso:country":"US",
    "sg:address":"3017 Federal Ave",
    "sg:city":"El Paso",
    "sg:classifiers":[
        {
            "category":"Manufacturing",
            "subcategory":"Retail Goods",
            "type":"Manufacturing & Wholesale Goods"
        }
    ],
    "sg:phone":"+1 915 566 8093",
    "sg:postcode":"79930",
    "sg:province":"TX",
    "sg:tags":[
        "textile",
        "screen",
        "printing"
    ],
    "wof:name":"Fc Smith Screen Printing",
    "wof:placetype":"venue"
},
  "geometry": {"coordinates":[-106.458665,31.791339],"type":"Point"}
}