{
  "type": "Feature",
  "properties": {
    "iso:country":"US",
    "sg:address":"245 Commerce Green Blvd",
    "sg:city":"Sugar Land",
    "sg:classifiers":[
        {
            "category":"Banks & Credit Unions",
            "subcategory":"Investment Brokerage",
            "type":"Services"
        },
        {
            "category":"Banks & Credit Unions",
            "subcategory":"Bank",
            "type":"Services"
        }
    ],
    "sg:phone":"+1 281 980 1968",
    "sg:postcode":"77478",
    "sg:province":"TX",
    "sg:tags":[
        "loan",
        "mortgage",
        "real estate"
    ],
    "sg:website":"www.accesslending.com",
    "wof:name":"Access Lending Corporation",
    "wof:placetype":"venue"
},
  "geometry": {"coordinates":[-95.609177,29.623451],"type":"Point"}
}