{
  "type": "Feature",
  "properties": {
    "iso:country":"US",
    "sg:address":"1812 N Haskell Ave",
    "sg:city":"Dallas",
    "sg:classifiers":[
        {
            "category":"Manufacturing",
            "subcategory":"Printing",
            "type":"Manufacturing & Wholesale Goods"
        }
    ],
    "sg:phone":"+1 214 821 5283",
    "sg:postcode":"75204",
    "sg:province":"TX",
    "sg:tags":[
        "ind",
        "paper",
        "commercial",
        "offset",
        "mfg"
    ],
    "wof:name":"Fox Quality Prtg & Graphics",
    "wof:placetype":"venue"
},
  "geometry": {"coordinates":[-96.78539000000001,32.801331],"type":"Point"}
}