{
  "type": "Feature",
  "properties": {
    "iso:country":"US",
    "sg:address":"521 N 1st St",
    "sg:city":"Lamesa",
    "sg:classifiers":[
        {
            "category":"Utilities",
            "subcategory":"Telephone",
            "type":"Services"
        }
    ],
    "sg:phone":"+1 806 872 9668",
    "sg:postcode":"79331",
    "sg:province":"TX",
    "sg:tags":[
        "communication",
        "computer",
        "design",
        "system",
        "network"
    ],
    "sg:website":"http://www.pics.net",
    "wof:name":"P I C S Net",
    "wof:placetype":"venue"
},
  "geometry": {"coordinates":[-101.95324100000001,32.732907],"type":"Point"}
}