{
  "type": "Feature",
  "properties": {
    "iso:country":"US",
    "sg:address":"1643 Hillcrest Cir",
    "sg:city":"Gordonville",
    "sg:classifiers":[
        {
            "category":"Professional",
            "type":"Services"
        }
    ],
    "sg:phone":"+1 903 523 3018",
    "sg:postcode":"76245",
    "sg:province":"TX",
    "wof:name":"Talisman Wood Arts",
    "wof:placetype":"venue"
},
  "geometry": {"coordinates":[-96.805741,33.854514],"type":"Point"}
}