{
  "type": "Feature",
  "properties": {
    "iso:country":"US",
    "sg:address":"102 Wonder World Dr",
    "sg:city":"San Marcos",
    "sg:classifiers":[
        {
            "category":"Cafe",
            "type":"Food & Drink"
        }
    ],
    "sg:menulink":"http://www.allmenus.com/tx/san-marcos/155754-wow-cafe--wingery/menu/",
    "sg:phone":"+1 512 878 8300",
    "sg:postcode":"78666",
    "sg:province":"TX",
    "sg:tags":[
        "american"
    ],
    "wof:name":"Wow Cafe & Wingery",
    "wof:placetype":"venue"
},
  "geometry": {"coordinates":[-97.963235,29.865573],"type":"Point"}
}