{
  "type": "Feature",
  "properties": {
    "iso:country":"US",
    "sg:address":"840 Connally St",
    "sg:city":"Sulphur Springs",
    "sg:classifiers":[
        {
            "category":"Organizations",
            "subcategory":"Religious Organization",
            "type":"Services"
        }
    ],
    "sg:phone":"+1 903 885 3660",
    "sg:postcode":"75482",
    "sg:province":"TX",
    "sg:tags":[
        "church"
    ],
    "sg:website":"www.centralbaptistonline.org",
    "wof:name":"Central Baptist Church",
    "wof:placetype":"venue"
},
  "geometry": {"coordinates":[-95.611497,33.1382],"type":"Point"}
}