{
  "type": "Feature",
  "properties": {
    "iso:country":"US",
    "sg:address":"5406 21st St",
    "sg:city":"Lubbock",
    "sg:classifiers":[
        {
            "category":"Real Estate",
            "subcategory":"Real Estate Agent",
            "type":"Services"
        }
    ],
    "sg:phone":"+1 806 792 4133",
    "sg:postcode":"79407",
    "sg:province":"TX",
    "wof:name":"Joiner Properties",
    "wof:placetype":"venue"
},
  "geometry": {"coordinates":[-101.93095,33.575609],"type":"Point"}
}