{
  "type": "Feature",
  "properties": {
    "iso:country":"US",
    "sg:address":"816 Texas Ave",
    "sg:city":"Lubbock",
    "sg:classifiers":[
        {
            "category":"Government",
            "subcategory":"Police Station",
            "type":"Public Place"
        }
    ],
    "sg:phone":"+1 806 767 2818",
    "sg:postcode":"79401",
    "sg:province":"TX",
    "sg:tags":[
        "department"
    ],
    "wof:name":"Lubbock Police-Property Room",
    "wof:placetype":"venue"
},
  "geometry": {"coordinates":[-101.84572,33.587534],"type":"Point"}
}