{
  "type": "Feature",
  "properties": {
    "iso:country":"US",
    "sg:address":"5700 S Co Rd 1200",
    "sg:city":"Midland",
    "sg:classifiers":[
        {
            "category":"Recreation",
            "subcategory":"Marina",
            "type":"Entertainment"
        }
    ],
    "sg:phone":"+1 432 683 1044",
    "sg:postcode":"79706",
    "sg:province":"TX",
    "sg:tags":[
        "operation"
    ],
    "wof:name":"American Rv & Boat Storage",
    "wof:placetype":"venue"
},
  "geometry": {"coordinates":[-102.07595999999999,31.922295],"type":"Point"}
}