{
  "type": "Feature",
  "properties": {
    "iso:country":"US",
    "sg:address":"7903 Ferguson Rd",
    "sg:city":"Dallas",
    "sg:classifiers":[
        {
            "category":"Organizations",
            "subcategory":"Religious Organization",
            "type":"Services"
        }
    ],
    "sg:phone":"+1 214 319 7072",
    "sg:postcode":"75228",
    "sg:province":"TX",
    "wof:name":"Emmanuel New Life Fellowship",
    "wof:placetype":"venue"
},
  "geometry": {"coordinates":[-96.714699,32.801399],"type":"Point"}
}