{
  "type": "Feature",
  "properties": {
    "iso:country":"US",
    "sg:address":"8554 Katy Fwy",
    "sg:city":"Houston",
    "sg:classifiers":[
        {
            "category":"Health Services",
            "subcategory":"Nursing And Care Facility",
            "type":"Services"
        },
        {
            "category":"Real Estate",
            "subcategory":"Real Estate Operator",
            "type":"Services"
        }
    ],
    "sg:phone":"+1 713 463 1700",
    "sg:postcode":"77024",
    "sg:province":"TX",
    "sg:tags":[
        "building",
        "retirement",
        "apartment",
        "community",
        "home"
    ],
    "sg:website":"www.belmontvillage.com",
    "wof:name":"Belmont Village",
    "wof:placetype":"venue"
},
  "geometry": {"coordinates":[-95.49338400000001,29.784277],"type":"Point"}
}