{
  "type": "Feature",
  "properties": {
    "iso:country":"US",
    "sg:address":"1211 Doubles Dr",
    "sg:city":"Arlington",
    "sg:classifiers":[
        {
            "category":"Professional",
            "type":"Services"
        }
    ],
    "sg:phone":"+1 817 557 3842",
    "sg:postcode":"76017",
    "sg:province":"TX",
    "wof:name":"Lm Services",
    "wof:placetype":"venue"
},
  "geometry": {"coordinates":[-97.132333,32.662894],"type":"Point"}
}