{
  "type": "Feature",
  "properties": {
    "iso:country":"US",
    "sg:address":"4727 Hondo Pass Ave",
    "sg:city":"El Paso",
    "sg:classifiers":[
        {
            "category":"Personal",
            "type":"Services"
        }
    ],
    "sg:phone":"+1 915 755 4522",
    "sg:postcode":"79904",
    "sg:province":"TX",
    "sg:tags":[
        "shop",
        "beauty"
    ],
    "wof:name":"Merle Norman Cosmetics",
    "wof:placetype":"venue"
},
  "geometry": {"coordinates":[-106.433009,31.869856],"type":"Point"}
}