{
  "type": "Feature",
  "properties": {
    "iso:country":"US",
    "sg:address":"12937 Honey Locust Cir",
    "sg:city":"Euless",
    "sg:classifiers":[
        {
            "category":"Manufacturing",
            "subcategory":"Printing",
            "type":"Manufacturing & Wholesale Goods"
        }
    ],
    "sg:phone":"+1 817 545 9866",
    "sg:postcode":"76040",
    "sg:province":"TX",
    "sg:tags":[
        "publishing"
    ],
    "wof:name":"Fellows Press of America Inc",
    "wof:placetype":"venue"
},
  "geometry": {"coordinates":[-97.08376800000001,32.821994],"type":"Point"}
}