{
  "type": "Feature",
  "properties": {
    "iso:country":"US",
    "sg:address":"4915 Red Birch Dr",
    "sg:city":"Arlington",
    "sg:classifiers":[
        {
            "category":"Education",
            "subcategory":"School",
            "type":"Public Place"
        }
    ],
    "sg:phone":"+1 682 867 5900",
    "sg:postcode":"76018",
    "sg:province":"TX",
    "sg:tags":[
        "elementary"
    ],
    "sg:website":"http://www.aisd.net",
    "wof:name":"Williams Elementary School",
    "wof:placetype":"venue"
},
  "geometry": {"coordinates":[-97.108698,32.665941],"type":"Point"}
}