{
  "type": "Feature",
  "properties": {
    "iso:country":"US",
    "sg:address":"5517 Charlestown Dr",
    "sg:city":"Dallas",
    "sg:classifiers":[
        {
            "category":"Food & Beverages",
            "subcategory":"Groceries & Convenience Stores",
            "type":"Retail Goods"
        }
    ],
    "sg:phone":"+1 972 386 3445",
    "sg:postcode":"75230",
    "sg:province":"TX",
    "wof:name":"Market Vision Inc",
    "wof:placetype":"venue"
},
  "geometry": {"coordinates":[-96.811958,32.917643],"type":"Point"}
}