{
  "type": "Feature",
  "properties": {
    "iso:country":"US",
    "sg:address":"8300 Douglas Ave Ste 725",
    "sg:city":"Dallas",
    "sg:classifiers":[
        {
            "category":"Shopping",
            "subcategory":"Jewelry",
            "type":"Retail Goods"
        }
    ],
    "sg:phone":"+1 214 363 6591",
    "sg:postcode":"75225",
    "sg:province":"TX",
    "wof:name":"Utay Oscar Jewelry Company",
    "wof:placetype":"venue"
},
  "geometry": {"coordinates":[-96.808502,32.863602],"type":"Point"}
}