{
  "type": "Feature",
  "properties": {
    "iso:country":"US",
    "sg:address":"1307 Jackson Rd",
    "sg:city":"Kerrville",
    "sg:classifiers":[
        {
            "category":"Professional",
            "subcategory":"Computer Services",
            "type":"Services"
        }
    ],
    "sg:phone":"+1 830 792 3141",
    "sg:postcode":"78028",
    "sg:province":"TX",
    "sg:tags":[
        "prepackaged",
        "software"
    ],
    "wof:name":"Legato Systems",
    "wof:placetype":"venue"
},
  "geometry": {"coordinates":[-99.163139,30.069435],"type":"Point"}
}