{
  "type": "Feature",
  "properties": {
    "iso:country":"US",
    "sg:address":"2229 Knob Hill Dr",
    "sg:city":"Denton",
    "sg:classifiers":[
        {
            "category":"Freight",
            "type":"Transportation"
        }
    ],
    "sg:phone":"+1 940 497 2094",
    "sg:postcode":"76210",
    "sg:province":"TX",
    "sg:tags":[
        "arrangement"
    ],
    "wof:name":"Industrial Packaging Cons",
    "wof:placetype":"venue"
},
  "geometry": {"coordinates":[-97.07405900000001,33.156957],"type":"Point"}
}