{
  "type": "Feature",
  "properties": {
    "iso:country":"US",
    "sg:address":"6440 North Fwy",
    "sg:city":"Fort Worth",
    "sg:classifiers":[
        {
            "category":"Restaurant",
            "type":"Food & Drink"
        }
    ],
    "sg:phone":"+1 817 232 8474",
    "sg:postcode":"76137",
    "sg:province":"TX",
    "wof:name":"Wendy's",
    "wof:placetype":"venue"
},
  "geometry": {"coordinates":[-97.313492,32.859886],"type":"Point"}
}