{
  "type": "Feature",
  "properties": {
    "iso:country":"US",
    "sg:address":"9403 Appin Falls Dr",
    "sg:city":"Spring",
    "sg:classifiers":[
        {
            "category":"Professional",
            "subcategory":"Management & Consulting",
            "type":"Services"
        }
    ],
    "sg:phone":"+1 281 251 4134",
    "sg:postcode":"77379",
    "sg:province":"TX",
    "sg:tags":[
        "consultant",
        "energy",
        "conservation"
    ],
    "wof:name":"Barodyne Inc",
    "wof:placetype":"venue"
},
  "geometry": {"coordinates":[-95.548895,30.003148],"type":"Point"}
}