{
  "type": "Feature",
  "properties": {
    "iso:country":"US",
    "sg:address":"7040 N Mesa St",
    "sg:city":"El Paso",
    "sg:classifiers":[
        {
            "category":"Health Services",
            "subcategory":"Doctor",
            "type":"Services"
        }
    ],
    "sg:phone":"+1 915 833 0222",
    "sg:postcode":"79912",
    "sg:province":"TX",
    "wof:name":"Eliezer Ben Joseph MD",
    "wof:placetype":"venue"
},
  "geometry": {"coordinates":[-106.55256,31.836274],"type":"Point"}
}