{
  "type": "Feature",
  "properties": {
    "iso:country":"US",
    "sg:address":"2201 Lake Austin Blvd",
    "sg:city":"Austin",
    "sg:classifiers":[
        {
            "category":"Shopping",
            "subcategory":"Shoes",
            "type":"Retail Goods"
        }
    ],
    "sg:phone":"+1 512 477 9464",
    "sg:postcode":"78703",
    "sg:province":"TX",
    "sg:website":"www.runtex.com",
    "wof:name":"Run-Tex",
    "wof:placetype":"venue"
},
  "geometry": {"coordinates":[-97.77131199999999,30.277466],"type":"Point"}
}