{
  "type": "Feature",
  "properties": {
    "iso:country":"US",
    "sg:address":"218 Lake Highlands Shopping Vlg",
    "sg:city":"Dallas",
    "sg:classifiers":[
        {
            "category":"Retail",
            "subcategory":"Laundry & Dry Cleaning",
            "type":"Services"
        }
    ],
    "sg:phone":"+1 214 328 7817",
    "sg:postcode":"75201",
    "sg:province":"TX",
    "wof:name":"Freeman's Village Cleaners",
    "wof:placetype":"venue"
},
  "geometry": {"coordinates":[-96.600869,32.777235],"type":"Point"}
}