{
  "type": "Feature",
  "properties": {
    "iso:country":"US",
    "sg:address":"814 E Main Ave",
    "sg:city":"Robstown",
    "sg:classifiers":[
        {
            "category":"Health Services",
            "subcategory":"Doctor",
            "type":"Services"
        }
    ],
    "sg:phone":"+1 361 387 6900",
    "sg:postcode":"78380",
    "sg:province":"TX",
    "sg:tags":[
        "physician",
        "family",
        "practice",
        "surgeons",
        "medicine",
        "surgeon"
    ],
    "wof:name":"Perez Abimael M D",
    "wof:placetype":"venue"
},
  "geometry": {"coordinates":[-97.658422,27.78862],"type":"Point"}
}