{
  "type": "Feature",
  "properties": {
    "iso:country":"US",
    "sg:address":"519 State Hwy 71 W",
    "sg:city":"Bastrop",
    "sg:classifiers":[
        {
            "category":"Freight",
            "type":"Transportation"
        }
    ],
    "sg:phone":"+1 512 303 1703",
    "sg:postcode":"78602",
    "sg:province":"TX",
    "sg:tags":[
        "special"
    ],
    "wof:name":"J & R Mini Storage",
    "wof:placetype":"venue"
},
  "geometry": {"coordinates":[-97.354462,30.110933],"type":"Point"}
}