{
  "type": "Feature",
  "properties": {
    "iso:country":"US",
    "sg:address":"1100 Raider Dr",
    "sg:city":"Euless",
    "sg:classifiers":[
        {
            "category":"Education",
            "subcategory":"School",
            "type":"Public Place"
        }
    ],
    "sg:phone":"+1 817 354 3398",
    "sg:postcode":"76040",
    "sg:province":"TX",
    "wof:name":"Alternative Education Program",
    "wof:placetype":"venue"
},
  "geometry": {"coordinates":[-97.134669,32.819809],"type":"Point"}
}