{
  "type": "Feature",
  "properties": {
    "iso:country":"US",
    "sg:address":"230 E Main St",
    "sg:city":"Munday",
    "sg:classifiers":[
        {
            "category":"Building & Trades",
            "subcategory":"Plumbing",
            "type":"Services"
        },
        {
            "category":"Building & Trades",
            "subcategory":"Electrical",
            "type":"Services"
        }
    ],
    "sg:phone":"+1 940 422 4415",
    "sg:postcode":"76371",
    "sg:province":"TX",
    "sg:tags":[
        "plumber",
        "industrial",
        "electrician",
        "electric",
        "contractors-commercial"
    ],
    "wof:name":"Carden Plumbing & Electric Co",
    "wof:placetype":"venue"
},
  "geometry": {"coordinates":[-99.622613,33.449012],"type":"Point"}
}