{
  "type": "Feature",
  "properties": {
    "iso:country":"US",
    "sg:address":"660 Central Expy",
    "sg:city":"Plano",
    "sg:classifiers":[
        {
            "category":"Utilities",
            "subcategory":"Telephone",
            "type":"Services"
        }
    ],
    "sg:phone":"+1 214 363 6600",
    "sg:postcode":"75074",
    "sg:province":"TX",
    "sg:tags":[
        "communications",
        "radiotelephone",
        "communication"
    ],
    "wof:name":"1477 Wireless",
    "wof:placetype":"venue"
},
  "geometry": {"coordinates":[-96.707211,33.007185],"type":"Point"}
}