{
  "type": "Feature",
  "properties": {
    "iso:country":"US",
    "sg:address":"548 State Hwy 36",
    "sg:city":"Cross Plains",
    "sg:classifiers":[
        {
            "category":"Insurance",
            "subcategory":"Insurance Agent",
            "type":"Services"
        }
    ],
    "sg:phone":"+1 254 725 6325",
    "sg:postcode":"76443",
    "sg:province":"TX",
    "wof:name":"Senior Benefits",
    "wof:placetype":"venue"
},
  "geometry": {"coordinates":[-99.16856900000001,32.121638],"type":"Point"}
}