{
  "type": "Feature",
  "properties": {
    "iso:country":"US",
    "sg:address":"4901 Shank Rd",
    "sg:city":"Pearland",
    "sg:classifiers":[
        {
            "category":"Utilities",
            "subcategory":"Refuse",
            "type":"Services"
        }
    ],
    "sg:phone":"+1 281 997 6969",
    "sg:postcode":"77581",
    "sg:province":"TX",
    "sg:tags":[
        "disposal",
        "waste"
    ],
    "wof:name":"Gulf Coast Vacuum Svc",
    "wof:placetype":"venue"
},
  "geometry": {"coordinates":[-95.295874,29.573495],"type":"Point"}
}