{
  "type": "Feature",
  "properties": {
    "iso:country":"US",
    "sg:address":"7304 Homestead Rd",
    "sg:city":"Houston",
    "sg:classifiers":[
        {
            "category":"Organizations",
            "subcategory":"Religious Organization",
            "type":"Services"
        }
    ],
    "sg:phone":"+1 713 633 6099",
    "sg:postcode":"77028",
    "sg:province":"TX",
    "sg:tags":[
        "real estate",
        "developer"
    ],
    "wof:name":"Upward Bound Community Development Corp",
    "wof:placetype":"venue"
},
  "geometry": {"coordinates":[-95.301697,29.828501],"type":"Point"}
}