{
  "type": "Feature",
  "properties": {
    "iso:country":"US",
    "sg:address":"25418 Tuckahoe Ln",
    "sg:city":"Spring",
    "sg:classifiers":[
        {
            "category":"Professional",
            "type":"Services"
        }
    ],
    "sg:phone":"+1 281 353 0135",
    "sg:postcode":"77373",
    "sg:province":"TX",
    "wof:name":"Technocash Inc",
    "wof:placetype":"venue"
},
  "geometry": {"coordinates":[-95.40270700000001,30.073068],"type":"Point"}
}