{
  "type": "Feature",
  "properties": {
    "iso:country":"US",
    "sg:address":"3203 Ohio Ave",
    "sg:city":"Dickinson",
    "sg:classifiers":[
        {
            "category":"Shopping",
            "subcategory":"Bicycles & Sporting Goods",
            "type":"Retail Goods"
        }
    ],
    "sg:phone":"+1 281 534 3112",
    "sg:postcode":"77539",
    "sg:province":"TX",
    "sg:tags":[
        "equipment",
        "exercise"
    ],
    "wof:name":"Winners Edge",
    "wof:placetype":"venue"
},
  "geometry": {"coordinates":[-95.048827,29.470458],"type":"Point"}
}