{
  "type": "Feature",
  "properties": {
    "iso:country":"US",
    "sg:address":"5201 E Grand Ave",
    "sg:city":"Dallas",
    "sg:classifiers":[
        {
            "category":"Bus Charters",
            "type":"Transportation"
        }
    ],
    "sg:phone":"+1 214 821 0365",
    "sg:postcode":"75223",
    "sg:province":"TX",
    "sg:tags":[
        "rental"
    ],
    "wof:name":"Aventura Tours Inc",
    "wof:placetype":"venue"
},
  "geometry": {"coordinates":[-96.750884,32.790498],"type":"Point"}
}