{
  "type": "Feature",
  "properties": {
    "iso:country":"US",
    "sg:address":"300 W Palm Dr",
    "sg:city":"Edinburg",
    "sg:classifiers":[
        {
            "category":"Sports & Exercise",
            "subcategory":"Golf",
            "type":"Entertainment"
        }
    ],
    "sg:phone":"+1 956 292 2144",
    "sg:postcode":"78539",
    "sg:province":"TX",
    "sg:tags":[
        "course",
        "executive",
        "public"
    ],
    "wof:name":"Ebony Golf Course",
    "wof:placetype":"venue"
},
  "geometry": {"coordinates":[-98.16536000000001,26.28494],"type":"Point"}
}