{
  "type": "Feature",
  "properties": {
    "iso:country":"US",
    "sg:address":"1121 Uptown Park Blvd Ste 19",
    "sg:city":"Houston",
    "sg:classifiers":[
        {
            "category":"Health Services",
            "subcategory":"Doctor",
            "type":"Services"
        },
        {
            "category":"Health Services",
            "subcategory":"Dentist",
            "type":"Services"
        }
    ],
    "sg:phone":"+1 713 621 4830",
    "sg:postcode":"77056",
    "sg:province":"TX",
    "sg:tags":[
        "surgeon",
        "oral",
        "cosmetic"
    ],
    "wof:name":"James G. Moore, DDS",
    "wof:placetype":"venue"
},
  "geometry": {"coordinates":[-95.45760300000001,29.7558],"type":"Point"}
}