{
  "type": "Feature",
  "properties": {
    "iso:country":"US",
    "sg:address":"1578 White Mound Rd",
    "sg:city":"Sherman",
    "sg:classifiers":[
        {
            "category":"Building & Trades",
            "subcategory":"Plumbing",
            "type":"Services"
        }
    ],
    "sg:phone":"+1 903 868 9517",
    "sg:postcode":"75489",
    "sg:province":"TX",
    "sg:tags":[
        "conditioning",
        "air",
        "system",
        "contractor"
    ],
    "wof:name":"N T Systems Inc",
    "wof:placetype":"venue"
},
  "geometry": {"coordinates":[-96.510194,33.512739],"type":"Point"}
}