{
  "type": "Feature",
  "properties": {
    "iso:country":"US",
    "sg:address":"6550 Fannin St",
    "sg:city":"Houston",
    "sg:phone":"+1 713 798 7438",
    "sg:postcode":"77030",
    "sg:province":"TX",
    "wof:name":"Ondo, William, Md - Baylor College Of Medicine",
    "wof:placetype":"venue"
},
  "geometry": {"coordinates":[-95.400159,29.710743],"type":"Point"}
}