{
  "type": "Feature",
  "properties": {
    "iso:country":"US",
    "sg:address":"111 Post Oak",
    "sg:city":"Elgin",
    "sg:classifiers":[
        {
            "category":"Building & Trades",
            "subcategory":"Construction",
            "type":"Services"
        }
    ],
    "sg:phone":"+1 512 281 5235",
    "sg:postcode":"78621",
    "sg:province":"TX",
    "sg:tags":[
        "fence",
        "contractor"
    ],
    "wof:name":"Centex Fence",
    "wof:placetype":"venue"
},
  "geometry": {"coordinates":[-97.342511,30.285463],"type":"Point"}
}