{
  "type": "Feature",
  "properties": {
    "iso:country":"US",
    "sg:address":"238 S Glenwood Blvd",
    "sg:city":"Tyler",
    "sg:classifiers":[
        {
            "category":"Shopping",
            "subcategory":"Used Merchandise",
            "type":"Retail Goods"
        }
    ],
    "sg:phone":"+1 903 592 3001",
    "sg:postcode":"75702",
    "sg:province":"TX",
    "sg:tags":[
        "sporting"
    ],
    "wof:name":"Money Tree Pawn Shop",
    "wof:placetype":"venue"
},
  "geometry": {"coordinates":[-95.317454,32.348973],"type":"Point"}
}