{
  "type": "Feature",
  "properties": {
    "iso:country":"US",
    "sg:address":"2000 Oak Ave",
    "sg:city":"Port Arthur",
    "sg:classifiers":[
        {
            "category":"Retail",
            "subcategory":"Repair Shop",
            "type":"Services"
        }
    ],
    "sg:phone":"+1 409 722 7431",
    "sg:postcode":"77642",
    "sg:province":"TX",
    "sg:tags":[
        "locksmith"
    ],
    "wof:name":"Boudreauxs Tim Safe & Lock S",
    "wof:placetype":"venue"
},
  "geometry": {"coordinates":[-93.920367,29.916012],"type":"Point"}
}