{
  "type": "Feature",
  "properties": {
    "iso:country":"US",
    "sg:address":"2700 Live Oak St",
    "sg:city":"Dallas",
    "sg:classifiers":[
        {
            "category":"Real Estate",
            "subcategory":"Real Estate Services",
            "type":"Services"
        }
    ],
    "sg:phone":"+1 214 827 5333",
    "sg:postcode":"75204",
    "sg:province":"TX",
    "sg:website":"www.title-tech.com",
    "wof:name":"Title-Tech",
    "wof:placetype":"venue"
},
  "geometry": {"coordinates":[-96.78848600000001,32.78933],"type":"Point"}
}