{
  "type": "Feature",
  "properties": {
    "iso:country":"US",
    "sg:address":"114 SW 2nd St",
    "sg:city":"Tulia",
    "sg:classifiers":[
        {
            "category":"Insurance",
            "subcategory":"Hazard Insurance",
            "type":"Services"
        }
    ],
    "sg:phone":"+1 806 995 2529",
    "sg:postcode":"79088",
    "sg:province":"TX",
    "sg:tags":[
        "bond"
    ],
    "wof:name":"Magallanes Bail Bonds",
    "wof:placetype":"venue"
},
  "geometry": {"coordinates":[-101.765677,34.536078],"type":"Point"}
}