{
  "type": "Feature",
  "properties": {
    "iso:country":"US",
    "sg:address":"801 Montecito Dr",
    "sg:city":"San Angelo",
    "sg:classifiers":[
        {
            "category":"Organizations",
            "subcategory":"Religious Organization",
            "type":"Services"
        }
    ],
    "sg:phone":"+1 325 653 6074",
    "sg:postcode":"76903",
    "sg:province":"TX",
    "sg:tags":[
        "church"
    ],
    "wof:name":"Greek Orthodox Church",
    "wof:placetype":"venue"
},
  "geometry": {"coordinates":[-100.447188,31.45067],"type":"Point"}
}