{
  "type": "Feature",
  "properties": {
    "iso:country":"US",
    "sg:address":"814 Cockrell Hill Rd",
    "sg:city":"Ovilla",
    "sg:classifiers":[
        {
            "category":"Wholesale",
            "subcategory":"Machinery & Supplies",
            "type":"Manufacturing & Wholesale Goods"
        }
    ],
    "sg:phone":"+1 972 217 4909",
    "sg:postcode":"75154",
    "sg:province":"TX",
    "sg:tags":[
        "truck"
    ],
    "wof:name":"Merto Deal",
    "wof:placetype":"venue"
},
  "geometry": {"coordinates":[-96.89096000000001,32.547151],"type":"Point"}
}