{
  "type": "Feature",
  "properties": {
    "iso:country":"US",
    "sg:address":"1614 N University Dr",
    "sg:city":"Nacogdoches",
    "sg:classifiers":[
        {
            "category":"Restaurant",
            "type":"Food & Drink"
        }
    ],
    "sg:menulink":"http://www.allmenus.com/tx/nacogdoches/223714-chicken-express/menu/",
    "sg:phone":"+1 936 559 0077",
    "sg:postcode":"75961",
    "sg:province":"TX",
    "sg:tags":[
        "american"
    ],
    "wof:name":"Chicken Express",
    "wof:placetype":"venue"
},
  "geometry": {"coordinates":[-94.639427,31.617199],"type":"Point"}
}