{
  "type": "Feature",
  "properties": {
    "iso:country":"US",
    "sg:address":"109 N McKinney St",
    "sg:city":"Mexia",
    "sg:classifiers":[
        {
            "category":"Insurance",
            "subcategory":"Insurance Agent",
            "type":"Services"
        }
    ],
    "sg:phone":"+1 254 562 3434",
    "sg:postcode":"76667",
    "sg:province":"TX",
    "wof:name":"Griffin Insurance Service",
    "wof:placetype":"venue"
},
  "geometry": {"coordinates":[-96.482561,31.681118],"type":"Point"}
}