{
  "type": "Feature",
  "properties": {
    "iso:country":"US",
    "sg:address":"1118 E Broadway St",
    "sg:city":"Sweetwater",
    "sg:classifiers":[
        {
            "category":"Utilities",
            "subcategory":"Cable",
            "type":"Services"
        }
    ],
    "sg:phone":"+1 325 236 6375",
    "sg:postcode":"79556",
    "sg:province":"TX",
    "sg:tags":[
        "television"
    ],
    "wof:name":"Cox Communications",
    "wof:placetype":"venue"
},
  "geometry": {"coordinates":[-100.394772,32.476302],"type":"Point"}
}