{
  "type": "Feature",
  "properties": {
    "iso:country":"US",
    "sg:address":"4019 N Galloway Ave Ste D",
    "sg:city":"Mesquite",
    "sg:classifiers":[
        {
            "category":"Professional",
            "subcategory":"Lawyer & Legal Services",
            "type":"Services"
        }
    ],
    "sg:phone":"+1 972 681 3272",
    "sg:postcode":"75150",
    "sg:province":"TX",
    "sg:tags":[
        "divorce",
        "law",
        "family"
    ],
    "wof:name":"Miller Chas E Jr Atty",
    "wof:placetype":"venue"
},
  "geometry": {"coordinates":[-96.616754,32.818695],"type":"Point"}
}