{
  "type": "Feature",
  "properties": {
    "iso:country":"US",
    "sg:address":"12525 Greenville Ave",
    "sg:city":"Dallas",
    "sg:classifiers":[
        {
            "category":"Travel",
            "subcategory":"Hotels & Motels",
            "type":"Entertainment"
        },
        {
            "category":"Retail",
            "subcategory":"Event Space",
            "type":"Services"
        }
    ],
    "sg:phone":"+1 877 660 8545",
    "sg:postcode":"75243",
    "sg:province":"TX",
    "sg:tags":[
        "facility",
        "banquet",
        "reception",
        "lodging",
        "corporate",
        "hall"
    ],
    "sg:website":"http://ad.doubleclick.net/clk;222817012;46581823;b?http://www.candlewoodsuites.com/redirect?path=hd&brandCode=cw&hotelCode=dalga&_PMID=99601036&cm_mmc=mdpr-_-yellowpages-_-cw-_-dalga",
    "wof:name":"Candlewood Suites Dallas Park Central",
    "wof:placetype":"venue"
},
  "geometry": {"coordinates":[-96.742985,32.917778],"type":"Point"}
}