{
  "type": "Feature",
  "properties": {
    "iso:country":"US",
    "sg:address":"10616 Hempstead Rd",
    "sg:city":"Houston",
    "sg:classifiers":[
        {
            "category":"Wholesale",
            "subcategory":"Durable Goods & Equipment",
            "type":"Manufacturing & Wholesale Goods"
        }
    ],
    "sg:phone":"+1 713 263 9497",
    "sg:postcode":"77092",
    "sg:province":"TX",
    "sg:tags":[
        "representative",
        "manufacturer"
    ],
    "wof:name":"Lumen Sales Warehouse",
    "wof:placetype":"venue"
},
  "geometry": {"coordinates":[-95.470516,29.809187],"type":"Point"}
}