{
  "type": "Feature",
  "properties": {
    "iso:country":"US",
    "sg:address":"9 Arrow Ln",
    "sg:city":"Luling",
    "sg:classifiers":[
        {
            "category":"Professional",
            "subcategory":"Lawyer & Legal Services",
            "type":"Services"
        }
    ],
    "sg:phone":"+1 830 875 2941",
    "sg:postcode":"78648",
    "sg:province":"TX",
    "sg:tags":[
        "attorney"
    ],
    "wof:name":"Watson & Watson",
    "wof:placetype":"venue"
},
  "geometry": {"coordinates":[-97.593903,29.65484],"type":"Point"}
}