{
  "type": "Feature",
  "properties": {
    "iso:country":"US",
    "sg:address":"5230 Flax Burton St",
    "sg:city":"Humble",
    "sg:classifiers":[
        {
            "category":"Wholesale",
            "subcategory":"Groceries",
            "type":"Manufacturing & Wholesale Goods"
        }
    ],
    "sg:phone":"+1 281 812 9556",
    "sg:postcode":"77346",
    "sg:province":"TX",
    "wof:name":"Greenspot USA",
    "wof:placetype":"venue"
},
  "geometry": {"coordinates":[-95.196597,29.993206],"type":"Point"}
}