{
  "type": "Feature",
  "properties": {
    "iso:country":"US",
    "sg:address":"2001 Ross Ave",
    "sg:city":"Dallas",
    "sg:classifiers":[
        {
            "category":"Personal",
            "subcategory":"Barber",
            "type":"Services"
        }
    ],
    "sg:phone":"+1 214 758 1534",
    "sg:postcode":"75201",
    "sg:province":"TX",
    "sg:tags":[
        "shop"
    ],
    "wof:name":"George Barber",
    "wof:placetype":"venue"
},
  "geometry": {"coordinates":[-96.79834700000001,32.787678],"type":"Point"}
}