{
  "type": "Feature",
  "properties": {
    "iso:country":"US",
    "sg:address":"2247 N Main St",
    "sg:city":"Pearland",
    "sg:classifiers":[
        {
            "category":"Shopping",
            "subcategory":"Jewelry",
            "type":"Retail Goods"
        }
    ],
    "sg:phone":"+1 281 485 6368",
    "sg:postcode":"77581",
    "sg:province":"TX",
    "sg:tags":[
        "jeweler"
    ],
    "wof:name":"Pearland Jewelry and Gifts",
    "wof:placetype":"venue"
},
  "geometry": {"coordinates":[-95.286006,29.566293],"type":"Point"}
}