{
  "type": "Feature",
  "properties": {
    "iso:country":"US",
    "sg:address":"1648 Globe Ave",
    "sg:city":"Fort Worth",
    "sg:classifiers":[
        {
            "category":"Retail",
            "subcategory":"Repair Shop",
            "type":"Services"
        }
    ],
    "sg:phone":"+1 817 232 4830",
    "sg:postcode":"76131",
    "sg:province":"TX",
    "wof:name":"Amos D Drain",
    "wof:placetype":"venue"
},
  "geometry": {"coordinates":[-97.340857,32.860456],"type":"Point"}
}