{
  "type": "Feature",
  "properties": {
    "iso:country":"US",
    "sg:address":"4848 Preston Rd",
    "sg:city":"Frisco",
    "sg:classifiers":[
        {
            "category":"Banks & Credit Unions",
            "subcategory":"Bank",
            "type":"Services"
        }
    ],
    "sg:phone":"+1 972 377 2472",
    "sg:postcode":"75034",
    "sg:province":"TX",
    "wof:name":"Wells Fargo Bank",
    "wof:placetype":"venue"
},
  "geometry": {"coordinates":[-96.805376,33.119489],"type":"Point"}
}