{
  "type": "Feature",
  "properties": {
    "iso:country":"US",
    "sg:address":"254 Coral Ave",
    "sg:city":"San Antonio",
    "sg:classifiers":[
        {
            "category":"Manufacturing",
            "subcategory":"Retail Goods",
            "type":"Manufacturing & Wholesale Goods"
        }
    ],
    "sg:phone":"+1 210 337 3785",
    "sg:postcode":"78223",
    "sg:province":"TX",
    "sg:tags":[
        "lead",
        "mfg"
    ],
    "wof:name":"Wilma P Black",
    "wof:placetype":"venue"
},
  "geometry": {"coordinates":[-98.443296,29.364325],"type":"Point"}
}