{
  "type": "Feature",
  "properties": {
    "iso:country":"US",
    "sg:address":"9602 Autumn Sound",
    "sg:city":"Boerne",
    "sg:classifiers":[
        {
            "category":"Real Estate",
            "subcategory":"Real Estate Services",
            "type":"Services"
        },
        {
            "category":"Real Estate",
            "subcategory":"Real Estate Agent",
            "type":"Services"
        }
    ],
    "sg:phone":"+1 210 698 5311",
    "sg:postcode":"78006",
    "sg:province":"TX",
    "sg:tags":[
        "buyer",
        "broker"
    ],
    "wof:name":"Christian Brother Realtors",
    "wof:placetype":"venue"
},
  "geometry": {"coordinates":[-98.67831200000001,29.695164],"type":"Point"}
}