{
  "type": "Feature",
  "properties": {
    "iso:country":"US",
    "sg:address":"1210 E 3rd St",
    "sg:city":"Mount Pleasant",
    "sg:classifiers":[
        {
            "category":"Shopping",
            "subcategory":"Gifts & Souvenirs",
            "type":"Retail Goods"
        }
    ],
    "sg:phone":"+1 903 572 3749",
    "sg:postcode":"75455",
    "sg:province":"TX",
    "wof:name":"Novedades Jr",
    "wof:placetype":"venue"
},
  "geometry": {"coordinates":[-94.952692,33.158173],"type":"Point"}
}