{
  "type": "Feature",
  "properties": {
    "iso:country":"US",
    "sg:address":"1481 E Hillpark Rd",
    "sg:city":"Lewisville",
    "sg:classifiers":[
        {
            "category":"Recreation",
            "subcategory":"Sailing Club",
            "type":"Entertainment"
        }
    ],
    "sg:phone":"+1 972 370 9415",
    "sg:postcode":"75056",
    "sg:province":"TX",
    "sg:tags":[
        "operation",
        "yacht"
    ],
    "wof:name":"Sea Lake Yacht Sales",
    "wof:placetype":"venue"
},
  "geometry": {"coordinates":[-96.92179899999999,33.074797],"type":"Point"}
}