{
  "type": "Feature",
  "properties": {
    "iso:country":"US",
    "sg:address":"2750 Oakland Ave",
    "sg:city":"Garland",
    "sg:classifiers":[
        {
            "category":"Building & Trades",
            "subcategory":"Construction",
            "type":"Services"
        }
    ],
    "sg:phone":"+1 972 271 7912",
    "sg:postcode":"75041",
    "sg:province":"TX",
    "sg:tags":[
        "contractor",
        "mfg"
    ],
    "wof:name":"All Metal Fixtures",
    "wof:placetype":"venue"
},
  "geometry": {"coordinates":[-96.669545,32.875994],"type":"Point"}
}