{
  "type": "Feature",
  "properties": {
    "iso:country":"US",
    "sg:address":"9515 Fulton St",
    "sg:city":"Houston",
    "sg:classifiers":[
        {
            "category":"Manufacturing",
            "subcategory":"Tools & Machinery",
            "type":"Manufacturing & Wholesale Goods"
        },
        {
            "category":"Retail",
            "subcategory":"Auto Repair",
            "type":"Services"
        }
    ],
    "sg:phone":"+1 713 697 6963",
    "sg:postcode":"77076",
    "sg:province":"TX",
    "sg:tags":[
        "shop",
        "machine",
        "general",
        "supply"
    ],
    "wof:name":"Davids Automotive Machine Shop",
    "wof:placetype":"venue"
},
  "geometry": {"coordinates":[-95.378201,29.846316],"type":"Point"}
}