{
  "type": "Feature",
  "properties": {
    "iso:country":"US",
    "sg:address":"2901 Azle Ave",
    "sg:city":"Fort Worth",
    "sg:classifiers":[
        {
            "category":"Organizations",
            "subcategory":"Religious Organization",
            "type":"Services"
        }
    ],
    "sg:phone":"+1 817 626 5556",
    "sg:postcode":"76106",
    "sg:province":"TX",
    "sg:tags":[
        "church"
    ],
    "wof:name":"Azle Avenue Baptist Church",
    "wof:placetype":"venue"
},
  "geometry": {"coordinates":[-97.382273,32.801339],"type":"Point"}
}