{
  "type": "Feature",
  "properties": {
    "iso:country":"US",
    "sg:address":"8501 W 34th Ave",
    "sg:city":"Amarillo",
    "sg:classifiers":[
        {
            "category":"Shopping",
            "subcategory":"Gifts & Souvenirs",
            "type":"Retail Goods"
        }
    ],
    "sg:phone":"+1 806 358 2103",
    "sg:postcode":"79121",
    "sg:province":"TX",
    "sg:tags":[
        "shop"
    ],
    "wof:name":"Keepsakes",
    "wof:placetype":"venue"
},
  "geometry": {"coordinates":[-101.939132,35.176531],"type":"Point"}
}