{
  "type": "Feature",
  "properties": {
    "iso:country":"US",
    "sg:address":"211 N Broadway St",
    "sg:city":"Mcallen",
    "sg:classifiers":[
        {
            "category":"Shopping",
            "type":"Retail Goods"
        }
    ],
    "sg:phone":"+1 956 262 8306",
    "sg:postcode":"78501",
    "sg:province":"TX",
    "sg:tags":[
        "perfume"
    ],
    "wof:name":"Heavenly Fragrances",
    "wof:placetype":"venue"
},
  "geometry": {"coordinates":[-98.233003,26.206246],"type":"Point"}
}