{
  "type": "Feature",
  "properties": {
    "iso:country":"US",
    "sg:address":"411 W Arapaho Rd",
    "sg:city":"Richardson",
    "sg:classifiers":[
        {
            "category":"Government",
            "subcategory":"Office",
            "type":"Public Place"
        }
    ],
    "sg:phone":"+1 972 744 4180",
    "sg:postcode":"75080",
    "sg:province":"TX",
    "sg:tags":[
        "village"
    ],
    "sg:website":"www.cor.net",
    "wof:name":"Richardson City Building Inspc",
    "wof:placetype":"venue"
},
  "geometry": {"coordinates":[-96.729162,32.96071],"type":"Point"}
}