{
  "type": "Feature",
  "properties": {
    "iso:country":"US",
    "sg:address":"206 W 7th St",
    "sg:city":"Anna",
    "sg:classifiers":[
        {
            "category":"Manufacturing",
            "subcategory":"Metals",
            "type":"Manufacturing & Wholesale Goods"
        }
    ],
    "sg:phone":"+1 972 924 2830",
    "sg:postcode":"75409",
    "sg:province":"TX",
    "sg:tags":[
        "steel"
    ],
    "wof:name":"Wells/Mc Coy Steel Svc",
    "wof:placetype":"venue"
},
  "geometry": {"coordinates":[-96.550391,33.346517],"type":"Point"}
}