{
  "type": "Feature",
  "properties": {
    "iso:country":"US",
    "sg:address":"8700 Preston Rd",
    "sg:city":"Plano",
    "sg:classifiers":[
        {
            "category":"Banks & Credit Unions",
            "subcategory":"Bank",
            "type":"Services"
        }
    ],
    "sg:phone":"+1 972 335 1252",
    "sg:postcode":"75024",
    "sg:province":"TX",
    "sg:tags":[
        "state",
        "commercial"
    ],
    "wof:name":"Comerica",
    "wof:placetype":"venue"
},
  "geometry": {"coordinates":[-96.80538,33.094904],"type":"Point"}
}