{
  "type": "Feature",
  "properties": {
    "iso:country":"US",
    "sg:address":"3312 Seaton Ct",
    "sg:city":"Flower Mound",
    "sg:classifiers":[
        {
            "category":"Building & Trades",
            "subcategory":"Electrical",
            "type":"Services"
        },
        {
            "category":"Professional",
            "type":"Services"
        }
    ],
    "sg:phone":"+1 972 724 4507",
    "sg:postcode":"75028",
    "sg:province":"TX",
    "sg:tags":[
        "establishment",
        "electrical",
        "contractor"
    ],
    "wof:name":"Vectco Sales Inc",
    "wof:placetype":"venue"
},
  "geometry": {"coordinates":[-97.059028,33.030676],"type":"Point"}
}