{
  "type": "Feature",
  "properties": {
    "iso:country":"US",
    "sg:address":"3744 S Alameda St",
    "sg:city":"Corpus Christi",
    "sg:classifiers":[
        {
            "category":"Wholesale",
            "subcategory":"Durable Goods & Equipment",
            "type":"Manufacturing & Wholesale Goods"
        }
    ],
    "sg:phone":"+1 361 225 3744",
    "sg:postcode":"78411",
    "sg:province":"TX",
    "wof:name":"Gatherings",
    "wof:placetype":"venue"
},
  "geometry": {"coordinates":[-97.38166699999999,27.744541],"type":"Point"}
}