{
  "type": "Feature",
  "properties": {
    "iso:country":"US",
    "sg:address":"706 W Oklahoma Ave",
    "sg:city":"Wheeler",
    "sg:classifiers":[
        {
            "category":"Restaurant",
            "type":"Food & Drink"
        }
    ],
    "sg:phone":"+1 806 826 3756",
    "sg:postcode":"79096",
    "sg:province":"TX",
    "sg:tags":[
        "american"
    ],
    "wof:name":"Mel's Diner",
    "wof:placetype":"venue"
},
  "geometry": {"coordinates":[-100.281203,35.444653],"type":"Point"}
}