{
  "type": "Feature",
  "properties": {
    "iso:country":"US",
    "sg:address":"12600 FM 1541",
    "sg:city":"Amarillo",
    "sg:classifiers":[
        {
            "category":"Freight",
            "type":"Transportation"
        }
    ],
    "sg:phone":"+1 806 622 9864",
    "sg:postcode":"79118",
    "sg:province":"TX",
    "sg:tags":[
        "recreational",
        "vehicle"
    ],
    "wof:name":"Panhandle Security Storage",
    "wof:placetype":"venue"
},
  "geometry": {"coordinates":[-101.848128,35.078551],"type":"Point"}
}