{
  "type": "Feature",
  "properties": {
    "iso:country":"US",
    "sg:address":"4128 Creekmont Dr",
    "sg:city":"Houston",
    "sg:classifiers":[
        {
            "category":"Manufacturing",
            "subcategory":"Tools & Machinery",
            "type":"Manufacturing & Wholesale Goods"
        }
    ],
    "sg:phone":"+1 713 939 0061",
    "sg:postcode":"77091",
    "sg:province":"TX",
    "sg:tags":[
        "machine",
        "shop",
        "industrial",
        "mfg"
    ],
    "wof:name":"Logik Precision Machine",
    "wof:placetype":"venue"
},
  "geometry": {"coordinates":[-95.454615,29.842377],"type":"Point"}
}