{
  "type": "Feature",
  "properties": {
    "iso:country":"US",
    "sg:address":"9501 Brookhollow Dr",
    "sg:city":"Waco",
    "sg:classifiers":[
        {
            "category":"Wholesale",
            "subcategory":"Vending Machines",
            "type":"Manufacturing & Wholesale Goods"
        }
    ],
    "sg:phone":"+1 254 776 2462",
    "sg:postcode":"76712",
    "sg:province":"TX",
    "wof:name":"Shayman Buys",
    "wof:placetype":"venue"
},
  "geometry": {"coordinates":[-97.233054,31.504859],"type":"Point"}
}