{
  "type": "Feature",
  "properties": {
    "iso:country":"US",
    "sg:address":"1600 N Redbud Blvd",
    "sg:city":"Mc Kinney",
    "sg:classifiers":[
        {
            "category":"Wholesale",
            "subcategory":"Durable Goods & Equipment",
            "type":"Manufacturing & Wholesale Goods"
        }
    ],
    "sg:phone":"+1 972 562 4418",
    "sg:postcode":"75069",
    "sg:province":"TX",
    "sg:tags":[
        "representative",
        "manufacturer"
    ],
    "wof:name":"Don White & Assoc",
    "wof:placetype":"venue"
},
  "geometry": {"coordinates":[-96.63414299999999,33.214127],"type":"Point"}
}