{
  "type": "Feature",
  "properties": {
    "iso:country":"US",
    "sg:address":"2233 N Prairie Creek Rd",
    "sg:city":"Dallas",
    "sg:classifiers":[
        {
            "category":"Shopping",
            "subcategory":"Beauty & Cosmetics",
            "type":"Retail Goods"
        }
    ],
    "sg:phone":"+1 214 275 8856",
    "sg:postcode":"75227",
    "sg:province":"TX",
    "sg:tags":[
        "supply"
    ],
    "wof:name":"Main Beauty Supply",
    "wof:placetype":"venue"
},
  "geometry": {"coordinates":[-96.66529800000001,32.750599],"type":"Point"}
}