{
  "type": "Feature",
  "properties": {
    "iso:country":"US",
    "sg:address":"629 Rodriguez",
    "sg:city":"Laredo",
    "sg:classifiers":[
        {
            "category":"Manufacturing",
            "subcategory":"Wood Products",
            "type":"Manufacturing & Wholesale Goods"
        }
    ],
    "sg:phone":"+1 956 795 1739",
    "sg:postcode":"78046",
    "sg:province":"TX",
    "sg:tags":[
        "mfg"
    ],
    "wof:name":"New Sun",
    "wof:placetype":"venue"
},
  "geometry": {"coordinates":[-99.495791,27.330148],"type":"Point"}
}