{
  "type": "Feature",
  "properties": {
    "iso:country":"US",
    "sg:address":"6701 Santa Fe Dr",
    "sg:city":"Lubbock",
    "sg:classifiers":[
        {
            "category":"Real Estate",
            "subcategory":"Architect",
            "type":"Services"
        }
    ],
    "sg:phone":"+1 806 548 3378",
    "sg:postcode":"79407",
    "sg:province":"TX",
    "sg:tags":[
        "architectural"
    ],
    "wof:name":"Michael Dertien Architect",
    "wof:placetype":"venue"
},
  "geometry": {"coordinates":[-101.970208,33.536299],"type":"Point"}
}