{
  "type": "Feature",
  "properties": {
    "iso:country":"US",
    "sg:address":"3836 Gramercy St",
    "sg:city":"Houston",
    "sg:classifiers":[
        {
            "category":"Mining & Drilling",
            "type":"Manufacturing & Wholesale Goods"
        }
    ],
    "sg:phone":"+1 713 668 2589",
    "sg:postcode":"77025",
    "sg:province":"TX",
    "sg:tags":[
        "exploration"
    ],
    "wof:name":"Seven D Oil & Gas Inc",
    "wof:placetype":"venue"
},
  "geometry": {"coordinates":[-95.439204,29.704641],"type":"Point"}
}