{
  "type": "Feature",
  "properties": {
    "iso:country":"US",
    "sg:address":"2280 Highland Village Rd",
    "sg:city":"Lewisville",
    "sg:classifiers":[
        {
            "category":"Health Services",
            "subcategory":"Doctor",
            "type":"Services"
        }
    ],
    "sg:phone":"+1 972 966 6686",
    "sg:postcode":"75077",
    "sg:province":"TX",
    "wof:name":"Waneta Chenault DDS",
    "wof:placetype":"venue"
},
  "geometry": {"coordinates":[-97.05755499999999,33.071992],"type":"Point"}
}