{
  "type": "Feature",
  "properties": {
    "iso:country":"US",
    "sg:address":"17401 Red Oak Dr",
    "sg:city":"Houston",
    "sg:classifiers":[
        {
            "category":"Real Estate",
            "subcategory":"Real Estate Operator",
            "type":"Services"
        }
    ],
    "sg:phone":"+1 281 586 9858",
    "sg:postcode":"77090",
    "sg:province":"TX",
    "sg:tags":[
        "property",
        "lessor"
    ],
    "wof:name":"Carmen Real Estate Inc",
    "wof:placetype":"venue"
},
  "geometry": {"coordinates":[-95.4466,30.020736],"type":"Point"}
}