{
  "type": "Feature",
  "properties": {
    "iso:country":"US",
    "sg:address":"4008 Wood Lake Dr",
    "sg:city":"Plano",
    "sg:classifiers":[
        {
            "category":"Professional",
            "subcategory":"Employment Agencies",
            "type":"Services"
        }
    ],
    "sg:phone":"+1 972 781 2585",
    "sg:postcode":"75093",
    "sg:province":"TX",
    "sg:tags":[
        "help",
        "supply"
    ],
    "wof:name":"G3 Staffing Inc",
    "wof:placetype":"venue"
},
  "geometry": {"coordinates":[-96.804804,33.051206],"type":"Point"}
}