{
  "type": "Feature",
  "properties": {
    "iso:country":"US",
    "sg:address":"25303 Oakhurst Dr",
    "sg:city":"Spring",
    "sg:classifiers":[
        {
            "category":"Retail",
            "subcategory":"Auto Repair",
            "type":"Services"
        }
    ],
    "sg:phone":"+1 281 296 7532",
    "sg:postcode":"77386",
    "sg:province":"TX",
    "sg:tags":[
        "repairing",
        "automobile",
        "general"
    ],
    "wof:name":"Phil's Auto Repair",
    "wof:placetype":"venue"
},
  "geometry": {"coordinates":[-95.44029500000001,30.132144],"type":"Point"}
}