{
  "type": "Feature",
  "properties": {
    "iso:country":"US",
    "sg:address":"900 W Davis St",
    "sg:city":"Conroe",
    "sg:classifiers":[
        {
            "category":"Insurance",
            "subcategory":"Insurance Agent",
            "type":"Services"
        }
    ],
    "sg:phone":"+1 936 537 5113",
    "sg:postcode":"77301",
    "sg:province":"TX",
    "sg:tags":[
        "processing"
    ],
    "wof:name":"Provider Reimbursement Svc",
    "wof:placetype":"venue"
},
  "geometry": {"coordinates":[-95.46913499999999,30.313883],"type":"Point"}
}