{
  "type": "Feature",
  "properties": {
    "iso:country":"US",
    "sg:address":"1618 E Tyler Ave",
    "sg:city":"Harlingen",
    "sg:classifiers":[
        {
            "category":"Health Services",
            "subcategory":"Clinic",
            "type":"Services"
        }
    ],
    "sg:phone":"+1 956 440 0830",
    "sg:postcode":"78550",
    "sg:province":"TX",
    "sg:tags":[
        "medical"
    ],
    "wof:name":"Rio Mobile X-Ray Inc",
    "wof:placetype":"venue"
},
  "geometry": {"coordinates":[-97.678988,26.189583],"type":"Point"}
}