{
  "type": "Feature",
  "properties": {
    "iso:country":"US",
    "sg:address":"3220 Samuell Blvd",
    "sg:city":"Dallas",
    "sg:classifiers":[
        {
            "category":"Shopping",
            "subcategory":"Used Merchandise",
            "type":"Retail Goods"
        }
    ],
    "sg:phone":"+1 214 285 9912",
    "sg:postcode":"75223",
    "sg:province":"TX",
    "wof:name":"One More Tavern",
    "wof:placetype":"venue"
},
  "geometry": {"coordinates":[-96.737657,32.792895],"type":"Point"}
}