{
  "type": "Feature",
  "properties": {
    "iso:country":"US",
    "sg:address":"5100 Creek Bend Dr",
    "sg:city":"Austin",
    "sg:classifiers":[
        {
            "category":"Professional",
            "type":"Services"
        }
    ],
    "sg:phone":"+1 512 443 6179",
    "sg:postcode":"78744",
    "sg:province":"TX",
    "wof:name":"Latino Rock Alliance Inc",
    "wof:placetype":"venue"
},
  "geometry": {"coordinates":[-97.74820200000001,30.183512],"type":"Point"}
}