{
  "type": "Feature",
  "properties": {
    "iso:country":"US",
    "sg:address":"11602 Bay Cedar Dr",
    "sg:city":"Houston",
    "sg:classifiers":[
        {
            "category":"Personal",
            "subcategory":"Beauty Salon",
            "type":"Services"
        }
    ],
    "sg:phone":"+1 713 734 3400",
    "sg:postcode":"77048",
    "sg:province":"TX",
    "sg:tags":[
        "shop"
    ],
    "wof:name":"Adams New ERA",
    "wof:placetype":"venue"
},
  "geometry": {"coordinates":[-95.350889,29.634481],"type":"Point"}
}