{
  "type": "Feature",
  "properties": {
    "iso:country":"US",
    "sg:address":"1236 E Main St",
    "sg:city":"League City",
    "sg:classifiers":[
        {
            "category":"Retail",
            "subcategory":"Veterinary Services",
            "type":"Services"
        }
    ],
    "sg:phone":"+1 281 332 3051",
    "sg:postcode":"77573",
    "sg:province":"TX",
    "sg:tags":[
        "hospital",
        "animal"
    ],
    "sg:website":"www.baycreekanimalclinic.com",
    "wof:name":"Bay Creek Animal Clinic",
    "wof:placetype":"venue"
},
  "geometry": {"coordinates":[-95.084879,29.515433],"type":"Point"}
}