{
  "type": "Feature",
  "properties": {
    "iso:country":"US",
    "sg:address":"1526 E Henderson St",
    "sg:city":"Cleburne",
    "sg:classifiers":[
        {
            "category":"Autos & Motor Vehicles",
            "subcategory":"Automobile Sales",
            "type":"Retail Goods"
        }
    ],
    "sg:phone":"+1 817 558 0266",
    "sg:postcode":"76031",
    "sg:province":"TX",
    "sg:tags":[
        "new",
        "used"
    ],
    "wof:name":"Pools Auto Sales",
    "wof:placetype":"venue"
},
  "geometry": {"coordinates":[-97.36077,32.359624],"type":"Point"}
}