{
  "type": "Feature",
  "properties": {
    "iso:country":"US",
    "sg:address":"1615 Santa Maria Ave",
    "sg:city":"Laredo",
    "sg:classifiers":[
        {
            "category":"Communications",
            "subcategory":"Radio Station",
            "type":"Services"
        }
    ],
    "sg:phone":"+1 956 722 8285",
    "sg:postcode":"78040",
    "sg:province":"TX",
    "sg:tags":[
        "equipment",
        "system"
    ],
    "wof:name":"Pomar Elec & Brdcstg Eqp",
    "wof:placetype":"venue"
},
  "geometry": {"coordinates":[-99.510296,27.513551],"type":"Point"}
}