{
  "type": "Feature",
  "properties": {
    "iso:country":"US",
    "sg:address":"303 Isles End Rd",
    "sg:city":"Galveston",
    "sg:classifiers":[
        {
            "category":"Real Estate",
            "subcategory":"Real Estate Operator",
            "type":"Services"
        }
    ],
    "sg:phone":"+1 409 908 9547",
    "sg:postcode":"77554",
    "sg:province":"TX",
    "sg:tags":[
        "building",
        "nonresidential"
    ],
    "wof:name":"Jupiter Properties LLC",
    "wof:placetype":"venue"
},
  "geometry": {"coordinates":[-94.925523,29.300558],"type":"Point"}
}