{
  "type": "Feature",
  "properties": {
    "iso:country":"US",
    "sg:address":"1401 E Ridge Rd",
    "sg:city":"Mcallen",
    "sg:classifiers":[
        {
            "category":"Health Services",
            "subcategory":"Doctor",
            "type":"Services"
        }
    ],
    "sg:phone":"+1 956 683 0234",
    "sg:postcode":"78503",
    "sg:province":"TX",
    "sg:tags":[
        "medical"
    ],
    "wof:name":"Valley Ctr For Pain Stress MGT",
    "wof:placetype":"venue"
},
  "geometry": {"coordinates":[-98.20681500000001,26.183547],"type":"Point"}
}