{
  "type": "Feature",
  "properties": {
    "iso:country":"US",
    "sg:address":"1917 Peavy Rd",
    "sg:city":"Dallas",
    "sg:classifiers":[
        {
            "category":"Shopping",
            "subcategory":"Pets & Pet Supplies",
            "type":"Retail Goods"
        }
    ],
    "sg:phone":"+1 214 824 7852",
    "sg:postcode":"75228",
    "sg:province":"TX",
    "sg:tags":[
        "furnishing",
        "dog",
        "store",
        "cat"
    ],
    "wof:name":"V I. Pets",
    "wof:placetype":"venue"
},
  "geometry": {"coordinates":[-96.686249,32.829556],"type":"Point"}
}