{
  "type": "Feature",
  "properties": {
    "iso:country":"US",
    "sg:address":"5 Cerrato Ln",
    "sg:city":"Texarkana",
    "sg:classifiers":[
        {
            "category":"Professional",
            "subcategory":"Secretarial Services",
            "type":"Services"
        }
    ],
    "sg:phone":"+1 903 838 4101",
    "sg:postcode":"75503",
    "sg:province":"TX",
    "sg:tags":[
        "convention",
        "court",
        "reporter"
    ],
    "wof:name":"May Reporting Svc",
    "wof:placetype":"venue"
},
  "geometry": {"coordinates":[-94.12230099999999,33.481357],"type":"Point"}
}