{
  "type": "Feature",
  "properties": {
    "iso:country":"US",
    "sg:address":"8017 Carrick St",
    "sg:city":"Fort Worth",
    "sg:classifiers":[
        {
            "category":"Autos & Motor Vehicles",
            "subcategory":"Auto Supplies",
            "type":"Retail Goods"
        }
    ],
    "sg:phone":"+1 817 244 8583",
    "sg:postcode":"76116",
    "sg:province":"TX",
    "sg:tags":[
        "home",
        "store"
    ],
    "wof:name":"Garcia Tires",
    "wof:placetype":"venue"
},
  "geometry": {"coordinates":[-97.454317,32.718661],"type":"Point"}
}