{
  "type": "Feature",
  "properties": {
    "iso:country":"US",
    "sg:address":"12200 Gulf Fwy",
    "sg:city":"Houston",
    "sg:classifiers":[
        {
            "category":"Shopping",
            "subcategory":"Department Store",
            "type":"Retail Goods"
        }
    ],
    "sg:phone":"+1 713 941 8701",
    "sg:postcode":"77034",
    "sg:province":"TX",
    "wof:name":"Burlington Coat Factory",
    "wof:placetype":"venue"
},
  "geometry": {"coordinates":[-95.223286,29.621998],"type":"Point"}
}