{
  "type": "Feature",
  "properties": {
    "iso:country":"US",
    "sg:address":"103 S Winston Ln",
    "sg:city":"San Antonio",
    "sg:classifiers":[
        {
            "category":"Personal",
            "subcategory":"Beauty Salon",
            "type":"Services"
        }
    ],
    "sg:phone":"+1 210 696 1501",
    "sg:postcode":"78213",
    "sg:province":"TX",
    "wof:name":"Polished",
    "wof:placetype":"venue"
},
  "geometry": {"coordinates":[-98.52819100000001,29.533752],"type":"Point"}
}