{
  "type": "Feature",
  "properties": {
    "iso:country":"US",
    "sg:address":"2261 Singleton Blvd",
    "sg:city":"Dallas",
    "sg:classifiers":[
        {
            "category":"Health Services",
            "subcategory":"Doctor",
            "type":"Services"
        },
        {
            "category":"Health Services",
            "subcategory":"Clinic",
            "type":"Services"
        }
    ],
    "sg:phone":"+1 214 630 9559",
    "sg:postcode":"75212",
    "sg:province":"TX",
    "sg:tags":[
        "physician",
        "family",
        "medical",
        "practice",
        "surgeons",
        "medicine"
    ],
    "wof:name":"Neighborcare Clinic",
    "wof:placetype":"venue"
},
  "geometry": {"coordinates":[-96.85952399999999,32.778887],"type":"Point"}
}