{
  "type": "Feature",
  "properties": {
    "iso:country":"US",
    "sg:address":"1398 W 7th Ave",
    "sg:city":"Corsicana",
    "sg:classifiers":[
        {
            "category":"Education",
            "subcategory":"Special Training",
            "type":"Public Place"
        }
    ],
    "sg:phone":"+1 903 872 6224",
    "sg:postcode":"75110",
    "sg:province":"TX",
    "sg:tags":[
        "school",
        "instruction",
        "art"
    ],
    "wof:name":"Studio/Kid Place",
    "wof:placetype":"venue"
},
  "geometry": {"coordinates":[-96.475948,32.085448],"type":"Point"}
}