{
  "type": "Feature",
  "properties": {
    "iso:country":"US",
    "sg:address":"5026 S Hulen St",
    "sg:city":"Fort Worth",
    "sg:classifiers":[
        {
            "category":"Shopping",
            "subcategory":"Department Store",
            "type":"Retail Goods"
        }
    ],
    "sg:phone":"+1 817 253 9048",
    "sg:postcode":"76132",
    "sg:province":"TX",
    "wof:name":"Stein Mart",
    "wof:placetype":"venue"
},
  "geometry": {"coordinates":[-97.399255,32.674142],"type":"Point"}
}