{
  "type": "Feature",
  "properties": {
    "iso:country":"US",
    "sg:address":"1922 Springrock Ln",
    "sg:city":"Houston",
    "sg:classifiers":[
        {
            "category":"Home & Garden",
            "subcategory":"Building Materials",
            "type":"Retail Goods"
        },
        {
            "category":"Building & Trades",
            "subcategory":"Construction",
            "type":"Services"
        }
    ],
    "sg:phone":"+1 713 973 0029",
    "sg:postcode":"77080",
    "sg:province":"TX",
    "sg:tags":[
        "concrete",
        "staining",
        "contractor"
    ],
    "wof:name":"T & S Concrete Service",
    "wof:placetype":"venue"
},
  "geometry": {"coordinates":[-95.529833,29.806787],"type":"Point"}
}