{
  "type": "Feature",
  "properties": {
    "iso:country":"US",
    "sg:address":"11002 Bentley St",
    "sg:city":"Houston",
    "sg:classifiers":[
        {
            "category":"Building & Trades",
            "subcategory":"Construction",
            "type":"Services"
        }
    ],
    "sg:phone":"+1 281 449 9628",
    "sg:postcode":"77093",
    "sg:province":"TX",
    "sg:tags":[
        "dry wall",
        "contractor"
    ],
    "wof:name":"Derby Drywall Inc",
    "wof:placetype":"venue"
},
  "geometry": {"coordinates":[-95.335435,29.876427],"type":"Point"}
}