{
  "type": "Feature",
  "properties": {
    "iso:country":"US",
    "sg:address":"14393 NW Military Hwy",
    "sg:city":"Shavano Park",
    "sg:classifiers":[
        {
            "category":"Autos & Motor Vehicles",
            "subcategory":"Fuel & Gas Station",
            "type":"Retail Goods"
        }
    ],
    "sg:phone":"+1 210 493 9834",
    "sg:postcode":"78231",
    "sg:province":"TX",
    "sg:tags":[
        "oil"
    ],
    "wof:name":"Diamond Shamrock",
    "wof:placetype":"venue"
},
  "geometry": {"coordinates":[-98.543539,29.572934],"type":"Point"}
}