{
  "type": "Feature",
  "properties": {
    "iso:country":"US",
    "sg:address":"15301 Spectrum Dr",
    "sg:city":"Addison",
    "sg:classifiers":[
        {
            "category":"Insurance",
            "subcategory":"Insurance Agent",
            "type":"Services"
        }
    ],
    "sg:phone":"+1 972 934 1840",
    "sg:postcode":"75001",
    "sg:province":"TX",
    "wof:name":"Aero One",
    "wof:placetype":"venue"
},
  "geometry": {"coordinates":[-96.824101,32.96073],"type":"Point"}
}