{
  "type": "Feature",
  "properties": {
    "iso:country":"US",
    "sg:address":"702 Hunters Glen Ct",
    "sg:city":"Mansfield",
    "sg:classifiers":[
        {
            "category":"Social Services",
            "type":"Services"
        }
    ],
    "sg:phone":"+1 817 453 9310",
    "sg:postcode":"76048",
    "sg:province":"TX",
    "wof:name":"Christian Counseling Mansfi",
    "wof:placetype":"venue"
},
  "geometry": {"coordinates":[-97.808545,32.39633],"type":"Point"}
}