{
  "type": "Feature",
  "properties": {
    "iso:country":"US",
    "sg:address":"1300 Gemini St",
    "sg:city":"Houston",
    "sg:classifiers":[
        {
            "category":"Professional",
            "type":"Services"
        }
    ],
    "sg:phone":"+1 281 286 2564",
    "sg:postcode":"77058",
    "sg:province":"TX",
    "wof:name":"AA Networks Inc",
    "wof:placetype":"venue"
},
  "geometry": {"coordinates":[-95.112892,29.557947],"type":"Point"}
}