{
  "type": "Feature",
  "properties": {
    "iso:country":"US",
    "sg:address":"2004 S Fairgrounds Rd",
    "sg:city":"Midland",
    "sg:classifiers":[
        {
            "category":"Autos & Motor Vehicles",
            "subcategory":"Auto Supplies",
            "type":"Retail Goods"
        }
    ],
    "sg:phone":"+1 432 682 5248",
    "sg:postcode":"79701",
    "sg:province":"TX",
    "sg:tags":[
        "tire"
    ],
    "wof:name":"Big 3 Tire",
    "wof:placetype":"venue"
},
  "geometry": {"coordinates":[-102.04225099999999,31.983757],"type":"Point"}
}