{
  "type": "Feature",
  "properties": {
    "iso:country":"US",
    "sg:address":"922 W Borderland Rd",
    "sg:city":"El Paso",
    "sg:classifiers":[
        {
            "category":"Organizations",
            "subcategory":"Non-profit Organization",
            "type":"Services"
        }
    ],
    "sg:phone":"+1 915 877 5006",
    "sg:postcode":"79932",
    "sg:province":"TX",
    "sg:tags":[
        "social"
    ],
    "wof:name":"Border Watch",
    "wof:placetype":"venue"
},
  "geometry": {"coordinates":[-106.62211499999999,31.885774],"type":"Point"}
}