{
  "type": "Feature",
  "properties": {
    "iso:country":"US",
    "sg:address":"210 Mill St",
    "sg:city":"Alto",
    "sg:classifiers":[
        {
            "category":"Organizations",
            "subcategory":"Religious Organization",
            "type":"Services"
        }
    ],
    "sg:phone":"+1 936 858 3002",
    "sg:postcode":"75925",
    "sg:province":"TX",
    "sg:tags":[
        "church"
    ],
    "sg:website":"www.htbc.us",
    "wof:name":"Hilltop Baptist Church",
    "wof:placetype":"venue"
},
  "geometry": {"coordinates":[-95.07049000000001,31.649311],"type":"Point"}
}