{
  "type": "Feature",
  "properties": {
    "iso:country":"US",
    "sg:address":"4122 Falkirk Ln",
    "sg:city":"Houston",
    "sg:classifiers":[
        {
            "category":"Organizations",
            "subcategory":"Community Association",
            "type":"Services"
        }
    ],
    "sg:phone":"+1 713 661 1891",
    "sg:postcode":"77025",
    "sg:province":"TX",
    "wof:name":"Terresa A Howell Pta",
    "wof:placetype":"venue"
},
  "geometry": {"coordinates":[-95.445294,29.692767],"type":"Point"}
}