{
  "type": "Feature",
  "properties": {
    "iso:country":"US",
    "sg:address":"701 W Pipeline Rd",
    "sg:city":"Hurst",
    "sg:classifiers":[
        {
            "category":"Shopping",
            "type":"Retail Goods"
        }
    ],
    "sg:phone":"+1 817 285 0606",
    "sg:postcode":"76053",
    "sg:province":"TX",
    "sg:tags":[
        "art",
        "gallery",
        "dealer"
    ],
    "wof:name":"Edward J Denari & Co",
    "wof:placetype":"venue"
},
  "geometry": {"coordinates":[-97.18644500000001,32.82365],"type":"Point"}
}