{
  "type": "Feature",
  "properties": {
    "iso:country":"US",
    "sg:address":"801 S 2nd St",
    "sg:city":"Mcallen",
    "sg:classifiers":[
        {
            "category":"Professional",
            "type":"Services"
        }
    ],
    "sg:phone":"+1 956 630 1684",
    "sg:postcode":"78501",
    "sg:province":"TX",
    "wof:name":"Socorro N McBurnett",
    "wof:placetype":"venue"
},
  "geometry": {"coordinates":[-98.22275999999999,26.193102],"type":"Point"}
}