{
  "type": "Feature",
  "properties": {
    "iso:country":"US",
    "sg:address":"136 E View Ct",
    "sg:city":"Lewisville",
    "sg:classifiers":[
        {
            "category":"Building & Trades",
            "subcategory":"Construction",
            "type":"Services"
        }
    ],
    "sg:phone":"+1 972 539 5527",
    "sg:postcode":"75077",
    "sg:province":"TX",
    "sg:tags":[
        "heavy"
    ],
    "wof:name":"P H Construction",
    "wof:placetype":"venue"
},
  "geometry": {"coordinates":[-97.091171,33.067418],"type":"Point"}
}