{
  "type": "Feature",
  "properties": {
    "iso:country":"US",
    "sg:address":"322 Texas St",
    "sg:city":"Denton",
    "sg:classifiers":[
        {
            "category":"Home & Garden",
            "subcategory":"Home Furnishings",
            "type":"Retail Goods"
        }
    ],
    "sg:phone":"+1 940 891 4211",
    "sg:postcode":"76201",
    "sg:province":"TX",
    "wof:name":"Rachel Westbrook Pottery",
    "wof:placetype":"venue"
},
  "geometry": {"coordinates":[-97.129732,33.222219],"type":"Point"}
}