{
  "type": "Feature",
  "properties": {
    "iso:country":"US",
    "sg:address":"146 Pine Ct",
    "sg:city":"Murchison",
    "sg:classifiers":[
        {
            "category":"Professional",
            "type":"Services"
        }
    ],
    "sg:phone":"+1 903 469 3563",
    "sg:postcode":"75755",
    "sg:province":"TX",
    "wof:name":"Robert H Lovegrove",
    "wof:placetype":"venue"
},
  "geometry": {"coordinates":[-95.128214,32.758933],"type":"Point"}
}